Workbook
Name hurdle: 'Setup'!$B$4
Name cap_budget: 'Setup'!$B$5
Name w_fin: 'Setup'!$B$6
Name w_fit: 'Setup'!$B$7
Name w_risk: 'Setup'!$B$8

Sheet README
A1: D09 · Strategic portfolio & capital allocation systems
A3: Domain D09: Strategic portfolio & capital allocation systems.
A4: Rank projects by NPV at the hurdle rate, IRR, profitability index and strategic/risk scores, and fund within the capital budget.
A5: How to use
A6: Copy this workbook into companies/<slug>/domains/D09_strategic-portfolio-capital-allocation/ before typing. Replace the SAMPLE rows (illustrative Tamil Nadu data) with company data.
A7: Type only into pale-yellow cells; white cells are formulas. Checks › OVERALL must be PASS before any value feeds K01/K02.
A8: Statutory rates are starting values - verify in 01_tamil-nadu/verification-register.md.
A9: Feeds
A10: D17 CapexPlan → K01 capex_monthly, da_monthly <= funded projects
A11: D23 green finance <= eligible projects
A12: W07 the ask <= funding decisions

Sheet Checks
A1: Checks - OVERALL must be PASS before this domain feeds the kernel
B3: OVERALL | C3: =IF(COUNTIF(C5:C6,"PASS")=COUNT(A5:A6),"PASS","FAIL")
A4: # | B4: check | C4: result
A5: 1 | B5: hurdle rate between 0 and 50% | C5: =IF(AND(Setup!$B$4>0,Setup!$B$4<0.5),"PASS","FAIL")
A6: 2 | B6: weights sum to 100% | C6: =IF(ABS(Setup!$B$6+Setup!$B$7+Setup!$B$8-1)<1E-9,"PASS","FAIL")

Sheet Setup
A1: Capital allocation setup
A4: hurdle rate (post-tax WACC, INR) | B4: 0.13
A5: capital budget available (₹) | B5: 150000000
A6: weight: financial (NPV index) | B6: 0.6
A7: weight: strategic fit (1-5) | B7: 0.25
A8: weight: risk (1-5, 5 = low risk) | B8: 0.15

Sheet Projects
A1: Projects (cash flows in ₹, after tax)
A4: project | B4: year-0 cash flow (capex as NEGATIVE) | C4: net cash flow Y1 | D4: net cash flow Y2 | E4: net cash flow Y3 | F4: net cash flow Y4 | G4: net cash flow Y5 | H4: net cash flow Y6 | I4: net cash flow Y7 | J4: net cash flow Y8 | K4: net cash flow Y9 | L4: net cash flow Y10 | M4: NPV @ hurdle | N4: IRR | O4: profitability index | P4: strategic fit 1-5 | Q4: risk 1-5 (5 = low) | R4: composite score | S4: rank | T4: cumulative capex by rank | U4: funded within budget?
A5: Hosur EV-component line | B5: -80000000 | C5: 15000000 | D5: 20000000 | E5: 24000000 | F5: 26000000 | G5: 26000000 | H5: 26000000 | I5: 24000000 | J5: 22000000 | K5: 20000000 | L5: 18000000 | M5: =IF(A5="","",B5+NPV(Setup!$B$4,C5:L5)) | N5: =IF(A5="","",IFERROR(IRR(B5:L5),"")) | O5: =IF(OR(A5="",N(B5)=0),"",(M5-B5)/(-B5)) | P5: 4 | Q5: 3 | R5: =IF(A5="","",Setup!$B$6*MIN(5,MAX(0,O5*2.5))+Setup!$B$7*N(P5)+Setup!$B$8*N(Q5)) | S5: =IF(A5="","",COUNTIF($R$5:$R$54,">"&R5)+COUNTIF($R$5:R5,R5)) | T5: =IF(A5="","",-SUMIF($S$5:$S$54,"<="&S5,$B$5:$B$54)) | U5: =IF(A5="","",AND(T5<=Setup!$B$5,M5>0))
A6: Rooftop solar 2 MW (Coimbatore) | B6: -90000000 | C6: 14000000 | D6: 14000000 | E6: 14000000 | F6: 14000000 | G6: 14000000 | H6: 14000000 | I6: 14000000 | J6: 14000000 | K6: 14000000 | L6: 14000000 | M6: =IF(A6="","",B6+NPV(Setup!$B$4,C6:L6)) | N6: =IF(A6="","",IFERROR(IRR(B6:L6),"")) | O6: =IF(OR(A6="",N(B6)=0),"",(M6-B6)/(-B6)) | P6: 3 | Q6: 5 | R6: =IF(A6="","",Setup!$B$6*MIN(5,MAX(0,O6*2.5))+Setup!$B$7*N(P6)+Setup!$B$8*N(Q6)) | S6: =IF(A6="","",COUNTIF($R$5:$R$54,">"&R6)+COUNTIF($R$5:R6,R6)) | T6: =IF(A6="","",-SUMIF($S$5:$S$54,"<="&S6,$B$5:$B$54)) | U6: =IF(A6="","",AND(T6<=Setup!$B$5,M6>0))
A7: ERP upgrade (Tally -> Zoho/SAP) | B7: -12000000 | C7: 3000000 | D7: 4000000 | E7: 4000000 | F7: 4000000 | G7: 3000000 | H7: 0 | I7: 0 | J7: 0 | K7: 0 | L7: 0 | M7: =IF(A7="","",B7+NPV(Setup!$B$4,C7:L7)) | N7: =IF(A7="","",IFERROR(IRR(B7:L7),"")) | O7: =IF(OR(A7="",N(B7)=0),"",(M7-B7)/(-B7)) | P7: 4 | Q7: 4 | R7: =IF(A7="","",Setup!$B$6*MIN(5,MAX(0,O7*2.5))+Setup!$B$7*N(P7)+Setup!$B$8*N(Q7)) | S7: =IF(A7="","",COUNTIF($R$5:$R$54,">"&R7)+COUNTIF($R$5:R7,R7)) | T7: =IF(A7="","",-SUMIF($S$5:$S$54,"<="&S7,$B$5:$B$54)) | U7: =IF(A7="","",AND(T7<=Setup!$B$5,M7>0))
M8: =IF(A8="","",B8+NPV(Setup!$B$4,C8:L8)) | N8: =IF(A8="","",IFERROR(IRR(B8:L8),"")) | O8: =IF(OR(A8="",N(B8)=0),"",(M8-B8)/(-B8)) | R8: =IF(A8="","",Setup!$B$6*MIN(5,MAX(0,O8*2.5))+Setup!$B$7*N(P8)+Setup!$B$8*N(Q8)) | S8: =IF(A8="","",COUNTIF($R$5:$R$54,">"&R8)+COUNTIF($R$5:R8,R8)) | T8: =IF(A8="","",-SUMIF($S$5:$S$54,"<="&S8,$B$5:$B$54)) | U8: =IF(A8="","",AND(T8<=Setup!$B$5,M8>0))
M9: =IF(A9="","",B9+NPV(Setup!$B$4,C9:L9)) | N9: =IF(A9="","",IFERROR(IRR(B9:L9),"")) | O9: =IF(OR(A9="",N(B9)=0),"",(M9-B9)/(-B9)) | R9: =IF(A9="","",Setup!$B$6*MIN(5,MAX(0,O9*2.5))+Setup!$B$7*N(P9)+Setup!$B$8*N(Q9)) | S9: =IF(A9="","",COUNTIF($R$5:$R$54,">"&R9)+COUNTIF($R$5:R9,R9)) | T9: =IF(A9="","",-SUMIF($S$5:$S$54,"<="&S9,$B$5:$B$54)) | U9: =IF(A9="","",AND(T9<=Setup!$B$5,M9>0))
M10: =IF(A10="","",B10+NPV(Setup!$B$4,C10:L10)) | N10: =IF(A10="","",IFERROR(IRR(B10:L10),"")) | O10: =IF(OR(A10="",N(B10)=0),"",(M10-B10)/(-B10)) | R10: =IF(A10="","",Setup!$B$6*MIN(5,MAX(0,O10*2.5))+Setup!$B$7*N(P10)+Setup!$B$8*N(Q10)) | S10: =IF(A10="","",COUNTIF($R$5:$R$54,">"&R10)+COUNTIF($R$5:R10,R10)) | T10: =IF(A10="","",-SUMIF($S$5:$S$54,"<="&S10,$B$5:$B$54)) | U10: =IF(A10="","",AND(T10<=Setup!$B$5,M10>0))
M11: =IF(A11="","",B11+NPV(Setup!$B$4,C11:L11)) | N11: =IF(A11="","",IFERROR(IRR(B11:L11),"")) | O11: =IF(OR(A11="",N(B11)=0),"",(M11-B11)/(-B11)) | R11: =IF(A11="","",Setup!$B$6*MIN(5,MAX(0,O11*2.5))+Setup!$B$7*N(P11)+Setup!$B$8*N(Q11)) | S11: =IF(A11="","",COUNTIF($R$5:$R$54,">"&R11)+COUNTIF($R$5:R11,R11)) | T11: =IF(A11="","",-SUMIF($S$5:$S$54,"<="&S11,$B$5:$B$54)) | U11: =IF(A11="","",AND(T11<=Setup!$B$5,M11>0))
M12: =IF(A12="","",B12+NPV(Setup!$B$4,C12:L12)) | N12: =IF(A12="","",IFERROR(IRR(B12:L12),"")) | O12: =IF(OR(A12="",N(B12)=0),"",(M12-B12)/(-B12)) | R12: =IF(A12="","",Setup!$B$6*MIN(5,MAX(0,O12*2.5))+Setup!$B$7*N(P12)+Setup!$B$8*N(Q12)) | S12: =IF(A12="","",COUNTIF($R$5:$R$54,">"&R12)+COUNTIF($R$5:R12,R12)) | T12: =IF(A12="","",-SUMIF($S$5:$S$54,"<="&S12,$B$5:$B$54)) | U12: =IF(A12="","",AND(T12<=Setup!$B$5,M12>0))
M13: =IF(A13="","",B13+NPV(Setup!$B$4,C13:L13)) | N13: =IF(A13="","",IFERROR(IRR(B13:L13),"")) | O13: =IF(OR(A13="",N(B13)=0),"",(M13-B13)/(-B13)) | R13: =IF(A13="","",Setup!$B$6*MIN(5,MAX(0,O13*2.5))+Setup!$B$7*N(P13)+Setup!$B$8*N(Q13)) | S13: =IF(A13="","",COUNTIF($R$5:$R$54,">"&R13)+COUNTIF($R$5:R13,R13)) | T13: =IF(A13="","",-SUMIF($S$5:$S$54,"<="&S13,$B$5:$B$54)) | U13: =IF(A13="","",AND(T13<=Setup!$B$5,M13>0))
M14: =IF(A14="","",B14+NPV(Setup!$B$4,C14:L14)) | N14: =IF(A14="","",IFERROR(IRR(B14:L14),"")) | O14: =IF(OR(A14="",N(B14)=0),"",(M14-B14)/(-B14)) | R14: =IF(A14="","",Setup!$B$6*MIN(5,MAX(0,O14*2.5))+Setup!$B$7*N(P14)+Setup!$B$8*N(Q14)) | S14: =IF(A14="","",COUNTIF($R$5:$R$54,">"&R14)+COUNTIF($R$5:R14,R14)) | T14: =IF(A14="","",-SUMIF($S$5:$S$54,"<="&S14,$B$5:$B$54)) | U14: =IF(A14="","",AND(T14<=Setup!$B$5,M14>0))
M15: =IF(A15="","",B15+NPV(Setup!$B$4,C15:L15)) | N15: =IF(A15="","",IFERROR(IRR(B15:L15),"")) | O15: =IF(OR(A15="",N(B15)=0),"",(M15-B15)/(-B15)) | R15: =IF(A15="","",Setup!$B$6*MIN(5,MAX(0,O15*2.5))+Setup!$B$7*N(P15)+Setup!$B$8*N(Q15)) | S15: =IF(A15="","",COUNTIF($R$5:$R$54,">"&R15)+COUNTIF($R$5:R15,R15)) | T15: =IF(A15="","",-SUMIF($S$5:$S$54,"<="&S15,$B$5:$B$54)) | U15: =IF(A15="","",AND(T15<=Setup!$B$5,M15>0))
M16: =IF(A16="","",B16+NPV(Setup!$B$4,C16:L16)) | N16: =IF(A16="","",IFERROR(IRR(B16:L16),"")) | O16: =IF(OR(A16="",N(B16)=0),"",(M16-B16)/(-B16)) | R16: =IF(A16="","",Setup!$B$6*MIN(5,MAX(0,O16*2.5))+Setup!$B$7*N(P16)+Setup!$B$8*N(Q16)) | S16: =IF(A16="","",COUNTIF($R$5:$R$54,">"&R16)+COUNTIF($R$5:R16,R16)) | T16: =IF(A16="","",-SUMIF($S$5:$S$54,"<="&S16,$B$5:$B$54)) | U16: =IF(A16="","",AND(T16<=Setup!$B$5,M16>0))
M17: =IF(A17="","",B17+NPV(Setup!$B$4,C17:L17)) | N17: =IF(A17="","",IFERROR(IRR(B17:L17),"")) | O17: =IF(OR(A17="",N(B17)=0),"",(M17-B17)/(-B17)) | R17: =IF(A17="","",Setup!$B$6*MIN(5,MAX(0,O17*2.5))+Setup!$B$7*N(P17)+Setup!$B$8*N(Q17)) | S17: =IF(A17="","",COUNTIF($R$5:$R$54,">"&R17)+COUNTIF($R$5:R17,R17)) | T17: =IF(A17="","",-SUMIF($S$5:$S$54,"<="&S17,$B$5:$B$54)) | U17: =IF(A17="","",AND(T17<=Setup!$B$5,M17>0))
M18: =IF(A18="","",B18+NPV(Setup!$B$4,C18:L18)) | N18: =IF(A18="","",IFERROR(IRR(B18:L18),"")) | O18: =IF(OR(A18="",N(B18)=0),"",(M18-B18)/(-B18)) | R18: =IF(A18="","",Setup!$B$6*MIN(5,MAX(0,O18*2.5))+Setup!$B$7*N(P18)+Setup!$B$8*N(Q18)) | S18: =IF(A18="","",COUNTIF($R$5:$R$54,">"&R18)+COUNTIF($R$5:R18,R18)) | T18: =IF(A18="","",-SUMIF($S$5:$S$54,"<="&S18,$B$5:$B$54)) | U18: =IF(A18="","",AND(T18<=Setup!$B$5,M18>0))
M19: =IF(A19="","",B19+NPV(Setup!$B$4,C19:L19)) | N19: =IF(A19="","",IFERROR(IRR(B19:L19),"")) | O19: =IF(OR(A19="",N(B19)=0),"",(M19-B19)/(-B19)) | R19: =IF(A19="","",Setup!$B$6*MIN(5,MAX(0,O19*2.5))+Setup!$B$7*N(P19)+Setup!$B$8*N(Q19)) | S19: =IF(A19="","",COUNTIF($R$5:$R$54,">"&R19)+COUNTIF($R$5:R19,R19)) | T19: =IF(A19="","",-SUMIF($S$5:$S$54,"<="&S19,$B$5:$B$54)) | U19: =IF(A19="","",AND(T19<=Setup!$B$5,M19>0))
... M54: =IF(A54="","",B54+NPV(Setup!$B$4,C54:L54)) | N54: =IF(A54="","",IFERROR(IRR(B54:L54),"")) | O54: =IF(OR(A54="",N(B54)=0),"",(M54-B54)/(-B54)) | R54: =IF(A54="","",Setup!$B$6*MIN(5,MAX(0,O54*2.5))+Setup!$B$7*N(P54)+Setup!$B$8*N(Q54)) | S54: =IF(A54="","",COUNTIF($R$5:$R$54,">"&R54)+COUNTIF($R$5:R54,R54)) | T54: =IF(A54="","",-SUMIF($S$5:$S$54,"<="&S54,$B$5:$B$54)) | U54: =IF(A54="","",AND(T54<=Setup!$B$5,M54>0))
