Workbook
Name cv_rev: 'Setup'!$B$4
Name cv_gp: 'Setup'!$B$5
Name cv_opex: 'Setup'!$B$6
Name cv_da: 'Setup'!$B$7
Name cv_capex: 'Setup'!$B$8
Name dv_rate: 'Setup'!$B$9
Name dv_tax: 'Setup'!$B$10
Name dv_debt: 'Setup'!$B$11
Name dv_cash: 'Setup'!$B$12
Name dv_n: 'Setup'!$B$13

Sheet README
A1: K08 · Divestiture / Carve-out & Leverage Sensitivity (no-code kernel)
A3: Replaces openfpa: pyfpa.analysis.divestiture (Carveout, divest, net_debt_to_ebitda) and the Fox Factory Marucci sensitivity grid.
A4: 1. Paste K01 'Export_Rows' VALUES (not formulas) into 'Forecast' (one row per month).
A5: 2. Enter the unit's MONTHLY contribution on 'Setup' (revenue, gross profit, opex, D&A, capex - positive numbers), interest rate on retired debt, tax rate, debt balance and cash for leverage.
A6: 3. Define up to 10 scenarios (label, sale_month = months RETAINED before the sale closes, proceeds). Slot 0 is always 'Hold'.
A7: Rules: from month sale_month+1 onward the carve-out is removed; interest falls by proceeds x rate / 12; tax = max(0, pre-tax) x tax rate (no loss carryforward); WC impact and principal held constant; one-time proceeds are EXCLUDED from FCF; ending cash is rebuilt from cumulative change in cash. The input forecast is never altered.
A8: Leverage = (debt - proceeds - cash) / EBITDA of the FINAL 12 months (run-rate). Negative = 'net cash'. Zero EBITDA = 'inf'.

Sheet Checks
A1: Checks - OVERALL must be PASS
B3: OVERALL | C3: =IF(COUNTIF(C5:C8,"PASS")=COUNT(A5:A8),"PASS","FAIL") | D3: =COUNTIF(C5:C8,"PASS")&" pass / "&COUNTIF(C5:C8,"FAIL")&" fail / "&(COUNT(A5:A8)-COUNTIF(C5:C8,"PASS")-COUNTIF(C5:C8,"FAIL"))&" error"
A4: # | B4: check | C4: result | D4: detail
A5: 1 | B5: forecast rows supplied | C5: =IF(Setup!$B$13>0,"PASS","FAIL") | D5: =Setup!$B$13
A6: 2 | B6: carve-out inputs >= 0 | C6: =IF(AND(Setup!$B$4>=0,Setup!$B$5>=0,Setup!$B$6>=0,Setup!$B$7>=0,Setup!$B$8>=0),"PASS","FAIL")
A7: 3 | B7: Hold scenario reproduces input FCF | C7: =IF(ABS(Grid!E5-SUM(Forecast!O5:O124))<0.005,"PASS","FAIL")
A8: 4 | B8: every scenario's sale_month is a whole number >= 0 | C8: =IF(SUMPRODUCT((Setup!B18:B27<>"")*((Setup!C18:C27<0)+(INT(N(Setup!C18:C27))<>N(Setup!C18:C27))))=0,"PASS","FAIL")

Sheet Setup
A1: Setup
A4: carve-out monthly revenue | B4: 25000000
A5: carve-out monthly gross_profit | B5: 12500000
A6: carve-out monthly opex | B6: 6250000
A7: carve-out monthly D&A | B7: 1833333.3
A8: carve-out monthly capex | B8: 416666.67
A9: annual rate on debt retired by proceeds | B9: 0.08
A10: tax rate for post-sale months | B10: 0.22
A11: debt balance for leverage | B11: 523538000
A12: cash for leverage (0 = gross of cash) | B12: 0
A13: months in forecast | B13: =SUMPRODUCT((Forecast!A5:A124<>"")*1)
A16: slot | B16: scenario label | C16: sale_month (months retained) | D16: proceeds
A17: 0 | B17: Hold | C17: =9999 | D17: 0
A18: 1 | B18: Sell at 6mo | C18: 6 | D18: 300000000
A19: 2 | B19: Sell at 12mo | C19: 12 | D19: 300000000
A20: 3 | B20: Sell at 18mo | C20: 18 | D20: 300000000
A21: 4 | B21: Sell at 24mo | C21: 24 | D21: 300000000
A22: 5 | B22: At cost (~$567M paid) @12mo | C22: 12 | D22: 567194000
A23: 6 | B23: Default markdown @12mo | C23: 12 | D23: 300000000
A24: 7 | B24: 8x EBITDA @12mo | C24: 12 | D24: 600000000
A25: 8 | B25: 12x EBITDA @12mo | C25: 12 | D25: 900000000
A26: 9
A27: 10

Sheet Forecast
A1: Forecast input - paste K01 Export_Rows values (month rows)
A4: month_no | B4: revenue | C4: gross_profit | D4: opex | E4: ebitda | F4: da | G4: interest | H4: pretax_income | I4: tax | J4: net_income | K4: wc_cash_impact | L4: operating_cash_flow | M4: capex | N4: principal | O4: free_cash_flow | P4: change_in_cash | Q4: ending_cash
A5: 1 | B5: 1.2671089e+08 | C5: 38279360 | D5: 18550253 | E5: 19729107 | F5: 7333333.3 | G5: 3490253.3 | H5: 8905520.2 | I5: 1959214.5 | J5: 6946305.8 | K5: -15872934 | L5: -1593295.3 | M5: 3500000 | N5: 2083333.3 | O5: -5093295.3 | P5: -7176628.6 | Q5: 50831371
A6: 2 | B6: 1.2671089e+08 | C6: 38279360 | D6: 18550253 | E6: 19729107 | F6: 7333333.3 | G6: 3476364.4 | H6: 8919409.1 | I6: 1962270 | J6: 6957139.1 | K6: 0 | L6: 14290472 | M6: 3500000 | N6: 2083333.3 | O6: 10790472 | P6: 8707139.1 | Q6: 59538511
A7: 3 | B7: 1.2671089e+08 | C7: 38279360 | D7: 18550253 | E7: 19729107 | F7: 7333333.3 | G7: 3462475.6 | H7: 8933298 | I7: 1965325.6 | J7: 6967972.5 | K7: 0 | L7: 14301306 | M7: 3500000 | N7: 2083333.3 | O7: 10801306 | P7: 8717972.5 | Q7: 68256483
A8: 4 | B8: 1.2671089e+08 | C8: 38279360 | D8: 18550253 | E8: 19729107 | F8: 7333333.3 | G8: 3448586.7 | H8: 8947186.9 | I8: 1968381.1 | J8: 6978805.8 | K8: 0 | L8: 14312139 | M8: 3500000 | N8: 2083333.3 | O8: 10812139 | P8: 8728805.8 | Q8: 76985289
A9: 5 | B9: 1.2671089e+08 | C9: 38279360 | D9: 18550253 | E9: 19729107 | F9: 7333333.3 | G9: 3434697.8 | H9: 8961075.8 | I9: 1971436.7 | J9: 6989639.1 | K9: 0 | L9: 14322972 | M9: 3500000 | N9: 2083333.3 | O9: 10822972 | P9: 8739639.1 | Q9: 85724928
A10: 6 | B10: 1.2671089e+08 | C10: 38279360 | D10: 18550253 | E10: 19729107 | F10: 7333333.3 | G10: 3420808.9 | H10: 8974964.7 | I10: 1974492.2 | J10: 7000472.5 | K10: 0 | L10: 14333806 | M10: 3500000 | N10: 2083333.3 | O10: 10833806 | P10: 8750472.5 | Q10: 94475400
A11: 7 | B11: 1.2671089e+08 | C11: 38279360 | D11: 18550253 | E11: 19729107 | F11: 7333333.3 | G11: 3406920 | H11: 8988853.6 | I11: 1977547.8 | J11: 7011305.8 | K11: 0 | L11: 14344639 | M11: 3500000 | N11: 2083333.3 | O11: 10844639 | P11: 8761305.8 | Q11: 1.0323671e+08
A12: 8 | B12: 1.2671089e+08 | C12: 38279360 | D12: 18550253 | E12: 19729107 | F12: 7333333.3 | G12: 3393031.1 | H12: 9002742.5 | I12: 1980603.3 | J12: 7022139.1 | K12: 0 | L12: 14355472 | M12: 3500000 | N12: 2083333.3 | O12: 10855472 | P12: 8772139.1 | Q12: 1.1200885e+08
A13: 9 | B13: 1.2671089e+08 | C13: 38279360 | D13: 18550253 | E13: 19729107 | F13: 7333333.3 | G13: 3379142.2 | H13: 9016631.3 | I13: 1983658.9 | J13: 7032972.5 | K13: 0 | L13: 14366306 | M13: 3500000 | N13: 2083333.3 | O13: 10866306 | P13: 8782972.5 | Q13: 1.2079182e+08
A14: 10 | B14: 1.2671089e+08 | C14: 38279360 | D14: 18550253 | E14: 19729107 | F14: 7333333.3 | G14: 3365253.3 | H14: 9030520.2 | I14: 1986714.5 | J14: 7043805.8 | K14: 0 | L14: 14377139 | M14: 3500000 | N14: 2083333.3 | O14: 10877139 | P14: 8793805.8 | Q14: 1.2958562e+08
A15: 11 | B15: 1.2671089e+08 | C15: 38279360 | D15: 18550253 | E15: 19729107 | F15: 7333333.3 | G15: 3351364.4 | H15: 9044409.1 | I15: 1989770 | J15: 7054639.1 | K15: 0 | L15: 14387972 | M15: 3500000 | N15: 2083333.3 | O15: 10887972 | P15: 8804639.1 | Q15: 1.3839026e+08
A16: 12 | B16: 1.2671089e+08 | C16: 38279360 | D16: 18550253 | E16: 19729107 | F16: 7333333.3 | G16: 3337475.6 | H16: 9058298 | I16: 1992825.6 | J16: 7065472.5 | K16: 0 | L16: 14398806 | M16: 3500000 | N16: 2083333.3 | O16: 10898806 | P16: 8815472.5 | Q16: 1.4720574e+08
... A28: 24 | B28: 1.3134653e+08 | C28: 40060693 | D28: 19199462 | E28: 20861231 | F28: 6833333.3 | G28: 3170808.9 | H28: 10857089 | I28: 2388559.5 | J28: 8468529.2 | K28: 0 | L28: 15301863 | M28: 3500000 | N28: 2083333.3 | O28: 11801863 | P28: 9718529.2 | Q28: 2.4761468e+08

Sheet S0
A1: Scenario slot 0
B2: =Setup!B17
A4: month_no | B4: post-sale? | C4: revenue | D4: gross_profit | E4: opex | F4: ebitda | G4: da | H4: interest | I4: pretax_income | J4: tax | K4: net_income | L4: operating_cash_flow | M4: capex | N4: free_cash_flow | O4: change_in_cash | P4: ending_cash
A5: =IF(Forecast!A5="","",Forecast!A5) | B5: =IF(A5="","",IF(0>=N(Setup!$C$17),1,0)) | C5: =IF(A5="","",IF($B5=1,Forecast!B5-Setup!$B$4,Forecast!B5)) | D5: =IF(A5="","",IF($B5=1,Forecast!C5-Setup!$B$5,Forecast!C5)) | E5: =IF(A5="","",IF($B5=1,Forecast!D5-Setup!$B$6,Forecast!D5)) | F5: =IF(A5="","",IF($B5=1,D5-E5,Forecast!E5)) | G5: =IF(A5="","",IF($B5=1,Forecast!F5-Setup!$B$7,Forecast!F5)) | H5: =IF(A5="","",IF($B5=1,Forecast!G5-N(Setup!$D$17)*Setup!$B$9/12,Forecast!G5)) | I5: =IF(A5="","",IF($B5=1,F5-G5-H5,Forecast!H5)) | J5: =IF(A5="","",IF($B5=1,MAX(0,I5)*Setup!$B$10,Forecast!I5)) | K5: =IF(A5="","",IF($B5=1,I5-J5,Forecast!J5)) | L5: =IF(A5="","",IF($B5=1,K5+G5+Forecast!K5,Forecast!L5)) | M5: =IF(A5="","",IF($B5=1,Forecast!M5-Setup!$B$8,Forecast!M5)) | N5: =IF(A5="","",IF($B5=1,L5-M5,Forecast!O5)) | O5: =IF(A5="","",IF($B5=1,N5-Forecast!N5,Forecast!P5)) | P5: =IF(A5="","",(Forecast!$Q$5-Forecast!$P$5)+SUM($O$5:O5))
A6: =IF(Forecast!A6="","",Forecast!A6) | B6: =IF(A6="","",IF(1>=N(Setup!$C$17),1,0)) | C6: =IF(A6="","",IF($B6=1,Forecast!B6-Setup!$B$4,Forecast!B6)) | D6: =IF(A6="","",IF($B6=1,Forecast!C6-Setup!$B$5,Forecast!C6)) | E6: =IF(A6="","",IF($B6=1,Forecast!D6-Setup!$B$6,Forecast!D6)) | F6: =IF(A6="","",IF($B6=1,D6-E6,Forecast!E6)) | G6: =IF(A6="","",IF($B6=1,Forecast!F6-Setup!$B$7,Forecast!F6)) | H6: =IF(A6="","",IF($B6=1,Forecast!G6-N(Setup!$D$17)*Setup!$B$9/12,Forecast!G6)) | I6: =IF(A6="","",IF($B6=1,F6-G6-H6,Forecast!H6)) | J6: =IF(A6="","",IF($B6=1,MAX(0,I6)*Setup!$B$10,Forecast!I6)) | K6: =IF(A6="","",IF($B6=1,I6-J6,Forecast!J6)) | L6: =IF(A6="","",IF($B6=1,K6+G6+Forecast!K6,Forecast!L6)) | M6: =IF(A6="","",IF($B6=1,Forecast!M6-Setup!$B$8,Forecast!M6)) | N6: =IF(A6="","",IF($B6=1,L6-M6,Forecast!O6)) | O6: =IF(A6="","",IF($B6=1,N6-Forecast!N6,Forecast!P6)) | P6: =IF(A6="","",(Forecast!$Q$5-Forecast!$P$5)+SUM($O$5:O6))
A7: =IF(Forecast!A7="","",Forecast!A7) | B7: =IF(A7="","",IF(2>=N(Setup!$C$17),1,0)) | C7: =IF(A7="","",IF($B7=1,Forecast!B7-Setup!$B$4,Forecast!B7)) | D7: =IF(A7="","",IF($B7=1,Forecast!C7-Setup!$B$5,Forecast!C7)) | E7: =IF(A7="","",IF($B7=1,Forecast!D7-Setup!$B$6,Forecast!D7)) | F7: =IF(A7="","",IF($B7=1,D7-E7,Forecast!E7)) | G7: =IF(A7="","",IF($B7=1,Forecast!F7-Setup!$B$7,Forecast!F7)) | H7: =IF(A7="","",IF($B7=1,Forecast!G7-N(Setup!$D$17)*Setup!$B$9/12,Forecast!G7)) | I7: =IF(A7="","",IF($B7=1,F7-G7-H7,Forecast!H7)) | J7: =IF(A7="","",IF($B7=1,MAX(0,I7)*Setup!$B$10,Forecast!I7)) | K7: =IF(A7="","",IF($B7=1,I7-J7,Forecast!J7)) | L7: =IF(A7="","",IF($B7=1,K7+G7+Forecast!K7,Forecast!L7)) | M7: =IF(A7="","",IF($B7=1,Forecast!M7-Setup!$B$8,Forecast!M7)) | N7: =IF(A7="","",IF($B7=1,L7-M7,Forecast!O7)) | O7: =IF(A7="","",IF($B7=1,N7-Forecast!N7,Forecast!P7)) | P7: =IF(A7="","",(Forecast!$Q$5-Forecast!$P$5)+SUM($O$5:O7))
A8: =IF(Forecast!A8="","",Forecast!A8) | B8: =IF(A8="","",IF(3>=N(Setup!$C$17),1,0)) | C8: =IF(A8="","",IF($B8=1,Forecast!B8-Setup!$B$4,Forecast!B8)) | D8: =IF(A8="","",IF($B8=1,Forecast!C8-Setup!$B$5,Forecast!C8)) | E8: =IF(A8="","",IF($B8=1,Forecast!D8-Setup!$B$6,Forecast!D8)) | F8: =IF(A8="","",IF($B8=1,D8-E8,Forecast!E8)) | G8: =IF(A8="","",IF($B8=1,Forecast!F8-Setup!$B$7,Forecast!F8)) | H8: =IF(A8="","",IF($B8=1,Forecast!G8-N(Setup!$D$17)*Setup!$B$9/12,Forecast!G8)) | I8: =IF(A8="","",IF($B8=1,F8-G8-H8,Forecast!H8)) | J8: =IF(A8="","",IF($B8=1,MAX(0,I8)*Setup!$B$10,Forecast!I8)) | K8: =IF(A8="","",IF($B8=1,I8-J8,Forecast!J8)) | L8: =IF(A8="","",IF($B8=1,K8+G8+Forecast!K8,Forecast!L8)) | M8: =IF(A8="","",IF($B8=1,Forecast!M8-Setup!$B$8,Forecast!M8)) | N8: =IF(A8="","",IF($B8=1,L8-M8,Forecast!O8)) | O8: =IF(A8="","",IF($B8=1,N8-Forecast!N8,Forecast!P8)) | P8: =IF(A8="","",(Forecast!$Q$5-Forecast!$P$5)+SUM($O$5:O8))
A9: =IF(Forecast!A9="","",Forecast!A9) | B9: =IF(A9="","",IF(4>=N(Setup!$C$17),1,0)) | C9: =IF(A9="","",IF($B9=1,Forecast!B9-Setup!$B$4,Forecast!B9)) | D9: =IF(A9="","",IF($B9=1,Forecast!C9-Setup!$B$5,Forecast!C9)) | E9: =IF(A9="","",IF($B9=1,Forecast!D9-Setup!$B$6,Forecast!D9)) | F9: =IF(A9="","",IF($B9=1,D9-E9,Forecast!E9)) | G9: =IF(A9="","",IF($B9=1,Forecast!F9-Setup!$B$7,Forecast!F9)) | H9: =IF(A9="","",IF($B9=1,Forecast!G9-N(Setup!$D$17)*Setup!$B$9/12,Forecast!G9)) | I9: =IF(A9="","",IF($B9=1,F9-G9-H9,Forecast!H9)) | J9: =IF(A9="","",IF($B9=1,MAX(0,I9)*Setup!$B$10,Forecast!I9)) | K9: =IF(A9="","",IF($B9=1,I9-J9,Forecast!J9)) | L9: =IF(A9="","",IF($B9=1,K9+G9+Forecast!K9,Forecast!L9)) | M9: =IF(A9="","",IF($B9=1,Forecast!M9-Setup!$B$8,Forecast!M9)) | N9: =IF(A9="","",IF($B9=1,L9-M9,Forecast!O9)) | O9: =IF(A9="","",IF($B9=1,N9-Forecast!N9,Forecast!P9)) | P9: =IF(A9="","",(Forecast!$Q$5-Forecast!$P$5)+SUM($O$5:O9))
A10: =IF(Forecast!A10="","",Forecast!A10) | B10: =IF(A10="","",IF(5>=N(Setup!$C$17),1,0)) | C10: =IF(A10="","",IF($B10=1,Forecast!B10-Setup!$B$4,Forecast!B10)) | D10: =IF(A10="","",IF($B10=1,Forecast!C10-Setup!$B$5,Forecast!C10)) | E10: =IF(A10="","",IF($B10=1,Forecast!D10-Setup!$B$6,Forecast!D10)) | F10: =IF(A10="","",IF($B10=1,D10-E10,Forecast!E10)) | G10: =IF(A10="","",IF($B10=1,Forecast!F10-Setup!$B$7,Forecast!F10)) | H10: =IF(A10="","",IF($B10=1,Forecast!G10-N(Setup!$D$17)*Setup!$B$9/12,Forecast!G10)) | I10: =IF(A10="","",IF($B10=1,F10-G10-H10,Forecast!H10)) | J10: =IF(A10="","",IF($B10=1,MAX(0,I10)*Setup!$B$10,Forecast!I10)) | K10: =IF(A10="","",IF($B10=1,I10-J10,Forecast!J10)) | L10: =IF(A10="","",IF($B10=1,K10+G10+Forecast!K10,Forecast!L10)) | M10: =IF(A10="","",IF($B10=1,Forecast!M10-Setup!$B$8,Forecast!M10)) | N10: =IF(A10="","",IF($B10=1,L10-M10,Forecast!O10)) | O10: =IF(A10="","",IF($B10=1,N10-Forecast!N10,Forecast!P10)) | P10: =IF(A10="","",(Forecast!$Q$5-Forecast!$P$5)+SUM($O$5:O10))
A11: =IF(Forecast!A11="","",Forecast!A11) | B11: =IF(A11="","",IF(6>=N(Setup!$C$17),1,0)) | C11: =IF(A11="","",IF($B11=1,Forecast!B11-Setup!$B$4,Forecast!B11)) | D11: =IF(A11="","",IF($B11=1,Forecast!C11-Setup!$B$5,Forecast!C11)) | E11: =IF(A11="","",IF($B11=1,Forecast!D11-Setup!$B$6,Forecast!D11)) | F11: =IF(A11="","",IF($B11=1,D11-E11,Forecast!E11)) | G11: =IF(A11="","",IF($B11=1,Forecast!F11-Setup!$B$7,Forecast!F11)) | H11: =IF(A11="","",IF($B11=1,Forecast!G11-N(Setup!$D$17)*Setup!$B$9/12,Forecast!G11)) | I11: =IF(A11="","",IF($B11=1,F11-G11-H11,Forecast!H11)) | J11: =IF(A11="","",IF($B11=1,MAX(0,I11)*Setup!$B$10,Forecast!I11)) | K11: =IF(A11="","",IF($B11=1,I11-J11,Forecast!J11)) | L11: =IF(A11="","",IF($B11=1,K11+G11+Forecast!K11,Forecast!L11)) | M11: =IF(A11="","",IF($B11=1,Forecast!M11-Setup!$B$8,Forecast!M11)) | N11: =IF(A11="","",IF($B11=1,L11-M11,Forecast!O11)) | O11: =IF(A11="","",IF($B11=1,N11-Forecast!N11,Forecast!P11)) | P11: =IF(A11="","",(Forecast!$Q$5-Forecast!$P$5)+SUM($O$5:O11))
A12: =IF(Forecast!A12="","",Forecast!A12) | B12: =IF(A12="","",IF(7>=N(Setup!$C$17),1,0)) | C12: =IF(A12="","",IF($B12=1,Forecast!B12-Setup!$B$4,Forecast!B12)) | D12: =IF(A12="","",IF($B12=1,Forecast!C12-Setup!$B$5,Forecast!C12)) | E12: =IF(A12="","",IF($B12=1,Forecast!D12-Setup!$B$6,Forecast!D12)) | F12: =IF(A12="","",IF($B12=1,D12-E12,Forecast!E12)) | G12: =IF(A12="","",IF($B12=1,Forecast!F12-Setup!$B$7,Forecast!F12)) | H12: =IF(A12="","",IF($B12=1,Forecast!G12-N(Setup!$D$17)*Setup!$B$9/12,Forecast!G12)) | I12: =IF(A12="","",IF($B12=1,F12-G12-H12,Forecast!H12)) | J12: =IF(A12="","",IF($B12=1,MAX(0,I12)*Setup!$B$10,Forecast!I12)) | K12: =IF(A12="","",IF($B12=1,I12-J12,Forecast!J12)) | L12: =IF(A12="","",IF($B12=1,K12+G12+Forecast!K12,Forecast!L12)) | M12: =IF(A12="","",IF($B12=1,Forecast!M12-Setup!$B$8,Forecast!M12)) | N12: =IF(A12="","",IF($B12=1,L12-M12,Forecast!O12)) | O12: =IF(A12="","",IF($B12=1,N12-Forecast!N12,Forecast!P12)) | P12: =IF(A12="","",(Forecast!$Q$5-Forecast!$P$5)+SUM($O$5:O12))
A13: =IF(Forecast!A13="","",Forecast!A13) | B13: =IF(A13="","",IF(8>=N(Setup!$C$17),1,0)) | C13: =IF(A13="","",IF($B13=1,Forecast!B13-Setup!$B$4,Forecast!B13)) | D13: =IF(A13="","",IF($B13=1,Forecast!C13-Setup!$B$5,Forecast!C13)) | E13: =IF(A13="","",IF($B13=1,Forecast!D13-Setup!$B$6,Forecast!D13)) | F13: =IF(A13="","",IF($B13=1,D13-E13,Forecast!E13)) | G13: =IF(A13="","",IF($B13=1,Forecast!F13-Setup!$B$7,Forecast!F13)) | H13: =IF(A13="","",IF($B13=1,Forecast!G13-N(Setup!$D$17)*Setup!$B$9/12,Forecast!G13)) | I13: =IF(A13="","",IF($B13=1,F13-G13-H13,Forecast!H13)) | J13: =IF(A13="","",IF($B13=1,MAX(0,I13)*Setup!$B$10,Forecast!I13)) | K13: =IF(A13="","",IF($B13=1,I13-J13,Forecast!J13)) | L13: =IF(A13="","",IF($B13=1,K13+G13+Forecast!K13,Forecast!L13)) | M13: =IF(A13="","",IF($B13=1,Forecast!M13-Setup!$B$8,Forecast!M13)) | N13: =IF(A13="","",IF($B13=1,L13-M13,Forecast!O13)) | O13: =IF(A13="","",IF($B13=1,N13-Forecast!N13,Forecast!P13)) | P13: =IF(A13="","",(Forecast!$Q$5-Forecast!$P$5)+SUM($O$5:O13))
A14: =IF(Forecast!A14="","",Forecast!A14) | B14: =IF(A14="","",IF(9>=N(Setup!$C$17),1,0)) | C14: =IF(A14="","",IF($B14=1,Forecast!B14-Setup!$B$4,Forecast!B14)) | D14: =IF(A14="","",IF($B14=1,Forecast!C14-Setup!$B$5,Forecast!C14)) | E14: =IF(A14="","",IF($B14=1,Forecast!D14-Setup!$B$6,Forecast!D14)) | F14: =IF(A14="","",IF($B14=1,D14-E14,Forecast!E14)) | G14: =IF(A14="","",IF($B14=1,Forecast!F14-Setup!$B$7,Forecast!F14)) | H14: =IF(A14="","",IF($B14=1,Forecast!G14-N(Setup!$D$17)*Setup!$B$9/12,Forecast!G14)) | I14: =IF(A14="","",IF($B14=1,F14-G14-H14,Forecast!H14)) | J14: =IF(A14="","",IF($B14=1,MAX(0,I14)*Setup!$B$10,Forecast!I14)) | K14: =IF(A14="","",IF($B14=1,I14-J14,Forecast!J14)) | L14: =IF(A14="","",IF($B14=1,K14+G14+Forecast!K14,Forecast!L14)) | M14: =IF(A14="","",IF($B14=1,Forecast!M14-Setup!$B$8,Forecast!M14)) | N14: =IF(A14="","",IF($B14=1,L14-M14,Forecast!O14)) | O14: =IF(A14="","",IF($B14=1,N14-Forecast!N14,Forecast!P14)) | P14: =IF(A14="","",(Forecast!$Q$5-Forecast!$P$5)+SUM($O$5:O14))
A15: =IF(Forecast!A15="","",Forecast!A15) | B15: =IF(A15="","",IF(10>=N(Setup!$C$17),1,0)) | C15: =IF(A15="","",IF($B15=1,Forecast!B15-Setup!$B$4,Forecast!B15)) | D15: =IF(A15="","",IF($B15=1,Forecast!C15-Setup!$B$5,Forecast!C15)) | E15: =IF(A15="","",IF($B15=1,Forecast!D15-Setup!$B$6,Forecast!D15)) | F15: =IF(A15="","",IF($B15=1,D15-E15,Forecast!E15)) | G15: =IF(A15="","",IF($B15=1,Forecast!F15-Setup!$B$7,Forecast!F15)) | H15: =IF(A15="","",IF($B15=1,Forecast!G15-N(Setup!$D$17)*Setup!$B$9/12,Forecast!G15)) | I15: =IF(A15="","",IF($B15=1,F15-G15-H15,Forecast!H15)) | J15: =IF(A15="","",IF($B15=1,MAX(0,I15)*Setup!$B$10,Forecast!I15)) | K15: =IF(A15="","",IF($B15=1,I15-J15,Forecast!J15)) | L15: =IF(A15="","",IF($B15=1,K15+G15+Forecast!K15,Forecast!L15)) | M15: =IF(A15="","",IF($B15=1,Forecast!M15-Setup!$B$8,Forecast!M15)) | N15: =IF(A15="","",IF($B15=1,L15-M15,Forecast!O15)) | O15: =IF(A15="","",IF($B15=1,N15-Forecast!N15,Forecast!P15)) | P15: =IF(A15="","",(Forecast!$Q$5-Forecast!$P$5)+SUM($O$5:O15))
A16: =IF(Forecast!A16="","",Forecast!A16) | B16: =IF(A16="","",IF(11>=N(Setup!$C$17),1,0)) | C16: =IF(A16="","",IF($B16=1,Forecast!B16-Setup!$B$4,Forecast!B16)) | D16: =IF(A16="","",IF($B16=1,Forecast!C16-Setup!$B$5,Forecast!C16)) | E16: =IF(A16="","",IF($B16=1,Forecast!D16-Setup!$B$6,Forecast!D16)) | F16: =IF(A16="","",IF($B16=1,D16-E16,Forecast!E16)) | G16: =IF(A16="","",IF($B16=1,Forecast!F16-Setup!$B$7,Forecast!F16)) | H16: =IF(A16="","",IF($B16=1,Forecast!G16-N(Setup!$D$17)*Setup!$B$9/12,Forecast!G16)) | I16: =IF(A16="","",IF($B16=1,F16-G16-H16,Forecast!H16)) | J16: =IF(A16="","",IF($B16=1,MAX(0,I16)*Setup!$B$10,Forecast!I16)) | K16: =IF(A16="","",IF($B16=1,I16-J16,Forecast!J16)) | L16: =IF(A16="","",IF($B16=1,K16+G16+Forecast!K16,Forecast!L16)) | M16: =IF(A16="","",IF($B16=1,Forecast!M16-Setup!$B$8,Forecast!M16)) | N16: =IF(A16="","",IF($B16=1,L16-M16,Forecast!O16)) | O16: =IF(A16="","",IF($B16=1,N16-Forecast!N16,Forecast!P16)) | P16: =IF(A16="","",(Forecast!$Q$5-Forecast!$P$5)+SUM($O$5:O16))
A17: =IF(Forecast!A17="","",Forecast!A17) | B17: =IF(A17="","",IF(12>=N(Setup!$C$17),1,0)) | C17: =IF(A17="","",IF($B17=1,Forecast!B17-Setup!$B$4,Forecast!B17)) | D17: =IF(A17="","",IF($B17=1,Forecast!C17-Setup!$B$5,Forecast!C17)) | E17: =IF(A17="","",IF($B17=1,Forecast!D17-Setup!$B$6,Forecast!D17)) | F17: =IF(A17="","",IF($B17=1,D17-E17,Forecast!E17)) | G17: =IF(A17="","",IF($B17=1,Forecast!F17-Setup!$B$7,Forecast!F17)) | H17: =IF(A17="","",IF($B17=1,Forecast!G17-N(Setup!$D$17)*Setup!$B$9/12,Forecast!G17)) | I17: =IF(A17="","",IF($B17=1,F17-G17-H17,Forecast!H17)) | J17: =IF(A17="","",IF($B17=1,MAX(0,I17)*Setup!$B$10,Forecast!I17)) | K17: =IF(A17="","",IF($B17=1,I17-J17,Forecast!J17)) | L17: =IF(A17="","",IF($B17=1,K17+G17+Forecast!K17,Forecast!L17)) | M17: =IF(A17="","",IF($B17=1,Forecast!M17-Setup!$B$8,Forecast!M17)) | N17: =IF(A17="","",IF($B17=1,L17-M17,Forecast!O17)) | O17: =IF(A17="","",IF($B17=1,N17-Forecast!N17,Forecast!P17)) | P17: =IF(A17="","",(Forecast!$Q$5-Forecast!$P$5)+SUM($O$5:O17))
A18: =IF(Forecast!A18="","",Forecast!A18) | B18: =IF(A18="","",IF(13>=N(Setup!$C$17),1,0)) | C18: =IF(A18="","",IF($B18=1,Forecast!B18-Setup!$B$4,Forecast!B18)) | D18: =IF(A18="","",IF($B18=1,Forecast!C18-Setup!$B$5,Forecast!C18)) | E18: =IF(A18="","",IF($B18=1,Forecast!D18-Setup!$B$6,Forecast!D18)) | F18: =IF(A18="","",IF($B18=1,D18-E18,Forecast!E18)) | G18: =IF(A18="","",IF($B18=1,Forecast!F18-Setup!$B$7,Forecast!F18)) | H18: =IF(A18="","",IF($B18=1,Forecast!G18-N(Setup!$D$17)*Setup!$B$9/12,Forecast!G18)) | I18: =IF(A18="","",IF($B18=1,F18-G18-H18,Forecast!H18)) | J18: =IF(A18="","",IF($B18=1,MAX(0,I18)*Setup!$B$10,Forecast!I18)) | K18: =IF(A18="","",IF($B18=1,I18-J18,Forecast!J18)) | L18: =IF(A18="","",IF($B18=1,K18+G18+Forecast!K18,Forecast!L18)) | M18: =IF(A18="","",IF($B18=1,Forecast!M18-Setup!$B$8,Forecast!M18)) | N18: =IF(A18="","",IF($B18=1,L18-M18,Forecast!O18)) | O18: =IF(A18="","",IF($B18=1,N18-Forecast!N18,Forecast!P18)) | P18: =IF(A18="","",(Forecast!$Q$5-Forecast!$P$5)+SUM($O$5:O18))
A19: =IF(Forecast!A19="","",Forecast!A19) | B19: =IF(A19="","",IF(14>=N(Setup!$C$17),1,0)) | C19: =IF(A19="","",IF($B19=1,Forecast!B19-Setup!$B$4,Forecast!B19)) | D19: =IF(A19="","",IF($B19=1,Forecast!C19-Setup!$B$5,Forecast!C19)) | E19: =IF(A19="","",IF($B19=1,Forecast!D19-Setup!$B$6,Forecast!D19)) | F19: =IF(A19="","",IF($B19=1,D19-E19,Forecast!E19)) | G19: =IF(A19="","",IF($B19=1,Forecast!F19-Setup!$B$7,Forecast!F19)) | H19: =IF(A19="","",IF($B19=1,Forecast!G19-N(Setup!$D$17)*Setup!$B$9/12,Forecast!G19)) | I19: =IF(A19="","",IF($B19=1,F19-G19-H19,Forecast!H19)) | J19: =IF(A19="","",IF($B19=1,MAX(0,I19)*Setup!$B$10,Forecast!I19)) | K19: =IF(A19="","",IF($B19=1,I19-J19,Forecast!J19)) | L19: =IF(A19="","",IF($B19=1,K19+G19+Forecast!K19,Forecast!L19)) | M19: =IF(A19="","",IF($B19=1,Forecast!M19-Setup!$B$8,Forecast!M19)) | N19: =IF(A19="","",IF($B19=1,L19-M19,Forecast!O19)) | O19: =IF(A19="","",IF($B19=1,N19-Forecast!N19,Forecast!P19)) | P19: =IF(A19="","",(Forecast!$Q$5-Forecast!$P$5)+SUM($O$5:O19))
A20: =IF(Forecast!A20="","",Forecast!A20) | B20: =IF(A20="","",IF(15>=N(Setup!$C$17),1,0)) | C20: =IF(A20="","",IF($B20=1,Forecast!B20-Setup!$B$4,Forecast!B20)) | D20: =IF(A20="","",IF($B20=1,Forecast!C20-Setup!$B$5,Forecast!C20)) | E20: =IF(A20="","",IF($B20=1,Forecast!D20-Setup!$B$6,Forecast!D20)) | F20: =IF(A20="","",IF($B20=1,D20-E20,Forecast!E20)) | G20: =IF(A20="","",IF($B20=1,Forecast!F20-Setup!$B$7,Forecast!F20)) | H20: =IF(A20="","",IF($B20=1,Forecast!G20-N(Setup!$D$17)*Setup!$B$9/12,Forecast!G20)) | I20: =IF(A20="","",IF($B20=1,F20-G20-H20,Forecast!H20)) | J20: =IF(A20="","",IF($B20=1,MAX(0,I20)*Setup!$B$10,Forecast!I20)) | K20: =IF(A20="","",IF($B20=1,I20-J20,Forecast!J20)) | L20: =IF(A20="","",IF($B20=1,K20+G20+Forecast!K20,Forecast!L20)) | M20: =IF(A20="","",IF($B20=1,Forecast!M20-Setup!$B$8,Forecast!M20)) | N20: =IF(A20="","",IF($B20=1,L20-M20,Forecast!O20)) | O20: =IF(A20="","",IF($B20=1,N20-Forecast!N20,Forecast!P20)) | P20: =IF(A20="","",(Forecast!$Q$5-Forecast!$P$5)+SUM($O$5:O20))
A21: =IF(Forecast!A21="","",Forecast!A21) | B21: =IF(A21="","",IF(16>=N(Setup!$C$17),1,0)) | C21: =IF(A21="","",IF($B21=1,Forecast!B21-Setup!$B$4,Forecast!B21)) | D21: =IF(A21="","",IF($B21=1,Forecast!C21-Setup!$B$5,Forecast!C21)) | E21: =IF(A21="","",IF($B21=1,Forecast!D21-Setup!$B$6,Forecast!D21)) | F21: =IF(A21="","",IF($B21=1,D21-E21,Forecast!E21)) | G21: =IF(A21="","",IF($B21=1,Forecast!F21-Setup!$B$7,Forecast!F21)) | H21: =IF(A21="","",IF($B21=1,Forecast!G21-N(Setup!$D$17)*Setup!$B$9/12,Forecast!G21)) | I21: =IF(A21="","",IF($B21=1,F21-G21-H21,Forecast!H21)) | J21: =IF(A21="","",IF($B21=1,MAX(0,I21)*Setup!$B$10,Forecast!I21)) | K21: =IF(A21="","",IF($B21=1,I21-J21,Forecast!J21)) | L21: =IF(A21="","",IF($B21=1,K21+G21+Forecast!K21,Forecast!L21)) | M21: =IF(A21="","",IF($B21=1,Forecast!M21-Setup!$B$8,Forecast!M21)) | N21: =IF(A21="","",IF($B21=1,L21-M21,Forecast!O21)) | O21: =IF(A21="","",IF($B21=1,N21-Forecast!N21,Forecast!P21)) | P21: =IF(A21="","",(Forecast!$Q$5-Forecast!$P$5)+SUM($O$5:O21))
A22: =IF(Forecast!A22="","",Forecast!A22) | B22: =IF(A22="","",IF(17>=N(Setup!$C$17),1,0)) | C22: =IF(A22="","",IF($B22=1,Forecast!B22-Setup!$B$4,Forecast!B22)) | D22: =IF(A22="","",IF($B22=1,Forecast!C22-Setup!$B$5,Forecast!C22)) | E22: =IF(A22="","",IF($B22=1,Forecast!D22-Setup!$B$6,Forecast!D22)) | F22: =IF(A22="","",IF($B22=1,D22-E22,Forecast!E22)) | G22: =IF(A22="","",IF($B22=1,Forecast!F22-Setup!$B$7,Forecast!F22)) | H22: =IF(A22="","",IF($B22=1,Forecast!G22-N(Setup!$D$17)*Setup!$B$9/12,Forecast!G22)) | I22: =IF(A22="","",IF($B22=1,F22-G22-H22,Forecast!H22)) | J22: =IF(A22="","",IF($B22=1,MAX(0,I22)*Setup!$B$10,Forecast!I22)) | K22: =IF(A22="","",IF($B22=1,I22-J22,Forecast!J22)) | L22: =IF(A22="","",IF($B22=1,K22+G22+Forecast!K22,Forecast!L22)) | M22: =IF(A22="","",IF($B22=1,Forecast!M22-Setup!$B$8,Forecast!M22)) | N22: =IF(A22="","",IF($B22=1,L22-M22,Forecast!O22)) | O22: =IF(A22="","",IF($B22=1,N22-Forecast!N22,Forecast!P22)) | P22: =IF(A22="","",(Forecast!$Q$5-Forecast!$P$5)+SUM($O$5:O22))
A23: =IF(Forecast!A23="","",Forecast!A23) | B23: =IF(A23="","",IF(18>=N(Setup!$C$17),1,0)) | C23: =IF(A23="","",IF($B23=1,Forecast!B23-Setup!$B$4,Forecast!B23)) | D23: =IF(A23="","",IF($B23=1,Forecast!C23-Setup!$B$5,Forecast!C23)) | E23: =IF(A23="","",IF($B23=1,Forecast!D23-Setup!$B$6,Forecast!D23)) | F23: =IF(A23="","",IF($B23=1,D23-E23,Forecast!E23)) | G23: =IF(A23="","",IF($B23=1,Forecast!F23-Setup!$B$7,Forecast!F23)) | H23: =IF(A23="","",IF($B23=1,Forecast!G23-N(Setup!$D$17)*Setup!$B$9/12,Forecast!G23)) | I23: =IF(A23="","",IF($B23=1,F23-G23-H23,Forecast!H23)) | J23: =IF(A23="","",IF($B23=1,MAX(0,I23)*Setup!$B$10,Forecast!I23)) | K23: =IF(A23="","",IF($B23=1,I23-J23,Forecast!J23)) | L23: =IF(A23="","",IF($B23=1,K23+G23+Forecast!K23,Forecast!L23)) | M23: =IF(A23="","",IF($B23=1,Forecast!M23-Setup!$B$8,Forecast!M23)) | N23: =IF(A23="","",IF($B23=1,L23-M23,Forecast!O23)) | O23: =IF(A23="","",IF($B23=1,N23-Forecast!N23,Forecast!P23)) | P23: =IF(A23="","",(Forecast!$Q$5-Forecast!$P$5)+SUM($O$5:O23))
A24: =IF(Forecast!A24="","",Forecast!A24) | B24: =IF(A24="","",IF(19>=N(Setup!$C$17),1,0)) | C24: =IF(A24="","",IF($B24=1,Forecast!B24-Setup!$B$4,Forecast!B24)) | D24: =IF(A24="","",IF($B24=1,Forecast!C24-Setup!$B$5,Forecast!C24)) | E24: =IF(A24="","",IF($B24=1,Forecast!D24-Setup!$B$6,Forecast!D24)) | F24: =IF(A24="","",IF($B24=1,D24-E24,Forecast!E24)) | G24: =IF(A24="","",IF($B24=1,Forecast!F24-Setup!$B$7,Forecast!F24)) | H24: =IF(A24="","",IF($B24=1,Forecast!G24-N(Setup!$D$17)*Setup!$B$9/12,Forecast!G24)) | I24: =IF(A24="","",IF($B24=1,F24-G24-H24,Forecast!H24)) | J24: =IF(A24="","",IF($B24=1,MAX(0,I24)*Setup!$B$10,Forecast!I24)) | K24: =IF(A24="","",IF($B24=1,I24-J24,Forecast!J24)) | L24: =IF(A24="","",IF($B24=1,K24+G24+Forecast!K24,Forecast!L24)) | M24: =IF(A24="","",IF($B24=1,Forecast!M24-Setup!$B$8,Forecast!M24)) | N24: =IF(A24="","",IF($B24=1,L24-M24,Forecast!O24)) | O24: =IF(A24="","",IF($B24=1,N24-Forecast!N24,Forecast!P24)) | P24: =IF(A24="","",(Forecast!$Q$5-Forecast!$P$5)+SUM($O$5:O24))
A25: =IF(Forecast!A25="","",Forecast!A25) | B25: =IF(A25="","",IF(20>=N(Setup!$C$17),1,0)) | C25: =IF(A25="","",IF($B25=1,Forecast!B25-Setup!$B$4,Forecast!B25)) | D25: =IF(A25="","",IF($B25=1,Forecast!C25-Setup!$B$5,Forecast!C25)) | E25: =IF(A25="","",IF($B25=1,Forecast!D25-Setup!$B$6,Forecast!D25)) | F25: =IF(A25="","",IF($B25=1,D25-E25,Forecast!E25)) | G25: =IF(A25="","",IF($B25=1,Forecast!F25-Setup!$B$7,Forecast!F25)) | H25: =IF(A25="","",IF($B25=1,Forecast!G25-N(Setup!$D$17)*Setup!$B$9/12,Forecast!G25)) | I25: =IF(A25="","",IF($B25=1,F25-G25-H25,Forecast!H25)) | J25: =IF(A25="","",IF($B25=1,MAX(0,I25)*Setup!$B$10,Forecast!I25)) | K25: =IF(A25="","",IF($B25=1,I25-J25,Forecast!J25)) | L25: =IF(A25="","",IF($B25=1,K25+G25+Forecast!K25,Forecast!L25)) | M25: =IF(A25="","",IF($B25=1,Forecast!M25-Setup!$B$8,Forecast!M25)) | N25: =IF(A25="","",IF($B25=1,L25-M25,Forecast!O25)) | O25: =IF(A25="","",IF($B25=1,N25-Forecast!N25,Forecast!P25)) | P25: =IF(A25="","",(Forecast!$Q$5-Forecast!$P$5)+SUM($O$5:O25))
A26: =IF(Forecast!A26="","",Forecast!A26) | B26: =IF(A26="","",IF(21>=N(Setup!$C$17),1,0)) | C26: =IF(A26="","",IF($B26=1,Forecast!B26-Setup!$B$4,Forecast!B26)) | D26: =IF(A26="","",IF($B26=1,Forecast!C26-Setup!$B$5,Forecast!C26)) | E26: =IF(A26="","",IF($B26=1,Forecast!D26-Setup!$B$6,Forecast!D26)) | F26: =IF(A26="","",IF($B26=1,D26-E26,Forecast!E26)) | G26: =IF(A26="","",IF($B26=1,Forecast!F26-Setup!$B$7,Forecast!F26)) | H26: =IF(A26="","",IF($B26=1,Forecast!G26-N(Setup!$D$17)*Setup!$B$9/12,Forecast!G26)) | I26: =IF(A26="","",IF($B26=1,F26-G26-H26,Forecast!H26)) | J26: =IF(A26="","",IF($B26=1,MAX(0,I26)*Setup!$B$10,Forecast!I26)) | K26: =IF(A26="","",IF($B26=1,I26-J26,Forecast!J26)) | L26: =IF(A26="","",IF($B26=1,K26+G26+Forecast!K26,Forecast!L26)) | M26: =IF(A26="","",IF($B26=1,Forecast!M26-Setup!$B$8,Forecast!M26)) | N26: =IF(A26="","",IF($B26=1,L26-M26,Forecast!O26)) | O26: =IF(A26="","",IF($B26=1,N26-Forecast!N26,Forecast!P26)) | P26: =IF(A26="","",(Forecast!$Q$5-Forecast!$P$5)+SUM($O$5:O26))
A27: =IF(Forecast!A27="","",Forecast!A27) | B27: =IF(A27="","",IF(22>=N(Setup!$C$17),1,0)) | C27: =IF(A27="","",IF($B27=1,Forecast!B27-Setup!$B$4,Forecast!B27)) | D27: =IF(A27="","",IF($B27=1,Forecast!C27-Setup!$B$5,Forecast!C27)) | E27: =IF(A27="","",IF($B27=1,Forecast!D27-Setup!$B$6,Forecast!D27)) | F27: =IF(A27="","",IF($B27=1,D27-E27,Forecast!E27)) | G27: =IF(A27="","",IF($B27=1,Forecast!F27-Setup!$B$7,Forecast!F27)) | H27: =IF(A27="","",IF($B27=1,Forecast!G27-N(Setup!$D$17)*Setup!$B$9/12,Forecast!G27)) | I27: =IF(A27="","",IF($B27=1,F27-G27-H27,Forecast!H27)) | J27: =IF(A27="","",IF($B27=1,MAX(0,I27)*Setup!$B$10,Forecast!I27)) | K27: =IF(A27="","",IF($B27=1,I27-J27,Forecast!J27)) | L27: =IF(A27="","",IF($B27=1,K27+G27+Forecast!K27,Forecast!L27)) | M27: =IF(A27="","",IF($B27=1,Forecast!M27-Setup!$B$8,Forecast!M27)) | N27: =IF(A27="","",IF($B27=1,L27-M27,Forecast!O27)) | O27: =IF(A27="","",IF($B27=1,N27-Forecast!N27,Forecast!P27)) | P27: =IF(A27="","",(Forecast!$Q$5-Forecast!$P$5)+SUM($O$5:O27))
A28: =IF(Forecast!A28="","",Forecast!A28) | B28: =IF(A28="","",IF(23>=N(Setup!$C$17),1,0)) | C28: =IF(A28="","",IF($B28=1,Forecast!B28-Setup!$B$4,Forecast!B28)) | D28: =IF(A28="","",IF($B28=1,Forecast!C28-Setup!$B$5,Forecast!C28)) | E28: =IF(A28="","",IF($B28=1,Forecast!D28-Setup!$B$6,Forecast!D28)) | F28: =IF(A28="","",IF($B28=1,D28-E28,Forecast!E28)) | G28: =IF(A28="","",IF($B28=1,Forecast!F28-Setup!$B$7,Forecast!F28)) | H28: =IF(A28="","",IF($B28=1,Forecast!G28-N(Setup!$D$17)*Setup!$B$9/12,Forecast!G28)) | I28: =IF(A28="","",IF($B28=1,F28-G28-H28,Forecast!H28)) | J28: =IF(A28="","",IF($B28=1,MAX(0,I28)*Setup!$B$10,Forecast!I28)) | K28: =IF(A28="","",IF($B28=1,I28-J28,Forecast!J28)) | L28: =IF(A28="","",IF($B28=1,K28+G28+Forecast!K28,Forecast!L28)) | M28: =IF(A28="","",IF($B28=1,Forecast!M28-Setup!$B$8,Forecast!M28)) | N28: =IF(A28="","",IF($B28=1,L28-M28,Forecast!O28)) | O28: =IF(A28="","",IF($B28=1,N28-Forecast!N28,Forecast!P28)) | P28: =IF(A28="","",(Forecast!$Q$5-Forecast!$P$5)+SUM($O$5:O28))
A29: =IF(Forecast!A29="","",Forecast!A29) | B29: =IF(A29="","",IF(24>=N(Setup!$C$17),1,0)) | C29: =IF(A29="","",IF($B29=1,Forecast!B29-Setup!$B$4,Forecast!B29)) | D29: =IF(A29="","",IF($B29=1,Forecast!C29-Setup!$B$5,Forecast!C29)) | E29: =IF(A29="","",IF($B29=1,Forecast!D29-Setup!$B$6,Forecast!D29)) | F29: =IF(A29="","",IF($B29=1,D29-E29,Forecast!E29)) | G29: =IF(A29="","",IF($B29=1,Forecast!F29-Setup!$B$7,Forecast!F29)) | H29: =IF(A29="","",IF($B29=1,Forecast!G29-N(Setup!$D$17)*Setup!$B$9/12,Forecast!G29)) | I29: =IF(A29="","",IF($B29=1,F29-G29-H29,Forecast!H29)) | J29: =IF(A29="","",IF($B29=1,MAX(0,I29)*Setup!$B$10,Forecast!I29)) | K29: =IF(A29="","",IF($B29=1,I29-J29,Forecast!J29)) | L29: =IF(A29="","",IF($B29=1,K29+G29+Forecast!K29,Forecast!L29)) | M29: =IF(A29="","",IF($B29=1,Forecast!M29-Setup!$B$8,Forecast!M29)) | N29: =IF(A29="","",IF($B29=1,L29-M29,Forecast!O29)) | O29: =IF(A29="","",IF($B29=1,N29-Forecast!N29,Forecast!P29)) | P29: =IF(A29="","",(Forecast!$Q$5-Forecast!$P$5)+SUM($O$5:O29))
A30: =IF(Forecast!A30="","",Forecast!A30) | B30: =IF(A30="","",IF(25>=N(Setup!$C$17),1,0)) | C30: =IF(A30="","",IF($B30=1,Forecast!B30-Setup!$B$4,Forecast!B30)) | D30: =IF(A30="","",IF($B30=1,Forecast!C30-Setup!$B$5,Forecast!C30)) | E30: =IF(A30="","",IF($B30=1,Forecast!D30-Setup!$B$6,Forecast!D30)) | F30: =IF(A30="","",IF($B30=1,D30-E30,Forecast!E30)) | G30: =IF(A30="","",IF($B30=1,Forecast!F30-Setup!$B$7,Forecast!F30)) | H30: =IF(A30="","",IF($B30=1,Forecast!G30-N(Setup!$D$17)*Setup!$B$9/12,Forecast!G30)) | I30: =IF(A30="","",IF($B30=1,F30-G30-H30,Forecast!H30)) | J30: =IF(A30="","",IF($B30=1,MAX(0,I30)*Setup!$B$10,Forecast!I30)) | K30: =IF(A30="","",IF($B30=1,I30-J30,Forecast!J30)) | L30: =IF(A30="","",IF($B30=1,K30+G30+Forecast!K30,Forecast!L30)) | M30: =IF(A30="","",IF($B30=1,Forecast!M30-Setup!$B$8,Forecast!M30)) | N30: =IF(A30="","",IF($B30=1,L30-M30,Forecast!O30)) | O30: =IF(A30="","",IF($B30=1,N30-Forecast!N30,Forecast!P30)) | P30: =IF(A30="","",(Forecast!$Q$5-Forecast!$P$5)+SUM($O$5:O30))
A31: =IF(Forecast!A31="","",Forecast!A31) | B31: =IF(A31="","",IF(26>=N(Setup!$C$17),1,0)) | C31: =IF(A31="","",IF($B31=1,Forecast!B31-Setup!$B$4,Forecast!B31)) | D31: =IF(A31="","",IF($B31=1,Forecast!C31-Setup!$B$5,Forecast!C31)) | E31: =IF(A31="","",IF($B31=1,Forecast!D31-Setup!$B$6,Forecast!D31)) | F31: =IF(A31="","",IF($B31=1,D31-E31,Forecast!E31)) | G31: =IF(A31="","",IF($B31=1,Forecast!F31-Setup!$B$7,Forecast!F31)) | H31: =IF(A31="","",IF($B31=1,Forecast!G31-N(Setup!$D$17)*Setup!$B$9/12,Forecast!G31)) | I31: =IF(A31="","",IF($B31=1,F31-G31-H31,Forecast!H31)) | J31: =IF(A31="","",IF($B31=1,MAX(0,I31)*Setup!$B$10,Forecast!I31)) | K31: =IF(A31="","",IF($B31=1,I31-J31,Forecast!J31)) | L31: =IF(A31="","",IF($B31=1,K31+G31+Forecast!K31,Forecast!L31)) | M31: =IF(A31="","",IF($B31=1,Forecast!M31-Setup!$B$8,Forecast!M31)) | N31: =IF(A31="","",IF($B31=1,L31-M31,Forecast!O31)) | O31: =IF(A31="","",IF($B31=1,N31-Forecast!N31,Forecast!P31)) | P31: =IF(A31="","",(Forecast!$Q$5-Forecast!$P$5)+SUM($O$5:O31))
A32: =IF(Forecast!A32="","",Forecast!A32) | B32: =IF(A32="","",IF(27>=N(Setup!$C$17),1,0)) | C32: =IF(A32="","",IF($B32=1,Forecast!B32-Setup!$B$4,Forecast!B32)) | D32: =IF(A32="","",IF($B32=1,Forecast!C32-Setup!$B$5,Forecast!C32)) | E32: =IF(A32="","",IF($B32=1,Forecast!D32-Setup!$B$6,Forecast!D32)) | F32: =IF(A32="","",IF($B32=1,D32-E32,Forecast!E32)) | G32: =IF(A32="","",IF($B32=1,Forecast!F32-Setup!$B$7,Forecast!F32)) | H32: =IF(A32="","",IF($B32=1,Forecast!G32-N(Setup!$D$17)*Setup!$B$9/12,Forecast!G32)) | I32: =IF(A32="","",IF($B32=1,F32-G32-H32,Forecast!H32)) | J32: =IF(A32="","",IF($B32=1,MAX(0,I32)*Setup!$B$10,Forecast!I32)) | K32: =IF(A32="","",IF($B32=1,I32-J32,Forecast!J32)) | L32: =IF(A32="","",IF($B32=1,K32+G32+Forecast!K32,Forecast!L32)) | M32: =IF(A32="","",IF($B32=1,Forecast!M32-Setup!$B$8,Forecast!M32)) | N32: =IF(A32="","",IF($B32=1,L32-M32,Forecast!O32)) | O32: =IF(A32="","",IF($B32=1,N32-Forecast!N32,Forecast!P32)) | P32: =IF(A32="","",(Forecast!$Q$5-Forecast!$P$5)+SUM($O$5:O32))
A33: =IF(Forecast!A33="","",Forecast!A33) | B33: =IF(A33="","",IF(28>=N(Setup!$C$17),1,0)) | C33: =IF(A33="","",IF($B33=1,Forecast!B33-Setup!$B$4,Forecast!B33)) | D33: =IF(A33="","",IF($B33=1,Forecast!C33-Setup!$B$5,Forecast!C33)) | E33: =IF(A33="","",IF($B33=1,Forecast!D33-Setup!$B$6,Forecast!D33)) | F33: =IF(A33="","",IF($B33=1,D33-E33,Forecast!E33)) | G33: =IF(A33="","",IF($B33=1,Forecast!F33-Setup!$B$7,Forecast!F33)) | H33: =IF(A33="","",IF($B33=1,Forecast!G33-N(Setup!$D$17)*Setup!$B$9/12,Forecast!G33)) | I33: =IF(A33="","",IF($B33=1,F33-G33-H33,Forecast!H33)) | J33: =IF(A33="","",IF($B33=1,MAX(0,I33)*Setup!$B$10,Forecast!I33)) | K33: =IF(A33="","",IF($B33=1,I33-J33,Forecast!J33)) | L33: =IF(A33="","",IF($B33=1,K33+G33+Forecast!K33,Forecast!L33)) | M33: =IF(A33="","",IF($B33=1,Forecast!M33-Setup!$B$8,Forecast!M33)) | N33: =IF(A33="","",IF($B33=1,L33-M33,Forecast!O33)) | O33: =IF(A33="","",IF($B33=1,N33-Forecast!N33,Forecast!P33)) | P33: =IF(A33="","",(Forecast!$Q$5-Forecast!$P$5)+SUM($O$5:O33))
A34: =IF(Forecast!A34="","",Forecast!A34) | B34: =IF(A34="","",IF(29>=N(Setup!$C$17),1,0)) | C34: =IF(A34="","",IF($B34=1,Forecast!B34-Setup!$B$4,Forecast!B34)) | D34: =IF(A34="","",IF($B34=1,Forecast!C34-Setup!$B$5,Forecast!C34)) | E34: =IF(A34="","",IF($B34=1,Forecast!D34-Setup!$B$6,Forecast!D34)) | F34: =IF(A34="","",IF($B34=1,D34-E34,Forecast!E34)) | G34: =IF(A34="","",IF($B34=1,Forecast!F34-Setup!$B$7,Forecast!F34)) | H34: =IF(A34="","",IF($B34=1,Forecast!G34-N(Setup!$D$17)*Setup!$B$9/12,Forecast!G34)) | I34: =IF(A34="","",IF($B34=1,F34-G34-H34,Forecast!H34)) | J34: =IF(A34="","",IF($B34=1,MAX(0,I34)*Setup!$B$10,Forecast!I34)) | K34: =IF(A34="","",IF($B34=1,I34-J34,Forecast!J34)) | L34: =IF(A34="","",IF($B34=1,K34+G34+Forecast!K34,Forecast!L34)) | M34: =IF(A34="","",IF($B34=1,Forecast!M34-Setup!$B$8,Forecast!M34)) | N34: =IF(A34="","",IF($B34=1,L34-M34,Forecast!O34)) | O34: =IF(A34="","",IF($B34=1,N34-Forecast!N34,Forecast!P34)) | P34: =IF(A34="","",(Forecast!$Q$5-Forecast!$P$5)+SUM($O$5:O34))
A35: =IF(Forecast!A35="","",Forecast!A35) | B35: =IF(A35="","",IF(30>=N(Setup!$C$17),1,0)) | C35: =IF(A35="","",IF($B35=1,Forecast!B35-Setup!$B$4,Forecast!B35)) | D35: =IF(A35="","",IF($B35=1,Forecast!C35-Setup!$B$5,Forecast!C35)) | E35: =IF(A35="","",IF($B35=1,Forecast!D35-Setup!$B$6,Forecast!D35)) | F35: =IF(A35="","",IF($B35=1,D35-E35,Forecast!E35)) | G35: =IF(A35="","",IF($B35=1,Forecast!F35-Setup!$B$7,Forecast!F35)) | H35: =IF(A35="","",IF($B35=1,Forecast!G35-N(Setup!$D$17)*Setup!$B$9/12,Forecast!G35)) | I35: =IF(A35="","",IF($B35=1,F35-G35-H35,Forecast!H35)) | J35: =IF(A35="","",IF($B35=1,MAX(0,I35)*Setup!$B$10,Forecast!I35)) | K35: =IF(A35="","",IF($B35=1,I35-J35,Forecast!J35)) | L35: =IF(A35="","",IF($B35=1,K35+G35+Forecast!K35,Forecast!L35)) | M35: =IF(A35="","",IF($B35=1,Forecast!M35-Setup!$B$8,Forecast!M35)) | N35: =IF(A35="","",IF($B35=1,L35-M35,Forecast!O35)) | O35: =IF(A35="","",IF($B35=1,N35-Forecast!N35,Forecast!P35)) | P35: =IF(A35="","",(Forecast!$Q$5-Forecast!$P$5)+SUM($O$5:O35))
A36: =IF(Forecast!A36="","",Forecast!A36) | B36: =IF(A36="","",IF(31>=N(Setup!$C$17),1,0)) | C36: =IF(A36="","",IF($B36=1,Forecast!B36-Setup!$B$4,Forecast!B36)) | D36: =IF(A36="","",IF($B36=1,Forecast!C36-Setup!$B$5,Forecast!C36)) | E36: =IF(A36="","",IF($B36=1,Forecast!D36-Setup!$B$6,Forecast!D36)) | F36: =IF(A36="","",IF($B36=1,D36-E36,Forecast!E36)) | G36: =IF(A36="","",IF($B36=1,Forecast!F36-Setup!$B$7,Forecast!F36)) | H36: =IF(A36="","",IF($B36=1,Forecast!G36-N(Setup!$D$17)*Setup!$B$9/12,Forecast!G36)) | I36: =IF(A36="","",IF($B36=1,F36-G36-H36,Forecast!H36)) | J36: =IF(A36="","",IF($B36=1,MAX(0,I36)*Setup!$B$10,Forecast!I36)) | K36: =IF(A36="","",IF($B36=1,I36-J36,Forecast!J36)) | L36: =IF(A36="","",IF($B36=1,K36+G36+Forecast!K36,Forecast!L36)) | M36: =IF(A36="","",IF($B36=1,Forecast!M36-Setup!$B$8,Forecast!M36)) | N36: =IF(A36="","",IF($B36=1,L36-M36,Forecast!O36)) | O36: =IF(A36="","",IF($B36=1,N36-Forecast!N36,Forecast!P36)) | P36: =IF(A36="","",(Forecast!$Q$5-Forecast!$P$5)+SUM($O$5:O36))
A37: =IF(Forecast!A37="","",Forecast!A37) | B37: =IF(A37="","",IF(32>=N(Setup!$C$17),1,0)) | C37: =IF(A37="","",IF($B37=1,Forecast!B37-Setup!$B$4,Forecast!B37)) | D37: =IF(A37="","",IF($B37=1,Forecast!C37-Setup!$B$5,Forecast!C37)) | E37: =IF(A37="","",IF($B37=1,Forecast!D37-Setup!$B$6,Forecast!D37)) | F37: =IF(A37="","",IF($B37=1,D37-E37,Forecast!E37)) | G37: =IF(A37="","",IF($B37=1,Forecast!F37-Setup!$B$7,Forecast!F37)) | H37: =IF(A37="","",IF($B37=1,Forecast!G37-N(Setup!$D$17)*Setup!$B$9/12,Forecast!G37)) | I37: =IF(A37="","",IF($B37=1,F37-G37-H37,Forecast!H37)) | J37: =IF(A37="","",IF($B37=1,MAX(0,I37)*Setup!$B$10,Forecast!I37)) | K37: =IF(A37="","",IF($B37=1,I37-J37,Forecast!J37)) | L37: =IF(A37="","",IF($B37=1,K37+G37+Forecast!K37,Forecast!L37)) | M37: =IF(A37="","",IF($B37=1,Forecast!M37-Setup!$B$8,Forecast!M37)) | N37: =IF(A37="","",IF($B37=1,L37-M37,Forecast!O37)) | O37: =IF(A37="","",IF($B37=1,N37-Forecast!N37,Forecast!P37)) | P37: =IF(A37="","",(Forecast!$Q$5-Forecast!$P$5)+SUM($O$5:O37))
A38: =IF(Forecast!A38="","",Forecast!A38) | B38: =IF(A38="","",IF(33>=N(Setup!$C$17),1,0)) | C38: =IF(A38="","",IF($B38=1,Forecast!B38-Setup!$B$4,Forecast!B38)) | D38: =IF(A38="","",IF($B38=1,Forecast!C38-Setup!$B$5,Forecast!C38)) | E38: =IF(A38="","",IF($B38=1,Forecast!D38-Setup!$B$6,Forecast!D38)) | F38: =IF(A38="","",IF($B38=1,D38-E38,Forecast!E38)) | G38: =IF(A38="","",IF($B38=1,Forecast!F38-Setup!$B$7,Forecast!F38)) | H38: =IF(A38="","",IF($B38=1,Forecast!G38-N(Setup!$D$17)*Setup!$B$9/12,Forecast!G38)) | I38: =IF(A38="","",IF($B38=1,F38-G38-H38,Forecast!H38)) | J38: =IF(A38="","",IF($B38=1,MAX(0,I38)*Setup!$B$10,Forecast!I38)) | K38: =IF(A38="","",IF($B38=1,I38-J38,Forecast!J38)) | L38: =IF(A38="","",IF($B38=1,K38+G38+Forecast!K38,Forecast!L38)) | M38: =IF(A38="","",IF($B38=1,Forecast!M38-Setup!$B$8,Forecast!M38)) | N38: =IF(A38="","",IF($B38=1,L38-M38,Forecast!O38)) | O38: =IF(A38="","",IF($B38=1,N38-Forecast!N38,Forecast!P38)) | P38: =IF(A38="","",(Forecast!$Q$5-Forecast!$P$5)+SUM($O$5:O38))
A39: =IF(Forecast!A39="","",Forecast!A39) | B39: =IF(A39="","",IF(34>=N(Setup!$C$17),1,0)) | C39: =IF(A39="","",IF($B39=1,Forecast!B39-Setup!$B$4,Forecast!B39)) | D39: =IF(A39="","",IF($B39=1,Forecast!C39-Setup!$B$5,Forecast!C39)) | E39: =IF(A39="","",IF($B39=1,Forecast!D39-Setup!$B$6,Forecast!D39)) | F39: =IF(A39="","",IF($B39=1,D39-E39,Forecast!E39)) | G39: =IF(A39="","",IF($B39=1,Forecast!F39-Setup!$B$7,Forecast!F39)) | H39: =IF(A39="","",IF($B39=1,Forecast!G39-N(Setup!$D$17)*Setup!$B$9/12,Forecast!G39)) | I39: =IF(A39="","",IF($B39=1,F39-G39-H39,Forecast!H39)) | J39: =IF(A39="","",IF($B39=1,MAX(0,I39)*Setup!$B$10,Forecast!I39)) | K39: =IF(A39="","",IF($B39=1,I39-J39,Forecast!J39)) | L39: =IF(A39="","",IF($B39=1,K39+G39+Forecast!K39,Forecast!L39)) | M39: =IF(A39="","",IF($B39=1,Forecast!M39-Setup!$B$8,Forecast!M39)) | N39: =IF(A39="","",IF($B39=1,L39-M39,Forecast!O39)) | O39: =IF(A39="","",IF($B39=1,N39-Forecast!N39,Forecast!P39)) | P39: =IF(A39="","",(Forecast!$Q$5-Forecast!$P$5)+SUM($O$5:O39))
A40: =IF(Forecast!A40="","",Forecast!A40) | B40: =IF(A40="","",IF(35>=N(Setup!$C$17),1,0)) | C40: =IF(A40="","",IF($B40=1,Forecast!B40-Setup!$B$4,Forecast!B40)) | D40: =IF(A40="","",IF($B40=1,Forecast!C40-Setup!$B$5,Forecast!C40)) | E40: =IF(A40="","",IF($B40=1,Forecast!D40-Setup!$B$6,Forecast!D40)) | F40: =IF(A40="","",IF($B40=1,D40-E40,Forecast!E40)) | G40: =IF(A40="","",IF($B40=1,Forecast!F40-Setup!$B$7,Forecast!F40)) | H40: =IF(A40="","",IF($B40=1,Forecast!G40-N(Setup!$D$17)*Setup!$B$9/12,Forecast!G40)) | I40: =IF(A40="","",IF($B40=1,F40-G40-H40,Forecast!H40)) | J40: =IF(A40="","",IF($B40=1,MAX(0,I40)*Setup!$B$10,Forecast!I40)) | K40: =IF(A40="","",IF($B40=1,I40-J40,Forecast!J40)) | L40: =IF(A40="","",IF($B40=1,K40+G40+Forecast!K40,Forecast!L40)) | M40: =IF(A40="","",IF($B40=1,Forecast!M40-Setup!$B$8,Forecast!M40)) | N40: =IF(A40="","",IF($B40=1,L40-M40,Forecast!O40)) | O40: =IF(A40="","",IF($B40=1,N40-Forecast!N40,Forecast!P40)) | P40: =IF(A40="","",(Forecast!$Q$5-Forecast!$P$5)+SUM($O$5:O40))
A41: =IF(Forecast!A41="","",Forecast!A41) | B41: =IF(A41="","",IF(36>=N(Setup!$C$17),1,0)) | C41: =IF(A41="","",IF($B41=1,Forecast!B41-Setup!$B$4,Forecast!B41)) | D41: =IF(A41="","",IF($B41=1,Forecast!C41-Setup!$B$5,Forecast!C41)) | E41: =IF(A41="","",IF($B41=1,Forecast!D41-Setup!$B$6,Forecast!D41)) | F41: =IF(A41="","",IF($B41=1,D41-E41,Forecast!E41)) | G41: =IF(A41="","",IF($B41=1,Forecast!F41-Setup!$B$7,Forecast!F41)) | H41: =IF(A41="","",IF($B41=1,Forecast!G41-N(Setup!$D$17)*Setup!$B$9/12,Forecast!G41)) | I41: =IF(A41="","",IF($B41=1,F41-G41-H41,Forecast!H41)) | J41: =IF(A41="","",IF($B41=1,MAX(0,I41)*Setup!$B$10,Forecast!I41)) | K41: =IF(A41="","",IF($B41=1,I41-J41,Forecast!J41)) | L41: =IF(A41="","",IF($B41=1,K41+G41+Forecast!K41,Forecast!L41)) | M41: =IF(A41="","",IF($B41=1,Forecast!M41-Setup!$B$8,Forecast!M41)) | N41: =IF(A41="","",IF($B41=1,L41-M41,Forecast!O41)) | O41: =IF(A41="","",IF($B41=1,N41-Forecast!N41,Forecast!P41)) | P41: =IF(A41="","",(Forecast!$Q$5-Forecast!$P$5)+SUM($O$5:O41))
A42: =IF(Forecast!A42="","",Forecast!A42) | B42: =IF(A42="","",IF(37>=N(Setup!$C$17),1,0)) | C42: =IF(A42="","",IF($B42=1,Forecast!B42-Setup!$B$4,Forecast!B42)) | D42: =IF(A42="","",IF($B42=1,Forecast!C42-Setup!$B$5,Forecast!C42)) | E42: =IF(A42="","",IF($B42=1,Forecast!D42-Setup!$B$6,Forecast!D42)) | F42: =IF(A42="","",IF($B42=1,D42-E42,Forecast!E42)) | G42: =IF(A42="","",IF($B42=1,Forecast!F42-Setup!$B$7,Forecast!F42)) | H42: =IF(A42="","",IF($B42=1,Forecast!G42-N(Setup!$D$17)*Setup!$B$9/12,Forecast!G42)) | I42: =IF(A42="","",IF($B42=1,F42-G42-H42,Forecast!H42)) | J42: =IF(A42="","",IF($B42=1,MAX(0,I42)*Setup!$B$10,Forecast!I42)) | K42: =IF(A42="","",IF($B42=1,I42-J42,Forecast!J42)) | L42: =IF(A42="","",IF($B42=1,K42+G42+Forecast!K42,Forecast!L42)) | M42: =IF(A42="","",IF($B42=1,Forecast!M42-Setup!$B$8,Forecast!M42)) | N42: =IF(A42="","",IF($B42=1,L42-M42,Forecast!O42)) | O42: =IF(A42="","",IF($B42=1,N42-Forecast!N42,Forecast!P42)) | P42: =IF(A42="","",(Forecast!$Q$5-Forecast!$P$5)+SUM($O$5:O42))
A43: =IF(Forecast!A43="","",Forecast!A43) | B43: =IF(A43="","",IF(38>=N(Setup!$C$17),1,0)) | C43: =IF(A43="","",IF($B43=1,Forecast!B43-Setup!$B$4,Forecast!B43)) | D43: =IF(A43="","",IF($B43=1,Forecast!C43-Setup!$B$5,Forecast!C43)) | E43: =IF(A43="","",IF($B43=1,Forecast!D43-Setup!$B$6,Forecast!D43)) | F43: =IF(A43="","",IF($B43=1,D43-E43,Forecast!E43)) | G43: =IF(A43="","",IF($B43=1,Forecast!F43-Setup!$B$7,Forecast!F43)) | H43: =IF(A43="","",IF($B43=1,Forecast!G43-N(Setup!$D$17)*Setup!$B$9/12,Forecast!G43)) | I43: =IF(A43="","",IF($B43=1,F43-G43-H43,Forecast!H43)) | J43: =IF(A43="","",IF($B43=1,MAX(0,I43)*Setup!$B$10,Forecast!I43)) | K43: =IF(A43="","",IF($B43=1,I43-J43,Forecast!J43)) | L43: =IF(A43="","",IF($B43=1,K43+G43+Forecast!K43,Forecast!L43)) | M43: =IF(A43="","",IF($B43=1,Forecast!M43-Setup!$B$8,Forecast!M43)) | N43: =IF(A43="","",IF($B43=1,L43-M43,Forecast!O43)) | O43: =IF(A43="","",IF($B43=1,N43-Forecast!N43,Forecast!P43)) | P43: =IF(A43="","",(Forecast!$Q$5-Forecast!$P$5)+SUM($O$5:O43))
A44: =IF(Forecast!A44="","",Forecast!A44) | B44: =IF(A44="","",IF(39>=N(Setup!$C$17),1,0)) | C44: =IF(A44="","",IF($B44=1,Forecast!B44-Setup!$B$4,Forecast!B44)) | D44: =IF(A44="","",IF($B44=1,Forecast!C44-Setup!$B$5,Forecast!C44)) | E44: =IF(A44="","",IF($B44=1,Forecast!D44-Setup!$B$6,Forecast!D44)) | F44: =IF(A44="","",IF($B44=1,D44-E44,Forecast!E44)) | G44: =IF(A44="","",IF($B44=1,Forecast!F44-Setup!$B$7,Forecast!F44)) | H44: =IF(A44="","",IF($B44=1,Forecast!G44-N(Setup!$D$17)*Setup!$B$9/12,Forecast!G44)) | I44: =IF(A44="","",IF($B44=1,F44-G44-H44,Forecast!H44)) | J44: =IF(A44="","",IF($B44=1,MAX(0,I44)*Setup!$B$10,Forecast!I44)) | K44: =IF(A44="","",IF($B44=1,I44-J44,Forecast!J44)) | L44: =IF(A44="","",IF($B44=1,K44+G44+Forecast!K44,Forecast!L44)) | M44: =IF(A44="","",IF($B44=1,Forecast!M44-Setup!$B$8,Forecast!M44)) | N44: =IF(A44="","",IF($B44=1,L44-M44,Forecast!O44)) | O44: =IF(A44="","",IF($B44=1,N44-Forecast!N44,Forecast!P44)) | P44: =IF(A44="","",(Forecast!$Q$5-Forecast!$P$5)+SUM($O$5:O44))
A45: =IF(Forecast!A45="","",Forecast!A45) | B45: =IF(A45="","",IF(40>=N(Setup!$C$17),1,0)) | C45: =IF(A45="","",IF($B45=1,Forecast!B45-Setup!$B$4,Forecast!B45)) | D45: =IF(A45="","",IF($B45=1,Forecast!C45-Setup!$B$5,Forecast!C45)) | E45: =IF(A45="","",IF($B45=1,Forecast!D45-Setup!$B$6,Forecast!D45)) | F45: =IF(A45="","",IF($B45=1,D45-E45,Forecast!E45)) | G45: =IF(A45="","",IF($B45=1,Forecast!F45-Setup!$B$7,Forecast!F45)) | H45: =IF(A45="","",IF($B45=1,Forecast!G45-N(Setup!$D$17)*Setup!$B$9/12,Forecast!G45)) | I45: =IF(A45="","",IF($B45=1,F45-G45-H45,Forecast!H45)) | J45: =IF(A45="","",IF($B45=1,MAX(0,I45)*Setup!$B$10,Forecast!I45)) | K45: =IF(A45="","",IF($B45=1,I45-J45,Forecast!J45)) | L45: =IF(A45="","",IF($B45=1,K45+G45+Forecast!K45,Forecast!L45)) | M45: =IF(A45="","",IF($B45=1,Forecast!M45-Setup!$B$8,Forecast!M45)) | N45: =IF(A45="","",IF($B45=1,L45-M45,Forecast!O45)) | O45: =IF(A45="","",IF($B45=1,N45-Forecast!N45,Forecast!P45)) | P45: =IF(A45="","",(Forecast!$Q$5-Forecast!$P$5)+SUM($O$5:O45))
A46: =IF(Forecast!A46="","",Forecast!A46) | B46: =IF(A46="","",IF(41>=N(Setup!$C$17),1,0)) | C46: =IF(A46="","",IF($B46=1,Forecast!B46-Setup!$B$4,Forecast!B46)) | D46: =IF(A46="","",IF($B46=1,Forecast!C46-Setup!$B$5,Forecast!C46)) | E46: =IF(A46="","",IF($B46=1,Forecast!D46-Setup!$B$6,Forecast!D46)) | F46: =IF(A46="","",IF($B46=1,D46-E46,Forecast!E46)) | G46: =IF(A46="","",IF($B46=1,Forecast!F46-Setup!$B$7,Forecast!F46)) | H46: =IF(A46="","",IF($B46=1,Forecast!G46-N(Setup!$D$17)*Setup!$B$9/12,Forecast!G46)) | I46: =IF(A46="","",IF($B46=1,F46-G46-H46,Forecast!H46)) | J46: =IF(A46="","",IF($B46=1,MAX(0,I46)*Setup!$B$10,Forecast!I46)) | K46: =IF(A46="","",IF($B46=1,I46-J46,Forecast!J46)) | L46: =IF(A46="","",IF($B46=1,K46+G46+Forecast!K46,Forecast!L46)) | M46: =IF(A46="","",IF($B46=1,Forecast!M46-Setup!$B$8,Forecast!M46)) | N46: =IF(A46="","",IF($B46=1,L46-M46,Forecast!O46)) | O46: =IF(A46="","",IF($B46=1,N46-Forecast!N46,Forecast!P46)) | P46: =IF(A46="","",(Forecast!$Q$5-Forecast!$P$5)+SUM($O$5:O46))
A47: =IF(Forecast!A47="","",Forecast!A47) | B47: =IF(A47="","",IF(42>=N(Setup!$C$17),1,0)) | C47: =IF(A47="","",IF($B47=1,Forecast!B47-Setup!$B$4,Forecast!B47)) | D47: =IF(A47="","",IF($B47=1,Forecast!C47-Setup!$B$5,Forecast!C47)) | E47: =IF(A47="","",IF($B47=1,Forecast!D47-Setup!$B$6,Forecast!D47)) | F47: =IF(A47="","",IF($B47=1,D47-E47,Forecast!E47)) | G47: =IF(A47="","",IF($B47=1,Forecast!F47-Setup!$B$7,Forecast!F47)) | H47: =IF(A47="","",IF($B47=1,Forecast!G47-N(Setup!$D$17)*Setup!$B$9/12,Forecast!G47)) | I47: =IF(A47="","",IF($B47=1,F47-G47-H47,Forecast!H47)) | J47: =IF(A47="","",IF($B47=1,MAX(0,I47)*Setup!$B$10,Forecast!I47)) | K47: =IF(A47="","",IF($B47=1,I47-J47,Forecast!J47)) | L47: =IF(A47="","",IF($B47=1,K47+G47+Forecast!K47,Forecast!L47)) | M47: =IF(A47="","",IF($B47=1,Forecast!M47-Setup!$B$8,Forecast!M47)) | N47: =IF(A47="","",IF($B47=1,L47-M47,Forecast!O47)) | O47: =IF(A47="","",IF($B47=1,N47-Forecast!N47,Forecast!P47)) | P47: =IF(A47="","",(Forecast!$Q$5-Forecast!$P$5)+SUM($O$5:O47))
A48: =IF(Forecast!A48="","",Forecast!A48) | B48: =IF(A48="","",IF(43>=N(Setup!$C$17),1,0)) | C48: =IF(A48="","",IF($B48=1,Forecast!B48-Setup!$B$4,Forecast!B48)) | D48: =IF(A48="","",IF($B48=1,Forecast!C48-Setup!$B$5,Forecast!C48)) | E48: =IF(A48="","",IF($B48=1,Forecast!D48-Setup!$B$6,Forecast!D48)) | F48: =IF(A48="","",IF($B48=1,D48-E48,Forecast!E48)) | G48: =IF(A48="","",IF($B48=1,Forecast!F48-Setup!$B$7,Forecast!F48)) | H48: =IF(A48="","",IF($B48=1,Forecast!G48-N(Setup!$D$17)*Setup!$B$9/12,Forecast!G48)) | I48: =IF(A48="","",IF($B48=1,F48-G48-H48,Forecast!H48)) | J48: =IF(A48="","",IF($B48=1,MAX(0,I48)*Setup!$B$10,Forecast!I48)) | K48: =IF(A48="","",IF($B48=1,I48-J48,Forecast!J48)) | L48: =IF(A48="","",IF($B48=1,K48+G48+Forecast!K48,Forecast!L48)) | M48: =IF(A48="","",IF($B48=1,Forecast!M48-Setup!$B$8,Forecast!M48)) | N48: =IF(A48="","",IF($B48=1,L48-M48,Forecast!O48)) | O48: =IF(A48="","",IF($B48=1,N48-Forecast!N48,Forecast!P48)) | P48: =IF(A48="","",(Forecast!$Q$5-Forecast!$P$5)+SUM($O$5:O48))
A49: =IF(Forecast!A49="","",Forecast!A49) | B49: =IF(A49="","",IF(44>=N(Setup!$C$17),1,0)) | C49: =IF(A49="","",IF($B49=1,Forecast!B49-Setup!$B$4,Forecast!B49)) | D49: =IF(A49="","",IF($B49=1,Forecast!C49-Setup!$B$5,Forecast!C49)) | E49: =IF(A49="","",IF($B49=1,Forecast!D49-Setup!$B$6,Forecast!D49)) | F49: =IF(A49="","",IF($B49=1,D49-E49,Forecast!E49)) | G49: =IF(A49="","",IF($B49=1,Forecast!F49-Setup!$B$7,Forecast!F49)) | H49: =IF(A49="","",IF($B49=1,Forecast!G49-N(Setup!$D$17)*Setup!$B$9/12,Forecast!G49)) | I49: =IF(A49="","",IF($B49=1,F49-G49-H49,Forecast!H49)) | J49: =IF(A49="","",IF($B49=1,MAX(0,I49)*Setup!$B$10,Forecast!I49)) | K49: =IF(A49="","",IF($B49=1,I49-J49,Forecast!J49)) | L49: =IF(A49="","",IF($B49=1,K49+G49+Forecast!K49,Forecast!L49)) | M49: =IF(A49="","",IF($B49=1,Forecast!M49-Setup!$B$8,Forecast!M49)) | N49: =IF(A49="","",IF($B49=1,L49-M49,Forecast!O49)) | O49: =IF(A49="","",IF($B49=1,N49-Forecast!N49,Forecast!P49)) | P49: =IF(A49="","",(Forecast!$Q$5-Forecast!$P$5)+SUM($O$5:O49))
A50: =IF(Forecast!A50="","",Forecast!A50) | B50: =IF(A50="","",IF(45>=N(Setup!$C$17),1,0)) | C50: =IF(A50="","",IF($B50=1,Forecast!B50-Setup!$B$4,Forecast!B50)) | D50: =IF(A50="","",IF($B50=1,Forecast!C50-Setup!$B$5,Forecast!C50)) | E50: =IF(A50="","",IF($B50=1,Forecast!D50-Setup!$B$6,Forecast!D50)) | F50: =IF(A50="","",IF($B50=1,D50-E50,Forecast!E50)) | G50: =IF(A50="","",IF($B50=1,Forecast!F50-Setup!$B$7,Forecast!F50)) | H50: =IF(A50="","",IF($B50=1,Forecast!G50-N(Setup!$D$17)*Setup!$B$9/12,Forecast!G50)) | I50: =IF(A50="","",IF($B50=1,F50-G50-H50,Forecast!H50)) | J50: =IF(A50="","",IF($B50=1,MAX(0,I50)*Setup!$B$10,Forecast!I50)) | K50: =IF(A50="","",IF($B50=1,I50-J50,Forecast!J50)) | L50: =IF(A50="","",IF($B50=1,K50+G50+Forecast!K50,Forecast!L50)) | M50: =IF(A50="","",IF($B50=1,Forecast!M50-Setup!$B$8,Forecast!M50)) | N50: =IF(A50="","",IF($B50=1,L50-M50,Forecast!O50)) | O50: =IF(A50="","",IF($B50=1,N50-Forecast!N50,Forecast!P50)) | P50: =IF(A50="","",(Forecast!$Q$5-Forecast!$P$5)+SUM($O$5:O50))
A51: =IF(Forecast!A51="","",Forecast!A51) | B51: =IF(A51="","",IF(46>=N(Setup!$C$17),1,0)) | C51: =IF(A51="","",IF($B51=1,Forecast!B51-Setup!$B$4,Forecast!B51)) | D51: =IF(A51="","",IF($B51=1,Forecast!C51-Setup!$B$5,Forecast!C51)) | E51: =IF(A51="","",IF($B51=1,Forecast!D51-Setup!$B$6,Forecast!D51)) | F51: =IF(A51="","",IF($B51=1,D51-E51,Forecast!E51)) | G51: =IF(A51="","",IF($B51=1,Forecast!F51-Setup!$B$7,Forecast!F51)) | H51: =IF(A51="","",IF($B51=1,Forecast!G51-N(Setup!$D$17)*Setup!$B$9/12,Forecast!G51)) | I51: =IF(A51="","",IF($B51=1,F51-G51-H51,Forecast!H51)) | J51: =IF(A51="","",IF($B51=1,MAX(0,I51)*Setup!$B$10,Forecast!I51)) | K51: =IF(A51="","",IF($B51=1,I51-J51,Forecast!J51)) | L51: =IF(A51="","",IF($B51=1,K51+G51+Forecast!K51,Forecast!L51)) | M51: =IF(A51="","",IF($B51=1,Forecast!M51-Setup!$B$8,Forecast!M51)) | N51: =IF(A51="","",IF($B51=1,L51-M51,Forecast!O51)) | O51: =IF(A51="","",IF($B51=1,N51-Forecast!N51,Forecast!P51)) | P51: =IF(A51="","",(Forecast!$Q$5-Forecast!$P$5)+SUM($O$5:O51))
A52: =IF(Forecast!A52="","",Forecast!A52) | B52: =IF(A52="","",IF(47>=N(Setup!$C$17),1,0)) | C52: =IF(A52="","",IF($B52=1,Forecast!B52-Setup!$B$4,Forecast!B52)) | D52: =IF(A52="","",IF($B52=1,Forecast!C52-Setup!$B$5,Forecast!C52)) | E52: =IF(A52="","",IF($B52=1,Forecast!D52-Setup!$B$6,Forecast!D52)) | F52: =IF(A52="","",IF($B52=1,D52-E52,Forecast!E52)) | G52: =IF(A52="","",IF($B52=1,Forecast!F52-Setup!$B$7,Forecast!F52)) | H52: =IF(A52="","",IF($B52=1,Forecast!G52-N(Setup!$D$17)*Setup!$B$9/12,Forecast!G52)) | I52: =IF(A52="","",IF($B52=1,F52-G52-H52,Forecast!H52)) | J52: =IF(A52="","",IF($B52=1,MAX(0,I52)*Setup!$B$10,Forecast!I52)) | K52: =IF(A52="","",IF($B52=1,I52-J52,Forecast!J52)) | L52: =IF(A52="","",IF($B52=1,K52+G52+Forecast!K52,Forecast!L52)) | M52: =IF(A52="","",IF($B52=1,Forecast!M52-Setup!$B$8,Forecast!M52)) | N52: =IF(A52="","",IF($B52=1,L52-M52,Forecast!O52)) | O52: =IF(A52="","",IF($B52=1,N52-Forecast!N52,Forecast!P52)) | P52: =IF(A52="","",(Forecast!$Q$5-Forecast!$P$5)+SUM($O$5:O52))
A53: =IF(Forecast!A53="","",Forecast!A53) | B53: =IF(A53="","",IF(48>=N(Setup!$C$17),1,0)) | C53: =IF(A53="","",IF($B53=1,Forecast!B53-Setup!$B$4,Forecast!B53)) | D53: =IF(A53="","",IF($B53=1,Forecast!C53-Setup!$B$5,Forecast!C53)) | E53: =IF(A53="","",IF($B53=1,Forecast!D53-Setup!$B$6,Forecast!D53)) | F53: =IF(A53="","",IF($B53=1,D53-E53,Forecast!E53)) | G53: =IF(A53="","",IF($B53=1,Forecast!F53-Setup!$B$7,Forecast!F53)) | H53: =IF(A53="","",IF($B53=1,Forecast!G53-N(Setup!$D$17)*Setup!$B$9/12,Forecast!G53)) | I53: =IF(A53="","",IF($B53=1,F53-G53-H53,Forecast!H53)) | J53: =IF(A53="","",IF($B53=1,MAX(0,I53)*Setup!$B$10,Forecast!I53)) | K53: =IF(A53="","",IF($B53=1,I53-J53,Forecast!J53)) | L53: =IF(A53="","",IF($B53=1,K53+G53+Forecast!K53,Forecast!L53)) | M53: =IF(A53="","",IF($B53=1,Forecast!M53-Setup!$B$8,Forecast!M53)) | N53: =IF(A53="","",IF($B53=1,L53-M53,Forecast!O53)) | O53: =IF(A53="","",IF($B53=1,N53-Forecast!N53,Forecast!P53)) | P53: =IF(A53="","",(Forecast!$Q$5-Forecast!$P$5)+SUM($O$5:O53))
A54: =IF(Forecast!A54="","",Forecast!A54) | B54: =IF(A54="","",IF(49>=N(Setup!$C$17),1,0)) | C54: =IF(A54="","",IF($B54=1,Forecast!B54-Setup!$B$4,Forecast!B54)) | D54: =IF(A54="","",IF($B54=1,Forecast!C54-Setup!$B$5,Forecast!C54)) | E54: =IF(A54="","",IF($B54=1,Forecast!D54-Setup!$B$6,Forecast!D54)) | F54: =IF(A54="","",IF($B54=1,D54-E54,Forecast!E54)) | G54: =IF(A54="","",IF($B54=1,Forecast!F54-Setup!$B$7,Forecast!F54)) | H54: =IF(A54="","",IF($B54=1,Forecast!G54-N(Setup!$D$17)*Setup!$B$9/12,Forecast!G54)) | I54: =IF(A54="","",IF($B54=1,F54-G54-H54,Forecast!H54)) | J54: =IF(A54="","",IF($B54=1,MAX(0,I54)*Setup!$B$10,Forecast!I54)) | K54: =IF(A54="","",IF($B54=1,I54-J54,Forecast!J54)) | L54: =IF(A54="","",IF($B54=1,K54+G54+Forecast!K54,Forecast!L54)) | M54: =IF(A54="","",IF($B54=1,Forecast!M54-Setup!$B$8,Forecast!M54)) | N54: =IF(A54="","",IF($B54=1,L54-M54,Forecast!O54)) | O54: =IF(A54="","",IF($B54=1,N54-Forecast!N54,Forecast!P54)) | P54: =IF(A54="","",(Forecast!$Q$5-Forecast!$P$5)+SUM($O$5:O54))
A55: =IF(Forecast!A55="","",Forecast!A55) | B55: =IF(A55="","",IF(50>=N(Setup!$C$17),1,0)) | C55: =IF(A55="","",IF($B55=1,Forecast!B55-Setup!$B$4,Forecast!B55)) | D55: =IF(A55="","",IF($B55=1,Forecast!C55-Setup!$B$5,Forecast!C55)) | E55: =IF(A55="","",IF($B55=1,Forecast!D55-Setup!$B$6,Forecast!D55)) | F55: =IF(A55="","",IF($B55=1,D55-E55,Forecast!E55)) | G55: =IF(A55="","",IF($B55=1,Forecast!F55-Setup!$B$7,Forecast!F55)) | H55: =IF(A55="","",IF($B55=1,Forecast!G55-N(Setup!$D$17)*Setup!$B$9/12,Forecast!G55)) | I55: =IF(A55="","",IF($B55=1,F55-G55-H55,Forecast!H55)) | J55: =IF(A55="","",IF($B55=1,MAX(0,I55)*Setup!$B$10,Forecast!I55)) | K55: =IF(A55="","",IF($B55=1,I55-J55,Forecast!J55)) | L55: =IF(A55="","",IF($B55=1,K55+G55+Forecast!K55,Forecast!L55)) | M55: =IF(A55="","",IF($B55=1,Forecast!M55-Setup!$B$8,Forecast!M55)) | N55: =IF(A55="","",IF($B55=1,L55-M55,Forecast!O55)) | O55: =IF(A55="","",IF($B55=1,N55-Forecast!N55,Forecast!P55)) | P55: =IF(A55="","",(Forecast!$Q$5-Forecast!$P$5)+SUM($O$5:O55))
A56: =IF(Forecast!A56="","",Forecast!A56) | B56: =IF(A56="","",IF(51>=N(Setup!$C$17),1,0)) | C56: =IF(A56="","",IF($B56=1,Forecast!B56-Setup!$B$4,Forecast!B56)) | D56: =IF(A56="","",IF($B56=1,Forecast!C56-Setup!$B$5,Forecast!C56)) | E56: =IF(A56="","",IF($B56=1,Forecast!D56-Setup!$B$6,Forecast!D56)) | F56: =IF(A56="","",IF($B56=1,D56-E56,Forecast!E56)) | G56: =IF(A56="","",IF($B56=1,Forecast!F56-Setup!$B$7,Forecast!F56)) | H56: =IF(A56="","",IF($B56=1,Forecast!G56-N(Setup!$D$17)*Setup!$B$9/12,Forecast!G56)) | I56: =IF(A56="","",IF($B56=1,F56-G56-H56,Forecast!H56)) | J56: =IF(A56="","",IF($B56=1,MAX(0,I56)*Setup!$B$10,Forecast!I56)) | K56: =IF(A56="","",IF($B56=1,I56-J56,Forecast!J56)) | L56: =IF(A56="","",IF($B56=1,K56+G56+Forecast!K56,Forecast!L56)) | M56: =IF(A56="","",IF($B56=1,Forecast!M56-Setup!$B$8,Forecast!M56)) | N56: =IF(A56="","",IF($B56=1,L56-M56,Forecast!O56)) | O56: =IF(A56="","",IF($B56=1,N56-Forecast!N56,Forecast!P56)) | P56: =IF(A56="","",(Forecast!$Q$5-Forecast!$P$5)+SUM($O$5:O56))
A57: =IF(Forecast!A57="","",Forecast!A57) | B57: =IF(A57="","",IF(52>=N(Setup!$C$17),1,0)) | C57: =IF(A57="","",IF($B57=1,Forecast!B57-Setup!$B$4,Forecast!B57)) | D57: =IF(A57="","",IF($B57=1,Forecast!C57-Setup!$B$5,Forecast!C57)) | E57: =IF(A57="","",IF($B57=1,Forecast!D57-Setup!$B$6,Forecast!D57)) | F57: =IF(A57="","",IF($B57=1,D57-E57,Forecast!E57)) | G57: =IF(A57="","",IF($B57=1,Forecast!F57-Setup!$B$7,Forecast!F57)) | H57: =IF(A57="","",IF($B57=1,Forecast!G57-N(Setup!$D$17)*Setup!$B$9/12,Forecast!G57)) | I57: =IF(A57="","",IF($B57=1,F57-G57-H57,Forecast!H57)) | J57: =IF(A57="","",IF($B57=1,MAX(0,I57)*Setup!$B$10,Forecast!I57)) | K57: =IF(A57="","",IF($B57=1,I57-J57,Forecast!J57)) | L57: =IF(A57="","",IF($B57=1,K57+G57+Forecast!K57,Forecast!L57)) | M57: =IF(A57="","",IF($B57=1,Forecast!M57-Setup!$B$8,Forecast!M57)) | N57: =IF(A57="","",IF($B57=1,L57-M57,Forecast!O57)) | O57: =IF(A57="","",IF($B57=1,N57-Forecast!N57,Forecast!P57)) | P57: =IF(A57="","",(Forecast!$Q$5-Forecast!$P$5)+SUM($O$5:O57))
A58: =IF(Forecast!A58="","",Forecast!A58) | B58: =IF(A58="","",IF(53>=N(Setup!$C$17),1,0)) | C58: =IF(A58="","",IF($B58=1,Forecast!B58-Setup!$B$4,Forecast!B58)) | D58: =IF(A58="","",IF($B58=1,Forecast!C58-Setup!$B$5,Forecast!C58)) | E58: =IF(A58="","",IF($B58=1,Forecast!D58-Setup!$B$6,Forecast!D58)) | F58: =IF(A58="","",IF($B58=1,D58-E58,Forecast!E58)) | G58: =IF(A58="","",IF($B58=1,Forecast!F58-Setup!$B$7,Forecast!F58)) | H58: =IF(A58="","",IF($B58=1,Forecast!G58-N(Setup!$D$17)*Setup!$B$9/12,Forecast!G58)) | I58: =IF(A58="","",IF($B58=1,F58-G58-H58,Forecast!H58)) | J58: =IF(A58="","",IF($B58=1,MAX(0,I58)*Setup!$B$10,Forecast!I58)) | K58: =IF(A58="","",IF($B58=1,I58-J58,Forecast!J58)) | L58: =IF(A58="","",IF($B58=1,K58+G58+Forecast!K58,Forecast!L58)) | M58: =IF(A58="","",IF($B58=1,Forecast!M58-Setup!$B$8,Forecast!M58)) | N58: =IF(A58="","",IF($B58=1,L58-M58,Forecast!O58)) | O58: =IF(A58="","",IF($B58=1,N58-Forecast!N58,Forecast!P58)) | P58: =IF(A58="","",(Forecast!$Q$5-Forecast!$P$5)+SUM($O$5:O58))
A59: =IF(Forecast!A59="","",Forecast!A59) | B59: =IF(A59="","",IF(54>=N(Setup!$C$17),1,0)) | C59: =IF(A59="","",IF($B59=1,Forecast!B59-Setup!$B$4,Forecast!B59)) | D59: =IF(A59="","",IF($B59=1,Forecast!C59-Setup!$B$5,Forecast!C59)) | E59: =IF(A59="","",IF($B59=1,Forecast!D59-Setup!$B$6,Forecast!D59)) | F59: =IF(A59="","",IF($B59=1,D59-E59,Forecast!E59)) | G59: =IF(A59="","",IF($B59=1,Forecast!F59-Setup!$B$7,Forecast!F59)) | H59: =IF(A59="","",IF($B59=1,Forecast!G59-N(Setup!$D$17)*Setup!$B$9/12,Forecast!G59)) | I59: =IF(A59="","",IF($B59=1,F59-G59-H59,Forecast!H59)) | J59: =IF(A59="","",IF($B59=1,MAX(0,I59)*Setup!$B$10,Forecast!I59)) | K59: =IF(A59="","",IF($B59=1,I59-J59,Forecast!J59)) | L59: =IF(A59="","",IF($B59=1,K59+G59+Forecast!K59,Forecast!L59)) | M59: =IF(A59="","",IF($B59=1,Forecast!M59-Setup!$B$8,Forecast!M59)) | N59: =IF(A59="","",IF($B59=1,L59-M59,Forecast!O59)) | O59: =IF(A59="","",IF($B59=1,N59-Forecast!N59,Forecast!P59)) | P59: =IF(A59="","",(Forecast!$Q$5-Forecast!$P$5)+SUM($O$5:O59))
A60: =IF(Forecast!A60="","",Forecast!A60) | B60: =IF(A60="","",IF(55>=N(Setup!$C$17),1,0)) | C60: =IF(A60="","",IF($B60=1,Forecast!B60-Setup!$B$4,Forecast!B60)) | D60: =IF(A60="","",IF($B60=1,Forecast!C60-Setup!$B$5,Forecast!C60)) | E60: =IF(A60="","",IF($B60=1,Forecast!D60-Setup!$B$6,Forecast!D60)) | F60: =IF(A60="","",IF($B60=1,D60-E60,Forecast!E60)) | G60: =IF(A60="","",IF($B60=1,Forecast!F60-Setup!$B$7,Forecast!F60)) | H60: =IF(A60="","",IF($B60=1,Forecast!G60-N(Setup!$D$17)*Setup!$B$9/12,Forecast!G60)) | I60: =IF(A60="","",IF($B60=1,F60-G60-H60,Forecast!H60)) | J60: =IF(A60="","",IF($B60=1,MAX(0,I60)*Setup!$B$10,Forecast!I60)) | K60: =IF(A60="","",IF($B60=1,I60-J60,Forecast!J60)) | L60: =IF(A60="","",IF($B60=1,K60+G60+Forecast!K60,Forecast!L60)) | M60: =IF(A60="","",IF($B60=1,Forecast!M60-Setup!$B$8,Forecast!M60)) | N60: =IF(A60="","",IF($B60=1,L60-M60,Forecast!O60)) | O60: =IF(A60="","",IF($B60=1,N60-Forecast!N60,Forecast!P60)) | P60: =IF(A60="","",(Forecast!$Q$5-Forecast!$P$5)+SUM($O$5:O60))
A61: =IF(Forecast!A61="","",Forecast!A61) | B61: =IF(A61="","",IF(56>=N(Setup!$C$17),1,0)) | C61: =IF(A61="","",IF($B61=1,Forecast!B61-Setup!$B$4,Forecast!B61)) | D61: =IF(A61="","",IF($B61=1,Forecast!C61-Setup!$B$5,Forecast!C61)) | E61: =IF(A61="","",IF($B61=1,Forecast!D61-Setup!$B$6,Forecast!D61)) | F61: =IF(A61="","",IF($B61=1,D61-E61,Forecast!E61)) | G61: =IF(A61="","",IF($B61=1,Forecast!F61-Setup!$B$7,Forecast!F61)) | H61: =IF(A61="","",IF($B61=1,Forecast!G61-N(Setup!$D$17)*Setup!$B$9/12,Forecast!G61)) | I61: =IF(A61="","",IF($B61=1,F61-G61-H61,Forecast!H61)) | J61: =IF(A61="","",IF($B61=1,MAX(0,I61)*Setup!$B$10,Forecast!I61)) | K61: =IF(A61="","",IF($B61=1,I61-J61,Forecast!J61)) | L61: =IF(A61="","",IF($B61=1,K61+G61+Forecast!K61,Forecast!L61)) | M61: =IF(A61="","",IF($B61=1,Forecast!M61-Setup!$B$8,Forecast!M61)) | N61: =IF(A61="","",IF($B61=1,L61-M61,Forecast!O61)) | O61: =IF(A61="","",IF($B61=1,N61-Forecast!N61,Forecast!P61)) | P61: =IF(A61="","",(Forecast!$Q$5-Forecast!$P$5)+SUM($O$5:O61))
A62: =IF(Forecast!A62="","",Forecast!A62) | B62: =IF(A62="","",IF(57>=N(Setup!$C$17),1,0)) | C62: =IF(A62="","",IF($B62=1,Forecast!B62-Setup!$B$4,Forecast!B62)) | D62: =IF(A62="","",IF($B62=1,Forecast!C62-Setup!$B$5,Forecast!C62)) | E62: =IF(A62="","",IF($B62=1,Forecast!D62-Setup!$B$6,Forecast!D62)) | F62: =IF(A62="","",IF($B62=1,D62-E62,Forecast!E62)) | G62: =IF(A62="","",IF($B62=1,Forecast!F62-Setup!$B$7,Forecast!F62)) | H62: =IF(A62="","",IF($B62=1,Forecast!G62-N(Setup!$D$17)*Setup!$B$9/12,Forecast!G62)) | I62: =IF(A62="","",IF($B62=1,F62-G62-H62,Forecast!H62)) | J62: =IF(A62="","",IF($B62=1,MAX(0,I62)*Setup!$B$10,Forecast!I62)) | K62: =IF(A62="","",IF($B62=1,I62-J62,Forecast!J62)) | L62: =IF(A62="","",IF($B62=1,K62+G62+Forecast!K62,Forecast!L62)) | M62: =IF(A62="","",IF($B62=1,Forecast!M62-Setup!$B$8,Forecast!M62)) | N62: =IF(A62="","",IF($B62=1,L62-M62,Forecast!O62)) | O62: =IF(A62="","",IF($B62=1,N62-Forecast!N62,Forecast!P62)) | P62: =IF(A62="","",(Forecast!$Q$5-Forecast!$P$5)+SUM($O$5:O62))
A63: =IF(Forecast!A63="","",Forecast!A63) | B63: =IF(A63="","",IF(58>=N(Setup!$C$17),1,0)) | C63: =IF(A63="","",IF($B63=1,Forecast!B63-Setup!$B$4,Forecast!B63)) | D63: =IF(A63="","",IF($B63=1,Forecast!C63-Setup!$B$5,Forecast!C63)) | E63: =IF(A63="","",IF($B63=1,Forecast!D63-Setup!$B$6,Forecast!D63)) | F63: =IF(A63="","",IF($B63=1,D63-E63,Forecast!E63)) | G63: =IF(A63="","",IF($B63=1,Forecast!F63-Setup!$B$7,Forecast!F63)) | H63: =IF(A63="","",IF($B63=1,Forecast!G63-N(Setup!$D$17)*Setup!$B$9/12,Forecast!G63)) | I63: =IF(A63="","",IF($B63=1,F63-G63-H63,Forecast!H63)) | J63: =IF(A63="","",IF($B63=1,MAX(0,I63)*Setup!$B$10,Forecast!I63)) | K63: =IF(A63="","",IF($B63=1,I63-J63,Forecast!J63)) | L63: =IF(A63="","",IF($B63=1,K63+G63+Forecast!K63,Forecast!L63)) | M63: =IF(A63="","",IF($B63=1,Forecast!M63-Setup!$B$8,Forecast!M63)) | N63: =IF(A63="","",IF($B63=1,L63-M63,Forecast!O63)) | O63: =IF(A63="","",IF($B63=1,N63-Forecast!N63,Forecast!P63)) | P63: =IF(A63="","",(Forecast!$Q$5-Forecast!$P$5)+SUM($O$5:O63))
A64: =IF(Forecast!A64="","",Forecast!A64) | B64: =IF(A64="","",IF(59>=N(Setup!$C$17),1,0)) | C64: =IF(A64="","",IF($B64=1,Forecast!B64-Setup!$B$4,Forecast!B64)) | D64: =IF(A64="","",IF($B64=1,Forecast!C64-Setup!$B$5,Forecast!C64)) | E64: =IF(A64="","",IF($B64=1,Forecast!D64-Setup!$B$6,Forecast!D64)) | F64: =IF(A64="","",IF($B64=1,D64-E64,Forecast!E64)) | G64: =IF(A64="","",IF($B64=1,Forecast!F64-Setup!$B$7,Forecast!F64)) | H64: =IF(A64="","",IF($B64=1,Forecast!G64-N(Setup!$D$17)*Setup!$B$9/12,Forecast!G64)) | I64: =IF(A64="","",IF($B64=1,F64-G64-H64,Forecast!H64)) | J64: =IF(A64="","",IF($B64=1,MAX(0,I64)*Setup!$B$10,Forecast!I64)) | K64: =IF(A64="","",IF($B64=1,I64-J64,Forecast!J64)) | L64: =IF(A64="","",IF($B64=1,K64+G64+Forecast!K64,Forecast!L64)) | M64: =IF(A64="","",IF($B64=1,Forecast!M64-Setup!$B$8,Forecast!M64)) | N64: =IF(A64="","",IF($B64=1,L64-M64,Forecast!O64)) | O64: =IF(A64="","",IF($B64=1,N64-Forecast!N64,Forecast!P64)) | P64: =IF(A64="","",(Forecast!$Q$5-Forecast!$P$5)+SUM($O$5:O64))
A65: =IF(Forecast!A65="","",Forecast!A65) | B65: =IF(A65="","",IF(60>=N(Setup!$C$17),1,0)) | C65: =IF(A65="","",IF($B65=1,Forecast!B65-Setup!$B$4,Forecast!B65)) | D65: =IF(A65="","",IF($B65=1,Forecast!C65-Setup!$B$5,Forecast!C65)) | E65: =IF(A65="","",IF($B65=1,Forecast!D65-Setup!$B$6,Forecast!D65)) | F65: =IF(A65="","",IF($B65=1,D65-E65,Forecast!E65)) | G65: =IF(A65="","",IF($B65=1,Forecast!F65-Setup!$B$7,Forecast!F65)) | H65: =IF(A65="","",IF($B65=1,Forecast!G65-N(Setup!$D$17)*Setup!$B$9/12,Forecast!G65)) | I65: =IF(A65="","",IF($B65=1,F65-G65-H65,Forecast!H65)) | J65: =IF(A65="","",IF($B65=1,MAX(0,I65)*Setup!$B$10,Forecast!I65)) | K65: =IF(A65="","",IF($B65=1,I65-J65,Forecast!J65)) | L65: =IF(A65="","",IF($B65=1,K65+G65+Forecast!K65,Forecast!L65)) | M65: =IF(A65="","",IF($B65=1,Forecast!M65-Setup!$B$8,Forecast!M65)) | N65: =IF(A65="","",IF($B65=1,L65-M65,Forecast!O65)) | O65: =IF(A65="","",IF($B65=1,N65-Forecast!N65,Forecast!P65)) | P65: =IF(A65="","",(Forecast!$Q$5-Forecast!$P$5)+SUM($O$5:O65))
A66: =IF(Forecast!A66="","",Forecast!A66) | B66: =IF(A66="","",IF(61>=N(Setup!$C$17),1,0)) | C66: =IF(A66="","",IF($B66=1,Forecast!B66-Setup!$B$4,Forecast!B66)) | D66: =IF(A66="","",IF($B66=1,Forecast!C66-Setup!$B$5,Forecast!C66)) | E66: =IF(A66="","",IF($B66=1,Forecast!D66-Setup!$B$6,Forecast!D66)) | F66: =IF(A66="","",IF($B66=1,D66-E66,Forecast!E66)) | G66: =IF(A66="","",IF($B66=1,Forecast!F66-Setup!$B$7,Forecast!F66)) | H66: =IF(A66="","",IF($B66=1,Forecast!G66-N(Setup!$D$17)*Setup!$B$9/12,Forecast!G66)) | I66: =IF(A66="","",IF($B66=1,F66-G66-H66,Forecast!H66)) | J66: =IF(A66="","",IF($B66=1,MAX(0,I66)*Setup!$B$10,Forecast!I66)) | K66: =IF(A66="","",IF($B66=1,I66-J66,Forecast!J66)) | L66: =IF(A66="","",IF($B66=1,K66+G66+Forecast!K66,Forecast!L66)) | M66: =IF(A66="","",IF($B66=1,Forecast!M66-Setup!$B$8,Forecast!M66)) | N66: =IF(A66="","",IF($B66=1,L66-M66,Forecast!O66)) | O66: =IF(A66="","",IF($B66=1,N66-Forecast!N66,Forecast!P66)) | P66: =IF(A66="","",(Forecast!$Q$5-Forecast!$P$5)+SUM($O$5:O66))
A67: =IF(Forecast!A67="","",Forecast!A67) | B67: =IF(A67="","",IF(62>=N(Setup!$C$17),1,0)) | C67: =IF(A67="","",IF($B67=1,Forecast!B67-Setup!$B$4,Forecast!B67)) | D67: =IF(A67="","",IF($B67=1,Forecast!C67-Setup!$B$5,Forecast!C67)) | E67: =IF(A67="","",IF($B67=1,Forecast!D67-Setup!$B$6,Forecast!D67)) | F67: =IF(A67="","",IF($B67=1,D67-E67,Forecast!E67)) | G67: =IF(A67="","",IF($B67=1,Forecast!F67-Setup!$B$7,Forecast!F67)) | H67: =IF(A67="","",IF($B67=1,Forecast!G67-N(Setup!$D$17)*Setup!$B$9/12,Forecast!G67)) | I67: =IF(A67="","",IF($B67=1,F67-G67-H67,Forecast!H67)) | J67: =IF(A67="","",IF($B67=1,MAX(0,I67)*Setup!$B$10,Forecast!I67)) | K67: =IF(A67="","",IF($B67=1,I67-J67,Forecast!J67)) | L67: =IF(A67="","",IF($B67=1,K67+G67+Forecast!K67,Forecast!L67)) | M67: =IF(A67="","",IF($B67=1,Forecast!M67-Setup!$B$8,Forecast!M67)) | N67: =IF(A67="","",IF($B67=1,L67-M67,Forecast!O67)) | O67: =IF(A67="","",IF($B67=1,N67-Forecast!N67,Forecast!P67)) | P67: =IF(A67="","",(Forecast!$Q$5-Forecast!$P$5)+SUM($O$5:O67))
A68: =IF(Forecast!A68="","",Forecast!A68) | B68: =IF(A68="","",IF(63>=N(Setup!$C$17),1,0)) | C68: =IF(A68="","",IF($B68=1,Forecast!B68-Setup!$B$4,Forecast!B68)) | D68: =IF(A68="","",IF($B68=1,Forecast!C68-Setup!$B$5,Forecast!C68)) | E68: =IF(A68="","",IF($B68=1,Forecast!D68-Setup!$B$6,Forecast!D68)) | F68: =IF(A68="","",IF($B68=1,D68-E68,Forecast!E68)) | G68: =IF(A68="","",IF($B68=1,Forecast!F68-Setup!$B$7,Forecast!F68)) | H68: =IF(A68="","",IF($B68=1,Forecast!G68-N(Setup!$D$17)*Setup!$B$9/12,Forecast!G68)) | I68: =IF(A68="","",IF($B68=1,F68-G68-H68,Forecast!H68)) | J68: =IF(A68="","",IF($B68=1,MAX(0,I68)*Setup!$B$10,Forecast!I68)) | K68: =IF(A68="","",IF($B68=1,I68-J68,Forecast!J68)) | L68: =IF(A68="","",IF($B68=1,K68+G68+Forecast!K68,Forecast!L68)) | M68: =IF(A68="","",IF($B68=1,Forecast!M68-Setup!$B$8,Forecast!M68)) | N68: =IF(A68="","",IF($B68=1,L68-M68,Forecast!O68)) | O68: =IF(A68="","",IF($B68=1,N68-Forecast!N68,Forecast!P68)) | P68: =IF(A68="","",(Forecast!$Q$5-Forecast!$P$5)+SUM($O$5:O68))
A69: =IF(Forecast!A69="","",Forecast!A69) | B69: =IF(A69="","",IF(64>=N(Setup!$C$17),1,0)) | C69: =IF(A69="","",IF($B69=1,Forecast!B69-Setup!$B$4,Forecast!B69)) | D69: =IF(A69="","",IF($B69=1,Forecast!C69-Setup!$B$5,Forecast!C69)) | E69: =IF(A69="","",IF($B69=1,Forecast!D69-Setup!$B$6,Forecast!D69)) | F69: =IF(A69="","",IF($B69=1,D69-E69,Forecast!E69)) | G69: =IF(A69="","",IF($B69=1,Forecast!F69-Setup!$B$7,Forecast!F69)) | H69: =IF(A69="","",IF($B69=1,Forecast!G69-N(Setup!$D$17)*Setup!$B$9/12,Forecast!G69)) | I69: =IF(A69="","",IF($B69=1,F69-G69-H69,Forecast!H69)) | J69: =IF(A69="","",IF($B69=1,MAX(0,I69)*Setup!$B$10,Forecast!I69)) | K69: =IF(A69="","",IF($B69=1,I69-J69,Forecast!J69)) | L69: =IF(A69="","",IF($B69=1,K69+G69+Forecast!K69,Forecast!L69)) | M69: =IF(A69="","",IF($B69=1,Forecast!M69-Setup!$B$8,Forecast!M69)) | N69: =IF(A69="","",IF($B69=1,L69-M69,Forecast!O69)) | O69: =IF(A69="","",IF($B69=1,N69-Forecast!N69,Forecast!P69)) | P69: =IF(A69="","",(Forecast!$Q$5-Forecast!$P$5)+SUM($O$5:O69))
A70: =IF(Forecast!A70="","",Forecast!A70) | B70: =IF(A70="","",IF(65>=N(Setup!$C$17),1,0)) | C70: =IF(A70="","",IF($B70=1,Forecast!B70-Setup!$B$4,Forecast!B70)) | D70: =IF(A70="","",IF($B70=1,Forecast!C70-Setup!$B$5,Forecast!C70)) | E70: =IF(A70="","",IF($B70=1,Forecast!D70-Setup!$B$6,Forecast!D70)) | F70: =IF(A70="","",IF($B70=1,D70-E70,Forecast!E70)) | G70: =IF(A70="","",IF($B70=1,Forecast!F70-Setup!$B$7,Forecast!F70)) | H70: =IF(A70="","",IF($B70=1,Forecast!G70-N(Setup!$D$17)*Setup!$B$9/12,Forecast!G70)) | I70: =IF(A70="","",IF($B70=1,F70-G70-H70,Forecast!H70)) | J70: =IF(A70="","",IF($B70=1,MAX(0,I70)*Setup!$B$10,Forecast!I70)) | K70: =IF(A70="","",IF($B70=1,I70-J70,Forecast!J70)) | L70: =IF(A70="","",IF($B70=1,K70+G70+Forecast!K70,Forecast!L70)) | M70: =IF(A70="","",IF($B70=1,Forecast!M70-Setup!$B$8,Forecast!M70)) | N70: =IF(A70="","",IF($B70=1,L70-M70,Forecast!O70)) | O70: =IF(A70="","",IF($B70=1,N70-Forecast!N70,Forecast!P70)) | P70: =IF(A70="","",(Forecast!$Q$5-Forecast!$P$5)+SUM($O$5:O70))
A71: =IF(Forecast!A71="","",Forecast!A71) | B71: =IF(A71="","",IF(66>=N(Setup!$C$17),1,0)) | C71: =IF(A71="","",IF($B71=1,Forecast!B71-Setup!$B$4,Forecast!B71)) | D71: =IF(A71="","",IF($B71=1,Forecast!C71-Setup!$B$5,Forecast!C71)) | E71: =IF(A71="","",IF($B71=1,Forecast!D71-Setup!$B$6,Forecast!D71)) | F71: =IF(A71="","",IF($B71=1,D71-E71,Forecast!E71)) | G71: =IF(A71="","",IF($B71=1,Forecast!F71-Setup!$B$7,Forecast!F71)) | H71: =IF(A71="","",IF($B71=1,Forecast!G71-N(Setup!$D$17)*Setup!$B$9/12,Forecast!G71)) | I71: =IF(A71="","",IF($B71=1,F71-G71-H71,Forecast!H71)) | J71: =IF(A71="","",IF($B71=1,MAX(0,I71)*Setup!$B$10,Forecast!I71)) | K71: =IF(A71="","",IF($B71=1,I71-J71,Forecast!J71)) | L71: =IF(A71="","",IF($B71=1,K71+G71+Forecast!K71,Forecast!L71)) | M71: =IF(A71="","",IF($B71=1,Forecast!M71-Setup!$B$8,Forecast!M71)) | N71: =IF(A71="","",IF($B71=1,L71-M71,Forecast!O71)) | O71: =IF(A71="","",IF($B71=1,N71-Forecast!N71,Forecast!P71)) | P71: =IF(A71="","",(Forecast!$Q$5-Forecast!$P$5)+SUM($O$5:O71))
A72: =IF(Forecast!A72="","",Forecast!A72) | B72: =IF(A72="","",IF(67>=N(Setup!$C$17),1,0)) | C72: =IF(A72="","",IF($B72=1,Forecast!B72-Setup!$B$4,Forecast!B72)) | D72: =IF(A72="","",IF($B72=1,Forecast!C72-Setup!$B$5,Forecast!C72)) | E72: =IF(A72="","",IF($B72=1,Forecast!D72-Setup!$B$6,Forecast!D72)) | F72: =IF(A72="","",IF($B72=1,D72-E72,Forecast!E72)) | G72: =IF(A72="","",IF($B72=1,Forecast!F72-Setup!$B$7,Forecast!F72)) | H72: =IF(A72="","",IF($B72=1,Forecast!G72-N(Setup!$D$17)*Setup!$B$9/12,Forecast!G72)) | I72: =IF(A72="","",IF($B72=1,F72-G72-H72,Forecast!H72)) | J72: =IF(A72="","",IF($B72=1,MAX(0,I72)*Setup!$B$10,Forecast!I72)) | K72: =IF(A72="","",IF($B72=1,I72-J72,Forecast!J72)) | L72: =IF(A72="","",IF($B72=1,K72+G72+Forecast!K72,Forecast!L72)) | M72: =IF(A72="","",IF($B72=1,Forecast!M72-Setup!$B$8,Forecast!M72)) | N72: =IF(A72="","",IF($B72=1,L72-M72,Forecast!O72)) | O72: =IF(A72="","",IF($B72=1,N72-Forecast!N72,Forecast!P72)) | P72: =IF(A72="","",(Forecast!$Q$5-Forecast!$P$5)+SUM($O$5:O72))
A73: =IF(Forecast!A73="","",Forecast!A73) | B73: =IF(A73="","",IF(68>=N(Setup!$C$17),1,0)) | C73: =IF(A73="","",IF($B73=1,Forecast!B73-Setup!$B$4,Forecast!B73)) | D73: =IF(A73="","",IF($B73=1,Forecast!C73-Setup!$B$5,Forecast!C73)) | E73: =IF(A73="","",IF($B73=1,Forecast!D73-Setup!$B$6,Forecast!D73)) | F73: =IF(A73="","",IF($B73=1,D73-E73,Forecast!E73)) | G73: =IF(A73="","",IF($B73=1,Forecast!F73-Setup!$B$7,Forecast!F73)) | H73: =IF(A73="","",IF($B73=1,Forecast!G73-N(Setup!$D$17)*Setup!$B$9/12,Forecast!G73)) | I73: =IF(A73="","",IF($B73=1,F73-G73-H73,Forecast!H73)) | J73: =IF(A73="","",IF($B73=1,MAX(0,I73)*Setup!$B$10,Forecast!I73)) | K73: =IF(A73="","",IF($B73=1,I73-J73,Forecast!J73)) | L73: =IF(A73="","",IF($B73=1,K73+G73+Forecast!K73,Forecast!L73)) | M73: =IF(A73="","",IF($B73=1,Forecast!M73-Setup!$B$8,Forecast!M73)) | N73: =IF(A73="","",IF($B73=1,L73-M73,Forecast!O73)) | O73: =IF(A73="","",IF($B73=1,N73-Forecast!N73,Forecast!P73)) | P73: =IF(A73="","",(Forecast!$Q$5-Forecast!$P$5)+SUM($O$5:O73))
A74: =IF(Forecast!A74="","",Forecast!A74) | B74: =IF(A74="","",IF(69>=N(Setup!$C$17),1,0)) | C74: =IF(A74="","",IF($B74=1,Forecast!B74-Setup!$B$4,Forecast!B74)) | D74: =IF(A74="","",IF($B74=1,Forecast!C74-Setup!$B$5,Forecast!C74)) | E74: =IF(A74="","",IF($B74=1,Forecast!D74-Setup!$B$6,Forecast!D74)) | F74: =IF(A74="","",IF($B74=1,D74-E74,Forecast!E74)) | G74: =IF(A74="","",IF($B74=1,Forecast!F74-Setup!$B$7,Forecast!F74)) | H74: =IF(A74="","",IF($B74=1,Forecast!G74-N(Setup!$D$17)*Setup!$B$9/12,Forecast!G74)) | I74: =IF(A74="","",IF($B74=1,F74-G74-H74,Forecast!H74)) | J74: =IF(A74="","",IF($B74=1,MAX(0,I74)*Setup!$B$10,Forecast!I74)) | K74: =IF(A74="","",IF($B74=1,I74-J74,Forecast!J74)) | L74: =IF(A74="","",IF($B74=1,K74+G74+Forecast!K74,Forecast!L74)) | M74: =IF(A74="","",IF($B74=1,Forecast!M74-Setup!$B$8,Forecast!M74)) | N74: =IF(A74="","",IF($B74=1,L74-M74,Forecast!O74)) | O74: =IF(A74="","",IF($B74=1,N74-Forecast!N74,Forecast!P74)) | P74: =IF(A74="","",(Forecast!$Q$5-Forecast!$P$5)+SUM($O$5:O74))
A75: =IF(Forecast!A75="","",Forecast!A75) | B75: =IF(A75="","",IF(70>=N(Setup!$C$17),1,0)) | C75: =IF(A75="","",IF($B75=1,Forecast!B75-Setup!$B$4,Forecast!B75)) | D75: =IF(A75="","",IF($B75=1,Forecast!C75-Setup!$B$5,Forecast!C75)) | E75: =IF(A75="","",IF($B75=1,Forecast!D75-Setup!$B$6,Forecast!D75)) | F75: =IF(A75="","",IF($B75=1,D75-E75,Forecast!E75)) | G75: =IF(A75="","",IF($B75=1,Forecast!F75-Setup!$B$7,Forecast!F75)) | H75: =IF(A75="","",IF($B75=1,Forecast!G75-N(Setup!$D$17)*Setup!$B$9/12,Forecast!G75)) | I75: =IF(A75="","",IF($B75=1,F75-G75-H75,Forecast!H75)) | J75: =IF(A75="","",IF($B75=1,MAX(0,I75)*Setup!$B$10,Forecast!I75)) | K75: =IF(A75="","",IF($B75=1,I75-J75,Forecast!J75)) | L75: =IF(A75="","",IF($B75=1,K75+G75+Forecast!K75,Forecast!L75)) | M75: =IF(A75="","",IF($B75=1,Forecast!M75-Setup!$B$8,Forecast!M75)) | N75: =IF(A75="","",IF($B75=1,L75-M75,Forecast!O75)) | O75: =IF(A75="","",IF($B75=1,N75-Forecast!N75,Forecast!P75)) | P75: =IF(A75="","",(Forecast!$Q$5-Forecast!$P$5)+SUM($O$5:O75))
A76: =IF(Forecast!A76="","",Forecast!A76) | B76: =IF(A76="","",IF(71>=N(Setup!$C$17),1,0)) | C76: =IF(A76="","",IF($B76=1,Forecast!B76-Setup!$B$4,Forecast!B76)) | D76: =IF(A76="","",IF($B76=1,Forecast!C76-Setup!$B$5,Forecast!C76)) | E76: =IF(A76="","",IF($B76=1,Forecast!D76-Setup!$B$6,Forecast!D76)) | F76: =IF(A76="","",IF($B76=1,D76-E76,Forecast!E76)) | G76: =IF(A76="","",IF($B76=1,Forecast!F76-Setup!$B$7,Forecast!F76)) | H76: =IF(A76="","",IF($B76=1,Forecast!G76-N(Setup!$D$17)*Setup!$B$9/12,Forecast!G76)) | I76: =IF(A76="","",IF($B76=1,F76-G76-H76,Forecast!H76)) | J76: =IF(A76="","",IF($B76=1,MAX(0,I76)*Setup!$B$10,Forecast!I76)) | K76: =IF(A76="","",IF($B76=1,I76-J76,Forecast!J76)) | L76: =IF(A76="","",IF($B76=1,K76+G76+Forecast!K76,Forecast!L76)) | M76: =IF(A76="","",IF($B76=1,Forecast!M76-Setup!$B$8,Forecast!M76)) | N76: =IF(A76="","",IF($B76=1,L76-M76,Forecast!O76)) | O76: =IF(A76="","",IF($B76=1,N76-Forecast!N76,Forecast!P76)) | P76: =IF(A76="","",(Forecast!$Q$5-Forecast!$P$5)+SUM($O$5:O76))
A77: =IF(Forecast!A77="","",Forecast!A77) | B77: =IF(A77="","",IF(72>=N(Setup!$C$17),1,0)) | C77: =IF(A77="","",IF($B77=1,Forecast!B77-Setup!$B$4,Forecast!B77)) | D77: =IF(A77="","",IF($B77=1,Forecast!C77-Setup!$B$5,Forecast!C77)) | E77: =IF(A77="","",IF($B77=1,Forecast!D77-Setup!$B$6,Forecast!D77)) | F77: =IF(A77="","",IF($B77=1,D77-E77,Forecast!E77)) | G77: =IF(A77="","",IF($B77=1,Forecast!F77-Setup!$B$7,Forecast!F77)) | H77: =IF(A77="","",IF($B77=1,Forecast!G77-N(Setup!$D$17)*Setup!$B$9/12,Forecast!G77)) | I77: =IF(A77="","",IF($B77=1,F77-G77-H77,Forecast!H77)) | J77: =IF(A77="","",IF($B77=1,MAX(0,I77)*Setup!$B$10,Forecast!I77)) | K77: =IF(A77="","",IF($B77=1,I77-J77,Forecast!J77)) | L77: =IF(A77="","",IF($B77=1,K77+G77+Forecast!K77,Forecast!L77)) | M77: =IF(A77="","",IF($B77=1,Forecast!M77-Setup!$B$8,Forecast!M77)) | N77: =IF(A77="","",IF($B77=1,L77-M77,Forecast!O77)) | O77: =IF(A77="","",IF($B77=1,N77-Forecast!N77,Forecast!P77)) | P77: =IF(A77="","",(Forecast!$Q$5-Forecast!$P$5)+SUM($O$5:O77))
A78: =IF(Forecast!A78="","",Forecast!A78) | B78: =IF(A78="","",IF(73>=N(Setup!$C$17),1,0)) | C78: =IF(A78="","",IF($B78=1,Forecast!B78-Setup!$B$4,Forecast!B78)) | D78: =IF(A78="","",IF($B78=1,Forecast!C78-Setup!$B$5,Forecast!C78)) | E78: =IF(A78="","",IF($B78=1,Forecast!D78-Setup!$B$6,Forecast!D78)) | F78: =IF(A78="","",IF($B78=1,D78-E78,Forecast!E78)) | G78: =IF(A78="","",IF($B78=1,Forecast!F78-Setup!$B$7,Forecast!F78)) | H78: =IF(A78="","",IF($B78=1,Forecast!G78-N(Setup!$D$17)*Setup!$B$9/12,Forecast!G78)) | I78: =IF(A78="","",IF($B78=1,F78-G78-H78,Forecast!H78)) | J78: =IF(A78="","",IF($B78=1,MAX(0,I78)*Setup!$B$10,Forecast!I78)) | K78: =IF(A78="","",IF($B78=1,I78-J78,Forecast!J78)) | L78: =IF(A78="","",IF($B78=1,K78+G78+Forecast!K78,Forecast!L78)) | M78: =IF(A78="","",IF($B78=1,Forecast!M78-Setup!$B$8,Forecast!M78)) | N78: =IF(A78="","",IF($B78=1,L78-M78,Forecast!O78)) | O78: =IF(A78="","",IF($B78=1,N78-Forecast!N78,Forecast!P78)) | P78: =IF(A78="","",(Forecast!$Q$5-Forecast!$P$5)+SUM($O$5:O78))
A79: =IF(Forecast!A79="","",Forecast!A79) | B79: =IF(A79="","",IF(74>=N(Setup!$C$17),1,0)) | C79: =IF(A79="","",IF($B79=1,Forecast!B79-Setup!$B$4,Forecast!B79)) | D79: =IF(A79="","",IF($B79=1,Forecast!C79-Setup!$B$5,Forecast!C79)) | E79: =IF(A79="","",IF($B79=1,Forecast!D79-Setup!$B$6,Forecast!D79)) | F79: =IF(A79="","",IF($B79=1,D79-E79,Forecast!E79)) | G79: =IF(A79="","",IF($B79=1,Forecast!F79-Setup!$B$7,Forecast!F79)) | H79: =IF(A79="","",IF($B79=1,Forecast!G79-N(Setup!$D$17)*Setup!$B$9/12,Forecast!G79)) | I79: =IF(A79="","",IF($B79=1,F79-G79-H79,Forecast!H79)) | J79: =IF(A79="","",IF($B79=1,MAX(0,I79)*Setup!$B$10,Forecast!I79)) | K79: =IF(A79="","",IF($B79=1,I79-J79,Forecast!J79)) | L79: =IF(A79="","",IF($B79=1,K79+G79+Forecast!K79,Forecast!L79)) | M79: =IF(A79="","",IF($B79=1,Forecast!M79-Setup!$B$8,Forecast!M79)) | N79: =IF(A79="","",IF($B79=1,L79-M79,Forecast!O79)) | O79: =IF(A79="","",IF($B79=1,N79-Forecast!N79,Forecast!P79)) | P79: =IF(A79="","",(Forecast!$Q$5-Forecast!$P$5)+SUM($O$5:O79))
A80: =IF(Forecast!A80="","",Forecast!A80) | B80: =IF(A80="","",IF(75>=N(Setup!$C$17),1,0)) | C80: =IF(A80="","",IF($B80=1,Forecast!B80-Setup!$B$4,Forecast!B80)) | D80: =IF(A80="","",IF($B80=1,Forecast!C80-Setup!$B$5,Forecast!C80)) | E80: =IF(A80="","",IF($B80=1,Forecast!D80-Setup!$B$6,Forecast!D80)) | F80: =IF(A80="","",IF($B80=1,D80-E80,Forecast!E80)) | G80: =IF(A80="","",IF($B80=1,Forecast!F80-Setup!$B$7,Forecast!F80)) | H80: =IF(A80="","",IF($B80=1,Forecast!G80-N(Setup!$D$17)*Setup!$B$9/12,Forecast!G80)) | I80: =IF(A80="","",IF($B80=1,F80-G80-H80,Forecast!H80)) | J80: =IF(A80="","",IF($B80=1,MAX(0,I80)*Setup!$B$10,Forecast!I80)) | K80: =IF(A80="","",IF($B80=1,I80-J80,Forecast!J80)) | L80: =IF(A80="","",IF($B80=1,K80+G80+Forecast!K80,Forecast!L80)) | M80: =IF(A80="","",IF($B80=1,Forecast!M80-Setup!$B$8,Forecast!M80)) | N80: =IF(A80="","",IF($B80=1,L80-M80,Forecast!O80)) | O80: =IF(A80="","",IF($B80=1,N80-Forecast!N80,Forecast!P80)) | P80: =IF(A80="","",(Forecast!$Q$5-Forecast!$P$5)+SUM($O$5:O80))
A81: =IF(Forecast!A81="","",Forecast!A81) | B81: =IF(A81="","",IF(76>=N(Setup!$C$17),1,0)) | C81: =IF(A81="","",IF($B81=1,Forecast!B81-Setup!$B$4,Forecast!B81)) | D81: =IF(A81="","",IF($B81=1,Forecast!C81-Setup!$B$5,Forecast!C81)) | E81: =IF(A81="","",IF($B81=1,Forecast!D81-Setup!$B$6,Forecast!D81)) | F81: =IF(A81="","",IF($B81=1,D81-E81,Forecast!E81)) | G81: =IF(A81="","",IF($B81=1,Forecast!F81-Setup!$B$7,Forecast!F81)) | H81: =IF(A81="","",IF($B81=1,Forecast!G81-N(Setup!$D$17)*Setup!$B$9/12,Forecast!G81)) | I81: =IF(A81="","",IF($B81=1,F81-G81-H81,Forecast!H81)) | J81: =IF(A81="","",IF($B81=1,MAX(0,I81)*Setup!$B$10,Forecast!I81)) | K81: =IF(A81="","",IF($B81=1,I81-J81,Forecast!J81)) | L81: =IF(A81="","",IF($B81=1,K81+G81+Forecast!K81,Forecast!L81)) | M81: =IF(A81="","",IF($B81=1,Forecast!M81-Setup!$B$8,Forecast!M81)) | N81: =IF(A81="","",IF($B81=1,L81-M81,Forecast!O81)) | O81: =IF(A81="","",IF($B81=1,N81-Forecast!N81,Forecast!P81)) | P81: =IF(A81="","",(Forecast!$Q$5-Forecast!$P$5)+SUM($O$5:O81))
A82: =IF(Forecast!A82="","",Forecast!A82) | B82: =IF(A82="","",IF(77>=N(Setup!$C$17),1,0)) | C82: =IF(A82="","",IF($B82=1,Forecast!B82-Setup!$B$4,Forecast!B82)) | D82: =IF(A82="","",IF($B82=1,Forecast!C82-Setup!$B$5,Forecast!C82)) | E82: =IF(A82="","",IF($B82=1,Forecast!D82-Setup!$B$6,Forecast!D82)) | F82: =IF(A82="","",IF($B82=1,D82-E82,Forecast!E82)) | G82: =IF(A82="","",IF($B82=1,Forecast!F82-Setup!$B$7,Forecast!F82)) | H82: =IF(A82="","",IF($B82=1,Forecast!G82-N(Setup!$D$17)*Setup!$B$9/12,Forecast!G82)) | I82: =IF(A82="","",IF($B82=1,F82-G82-H82,Forecast!H82)) | J82: =IF(A82="","",IF($B82=1,MAX(0,I82)*Setup!$B$10,Forecast!I82)) | K82: =IF(A82="","",IF($B82=1,I82-J82,Forecast!J82)) | L82: =IF(A82="","",IF($B82=1,K82+G82+Forecast!K82,Forecast!L82)) | M82: =IF(A82="","",IF($B82=1,Forecast!M82-Setup!$B$8,Forecast!M82)) | N82: =IF(A82="","",IF($B82=1,L82-M82,Forecast!O82)) | O82: =IF(A82="","",IF($B82=1,N82-Forecast!N82,Forecast!P82)) | P82: =IF(A82="","",(Forecast!$Q$5-Forecast!$P$5)+SUM($O$5:O82))
A83: =IF(Forecast!A83="","",Forecast!A83) | B83: =IF(A83="","",IF(78>=N(Setup!$C$17),1,0)) | C83: =IF(A83="","",IF($B83=1,Forecast!B83-Setup!$B$4,Forecast!B83)) | D83: =IF(A83="","",IF($B83=1,Forecast!C83-Setup!$B$5,Forecast!C83)) | E83: =IF(A83="","",IF($B83=1,Forecast!D83-Setup!$B$6,Forecast!D83)) | F83: =IF(A83="","",IF($B83=1,D83-E83,Forecast!E83)) | G83: =IF(A83="","",IF($B83=1,Forecast!F83-Setup!$B$7,Forecast!F83)) | H83: =IF(A83="","",IF($B83=1,Forecast!G83-N(Setup!$D$17)*Setup!$B$9/12,Forecast!G83)) | I83: =IF(A83="","",IF($B83=1,F83-G83-H83,Forecast!H83)) | J83: =IF(A83="","",IF($B83=1,MAX(0,I83)*Setup!$B$10,Forecast!I83)) | K83: =IF(A83="","",IF($B83=1,I83-J83,Forecast!J83)) | L83: =IF(A83="","",IF($B83=1,K83+G83+Forecast!K83,Forecast!L83)) | M83: =IF(A83="","",IF($B83=1,Forecast!M83-Setup!$B$8,Forecast!M83)) | N83: =IF(A83="","",IF($B83=1,L83-M83,Forecast!O83)) | O83: =IF(A83="","",IF($B83=1,N83-Forecast!N83,Forecast!P83)) | P83: =IF(A83="","",(Forecast!$Q$5-Forecast!$P$5)+SUM($O$5:O83))
A84: =IF(Forecast!A84="","",Forecast!A84) | B84: =IF(A84="","",IF(79>=N(Setup!$C$17),1,0)) | C84: =IF(A84="","",IF($B84=1,Forecast!B84-Setup!$B$4,Forecast!B84)) | D84: =IF(A84="","",IF($B84=1,Forecast!C84-Setup!$B$5,Forecast!C84)) | E84: =IF(A84="","",IF($B84=1,Forecast!D84-Setup!$B$6,Forecast!D84)) | F84: =IF(A84="","",IF($B84=1,D84-E84,Forecast!E84)) | G84: =IF(A84="","",IF($B84=1,Forecast!F84-Setup!$B$7,Forecast!F84)) | H84: =IF(A84="","",IF($B84=1,Forecast!G84-N(Setup!$D$17)*Setup!$B$9/12,Forecast!G84)) | I84: =IF(A84="","",IF($B84=1,F84-G84-H84,Forecast!H84)) | J84: =IF(A84="","",IF($B84=1,MAX(0,I84)*Setup!$B$10,Forecast!I84)) | K84: =IF(A84="","",IF($B84=1,I84-J84,Forecast!J84)) | L84: =IF(A84="","",IF($B84=1,K84+G84+Forecast!K84,Forecast!L84)) | M84: =IF(A84="","",IF($B84=1,Forecast!M84-Setup!$B$8,Forecast!M84)) | N84: =IF(A84="","",IF($B84=1,L84-M84,Forecast!O84)) | O84: =IF(A84="","",IF($B84=1,N84-Forecast!N84,Forecast!P84)) | P84: =IF(A84="","",(Forecast!$Q$5-Forecast!$P$5)+SUM($O$5:O84))
A85: =IF(Forecast!A85="","",Forecast!A85) | B85: =IF(A85="","",IF(80>=N(Setup!$C$17),1,0)) | C85: =IF(A85="","",IF($B85=1,Forecast!B85-Setup!$B$4,Forecast!B85)) | D85: =IF(A85="","",IF($B85=1,Forecast!C85-Setup!$B$5,Forecast!C85)) | E85: =IF(A85="","",IF($B85=1,Forecast!D85-Setup!$B$6,Forecast!D85)) | F85: =IF(A85="","",IF($B85=1,D85-E85,Forecast!E85)) | G85: =IF(A85="","",IF($B85=1,Forecast!F85-Setup!$B$7,Forecast!F85)) | H85: =IF(A85="","",IF($B85=1,Forecast!G85-N(Setup!$D$17)*Setup!$B$9/12,Forecast!G85)) | I85: =IF(A85="","",IF($B85=1,F85-G85-H85,Forecast!H85)) | J85: =IF(A85="","",IF($B85=1,MAX(0,I85)*Setup!$B$10,Forecast!I85)) | K85: =IF(A85="","",IF($B85=1,I85-J85,Forecast!J85)) | L85: =IF(A85="","",IF($B85=1,K85+G85+Forecast!K85,Forecast!L85)) | M85: =IF(A85="","",IF($B85=1,Forecast!M85-Setup!$B$8,Forecast!M85)) | N85: =IF(A85="","",IF($B85=1,L85-M85,Forecast!O85)) | O85: =IF(A85="","",IF($B85=1,N85-Forecast!N85,Forecast!P85)) | P85: =IF(A85="","",(Forecast!$Q$5-Forecast!$P$5)+SUM($O$5:O85))
A86: =IF(Forecast!A86="","",Forecast!A86) | B86: =IF(A86="","",IF(81>=N(Setup!$C$17),1,0)) | C86: =IF(A86="","",IF($B86=1,Forecast!B86-Setup!$B$4,Forecast!B86)) | D86: =IF(A86="","",IF($B86=1,Forecast!C86-Setup!$B$5,Forecast!C86)) | E86: =IF(A86="","",IF($B86=1,Forecast!D86-Setup!$B$6,Forecast!D86)) | F86: =IF(A86="","",IF($B86=1,D86-E86,Forecast!E86)) | G86: =IF(A86="","",IF($B86=1,Forecast!F86-Setup!$B$7,Forecast!F86)) | H86: =IF(A86="","",IF($B86=1,Forecast!G86-N(Setup!$D$17)*Setup!$B$9/12,Forecast!G86)) | I86: =IF(A86="","",IF($B86=1,F86-G86-H86,Forecast!H86)) | J86: =IF(A86="","",IF($B86=1,MAX(0,I86)*Setup!$B$10,Forecast!I86)) | K86: =IF(A86="","",IF($B86=1,I86-J86,Forecast!J86)) | L86: =IF(A86="","",IF($B86=1,K86+G86+Forecast!K86,Forecast!L86)) | M86: =IF(A86="","",IF($B86=1,Forecast!M86-Setup!$B$8,Forecast!M86)) | N86: =IF(A86="","",IF($B86=1,L86-M86,Forecast!O86)) | O86: =IF(A86="","",IF($B86=1,N86-Forecast!N86,Forecast!P86)) | P86: =IF(A86="","",(Forecast!$Q$5-Forecast!$P$5)+SUM($O$5:O86))
A87: =IF(Forecast!A87="","",Forecast!A87) | B87: =IF(A87="","",IF(82>=N(Setup!$C$17),1,0)) | C87: =IF(A87="","",IF($B87=1,Forecast!B87-Setup!$B$4,Forecast!B87)) | D87: =IF(A87="","",IF($B87=1,Forecast!C87-Setup!$B$5,Forecast!C87)) | E87: =IF(A87="","",IF($B87=1,Forecast!D87-Setup!$B$6,Forecast!D87)) | F87: =IF(A87="","",IF($B87=1,D87-E87,Forecast!E87)) | G87: =IF(A87="","",IF($B87=1,Forecast!F87-Setup!$B$7,Forecast!F87)) | H87: =IF(A87="","",IF($B87=1,Forecast!G87-N(Setup!$D$17)*Setup!$B$9/12,Forecast!G87)) | I87: =IF(A87="","",IF($B87=1,F87-G87-H87,Forecast!H87)) | J87: =IF(A87="","",IF($B87=1,MAX(0,I87)*Setup!$B$10,Forecast!I87)) | K87: =IF(A87="","",IF($B87=1,I87-J87,Forecast!J87)) | L87: =IF(A87="","",IF($B87=1,K87+G87+Forecast!K87,Forecast!L87)) | M87: =IF(A87="","",IF($B87=1,Forecast!M87-Setup!$B$8,Forecast!M87)) | N87: =IF(A87="","",IF($B87=1,L87-M87,Forecast!O87)) | O87: =IF(A87="","",IF($B87=1,N87-Forecast!N87,Forecast!P87)) | P87: =IF(A87="","",(Forecast!$Q$5-Forecast!$P$5)+SUM($O$5:O87))
A88: =IF(Forecast!A88="","",Forecast!A88) | B88: =IF(A88="","",IF(83>=N(Setup!$C$17),1,0)) | C88: =IF(A88="","",IF($B88=1,Forecast!B88-Setup!$B$4,Forecast!B88)) | D88: =IF(A88="","",IF($B88=1,Forecast!C88-Setup!$B$5,Forecast!C88)) | E88: =IF(A88="","",IF($B88=1,Forecast!D88-Setup!$B$6,Forecast!D88)) | F88: =IF(A88="","",IF($B88=1,D88-E88,Forecast!E88)) | G88: =IF(A88="","",IF($B88=1,Forecast!F88-Setup!$B$7,Forecast!F88)) | H88: =IF(A88="","",IF($B88=1,Forecast!G88-N(Setup!$D$17)*Setup!$B$9/12,Forecast!G88)) | I88: =IF(A88="","",IF($B88=1,F88-G88-H88,Forecast!H88)) | J88: =IF(A88="","",IF($B88=1,MAX(0,I88)*Setup!$B$10,Forecast!I88)) | K88: =IF(A88="","",IF($B88=1,I88-J88,Forecast!J88)) | L88: =IF(A88="","",IF($B88=1,K88+G88+Forecast!K88,Forecast!L88)) | M88: =IF(A88="","",IF($B88=1,Forecast!M88-Setup!$B$8,Forecast!M88)) | N88: =IF(A88="","",IF($B88=1,L88-M88,Forecast!O88)) | O88: =IF(A88="","",IF($B88=1,N88-Forecast!N88,Forecast!P88)) | P88: =IF(A88="","",(Forecast!$Q$5-Forecast!$P$5)+SUM($O$5:O88))
A89: =IF(Forecast!A89="","",Forecast!A89) | B89: =IF(A89="","",IF(84>=N(Setup!$C$17),1,0)) | C89: =IF(A89="","",IF($B89=1,Forecast!B89-Setup!$B$4,Forecast!B89)) | D89: =IF(A89="","",IF($B89=1,Forecast!C89-Setup!$B$5,Forecast!C89)) | E89: =IF(A89="","",IF($B89=1,Forecast!D89-Setup!$B$6,Forecast!D89)) | F89: =IF(A89="","",IF($B89=1,D89-E89,Forecast!E89)) | G89: =IF(A89="","",IF($B89=1,Forecast!F89-Setup!$B$7,Forecast!F89)) | H89: =IF(A89="","",IF($B89=1,Forecast!G89-N(Setup!$D$17)*Setup!$B$9/12,Forecast!G89)) | I89: =IF(A89="","",IF($B89=1,F89-G89-H89,Forecast!H89)) | J89: =IF(A89="","",IF($B89=1,MAX(0,I89)*Setup!$B$10,Forecast!I89)) | K89: =IF(A89="","",IF($B89=1,I89-J89,Forecast!J89)) | L89: =IF(A89="","",IF($B89=1,K89+G89+Forecast!K89,Forecast!L89)) | M89: =IF(A89="","",IF($B89=1,Forecast!M89-Setup!$B$8,Forecast!M89)) | N89: =IF(A89="","",IF($B89=1,L89-M89,Forecast!O89)) | O89: =IF(A89="","",IF($B89=1,N89-Forecast!N89,Forecast!P89)) | P89: =IF(A89="","",(Forecast!$Q$5-Forecast!$P$5)+SUM($O$5:O89))
A90: =IF(Forecast!A90="","",Forecast!A90) | B90: =IF(A90="","",IF(85>=N(Setup!$C$17),1,0)) | C90: =IF(A90="","",IF($B90=1,Forecast!B90-Setup!$B$4,Forecast!B90)) | D90: =IF(A90="","",IF($B90=1,Forecast!C90-Setup!$B$5,Forecast!C90)) | E90: =IF(A90="","",IF($B90=1,Forecast!D90-Setup!$B$6,Forecast!D90)) | F90: =IF(A90="","",IF($B90=1,D90-E90,Forecast!E90)) | G90: =IF(A90="","",IF($B90=1,Forecast!F90-Setup!$B$7,Forecast!F90)) | H90: =IF(A90="","",IF($B90=1,Forecast!G90-N(Setup!$D$17)*Setup!$B$9/12,Forecast!G90)) | I90: =IF(A90="","",IF($B90=1,F90-G90-H90,Forecast!H90)) | J90: =IF(A90="","",IF($B90=1,MAX(0,I90)*Setup!$B$10,Forecast!I90)) | K90: =IF(A90="","",IF($B90=1,I90-J90,Forecast!J90)) | L90: =IF(A90="","",IF($B90=1,K90+G90+Forecast!K90,Forecast!L90)) | M90: =IF(A90="","",IF($B90=1,Forecast!M90-Setup!$B$8,Forecast!M90)) | N90: =IF(A90="","",IF($B90=1,L90-M90,Forecast!O90)) | O90: =IF(A90="","",IF($B90=1,N90-Forecast!N90,Forecast!P90)) | P90: =IF(A90="","",(Forecast!$Q$5-Forecast!$P$5)+SUM($O$5:O90))
A91: =IF(Forecast!A91="","",Forecast!A91) | B91: =IF(A91="","",IF(86>=N(Setup!$C$17),1,0)) | C91: =IF(A91="","",IF($B91=1,Forecast!B91-Setup!$B$4,Forecast!B91)) | D91: =IF(A91="","",IF($B91=1,Forecast!C91-Setup!$B$5,Forecast!C91)) | E91: =IF(A91="","",IF($B91=1,Forecast!D91-Setup!$B$6,Forecast!D91)) | F91: =IF(A91="","",IF($B91=1,D91-E91,Forecast!E91)) | G91: =IF(A91="","",IF($B91=1,Forecast!F91-Setup!$B$7,Forecast!F91)) | H91: =IF(A91="","",IF($B91=1,Forecast!G91-N(Setup!$D$17)*Setup!$B$9/12,Forecast!G91)) | I91: =IF(A91="","",IF($B91=1,F91-G91-H91,Forecast!H91)) | J91: =IF(A91="","",IF($B91=1,MAX(0,I91)*Setup!$B$10,Forecast!I91)) | K91: =IF(A91="","",IF($B91=1,I91-J91,Forecast!J91)) | L91: =IF(A91="","",IF($B91=1,K91+G91+Forecast!K91,Forecast!L91)) | M91: =IF(A91="","",IF($B91=1,Forecast!M91-Setup!$B$8,Forecast!M91)) | N91: =IF(A91="","",IF($B91=1,L91-M91,Forecast!O91)) | O91: =IF(A91="","",IF($B91=1,N91-Forecast!N91,Forecast!P91)) | P91: =IF(A91="","",(Forecast!$Q$5-Forecast!$P$5)+SUM($O$5:O91))
A92: =IF(Forecast!A92="","",Forecast!A92) | B92: =IF(A92="","",IF(87>=N(Setup!$C$17),1,0)) | C92: =IF(A92="","",IF($B92=1,Forecast!B92-Setup!$B$4,Forecast!B92)) | D92: =IF(A92="","",IF($B92=1,Forecast!C92-Setup!$B$5,Forecast!C92)) | E92: =IF(A92="","",IF($B92=1,Forecast!D92-Setup!$B$6,Forecast!D92)) | F92: =IF(A92="","",IF($B92=1,D92-E92,Forecast!E92)) | G92: =IF(A92="","",IF($B92=1,Forecast!F92-Setup!$B$7,Forecast!F92)) | H92: =IF(A92="","",IF($B92=1,Forecast!G92-N(Setup!$D$17)*Setup!$B$9/12,Forecast!G92)) | I92: =IF(A92="","",IF($B92=1,F92-G92-H92,Forecast!H92)) | J92: =IF(A92="","",IF($B92=1,MAX(0,I92)*Setup!$B$10,Forecast!I92)) | K92: =IF(A92="","",IF($B92=1,I92-J92,Forecast!J92)) | L92: =IF(A92="","",IF($B92=1,K92+G92+Forecast!K92,Forecast!L92)) | M92: =IF(A92="","",IF($B92=1,Forecast!M92-Setup!$B$8,Forecast!M92)) | N92: =IF(A92="","",IF($B92=1,L92-M92,Forecast!O92)) | O92: =IF(A92="","",IF($B92=1,N92-Forecast!N92,Forecast!P92)) | P92: =IF(A92="","",(Forecast!$Q$5-Forecast!$P$5)+SUM($O$5:O92))
A93: =IF(Forecast!A93="","",Forecast!A93) | B93: =IF(A93="","",IF(88>=N(Setup!$C$17),1,0)) | C93: =IF(A93="","",IF($B93=1,Forecast!B93-Setup!$B$4,Forecast!B93)) | D93: =IF(A93="","",IF($B93=1,Forecast!C93-Setup!$B$5,Forecast!C93)) | E93: =IF(A93="","",IF($B93=1,Forecast!D93-Setup!$B$6,Forecast!D93)) | F93: =IF(A93="","",IF($B93=1,D93-E93,Forecast!E93)) | G93: =IF(A93="","",IF($B93=1,Forecast!F93-Setup!$B$7,Forecast!F93)) | H93: =IF(A93="","",IF($B93=1,Forecast!G93-N(Setup!$D$17)*Setup!$B$9/12,Forecast!G93)) | I93: =IF(A93="","",IF($B93=1,F93-G93-H93,Forecast!H93)) | J93: =IF(A93="","",IF($B93=1,MAX(0,I93)*Setup!$B$10,Forecast!I93)) | K93: =IF(A93="","",IF($B93=1,I93-J93,Forecast!J93)) | L93: =IF(A93="","",IF($B93=1,K93+G93+Forecast!K93,Forecast!L93)) | M93: =IF(A93="","",IF($B93=1,Forecast!M93-Setup!$B$8,Forecast!M93)) | N93: =IF(A93="","",IF($B93=1,L93-M93,Forecast!O93)) | O93: =IF(A93="","",IF($B93=1,N93-Forecast!N93,Forecast!P93)) | P93: =IF(A93="","",(Forecast!$Q$5-Forecast!$P$5)+SUM($O$5:O93))
A94: =IF(Forecast!A94="","",Forecast!A94) | B94: =IF(A94="","",IF(89>=N(Setup!$C$17),1,0)) | C94: =IF(A94="","",IF($B94=1,Forecast!B94-Setup!$B$4,Forecast!B94)) | D94: =IF(A94="","",IF($B94=1,Forecast!C94-Setup!$B$5,Forecast!C94)) | E94: =IF(A94="","",IF($B94=1,Forecast!D94-Setup!$B$6,Forecast!D94)) | F94: =IF(A94="","",IF($B94=1,D94-E94,Forecast!E94)) | G94: =IF(A94="","",IF($B94=1,Forecast!F94-Setup!$B$7,Forecast!F94)) | H94: =IF(A94="","",IF($B94=1,Forecast!G94-N(Setup!$D$17)*Setup!$B$9/12,Forecast!G94)) | I94: =IF(A94="","",IF($B94=1,F94-G94-H94,Forecast!H94)) | J94: =IF(A94="","",IF($B94=1,MAX(0,I94)*Setup!$B$10,Forecast!I94)) | K94: =IF(A94="","",IF($B94=1,I94-J94,Forecast!J94)) | L94: =IF(A94="","",IF($B94=1,K94+G94+Forecast!K94,Forecast!L94)) | M94: =IF(A94="","",IF($B94=1,Forecast!M94-Setup!$B$8,Forecast!M94)) | N94: =IF(A94="","",IF($B94=1,L94-M94,Forecast!O94)) | O94: =IF(A94="","",IF($B94=1,N94-Forecast!N94,Forecast!P94)) | P94: =IF(A94="","",(Forecast!$Q$5-Forecast!$P$5)+SUM($O$5:O94))
A95: =IF(Forecast!A95="","",Forecast!A95) | B95: =IF(A95="","",IF(90>=N(Setup!$C$17),1,0)) | C95: =IF(A95="","",IF($B95=1,Forecast!B95-Setup!$B$4,Forecast!B95)) | D95: =IF(A95="","",IF($B95=1,Forecast!C95-Setup!$B$5,Forecast!C95)) | E95: =IF(A95="","",IF($B95=1,Forecast!D95-Setup!$B$6,Forecast!D95)) | F95: =IF(A95="","",IF($B95=1,D95-E95,Forecast!E95)) | G95: =IF(A95="","",IF($B95=1,Forecast!F95-Setup!$B$7,Forecast!F95)) | H95: =IF(A95="","",IF($B95=1,Forecast!G95-N(Setup!$D$17)*Setup!$B$9/12,Forecast!G95)) | I95: =IF(A95="","",IF($B95=1,F95-G95-H95,Forecast!H95)) | J95: =IF(A95="","",IF($B95=1,MAX(0,I95)*Setup!$B$10,Forecast!I95)) | K95: =IF(A95="","",IF($B95=1,I95-J95,Forecast!J95)) | L95: =IF(A95="","",IF($B95=1,K95+G95+Forecast!K95,Forecast!L95)) | M95: =IF(A95="","",IF($B95=1,Forecast!M95-Setup!$B$8,Forecast!M95)) | N95: =IF(A95="","",IF($B95=1,L95-M95,Forecast!O95)) | O95: =IF(A95="","",IF($B95=1,N95-Forecast!N95,Forecast!P95)) | P95: =IF(A95="","",(Forecast!$Q$5-Forecast!$P$5)+SUM($O$5:O95))
A96: =IF(Forecast!A96="","",Forecast!A96) | B96: =IF(A96="","",IF(91>=N(Setup!$C$17),1,0)) | C96: =IF(A96="","",IF($B96=1,Forecast!B96-Setup!$B$4,Forecast!B96)) | D96: =IF(A96="","",IF($B96=1,Forecast!C96-Setup!$B$5,Forecast!C96)) | E96: =IF(A96="","",IF($B96=1,Forecast!D96-Setup!$B$6,Forecast!D96)) | F96: =IF(A96="","",IF($B96=1,D96-E96,Forecast!E96)) | G96: =IF(A96="","",IF($B96=1,Forecast!F96-Setup!$B$7,Forecast!F96)) | H96: =IF(A96="","",IF($B96=1,Forecast!G96-N(Setup!$D$17)*Setup!$B$9/12,Forecast!G96)) | I96: =IF(A96="","",IF($B96=1,F96-G96-H96,Forecast!H96)) | J96: =IF(A96="","",IF($B96=1,MAX(0,I96)*Setup!$B$10,Forecast!I96)) | K96: =IF(A96="","",IF($B96=1,I96-J96,Forecast!J96)) | L96: =IF(A96="","",IF($B96=1,K96+G96+Forecast!K96,Forecast!L96)) | M96: =IF(A96="","",IF($B96=1,Forecast!M96-Setup!$B$8,Forecast!M96)) | N96: =IF(A96="","",IF($B96=1,L96-M96,Forecast!O96)) | O96: =IF(A96="","",IF($B96=1,N96-Forecast!N96,Forecast!P96)) | P96: =IF(A96="","",(Forecast!$Q$5-Forecast!$P$5)+SUM($O$5:O96))
A97: =IF(Forecast!A97="","",Forecast!A97) | B97: =IF(A97="","",IF(92>=N(Setup!$C$17),1,0)) | C97: =IF(A97="","",IF($B97=1,Forecast!B97-Setup!$B$4,Forecast!B97)) | D97: =IF(A97="","",IF($B97=1,Forecast!C97-Setup!$B$5,Forecast!C97)) | E97: =IF(A97="","",IF($B97=1,Forecast!D97-Setup!$B$6,Forecast!D97)) | F97: =IF(A97="","",IF($B97=1,D97-E97,Forecast!E97)) | G97: =IF(A97="","",IF($B97=1,Forecast!F97-Setup!$B$7,Forecast!F97)) | H97: =IF(A97="","",IF($B97=1,Forecast!G97-N(Setup!$D$17)*Setup!$B$9/12,Forecast!G97)) | I97: =IF(A97="","",IF($B97=1,F97-G97-H97,Forecast!H97)) | J97: =IF(A97="","",IF($B97=1,MAX(0,I97)*Setup!$B$10,Forecast!I97)) | K97: =IF(A97="","",IF($B97=1,I97-J97,Forecast!J97)) | L97: =IF(A97="","",IF($B97=1,K97+G97+Forecast!K97,Forecast!L97)) | M97: =IF(A97="","",IF($B97=1,Forecast!M97-Setup!$B$8,Forecast!M97)) | N97: =IF(A97="","",IF($B97=1,L97-M97,Forecast!O97)) | O97: =IF(A97="","",IF($B97=1,N97-Forecast!N97,Forecast!P97)) | P97: =IF(A97="","",(Forecast!$Q$5-Forecast!$P$5)+SUM($O$5:O97))
A98: =IF(Forecast!A98="","",Forecast!A98) | B98: =IF(A98="","",IF(93>=N(Setup!$C$17),1,0)) | C98: =IF(A98="","",IF($B98=1,Forecast!B98-Setup!$B$4,Forecast!B98)) | D98: =IF(A98="","",IF($B98=1,Forecast!C98-Setup!$B$5,Forecast!C98)) | E98: =IF(A98="","",IF($B98=1,Forecast!D98-Setup!$B$6,Forecast!D98)) | F98: =IF(A98="","",IF($B98=1,D98-E98,Forecast!E98)) | G98: =IF(A98="","",IF($B98=1,Forecast!F98-Setup!$B$7,Forecast!F98)) | H98: =IF(A98="","",IF($B98=1,Forecast!G98-N(Setup!$D$17)*Setup!$B$9/12,Forecast!G98)) | I98: =IF(A98="","",IF($B98=1,F98-G98-H98,Forecast!H98)) | J98: =IF(A98="","",IF($B98=1,MAX(0,I98)*Setup!$B$10,Forecast!I98)) | K98: =IF(A98="","",IF($B98=1,I98-J98,Forecast!J98)) | L98: =IF(A98="","",IF($B98=1,K98+G98+Forecast!K98,Forecast!L98)) | M98: =IF(A98="","",IF($B98=1,Forecast!M98-Setup!$B$8,Forecast!M98)) | N98: =IF(A98="","",IF($B98=1,L98-M98,Forecast!O98)) | O98: =IF(A98="","",IF($B98=1,N98-Forecast!N98,Forecast!P98)) | P98: =IF(A98="","",(Forecast!$Q$5-Forecast!$P$5)+SUM($O$5:O98))
A99: =IF(Forecast!A99="","",Forecast!A99) | B99: =IF(A99="","",IF(94>=N(Setup!$C$17),1,0)) | C99: =IF(A99="","",IF($B99=1,Forecast!B99-Setup!$B$4,Forecast!B99)) | D99: =IF(A99="","",IF($B99=1,Forecast!C99-Setup!$B$5,Forecast!C99)) | E99: =IF(A99="","",IF($B99=1,Forecast!D99-Setup!$B$6,Forecast!D99)) | F99: =IF(A99="","",IF($B99=1,D99-E99,Forecast!E99)) | G99: =IF(A99="","",IF($B99=1,Forecast!F99-Setup!$B$7,Forecast!F99)) | H99: =IF(A99="","",IF($B99=1,Forecast!G99-N(Setup!$D$17)*Setup!$B$9/12,Forecast!G99)) | I99: =IF(A99="","",IF($B99=1,F99-G99-H99,Forecast!H99)) | J99: =IF(A99="","",IF($B99=1,MAX(0,I99)*Setup!$B$10,Forecast!I99)) | K99: =IF(A99="","",IF($B99=1,I99-J99,Forecast!J99)) | L99: =IF(A99="","",IF($B99=1,K99+G99+Forecast!K99,Forecast!L99)) | M99: =IF(A99="","",IF($B99=1,Forecast!M99-Setup!$B$8,Forecast!M99)) | N99: =IF(A99="","",IF($B99=1,L99-M99,Forecast!O99)) | O99: =IF(A99="","",IF($B99=1,N99-Forecast!N99,Forecast!P99)) | P99: =IF(A99="","",(Forecast!$Q$5-Forecast!$P$5)+SUM($O$5:O99))
A100: =IF(Forecast!A100="","",Forecast!A100) | B100: =IF(A100="","",IF(95>=N(Setup!$C$17),1,0)) | C100: =IF(A100="","",IF($B100=1,Forecast!B100-Setup!$B$4,Forecast!B100)) | D100: =IF(A100="","",IF($B100=1,Forecast!C100-Setup!$B$5,Forecast!C100)) | E100: =IF(A100="","",IF($B100=1,Forecast!D100-Setup!$B$6,Forecast!D100)) | F100: =IF(A100="","",IF($B100=1,D100-E100,Forecast!E100)) | G100: =IF(A100="","",IF($B100=1,Forecast!F100-Setup!$B$7,Forecast!F100)) | H100: =IF(A100="","",IF($B100=1,Forecast!G100-N(Setup!$D$17)*Setup!$B$9/12,Forecast!G100)) | I100: =IF(A100="","",IF($B100=1,F100-G100-H100,Forecast!H100)) | J100: =IF(A100="","",IF($B100=1,MAX(0,I100)*Setup!$B$10,Forecast!I100)) | K100: =IF(A100="","",IF($B100=1,I100-J100,Forecast!J100)) | L100: =IF(A100="","",IF($B100=1,K100+G100+Forecast!K100,Forecast!L100)) | M100: =IF(A100="","",IF($B100=1,Forecast!M100-Setup!$B$8,Forecast!M100)) | N100: =IF(A100="","",IF($B100=1,L100-M100,Forecast!O100)) | O100: =IF(A100="","",IF($B100=1,N100-Forecast!N100,Forecast!P100)) | P100: =IF(A100="","",(Forecast!$Q$5-Forecast!$P$5)+SUM($O$5:O100))
A101: =IF(Forecast!A101="","",Forecast!A101) | B101: =IF(A101="","",IF(96>=N(Setup!$C$17),1,0)) | C101: =IF(A101="","",IF($B101=1,Forecast!B101-Setup!$B$4,Forecast!B101)) | D101: =IF(A101="","",IF($B101=1,Forecast!C101-Setup!$B$5,Forecast!C101)) | E101: =IF(A101="","",IF($B101=1,Forecast!D101-Setup!$B$6,Forecast!D101)) | F101: =IF(A101="","",IF($B101=1,D101-E101,Forecast!E101)) | G101: =IF(A101="","",IF($B101=1,Forecast!F101-Setup!$B$7,Forecast!F101)) | H101: =IF(A101="","",IF($B101=1,Forecast!G101-N(Setup!$D$17)*Setup!$B$9/12,Forecast!G101)) | I101: =IF(A101="","",IF($B101=1,F101-G101-H101,Forecast!H101)) | J101: =IF(A101="","",IF($B101=1,MAX(0,I101)*Setup!$B$10,Forecast!I101)) | K101: =IF(A101="","",IF($B101=1,I101-J101,Forecast!J101)) | L101: =IF(A101="","",IF($B101=1,K101+G101+Forecast!K101,Forecast!L101)) | M101: =IF(A101="","",IF($B101=1,Forecast!M101-Setup!$B$8,Forecast!M101)) | N101: =IF(A101="","",IF($B101=1,L101-M101,Forecast!O101)) | O101: =IF(A101="","",IF($B101=1,N101-Forecast!N101,Forecast!P101)) | P101: =IF(A101="","",(Forecast!$Q$5-Forecast!$P$5)+SUM($O$5:O101))
...

Sheet S1
A1: Scenario slot 1
B2: =Setup!B18
A4: month_no | B4: post-sale? | C4: revenue | D4: gross_profit | E4: opex | F4: ebitda | G4: da | H4: interest | I4: pretax_income | J4: tax | K4: net_income | L4: operating_cash_flow | M4: capex | N4: free_cash_flow | O4: change_in_cash | P4: ending_cash
A5: =IF(Forecast!A5="","",Forecast!A5) | B5: =IF(A5="","",IF(0>=N(Setup!$C$18),1,0)) | C5: =IF(A5="","",IF($B5=1,Forecast!B5-Setup!$B$4,Forecast!B5)) | D5: =IF(A5="","",IF($B5=1,Forecast!C5-Setup!$B$5,Forecast!C5)) | E5: =IF(A5="","",IF($B5=1,Forecast!D5-Setup!$B$6,Forecast!D5)) | F5: =IF(A5="","",IF($B5=1,D5-E5,Forecast!E5)) | G5: =IF(A5="","",IF($B5=1,Forecast!F5-Setup!$B$7,Forecast!F5)) | H5: =IF(A5="","",IF($B5=1,Forecast!G5-N(Setup!$D$18)*Setup!$B$9/12,Forecast!G5)) | I5: =IF(A5="","",IF($B5=1,F5-G5-H5,Forecast!H5)) | J5: =IF(A5="","",IF($B5=1,MAX(0,I5)*Setup!$B$10,Forecast!I5)) | K5: =IF(A5="","",IF($B5=1,I5-J5,Forecast!J5)) | L5: =IF(A5="","",IF($B5=1,K5+G5+Forecast!K5,Forecast!L5)) | M5: =IF(A5="","",IF($B5=1,Forecast!M5-Setup!$B$8,Forecast!M5)) | N5: =IF(A5="","",IF($B5=1,L5-M5,Forecast!O5)) | O5: =IF(A5="","",IF($B5=1,N5-Forecast!N5,Forecast!P5)) | P5: =IF(A5="","",(Forecast!$Q$5-Forecast!$P$5)+SUM($O$5:O5))
A6: =IF(Forecast!A6="","",Forecast!A6) | B6: =IF(A6="","",IF(1>=N(Setup!$C$18),1,0)) | C6: =IF(A6="","",IF($B6=1,Forecast!B6-Setup!$B$4,Forecast!B6)) | D6: =IF(A6="","",IF($B6=1,Forecast!C6-Setup!$B$5,Forecast!C6)) | E6: =IF(A6="","",IF($B6=1,Forecast!D6-Setup!$B$6,Forecast!D6)) | F6: =IF(A6="","",IF($B6=1,D6-E6,Forecast!E6)) | G6: =IF(A6="","",IF($B6=1,Forecast!F6-Setup!$B$7,Forecast!F6)) | H6: =IF(A6="","",IF($B6=1,Forecast!G6-N(Setup!$D$18)*Setup!$B$9/12,Forecast!G6)) | I6: =IF(A6="","",IF($B6=1,F6-G6-H6,Forecast!H6)) | J6: =IF(A6="","",IF($B6=1,MAX(0,I6)*Setup!$B$10,Forecast!I6)) | K6: =IF(A6="","",IF($B6=1,I6-J6,Forecast!J6)) | L6: =IF(A6="","",IF($B6=1,K6+G6+Forecast!K6,Forecast!L6)) | M6: =IF(A6="","",IF($B6=1,Forecast!M6-Setup!$B$8,Forecast!M6)) | N6: =IF(A6="","",IF($B6=1,L6-M6,Forecast!O6)) | O6: =IF(A6="","",IF($B6=1,N6-Forecast!N6,Forecast!P6)) | P6: =IF(A6="","",(Forecast!$Q$5-Forecast!$P$5)+SUM($O$5:O6))
A7: =IF(Forecast!A7="","",Forecast!A7) | B7: =IF(A7="","",IF(2>=N(Setup!$C$18),1,0)) | C7: =IF(A7="","",IF($B7=1,Forecast!B7-Setup!$B$4,Forecast!B7)) | D7: =IF(A7="","",IF($B7=1,Forecast!C7-Setup!$B$5,Forecast!C7)) | E7: =IF(A7="","",IF($B7=1,Forecast!D7-Setup!$B$6,Forecast!D7)) | F7: =IF(A7="","",IF($B7=1,D7-E7,Forecast!E7)) | G7: =IF(A7="","",IF($B7=1,Forecast!F7-Setup!$B$7,Forecast!F7)) | H7: =IF(A7="","",IF($B7=1,Forecast!G7-N(Setup!$D$18)*Setup!$B$9/12,Forecast!G7)) | I7: =IF(A7="","",IF($B7=1,F7-G7-H7,Forecast!H7)) | J7: =IF(A7="","",IF($B7=1,MAX(0,I7)*Setup!$B$10,Forecast!I7)) | K7: =IF(A7="","",IF($B7=1,I7-J7,Forecast!J7)) | L7: =IF(A7="","",IF($B7=1,K7+G7+Forecast!K7,Forecast!L7)) | M7: =IF(A7="","",IF($B7=1,Forecast!M7-Setup!$B$8,Forecast!M7)) | N7: =IF(A7="","",IF($B7=1,L7-M7,Forecast!O7)) | O7: =IF(A7="","",IF($B7=1,N7-Forecast!N7,Forecast!P7)) | P7: =IF(A7="","",(Forecast!$Q$5-Forecast!$P$5)+SUM($O$5:O7))
A8: =IF(Forecast!A8="","",Forecast!A8) | B8: =IF(A8="","",IF(3>=N(Setup!$C$18),1,0)) | C8: =IF(A8="","",IF($B8=1,Forecast!B8-Setup!$B$4,Forecast!B8)) | D8: =IF(A8="","",IF($B8=1,Forecast!C8-Setup!$B$5,Forecast!C8)) | E8: =IF(A8="","",IF($B8=1,Forecast!D8-Setup!$B$6,Forecast!D8)) | F8: =IF(A8="","",IF($B8=1,D8-E8,Forecast!E8)) | G8: =IF(A8="","",IF($B8=1,Forecast!F8-Setup!$B$7,Forecast!F8)) | H8: =IF(A8="","",IF($B8=1,Forecast!G8-N(Setup!$D$18)*Setup!$B$9/12,Forecast!G8)) | I8: =IF(A8="","",IF($B8=1,F8-G8-H8,Forecast!H8)) | J8: =IF(A8="","",IF($B8=1,MAX(0,I8)*Setup!$B$10,Forecast!I8)) | K8: =IF(A8="","",IF($B8=1,I8-J8,Forecast!J8)) | L8: =IF(A8="","",IF($B8=1,K8+G8+Forecast!K8,Forecast!L8)) | M8: =IF(A8="","",IF($B8=1,Forecast!M8-Setup!$B$8,Forecast!M8)) | N8: =IF(A8="","",IF($B8=1,L8-M8,Forecast!O8)) | O8: =IF(A8="","",IF($B8=1,N8-Forecast!N8,Forecast!P8)) | P8: =IF(A8="","",(Forecast!$Q$5-Forecast!$P$5)+SUM($O$5:O8))
A9: =IF(Forecast!A9="","",Forecast!A9) | B9: =IF(A9="","",IF(4>=N(Setup!$C$18),1,0)) | C9: =IF(A9="","",IF($B9=1,Forecast!B9-Setup!$B$4,Forecast!B9)) | D9: =IF(A9="","",IF($B9=1,Forecast!C9-Setup!$B$5,Forecast!C9)) | E9: =IF(A9="","",IF($B9=1,Forecast!D9-Setup!$B$6,Forecast!D9)) | F9: =IF(A9="","",IF($B9=1,D9-E9,Forecast!E9)) | G9: =IF(A9="","",IF($B9=1,Forecast!F9-Setup!$B$7,Forecast!F9)) | H9: =IF(A9="","",IF($B9=1,Forecast!G9-N(Setup!$D$18)*Setup!$B$9/12,Forecast!G9)) | I9: =IF(A9="","",IF($B9=1,F9-G9-H9,Forecast!H9)) | J9: =IF(A9="","",IF($B9=1,MAX(0,I9)*Setup!$B$10,Forecast!I9)) | K9: =IF(A9="","",IF($B9=1,I9-J9,Forecast!J9)) | L9: =IF(A9="","",IF($B9=1,K9+G9+Forecast!K9,Forecast!L9)) | M9: =IF(A9="","",IF($B9=1,Forecast!M9-Setup!$B$8,Forecast!M9)) | N9: =IF(A9="","",IF($B9=1,L9-M9,Forecast!O9)) | O9: =IF(A9="","",IF($B9=1,N9-Forecast!N9,Forecast!P9)) | P9: =IF(A9="","",(Forecast!$Q$5-Forecast!$P$5)+SUM($O$5:O9))
A10: =IF(Forecast!A10="","",Forecast!A10) | B10: =IF(A10="","",IF(5>=N(Setup!$C$18),1,0)) | C10: =IF(A10="","",IF($B10=1,Forecast!B10-Setup!$B$4,Forecast!B10)) | D10: =IF(A10="","",IF($B10=1,Forecast!C10-Setup!$B$5,Forecast!C10)) | E10: =IF(A10="","",IF($B10=1,Forecast!D10-Setup!$B$6,Forecast!D10)) | F10: =IF(A10="","",IF($B10=1,D10-E10,Forecast!E10)) | G10: =IF(A10="","",IF($B10=1,Forecast!F10-Setup!$B$7,Forecast!F10)) | H10: =IF(A10="","",IF($B10=1,Forecast!G10-N(Setup!$D$18)*Setup!$B$9/12,Forecast!G10)) | I10: =IF(A10="","",IF($B10=1,F10-G10-H10,Forecast!H10)) | J10: =IF(A10="","",IF($B10=1,MAX(0,I10)*Setup!$B$10,Forecast!I10)) | K10: =IF(A10="","",IF($B10=1,I10-J10,Forecast!J10)) | L10: =IF(A10="","",IF($B10=1,K10+G10+Forecast!K10,Forecast!L10)) | M10: =IF(A10="","",IF($B10=1,Forecast!M10-Setup!$B$8,Forecast!M10)) | N10: =IF(A10="","",IF($B10=1,L10-M10,Forecast!O10)) | O10: =IF(A10="","",IF($B10=1,N10-Forecast!N10,Forecast!P10)) | P10: =IF(A10="","",(Forecast!$Q$5-Forecast!$P$5)+SUM($O$5:O10))
A11: =IF(Forecast!A11="","",Forecast!A11) | B11: =IF(A11="","",IF(6>=N(Setup!$C$18),1,0)) | C11: =IF(A11="","",IF($B11=1,Forecast!B11-Setup!$B$4,Forecast!B11)) | D11: =IF(A11="","",IF($B11=1,Forecast!C11-Setup!$B$5,Forecast!C11)) | E11: =IF(A11="","",IF($B11=1,Forecast!D11-Setup!$B$6,Forecast!D11)) | F11: =IF(A11="","",IF($B11=1,D11-E11,Forecast!E11)) | G11: =IF(A11="","",IF($B11=1,Forecast!F11-Setup!$B$7,Forecast!F11)) | H11: =IF(A11="","",IF($B11=1,Forecast!G11-N(Setup!$D$18)*Setup!$B$9/12,Forecast!G11)) | I11: =IF(A11="","",IF($B11=1,F11-G11-H11,Forecast!H11)) | J11: =IF(A11="","",IF($B11=1,MAX(0,I11)*Setup!$B$10,Forecast!I11)) | K11: =IF(A11="","",IF($B11=1,I11-J11,Forecast!J11)) | L11: =IF(A11="","",IF($B11=1,K11+G11+Forecast!K11,Forecast!L11)) | M11: =IF(A11="","",IF($B11=1,Forecast!M11-Setup!$B$8,Forecast!M11)) | N11: =IF(A11="","",IF($B11=1,L11-M11,Forecast!O11)) | O11: =IF(A11="","",IF($B11=1,N11-Forecast!N11,Forecast!P11)) | P11: =IF(A11="","",(Forecast!$Q$5-Forecast!$P$5)+SUM($O$5:O11))
A12: =IF(Forecast!A12="","",Forecast!A12) | B12: =IF(A12="","",IF(7>=N(Setup!$C$18),1,0)) | C12: =IF(A12="","",IF($B12=1,Forecast!B12-Setup!$B$4,Forecast!B12)) | D12: =IF(A12="","",IF($B12=1,Forecast!C12-Setup!$B$5,Forecast!C12)) | E12: =IF(A12="","",IF($B12=1,Forecast!D12-Setup!$B$6,Forecast!D12)) | F12: =IF(A12="","",IF($B12=1,D12-E12,Forecast!E12)) | G12: =IF(A12="","",IF($B12=1,Forecast!F12-Setup!$B$7,Forecast!F12)) | H12: =IF(A12="","",IF($B12=1,Forecast!G12-N(Setup!$D$18)*Setup!$B$9/12,Forecast!G12)) | I12: =IF(A12="","",IF($B12=1,F12-G12-H12,Forecast!H12)) | J12: =IF(A12="","",IF($B12=1,MAX(0,I12)*Setup!$B$10,Forecast!I12)) | K12: =IF(A12="","",IF($B12=1,I12-J12,Forecast!J12)) | L12: =IF(A12="","",IF($B12=1,K12+G12+Forecast!K12,Forecast!L12)) | M12: =IF(A12="","",IF($B12=1,Forecast!M12-Setup!$B$8,Forecast!M12)) | N12: =IF(A12="","",IF($B12=1,L12-M12,Forecast!O12)) | O12: =IF(A12="","",IF($B12=1,N12-Forecast!N12,Forecast!P12)) | P12: =IF(A12="","",(Forecast!$Q$5-Forecast!$P$5)+SUM($O$5:O12))
A13: =IF(Forecast!A13="","",Forecast!A13) | B13: =IF(A13="","",IF(8>=N(Setup!$C$18),1,0)) | C13: =IF(A13="","",IF($B13=1,Forecast!B13-Setup!$B$4,Forecast!B13)) | D13: =IF(A13="","",IF($B13=1,Forecast!C13-Setup!$B$5,Forecast!C13)) | E13: =IF(A13="","",IF($B13=1,Forecast!D13-Setup!$B$6,Forecast!D13)) | F13: =IF(A13="","",IF($B13=1,D13-E13,Forecast!E13)) | G13: =IF(A13="","",IF($B13=1,Forecast!F13-Setup!$B$7,Forecast!F13)) | H13: =IF(A13="","",IF($B13=1,Forecast!G13-N(Setup!$D$18)*Setup!$B$9/12,Forecast!G13)) | I13: =IF(A13="","",IF($B13=1,F13-G13-H13,Forecast!H13)) | J13: =IF(A13="","",IF($B13=1,MAX(0,I13)*Setup!$B$10,Forecast!I13)) | K13: =IF(A13="","",IF($B13=1,I13-J13,Forecast!J13)) | L13: =IF(A13="","",IF($B13=1,K13+G13+Forecast!K13,Forecast!L13)) | M13: =IF(A13="","",IF($B13=1,Forecast!M13-Setup!$B$8,Forecast!M13)) | N13: =IF(A13="","",IF($B13=1,L13-M13,Forecast!O13)) | O13: =IF(A13="","",IF($B13=1,N13-Forecast!N13,Forecast!P13)) | P13: =IF(A13="","",(Forecast!$Q$5-Forecast!$P$5)+SUM($O$5:O13))
A14: =IF(Forecast!A14="","",Forecast!A14) | B14: =IF(A14="","",IF(9>=N(Setup!$C$18),1,0)) | C14: =IF(A14="","",IF($B14=1,Forecast!B14-Setup!$B$4,Forecast!B14)) | D14: =IF(A14="","",IF($B14=1,Forecast!C14-Setup!$B$5,Forecast!C14)) | E14: =IF(A14="","",IF($B14=1,Forecast!D14-Setup!$B$6,Forecast!D14)) | F14: =IF(A14="","",IF($B14=1,D14-E14,Forecast!E14)) | G14: =IF(A14="","",IF($B14=1,Forecast!F14-Setup!$B$7,Forecast!F14)) | H14: =IF(A14="","",IF($B14=1,Forecast!G14-N(Setup!$D$18)*Setup!$B$9/12,Forecast!G14)) | I14: =IF(A14="","",IF($B14=1,F14-G14-H14,Forecast!H14)) | J14: =IF(A14="","",IF($B14=1,MAX(0,I14)*Setup!$B$10,Forecast!I14)) | K14: =IF(A14="","",IF($B14=1,I14-J14,Forecast!J14)) | L14: =IF(A14="","",IF($B14=1,K14+G14+Forecast!K14,Forecast!L14)) | M14: =IF(A14="","",IF($B14=1,Forecast!M14-Setup!$B$8,Forecast!M14)) | N14: =IF(A14="","",IF($B14=1,L14-M14,Forecast!O14)) | O14: =IF(A14="","",IF($B14=1,N14-Forecast!N14,Forecast!P14)) | P14: =IF(A14="","",(Forecast!$Q$5-Forecast!$P$5)+SUM($O$5:O14))
A15: =IF(Forecast!A15="","",Forecast!A15) | B15: =IF(A15="","",IF(10>=N(Setup!$C$18),1,0)) | C15: =IF(A15="","",IF($B15=1,Forecast!B15-Setup!$B$4,Forecast!B15)) | D15: =IF(A15="","",IF($B15=1,Forecast!C15-Setup!$B$5,Forecast!C15)) | E15: =IF(A15="","",IF($B15=1,Forecast!D15-Setup!$B$6,Forecast!D15)) | F15: =IF(A15="","",IF($B15=1,D15-E15,Forecast!E15)) | G15: =IF(A15="","",IF($B15=1,Forecast!F15-Setup!$B$7,Forecast!F15)) | H15: =IF(A15="","",IF($B15=1,Forecast!G15-N(Setup!$D$18)*Setup!$B$9/12,Forecast!G15)) | I15: =IF(A15="","",IF($B15=1,F15-G15-H15,Forecast!H15)) | J15: =IF(A15="","",IF($B15=1,MAX(0,I15)*Setup!$B$10,Forecast!I15)) | K15: =IF(A15="","",IF($B15=1,I15-J15,Forecast!J15)) | L15: =IF(A15="","",IF($B15=1,K15+G15+Forecast!K15,Forecast!L15)) | M15: =IF(A15="","",IF($B15=1,Forecast!M15-Setup!$B$8,Forecast!M15)) | N15: =IF(A15="","",IF($B15=1,L15-M15,Forecast!O15)) | O15: =IF(A15="","",IF($B15=1,N15-Forecast!N15,Forecast!P15)) | P15: =IF(A15="","",(Forecast!$Q$5-Forecast!$P$5)+SUM($O$5:O15))
A16: =IF(Forecast!A16="","",Forecast!A16) | B16: =IF(A16="","",IF(11>=N(Setup!$C$18),1,0)) | C16: =IF(A16="","",IF($B16=1,Forecast!B16-Setup!$B$4,Forecast!B16)) | D16: =IF(A16="","",IF($B16=1,Forecast!C16-Setup!$B$5,Forecast!C16)) | E16: =IF(A16="","",IF($B16=1,Forecast!D16-Setup!$B$6,Forecast!D16)) | F16: =IF(A16="","",IF($B16=1,D16-E16,Forecast!E16)) | G16: =IF(A16="","",IF($B16=1,Forecast!F16-Setup!$B$7,Forecast!F16)) | H16: =IF(A16="","",IF($B16=1,Forecast!G16-N(Setup!$D$18)*Setup!$B$9/12,Forecast!G16)) | I16: =IF(A16="","",IF($B16=1,F16-G16-H16,Forecast!H16)) | J16: =IF(A16="","",IF($B16=1,MAX(0,I16)*Setup!$B$10,Forecast!I16)) | K16: =IF(A16="","",IF($B16=1,I16-J16,Forecast!J16)) | L16: =IF(A16="","",IF($B16=1,K16+G16+Forecast!K16,Forecast!L16)) | M16: =IF(A16="","",IF($B16=1,Forecast!M16-Setup!$B$8,Forecast!M16)) | N16: =IF(A16="","",IF($B16=1,L16-M16,Forecast!O16)) | O16: =IF(A16="","",IF($B16=1,N16-Forecast!N16,Forecast!P16)) | P16: =IF(A16="","",(Forecast!$Q$5-Forecast!$P$5)+SUM($O$5:O16))
A17: =IF(Forecast!A17="","",Forecast!A17) | B17: =IF(A17="","",IF(12>=N(Setup!$C$18),1,0)) | C17: =IF(A17="","",IF($B17=1,Forecast!B17-Setup!$B$4,Forecast!B17)) | D17: =IF(A17="","",IF($B17=1,Forecast!C17-Setup!$B$5,Forecast!C17)) | E17: =IF(A17="","",IF($B17=1,Forecast!D17-Setup!$B$6,Forecast!D17)) | F17: =IF(A17="","",IF($B17=1,D17-E17,Forecast!E17)) | G17: =IF(A17="","",IF($B17=1,Forecast!F17-Setup!$B$7,Forecast!F17)) | H17: =IF(A17="","",IF($B17=1,Forecast!G17-N(Setup!$D$18)*Setup!$B$9/12,Forecast!G17)) | I17: =IF(A17="","",IF($B17=1,F17-G17-H17,Forecast!H17)) | J17: =IF(A17="","",IF($B17=1,MAX(0,I17)*Setup!$B$10,Forecast!I17)) | K17: =IF(A17="","",IF($B17=1,I17-J17,Forecast!J17)) | L17: =IF(A17="","",IF($B17=1,K17+G17+Forecast!K17,Forecast!L17)) | M17: =IF(A17="","",IF($B17=1,Forecast!M17-Setup!$B$8,Forecast!M17)) | N17: =IF(A17="","",IF($B17=1,L17-M17,Forecast!O17)) | O17: =IF(A17="","",IF($B17=1,N17-Forecast!N17,Forecast!P17)) | P17: =IF(A17="","",(Forecast!$Q$5-Forecast!$P$5)+SUM($O$5:O17))
A18: =IF(Forecast!A18="","",Forecast!A18) | B18: =IF(A18="","",IF(13>=N(Setup!$C$18),1,0)) | C18: =IF(A18="","",IF($B18=1,Forecast!B18-Setup!$B$4,Forecast!B18)) | D18: =IF(A18="","",IF($B18=1,Forecast!C18-Setup!$B$5,Forecast!C18)) | E18: =IF(A18="","",IF($B18=1,Forecast!D18-Setup!$B$6,Forecast!D18)) | F18: =IF(A18="","",IF($B18=1,D18-E18,Forecast!E18)) | G18: =IF(A18="","",IF($B18=1,Forecast!F18-Setup!$B$7,Forecast!F18)) | H18: =IF(A18="","",IF($B18=1,Forecast!G18-N(Setup!$D$18)*Setup!$B$9/12,Forecast!G18)) | I18: =IF(A18="","",IF($B18=1,F18-G18-H18,Forecast!H18)) | J18: =IF(A18="","",IF($B18=1,MAX(0,I18)*Setup!$B$10,Forecast!I18)) | K18: =IF(A18="","",IF($B18=1,I18-J18,Forecast!J18)) | L18: =IF(A18="","",IF($B18=1,K18+G18+Forecast!K18,Forecast!L18)) | M18: =IF(A18="","",IF($B18=1,Forecast!M18-Setup!$B$8,Forecast!M18)) | N18: =IF(A18="","",IF($B18=1,L18-M18,Forecast!O18)) | O18: =IF(A18="","",IF($B18=1,N18-Forecast!N18,Forecast!P18)) | P18: =IF(A18="","",(Forecast!$Q$5-Forecast!$P$5)+SUM($O$5:O18))
A19: =IF(Forecast!A19="","",Forecast!A19) | B19: =IF(A19="","",IF(14>=N(Setup!$C$18),1,0)) | C19: =IF(A19="","",IF($B19=1,Forecast!B19-Setup!$B$4,Forecast!B19)) | D19: =IF(A19="","",IF($B19=1,Forecast!C19-Setup!$B$5,Forecast!C19)) | E19: =IF(A19="","",IF($B19=1,Forecast!D19-Setup!$B$6,Forecast!D19)) | F19: =IF(A19="","",IF($B19=1,D19-E19,Forecast!E19)) | G19: =IF(A19="","",IF($B19=1,Forecast!F19-Setup!$B$7,Forecast!F19)) | H19: =IF(A19="","",IF($B19=1,Forecast!G19-N(Setup!$D$18)*Setup!$B$9/12,Forecast!G19)) | I19: =IF(A19="","",IF($B19=1,F19-G19-H19,Forecast!H19)) | J19: =IF(A19="","",IF($B19=1,MAX(0,I19)*Setup!$B$10,Forecast!I19)) | K19: =IF(A19="","",IF($B19=1,I19-J19,Forecast!J19)) | L19: =IF(A19="","",IF($B19=1,K19+G19+Forecast!K19,Forecast!L19)) | M19: =IF(A19="","",IF($B19=1,Forecast!M19-Setup!$B$8,Forecast!M19)) | N19: =IF(A19="","",IF($B19=1,L19-M19,Forecast!O19)) | O19: =IF(A19="","",IF($B19=1,N19-Forecast!N19,Forecast!P19)) | P19: =IF(A19="","",(Forecast!$Q$5-Forecast!$P$5)+SUM($O$5:O19))
A20: =IF(Forecast!A20="","",Forecast!A20) | B20: =IF(A20="","",IF(15>=N(Setup!$C$18),1,0)) | C20: =IF(A20="","",IF($B20=1,Forecast!B20-Setup!$B$4,Forecast!B20)) | D20: =IF(A20="","",IF($B20=1,Forecast!C20-Setup!$B$5,Forecast!C20)) | E20: =IF(A20="","",IF($B20=1,Forecast!D20-Setup!$B$6,Forecast!D20)) | F20: =IF(A20="","",IF($B20=1,D20-E20,Forecast!E20)) | G20: =IF(A20="","",IF($B20=1,Forecast!F20-Setup!$B$7,Forecast!F20)) | H20: =IF(A20="","",IF($B20=1,Forecast!G20-N(Setup!$D$18)*Setup!$B$9/12,Forecast!G20)) | I20: =IF(A20="","",IF($B20=1,F20-G20-H20,Forecast!H20)) | J20: =IF(A20="","",IF($B20=1,MAX(0,I20)*Setup!$B$10,Forecast!I20)) | K20: =IF(A20="","",IF($B20=1,I20-J20,Forecast!J20)) | L20: =IF(A20="","",IF($B20=1,K20+G20+Forecast!K20,Forecast!L20)) | M20: =IF(A20="","",IF($B20=1,Forecast!M20-Setup!$B$8,Forecast!M20)) | N20: =IF(A20="","",IF($B20=1,L20-M20,Forecast!O20)) | O20: =IF(A20="","",IF($B20=1,N20-Forecast!N20,Forecast!P20)) | P20: =IF(A20="","",(Forecast!$Q$5-Forecast!$P$5)+SUM($O$5:O20))
A21: =IF(Forecast!A21="","",Forecast!A21) | B21: =IF(A21="","",IF(16>=N(Setup!$C$18),1,0)) | C21: =IF(A21="","",IF($B21=1,Forecast!B21-Setup!$B$4,Forecast!B21)) | D21: =IF(A21="","",IF($B21=1,Forecast!C21-Setup!$B$5,Forecast!C21)) | E21: =IF(A21="","",IF($B21=1,Forecast!D21-Setup!$B$6,Forecast!D21)) | F21: =IF(A21="","",IF($B21=1,D21-E21,Forecast!E21)) | G21: =IF(A21="","",IF($B21=1,Forecast!F21-Setup!$B$7,Forecast!F21)) | H21: =IF(A21="","",IF($B21=1,Forecast!G21-N(Setup!$D$18)*Setup!$B$9/12,Forecast!G21)) | I21: =IF(A21="","",IF($B21=1,F21-G21-H21,Forecast!H21)) | J21: =IF(A21="","",IF($B21=1,MAX(0,I21)*Setup!$B$10,Forecast!I21)) | K21: =IF(A21="","",IF($B21=1,I21-J21,Forecast!J21)) | L21: =IF(A21="","",IF($B21=1,K21+G21+Forecast!K21,Forecast!L21)) | M21: =IF(A21="","",IF($B21=1,Forecast!M21-Setup!$B$8,Forecast!M21)) | N21: =IF(A21="","",IF($B21=1,L21-M21,Forecast!O21)) | O21: =IF(A21="","",IF($B21=1,N21-Forecast!N21,Forecast!P21)) | P21: =IF(A21="","",(Forecast!$Q$5-Forecast!$P$5)+SUM($O$5:O21))
A22: =IF(Forecast!A22="","",Forecast!A22) | B22: =IF(A22="","",IF(17>=N(Setup!$C$18),1,0)) | C22: =IF(A22="","",IF($B22=1,Forecast!B22-Setup!$B$4,Forecast!B22)) | D22: =IF(A22="","",IF($B22=1,Forecast!C22-Setup!$B$5,Forecast!C22)) | E22: =IF(A22="","",IF($B22=1,Forecast!D22-Setup!$B$6,Forecast!D22)) | F22: =IF(A22="","",IF($B22=1,D22-E22,Forecast!E22)) | G22: =IF(A22="","",IF($B22=1,Forecast!F22-Setup!$B$7,Forecast!F22)) | H22: =IF(A22="","",IF($B22=1,Forecast!G22-N(Setup!$D$18)*Setup!$B$9/12,Forecast!G22)) | I22: =IF(A22="","",IF($B22=1,F22-G22-H22,Forecast!H22)) | J22: =IF(A22="","",IF($B22=1,MAX(0,I22)*Setup!$B$10,Forecast!I22)) | K22: =IF(A22="","",IF($B22=1,I22-J22,Forecast!J22)) | L22: =IF(A22="","",IF($B22=1,K22+G22+Forecast!K22,Forecast!L22)) | M22: =IF(A22="","",IF($B22=1,Forecast!M22-Setup!$B$8,Forecast!M22)) | N22: =IF(A22="","",IF($B22=1,L22-M22,Forecast!O22)) | O22: =IF(A22="","",IF($B22=1,N22-Forecast!N22,Forecast!P22)) | P22: =IF(A22="","",(Forecast!$Q$5-Forecast!$P$5)+SUM($O$5:O22))
A23: =IF(Forecast!A23="","",Forecast!A23) | B23: =IF(A23="","",IF(18>=N(Setup!$C$18),1,0)) | C23: =IF(A23="","",IF($B23=1,Forecast!B23-Setup!$B$4,Forecast!B23)) | D23: =IF(A23="","",IF($B23=1,Forecast!C23-Setup!$B$5,Forecast!C23)) | E23: =IF(A23="","",IF($B23=1,Forecast!D23-Setup!$B$6,Forecast!D23)) | F23: =IF(A23="","",IF($B23=1,D23-E23,Forecast!E23)) | G23: =IF(A23="","",IF($B23=1,Forecast!F23-Setup!$B$7,Forecast!F23)) | H23: =IF(A23="","",IF($B23=1,Forecast!G23-N(Setup!$D$18)*Setup!$B$9/12,Forecast!G23)) | I23: =IF(A23="","",IF($B23=1,F23-G23-H23,Forecast!H23)) | J23: =IF(A23="","",IF($B23=1,MAX(0,I23)*Setup!$B$10,Forecast!I23)) | K23: =IF(A23="","",IF($B23=1,I23-J23,Forecast!J23)) | L23: =IF(A23="","",IF($B23=1,K23+G23+Forecast!K23,Forecast!L23)) | M23: =IF(A23="","",IF($B23=1,Forecast!M23-Setup!$B$8,Forecast!M23)) | N23: =IF(A23="","",IF($B23=1,L23-M23,Forecast!O23)) | O23: =IF(A23="","",IF($B23=1,N23-Forecast!N23,Forecast!P23)) | P23: =IF(A23="","",(Forecast!$Q$5-Forecast!$P$5)+SUM($O$5:O23))
A24: =IF(Forecast!A24="","",Forecast!A24) | B24: =IF(A24="","",IF(19>=N(Setup!$C$18),1,0)) | C24: =IF(A24="","",IF($B24=1,Forecast!B24-Setup!$B$4,Forecast!B24)) | D24: =IF(A24="","",IF($B24=1,Forecast!C24-Setup!$B$5,Forecast!C24)) | E24: =IF(A24="","",IF($B24=1,Forecast!D24-Setup!$B$6,Forecast!D24)) | F24: =IF(A24="","",IF($B24=1,D24-E24,Forecast!E24)) | G24: =IF(A24="","",IF($B24=1,Forecast!F24-Setup!$B$7,Forecast!F24)) | H24: =IF(A24="","",IF($B24=1,Forecast!G24-N(Setup!$D$18)*Setup!$B$9/12,Forecast!G24)) | I24: =IF(A24="","",IF($B24=1,F24-G24-H24,Forecast!H24)) | J24: =IF(A24="","",IF($B24=1,MAX(0,I24)*Setup!$B$10,Forecast!I24)) | K24: =IF(A24="","",IF($B24=1,I24-J24,Forecast!J24)) | L24: =IF(A24="","",IF($B24=1,K24+G24+Forecast!K24,Forecast!L24)) | M24: =IF(A24="","",IF($B24=1,Forecast!M24-Setup!$B$8,Forecast!M24)) | N24: =IF(A24="","",IF($B24=1,L24-M24,Forecast!O24)) | O24: =IF(A24="","",IF($B24=1,N24-Forecast!N24,Forecast!P24)) | P24: =IF(A24="","",(Forecast!$Q$5-Forecast!$P$5)+SUM($O$5:O24))
A25: =IF(Forecast!A25="","",Forecast!A25) | B25: =IF(A25="","",IF(20>=N(Setup!$C$18),1,0)) | C25: =IF(A25="","",IF($B25=1,Forecast!B25-Setup!$B$4,Forecast!B25)) | D25: =IF(A25="","",IF($B25=1,Forecast!C25-Setup!$B$5,Forecast!C25)) | E25: =IF(A25="","",IF($B25=1,Forecast!D25-Setup!$B$6,Forecast!D25)) | F25: =IF(A25="","",IF($B25=1,D25-E25,Forecast!E25)) | G25: =IF(A25="","",IF($B25=1,Forecast!F25-Setup!$B$7,Forecast!F25)) | H25: =IF(A25="","",IF($B25=1,Forecast!G25-N(Setup!$D$18)*Setup!$B$9/12,Forecast!G25)) | I25: =IF(A25="","",IF($B25=1,F25-G25-H25,Forecast!H25)) | J25: =IF(A25="","",IF($B25=1,MAX(0,I25)*Setup!$B$10,Forecast!I25)) | K25: =IF(A25="","",IF($B25=1,I25-J25,Forecast!J25)) | L25: =IF(A25="","",IF($B25=1,K25+G25+Forecast!K25,Forecast!L25)) | M25: =IF(A25="","",IF($B25=1,Forecast!M25-Setup!$B$8,Forecast!M25)) | N25: =IF(A25="","",IF($B25=1,L25-M25,Forecast!O25)) | O25: =IF(A25="","",IF($B25=1,N25-Forecast!N25,Forecast!P25)) | P25: =IF(A25="","",(Forecast!$Q$5-Forecast!$P$5)+SUM($O$5:O25))
A26: =IF(Forecast!A26="","",Forecast!A26) | B26: =IF(A26="","",IF(21>=N(Setup!$C$18),1,0)) | C26: =IF(A26="","",IF($B26=1,Forecast!B26-Setup!$B$4,Forecast!B26)) | D26: =IF(A26="","",IF($B26=1,Forecast!C26-Setup!$B$5,Forecast!C26)) | E26: =IF(A26="","",IF($B26=1,Forecast!D26-Setup!$B$6,Forecast!D26)) | F26: =IF(A26="","",IF($B26=1,D26-E26,Forecast!E26)) | G26: =IF(A26="","",IF($B26=1,Forecast!F26-Setup!$B$7,Forecast!F26)) | H26: =IF(A26="","",IF($B26=1,Forecast!G26-N(Setup!$D$18)*Setup!$B$9/12,Forecast!G26)) | I26: =IF(A26="","",IF($B26=1,F26-G26-H26,Forecast!H26)) | J26: =IF(A26="","",IF($B26=1,MAX(0,I26)*Setup!$B$10,Forecast!I26)) | K26: =IF(A26="","",IF($B26=1,I26-J26,Forecast!J26)) | L26: =IF(A26="","",IF($B26=1,K26+G26+Forecast!K26,Forecast!L26)) | M26: =IF(A26="","",IF($B26=1,Forecast!M26-Setup!$B$8,Forecast!M26)) | N26: =IF(A26="","",IF($B26=1,L26-M26,Forecast!O26)) | O26: =IF(A26="","",IF($B26=1,N26-Forecast!N26,Forecast!P26)) | P26: =IF(A26="","",(Forecast!$Q$5-Forecast!$P$5)+SUM($O$5:O26))
A27: =IF(Forecast!A27="","",Forecast!A27) | B27: =IF(A27="","",IF(22>=N(Setup!$C$18),1,0)) | C27: =IF(A27="","",IF($B27=1,Forecast!B27-Setup!$B$4,Forecast!B27)) | D27: =IF(A27="","",IF($B27=1,Forecast!C27-Setup!$B$5,Forecast!C27)) | E27: =IF(A27="","",IF($B27=1,Forecast!D27-Setup!$B$6,Forecast!D27)) | F27: =IF(A27="","",IF($B27=1,D27-E27,Forecast!E27)) | G27: =IF(A27="","",IF($B27=1,Forecast!F27-Setup!$B$7,Forecast!F27)) | H27: =IF(A27="","",IF($B27=1,Forecast!G27-N(Setup!$D$18)*Setup!$B$9/12,Forecast!G27)) | I27: =IF(A27="","",IF($B27=1,F27-G27-H27,Forecast!H27)) | J27: =IF(A27="","",IF($B27=1,MAX(0,I27)*Setup!$B$10,Forecast!I27)) | K27: =IF(A27="","",IF($B27=1,I27-J27,Forecast!J27)) | L27: =IF(A27="","",IF($B27=1,K27+G27+Forecast!K27,Forecast!L27)) | M27: =IF(A27="","",IF($B27=1,Forecast!M27-Setup!$B$8,Forecast!M27)) | N27: =IF(A27="","",IF($B27=1,L27-M27,Forecast!O27)) | O27: =IF(A27="","",IF($B27=1,N27-Forecast!N27,Forecast!P27)) | P27: =IF(A27="","",(Forecast!$Q$5-Forecast!$P$5)+SUM($O$5:O27))
A28: =IF(Forecast!A28="","",Forecast!A28) | B28: =IF(A28="","",IF(23>=N(Setup!$C$18),1,0)) | C28: =IF(A28="","",IF($B28=1,Forecast!B28-Setup!$B$4,Forecast!B28)) | D28: =IF(A28="","",IF($B28=1,Forecast!C28-Setup!$B$5,Forecast!C28)) | E28: =IF(A28="","",IF($B28=1,Forecast!D28-Setup!$B$6,Forecast!D28)) | F28: =IF(A28="","",IF($B28=1,D28-E28,Forecast!E28)) | G28: =IF(A28="","",IF($B28=1,Forecast!F28-Setup!$B$7,Forecast!F28)) | H28: =IF(A28="","",IF($B28=1,Forecast!G28-N(Setup!$D$18)*Setup!$B$9/12,Forecast!G28)) | I28: =IF(A28="","",IF($B28=1,F28-G28-H28,Forecast!H28)) | J28: =IF(A28="","",IF($B28=1,MAX(0,I28)*Setup!$B$10,Forecast!I28)) | K28: =IF(A28="","",IF($B28=1,I28-J28,Forecast!J28)) | L28: =IF(A28="","",IF($B28=1,K28+G28+Forecast!K28,Forecast!L28)) | M28: =IF(A28="","",IF($B28=1,Forecast!M28-Setup!$B$8,Forecast!M28)) | N28: =IF(A28="","",IF($B28=1,L28-M28,Forecast!O28)) | O28: =IF(A28="","",IF($B28=1,N28-Forecast!N28,Forecast!P28)) | P28: =IF(A28="","",(Forecast!$Q$5-Forecast!$P$5)+SUM($O$5:O28))
A29: =IF(Forecast!A29="","",Forecast!A29) | B29: =IF(A29="","",IF(24>=N(Setup!$C$18),1,0)) | C29: =IF(A29="","",IF($B29=1,Forecast!B29-Setup!$B$4,Forecast!B29)) | D29: =IF(A29="","",IF($B29=1,Forecast!C29-Setup!$B$5,Forecast!C29)) | E29: =IF(A29="","",IF($B29=1,Forecast!D29-Setup!$B$6,Forecast!D29)) | F29: =IF(A29="","",IF($B29=1,D29-E29,Forecast!E29)) | G29: =IF(A29="","",IF($B29=1,Forecast!F29-Setup!$B$7,Forecast!F29)) | H29: =IF(A29="","",IF($B29=1,Forecast!G29-N(Setup!$D$18)*Setup!$B$9/12,Forecast!G29)) | I29: =IF(A29="","",IF($B29=1,F29-G29-H29,Forecast!H29)) | J29: =IF(A29="","",IF($B29=1,MAX(0,I29)*Setup!$B$10,Forecast!I29)) | K29: =IF(A29="","",IF($B29=1,I29-J29,Forecast!J29)) | L29: =IF(A29="","",IF($B29=1,K29+G29+Forecast!K29,Forecast!L29)) | M29: =IF(A29="","",IF($B29=1,Forecast!M29-Setup!$B$8,Forecast!M29)) | N29: =IF(A29="","",IF($B29=1,L29-M29,Forecast!O29)) | O29: =IF(A29="","",IF($B29=1,N29-Forecast!N29,Forecast!P29)) | P29: =IF(A29="","",(Forecast!$Q$5-Forecast!$P$5)+SUM($O$5:O29))
A30: =IF(Forecast!A30="","",Forecast!A30) | B30: =IF(A30="","",IF(25>=N(Setup!$C$18),1,0)) | C30: =IF(A30="","",IF($B30=1,Forecast!B30-Setup!$B$4,Forecast!B30)) | D30: =IF(A30="","",IF($B30=1,Forecast!C30-Setup!$B$5,Forecast!C30)) | E30: =IF(A30="","",IF($B30=1,Forecast!D30-Setup!$B$6,Forecast!D30)) | F30: =IF(A30="","",IF($B30=1,D30-E30,Forecast!E30)) | G30: =IF(A30="","",IF($B30=1,Forecast!F30-Setup!$B$7,Forecast!F30)) | H30: =IF(A30="","",IF($B30=1,Forecast!G30-N(Setup!$D$18)*Setup!$B$9/12,Forecast!G30)) | I30: =IF(A30="","",IF($B30=1,F30-G30-H30,Forecast!H30)) | J30: =IF(A30="","",IF($B30=1,MAX(0,I30)*Setup!$B$10,Forecast!I30)) | K30: =IF(A30="","",IF($B30=1,I30-J30,Forecast!J30)) | L30: =IF(A30="","",IF($B30=1,K30+G30+Forecast!K30,Forecast!L30)) | M30: =IF(A30="","",IF($B30=1,Forecast!M30-Setup!$B$8,Forecast!M30)) | N30: =IF(A30="","",IF($B30=1,L30-M30,Forecast!O30)) | O30: =IF(A30="","",IF($B30=1,N30-Forecast!N30,Forecast!P30)) | P30: =IF(A30="","",(Forecast!$Q$5-Forecast!$P$5)+SUM($O$5:O30))
A31: =IF(Forecast!A31="","",Forecast!A31) | B31: =IF(A31="","",IF(26>=N(Setup!$C$18),1,0)) | C31: =IF(A31="","",IF($B31=1,Forecast!B31-Setup!$B$4,Forecast!B31)) | D31: =IF(A31="","",IF($B31=1,Forecast!C31-Setup!$B$5,Forecast!C31)) | E31: =IF(A31="","",IF($B31=1,Forecast!D31-Setup!$B$6,Forecast!D31)) | F31: =IF(A31="","",IF($B31=1,D31-E31,Forecast!E31)) | G31: =IF(A31="","",IF($B31=1,Forecast!F31-Setup!$B$7,Forecast!F31)) | H31: =IF(A31="","",IF($B31=1,Forecast!G31-N(Setup!$D$18)*Setup!$B$9/12,Forecast!G31)) | I31: =IF(A31="","",IF($B31=1,F31-G31-H31,Forecast!H31)) | J31: =IF(A31="","",IF($B31=1,MAX(0,I31)*Setup!$B$10,Forecast!I31)) | K31: =IF(A31="","",IF($B31=1,I31-J31,Forecast!J31)) | L31: =IF(A31="","",IF($B31=1,K31+G31+Forecast!K31,Forecast!L31)) | M31: =IF(A31="","",IF($B31=1,Forecast!M31-Setup!$B$8,Forecast!M31)) | N31: =IF(A31="","",IF($B31=1,L31-M31,Forecast!O31)) | O31: =IF(A31="","",IF($B31=1,N31-Forecast!N31,Forecast!P31)) | P31: =IF(A31="","",(Forecast!$Q$5-Forecast!$P$5)+SUM($O$5:O31))
A32: =IF(Forecast!A32="","",Forecast!A32) | B32: =IF(A32="","",IF(27>=N(Setup!$C$18),1,0)) | C32: =IF(A32="","",IF($B32=1,Forecast!B32-Setup!$B$4,Forecast!B32)) | D32: =IF(A32="","",IF($B32=1,Forecast!C32-Setup!$B$5,Forecast!C32)) | E32: =IF(A32="","",IF($B32=1,Forecast!D32-Setup!$B$6,Forecast!D32)) | F32: =IF(A32="","",IF($B32=1,D32-E32,Forecast!E32)) | G32: =IF(A32="","",IF($B32=1,Forecast!F32-Setup!$B$7,Forecast!F32)) | H32: =IF(A32="","",IF($B32=1,Forecast!G32-N(Setup!$D$18)*Setup!$B$9/12,Forecast!G32)) | I32: =IF(A32="","",IF($B32=1,F32-G32-H32,Forecast!H32)) | J32: =IF(A32="","",IF($B32=1,MAX(0,I32)*Setup!$B$10,Forecast!I32)) | K32: =IF(A32="","",IF($B32=1,I32-J32,Forecast!J32)) | L32: =IF(A32="","",IF($B32=1,K32+G32+Forecast!K32,Forecast!L32)) | M32: =IF(A32="","",IF($B32=1,Forecast!M32-Setup!$B$8,Forecast!M32)) | N32: =IF(A32="","",IF($B32=1,L32-M32,Forecast!O32)) | O32: =IF(A32="","",IF($B32=1,N32-Forecast!N32,Forecast!P32)) | P32: =IF(A32="","",(Forecast!$Q$5-Forecast!$P$5)+SUM($O$5:O32))
A33: =IF(Forecast!A33="","",Forecast!A33) | B33: =IF(A33="","",IF(28>=N(Setup!$C$18),1,0)) | C33: =IF(A33="","",IF($B33=1,Forecast!B33-Setup!$B$4,Forecast!B33)) | D33: =IF(A33="","",IF($B33=1,Forecast!C33-Setup!$B$5,Forecast!C33)) | E33: =IF(A33="","",IF($B33=1,Forecast!D33-Setup!$B$6,Forecast!D33)) | F33: =IF(A33="","",IF($B33=1,D33-E33,Forecast!E33)) | G33: =IF(A33="","",IF($B33=1,Forecast!F33-Setup!$B$7,Forecast!F33)) | H33: =IF(A33="","",IF($B33=1,Forecast!G33-N(Setup!$D$18)*Setup!$B$9/12,Forecast!G33)) | I33: =IF(A33="","",IF($B33=1,F33-G33-H33,Forecast!H33)) | J33: =IF(A33="","",IF($B33=1,MAX(0,I33)*Setup!$B$10,Forecast!I33)) | K33: =IF(A33="","",IF($B33=1,I33-J33,Forecast!J33)) | L33: =IF(A33="","",IF($B33=1,K33+G33+Forecast!K33,Forecast!L33)) | M33: =IF(A33="","",IF($B33=1,Forecast!M33-Setup!$B$8,Forecast!M33)) | N33: =IF(A33="","",IF($B33=1,L33-M33,Forecast!O33)) | O33: =IF(A33="","",IF($B33=1,N33-Forecast!N33,Forecast!P33)) | P33: =IF(A33="","",(Forecast!$Q$5-Forecast!$P$5)+SUM($O$5:O33))
A34: =IF(Forecast!A34="","",Forecast!A34) | B34: =IF(A34="","",IF(29>=N(Setup!$C$18),1,0)) | C34: =IF(A34="","",IF($B34=1,Forecast!B34-Setup!$B$4,Forecast!B34)) | D34: =IF(A34="","",IF($B34=1,Forecast!C34-Setup!$B$5,Forecast!C34)) | E34: =IF(A34="","",IF($B34=1,Forecast!D34-Setup!$B$6,Forecast!D34)) | F34: =IF(A34="","",IF($B34=1,D34-E34,Forecast!E34)) | G34: =IF(A34="","",IF($B34=1,Forecast!F34-Setup!$B$7,Forecast!F34)) | H34: =IF(A34="","",IF($B34=1,Forecast!G34-N(Setup!$D$18)*Setup!$B$9/12,Forecast!G34)) | I34: =IF(A34="","",IF($B34=1,F34-G34-H34,Forecast!H34)) | J34: =IF(A34="","",IF($B34=1,MAX(0,I34)*Setup!$B$10,Forecast!I34)) | K34: =IF(A34="","",IF($B34=1,I34-J34,Forecast!J34)) | L34: =IF(A34="","",IF($B34=1,K34+G34+Forecast!K34,Forecast!L34)) | M34: =IF(A34="","",IF($B34=1,Forecast!M34-Setup!$B$8,Forecast!M34)) | N34: =IF(A34="","",IF($B34=1,L34-M34,Forecast!O34)) | O34: =IF(A34="","",IF($B34=1,N34-Forecast!N34,Forecast!P34)) | P34: =IF(A34="","",(Forecast!$Q$5-Forecast!$P$5)+SUM($O$5:O34))
A35: =IF(Forecast!A35="","",Forecast!A35) | B35: =IF(A35="","",IF(30>=N(Setup!$C$18),1,0)) | C35: =IF(A35="","",IF($B35=1,Forecast!B35-Setup!$B$4,Forecast!B35)) | D35: =IF(A35="","",IF($B35=1,Forecast!C35-Setup!$B$5,Forecast!C35)) | E35: =IF(A35="","",IF($B35=1,Forecast!D35-Setup!$B$6,Forecast!D35)) | F35: =IF(A35="","",IF($B35=1,D35-E35,Forecast!E35)) | G35: =IF(A35="","",IF($B35=1,Forecast!F35-Setup!$B$7,Forecast!F35)) | H35: =IF(A35="","",IF($B35=1,Forecast!G35-N(Setup!$D$18)*Setup!$B$9/12,Forecast!G35)) | I35: =IF(A35="","",IF($B35=1,F35-G35-H35,Forecast!H35)) | J35: =IF(A35="","",IF($B35=1,MAX(0,I35)*Setup!$B$10,Forecast!I35)) | K35: =IF(A35="","",IF($B35=1,I35-J35,Forecast!J35)) | L35: =IF(A35="","",IF($B35=1,K35+G35+Forecast!K35,Forecast!L35)) | M35: =IF(A35="","",IF($B35=1,Forecast!M35-Setup!$B$8,Forecast!M35)) | N35: =IF(A35="","",IF($B35=1,L35-M35,Forecast!O35)) | O35: =IF(A35="","",IF($B35=1,N35-Forecast!N35,Forecast!P35)) | P35: =IF(A35="","",(Forecast!$Q$5-Forecast!$P$5)+SUM($O$5:O35))
A36: =IF(Forecast!A36="","",Forecast!A36) | B36: =IF(A36="","",IF(31>=N(Setup!$C$18),1,0)) | C36: =IF(A36="","",IF($B36=1,Forecast!B36-Setup!$B$4,Forecast!B36)) | D36: =IF(A36="","",IF($B36=1,Forecast!C36-Setup!$B$5,Forecast!C36)) | E36: =IF(A36="","",IF($B36=1,Forecast!D36-Setup!$B$6,Forecast!D36)) | F36: =IF(A36="","",IF($B36=1,D36-E36,Forecast!E36)) | G36: =IF(A36="","",IF($B36=1,Forecast!F36-Setup!$B$7,Forecast!F36)) | H36: =IF(A36="","",IF($B36=1,Forecast!G36-N(Setup!$D$18)*Setup!$B$9/12,Forecast!G36)) | I36: =IF(A36="","",IF($B36=1,F36-G36-H36,Forecast!H36)) | J36: =IF(A36="","",IF($B36=1,MAX(0,I36)*Setup!$B$10,Forecast!I36)) | K36: =IF(A36="","",IF($B36=1,I36-J36,Forecast!J36)) | L36: =IF(A36="","",IF($B36=1,K36+G36+Forecast!K36,Forecast!L36)) | M36: =IF(A36="","",IF($B36=1,Forecast!M36-Setup!$B$8,Forecast!M36)) | N36: =IF(A36="","",IF($B36=1,L36-M36,Forecast!O36)) | O36: =IF(A36="","",IF($B36=1,N36-Forecast!N36,Forecast!P36)) | P36: =IF(A36="","",(Forecast!$Q$5-Forecast!$P$5)+SUM($O$5:O36))
A37: =IF(Forecast!A37="","",Forecast!A37) | B37: =IF(A37="","",IF(32>=N(Setup!$C$18),1,0)) | C37: =IF(A37="","",IF($B37=1,Forecast!B37-Setup!$B$4,Forecast!B37)) | D37: =IF(A37="","",IF($B37=1,Forecast!C37-Setup!$B$5,Forecast!C37)) | E37: =IF(A37="","",IF($B37=1,Forecast!D37-Setup!$B$6,Forecast!D37)) | F37: =IF(A37="","",IF($B37=1,D37-E37,Forecast!E37)) | G37: =IF(A37="","",IF($B37=1,Forecast!F37-Setup!$B$7,Forecast!F37)) | H37: =IF(A37="","",IF($B37=1,Forecast!G37-N(Setup!$D$18)*Setup!$B$9/12,Forecast!G37)) | I37: =IF(A37="","",IF($B37=1,F37-G37-H37,Forecast!H37)) | J37: =IF(A37="","",IF($B37=1,MAX(0,I37)*Setup!$B$10,Forecast!I37)) | K37: =IF(A37="","",IF($B37=1,I37-J37,Forecast!J37)) | L37: =IF(A37="","",IF($B37=1,K37+G37+Forecast!K37,Forecast!L37)) | M37: =IF(A37="","",IF($B37=1,Forecast!M37-Setup!$B$8,Forecast!M37)) | N37: =IF(A37="","",IF($B37=1,L37-M37,Forecast!O37)) | O37: =IF(A37="","",IF($B37=1,N37-Forecast!N37,Forecast!P37)) | P37: =IF(A37="","",(Forecast!$Q$5-Forecast!$P$5)+SUM($O$5:O37))
A38: =IF(Forecast!A38="","",Forecast!A38) | B38: =IF(A38="","",IF(33>=N(Setup!$C$18),1,0)) | C38: =IF(A38="","",IF($B38=1,Forecast!B38-Setup!$B$4,Forecast!B38)) | D38: =IF(A38="","",IF($B38=1,Forecast!C38-Setup!$B$5,Forecast!C38)) | E38: =IF(A38="","",IF($B38=1,Forecast!D38-Setup!$B$6,Forecast!D38)) | F38: =IF(A38="","",IF($B38=1,D38-E38,Forecast!E38)) | G38: =IF(A38="","",IF($B38=1,Forecast!F38-Setup!$B$7,Forecast!F38)) | H38: =IF(A38="","",IF($B38=1,Forecast!G38-N(Setup!$D$18)*Setup!$B$9/12,Forecast!G38)) | I38: =IF(A38="","",IF($B38=1,F38-G38-H38,Forecast!H38)) | J38: =IF(A38="","",IF($B38=1,MAX(0,I38)*Setup!$B$10,Forecast!I38)) | K38: =IF(A38="","",IF($B38=1,I38-J38,Forecast!J38)) | L38: =IF(A38="","",IF($B38=1,K38+G38+Forecast!K38,Forecast!L38)) | M38: =IF(A38="","",IF($B38=1,Forecast!M38-Setup!$B$8,Forecast!M38)) | N38: =IF(A38="","",IF($B38=1,L38-M38,Forecast!O38)) | O38: =IF(A38="","",IF($B38=1,N38-Forecast!N38,Forecast!P38)) | P38: =IF(A38="","",(Forecast!$Q$5-Forecast!$P$5)+SUM($O$5:O38))
A39: =IF(Forecast!A39="","",Forecast!A39) | B39: =IF(A39="","",IF(34>=N(Setup!$C$18),1,0)) | C39: =IF(A39="","",IF($B39=1,Forecast!B39-Setup!$B$4,Forecast!B39)) | D39: =IF(A39="","",IF($B39=1,Forecast!C39-Setup!$B$5,Forecast!C39)) | E39: =IF(A39="","",IF($B39=1,Forecast!D39-Setup!$B$6,Forecast!D39)) | F39: =IF(A39="","",IF($B39=1,D39-E39,Forecast!E39)) | G39: =IF(A39="","",IF($B39=1,Forecast!F39-Setup!$B$7,Forecast!F39)) | H39: =IF(A39="","",IF($B39=1,Forecast!G39-N(Setup!$D$18)*Setup!$B$9/12,Forecast!G39)) | I39: =IF(A39="","",IF($B39=1,F39-G39-H39,Forecast!H39)) | J39: =IF(A39="","",IF($B39=1,MAX(0,I39)*Setup!$B$10,Forecast!I39)) | K39: =IF(A39="","",IF($B39=1,I39-J39,Forecast!J39)) | L39: =IF(A39="","",IF($B39=1,K39+G39+Forecast!K39,Forecast!L39)) | M39: =IF(A39="","",IF($B39=1,Forecast!M39-Setup!$B$8,Forecast!M39)) | N39: =IF(A39="","",IF($B39=1,L39-M39,Forecast!O39)) | O39: =IF(A39="","",IF($B39=1,N39-Forecast!N39,Forecast!P39)) | P39: =IF(A39="","",(Forecast!$Q$5-Forecast!$P$5)+SUM($O$5:O39))
A40: =IF(Forecast!A40="","",Forecast!A40) | B40: =IF(A40="","",IF(35>=N(Setup!$C$18),1,0)) | C40: =IF(A40="","",IF($B40=1,Forecast!B40-Setup!$B$4,Forecast!B40)) | D40: =IF(A40="","",IF($B40=1,Forecast!C40-Setup!$B$5,Forecast!C40)) | E40: =IF(A40="","",IF($B40=1,Forecast!D40-Setup!$B$6,Forecast!D40)) | F40: =IF(A40="","",IF($B40=1,D40-E40,Forecast!E40)) | G40: =IF(A40="","",IF($B40=1,Forecast!F40-Setup!$B$7,Forecast!F40)) | H40: =IF(A40="","",IF($B40=1,Forecast!G40-N(Setup!$D$18)*Setup!$B$9/12,Forecast!G40)) | I40: =IF(A40="","",IF($B40=1,F40-G40-H40,Forecast!H40)) | J40: =IF(A40="","",IF($B40=1,MAX(0,I40)*Setup!$B$10,Forecast!I40)) | K40: =IF(A40="","",IF($B40=1,I40-J40,Forecast!J40)) | L40: =IF(A40="","",IF($B40=1,K40+G40+Forecast!K40,Forecast!L40)) | M40: =IF(A40="","",IF($B40=1,Forecast!M40-Setup!$B$8,Forecast!M40)) | N40: =IF(A40="","",IF($B40=1,L40-M40,Forecast!O40)) | O40: =IF(A40="","",IF($B40=1,N40-Forecast!N40,Forecast!P40)) | P40: =IF(A40="","",(Forecast!$Q$5-Forecast!$P$5)+SUM($O$5:O40))
A41: =IF(Forecast!A41="","",Forecast!A41) | B41: =IF(A41="","",IF(36>=N(Setup!$C$18),1,0)) | C41: =IF(A41="","",IF($B41=1,Forecast!B41-Setup!$B$4,Forecast!B41)) | D41: =IF(A41="","",IF($B41=1,Forecast!C41-Setup!$B$5,Forecast!C41)) | E41: =IF(A41="","",IF($B41=1,Forecast!D41-Setup!$B$6,Forecast!D41)) | F41: =IF(A41="","",IF($B41=1,D41-E41,Forecast!E41)) | G41: =IF(A41="","",IF($B41=1,Forecast!F41-Setup!$B$7,Forecast!F41)) | H41: =IF(A41="","",IF($B41=1,Forecast!G41-N(Setup!$D$18)*Setup!$B$9/12,Forecast!G41)) | I41: =IF(A41="","",IF($B41=1,F41-G41-H41,Forecast!H41)) | J41: =IF(A41="","",IF($B41=1,MAX(0,I41)*Setup!$B$10,Forecast!I41)) | K41: =IF(A41="","",IF($B41=1,I41-J41,Forecast!J41)) | L41: =IF(A41="","",IF($B41=1,K41+G41+Forecast!K41,Forecast!L41)) | M41: =IF(A41="","",IF($B41=1,Forecast!M41-Setup!$B$8,Forecast!M41)) | N41: =IF(A41="","",IF($B41=1,L41-M41,Forecast!O41)) | O41: =IF(A41="","",IF($B41=1,N41-Forecast!N41,Forecast!P41)) | P41: =IF(A41="","",(Forecast!$Q$5-Forecast!$P$5)+SUM($O$5:O41))
A42: =IF(Forecast!A42="","",Forecast!A42) | B42: =IF(A42="","",IF(37>=N(Setup!$C$18),1,0)) | C42: =IF(A42="","",IF($B42=1,Forecast!B42-Setup!$B$4,Forecast!B42)) | D42: =IF(A42="","",IF($B42=1,Forecast!C42-Setup!$B$5,Forecast!C42)) | E42: =IF(A42="","",IF($B42=1,Forecast!D42-Setup!$B$6,Forecast!D42)) | F42: =IF(A42="","",IF($B42=1,D42-E42,Forecast!E42)) | G42: =IF(A42="","",IF($B42=1,Forecast!F42-Setup!$B$7,Forecast!F42)) | H42: =IF(A42="","",IF($B42=1,Forecast!G42-N(Setup!$D$18)*Setup!$B$9/12,Forecast!G42)) | I42: =IF(A42="","",IF($B42=1,F42-G42-H42,Forecast!H42)) | J42: =IF(A42="","",IF($B42=1,MAX(0,I42)*Setup!$B$10,Forecast!I42)) | K42: =IF(A42="","",IF($B42=1,I42-J42,Forecast!J42)) | L42: =IF(A42="","",IF($B42=1,K42+G42+Forecast!K42,Forecast!L42)) | M42: =IF(A42="","",IF($B42=1,Forecast!M42-Setup!$B$8,Forecast!M42)) | N42: =IF(A42="","",IF($B42=1,L42-M42,Forecast!O42)) | O42: =IF(A42="","",IF($B42=1,N42-Forecast!N42,Forecast!P42)) | P42: =IF(A42="","",(Forecast!$Q$5-Forecast!$P$5)+SUM($O$5:O42))
A43: =IF(Forecast!A43="","",Forecast!A43) | B43: =IF(A43="","",IF(38>=N(Setup!$C$18),1,0)) | C43: =IF(A43="","",IF($B43=1,Forecast!B43-Setup!$B$4,Forecast!B43)) | D43: =IF(A43="","",IF($B43=1,Forecast!C43-Setup!$B$5,Forecast!C43)) | E43: =IF(A43="","",IF($B43=1,Forecast!D43-Setup!$B$6,Forecast!D43)) | F43: =IF(A43="","",IF($B43=1,D43-E43,Forecast!E43)) | G43: =IF(A43="","",IF($B43=1,Forecast!F43-Setup!$B$7,Forecast!F43)) | H43: =IF(A43="","",IF($B43=1,Forecast!G43-N(Setup!$D$18)*Setup!$B$9/12,Forecast!G43)) | I43: =IF(A43="","",IF($B43=1,F43-G43-H43,Forecast!H43)) | J43: =IF(A43="","",IF($B43=1,MAX(0,I43)*Setup!$B$10,Forecast!I43)) | K43: =IF(A43="","",IF($B43=1,I43-J43,Forecast!J43)) | L43: =IF(A43="","",IF($B43=1,K43+G43+Forecast!K43,Forecast!L43)) | M43: =IF(A43="","",IF($B43=1,Forecast!M43-Setup!$B$8,Forecast!M43)) | N43: =IF(A43="","",IF($B43=1,L43-M43,Forecast!O43)) | O43: =IF(A43="","",IF($B43=1,N43-Forecast!N43,Forecast!P43)) | P43: =IF(A43="","",(Forecast!$Q$5-Forecast!$P$5)+SUM($O$5:O43))
A44: =IF(Forecast!A44="","",Forecast!A44) | B44: =IF(A44="","",IF(39>=N(Setup!$C$18),1,0)) | C44: =IF(A44="","",IF($B44=1,Forecast!B44-Setup!$B$4,Forecast!B44)) | D44: =IF(A44="","",IF($B44=1,Forecast!C44-Setup!$B$5,Forecast!C44)) | E44: =IF(A44="","",IF($B44=1,Forecast!D44-Setup!$B$6,Forecast!D44)) | F44: =IF(A44="","",IF($B44=1,D44-E44,Forecast!E44)) | G44: =IF(A44="","",IF($B44=1,Forecast!F44-Setup!$B$7,Forecast!F44)) | H44: =IF(A44="","",IF($B44=1,Forecast!G44-N(Setup!$D$18)*Setup!$B$9/12,Forecast!G44)) | I44: =IF(A44="","",IF($B44=1,F44-G44-H44,Forecast!H44)) | J44: =IF(A44="","",IF($B44=1,MAX(0,I44)*Setup!$B$10,Forecast!I44)) | K44: =IF(A44="","",IF($B44=1,I44-J44,Forecast!J44)) | L44: =IF(A44="","",IF($B44=1,K44+G44+Forecast!K44,Forecast!L44)) | M44: =IF(A44="","",IF($B44=1,Forecast!M44-Setup!$B$8,Forecast!M44)) | N44: =IF(A44="","",IF($B44=1,L44-M44,Forecast!O44)) | O44: =IF(A44="","",IF($B44=1,N44-Forecast!N44,Forecast!P44)) | P44: =IF(A44="","",(Forecast!$Q$5-Forecast!$P$5)+SUM($O$5:O44))
A45: =IF(Forecast!A45="","",Forecast!A45) | B45: =IF(A45="","",IF(40>=N(Setup!$C$18),1,0)) | C45: =IF(A45="","",IF($B45=1,Forecast!B45-Setup!$B$4,Forecast!B45)) | D45: =IF(A45="","",IF($B45=1,Forecast!C45-Setup!$B$5,Forecast!C45)) | E45: =IF(A45="","",IF($B45=1,Forecast!D45-Setup!$B$6,Forecast!D45)) | F45: =IF(A45="","",IF($B45=1,D45-E45,Forecast!E45)) | G45: =IF(A45="","",IF($B45=1,Forecast!F45-Setup!$B$7,Forecast!F45)) | H45: =IF(A45="","",IF($B45=1,Forecast!G45-N(Setup!$D$18)*Setup!$B$9/12,Forecast!G45)) | I45: =IF(A45="","",IF($B45=1,F45-G45-H45,Forecast!H45)) | J45: =IF(A45="","",IF($B45=1,MAX(0,I45)*Setup!$B$10,Forecast!I45)) | K45: =IF(A45="","",IF($B45=1,I45-J45,Forecast!J45)) | L45: =IF(A45="","",IF($B45=1,K45+G45+Forecast!K45,Forecast!L45)) | M45: =IF(A45="","",IF($B45=1,Forecast!M45-Setup!$B$8,Forecast!M45)) | N45: =IF(A45="","",IF($B45=1,L45-M45,Forecast!O45)) | O45: =IF(A45="","",IF($B45=1,N45-Forecast!N45,Forecast!P45)) | P45: =IF(A45="","",(Forecast!$Q$5-Forecast!$P$5)+SUM($O$5:O45))
A46: =IF(Forecast!A46="","",Forecast!A46) | B46: =IF(A46="","",IF(41>=N(Setup!$C$18),1,0)) | C46: =IF(A46="","",IF($B46=1,Forecast!B46-Setup!$B$4,Forecast!B46)) | D46: =IF(A46="","",IF($B46=1,Forecast!C46-Setup!$B$5,Forecast!C46)) | E46: =IF(A46="","",IF($B46=1,Forecast!D46-Setup!$B$6,Forecast!D46)) | F46: =IF(A46="","",IF($B46=1,D46-E46,Forecast!E46)) | G46: =IF(A46="","",IF($B46=1,Forecast!F46-Setup!$B$7,Forecast!F46)) | H46: =IF(A46="","",IF($B46=1,Forecast!G46-N(Setup!$D$18)*Setup!$B$9/12,Forecast!G46)) | I46: =IF(A46="","",IF($B46=1,F46-G46-H46,Forecast!H46)) | J46: =IF(A46="","",IF($B46=1,MAX(0,I46)*Setup!$B$10,Forecast!I46)) | K46: =IF(A46="","",IF($B46=1,I46-J46,Forecast!J46)) | L46: =IF(A46="","",IF($B46=1,K46+G46+Forecast!K46,Forecast!L46)) | M46: =IF(A46="","",IF($B46=1,Forecast!M46-Setup!$B$8,Forecast!M46)) | N46: =IF(A46="","",IF($B46=1,L46-M46,Forecast!O46)) | O46: =IF(A46="","",IF($B46=1,N46-Forecast!N46,Forecast!P46)) | P46: =IF(A46="","",(Forecast!$Q$5-Forecast!$P$5)+SUM($O$5:O46))
A47: =IF(Forecast!A47="","",Forecast!A47) | B47: =IF(A47="","",IF(42>=N(Setup!$C$18),1,0)) | C47: =IF(A47="","",IF($B47=1,Forecast!B47-Setup!$B$4,Forecast!B47)) | D47: =IF(A47="","",IF($B47=1,Forecast!C47-Setup!$B$5,Forecast!C47)) | E47: =IF(A47="","",IF($B47=1,Forecast!D47-Setup!$B$6,Forecast!D47)) | F47: =IF(A47="","",IF($B47=1,D47-E47,Forecast!E47)) | G47: =IF(A47="","",IF($B47=1,Forecast!F47-Setup!$B$7,Forecast!F47)) | H47: =IF(A47="","",IF($B47=1,Forecast!G47-N(Setup!$D$18)*Setup!$B$9/12,Forecast!G47)) | I47: =IF(A47="","",IF($B47=1,F47-G47-H47,Forecast!H47)) | J47: =IF(A47="","",IF($B47=1,MAX(0,I47)*Setup!$B$10,Forecast!I47)) | K47: =IF(A47="","",IF($B47=1,I47-J47,Forecast!J47)) | L47: =IF(A47="","",IF($B47=1,K47+G47+Forecast!K47,Forecast!L47)) | M47: =IF(A47="","",IF($B47=1,Forecast!M47-Setup!$B$8,Forecast!M47)) | N47: =IF(A47="","",IF($B47=1,L47-M47,Forecast!O47)) | O47: =IF(A47="","",IF($B47=1,N47-Forecast!N47,Forecast!P47)) | P47: =IF(A47="","",(Forecast!$Q$5-Forecast!$P$5)+SUM($O$5:O47))
A48: =IF(Forecast!A48="","",Forecast!A48) | B48: =IF(A48="","",IF(43>=N(Setup!$C$18),1,0)) | C48: =IF(A48="","",IF($B48=1,Forecast!B48-Setup!$B$4,Forecast!B48)) | D48: =IF(A48="","",IF($B48=1,Forecast!C48-Setup!$B$5,Forecast!C48)) | E48: =IF(A48="","",IF($B48=1,Forecast!D48-Setup!$B$6,Forecast!D48)) | F48: =IF(A48="","",IF($B48=1,D48-E48,Forecast!E48)) | G48: =IF(A48="","",IF($B48=1,Forecast!F48-Setup!$B$7,Forecast!F48)) | H48: =IF(A48="","",IF($B48=1,Forecast!G48-N(Setup!$D$18)*Setup!$B$9/12,Forecast!G48)) | I48: =IF(A48="","",IF($B48=1,F48-G48-H48,Forecast!H48)) | J48: =IF(A48="","",IF($B48=1,MAX(0,I48)*Setup!$B$10,Forecast!I48)) | K48: =IF(A48="","",IF($B48=1,I48-J48,Forecast!J48)) | L48: =IF(A48="","",IF($B48=1,K48+G48+Forecast!K48,Forecast!L48)) | M48: =IF(A48="","",IF($B48=1,Forecast!M48-Setup!$B$8,Forecast!M48)) | N48: =IF(A48="","",IF($B48=1,L48-M48,Forecast!O48)) | O48: =IF(A48="","",IF($B48=1,N48-Forecast!N48,Forecast!P48)) | P48: =IF(A48="","",(Forecast!$Q$5-Forecast!$P$5)+SUM($O$5:O48))
A49: =IF(Forecast!A49="","",Forecast!A49) | B49: =IF(A49="","",IF(44>=N(Setup!$C$18),1,0)) | C49: =IF(A49="","",IF($B49=1,Forecast!B49-Setup!$B$4,Forecast!B49)) | D49: =IF(A49="","",IF($B49=1,Forecast!C49-Setup!$B$5,Forecast!C49)) | E49: =IF(A49="","",IF($B49=1,Forecast!D49-Setup!$B$6,Forecast!D49)) | F49: =IF(A49="","",IF($B49=1,D49-E49,Forecast!E49)) | G49: =IF(A49="","",IF($B49=1,Forecast!F49-Setup!$B$7,Forecast!F49)) | H49: =IF(A49="","",IF($B49=1,Forecast!G49-N(Setup!$D$18)*Setup!$B$9/12,Forecast!G49)) | I49: =IF(A49="","",IF($B49=1,F49-G49-H49,Forecast!H49)) | J49: =IF(A49="","",IF($B49=1,MAX(0,I49)*Setup!$B$10,Forecast!I49)) | K49: =IF(A49="","",IF($B49=1,I49-J49,Forecast!J49)) | L49: =IF(A49="","",IF($B49=1,K49+G49+Forecast!K49,Forecast!L49)) | M49: =IF(A49="","",IF($B49=1,Forecast!M49-Setup!$B$8,Forecast!M49)) | N49: =IF(A49="","",IF($B49=1,L49-M49,Forecast!O49)) | O49: =IF(A49="","",IF($B49=1,N49-Forecast!N49,Forecast!P49)) | P49: =IF(A49="","",(Forecast!$Q$5-Forecast!$P$5)+SUM($O$5:O49))
A50: =IF(Forecast!A50="","",Forecast!A50) | B50: =IF(A50="","",IF(45>=N(Setup!$C$18),1,0)) | C50: =IF(A50="","",IF($B50=1,Forecast!B50-Setup!$B$4,Forecast!B50)) | D50: =IF(A50="","",IF($B50=1,Forecast!C50-Setup!$B$5,Forecast!C50)) | E50: =IF(A50="","",IF($B50=1,Forecast!D50-Setup!$B$6,Forecast!D50)) | F50: =IF(A50="","",IF($B50=1,D50-E50,Forecast!E50)) | G50: =IF(A50="","",IF($B50=1,Forecast!F50-Setup!$B$7,Forecast!F50)) | H50: =IF(A50="","",IF($B50=1,Forecast!G50-N(Setup!$D$18)*Setup!$B$9/12,Forecast!G50)) | I50: =IF(A50="","",IF($B50=1,F50-G50-H50,Forecast!H50)) | J50: =IF(A50="","",IF($B50=1,MAX(0,I50)*Setup!$B$10,Forecast!I50)) | K50: =IF(A50="","",IF($B50=1,I50-J50,Forecast!J50)) | L50: =IF(A50="","",IF($B50=1,K50+G50+Forecast!K50,Forecast!L50)) | M50: =IF(A50="","",IF($B50=1,Forecast!M50-Setup!$B$8,Forecast!M50)) | N50: =IF(A50="","",IF($B50=1,L50-M50,Forecast!O50)) | O50: =IF(A50="","",IF($B50=1,N50-Forecast!N50,Forecast!P50)) | P50: =IF(A50="","",(Forecast!$Q$5-Forecast!$P$5)+SUM($O$5:O50))
A51: =IF(Forecast!A51="","",Forecast!A51) | B51: =IF(A51="","",IF(46>=N(Setup!$C$18),1,0)) | C51: =IF(A51="","",IF($B51=1,Forecast!B51-Setup!$B$4,Forecast!B51)) | D51: =IF(A51="","",IF($B51=1,Forecast!C51-Setup!$B$5,Forecast!C51)) | E51: =IF(A51="","",IF($B51=1,Forecast!D51-Setup!$B$6,Forecast!D51)) | F51: =IF(A51="","",IF($B51=1,D51-E51,Forecast!E51)) | G51: =IF(A51="","",IF($B51=1,Forecast!F51-Setup!$B$7,Forecast!F51)) | H51: =IF(A51="","",IF($B51=1,Forecast!G51-N(Setup!$D$18)*Setup!$B$9/12,Forecast!G51)) | I51: =IF(A51="","",IF($B51=1,F51-G51-H51,Forecast!H51)) | J51: =IF(A51="","",IF($B51=1,MAX(0,I51)*Setup!$B$10,Forecast!I51)) | K51: =IF(A51="","",IF($B51=1,I51-J51,Forecast!J51)) | L51: =IF(A51="","",IF($B51=1,K51+G51+Forecast!K51,Forecast!L51)) | M51: =IF(A51="","",IF($B51=1,Forecast!M51-Setup!$B$8,Forecast!M51)) | N51: =IF(A51="","",IF($B51=1,L51-M51,Forecast!O51)) | O51: =IF(A51="","",IF($B51=1,N51-Forecast!N51,Forecast!P51)) | P51: =IF(A51="","",(Forecast!$Q$5-Forecast!$P$5)+SUM($O$5:O51))
A52: =IF(Forecast!A52="","",Forecast!A52) | B52: =IF(A52="","",IF(47>=N(Setup!$C$18),1,0)) | C52: =IF(A52="","",IF($B52=1,Forecast!B52-Setup!$B$4,Forecast!B52)) | D52: =IF(A52="","",IF($B52=1,Forecast!C52-Setup!$B$5,Forecast!C52)) | E52: =IF(A52="","",IF($B52=1,Forecast!D52-Setup!$B$6,Forecast!D52)) | F52: =IF(A52="","",IF($B52=1,D52-E52,Forecast!E52)) | G52: =IF(A52="","",IF($B52=1,Forecast!F52-Setup!$B$7,Forecast!F52)) | H52: =IF(A52="","",IF($B52=1,Forecast!G52-N(Setup!$D$18)*Setup!$B$9/12,Forecast!G52)) | I52: =IF(A52="","",IF($B52=1,F52-G52-H52,Forecast!H52)) | J52: =IF(A52="","",IF($B52=1,MAX(0,I52)*Setup!$B$10,Forecast!I52)) | K52: =IF(A52="","",IF($B52=1,I52-J52,Forecast!J52)) | L52: =IF(A52="","",IF($B52=1,K52+G52+Forecast!K52,Forecast!L52)) | M52: =IF(A52="","",IF($B52=1,Forecast!M52-Setup!$B$8,Forecast!M52)) | N52: =IF(A52="","",IF($B52=1,L52-M52,Forecast!O52)) | O52: =IF(A52="","",IF($B52=1,N52-Forecast!N52,Forecast!P52)) | P52: =IF(A52="","",(Forecast!$Q$5-Forecast!$P$5)+SUM($O$5:O52))
A53: =IF(Forecast!A53="","",Forecast!A53) | B53: =IF(A53="","",IF(48>=N(Setup!$C$18),1,0)) | C53: =IF(A53="","",IF($B53=1,Forecast!B53-Setup!$B$4,Forecast!B53)) | D53: =IF(A53="","",IF($B53=1,Forecast!C53-Setup!$B$5,Forecast!C53)) | E53: =IF(A53="","",IF($B53=1,Forecast!D53-Setup!$B$6,Forecast!D53)) | F53: =IF(A53="","",IF($B53=1,D53-E53,Forecast!E53)) | G53: =IF(A53="","",IF($B53=1,Forecast!F53-Setup!$B$7,Forecast!F53)) | H53: =IF(A53="","",IF($B53=1,Forecast!G53-N(Setup!$D$18)*Setup!$B$9/12,Forecast!G53)) | I53: =IF(A53="","",IF($B53=1,F53-G53-H53,Forecast!H53)) | J53: =IF(A53="","",IF($B53=1,MAX(0,I53)*Setup!$B$10,Forecast!I53)) | K53: =IF(A53="","",IF($B53=1,I53-J53,Forecast!J53)) | L53: =IF(A53="","",IF($B53=1,K53+G53+Forecast!K53,Forecast!L53)) | M53: =IF(A53="","",IF($B53=1,Forecast!M53-Setup!$B$8,Forecast!M53)) | N53: =IF(A53="","",IF($B53=1,L53-M53,Forecast!O53)) | O53: =IF(A53="","",IF($B53=1,N53-Forecast!N53,Forecast!P53)) | P53: =IF(A53="","",(Forecast!$Q$5-Forecast!$P$5)+SUM($O$5:O53))
A54: =IF(Forecast!A54="","",Forecast!A54) | B54: =IF(A54="","",IF(49>=N(Setup!$C$18),1,0)) | C54: =IF(A54="","",IF($B54=1,Forecast!B54-Setup!$B$4,Forecast!B54)) | D54: =IF(A54="","",IF($B54=1,Forecast!C54-Setup!$B$5,Forecast!C54)) | E54: =IF(A54="","",IF($B54=1,Forecast!D54-Setup!$B$6,Forecast!D54)) | F54: =IF(A54="","",IF($B54=1,D54-E54,Forecast!E54)) | G54: =IF(A54="","",IF($B54=1,Forecast!F54-Setup!$B$7,Forecast!F54)) | H54: =IF(A54="","",IF($B54=1,Forecast!G54-N(Setup!$D$18)*Setup!$B$9/12,Forecast!G54)) | I54: =IF(A54="","",IF($B54=1,F54-G54-H54,Forecast!H54)) | J54: =IF(A54="","",IF($B54=1,MAX(0,I54)*Setup!$B$10,Forecast!I54)) | K54: =IF(A54="","",IF($B54=1,I54-J54,Forecast!J54)) | L54: =IF(A54="","",IF($B54=1,K54+G54+Forecast!K54,Forecast!L54)) | M54: =IF(A54="","",IF($B54=1,Forecast!M54-Setup!$B$8,Forecast!M54)) | N54: =IF(A54="","",IF($B54=1,L54-M54,Forecast!O54)) | O54: =IF(A54="","",IF($B54=1,N54-Forecast!N54,Forecast!P54)) | P54: =IF(A54="","",(Forecast!$Q$5-Forecast!$P$5)+SUM($O$5:O54))
A55: =IF(Forecast!A55="","",Forecast!A55) | B55: =IF(A55="","",IF(50>=N(Setup!$C$18),1,0)) | C55: =IF(A55="","",IF($B55=1,Forecast!B55-Setup!$B$4,Forecast!B55)) | D55: =IF(A55="","",IF($B55=1,Forecast!C55-Setup!$B$5,Forecast!C55)) | E55: =IF(A55="","",IF($B55=1,Forecast!D55-Setup!$B$6,Forecast!D55)) | F55: =IF(A55="","",IF($B55=1,D55-E55,Forecast!E55)) | G55: =IF(A55="","",IF($B55=1,Forecast!F55-Setup!$B$7,Forecast!F55)) | H55: =IF(A55="","",IF($B55=1,Forecast!G55-N(Setup!$D$18)*Setup!$B$9/12,Forecast!G55)) | I55: =IF(A55="","",IF($B55=1,F55-G55-H55,Forecast!H55)) | J55: =IF(A55="","",IF($B55=1,MAX(0,I55)*Setup!$B$10,Forecast!I55)) | K55: =IF(A55="","",IF($B55=1,I55-J55,Forecast!J55)) | L55: =IF(A55="","",IF($B55=1,K55+G55+Forecast!K55,Forecast!L55)) | M55: =IF(A55="","",IF($B55=1,Forecast!M55-Setup!$B$8,Forecast!M55)) | N55: =IF(A55="","",IF($B55=1,L55-M55,Forecast!O55)) | O55: =IF(A55="","",IF($B55=1,N55-Forecast!N55,Forecast!P55)) | P55: =IF(A55="","",(Forecast!$Q$5-Forecast!$P$5)+SUM($O$5:O55))
A56: =IF(Forecast!A56="","",Forecast!A56) | B56: =IF(A56="","",IF(51>=N(Setup!$C$18),1,0)) | C56: =IF(A56="","",IF($B56=1,Forecast!B56-Setup!$B$4,Forecast!B56)) | D56: =IF(A56="","",IF($B56=1,Forecast!C56-Setup!$B$5,Forecast!C56)) | E56: =IF(A56="","",IF($B56=1,Forecast!D56-Setup!$B$6,Forecast!D56)) | F56: =IF(A56="","",IF($B56=1,D56-E56,Forecast!E56)) | G56: =IF(A56="","",IF($B56=1,Forecast!F56-Setup!$B$7,Forecast!F56)) | H56: =IF(A56="","",IF($B56=1,Forecast!G56-N(Setup!$D$18)*Setup!$B$9/12,Forecast!G56)) | I56: =IF(A56="","",IF($B56=1,F56-G56-H56,Forecast!H56)) | J56: =IF(A56="","",IF($B56=1,MAX(0,I56)*Setup!$B$10,Forecast!I56)) | K56: =IF(A56="","",IF($B56=1,I56-J56,Forecast!J56)) | L56: =IF(A56="","",IF($B56=1,K56+G56+Forecast!K56,Forecast!L56)) | M56: =IF(A56="","",IF($B56=1,Forecast!M56-Setup!$B$8,Forecast!M56)) | N56: =IF(A56="","",IF($B56=1,L56-M56,Forecast!O56)) | O56: =IF(A56="","",IF($B56=1,N56-Forecast!N56,Forecast!P56)) | P56: =IF(A56="","",(Forecast!$Q$5-Forecast!$P$5)+SUM($O$5:O56))
A57: =IF(Forecast!A57="","",Forecast!A57) | B57: =IF(A57="","",IF(52>=N(Setup!$C$18),1,0)) | C57: =IF(A57="","",IF($B57=1,Forecast!B57-Setup!$B$4,Forecast!B57)) | D57: =IF(A57="","",IF($B57=1,Forecast!C57-Setup!$B$5,Forecast!C57)) | E57: =IF(A57="","",IF($B57=1,Forecast!D57-Setup!$B$6,Forecast!D57)) | F57: =IF(A57="","",IF($B57=1,D57-E57,Forecast!E57)) | G57: =IF(A57="","",IF($B57=1,Forecast!F57-Setup!$B$7,Forecast!F57)) | H57: =IF(A57="","",IF($B57=1,Forecast!G57-N(Setup!$D$18)*Setup!$B$9/12,Forecast!G57)) | I57: =IF(A57="","",IF($B57=1,F57-G57-H57,Forecast!H57)) | J57: =IF(A57="","",IF($B57=1,MAX(0,I57)*Setup!$B$10,Forecast!I57)) | K57: =IF(A57="","",IF($B57=1,I57-J57,Forecast!J57)) | L57: =IF(A57="","",IF($B57=1,K57+G57+Forecast!K57,Forecast!L57)) | M57: =IF(A57="","",IF($B57=1,Forecast!M57-Setup!$B$8,Forecast!M57)) | N57: =IF(A57="","",IF($B57=1,L57-M57,Forecast!O57)) | O57: =IF(A57="","",IF($B57=1,N57-Forecast!N57,Forecast!P57)) | P57: =IF(A57="","",(Forecast!$Q$5-Forecast!$P$5)+SUM($O$5:O57))
A58: =IF(Forecast!A58="","",Forecast!A58) | B58: =IF(A58="","",IF(53>=N(Setup!$C$18),1,0)) | C58: =IF(A58="","",IF($B58=1,Forecast!B58-Setup!$B$4,Forecast!B58)) | D58: =IF(A58="","",IF($B58=1,Forecast!C58-Setup!$B$5,Forecast!C58)) | E58: =IF(A58="","",IF($B58=1,Forecast!D58-Setup!$B$6,Forecast!D58)) | F58: =IF(A58="","",IF($B58=1,D58-E58,Forecast!E58)) | G58: =IF(A58="","",IF($B58=1,Forecast!F58-Setup!$B$7,Forecast!F58)) | H58: =IF(A58="","",IF($B58=1,Forecast!G58-N(Setup!$D$18)*Setup!$B$9/12,Forecast!G58)) | I58: =IF(A58="","",IF($B58=1,F58-G58-H58,Forecast!H58)) | J58: =IF(A58="","",IF($B58=1,MAX(0,I58)*Setup!$B$10,Forecast!I58)) | K58: =IF(A58="","",IF($B58=1,I58-J58,Forecast!J58)) | L58: =IF(A58="","",IF($B58=1,K58+G58+Forecast!K58,Forecast!L58)) | M58: =IF(A58="","",IF($B58=1,Forecast!M58-Setup!$B$8,Forecast!M58)) | N58: =IF(A58="","",IF($B58=1,L58-M58,Forecast!O58)) | O58: =IF(A58="","",IF($B58=1,N58-Forecast!N58,Forecast!P58)) | P58: =IF(A58="","",(Forecast!$Q$5-Forecast!$P$5)+SUM($O$5:O58))
A59: =IF(Forecast!A59="","",Forecast!A59) | B59: =IF(A59="","",IF(54>=N(Setup!$C$18),1,0)) | C59: =IF(A59="","",IF($B59=1,Forecast!B59-Setup!$B$4,Forecast!B59)) | D59: =IF(A59="","",IF($B59=1,Forecast!C59-Setup!$B$5,Forecast!C59)) | E59: =IF(A59="","",IF($B59=1,Forecast!D59-Setup!$B$6,Forecast!D59)) | F59: =IF(A59="","",IF($B59=1,D59-E59,Forecast!E59)) | G59: =IF(A59="","",IF($B59=1,Forecast!F59-Setup!$B$7,Forecast!F59)) | H59: =IF(A59="","",IF($B59=1,Forecast!G59-N(Setup!$D$18)*Setup!$B$9/12,Forecast!G59)) | I59: =IF(A59="","",IF($B59=1,F59-G59-H59,Forecast!H59)) | J59: =IF(A59="","",IF($B59=1,MAX(0,I59)*Setup!$B$10,Forecast!I59)) | K59: =IF(A59="","",IF($B59=1,I59-J59,Forecast!J59)) | L59: =IF(A59="","",IF($B59=1,K59+G59+Forecast!K59,Forecast!L59)) | M59: =IF(A59="","",IF($B59=1,Forecast!M59-Setup!$B$8,Forecast!M59)) | N59: =IF(A59="","",IF($B59=1,L59-M59,Forecast!O59)) | O59: =IF(A59="","",IF($B59=1,N59-Forecast!N59,Forecast!P59)) | P59: =IF(A59="","",(Forecast!$Q$5-Forecast!$P$5)+SUM($O$5:O59))
A60: =IF(Forecast!A60="","",Forecast!A60) | B60: =IF(A60="","",IF(55>=N(Setup!$C$18),1,0)) | C60: =IF(A60="","",IF($B60=1,Forecast!B60-Setup!$B$4,Forecast!B60)) | D60: =IF(A60="","",IF($B60=1,Forecast!C60-Setup!$B$5,Forecast!C60)) | E60: =IF(A60="","",IF($B60=1,Forecast!D60-Setup!$B$6,Forecast!D60)) | F60: =IF(A60="","",IF($B60=1,D60-E60,Forecast!E60)) | G60: =IF(A60="","",IF($B60=1,Forecast!F60-Setup!$B$7,Forecast!F60)) | H60: =IF(A60="","",IF($B60=1,Forecast!G60-N(Setup!$D$18)*Setup!$B$9/12,Forecast!G60)) | I60: =IF(A60="","",IF($B60=1,F60-G60-H60,Forecast!H60)) | J60: =IF(A60="","",IF($B60=1,MAX(0,I60)*Setup!$B$10,Forecast!I60)) | K60: =IF(A60="","",IF($B60=1,I60-J60,Forecast!J60)) | L60: =IF(A60="","",IF($B60=1,K60+G60+Forecast!K60,Forecast!L60)) | M60: =IF(A60="","",IF($B60=1,Forecast!M60-Setup!$B$8,Forecast!M60)) | N60: =IF(A60="","",IF($B60=1,L60-M60,Forecast!O60)) | O60: =IF(A60="","",IF($B60=1,N60-Forecast!N60,Forecast!P60)) | P60: =IF(A60="","",(Forecast!$Q$5-Forecast!$P$5)+SUM($O$5:O60))
A61: =IF(Forecast!A61="","",Forecast!A61) | B61: =IF(A61="","",IF(56>=N(Setup!$C$18),1,0)) | C61: =IF(A61="","",IF($B61=1,Forecast!B61-Setup!$B$4,Forecast!B61)) | D61: =IF(A61="","",IF($B61=1,Forecast!C61-Setup!$B$5,Forecast!C61)) | E61: =IF(A61="","",IF($B61=1,Forecast!D61-Setup!$B$6,Forecast!D61)) | F61: =IF(A61="","",IF($B61=1,D61-E61,Forecast!E61)) | G61: =IF(A61="","",IF($B61=1,Forecast!F61-Setup!$B$7,Forecast!F61)) | H61: =IF(A61="","",IF($B61=1,Forecast!G61-N(Setup!$D$18)*Setup!$B$9/12,Forecast!G61)) | I61: =IF(A61="","",IF($B61=1,F61-G61-H61,Forecast!H61)) | J61: =IF(A61="","",IF($B61=1,MAX(0,I61)*Setup!$B$10,Forecast!I61)) | K61: =IF(A61="","",IF($B61=1,I61-J61,Forecast!J61)) | L61: =IF(A61="","",IF($B61=1,K61+G61+Forecast!K61,Forecast!L61)) | M61: =IF(A61="","",IF($B61=1,Forecast!M61-Setup!$B$8,Forecast!M61)) | N61: =IF(A61="","",IF($B61=1,L61-M61,Forecast!O61)) | O61: =IF(A61="","",IF($B61=1,N61-Forecast!N61,Forecast!P61)) | P61: =IF(A61="","",(Forecast!$Q$5-Forecast!$P$5)+SUM($O$5:O61))
A62: =IF(Forecast!A62="","",Forecast!A62) | B62: =IF(A62="","",IF(57>=N(Setup!$C$18),1,0)) | C62: =IF(A62="","",IF($B62=1,Forecast!B62-Setup!$B$4,Forecast!B62)) | D62: =IF(A62="","",IF($B62=1,Forecast!C62-Setup!$B$5,Forecast!C62)) | E62: =IF(A62="","",IF($B62=1,Forecast!D62-Setup!$B$6,Forecast!D62)) | F62: =IF(A62="","",IF($B62=1,D62-E62,Forecast!E62)) | G62: =IF(A62="","",IF($B62=1,Forecast!F62-Setup!$B$7,Forecast!F62)) | H62: =IF(A62="","",IF($B62=1,Forecast!G62-N(Setup!$D$18)*Setup!$B$9/12,Forecast!G62)) | I62: =IF(A62="","",IF($B62=1,F62-G62-H62,Forecast!H62)) | J62: =IF(A62="","",IF($B62=1,MAX(0,I62)*Setup!$B$10,Forecast!I62)) | K62: =IF(A62="","",IF($B62=1,I62-J62,Forecast!J62)) | L62: =IF(A62="","",IF($B62=1,K62+G62+Forecast!K62,Forecast!L62)) | M62: =IF(A62="","",IF($B62=1,Forecast!M62-Setup!$B$8,Forecast!M62)) | N62: =IF(A62="","",IF($B62=1,L62-M62,Forecast!O62)) | O62: =IF(A62="","",IF($B62=1,N62-Forecast!N62,Forecast!P62)) | P62: =IF(A62="","",(Forecast!$Q$5-Forecast!$P$5)+SUM($O$5:O62))
A63: =IF(Forecast!A63="","",Forecast!A63) | B63: =IF(A63="","",IF(58>=N(Setup!$C$18),1,0)) | C63: =IF(A63="","",IF($B63=1,Forecast!B63-Setup!$B$4,Forecast!B63)) | D63: =IF(A63="","",IF($B63=1,Forecast!C63-Setup!$B$5,Forecast!C63)) | E63: =IF(A63="","",IF($B63=1,Forecast!D63-Setup!$B$6,Forecast!D63)) | F63: =IF(A63="","",IF($B63=1,D63-E63,Forecast!E63)) | G63: =IF(A63="","",IF($B63=1,Forecast!F63-Setup!$B$7,Forecast!F63)) | H63: =IF(A63="","",IF($B63=1,Forecast!G63-N(Setup!$D$18)*Setup!$B$9/12,Forecast!G63)) | I63: =IF(A63="","",IF($B63=1,F63-G63-H63,Forecast!H63)) | J63: =IF(A63="","",IF($B63=1,MAX(0,I63)*Setup!$B$10,Forecast!I63)) | K63: =IF(A63="","",IF($B63=1,I63-J63,Forecast!J63)) | L63: =IF(A63="","",IF($B63=1,K63+G63+Forecast!K63,Forecast!L63)) | M63: =IF(A63="","",IF($B63=1,Forecast!M63-Setup!$B$8,Forecast!M63)) | N63: =IF(A63="","",IF($B63=1,L63-M63,Forecast!O63)) | O63: =IF(A63="","",IF($B63=1,N63-Forecast!N63,Forecast!P63)) | P63: =IF(A63="","",(Forecast!$Q$5-Forecast!$P$5)+SUM($O$5:O63))
A64: =IF(Forecast!A64="","",Forecast!A64) | B64: =IF(A64="","",IF(59>=N(Setup!$C$18),1,0)) | C64: =IF(A64="","",IF($B64=1,Forecast!B64-Setup!$B$4,Forecast!B64)) | D64: =IF(A64="","",IF($B64=1,Forecast!C64-Setup!$B$5,Forecast!C64)) | E64: =IF(A64="","",IF($B64=1,Forecast!D64-Setup!$B$6,Forecast!D64)) | F64: =IF(A64="","",IF($B64=1,D64-E64,Forecast!E64)) | G64: =IF(A64="","",IF($B64=1,Forecast!F64-Setup!$B$7,Forecast!F64)) | H64: =IF(A64="","",IF($B64=1,Forecast!G64-N(Setup!$D$18)*Setup!$B$9/12,Forecast!G64)) | I64: =IF(A64="","",IF($B64=1,F64-G64-H64,Forecast!H64)) | J64: =IF(A64="","",IF($B64=1,MAX(0,I64)*Setup!$B$10,Forecast!I64)) | K64: =IF(A64="","",IF($B64=1,I64-J64,Forecast!J64)) | L64: =IF(A64="","",IF($B64=1,K64+G64+Forecast!K64,Forecast!L64)) | M64: =IF(A64="","",IF($B64=1,Forecast!M64-Setup!$B$8,Forecast!M64)) | N64: =IF(A64="","",IF($B64=1,L64-M64,Forecast!O64)) | O64: =IF(A64="","",IF($B64=1,N64-Forecast!N64,Forecast!P64)) | P64: =IF(A64="","",(Forecast!$Q$5-Forecast!$P$5)+SUM($O$5:O64))
A65: =IF(Forecast!A65="","",Forecast!A65) | B65: =IF(A65="","",IF(60>=N(Setup!$C$18),1,0)) | C65: =IF(A65="","",IF($B65=1,Forecast!B65-Setup!$B$4,Forecast!B65)) | D65: =IF(A65="","",IF($B65=1,Forecast!C65-Setup!$B$5,Forecast!C65)) | E65: =IF(A65="","",IF($B65=1,Forecast!D65-Setup!$B$6,Forecast!D65)) | F65: =IF(A65="","",IF($B65=1,D65-E65,Forecast!E65)) | G65: =IF(A65="","",IF($B65=1,Forecast!F65-Setup!$B$7,Forecast!F65)) | H65: =IF(A65="","",IF($B65=1,Forecast!G65-N(Setup!$D$18)*Setup!$B$9/12,Forecast!G65)) | I65: =IF(A65="","",IF($B65=1,F65-G65-H65,Forecast!H65)) | J65: =IF(A65="","",IF($B65=1,MAX(0,I65)*Setup!$B$10,Forecast!I65)) | K65: =IF(A65="","",IF($B65=1,I65-J65,Forecast!J65)) | L65: =IF(A65="","",IF($B65=1,K65+G65+Forecast!K65,Forecast!L65)) | M65: =IF(A65="","",IF($B65=1,Forecast!M65-Setup!$B$8,Forecast!M65)) | N65: =IF(A65="","",IF($B65=1,L65-M65,Forecast!O65)) | O65: =IF(A65="","",IF($B65=1,N65-Forecast!N65,Forecast!P65)) | P65: =IF(A65="","",(Forecast!$Q$5-Forecast!$P$5)+SUM($O$5:O65))
A66: =IF(Forecast!A66="","",Forecast!A66) | B66: =IF(A66="","",IF(61>=N(Setup!$C$18),1,0)) | C66: =IF(A66="","",IF($B66=1,Forecast!B66-Setup!$B$4,Forecast!B66)) | D66: =IF(A66="","",IF($B66=1,Forecast!C66-Setup!$B$5,Forecast!C66)) | E66: =IF(A66="","",IF($B66=1,Forecast!D66-Setup!$B$6,Forecast!D66)) | F66: =IF(A66="","",IF($B66=1,D66-E66,Forecast!E66)) | G66: =IF(A66="","",IF($B66=1,Forecast!F66-Setup!$B$7,Forecast!F66)) | H66: =IF(A66="","",IF($B66=1,Forecast!G66-N(Setup!$D$18)*Setup!$B$9/12,Forecast!G66)) | I66: =IF(A66="","",IF($B66=1,F66-G66-H66,Forecast!H66)) | J66: =IF(A66="","",IF($B66=1,MAX(0,I66)*Setup!$B$10,Forecast!I66)) | K66: =IF(A66="","",IF($B66=1,I66-J66,Forecast!J66)) | L66: =IF(A66="","",IF($B66=1,K66+G66+Forecast!K66,Forecast!L66)) | M66: =IF(A66="","",IF($B66=1,Forecast!M66-Setup!$B$8,Forecast!M66)) | N66: =IF(A66="","",IF($B66=1,L66-M66,Forecast!O66)) | O66: =IF(A66="","",IF($B66=1,N66-Forecast!N66,Forecast!P66)) | P66: =IF(A66="","",(Forecast!$Q$5-Forecast!$P$5)+SUM($O$5:O66))
A67: =IF(Forecast!A67="","",Forecast!A67) | B67: =IF(A67="","",IF(62>=N(Setup!$C$18),1,0)) | C67: =IF(A67="","",IF($B67=1,Forecast!B67-Setup!$B$4,Forecast!B67)) | D67: =IF(A67="","",IF($B67=1,Forecast!C67-Setup!$B$5,Forecast!C67)) | E67: =IF(A67="","",IF($B67=1,Forecast!D67-Setup!$B$6,Forecast!D67)) | F67: =IF(A67="","",IF($B67=1,D67-E67,Forecast!E67)) | G67: =IF(A67="","",IF($B67=1,Forecast!F67-Setup!$B$7,Forecast!F67)) | H67: =IF(A67="","",IF($B67=1,Forecast!G67-N(Setup!$D$18)*Setup!$B$9/12,Forecast!G67)) | I67: =IF(A67="","",IF($B67=1,F67-G67-H67,Forecast!H67)) | J67: =IF(A67="","",IF($B67=1,MAX(0,I67)*Setup!$B$10,Forecast!I67)) | K67: =IF(A67="","",IF($B67=1,I67-J67,Forecast!J67)) | L67: =IF(A67="","",IF($B67=1,K67+G67+Forecast!K67,Forecast!L67)) | M67: =IF(A67="","",IF($B67=1,Forecast!M67-Setup!$B$8,Forecast!M67)) | N67: =IF(A67="","",IF($B67=1,L67-M67,Forecast!O67)) | O67: =IF(A67="","",IF($B67=1,N67-Forecast!N67,Forecast!P67)) | P67: =IF(A67="","",(Forecast!$Q$5-Forecast!$P$5)+SUM($O$5:O67))
A68: =IF(Forecast!A68="","",Forecast!A68) | B68: =IF(A68="","",IF(63>=N(Setup!$C$18),1,0)) | C68: =IF(A68="","",IF($B68=1,Forecast!B68-Setup!$B$4,Forecast!B68)) | D68: =IF(A68="","",IF($B68=1,Forecast!C68-Setup!$B$5,Forecast!C68)) | E68: =IF(A68="","",IF($B68=1,Forecast!D68-Setup!$B$6,Forecast!D68)) | F68: =IF(A68="","",IF($B68=1,D68-E68,Forecast!E68)) | G68: =IF(A68="","",IF($B68=1,Forecast!F68-Setup!$B$7,Forecast!F68)) | H68: =IF(A68="","",IF($B68=1,Forecast!G68-N(Setup!$D$18)*Setup!$B$9/12,Forecast!G68)) | I68: =IF(A68="","",IF($B68=1,F68-G68-H68,Forecast!H68)) | J68: =IF(A68="","",IF($B68=1,MAX(0,I68)*Setup!$B$10,Forecast!I68)) | K68: =IF(A68="","",IF($B68=1,I68-J68,Forecast!J68)) | L68: =IF(A68="","",IF($B68=1,K68+G68+Forecast!K68,Forecast!L68)) | M68: =IF(A68="","",IF($B68=1,Forecast!M68-Setup!$B$8,Forecast!M68)) | N68: =IF(A68="","",IF($B68=1,L68-M68,Forecast!O68)) | O68: =IF(A68="","",IF($B68=1,N68-Forecast!N68,Forecast!P68)) | P68: =IF(A68="","",(Forecast!$Q$5-Forecast!$P$5)+SUM($O$5:O68))
A69: =IF(Forecast!A69="","",Forecast!A69) | B69: =IF(A69="","",IF(64>=N(Setup!$C$18),1,0)) | C69: =IF(A69="","",IF($B69=1,Forecast!B69-Setup!$B$4,Forecast!B69)) | D69: =IF(A69="","",IF($B69=1,Forecast!C69-Setup!$B$5,Forecast!C69)) | E69: =IF(A69="","",IF($B69=1,Forecast!D69-Setup!$B$6,Forecast!D69)) | F69: =IF(A69="","",IF($B69=1,D69-E69,Forecast!E69)) | G69: =IF(A69="","",IF($B69=1,Forecast!F69-Setup!$B$7,Forecast!F69)) | H69: =IF(A69="","",IF($B69=1,Forecast!G69-N(Setup!$D$18)*Setup!$B$9/12,Forecast!G69)) | I69: =IF(A69="","",IF($B69=1,F69-G69-H69,Forecast!H69)) | J69: =IF(A69="","",IF($B69=1,MAX(0,I69)*Setup!$B$10,Forecast!I69)) | K69: =IF(A69="","",IF($B69=1,I69-J69,Forecast!J69)) | L69: =IF(A69="","",IF($B69=1,K69+G69+Forecast!K69,Forecast!L69)) | M69: =IF(A69="","",IF($B69=1,Forecast!M69-Setup!$B$8,Forecast!M69)) | N69: =IF(A69="","",IF($B69=1,L69-M69,Forecast!O69)) | O69: =IF(A69="","",IF($B69=1,N69-Forecast!N69,Forecast!P69)) | P69: =IF(A69="","",(Forecast!$Q$5-Forecast!$P$5)+SUM($O$5:O69))
A70: =IF(Forecast!A70="","",Forecast!A70) | B70: =IF(A70="","",IF(65>=N(Setup!$C$18),1,0)) | C70: =IF(A70="","",IF($B70=1,Forecast!B70-Setup!$B$4,Forecast!B70)) | D70: =IF(A70="","",IF($B70=1,Forecast!C70-Setup!$B$5,Forecast!C70)) | E70: =IF(A70="","",IF($B70=1,Forecast!D70-Setup!$B$6,Forecast!D70)) | F70: =IF(A70="","",IF($B70=1,D70-E70,Forecast!E70)) | G70: =IF(A70="","",IF($B70=1,Forecast!F70-Setup!$B$7,Forecast!F70)) | H70: =IF(A70="","",IF($B70=1,Forecast!G70-N(Setup!$D$18)*Setup!$B$9/12,Forecast!G70)) | I70: =IF(A70="","",IF($B70=1,F70-G70-H70,Forecast!H70)) | J70: =IF(A70="","",IF($B70=1,MAX(0,I70)*Setup!$B$10,Forecast!I70)) | K70: =IF(A70="","",IF($B70=1,I70-J70,Forecast!J70)) | L70: =IF(A70="","",IF($B70=1,K70+G70+Forecast!K70,Forecast!L70)) | M70: =IF(A70="","",IF($B70=1,Forecast!M70-Setup!$B$8,Forecast!M70)) | N70: =IF(A70="","",IF($B70=1,L70-M70,Forecast!O70)) | O70: =IF(A70="","",IF($B70=1,N70-Forecast!N70,Forecast!P70)) | P70: =IF(A70="","",(Forecast!$Q$5-Forecast!$P$5)+SUM($O$5:O70))
A71: =IF(Forecast!A71="","",Forecast!A71) | B71: =IF(A71="","",IF(66>=N(Setup!$C$18),1,0)) | C71: =IF(A71="","",IF($B71=1,Forecast!B71-Setup!$B$4,Forecast!B71)) | D71: =IF(A71="","",IF($B71=1,Forecast!C71-Setup!$B$5,Forecast!C71)) | E71: =IF(A71="","",IF($B71=1,Forecast!D71-Setup!$B$6,Forecast!D71)) | F71: =IF(A71="","",IF($B71=1,D71-E71,Forecast!E71)) | G71: =IF(A71="","",IF($B71=1,Forecast!F71-Setup!$B$7,Forecast!F71)) | H71: =IF(A71="","",IF($B71=1,Forecast!G71-N(Setup!$D$18)*Setup!$B$9/12,Forecast!G71)) | I71: =IF(A71="","",IF($B71=1,F71-G71-H71,Forecast!H71)) | J71: =IF(A71="","",IF($B71=1,MAX(0,I71)*Setup!$B$10,Forecast!I71)) | K71: =IF(A71="","",IF($B71=1,I71-J71,Forecast!J71)) | L71: =IF(A71="","",IF($B71=1,K71+G71+Forecast!K71,Forecast!L71)) | M71: =IF(A71="","",IF($B71=1,Forecast!M71-Setup!$B$8,Forecast!M71)) | N71: =IF(A71="","",IF($B71=1,L71-M71,Forecast!O71)) | O71: =IF(A71="","",IF($B71=1,N71-Forecast!N71,Forecast!P71)) | P71: =IF(A71="","",(Forecast!$Q$5-Forecast!$P$5)+SUM($O$5:O71))
A72: =IF(Forecast!A72="","",Forecast!A72) | B72: =IF(A72="","",IF(67>=N(Setup!$C$18),1,0)) | C72: =IF(A72="","",IF($B72=1,Forecast!B72-Setup!$B$4,Forecast!B72)) | D72: =IF(A72="","",IF($B72=1,Forecast!C72-Setup!$B$5,Forecast!C72)) | E72: =IF(A72="","",IF($B72=1,Forecast!D72-Setup!$B$6,Forecast!D72)) | F72: =IF(A72="","",IF($B72=1,D72-E72,Forecast!E72)) | G72: =IF(A72="","",IF($B72=1,Forecast!F72-Setup!$B$7,Forecast!F72)) | H72: =IF(A72="","",IF($B72=1,Forecast!G72-N(Setup!$D$18)*Setup!$B$9/12,Forecast!G72)) | I72: =IF(A72="","",IF($B72=1,F72-G72-H72,Forecast!H72)) | J72: =IF(A72="","",IF($B72=1,MAX(0,I72)*Setup!$B$10,Forecast!I72)) | K72: =IF(A72="","",IF($B72=1,I72-J72,Forecast!J72)) | L72: =IF(A72="","",IF($B72=1,K72+G72+Forecast!K72,Forecast!L72)) | M72: =IF(A72="","",IF($B72=1,Forecast!M72-Setup!$B$8,Forecast!M72)) | N72: =IF(A72="","",IF($B72=1,L72-M72,Forecast!O72)) | O72: =IF(A72="","",IF($B72=1,N72-Forecast!N72,Forecast!P72)) | P72: =IF(A72="","",(Forecast!$Q$5-Forecast!$P$5)+SUM($O$5:O72))
A73: =IF(Forecast!A73="","",Forecast!A73) | B73: =IF(A73="","",IF(68>=N(Setup!$C$18),1,0)) | C73: =IF(A73="","",IF($B73=1,Forecast!B73-Setup!$B$4,Forecast!B73)) | D73: =IF(A73="","",IF($B73=1,Forecast!C73-Setup!$B$5,Forecast!C73)) | E73: =IF(A73="","",IF($B73=1,Forecast!D73-Setup!$B$6,Forecast!D73)) | F73: =IF(A73="","",IF($B73=1,D73-E73,Forecast!E73)) | G73: =IF(A73="","",IF($B73=1,Forecast!F73-Setup!$B$7,Forecast!F73)) | H73: =IF(A73="","",IF($B73=1,Forecast!G73-N(Setup!$D$18)*Setup!$B$9/12,Forecast!G73)) | I73: =IF(A73="","",IF($B73=1,F73-G73-H73,Forecast!H73)) | J73: =IF(A73="","",IF($B73=1,MAX(0,I73)*Setup!$B$10,Forecast!I73)) | K73: =IF(A73="","",IF($B73=1,I73-J73,Forecast!J73)) | L73: =IF(A73="","",IF($B73=1,K73+G73+Forecast!K73,Forecast!L73)) | M73: =IF(A73="","",IF($B73=1,Forecast!M73-Setup!$B$8,Forecast!M73)) | N73: =IF(A73="","",IF($B73=1,L73-M73,Forecast!O73)) | O73: =IF(A73="","",IF($B73=1,N73-Forecast!N73,Forecast!P73)) | P73: =IF(A73="","",(Forecast!$Q$5-Forecast!$P$5)+SUM($O$5:O73))
A74: =IF(Forecast!A74="","",Forecast!A74) | B74: =IF(A74="","",IF(69>=N(Setup!$C$18),1,0)) | C74: =IF(A74="","",IF($B74=1,Forecast!B74-Setup!$B$4,Forecast!B74)) | D74: =IF(A74="","",IF($B74=1,Forecast!C74-Setup!$B$5,Forecast!C74)) | E74: =IF(A74="","",IF($B74=1,Forecast!D74-Setup!$B$6,Forecast!D74)) | F74: =IF(A74="","",IF($B74=1,D74-E74,Forecast!E74)) | G74: =IF(A74="","",IF($B74=1,Forecast!F74-Setup!$B$7,Forecast!F74)) | H74: =IF(A74="","",IF($B74=1,Forecast!G74-N(Setup!$D$18)*Setup!$B$9/12,Forecast!G74)) | I74: =IF(A74="","",IF($B74=1,F74-G74-H74,Forecast!H74)) | J74: =IF(A74="","",IF($B74=1,MAX(0,I74)*Setup!$B$10,Forecast!I74)) | K74: =IF(A74="","",IF($B74=1,I74-J74,Forecast!J74)) | L74: =IF(A74="","",IF($B74=1,K74+G74+Forecast!K74,Forecast!L74)) | M74: =IF(A74="","",IF($B74=1,Forecast!M74-Setup!$B$8,Forecast!M74)) | N74: =IF(A74="","",IF($B74=1,L74-M74,Forecast!O74)) | O74: =IF(A74="","",IF($B74=1,N74-Forecast!N74,Forecast!P74)) | P74: =IF(A74="","",(Forecast!$Q$5-Forecast!$P$5)+SUM($O$5:O74))
A75: =IF(Forecast!A75="","",Forecast!A75) | B75: =IF(A75="","",IF(70>=N(Setup!$C$18),1,0)) | C75: =IF(A75="","",IF($B75=1,Forecast!B75-Setup!$B$4,Forecast!B75)) | D75: =IF(A75="","",IF($B75=1,Forecast!C75-Setup!$B$5,Forecast!C75)) | E75: =IF(A75="","",IF($B75=1,Forecast!D75-Setup!$B$6,Forecast!D75)) | F75: =IF(A75="","",IF($B75=1,D75-E75,Forecast!E75)) | G75: =IF(A75="","",IF($B75=1,Forecast!F75-Setup!$B$7,Forecast!F75)) | H75: =IF(A75="","",IF($B75=1,Forecast!G75-N(Setup!$D$18)*Setup!$B$9/12,Forecast!G75)) | I75: =IF(A75="","",IF($B75=1,F75-G75-H75,Forecast!H75)) | J75: =IF(A75="","",IF($B75=1,MAX(0,I75)*Setup!$B$10,Forecast!I75)) | K75: =IF(A75="","",IF($B75=1,I75-J75,Forecast!J75)) | L75: =IF(A75="","",IF($B75=1,K75+G75+Forecast!K75,Forecast!L75)) | M75: =IF(A75="","",IF($B75=1,Forecast!M75-Setup!$B$8,Forecast!M75)) | N75: =IF(A75="","",IF($B75=1,L75-M75,Forecast!O75)) | O75: =IF(A75="","",IF($B75=1,N75-Forecast!N75,Forecast!P75)) | P75: =IF(A75="","",(Forecast!$Q$5-Forecast!$P$5)+SUM($O$5:O75))
A76: =IF(Forecast!A76="","",Forecast!A76) | B76: =IF(A76="","",IF(71>=N(Setup!$C$18),1,0)) | C76: =IF(A76="","",IF($B76=1,Forecast!B76-Setup!$B$4,Forecast!B76)) | D76: =IF(A76="","",IF($B76=1,Forecast!C76-Setup!$B$5,Forecast!C76)) | E76: =IF(A76="","",IF($B76=1,Forecast!D76-Setup!$B$6,Forecast!D76)) | F76: =IF(A76="","",IF($B76=1,D76-E76,Forecast!E76)) | G76: =IF(A76="","",IF($B76=1,Forecast!F76-Setup!$B$7,Forecast!F76)) | H76: =IF(A76="","",IF($B76=1,Forecast!G76-N(Setup!$D$18)*Setup!$B$9/12,Forecast!G76)) | I76: =IF(A76="","",IF($B76=1,F76-G76-H76,Forecast!H76)) | J76: =IF(A76="","",IF($B76=1,MAX(0,I76)*Setup!$B$10,Forecast!I76)) | K76: =IF(A76="","",IF($B76=1,I76-J76,Forecast!J76)) | L76: =IF(A76="","",IF($B76=1,K76+G76+Forecast!K76,Forecast!L76)) | M76: =IF(A76="","",IF($B76=1,Forecast!M76-Setup!$B$8,Forecast!M76)) | N76: =IF(A76="","",IF($B76=1,L76-M76,Forecast!O76)) | O76: =IF(A76="","",IF($B76=1,N76-Forecast!N76,Forecast!P76)) | P76: =IF(A76="","",(Forecast!$Q$5-Forecast!$P$5)+SUM($O$5:O76))
A77: =IF(Forecast!A77="","",Forecast!A77) | B77: =IF(A77="","",IF(72>=N(Setup!$C$18),1,0)) | C77: =IF(A77="","",IF($B77=1,Forecast!B77-Setup!$B$4,Forecast!B77)) | D77: =IF(A77="","",IF($B77=1,Forecast!C77-Setup!$B$5,Forecast!C77)) | E77: =IF(A77="","",IF($B77=1,Forecast!D77-Setup!$B$6,Forecast!D77)) | F77: =IF(A77="","",IF($B77=1,D77-E77,Forecast!E77)) | G77: =IF(A77="","",IF($B77=1,Forecast!F77-Setup!$B$7,Forecast!F77)) | H77: =IF(A77="","",IF($B77=1,Forecast!G77-N(Setup!$D$18)*Setup!$B$9/12,Forecast!G77)) | I77: =IF(A77="","",IF($B77=1,F77-G77-H77,Forecast!H77)) | J77: =IF(A77="","",IF($B77=1,MAX(0,I77)*Setup!$B$10,Forecast!I77)) | K77: =IF(A77="","",IF($B77=1,I77-J77,Forecast!J77)) | L77: =IF(A77="","",IF($B77=1,K77+G77+Forecast!K77,Forecast!L77)) | M77: =IF(A77="","",IF($B77=1,Forecast!M77-Setup!$B$8,Forecast!M77)) | N77: =IF(A77="","",IF($B77=1,L77-M77,Forecast!O77)) | O77: =IF(A77="","",IF($B77=1,N77-Forecast!N77,Forecast!P77)) | P77: =IF(A77="","",(Forecast!$Q$5-Forecast!$P$5)+SUM($O$5:O77))
A78: =IF(Forecast!A78="","",Forecast!A78) | B78: =IF(A78="","",IF(73>=N(Setup!$C$18),1,0)) | C78: =IF(A78="","",IF($B78=1,Forecast!B78-Setup!$B$4,Forecast!B78)) | D78: =IF(A78="","",IF($B78=1,Forecast!C78-Setup!$B$5,Forecast!C78)) | E78: =IF(A78="","",IF($B78=1,Forecast!D78-Setup!$B$6,Forecast!D78)) | F78: =IF(A78="","",IF($B78=1,D78-E78,Forecast!E78)) | G78: =IF(A78="","",IF($B78=1,Forecast!F78-Setup!$B$7,Forecast!F78)) | H78: =IF(A78="","",IF($B78=1,Forecast!G78-N(Setup!$D$18)*Setup!$B$9/12,Forecast!G78)) | I78: =IF(A78="","",IF($B78=1,F78-G78-H78,Forecast!H78)) | J78: =IF(A78="","",IF($B78=1,MAX(0,I78)*Setup!$B$10,Forecast!I78)) | K78: =IF(A78="","",IF($B78=1,I78-J78,Forecast!J78)) | L78: =IF(A78="","",IF($B78=1,K78+G78+Forecast!K78,Forecast!L78)) | M78: =IF(A78="","",IF($B78=1,Forecast!M78-Setup!$B$8,Forecast!M78)) | N78: =IF(A78="","",IF($B78=1,L78-M78,Forecast!O78)) | O78: =IF(A78="","",IF($B78=1,N78-Forecast!N78,Forecast!P78)) | P78: =IF(A78="","",(Forecast!$Q$5-Forecast!$P$5)+SUM($O$5:O78))
A79: =IF(Forecast!A79="","",Forecast!A79) | B79: =IF(A79="","",IF(74>=N(Setup!$C$18),1,0)) | C79: =IF(A79="","",IF($B79=1,Forecast!B79-Setup!$B$4,Forecast!B79)) | D79: =IF(A79="","",IF($B79=1,Forecast!C79-Setup!$B$5,Forecast!C79)) | E79: =IF(A79="","",IF($B79=1,Forecast!D79-Setup!$B$6,Forecast!D79)) | F79: =IF(A79="","",IF($B79=1,D79-E79,Forecast!E79)) | G79: =IF(A79="","",IF($B79=1,Forecast!F79-Setup!$B$7,Forecast!F79)) | H79: =IF(A79="","",IF($B79=1,Forecast!G79-N(Setup!$D$18)*Setup!$B$9/12,Forecast!G79)) | I79: =IF(A79="","",IF($B79=1,F79-G79-H79,Forecast!H79)) | J79: =IF(A79="","",IF($B79=1,MAX(0,I79)*Setup!$B$10,Forecast!I79)) | K79: =IF(A79="","",IF($B79=1,I79-J79,Forecast!J79)) | L79: =IF(A79="","",IF($B79=1,K79+G79+Forecast!K79,Forecast!L79)) | M79: =IF(A79="","",IF($B79=1,Forecast!M79-Setup!$B$8,Forecast!M79)) | N79: =IF(A79="","",IF($B79=1,L79-M79,Forecast!O79)) | O79: =IF(A79="","",IF($B79=1,N79-Forecast!N79,Forecast!P79)) | P79: =IF(A79="","",(Forecast!$Q$5-Forecast!$P$5)+SUM($O$5:O79))
A80: =IF(Forecast!A80="","",Forecast!A80) | B80: =IF(A80="","",IF(75>=N(Setup!$C$18),1,0)) | C80: =IF(A80="","",IF($B80=1,Forecast!B80-Setup!$B$4,Forecast!B80)) | D80: =IF(A80="","",IF($B80=1,Forecast!C80-Setup!$B$5,Forecast!C80)) | E80: =IF(A80="","",IF($B80=1,Forecast!D80-Setup!$B$6,Forecast!D80)) | F80: =IF(A80="","",IF($B80=1,D80-E80,Forecast!E80)) | G80: =IF(A80="","",IF($B80=1,Forecast!F80-Setup!$B$7,Forecast!F80)) | H80: =IF(A80="","",IF($B80=1,Forecast!G80-N(Setup!$D$18)*Setup!$B$9/12,Forecast!G80)) | I80: =IF(A80="","",IF($B80=1,F80-G80-H80,Forecast!H80)) | J80: =IF(A80="","",IF($B80=1,MAX(0,I80)*Setup!$B$10,Forecast!I80)) | K80: =IF(A80="","",IF($B80=1,I80-J80,Forecast!J80)) | L80: =IF(A80="","",IF($B80=1,K80+G80+Forecast!K80,Forecast!L80)) | M80: =IF(A80="","",IF($B80=1,Forecast!M80-Setup!$B$8,Forecast!M80)) | N80: =IF(A80="","",IF($B80=1,L80-M80,Forecast!O80)) | O80: =IF(A80="","",IF($B80=1,N80-Forecast!N80,Forecast!P80)) | P80: =IF(A80="","",(Forecast!$Q$5-Forecast!$P$5)+SUM($O$5:O80))
A81: =IF(Forecast!A81="","",Forecast!A81) | B81: =IF(A81="","",IF(76>=N(Setup!$C$18),1,0)) | C81: =IF(A81="","",IF($B81=1,Forecast!B81-Setup!$B$4,Forecast!B81)) | D81: =IF(A81="","",IF($B81=1,Forecast!C81-Setup!$B$5,Forecast!C81)) | E81: =IF(A81="","",IF($B81=1,Forecast!D81-Setup!$B$6,Forecast!D81)) | F81: =IF(A81="","",IF($B81=1,D81-E81,Forecast!E81)) | G81: =IF(A81="","",IF($B81=1,Forecast!F81-Setup!$B$7,Forecast!F81)) | H81: =IF(A81="","",IF($B81=1,Forecast!G81-N(Setup!$D$18)*Setup!$B$9/12,Forecast!G81)) | I81: =IF(A81="","",IF($B81=1,F81-G81-H81,Forecast!H81)) | J81: =IF(A81="","",IF($B81=1,MAX(0,I81)*Setup!$B$10,Forecast!I81)) | K81: =IF(A81="","",IF($B81=1,I81-J81,Forecast!J81)) | L81: =IF(A81="","",IF($B81=1,K81+G81+Forecast!K81,Forecast!L81)) | M81: =IF(A81="","",IF($B81=1,Forecast!M81-Setup!$B$8,Forecast!M81)) | N81: =IF(A81="","",IF($B81=1,L81-M81,Forecast!O81)) | O81: =IF(A81="","",IF($B81=1,N81-Forecast!N81,Forecast!P81)) | P81: =IF(A81="","",(Forecast!$Q$5-Forecast!$P$5)+SUM($O$5:O81))
A82: =IF(Forecast!A82="","",Forecast!A82) | B82: =IF(A82="","",IF(77>=N(Setup!$C$18),1,0)) | C82: =IF(A82="","",IF($B82=1,Forecast!B82-Setup!$B$4,Forecast!B82)) | D82: =IF(A82="","",IF($B82=1,Forecast!C82-Setup!$B$5,Forecast!C82)) | E82: =IF(A82="","",IF($B82=1,Forecast!D82-Setup!$B$6,Forecast!D82)) | F82: =IF(A82="","",IF($B82=1,D82-E82,Forecast!E82)) | G82: =IF(A82="","",IF($B82=1,Forecast!F82-Setup!$B$7,Forecast!F82)) | H82: =IF(A82="","",IF($B82=1,Forecast!G82-N(Setup!$D$18)*Setup!$B$9/12,Forecast!G82)) | I82: =IF(A82="","",IF($B82=1,F82-G82-H82,Forecast!H82)) | J82: =IF(A82="","",IF($B82=1,MAX(0,I82)*Setup!$B$10,Forecast!I82)) | K82: =IF(A82="","",IF($B82=1,I82-J82,Forecast!J82)) | L82: =IF(A82="","",IF($B82=1,K82+G82+Forecast!K82,Forecast!L82)) | M82: =IF(A82="","",IF($B82=1,Forecast!M82-Setup!$B$8,Forecast!M82)) | N82: =IF(A82="","",IF($B82=1,L82-M82,Forecast!O82)) | O82: =IF(A82="","",IF($B82=1,N82-Forecast!N82,Forecast!P82)) | P82: =IF(A82="","",(Forecast!$Q$5-Forecast!$P$5)+SUM($O$5:O82))
A83: =IF(Forecast!A83="","",Forecast!A83) | B83: =IF(A83="","",IF(78>=N(Setup!$C$18),1,0)) | C83: =IF(A83="","",IF($B83=1,Forecast!B83-Setup!$B$4,Forecast!B83)) | D83: =IF(A83="","",IF($B83=1,Forecast!C83-Setup!$B$5,Forecast!C83)) | E83: =IF(A83="","",IF($B83=1,Forecast!D83-Setup!$B$6,Forecast!D83)) | F83: =IF(A83="","",IF($B83=1,D83-E83,Forecast!E83)) | G83: =IF(A83="","",IF($B83=1,Forecast!F83-Setup!$B$7,Forecast!F83)) | H83: =IF(A83="","",IF($B83=1,Forecast!G83-N(Setup!$D$18)*Setup!$B$9/12,Forecast!G83)) | I83: =IF(A83="","",IF($B83=1,F83-G83-H83,Forecast!H83)) | J83: =IF(A83="","",IF($B83=1,MAX(0,I83)*Setup!$B$10,Forecast!I83)) | K83: =IF(A83="","",IF($B83=1,I83-J83,Forecast!J83)) | L83: =IF(A83="","",IF($B83=1,K83+G83+Forecast!K83,Forecast!L83)) | M83: =IF(A83="","",IF($B83=1,Forecast!M83-Setup!$B$8,Forecast!M83)) | N83: =IF(A83="","",IF($B83=1,L83-M83,Forecast!O83)) | O83: =IF(A83="","",IF($B83=1,N83-Forecast!N83,Forecast!P83)) | P83: =IF(A83="","",(Forecast!$Q$5-Forecast!$P$5)+SUM($O$5:O83))
A84: =IF(Forecast!A84="","",Forecast!A84) | B84: =IF(A84="","",IF(79>=N(Setup!$C$18),1,0)) | C84: =IF(A84="","",IF($B84=1,Forecast!B84-Setup!$B$4,Forecast!B84)) | D84: =IF(A84="","",IF($B84=1,Forecast!C84-Setup!$B$5,Forecast!C84)) | E84: =IF(A84="","",IF($B84=1,Forecast!D84-Setup!$B$6,Forecast!D84)) | F84: =IF(A84="","",IF($B84=1,D84-E84,Forecast!E84)) | G84: =IF(A84="","",IF($B84=1,Forecast!F84-Setup!$B$7,Forecast!F84)) | H84: =IF(A84="","",IF($B84=1,Forecast!G84-N(Setup!$D$18)*Setup!$B$9/12,Forecast!G84)) | I84: =IF(A84="","",IF($B84=1,F84-G84-H84,Forecast!H84)) | J84: =IF(A84="","",IF($B84=1,MAX(0,I84)*Setup!$B$10,Forecast!I84)) | K84: =IF(A84="","",IF($B84=1,I84-J84,Forecast!J84)) | L84: =IF(A84="","",IF($B84=1,K84+G84+Forecast!K84,Forecast!L84)) | M84: =IF(A84="","",IF($B84=1,Forecast!M84-Setup!$B$8,Forecast!M84)) | N84: =IF(A84="","",IF($B84=1,L84-M84,Forecast!O84)) | O84: =IF(A84="","",IF($B84=1,N84-Forecast!N84,Forecast!P84)) | P84: =IF(A84="","",(Forecast!$Q$5-Forecast!$P$5)+SUM($O$5:O84))
A85: =IF(Forecast!A85="","",Forecast!A85) | B85: =IF(A85="","",IF(80>=N(Setup!$C$18),1,0)) | C85: =IF(A85="","",IF($B85=1,Forecast!B85-Setup!$B$4,Forecast!B85)) | D85: =IF(A85="","",IF($B85=1,Forecast!C85-Setup!$B$5,Forecast!C85)) | E85: =IF(A85="","",IF($B85=1,Forecast!D85-Setup!$B$6,Forecast!D85)) | F85: =IF(A85="","",IF($B85=1,D85-E85,Forecast!E85)) | G85: =IF(A85="","",IF($B85=1,Forecast!F85-Setup!$B$7,Forecast!F85)) | H85: =IF(A85="","",IF($B85=1,Forecast!G85-N(Setup!$D$18)*Setup!$B$9/12,Forecast!G85)) | I85: =IF(A85="","",IF($B85=1,F85-G85-H85,Forecast!H85)) | J85: =IF(A85="","",IF($B85=1,MAX(0,I85)*Setup!$B$10,Forecast!I85)) | K85: =IF(A85="","",IF($B85=1,I85-J85,Forecast!J85)) | L85: =IF(A85="","",IF($B85=1,K85+G85+Forecast!K85,Forecast!L85)) | M85: =IF(A85="","",IF($B85=1,Forecast!M85-Setup!$B$8,Forecast!M85)) | N85: =IF(A85="","",IF($B85=1,L85-M85,Forecast!O85)) | O85: =IF(A85="","",IF($B85=1,N85-Forecast!N85,Forecast!P85)) | P85: =IF(A85="","",(Forecast!$Q$5-Forecast!$P$5)+SUM($O$5:O85))
A86: =IF(Forecast!A86="","",Forecast!A86) | B86: =IF(A86="","",IF(81>=N(Setup!$C$18),1,0)) | C86: =IF(A86="","",IF($B86=1,Forecast!B86-Setup!$B$4,Forecast!B86)) | D86: =IF(A86="","",IF($B86=1,Forecast!C86-Setup!$B$5,Forecast!C86)) | E86: =IF(A86="","",IF($B86=1,Forecast!D86-Setup!$B$6,Forecast!D86)) | F86: =IF(A86="","",IF($B86=1,D86-E86,Forecast!E86)) | G86: =IF(A86="","",IF($B86=1,Forecast!F86-Setup!$B$7,Forecast!F86)) | H86: =IF(A86="","",IF($B86=1,Forecast!G86-N(Setup!$D$18)*Setup!$B$9/12,Forecast!G86)) | I86: =IF(A86="","",IF($B86=1,F86-G86-H86,Forecast!H86)) | J86: =IF(A86="","",IF($B86=1,MAX(0,I86)*Setup!$B$10,Forecast!I86)) | K86: =IF(A86="","",IF($B86=1,I86-J86,Forecast!J86)) | L86: =IF(A86="","",IF($B86=1,K86+G86+Forecast!K86,Forecast!L86)) | M86: =IF(A86="","",IF($B86=1,Forecast!M86-Setup!$B$8,Forecast!M86)) | N86: =IF(A86="","",IF($B86=1,L86-M86,Forecast!O86)) | O86: =IF(A86="","",IF($B86=1,N86-Forecast!N86,Forecast!P86)) | P86: =IF(A86="","",(Forecast!$Q$5-Forecast!$P$5)+SUM($O$5:O86))
A87: =IF(Forecast!A87="","",Forecast!A87) | B87: =IF(A87="","",IF(82>=N(Setup!$C$18),1,0)) | C87: =IF(A87="","",IF($B87=1,Forecast!B87-Setup!$B$4,Forecast!B87)) | D87: =IF(A87="","",IF($B87=1,Forecast!C87-Setup!$B$5,Forecast!C87)) | E87: =IF(A87="","",IF($B87=1,Forecast!D87-Setup!$B$6,Forecast!D87)) | F87: =IF(A87="","",IF($B87=1,D87-E87,Forecast!E87)) | G87: =IF(A87="","",IF($B87=1,Forecast!F87-Setup!$B$7,Forecast!F87)) | H87: =IF(A87="","",IF($B87=1,Forecast!G87-N(Setup!$D$18)*Setup!$B$9/12,Forecast!G87)) | I87: =IF(A87="","",IF($B87=1,F87-G87-H87,Forecast!H87)) | J87: =IF(A87="","",IF($B87=1,MAX(0,I87)*Setup!$B$10,Forecast!I87)) | K87: =IF(A87="","",IF($B87=1,I87-J87,Forecast!J87)) | L87: =IF(A87="","",IF($B87=1,K87+G87+Forecast!K87,Forecast!L87)) | M87: =IF(A87="","",IF($B87=1,Forecast!M87-Setup!$B$8,Forecast!M87)) | N87: =IF(A87="","",IF($B87=1,L87-M87,Forecast!O87)) | O87: =IF(A87="","",IF($B87=1,N87-Forecast!N87,Forecast!P87)) | P87: =IF(A87="","",(Forecast!$Q$5-Forecast!$P$5)+SUM($O$5:O87))
A88: =IF(Forecast!A88="","",Forecast!A88) | B88: =IF(A88="","",IF(83>=N(Setup!$C$18),1,0)) | C88: =IF(A88="","",IF($B88=1,Forecast!B88-Setup!$B$4,Forecast!B88)) | D88: =IF(A88="","",IF($B88=1,Forecast!C88-Setup!$B$5,Forecast!C88)) | E88: =IF(A88="","",IF($B88=1,Forecast!D88-Setup!$B$6,Forecast!D88)) | F88: =IF(A88="","",IF($B88=1,D88-E88,Forecast!E88)) | G88: =IF(A88="","",IF($B88=1,Forecast!F88-Setup!$B$7,Forecast!F88)) | H88: =IF(A88="","",IF($B88=1,Forecast!G88-N(Setup!$D$18)*Setup!$B$9/12,Forecast!G88)) | I88: =IF(A88="","",IF($B88=1,F88-G88-H88,Forecast!H88)) | J88: =IF(A88="","",IF($B88=1,MAX(0,I88)*Setup!$B$10,Forecast!I88)) | K88: =IF(A88="","",IF($B88=1,I88-J88,Forecast!J88)) | L88: =IF(A88="","",IF($B88=1,K88+G88+Forecast!K88,Forecast!L88)) | M88: =IF(A88="","",IF($B88=1,Forecast!M88-Setup!$B$8,Forecast!M88)) | N88: =IF(A88="","",IF($B88=1,L88-M88,Forecast!O88)) | O88: =IF(A88="","",IF($B88=1,N88-Forecast!N88,Forecast!P88)) | P88: =IF(A88="","",(Forecast!$Q$5-Forecast!$P$5)+SUM($O$5:O88))
A89: =IF(Forecast!A89="","",Forecast!A89) | B89: =IF(A89="","",IF(84>=N(Setup!$C$18),1,0)) | C89: =IF(A89="","",IF($B89=1,Forecast!B89-Setup!$B$4,Forecast!B89)) | D89: =IF(A89="","",IF($B89=1,Forecast!C89-Setup!$B$5,Forecast!C89)) | E89: =IF(A89="","",IF($B89=1,Forecast!D89-Setup!$B$6,Forecast!D89)) | F89: =IF(A89="","",IF($B89=1,D89-E89,Forecast!E89)) | G89: =IF(A89="","",IF($B89=1,Forecast!F89-Setup!$B$7,Forecast!F89)) | H89: =IF(A89="","",IF($B89=1,Forecast!G89-N(Setup!$D$18)*Setup!$B$9/12,Forecast!G89)) | I89: =IF(A89="","",IF($B89=1,F89-G89-H89,Forecast!H89)) | J89: =IF(A89="","",IF($B89=1,MAX(0,I89)*Setup!$B$10,Forecast!I89)) | K89: =IF(A89="","",IF($B89=1,I89-J89,Forecast!J89)) | L89: =IF(A89="","",IF($B89=1,K89+G89+Forecast!K89,Forecast!L89)) | M89: =IF(A89="","",IF($B89=1,Forecast!M89-Setup!$B$8,Forecast!M89)) | N89: =IF(A89="","",IF($B89=1,L89-M89,Forecast!O89)) | O89: =IF(A89="","",IF($B89=1,N89-Forecast!N89,Forecast!P89)) | P89: =IF(A89="","",(Forecast!$Q$5-Forecast!$P$5)+SUM($O$5:O89))
A90: =IF(Forecast!A90="","",Forecast!A90) | B90: =IF(A90="","",IF(85>=N(Setup!$C$18),1,0)) | C90: =IF(A90="","",IF($B90=1,Forecast!B90-Setup!$B$4,Forecast!B90)) | D90: =IF(A90="","",IF($B90=1,Forecast!C90-Setup!$B$5,Forecast!C90)) | E90: =IF(A90="","",IF($B90=1,Forecast!D90-Setup!$B$6,Forecast!D90)) | F90: =IF(A90="","",IF($B90=1,D90-E90,Forecast!E90)) | G90: =IF(A90="","",IF($B90=1,Forecast!F90-Setup!$B$7,Forecast!F90)) | H90: =IF(A90="","",IF($B90=1,Forecast!G90-N(Setup!$D$18)*Setup!$B$9/12,Forecast!G90)) | I90: =IF(A90="","",IF($B90=1,F90-G90-H90,Forecast!H90)) | J90: =IF(A90="","",IF($B90=1,MAX(0,I90)*Setup!$B$10,Forecast!I90)) | K90: =IF(A90="","",IF($B90=1,I90-J90,Forecast!J90)) | L90: =IF(A90="","",IF($B90=1,K90+G90+Forecast!K90,Forecast!L90)) | M90: =IF(A90="","",IF($B90=1,Forecast!M90-Setup!$B$8,Forecast!M90)) | N90: =IF(A90="","",IF($B90=1,L90-M90,Forecast!O90)) | O90: =IF(A90="","",IF($B90=1,N90-Forecast!N90,Forecast!P90)) | P90: =IF(A90="","",(Forecast!$Q$5-Forecast!$P$5)+SUM($O$5:O90))
A91: =IF(Forecast!A91="","",Forecast!A91) | B91: =IF(A91="","",IF(86>=N(Setup!$C$18),1,0)) | C91: =IF(A91="","",IF($B91=1,Forecast!B91-Setup!$B$4,Forecast!B91)) | D91: =IF(A91="","",IF($B91=1,Forecast!C91-Setup!$B$5,Forecast!C91)) | E91: =IF(A91="","",IF($B91=1,Forecast!D91-Setup!$B$6,Forecast!D91)) | F91: =IF(A91="","",IF($B91=1,D91-E91,Forecast!E91)) | G91: =IF(A91="","",IF($B91=1,Forecast!F91-Setup!$B$7,Forecast!F91)) | H91: =IF(A91="","",IF($B91=1,Forecast!G91-N(Setup!$D$18)*Setup!$B$9/12,Forecast!G91)) | I91: =IF(A91="","",IF($B91=1,F91-G91-H91,Forecast!H91)) | J91: =IF(A91="","",IF($B91=1,MAX(0,I91)*Setup!$B$10,Forecast!I91)) | K91: =IF(A91="","",IF($B91=1,I91-J91,Forecast!J91)) | L91: =IF(A91="","",IF($B91=1,K91+G91+Forecast!K91,Forecast!L91)) | M91: =IF(A91="","",IF($B91=1,Forecast!M91-Setup!$B$8,Forecast!M91)) | N91: =IF(A91="","",IF($B91=1,L91-M91,Forecast!O91)) | O91: =IF(A91="","",IF($B91=1,N91-Forecast!N91,Forecast!P91)) | P91: =IF(A91="","",(Forecast!$Q$5-Forecast!$P$5)+SUM($O$5:O91))
A92: =IF(Forecast!A92="","",Forecast!A92) | B92: =IF(A92="","",IF(87>=N(Setup!$C$18),1,0)) | C92: =IF(A92="","",IF($B92=1,Forecast!B92-Setup!$B$4,Forecast!B92)) | D92: =IF(A92="","",IF($B92=1,Forecast!C92-Setup!$B$5,Forecast!C92)) | E92: =IF(A92="","",IF($B92=1,Forecast!D92-Setup!$B$6,Forecast!D92)) | F92: =IF(A92="","",IF($B92=1,D92-E92,Forecast!E92)) | G92: =IF(A92="","",IF($B92=1,Forecast!F92-Setup!$B$7,Forecast!F92)) | H92: =IF(A92="","",IF($B92=1,Forecast!G92-N(Setup!$D$18)*Setup!$B$9/12,Forecast!G92)) | I92: =IF(A92="","",IF($B92=1,F92-G92-H92,Forecast!H92)) | J92: =IF(A92="","",IF($B92=1,MAX(0,I92)*Setup!$B$10,Forecast!I92)) | K92: =IF(A92="","",IF($B92=1,I92-J92,Forecast!J92)) | L92: =IF(A92="","",IF($B92=1,K92+G92+Forecast!K92,Forecast!L92)) | M92: =IF(A92="","",IF($B92=1,Forecast!M92-Setup!$B$8,Forecast!M92)) | N92: =IF(A92="","",IF($B92=1,L92-M92,Forecast!O92)) | O92: =IF(A92="","",IF($B92=1,N92-Forecast!N92,Forecast!P92)) | P92: =IF(A92="","",(Forecast!$Q$5-Forecast!$P$5)+SUM($O$5:O92))
A93: =IF(Forecast!A93="","",Forecast!A93) | B93: =IF(A93="","",IF(88>=N(Setup!$C$18),1,0)) | C93: =IF(A93="","",IF($B93=1,Forecast!B93-Setup!$B$4,Forecast!B93)) | D93: =IF(A93="","",IF($B93=1,Forecast!C93-Setup!$B$5,Forecast!C93)) | E93: =IF(A93="","",IF($B93=1,Forecast!D93-Setup!$B$6,Forecast!D93)) | F93: =IF(A93="","",IF($B93=1,D93-E93,Forecast!E93)) | G93: =IF(A93="","",IF($B93=1,Forecast!F93-Setup!$B$7,Forecast!F93)) | H93: =IF(A93="","",IF($B93=1,Forecast!G93-N(Setup!$D$18)*Setup!$B$9/12,Forecast!G93)) | I93: =IF(A93="","",IF($B93=1,F93-G93-H93,Forecast!H93)) | J93: =IF(A93="","",IF($B93=1,MAX(0,I93)*Setup!$B$10,Forecast!I93)) | K93: =IF(A93="","",IF($B93=1,I93-J93,Forecast!J93)) | L93: =IF(A93="","",IF($B93=1,K93+G93+Forecast!K93,Forecast!L93)) | M93: =IF(A93="","",IF($B93=1,Forecast!M93-Setup!$B$8,Forecast!M93)) | N93: =IF(A93="","",IF($B93=1,L93-M93,Forecast!O93)) | O93: =IF(A93="","",IF($B93=1,N93-Forecast!N93,Forecast!P93)) | P93: =IF(A93="","",(Forecast!$Q$5-Forecast!$P$5)+SUM($O$5:O93))
A94: =IF(Forecast!A94="","",Forecast!A94) | B94: =IF(A94="","",IF(89>=N(Setup!$C$18),1,0)) | C94: =IF(A94="","",IF($B94=1,Forecast!B94-Setup!$B$4,Forecast!B94)) | D94: =IF(A94="","",IF($B94=1,Forecast!C94-Setup!$B$5,Forecast!C94)) | E94: =IF(A94="","",IF($B94=1,Forecast!D94-Setup!$B$6,Forecast!D94)) | F94: =IF(A94="","",IF($B94=1,D94-E94,Forecast!E94)) | G94: =IF(A94="","",IF($B94=1,Forecast!F94-Setup!$B$7,Forecast!F94)) | H94: =IF(A94="","",IF($B94=1,Forecast!G94-N(Setup!$D$18)*Setup!$B$9/12,Forecast!G94)) | I94: =IF(A94="","",IF($B94=1,F94-G94-H94,Forecast!H94)) | J94: =IF(A94="","",IF($B94=1,MAX(0,I94)*Setup!$B$10,Forecast!I94)) | K94: =IF(A94="","",IF($B94=1,I94-J94,Forecast!J94)) | L94: =IF(A94="","",IF($B94=1,K94+G94+Forecast!K94,Forecast!L94)) | M94: =IF(A94="","",IF($B94=1,Forecast!M94-Setup!$B$8,Forecast!M94)) | N94: =IF(A94="","",IF($B94=1,L94-M94,Forecast!O94)) | O94: =IF(A94="","",IF($B94=1,N94-Forecast!N94,Forecast!P94)) | P94: =IF(A94="","",(Forecast!$Q$5-Forecast!$P$5)+SUM($O$5:O94))
A95: =IF(Forecast!A95="","",Forecast!A95) | B95: =IF(A95="","",IF(90>=N(Setup!$C$18),1,0)) | C95: =IF(A95="","",IF($B95=1,Forecast!B95-Setup!$B$4,Forecast!B95)) | D95: =IF(A95="","",IF($B95=1,Forecast!C95-Setup!$B$5,Forecast!C95)) | E95: =IF(A95="","",IF($B95=1,Forecast!D95-Setup!$B$6,Forecast!D95)) | F95: =IF(A95="","",IF($B95=1,D95-E95,Forecast!E95)) | G95: =IF(A95="","",IF($B95=1,Forecast!F95-Setup!$B$7,Forecast!F95)) | H95: =IF(A95="","",IF($B95=1,Forecast!G95-N(Setup!$D$18)*Setup!$B$9/12,Forecast!G95)) | I95: =IF(A95="","",IF($B95=1,F95-G95-H95,Forecast!H95)) | J95: =IF(A95="","",IF($B95=1,MAX(0,I95)*Setup!$B$10,Forecast!I95)) | K95: =IF(A95="","",IF($B95=1,I95-J95,Forecast!J95)) | L95: =IF(A95="","",IF($B95=1,K95+G95+Forecast!K95,Forecast!L95)) | M95: =IF(A95="","",IF($B95=1,Forecast!M95-Setup!$B$8,Forecast!M95)) | N95: =IF(A95="","",IF($B95=1,L95-M95,Forecast!O95)) | O95: =IF(A95="","",IF($B95=1,N95-Forecast!N95,Forecast!P95)) | P95: =IF(A95="","",(Forecast!$Q$5-Forecast!$P$5)+SUM($O$5:O95))
A96: =IF(Forecast!A96="","",Forecast!A96) | B96: =IF(A96="","",IF(91>=N(Setup!$C$18),1,0)) | C96: =IF(A96="","",IF($B96=1,Forecast!B96-Setup!$B$4,Forecast!B96)) | D96: =IF(A96="","",IF($B96=1,Forecast!C96-Setup!$B$5,Forecast!C96)) | E96: =IF(A96="","",IF($B96=1,Forecast!D96-Setup!$B$6,Forecast!D96)) | F96: =IF(A96="","",IF($B96=1,D96-E96,Forecast!E96)) | G96: =IF(A96="","",IF($B96=1,Forecast!F96-Setup!$B$7,Forecast!F96)) | H96: =IF(A96="","",IF($B96=1,Forecast!G96-N(Setup!$D$18)*Setup!$B$9/12,Forecast!G96)) | I96: =IF(A96="","",IF($B96=1,F96-G96-H96,Forecast!H96)) | J96: =IF(A96="","",IF($B96=1,MAX(0,I96)*Setup!$B$10,Forecast!I96)) | K96: =IF(A96="","",IF($B96=1,I96-J96,Forecast!J96)) | L96: =IF(A96="","",IF($B96=1,K96+G96+Forecast!K96,Forecast!L96)) | M96: =IF(A96="","",IF($B96=1,Forecast!M96-Setup!$B$8,Forecast!M96)) | N96: =IF(A96="","",IF($B96=1,L96-M96,Forecast!O96)) | O96: =IF(A96="","",IF($B96=1,N96-Forecast!N96,Forecast!P96)) | P96: =IF(A96="","",(Forecast!$Q$5-Forecast!$P$5)+SUM($O$5:O96))
A97: =IF(Forecast!A97="","",Forecast!A97) | B97: =IF(A97="","",IF(92>=N(Setup!$C$18),1,0)) | C97: =IF(A97="","",IF($B97=1,Forecast!B97-Setup!$B$4,Forecast!B97)) | D97: =IF(A97="","",IF($B97=1,Forecast!C97-Setup!$B$5,Forecast!C97)) | E97: =IF(A97="","",IF($B97=1,Forecast!D97-Setup!$B$6,Forecast!D97)) | F97: =IF(A97="","",IF($B97=1,D97-E97,Forecast!E97)) | G97: =IF(A97="","",IF($B97=1,Forecast!F97-Setup!$B$7,Forecast!F97)) | H97: =IF(A97="","",IF($B97=1,Forecast!G97-N(Setup!$D$18)*Setup!$B$9/12,Forecast!G97)) | I97: =IF(A97="","",IF($B97=1,F97-G97-H97,Forecast!H97)) | J97: =IF(A97="","",IF($B97=1,MAX(0,I97)*Setup!$B$10,Forecast!I97)) | K97: =IF(A97="","",IF($B97=1,I97-J97,Forecast!J97)) | L97: =IF(A97="","",IF($B97=1,K97+G97+Forecast!K97,Forecast!L97)) | M97: =IF(A97="","",IF($B97=1,Forecast!M97-Setup!$B$8,Forecast!M97)) | N97: =IF(A97="","",IF($B97=1,L97-M97,Forecast!O97)) | O97: =IF(A97="","",IF($B97=1,N97-Forecast!N97,Forecast!P97)) | P97: =IF(A97="","",(Forecast!$Q$5-Forecast!$P$5)+SUM($O$5:O97))
