Workbook
Name ep_gain_col: 'Epochs'!$AW$5:$AW$44

Sheet README
A1: K05 · Research Loop Evaluator - champion vs challenger (no-code kernel)
A3: Replaces openfpa: pyfpa.research (ResearchObjective, evaluate_challenger, ResearchEpoch status rules, register_challenger, promote_challenger with recompute guard).
A4: Evaluation (identical maths)
A5: For each objective metric: if champion = 0 -> improvement 0 when challenger = 0, else -1 (lower-is-better) or +1 (higher-is-better).
A6: Otherwise improvement = (champion - challenger)/|champion| for lower-is-better, (challenger - champion)/|champion| for higher-is-better.
A7: Regression guard (on the RAW improvement): fails if any raw improvement < -max_metric_regression. Then clamp to [-1, +1].
A8: weighted_improvement = sum(weight/total_weight x clamped improvement); complexity_cost = complexity_penalty x max(0, challenger_complexity - champion_complexity); objective_gain = weighted - cost.
A9: hard_checks_passed = every objective hard check present with result 'pass' (a missing check is an ERROR). promotion_eligible = hard checks AND guard AND objective_gain >= min_improvement.
A10: Status rules
A11: generated needs no evaluation; evaluated/discarded/proposed/promoted need one; only promotion-eligible epochs may be proposed or promoted. Weak or failed challengers are marked discarded and KEPT.
A12: Promotion (human gate)
A13: Promotion requires: approved_by non-blank, epoch status proposed, eligible on RECOMPUTE from the stored metrics (guards against hand-edited files), epoch challenger = registry challenger, challenger source_epoch = epoch_id. Then the old champion moves to retired and a promotion row is appended.

Sheet Checks
A1: Checks - OVERALL must be PASS
B3: OVERALL | C3: =IF(COUNTIF(C5:C8,"PASS")=COUNT(A5:A8),"PASS","FAIL") | D3: =COUNTIF(C5:C8,"PASS")&" pass / "&COUNTIF(C5:C8,"FAIL")&" fail / "&(COUNT(A5:A8)-COUNTIF(C5:C8,"PASS")-COUNTIF(C5:C8,"FAIL"))&" error"
A4: # | B4: check | C4: result | D4: detail
A5: 1 | B5: objective has >= 1 metric and positive weights | C5: =IF(AND(COUNTA(Objective!A5:A12)>=1,COUNTIF(Objective!B5:B12,"<=0")=0),"PASS","FAIL")
A6: 2 | B6: metric names unique | C6: =IF(SUMPRODUCT((Objective!A5:A12<>"")/COUNTIF(Objective!A5:A12,Objective!A5:A12&""))=COUNTA(Objective!A5:A12),"PASS","FAIL")
A7: 3 | B7: min_improvement and complexity_penalty >= 0; max_metric_regression blank or > 0 | C7: =IF(AND(Objective!B22>=0,Objective!B23>=0,OR(Objective!B24="",Objective!B24>0)),"PASS","FAIL")
A8: 4 | B8: every epoch's requested status is consistent with its evaluation | C8: =IF(COUNTIF(Epochs!BA5:BA44,FALSE)=0,"PASS","FAIL")

Sheet Objective
A1: Objective (memory/research/objective.md)
A4: metric | B4: weight | C4: direction (lower/higher)
A5: revenue_error | B5: 0.3 | C5: lower
A6: gross_profit_error | B6: 0.2 | C6: lower
A7: adjusted_ebitda_error | B7: 0.3 | C7: lower
A8: working_capital_balance_error | B8: 0.2 | C8: lower
A14: hard check name
A15: holdout separation
A16: segment rollup
A17: working capital continuity
A22: min_improvement (>=0) | B22: 0.02
A23: complexity_penalty (>=0) | B23: 0.01
A24: max_metric_regression (>0, blank = off) | B24: 0.5
A25: total weight | B25: =SUM(B5:B12)

Sheet Epochs
A1: Epochs - one row per memory/research/epochs/<epoch_id>.md (champion vs challenger)
I3: =Objective!A5 | J3: =Objective!A6 | K3: =Objective!A7 | L3: =Objective!A8 | M3: =Objective!A9 | N3: =Objective!A10 | O3: =Objective!A11 | P3: =Objective!A12 | Q3: =Objective!A5 | R3: =Objective!A6 | S3: =Objective!A7 | T3: =Objective!A8 | U3: =Objective!A9 | V3: =Objective!A10 | W3: =Objective!A11 | X3: =Objective!A12 | Y3: =Objective!A15 | Z3: =Objective!A16 | AA3: =Objective!A17 | AB3: =Objective!A18 | AC3: =Objective!A19 | AD3: =Objective!A20
A4: epoch_id | B4: created | C4: requested status | D4: hypothesis | E4: champion_id | F4: challenger_id | G4: champion complexity | H4: challenger complexity | I4: champion m1 | J4: champion m2 | K4: champion m3 | L4: champion m4 | M4: champion m5 | N4: champion m6 | O4: champion m7 | P4: champion m8 | Q4: challenger m1 | R4: challenger m2 | S4: challenger m3 | T4: challenger m4 | U4: challenger m5 | V4: challenger m6 | W4: challenger m7 | X4: challenger m8 | Y4: check 1 result | Z4: check 2 result | AA4: check 3 result | AB4: check 4 result | AC4: check 5 result | AD4: check 6 result | AE4: raw impr m1 | AF4: raw impr m2 | AG4: raw impr m3 | AH4: raw impr m4 | AI4: raw impr m5 | AJ4: raw impr m6 | AK4: raw impr m7 | AL4: raw impr m8 | AM4: clamped m1 | AN4: clamped m2 | AO4: clamped m3 | AP4: clamped m4 | AQ4: clamped m5 | AR4: clamped m6 | AS4: clamped m7 | AT4: clamped m8 | AU4: weighted_improvement | AV4: complexity_cost | AW4: objective_gain | AX4: hard_checks_passed | AY4: regression_guard_passed | AZ4: promotion_eligible | BA4: status valid? | BB4: suggested status
A5: foxf-fy2025-001-broad-mean-reversion | B5: 2026-06-09 | C5: discarded | D5: After the FY2024 trough, both segment revenue and margins recover halfway toward FY2023. | E5: foxf-flat-fy2024-run-rate | F5: foxf-broad-half-mean-reversion | G5: 1 | H5: 1.1 | I5: 0.050023137 | J5: 0.044379319 | K5: 0.010274974 | L5: 0.07038772 | Q5: 0.026082568 | R5: 0.001598294 | S5: 0.20394356 | T5: 0.063491568 | Y5: pass | Z5: pass | AA5: pass | AE5: =IF(OR($A5="",Objective!$A$5=""),"",IF(I5=0,IF(Q5=0,0,IF(Objective!$C$5="lower",-1,1)),IF(Objective!$C$5="lower",(I5-Q5)/ABS(I5),(Q5-I5)/ABS(I5)))) | AF5: =IF(OR($A5="",Objective!$A$6=""),"",IF(J5=0,IF(R5=0,0,IF(Objective!$C$6="lower",-1,1)),IF(Objective!$C$6="lower",(J5-R5)/ABS(J5),(R5-J5)/ABS(J5)))) | AG5: =IF(OR($A5="",Objective!$A$7=""),"",IF(K5=0,IF(S5=0,0,IF(Objective!$C$7="lower",-1,1)),IF(Objective!$C$7="lower",(K5-S5)/ABS(K5),(S5-K5)/ABS(K5)))) | AH5: =IF(OR($A5="",Objective!$A$8=""),"",IF(L5=0,IF(T5=0,0,IF(Objective!$C$8="lower",-1,1)),IF(Objective!$C$8="lower",(L5-T5)/ABS(L5),(T5-L5)/ABS(L5)))) | AI5: =IF(OR($A5="",Objective!$A$9=""),"",IF(M5=0,IF(U5=0,0,IF(Objective!$C$9="lower",-1,1)),IF(Objective!$C$9="lower",(M5-U5)/ABS(M5),(U5-M5)/ABS(M5)))) | AJ5: =IF(OR($A5="",Objective!$A$10=""),"",IF(N5=0,IF(V5=0,0,IF(Objective!$C$10="lower",-1,1)),IF(Objective!$C$10="lower",(N5-V5)/ABS(N5),(V5-N5)/ABS(N5)))) | AK5: =IF(OR($A5="",Objective!$A$11=""),"",IF(O5=0,IF(W5=0,0,IF(Objective!$C$11="lower",-1,1)),IF(Objective!$C$11="lower",(O5-W5)/ABS(O5),(W5-O5)/ABS(O5)))) | AL5: =IF(OR($A5="",Objective!$A$12=""),"",IF(P5=0,IF(X5=0,0,IF(Objective!$C$12="lower",-1,1)),IF(Objective!$C$12="lower",(P5-X5)/ABS(P5),(X5-P5)/ABS(P5)))) | AM5: =IF(AE5="","",MAX(-1,MIN(1,AE5))) | AN5: =IF(AF5="","",MAX(-1,MIN(1,AF5))) | AO5: =IF(AG5="","",MAX(-1,MIN(1,AG5))) | AP5: =IF(AH5="","",MAX(-1,MIN(1,AH5))) | AQ5: =IF(AI5="","",MAX(-1,MIN(1,AI5))) | AR5: =IF(AJ5="","",MAX(-1,MIN(1,AJ5))) | AS5: =IF(AK5="","",MAX(-1,MIN(1,AK5))) | AT5: =IF(AL5="","",MAX(-1,MIN(1,AL5))) | AU5: =IF($A5="","",IF(AM5="",0,Objective!$B$5/Objective!$B$25*AM5)+IF(AN5="",0,Objective!$B$6/Objective!$B$25*AN5)+IF(AO5="",0,Objective!$B$7/Objective!$B$25*AO5)+IF(AP5="",0,Objective!$B$8/Objective!$B$25*AP5)+IF(AQ5="",0,Objective!$B$9/Objective!$B$25*AQ5)+IF(AR5="",0,Objective!$B$10/Objective!$B$25*AR5)+IF(AS5="",0,Objective!$B$11/Objective!$B$25*AS5)+IF(AT5="",0,Objective!$B$12/Objective!$B$25*AT5)) | AV5: =IF($A5="","",Objective!$B$23*MAX(0,N($H5)-N($G5))) | AW5: =IF($A5="","",AU5-AV5) | AX5: =IF($A5="","",AND(OR(Objective!$A$15="",LOWER(Y5)="pass"),OR(Objective!$A$16="",LOWER(Z5)="pass"),OR(Objective!$A$17="",LOWER(AA5)="pass"),OR(Objective!$A$18="",LOWER(AB5)="pass"),OR(Objective!$A$19="",LOWER(AC5)="pass"),OR(Objective!$A$20="",LOWER(AD5)="pass"))) | AY5: =IF($A5="","",AND(OR(AE5="",Objective!$B$24="",AE5>=-Objective!$B$24),OR(AF5="",Objective!$B$24="",AF5>=-Objective!$B$24),OR(AG5="",Objective!$B$24="",AG5>=-Objective!$B$24),OR(AH5="",Objective!$B$24="",AH5>=-Objective!$B$24),OR(AI5="",Objective!$B$24="",AI5>=-Objective!$B$24),OR(AJ5="",Objective!$B$24="",AJ5>=-Objective!$B$24),OR(AK5="",Objective!$B$24="",AK5>=-Objective!$B$24),OR(AL5="",Objective!$B$24="",AL5>=-Objective!$B$24))) | AZ5: =IF($A5="","",AND(AX5,AY5,AW5>=Objective!$B$22)) | BA5: =IF($A5="","",IF(OR(LOWER($C5)="generated",LOWER($C5)="evaluated",LOWER($C5)="discarded"),TRUE,IF(OR(LOWER($C5)="proposed",LOWER($C5)="promoted"),AZ5,FALSE))) | BB5: =IF($A5="","",IF(AZ5,"proposed (eligible - present to human)","discarded (keep the record and the reason)"))
A6: foxf-fy2025-002-slow-margin-recovery | B6: 2026-06-09 | C6: proposed | D6: After the FY2024 trough, segment revenue partially mean-reverts toward FY2023 while margins recover much more slowly. | E6: foxf-flat-fy2024-run-rate | F6: foxf-revenue-recovery-slow-margin | G6: 1 | H6: 1.1 | I6: 0.050023137 | J6: 0.044379319 | K6: 0.010274974 | L6: 0.07038772 | Q6: 0.026082568 | R6: 0.001598294 | S6: 0.0013964803 | T6: 0.063491568 | Y6: pass | Z6: pass | AA6: pass | AE6: =IF(OR($A6="",Objective!$A$5=""),"",IF(I6=0,IF(Q6=0,0,IF(Objective!$C$5="lower",-1,1)),IF(Objective!$C$5="lower",(I6-Q6)/ABS(I6),(Q6-I6)/ABS(I6)))) | AF6: =IF(OR($A6="",Objective!$A$6=""),"",IF(J6=0,IF(R6=0,0,IF(Objective!$C$6="lower",-1,1)),IF(Objective!$C$6="lower",(J6-R6)/ABS(J6),(R6-J6)/ABS(J6)))) | AG6: =IF(OR($A6="",Objective!$A$7=""),"",IF(K6=0,IF(S6=0,0,IF(Objective!$C$7="lower",-1,1)),IF(Objective!$C$7="lower",(K6-S6)/ABS(K6),(S6-K6)/ABS(K6)))) | AH6: =IF(OR($A6="",Objective!$A$8=""),"",IF(L6=0,IF(T6=0,0,IF(Objective!$C$8="lower",-1,1)),IF(Objective!$C$8="lower",(L6-T6)/ABS(L6),(T6-L6)/ABS(L6)))) | AI6: =IF(OR($A6="",Objective!$A$9=""),"",IF(M6=0,IF(U6=0,0,IF(Objective!$C$9="lower",-1,1)),IF(Objective!$C$9="lower",(M6-U6)/ABS(M6),(U6-M6)/ABS(M6)))) | AJ6: =IF(OR($A6="",Objective!$A$10=""),"",IF(N6=0,IF(V6=0,0,IF(Objective!$C$10="lower",-1,1)),IF(Objective!$C$10="lower",(N6-V6)/ABS(N6),(V6-N6)/ABS(N6)))) | AK6: =IF(OR($A6="",Objective!$A$11=""),"",IF(O6=0,IF(W6=0,0,IF(Objective!$C$11="lower",-1,1)),IF(Objective!$C$11="lower",(O6-W6)/ABS(O6),(W6-O6)/ABS(O6)))) | AL6: =IF(OR($A6="",Objective!$A$12=""),"",IF(P6=0,IF(X6=0,0,IF(Objective!$C$12="lower",-1,1)),IF(Objective!$C$12="lower",(P6-X6)/ABS(P6),(X6-P6)/ABS(P6)))) | AM6: =IF(AE6="","",MAX(-1,MIN(1,AE6))) | AN6: =IF(AF6="","",MAX(-1,MIN(1,AF6))) | AO6: =IF(AG6="","",MAX(-1,MIN(1,AG6))) | AP6: =IF(AH6="","",MAX(-1,MIN(1,AH6))) | AQ6: =IF(AI6="","",MAX(-1,MIN(1,AI6))) | AR6: =IF(AJ6="","",MAX(-1,MIN(1,AJ6))) | AS6: =IF(AK6="","",MAX(-1,MIN(1,AK6))) | AT6: =IF(AL6="","",MAX(-1,MIN(1,AL6))) | AU6: =IF($A6="","",IF(AM6="",0,Objective!$B$5/Objective!$B$25*AM6)+IF(AN6="",0,Objective!$B$6/Objective!$B$25*AN6)+IF(AO6="",0,Objective!$B$7/Objective!$B$25*AO6)+IF(AP6="",0,Objective!$B$8/Objective!$B$25*AP6)+IF(AQ6="",0,Objective!$B$9/Objective!$B$25*AQ6)+IF(AR6="",0,Objective!$B$10/Objective!$B$25*AR6)+IF(AS6="",0,Objective!$B$11/Objective!$B$25*AS6)+IF(AT6="",0,Objective!$B$12/Objective!$B$25*AT6)) | AV6: =IF($A6="","",Objective!$B$23*MAX(0,N($H6)-N($G6))) | AW6: =IF($A6="","",AU6-AV6) | AX6: =IF($A6="","",AND(OR(Objective!$A$15="",LOWER(Y6)="pass"),OR(Objective!$A$16="",LOWER(Z6)="pass"),OR(Objective!$A$17="",LOWER(AA6)="pass"),OR(Objective!$A$18="",LOWER(AB6)="pass"),OR(Objective!$A$19="",LOWER(AC6)="pass"),OR(Objective!$A$20="",LOWER(AD6)="pass"))) | AY6: =IF($A6="","",AND(OR(AE6="",Objective!$B$24="",AE6>=-Objective!$B$24),OR(AF6="",Objective!$B$24="",AF6>=-Objective!$B$24),OR(AG6="",Objective!$B$24="",AG6>=-Objective!$B$24),OR(AH6="",Objective!$B$24="",AH6>=-Objective!$B$24),OR(AI6="",Objective!$B$24="",AI6>=-Objective!$B$24),OR(AJ6="",Objective!$B$24="",AJ6>=-Objective!$B$24),OR(AK6="",Objective!$B$24="",AK6>=-Objective!$B$24),OR(AL6="",Objective!$B$24="",AL6>=-Objective!$B$24))) | AZ6: =IF($A6="","",AND(AX6,AY6,AW6>=Objective!$B$22)) | BA6: =IF($A6="","",IF(OR(LOWER($C6)="generated",LOWER($C6)="evaluated",LOWER($C6)="discarded"),TRUE,IF(OR(LOWER($C6)="proposed",LOWER($C6)="promoted"),AZ6,FALSE))) | BB6: =IF($A6="","",IF(AZ6,"proposed (eligible - present to human)","discarded (keep the record and the reason)"))
AE7: =IF(OR($A7="",Objective!$A$5=""),"",IF(I7=0,IF(Q7=0,0,IF(Objective!$C$5="lower",-1,1)),IF(Objective!$C$5="lower",(I7-Q7)/ABS(I7),(Q7-I7)/ABS(I7)))) | AF7: =IF(OR($A7="",Objective!$A$6=""),"",IF(J7=0,IF(R7=0,0,IF(Objective!$C$6="lower",-1,1)),IF(Objective!$C$6="lower",(J7-R7)/ABS(J7),(R7-J7)/ABS(J7)))) | AG7: =IF(OR($A7="",Objective!$A$7=""),"",IF(K7=0,IF(S7=0,0,IF(Objective!$C$7="lower",-1,1)),IF(Objective!$C$7="lower",(K7-S7)/ABS(K7),(S7-K7)/ABS(K7)))) | AH7: =IF(OR($A7="",Objective!$A$8=""),"",IF(L7=0,IF(T7=0,0,IF(Objective!$C$8="lower",-1,1)),IF(Objective!$C$8="lower",(L7-T7)/ABS(L7),(T7-L7)/ABS(L7)))) | AI7: =IF(OR($A7="",Objective!$A$9=""),"",IF(M7=0,IF(U7=0,0,IF(Objective!$C$9="lower",-1,1)),IF(Objective!$C$9="lower",(M7-U7)/ABS(M7),(U7-M7)/ABS(M7)))) | AJ7: =IF(OR($A7="",Objective!$A$10=""),"",IF(N7=0,IF(V7=0,0,IF(Objective!$C$10="lower",-1,1)),IF(Objective!$C$10="lower",(N7-V7)/ABS(N7),(V7-N7)/ABS(N7)))) | AK7: =IF(OR($A7="",Objective!$A$11=""),"",IF(O7=0,IF(W7=0,0,IF(Objective!$C$11="lower",-1,1)),IF(Objective!$C$11="lower",(O7-W7)/ABS(O7),(W7-O7)/ABS(O7)))) | AL7: =IF(OR($A7="",Objective!$A$12=""),"",IF(P7=0,IF(X7=0,0,IF(Objective!$C$12="lower",-1,1)),IF(Objective!$C$12="lower",(P7-X7)/ABS(P7),(X7-P7)/ABS(P7)))) | AM7: =IF(AE7="","",MAX(-1,MIN(1,AE7))) | AN7: =IF(AF7="","",MAX(-1,MIN(1,AF7))) | AO7: =IF(AG7="","",MAX(-1,MIN(1,AG7))) | AP7: =IF(AH7="","",MAX(-1,MIN(1,AH7))) | AQ7: =IF(AI7="","",MAX(-1,MIN(1,AI7))) | AR7: =IF(AJ7="","",MAX(-1,MIN(1,AJ7))) | AS7: =IF(AK7="","",MAX(-1,MIN(1,AK7))) | AT7: =IF(AL7="","",MAX(-1,MIN(1,AL7))) | AU7: =IF($A7="","",IF(AM7="",0,Objective!$B$5/Objective!$B$25*AM7)+IF(AN7="",0,Objective!$B$6/Objective!$B$25*AN7)+IF(AO7="",0,Objective!$B$7/Objective!$B$25*AO7)+IF(AP7="",0,Objective!$B$8/Objective!$B$25*AP7)+IF(AQ7="",0,Objective!$B$9/Objective!$B$25*AQ7)+IF(AR7="",0,Objective!$B$10/Objective!$B$25*AR7)+IF(AS7="",0,Objective!$B$11/Objective!$B$25*AS7)+IF(AT7="",0,Objective!$B$12/Objective!$B$25*AT7)) | AV7: =IF($A7="","",Objective!$B$23*MAX(0,N($H7)-N($G7))) | AW7: =IF($A7="","",AU7-AV7) | AX7: =IF($A7="","",AND(OR(Objective!$A$15="",LOWER(Y7)="pass"),OR(Objective!$A$16="",LOWER(Z7)="pass"),OR(Objective!$A$17="",LOWER(AA7)="pass"),OR(Objective!$A$18="",LOWER(AB7)="pass"),OR(Objective!$A$19="",LOWER(AC7)="pass"),OR(Objective!$A$20="",LOWER(AD7)="pass"))) | AY7: =IF($A7="","",AND(OR(AE7="",Objective!$B$24="",AE7>=-Objective!$B$24),OR(AF7="",Objective!$B$24="",AF7>=-Objective!$B$24),OR(AG7="",Objective!$B$24="",AG7>=-Objective!$B$24),OR(AH7="",Objective!$B$24="",AH7>=-Objective!$B$24),OR(AI7="",Objective!$B$24="",AI7>=-Objective!$B$24),OR(AJ7="",Objective!$B$24="",AJ7>=-Objective!$B$24),OR(AK7="",Objective!$B$24="",AK7>=-Objective!$B$24),OR(AL7="",Objective!$B$24="",AL7>=-Objective!$B$24))) | AZ7: =IF($A7="","",AND(AX7,AY7,AW7>=Objective!$B$22)) | BA7: =IF($A7="","",IF(OR(LOWER($C7)="generated",LOWER($C7)="evaluated",LOWER($C7)="discarded"),TRUE,IF(OR(LOWER($C7)="proposed",LOWER($C7)="promoted"),AZ7,FALSE))) | BB7: =IF($A7="","",IF(AZ7,"proposed (eligible - present to human)","discarded (keep the record and the reason)"))
AE8: =IF(OR($A8="",Objective!$A$5=""),"",IF(I8=0,IF(Q8=0,0,IF(Objective!$C$5="lower",-1,1)),IF(Objective!$C$5="lower",(I8-Q8)/ABS(I8),(Q8-I8)/ABS(I8)))) | AF8: =IF(OR($A8="",Objective!$A$6=""),"",IF(J8=0,IF(R8=0,0,IF(Objective!$C$6="lower",-1,1)),IF(Objective!$C$6="lower",(J8-R8)/ABS(J8),(R8-J8)/ABS(J8)))) | AG8: =IF(OR($A8="",Objective!$A$7=""),"",IF(K8=0,IF(S8=0,0,IF(Objective!$C$7="lower",-1,1)),IF(Objective!$C$7="lower",(K8-S8)/ABS(K8),(S8-K8)/ABS(K8)))) | AH8: =IF(OR($A8="",Objective!$A$8=""),"",IF(L8=0,IF(T8=0,0,IF(Objective!$C$8="lower",-1,1)),IF(Objective!$C$8="lower",(L8-T8)/ABS(L8),(T8-L8)/ABS(L8)))) | AI8: =IF(OR($A8="",Objective!$A$9=""),"",IF(M8=0,IF(U8=0,0,IF(Objective!$C$9="lower",-1,1)),IF(Objective!$C$9="lower",(M8-U8)/ABS(M8),(U8-M8)/ABS(M8)))) | AJ8: =IF(OR($A8="",Objective!$A$10=""),"",IF(N8=0,IF(V8=0,0,IF(Objective!$C$10="lower",-1,1)),IF(Objective!$C$10="lower",(N8-V8)/ABS(N8),(V8-N8)/ABS(N8)))) | AK8: =IF(OR($A8="",Objective!$A$11=""),"",IF(O8=0,IF(W8=0,0,IF(Objective!$C$11="lower",-1,1)),IF(Objective!$C$11="lower",(O8-W8)/ABS(O8),(W8-O8)/ABS(O8)))) | AL8: =IF(OR($A8="",Objective!$A$12=""),"",IF(P8=0,IF(X8=0,0,IF(Objective!$C$12="lower",-1,1)),IF(Objective!$C$12="lower",(P8-X8)/ABS(P8),(X8-P8)/ABS(P8)))) | AM8: =IF(AE8="","",MAX(-1,MIN(1,AE8))) | AN8: =IF(AF8="","",MAX(-1,MIN(1,AF8))) | AO8: =IF(AG8="","",MAX(-1,MIN(1,AG8))) | AP8: =IF(AH8="","",MAX(-1,MIN(1,AH8))) | AQ8: =IF(AI8="","",MAX(-1,MIN(1,AI8))) | AR8: =IF(AJ8="","",MAX(-1,MIN(1,AJ8))) | AS8: =IF(AK8="","",MAX(-1,MIN(1,AK8))) | AT8: =IF(AL8="","",MAX(-1,MIN(1,AL8))) | AU8: =IF($A8="","",IF(AM8="",0,Objective!$B$5/Objective!$B$25*AM8)+IF(AN8="",0,Objective!$B$6/Objective!$B$25*AN8)+IF(AO8="",0,Objective!$B$7/Objective!$B$25*AO8)+IF(AP8="",0,Objective!$B$8/Objective!$B$25*AP8)+IF(AQ8="",0,Objective!$B$9/Objective!$B$25*AQ8)+IF(AR8="",0,Objective!$B$10/Objective!$B$25*AR8)+IF(AS8="",0,Objective!$B$11/Objective!$B$25*AS8)+IF(AT8="",0,Objective!$B$12/Objective!$B$25*AT8)) | AV8: =IF($A8="","",Objective!$B$23*MAX(0,N($H8)-N($G8))) | AW8: =IF($A8="","",AU8-AV8) | AX8: =IF($A8="","",AND(OR(Objective!$A$15="",LOWER(Y8)="pass"),OR(Objective!$A$16="",LOWER(Z8)="pass"),OR(Objective!$A$17="",LOWER(AA8)="pass"),OR(Objective!$A$18="",LOWER(AB8)="pass"),OR(Objective!$A$19="",LOWER(AC8)="pass"),OR(Objective!$A$20="",LOWER(AD8)="pass"))) | AY8: =IF($A8="","",AND(OR(AE8="",Objective!$B$24="",AE8>=-Objective!$B$24),OR(AF8="",Objective!$B$24="",AF8>=-Objective!$B$24),OR(AG8="",Objective!$B$24="",AG8>=-Objective!$B$24),OR(AH8="",Objective!$B$24="",AH8>=-Objective!$B$24),OR(AI8="",Objective!$B$24="",AI8>=-Objective!$B$24),OR(AJ8="",Objective!$B$24="",AJ8>=-Objective!$B$24),OR(AK8="",Objective!$B$24="",AK8>=-Objective!$B$24),OR(AL8="",Objective!$B$24="",AL8>=-Objective!$B$24))) | AZ8: =IF($A8="","",AND(AX8,AY8,AW8>=Objective!$B$22)) | BA8: =IF($A8="","",IF(OR(LOWER($C8)="generated",LOWER($C8)="evaluated",LOWER($C8)="discarded"),TRUE,IF(OR(LOWER($C8)="proposed",LOWER($C8)="promoted"),AZ8,FALSE))) | BB8: =IF($A8="","",IF(AZ8,"proposed (eligible - present to human)","discarded (keep the record and the reason)"))
AE9: =IF(OR($A9="",Objective!$A$5=""),"",IF(I9=0,IF(Q9=0,0,IF(Objective!$C$5="lower",-1,1)),IF(Objective!$C$5="lower",(I9-Q9)/ABS(I9),(Q9-I9)/ABS(I9)))) | AF9: =IF(OR($A9="",Objective!$A$6=""),"",IF(J9=0,IF(R9=0,0,IF(Objective!$C$6="lower",-1,1)),IF(Objective!$C$6="lower",(J9-R9)/ABS(J9),(R9-J9)/ABS(J9)))) | AG9: =IF(OR($A9="",Objective!$A$7=""),"",IF(K9=0,IF(S9=0,0,IF(Objective!$C$7="lower",-1,1)),IF(Objective!$C$7="lower",(K9-S9)/ABS(K9),(S9-K9)/ABS(K9)))) | AH9: =IF(OR($A9="",Objective!$A$8=""),"",IF(L9=0,IF(T9=0,0,IF(Objective!$C$8="lower",-1,1)),IF(Objective!$C$8="lower",(L9-T9)/ABS(L9),(T9-L9)/ABS(L9)))) | AI9: =IF(OR($A9="",Objective!$A$9=""),"",IF(M9=0,IF(U9=0,0,IF(Objective!$C$9="lower",-1,1)),IF(Objective!$C$9="lower",(M9-U9)/ABS(M9),(U9-M9)/ABS(M9)))) | AJ9: =IF(OR($A9="",Objective!$A$10=""),"",IF(N9=0,IF(V9=0,0,IF(Objective!$C$10="lower",-1,1)),IF(Objective!$C$10="lower",(N9-V9)/ABS(N9),(V9-N9)/ABS(N9)))) | AK9: =IF(OR($A9="",Objective!$A$11=""),"",IF(O9=0,IF(W9=0,0,IF(Objective!$C$11="lower",-1,1)),IF(Objective!$C$11="lower",(O9-W9)/ABS(O9),(W9-O9)/ABS(O9)))) | AL9: =IF(OR($A9="",Objective!$A$12=""),"",IF(P9=0,IF(X9=0,0,IF(Objective!$C$12="lower",-1,1)),IF(Objective!$C$12="lower",(P9-X9)/ABS(P9),(X9-P9)/ABS(P9)))) | AM9: =IF(AE9="","",MAX(-1,MIN(1,AE9))) | AN9: =IF(AF9="","",MAX(-1,MIN(1,AF9))) | AO9: =IF(AG9="","",MAX(-1,MIN(1,AG9))) | AP9: =IF(AH9="","",MAX(-1,MIN(1,AH9))) | AQ9: =IF(AI9="","",MAX(-1,MIN(1,AI9))) | AR9: =IF(AJ9="","",MAX(-1,MIN(1,AJ9))) | AS9: =IF(AK9="","",MAX(-1,MIN(1,AK9))) | AT9: =IF(AL9="","",MAX(-1,MIN(1,AL9))) | AU9: =IF($A9="","",IF(AM9="",0,Objective!$B$5/Objective!$B$25*AM9)+IF(AN9="",0,Objective!$B$6/Objective!$B$25*AN9)+IF(AO9="",0,Objective!$B$7/Objective!$B$25*AO9)+IF(AP9="",0,Objective!$B$8/Objective!$B$25*AP9)+IF(AQ9="",0,Objective!$B$9/Objective!$B$25*AQ9)+IF(AR9="",0,Objective!$B$10/Objective!$B$25*AR9)+IF(AS9="",0,Objective!$B$11/Objective!$B$25*AS9)+IF(AT9="",0,Objective!$B$12/Objective!$B$25*AT9)) | AV9: =IF($A9="","",Objective!$B$23*MAX(0,N($H9)-N($G9))) | AW9: =IF($A9="","",AU9-AV9) | AX9: =IF($A9="","",AND(OR(Objective!$A$15="",LOWER(Y9)="pass"),OR(Objective!$A$16="",LOWER(Z9)="pass"),OR(Objective!$A$17="",LOWER(AA9)="pass"),OR(Objective!$A$18="",LOWER(AB9)="pass"),OR(Objective!$A$19="",LOWER(AC9)="pass"),OR(Objective!$A$20="",LOWER(AD9)="pass"))) | AY9: =IF($A9="","",AND(OR(AE9="",Objective!$B$24="",AE9>=-Objective!$B$24),OR(AF9="",Objective!$B$24="",AF9>=-Objective!$B$24),OR(AG9="",Objective!$B$24="",AG9>=-Objective!$B$24),OR(AH9="",Objective!$B$24="",AH9>=-Objective!$B$24),OR(AI9="",Objective!$B$24="",AI9>=-Objective!$B$24),OR(AJ9="",Objective!$B$24="",AJ9>=-Objective!$B$24),OR(AK9="",Objective!$B$24="",AK9>=-Objective!$B$24),OR(AL9="",Objective!$B$24="",AL9>=-Objective!$B$24))) | AZ9: =IF($A9="","",AND(AX9,AY9,AW9>=Objective!$B$22)) | BA9: =IF($A9="","",IF(OR(LOWER($C9)="generated",LOWER($C9)="evaluated",LOWER($C9)="discarded"),TRUE,IF(OR(LOWER($C9)="proposed",LOWER($C9)="promoted"),AZ9,FALSE))) | BB9: =IF($A9="","",IF(AZ9,"proposed (eligible - present to human)","discarded (keep the record and the reason)"))
AE10: =IF(OR($A10="",Objective!$A$5=""),"",IF(I10=0,IF(Q10=0,0,IF(Objective!$C$5="lower",-1,1)),IF(Objective!$C$5="lower",(I10-Q10)/ABS(I10),(Q10-I10)/ABS(I10)))) | AF10: =IF(OR($A10="",Objective!$A$6=""),"",IF(J10=0,IF(R10=0,0,IF(Objective!$C$6="lower",-1,1)),IF(Objective!$C$6="lower",(J10-R10)/ABS(J10),(R10-J10)/ABS(J10)))) | AG10: =IF(OR($A10="",Objective!$A$7=""),"",IF(K10=0,IF(S10=0,0,IF(Objective!$C$7="lower",-1,1)),IF(Objective!$C$7="lower",(K10-S10)/ABS(K10),(S10-K10)/ABS(K10)))) | AH10: =IF(OR($A10="",Objective!$A$8=""),"",IF(L10=0,IF(T10=0,0,IF(Objective!$C$8="lower",-1,1)),IF(Objective!$C$8="lower",(L10-T10)/ABS(L10),(T10-L10)/ABS(L10)))) | AI10: =IF(OR($A10="",Objective!$A$9=""),"",IF(M10=0,IF(U10=0,0,IF(Objective!$C$9="lower",-1,1)),IF(Objective!$C$9="lower",(M10-U10)/ABS(M10),(U10-M10)/ABS(M10)))) | AJ10: =IF(OR($A10="",Objective!$A$10=""),"",IF(N10=0,IF(V10=0,0,IF(Objective!$C$10="lower",-1,1)),IF(Objective!$C$10="lower",(N10-V10)/ABS(N10),(V10-N10)/ABS(N10)))) | AK10: =IF(OR($A10="",Objective!$A$11=""),"",IF(O10=0,IF(W10=0,0,IF(Objective!$C$11="lower",-1,1)),IF(Objective!$C$11="lower",(O10-W10)/ABS(O10),(W10-O10)/ABS(O10)))) | AL10: =IF(OR($A10="",Objective!$A$12=""),"",IF(P10=0,IF(X10=0,0,IF(Objective!$C$12="lower",-1,1)),IF(Objective!$C$12="lower",(P10-X10)/ABS(P10),(X10-P10)/ABS(P10)))) | AM10: =IF(AE10="","",MAX(-1,MIN(1,AE10))) | AN10: =IF(AF10="","",MAX(-1,MIN(1,AF10))) | AO10: =IF(AG10="","",MAX(-1,MIN(1,AG10))) | AP10: =IF(AH10="","",MAX(-1,MIN(1,AH10))) | AQ10: =IF(AI10="","",MAX(-1,MIN(1,AI10))) | AR10: =IF(AJ10="","",MAX(-1,MIN(1,AJ10))) | AS10: =IF(AK10="","",MAX(-1,MIN(1,AK10))) | AT10: =IF(AL10="","",MAX(-1,MIN(1,AL10))) | AU10: =IF($A10="","",IF(AM10="",0,Objective!$B$5/Objective!$B$25*AM10)+IF(AN10="",0,Objective!$B$6/Objective!$B$25*AN10)+IF(AO10="",0,Objective!$B$7/Objective!$B$25*AO10)+IF(AP10="",0,Objective!$B$8/Objective!$B$25*AP10)+IF(AQ10="",0,Objective!$B$9/Objective!$B$25*AQ10)+IF(AR10="",0,Objective!$B$10/Objective!$B$25*AR10)+IF(AS10="",0,Objective!$B$11/Objective!$B$25*AS10)+IF(AT10="",0,Objective!$B$12/Objective!$B$25*AT10)) | AV10: =IF($A10="","",Objective!$B$23*MAX(0,N($H10)-N($G10))) | AW10: =IF($A10="","",AU10-AV10) | AX10: =IF($A10="","",AND(OR(Objective!$A$15="",LOWER(Y10)="pass"),OR(Objective!$A$16="",LOWER(Z10)="pass"),OR(Objective!$A$17="",LOWER(AA10)="pass"),OR(Objective!$A$18="",LOWER(AB10)="pass"),OR(Objective!$A$19="",LOWER(AC10)="pass"),OR(Objective!$A$20="",LOWER(AD10)="pass"))) | AY10: =IF($A10="","",AND(OR(AE10="",Objective!$B$24="",AE10>=-Objective!$B$24),OR(AF10="",Objective!$B$24="",AF10>=-Objective!$B$24),OR(AG10="",Objective!$B$24="",AG10>=-Objective!$B$24),OR(AH10="",Objective!$B$24="",AH10>=-Objective!$B$24),OR(AI10="",Objective!$B$24="",AI10>=-Objective!$B$24),OR(AJ10="",Objective!$B$24="",AJ10>=-Objective!$B$24),OR(AK10="",Objective!$B$24="",AK10>=-Objective!$B$24),OR(AL10="",Objective!$B$24="",AL10>=-Objective!$B$24))) | AZ10: =IF($A10="","",AND(AX10,AY10,AW10>=Objective!$B$22)) | BA10: =IF($A10="","",IF(OR(LOWER($C10)="generated",LOWER($C10)="evaluated",LOWER($C10)="discarded"),TRUE,IF(OR(LOWER($C10)="proposed",LOWER($C10)="promoted"),AZ10,FALSE))) | BB10: =IF($A10="","",IF(AZ10,"proposed (eligible - present to human)","discarded (keep the record and the reason)"))
AE11: =IF(OR($A11="",Objective!$A$5=""),"",IF(I11=0,IF(Q11=0,0,IF(Objective!$C$5="lower",-1,1)),IF(Objective!$C$5="lower",(I11-Q11)/ABS(I11),(Q11-I11)/ABS(I11)))) | AF11: =IF(OR($A11="",Objective!$A$6=""),"",IF(J11=0,IF(R11=0,0,IF(Objective!$C$6="lower",-1,1)),IF(Objective!$C$6="lower",(J11-R11)/ABS(J11),(R11-J11)/ABS(J11)))) | AG11: =IF(OR($A11="",Objective!$A$7=""),"",IF(K11=0,IF(S11=0,0,IF(Objective!$C$7="lower",-1,1)),IF(Objective!$C$7="lower",(K11-S11)/ABS(K11),(S11-K11)/ABS(K11)))) | AH11: =IF(OR($A11="",Objective!$A$8=""),"",IF(L11=0,IF(T11=0,0,IF(Objective!$C$8="lower",-1,1)),IF(Objective!$C$8="lower",(L11-T11)/ABS(L11),(T11-L11)/ABS(L11)))) | AI11: =IF(OR($A11="",Objective!$A$9=""),"",IF(M11=0,IF(U11=0,0,IF(Objective!$C$9="lower",-1,1)),IF(Objective!$C$9="lower",(M11-U11)/ABS(M11),(U11-M11)/ABS(M11)))) | AJ11: =IF(OR($A11="",Objective!$A$10=""),"",IF(N11=0,IF(V11=0,0,IF(Objective!$C$10="lower",-1,1)),IF(Objective!$C$10="lower",(N11-V11)/ABS(N11),(V11-N11)/ABS(N11)))) | AK11: =IF(OR($A11="",Objective!$A$11=""),"",IF(O11=0,IF(W11=0,0,IF(Objective!$C$11="lower",-1,1)),IF(Objective!$C$11="lower",(O11-W11)/ABS(O11),(W11-O11)/ABS(O11)))) | AL11: =IF(OR($A11="",Objective!$A$12=""),"",IF(P11=0,IF(X11=0,0,IF(Objective!$C$12="lower",-1,1)),IF(Objective!$C$12="lower",(P11-X11)/ABS(P11),(X11-P11)/ABS(P11)))) | AM11: =IF(AE11="","",MAX(-1,MIN(1,AE11))) | AN11: =IF(AF11="","",MAX(-1,MIN(1,AF11))) | AO11: =IF(AG11="","",MAX(-1,MIN(1,AG11))) | AP11: =IF(AH11="","",MAX(-1,MIN(1,AH11))) | AQ11: =IF(AI11="","",MAX(-1,MIN(1,AI11))) | AR11: =IF(AJ11="","",MAX(-1,MIN(1,AJ11))) | AS11: =IF(AK11="","",MAX(-1,MIN(1,AK11))) | AT11: =IF(AL11="","",MAX(-1,MIN(1,AL11))) | AU11: =IF($A11="","",IF(AM11="",0,Objective!$B$5/Objective!$B$25*AM11)+IF(AN11="",0,Objective!$B$6/Objective!$B$25*AN11)+IF(AO11="",0,Objective!$B$7/Objective!$B$25*AO11)+IF(AP11="",0,Objective!$B$8/Objective!$B$25*AP11)+IF(AQ11="",0,Objective!$B$9/Objective!$B$25*AQ11)+IF(AR11="",0,Objective!$B$10/Objective!$B$25*AR11)+IF(AS11="",0,Objective!$B$11/Objective!$B$25*AS11)+IF(AT11="",0,Objective!$B$12/Objective!$B$25*AT11)) | AV11: =IF($A11="","",Objective!$B$23*MAX(0,N($H11)-N($G11))) | AW11: =IF($A11="","",AU11-AV11) | AX11: =IF($A11="","",AND(OR(Objective!$A$15="",LOWER(Y11)="pass"),OR(Objective!$A$16="",LOWER(Z11)="pass"),OR(Objective!$A$17="",LOWER(AA11)="pass"),OR(Objective!$A$18="",LOWER(AB11)="pass"),OR(Objective!$A$19="",LOWER(AC11)="pass"),OR(Objective!$A$20="",LOWER(AD11)="pass"))) | AY11: =IF($A11="","",AND(OR(AE11="",Objective!$B$24="",AE11>=-Objective!$B$24),OR(AF11="",Objective!$B$24="",AF11>=-Objective!$B$24),OR(AG11="",Objective!$B$24="",AG11>=-Objective!$B$24),OR(AH11="",Objective!$B$24="",AH11>=-Objective!$B$24),OR(AI11="",Objective!$B$24="",AI11>=-Objective!$B$24),OR(AJ11="",Objective!$B$24="",AJ11>=-Objective!$B$24),OR(AK11="",Objective!$B$24="",AK11>=-Objective!$B$24),OR(AL11="",Objective!$B$24="",AL11>=-Objective!$B$24))) | AZ11: =IF($A11="","",AND(AX11,AY11,AW11>=Objective!$B$22)) | BA11: =IF($A11="","",IF(OR(LOWER($C11)="generated",LOWER($C11)="evaluated",LOWER($C11)="discarded"),TRUE,IF(OR(LOWER($C11)="proposed",LOWER($C11)="promoted"),AZ11,FALSE))) | BB11: =IF($A11="","",IF(AZ11,"proposed (eligible - present to human)","discarded (keep the record and the reason)"))
AE12: =IF(OR($A12="",Objective!$A$5=""),"",IF(I12=0,IF(Q12=0,0,IF(Objective!$C$5="lower",-1,1)),IF(Objective!$C$5="lower",(I12-Q12)/ABS(I12),(Q12-I12)/ABS(I12)))) | AF12: =IF(OR($A12="",Objective!$A$6=""),"",IF(J12=0,IF(R12=0,0,IF(Objective!$C$6="lower",-1,1)),IF(Objective!$C$6="lower",(J12-R12)/ABS(J12),(R12-J12)/ABS(J12)))) | AG12: =IF(OR($A12="",Objective!$A$7=""),"",IF(K12=0,IF(S12=0,0,IF(Objective!$C$7="lower",-1,1)),IF(Objective!$C$7="lower",(K12-S12)/ABS(K12),(S12-K12)/ABS(K12)))) | AH12: =IF(OR($A12="",Objective!$A$8=""),"",IF(L12=0,IF(T12=0,0,IF(Objective!$C$8="lower",-1,1)),IF(Objective!$C$8="lower",(L12-T12)/ABS(L12),(T12-L12)/ABS(L12)))) | AI12: =IF(OR($A12="",Objective!$A$9=""),"",IF(M12=0,IF(U12=0,0,IF(Objective!$C$9="lower",-1,1)),IF(Objective!$C$9="lower",(M12-U12)/ABS(M12),(U12-M12)/ABS(M12)))) | AJ12: =IF(OR($A12="",Objective!$A$10=""),"",IF(N12=0,IF(V12=0,0,IF(Objective!$C$10="lower",-1,1)),IF(Objective!$C$10="lower",(N12-V12)/ABS(N12),(V12-N12)/ABS(N12)))) | AK12: =IF(OR($A12="",Objective!$A$11=""),"",IF(O12=0,IF(W12=0,0,IF(Objective!$C$11="lower",-1,1)),IF(Objective!$C$11="lower",(O12-W12)/ABS(O12),(W12-O12)/ABS(O12)))) | AL12: =IF(OR($A12="",Objective!$A$12=""),"",IF(P12=0,IF(X12=0,0,IF(Objective!$C$12="lower",-1,1)),IF(Objective!$C$12="lower",(P12-X12)/ABS(P12),(X12-P12)/ABS(P12)))) | AM12: =IF(AE12="","",MAX(-1,MIN(1,AE12))) | AN12: =IF(AF12="","",MAX(-1,MIN(1,AF12))) | AO12: =IF(AG12="","",MAX(-1,MIN(1,AG12))) | AP12: =IF(AH12="","",MAX(-1,MIN(1,AH12))) | AQ12: =IF(AI12="","",MAX(-1,MIN(1,AI12))) | AR12: =IF(AJ12="","",MAX(-1,MIN(1,AJ12))) | AS12: =IF(AK12="","",MAX(-1,MIN(1,AK12))) | AT12: =IF(AL12="","",MAX(-1,MIN(1,AL12))) | AU12: =IF($A12="","",IF(AM12="",0,Objective!$B$5/Objective!$B$25*AM12)+IF(AN12="",0,Objective!$B$6/Objective!$B$25*AN12)+IF(AO12="",0,Objective!$B$7/Objective!$B$25*AO12)+IF(AP12="",0,Objective!$B$8/Objective!$B$25*AP12)+IF(AQ12="",0,Objective!$B$9/Objective!$B$25*AQ12)+IF(AR12="",0,Objective!$B$10/Objective!$B$25*AR12)+IF(AS12="",0,Objective!$B$11/Objective!$B$25*AS12)+IF(AT12="",0,Objective!$B$12/Objective!$B$25*AT12)) | AV12: =IF($A12="","",Objective!$B$23*MAX(0,N($H12)-N($G12))) | AW12: =IF($A12="","",AU12-AV12) | AX12: =IF($A12="","",AND(OR(Objective!$A$15="",LOWER(Y12)="pass"),OR(Objective!$A$16="",LOWER(Z12)="pass"),OR(Objective!$A$17="",LOWER(AA12)="pass"),OR(Objective!$A$18="",LOWER(AB12)="pass"),OR(Objective!$A$19="",LOWER(AC12)="pass"),OR(Objective!$A$20="",LOWER(AD12)="pass"))) | AY12: =IF($A12="","",AND(OR(AE12="",Objective!$B$24="",AE12>=-Objective!$B$24),OR(AF12="",Objective!$B$24="",AF12>=-Objective!$B$24),OR(AG12="",Objective!$B$24="",AG12>=-Objective!$B$24),OR(AH12="",Objective!$B$24="",AH12>=-Objective!$B$24),OR(AI12="",Objective!$B$24="",AI12>=-Objective!$B$24),OR(AJ12="",Objective!$B$24="",AJ12>=-Objective!$B$24),OR(AK12="",Objective!$B$24="",AK12>=-Objective!$B$24),OR(AL12="",Objective!$B$24="",AL12>=-Objective!$B$24))) | AZ12: =IF($A12="","",AND(AX12,AY12,AW12>=Objective!$B$22)) | BA12: =IF($A12="","",IF(OR(LOWER($C12)="generated",LOWER($C12)="evaluated",LOWER($C12)="discarded"),TRUE,IF(OR(LOWER($C12)="proposed",LOWER($C12)="promoted"),AZ12,FALSE))) | BB12: =IF($A12="","",IF(AZ12,"proposed (eligible - present to human)","discarded (keep the record and the reason)"))
AE13: =IF(OR($A13="",Objective!$A$5=""),"",IF(I13=0,IF(Q13=0,0,IF(Objective!$C$5="lower",-1,1)),IF(Objective!$C$5="lower",(I13-Q13)/ABS(I13),(Q13-I13)/ABS(I13)))) | AF13: =IF(OR($A13="",Objective!$A$6=""),"",IF(J13=0,IF(R13=0,0,IF(Objective!$C$6="lower",-1,1)),IF(Objective!$C$6="lower",(J13-R13)/ABS(J13),(R13-J13)/ABS(J13)))) | AG13: =IF(OR($A13="",Objective!$A$7=""),"",IF(K13=0,IF(S13=0,0,IF(Objective!$C$7="lower",-1,1)),IF(Objective!$C$7="lower",(K13-S13)/ABS(K13),(S13-K13)/ABS(K13)))) | AH13: =IF(OR($A13="",Objective!$A$8=""),"",IF(L13=0,IF(T13=0,0,IF(Objective!$C$8="lower",-1,1)),IF(Objective!$C$8="lower",(L13-T13)/ABS(L13),(T13-L13)/ABS(L13)))) | AI13: =IF(OR($A13="",Objective!$A$9=""),"",IF(M13=0,IF(U13=0,0,IF(Objective!$C$9="lower",-1,1)),IF(Objective!$C$9="lower",(M13-U13)/ABS(M13),(U13-M13)/ABS(M13)))) | AJ13: =IF(OR($A13="",Objective!$A$10=""),"",IF(N13=0,IF(V13=0,0,IF(Objective!$C$10="lower",-1,1)),IF(Objective!$C$10="lower",(N13-V13)/ABS(N13),(V13-N13)/ABS(N13)))) | AK13: =IF(OR($A13="",Objective!$A$11=""),"",IF(O13=0,IF(W13=0,0,IF(Objective!$C$11="lower",-1,1)),IF(Objective!$C$11="lower",(O13-W13)/ABS(O13),(W13-O13)/ABS(O13)))) | AL13: =IF(OR($A13="",Objective!$A$12=""),"",IF(P13=0,IF(X13=0,0,IF(Objective!$C$12="lower",-1,1)),IF(Objective!$C$12="lower",(P13-X13)/ABS(P13),(X13-P13)/ABS(P13)))) | AM13: =IF(AE13="","",MAX(-1,MIN(1,AE13))) | AN13: =IF(AF13="","",MAX(-1,MIN(1,AF13))) | AO13: =IF(AG13="","",MAX(-1,MIN(1,AG13))) | AP13: =IF(AH13="","",MAX(-1,MIN(1,AH13))) | AQ13: =IF(AI13="","",MAX(-1,MIN(1,AI13))) | AR13: =IF(AJ13="","",MAX(-1,MIN(1,AJ13))) | AS13: =IF(AK13="","",MAX(-1,MIN(1,AK13))) | AT13: =IF(AL13="","",MAX(-1,MIN(1,AL13))) | AU13: =IF($A13="","",IF(AM13="",0,Objective!$B$5/Objective!$B$25*AM13)+IF(AN13="",0,Objective!$B$6/Objective!$B$25*AN13)+IF(AO13="",0,Objective!$B$7/Objective!$B$25*AO13)+IF(AP13="",0,Objective!$B$8/Objective!$B$25*AP13)+IF(AQ13="",0,Objective!$B$9/Objective!$B$25*AQ13)+IF(AR13="",0,Objective!$B$10/Objective!$B$25*AR13)+IF(AS13="",0,Objective!$B$11/Objective!$B$25*AS13)+IF(AT13="",0,Objective!$B$12/Objective!$B$25*AT13)) | AV13: =IF($A13="","",Objective!$B$23*MAX(0,N($H13)-N($G13))) | AW13: =IF($A13="","",AU13-AV13) | AX13: =IF($A13="","",AND(OR(Objective!$A$15="",LOWER(Y13)="pass"),OR(Objective!$A$16="",LOWER(Z13)="pass"),OR(Objective!$A$17="",LOWER(AA13)="pass"),OR(Objective!$A$18="",LOWER(AB13)="pass"),OR(Objective!$A$19="",LOWER(AC13)="pass"),OR(Objective!$A$20="",LOWER(AD13)="pass"))) | AY13: =IF($A13="","",AND(OR(AE13="",Objective!$B$24="",AE13>=-Objective!$B$24),OR(AF13="",Objective!$B$24="",AF13>=-Objective!$B$24),OR(AG13="",Objective!$B$24="",AG13>=-Objective!$B$24),OR(AH13="",Objective!$B$24="",AH13>=-Objective!$B$24),OR(AI13="",Objective!$B$24="",AI13>=-Objective!$B$24),OR(AJ13="",Objective!$B$24="",AJ13>=-Objective!$B$24),OR(AK13="",Objective!$B$24="",AK13>=-Objective!$B$24),OR(AL13="",Objective!$B$24="",AL13>=-Objective!$B$24))) | AZ13: =IF($A13="","",AND(AX13,AY13,AW13>=Objective!$B$22)) | BA13: =IF($A13="","",IF(OR(LOWER($C13)="generated",LOWER($C13)="evaluated",LOWER($C13)="discarded"),TRUE,IF(OR(LOWER($C13)="proposed",LOWER($C13)="promoted"),AZ13,FALSE))) | BB13: =IF($A13="","",IF(AZ13,"proposed (eligible - present to human)","discarded (keep the record and the reason)"))
AE14: =IF(OR($A14="",Objective!$A$5=""),"",IF(I14=0,IF(Q14=0,0,IF(Objective!$C$5="lower",-1,1)),IF(Objective!$C$5="lower",(I14-Q14)/ABS(I14),(Q14-I14)/ABS(I14)))) | AF14: =IF(OR($A14="",Objective!$A$6=""),"",IF(J14=0,IF(R14=0,0,IF(Objective!$C$6="lower",-1,1)),IF(Objective!$C$6="lower",(J14-R14)/ABS(J14),(R14-J14)/ABS(J14)))) | AG14: =IF(OR($A14="",Objective!$A$7=""),"",IF(K14=0,IF(S14=0,0,IF(Objective!$C$7="lower",-1,1)),IF(Objective!$C$7="lower",(K14-S14)/ABS(K14),(S14-K14)/ABS(K14)))) | AH14: =IF(OR($A14="",Objective!$A$8=""),"",IF(L14=0,IF(T14=0,0,IF(Objective!$C$8="lower",-1,1)),IF(Objective!$C$8="lower",(L14-T14)/ABS(L14),(T14-L14)/ABS(L14)))) | AI14: =IF(OR($A14="",Objective!$A$9=""),"",IF(M14=0,IF(U14=0,0,IF(Objective!$C$9="lower",-1,1)),IF(Objective!$C$9="lower",(M14-U14)/ABS(M14),(U14-M14)/ABS(M14)))) | AJ14: =IF(OR($A14="",Objective!$A$10=""),"",IF(N14=0,IF(V14=0,0,IF(Objective!$C$10="lower",-1,1)),IF(Objective!$C$10="lower",(N14-V14)/ABS(N14),(V14-N14)/ABS(N14)))) | AK14: =IF(OR($A14="",Objective!$A$11=""),"",IF(O14=0,IF(W14=0,0,IF(Objective!$C$11="lower",-1,1)),IF(Objective!$C$11="lower",(O14-W14)/ABS(O14),(W14-O14)/ABS(O14)))) | AL14: =IF(OR($A14="",Objective!$A$12=""),"",IF(P14=0,IF(X14=0,0,IF(Objective!$C$12="lower",-1,1)),IF(Objective!$C$12="lower",(P14-X14)/ABS(P14),(X14-P14)/ABS(P14)))) | AM14: =IF(AE14="","",MAX(-1,MIN(1,AE14))) | AN14: =IF(AF14="","",MAX(-1,MIN(1,AF14))) | AO14: =IF(AG14="","",MAX(-1,MIN(1,AG14))) | AP14: =IF(AH14="","",MAX(-1,MIN(1,AH14))) | AQ14: =IF(AI14="","",MAX(-1,MIN(1,AI14))) | AR14: =IF(AJ14="","",MAX(-1,MIN(1,AJ14))) | AS14: =IF(AK14="","",MAX(-1,MIN(1,AK14))) | AT14: =IF(AL14="","",MAX(-1,MIN(1,AL14))) | AU14: =IF($A14="","",IF(AM14="",0,Objective!$B$5/Objective!$B$25*AM14)+IF(AN14="",0,Objective!$B$6/Objective!$B$25*AN14)+IF(AO14="",0,Objective!$B$7/Objective!$B$25*AO14)+IF(AP14="",0,Objective!$B$8/Objective!$B$25*AP14)+IF(AQ14="",0,Objective!$B$9/Objective!$B$25*AQ14)+IF(AR14="",0,Objective!$B$10/Objective!$B$25*AR14)+IF(AS14="",0,Objective!$B$11/Objective!$B$25*AS14)+IF(AT14="",0,Objective!$B$12/Objective!$B$25*AT14)) | AV14: =IF($A14="","",Objective!$B$23*MAX(0,N($H14)-N($G14))) | AW14: =IF($A14="","",AU14-AV14) | AX14: =IF($A14="","",AND(OR(Objective!$A$15="",LOWER(Y14)="pass"),OR(Objective!$A$16="",LOWER(Z14)="pass"),OR(Objective!$A$17="",LOWER(AA14)="pass"),OR(Objective!$A$18="",LOWER(AB14)="pass"),OR(Objective!$A$19="",LOWER(AC14)="pass"),OR(Objective!$A$20="",LOWER(AD14)="pass"))) | AY14: =IF($A14="","",AND(OR(AE14="",Objective!$B$24="",AE14>=-Objective!$B$24),OR(AF14="",Objective!$B$24="",AF14>=-Objective!$B$24),OR(AG14="",Objective!$B$24="",AG14>=-Objective!$B$24),OR(AH14="",Objective!$B$24="",AH14>=-Objective!$B$24),OR(AI14="",Objective!$B$24="",AI14>=-Objective!$B$24),OR(AJ14="",Objective!$B$24="",AJ14>=-Objective!$B$24),OR(AK14="",Objective!$B$24="",AK14>=-Objective!$B$24),OR(AL14="",Objective!$B$24="",AL14>=-Objective!$B$24))) | AZ14: =IF($A14="","",AND(AX14,AY14,AW14>=Objective!$B$22)) | BA14: =IF($A14="","",IF(OR(LOWER($C14)="generated",LOWER($C14)="evaluated",LOWER($C14)="discarded"),TRUE,IF(OR(LOWER($C14)="proposed",LOWER($C14)="promoted"),AZ14,FALSE))) | BB14: =IF($A14="","",IF(AZ14,"proposed (eligible - present to human)","discarded (keep the record and the reason)"))
AE15: =IF(OR($A15="",Objective!$A$5=""),"",IF(I15=0,IF(Q15=0,0,IF(Objective!$C$5="lower",-1,1)),IF(Objective!$C$5="lower",(I15-Q15)/ABS(I15),(Q15-I15)/ABS(I15)))) | AF15: =IF(OR($A15="",Objective!$A$6=""),"",IF(J15=0,IF(R15=0,0,IF(Objective!$C$6="lower",-1,1)),IF(Objective!$C$6="lower",(J15-R15)/ABS(J15),(R15-J15)/ABS(J15)))) | AG15: =IF(OR($A15="",Objective!$A$7=""),"",IF(K15=0,IF(S15=0,0,IF(Objective!$C$7="lower",-1,1)),IF(Objective!$C$7="lower",(K15-S15)/ABS(K15),(S15-K15)/ABS(K15)))) | AH15: =IF(OR($A15="",Objective!$A$8=""),"",IF(L15=0,IF(T15=0,0,IF(Objective!$C$8="lower",-1,1)),IF(Objective!$C$8="lower",(L15-T15)/ABS(L15),(T15-L15)/ABS(L15)))) | AI15: =IF(OR($A15="",Objective!$A$9=""),"",IF(M15=0,IF(U15=0,0,IF(Objective!$C$9="lower",-1,1)),IF(Objective!$C$9="lower",(M15-U15)/ABS(M15),(U15-M15)/ABS(M15)))) | AJ15: =IF(OR($A15="",Objective!$A$10=""),"",IF(N15=0,IF(V15=0,0,IF(Objective!$C$10="lower",-1,1)),IF(Objective!$C$10="lower",(N15-V15)/ABS(N15),(V15-N15)/ABS(N15)))) | AK15: =IF(OR($A15="",Objective!$A$11=""),"",IF(O15=0,IF(W15=0,0,IF(Objective!$C$11="lower",-1,1)),IF(Objective!$C$11="lower",(O15-W15)/ABS(O15),(W15-O15)/ABS(O15)))) | AL15: =IF(OR($A15="",Objective!$A$12=""),"",IF(P15=0,IF(X15=0,0,IF(Objective!$C$12="lower",-1,1)),IF(Objective!$C$12="lower",(P15-X15)/ABS(P15),(X15-P15)/ABS(P15)))) | AM15: =IF(AE15="","",MAX(-1,MIN(1,AE15))) | AN15: =IF(AF15="","",MAX(-1,MIN(1,AF15))) | AO15: =IF(AG15="","",MAX(-1,MIN(1,AG15))) | AP15: =IF(AH15="","",MAX(-1,MIN(1,AH15))) | AQ15: =IF(AI15="","",MAX(-1,MIN(1,AI15))) | AR15: =IF(AJ15="","",MAX(-1,MIN(1,AJ15))) | AS15: =IF(AK15="","",MAX(-1,MIN(1,AK15))) | AT15: =IF(AL15="","",MAX(-1,MIN(1,AL15))) | AU15: =IF($A15="","",IF(AM15="",0,Objective!$B$5/Objective!$B$25*AM15)+IF(AN15="",0,Objective!$B$6/Objective!$B$25*AN15)+IF(AO15="",0,Objective!$B$7/Objective!$B$25*AO15)+IF(AP15="",0,Objective!$B$8/Objective!$B$25*AP15)+IF(AQ15="",0,Objective!$B$9/Objective!$B$25*AQ15)+IF(AR15="",0,Objective!$B$10/Objective!$B$25*AR15)+IF(AS15="",0,Objective!$B$11/Objective!$B$25*AS15)+IF(AT15="",0,Objective!$B$12/Objective!$B$25*AT15)) | AV15: =IF($A15="","",Objective!$B$23*MAX(0,N($H15)-N($G15))) | AW15: =IF($A15="","",AU15-AV15) | AX15: =IF($A15="","",AND(OR(Objective!$A$15="",LOWER(Y15)="pass"),OR(Objective!$A$16="",LOWER(Z15)="pass"),OR(Objective!$A$17="",LOWER(AA15)="pass"),OR(Objective!$A$18="",LOWER(AB15)="pass"),OR(Objective!$A$19="",LOWER(AC15)="pass"),OR(Objective!$A$20="",LOWER(AD15)="pass"))) | AY15: =IF($A15="","",AND(OR(AE15="",Objective!$B$24="",AE15>=-Objective!$B$24),OR(AF15="",Objective!$B$24="",AF15>=-Objective!$B$24),OR(AG15="",Objective!$B$24="",AG15>=-Objective!$B$24),OR(AH15="",Objective!$B$24="",AH15>=-Objective!$B$24),OR(AI15="",Objective!$B$24="",AI15>=-Objective!$B$24),OR(AJ15="",Objective!$B$24="",AJ15>=-Objective!$B$24),OR(AK15="",Objective!$B$24="",AK15>=-Objective!$B$24),OR(AL15="",Objective!$B$24="",AL15>=-Objective!$B$24))) | AZ15: =IF($A15="","",AND(AX15,AY15,AW15>=Objective!$B$22)) | BA15: =IF($A15="","",IF(OR(LOWER($C15)="generated",LOWER($C15)="evaluated",LOWER($C15)="discarded"),TRUE,IF(OR(LOWER($C15)="proposed",LOWER($C15)="promoted"),AZ15,FALSE))) | BB15: =IF($A15="","",IF(AZ15,"proposed (eligible - present to human)","discarded (keep the record and the reason)"))
AE16: =IF(OR($A16="",Objective!$A$5=""),"",IF(I16=0,IF(Q16=0,0,IF(Objective!$C$5="lower",-1,1)),IF(Objective!$C$5="lower",(I16-Q16)/ABS(I16),(Q16-I16)/ABS(I16)))) | AF16: =IF(OR($A16="",Objective!$A$6=""),"",IF(J16=0,IF(R16=0,0,IF(Objective!$C$6="lower",-1,1)),IF(Objective!$C$6="lower",(J16-R16)/ABS(J16),(R16-J16)/ABS(J16)))) | AG16: =IF(OR($A16="",Objective!$A$7=""),"",IF(K16=0,IF(S16=0,0,IF(Objective!$C$7="lower",-1,1)),IF(Objective!$C$7="lower",(K16-S16)/ABS(K16),(S16-K16)/ABS(K16)))) | AH16: =IF(OR($A16="",Objective!$A$8=""),"",IF(L16=0,IF(T16=0,0,IF(Objective!$C$8="lower",-1,1)),IF(Objective!$C$8="lower",(L16-T16)/ABS(L16),(T16-L16)/ABS(L16)))) | AI16: =IF(OR($A16="",Objective!$A$9=""),"",IF(M16=0,IF(U16=0,0,IF(Objective!$C$9="lower",-1,1)),IF(Objective!$C$9="lower",(M16-U16)/ABS(M16),(U16-M16)/ABS(M16)))) | AJ16: =IF(OR($A16="",Objective!$A$10=""),"",IF(N16=0,IF(V16=0,0,IF(Objective!$C$10="lower",-1,1)),IF(Objective!$C$10="lower",(N16-V16)/ABS(N16),(V16-N16)/ABS(N16)))) | AK16: =IF(OR($A16="",Objective!$A$11=""),"",IF(O16=0,IF(W16=0,0,IF(Objective!$C$11="lower",-1,1)),IF(Objective!$C$11="lower",(O16-W16)/ABS(O16),(W16-O16)/ABS(O16)))) | AL16: =IF(OR($A16="",Objective!$A$12=""),"",IF(P16=0,IF(X16=0,0,IF(Objective!$C$12="lower",-1,1)),IF(Objective!$C$12="lower",(P16-X16)/ABS(P16),(X16-P16)/ABS(P16)))) | AM16: =IF(AE16="","",MAX(-1,MIN(1,AE16))) | AN16: =IF(AF16="","",MAX(-1,MIN(1,AF16))) | AO16: =IF(AG16="","",MAX(-1,MIN(1,AG16))) | AP16: =IF(AH16="","",MAX(-1,MIN(1,AH16))) | AQ16: =IF(AI16="","",MAX(-1,MIN(1,AI16))) | AR16: =IF(AJ16="","",MAX(-1,MIN(1,AJ16))) | AS16: =IF(AK16="","",MAX(-1,MIN(1,AK16))) | AT16: =IF(AL16="","",MAX(-1,MIN(1,AL16))) | AU16: =IF($A16="","",IF(AM16="",0,Objective!$B$5/Objective!$B$25*AM16)+IF(AN16="",0,Objective!$B$6/Objective!$B$25*AN16)+IF(AO16="",0,Objective!$B$7/Objective!$B$25*AO16)+IF(AP16="",0,Objective!$B$8/Objective!$B$25*AP16)+IF(AQ16="",0,Objective!$B$9/Objective!$B$25*AQ16)+IF(AR16="",0,Objective!$B$10/Objective!$B$25*AR16)+IF(AS16="",0,Objective!$B$11/Objective!$B$25*AS16)+IF(AT16="",0,Objective!$B$12/Objective!$B$25*AT16)) | AV16: =IF($A16="","",Objective!$B$23*MAX(0,N($H16)-N($G16))) | AW16: =IF($A16="","",AU16-AV16) | AX16: =IF($A16="","",AND(OR(Objective!$A$15="",LOWER(Y16)="pass"),OR(Objective!$A$16="",LOWER(Z16)="pass"),OR(Objective!$A$17="",LOWER(AA16)="pass"),OR(Objective!$A$18="",LOWER(AB16)="pass"),OR(Objective!$A$19="",LOWER(AC16)="pass"),OR(Objective!$A$20="",LOWER(AD16)="pass"))) | AY16: =IF($A16="","",AND(OR(AE16="",Objective!$B$24="",AE16>=-Objective!$B$24),OR(AF16="",Objective!$B$24="",AF16>=-Objective!$B$24),OR(AG16="",Objective!$B$24="",AG16>=-Objective!$B$24),OR(AH16="",Objective!$B$24="",AH16>=-Objective!$B$24),OR(AI16="",Objective!$B$24="",AI16>=-Objective!$B$24),OR(AJ16="",Objective!$B$24="",AJ16>=-Objective!$B$24),OR(AK16="",Objective!$B$24="",AK16>=-Objective!$B$24),OR(AL16="",Objective!$B$24="",AL16>=-Objective!$B$24))) | AZ16: =IF($A16="","",AND(AX16,AY16,AW16>=Objective!$B$22)) | BA16: =IF($A16="","",IF(OR(LOWER($C16)="generated",LOWER($C16)="evaluated",LOWER($C16)="discarded"),TRUE,IF(OR(LOWER($C16)="proposed",LOWER($C16)="promoted"),AZ16,FALSE))) | BB16: =IF($A16="","",IF(AZ16,"proposed (eligible - present to human)","discarded (keep the record and the reason)"))
AE17: =IF(OR($A17="",Objective!$A$5=""),"",IF(I17=0,IF(Q17=0,0,IF(Objective!$C$5="lower",-1,1)),IF(Objective!$C$5="lower",(I17-Q17)/ABS(I17),(Q17-I17)/ABS(I17)))) | AF17: =IF(OR($A17="",Objective!$A$6=""),"",IF(J17=0,IF(R17=0,0,IF(Objective!$C$6="lower",-1,1)),IF(Objective!$C$6="lower",(J17-R17)/ABS(J17),(R17-J17)/ABS(J17)))) | AG17: =IF(OR($A17="",Objective!$A$7=""),"",IF(K17=0,IF(S17=0,0,IF(Objective!$C$7="lower",-1,1)),IF(Objective!$C$7="lower",(K17-S17)/ABS(K17),(S17-K17)/ABS(K17)))) | AH17: =IF(OR($A17="",Objective!$A$8=""),"",IF(L17=0,IF(T17=0,0,IF(Objective!$C$8="lower",-1,1)),IF(Objective!$C$8="lower",(L17-T17)/ABS(L17),(T17-L17)/ABS(L17)))) | AI17: =IF(OR($A17="",Objective!$A$9=""),"",IF(M17=0,IF(U17=0,0,IF(Objective!$C$9="lower",-1,1)),IF(Objective!$C$9="lower",(M17-U17)/ABS(M17),(U17-M17)/ABS(M17)))) | AJ17: =IF(OR($A17="",Objective!$A$10=""),"",IF(N17=0,IF(V17=0,0,IF(Objective!$C$10="lower",-1,1)),IF(Objective!$C$10="lower",(N17-V17)/ABS(N17),(V17-N17)/ABS(N17)))) | AK17: =IF(OR($A17="",Objective!$A$11=""),"",IF(O17=0,IF(W17=0,0,IF(Objective!$C$11="lower",-1,1)),IF(Objective!$C$11="lower",(O17-W17)/ABS(O17),(W17-O17)/ABS(O17)))) | AL17: =IF(OR($A17="",Objective!$A$12=""),"",IF(P17=0,IF(X17=0,0,IF(Objective!$C$12="lower",-1,1)),IF(Objective!$C$12="lower",(P17-X17)/ABS(P17),(X17-P17)/ABS(P17)))) | AM17: =IF(AE17="","",MAX(-1,MIN(1,AE17))) | AN17: =IF(AF17="","",MAX(-1,MIN(1,AF17))) | AO17: =IF(AG17="","",MAX(-1,MIN(1,AG17))) | AP17: =IF(AH17="","",MAX(-1,MIN(1,AH17))) | AQ17: =IF(AI17="","",MAX(-1,MIN(1,AI17))) | AR17: =IF(AJ17="","",MAX(-1,MIN(1,AJ17))) | AS17: =IF(AK17="","",MAX(-1,MIN(1,AK17))) | AT17: =IF(AL17="","",MAX(-1,MIN(1,AL17))) | AU17: =IF($A17="","",IF(AM17="",0,Objective!$B$5/Objective!$B$25*AM17)+IF(AN17="",0,Objective!$B$6/Objective!$B$25*AN17)+IF(AO17="",0,Objective!$B$7/Objective!$B$25*AO17)+IF(AP17="",0,Objective!$B$8/Objective!$B$25*AP17)+IF(AQ17="",0,Objective!$B$9/Objective!$B$25*AQ17)+IF(AR17="",0,Objective!$B$10/Objective!$B$25*AR17)+IF(AS17="",0,Objective!$B$11/Objective!$B$25*AS17)+IF(AT17="",0,Objective!$B$12/Objective!$B$25*AT17)) | AV17: =IF($A17="","",Objective!$B$23*MAX(0,N($H17)-N($G17))) | AW17: =IF($A17="","",AU17-AV17) | AX17: =IF($A17="","",AND(OR(Objective!$A$15="",LOWER(Y17)="pass"),OR(Objective!$A$16="",LOWER(Z17)="pass"),OR(Objective!$A$17="",LOWER(AA17)="pass"),OR(Objective!$A$18="",LOWER(AB17)="pass"),OR(Objective!$A$19="",LOWER(AC17)="pass"),OR(Objective!$A$20="",LOWER(AD17)="pass"))) | AY17: =IF($A17="","",AND(OR(AE17="",Objective!$B$24="",AE17>=-Objective!$B$24),OR(AF17="",Objective!$B$24="",AF17>=-Objective!$B$24),OR(AG17="",Objective!$B$24="",AG17>=-Objective!$B$24),OR(AH17="",Objective!$B$24="",AH17>=-Objective!$B$24),OR(AI17="",Objective!$B$24="",AI17>=-Objective!$B$24),OR(AJ17="",Objective!$B$24="",AJ17>=-Objective!$B$24),OR(AK17="",Objective!$B$24="",AK17>=-Objective!$B$24),OR(AL17="",Objective!$B$24="",AL17>=-Objective!$B$24))) | AZ17: =IF($A17="","",AND(AX17,AY17,AW17>=Objective!$B$22)) | BA17: =IF($A17="","",IF(OR(LOWER($C17)="generated",LOWER($C17)="evaluated",LOWER($C17)="discarded"),TRUE,IF(OR(LOWER($C17)="proposed",LOWER($C17)="promoted"),AZ17,FALSE))) | BB17: =IF($A17="","",IF(AZ17,"proposed (eligible - present to human)","discarded (keep the record and the reason)"))
AE18: =IF(OR($A18="",Objective!$A$5=""),"",IF(I18=0,IF(Q18=0,0,IF(Objective!$C$5="lower",-1,1)),IF(Objective!$C$5="lower",(I18-Q18)/ABS(I18),(Q18-I18)/ABS(I18)))) | AF18: =IF(OR($A18="",Objective!$A$6=""),"",IF(J18=0,IF(R18=0,0,IF(Objective!$C$6="lower",-1,1)),IF(Objective!$C$6="lower",(J18-R18)/ABS(J18),(R18-J18)/ABS(J18)))) | AG18: =IF(OR($A18="",Objective!$A$7=""),"",IF(K18=0,IF(S18=0,0,IF(Objective!$C$7="lower",-1,1)),IF(Objective!$C$7="lower",(K18-S18)/ABS(K18),(S18-K18)/ABS(K18)))) | AH18: =IF(OR($A18="",Objective!$A$8=""),"",IF(L18=0,IF(T18=0,0,IF(Objective!$C$8="lower",-1,1)),IF(Objective!$C$8="lower",(L18-T18)/ABS(L18),(T18-L18)/ABS(L18)))) | AI18: =IF(OR($A18="",Objective!$A$9=""),"",IF(M18=0,IF(U18=0,0,IF(Objective!$C$9="lower",-1,1)),IF(Objective!$C$9="lower",(M18-U18)/ABS(M18),(U18-M18)/ABS(M18)))) | AJ18: =IF(OR($A18="",Objective!$A$10=""),"",IF(N18=0,IF(V18=0,0,IF(Objective!$C$10="lower",-1,1)),IF(Objective!$C$10="lower",(N18-V18)/ABS(N18),(V18-N18)/ABS(N18)))) | AK18: =IF(OR($A18="",Objective!$A$11=""),"",IF(O18=0,IF(W18=0,0,IF(Objective!$C$11="lower",-1,1)),IF(Objective!$C$11="lower",(O18-W18)/ABS(O18),(W18-O18)/ABS(O18)))) | AL18: =IF(OR($A18="",Objective!$A$12=""),"",IF(P18=0,IF(X18=0,0,IF(Objective!$C$12="lower",-1,1)),IF(Objective!$C$12="lower",(P18-X18)/ABS(P18),(X18-P18)/ABS(P18)))) | AM18: =IF(AE18="","",MAX(-1,MIN(1,AE18))) | AN18: =IF(AF18="","",MAX(-1,MIN(1,AF18))) | AO18: =IF(AG18="","",MAX(-1,MIN(1,AG18))) | AP18: =IF(AH18="","",MAX(-1,MIN(1,AH18))) | AQ18: =IF(AI18="","",MAX(-1,MIN(1,AI18))) | AR18: =IF(AJ18="","",MAX(-1,MIN(1,AJ18))) | AS18: =IF(AK18="","",MAX(-1,MIN(1,AK18))) | AT18: =IF(AL18="","",MAX(-1,MIN(1,AL18))) | AU18: =IF($A18="","",IF(AM18="",0,Objective!$B$5/Objective!$B$25*AM18)+IF(AN18="",0,Objective!$B$6/Objective!$B$25*AN18)+IF(AO18="",0,Objective!$B$7/Objective!$B$25*AO18)+IF(AP18="",0,Objective!$B$8/Objective!$B$25*AP18)+IF(AQ18="",0,Objective!$B$9/Objective!$B$25*AQ18)+IF(AR18="",0,Objective!$B$10/Objective!$B$25*AR18)+IF(AS18="",0,Objective!$B$11/Objective!$B$25*AS18)+IF(AT18="",0,Objective!$B$12/Objective!$B$25*AT18)) | AV18: =IF($A18="","",Objective!$B$23*MAX(0,N($H18)-N($G18))) | AW18: =IF($A18="","",AU18-AV18) | AX18: =IF($A18="","",AND(OR(Objective!$A$15="",LOWER(Y18)="pass"),OR(Objective!$A$16="",LOWER(Z18)="pass"),OR(Objective!$A$17="",LOWER(AA18)="pass"),OR(Objective!$A$18="",LOWER(AB18)="pass"),OR(Objective!$A$19="",LOWER(AC18)="pass"),OR(Objective!$A$20="",LOWER(AD18)="pass"))) | AY18: =IF($A18="","",AND(OR(AE18="",Objective!$B$24="",AE18>=-Objective!$B$24),OR(AF18="",Objective!$B$24="",AF18>=-Objective!$B$24),OR(AG18="",Objective!$B$24="",AG18>=-Objective!$B$24),OR(AH18="",Objective!$B$24="",AH18>=-Objective!$B$24),OR(AI18="",Objective!$B$24="",AI18>=-Objective!$B$24),OR(AJ18="",Objective!$B$24="",AJ18>=-Objective!$B$24),OR(AK18="",Objective!$B$24="",AK18>=-Objective!$B$24),OR(AL18="",Objective!$B$24="",AL18>=-Objective!$B$24))) | AZ18: =IF($A18="","",AND(AX18,AY18,AW18>=Objective!$B$22)) | BA18: =IF($A18="","",IF(OR(LOWER($C18)="generated",LOWER($C18)="evaluated",LOWER($C18)="discarded"),TRUE,IF(OR(LOWER($C18)="proposed",LOWER($C18)="promoted"),AZ18,FALSE))) | BB18: =IF($A18="","",IF(AZ18,"proposed (eligible - present to human)","discarded (keep the record and the reason)"))
... AE44: =IF(OR($A44="",Objective!$A$5=""),"",IF(I44=0,IF(Q44=0,0,IF(Objective!$C$5="lower",-1,1)),IF(Objective!$C$5="lower",(I44-Q44)/ABS(I44),(Q44-I44)/ABS(I44)))) | AF44: =IF(OR($A44="",Objective!$A$6=""),"",IF(J44=0,IF(R44=0,0,IF(Objective!$C$6="lower",-1,1)),IF(Objective!$C$6="lower",(J44-R44)/ABS(J44),(R44-J44)/ABS(J44)))) | AG44: =IF(OR($A44="",Objective!$A$7=""),"",IF(K44=0,IF(S44=0,0,IF(Objective!$C$7="lower",-1,1)),IF(Objective!$C$7="lower",(K44-S44)/ABS(K44),(S44-K44)/ABS(K44)))) | AH44: =IF(OR($A44="",Objective!$A$8=""),"",IF(L44=0,IF(T44=0,0,IF(Objective!$C$8="lower",-1,1)),IF(Objective!$C$8="lower",(L44-T44)/ABS(L44),(T44-L44)/ABS(L44)))) | AI44: =IF(OR($A44="",Objective!$A$9=""),"",IF(M44=0,IF(U44=0,0,IF(Objective!$C$9="lower",-1,1)),IF(Objective!$C$9="lower",(M44-U44)/ABS(M44),(U44-M44)/ABS(M44)))) | AJ44: =IF(OR($A44="",Objective!$A$10=""),"",IF(N44=0,IF(V44=0,0,IF(Objective!$C$10="lower",-1,1)),IF(Objective!$C$10="lower",(N44-V44)/ABS(N44),(V44-N44)/ABS(N44)))) | AK44: =IF(OR($A44="",Objective!$A$11=""),"",IF(O44=0,IF(W44=0,0,IF(Objective!$C$11="lower",-1,1)),IF(Objective!$C$11="lower",(O44-W44)/ABS(O44),(W44-O44)/ABS(O44)))) | AL44: =IF(OR($A44="",Objective!$A$12=""),"",IF(P44=0,IF(X44=0,0,IF(Objective!$C$12="lower",-1,1)),IF(Objective!$C$12="lower",(P44-X44)/ABS(P44),(X44-P44)/ABS(P44)))) | AM44: =IF(AE44="","",MAX(-1,MIN(1,AE44))) | AN44: =IF(AF44="","",MAX(-1,MIN(1,AF44))) | AO44: =IF(AG44="","",MAX(-1,MIN(1,AG44))) | AP44: =IF(AH44="","",MAX(-1,MIN(1,AH44))) | AQ44: =IF(AI44="","",MAX(-1,MIN(1,AI44))) | AR44: =IF(AJ44="","",MAX(-1,MIN(1,AJ44))) | AS44: =IF(AK44="","",MAX(-1,MIN(1,AK44))) | AT44: =IF(AL44="","",MAX(-1,MIN(1,AL44))) | AU44: =IF($A44="","",IF(AM44="",0,Objective!$B$5/Objective!$B$25*AM44)+IF(AN44="",0,Objective!$B$6/Objective!$B$25*AN44)+IF(AO44="",0,Objective!$B$7/Objective!$B$25*AO44)+IF(AP44="",0,Objective!$B$8/Objective!$B$25*AP44)+IF(AQ44="",0,Objective!$B$9/Objective!$B$25*AQ44)+IF(AR44="",0,Objective!$B$10/Objective!$B$25*AR44)+IF(AS44="",0,Objective!$B$11/Objective!$B$25*AS44)+IF(AT44="",0,Objective!$B$12/Objective!$B$25*AT44)) | AV44: =IF($A44="","",Objective!$B$23*MAX(0,N($H44)-N($G44))) | AW44: =IF($A44="","",AU44-AV44) | AX44: =IF($A44="","",AND(OR(Objective!$A$15="",LOWER(Y44)="pass"),OR(Objective!$A$16="",LOWER(Z44)="pass"),OR(Objective!$A$17="",LOWER(AA44)="pass"),OR(Objective!$A$18="",LOWER(AB44)="pass"),OR(Objective!$A$19="",LOWER(AC44)="pass"),OR(Objective!$A$20="",LOWER(AD44)="pass"))) | AY44: =IF($A44="","",AND(OR(AE44="",Objective!$B$24="",AE44>=-Objective!$B$24),OR(AF44="",Objective!$B$24="",AF44>=-Objective!$B$24),OR(AG44="",Objective!$B$24="",AG44>=-Objective!$B$24),OR(AH44="",Objective!$B$24="",AH44>=-Objective!$B$24),OR(AI44="",Objective!$B$24="",AI44>=-Objective!$B$24),OR(AJ44="",Objective!$B$24="",AJ44>=-Objective!$B$24),OR(AK44="",Objective!$B$24="",AK44>=-Objective!$B$24),OR(AL44="",Objective!$B$24="",AL44>=-Objective!$B$24))) | AZ44: =IF($A44="","",AND(AX44,AY44,AW44>=Objective!$B$22)) | BA44: =IF($A44="","",IF(OR(LOWER($C44)="generated",LOWER($C44)="evaluated",LOWER($C44)="discarded"),TRUE,IF(OR(LOWER($C44)="proposed",LOWER($C44)="promoted"),AZ44,FALSE))) | BB44: =IF($A44="","",IF(AZ44,"proposed (eligible - present to human)","discarded (keep the record and the reason)"))

Sheet Promotion
A1: Promotion gate (promote_challenger) - the ONLY step that needs human approval
A4: epoch row number on Epochs sheet (5..44)
A5: registry challenger model_id
A6: registry challenger source_epoch
A7: current champion model_id (blank if none)
A8: approved_by (human name)
A9: approved_at (YYYY-MM-DD)
A11: epoch status is proposed | B11: =IF(B4="",FALSE,LOWER(INDEX(Epochs!C1:C44,B4))="proposed")
A12: recomputed promotion_eligible | B12: =IF(B4="",FALSE,INDEX(Epochs!AZ1:AZ44,B4)=TRUE)
A13: epoch challenger_id = registry challenger | B13: =IF(B4="",FALSE,INDEX(Epochs!F1:F44,B4)=B5)
A14: challenger source_epoch = epoch_id | B14: =IF(B4="",FALSE,INDEX(Epochs!A1:A44,B4)=B6)
A15: approved_by present | B15: =TRIM(B8&"")<>""
A17: PROMOTE? | B17: =IF(AND(B11,B12,B13,B14,B15),"PROMOTE","DO NOT PROMOTE")
A19: registry edits on PROMOTE (memory/models/model-versions.csv and promotions.csv):
A20: =IF(B17<>"PROMOTE","","1. set role of "&B5&" to champion")
A21: =IF(OR(B17<>"PROMOTE",B7=""),"","2. set role of "&B7&" to retired")
A22: =IF(B17<>"PROMOTE","","3. append promotions row: from_model="&B7&", to_model="&B5&", epoch_id="&B6&", approved_by="&B8&", approved_at="&B9)
A23: =IF(B17<>"PROMOTE","","4. set epoch "&B6&" status to promoted (explicit overwrite)")
