Workbook
Name fy_start: 'Setup'!$B$4
Name resid: 'Setup'!$B$5
Name h_months: 'ToKernel'!$B$4

Sheet README
A1: D17 · Capex & asset lifecycle management systems
A3: Domain D17: Capex & asset lifecycle management systems.
A4: Fixed asset register with Schedule II book depreciation and income-tax WDV depreciation, CWIP ageing, and a capex plan that sets K01 capex_monthly and da_monthly.
A5: How to use
A6: Copy this workbook into companies/<slug>/domains/D17_capex-asset-lifecycle/ before typing. Replace the SAMPLE rows (illustrative Tamil Nadu data) with company data.
A7: Type only into pale-yellow cells; white cells are formulas. Checks › OVERALL must be PASS before any value feeds K01/K02.
A8: Statutory rates are starting values - verify in 01_tamil-nadu/verification-register.md.
A9: Feeds
A10: K01 capex_monthly <= ToKernel
A11: K01 da_monthly <= ToKernel
A12: D24 deferred tax view <= timing difference

Sheet Checks
A1: Checks - OVERALL must be PASS before this domain feeds the kernel
B3: OVERALL | C3: =IF(COUNTIF(C5:C6,"PASS")=COUNT(A5:A6),"PASS","FAIL")
A4: # | B4: check | C4: result
A5: 1 | B5: useful lives positive | C5: =IF(SUMPRODUCT((Assets!A5:A504<>"")*(Assets!C5:C504<=0))=0,"PASS","FAIL")
A6: 2 | B6: asset ids unique | C6: =IF(SUMPRODUCT((Assets!A5:A504<>"")*(COUNTIF(Assets!A5:A504,Assets!A5:A504)>1))=0,"PASS","FAIL")

Sheet Setup
A1: Setup
A4: FY start (1 April) | B4: 46113
A5: residual value % (Schedule II default) | B5: 0.05

Sheet Assets
A1: Fixed asset register (Companies Act Schedule II SLM for books; Income-tax WDV block for tax)
A4: asset id | B4: description | C4: Schedule II useful life (years) | D4: tax block rate (WDV) | E4: cost | F4: put to use date | G4: location | H4: book depreciation / month (SLM) | I4: months used in this FY | J4: book depreciation this FY | K4: tax depreciation this FY (half rate if < 180 days) | L4: timing difference (tax - book) | M4: physically verified on
A5: PM-0001 | B5: CNC turning centre | C5: 15 | D5: 0.15 | E5: 6500000 | F5: 45818 | G5: Coimbatore | H5: =IF(A5="","",E5*(1-Setup!$B$5)/(C5*12)) | I5: =IF(A5="","",MAX(0,MIN(12,DATEDIF(MAX(F5,Setup!$B$4),EDATE(Setup!$B$4,12),"m")))) | J5: =IF(A5="","",H5*I5) | K5: =IF(A5="","",E5*D5*IF(AND(F5>=Setup!$B$4,EDATE(Setup!$B$4,12)-F5<180),0.5,1)) | L5: =IF(A5="","",K5-J5)
A6: IT-0042 | B6: Laptops (20) | C6: 3 | D6: 0.4 | E6: 1400000 | F6: 46346 | G6: Chennai | H6: =IF(A6="","",E6*(1-Setup!$B$5)/(C6*12)) | I6: =IF(A6="","",MAX(0,MIN(12,DATEDIF(MAX(F6,Setup!$B$4),EDATE(Setup!$B$4,12),"m")))) | J6: =IF(A6="","",H6*I6) | K6: =IF(A6="","",E6*D6*IF(AND(F6>=Setup!$B$4,EDATE(Setup!$B$4,12)-F6<180),0.5,1)) | L6: =IF(A6="","",K6-J6)
A7: BLD-0003 | B7: Factory building | C7: 30 | D7: 0.1 | E7: 42000000 | F7: 43556 | G7: Hosur | H7: =IF(A7="","",E7*(1-Setup!$B$5)/(C7*12)) | I7: =IF(A7="","",MAX(0,MIN(12,DATEDIF(MAX(F7,Setup!$B$4),EDATE(Setup!$B$4,12),"m")))) | J7: =IF(A7="","",H7*I7) | K7: =IF(A7="","",E7*D7*IF(AND(F7>=Setup!$B$4,EDATE(Setup!$B$4,12)-F7<180),0.5,1)) | L7: =IF(A7="","",K7-J7)
H8: =IF(A8="","",E8*(1-Setup!$B$5)/(C8*12)) | I8: =IF(A8="","",MAX(0,MIN(12,DATEDIF(MAX(F8,Setup!$B$4),EDATE(Setup!$B$4,12),"m")))) | J8: =IF(A8="","",H8*I8) | K8: =IF(A8="","",E8*D8*IF(AND(F8>=Setup!$B$4,EDATE(Setup!$B$4,12)-F8<180),0.5,1)) | L8: =IF(A8="","",K8-J8)
H9: =IF(A9="","",E9*(1-Setup!$B$5)/(C9*12)) | I9: =IF(A9="","",MAX(0,MIN(12,DATEDIF(MAX(F9,Setup!$B$4),EDATE(Setup!$B$4,12),"m")))) | J9: =IF(A9="","",H9*I9) | K9: =IF(A9="","",E9*D9*IF(AND(F9>=Setup!$B$4,EDATE(Setup!$B$4,12)-F9<180),0.5,1)) | L9: =IF(A9="","",K9-J9)
H10: =IF(A10="","",E10*(1-Setup!$B$5)/(C10*12)) | I10: =IF(A10="","",MAX(0,MIN(12,DATEDIF(MAX(F10,Setup!$B$4),EDATE(Setup!$B$4,12),"m")))) | J10: =IF(A10="","",H10*I10) | K10: =IF(A10="","",E10*D10*IF(AND(F10>=Setup!$B$4,EDATE(Setup!$B$4,12)-F10<180),0.5,1)) | L10: =IF(A10="","",K10-J10)
H11: =IF(A11="","",E11*(1-Setup!$B$5)/(C11*12)) | I11: =IF(A11="","",MAX(0,MIN(12,DATEDIF(MAX(F11,Setup!$B$4),EDATE(Setup!$B$4,12),"m")))) | J11: =IF(A11="","",H11*I11) | K11: =IF(A11="","",E11*D11*IF(AND(F11>=Setup!$B$4,EDATE(Setup!$B$4,12)-F11<180),0.5,1)) | L11: =IF(A11="","",K11-J11)
H12: =IF(A12="","",E12*(1-Setup!$B$5)/(C12*12)) | I12: =IF(A12="","",MAX(0,MIN(12,DATEDIF(MAX(F12,Setup!$B$4),EDATE(Setup!$B$4,12),"m")))) | J12: =IF(A12="","",H12*I12) | K12: =IF(A12="","",E12*D12*IF(AND(F12>=Setup!$B$4,EDATE(Setup!$B$4,12)-F12<180),0.5,1)) | L12: =IF(A12="","",K12-J12)
H13: =IF(A13="","",E13*(1-Setup!$B$5)/(C13*12)) | I13: =IF(A13="","",MAX(0,MIN(12,DATEDIF(MAX(F13,Setup!$B$4),EDATE(Setup!$B$4,12),"m")))) | J13: =IF(A13="","",H13*I13) | K13: =IF(A13="","",E13*D13*IF(AND(F13>=Setup!$B$4,EDATE(Setup!$B$4,12)-F13<180),0.5,1)) | L13: =IF(A13="","",K13-J13)
H14: =IF(A14="","",E14*(1-Setup!$B$5)/(C14*12)) | I14: =IF(A14="","",MAX(0,MIN(12,DATEDIF(MAX(F14,Setup!$B$4),EDATE(Setup!$B$4,12),"m")))) | J14: =IF(A14="","",H14*I14) | K14: =IF(A14="","",E14*D14*IF(AND(F14>=Setup!$B$4,EDATE(Setup!$B$4,12)-F14<180),0.5,1)) | L14: =IF(A14="","",K14-J14)
H15: =IF(A15="","",E15*(1-Setup!$B$5)/(C15*12)) | I15: =IF(A15="","",MAX(0,MIN(12,DATEDIF(MAX(F15,Setup!$B$4),EDATE(Setup!$B$4,12),"m")))) | J15: =IF(A15="","",H15*I15) | K15: =IF(A15="","",E15*D15*IF(AND(F15>=Setup!$B$4,EDATE(Setup!$B$4,12)-F15<180),0.5,1)) | L15: =IF(A15="","",K15-J15)
H16: =IF(A16="","",E16*(1-Setup!$B$5)/(C16*12)) | I16: =IF(A16="","",MAX(0,MIN(12,DATEDIF(MAX(F16,Setup!$B$4),EDATE(Setup!$B$4,12),"m")))) | J16: =IF(A16="","",H16*I16) | K16: =IF(A16="","",E16*D16*IF(AND(F16>=Setup!$B$4,EDATE(Setup!$B$4,12)-F16<180),0.5,1)) | L16: =IF(A16="","",K16-J16)
H17: =IF(A17="","",E17*(1-Setup!$B$5)/(C17*12)) | I17: =IF(A17="","",MAX(0,MIN(12,DATEDIF(MAX(F17,Setup!$B$4),EDATE(Setup!$B$4,12),"m")))) | J17: =IF(A17="","",H17*I17) | K17: =IF(A17="","",E17*D17*IF(AND(F17>=Setup!$B$4,EDATE(Setup!$B$4,12)-F17<180),0.5,1)) | L17: =IF(A17="","",K17-J17)
H18: =IF(A18="","",E18*(1-Setup!$B$5)/(C18*12)) | I18: =IF(A18="","",MAX(0,MIN(12,DATEDIF(MAX(F18,Setup!$B$4),EDATE(Setup!$B$4,12),"m")))) | J18: =IF(A18="","",H18*I18) | K18: =IF(A18="","",E18*D18*IF(AND(F18>=Setup!$B$4,EDATE(Setup!$B$4,12)-F18<180),0.5,1)) | L18: =IF(A18="","",K18-J18)
H19: =IF(A19="","",E19*(1-Setup!$B$5)/(C19*12)) | I19: =IF(A19="","",MAX(0,MIN(12,DATEDIF(MAX(F19,Setup!$B$4),EDATE(Setup!$B$4,12),"m")))) | J19: =IF(A19="","",H19*I19) | K19: =IF(A19="","",E19*D19*IF(AND(F19>=Setup!$B$4,EDATE(Setup!$B$4,12)-F19<180),0.5,1)) | L19: =IF(A19="","",K19-J19)
... H504: =IF(A504="","",E504*(1-Setup!$B$5)/(C504*12)) | I504: =IF(A504="","",MAX(0,MIN(12,DATEDIF(MAX(F504,Setup!$B$4),EDATE(Setup!$B$4,12),"m")))) | J504: =IF(A504="","",H504*I504) | K504: =IF(A504="","",E504*D504*IF(AND(F504>=Setup!$B$4,EDATE(Setup!$B$4,12)-F504<180),0.5,1)) | L504: =IF(A504="","",K504-J504)

Sheet CapexPlan
A1: Capex plan by K01 month (feeds capex_monthly = average, da_monthly = average)
A4: month no. | B4: capex | C4: new D&A per month from this capex
A5: 1 | B5: 2500000 | C5: 14000
A6: 4 | B6: 8000000 | C6: 45000

Sheet CWIP
A1: Capital work-in-progress ageing (Schedule III disclosure)
A4: project | B4: amount | C4: start date | D4: age years | E4: bucket
A5: Hosur EV line civil works | B5: 18000000 | C5: 45870 | D5: =IF(A5="","",(Setup!$B$4+365-C5)/365) | E5: =IF(A5="","",IF(D5<1,"< 1 year",IF(D5<2,"1-2 years",IF(D5<3,"2-3 years","> 3 years"))))
D6: =IF(A6="","",(Setup!$B$4+365-C6)/365) | E6: =IF(A6="","",IF(D6<1,"< 1 year",IF(D6<2,"1-2 years",IF(D6<3,"2-3 years","> 3 years"))))
D7: =IF(A7="","",(Setup!$B$4+365-C7)/365) | E7: =IF(A7="","",IF(D7<1,"< 1 year",IF(D7<2,"1-2 years",IF(D7<3,"2-3 years","> 3 years"))))
D8: =IF(A8="","",(Setup!$B$4+365-C8)/365) | E8: =IF(A8="","",IF(D8<1,"< 1 year",IF(D8<2,"1-2 years",IF(D8<3,"2-3 years","> 3 years"))))
D9: =IF(A9="","",(Setup!$B$4+365-C9)/365) | E9: =IF(A9="","",IF(D9<1,"< 1 year",IF(D9<2,"1-2 years",IF(D9<3,"2-3 years","> 3 years"))))
D10: =IF(A10="","",(Setup!$B$4+365-C10)/365) | E10: =IF(A10="","",IF(D10<1,"< 1 year",IF(D10<2,"1-2 years",IF(D10<3,"2-3 years","> 3 years"))))
D11: =IF(A11="","",(Setup!$B$4+365-C11)/365) | E11: =IF(A11="","",IF(D11<1,"< 1 year",IF(D11<2,"1-2 years",IF(D11<3,"2-3 years","> 3 years"))))
D12: =IF(A12="","",(Setup!$B$4+365-C12)/365) | E12: =IF(A12="","",IF(D12<1,"< 1 year",IF(D12<2,"1-2 years",IF(D12<3,"2-3 years","> 3 years"))))
D13: =IF(A13="","",(Setup!$B$4+365-C13)/365) | E13: =IF(A13="","",IF(D13<1,"< 1 year",IF(D13<2,"1-2 years",IF(D13<3,"2-3 years","> 3 years"))))
D14: =IF(A14="","",(Setup!$B$4+365-C14)/365) | E14: =IF(A14="","",IF(D14<1,"< 1 year",IF(D14<2,"1-2 years",IF(D14<3,"2-3 years","> 3 years"))))
D15: =IF(A15="","",(Setup!$B$4+365-C15)/365) | E15: =IF(A15="","",IF(D15<1,"< 1 year",IF(D15<2,"1-2 years",IF(D15<3,"2-3 years","> 3 years"))))
D16: =IF(A16="","",(Setup!$B$4+365-C16)/365) | E16: =IF(A16="","",IF(D16<1,"< 1 year",IF(D16<2,"1-2 years",IF(D16<3,"2-3 years","> 3 years"))))
D17: =IF(A17="","",(Setup!$B$4+365-C17)/365) | E17: =IF(A17="","",IF(D17<1,"< 1 year",IF(D17<2,"1-2 years",IF(D17<3,"2-3 years","> 3 years"))))
... D44: =IF(A44="","",(Setup!$B$4+365-C44)/365) | E44: =IF(A44="","",IF(D44<1,"< 1 year",IF(D44<2,"1-2 years",IF(D44<3,"2-3 years","> 3 years"))))

Sheet ToKernel
A1: Feeds K01
A4: capex_monthly (average over horizon months) | B4: 12
A5: capex_monthly -> K01 | B5: =SUM(CapexPlan!B5:B124)/ToKernel!$B$4
A6: existing book D&A per month | B6: =SUM(Assets!H5:H504)
A7: da_monthly -> K01 (existing + average new) | B7: =B6+SUMPRODUCT(CapexPlan!C5:C124*(ToKernel!$B$4-CapexPlan!A5:A124+1)*(CapexPlan!A5:A124<=ToKernel!$B$4))/ToKernel!$B$4
