Workbook
Name m_wacc: 'DCF'!$B$4
Name m_g: 'DCF'!$B$5
Name f1: 'DCF'!$B$6
Name f2: 'DCF'!$B$7
Name f3: 'DCF'!$B$8
Name f4: 'DCF'!$B$9
Name f5: 'DCF'!$B$10
Name ev_dcf: 'DCF'!$B$14
Name t_nd: 'DCF'!$B$15
Name t_ebitda: 'Multiples'!$B$5
Name a_ni: 'AccretionDilution'!$B$4
Name a_sh: 'AccretionDilution'!$B$5
Name t_ni: 'AccretionDilution'!$B$6
Name pp: 'AccretionDilution'!$B$7
Name pct_sh: 'AccretionDilution'!$B$8
Name a_px: 'AccretionDilution'!$B$9
Name c_debt: 'AccretionDilution'!$B$10
Name a_tax: 'AccretionDilution'!$B$11
Name syn: 'AccretionDilution'!$B$12

Sheet README
A1: D21 · M&A systems
A3: Domain D21: M&A systems.
A4: Target valuation (DCF from a K01 copy of the target, trading/transaction multiples), accretion/dilution, and divestiture via K08.
A5: How to use
A6: Copy this workbook into companies/<slug>/domains/D21_mergers-acquisitions/ before typing. Replace the SAMPLE rows (illustrative Tamil Nadu data) with company data.
A7: Type only into pale-yellow cells; white cells are formulas. Checks › OVERALL must be PASS before any value feeds K01/K02.
A8: Statutory rates are starting values - verify in 01_tamil-nadu/verification-register.md.
A9: Feeds
A10: K01 copy of target <= FCF
A11: K08 divestiture <= carve-outs
A12: D22 cap table <= share-funded deals

Sheet Checks
A1: Checks - OVERALL must be PASS before this domain feeds the kernel
B3: OVERALL | C3: =IF(COUNTIF(C5:C5,"PASS")=COUNT(A5:A5),"PASS","FAIL")
A4: # | B4: check | C4: result
A5: 1 | B5: WACC above terminal growth | C5: =IF(DCF!$B$4>DCF!$B$5,"PASS","FAIL")

Sheet DCF
A1: Target DCF (₹) - use K01 copy of the target for FCF
A4: WACC | B4: 0.13
A5: terminal growth | B5: 0.05
A6: FCF Y1
A7: FCF Y2
A8: FCF Y3
A9: FCF Y4
A10: FCF Y5
A11: PV of explicit FCF | B11: =NPV(DCF!$B$4,DCF!$B$6,DCF!$B$7,DCF!$B$8,DCF!$B$9,DCF!$B$10)
A12: terminal value (Gordon) | B12: =IF(DCF!$B$4<=DCF!$B$5,"",DCF!$B$10*(1+DCF!$B$5)/(DCF!$B$4-DCF!$B$5))
A13: PV of terminal value | B13: =IF(B12="","",B12/(1+DCF!$B$4)^5)
A14: enterprise value (DCF) | B14: =IF(B13="","",B11+B13)
A15: net debt of target
A16: equity value (DCF) | B16: =IF(DCF!$B$14="","",DCF!$B$14-DCF!$B$15)

Sheet Comps
A1: Trading / transaction comparables
A4: company | B4: EV | C4: EBITDA | D4: EV/EBITDA
D5: =IF(OR(A5="",N(C5)=0),"",B5/C5)
D6: =IF(OR(A6="",N(C6)=0),"",B6/C6)
D7: =IF(OR(A7="",N(C7)=0),"",B7/C7)
D8: =IF(OR(A8="",N(C8)=0),"",B8/C8)
D9: =IF(OR(A9="",N(C9)=0),"",B9/C9)
D10: =IF(OR(A10="",N(C10)=0),"",B10/C10)
D11: =IF(OR(A11="",N(C11)=0),"",B11/C11)
D12: =IF(OR(A12="",N(C12)=0),"",B12/C12)
D13: =IF(OR(A13="",N(C13)=0),"",B13/C13)
D14: =IF(OR(A14="",N(C14)=0),"",B14/C14)
D15: =IF(OR(A15="",N(C15)=0),"",B15/C15)
D16: =IF(OR(A16="",N(C16)=0),"",B16/C16)
... D34: =IF(OR(A34="",N(C34)=0),"",B34/C34)

Sheet Multiples
A1: Multiples valuation
A4: median EV/EBITDA of comps | B4: =IFERROR(MEDIAN(Comps!D5:D34),"")
A5: target EBITDA (TTM)
A6: EV (multiples) | B6: =IF(B4="","",B4*Multiples!$B$5)

Sheet AccretionDilution
A1: Accretion / dilution (year 1)
A4: acquirer net income
A5: acquirer shares outstanding
A6: target net income
A7: purchase price (equity)
A8: % paid in new shares | B8: 0
A9: acquirer share price
A10: pre-tax cost of new debt / lost interest on cash | B10: 0.09
A11: tax rate | B11: 0.2517
A12: after-tax synergies year 1 | B12: 0
A13: new shares issued | B13: =IF(OR(N(AccretionDilution!$B$9)=0,N(AccretionDilution!$B$7)=0),0,AccretionDilution!$B$7*AccretionDilution!$B$8/AccretionDilution!$B$9)
A14: after-tax financing cost | B14: =AccretionDilution!$B$7*(1-AccretionDilution!$B$8)*AccretionDilution!$B$10*(1-AccretionDilution!$B$11)
A15: pro-forma EPS | B15: =IF(N(AccretionDilution!$B$5)=0,"",(AccretionDilution!$B$4+AccretionDilution!$B$6+AccretionDilution!$B$12-B14)/(AccretionDilution!$B$5+B13))
A16: standalone EPS | B16: =IF(N(AccretionDilution!$B$5)=0,"",AccretionDilution!$B$4/AccretionDilution!$B$5)
A17: accretion / (dilution) % | B17: =IF(OR(B15="",N(B16)=0),"",B15/B16-1)
