Workbook
Name rev_cr: 'BRSR'!$B$6

Sheet README
A1: D23 · ESG & sustainability accounting / green finance platforms
A3: Domain D23: ESG & sustainability accounting / green finance platforms.
A4: Scope 1/2 GHG inventory from activity data and dated emission factors, intensity per ₹ crore, BRSR KPIs, and green-finance use of proceeds.
A5: How to use
A6: Copy this workbook into companies/<slug>/domains/D23_esg-sustainability-green-finance/ before typing. Replace the SAMPLE rows (illustrative Tamil Nadu data) with company data.
A7: Type only into pale-yellow cells; white cells are formulas. Checks › OVERALL must be PASS before any value feeds K01/K02.
A8: Statutory rates are starting values - verify in 01_tamil-nadu/verification-register.md.
A9: Feeds
A10: K01 opex (energy costs) <= Activity
A11: D09 projects (solar/efficiency) <= GreenFinance
A12: D19 BRSR disclosures <= BRSR

Sheet Checks
A1: Checks - OVERALL must be PASS before this domain feeds the kernel
B3: OVERALL | C3: =IF(COUNTIF(C5:C6,"PASS")=COUNT(A5:A6),"PASS","FAIL")
A4: # | B4: check | C4: result
A5: 1 | B5: every activity matches a factor | C5: =IF(COUNTIF(Activity!F5:F1004,"UNMATCHED")=0,"PASS","FAIL")
A6: 2 | B6: every factor has a source | C6: =IF(SUMPRODUCT((Factors!A5:A34<>"")*(Factors!E5:E34=""))=0,"PASS","FAIL")

Sheet Factors
A1: Emission factors (edit with source + year; never undated)
A4: activity | B4: unit | C4: kgCO2e per unit | D4: scope | E4: source & year
A5: Grid electricity (India) | B5: kWh | C5: 0.71 | D5: 2 | E5: CEA CO2 Baseline Database (verify latest version)
A6: Diesel (DG sets, vehicles) | B6: litre | C6: 2.68 | D6: 1 | E6: IPCC 2006 / GHG Protocol
A7: LPG | B7: kg | C7: 2.98 | D7: 1 | E7: IPCC 2006
A8: Rooftop solar / green open access | B8: kWh | C8: 0 | D8: 2 | E8: market-based, with RECs / green tariff evidence
A9: Petrol | B9: litre | C9: 2.31 | D9: 1 | E9: IPCC 2006
A10: Furnace oil | B10: litre | C10: 3.1 | D10: 1 | E10: IPCC 2006 (verify density)

Sheet Activity
A1: Activity data by site and month
A4: site | B4: month | C4: activity (must match Factors) | D4: quantity | E4: kgCO2e | F4: scope
A5: Coimbatore plant | B5: 2026-04 | C5: Grid electricity (India) | D5: 410000 | E5: =IF(A5="","",D5*IFERROR(INDEX(Factors!$C$5:$C$34,MATCH(C5,Factors!$A$5:$A$34,0)),0)) | F5: =IF(A5="","",IFERROR(INDEX(Factors!$D$5:$D$34,MATCH(C5,Factors!$A$5:$A$34,0)),"UNMATCHED"))
A6: Coimbatore plant | B6: 2026-04 | C6: Rooftop solar / green open access | D6: 120000 | E6: =IF(A6="","",D6*IFERROR(INDEX(Factors!$C$5:$C$34,MATCH(C6,Factors!$A$5:$A$34,0)),0)) | F6: =IF(A6="","",IFERROR(INDEX(Factors!$D$5:$D$34,MATCH(C6,Factors!$A$5:$A$34,0)),"UNMATCHED"))
A7: Coimbatore plant | B7: 2026-04 | C7: Diesel (DG sets, vehicles) | D7: 3800 | E7: =IF(A7="","",D7*IFERROR(INDEX(Factors!$C$5:$C$34,MATCH(C7,Factors!$A$5:$A$34,0)),0)) | F7: =IF(A7="","",IFERROR(INDEX(Factors!$D$5:$D$34,MATCH(C7,Factors!$A$5:$A$34,0)),"UNMATCHED"))
E8: =IF(A8="","",D8*IFERROR(INDEX(Factors!$C$5:$C$34,MATCH(C8,Factors!$A$5:$A$34,0)),0)) | F8: =IF(A8="","",IFERROR(INDEX(Factors!$D$5:$D$34,MATCH(C8,Factors!$A$5:$A$34,0)),"UNMATCHED"))
E9: =IF(A9="","",D9*IFERROR(INDEX(Factors!$C$5:$C$34,MATCH(C9,Factors!$A$5:$A$34,0)),0)) | F9: =IF(A9="","",IFERROR(INDEX(Factors!$D$5:$D$34,MATCH(C9,Factors!$A$5:$A$34,0)),"UNMATCHED"))
E10: =IF(A10="","",D10*IFERROR(INDEX(Factors!$C$5:$C$34,MATCH(C10,Factors!$A$5:$A$34,0)),0)) | F10: =IF(A10="","",IFERROR(INDEX(Factors!$D$5:$D$34,MATCH(C10,Factors!$A$5:$A$34,0)),"UNMATCHED"))
E11: =IF(A11="","",D11*IFERROR(INDEX(Factors!$C$5:$C$34,MATCH(C11,Factors!$A$5:$A$34,0)),0)) | F11: =IF(A11="","",IFERROR(INDEX(Factors!$D$5:$D$34,MATCH(C11,Factors!$A$5:$A$34,0)),"UNMATCHED"))
E12: =IF(A12="","",D12*IFERROR(INDEX(Factors!$C$5:$C$34,MATCH(C12,Factors!$A$5:$A$34,0)),0)) | F12: =IF(A12="","",IFERROR(INDEX(Factors!$D$5:$D$34,MATCH(C12,Factors!$A$5:$A$34,0)),"UNMATCHED"))
E13: =IF(A13="","",D13*IFERROR(INDEX(Factors!$C$5:$C$34,MATCH(C13,Factors!$A$5:$A$34,0)),0)) | F13: =IF(A13="","",IFERROR(INDEX(Factors!$D$5:$D$34,MATCH(C13,Factors!$A$5:$A$34,0)),"UNMATCHED"))
E14: =IF(A14="","",D14*IFERROR(INDEX(Factors!$C$5:$C$34,MATCH(C14,Factors!$A$5:$A$34,0)),0)) | F14: =IF(A14="","",IFERROR(INDEX(Factors!$D$5:$D$34,MATCH(C14,Factors!$A$5:$A$34,0)),"UNMATCHED"))
E15: =IF(A15="","",D15*IFERROR(INDEX(Factors!$C$5:$C$34,MATCH(C15,Factors!$A$5:$A$34,0)),0)) | F15: =IF(A15="","",IFERROR(INDEX(Factors!$D$5:$D$34,MATCH(C15,Factors!$A$5:$A$34,0)),"UNMATCHED"))
E16: =IF(A16="","",D16*IFERROR(INDEX(Factors!$C$5:$C$34,MATCH(C16,Factors!$A$5:$A$34,0)),0)) | F16: =IF(A16="","",IFERROR(INDEX(Factors!$D$5:$D$34,MATCH(C16,Factors!$A$5:$A$34,0)),"UNMATCHED"))
E17: =IF(A17="","",D17*IFERROR(INDEX(Factors!$C$5:$C$34,MATCH(C17,Factors!$A$5:$A$34,0)),0)) | F17: =IF(A17="","",IFERROR(INDEX(Factors!$D$5:$D$34,MATCH(C17,Factors!$A$5:$A$34,0)),"UNMATCHED"))
E18: =IF(A18="","",D18*IFERROR(INDEX(Factors!$C$5:$C$34,MATCH(C18,Factors!$A$5:$A$34,0)),0)) | F18: =IF(A18="","",IFERROR(INDEX(Factors!$D$5:$D$34,MATCH(C18,Factors!$A$5:$A$34,0)),"UNMATCHED"))
E19: =IF(A19="","",D19*IFERROR(INDEX(Factors!$C$5:$C$34,MATCH(C19,Factors!$A$5:$A$34,0)),0)) | F19: =IF(A19="","",IFERROR(INDEX(Factors!$D$5:$D$34,MATCH(C19,Factors!$A$5:$A$34,0)),"UNMATCHED"))
... E1004: =IF(A1004="","",D1004*IFERROR(INDEX(Factors!$C$5:$C$34,MATCH(C1004,Factors!$A$5:$A$34,0)),0)) | F1004: =IF(A1004="","",IFERROR(INDEX(Factors!$D$5:$D$34,MATCH(C1004,Factors!$A$5:$A$34,0)),"UNMATCHED"))

Sheet BRSR
A1: BRSR / sustainability KPIs
A4: Scope 1 tCO2e | B4: =SUMIF(Activity!F5:F1004,1,Activity!E5:E1004)/1000
A5: Scope 2 tCO2e (location/market per factor table) | B5: =SUMIF(Activity!F5:F1004,2,Activity!E5:E1004)/1000
A6: revenue (₹ crore) for intensity
A7: Scope 1+2 intensity (tCO2e per ₹ crore) | B7: =IF(N(BRSR!$B$6)=0,"",(B4+B5)/BRSR!$B$6)
A8: renewable share of electricity | B8: =IFERROR(SUMIF(Activity!C5:C1004,"Rooftop solar / green open access",Activity!D5:D1004)/(SUMIF(Activity!C5:C1004,"Rooftop solar / green open access",Activity!D5:D1004)+SUMIF(Activity!C5:C1004,"Grid electricity (India)",Activity!D5:D1004)),"")
A9: water withdrawal (kL)
A10: hazardous waste (t) - TNPCB authorisation

Sheet GreenFinance
A1: Green / sustainability-linked finance use-of-proceeds
A4: instrument | B4: lender / investor | C4: amount | D4: eligible project (D09 id) | E4: allocated to date | F4: unallocated | G4: KPI / SPT
A5: Green term loan | B5: SIDBI / bank | C5: 90000000 | D5: Rooftop solar 2 MW (Coimbatore) | E5: 60000000 | F5: =IF(A5="","",C5-E5) | G5: renewable share >= 40%
F6: =IF(A6="","",C6-E6)
F7: =IF(A7="","",C7-E7)
F8: =IF(A8="","",C8-E8)
F9: =IF(A9="","",C9-E9)
F10: =IF(A10="","",C10-E10)
F11: =IF(A11="","",C11-E11)
F12: =IF(A12="","",C12-E12)
F13: =IF(A13="","",C13-E13)
F14: =IF(A14="","",C14-E14)
F15: =IF(A15="","",C15-E15)
F16: =IF(A16="","",C16-E16)
F17: =IF(A17="","",C17-E17)
... F34: =IF(A34="","",C34-E34)
