Workbook
Name pvm_diff: 'Bridge'!$B$9

Sheet README
A1: D13 · Revenue operations & pricing optimisation
A3: Domain D13: Revenue operations & pricing optimisation.
A4: Explain revenue with a price–volume–mix bridge and see true pocket price after GST, dealer discounts, schemes, marketplace commission and freight.
A5: How to use
A6: Copy this workbook into companies/<slug>/domains/D13_revenue-operations-pricing/ before typing. Replace the SAMPLE rows (illustrative Tamil Nadu data) with company data.
A7: Type only into pale-yellow cells; white cells are formulas. Checks › OVERALL must be PASS before any value feeds K01/K02.
A8: Statutory rates are starting values - verify in 01_tamil-nadu/verification-register.md.
A9: Feeds
A10: K01 channels growth_rate / cogs_pct <= PVM trends
A11: W04 variance drivers <= volume / price / mix
A12: K06 SKU economics <= pocket price

Sheet Checks
A1: Checks - OVERALL must be PASS before this domain feeds the kernel
B3: OVERALL | C3: =IF(COUNTIF(C5:C5,"PASS")=COUNT(A5:A5),"PASS","FAIL")
A4: # | B4: check | C4: result
A5: 1 | B5: bridge reconciles to current revenue | C5: =IF(ABS(Bridge!$B$9)<1,"PASS","FAIL")

Sheet PVM
A1: Price-volume-mix bridge (prior period vs current, per product)
A4: product | B4: prior units | C4: prior net price | D4: current units | E4: current net price | F4: prior revenue | G4: current revenue | H4: volume effect (at prior mix & price) | I4: mix effect | J4: price effect
A5: Office chair - mesh | B5: 12000 | C5: 6200 | D5: 13500 | E5: 6400 | F5: =IF(A5="","",B5*C5) | G5: =IF(A5="","",D5*E5) | H5: =IF(A5="","",(SUM($D$5:$D$104)-SUM($B$5:$B$104))*IF(SUM($B$5:$B$104)=0,0,B5/SUM($B$5:$B$104))*C5) | I5: =IF(A5="","",(D5-SUM($D$5:$D$104)*IF(SUM($B$5:$B$104)=0,0,B5/SUM($B$5:$B$104)))*C5) | J5: =IF(A5="","",(E5-C5)*D5)
A6: Plastic chair (bulk) | B6: 90000 | C6: 420 | D6: 82000 | E6: 445 | F6: =IF(A6="","",B6*C6) | G6: =IF(A6="","",D6*E6) | H6: =IF(A6="","",(SUM($D$5:$D$104)-SUM($B$5:$B$104))*IF(SUM($B$5:$B$104)=0,0,B6/SUM($B$5:$B$104))*C6) | I6: =IF(A6="","",(D6-SUM($D$5:$D$104)*IF(SUM($B$5:$B$104)=0,0,B6/SUM($B$5:$B$104)))*C6) | J6: =IF(A6="","",(E6-C6)*D6)
A7: Recliner | B7: 2500 | C7: 18500 | D7: 2900 | E7: 18200 | F7: =IF(A7="","",B7*C7) | G7: =IF(A7="","",D7*E7) | H7: =IF(A7="","",(SUM($D$5:$D$104)-SUM($B$5:$B$104))*IF(SUM($B$5:$B$104)=0,0,B7/SUM($B$5:$B$104))*C7) | I7: =IF(A7="","",(D7-SUM($D$5:$D$104)*IF(SUM($B$5:$B$104)=0,0,B7/SUM($B$5:$B$104)))*C7) | J7: =IF(A7="","",(E7-C7)*D7)
F8: =IF(A8="","",B8*C8) | G8: =IF(A8="","",D8*E8) | H8: =IF(A8="","",(SUM($D$5:$D$104)-SUM($B$5:$B$104))*IF(SUM($B$5:$B$104)=0,0,B8/SUM($B$5:$B$104))*C8) | I8: =IF(A8="","",(D8-SUM($D$5:$D$104)*IF(SUM($B$5:$B$104)=0,0,B8/SUM($B$5:$B$104)))*C8) | J8: =IF(A8="","",(E8-C8)*D8)
F9: =IF(A9="","",B9*C9) | G9: =IF(A9="","",D9*E9) | H9: =IF(A9="","",(SUM($D$5:$D$104)-SUM($B$5:$B$104))*IF(SUM($B$5:$B$104)=0,0,B9/SUM($B$5:$B$104))*C9) | I9: =IF(A9="","",(D9-SUM($D$5:$D$104)*IF(SUM($B$5:$B$104)=0,0,B9/SUM($B$5:$B$104)))*C9) | J9: =IF(A9="","",(E9-C9)*D9)
F10: =IF(A10="","",B10*C10) | G10: =IF(A10="","",D10*E10) | H10: =IF(A10="","",(SUM($D$5:$D$104)-SUM($B$5:$B$104))*IF(SUM($B$5:$B$104)=0,0,B10/SUM($B$5:$B$104))*C10) | I10: =IF(A10="","",(D10-SUM($D$5:$D$104)*IF(SUM($B$5:$B$104)=0,0,B10/SUM($B$5:$B$104)))*C10) | J10: =IF(A10="","",(E10-C10)*D10)
F11: =IF(A11="","",B11*C11) | G11: =IF(A11="","",D11*E11) | H11: =IF(A11="","",(SUM($D$5:$D$104)-SUM($B$5:$B$104))*IF(SUM($B$5:$B$104)=0,0,B11/SUM($B$5:$B$104))*C11) | I11: =IF(A11="","",(D11-SUM($D$5:$D$104)*IF(SUM($B$5:$B$104)=0,0,B11/SUM($B$5:$B$104)))*C11) | J11: =IF(A11="","",(E11-C11)*D11)
F12: =IF(A12="","",B12*C12) | G12: =IF(A12="","",D12*E12) | H12: =IF(A12="","",(SUM($D$5:$D$104)-SUM($B$5:$B$104))*IF(SUM($B$5:$B$104)=0,0,B12/SUM($B$5:$B$104))*C12) | I12: =IF(A12="","",(D12-SUM($D$5:$D$104)*IF(SUM($B$5:$B$104)=0,0,B12/SUM($B$5:$B$104)))*C12) | J12: =IF(A12="","",(E12-C12)*D12)
F13: =IF(A13="","",B13*C13) | G13: =IF(A13="","",D13*E13) | H13: =IF(A13="","",(SUM($D$5:$D$104)-SUM($B$5:$B$104))*IF(SUM($B$5:$B$104)=0,0,B13/SUM($B$5:$B$104))*C13) | I13: =IF(A13="","",(D13-SUM($D$5:$D$104)*IF(SUM($B$5:$B$104)=0,0,B13/SUM($B$5:$B$104)))*C13) | J13: =IF(A13="","",(E13-C13)*D13)
F14: =IF(A14="","",B14*C14) | G14: =IF(A14="","",D14*E14) | H14: =IF(A14="","",(SUM($D$5:$D$104)-SUM($B$5:$B$104))*IF(SUM($B$5:$B$104)=0,0,B14/SUM($B$5:$B$104))*C14) | I14: =IF(A14="","",(D14-SUM($D$5:$D$104)*IF(SUM($B$5:$B$104)=0,0,B14/SUM($B$5:$B$104)))*C14) | J14: =IF(A14="","",(E14-C14)*D14)
F15: =IF(A15="","",B15*C15) | G15: =IF(A15="","",D15*E15) | H15: =IF(A15="","",(SUM($D$5:$D$104)-SUM($B$5:$B$104))*IF(SUM($B$5:$B$104)=0,0,B15/SUM($B$5:$B$104))*C15) | I15: =IF(A15="","",(D15-SUM($D$5:$D$104)*IF(SUM($B$5:$B$104)=0,0,B15/SUM($B$5:$B$104)))*C15) | J15: =IF(A15="","",(E15-C15)*D15)
F16: =IF(A16="","",B16*C16) | G16: =IF(A16="","",D16*E16) | H16: =IF(A16="","",(SUM($D$5:$D$104)-SUM($B$5:$B$104))*IF(SUM($B$5:$B$104)=0,0,B16/SUM($B$5:$B$104))*C16) | I16: =IF(A16="","",(D16-SUM($D$5:$D$104)*IF(SUM($B$5:$B$104)=0,0,B16/SUM($B$5:$B$104)))*C16) | J16: =IF(A16="","",(E16-C16)*D16)
F17: =IF(A17="","",B17*C17) | G17: =IF(A17="","",D17*E17) | H17: =IF(A17="","",(SUM($D$5:$D$104)-SUM($B$5:$B$104))*IF(SUM($B$5:$B$104)=0,0,B17/SUM($B$5:$B$104))*C17) | I17: =IF(A17="","",(D17-SUM($D$5:$D$104)*IF(SUM($B$5:$B$104)=0,0,B17/SUM($B$5:$B$104)))*C17) | J17: =IF(A17="","",(E17-C17)*D17)
F18: =IF(A18="","",B18*C18) | G18: =IF(A18="","",D18*E18) | H18: =IF(A18="","",(SUM($D$5:$D$104)-SUM($B$5:$B$104))*IF(SUM($B$5:$B$104)=0,0,B18/SUM($B$5:$B$104))*C18) | I18: =IF(A18="","",(D18-SUM($D$5:$D$104)*IF(SUM($B$5:$B$104)=0,0,B18/SUM($B$5:$B$104)))*C18) | J18: =IF(A18="","",(E18-C18)*D18)
F19: =IF(A19="","",B19*C19) | G19: =IF(A19="","",D19*E19) | H19: =IF(A19="","",(SUM($D$5:$D$104)-SUM($B$5:$B$104))*IF(SUM($B$5:$B$104)=0,0,B19/SUM($B$5:$B$104))*C19) | I19: =IF(A19="","",(D19-SUM($D$5:$D$104)*IF(SUM($B$5:$B$104)=0,0,B19/SUM($B$5:$B$104)))*C19) | J19: =IF(A19="","",(E19-C19)*D19)
... F104: =IF(A104="","",B104*C104) | G104: =IF(A104="","",D104*E104) | H104: =IF(A104="","",(SUM($D$5:$D$104)-SUM($B$5:$B$104))*IF(SUM($B$5:$B$104)=0,0,B104/SUM($B$5:$B$104))*C104) | I104: =IF(A104="","",(D104-SUM($D$5:$D$104)*IF(SUM($B$5:$B$104)=0,0,B104/SUM($B$5:$B$104)))*C104) | J104: =IF(A104="","",(E104-C104)*D104)

Sheet Bridge
A1: Revenue bridge
A4: prior revenue | B4: =SUM(PVM!F5:F104)
A5: + volume | B5: =SUM(PVM!H5:H104)
A6: + mix | B6: =SUM(PVM!I5:I104)
A7: + price | B7: =SUM(PVM!J5:J104)
A8: current revenue (sum of bridge) | B8: =B4+B5+B6+B7
A9: check vs actual current revenue | B9: =ROUND(B8-SUM(PVM!G5:G104),2)

Sheet Waterfall
A1: Price waterfall (MRP is GST-inclusive under Legal Metrology rules)
A4: SKU | B4: MRP incl. GST | C4: GST rate | D4: trade / dealer discount % | E4: scheme / cash discount % | F4: marketplace commission % (if e-commerce) | G4: freight per unit | H4: price excl. GST | I4: invoice price to dealer | J4: pocket price | K4: pocket as % of ex-GST MRP
A5: CH-MESH-01 | B5: 7499 | C5: 0.18 | D5: 0.22 | E5: 0.02 | F5: 0 | G5: 180 | H5: =IF(A5="","",B5/(1+C5)) | I5: =IF(A5="","",H5*(1-D5)) | J5: =IF(A5="","",I5*(1-E5)*(1-F5)-N(G5)) | K5: =IF(OR(A5="",N(H5)=0),"",J5/H5)
H6: =IF(A6="","",B6/(1+C6)) | I6: =IF(A6="","",H6*(1-D6)) | J6: =IF(A6="","",I6*(1-E6)*(1-F6)-N(G6)) | K6: =IF(OR(A6="",N(H6)=0),"",J6/H6)
H7: =IF(A7="","",B7/(1+C7)) | I7: =IF(A7="","",H7*(1-D7)) | J7: =IF(A7="","",I7*(1-E7)*(1-F7)-N(G7)) | K7: =IF(OR(A7="",N(H7)=0),"",J7/H7)
H8: =IF(A8="","",B8/(1+C8)) | I8: =IF(A8="","",H8*(1-D8)) | J8: =IF(A8="","",I8*(1-E8)*(1-F8)-N(G8)) | K8: =IF(OR(A8="",N(H8)=0),"",J8/H8)
H9: =IF(A9="","",B9/(1+C9)) | I9: =IF(A9="","",H9*(1-D9)) | J9: =IF(A9="","",I9*(1-E9)*(1-F9)-N(G9)) | K9: =IF(OR(A9="",N(H9)=0),"",J9/H9)
H10: =IF(A10="","",B10/(1+C10)) | I10: =IF(A10="","",H10*(1-D10)) | J10: =IF(A10="","",I10*(1-E10)*(1-F10)-N(G10)) | K10: =IF(OR(A10="",N(H10)=0),"",J10/H10)
H11: =IF(A11="","",B11/(1+C11)) | I11: =IF(A11="","",H11*(1-D11)) | J11: =IF(A11="","",I11*(1-E11)*(1-F11)-N(G11)) | K11: =IF(OR(A11="",N(H11)=0),"",J11/H11)
H12: =IF(A12="","",B12/(1+C12)) | I12: =IF(A12="","",H12*(1-D12)) | J12: =IF(A12="","",I12*(1-E12)*(1-F12)-N(G12)) | K12: =IF(OR(A12="",N(H12)=0),"",J12/H12)
H13: =IF(A13="","",B13/(1+C13)) | I13: =IF(A13="","",H13*(1-D13)) | J13: =IF(A13="","",I13*(1-E13)*(1-F13)-N(G13)) | K13: =IF(OR(A13="",N(H13)=0),"",J13/H13)
H14: =IF(A14="","",B14/(1+C14)) | I14: =IF(A14="","",H14*(1-D14)) | J14: =IF(A14="","",I14*(1-E14)*(1-F14)-N(G14)) | K14: =IF(OR(A14="",N(H14)=0),"",J14/H14)
H15: =IF(A15="","",B15/(1+C15)) | I15: =IF(A15="","",H15*(1-D15)) | J15: =IF(A15="","",I15*(1-E15)*(1-F15)-N(G15)) | K15: =IF(OR(A15="",N(H15)=0),"",J15/H15)
H16: =IF(A16="","",B16/(1+C16)) | I16: =IF(A16="","",H16*(1-D16)) | J16: =IF(A16="","",I16*(1-E16)*(1-F16)-N(G16)) | K16: =IF(OR(A16="",N(H16)=0),"",J16/H16)
H17: =IF(A17="","",B17/(1+C17)) | I17: =IF(A17="","",H17*(1-D17)) | J17: =IF(A17="","",I17*(1-E17)*(1-F17)-N(G17)) | K17: =IF(OR(A17="",N(H17)=0),"",J17/H17)
... H104: =IF(A104="","",B104/(1+C104)) | I104: =IF(A104="","",H104*(1-D104)) | J104: =IF(A104="","",I104*(1-E104)*(1-F104)-N(G104)) | K104: =IF(OR(A104="",N(H104)=0),"",J104/H104)
