Workbook
Name K02start: 'Setup'!$B$4

Sheet README
A1: D07 · Customer relationship management systems
A3: Domain D07: Customer relationship management systems.
A4: Use pipeline and invoice data to sanity-check K01 revenue and to schedule K02 collections by week; derive DSO evidence.
A5: How to use
A6: Copy this workbook into companies/<slug>/domains/D07_crm-customer-relationship/ before typing. Replace the SAMPLE rows (illustrative Tamil Nadu data) with company data.
A7: Type only into pale-yellow cells; white cells are formulas. Checks › OVERALL must be PASS before any value feeds K01/K02.
A8: Statutory rates are starting values - verify in 01_tamil-nadu/verification-register.md.
A9: Feeds
A10: K01 channels revenue (sanity check) <= WeightedByMonth
A11: K02 receipts by week <= Collections K02 week
A12: K01 working_capital.dso_days <= collection history

Sheet Checks
A1: Checks - OVERALL must be PASS before this domain feeds the kernel
B3: OVERALL | C3: =IF(COUNTIF(C5:C5,"PASS")=COUNT(A5:A5),"PASS","FAIL")
A4: # | B4: check | C4: result
A5: 1 | B5: every pipeline stage exists in the stage table | C5: =IF(SUMPRODUCT((Pipeline!A5:A504<>"")*(COUNTIF(Stages!A5:A12,Pipeline!D5:D504)=0))=0,"PASS","FAIL")

Sheet Stages
A1: Stage probabilities (calibrate quarterly from won/lost history)
A4: stage | B4: probability
A5: Lead | B5: 0.05
A6: Qualified | B6: 0.15
A7: Quotation sent | B7: 0.35
A8: Negotiation | B8: 0.6
A9: PO received | B9: 0.9
A10: Won (invoiced) | B10: 1
A11: Lost | B11: 0

Sheet Pipeline
A1: Opportunities (export from Zoho CRM / Freshsales / Salesforce / dealer register)
A4: opportunity | B4: customer | C4: channel (K01 channel name) | D4: stage | E4: amount excl. GST | F4: expected invoice month no. (1 = K01 month 1) | G4: probability | H4: weighted amount
A5: OPP-101 | B5: Chennai Metro Rail vendor | C5: Institutional | D5: Negotiation | E5: 12000000 | F5: 2 | G5: =IF(A5="","",IFERROR(INDEX(Stages!$B$5:$B$12,MATCH(D5,Stages!$A$5:$A$12,0)),0)) | H5: =IF(A5="","",E5*G5)
A6: OPP-102 | B6: Coimbatore dealer cluster | C6: Dealer network | D6: PO received | E6: 8500000 | F6: 1 | G6: =IF(A6="","",IFERROR(INDEX(Stages!$B$5:$B$12,MATCH(D6,Stages!$A$5:$A$12,0)),0)) | H6: =IF(A6="","",E6*G6)
G7: =IF(A7="","",IFERROR(INDEX(Stages!$B$5:$B$12,MATCH(D7,Stages!$A$5:$A$12,0)),0)) | H7: =IF(A7="","",E7*G7)
G8: =IF(A8="","",IFERROR(INDEX(Stages!$B$5:$B$12,MATCH(D8,Stages!$A$5:$A$12,0)),0)) | H8: =IF(A8="","",E8*G8)
G9: =IF(A9="","",IFERROR(INDEX(Stages!$B$5:$B$12,MATCH(D9,Stages!$A$5:$A$12,0)),0)) | H9: =IF(A9="","",E9*G9)
G10: =IF(A10="","",IFERROR(INDEX(Stages!$B$5:$B$12,MATCH(D10,Stages!$A$5:$A$12,0)),0)) | H10: =IF(A10="","",E10*G10)
G11: =IF(A11="","",IFERROR(INDEX(Stages!$B$5:$B$12,MATCH(D11,Stages!$A$5:$A$12,0)),0)) | H11: =IF(A11="","",E11*G11)
G12: =IF(A12="","",IFERROR(INDEX(Stages!$B$5:$B$12,MATCH(D12,Stages!$A$5:$A$12,0)),0)) | H12: =IF(A12="","",E12*G12)
G13: =IF(A13="","",IFERROR(INDEX(Stages!$B$5:$B$12,MATCH(D13,Stages!$A$5:$A$12,0)),0)) | H13: =IF(A13="","",E13*G13)
G14: =IF(A14="","",IFERROR(INDEX(Stages!$B$5:$B$12,MATCH(D14,Stages!$A$5:$A$12,0)),0)) | H14: =IF(A14="","",E14*G14)
G15: =IF(A15="","",IFERROR(INDEX(Stages!$B$5:$B$12,MATCH(D15,Stages!$A$5:$A$12,0)),0)) | H15: =IF(A15="","",E15*G15)
G16: =IF(A16="","",IFERROR(INDEX(Stages!$B$5:$B$12,MATCH(D16,Stages!$A$5:$A$12,0)),0)) | H16: =IF(A16="","",E16*G16)
G17: =IF(A17="","",IFERROR(INDEX(Stages!$B$5:$B$12,MATCH(D17,Stages!$A$5:$A$12,0)),0)) | H17: =IF(A17="","",E17*G17)
G18: =IF(A18="","",IFERROR(INDEX(Stages!$B$5:$B$12,MATCH(D18,Stages!$A$5:$A$12,0)),0)) | H18: =IF(A18="","",E18*G18)
... G504: =IF(A504="","",IFERROR(INDEX(Stages!$B$5:$B$12,MATCH(D504,Stages!$A$5:$A$12,0)),0)) | H504: =IF(A504="","",E504*G504)

Sheet WeightedByMonth
A1: Weighted pipeline by month and channel (sanity-check K01 revenue)
A4: month no. | B4: channel | C4: weighted pipeline
A5: 1 | B5: Dealer network | C5: =IF(A5="","",SUMIFS(Pipeline!$H$5:$H$504,Pipeline!$F$5:$F$504,A5,Pipeline!$C$5:$C$504,B5))
A6: 2 | B6: Institutional | C6: =IF(A6="","",SUMIFS(Pipeline!$H$5:$H$504,Pipeline!$F$5:$F$504,A6,Pipeline!$C$5:$C$504,B6))
C7: =IF(A7="","",SUMIFS(Pipeline!$H$5:$H$504,Pipeline!$F$5:$F$504,A7,Pipeline!$C$5:$C$504,B7))
C8: =IF(A8="","",SUMIFS(Pipeline!$H$5:$H$504,Pipeline!$F$5:$F$504,A8,Pipeline!$C$5:$C$504,B8))
C9: =IF(A9="","",SUMIFS(Pipeline!$H$5:$H$504,Pipeline!$F$5:$F$504,A9,Pipeline!$C$5:$C$504,B9))
C10: =IF(A10="","",SUMIFS(Pipeline!$H$5:$H$504,Pipeline!$F$5:$F$504,A10,Pipeline!$C$5:$C$504,B10))
C11: =IF(A11="","",SUMIFS(Pipeline!$H$5:$H$504,Pipeline!$F$5:$F$504,A11,Pipeline!$C$5:$C$504,B11))
C12: =IF(A12="","",SUMIFS(Pipeline!$H$5:$H$504,Pipeline!$F$5:$F$504,A12,Pipeline!$C$5:$C$504,B12))
C13: =IF(A13="","",SUMIFS(Pipeline!$H$5:$H$504,Pipeline!$F$5:$F$504,A13,Pipeline!$C$5:$C$504,B13))
C14: =IF(A14="","",SUMIFS(Pipeline!$H$5:$H$504,Pipeline!$F$5:$F$504,A14,Pipeline!$C$5:$C$504,B14))
C15: =IF(A15="","",SUMIFS(Pipeline!$H$5:$H$504,Pipeline!$F$5:$F$504,A15,Pipeline!$C$5:$C$504,B15))
C16: =IF(A16="","",SUMIFS(Pipeline!$H$5:$H$504,Pipeline!$F$5:$F$504,A16,Pipeline!$C$5:$C$504,B16))
C17: =IF(A17="","",SUMIFS(Pipeline!$H$5:$H$504,Pipeline!$F$5:$F$504,A17,Pipeline!$C$5:$C$504,B17))
C18: =IF(A18="","",SUMIFS(Pipeline!$H$5:$H$504,Pipeline!$F$5:$F$504,A18,Pipeline!$C$5:$C$504,B18))
... C64: =IF(A64="","",SUMIFS(Pipeline!$H$5:$H$504,Pipeline!$F$5:$F$504,A64,Pipeline!$C$5:$C$504,B64))

Sheet Collections
A1: Invoice register -> expected collection week for K02 (week 1 = K02 start date)
A4: invoice no. | B4: customer | C4: invoice date | D4: amount incl. GST | E4: credit days | F4: historic slip days (customer) | G4: expected receipt date | H4: K02 week
A5: TN/26-27/0412 | B5: Sri Murugan Traders | C5: 46114 | D5: 1180000 | E5: 45 | F5: 12 | G5: =IF(A5="","",C5+E5+N(F5)) | H5: =IF(A5="","",INT((G5-Setup!$B$4)/7)+1)
G6: =IF(A6="","",C6+E6+N(F6)) | H6: =IF(A6="","",INT((G6-Setup!$B$4)/7)+1)
G7: =IF(A7="","",C7+E7+N(F7)) | H7: =IF(A7="","",INT((G7-Setup!$B$4)/7)+1)
G8: =IF(A8="","",C8+E8+N(F8)) | H8: =IF(A8="","",INT((G8-Setup!$B$4)/7)+1)
G9: =IF(A9="","",C9+E9+N(F9)) | H9: =IF(A9="","",INT((G9-Setup!$B$4)/7)+1)
G10: =IF(A10="","",C10+E10+N(F10)) | H10: =IF(A10="","",INT((G10-Setup!$B$4)/7)+1)
G11: =IF(A11="","",C11+E11+N(F11)) | H11: =IF(A11="","",INT((G11-Setup!$B$4)/7)+1)
G12: =IF(A12="","",C12+E12+N(F12)) | H12: =IF(A12="","",INT((G12-Setup!$B$4)/7)+1)
G13: =IF(A13="","",C13+E13+N(F13)) | H13: =IF(A13="","",INT((G13-Setup!$B$4)/7)+1)
G14: =IF(A14="","",C14+E14+N(F14)) | H14: =IF(A14="","",INT((G14-Setup!$B$4)/7)+1)
G15: =IF(A15="","",C15+E15+N(F15)) | H15: =IF(A15="","",INT((G15-Setup!$B$4)/7)+1)
G16: =IF(A16="","",C16+E16+N(F16)) | H16: =IF(A16="","",INT((G16-Setup!$B$4)/7)+1)
G17: =IF(A17="","",C17+E17+N(F17)) | H17: =IF(A17="","",INT((G17-Setup!$B$4)/7)+1)
... G504: =IF(A504="","",C504+E504+N(F504)) | H504: =IF(A504="","",INT((G504-Setup!$B$4)/7)+1)

Sheet Setup
A1: Setup
A4: K02 week-1 start date | B4: 46118
