Workbook
Name rc_source: 'Setup'!$B$4
Name rc_tol: 'Setup'!$B$5
Name rc_crsign: 'Setup'!$B$6
Name rc_allow: 'Setup'!$B$9
Name rc_passed: 'Reconcile'!$B$9

Sheet README
A1: K03 · Inspect, Profile, Map & Reconcile Sources (no-code kernel)
A3: Replaces openfpa CLI: inspect-data, source-profile, reconcile-source, connector-validate (fixture mode) and pyfpa read_pl_csv / _parse_amount.
A4: Sheets
A5: Inspect - paste a file listing (relative path, bytes) of a data folder; each file gets extension, candidate flag and a category from the classifier table. Missing priority categories are listed.
A6: Profile - paste any table (header row + up to 1,000 rows x 15 columns) exported from CSV/TSV/XLS/XLSX/ODS; returns rows, columns, empty cells per column and duplicate rows (pandas.duplicated semantics: repeats of an earlier row).
A7: Mapping - paste memory/mappings/registry.csv rows (source_id, source_value, target, status mapped/ignored, rationale).
A8: Reconcile - paste the source's Account and Amount columns (up to 1,500 rows). Amounts are parsed like openfpa (currency symbol, thousands separators, (parens)=negative, blank/'-'=0) plus India rules: ₹, Rs., INR, lakh-style commas, and a trailing Dr/Cr (Cr sign set on Setup).
A9: Output: row count, source total, mapped total, mapped totals per target, duplicates, unmapped, ignored, variances vs expected totals, PASSED.
A10: Connector validation = the same sheet with tolerance 0 and expected = the golden totals stored in the connector contract (connectors/<name>/connector.md). It never touches a live system.
A11: Rules (identical to openfpa)
A12: Blank account rows are skipped. Any duplicate account FAILS. Any account without a mapping rule for this source FAILS (never silently dropped). Ignored rules need a rationale and are excluded from totals.
A13: Variance = mapped - expected; variance_pct = variance/expected (0 if expected is 0); within tolerance when |variance_pct| <= tolerance, or exact equality when expected is 0.
A14: When expected totals are provided every mapped target is compared; a mapped target missing from the expected list is compared to 0.

Sheet Checks
A1: Checks - OVERALL must be PASS
B3: OVERALL | C3: =IF(COUNTIF(C5:C11,"PASS")=COUNT(A5:A11),"PASS","FAIL") | D3: =COUNTIF(C5:C11,"PASS")&" pass / "&COUNTIF(C5:C11,"FAIL")&" fail / "&(COUNT(A5:A11)-COUNTIF(C5:C11,"PASS")-COUNTIF(C5:C11,"FAIL"))&" error"
A4: # | B4: check | C4: result | D4: detail
A5: 1 | B5: source_id set | C5: =IF(TRIM(Setup!$B$4)<>"","PASS","FAIL") | D5: =Setup!$B$4
A6: 2 | B6: every mapping rule valid (mapped needs target; ignored needs rationale) | C6: =IF(COUNTIF(Mapping!$G$5:$G$504,0)=0,"PASS","FAIL") | D6: =COUNTIF(Mapping!$G$5:$G$504,0)&" invalid"
A7: 3 | B7: no duplicate (source_id, source_value) mapping keys in first 60 rules | C7: =IF((IF(Mapping!F5="",0,IF(SUMPRODUCT((Mapping!$F$5:$F$504=Mapping!F5)*1)>1,1,0))+IF(Mapping!F6="",0,IF(SUMPRODUCT((Mapping!$F$5:$F$504=Mapping!F6)*1)>1,1,0))+IF(Mapping!F7="",0,IF(SUMPRODUCT((Mapping!$F$5:$F$504=Mapping!F7)*1)>1,1,0))+IF(Mapping!F8="",0,IF(SUMPRODUCT((Mapping!$F$5:$F$504=Mapping!F8)*1)>1,1,0))+IF(Mapping!F9="",0,IF(SUMPRODUCT((Mapping!$F$5:$F$504=Mapping!F9)*1)>1,1,0))+IF(Mapping!F10="",0,IF(SUMPRODUCT((Mapping!$F$5:$F$504=Mapping!F10)*1)>1,1,0))+IF(Mapping!F11="",0,IF(SUMPRODUCT((Mapping!$F$5:$F$504=Mapping!F11)*1)>1,1,0))+IF(Mapping!F12="",0,IF(SUMPRODUCT((Mapping!$F$5:$F$504=Mapping!F12)*1)>1,1,0))+IF(Mapping!F13="",0,IF(SUMPRODUCT((Mapping!$F$5:$F$504=Mapping!F13)*1)>1,1,0))+IF(Mapping!F14="",0,IF(SUMPRODUCT((Mapping!$F$5:$F$504=Mapping!F14)*1)>1,1,0))+IF(Mapping!F15="",0,IF(SUMPRODUCT((Mapping!$F$5:$F$504=Mapping!F15)*1)>1,1,0))+IF(Mapping!F16="",0,IF(SUMPRODUCT((Mapping!$F$5:$F$504=Mapping!F16)*1)>1,1,0))+IF(Mapping!F17="",0,IF(SUMPRODUCT((Mapping!$F$5:$F$504=Mapping!F17)*1)>1,1,0))+IF(Mapping!F18="",0,IF(SUMPRODUCT((Mapping!$F$5:$F$504=Mapping!F18)*1)>1,1,0))+IF(Mapping!F19="",0,IF(SUMPRODUCT((Mapping!$F$5:$F$504=Mapping!F19)*1)>1,1,0))+IF(Mapping!F20="",0,IF(SUMPRODUCT((Mapping!$F$5:$F$504=Mapping!F20)*1)>1,1,0))+IF(Mapping!F21="",0,IF(SUMPRODUCT((Mapping!$F$5:$F$504=Mapping!F21)*1)>1,1,0))+IF(Mapping!F22="",0,IF(SUMPRODUCT((Mapping!$F$5:$F$504=Mapping!F22)*1)>1,1,0))+IF(Mapping!F23="",0,IF(SUMPRODUCT((Mapping!$F$5:$F$504=Mapping!F23)*1)>1,1,0))+IF(Mapping!F24="",0,IF(SUMPRODUCT((Mapping!$F$5:$F$504=Mapping!F24)*1)>1,1,0))+IF(Mapping!F25="",0,IF(SUMPRODUCT((Mapping!$F$5:$F$504=Mapping!F25)*1)>1,1,0))+IF(Mapping!F26="",0,IF(SUMPRODUCT((Mapping!$F$5:$F$504=Mapping!F26)*1)>1,1,0))+IF(Mapping!F27="",0,IF(SUMPRODUCT((Mapping!$F$5:$F$504=Mapping!F27)*1)>1,1,0))+IF(Mapping!F28="",0,IF(SUMPRODUCT((Mapping!$F$5:$F$504=Mapping!F28)*1)>1,1,0))+IF(Mapping!F29="",0,IF(SUMPRODUCT((Mapping!$F$5:$F$504=Mapping!F29)*1)>1,1,0))+IF(Mapping!F30="",0,IF(SUMPRODUCT((Mapping!$F$5:$F$504=Mapping!F30)*1)>1,1,0))+IF(Mapping!F31="",0,IF(SUMPRODUCT((Mapping!$F$5:$F$504=Mapping!F31)*1)>1,1,0))+IF(Mapping!F32="",0,IF(SUMPRODUCT((Mapping!$F$5:$F$504=Mapping!F32)*1)>1,1,0))+IF(Mapping!F33="",0,IF(SUMPRODUCT((Mapping!$F$5:$F$504=Mapping!F33)*1)>1,1,0))+IF(Mapping!F34="",0,IF(SUMPRODUCT((Mapping!$F$5:$F$504=Mapping!F34)*1)>1,1,0))+IF(Mapping!F35="",0,IF(SUMPRODUCT((Mapping!$F$5:$F$504=Mapping!F35)*1)>1,1,0))+IF(Mapping!F36="",0,IF(SUMPRODUCT((Mapping!$F$5:$F$504=Mapping!F36)*1)>1,1,0))+IF(Mapping!F37="",0,IF(SUMPRODUCT((Mapping!$F$5:$F$504=Mapping!F37)*1)>1,1,0))+IF(Mapping!F38="",0,IF(SUMPRODUCT((Mapping!$F$5:$F$504=Mapping!F38)*1)>1,1,0))+IF(Mapping!F39="",0,IF(SUMPRODUCT((Mapping!$F$5:$F$504=Mapping!F39)*1)>1,1,0))+IF(Mapping!F40="",0,IF(SUMPRODUCT((Mapping!$F$5:$F$504=Mapping!F40)*1)>1,1,0))+IF(Mapping!F41="",0,IF(SUMPRODUCT((Mapping!$F$5:$F$504=Mapping!F41)*1)>1,1,0))+IF(Mapping!F42="",0,IF(SUMPRODUCT((Mapping!$F$5:$F$504=Mapping!F42)*1)>1,1,0))+IF(Mapping!F43="",0,IF(SUMPRODUCT((Mapping!$F$5:$F$504=Mapping!F43)*1)>1,1,0))+IF(Mapping!F44="",0,IF(SUMPRODUCT((Mapping!$F$5:$F$504=Mapping!F44)*1)>1,1,0))+IF(Mapping!F45="",0,IF(SUMPRODUCT((Mapping!$F$5:$F$504=Mapping!F45)*1)>1,1,0))+IF(Mapping!F46="",0,IF(SUMPRODUCT((Mapping!$F$5:$F$504=Mapping!F46)*1)>1,1,0))+IF(Mapping!F47="",0,IF(SUMPRODUCT((Mapping!$F$5:$F$504=Mapping!F47)*1)>1,1,0))+IF(Mapping!F48="",0,IF(SUMPRODUCT((Mapping!$F$5:$F$504=Mapping!F48)*1)>1,1,0))+IF(Mapping!F49="",0,IF(SUMPRODUCT((Mapping!$F$5:$F$504=Mapping!F49)*1)>1,1,0))+IF(Mapping!F50="",0,IF(SUMPRODUCT((Mapping!$F$5:$F$504=Mapping!F50)*1)>1,1,0))+IF(Mapping!F51="",0,IF(SUMPRODUCT((Mapping!$F$5:$F$504=Mapping!F51)*1)>1,1,0))+IF(Mapping!F52="",0,IF(SUMPRODUCT((Mapping!$F$5:$F$504=Mapping!F52)*1)>1,1,0))+IF(Mapping!F53="",0,IF(SUMPRODUCT((Mapping!$F$5:$F$504=Mapping!F53)*1)>1,1,0))+IF(Mapping!F54="",0,IF(SUMPRODUCT((Mapping!$F$5:$F$504=Mapping!F54)*1)>1,1,0))+IF(Mapping!F55="",0,IF(SUMPRODUCT((Mapping!$F$5:$F$504=Mapping!F55)*1)>1,1,0))+IF(Mapping!F56="",0,IF(SUMPRODUCT((Mapping!$F$5:$F$504=Mapping!F56)*1)>1,1,0))+IF(Mapping!F57="",0,IF(SUMPRODUCT((Mapping!$F$5:$F$504=Mapping!F57)*1)>1,1,0))+IF(Mapping!F58="",0,IF(SUMPRODUCT((Mapping!$F$5:$F$504=Mapping!F58)*1)>1,1,0))+IF(Mapping!F59="",0,IF(SUMPRODUCT((Mapping!$F$5:$F$504=Mapping!F59)*1)>1,1,0))+IF(Mapping!F60="",0,IF(SUMPRODUCT((Mapping!$F$5:$F$504=Mapping!F60)*1)>1,1,0))+IF(Mapping!F61="",0,IF(SUMPRODUCT((Mapping!$F$5:$F$504=Mapping!F61)*1)>1,1,0))+IF(Mapping!F62="",0,IF(SUMPRODUCT((Mapping!$F$5:$F$504=Mapping!F62)*1)>1,1,0))+IF(Mapping!F63="",0,IF(SUMPRODUCT((Mapping!$F$5:$F$504=Mapping!F63)*1)>1,1,0))+IF(Mapping!F64="",0,IF(SUMPRODUCT((Mapping!$F$5:$F$504=Mapping!F64)*1)>1,1,0)))=0,"PASS","FAIL")
A8: 4 | B8: no duplicate accounts in source | C8: =IF(Reconcile!B6=0,"PASS","FAIL") | D8: =Reconcile!B6
A9: 5 | B9: no unmapped accounts (never silently dropped; allowed only when Setup says yes - still listed in Results) | C9: =IF(OR(Reconcile!B7=0,LOWER(Setup!$B$9)="yes"),"PASS","FAIL") | D9: =Reconcile!B7
A10: 6 | B10: all amounts parse | C10: =IF(Reconcile!B8=0,"PASS","FAIL") | D10: =Reconcile!B8
A11: 7 | B11: expected totals within tolerance (if provided) | C11: =IF(Results!B3,"PASS","FAIL")

Sheet Setup
A1: Setup
A4: source_id | B4: tally-pl-monthly
A5: tolerance (0.01 = 1%; 0 for connector validation) | B5: 0.01
A6: sign applied to amounts suffixed 'Cr' | B6: -1
A7: account column name in source | B7: Particulars
A8: amount column name in source | B8: Closing Balance
A9: allow unmapped? (yes = --allow-unmapped: unmapped listed but do not fail; duplicates still fail) | B9: no

Sheet Inspect
A1: Inspect (inspect-data): paste a file listing; classification is formula-driven
A4: relative path | B4: bytes | C4: file name | D4: extension | E4: stem (normalised) | F4: data ext? | G4: context signal? | H4: candidate? | I4: category | J4: profit_and_loss | K4: balance_sheet | L4: ar_aging | M4: ap_aging | N4: inventory | O4: cash_and_bank | P4: payroll_and_headcount | Q4: sales_and_revenue | R4: budget_and_forecast | S4: operations | T4: gst_and_indirect_tax | U4: tds_and_direct_tax | V4: statutory_payroll | W4: tally_or_erp_export
C5: =IF(A5="","",TRIM(RIGHT(SUBSTITUTE(A5,"/",REPT(" ",250)),250))) | D5: =IF(C5="","",IF(ISNUMBER(SEARCH(".",C5)),LOWER("."&TRIM(RIGHT(SUBSTITUTE(C5,".",REPT(" ",250)),250))),"")) | E5: =IF(C5="","",TRIM(SUBSTITUTE(SUBSTITUTE(SUBSTITUTE(SUBSTITUTE(SUBSTITUTE(SUBSTITUTE(SUBSTITUTE(SUBSTITUTE(SUBSTITUTE(SUBSTITUTE(SUBSTITUTE(SUBSTITUTE(SUBSTITUTE(SUBSTITUTE(SUBSTITUTE(SUBSTITUTE(SUBSTITUTE(SUBSTITUTE(SUBSTITUTE(SUBSTITUTE(LOWER(LEFT(C5,LEN(C5)-LEN(D5))),"_"," "),"-"," "),"."," "),","," "),"("," "),")"," "),"["," "),"]"," "),"&"," "),"+"," "),"@"," "),"#"," "),"!"," "),"'"," "),"/"," "),":"," "),";"," "),"="," "),"~"," "),"%"," "))) | F5: =IF(C5="","",IF(COUNTIF(Classifiers!$A$23:$A$40,D5)>0,1,0)) | G5: =IF(C5="","",IF(COUNTIF(Classifiers!$C$23:$C$30,D5)>0,IF((IF(ISNUMBER(SEARCH(Classifiers!$E$23,E5)),1,0)+IF(ISNUMBER(SEARCH(Classifiers!$E$24,E5)),1,0)+IF(ISNUMBER(SEARCH(Classifiers!$E$25,E5)),1,0)+IF(ISNUMBER(SEARCH(Classifiers!$E$26,E5)),1,0)+IF(ISNUMBER(SEARCH(Classifiers!$E$27,E5)),1,0)+IF(ISNUMBER(SEARCH(Classifiers!$E$28,E5)),1,0)+IF(ISNUMBER(SEARCH(Classifiers!$E$29,E5)),1,0)+IF(ISNUMBER(SEARCH(Classifiers!$E$30,E5)),1,0))>0,1,0),0)) | H5: =IF(C5="","",IF(OR(LEFT(C5,1)=".",AND(F5=0,G5=0)),0,1)) | I5: =IF(H5<>1,"",IF(SUM(J5:W5)=0,"unclassified",INDEX(Classifiers!$A$5:$A$18,MATCH(1,J5:W5,0),1))) | J5: =IF(H5<>1,0,IF((IF(Classifiers!$B$5="",0,IF(ISNUMBER(SEARCH(Classifiers!$B$5,E5)),1,0))+IF(Classifiers!$C$5="",0,IF(ISNUMBER(SEARCH(Classifiers!$C$5,E5)),1,0))+IF(Classifiers!$D$5="",0,IF(ISNUMBER(SEARCH(Classifiers!$D$5,E5)),1,0))+IF(Classifiers!$E$5="",0,IF(ISNUMBER(SEARCH(Classifiers!$E$5,E5)),1,0))+IF(Classifiers!$F$5="",0,IF(ISNUMBER(SEARCH(Classifiers!$F$5,E5)),1,0))+IF(Classifiers!$G$5="",0,IF(ISNUMBER(SEARCH(Classifiers!$G$5,E5)),1,0)))>0,1,0)) | K5: =IF(H5<>1,0,IF((IF(Classifiers!$B$6="",0,IF(ISNUMBER(SEARCH(Classifiers!$B$6,E5)),1,0))+IF(Classifiers!$C$6="",0,IF(ISNUMBER(SEARCH(Classifiers!$C$6,E5)),1,0))+IF(Classifiers!$D$6="",0,IF(ISNUMBER(SEARCH(Classifiers!$D$6,E5)),1,0))+IF(Classifiers!$E$6="",0,IF(ISNUMBER(SEARCH(Classifiers!$E$6,E5)),1,0))+IF(Classifiers!$F$6="",0,IF(ISNUMBER(SEARCH(Classifiers!$F$6,E5)),1,0))+IF(Classifiers!$G$6="",0,IF(ISNUMBER(SEARCH(Classifiers!$G$6,E5)),1,0)))>0,1,0)) | L5: =IF(H5<>1,0,IF((IF(Classifiers!$B$7="",0,IF(ISNUMBER(SEARCH(Classifiers!$B$7,E5)),1,0))+IF(Classifiers!$C$7="",0,IF(ISNUMBER(SEARCH(Classifiers!$C$7,E5)),1,0))+IF(Classifiers!$D$7="",0,IF(ISNUMBER(SEARCH(Classifiers!$D$7,E5)),1,0))+IF(Classifiers!$E$7="",0,IF(ISNUMBER(SEARCH(Classifiers!$E$7,E5)),1,0))+IF(Classifiers!$F$7="",0,IF(ISNUMBER(SEARCH(Classifiers!$F$7,E5)),1,0))+IF(Classifiers!$G$7="",0,IF(ISNUMBER(SEARCH(Classifiers!$G$7,E5)),1,0)))>0,1,0)) | M5: =IF(H5<>1,0,IF((IF(Classifiers!$B$8="",0,IF(ISNUMBER(SEARCH(Classifiers!$B$8,E5)),1,0))+IF(Classifiers!$C$8="",0,IF(ISNUMBER(SEARCH(Classifiers!$C$8,E5)),1,0))+IF(Classifiers!$D$8="",0,IF(ISNUMBER(SEARCH(Classifiers!$D$8,E5)),1,0))+IF(Classifiers!$E$8="",0,IF(ISNUMBER(SEARCH(Classifiers!$E$8,E5)),1,0))+IF(Classifiers!$F$8="",0,IF(ISNUMBER(SEARCH(Classifiers!$F$8,E5)),1,0))+IF(Classifiers!$G$8="",0,IF(ISNUMBER(SEARCH(Classifiers!$G$8,E5)),1,0)))>0,1,0)) | N5: =IF(H5<>1,0,IF((IF(Classifiers!$B$9="",0,IF(ISNUMBER(SEARCH(Classifiers!$B$9,E5)),1,0))+IF(Classifiers!$C$9="",0,IF(ISNUMBER(SEARCH(Classifiers!$C$9,E5)),1,0))+IF(Classifiers!$D$9="",0,IF(ISNUMBER(SEARCH(Classifiers!$D$9,E5)),1,0))+IF(Classifiers!$E$9="",0,IF(ISNUMBER(SEARCH(Classifiers!$E$9,E5)),1,0))+IF(Classifiers!$F$9="",0,IF(ISNUMBER(SEARCH(Classifiers!$F$9,E5)),1,0))+IF(Classifiers!$G$9="",0,IF(ISNUMBER(SEARCH(Classifiers!$G$9,E5)),1,0)))>0,1,0)) | O5: =IF(H5<>1,0,IF((IF(Classifiers!$B$10="",0,IF(ISNUMBER(SEARCH(Classifiers!$B$10,E5)),1,0))+IF(Classifiers!$C$10="",0,IF(ISNUMBER(SEARCH(Classifiers!$C$10,E5)),1,0))+IF(Classifiers!$D$10="",0,IF(ISNUMBER(SEARCH(Classifiers!$D$10,E5)),1,0))+IF(Classifiers!$E$10="",0,IF(ISNUMBER(SEARCH(Classifiers!$E$10,E5)),1,0))+IF(Classifiers!$F$10="",0,IF(ISNUMBER(SEARCH(Classifiers!$F$10,E5)),1,0))+IF(Classifiers!$G$10="",0,IF(ISNUMBER(SEARCH(Classifiers!$G$10,E5)),1,0)))>0,1,0)) | P5: =IF(H5<>1,0,IF((IF(Classifiers!$B$11="",0,IF(ISNUMBER(SEARCH(Classifiers!$B$11,E5)),1,0))+IF(Classifiers!$C$11="",0,IF(ISNUMBER(SEARCH(Classifiers!$C$11,E5)),1,0))+IF(Classifiers!$D$11="",0,IF(ISNUMBER(SEARCH(Classifiers!$D$11,E5)),1,0))+IF(Classifiers!$E$11="",0,IF(ISNUMBER(SEARCH(Classifiers!$E$11,E5)),1,0))+IF(Classifiers!$F$11="",0,IF(ISNUMBER(SEARCH(Classifiers!$F$11,E5)),1,0))+IF(Classifiers!$G$11="",0,IF(ISNUMBER(SEARCH(Classifiers!$G$11,E5)),1,0)))>0,1,0)) | Q5: =IF(H5<>1,0,IF((IF(Classifiers!$B$12="",0,IF(ISNUMBER(SEARCH(Classifiers!$B$12,E5)),1,0))+IF(Classifiers!$C$12="",0,IF(ISNUMBER(SEARCH(Classifiers!$C$12,E5)),1,0))+IF(Classifiers!$D$12="",0,IF(ISNUMBER(SEARCH(Classifiers!$D$12,E5)),1,0))+IF(Classifiers!$E$12="",0,IF(ISNUMBER(SEARCH(Classifiers!$E$12,E5)),1,0))+IF(Classifiers!$F$12="",0,IF(ISNUMBER(SEARCH(Classifiers!$F$12,E5)),1,0))+IF(Classifiers!$G$12="",0,IF(ISNUMBER(SEARCH(Classifiers!$G$12,E5)),1,0)))>0,1,0)) | R5: =IF(H5<>1,0,IF((IF(Classifiers!$B$13="",0,IF(ISNUMBER(SEARCH(Classifiers!$B$13,E5)),1,0))+IF(Classifiers!$C$13="",0,IF(ISNUMBER(SEARCH(Classifiers!$C$13,E5)),1,0))+IF(Classifiers!$D$13="",0,IF(ISNUMBER(SEARCH(Classifiers!$D$13,E5)),1,0))+IF(Classifiers!$E$13="",0,IF(ISNUMBER(SEARCH(Classifiers!$E$13,E5)),1,0))+IF(Classifiers!$F$13="",0,IF(ISNUMBER(SEARCH(Classifiers!$F$13,E5)),1,0))+IF(Classifiers!$G$13="",0,IF(ISNUMBER(SEARCH(Classifiers!$G$13,E5)),1,0)))>0,1,0)) | S5: =IF(H5<>1,0,IF((IF(Classifiers!$B$14="",0,IF(ISNUMBER(SEARCH(Classifiers!$B$14,E5)),1,0))+IF(Classifiers!$C$14="",0,IF(ISNUMBER(SEARCH(Classifiers!$C$14,E5)),1,0))+IF(Classifiers!$D$14="",0,IF(ISNUMBER(SEARCH(Classifiers!$D$14,E5)),1,0))+IF(Classifiers!$E$14="",0,IF(ISNUMBER(SEARCH(Classifiers!$E$14,E5)),1,0))+IF(Classifiers!$F$14="",0,IF(ISNUMBER(SEARCH(Classifiers!$F$14,E5)),1,0))+IF(Classifiers!$G$14="",0,IF(ISNUMBER(SEARCH(Classifiers!$G$14,E5)),1,0)))>0,1,0)) | T5: =IF(H5<>1,0,IF((IF(Classifiers!$B$15="",0,IF(ISNUMBER(SEARCH(Classifiers!$B$15,E5)),1,0))+IF(Classifiers!$C$15="",0,IF(ISNUMBER(SEARCH(Classifiers!$C$15,E5)),1,0))+IF(Classifiers!$D$15="",0,IF(ISNUMBER(SEARCH(Classifiers!$D$15,E5)),1,0))+IF(Classifiers!$E$15="",0,IF(ISNUMBER(SEARCH(Classifiers!$E$15,E5)),1,0))+IF(Classifiers!$F$15="",0,IF(ISNUMBER(SEARCH(Classifiers!$F$15,E5)),1,0))+IF(Classifiers!$G$15="",0,IF(ISNUMBER(SEARCH(Classifiers!$G$15,E5)),1,0)))>0,1,0)) | U5: =IF(H5<>1,0,IF((IF(Classifiers!$B$16="",0,IF(ISNUMBER(SEARCH(Classifiers!$B$16,E5)),1,0))+IF(Classifiers!$C$16="",0,IF(ISNUMBER(SEARCH(Classifiers!$C$16,E5)),1,0))+IF(Classifiers!$D$16="",0,IF(ISNUMBER(SEARCH(Classifiers!$D$16,E5)),1,0))+IF(Classifiers!$E$16="",0,IF(ISNUMBER(SEARCH(Classifiers!$E$16,E5)),1,0))+IF(Classifiers!$F$16="",0,IF(ISNUMBER(SEARCH(Classifiers!$F$16,E5)),1,0))+IF(Classifiers!$G$16="",0,IF(ISNUMBER(SEARCH(Classifiers!$G$16,E5)),1,0)))>0,1,0)) | V5: =IF(H5<>1,0,IF((IF(Classifiers!$B$17="",0,IF(ISNUMBER(SEARCH(Classifiers!$B$17,E5)),1,0))+IF(Classifiers!$C$17="",0,IF(ISNUMBER(SEARCH(Classifiers!$C$17,E5)),1,0))+IF(Classifiers!$D$17="",0,IF(ISNUMBER(SEARCH(Classifiers!$D$17,E5)),1,0))+IF(Classifiers!$E$17="",0,IF(ISNUMBER(SEARCH(Classifiers!$E$17,E5)),1,0))+IF(Classifiers!$F$17="",0,IF(ISNUMBER(SEARCH(Classifiers!$F$17,E5)),1,0))+IF(Classifiers!$G$17="",0,IF(ISNUMBER(SEARCH(Classifiers!$G$17,E5)),1,0)))>0,1,0)) | W5: =IF(H5<>1,0,IF((IF(Classifiers!$B$18="",0,IF(ISNUMBER(SEARCH(Classifiers!$B$18,E5)),1,0))+IF(Classifiers!$C$18="",0,IF(ISNUMBER(SEARCH(Classifiers!$C$18,E5)),1,0))+IF(Classifiers!$D$18="",0,IF(ISNUMBER(SEARCH(Classifiers!$D$18,E5)),1,0))+IF(Classifiers!$E$18="",0,IF(ISNUMBER(SEARCH(Classifiers!$E$18,E5)),1,0))+IF(Classifiers!$F$18="",0,IF(ISNUMBER(SEARCH(Classifiers!$F$18,E5)),1,0))+IF(Classifiers!$G$18="",0,IF(ISNUMBER(SEARCH(Classifiers!$G$18,E5)),1,0)))>0,1,0))
C6: =IF(A6="","",TRIM(RIGHT(SUBSTITUTE(A6,"/",REPT(" ",250)),250))) | D6: =IF(C6="","",IF(ISNUMBER(SEARCH(".",C6)),LOWER("."&TRIM(RIGHT(SUBSTITUTE(C6,".",REPT(" ",250)),250))),"")) | E6: =IF(C6="","",TRIM(SUBSTITUTE(SUBSTITUTE(SUBSTITUTE(SUBSTITUTE(SUBSTITUTE(SUBSTITUTE(SUBSTITUTE(SUBSTITUTE(SUBSTITUTE(SUBSTITUTE(SUBSTITUTE(SUBSTITUTE(SUBSTITUTE(SUBSTITUTE(SUBSTITUTE(SUBSTITUTE(SUBSTITUTE(SUBSTITUTE(SUBSTITUTE(SUBSTITUTE(LOWER(LEFT(C6,LEN(C6)-LEN(D6))),"_"," "),"-"," "),"."," "),","," "),"("," "),")"," "),"["," "),"]"," "),"&"," "),"+"," "),"@"," "),"#"," "),"!"," "),"'"," "),"/"," "),":"," "),";"," "),"="," "),"~"," "),"%"," "))) | F6: =IF(C6="","",IF(COUNTIF(Classifiers!$A$23:$A$40,D6)>0,1,0)) | G6: =IF(C6="","",IF(COUNTIF(Classifiers!$C$23:$C$30,D6)>0,IF((IF(ISNUMBER(SEARCH(Classifiers!$E$23,E6)),1,0)+IF(ISNUMBER(SEARCH(Classifiers!$E$24,E6)),1,0)+IF(ISNUMBER(SEARCH(Classifiers!$E$25,E6)),1,0)+IF(ISNUMBER(SEARCH(Classifiers!$E$26,E6)),1,0)+IF(ISNUMBER(SEARCH(Classifiers!$E$27,E6)),1,0)+IF(ISNUMBER(SEARCH(Classifiers!$E$28,E6)),1,0)+IF(ISNUMBER(SEARCH(Classifiers!$E$29,E6)),1,0)+IF(ISNUMBER(SEARCH(Classifiers!$E$30,E6)),1,0))>0,1,0),0)) | H6: =IF(C6="","",IF(OR(LEFT(C6,1)=".",AND(F6=0,G6=0)),0,1)) | I6: =IF(H6<>1,"",IF(SUM(J6:W6)=0,"unclassified",INDEX(Classifiers!$A$5:$A$18,MATCH(1,J6:W6,0),1))) | J6: =IF(H6<>1,0,IF((IF(Classifiers!$B$5="",0,IF(ISNUMBER(SEARCH(Classifiers!$B$5,E6)),1,0))+IF(Classifiers!$C$5="",0,IF(ISNUMBER(SEARCH(Classifiers!$C$5,E6)),1,0))+IF(Classifiers!$D$5="",0,IF(ISNUMBER(SEARCH(Classifiers!$D$5,E6)),1,0))+IF(Classifiers!$E$5="",0,IF(ISNUMBER(SEARCH(Classifiers!$E$5,E6)),1,0))+IF(Classifiers!$F$5="",0,IF(ISNUMBER(SEARCH(Classifiers!$F$5,E6)),1,0))+IF(Classifiers!$G$5="",0,IF(ISNUMBER(SEARCH(Classifiers!$G$5,E6)),1,0)))>0,1,0)) | K6: =IF(H6<>1,0,IF((IF(Classifiers!$B$6="",0,IF(ISNUMBER(SEARCH(Classifiers!$B$6,E6)),1,0))+IF(Classifiers!$C$6="",0,IF(ISNUMBER(SEARCH(Classifiers!$C$6,E6)),1,0))+IF(Classifiers!$D$6="",0,IF(ISNUMBER(SEARCH(Classifiers!$D$6,E6)),1,0))+IF(Classifiers!$E$6="",0,IF(ISNUMBER(SEARCH(Classifiers!$E$6,E6)),1,0))+IF(Classifiers!$F$6="",0,IF(ISNUMBER(SEARCH(Classifiers!$F$6,E6)),1,0))+IF(Classifiers!$G$6="",0,IF(ISNUMBER(SEARCH(Classifiers!$G$6,E6)),1,0)))>0,1,0)) | L6: =IF(H6<>1,0,IF((IF(Classifiers!$B$7="",0,IF(ISNUMBER(SEARCH(Classifiers!$B$7,E6)),1,0))+IF(Classifiers!$C$7="",0,IF(ISNUMBER(SEARCH(Classifiers!$C$7,E6)),1,0))+IF(Classifiers!$D$7="",0,IF(ISNUMBER(SEARCH(Classifiers!$D$7,E6)),1,0))+IF(Classifiers!$E$7="",0,IF(ISNUMBER(SEARCH(Classifiers!$E$7,E6)),1,0))+IF(Classifiers!$F$7="",0,IF(ISNUMBER(SEARCH(Classifiers!$F$7,E6)),1,0))+IF(Classifiers!$G$7="",0,IF(ISNUMBER(SEARCH(Classifiers!$G$7,E6)),1,0)))>0,1,0)) | M6: =IF(H6<>1,0,IF((IF(Classifiers!$B$8="",0,IF(ISNUMBER(SEARCH(Classifiers!$B$8,E6)),1,0))+IF(Classifiers!$C$8="",0,IF(ISNUMBER(SEARCH(Classifiers!$C$8,E6)),1,0))+IF(Classifiers!$D$8="",0,IF(ISNUMBER(SEARCH(Classifiers!$D$8,E6)),1,0))+IF(Classifiers!$E$8="",0,IF(ISNUMBER(SEARCH(Classifiers!$E$8,E6)),1,0))+IF(Classifiers!$F$8="",0,IF(ISNUMBER(SEARCH(Classifiers!$F$8,E6)),1,0))+IF(Classifiers!$G$8="",0,IF(ISNUMBER(SEARCH(Classifiers!$G$8,E6)),1,0)))>0,1,0)) | N6: =IF(H6<>1,0,IF((IF(Classifiers!$B$9="",0,IF(ISNUMBER(SEARCH(Classifiers!$B$9,E6)),1,0))+IF(Classifiers!$C$9="",0,IF(ISNUMBER(SEARCH(Classifiers!$C$9,E6)),1,0))+IF(Classifiers!$D$9="",0,IF(ISNUMBER(SEARCH(Classifiers!$D$9,E6)),1,0))+IF(Classifiers!$E$9="",0,IF(ISNUMBER(SEARCH(Classifiers!$E$9,E6)),1,0))+IF(Classifiers!$F$9="",0,IF(ISNUMBER(SEARCH(Classifiers!$F$9,E6)),1,0))+IF(Classifiers!$G$9="",0,IF(ISNUMBER(SEARCH(Classifiers!$G$9,E6)),1,0)))>0,1,0)) | O6: =IF(H6<>1,0,IF((IF(Classifiers!$B$10="",0,IF(ISNUMBER(SEARCH(Classifiers!$B$10,E6)),1,0))+IF(Classifiers!$C$10="",0,IF(ISNUMBER(SEARCH(Classifiers!$C$10,E6)),1,0))+IF(Classifiers!$D$10="",0,IF(ISNUMBER(SEARCH(Classifiers!$D$10,E6)),1,0))+IF(Classifiers!$E$10="",0,IF(ISNUMBER(SEARCH(Classifiers!$E$10,E6)),1,0))+IF(Classifiers!$F$10="",0,IF(ISNUMBER(SEARCH(Classifiers!$F$10,E6)),1,0))+IF(Classifiers!$G$10="",0,IF(ISNUMBER(SEARCH(Classifiers!$G$10,E6)),1,0)))>0,1,0)) | P6: =IF(H6<>1,0,IF((IF(Classifiers!$B$11="",0,IF(ISNUMBER(SEARCH(Classifiers!$B$11,E6)),1,0))+IF(Classifiers!$C$11="",0,IF(ISNUMBER(SEARCH(Classifiers!$C$11,E6)),1,0))+IF(Classifiers!$D$11="",0,IF(ISNUMBER(SEARCH(Classifiers!$D$11,E6)),1,0))+IF(Classifiers!$E$11="",0,IF(ISNUMBER(SEARCH(Classifiers!$E$11,E6)),1,0))+IF(Classifiers!$F$11="",0,IF(ISNUMBER(SEARCH(Classifiers!$F$11,E6)),1,0))+IF(Classifiers!$G$11="",0,IF(ISNUMBER(SEARCH(Classifiers!$G$11,E6)),1,0)))>0,1,0)) | Q6: =IF(H6<>1,0,IF((IF(Classifiers!$B$12="",0,IF(ISNUMBER(SEARCH(Classifiers!$B$12,E6)),1,0))+IF(Classifiers!$C$12="",0,IF(ISNUMBER(SEARCH(Classifiers!$C$12,E6)),1,0))+IF(Classifiers!$D$12="",0,IF(ISNUMBER(SEARCH(Classifiers!$D$12,E6)),1,0))+IF(Classifiers!$E$12="",0,IF(ISNUMBER(SEARCH(Classifiers!$E$12,E6)),1,0))+IF(Classifiers!$F$12="",0,IF(ISNUMBER(SEARCH(Classifiers!$F$12,E6)),1,0))+IF(Classifiers!$G$12="",0,IF(ISNUMBER(SEARCH(Classifiers!$G$12,E6)),1,0)))>0,1,0)) | R6: =IF(H6<>1,0,IF((IF(Classifiers!$B$13="",0,IF(ISNUMBER(SEARCH(Classifiers!$B$13,E6)),1,0))+IF(Classifiers!$C$13="",0,IF(ISNUMBER(SEARCH(Classifiers!$C$13,E6)),1,0))+IF(Classifiers!$D$13="",0,IF(ISNUMBER(SEARCH(Classifiers!$D$13,E6)),1,0))+IF(Classifiers!$E$13="",0,IF(ISNUMBER(SEARCH(Classifiers!$E$13,E6)),1,0))+IF(Classifiers!$F$13="",0,IF(ISNUMBER(SEARCH(Classifiers!$F$13,E6)),1,0))+IF(Classifiers!$G$13="",0,IF(ISNUMBER(SEARCH(Classifiers!$G$13,E6)),1,0)))>0,1,0)) | S6: =IF(H6<>1,0,IF((IF(Classifiers!$B$14="",0,IF(ISNUMBER(SEARCH(Classifiers!$B$14,E6)),1,0))+IF(Classifiers!$C$14="",0,IF(ISNUMBER(SEARCH(Classifiers!$C$14,E6)),1,0))+IF(Classifiers!$D$14="",0,IF(ISNUMBER(SEARCH(Classifiers!$D$14,E6)),1,0))+IF(Classifiers!$E$14="",0,IF(ISNUMBER(SEARCH(Classifiers!$E$14,E6)),1,0))+IF(Classifiers!$F$14="",0,IF(ISNUMBER(SEARCH(Classifiers!$F$14,E6)),1,0))+IF(Classifiers!$G$14="",0,IF(ISNUMBER(SEARCH(Classifiers!$G$14,E6)),1,0)))>0,1,0)) | T6: =IF(H6<>1,0,IF((IF(Classifiers!$B$15="",0,IF(ISNUMBER(SEARCH(Classifiers!$B$15,E6)),1,0))+IF(Classifiers!$C$15="",0,IF(ISNUMBER(SEARCH(Classifiers!$C$15,E6)),1,0))+IF(Classifiers!$D$15="",0,IF(ISNUMBER(SEARCH(Classifiers!$D$15,E6)),1,0))+IF(Classifiers!$E$15="",0,IF(ISNUMBER(SEARCH(Classifiers!$E$15,E6)),1,0))+IF(Classifiers!$F$15="",0,IF(ISNUMBER(SEARCH(Classifiers!$F$15,E6)),1,0))+IF(Classifiers!$G$15="",0,IF(ISNUMBER(SEARCH(Classifiers!$G$15,E6)),1,0)))>0,1,0)) | U6: =IF(H6<>1,0,IF((IF(Classifiers!$B$16="",0,IF(ISNUMBER(SEARCH(Classifiers!$B$16,E6)),1,0))+IF(Classifiers!$C$16="",0,IF(ISNUMBER(SEARCH(Classifiers!$C$16,E6)),1,0))+IF(Classifiers!$D$16="",0,IF(ISNUMBER(SEARCH(Classifiers!$D$16,E6)),1,0))+IF(Classifiers!$E$16="",0,IF(ISNUMBER(SEARCH(Classifiers!$E$16,E6)),1,0))+IF(Classifiers!$F$16="",0,IF(ISNUMBER(SEARCH(Classifiers!$F$16,E6)),1,0))+IF(Classifiers!$G$16="",0,IF(ISNUMBER(SEARCH(Classifiers!$G$16,E6)),1,0)))>0,1,0)) | V6: =IF(H6<>1,0,IF((IF(Classifiers!$B$17="",0,IF(ISNUMBER(SEARCH(Classifiers!$B$17,E6)),1,0))+IF(Classifiers!$C$17="",0,IF(ISNUMBER(SEARCH(Classifiers!$C$17,E6)),1,0))+IF(Classifiers!$D$17="",0,IF(ISNUMBER(SEARCH(Classifiers!$D$17,E6)),1,0))+IF(Classifiers!$E$17="",0,IF(ISNUMBER(SEARCH(Classifiers!$E$17,E6)),1,0))+IF(Classifiers!$F$17="",0,IF(ISNUMBER(SEARCH(Classifiers!$F$17,E6)),1,0))+IF(Classifiers!$G$17="",0,IF(ISNUMBER(SEARCH(Classifiers!$G$17,E6)),1,0)))>0,1,0)) | W6: =IF(H6<>1,0,IF((IF(Classifiers!$B$18="",0,IF(ISNUMBER(SEARCH(Classifiers!$B$18,E6)),1,0))+IF(Classifiers!$C$18="",0,IF(ISNUMBER(SEARCH(Classifiers!$C$18,E6)),1,0))+IF(Classifiers!$D$18="",0,IF(ISNUMBER(SEARCH(Classifiers!$D$18,E6)),1,0))+IF(Classifiers!$E$18="",0,IF(ISNUMBER(SEARCH(Classifiers!$E$18,E6)),1,0))+IF(Classifiers!$F$18="",0,IF(ISNUMBER(SEARCH(Classifiers!$F$18,E6)),1,0))+IF(Classifiers!$G$18="",0,IF(ISNUMBER(SEARCH(Classifiers!$G$18,E6)),1,0)))>0,1,0))
C7: =IF(A7="","",TRIM(RIGHT(SUBSTITUTE(A7,"/",REPT(" ",250)),250))) | D7: =IF(C7="","",IF(ISNUMBER(SEARCH(".",C7)),LOWER("."&TRIM(RIGHT(SUBSTITUTE(C7,".",REPT(" ",250)),250))),"")) | E7: =IF(C7="","",TRIM(SUBSTITUTE(SUBSTITUTE(SUBSTITUTE(SUBSTITUTE(SUBSTITUTE(SUBSTITUTE(SUBSTITUTE(SUBSTITUTE(SUBSTITUTE(SUBSTITUTE(SUBSTITUTE(SUBSTITUTE(SUBSTITUTE(SUBSTITUTE(SUBSTITUTE(SUBSTITUTE(SUBSTITUTE(SUBSTITUTE(SUBSTITUTE(SUBSTITUTE(LOWER(LEFT(C7,LEN(C7)-LEN(D7))),"_"," "),"-"," "),"."," "),","," "),"("," "),")"," "),"["," "),"]"," "),"&"," "),"+"," "),"@"," "),"#"," "),"!"," "),"'"," "),"/"," "),":"," "),";"," "),"="," "),"~"," "),"%"," "))) | F7: =IF(C7="","",IF(COUNTIF(Classifiers!$A$23:$A$40,D7)>0,1,0)) | G7: =IF(C7="","",IF(COUNTIF(Classifiers!$C$23:$C$30,D7)>0,IF((IF(ISNUMBER(SEARCH(Classifiers!$E$23,E7)),1,0)+IF(ISNUMBER(SEARCH(Classifiers!$E$24,E7)),1,0)+IF(ISNUMBER(SEARCH(Classifiers!$E$25,E7)),1,0)+IF(ISNUMBER(SEARCH(Classifiers!$E$26,E7)),1,0)+IF(ISNUMBER(SEARCH(Classifiers!$E$27,E7)),1,0)+IF(ISNUMBER(SEARCH(Classifiers!$E$28,E7)),1,0)+IF(ISNUMBER(SEARCH(Classifiers!$E$29,E7)),1,0)+IF(ISNUMBER(SEARCH(Classifiers!$E$30,E7)),1,0))>0,1,0),0)) | H7: =IF(C7="","",IF(OR(LEFT(C7,1)=".",AND(F7=0,G7=0)),0,1)) | I7: =IF(H7<>1,"",IF(SUM(J7:W7)=0,"unclassified",INDEX(Classifiers!$A$5:$A$18,MATCH(1,J7:W7,0),1))) | J7: =IF(H7<>1,0,IF((IF(Classifiers!$B$5="",0,IF(ISNUMBER(SEARCH(Classifiers!$B$5,E7)),1,0))+IF(Classifiers!$C$5="",0,IF(ISNUMBER(SEARCH(Classifiers!$C$5,E7)),1,0))+IF(Classifiers!$D$5="",0,IF(ISNUMBER(SEARCH(Classifiers!$D$5,E7)),1,0))+IF(Classifiers!$E$5="",0,IF(ISNUMBER(SEARCH(Classifiers!$E$5,E7)),1,0))+IF(Classifiers!$F$5="",0,IF(ISNUMBER(SEARCH(Classifiers!$F$5,E7)),1,0))+IF(Classifiers!$G$5="",0,IF(ISNUMBER(SEARCH(Classifiers!$G$5,E7)),1,0)))>0,1,0)) | K7: =IF(H7<>1,0,IF((IF(Classifiers!$B$6="",0,IF(ISNUMBER(SEARCH(Classifiers!$B$6,E7)),1,0))+IF(Classifiers!$C$6="",0,IF(ISNUMBER(SEARCH(Classifiers!$C$6,E7)),1,0))+IF(Classifiers!$D$6="",0,IF(ISNUMBER(SEARCH(Classifiers!$D$6,E7)),1,0))+IF(Classifiers!$E$6="",0,IF(ISNUMBER(SEARCH(Classifiers!$E$6,E7)),1,0))+IF(Classifiers!$F$6="",0,IF(ISNUMBER(SEARCH(Classifiers!$F$6,E7)),1,0))+IF(Classifiers!$G$6="",0,IF(ISNUMBER(SEARCH(Classifiers!$G$6,E7)),1,0)))>0,1,0)) | L7: =IF(H7<>1,0,IF((IF(Classifiers!$B$7="",0,IF(ISNUMBER(SEARCH(Classifiers!$B$7,E7)),1,0))+IF(Classifiers!$C$7="",0,IF(ISNUMBER(SEARCH(Classifiers!$C$7,E7)),1,0))+IF(Classifiers!$D$7="",0,IF(ISNUMBER(SEARCH(Classifiers!$D$7,E7)),1,0))+IF(Classifiers!$E$7="",0,IF(ISNUMBER(SEARCH(Classifiers!$E$7,E7)),1,0))+IF(Classifiers!$F$7="",0,IF(ISNUMBER(SEARCH(Classifiers!$F$7,E7)),1,0))+IF(Classifiers!$G$7="",0,IF(ISNUMBER(SEARCH(Classifiers!$G$7,E7)),1,0)))>0,1,0)) | M7: =IF(H7<>1,0,IF((IF(Classifiers!$B$8="",0,IF(ISNUMBER(SEARCH(Classifiers!$B$8,E7)),1,0))+IF(Classifiers!$C$8="",0,IF(ISNUMBER(SEARCH(Classifiers!$C$8,E7)),1,0))+IF(Classifiers!$D$8="",0,IF(ISNUMBER(SEARCH(Classifiers!$D$8,E7)),1,0))+IF(Classifiers!$E$8="",0,IF(ISNUMBER(SEARCH(Classifiers!$E$8,E7)),1,0))+IF(Classifiers!$F$8="",0,IF(ISNUMBER(SEARCH(Classifiers!$F$8,E7)),1,0))+IF(Classifiers!$G$8="",0,IF(ISNUMBER(SEARCH(Classifiers!$G$8,E7)),1,0)))>0,1,0)) | N7: =IF(H7<>1,0,IF((IF(Classifiers!$B$9="",0,IF(ISNUMBER(SEARCH(Classifiers!$B$9,E7)),1,0))+IF(Classifiers!$C$9="",0,IF(ISNUMBER(SEARCH(Classifiers!$C$9,E7)),1,0))+IF(Classifiers!$D$9="",0,IF(ISNUMBER(SEARCH(Classifiers!$D$9,E7)),1,0))+IF(Classifiers!$E$9="",0,IF(ISNUMBER(SEARCH(Classifiers!$E$9,E7)),1,0))+IF(Classifiers!$F$9="",0,IF(ISNUMBER(SEARCH(Classifiers!$F$9,E7)),1,0))+IF(Classifiers!$G$9="",0,IF(ISNUMBER(SEARCH(Classifiers!$G$9,E7)),1,0)))>0,1,0)) | O7: =IF(H7<>1,0,IF((IF(Classifiers!$B$10="",0,IF(ISNUMBER(SEARCH(Classifiers!$B$10,E7)),1,0))+IF(Classifiers!$C$10="",0,IF(ISNUMBER(SEARCH(Classifiers!$C$10,E7)),1,0))+IF(Classifiers!$D$10="",0,IF(ISNUMBER(SEARCH(Classifiers!$D$10,E7)),1,0))+IF(Classifiers!$E$10="",0,IF(ISNUMBER(SEARCH(Classifiers!$E$10,E7)),1,0))+IF(Classifiers!$F$10="",0,IF(ISNUMBER(SEARCH(Classifiers!$F$10,E7)),1,0))+IF(Classifiers!$G$10="",0,IF(ISNUMBER(SEARCH(Classifiers!$G$10,E7)),1,0)))>0,1,0)) | P7: =IF(H7<>1,0,IF((IF(Classifiers!$B$11="",0,IF(ISNUMBER(SEARCH(Classifiers!$B$11,E7)),1,0))+IF(Classifiers!$C$11="",0,IF(ISNUMBER(SEARCH(Classifiers!$C$11,E7)),1,0))+IF(Classifiers!$D$11="",0,IF(ISNUMBER(SEARCH(Classifiers!$D$11,E7)),1,0))+IF(Classifiers!$E$11="",0,IF(ISNUMBER(SEARCH(Classifiers!$E$11,E7)),1,0))+IF(Classifiers!$F$11="",0,IF(ISNUMBER(SEARCH(Classifiers!$F$11,E7)),1,0))+IF(Classifiers!$G$11="",0,IF(ISNUMBER(SEARCH(Classifiers!$G$11,E7)),1,0)))>0,1,0)) | Q7: =IF(H7<>1,0,IF((IF(Classifiers!$B$12="",0,IF(ISNUMBER(SEARCH(Classifiers!$B$12,E7)),1,0))+IF(Classifiers!$C$12="",0,IF(ISNUMBER(SEARCH(Classifiers!$C$12,E7)),1,0))+IF(Classifiers!$D$12="",0,IF(ISNUMBER(SEARCH(Classifiers!$D$12,E7)),1,0))+IF(Classifiers!$E$12="",0,IF(ISNUMBER(SEARCH(Classifiers!$E$12,E7)),1,0))+IF(Classifiers!$F$12="",0,IF(ISNUMBER(SEARCH(Classifiers!$F$12,E7)),1,0))+IF(Classifiers!$G$12="",0,IF(ISNUMBER(SEARCH(Classifiers!$G$12,E7)),1,0)))>0,1,0)) | R7: =IF(H7<>1,0,IF((IF(Classifiers!$B$13="",0,IF(ISNUMBER(SEARCH(Classifiers!$B$13,E7)),1,0))+IF(Classifiers!$C$13="",0,IF(ISNUMBER(SEARCH(Classifiers!$C$13,E7)),1,0))+IF(Classifiers!$D$13="",0,IF(ISNUMBER(SEARCH(Classifiers!$D$13,E7)),1,0))+IF(Classifiers!$E$13="",0,IF(ISNUMBER(SEARCH(Classifiers!$E$13,E7)),1,0))+IF(Classifiers!$F$13="",0,IF(ISNUMBER(SEARCH(Classifiers!$F$13,E7)),1,0))+IF(Classifiers!$G$13="",0,IF(ISNUMBER(SEARCH(Classifiers!$G$13,E7)),1,0)))>0,1,0)) | S7: =IF(H7<>1,0,IF((IF(Classifiers!$B$14="",0,IF(ISNUMBER(SEARCH(Classifiers!$B$14,E7)),1,0))+IF(Classifiers!$C$14="",0,IF(ISNUMBER(SEARCH(Classifiers!$C$14,E7)),1,0))+IF(Classifiers!$D$14="",0,IF(ISNUMBER(SEARCH(Classifiers!$D$14,E7)),1,0))+IF(Classifiers!$E$14="",0,IF(ISNUMBER(SEARCH(Classifiers!$E$14,E7)),1,0))+IF(Classifiers!$F$14="",0,IF(ISNUMBER(SEARCH(Classifiers!$F$14,E7)),1,0))+IF(Classifiers!$G$14="",0,IF(ISNUMBER(SEARCH(Classifiers!$G$14,E7)),1,0)))>0,1,0)) | T7: =IF(H7<>1,0,IF((IF(Classifiers!$B$15="",0,IF(ISNUMBER(SEARCH(Classifiers!$B$15,E7)),1,0))+IF(Classifiers!$C$15="",0,IF(ISNUMBER(SEARCH(Classifiers!$C$15,E7)),1,0))+IF(Classifiers!$D$15="",0,IF(ISNUMBER(SEARCH(Classifiers!$D$15,E7)),1,0))+IF(Classifiers!$E$15="",0,IF(ISNUMBER(SEARCH(Classifiers!$E$15,E7)),1,0))+IF(Classifiers!$F$15="",0,IF(ISNUMBER(SEARCH(Classifiers!$F$15,E7)),1,0))+IF(Classifiers!$G$15="",0,IF(ISNUMBER(SEARCH(Classifiers!$G$15,E7)),1,0)))>0,1,0)) | U7: =IF(H7<>1,0,IF((IF(Classifiers!$B$16="",0,IF(ISNUMBER(SEARCH(Classifiers!$B$16,E7)),1,0))+IF(Classifiers!$C$16="",0,IF(ISNUMBER(SEARCH(Classifiers!$C$16,E7)),1,0))+IF(Classifiers!$D$16="",0,IF(ISNUMBER(SEARCH(Classifiers!$D$16,E7)),1,0))+IF(Classifiers!$E$16="",0,IF(ISNUMBER(SEARCH(Classifiers!$E$16,E7)),1,0))+IF(Classifiers!$F$16="",0,IF(ISNUMBER(SEARCH(Classifiers!$F$16,E7)),1,0))+IF(Classifiers!$G$16="",0,IF(ISNUMBER(SEARCH(Classifiers!$G$16,E7)),1,0)))>0,1,0)) | V7: =IF(H7<>1,0,IF((IF(Classifiers!$B$17="",0,IF(ISNUMBER(SEARCH(Classifiers!$B$17,E7)),1,0))+IF(Classifiers!$C$17="",0,IF(ISNUMBER(SEARCH(Classifiers!$C$17,E7)),1,0))+IF(Classifiers!$D$17="",0,IF(ISNUMBER(SEARCH(Classifiers!$D$17,E7)),1,0))+IF(Classifiers!$E$17="",0,IF(ISNUMBER(SEARCH(Classifiers!$E$17,E7)),1,0))+IF(Classifiers!$F$17="",0,IF(ISNUMBER(SEARCH(Classifiers!$F$17,E7)),1,0))+IF(Classifiers!$G$17="",0,IF(ISNUMBER(SEARCH(Classifiers!$G$17,E7)),1,0)))>0,1,0)) | W7: =IF(H7<>1,0,IF((IF(Classifiers!$B$18="",0,IF(ISNUMBER(SEARCH(Classifiers!$B$18,E7)),1,0))+IF(Classifiers!$C$18="",0,IF(ISNUMBER(SEARCH(Classifiers!$C$18,E7)),1,0))+IF(Classifiers!$D$18="",0,IF(ISNUMBER(SEARCH(Classifiers!$D$18,E7)),1,0))+IF(Classifiers!$E$18="",0,IF(ISNUMBER(SEARCH(Classifiers!$E$18,E7)),1,0))+IF(Classifiers!$F$18="",0,IF(ISNUMBER(SEARCH(Classifiers!$F$18,E7)),1,0))+IF(Classifiers!$G$18="",0,IF(ISNUMBER(SEARCH(Classifiers!$G$18,E7)),1,0)))>0,1,0))
C8: =IF(A8="","",TRIM(RIGHT(SUBSTITUTE(A8,"/",REPT(" ",250)),250))) | D8: =IF(C8="","",IF(ISNUMBER(SEARCH(".",C8)),LOWER("."&TRIM(RIGHT(SUBSTITUTE(C8,".",REPT(" ",250)),250))),"")) | E8: =IF(C8="","",TRIM(SUBSTITUTE(SUBSTITUTE(SUBSTITUTE(SUBSTITUTE(SUBSTITUTE(SUBSTITUTE(SUBSTITUTE(SUBSTITUTE(SUBSTITUTE(SUBSTITUTE(SUBSTITUTE(SUBSTITUTE(SUBSTITUTE(SUBSTITUTE(SUBSTITUTE(SUBSTITUTE(SUBSTITUTE(SUBSTITUTE(SUBSTITUTE(SUBSTITUTE(LOWER(LEFT(C8,LEN(C8)-LEN(D8))),"_"," "),"-"," "),"."," "),","," "),"("," "),")"," "),"["," "),"]"," "),"&"," "),"+"," "),"@"," "),"#"," "),"!"," "),"'"," "),"/"," "),":"," "),";"," "),"="," "),"~"," "),"%"," "))) | F8: =IF(C8="","",IF(COUNTIF(Classifiers!$A$23:$A$40,D8)>0,1,0)) | G8: =IF(C8="","",IF(COUNTIF(Classifiers!$C$23:$C$30,D8)>0,IF((IF(ISNUMBER(SEARCH(Classifiers!$E$23,E8)),1,0)+IF(ISNUMBER(SEARCH(Classifiers!$E$24,E8)),1,0)+IF(ISNUMBER(SEARCH(Classifiers!$E$25,E8)),1,0)+IF(ISNUMBER(SEARCH(Classifiers!$E$26,E8)),1,0)+IF(ISNUMBER(SEARCH(Classifiers!$E$27,E8)),1,0)+IF(ISNUMBER(SEARCH(Classifiers!$E$28,E8)),1,0)+IF(ISNUMBER(SEARCH(Classifiers!$E$29,E8)),1,0)+IF(ISNUMBER(SEARCH(Classifiers!$E$30,E8)),1,0))>0,1,0),0)) | H8: =IF(C8="","",IF(OR(LEFT(C8,1)=".",AND(F8=0,G8=0)),0,1)) | I8: =IF(H8<>1,"",IF(SUM(J8:W8)=0,"unclassified",INDEX(Classifiers!$A$5:$A$18,MATCH(1,J8:W8,0),1))) | J8: =IF(H8<>1,0,IF((IF(Classifiers!$B$5="",0,IF(ISNUMBER(SEARCH(Classifiers!$B$5,E8)),1,0))+IF(Classifiers!$C$5="",0,IF(ISNUMBER(SEARCH(Classifiers!$C$5,E8)),1,0))+IF(Classifiers!$D$5="",0,IF(ISNUMBER(SEARCH(Classifiers!$D$5,E8)),1,0))+IF(Classifiers!$E$5="",0,IF(ISNUMBER(SEARCH(Classifiers!$E$5,E8)),1,0))+IF(Classifiers!$F$5="",0,IF(ISNUMBER(SEARCH(Classifiers!$F$5,E8)),1,0))+IF(Classifiers!$G$5="",0,IF(ISNUMBER(SEARCH(Classifiers!$G$5,E8)),1,0)))>0,1,0)) | K8: =IF(H8<>1,0,IF((IF(Classifiers!$B$6="",0,IF(ISNUMBER(SEARCH(Classifiers!$B$6,E8)),1,0))+IF(Classifiers!$C$6="",0,IF(ISNUMBER(SEARCH(Classifiers!$C$6,E8)),1,0))+IF(Classifiers!$D$6="",0,IF(ISNUMBER(SEARCH(Classifiers!$D$6,E8)),1,0))+IF(Classifiers!$E$6="",0,IF(ISNUMBER(SEARCH(Classifiers!$E$6,E8)),1,0))+IF(Classifiers!$F$6="",0,IF(ISNUMBER(SEARCH(Classifiers!$F$6,E8)),1,0))+IF(Classifiers!$G$6="",0,IF(ISNUMBER(SEARCH(Classifiers!$G$6,E8)),1,0)))>0,1,0)) | L8: =IF(H8<>1,0,IF((IF(Classifiers!$B$7="",0,IF(ISNUMBER(SEARCH(Classifiers!$B$7,E8)),1,0))+IF(Classifiers!$C$7="",0,IF(ISNUMBER(SEARCH(Classifiers!$C$7,E8)),1,0))+IF(Classifiers!$D$7="",0,IF(ISNUMBER(SEARCH(Classifiers!$D$7,E8)),1,0))+IF(Classifiers!$E$7="",0,IF(ISNUMBER(SEARCH(Classifiers!$E$7,E8)),1,0))+IF(Classifiers!$F$7="",0,IF(ISNUMBER(SEARCH(Classifiers!$F$7,E8)),1,0))+IF(Classifiers!$G$7="",0,IF(ISNUMBER(SEARCH(Classifiers!$G$7,E8)),1,0)))>0,1,0)) | M8: =IF(H8<>1,0,IF((IF(Classifiers!$B$8="",0,IF(ISNUMBER(SEARCH(Classifiers!$B$8,E8)),1,0))+IF(Classifiers!$C$8="",0,IF(ISNUMBER(SEARCH(Classifiers!$C$8,E8)),1,0))+IF(Classifiers!$D$8="",0,IF(ISNUMBER(SEARCH(Classifiers!$D$8,E8)),1,0))+IF(Classifiers!$E$8="",0,IF(ISNUMBER(SEARCH(Classifiers!$E$8,E8)),1,0))+IF(Classifiers!$F$8="",0,IF(ISNUMBER(SEARCH(Classifiers!$F$8,E8)),1,0))+IF(Classifiers!$G$8="",0,IF(ISNUMBER(SEARCH(Classifiers!$G$8,E8)),1,0)))>0,1,0)) | N8: =IF(H8<>1,0,IF((IF(Classifiers!$B$9="",0,IF(ISNUMBER(SEARCH(Classifiers!$B$9,E8)),1,0))+IF(Classifiers!$C$9="",0,IF(ISNUMBER(SEARCH(Classifiers!$C$9,E8)),1,0))+IF(Classifiers!$D$9="",0,IF(ISNUMBER(SEARCH(Classifiers!$D$9,E8)),1,0))+IF(Classifiers!$E$9="",0,IF(ISNUMBER(SEARCH(Classifiers!$E$9,E8)),1,0))+IF(Classifiers!$F$9="",0,IF(ISNUMBER(SEARCH(Classifiers!$F$9,E8)),1,0))+IF(Classifiers!$G$9="",0,IF(ISNUMBER(SEARCH(Classifiers!$G$9,E8)),1,0)))>0,1,0)) | O8: =IF(H8<>1,0,IF((IF(Classifiers!$B$10="",0,IF(ISNUMBER(SEARCH(Classifiers!$B$10,E8)),1,0))+IF(Classifiers!$C$10="",0,IF(ISNUMBER(SEARCH(Classifiers!$C$10,E8)),1,0))+IF(Classifiers!$D$10="",0,IF(ISNUMBER(SEARCH(Classifiers!$D$10,E8)),1,0))+IF(Classifiers!$E$10="",0,IF(ISNUMBER(SEARCH(Classifiers!$E$10,E8)),1,0))+IF(Classifiers!$F$10="",0,IF(ISNUMBER(SEARCH(Classifiers!$F$10,E8)),1,0))+IF(Classifiers!$G$10="",0,IF(ISNUMBER(SEARCH(Classifiers!$G$10,E8)),1,0)))>0,1,0)) | P8: =IF(H8<>1,0,IF((IF(Classifiers!$B$11="",0,IF(ISNUMBER(SEARCH(Classifiers!$B$11,E8)),1,0))+IF(Classifiers!$C$11="",0,IF(ISNUMBER(SEARCH(Classifiers!$C$11,E8)),1,0))+IF(Classifiers!$D$11="",0,IF(ISNUMBER(SEARCH(Classifiers!$D$11,E8)),1,0))+IF(Classifiers!$E$11="",0,IF(ISNUMBER(SEARCH(Classifiers!$E$11,E8)),1,0))+IF(Classifiers!$F$11="",0,IF(ISNUMBER(SEARCH(Classifiers!$F$11,E8)),1,0))+IF(Classifiers!$G$11="",0,IF(ISNUMBER(SEARCH(Classifiers!$G$11,E8)),1,0)))>0,1,0)) | Q8: =IF(H8<>1,0,IF((IF(Classifiers!$B$12="",0,IF(ISNUMBER(SEARCH(Classifiers!$B$12,E8)),1,0))+IF(Classifiers!$C$12="",0,IF(ISNUMBER(SEARCH(Classifiers!$C$12,E8)),1,0))+IF(Classifiers!$D$12="",0,IF(ISNUMBER(SEARCH(Classifiers!$D$12,E8)),1,0))+IF(Classifiers!$E$12="",0,IF(ISNUMBER(SEARCH(Classifiers!$E$12,E8)),1,0))+IF(Classifiers!$F$12="",0,IF(ISNUMBER(SEARCH(Classifiers!$F$12,E8)),1,0))+IF(Classifiers!$G$12="",0,IF(ISNUMBER(SEARCH(Classifiers!$G$12,E8)),1,0)))>0,1,0)) | R8: =IF(H8<>1,0,IF((IF(Classifiers!$B$13="",0,IF(ISNUMBER(SEARCH(Classifiers!$B$13,E8)),1,0))+IF(Classifiers!$C$13="",0,IF(ISNUMBER(SEARCH(Classifiers!$C$13,E8)),1,0))+IF(Classifiers!$D$13="",0,IF(ISNUMBER(SEARCH(Classifiers!$D$13,E8)),1,0))+IF(Classifiers!$E$13="",0,IF(ISNUMBER(SEARCH(Classifiers!$E$13,E8)),1,0))+IF(Classifiers!$F$13="",0,IF(ISNUMBER(SEARCH(Classifiers!$F$13,E8)),1,0))+IF(Classifiers!$G$13="",0,IF(ISNUMBER(SEARCH(Classifiers!$G$13,E8)),1,0)))>0,1,0)) | S8: =IF(H8<>1,0,IF((IF(Classifiers!$B$14="",0,IF(ISNUMBER(SEARCH(Classifiers!$B$14,E8)),1,0))+IF(Classifiers!$C$14="",0,IF(ISNUMBER(SEARCH(Classifiers!$C$14,E8)),1,0))+IF(Classifiers!$D$14="",0,IF(ISNUMBER(SEARCH(Classifiers!$D$14,E8)),1,0))+IF(Classifiers!$E$14="",0,IF(ISNUMBER(SEARCH(Classifiers!$E$14,E8)),1,0))+IF(Classifiers!$F$14="",0,IF(ISNUMBER(SEARCH(Classifiers!$F$14,E8)),1,0))+IF(Classifiers!$G$14="",0,IF(ISNUMBER(SEARCH(Classifiers!$G$14,E8)),1,0)))>0,1,0)) | T8: =IF(H8<>1,0,IF((IF(Classifiers!$B$15="",0,IF(ISNUMBER(SEARCH(Classifiers!$B$15,E8)),1,0))+IF(Classifiers!$C$15="",0,IF(ISNUMBER(SEARCH(Classifiers!$C$15,E8)),1,0))+IF(Classifiers!$D$15="",0,IF(ISNUMBER(SEARCH(Classifiers!$D$15,E8)),1,0))+IF(Classifiers!$E$15="",0,IF(ISNUMBER(SEARCH(Classifiers!$E$15,E8)),1,0))+IF(Classifiers!$F$15="",0,IF(ISNUMBER(SEARCH(Classifiers!$F$15,E8)),1,0))+IF(Classifiers!$G$15="",0,IF(ISNUMBER(SEARCH(Classifiers!$G$15,E8)),1,0)))>0,1,0)) | U8: =IF(H8<>1,0,IF((IF(Classifiers!$B$16="",0,IF(ISNUMBER(SEARCH(Classifiers!$B$16,E8)),1,0))+IF(Classifiers!$C$16="",0,IF(ISNUMBER(SEARCH(Classifiers!$C$16,E8)),1,0))+IF(Classifiers!$D$16="",0,IF(ISNUMBER(SEARCH(Classifiers!$D$16,E8)),1,0))+IF(Classifiers!$E$16="",0,IF(ISNUMBER(SEARCH(Classifiers!$E$16,E8)),1,0))+IF(Classifiers!$F$16="",0,IF(ISNUMBER(SEARCH(Classifiers!$F$16,E8)),1,0))+IF(Classifiers!$G$16="",0,IF(ISNUMBER(SEARCH(Classifiers!$G$16,E8)),1,0)))>0,1,0)) | V8: =IF(H8<>1,0,IF((IF(Classifiers!$B$17="",0,IF(ISNUMBER(SEARCH(Classifiers!$B$17,E8)),1,0))+IF(Classifiers!$C$17="",0,IF(ISNUMBER(SEARCH(Classifiers!$C$17,E8)),1,0))+IF(Classifiers!$D$17="",0,IF(ISNUMBER(SEARCH(Classifiers!$D$17,E8)),1,0))+IF(Classifiers!$E$17="",0,IF(ISNUMBER(SEARCH(Classifiers!$E$17,E8)),1,0))+IF(Classifiers!$F$17="",0,IF(ISNUMBER(SEARCH(Classifiers!$F$17,E8)),1,0))+IF(Classifiers!$G$17="",0,IF(ISNUMBER(SEARCH(Classifiers!$G$17,E8)),1,0)))>0,1,0)) | W8: =IF(H8<>1,0,IF((IF(Classifiers!$B$18="",0,IF(ISNUMBER(SEARCH(Classifiers!$B$18,E8)),1,0))+IF(Classifiers!$C$18="",0,IF(ISNUMBER(SEARCH(Classifiers!$C$18,E8)),1,0))+IF(Classifiers!$D$18="",0,IF(ISNUMBER(SEARCH(Classifiers!$D$18,E8)),1,0))+IF(Classifiers!$E$18="",0,IF(ISNUMBER(SEARCH(Classifiers!$E$18,E8)),1,0))+IF(Classifiers!$F$18="",0,IF(ISNUMBER(SEARCH(Classifiers!$F$18,E8)),1,0))+IF(Classifiers!$G$18="",0,IF(ISNUMBER(SEARCH(Classifiers!$G$18,E8)),1,0)))>0,1,0))
C9: =IF(A9="","",TRIM(RIGHT(SUBSTITUTE(A9,"/",REPT(" ",250)),250))) | D9: =IF(C9="","",IF(ISNUMBER(SEARCH(".",C9)),LOWER("."&TRIM(RIGHT(SUBSTITUTE(C9,".",REPT(" ",250)),250))),"")) | E9: =IF(C9="","",TRIM(SUBSTITUTE(SUBSTITUTE(SUBSTITUTE(SUBSTITUTE(SUBSTITUTE(SUBSTITUTE(SUBSTITUTE(SUBSTITUTE(SUBSTITUTE(SUBSTITUTE(SUBSTITUTE(SUBSTITUTE(SUBSTITUTE(SUBSTITUTE(SUBSTITUTE(SUBSTITUTE(SUBSTITUTE(SUBSTITUTE(SUBSTITUTE(SUBSTITUTE(LOWER(LEFT(C9,LEN(C9)-LEN(D9))),"_"," "),"-"," "),"."," "),","," "),"("," "),")"," "),"["," "),"]"," "),"&"," "),"+"," "),"@"," "),"#"," "),"!"," "),"'"," "),"/"," "),":"," "),";"," "),"="," "),"~"," "),"%"," "))) | F9: =IF(C9="","",IF(COUNTIF(Classifiers!$A$23:$A$40,D9)>0,1,0)) | G9: =IF(C9="","",IF(COUNTIF(Classifiers!$C$23:$C$30,D9)>0,IF((IF(ISNUMBER(SEARCH(Classifiers!$E$23,E9)),1,0)+IF(ISNUMBER(SEARCH(Classifiers!$E$24,E9)),1,0)+IF(ISNUMBER(SEARCH(Classifiers!$E$25,E9)),1,0)+IF(ISNUMBER(SEARCH(Classifiers!$E$26,E9)),1,0)+IF(ISNUMBER(SEARCH(Classifiers!$E$27,E9)),1,0)+IF(ISNUMBER(SEARCH(Classifiers!$E$28,E9)),1,0)+IF(ISNUMBER(SEARCH(Classifiers!$E$29,E9)),1,0)+IF(ISNUMBER(SEARCH(Classifiers!$E$30,E9)),1,0))>0,1,0),0)) | H9: =IF(C9="","",IF(OR(LEFT(C9,1)=".",AND(F9=0,G9=0)),0,1)) | I9: =IF(H9<>1,"",IF(SUM(J9:W9)=0,"unclassified",INDEX(Classifiers!$A$5:$A$18,MATCH(1,J9:W9,0),1))) | J9: =IF(H9<>1,0,IF((IF(Classifiers!$B$5="",0,IF(ISNUMBER(SEARCH(Classifiers!$B$5,E9)),1,0))+IF(Classifiers!$C$5="",0,IF(ISNUMBER(SEARCH(Classifiers!$C$5,E9)),1,0))+IF(Classifiers!$D$5="",0,IF(ISNUMBER(SEARCH(Classifiers!$D$5,E9)),1,0))+IF(Classifiers!$E$5="",0,IF(ISNUMBER(SEARCH(Classifiers!$E$5,E9)),1,0))+IF(Classifiers!$F$5="",0,IF(ISNUMBER(SEARCH(Classifiers!$F$5,E9)),1,0))+IF(Classifiers!$G$5="",0,IF(ISNUMBER(SEARCH(Classifiers!$G$5,E9)),1,0)))>0,1,0)) | K9: =IF(H9<>1,0,IF((IF(Classifiers!$B$6="",0,IF(ISNUMBER(SEARCH(Classifiers!$B$6,E9)),1,0))+IF(Classifiers!$C$6="",0,IF(ISNUMBER(SEARCH(Classifiers!$C$6,E9)),1,0))+IF(Classifiers!$D$6="",0,IF(ISNUMBER(SEARCH(Classifiers!$D$6,E9)),1,0))+IF(Classifiers!$E$6="",0,IF(ISNUMBER(SEARCH(Classifiers!$E$6,E9)),1,0))+IF(Classifiers!$F$6="",0,IF(ISNUMBER(SEARCH(Classifiers!$F$6,E9)),1,0))+IF(Classifiers!$G$6="",0,IF(ISNUMBER(SEARCH(Classifiers!$G$6,E9)),1,0)))>0,1,0)) | L9: =IF(H9<>1,0,IF((IF(Classifiers!$B$7="",0,IF(ISNUMBER(SEARCH(Classifiers!$B$7,E9)),1,0))+IF(Classifiers!$C$7="",0,IF(ISNUMBER(SEARCH(Classifiers!$C$7,E9)),1,0))+IF(Classifiers!$D$7="",0,IF(ISNUMBER(SEARCH(Classifiers!$D$7,E9)),1,0))+IF(Classifiers!$E$7="",0,IF(ISNUMBER(SEARCH(Classifiers!$E$7,E9)),1,0))+IF(Classifiers!$F$7="",0,IF(ISNUMBER(SEARCH(Classifiers!$F$7,E9)),1,0))+IF(Classifiers!$G$7="",0,IF(ISNUMBER(SEARCH(Classifiers!$G$7,E9)),1,0)))>0,1,0)) | M9: =IF(H9<>1,0,IF((IF(Classifiers!$B$8="",0,IF(ISNUMBER(SEARCH(Classifiers!$B$8,E9)),1,0))+IF(Classifiers!$C$8="",0,IF(ISNUMBER(SEARCH(Classifiers!$C$8,E9)),1,0))+IF(Classifiers!$D$8="",0,IF(ISNUMBER(SEARCH(Classifiers!$D$8,E9)),1,0))+IF(Classifiers!$E$8="",0,IF(ISNUMBER(SEARCH(Classifiers!$E$8,E9)),1,0))+IF(Classifiers!$F$8="",0,IF(ISNUMBER(SEARCH(Classifiers!$F$8,E9)),1,0))+IF(Classifiers!$G$8="",0,IF(ISNUMBER(SEARCH(Classifiers!$G$8,E9)),1,0)))>0,1,0)) | N9: =IF(H9<>1,0,IF((IF(Classifiers!$B$9="",0,IF(ISNUMBER(SEARCH(Classifiers!$B$9,E9)),1,0))+IF(Classifiers!$C$9="",0,IF(ISNUMBER(SEARCH(Classifiers!$C$9,E9)),1,0))+IF(Classifiers!$D$9="",0,IF(ISNUMBER(SEARCH(Classifiers!$D$9,E9)),1,0))+IF(Classifiers!$E$9="",0,IF(ISNUMBER(SEARCH(Classifiers!$E$9,E9)),1,0))+IF(Classifiers!$F$9="",0,IF(ISNUMBER(SEARCH(Classifiers!$F$9,E9)),1,0))+IF(Classifiers!$G$9="",0,IF(ISNUMBER(SEARCH(Classifiers!$G$9,E9)),1,0)))>0,1,0)) | O9: =IF(H9<>1,0,IF((IF(Classifiers!$B$10="",0,IF(ISNUMBER(SEARCH(Classifiers!$B$10,E9)),1,0))+IF(Classifiers!$C$10="",0,IF(ISNUMBER(SEARCH(Classifiers!$C$10,E9)),1,0))+IF(Classifiers!$D$10="",0,IF(ISNUMBER(SEARCH(Classifiers!$D$10,E9)),1,0))+IF(Classifiers!$E$10="",0,IF(ISNUMBER(SEARCH(Classifiers!$E$10,E9)),1,0))+IF(Classifiers!$F$10="",0,IF(ISNUMBER(SEARCH(Classifiers!$F$10,E9)),1,0))+IF(Classifiers!$G$10="",0,IF(ISNUMBER(SEARCH(Classifiers!$G$10,E9)),1,0)))>0,1,0)) | P9: =IF(H9<>1,0,IF((IF(Classifiers!$B$11="",0,IF(ISNUMBER(SEARCH(Classifiers!$B$11,E9)),1,0))+IF(Classifiers!$C$11="",0,IF(ISNUMBER(SEARCH(Classifiers!$C$11,E9)),1,0))+IF(Classifiers!$D$11="",0,IF(ISNUMBER(SEARCH(Classifiers!$D$11,E9)),1,0))+IF(Classifiers!$E$11="",0,IF(ISNUMBER(SEARCH(Classifiers!$E$11,E9)),1,0))+IF(Classifiers!$F$11="",0,IF(ISNUMBER(SEARCH(Classifiers!$F$11,E9)),1,0))+IF(Classifiers!$G$11="",0,IF(ISNUMBER(SEARCH(Classifiers!$G$11,E9)),1,0)))>0,1,0)) | Q9: =IF(H9<>1,0,IF((IF(Classifiers!$B$12="",0,IF(ISNUMBER(SEARCH(Classifiers!$B$12,E9)),1,0))+IF(Classifiers!$C$12="",0,IF(ISNUMBER(SEARCH(Classifiers!$C$12,E9)),1,0))+IF(Classifiers!$D$12="",0,IF(ISNUMBER(SEARCH(Classifiers!$D$12,E9)),1,0))+IF(Classifiers!$E$12="",0,IF(ISNUMBER(SEARCH(Classifiers!$E$12,E9)),1,0))+IF(Classifiers!$F$12="",0,IF(ISNUMBER(SEARCH(Classifiers!$F$12,E9)),1,0))+IF(Classifiers!$G$12="",0,IF(ISNUMBER(SEARCH(Classifiers!$G$12,E9)),1,0)))>0,1,0)) | R9: =IF(H9<>1,0,IF((IF(Classifiers!$B$13="",0,IF(ISNUMBER(SEARCH(Classifiers!$B$13,E9)),1,0))+IF(Classifiers!$C$13="",0,IF(ISNUMBER(SEARCH(Classifiers!$C$13,E9)),1,0))+IF(Classifiers!$D$13="",0,IF(ISNUMBER(SEARCH(Classifiers!$D$13,E9)),1,0))+IF(Classifiers!$E$13="",0,IF(ISNUMBER(SEARCH(Classifiers!$E$13,E9)),1,0))+IF(Classifiers!$F$13="",0,IF(ISNUMBER(SEARCH(Classifiers!$F$13,E9)),1,0))+IF(Classifiers!$G$13="",0,IF(ISNUMBER(SEARCH(Classifiers!$G$13,E9)),1,0)))>0,1,0)) | S9: =IF(H9<>1,0,IF((IF(Classifiers!$B$14="",0,IF(ISNUMBER(SEARCH(Classifiers!$B$14,E9)),1,0))+IF(Classifiers!$C$14="",0,IF(ISNUMBER(SEARCH(Classifiers!$C$14,E9)),1,0))+IF(Classifiers!$D$14="",0,IF(ISNUMBER(SEARCH(Classifiers!$D$14,E9)),1,0))+IF(Classifiers!$E$14="",0,IF(ISNUMBER(SEARCH(Classifiers!$E$14,E9)),1,0))+IF(Classifiers!$F$14="",0,IF(ISNUMBER(SEARCH(Classifiers!$F$14,E9)),1,0))+IF(Classifiers!$G$14="",0,IF(ISNUMBER(SEARCH(Classifiers!$G$14,E9)),1,0)))>0,1,0)) | T9: =IF(H9<>1,0,IF((IF(Classifiers!$B$15="",0,IF(ISNUMBER(SEARCH(Classifiers!$B$15,E9)),1,0))+IF(Classifiers!$C$15="",0,IF(ISNUMBER(SEARCH(Classifiers!$C$15,E9)),1,0))+IF(Classifiers!$D$15="",0,IF(ISNUMBER(SEARCH(Classifiers!$D$15,E9)),1,0))+IF(Classifiers!$E$15="",0,IF(ISNUMBER(SEARCH(Classifiers!$E$15,E9)),1,0))+IF(Classifiers!$F$15="",0,IF(ISNUMBER(SEARCH(Classifiers!$F$15,E9)),1,0))+IF(Classifiers!$G$15="",0,IF(ISNUMBER(SEARCH(Classifiers!$G$15,E9)),1,0)))>0,1,0)) | U9: =IF(H9<>1,0,IF((IF(Classifiers!$B$16="",0,IF(ISNUMBER(SEARCH(Classifiers!$B$16,E9)),1,0))+IF(Classifiers!$C$16="",0,IF(ISNUMBER(SEARCH(Classifiers!$C$16,E9)),1,0))+IF(Classifiers!$D$16="",0,IF(ISNUMBER(SEARCH(Classifiers!$D$16,E9)),1,0))+IF(Classifiers!$E$16="",0,IF(ISNUMBER(SEARCH(Classifiers!$E$16,E9)),1,0))+IF(Classifiers!$F$16="",0,IF(ISNUMBER(SEARCH(Classifiers!$F$16,E9)),1,0))+IF(Classifiers!$G$16="",0,IF(ISNUMBER(SEARCH(Classifiers!$G$16,E9)),1,0)))>0,1,0)) | V9: =IF(H9<>1,0,IF((IF(Classifiers!$B$17="",0,IF(ISNUMBER(SEARCH(Classifiers!$B$17,E9)),1,0))+IF(Classifiers!$C$17="",0,IF(ISNUMBER(SEARCH(Classifiers!$C$17,E9)),1,0))+IF(Classifiers!$D$17="",0,IF(ISNUMBER(SEARCH(Classifiers!$D$17,E9)),1,0))+IF(Classifiers!$E$17="",0,IF(ISNUMBER(SEARCH(Classifiers!$E$17,E9)),1,0))+IF(Classifiers!$F$17="",0,IF(ISNUMBER(SEARCH(Classifiers!$F$17,E9)),1,0))+IF(Classifiers!$G$17="",0,IF(ISNUMBER(SEARCH(Classifiers!$G$17,E9)),1,0)))>0,1,0)) | W9: =IF(H9<>1,0,IF((IF(Classifiers!$B$18="",0,IF(ISNUMBER(SEARCH(Classifiers!$B$18,E9)),1,0))+IF(Classifiers!$C$18="",0,IF(ISNUMBER(SEARCH(Classifiers!$C$18,E9)),1,0))+IF(Classifiers!$D$18="",0,IF(ISNUMBER(SEARCH(Classifiers!$D$18,E9)),1,0))+IF(Classifiers!$E$18="",0,IF(ISNUMBER(SEARCH(Classifiers!$E$18,E9)),1,0))+IF(Classifiers!$F$18="",0,IF(ISNUMBER(SEARCH(Classifiers!$F$18,E9)),1,0))+IF(Classifiers!$G$18="",0,IF(ISNUMBER(SEARCH(Classifiers!$G$18,E9)),1,0)))>0,1,0))
C10: =IF(A10="","",TRIM(RIGHT(SUBSTITUTE(A10,"/",REPT(" ",250)),250))) | D10: =IF(C10="","",IF(ISNUMBER(SEARCH(".",C10)),LOWER("."&TRIM(RIGHT(SUBSTITUTE(C10,".",REPT(" ",250)),250))),"")) | E10: =IF(C10="","",TRIM(SUBSTITUTE(SUBSTITUTE(SUBSTITUTE(SUBSTITUTE(SUBSTITUTE(SUBSTITUTE(SUBSTITUTE(SUBSTITUTE(SUBSTITUTE(SUBSTITUTE(SUBSTITUTE(SUBSTITUTE(SUBSTITUTE(SUBSTITUTE(SUBSTITUTE(SUBSTITUTE(SUBSTITUTE(SUBSTITUTE(SUBSTITUTE(SUBSTITUTE(LOWER(LEFT(C10,LEN(C10)-LEN(D10))),"_"," "),"-"," "),"."," "),","," "),"("," "),")"," "),"["," "),"]"," "),"&"," "),"+"," "),"@"," "),"#"," "),"!"," "),"'"," "),"/"," "),":"," "),";"," "),"="," "),"~"," "),"%"," "))) | F10: =IF(C10="","",IF(COUNTIF(Classifiers!$A$23:$A$40,D10)>0,1,0)) | G10: =IF(C10="","",IF(COUNTIF(Classifiers!$C$23:$C$30,D10)>0,IF((IF(ISNUMBER(SEARCH(Classifiers!$E$23,E10)),1,0)+IF(ISNUMBER(SEARCH(Classifiers!$E$24,E10)),1,0)+IF(ISNUMBER(SEARCH(Classifiers!$E$25,E10)),1,0)+IF(ISNUMBER(SEARCH(Classifiers!$E$26,E10)),1,0)+IF(ISNUMBER(SEARCH(Classifiers!$E$27,E10)),1,0)+IF(ISNUMBER(SEARCH(Classifiers!$E$28,E10)),1,0)+IF(ISNUMBER(SEARCH(Classifiers!$E$29,E10)),1,0)+IF(ISNUMBER(SEARCH(Classifiers!$E$30,E10)),1,0))>0,1,0),0)) | H10: =IF(C10="","",IF(OR(LEFT(C10,1)=".",AND(F10=0,G10=0)),0,1)) | I10: =IF(H10<>1,"",IF(SUM(J10:W10)=0,"unclassified",INDEX(Classifiers!$A$5:$A$18,MATCH(1,J10:W10,0),1))) | J10: =IF(H10<>1,0,IF((IF(Classifiers!$B$5="",0,IF(ISNUMBER(SEARCH(Classifiers!$B$5,E10)),1,0))+IF(Classifiers!$C$5="",0,IF(ISNUMBER(SEARCH(Classifiers!$C$5,E10)),1,0))+IF(Classifiers!$D$5="",0,IF(ISNUMBER(SEARCH(Classifiers!$D$5,E10)),1,0))+IF(Classifiers!$E$5="",0,IF(ISNUMBER(SEARCH(Classifiers!$E$5,E10)),1,0))+IF(Classifiers!$F$5="",0,IF(ISNUMBER(SEARCH(Classifiers!$F$5,E10)),1,0))+IF(Classifiers!$G$5="",0,IF(ISNUMBER(SEARCH(Classifiers!$G$5,E10)),1,0)))>0,1,0)) | K10: =IF(H10<>1,0,IF((IF(Classifiers!$B$6="",0,IF(ISNUMBER(SEARCH(Classifiers!$B$6,E10)),1,0))+IF(Classifiers!$C$6="",0,IF(ISNUMBER(SEARCH(Classifiers!$C$6,E10)),1,0))+IF(Classifiers!$D$6="",0,IF(ISNUMBER(SEARCH(Classifiers!$D$6,E10)),1,0))+IF(Classifiers!$E$6="",0,IF(ISNUMBER(SEARCH(Classifiers!$E$6,E10)),1,0))+IF(Classifiers!$F$6="",0,IF(ISNUMBER(SEARCH(Classifiers!$F$6,E10)),1,0))+IF(Classifiers!$G$6="",0,IF(ISNUMBER(SEARCH(Classifiers!$G$6,E10)),1,0)))>0,1,0)) | L10: =IF(H10<>1,0,IF((IF(Classifiers!$B$7="",0,IF(ISNUMBER(SEARCH(Classifiers!$B$7,E10)),1,0))+IF(Classifiers!$C$7="",0,IF(ISNUMBER(SEARCH(Classifiers!$C$7,E10)),1,0))+IF(Classifiers!$D$7="",0,IF(ISNUMBER(SEARCH(Classifiers!$D$7,E10)),1,0))+IF(Classifiers!$E$7="",0,IF(ISNUMBER(SEARCH(Classifiers!$E$7,E10)),1,0))+IF(Classifiers!$F$7="",0,IF(ISNUMBER(SEARCH(Classifiers!$F$7,E10)),1,0))+IF(Classifiers!$G$7="",0,IF(ISNUMBER(SEARCH(Classifiers!$G$7,E10)),1,0)))>0,1,0)) | M10: =IF(H10<>1,0,IF((IF(Classifiers!$B$8="",0,IF(ISNUMBER(SEARCH(Classifiers!$B$8,E10)),1,0))+IF(Classifiers!$C$8="",0,IF(ISNUMBER(SEARCH(Classifiers!$C$8,E10)),1,0))+IF(Classifiers!$D$8="",0,IF(ISNUMBER(SEARCH(Classifiers!$D$8,E10)),1,0))+IF(Classifiers!$E$8="",0,IF(ISNUMBER(SEARCH(Classifiers!$E$8,E10)),1,0))+IF(Classifiers!$F$8="",0,IF(ISNUMBER(SEARCH(Classifiers!$F$8,E10)),1,0))+IF(Classifiers!$G$8="",0,IF(ISNUMBER(SEARCH(Classifiers!$G$8,E10)),1,0)))>0,1,0)) | N10: =IF(H10<>1,0,IF((IF(Classifiers!$B$9="",0,IF(ISNUMBER(SEARCH(Classifiers!$B$9,E10)),1,0))+IF(Classifiers!$C$9="",0,IF(ISNUMBER(SEARCH(Classifiers!$C$9,E10)),1,0))+IF(Classifiers!$D$9="",0,IF(ISNUMBER(SEARCH(Classifiers!$D$9,E10)),1,0))+IF(Classifiers!$E$9="",0,IF(ISNUMBER(SEARCH(Classifiers!$E$9,E10)),1,0))+IF(Classifiers!$F$9="",0,IF(ISNUMBER(SEARCH(Classifiers!$F$9,E10)),1,0))+IF(Classifiers!$G$9="",0,IF(ISNUMBER(SEARCH(Classifiers!$G$9,E10)),1,0)))>0,1,0)) | O10: =IF(H10<>1,0,IF((IF(Classifiers!$B$10="",0,IF(ISNUMBER(SEARCH(Classifiers!$B$10,E10)),1,0))+IF(Classifiers!$C$10="",0,IF(ISNUMBER(SEARCH(Classifiers!$C$10,E10)),1,0))+IF(Classifiers!$D$10="",0,IF(ISNUMBER(SEARCH(Classifiers!$D$10,E10)),1,0))+IF(Classifiers!$E$10="",0,IF(ISNUMBER(SEARCH(Classifiers!$E$10,E10)),1,0))+IF(Classifiers!$F$10="",0,IF(ISNUMBER(SEARCH(Classifiers!$F$10,E10)),1,0))+IF(Classifiers!$G$10="",0,IF(ISNUMBER(SEARCH(Classifiers!$G$10,E10)),1,0)))>0,1,0)) | P10: =IF(H10<>1,0,IF((IF(Classifiers!$B$11="",0,IF(ISNUMBER(SEARCH(Classifiers!$B$11,E10)),1,0))+IF(Classifiers!$C$11="",0,IF(ISNUMBER(SEARCH(Classifiers!$C$11,E10)),1,0))+IF(Classifiers!$D$11="",0,IF(ISNUMBER(SEARCH(Classifiers!$D$11,E10)),1,0))+IF(Classifiers!$E$11="",0,IF(ISNUMBER(SEARCH(Classifiers!$E$11,E10)),1,0))+IF(Classifiers!$F$11="",0,IF(ISNUMBER(SEARCH(Classifiers!$F$11,E10)),1,0))+IF(Classifiers!$G$11="",0,IF(ISNUMBER(SEARCH(Classifiers!$G$11,E10)),1,0)))>0,1,0)) | Q10: =IF(H10<>1,0,IF((IF(Classifiers!$B$12="",0,IF(ISNUMBER(SEARCH(Classifiers!$B$12,E10)),1,0))+IF(Classifiers!$C$12="",0,IF(ISNUMBER(SEARCH(Classifiers!$C$12,E10)),1,0))+IF(Classifiers!$D$12="",0,IF(ISNUMBER(SEARCH(Classifiers!$D$12,E10)),1,0))+IF(Classifiers!$E$12="",0,IF(ISNUMBER(SEARCH(Classifiers!$E$12,E10)),1,0))+IF(Classifiers!$F$12="",0,IF(ISNUMBER(SEARCH(Classifiers!$F$12,E10)),1,0))+IF(Classifiers!$G$12="",0,IF(ISNUMBER(SEARCH(Classifiers!$G$12,E10)),1,0)))>0,1,0)) | R10: =IF(H10<>1,0,IF((IF(Classifiers!$B$13="",0,IF(ISNUMBER(SEARCH(Classifiers!$B$13,E10)),1,0))+IF(Classifiers!$C$13="",0,IF(ISNUMBER(SEARCH(Classifiers!$C$13,E10)),1,0))+IF(Classifiers!$D$13="",0,IF(ISNUMBER(SEARCH(Classifiers!$D$13,E10)),1,0))+IF(Classifiers!$E$13="",0,IF(ISNUMBER(SEARCH(Classifiers!$E$13,E10)),1,0))+IF(Classifiers!$F$13="",0,IF(ISNUMBER(SEARCH(Classifiers!$F$13,E10)),1,0))+IF(Classifiers!$G$13="",0,IF(ISNUMBER(SEARCH(Classifiers!$G$13,E10)),1,0)))>0,1,0)) | S10: =IF(H10<>1,0,IF((IF(Classifiers!$B$14="",0,IF(ISNUMBER(SEARCH(Classifiers!$B$14,E10)),1,0))+IF(Classifiers!$C$14="",0,IF(ISNUMBER(SEARCH(Classifiers!$C$14,E10)),1,0))+IF(Classifiers!$D$14="",0,IF(ISNUMBER(SEARCH(Classifiers!$D$14,E10)),1,0))+IF(Classifiers!$E$14="",0,IF(ISNUMBER(SEARCH(Classifiers!$E$14,E10)),1,0))+IF(Classifiers!$F$14="",0,IF(ISNUMBER(SEARCH(Classifiers!$F$14,E10)),1,0))+IF(Classifiers!$G$14="",0,IF(ISNUMBER(SEARCH(Classifiers!$G$14,E10)),1,0)))>0,1,0)) | T10: =IF(H10<>1,0,IF((IF(Classifiers!$B$15="",0,IF(ISNUMBER(SEARCH(Classifiers!$B$15,E10)),1,0))+IF(Classifiers!$C$15="",0,IF(ISNUMBER(SEARCH(Classifiers!$C$15,E10)),1,0))+IF(Classifiers!$D$15="",0,IF(ISNUMBER(SEARCH(Classifiers!$D$15,E10)),1,0))+IF(Classifiers!$E$15="",0,IF(ISNUMBER(SEARCH(Classifiers!$E$15,E10)),1,0))+IF(Classifiers!$F$15="",0,IF(ISNUMBER(SEARCH(Classifiers!$F$15,E10)),1,0))+IF(Classifiers!$G$15="",0,IF(ISNUMBER(SEARCH(Classifiers!$G$15,E10)),1,0)))>0,1,0)) | U10: =IF(H10<>1,0,IF((IF(Classifiers!$B$16="",0,IF(ISNUMBER(SEARCH(Classifiers!$B$16,E10)),1,0))+IF(Classifiers!$C$16="",0,IF(ISNUMBER(SEARCH(Classifiers!$C$16,E10)),1,0))+IF(Classifiers!$D$16="",0,IF(ISNUMBER(SEARCH(Classifiers!$D$16,E10)),1,0))+IF(Classifiers!$E$16="",0,IF(ISNUMBER(SEARCH(Classifiers!$E$16,E10)),1,0))+IF(Classifiers!$F$16="",0,IF(ISNUMBER(SEARCH(Classifiers!$F$16,E10)),1,0))+IF(Classifiers!$G$16="",0,IF(ISNUMBER(SEARCH(Classifiers!$G$16,E10)),1,0)))>0,1,0)) | V10: =IF(H10<>1,0,IF((IF(Classifiers!$B$17="",0,IF(ISNUMBER(SEARCH(Classifiers!$B$17,E10)),1,0))+IF(Classifiers!$C$17="",0,IF(ISNUMBER(SEARCH(Classifiers!$C$17,E10)),1,0))+IF(Classifiers!$D$17="",0,IF(ISNUMBER(SEARCH(Classifiers!$D$17,E10)),1,0))+IF(Classifiers!$E$17="",0,IF(ISNUMBER(SEARCH(Classifiers!$E$17,E10)),1,0))+IF(Classifiers!$F$17="",0,IF(ISNUMBER(SEARCH(Classifiers!$F$17,E10)),1,0))+IF(Classifiers!$G$17="",0,IF(ISNUMBER(SEARCH(Classifiers!$G$17,E10)),1,0)))>0,1,0)) | W10: =IF(H10<>1,0,IF((IF(Classifiers!$B$18="",0,IF(ISNUMBER(SEARCH(Classifiers!$B$18,E10)),1,0))+IF(Classifiers!$C$18="",0,IF(ISNUMBER(SEARCH(Classifiers!$C$18,E10)),1,0))+IF(Classifiers!$D$18="",0,IF(ISNUMBER(SEARCH(Classifiers!$D$18,E10)),1,0))+IF(Classifiers!$E$18="",0,IF(ISNUMBER(SEARCH(Classifiers!$E$18,E10)),1,0))+IF(Classifiers!$F$18="",0,IF(ISNUMBER(SEARCH(Classifiers!$F$18,E10)),1,0))+IF(Classifiers!$G$18="",0,IF(ISNUMBER(SEARCH(Classifiers!$G$18,E10)),1,0)))>0,1,0))
C11: =IF(A11="","",TRIM(RIGHT(SUBSTITUTE(A11,"/",REPT(" ",250)),250))) | D11: =IF(C11="","",IF(ISNUMBER(SEARCH(".",C11)),LOWER("."&TRIM(RIGHT(SUBSTITUTE(C11,".",REPT(" ",250)),250))),"")) | E11: =IF(C11="","",TRIM(SUBSTITUTE(SUBSTITUTE(SUBSTITUTE(SUBSTITUTE(SUBSTITUTE(SUBSTITUTE(SUBSTITUTE(SUBSTITUTE(SUBSTITUTE(SUBSTITUTE(SUBSTITUTE(SUBSTITUTE(SUBSTITUTE(SUBSTITUTE(SUBSTITUTE(SUBSTITUTE(SUBSTITUTE(SUBSTITUTE(SUBSTITUTE(SUBSTITUTE(LOWER(LEFT(C11,LEN(C11)-LEN(D11))),"_"," "),"-"," "),"."," "),","," "),"("," "),")"," "),"["," "),"]"," "),"&"," "),"+"," "),"@"," "),"#"," "),"!"," "),"'"," "),"/"," "),":"," "),";"," "),"="," "),"~"," "),"%"," "))) | F11: =IF(C11="","",IF(COUNTIF(Classifiers!$A$23:$A$40,D11)>0,1,0)) | G11: =IF(C11="","",IF(COUNTIF(Classifiers!$C$23:$C$30,D11)>0,IF((IF(ISNUMBER(SEARCH(Classifiers!$E$23,E11)),1,0)+IF(ISNUMBER(SEARCH(Classifiers!$E$24,E11)),1,0)+IF(ISNUMBER(SEARCH(Classifiers!$E$25,E11)),1,0)+IF(ISNUMBER(SEARCH(Classifiers!$E$26,E11)),1,0)+IF(ISNUMBER(SEARCH(Classifiers!$E$27,E11)),1,0)+IF(ISNUMBER(SEARCH(Classifiers!$E$28,E11)),1,0)+IF(ISNUMBER(SEARCH(Classifiers!$E$29,E11)),1,0)+IF(ISNUMBER(SEARCH(Classifiers!$E$30,E11)),1,0))>0,1,0),0)) | H11: =IF(C11="","",IF(OR(LEFT(C11,1)=".",AND(F11=0,G11=0)),0,1)) | I11: =IF(H11<>1,"",IF(SUM(J11:W11)=0,"unclassified",INDEX(Classifiers!$A$5:$A$18,MATCH(1,J11:W11,0),1))) | J11: =IF(H11<>1,0,IF((IF(Classifiers!$B$5="",0,IF(ISNUMBER(SEARCH(Classifiers!$B$5,E11)),1,0))+IF(Classifiers!$C$5="",0,IF(ISNUMBER(SEARCH(Classifiers!$C$5,E11)),1,0))+IF(Classifiers!$D$5="",0,IF(ISNUMBER(SEARCH(Classifiers!$D$5,E11)),1,0))+IF(Classifiers!$E$5="",0,IF(ISNUMBER(SEARCH(Classifiers!$E$5,E11)),1,0))+IF(Classifiers!$F$5="",0,IF(ISNUMBER(SEARCH(Classifiers!$F$5,E11)),1,0))+IF(Classifiers!$G$5="",0,IF(ISNUMBER(SEARCH(Classifiers!$G$5,E11)),1,0)))>0,1,0)) | K11: =IF(H11<>1,0,IF((IF(Classifiers!$B$6="",0,IF(ISNUMBER(SEARCH(Classifiers!$B$6,E11)),1,0))+IF(Classifiers!$C$6="",0,IF(ISNUMBER(SEARCH(Classifiers!$C$6,E11)),1,0))+IF(Classifiers!$D$6="",0,IF(ISNUMBER(SEARCH(Classifiers!$D$6,E11)),1,0))+IF(Classifiers!$E$6="",0,IF(ISNUMBER(SEARCH(Classifiers!$E$6,E11)),1,0))+IF(Classifiers!$F$6="",0,IF(ISNUMBER(SEARCH(Classifiers!$F$6,E11)),1,0))+IF(Classifiers!$G$6="",0,IF(ISNUMBER(SEARCH(Classifiers!$G$6,E11)),1,0)))>0,1,0)) | L11: =IF(H11<>1,0,IF((IF(Classifiers!$B$7="",0,IF(ISNUMBER(SEARCH(Classifiers!$B$7,E11)),1,0))+IF(Classifiers!$C$7="",0,IF(ISNUMBER(SEARCH(Classifiers!$C$7,E11)),1,0))+IF(Classifiers!$D$7="",0,IF(ISNUMBER(SEARCH(Classifiers!$D$7,E11)),1,0))+IF(Classifiers!$E$7="",0,IF(ISNUMBER(SEARCH(Classifiers!$E$7,E11)),1,0))+IF(Classifiers!$F$7="",0,IF(ISNUMBER(SEARCH(Classifiers!$F$7,E11)),1,0))+IF(Classifiers!$G$7="",0,IF(ISNUMBER(SEARCH(Classifiers!$G$7,E11)),1,0)))>0,1,0)) | M11: =IF(H11<>1,0,IF((IF(Classifiers!$B$8="",0,IF(ISNUMBER(SEARCH(Classifiers!$B$8,E11)),1,0))+IF(Classifiers!$C$8="",0,IF(ISNUMBER(SEARCH(Classifiers!$C$8,E11)),1,0))+IF(Classifiers!$D$8="",0,IF(ISNUMBER(SEARCH(Classifiers!$D$8,E11)),1,0))+IF(Classifiers!$E$8="",0,IF(ISNUMBER(SEARCH(Classifiers!$E$8,E11)),1,0))+IF(Classifiers!$F$8="",0,IF(ISNUMBER(SEARCH(Classifiers!$F$8,E11)),1,0))+IF(Classifiers!$G$8="",0,IF(ISNUMBER(SEARCH(Classifiers!$G$8,E11)),1,0)))>0,1,0)) | N11: =IF(H11<>1,0,IF((IF(Classifiers!$B$9="",0,IF(ISNUMBER(SEARCH(Classifiers!$B$9,E11)),1,0))+IF(Classifiers!$C$9="",0,IF(ISNUMBER(SEARCH(Classifiers!$C$9,E11)),1,0))+IF(Classifiers!$D$9="",0,IF(ISNUMBER(SEARCH(Classifiers!$D$9,E11)),1,0))+IF(Classifiers!$E$9="",0,IF(ISNUMBER(SEARCH(Classifiers!$E$9,E11)),1,0))+IF(Classifiers!$F$9="",0,IF(ISNUMBER(SEARCH(Classifiers!$F$9,E11)),1,0))+IF(Classifiers!$G$9="",0,IF(ISNUMBER(SEARCH(Classifiers!$G$9,E11)),1,0)))>0,1,0)) | O11: =IF(H11<>1,0,IF((IF(Classifiers!$B$10="",0,IF(ISNUMBER(SEARCH(Classifiers!$B$10,E11)),1,0))+IF(Classifiers!$C$10="",0,IF(ISNUMBER(SEARCH(Classifiers!$C$10,E11)),1,0))+IF(Classifiers!$D$10="",0,IF(ISNUMBER(SEARCH(Classifiers!$D$10,E11)),1,0))+IF(Classifiers!$E$10="",0,IF(ISNUMBER(SEARCH(Classifiers!$E$10,E11)),1,0))+IF(Classifiers!$F$10="",0,IF(ISNUMBER(SEARCH(Classifiers!$F$10,E11)),1,0))+IF(Classifiers!$G$10="",0,IF(ISNUMBER(SEARCH(Classifiers!$G$10,E11)),1,0)))>0,1,0)) | P11: =IF(H11<>1,0,IF((IF(Classifiers!$B$11="",0,IF(ISNUMBER(SEARCH(Classifiers!$B$11,E11)),1,0))+IF(Classifiers!$C$11="",0,IF(ISNUMBER(SEARCH(Classifiers!$C$11,E11)),1,0))+IF(Classifiers!$D$11="",0,IF(ISNUMBER(SEARCH(Classifiers!$D$11,E11)),1,0))+IF(Classifiers!$E$11="",0,IF(ISNUMBER(SEARCH(Classifiers!$E$11,E11)),1,0))+IF(Classifiers!$F$11="",0,IF(ISNUMBER(SEARCH(Classifiers!$F$11,E11)),1,0))+IF(Classifiers!$G$11="",0,IF(ISNUMBER(SEARCH(Classifiers!$G$11,E11)),1,0)))>0,1,0)) | Q11: =IF(H11<>1,0,IF((IF(Classifiers!$B$12="",0,IF(ISNUMBER(SEARCH(Classifiers!$B$12,E11)),1,0))+IF(Classifiers!$C$12="",0,IF(ISNUMBER(SEARCH(Classifiers!$C$12,E11)),1,0))+IF(Classifiers!$D$12="",0,IF(ISNUMBER(SEARCH(Classifiers!$D$12,E11)),1,0))+IF(Classifiers!$E$12="",0,IF(ISNUMBER(SEARCH(Classifiers!$E$12,E11)),1,0))+IF(Classifiers!$F$12="",0,IF(ISNUMBER(SEARCH(Classifiers!$F$12,E11)),1,0))+IF(Classifiers!$G$12="",0,IF(ISNUMBER(SEARCH(Classifiers!$G$12,E11)),1,0)))>0,1,0)) | R11: =IF(H11<>1,0,IF((IF(Classifiers!$B$13="",0,IF(ISNUMBER(SEARCH(Classifiers!$B$13,E11)),1,0))+IF(Classifiers!$C$13="",0,IF(ISNUMBER(SEARCH(Classifiers!$C$13,E11)),1,0))+IF(Classifiers!$D$13="",0,IF(ISNUMBER(SEARCH(Classifiers!$D$13,E11)),1,0))+IF(Classifiers!$E$13="",0,IF(ISNUMBER(SEARCH(Classifiers!$E$13,E11)),1,0))+IF(Classifiers!$F$13="",0,IF(ISNUMBER(SEARCH(Classifiers!$F$13,E11)),1,0))+IF(Classifiers!$G$13="",0,IF(ISNUMBER(SEARCH(Classifiers!$G$13,E11)),1,0)))>0,1,0)) | S11: =IF(H11<>1,0,IF((IF(Classifiers!$B$14="",0,IF(ISNUMBER(SEARCH(Classifiers!$B$14,E11)),1,0))+IF(Classifiers!$C$14="",0,IF(ISNUMBER(SEARCH(Classifiers!$C$14,E11)),1,0))+IF(Classifiers!$D$14="",0,IF(ISNUMBER(SEARCH(Classifiers!$D$14,E11)),1,0))+IF(Classifiers!$E$14="",0,IF(ISNUMBER(SEARCH(Classifiers!$E$14,E11)),1,0))+IF(Classifiers!$F$14="",0,IF(ISNUMBER(SEARCH(Classifiers!$F$14,E11)),1,0))+IF(Classifiers!$G$14="",0,IF(ISNUMBER(SEARCH(Classifiers!$G$14,E11)),1,0)))>0,1,0)) | T11: =IF(H11<>1,0,IF((IF(Classifiers!$B$15="",0,IF(ISNUMBER(SEARCH(Classifiers!$B$15,E11)),1,0))+IF(Classifiers!$C$15="",0,IF(ISNUMBER(SEARCH(Classifiers!$C$15,E11)),1,0))+IF(Classifiers!$D$15="",0,IF(ISNUMBER(SEARCH(Classifiers!$D$15,E11)),1,0))+IF(Classifiers!$E$15="",0,IF(ISNUMBER(SEARCH(Classifiers!$E$15,E11)),1,0))+IF(Classifiers!$F$15="",0,IF(ISNUMBER(SEARCH(Classifiers!$F$15,E11)),1,0))+IF(Classifiers!$G$15="",0,IF(ISNUMBER(SEARCH(Classifiers!$G$15,E11)),1,0)))>0,1,0)) | U11: =IF(H11<>1,0,IF((IF(Classifiers!$B$16="",0,IF(ISNUMBER(SEARCH(Classifiers!$B$16,E11)),1,0))+IF(Classifiers!$C$16="",0,IF(ISNUMBER(SEARCH(Classifiers!$C$16,E11)),1,0))+IF(Classifiers!$D$16="",0,IF(ISNUMBER(SEARCH(Classifiers!$D$16,E11)),1,0))+IF(Classifiers!$E$16="",0,IF(ISNUMBER(SEARCH(Classifiers!$E$16,E11)),1,0))+IF(Classifiers!$F$16="",0,IF(ISNUMBER(SEARCH(Classifiers!$F$16,E11)),1,0))+IF(Classifiers!$G$16="",0,IF(ISNUMBER(SEARCH(Classifiers!$G$16,E11)),1,0)))>0,1,0)) | V11: =IF(H11<>1,0,IF((IF(Classifiers!$B$17="",0,IF(ISNUMBER(SEARCH(Classifiers!$B$17,E11)),1,0))+IF(Classifiers!$C$17="",0,IF(ISNUMBER(SEARCH(Classifiers!$C$17,E11)),1,0))+IF(Classifiers!$D$17="",0,IF(ISNUMBER(SEARCH(Classifiers!$D$17,E11)),1,0))+IF(Classifiers!$E$17="",0,IF(ISNUMBER(SEARCH(Classifiers!$E$17,E11)),1,0))+IF(Classifiers!$F$17="",0,IF(ISNUMBER(SEARCH(Classifiers!$F$17,E11)),1,0))+IF(Classifiers!$G$17="",0,IF(ISNUMBER(SEARCH(Classifiers!$G$17,E11)),1,0)))>0,1,0)) | W11: =IF(H11<>1,0,IF((IF(Classifiers!$B$18="",0,IF(ISNUMBER(SEARCH(Classifiers!$B$18,E11)),1,0))+IF(Classifiers!$C$18="",0,IF(ISNUMBER(SEARCH(Classifiers!$C$18,E11)),1,0))+IF(Classifiers!$D$18="",0,IF(ISNUMBER(SEARCH(Classifiers!$D$18,E11)),1,0))+IF(Classifiers!$E$18="",0,IF(ISNUMBER(SEARCH(Classifiers!$E$18,E11)),1,0))+IF(Classifiers!$F$18="",0,IF(ISNUMBER(SEARCH(Classifiers!$F$18,E11)),1,0))+IF(Classifiers!$G$18="",0,IF(ISNUMBER(SEARCH(Classifiers!$G$18,E11)),1,0)))>0,1,0))
C12: =IF(A12="","",TRIM(RIGHT(SUBSTITUTE(A12,"/",REPT(" ",250)),250))) | D12: =IF(C12="","",IF(ISNUMBER(SEARCH(".",C12)),LOWER("."&TRIM(RIGHT(SUBSTITUTE(C12,".",REPT(" ",250)),250))),"")) | E12: =IF(C12="","",TRIM(SUBSTITUTE(SUBSTITUTE(SUBSTITUTE(SUBSTITUTE(SUBSTITUTE(SUBSTITUTE(SUBSTITUTE(SUBSTITUTE(SUBSTITUTE(SUBSTITUTE(SUBSTITUTE(SUBSTITUTE(SUBSTITUTE(SUBSTITUTE(SUBSTITUTE(SUBSTITUTE(SUBSTITUTE(SUBSTITUTE(SUBSTITUTE(SUBSTITUTE(LOWER(LEFT(C12,LEN(C12)-LEN(D12))),"_"," "),"-"," "),"."," "),","," "),"("," "),")"," "),"["," "),"]"," "),"&"," "),"+"," "),"@"," "),"#"," "),"!"," "),"'"," "),"/"," "),":"," "),";"," "),"="," "),"~"," "),"%"," "))) | F12: =IF(C12="","",IF(COUNTIF(Classifiers!$A$23:$A$40,D12)>0,1,0)) | G12: =IF(C12="","",IF(COUNTIF(Classifiers!$C$23:$C$30,D12)>0,IF((IF(ISNUMBER(SEARCH(Classifiers!$E$23,E12)),1,0)+IF(ISNUMBER(SEARCH(Classifiers!$E$24,E12)),1,0)+IF(ISNUMBER(SEARCH(Classifiers!$E$25,E12)),1,0)+IF(ISNUMBER(SEARCH(Classifiers!$E$26,E12)),1,0)+IF(ISNUMBER(SEARCH(Classifiers!$E$27,E12)),1,0)+IF(ISNUMBER(SEARCH(Classifiers!$E$28,E12)),1,0)+IF(ISNUMBER(SEARCH(Classifiers!$E$29,E12)),1,0)+IF(ISNUMBER(SEARCH(Classifiers!$E$30,E12)),1,0))>0,1,0),0)) | H12: =IF(C12="","",IF(OR(LEFT(C12,1)=".",AND(F12=0,G12=0)),0,1)) | I12: =IF(H12<>1,"",IF(SUM(J12:W12)=0,"unclassified",INDEX(Classifiers!$A$5:$A$18,MATCH(1,J12:W12,0),1))) | J12: =IF(H12<>1,0,IF((IF(Classifiers!$B$5="",0,IF(ISNUMBER(SEARCH(Classifiers!$B$5,E12)),1,0))+IF(Classifiers!$C$5="",0,IF(ISNUMBER(SEARCH(Classifiers!$C$5,E12)),1,0))+IF(Classifiers!$D$5="",0,IF(ISNUMBER(SEARCH(Classifiers!$D$5,E12)),1,0))+IF(Classifiers!$E$5="",0,IF(ISNUMBER(SEARCH(Classifiers!$E$5,E12)),1,0))+IF(Classifiers!$F$5="",0,IF(ISNUMBER(SEARCH(Classifiers!$F$5,E12)),1,0))+IF(Classifiers!$G$5="",0,IF(ISNUMBER(SEARCH(Classifiers!$G$5,E12)),1,0)))>0,1,0)) | K12: =IF(H12<>1,0,IF((IF(Classifiers!$B$6="",0,IF(ISNUMBER(SEARCH(Classifiers!$B$6,E12)),1,0))+IF(Classifiers!$C$6="",0,IF(ISNUMBER(SEARCH(Classifiers!$C$6,E12)),1,0))+IF(Classifiers!$D$6="",0,IF(ISNUMBER(SEARCH(Classifiers!$D$6,E12)),1,0))+IF(Classifiers!$E$6="",0,IF(ISNUMBER(SEARCH(Classifiers!$E$6,E12)),1,0))+IF(Classifiers!$F$6="",0,IF(ISNUMBER(SEARCH(Classifiers!$F$6,E12)),1,0))+IF(Classifiers!$G$6="",0,IF(ISNUMBER(SEARCH(Classifiers!$G$6,E12)),1,0)))>0,1,0)) | L12: =IF(H12<>1,0,IF((IF(Classifiers!$B$7="",0,IF(ISNUMBER(SEARCH(Classifiers!$B$7,E12)),1,0))+IF(Classifiers!$C$7="",0,IF(ISNUMBER(SEARCH(Classifiers!$C$7,E12)),1,0))+IF(Classifiers!$D$7="",0,IF(ISNUMBER(SEARCH(Classifiers!$D$7,E12)),1,0))+IF(Classifiers!$E$7="",0,IF(ISNUMBER(SEARCH(Classifiers!$E$7,E12)),1,0))+IF(Classifiers!$F$7="",0,IF(ISNUMBER(SEARCH(Classifiers!$F$7,E12)),1,0))+IF(Classifiers!$G$7="",0,IF(ISNUMBER(SEARCH(Classifiers!$G$7,E12)),1,0)))>0,1,0)) | M12: =IF(H12<>1,0,IF((IF(Classifiers!$B$8="",0,IF(ISNUMBER(SEARCH(Classifiers!$B$8,E12)),1,0))+IF(Classifiers!$C$8="",0,IF(ISNUMBER(SEARCH(Classifiers!$C$8,E12)),1,0))+IF(Classifiers!$D$8="",0,IF(ISNUMBER(SEARCH(Classifiers!$D$8,E12)),1,0))+IF(Classifiers!$E$8="",0,IF(ISNUMBER(SEARCH(Classifiers!$E$8,E12)),1,0))+IF(Classifiers!$F$8="",0,IF(ISNUMBER(SEARCH(Classifiers!$F$8,E12)),1,0))+IF(Classifiers!$G$8="",0,IF(ISNUMBER(SEARCH(Classifiers!$G$8,E12)),1,0)))>0,1,0)) | N12: =IF(H12<>1,0,IF((IF(Classifiers!$B$9="",0,IF(ISNUMBER(SEARCH(Classifiers!$B$9,E12)),1,0))+IF(Classifiers!$C$9="",0,IF(ISNUMBER(SEARCH(Classifiers!$C$9,E12)),1,0))+IF(Classifiers!$D$9="",0,IF(ISNUMBER(SEARCH(Classifiers!$D$9,E12)),1,0))+IF(Classifiers!$E$9="",0,IF(ISNUMBER(SEARCH(Classifiers!$E$9,E12)),1,0))+IF(Classifiers!$F$9="",0,IF(ISNUMBER(SEARCH(Classifiers!$F$9,E12)),1,0))+IF(Classifiers!$G$9="",0,IF(ISNUMBER(SEARCH(Classifiers!$G$9,E12)),1,0)))>0,1,0)) | O12: =IF(H12<>1,0,IF((IF(Classifiers!$B$10="",0,IF(ISNUMBER(SEARCH(Classifiers!$B$10,E12)),1,0))+IF(Classifiers!$C$10="",0,IF(ISNUMBER(SEARCH(Classifiers!$C$10,E12)),1,0))+IF(Classifiers!$D$10="",0,IF(ISNUMBER(SEARCH(Classifiers!$D$10,E12)),1,0))+IF(Classifiers!$E$10="",0,IF(ISNUMBER(SEARCH(Classifiers!$E$10,E12)),1,0))+IF(Classifiers!$F$10="",0,IF(ISNUMBER(SEARCH(Classifiers!$F$10,E12)),1,0))+IF(Classifiers!$G$10="",0,IF(ISNUMBER(SEARCH(Classifiers!$G$10,E12)),1,0)))>0,1,0)) | P12: =IF(H12<>1,0,IF((IF(Classifiers!$B$11="",0,IF(ISNUMBER(SEARCH(Classifiers!$B$11,E12)),1,0))+IF(Classifiers!$C$11="",0,IF(ISNUMBER(SEARCH(Classifiers!$C$11,E12)),1,0))+IF(Classifiers!$D$11="",0,IF(ISNUMBER(SEARCH(Classifiers!$D$11,E12)),1,0))+IF(Classifiers!$E$11="",0,IF(ISNUMBER(SEARCH(Classifiers!$E$11,E12)),1,0))+IF(Classifiers!$F$11="",0,IF(ISNUMBER(SEARCH(Classifiers!$F$11,E12)),1,0))+IF(Classifiers!$G$11="",0,IF(ISNUMBER(SEARCH(Classifiers!$G$11,E12)),1,0)))>0,1,0)) | Q12: =IF(H12<>1,0,IF((IF(Classifiers!$B$12="",0,IF(ISNUMBER(SEARCH(Classifiers!$B$12,E12)),1,0))+IF(Classifiers!$C$12="",0,IF(ISNUMBER(SEARCH(Classifiers!$C$12,E12)),1,0))+IF(Classifiers!$D$12="",0,IF(ISNUMBER(SEARCH(Classifiers!$D$12,E12)),1,0))+IF(Classifiers!$E$12="",0,IF(ISNUMBER(SEARCH(Classifiers!$E$12,E12)),1,0))+IF(Classifiers!$F$12="",0,IF(ISNUMBER(SEARCH(Classifiers!$F$12,E12)),1,0))+IF(Classifiers!$G$12="",0,IF(ISNUMBER(SEARCH(Classifiers!$G$12,E12)),1,0)))>0,1,0)) | R12: =IF(H12<>1,0,IF((IF(Classifiers!$B$13="",0,IF(ISNUMBER(SEARCH(Classifiers!$B$13,E12)),1,0))+IF(Classifiers!$C$13="",0,IF(ISNUMBER(SEARCH(Classifiers!$C$13,E12)),1,0))+IF(Classifiers!$D$13="",0,IF(ISNUMBER(SEARCH(Classifiers!$D$13,E12)),1,0))+IF(Classifiers!$E$13="",0,IF(ISNUMBER(SEARCH(Classifiers!$E$13,E12)),1,0))+IF(Classifiers!$F$13="",0,IF(ISNUMBER(SEARCH(Classifiers!$F$13,E12)),1,0))+IF(Classifiers!$G$13="",0,IF(ISNUMBER(SEARCH(Classifiers!$G$13,E12)),1,0)))>0,1,0)) | S12: =IF(H12<>1,0,IF((IF(Classifiers!$B$14="",0,IF(ISNUMBER(SEARCH(Classifiers!$B$14,E12)),1,0))+IF(Classifiers!$C$14="",0,IF(ISNUMBER(SEARCH(Classifiers!$C$14,E12)),1,0))+IF(Classifiers!$D$14="",0,IF(ISNUMBER(SEARCH(Classifiers!$D$14,E12)),1,0))+IF(Classifiers!$E$14="",0,IF(ISNUMBER(SEARCH(Classifiers!$E$14,E12)),1,0))+IF(Classifiers!$F$14="",0,IF(ISNUMBER(SEARCH(Classifiers!$F$14,E12)),1,0))+IF(Classifiers!$G$14="",0,IF(ISNUMBER(SEARCH(Classifiers!$G$14,E12)),1,0)))>0,1,0)) | T12: =IF(H12<>1,0,IF((IF(Classifiers!$B$15="",0,IF(ISNUMBER(SEARCH(Classifiers!$B$15,E12)),1,0))+IF(Classifiers!$C$15="",0,IF(ISNUMBER(SEARCH(Classifiers!$C$15,E12)),1,0))+IF(Classifiers!$D$15="",0,IF(ISNUMBER(SEARCH(Classifiers!$D$15,E12)),1,0))+IF(Classifiers!$E$15="",0,IF(ISNUMBER(SEARCH(Classifiers!$E$15,E12)),1,0))+IF(Classifiers!$F$15="",0,IF(ISNUMBER(SEARCH(Classifiers!$F$15,E12)),1,0))+IF(Classifiers!$G$15="",0,IF(ISNUMBER(SEARCH(Classifiers!$G$15,E12)),1,0)))>0,1,0)) | U12: =IF(H12<>1,0,IF((IF(Classifiers!$B$16="",0,IF(ISNUMBER(SEARCH(Classifiers!$B$16,E12)),1,0))+IF(Classifiers!$C$16="",0,IF(ISNUMBER(SEARCH(Classifiers!$C$16,E12)),1,0))+IF(Classifiers!$D$16="",0,IF(ISNUMBER(SEARCH(Classifiers!$D$16,E12)),1,0))+IF(Classifiers!$E$16="",0,IF(ISNUMBER(SEARCH(Classifiers!$E$16,E12)),1,0))+IF(Classifiers!$F$16="",0,IF(ISNUMBER(SEARCH(Classifiers!$F$16,E12)),1,0))+IF(Classifiers!$G$16="",0,IF(ISNUMBER(SEARCH(Classifiers!$G$16,E12)),1,0)))>0,1,0)) | V12: =IF(H12<>1,0,IF((IF(Classifiers!$B$17="",0,IF(ISNUMBER(SEARCH(Classifiers!$B$17,E12)),1,0))+IF(Classifiers!$C$17="",0,IF(ISNUMBER(SEARCH(Classifiers!$C$17,E12)),1,0))+IF(Classifiers!$D$17="",0,IF(ISNUMBER(SEARCH(Classifiers!$D$17,E12)),1,0))+IF(Classifiers!$E$17="",0,IF(ISNUMBER(SEARCH(Classifiers!$E$17,E12)),1,0))+IF(Classifiers!$F$17="",0,IF(ISNUMBER(SEARCH(Classifiers!$F$17,E12)),1,0))+IF(Classifiers!$G$17="",0,IF(ISNUMBER(SEARCH(Classifiers!$G$17,E12)),1,0)))>0,1,0)) | W12: =IF(H12<>1,0,IF((IF(Classifiers!$B$18="",0,IF(ISNUMBER(SEARCH(Classifiers!$B$18,E12)),1,0))+IF(Classifiers!$C$18="",0,IF(ISNUMBER(SEARCH(Classifiers!$C$18,E12)),1,0))+IF(Classifiers!$D$18="",0,IF(ISNUMBER(SEARCH(Classifiers!$D$18,E12)),1,0))+IF(Classifiers!$E$18="",0,IF(ISNUMBER(SEARCH(Classifiers!$E$18,E12)),1,0))+IF(Classifiers!$F$18="",0,IF(ISNUMBER(SEARCH(Classifiers!$F$18,E12)),1,0))+IF(Classifiers!$G$18="",0,IF(ISNUMBER(SEARCH(Classifiers!$G$18,E12)),1,0)))>0,1,0))
C13: =IF(A13="","",TRIM(RIGHT(SUBSTITUTE(A13,"/",REPT(" ",250)),250))) | D13: =IF(C13="","",IF(ISNUMBER(SEARCH(".",C13)),LOWER("."&TRIM(RIGHT(SUBSTITUTE(C13,".",REPT(" ",250)),250))),"")) | E13: =IF(C13="","",TRIM(SUBSTITUTE(SUBSTITUTE(SUBSTITUTE(SUBSTITUTE(SUBSTITUTE(SUBSTITUTE(SUBSTITUTE(SUBSTITUTE(SUBSTITUTE(SUBSTITUTE(SUBSTITUTE(SUBSTITUTE(SUBSTITUTE(SUBSTITUTE(SUBSTITUTE(SUBSTITUTE(SUBSTITUTE(SUBSTITUTE(SUBSTITUTE(SUBSTITUTE(LOWER(LEFT(C13,LEN(C13)-LEN(D13))),"_"," "),"-"," "),"."," "),","," "),"("," "),")"," "),"["," "),"]"," "),"&"," "),"+"," "),"@"," "),"#"," "),"!"," "),"'"," "),"/"," "),":"," "),";"," "),"="," "),"~"," "),"%"," "))) | F13: =IF(C13="","",IF(COUNTIF(Classifiers!$A$23:$A$40,D13)>0,1,0)) | G13: =IF(C13="","",IF(COUNTIF(Classifiers!$C$23:$C$30,D13)>0,IF((IF(ISNUMBER(SEARCH(Classifiers!$E$23,E13)),1,0)+IF(ISNUMBER(SEARCH(Classifiers!$E$24,E13)),1,0)+IF(ISNUMBER(SEARCH(Classifiers!$E$25,E13)),1,0)+IF(ISNUMBER(SEARCH(Classifiers!$E$26,E13)),1,0)+IF(ISNUMBER(SEARCH(Classifiers!$E$27,E13)),1,0)+IF(ISNUMBER(SEARCH(Classifiers!$E$28,E13)),1,0)+IF(ISNUMBER(SEARCH(Classifiers!$E$29,E13)),1,0)+IF(ISNUMBER(SEARCH(Classifiers!$E$30,E13)),1,0))>0,1,0),0)) | H13: =IF(C13="","",IF(OR(LEFT(C13,1)=".",AND(F13=0,G13=0)),0,1)) | I13: =IF(H13<>1,"",IF(SUM(J13:W13)=0,"unclassified",INDEX(Classifiers!$A$5:$A$18,MATCH(1,J13:W13,0),1))) | J13: =IF(H13<>1,0,IF((IF(Classifiers!$B$5="",0,IF(ISNUMBER(SEARCH(Classifiers!$B$5,E13)),1,0))+IF(Classifiers!$C$5="",0,IF(ISNUMBER(SEARCH(Classifiers!$C$5,E13)),1,0))+IF(Classifiers!$D$5="",0,IF(ISNUMBER(SEARCH(Classifiers!$D$5,E13)),1,0))+IF(Classifiers!$E$5="",0,IF(ISNUMBER(SEARCH(Classifiers!$E$5,E13)),1,0))+IF(Classifiers!$F$5="",0,IF(ISNUMBER(SEARCH(Classifiers!$F$5,E13)),1,0))+IF(Classifiers!$G$5="",0,IF(ISNUMBER(SEARCH(Classifiers!$G$5,E13)),1,0)))>0,1,0)) | K13: =IF(H13<>1,0,IF((IF(Classifiers!$B$6="",0,IF(ISNUMBER(SEARCH(Classifiers!$B$6,E13)),1,0))+IF(Classifiers!$C$6="",0,IF(ISNUMBER(SEARCH(Classifiers!$C$6,E13)),1,0))+IF(Classifiers!$D$6="",0,IF(ISNUMBER(SEARCH(Classifiers!$D$6,E13)),1,0))+IF(Classifiers!$E$6="",0,IF(ISNUMBER(SEARCH(Classifiers!$E$6,E13)),1,0))+IF(Classifiers!$F$6="",0,IF(ISNUMBER(SEARCH(Classifiers!$F$6,E13)),1,0))+IF(Classifiers!$G$6="",0,IF(ISNUMBER(SEARCH(Classifiers!$G$6,E13)),1,0)))>0,1,0)) | L13: =IF(H13<>1,0,IF((IF(Classifiers!$B$7="",0,IF(ISNUMBER(SEARCH(Classifiers!$B$7,E13)),1,0))+IF(Classifiers!$C$7="",0,IF(ISNUMBER(SEARCH(Classifiers!$C$7,E13)),1,0))+IF(Classifiers!$D$7="",0,IF(ISNUMBER(SEARCH(Classifiers!$D$7,E13)),1,0))+IF(Classifiers!$E$7="",0,IF(ISNUMBER(SEARCH(Classifiers!$E$7,E13)),1,0))+IF(Classifiers!$F$7="",0,IF(ISNUMBER(SEARCH(Classifiers!$F$7,E13)),1,0))+IF(Classifiers!$G$7="",0,IF(ISNUMBER(SEARCH(Classifiers!$G$7,E13)),1,0)))>0,1,0)) | M13: =IF(H13<>1,0,IF((IF(Classifiers!$B$8="",0,IF(ISNUMBER(SEARCH(Classifiers!$B$8,E13)),1,0))+IF(Classifiers!$C$8="",0,IF(ISNUMBER(SEARCH(Classifiers!$C$8,E13)),1,0))+IF(Classifiers!$D$8="",0,IF(ISNUMBER(SEARCH(Classifiers!$D$8,E13)),1,0))+IF(Classifiers!$E$8="",0,IF(ISNUMBER(SEARCH(Classifiers!$E$8,E13)),1,0))+IF(Classifiers!$F$8="",0,IF(ISNUMBER(SEARCH(Classifiers!$F$8,E13)),1,0))+IF(Classifiers!$G$8="",0,IF(ISNUMBER(SEARCH(Classifiers!$G$8,E13)),1,0)))>0,1,0)) | N13: =IF(H13<>1,0,IF((IF(Classifiers!$B$9="",0,IF(ISNUMBER(SEARCH(Classifiers!$B$9,E13)),1,0))+IF(Classifiers!$C$9="",0,IF(ISNUMBER(SEARCH(Classifiers!$C$9,E13)),1,0))+IF(Classifiers!$D$9="",0,IF(ISNUMBER(SEARCH(Classifiers!$D$9,E13)),1,0))+IF(Classifiers!$E$9="",0,IF(ISNUMBER(SEARCH(Classifiers!$E$9,E13)),1,0))+IF(Classifiers!$F$9="",0,IF(ISNUMBER(SEARCH(Classifiers!$F$9,E13)),1,0))+IF(Classifiers!$G$9="",0,IF(ISNUMBER(SEARCH(Classifiers!$G$9,E13)),1,0)))>0,1,0)) | O13: =IF(H13<>1,0,IF((IF(Classifiers!$B$10="",0,IF(ISNUMBER(SEARCH(Classifiers!$B$10,E13)),1,0))+IF(Classifiers!$C$10="",0,IF(ISNUMBER(SEARCH(Classifiers!$C$10,E13)),1,0))+IF(Classifiers!$D$10="",0,IF(ISNUMBER(SEARCH(Classifiers!$D$10,E13)),1,0))+IF(Classifiers!$E$10="",0,IF(ISNUMBER(SEARCH(Classifiers!$E$10,E13)),1,0))+IF(Classifiers!$F$10="",0,IF(ISNUMBER(SEARCH(Classifiers!$F$10,E13)),1,0))+IF(Classifiers!$G$10="",0,IF(ISNUMBER(SEARCH(Classifiers!$G$10,E13)),1,0)))>0,1,0)) | P13: =IF(H13<>1,0,IF((IF(Classifiers!$B$11="",0,IF(ISNUMBER(SEARCH(Classifiers!$B$11,E13)),1,0))+IF(Classifiers!$C$11="",0,IF(ISNUMBER(SEARCH(Classifiers!$C$11,E13)),1,0))+IF(Classifiers!$D$11="",0,IF(ISNUMBER(SEARCH(Classifiers!$D$11,E13)),1,0))+IF(Classifiers!$E$11="",0,IF(ISNUMBER(SEARCH(Classifiers!$E$11,E13)),1,0))+IF(Classifiers!$F$11="",0,IF(ISNUMBER(SEARCH(Classifiers!$F$11,E13)),1,0))+IF(Classifiers!$G$11="",0,IF(ISNUMBER(SEARCH(Classifiers!$G$11,E13)),1,0)))>0,1,0)) | Q13: =IF(H13<>1,0,IF((IF(Classifiers!$B$12="",0,IF(ISNUMBER(SEARCH(Classifiers!$B$12,E13)),1,0))+IF(Classifiers!$C$12="",0,IF(ISNUMBER(SEARCH(Classifiers!$C$12,E13)),1,0))+IF(Classifiers!$D$12="",0,IF(ISNUMBER(SEARCH(Classifiers!$D$12,E13)),1,0))+IF(Classifiers!$E$12="",0,IF(ISNUMBER(SEARCH(Classifiers!$E$12,E13)),1,0))+IF(Classifiers!$F$12="",0,IF(ISNUMBER(SEARCH(Classifiers!$F$12,E13)),1,0))+IF(Classifiers!$G$12="",0,IF(ISNUMBER(SEARCH(Classifiers!$G$12,E13)),1,0)))>0,1,0)) | R13: =IF(H13<>1,0,IF((IF(Classifiers!$B$13="",0,IF(ISNUMBER(SEARCH(Classifiers!$B$13,E13)),1,0))+IF(Classifiers!$C$13="",0,IF(ISNUMBER(SEARCH(Classifiers!$C$13,E13)),1,0))+IF(Classifiers!$D$13="",0,IF(ISNUMBER(SEARCH(Classifiers!$D$13,E13)),1,0))+IF(Classifiers!$E$13="",0,IF(ISNUMBER(SEARCH(Classifiers!$E$13,E13)),1,0))+IF(Classifiers!$F$13="",0,IF(ISNUMBER(SEARCH(Classifiers!$F$13,E13)),1,0))+IF(Classifiers!$G$13="",0,IF(ISNUMBER(SEARCH(Classifiers!$G$13,E13)),1,0)))>0,1,0)) | S13: =IF(H13<>1,0,IF((IF(Classifiers!$B$14="",0,IF(ISNUMBER(SEARCH(Classifiers!$B$14,E13)),1,0))+IF(Classifiers!$C$14="",0,IF(ISNUMBER(SEARCH(Classifiers!$C$14,E13)),1,0))+IF(Classifiers!$D$14="",0,IF(ISNUMBER(SEARCH(Classifiers!$D$14,E13)),1,0))+IF(Classifiers!$E$14="",0,IF(ISNUMBER(SEARCH(Classifiers!$E$14,E13)),1,0))+IF(Classifiers!$F$14="",0,IF(ISNUMBER(SEARCH(Classifiers!$F$14,E13)),1,0))+IF(Classifiers!$G$14="",0,IF(ISNUMBER(SEARCH(Classifiers!$G$14,E13)),1,0)))>0,1,0)) | T13: =IF(H13<>1,0,IF((IF(Classifiers!$B$15="",0,IF(ISNUMBER(SEARCH(Classifiers!$B$15,E13)),1,0))+IF(Classifiers!$C$15="",0,IF(ISNUMBER(SEARCH(Classifiers!$C$15,E13)),1,0))+IF(Classifiers!$D$15="",0,IF(ISNUMBER(SEARCH(Classifiers!$D$15,E13)),1,0))+IF(Classifiers!$E$15="",0,IF(ISNUMBER(SEARCH(Classifiers!$E$15,E13)),1,0))+IF(Classifiers!$F$15="",0,IF(ISNUMBER(SEARCH(Classifiers!$F$15,E13)),1,0))+IF(Classifiers!$G$15="",0,IF(ISNUMBER(SEARCH(Classifiers!$G$15,E13)),1,0)))>0,1,0)) | U13: =IF(H13<>1,0,IF((IF(Classifiers!$B$16="",0,IF(ISNUMBER(SEARCH(Classifiers!$B$16,E13)),1,0))+IF(Classifiers!$C$16="",0,IF(ISNUMBER(SEARCH(Classifiers!$C$16,E13)),1,0))+IF(Classifiers!$D$16="",0,IF(ISNUMBER(SEARCH(Classifiers!$D$16,E13)),1,0))+IF(Classifiers!$E$16="",0,IF(ISNUMBER(SEARCH(Classifiers!$E$16,E13)),1,0))+IF(Classifiers!$F$16="",0,IF(ISNUMBER(SEARCH(Classifiers!$F$16,E13)),1,0))+IF(Classifiers!$G$16="",0,IF(ISNUMBER(SEARCH(Classifiers!$G$16,E13)),1,0)))>0,1,0)) | V13: =IF(H13<>1,0,IF((IF(Classifiers!$B$17="",0,IF(ISNUMBER(SEARCH(Classifiers!$B$17,E13)),1,0))+IF(Classifiers!$C$17="",0,IF(ISNUMBER(SEARCH(Classifiers!$C$17,E13)),1,0))+IF(Classifiers!$D$17="",0,IF(ISNUMBER(SEARCH(Classifiers!$D$17,E13)),1,0))+IF(Classifiers!$E$17="",0,IF(ISNUMBER(SEARCH(Classifiers!$E$17,E13)),1,0))+IF(Classifiers!$F$17="",0,IF(ISNUMBER(SEARCH(Classifiers!$F$17,E13)),1,0))+IF(Classifiers!$G$17="",0,IF(ISNUMBER(SEARCH(Classifiers!$G$17,E13)),1,0)))>0,1,0)) | W13: =IF(H13<>1,0,IF((IF(Classifiers!$B$18="",0,IF(ISNUMBER(SEARCH(Classifiers!$B$18,E13)),1,0))+IF(Classifiers!$C$18="",0,IF(ISNUMBER(SEARCH(Classifiers!$C$18,E13)),1,0))+IF(Classifiers!$D$18="",0,IF(ISNUMBER(SEARCH(Classifiers!$D$18,E13)),1,0))+IF(Classifiers!$E$18="",0,IF(ISNUMBER(SEARCH(Classifiers!$E$18,E13)),1,0))+IF(Classifiers!$F$18="",0,IF(ISNUMBER(SEARCH(Classifiers!$F$18,E13)),1,0))+IF(Classifiers!$G$18="",0,IF(ISNUMBER(SEARCH(Classifiers!$G$18,E13)),1,0)))>0,1,0))
C14: =IF(A14="","",TRIM(RIGHT(SUBSTITUTE(A14,"/",REPT(" ",250)),250))) | D14: =IF(C14="","",IF(ISNUMBER(SEARCH(".",C14)),LOWER("."&TRIM(RIGHT(SUBSTITUTE(C14,".",REPT(" ",250)),250))),"")) | E14: =IF(C14="","",TRIM(SUBSTITUTE(SUBSTITUTE(SUBSTITUTE(SUBSTITUTE(SUBSTITUTE(SUBSTITUTE(SUBSTITUTE(SUBSTITUTE(SUBSTITUTE(SUBSTITUTE(SUBSTITUTE(SUBSTITUTE(SUBSTITUTE(SUBSTITUTE(SUBSTITUTE(SUBSTITUTE(SUBSTITUTE(SUBSTITUTE(SUBSTITUTE(SUBSTITUTE(LOWER(LEFT(C14,LEN(C14)-LEN(D14))),"_"," "),"-"," "),"."," "),","," "),"("," "),")"," "),"["," "),"]"," "),"&"," "),"+"," "),"@"," "),"#"," "),"!"," "),"'"," "),"/"," "),":"," "),";"," "),"="," "),"~"," "),"%"," "))) | F14: =IF(C14="","",IF(COUNTIF(Classifiers!$A$23:$A$40,D14)>0,1,0)) | G14: =IF(C14="","",IF(COUNTIF(Classifiers!$C$23:$C$30,D14)>0,IF((IF(ISNUMBER(SEARCH(Classifiers!$E$23,E14)),1,0)+IF(ISNUMBER(SEARCH(Classifiers!$E$24,E14)),1,0)+IF(ISNUMBER(SEARCH(Classifiers!$E$25,E14)),1,0)+IF(ISNUMBER(SEARCH(Classifiers!$E$26,E14)),1,0)+IF(ISNUMBER(SEARCH(Classifiers!$E$27,E14)),1,0)+IF(ISNUMBER(SEARCH(Classifiers!$E$28,E14)),1,0)+IF(ISNUMBER(SEARCH(Classifiers!$E$29,E14)),1,0)+IF(ISNUMBER(SEARCH(Classifiers!$E$30,E14)),1,0))>0,1,0),0)) | H14: =IF(C14="","",IF(OR(LEFT(C14,1)=".",AND(F14=0,G14=0)),0,1)) | I14: =IF(H14<>1,"",IF(SUM(J14:W14)=0,"unclassified",INDEX(Classifiers!$A$5:$A$18,MATCH(1,J14:W14,0),1))) | J14: =IF(H14<>1,0,IF((IF(Classifiers!$B$5="",0,IF(ISNUMBER(SEARCH(Classifiers!$B$5,E14)),1,0))+IF(Classifiers!$C$5="",0,IF(ISNUMBER(SEARCH(Classifiers!$C$5,E14)),1,0))+IF(Classifiers!$D$5="",0,IF(ISNUMBER(SEARCH(Classifiers!$D$5,E14)),1,0))+IF(Classifiers!$E$5="",0,IF(ISNUMBER(SEARCH(Classifiers!$E$5,E14)),1,0))+IF(Classifiers!$F$5="",0,IF(ISNUMBER(SEARCH(Classifiers!$F$5,E14)),1,0))+IF(Classifiers!$G$5="",0,IF(ISNUMBER(SEARCH(Classifiers!$G$5,E14)),1,0)))>0,1,0)) | K14: =IF(H14<>1,0,IF((IF(Classifiers!$B$6="",0,IF(ISNUMBER(SEARCH(Classifiers!$B$6,E14)),1,0))+IF(Classifiers!$C$6="",0,IF(ISNUMBER(SEARCH(Classifiers!$C$6,E14)),1,0))+IF(Classifiers!$D$6="",0,IF(ISNUMBER(SEARCH(Classifiers!$D$6,E14)),1,0))+IF(Classifiers!$E$6="",0,IF(ISNUMBER(SEARCH(Classifiers!$E$6,E14)),1,0))+IF(Classifiers!$F$6="",0,IF(ISNUMBER(SEARCH(Classifiers!$F$6,E14)),1,0))+IF(Classifiers!$G$6="",0,IF(ISNUMBER(SEARCH(Classifiers!$G$6,E14)),1,0)))>0,1,0)) | L14: =IF(H14<>1,0,IF((IF(Classifiers!$B$7="",0,IF(ISNUMBER(SEARCH(Classifiers!$B$7,E14)),1,0))+IF(Classifiers!$C$7="",0,IF(ISNUMBER(SEARCH(Classifiers!$C$7,E14)),1,0))+IF(Classifiers!$D$7="",0,IF(ISNUMBER(SEARCH(Classifiers!$D$7,E14)),1,0))+IF(Classifiers!$E$7="",0,IF(ISNUMBER(SEARCH(Classifiers!$E$7,E14)),1,0))+IF(Classifiers!$F$7="",0,IF(ISNUMBER(SEARCH(Classifiers!$F$7,E14)),1,0))+IF(Classifiers!$G$7="",0,IF(ISNUMBER(SEARCH(Classifiers!$G$7,E14)),1,0)))>0,1,0)) | M14: =IF(H14<>1,0,IF((IF(Classifiers!$B$8="",0,IF(ISNUMBER(SEARCH(Classifiers!$B$8,E14)),1,0))+IF(Classifiers!$C$8="",0,IF(ISNUMBER(SEARCH(Classifiers!$C$8,E14)),1,0))+IF(Classifiers!$D$8="",0,IF(ISNUMBER(SEARCH(Classifiers!$D$8,E14)),1,0))+IF(Classifiers!$E$8="",0,IF(ISNUMBER(SEARCH(Classifiers!$E$8,E14)),1,0))+IF(Classifiers!$F$8="",0,IF(ISNUMBER(SEARCH(Classifiers!$F$8,E14)),1,0))+IF(Classifiers!$G$8="",0,IF(ISNUMBER(SEARCH(Classifiers!$G$8,E14)),1,0)))>0,1,0)) | N14: =IF(H14<>1,0,IF((IF(Classifiers!$B$9="",0,IF(ISNUMBER(SEARCH(Classifiers!$B$9,E14)),1,0))+IF(Classifiers!$C$9="",0,IF(ISNUMBER(SEARCH(Classifiers!$C$9,E14)),1,0))+IF(Classifiers!$D$9="",0,IF(ISNUMBER(SEARCH(Classifiers!$D$9,E14)),1,0))+IF(Classifiers!$E$9="",0,IF(ISNUMBER(SEARCH(Classifiers!$E$9,E14)),1,0))+IF(Classifiers!$F$9="",0,IF(ISNUMBER(SEARCH(Classifiers!$F$9,E14)),1,0))+IF(Classifiers!$G$9="",0,IF(ISNUMBER(SEARCH(Classifiers!$G$9,E14)),1,0)))>0,1,0)) | O14: =IF(H14<>1,0,IF((IF(Classifiers!$B$10="",0,IF(ISNUMBER(SEARCH(Classifiers!$B$10,E14)),1,0))+IF(Classifiers!$C$10="",0,IF(ISNUMBER(SEARCH(Classifiers!$C$10,E14)),1,0))+IF(Classifiers!$D$10="",0,IF(ISNUMBER(SEARCH(Classifiers!$D$10,E14)),1,0))+IF(Classifiers!$E$10="",0,IF(ISNUMBER(SEARCH(Classifiers!$E$10,E14)),1,0))+IF(Classifiers!$F$10="",0,IF(ISNUMBER(SEARCH(Classifiers!$F$10,E14)),1,0))+IF(Classifiers!$G$10="",0,IF(ISNUMBER(SEARCH(Classifiers!$G$10,E14)),1,0)))>0,1,0)) | P14: =IF(H14<>1,0,IF((IF(Classifiers!$B$11="",0,IF(ISNUMBER(SEARCH(Classifiers!$B$11,E14)),1,0))+IF(Classifiers!$C$11="",0,IF(ISNUMBER(SEARCH(Classifiers!$C$11,E14)),1,0))+IF(Classifiers!$D$11="",0,IF(ISNUMBER(SEARCH(Classifiers!$D$11,E14)),1,0))+IF(Classifiers!$E$11="",0,IF(ISNUMBER(SEARCH(Classifiers!$E$11,E14)),1,0))+IF(Classifiers!$F$11="",0,IF(ISNUMBER(SEARCH(Classifiers!$F$11,E14)),1,0))+IF(Classifiers!$G$11="",0,IF(ISNUMBER(SEARCH(Classifiers!$G$11,E14)),1,0)))>0,1,0)) | Q14: =IF(H14<>1,0,IF((IF(Classifiers!$B$12="",0,IF(ISNUMBER(SEARCH(Classifiers!$B$12,E14)),1,0))+IF(Classifiers!$C$12="",0,IF(ISNUMBER(SEARCH(Classifiers!$C$12,E14)),1,0))+IF(Classifiers!$D$12="",0,IF(ISNUMBER(SEARCH(Classifiers!$D$12,E14)),1,0))+IF(Classifiers!$E$12="",0,IF(ISNUMBER(SEARCH(Classifiers!$E$12,E14)),1,0))+IF(Classifiers!$F$12="",0,IF(ISNUMBER(SEARCH(Classifiers!$F$12,E14)),1,0))+IF(Classifiers!$G$12="",0,IF(ISNUMBER(SEARCH(Classifiers!$G$12,E14)),1,0)))>0,1,0)) | R14: =IF(H14<>1,0,IF((IF(Classifiers!$B$13="",0,IF(ISNUMBER(SEARCH(Classifiers!$B$13,E14)),1,0))+IF(Classifiers!$C$13="",0,IF(ISNUMBER(SEARCH(Classifiers!$C$13,E14)),1,0))+IF(Classifiers!$D$13="",0,IF(ISNUMBER(SEARCH(Classifiers!$D$13,E14)),1,0))+IF(Classifiers!$E$13="",0,IF(ISNUMBER(SEARCH(Classifiers!$E$13,E14)),1,0))+IF(Classifiers!$F$13="",0,IF(ISNUMBER(SEARCH(Classifiers!$F$13,E14)),1,0))+IF(Classifiers!$G$13="",0,IF(ISNUMBER(SEARCH(Classifiers!$G$13,E14)),1,0)))>0,1,0)) | S14: =IF(H14<>1,0,IF((IF(Classifiers!$B$14="",0,IF(ISNUMBER(SEARCH(Classifiers!$B$14,E14)),1,0))+IF(Classifiers!$C$14="",0,IF(ISNUMBER(SEARCH(Classifiers!$C$14,E14)),1,0))+IF(Classifiers!$D$14="",0,IF(ISNUMBER(SEARCH(Classifiers!$D$14,E14)),1,0))+IF(Classifiers!$E$14="",0,IF(ISNUMBER(SEARCH(Classifiers!$E$14,E14)),1,0))+IF(Classifiers!$F$14="",0,IF(ISNUMBER(SEARCH(Classifiers!$F$14,E14)),1,0))+IF(Classifiers!$G$14="",0,IF(ISNUMBER(SEARCH(Classifiers!$G$14,E14)),1,0)))>0,1,0)) | T14: =IF(H14<>1,0,IF((IF(Classifiers!$B$15="",0,IF(ISNUMBER(SEARCH(Classifiers!$B$15,E14)),1,0))+IF(Classifiers!$C$15="",0,IF(ISNUMBER(SEARCH(Classifiers!$C$15,E14)),1,0))+IF(Classifiers!$D$15="",0,IF(ISNUMBER(SEARCH(Classifiers!$D$15,E14)),1,0))+IF(Classifiers!$E$15="",0,IF(ISNUMBER(SEARCH(Classifiers!$E$15,E14)),1,0))+IF(Classifiers!$F$15="",0,IF(ISNUMBER(SEARCH(Classifiers!$F$15,E14)),1,0))+IF(Classifiers!$G$15="",0,IF(ISNUMBER(SEARCH(Classifiers!$G$15,E14)),1,0)))>0,1,0)) | U14: =IF(H14<>1,0,IF((IF(Classifiers!$B$16="",0,IF(ISNUMBER(SEARCH(Classifiers!$B$16,E14)),1,0))+IF(Classifiers!$C$16="",0,IF(ISNUMBER(SEARCH(Classifiers!$C$16,E14)),1,0))+IF(Classifiers!$D$16="",0,IF(ISNUMBER(SEARCH(Classifiers!$D$16,E14)),1,0))+IF(Classifiers!$E$16="",0,IF(ISNUMBER(SEARCH(Classifiers!$E$16,E14)),1,0))+IF(Classifiers!$F$16="",0,IF(ISNUMBER(SEARCH(Classifiers!$F$16,E14)),1,0))+IF(Classifiers!$G$16="",0,IF(ISNUMBER(SEARCH(Classifiers!$G$16,E14)),1,0)))>0,1,0)) | V14: =IF(H14<>1,0,IF((IF(Classifiers!$B$17="",0,IF(ISNUMBER(SEARCH(Classifiers!$B$17,E14)),1,0))+IF(Classifiers!$C$17="",0,IF(ISNUMBER(SEARCH(Classifiers!$C$17,E14)),1,0))+IF(Classifiers!$D$17="",0,IF(ISNUMBER(SEARCH(Classifiers!$D$17,E14)),1,0))+IF(Classifiers!$E$17="",0,IF(ISNUMBER(SEARCH(Classifiers!$E$17,E14)),1,0))+IF(Classifiers!$F$17="",0,IF(ISNUMBER(SEARCH(Classifiers!$F$17,E14)),1,0))+IF(Classifiers!$G$17="",0,IF(ISNUMBER(SEARCH(Classifiers!$G$17,E14)),1,0)))>0,1,0)) | W14: =IF(H14<>1,0,IF((IF(Classifiers!$B$18="",0,IF(ISNUMBER(SEARCH(Classifiers!$B$18,E14)),1,0))+IF(Classifiers!$C$18="",0,IF(ISNUMBER(SEARCH(Classifiers!$C$18,E14)),1,0))+IF(Classifiers!$D$18="",0,IF(ISNUMBER(SEARCH(Classifiers!$D$18,E14)),1,0))+IF(Classifiers!$E$18="",0,IF(ISNUMBER(SEARCH(Classifiers!$E$18,E14)),1,0))+IF(Classifiers!$F$18="",0,IF(ISNUMBER(SEARCH(Classifiers!$F$18,E14)),1,0))+IF(Classifiers!$G$18="",0,IF(ISNUMBER(SEARCH(Classifiers!$G$18,E14)),1,0)))>0,1,0))
C15: =IF(A15="","",TRIM(RIGHT(SUBSTITUTE(A15,"/",REPT(" ",250)),250))) | D15: =IF(C15="","",IF(ISNUMBER(SEARCH(".",C15)),LOWER("."&TRIM(RIGHT(SUBSTITUTE(C15,".",REPT(" ",250)),250))),"")) | E15: =IF(C15="","",TRIM(SUBSTITUTE(SUBSTITUTE(SUBSTITUTE(SUBSTITUTE(SUBSTITUTE(SUBSTITUTE(SUBSTITUTE(SUBSTITUTE(SUBSTITUTE(SUBSTITUTE(SUBSTITUTE(SUBSTITUTE(SUBSTITUTE(SUBSTITUTE(SUBSTITUTE(SUBSTITUTE(SUBSTITUTE(SUBSTITUTE(SUBSTITUTE(SUBSTITUTE(LOWER(LEFT(C15,LEN(C15)-LEN(D15))),"_"," "),"-"," "),"."," "),","," "),"("," "),")"," "),"["," "),"]"," "),"&"," "),"+"," "),"@"," "),"#"," "),"!"," "),"'"," "),"/"," "),":"," "),";"," "),"="," "),"~"," "),"%"," "))) | F15: =IF(C15="","",IF(COUNTIF(Classifiers!$A$23:$A$40,D15)>0,1,0)) | G15: =IF(C15="","",IF(COUNTIF(Classifiers!$C$23:$C$30,D15)>0,IF((IF(ISNUMBER(SEARCH(Classifiers!$E$23,E15)),1,0)+IF(ISNUMBER(SEARCH(Classifiers!$E$24,E15)),1,0)+IF(ISNUMBER(SEARCH(Classifiers!$E$25,E15)),1,0)+IF(ISNUMBER(SEARCH(Classifiers!$E$26,E15)),1,0)+IF(ISNUMBER(SEARCH(Classifiers!$E$27,E15)),1,0)+IF(ISNUMBER(SEARCH(Classifiers!$E$28,E15)),1,0)+IF(ISNUMBER(SEARCH(Classifiers!$E$29,E15)),1,0)+IF(ISNUMBER(SEARCH(Classifiers!$E$30,E15)),1,0))>0,1,0),0)) | H15: =IF(C15="","",IF(OR(LEFT(C15,1)=".",AND(F15=0,G15=0)),0,1)) | I15: =IF(H15<>1,"",IF(SUM(J15:W15)=0,"unclassified",INDEX(Classifiers!$A$5:$A$18,MATCH(1,J15:W15,0),1))) | J15: =IF(H15<>1,0,IF((IF(Classifiers!$B$5="",0,IF(ISNUMBER(SEARCH(Classifiers!$B$5,E15)),1,0))+IF(Classifiers!$C$5="",0,IF(ISNUMBER(SEARCH(Classifiers!$C$5,E15)),1,0))+IF(Classifiers!$D$5="",0,IF(ISNUMBER(SEARCH(Classifiers!$D$5,E15)),1,0))+IF(Classifiers!$E$5="",0,IF(ISNUMBER(SEARCH(Classifiers!$E$5,E15)),1,0))+IF(Classifiers!$F$5="",0,IF(ISNUMBER(SEARCH(Classifiers!$F$5,E15)),1,0))+IF(Classifiers!$G$5="",0,IF(ISNUMBER(SEARCH(Classifiers!$G$5,E15)),1,0)))>0,1,0)) | K15: =IF(H15<>1,0,IF((IF(Classifiers!$B$6="",0,IF(ISNUMBER(SEARCH(Classifiers!$B$6,E15)),1,0))+IF(Classifiers!$C$6="",0,IF(ISNUMBER(SEARCH(Classifiers!$C$6,E15)),1,0))+IF(Classifiers!$D$6="",0,IF(ISNUMBER(SEARCH(Classifiers!$D$6,E15)),1,0))+IF(Classifiers!$E$6="",0,IF(ISNUMBER(SEARCH(Classifiers!$E$6,E15)),1,0))+IF(Classifiers!$F$6="",0,IF(ISNUMBER(SEARCH(Classifiers!$F$6,E15)),1,0))+IF(Classifiers!$G$6="",0,IF(ISNUMBER(SEARCH(Classifiers!$G$6,E15)),1,0)))>0,1,0)) | L15: =IF(H15<>1,0,IF((IF(Classifiers!$B$7="",0,IF(ISNUMBER(SEARCH(Classifiers!$B$7,E15)),1,0))+IF(Classifiers!$C$7="",0,IF(ISNUMBER(SEARCH(Classifiers!$C$7,E15)),1,0))+IF(Classifiers!$D$7="",0,IF(ISNUMBER(SEARCH(Classifiers!$D$7,E15)),1,0))+IF(Classifiers!$E$7="",0,IF(ISNUMBER(SEARCH(Classifiers!$E$7,E15)),1,0))+IF(Classifiers!$F$7="",0,IF(ISNUMBER(SEARCH(Classifiers!$F$7,E15)),1,0))+IF(Classifiers!$G$7="",0,IF(ISNUMBER(SEARCH(Classifiers!$G$7,E15)),1,0)))>0,1,0)) | M15: =IF(H15<>1,0,IF((IF(Classifiers!$B$8="",0,IF(ISNUMBER(SEARCH(Classifiers!$B$8,E15)),1,0))+IF(Classifiers!$C$8="",0,IF(ISNUMBER(SEARCH(Classifiers!$C$8,E15)),1,0))+IF(Classifiers!$D$8="",0,IF(ISNUMBER(SEARCH(Classifiers!$D$8,E15)),1,0))+IF(Classifiers!$E$8="",0,IF(ISNUMBER(SEARCH(Classifiers!$E$8,E15)),1,0))+IF(Classifiers!$F$8="",0,IF(ISNUMBER(SEARCH(Classifiers!$F$8,E15)),1,0))+IF(Classifiers!$G$8="",0,IF(ISNUMBER(SEARCH(Classifiers!$G$8,E15)),1,0)))>0,1,0)) | N15: =IF(H15<>1,0,IF((IF(Classifiers!$B$9="",0,IF(ISNUMBER(SEARCH(Classifiers!$B$9,E15)),1,0))+IF(Classifiers!$C$9="",0,IF(ISNUMBER(SEARCH(Classifiers!$C$9,E15)),1,0))+IF(Classifiers!$D$9="",0,IF(ISNUMBER(SEARCH(Classifiers!$D$9,E15)),1,0))+IF(Classifiers!$E$9="",0,IF(ISNUMBER(SEARCH(Classifiers!$E$9,E15)),1,0))+IF(Classifiers!$F$9="",0,IF(ISNUMBER(SEARCH(Classifiers!$F$9,E15)),1,0))+IF(Classifiers!$G$9="",0,IF(ISNUMBER(SEARCH(Classifiers!$G$9,E15)),1,0)))>0,1,0)) | O15: =IF(H15<>1,0,IF((IF(Classifiers!$B$10="",0,IF(ISNUMBER(SEARCH(Classifiers!$B$10,E15)),1,0))+IF(Classifiers!$C$10="",0,IF(ISNUMBER(SEARCH(Classifiers!$C$10,E15)),1,0))+IF(Classifiers!$D$10="",0,IF(ISNUMBER(SEARCH(Classifiers!$D$10,E15)),1,0))+IF(Classifiers!$E$10="",0,IF(ISNUMBER(SEARCH(Classifiers!$E$10,E15)),1,0))+IF(Classifiers!$F$10="",0,IF(ISNUMBER(SEARCH(Classifiers!$F$10,E15)),1,0))+IF(Classifiers!$G$10="",0,IF(ISNUMBER(SEARCH(Classifiers!$G$10,E15)),1,0)))>0,1,0)) | P15: =IF(H15<>1,0,IF((IF(Classifiers!$B$11="",0,IF(ISNUMBER(SEARCH(Classifiers!$B$11,E15)),1,0))+IF(Classifiers!$C$11="",0,IF(ISNUMBER(SEARCH(Classifiers!$C$11,E15)),1,0))+IF(Classifiers!$D$11="",0,IF(ISNUMBER(SEARCH(Classifiers!$D$11,E15)),1,0))+IF(Classifiers!$E$11="",0,IF(ISNUMBER(SEARCH(Classifiers!$E$11,E15)),1,0))+IF(Classifiers!$F$11="",0,IF(ISNUMBER(SEARCH(Classifiers!$F$11,E15)),1,0))+IF(Classifiers!$G$11="",0,IF(ISNUMBER(SEARCH(Classifiers!$G$11,E15)),1,0)))>0,1,0)) | Q15: =IF(H15<>1,0,IF((IF(Classifiers!$B$12="",0,IF(ISNUMBER(SEARCH(Classifiers!$B$12,E15)),1,0))+IF(Classifiers!$C$12="",0,IF(ISNUMBER(SEARCH(Classifiers!$C$12,E15)),1,0))+IF(Classifiers!$D$12="",0,IF(ISNUMBER(SEARCH(Classifiers!$D$12,E15)),1,0))+IF(Classifiers!$E$12="",0,IF(ISNUMBER(SEARCH(Classifiers!$E$12,E15)),1,0))+IF(Classifiers!$F$12="",0,IF(ISNUMBER(SEARCH(Classifiers!$F$12,E15)),1,0))+IF(Classifiers!$G$12="",0,IF(ISNUMBER(SEARCH(Classifiers!$G$12,E15)),1,0)))>0,1,0)) | R15: =IF(H15<>1,0,IF((IF(Classifiers!$B$13="",0,IF(ISNUMBER(SEARCH(Classifiers!$B$13,E15)),1,0))+IF(Classifiers!$C$13="",0,IF(ISNUMBER(SEARCH(Classifiers!$C$13,E15)),1,0))+IF(Classifiers!$D$13="",0,IF(ISNUMBER(SEARCH(Classifiers!$D$13,E15)),1,0))+IF(Classifiers!$E$13="",0,IF(ISNUMBER(SEARCH(Classifiers!$E$13,E15)),1,0))+IF(Classifiers!$F$13="",0,IF(ISNUMBER(SEARCH(Classifiers!$F$13,E15)),1,0))+IF(Classifiers!$G$13="",0,IF(ISNUMBER(SEARCH(Classifiers!$G$13,E15)),1,0)))>0,1,0)) | S15: =IF(H15<>1,0,IF((IF(Classifiers!$B$14="",0,IF(ISNUMBER(SEARCH(Classifiers!$B$14,E15)),1,0))+IF(Classifiers!$C$14="",0,IF(ISNUMBER(SEARCH(Classifiers!$C$14,E15)),1,0))+IF(Classifiers!$D$14="",0,IF(ISNUMBER(SEARCH(Classifiers!$D$14,E15)),1,0))+IF(Classifiers!$E$14="",0,IF(ISNUMBER(SEARCH(Classifiers!$E$14,E15)),1,0))+IF(Classifiers!$F$14="",0,IF(ISNUMBER(SEARCH(Classifiers!$F$14,E15)),1,0))+IF(Classifiers!$G$14="",0,IF(ISNUMBER(SEARCH(Classifiers!$G$14,E15)),1,0)))>0,1,0)) | T15: =IF(H15<>1,0,IF((IF(Classifiers!$B$15="",0,IF(ISNUMBER(SEARCH(Classifiers!$B$15,E15)),1,0))+IF(Classifiers!$C$15="",0,IF(ISNUMBER(SEARCH(Classifiers!$C$15,E15)),1,0))+IF(Classifiers!$D$15="",0,IF(ISNUMBER(SEARCH(Classifiers!$D$15,E15)),1,0))+IF(Classifiers!$E$15="",0,IF(ISNUMBER(SEARCH(Classifiers!$E$15,E15)),1,0))+IF(Classifiers!$F$15="",0,IF(ISNUMBER(SEARCH(Classifiers!$F$15,E15)),1,0))+IF(Classifiers!$G$15="",0,IF(ISNUMBER(SEARCH(Classifiers!$G$15,E15)),1,0)))>0,1,0)) | U15: =IF(H15<>1,0,IF((IF(Classifiers!$B$16="",0,IF(ISNUMBER(SEARCH(Classifiers!$B$16,E15)),1,0))+IF(Classifiers!$C$16="",0,IF(ISNUMBER(SEARCH(Classifiers!$C$16,E15)),1,0))+IF(Classifiers!$D$16="",0,IF(ISNUMBER(SEARCH(Classifiers!$D$16,E15)),1,0))+IF(Classifiers!$E$16="",0,IF(ISNUMBER(SEARCH(Classifiers!$E$16,E15)),1,0))+IF(Classifiers!$F$16="",0,IF(ISNUMBER(SEARCH(Classifiers!$F$16,E15)),1,0))+IF(Classifiers!$G$16="",0,IF(ISNUMBER(SEARCH(Classifiers!$G$16,E15)),1,0)))>0,1,0)) | V15: =IF(H15<>1,0,IF((IF(Classifiers!$B$17="",0,IF(ISNUMBER(SEARCH(Classifiers!$B$17,E15)),1,0))+IF(Classifiers!$C$17="",0,IF(ISNUMBER(SEARCH(Classifiers!$C$17,E15)),1,0))+IF(Classifiers!$D$17="",0,IF(ISNUMBER(SEARCH(Classifiers!$D$17,E15)),1,0))+IF(Classifiers!$E$17="",0,IF(ISNUMBER(SEARCH(Classifiers!$E$17,E15)),1,0))+IF(Classifiers!$F$17="",0,IF(ISNUMBER(SEARCH(Classifiers!$F$17,E15)),1,0))+IF(Classifiers!$G$17="",0,IF(ISNUMBER(SEARCH(Classifiers!$G$17,E15)),1,0)))>0,1,0)) | W15: =IF(H15<>1,0,IF((IF(Classifiers!$B$18="",0,IF(ISNUMBER(SEARCH(Classifiers!$B$18,E15)),1,0))+IF(Classifiers!$C$18="",0,IF(ISNUMBER(SEARCH(Classifiers!$C$18,E15)),1,0))+IF(Classifiers!$D$18="",0,IF(ISNUMBER(SEARCH(Classifiers!$D$18,E15)),1,0))+IF(Classifiers!$E$18="",0,IF(ISNUMBER(SEARCH(Classifiers!$E$18,E15)),1,0))+IF(Classifiers!$F$18="",0,IF(ISNUMBER(SEARCH(Classifiers!$F$18,E15)),1,0))+IF(Classifiers!$G$18="",0,IF(ISNUMBER(SEARCH(Classifiers!$G$18,E15)),1,0)))>0,1,0))
C16: =IF(A16="","",TRIM(RIGHT(SUBSTITUTE(A16,"/",REPT(" ",250)),250))) | D16: =IF(C16="","",IF(ISNUMBER(SEARCH(".",C16)),LOWER("."&TRIM(RIGHT(SUBSTITUTE(C16,".",REPT(" ",250)),250))),"")) | E16: =IF(C16="","",TRIM(SUBSTITUTE(SUBSTITUTE(SUBSTITUTE(SUBSTITUTE(SUBSTITUTE(SUBSTITUTE(SUBSTITUTE(SUBSTITUTE(SUBSTITUTE(SUBSTITUTE(SUBSTITUTE(SUBSTITUTE(SUBSTITUTE(SUBSTITUTE(SUBSTITUTE(SUBSTITUTE(SUBSTITUTE(SUBSTITUTE(SUBSTITUTE(SUBSTITUTE(LOWER(LEFT(C16,LEN(C16)-LEN(D16))),"_"," "),"-"," "),"."," "),","," "),"("," "),")"," "),"["," "),"]"," "),"&"," "),"+"," "),"@"," "),"#"," "),"!"," "),"'"," "),"/"," "),":"," "),";"," "),"="," "),"~"," "),"%"," "))) | F16: =IF(C16="","",IF(COUNTIF(Classifiers!$A$23:$A$40,D16)>0,1,0)) | G16: =IF(C16="","",IF(COUNTIF(Classifiers!$C$23:$C$30,D16)>0,IF((IF(ISNUMBER(SEARCH(Classifiers!$E$23,E16)),1,0)+IF(ISNUMBER(SEARCH(Classifiers!$E$24,E16)),1,0)+IF(ISNUMBER(SEARCH(Classifiers!$E$25,E16)),1,0)+IF(ISNUMBER(SEARCH(Classifiers!$E$26,E16)),1,0)+IF(ISNUMBER(SEARCH(Classifiers!$E$27,E16)),1,0)+IF(ISNUMBER(SEARCH(Classifiers!$E$28,E16)),1,0)+IF(ISNUMBER(SEARCH(Classifiers!$E$29,E16)),1,0)+IF(ISNUMBER(SEARCH(Classifiers!$E$30,E16)),1,0))>0,1,0),0)) | H16: =IF(C16="","",IF(OR(LEFT(C16,1)=".",AND(F16=0,G16=0)),0,1)) | I16: =IF(H16<>1,"",IF(SUM(J16:W16)=0,"unclassified",INDEX(Classifiers!$A$5:$A$18,MATCH(1,J16:W16,0),1))) | J16: =IF(H16<>1,0,IF((IF(Classifiers!$B$5="",0,IF(ISNUMBER(SEARCH(Classifiers!$B$5,E16)),1,0))+IF(Classifiers!$C$5="",0,IF(ISNUMBER(SEARCH(Classifiers!$C$5,E16)),1,0))+IF(Classifiers!$D$5="",0,IF(ISNUMBER(SEARCH(Classifiers!$D$5,E16)),1,0))+IF(Classifiers!$E$5="",0,IF(ISNUMBER(SEARCH(Classifiers!$E$5,E16)),1,0))+IF(Classifiers!$F$5="",0,IF(ISNUMBER(SEARCH(Classifiers!$F$5,E16)),1,0))+IF(Classifiers!$G$5="",0,IF(ISNUMBER(SEARCH(Classifiers!$G$5,E16)),1,0)))>0,1,0)) | K16: =IF(H16<>1,0,IF((IF(Classifiers!$B$6="",0,IF(ISNUMBER(SEARCH(Classifiers!$B$6,E16)),1,0))+IF(Classifiers!$C$6="",0,IF(ISNUMBER(SEARCH(Classifiers!$C$6,E16)),1,0))+IF(Classifiers!$D$6="",0,IF(ISNUMBER(SEARCH(Classifiers!$D$6,E16)),1,0))+IF(Classifiers!$E$6="",0,IF(ISNUMBER(SEARCH(Classifiers!$E$6,E16)),1,0))+IF(Classifiers!$F$6="",0,IF(ISNUMBER(SEARCH(Classifiers!$F$6,E16)),1,0))+IF(Classifiers!$G$6="",0,IF(ISNUMBER(SEARCH(Classifiers!$G$6,E16)),1,0)))>0,1,0)) | L16: =IF(H16<>1,0,IF((IF(Classifiers!$B$7="",0,IF(ISNUMBER(SEARCH(Classifiers!$B$7,E16)),1,0))+IF(Classifiers!$C$7="",0,IF(ISNUMBER(SEARCH(Classifiers!$C$7,E16)),1,0))+IF(Classifiers!$D$7="",0,IF(ISNUMBER(SEARCH(Classifiers!$D$7,E16)),1,0))+IF(Classifiers!$E$7="",0,IF(ISNUMBER(SEARCH(Classifiers!$E$7,E16)),1,0))+IF(Classifiers!$F$7="",0,IF(ISNUMBER(SEARCH(Classifiers!$F$7,E16)),1,0))+IF(Classifiers!$G$7="",0,IF(ISNUMBER(SEARCH(Classifiers!$G$7,E16)),1,0)))>0,1,0)) | M16: =IF(H16<>1,0,IF((IF(Classifiers!$B$8="",0,IF(ISNUMBER(SEARCH(Classifiers!$B$8,E16)),1,0))+IF(Classifiers!$C$8="",0,IF(ISNUMBER(SEARCH(Classifiers!$C$8,E16)),1,0))+IF(Classifiers!$D$8="",0,IF(ISNUMBER(SEARCH(Classifiers!$D$8,E16)),1,0))+IF(Classifiers!$E$8="",0,IF(ISNUMBER(SEARCH(Classifiers!$E$8,E16)),1,0))+IF(Classifiers!$F$8="",0,IF(ISNUMBER(SEARCH(Classifiers!$F$8,E16)),1,0))+IF(Classifiers!$G$8="",0,IF(ISNUMBER(SEARCH(Classifiers!$G$8,E16)),1,0)))>0,1,0)) | N16: =IF(H16<>1,0,IF((IF(Classifiers!$B$9="",0,IF(ISNUMBER(SEARCH(Classifiers!$B$9,E16)),1,0))+IF(Classifiers!$C$9="",0,IF(ISNUMBER(SEARCH(Classifiers!$C$9,E16)),1,0))+IF(Classifiers!$D$9="",0,IF(ISNUMBER(SEARCH(Classifiers!$D$9,E16)),1,0))+IF(Classifiers!$E$9="",0,IF(ISNUMBER(SEARCH(Classifiers!$E$9,E16)),1,0))+IF(Classifiers!$F$9="",0,IF(ISNUMBER(SEARCH(Classifiers!$F$9,E16)),1,0))+IF(Classifiers!$G$9="",0,IF(ISNUMBER(SEARCH(Classifiers!$G$9,E16)),1,0)))>0,1,0)) | O16: =IF(H16<>1,0,IF((IF(Classifiers!$B$10="",0,IF(ISNUMBER(SEARCH(Classifiers!$B$10,E16)),1,0))+IF(Classifiers!$C$10="",0,IF(ISNUMBER(SEARCH(Classifiers!$C$10,E16)),1,0))+IF(Classifiers!$D$10="",0,IF(ISNUMBER(SEARCH(Classifiers!$D$10,E16)),1,0))+IF(Classifiers!$E$10="",0,IF(ISNUMBER(SEARCH(Classifiers!$E$10,E16)),1,0))+IF(Classifiers!$F$10="",0,IF(ISNUMBER(SEARCH(Classifiers!$F$10,E16)),1,0))+IF(Classifiers!$G$10="",0,IF(ISNUMBER(SEARCH(Classifiers!$G$10,E16)),1,0)))>0,1,0)) | P16: =IF(H16<>1,0,IF((IF(Classifiers!$B$11="",0,IF(ISNUMBER(SEARCH(Classifiers!$B$11,E16)),1,0))+IF(Classifiers!$C$11="",0,IF(ISNUMBER(SEARCH(Classifiers!$C$11,E16)),1,0))+IF(Classifiers!$D$11="",0,IF(ISNUMBER(SEARCH(Classifiers!$D$11,E16)),1,0))+IF(Classifiers!$E$11="",0,IF(ISNUMBER(SEARCH(Classifiers!$E$11,E16)),1,0))+IF(Classifiers!$F$11="",0,IF(ISNUMBER(SEARCH(Classifiers!$F$11,E16)),1,0))+IF(Classifiers!$G$11="",0,IF(ISNUMBER(SEARCH(Classifiers!$G$11,E16)),1,0)))>0,1,0)) | Q16: =IF(H16<>1,0,IF((IF(Classifiers!$B$12="",0,IF(ISNUMBER(SEARCH(Classifiers!$B$12,E16)),1,0))+IF(Classifiers!$C$12="",0,IF(ISNUMBER(SEARCH(Classifiers!$C$12,E16)),1,0))+IF(Classifiers!$D$12="",0,IF(ISNUMBER(SEARCH(Classifiers!$D$12,E16)),1,0))+IF(Classifiers!$E$12="",0,IF(ISNUMBER(SEARCH(Classifiers!$E$12,E16)),1,0))+IF(Classifiers!$F$12="",0,IF(ISNUMBER(SEARCH(Classifiers!$F$12,E16)),1,0))+IF(Classifiers!$G$12="",0,IF(ISNUMBER(SEARCH(Classifiers!$G$12,E16)),1,0)))>0,1,0)) | R16: =IF(H16<>1,0,IF((IF(Classifiers!$B$13="",0,IF(ISNUMBER(SEARCH(Classifiers!$B$13,E16)),1,0))+IF(Classifiers!$C$13="",0,IF(ISNUMBER(SEARCH(Classifiers!$C$13,E16)),1,0))+IF(Classifiers!$D$13="",0,IF(ISNUMBER(SEARCH(Classifiers!$D$13,E16)),1,0))+IF(Classifiers!$E$13="",0,IF(ISNUMBER(SEARCH(Classifiers!$E$13,E16)),1,0))+IF(Classifiers!$F$13="",0,IF(ISNUMBER(SEARCH(Classifiers!$F$13,E16)),1,0))+IF(Classifiers!$G$13="",0,IF(ISNUMBER(SEARCH(Classifiers!$G$13,E16)),1,0)))>0,1,0)) | S16: =IF(H16<>1,0,IF((IF(Classifiers!$B$14="",0,IF(ISNUMBER(SEARCH(Classifiers!$B$14,E16)),1,0))+IF(Classifiers!$C$14="",0,IF(ISNUMBER(SEARCH(Classifiers!$C$14,E16)),1,0))+IF(Classifiers!$D$14="",0,IF(ISNUMBER(SEARCH(Classifiers!$D$14,E16)),1,0))+IF(Classifiers!$E$14="",0,IF(ISNUMBER(SEARCH(Classifiers!$E$14,E16)),1,0))+IF(Classifiers!$F$14="",0,IF(ISNUMBER(SEARCH(Classifiers!$F$14,E16)),1,0))+IF(Classifiers!$G$14="",0,IF(ISNUMBER(SEARCH(Classifiers!$G$14,E16)),1,0)))>0,1,0)) | T16: =IF(H16<>1,0,IF((IF(Classifiers!$B$15="",0,IF(ISNUMBER(SEARCH(Classifiers!$B$15,E16)),1,0))+IF(Classifiers!$C$15="",0,IF(ISNUMBER(SEARCH(Classifiers!$C$15,E16)),1,0))+IF(Classifiers!$D$15="",0,IF(ISNUMBER(SEARCH(Classifiers!$D$15,E16)),1,0))+IF(Classifiers!$E$15="",0,IF(ISNUMBER(SEARCH(Classifiers!$E$15,E16)),1,0))+IF(Classifiers!$F$15="",0,IF(ISNUMBER(SEARCH(Classifiers!$F$15,E16)),1,0))+IF(Classifiers!$G$15="",0,IF(ISNUMBER(SEARCH(Classifiers!$G$15,E16)),1,0)))>0,1,0)) | U16: =IF(H16<>1,0,IF((IF(Classifiers!$B$16="",0,IF(ISNUMBER(SEARCH(Classifiers!$B$16,E16)),1,0))+IF(Classifiers!$C$16="",0,IF(ISNUMBER(SEARCH(Classifiers!$C$16,E16)),1,0))+IF(Classifiers!$D$16="",0,IF(ISNUMBER(SEARCH(Classifiers!$D$16,E16)),1,0))+IF(Classifiers!$E$16="",0,IF(ISNUMBER(SEARCH(Classifiers!$E$16,E16)),1,0))+IF(Classifiers!$F$16="",0,IF(ISNUMBER(SEARCH(Classifiers!$F$16,E16)),1,0))+IF(Classifiers!$G$16="",0,IF(ISNUMBER(SEARCH(Classifiers!$G$16,E16)),1,0)))>0,1,0)) | V16: =IF(H16<>1,0,IF((IF(Classifiers!$B$17="",0,IF(ISNUMBER(SEARCH(Classifiers!$B$17,E16)),1,0))+IF(Classifiers!$C$17="",0,IF(ISNUMBER(SEARCH(Classifiers!$C$17,E16)),1,0))+IF(Classifiers!$D$17="",0,IF(ISNUMBER(SEARCH(Classifiers!$D$17,E16)),1,0))+IF(Classifiers!$E$17="",0,IF(ISNUMBER(SEARCH(Classifiers!$E$17,E16)),1,0))+IF(Classifiers!$F$17="",0,IF(ISNUMBER(SEARCH(Classifiers!$F$17,E16)),1,0))+IF(Classifiers!$G$17="",0,IF(ISNUMBER(SEARCH(Classifiers!$G$17,E16)),1,0)))>0,1,0)) | W16: =IF(H16<>1,0,IF((IF(Classifiers!$B$18="",0,IF(ISNUMBER(SEARCH(Classifiers!$B$18,E16)),1,0))+IF(Classifiers!$C$18="",0,IF(ISNUMBER(SEARCH(Classifiers!$C$18,E16)),1,0))+IF(Classifiers!$D$18="",0,IF(ISNUMBER(SEARCH(Classifiers!$D$18,E16)),1,0))+IF(Classifiers!$E$18="",0,IF(ISNUMBER(SEARCH(Classifiers!$E$18,E16)),1,0))+IF(Classifiers!$F$18="",0,IF(ISNUMBER(SEARCH(Classifiers!$F$18,E16)),1,0))+IF(Classifiers!$G$18="",0,IF(ISNUMBER(SEARCH(Classifiers!$G$18,E16)),1,0)))>0,1,0))
... C504: =IF(A504="","",TRIM(RIGHT(SUBSTITUTE(A504,"/",REPT(" ",250)),250))) | D504: =IF(C504="","",IF(ISNUMBER(SEARCH(".",C504)),LOWER("."&TRIM(RIGHT(SUBSTITUTE(C504,".",REPT(" ",250)),250))),"")) | E504: =IF(C504="","",TRIM(SUBSTITUTE(SUBSTITUTE(SUBSTITUTE(SUBSTITUTE(SUBSTITUTE(SUBSTITUTE(SUBSTITUTE(SUBSTITUTE(SUBSTITUTE(SUBSTITUTE(SUBSTITUTE(SUBSTITUTE(SUBSTITUTE(SUBSTITUTE(SUBSTITUTE(SUBSTITUTE(SUBSTITUTE(SUBSTITUTE(SUBSTITUTE(SUBSTITUTE(LOWER(LEFT(C504,LEN(C504)-LEN(D504))),"_"," "),"-"," "),"."," "),","," "),"("," "),")"," "),"["," "),"]"," "),"&"," "),"+"," "),"@"," "),"#"," "),"!"," "),"'"," "),"/"," "),":"," "),";"," "),"="," "),"~"," "),"%"," "))) | F504: =IF(C504="","",IF(COUNTIF(Classifiers!$A$23:$A$40,D504)>0,1,0)) | G504: =IF(C504="","",IF(COUNTIF(Classifiers!$C$23:$C$30,D504)>0,IF((IF(ISNUMBER(SEARCH(Classifiers!$E$23,E504)),1,0)+IF(ISNUMBER(SEARCH(Classifiers!$E$24,E504)),1,0)+IF(ISNUMBER(SEARCH(Classifiers!$E$25,E504)),1,0)+IF(ISNUMBER(SEARCH(Classifiers!$E$26,E504)),1,0)+IF(ISNUMBER(SEARCH(Classifiers!$E$27,E504)),1,0)+IF(ISNUMBER(SEARCH(Classifiers!$E$28,E504)),1,0)+IF(ISNUMBER(SEARCH(Classifiers!$E$29,E504)),1,0)+IF(ISNUMBER(SEARCH(Classifiers!$E$30,E504)),1,0))>0,1,0),0)) | H504: =IF(C504="","",IF(OR(LEFT(C504,1)=".",AND(F504=0,G504=0)),0,1)) | I504: =IF(H504<>1,"",IF(SUM(J504:W504)=0,"unclassified",INDEX(Classifiers!$A$5:$A$18,MATCH(1,J504:W504,0),1))) | J504: =IF(H504<>1,0,IF((IF(Classifiers!$B$5="",0,IF(ISNUMBER(SEARCH(Classifiers!$B$5,E504)),1,0))+IF(Classifiers!$C$5="",0,IF(ISNUMBER(SEARCH(Classifiers!$C$5,E504)),1,0))+IF(Classifiers!$D$5="",0,IF(ISNUMBER(SEARCH(Classifiers!$D$5,E504)),1,0))+IF(Classifiers!$E$5="",0,IF(ISNUMBER(SEARCH(Classifiers!$E$5,E504)),1,0))+IF(Classifiers!$F$5="",0,IF(ISNUMBER(SEARCH(Classifiers!$F$5,E504)),1,0))+IF(Classifiers!$G$5="",0,IF(ISNUMBER(SEARCH(Classifiers!$G$5,E504)),1,0)))>0,1,0)) | K504: =IF(H504<>1,0,IF((IF(Classifiers!$B$6="",0,IF(ISNUMBER(SEARCH(Classifiers!$B$6,E504)),1,0))+IF(Classifiers!$C$6="",0,IF(ISNUMBER(SEARCH(Classifiers!$C$6,E504)),1,0))+IF(Classifiers!$D$6="",0,IF(ISNUMBER(SEARCH(Classifiers!$D$6,E504)),1,0))+IF(Classifiers!$E$6="",0,IF(ISNUMBER(SEARCH(Classifiers!$E$6,E504)),1,0))+IF(Classifiers!$F$6="",0,IF(ISNUMBER(SEARCH(Classifiers!$F$6,E504)),1,0))+IF(Classifiers!$G$6="",0,IF(ISNUMBER(SEARCH(Classifiers!$G$6,E504)),1,0)))>0,1,0)) | L504: =IF(H504<>1,0,IF((IF(Classifiers!$B$7="",0,IF(ISNUMBER(SEARCH(Classifiers!$B$7,E504)),1,0))+IF(Classifiers!$C$7="",0,IF(ISNUMBER(SEARCH(Classifiers!$C$7,E504)),1,0))+IF(Classifiers!$D$7="",0,IF(ISNUMBER(SEARCH(Classifiers!$D$7,E504)),1,0))+IF(Classifiers!$E$7="",0,IF(ISNUMBER(SEARCH(Classifiers!$E$7,E504)),1,0))+IF(Classifiers!$F$7="",0,IF(ISNUMBER(SEARCH(Classifiers!$F$7,E504)),1,0))+IF(Classifiers!$G$7="",0,IF(ISNUMBER(SEARCH(Classifiers!$G$7,E504)),1,0)))>0,1,0)) | M504: =IF(H504<>1,0,IF((IF(Classifiers!$B$8="",0,IF(ISNUMBER(SEARCH(Classifiers!$B$8,E504)),1,0))+IF(Classifiers!$C$8="",0,IF(ISNUMBER(SEARCH(Classifiers!$C$8,E504)),1,0))+IF(Classifiers!$D$8="",0,IF(ISNUMBER(SEARCH(Classifiers!$D$8,E504)),1,0))+IF(Classifiers!$E$8="",0,IF(ISNUMBER(SEARCH(Classifiers!$E$8,E504)),1,0))+IF(Classifiers!$F$8="",0,IF(ISNUMBER(SEARCH(Classifiers!$F$8,E504)),1,0))+IF(Classifiers!$G$8="",0,IF(ISNUMBER(SEARCH(Classifiers!$G$8,E504)),1,0)))>0,1,0)) | N504: =IF(H504<>1,0,IF((IF(Classifiers!$B$9="",0,IF(ISNUMBER(SEARCH(Classifiers!$B$9,E504)),1,0))+IF(Classifiers!$C$9="",0,IF(ISNUMBER(SEARCH(Classifiers!$C$9,E504)),1,0))+IF(Classifiers!$D$9="",0,IF(ISNUMBER(SEARCH(Classifiers!$D$9,E504)),1,0))+IF(Classifiers!$E$9="",0,IF(ISNUMBER(SEARCH(Classifiers!$E$9,E504)),1,0))+IF(Classifiers!$F$9="",0,IF(ISNUMBER(SEARCH(Classifiers!$F$9,E504)),1,0))+IF(Classifiers!$G$9="",0,IF(ISNUMBER(SEARCH(Classifiers!$G$9,E504)),1,0)))>0,1,0)) | O504: =IF(H504<>1,0,IF((IF(Classifiers!$B$10="",0,IF(ISNUMBER(SEARCH(Classifiers!$B$10,E504)),1,0))+IF(Classifiers!$C$10="",0,IF(ISNUMBER(SEARCH(Classifiers!$C$10,E504)),1,0))+IF(Classifiers!$D$10="",0,IF(ISNUMBER(SEARCH(Classifiers!$D$10,E504)),1,0))+IF(Classifiers!$E$10="",0,IF(ISNUMBER(SEARCH(Classifiers!$E$10,E504)),1,0))+IF(Classifiers!$F$10="",0,IF(ISNUMBER(SEARCH(Classifiers!$F$10,E504)),1,0))+IF(Classifiers!$G$10="",0,IF(ISNUMBER(SEARCH(Classifiers!$G$10,E504)),1,0)))>0,1,0)) | P504: =IF(H504<>1,0,IF((IF(Classifiers!$B$11="",0,IF(ISNUMBER(SEARCH(Classifiers!$B$11,E504)),1,0))+IF(Classifiers!$C$11="",0,IF(ISNUMBER(SEARCH(Classifiers!$C$11,E504)),1,0))+IF(Classifiers!$D$11="",0,IF(ISNUMBER(SEARCH(Classifiers!$D$11,E504)),1,0))+IF(Classifiers!$E$11="",0,IF(ISNUMBER(SEARCH(Classifiers!$E$11,E504)),1,0))+IF(Classifiers!$F$11="",0,IF(ISNUMBER(SEARCH(Classifiers!$F$11,E504)),1,0))+IF(Classifiers!$G$11="",0,IF(ISNUMBER(SEARCH(Classifiers!$G$11,E504)),1,0)))>0,1,0)) | Q504: =IF(H504<>1,0,IF((IF(Classifiers!$B$12="",0,IF(ISNUMBER(SEARCH(Classifiers!$B$12,E504)),1,0))+IF(Classifiers!$C$12="",0,IF(ISNUMBER(SEARCH(Classifiers!$C$12,E504)),1,0))+IF(Classifiers!$D$12="",0,IF(ISNUMBER(SEARCH(Classifiers!$D$12,E504)),1,0))+IF(Classifiers!$E$12="",0,IF(ISNUMBER(SEARCH(Classifiers!$E$12,E504)),1,0))+IF(Classifiers!$F$12="",0,IF(ISNUMBER(SEARCH(Classifiers!$F$12,E504)),1,0))+IF(Classifiers!$G$12="",0,IF(ISNUMBER(SEARCH(Classifiers!$G$12,E504)),1,0)))>0,1,0)) | R504: =IF(H504<>1,0,IF((IF(Classifiers!$B$13="",0,IF(ISNUMBER(SEARCH(Classifiers!$B$13,E504)),1,0))+IF(Classifiers!$C$13="",0,IF(ISNUMBER(SEARCH(Classifiers!$C$13,E504)),1,0))+IF(Classifiers!$D$13="",0,IF(ISNUMBER(SEARCH(Classifiers!$D$13,E504)),1,0))+IF(Classifiers!$E$13="",0,IF(ISNUMBER(SEARCH(Classifiers!$E$13,E504)),1,0))+IF(Classifiers!$F$13="",0,IF(ISNUMBER(SEARCH(Classifiers!$F$13,E504)),1,0))+IF(Classifiers!$G$13="",0,IF(ISNUMBER(SEARCH(Classifiers!$G$13,E504)),1,0)))>0,1,0)) | S504: =IF(H504<>1,0,IF((IF(Classifiers!$B$14="",0,IF(ISNUMBER(SEARCH(Classifiers!$B$14,E504)),1,0))+IF(Classifiers!$C$14="",0,IF(ISNUMBER(SEARCH(Classifiers!$C$14,E504)),1,0))+IF(Classifiers!$D$14="",0,IF(ISNUMBER(SEARCH(Classifiers!$D$14,E504)),1,0))+IF(Classifiers!$E$14="",0,IF(ISNUMBER(SEARCH(Classifiers!$E$14,E504)),1,0))+IF(Classifiers!$F$14="",0,IF(ISNUMBER(SEARCH(Classifiers!$F$14,E504)),1,0))+IF(Classifiers!$G$14="",0,IF(ISNUMBER(SEARCH(Classifiers!$G$14,E504)),1,0)))>0,1,0)) | T504: =IF(H504<>1,0,IF((IF(Classifiers!$B$15="",0,IF(ISNUMBER(SEARCH(Classifiers!$B$15,E504)),1,0))+IF(Classifiers!$C$15="",0,IF(ISNUMBER(SEARCH(Classifiers!$C$15,E504)),1,0))+IF(Classifiers!$D$15="",0,IF(ISNUMBER(SEARCH(Classifiers!$D$15,E504)),1,0))+IF(Classifiers!$E$15="",0,IF(ISNUMBER(SEARCH(Classifiers!$E$15,E504)),1,0))+IF(Classifiers!$F$15="",0,IF(ISNUMBER(SEARCH(Classifiers!$F$15,E504)),1,0))+IF(Classifiers!$G$15="",0,IF(ISNUMBER(SEARCH(Classifiers!$G$15,E504)),1,0)))>0,1,0)) | U504: =IF(H504<>1,0,IF((IF(Classifiers!$B$16="",0,IF(ISNUMBER(SEARCH(Classifiers!$B$16,E504)),1,0))+IF(Classifiers!$C$16="",0,IF(ISNUMBER(SEARCH(Classifiers!$C$16,E504)),1,0))+IF(Classifiers!$D$16="",0,IF(ISNUMBER(SEARCH(Classifiers!$D$16,E504)),1,0))+IF(Classifiers!$E$16="",0,IF(ISNUMBER(SEARCH(Classifiers!$E$16,E504)),1,0))+IF(Classifiers!$F$16="",0,IF(ISNUMBER(SEARCH(Classifiers!$F$16,E504)),1,0))+IF(Classifiers!$G$16="",0,IF(ISNUMBER(SEARCH(Classifiers!$G$16,E504)),1,0)))>0,1,0)) | V504: =IF(H504<>1,0,IF((IF(Classifiers!$B$17="",0,IF(ISNUMBER(SEARCH(Classifiers!$B$17,E504)),1,0))+IF(Classifiers!$C$17="",0,IF(ISNUMBER(SEARCH(Classifiers!$C$17,E504)),1,0))+IF(Classifiers!$D$17="",0,IF(ISNUMBER(SEARCH(Classifiers!$D$17,E504)),1,0))+IF(Classifiers!$E$17="",0,IF(ISNUMBER(SEARCH(Classifiers!$E$17,E504)),1,0))+IF(Classifiers!$F$17="",0,IF(ISNUMBER(SEARCH(Classifiers!$F$17,E504)),1,0))+IF(Classifiers!$G$17="",0,IF(ISNUMBER(SEARCH(Classifiers!$G$17,E504)),1,0)))>0,1,0)) | W504: =IF(H504<>1,0,IF((IF(Classifiers!$B$18="",0,IF(ISNUMBER(SEARCH(Classifiers!$B$18,E504)),1,0))+IF(Classifiers!$C$18="",0,IF(ISNUMBER(SEARCH(Classifiers!$C$18,E504)),1,0))+IF(Classifiers!$D$18="",0,IF(ISNUMBER(SEARCH(Classifiers!$D$18,E504)),1,0))+IF(Classifiers!$E$18="",0,IF(ISNUMBER(SEARCH(Classifiers!$E$18,E504)),1,0))+IF(Classifiers!$F$18="",0,IF(ISNUMBER(SEARCH(Classifiers!$F$18,E504)),1,0))+IF(Classifiers!$G$18="",0,IF(ISNUMBER(SEARCH(Classifiers!$G$18,E504)),1,0)))>0,1,0))

Sheet Classifiers
A1: Classifier rules (category order = priority; signals are substrings of the normalised file stem)
A4: category | B4: signal 1 | C4: signal 2 | D4: signal 3 | E4: signal 4 | F4: signal 5 | G4: signal 6
A5: profit_and_loss | B5: pnl | C5: p l | D5: profit loss | E5: income statement
A6: balance_sheet | B6: balance sheet | C6: trial balance
A7: ar_aging | B7: ar aging | C7: accounts receivable | D7: receivable aging
A8: ap_aging | B8: ap aging | C8: accounts payable | D8: payable aging
A9: inventory | B9: inventory | C9: stock on hand | D9: sku | E9: item detail
A10: cash_and_bank | B10: cash | C10: bank | D10: treasury
A11: payroll_and_headcount | B11: payroll | C11: headcount | D11: wages | E11: compensation
A12: sales_and_revenue | B12: sales | C12: revenue | D12: bookings | E12: orders | F12: crm
A13: budget_and_forecast | B13: budget | C13: forecast | D13: plan | E13: scenario
A14: operations | B14: operations | C14: operational | D14: production | E14: utilization | F14: fleet
A15: gst_and_indirect_tax | B15: gstr | C15: gst | D15: e way | E15: eway | F15: e invoice | G15: itc
A16: tds_and_direct_tax | B16: tds | C16: 26as | D16: ais | E16: form 16 | F16: advance tax | G16: itr
A17: statutory_payroll | B17: epf | C17: pf ecr | D17: esi | E17: professional tax | F17: lwf | G17: gratuity
A18: tally_or_erp_export | B18: tally | C18: daybook | D18: day book | E18: ledger | F18: zoho books | G18: busy
A22: data extensions | C22: context extensions | E22: context signals | G22: priority categories
A23: .csv | C23: .md | E23: business | G23: profit_and_loss
A24: .json | C24: .txt | E24: board | G24: balance_sheet
A25: .parquet | E25: covenant | G25: ar_aging
A26: .pdf | E26: finance | G26: ap_aging
A27: .tsv | E27: model | G27: inventory
A28: .xls | E28: planning
A29: .xlsm | E29: pricing
A30: .xlsx | E30: strategy
A31: .xml
A32: .yaml
A33: .yml
A34: .ods

Sheet Inspect_Summary
A1: Inspect summary (InspectionResult)
A4: candidate file_count | B4: =SUM(Inspect!H5:H504)
A6: category | B6: count | C6: priority? | D6: missing priority?
A7: profit_and_loss | B7: =COUNTIF(Inspect!$I$5:$I$504,A7) | C7: =IF(COUNTIF(Classifiers!$G$23:$G$30,A7)>0,"yes","") | D7: =IF(AND(C7="yes",B7=0),"MISSING","")
A8: balance_sheet | B8: =COUNTIF(Inspect!$I$5:$I$504,A8) | C8: =IF(COUNTIF(Classifiers!$G$23:$G$30,A8)>0,"yes","") | D8: =IF(AND(C8="yes",B8=0),"MISSING","")
A9: ar_aging | B9: =COUNTIF(Inspect!$I$5:$I$504,A9) | C9: =IF(COUNTIF(Classifiers!$G$23:$G$30,A9)>0,"yes","") | D9: =IF(AND(C9="yes",B9=0),"MISSING","")
A10: ap_aging | B10: =COUNTIF(Inspect!$I$5:$I$504,A10) | C10: =IF(COUNTIF(Classifiers!$G$23:$G$30,A10)>0,"yes","") | D10: =IF(AND(C10="yes",B10=0),"MISSING","")
A11: inventory | B11: =COUNTIF(Inspect!$I$5:$I$504,A11) | C11: =IF(COUNTIF(Classifiers!$G$23:$G$30,A11)>0,"yes","") | D11: =IF(AND(C11="yes",B11=0),"MISSING","")
A12: cash_and_bank | B12: =COUNTIF(Inspect!$I$5:$I$504,A12) | C12: =IF(COUNTIF(Classifiers!$G$23:$G$30,A12)>0,"yes","") | D12: =IF(AND(C12="yes",B12=0),"MISSING","")
A13: payroll_and_headcount | B13: =COUNTIF(Inspect!$I$5:$I$504,A13) | C13: =IF(COUNTIF(Classifiers!$G$23:$G$30,A13)>0,"yes","") | D13: =IF(AND(C13="yes",B13=0),"MISSING","")
A14: sales_and_revenue | B14: =COUNTIF(Inspect!$I$5:$I$504,A14) | C14: =IF(COUNTIF(Classifiers!$G$23:$G$30,A14)>0,"yes","") | D14: =IF(AND(C14="yes",B14=0),"MISSING","")
A15: budget_and_forecast | B15: =COUNTIF(Inspect!$I$5:$I$504,A15) | C15: =IF(COUNTIF(Classifiers!$G$23:$G$30,A15)>0,"yes","") | D15: =IF(AND(C15="yes",B15=0),"MISSING","")
A16: operations | B16: =COUNTIF(Inspect!$I$5:$I$504,A16) | C16: =IF(COUNTIF(Classifiers!$G$23:$G$30,A16)>0,"yes","") | D16: =IF(AND(C16="yes",B16=0),"MISSING","")
A17: gst_and_indirect_tax | B17: =COUNTIF(Inspect!$I$5:$I$504,A17) | C17: =IF(COUNTIF(Classifiers!$G$23:$G$30,A17)>0,"yes","") | D17: =IF(AND(C17="yes",B17=0),"MISSING","")
A18: tds_and_direct_tax | B18: =COUNTIF(Inspect!$I$5:$I$504,A18) | C18: =IF(COUNTIF(Classifiers!$G$23:$G$30,A18)>0,"yes","") | D18: =IF(AND(C18="yes",B18=0),"MISSING","")
... A21: unclassified | B21: =COUNTIF(Inspect!$I$5:$I$504,A21) | C21: =IF(COUNTIF(Classifiers!$G$23:$G$30,A21)>0,"yes","") | D21: =IF(AND(C21="yes",B21=0),"MISSING","")

Sheet Profile
A1: Profile (source-profile): paste header in row 10 and data from row 11 (cols A..O, up to 1,000 rows)
A3: rows (non-empty) | B3: =SUM(R11:R1010)
A4: duplicate_rows (repeats of an earlier row) | B4: =SUM(S11:S1010)
A5: columns | B5: =SUMPRODUCT((A10:O10<>"")*1)
A7: empty_by_column ->
A8: =IF(A10="","",SUMPRODUCT(($R$11:$R$1010=1)*(A11:A1010=""))) | B8: =IF(B10="","",SUMPRODUCT(($R$11:$R$1010=1)*(B11:B1010=""))) | C8: =IF(C10="","",SUMPRODUCT(($R$11:$R$1010=1)*(C11:C1010=""))) | D8: =IF(D10="","",SUMPRODUCT(($R$11:$R$1010=1)*(D11:D1010=""))) | E8: =IF(E10="","",SUMPRODUCT(($R$11:$R$1010=1)*(E11:E1010=""))) | F8: =IF(F10="","",SUMPRODUCT(($R$11:$R$1010=1)*(F11:F1010=""))) | G8: =IF(G10="","",SUMPRODUCT(($R$11:$R$1010=1)*(G11:G1010=""))) | H8: =IF(H10="","",SUMPRODUCT(($R$11:$R$1010=1)*(H11:H1010=""))) | ... O8: =IF(O10="","",SUMPRODUCT(($R$11:$R$1010=1)*(O11:O1010="")))
Q9: row key (helper) | R9: non-empty | S9: duplicate of earlier
Q11: =A11&"|"&B11&"|"&C11&"|"&D11&"|"&E11&"|"&F11&"|"&G11&"|"&H11&"|"&I11&"|"&J11&"|"&K11&"|"&L11&"|"&M11&"|"&N11&"|"&O11 | R11: =IF(Q11=REPT("|",14),0,1) | S11: =0
Q12: =A12&"|"&B12&"|"&C12&"|"&D12&"|"&E12&"|"&F12&"|"&G12&"|"&H12&"|"&I12&"|"&J12&"|"&K12&"|"&L12&"|"&M12&"|"&N12&"|"&O12 | R12: =IF(Q12=REPT("|",14),0,1) | S12: =IF(R12=0,0,IF(SUMPRODUCT(($Q$11:Q11=Q12)*($R$11:R11=1))>0,1,0))
Q13: =A13&"|"&B13&"|"&C13&"|"&D13&"|"&E13&"|"&F13&"|"&G13&"|"&H13&"|"&I13&"|"&J13&"|"&K13&"|"&L13&"|"&M13&"|"&N13&"|"&O13 | R13: =IF(Q13=REPT("|",14),0,1) | S13: =IF(R13=0,0,IF(SUMPRODUCT(($Q$11:Q12=Q13)*($R$11:R12=1))>0,1,0))
Q14: =A14&"|"&B14&"|"&C14&"|"&D14&"|"&E14&"|"&F14&"|"&G14&"|"&H14&"|"&I14&"|"&J14&"|"&K14&"|"&L14&"|"&M14&"|"&N14&"|"&O14 | R14: =IF(Q14=REPT("|",14),0,1) | S14: =IF(R14=0,0,IF(SUMPRODUCT(($Q$11:Q13=Q14)*($R$11:R13=1))>0,1,0))
Q15: =A15&"|"&B15&"|"&C15&"|"&D15&"|"&E15&"|"&F15&"|"&G15&"|"&H15&"|"&I15&"|"&J15&"|"&K15&"|"&L15&"|"&M15&"|"&N15&"|"&O15 | R15: =IF(Q15=REPT("|",14),0,1) | S15: =IF(R15=0,0,IF(SUMPRODUCT(($Q$11:Q14=Q15)*($R$11:R14=1))>0,1,0))
Q16: =A16&"|"&B16&"|"&C16&"|"&D16&"|"&E16&"|"&F16&"|"&G16&"|"&H16&"|"&I16&"|"&J16&"|"&K16&"|"&L16&"|"&M16&"|"&N16&"|"&O16 | R16: =IF(Q16=REPT("|",14),0,1) | S16: =IF(R16=0,0,IF(SUMPRODUCT(($Q$11:Q15=Q16)*($R$11:R15=1))>0,1,0))
Q17: =A17&"|"&B17&"|"&C17&"|"&D17&"|"&E17&"|"&F17&"|"&G17&"|"&H17&"|"&I17&"|"&J17&"|"&K17&"|"&L17&"|"&M17&"|"&N17&"|"&O17 | R17: =IF(Q17=REPT("|",14),0,1) | S17: =IF(R17=0,0,IF(SUMPRODUCT(($Q$11:Q16=Q17)*($R$11:R16=1))>0,1,0))
Q18: =A18&"|"&B18&"|"&C18&"|"&D18&"|"&E18&"|"&F18&"|"&G18&"|"&H18&"|"&I18&"|"&J18&"|"&K18&"|"&L18&"|"&M18&"|"&N18&"|"&O18 | R18: =IF(Q18=REPT("|",14),0,1) | S18: =IF(R18=0,0,IF(SUMPRODUCT(($Q$11:Q17=Q18)*($R$11:R17=1))>0,1,0))
Q19: =A19&"|"&B19&"|"&C19&"|"&D19&"|"&E19&"|"&F19&"|"&G19&"|"&H19&"|"&I19&"|"&J19&"|"&K19&"|"&L19&"|"&M19&"|"&N19&"|"&O19 | R19: =IF(Q19=REPT("|",14),0,1) | S19: =IF(R19=0,0,IF(SUMPRODUCT(($Q$11:Q18=Q19)*($R$11:R18=1))>0,1,0))
Q20: =A20&"|"&B20&"|"&C20&"|"&D20&"|"&E20&"|"&F20&"|"&G20&"|"&H20&"|"&I20&"|"&J20&"|"&K20&"|"&L20&"|"&M20&"|"&N20&"|"&O20 | R20: =IF(Q20=REPT("|",14),0,1) | S20: =IF(R20=0,0,IF(SUMPRODUCT(($Q$11:Q19=Q20)*($R$11:R19=1))>0,1,0))
Q21: =A21&"|"&B21&"|"&C21&"|"&D21&"|"&E21&"|"&F21&"|"&G21&"|"&H21&"|"&I21&"|"&J21&"|"&K21&"|"&L21&"|"&M21&"|"&N21&"|"&O21 | R21: =IF(Q21=REPT("|",14),0,1) | S21: =IF(R21=0,0,IF(SUMPRODUCT(($Q$11:Q20=Q21)*($R$11:R20=1))>0,1,0))
Q22: =A22&"|"&B22&"|"&C22&"|"&D22&"|"&E22&"|"&F22&"|"&G22&"|"&H22&"|"&I22&"|"&J22&"|"&K22&"|"&L22&"|"&M22&"|"&N22&"|"&O22 | R22: =IF(Q22=REPT("|",14),0,1) | S22: =IF(R22=0,0,IF(SUMPRODUCT(($Q$11:Q21=Q22)*($R$11:R21=1))>0,1,0))
Q23: =A23&"|"&B23&"|"&C23&"|"&D23&"|"&E23&"|"&F23&"|"&G23&"|"&H23&"|"&I23&"|"&J23&"|"&K23&"|"&L23&"|"&M23&"|"&N23&"|"&O23 | R23: =IF(Q23=REPT("|",14),0,1) | S23: =IF(R23=0,0,IF(SUMPRODUCT(($Q$11:Q22=Q23)*($R$11:R22=1))>0,1,0))
... Q1010: =A1010&"|"&B1010&"|"&C1010&"|"&D1010&"|"&E1010&"|"&F1010&"|"&G1010&"|"&H1010&"|"&I1010&"|"&J1010&"|"&K1010&"|"&L1010&"|"&M1010&"|"&N1010&"|"&O1010 | R1010: =IF(Q1010=REPT("|",14),0,1) | S1010: =IF(R1010=0,0,IF(SUMPRODUCT(($Q$11:Q1009=Q1010)*($R$11:R1009=1))>0,1,0))

Sheet Mapping
A1: Mapping registry rows (paste memory/mappings/registry.csv)
A4: source_id | B4: source_value | C4: target | D4: status (mapped/ignored) | E4: rationale | F4: key (formula) | G4: valid rule? | H4: first target occurrence (helper)
A5: tally-pl-monthly | B5: Sales - Domestic (TN) @18% | C5: income_statement.revenue | D5: mapped | F5: =IF(B5="","",TRIM(A5)&"||"&TRIM(B5)) | G5: =IF(B5="","",IF(OR(AND(LOWER(D5)="mapped",TRIM(C5)<>""),AND(LOWER(D5)="ignored",TRIM(E5)<>"")),1,0)) | H5: =IF(AND(TRIM(A5)=Setup!$B$4,LOWER(D5)="mapped",TRIM(C5)<>""),IF(SUMPRODUCT((TRIM($A$5:A5)=Setup!$B$4)*(LOWER($D$5:D5)="mapped")*(TRIM($C$5:C5)=TRIM(C5)))=1,ROW(),""),"")
A6: tally-pl-monthly | B6: Sales - Interstate (Kerala/Karnataka) @18% | C6: income_statement.revenue | D6: mapped | F6: =IF(B6="","",TRIM(A6)&"||"&TRIM(B6)) | G6: =IF(B6="","",IF(OR(AND(LOWER(D6)="mapped",TRIM(C6)<>""),AND(LOWER(D6)="ignored",TRIM(E6)<>"")),1,0)) | H6: =IF(AND(TRIM(A6)=Setup!$B$4,LOWER(D6)="mapped",TRIM(C6)<>""),IF(SUMPRODUCT((TRIM($A$5:A6)=Setup!$B$4)*(LOWER($D$5:D6)="mapped")*(TRIM($C$5:C6)=TRIM(C6)))=1,ROW(),""),"")
A7: tally-pl-monthly | B7: Sales - Marketplace (Amazon/Flipkart) | C7: income_statement.revenue | D7: mapped | F7: =IF(B7="","",TRIM(A7)&"||"&TRIM(B7)) | G7: =IF(B7="","",IF(OR(AND(LOWER(D7)="mapped",TRIM(C7)<>""),AND(LOWER(D7)="ignored",TRIM(E7)<>"")),1,0)) | H7: =IF(AND(TRIM(A7)=Setup!$B$4,LOWER(D7)="mapped",TRIM(C7)<>""),IF(SUMPRODUCT((TRIM($A$5:A7)=Setup!$B$4)*(LOWER($D$5:D7)="mapped")*(TRIM($C$5:C7)=TRIM(C7)))=1,ROW(),""),"")
A8: tally-pl-monthly | B8: Sales Returns & Dealer Schemes | C8: income_statement.revenue | D8: mapped | E8: schemes are revenue deductions (Ind AS 115 / AS 9) | F8: =IF(B8="","",TRIM(A8)&"||"&TRIM(B8)) | G8: =IF(B8="","",IF(OR(AND(LOWER(D8)="mapped",TRIM(C8)<>""),AND(LOWER(D8)="ignored",TRIM(E8)<>"")),1,0)) | H8: =IF(AND(TRIM(A8)=Setup!$B$4,LOWER(D8)="mapped",TRIM(C8)<>""),IF(SUMPRODUCT((TRIM($A$5:A8)=Setup!$B$4)*(LOWER($D$5:D8)="mapped")*(TRIM($C$5:C8)=TRIM(C8)))=1,ROW(),""),"")
A9: tally-pl-monthly | B9: Purchase - Rubberwood & Teak | C9: income_statement.cogs | D9: mapped | F9: =IF(B9="","",TRIM(A9)&"||"&TRIM(B9)) | G9: =IF(B9="","",IF(OR(AND(LOWER(D9)="mapped",TRIM(C9)<>""),AND(LOWER(D9)="ignored",TRIM(E9)<>"")),1,0)) | H9: =IF(AND(TRIM(A9)=Setup!$B$4,LOWER(D9)="mapped",TRIM(C9)<>""),IF(SUMPRODUCT((TRIM($A$5:A9)=Setup!$B$4)*(LOWER($D$5:D9)="mapped")*(TRIM($C$5:C9)=TRIM(C9)))=1,ROW(),""),"")
A10: tally-pl-monthly | B10: Purchase - Steel & Mechanisms (incl. import) | C10: income_statement.cogs | D10: mapped | F10: =IF(B10="","",TRIM(A10)&"||"&TRIM(B10)) | G10: =IF(B10="","",IF(OR(AND(LOWER(D10)="mapped",TRIM(C10)<>""),AND(LOWER(D10)="ignored",TRIM(E10)<>"")),1,0)) | H10: =IF(AND(TRIM(A10)=Setup!$B$4,LOWER(D10)="mapped",TRIM(C10)<>""),IF(SUMPRODUCT((TRIM($A$5:A10)=Setup!$B$4)*(LOWER($D$5:D10)="mapped")*(TRIM($C$5:C10)=TRIM(C10)))=1,ROW(),""),"")
A11: tally-pl-monthly | B11: Factory Wages & Job Work | C11: income_statement.cogs | D11: mapped | F11: =IF(B11="","",TRIM(A11)&"||"&TRIM(B11)) | G11: =IF(B11="","",IF(OR(AND(LOWER(D11)="mapped",TRIM(C11)<>""),AND(LOWER(D11)="ignored",TRIM(E11)<>"")),1,0)) | H11: =IF(AND(TRIM(A11)=Setup!$B$4,LOWER(D11)="mapped",TRIM(C11)<>""),IF(SUMPRODUCT((TRIM($A$5:A11)=Setup!$B$4)*(LOWER($D$5:D11)="mapped")*(TRIM($C$5:C11)=TRIM(C11)))=1,ROW(),""),"")
A12: tally-pl-monthly | B12: Marketplace Commission & Fees | C12: income_statement.cogs | D12: mapped | E12: channel cost kept in online COGS | F12: =IF(B12="","",TRIM(A12)&"||"&TRIM(B12)) | G12: =IF(B12="","",IF(OR(AND(LOWER(D12)="mapped",TRIM(C12)<>""),AND(LOWER(D12)="ignored",TRIM(E12)<>"")),1,0)) | H12: =IF(AND(TRIM(A12)=Setup!$B$4,LOWER(D12)="mapped",TRIM(C12)<>""),IF(SUMPRODUCT((TRIM($A$5:A12)=Setup!$B$4)*(LOWER($D$5:D12)="mapped")*(TRIM($C$5:C12)=TRIM(C12)))=1,ROW(),""),"")
A13: tally-pl-monthly | B13: Salaries & Staff Welfare (office/sales) | C13: opex.payroll | D13: mapped | F13: =IF(B13="","",TRIM(A13)&"||"&TRIM(B13)) | G13: =IF(B13="","",IF(OR(AND(LOWER(D13)="mapped",TRIM(C13)<>""),AND(LOWER(D13)="ignored",TRIM(E13)<>"")),1,0)) | H13: =IF(AND(TRIM(A13)=Setup!$B$4,LOWER(D13)="mapped",TRIM(C13)<>""),IF(SUMPRODUCT((TRIM($A$5:A13)=Setup!$B$4)*(LOWER($D$5:D13)="mapped")*(TRIM($C$5:C13)=TRIM(C13)))=1,ROW(),""),"")
A14: tally-pl-monthly | B14: PF & ESI - Employer | C14: opex.payroll | D14: mapped | F14: =IF(B14="","",TRIM(A14)&"||"&TRIM(B14)) | G14: =IF(B14="","",IF(OR(AND(LOWER(D14)="mapped",TRIM(C14)<>""),AND(LOWER(D14)="ignored",TRIM(E14)<>"")),1,0)) | H14: =IF(AND(TRIM(A14)=Setup!$B$4,LOWER(D14)="mapped",TRIM(C14)<>""),IF(SUMPRODUCT((TRIM($A$5:A14)=Setup!$B$4)*(LOWER($D$5:D14)="mapped")*(TRIM($C$5:C14)=TRIM(C14)))=1,ROW(),""),"")
A15: tally-pl-monthly | B15: Advertisement & Dealer Meets | C15: opex.marketing | D15: mapped | F15: =IF(B15="","",TRIM(A15)&"||"&TRIM(B15)) | G15: =IF(B15="","",IF(OR(AND(LOWER(D15)="mapped",TRIM(C15)<>""),AND(LOWER(D15)="ignored",TRIM(E15)<>"")),1,0)) | H15: =IF(AND(TRIM(A15)=Setup!$B$4,LOWER(D15)="mapped",TRIM(C15)<>""),IF(SUMPRODUCT((TRIM($A$5:A15)=Setup!$B$4)*(LOWER($D$5:D15)="mapped")*(TRIM($C$5:C15)=TRIM(C15)))=1,ROW(),""),"")
A16: tally-pl-monthly | B16: Freight Outward | C16: opex.freight | D16: mapped | F16: =IF(B16="","",TRIM(A16)&"||"&TRIM(B16)) | G16: =IF(B16="","",IF(OR(AND(LOWER(D16)="mapped",TRIM(C16)<>""),AND(LOWER(D16)="ignored",TRIM(E16)<>"")),1,0)) | H16: =IF(AND(TRIM(A16)=Setup!$B$4,LOWER(D16)="mapped",TRIM(C16)<>""),IF(SUMPRODUCT((TRIM($A$5:A16)=Setup!$B$4)*(LOWER($D$5:D16)="mapped")*(TRIM($C$5:C16)=TRIM(C16)))=1,ROW(),""),"")
A17: tally-pl-monthly | B17: Rent - Factory Land (related party) | C17: opex.rent_facilities | D17: mapped | E17: RPT - see D28 | F17: =IF(B17="","",TRIM(A17)&"||"&TRIM(B17)) | G17: =IF(B17="","",IF(OR(AND(LOWER(D17)="mapped",TRIM(C17)<>""),AND(LOWER(D17)="ignored",TRIM(E17)<>"")),1,0)) | H17: =IF(AND(TRIM(A17)=Setup!$B$4,LOWER(D17)="mapped",TRIM(C17)<>""),IF(SUMPRODUCT((TRIM($A$5:A17)=Setup!$B$4)*(LOWER($D$5:D17)="mapped")*(TRIM($C$5:C17)=TRIM(C17)))=1,ROW(),""),"")
A18: tally-pl-monthly | B18: Electricity (TNPDCL) & Maintenance | C18: opex.rent_facilities | D18: mapped | F18: =IF(B18="","",TRIM(A18)&"||"&TRIM(B18)) | G18: =IF(B18="","",IF(OR(AND(LOWER(D18)="mapped",TRIM(C18)<>""),AND(LOWER(D18)="ignored",TRIM(E18)<>"")),1,0)) | H18: =IF(AND(TRIM(A18)=Setup!$B$4,LOWER(D18)="mapped",TRIM(C18)<>""),IF(SUMPRODUCT((TRIM($A$5:A18)=Setup!$B$4)*(LOWER($D$5:D18)="mapped")*(TRIM($C$5:C18)=TRIM(C18)))=1,ROW(),""),"")
A19: tally-pl-monthly | B19: Professional Fees, Software & Admin | C19: opex.admin | D19: mapped | F19: =IF(B19="","",TRIM(A19)&"||"&TRIM(B19)) | G19: =IF(B19="","",IF(OR(AND(LOWER(D19)="mapped",TRIM(C19)<>""),AND(LOWER(D19)="ignored",TRIM(E19)<>"")),1,0)) | H19: =IF(AND(TRIM(A19)=Setup!$B$4,LOWER(D19)="mapped",TRIM(C19)<>""),IF(SUMPRODUCT((TRIM($A$5:A19)=Setup!$B$4)*(LOWER($D$5:D19)="mapped")*(TRIM($C$5:C19)=TRIM(C19)))=1,ROW(),""),"")
A20: tally-pl-monthly | B20: Interest on Cash Credit | D20: ignored | E20: modelled in K01 debt schedule | F20: =IF(B20="","",TRIM(A20)&"||"&TRIM(B20)) | G20: =IF(B20="","",IF(OR(AND(LOWER(D20)="mapped",TRIM(C20)<>""),AND(LOWER(D20)="ignored",TRIM(E20)<>"")),1,0)) | H20: =IF(AND(TRIM(A20)=Setup!$B$4,LOWER(D20)="mapped",TRIM(C20)<>""),IF(SUMPRODUCT((TRIM($A$5:A20)=Setup!$B$4)*(LOWER($D$5:D20)="mapped")*(TRIM($C$5:C20)=TRIM(C20)))=1,ROW(),""),"")
A21: tally-pl-monthly | B21: Interest on TIIC Term Loan | D21: ignored | E21: modelled in K01 debt schedule | F21: =IF(B21="","",TRIM(A21)&"||"&TRIM(B21)) | G21: =IF(B21="","",IF(OR(AND(LOWER(D21)="mapped",TRIM(C21)<>""),AND(LOWER(D21)="ignored",TRIM(E21)<>"")),1,0)) | H21: =IF(AND(TRIM(A21)=Setup!$B$4,LOWER(D21)="mapped",TRIM(C21)<>""),IF(SUMPRODUCT((TRIM($A$5:A21)=Setup!$B$4)*(LOWER($D$5:D21)="mapped")*(TRIM($C$5:C21)=TRIM(C21)))=1,ROW(),""),"")
A22: tally-pl-monthly | B22: Depreciation | C22: da | D22: mapped | F22: =IF(B22="","",TRIM(A22)&"||"&TRIM(B22)) | G22: =IF(B22="","",IF(OR(AND(LOWER(D22)="mapped",TRIM(C22)<>""),AND(LOWER(D22)="ignored",TRIM(E22)<>"")),1,0)) | H22: =IF(AND(TRIM(A22)=Setup!$B$4,LOWER(D22)="mapped",TRIM(C22)<>""),IF(SUMPRODUCT((TRIM($A$5:A22)=Setup!$B$4)*(LOWER($D$5:D22)="mapped")*(TRIM($C$5:C22)=TRIM(C22)))=1,ROW(),""),"")
A23: tally-pl-monthly | B23: Output CGST | D23: ignored | E23: GST control ledger - GST cash in K02 via D24 | F23: =IF(B23="","",TRIM(A23)&"||"&TRIM(B23)) | G23: =IF(B23="","",IF(OR(AND(LOWER(D23)="mapped",TRIM(C23)<>""),AND(LOWER(D23)="ignored",TRIM(E23)<>"")),1,0)) | H23: =IF(AND(TRIM(A23)=Setup!$B$4,LOWER(D23)="mapped",TRIM(C23)<>""),IF(SUMPRODUCT((TRIM($A$5:A23)=Setup!$B$4)*(LOWER($D$5:D23)="mapped")*(TRIM($C$5:C23)=TRIM(C23)))=1,ROW(),""),"")
A24: tally-pl-monthly | B24: Output SGST | D24: ignored | E24: GST control ledger - GST cash in K02 via D24 | F24: =IF(B24="","",TRIM(A24)&"||"&TRIM(B24)) | G24: =IF(B24="","",IF(OR(AND(LOWER(D24)="mapped",TRIM(C24)<>""),AND(LOWER(D24)="ignored",TRIM(E24)<>"")),1,0)) | H24: =IF(AND(TRIM(A24)=Setup!$B$4,LOWER(D24)="mapped",TRIM(C24)<>""),IF(SUMPRODUCT((TRIM($A$5:A24)=Setup!$B$4)*(LOWER($D$5:D24)="mapped")*(TRIM($C$5:C24)=TRIM(C24)))=1,ROW(),""),"")
F25: =IF(B25="","",TRIM(A25)&"||"&TRIM(B25)) | G25: =IF(B25="","",IF(OR(AND(LOWER(D25)="mapped",TRIM(C25)<>""),AND(LOWER(D25)="ignored",TRIM(E25)<>"")),1,0)) | H25: =IF(AND(TRIM(A25)=Setup!$B$4,LOWER(D25)="mapped",TRIM(C25)<>""),IF(SUMPRODUCT((TRIM($A$5:A25)=Setup!$B$4)*(LOWER($D$5:D25)="mapped")*(TRIM($C$5:C25)=TRIM(C25)))=1,ROW(),""),"")
F26: =IF(B26="","",TRIM(A26)&"||"&TRIM(B26)) | G26: =IF(B26="","",IF(OR(AND(LOWER(D26)="mapped",TRIM(C26)<>""),AND(LOWER(D26)="ignored",TRIM(E26)<>"")),1,0)) | H26: =IF(AND(TRIM(A26)=Setup!$B$4,LOWER(D26)="mapped",TRIM(C26)<>""),IF(SUMPRODUCT((TRIM($A$5:A26)=Setup!$B$4)*(LOWER($D$5:D26)="mapped")*(TRIM($C$5:C26)=TRIM(C26)))=1,ROW(),""),"")
F27: =IF(B27="","",TRIM(A27)&"||"&TRIM(B27)) | G27: =IF(B27="","",IF(OR(AND(LOWER(D27)="mapped",TRIM(C27)<>""),AND(LOWER(D27)="ignored",TRIM(E27)<>"")),1,0)) | H27: =IF(AND(TRIM(A27)=Setup!$B$4,LOWER(D27)="mapped",TRIM(C27)<>""),IF(SUMPRODUCT((TRIM($A$5:A27)=Setup!$B$4)*(LOWER($D$5:D27)="mapped")*(TRIM($C$5:C27)=TRIM(C27)))=1,ROW(),""),"")
F28: =IF(B28="","",TRIM(A28)&"||"&TRIM(B28)) | G28: =IF(B28="","",IF(OR(AND(LOWER(D28)="mapped",TRIM(C28)<>""),AND(LOWER(D28)="ignored",TRIM(E28)<>"")),1,0)) | H28: =IF(AND(TRIM(A28)=Setup!$B$4,LOWER(D28)="mapped",TRIM(C28)<>""),IF(SUMPRODUCT((TRIM($A$5:A28)=Setup!$B$4)*(LOWER($D$5:D28)="mapped")*(TRIM($C$5:C28)=TRIM(C28)))=1,ROW(),""),"")
F29: =IF(B29="","",TRIM(A29)&"||"&TRIM(B29)) | G29: =IF(B29="","",IF(OR(AND(LOWER(D29)="mapped",TRIM(C29)<>""),AND(LOWER(D29)="ignored",TRIM(E29)<>"")),1,0)) | H29: =IF(AND(TRIM(A29)=Setup!$B$4,LOWER(D29)="mapped",TRIM(C29)<>""),IF(SUMPRODUCT((TRIM($A$5:A29)=Setup!$B$4)*(LOWER($D$5:D29)="mapped")*(TRIM($C$5:C29)=TRIM(C29)))=1,ROW(),""),"")
F30: =IF(B30="","",TRIM(A30)&"||"&TRIM(B30)) | G30: =IF(B30="","",IF(OR(AND(LOWER(D30)="mapped",TRIM(C30)<>""),AND(LOWER(D30)="ignored",TRIM(E30)<>"")),1,0)) | H30: =IF(AND(TRIM(A30)=Setup!$B$4,LOWER(D30)="mapped",TRIM(C30)<>""),IF(SUMPRODUCT((TRIM($A$5:A30)=Setup!$B$4)*(LOWER($D$5:D30)="mapped")*(TRIM($C$5:C30)=TRIM(C30)))=1,ROW(),""),"")
F31: =IF(B31="","",TRIM(A31)&"||"&TRIM(B31)) | G31: =IF(B31="","",IF(OR(AND(LOWER(D31)="mapped",TRIM(C31)<>""),AND(LOWER(D31)="ignored",TRIM(E31)<>"")),1,0)) | H31: =IF(AND(TRIM(A31)=Setup!$B$4,LOWER(D31)="mapped",TRIM(C31)<>""),IF(SUMPRODUCT((TRIM($A$5:A31)=Setup!$B$4)*(LOWER($D$5:D31)="mapped")*(TRIM($C$5:C31)=TRIM(C31)))=1,ROW(),""),"")
F32: =IF(B32="","",TRIM(A32)&"||"&TRIM(B32)) | G32: =IF(B32="","",IF(OR(AND(LOWER(D32)="mapped",TRIM(C32)<>""),AND(LOWER(D32)="ignored",TRIM(E32)<>"")),1,0)) | H32: =IF(AND(TRIM(A32)=Setup!$B$4,LOWER(D32)="mapped",TRIM(C32)<>""),IF(SUMPRODUCT((TRIM($A$5:A32)=Setup!$B$4)*(LOWER($D$5:D32)="mapped")*(TRIM($C$5:C32)=TRIM(C32)))=1,ROW(),""),"")
F33: =IF(B33="","",TRIM(A33)&"||"&TRIM(B33)) | G33: =IF(B33="","",IF(OR(AND(LOWER(D33)="mapped",TRIM(C33)<>""),AND(LOWER(D33)="ignored",TRIM(E33)<>"")),1,0)) | H33: =IF(AND(TRIM(A33)=Setup!$B$4,LOWER(D33)="mapped",TRIM(C33)<>""),IF(SUMPRODUCT((TRIM($A$5:A33)=Setup!$B$4)*(LOWER($D$5:D33)="mapped")*(TRIM($C$5:C33)=TRIM(C33)))=1,ROW(),""),"")
F34: =IF(B34="","",TRIM(A34)&"||"&TRIM(B34)) | G34: =IF(B34="","",IF(OR(AND(LOWER(D34)="mapped",TRIM(C34)<>""),AND(LOWER(D34)="ignored",TRIM(E34)<>"")),1,0)) | H34: =IF(AND(TRIM(A34)=Setup!$B$4,LOWER(D34)="mapped",TRIM(C34)<>""),IF(SUMPRODUCT((TRIM($A$5:A34)=Setup!$B$4)*(LOWER($D$5:D34)="mapped")*(TRIM($C$5:C34)=TRIM(C34)))=1,ROW(),""),"")
F35: =IF(B35="","",TRIM(A35)&"||"&TRIM(B35)) | G35: =IF(B35="","",IF(OR(AND(LOWER(D35)="mapped",TRIM(C35)<>""),AND(LOWER(D35)="ignored",TRIM(E35)<>"")),1,0)) | H35: =IF(AND(TRIM(A35)=Setup!$B$4,LOWER(D35)="mapped",TRIM(C35)<>""),IF(SUMPRODUCT((TRIM($A$5:A35)=Setup!$B$4)*(LOWER($D$5:D35)="mapped")*(TRIM($C$5:C35)=TRIM(C35)))=1,ROW(),""),"")
F36: =IF(B36="","",TRIM(A36)&"||"&TRIM(B36)) | G36: =IF(B36="","",IF(OR(AND(LOWER(D36)="mapped",TRIM(C36)<>""),AND(LOWER(D36)="ignored",TRIM(E36)<>"")),1,0)) | H36: =IF(AND(TRIM(A36)=Setup!$B$4,LOWER(D36)="mapped",TRIM(C36)<>""),IF(SUMPRODUCT((TRIM($A$5:A36)=Setup!$B$4)*(LOWER($D$5:D36)="mapped")*(TRIM($C$5:C36)=TRIM(C36)))=1,ROW(),""),"")
... F504: =IF(B504="","",TRIM(A504)&"||"&TRIM(B504)) | G504: =IF(B504="","",IF(OR(AND(LOWER(D504)="mapped",TRIM(C504)<>""),AND(LOWER(D504)="ignored",TRIM(E504)<>"")),1,0)) | H504: =IF(AND(TRIM(A504)=Setup!$B$4,LOWER(D504)="mapped",TRIM(C504)<>""),IF(SUMPRODUCT((TRIM($A$5:A504)=Setup!$B$4)*(LOWER($D$5:D504)="mapped")*(TRIM($C$5:C504)=TRIM(C504)))=1,ROW(),""),"")

Sheet Reconcile
A1: Reconcile (reconcile-source / connector-validate). Paste Account in A and Amount in B from row 12.
A3: row_count | B3: =SUMPRODUCT((C12:C1511<>"")*1)
A4: source_total | B4: =SUM(G12:G1511)
A5: mapped_total | B5: =SUMIF(K12:K1511,"mapped",G12:G1511)
A6: duplicates (count of distinct accounts) | B6: =COUNT(O12:O1511)
A7: unmapped (distinct) | B7: =COUNT(N12:N1511)
A8: unparseable amounts | B8: =COUNTIF(H12:H1511,0)
A9: PASSED | B9: =IF(AND(B6=0,OR(B7=0,LOWER(Setup!$B$9)="yes"),B8=0,Results!B3),"PASS","FAIL")
A11: account (raw) | B11: amount (raw) | C11: account | D11: cleaned | E11: Dr/Cr | F11: paren? | G11: amount (parsed) | H11: parse ok? | I11: duplicate? | J11: rule row | K11: status | L11: target | M11: first-occurrence (helper) | N11: unmapped list (helper) | O11: dup list (helper) | P11: ignored list (helper)
A12: Sales - Domestic (TN) @18% | B12: 21,84,00,000.00 Cr | C12: =TRIM(A12&"") | D12: =IF(C12="","",SUBSTITUTE(SUBSTITUTE(SUBSTITUTE(SUBSTITUTE(SUBSTITUTE(SUBSTITUTE(SUBSTITUTE(UPPER(TRIM(B12&"")),"₹",""),"RS.",""),"RS",""),"INR",""),"$",""),",","")," ","")) | E12: =IF(C12="","",IF(RIGHT(D12,2)="CR","Cr",IF(RIGHT(D12,2)="DR","Dr",""))) | F12: =IF(C12="","",IF(E12<>"",LEFT(D12,LEN(D12)-2),D12)) | G12: =IF(C12="","",IF(OR(IF(AND(LEFT(F12,1)="(",RIGHT(F12,1)=")"),MID(F12,2,LEN(F12)-2),F12)="",IF(AND(LEFT(F12,1)="(",RIGHT(F12,1)=")"),MID(F12,2,LEN(F12)-2),F12)="-"),0,IFERROR(VALUE(IF(AND(LEFT(F12,1)="(",RIGHT(F12,1)=")"),MID(F12,2,LEN(F12)-2),F12))*IF(AND(LEFT(F12,1)="(",RIGHT(F12,1)=")"),-1,1)*IF(E12="Cr",Setup!$B$6,1),"ERR"))) | H12: =IF(C12="","",IF(ISNUMBER(G12),1,0)) | I12: =IF(C12="","",IF(SUMPRODUCT(($C$12:$C$1511=C12)*1)>1,1,0)) | J12: =IF(C12="","",SUMPRODUCT((Mapping!$F$5:$F$504=Setup!$B$4&"||"&C12)*ROW(Mapping!$F$5:$F$504))) | K12: =IF(C12="","",IF(J12=0,"UNMAPPED",LOWER(INDEX(Mapping!$D$1:$D$504,J12)))) | L12: =IF(K12="mapped",TRIM(INDEX(Mapping!$C$1:$C$504,J12)),"") | M12: =IF(C12="","",IF(SUMPRODUCT(($C$12:C12=C12)*1)=1,1,0)) | N12: =IF(AND(K12="UNMAPPED",M12=1),ROW(),"") | O12: =IF(AND(I12=1,M12=1),ROW(),"") | P12: =IF(AND(K12="ignored",M12=1),ROW(),"")
A13: Sales - Interstate (Kerala/Karnataka) @18% | B13: 4,68,00,000.00 Cr | C13: =TRIM(A13&"") | D13: =IF(C13="","",SUBSTITUTE(SUBSTITUTE(SUBSTITUTE(SUBSTITUTE(SUBSTITUTE(SUBSTITUTE(SUBSTITUTE(UPPER(TRIM(B13&"")),"₹",""),"RS.",""),"RS",""),"INR",""),"$",""),",","")," ","")) | E13: =IF(C13="","",IF(RIGHT(D13,2)="CR","Cr",IF(RIGHT(D13,2)="DR","Dr",""))) | F13: =IF(C13="","",IF(E13<>"",LEFT(D13,LEN(D13)-2),D13)) | G13: =IF(C13="","",IF(OR(IF(AND(LEFT(F13,1)="(",RIGHT(F13,1)=")"),MID(F13,2,LEN(F13)-2),F13)="",IF(AND(LEFT(F13,1)="(",RIGHT(F13,1)=")"),MID(F13,2,LEN(F13)-2),F13)="-"),0,IFERROR(VALUE(IF(AND(LEFT(F13,1)="(",RIGHT(F13,1)=")"),MID(F13,2,LEN(F13)-2),F13))*IF(AND(LEFT(F13,1)="(",RIGHT(F13,1)=")"),-1,1)*IF(E13="Cr",Setup!$B$6,1),"ERR"))) | H13: =IF(C13="","",IF(ISNUMBER(G13),1,0)) | I13: =IF(C13="","",IF(SUMPRODUCT(($C$12:$C$1511=C13)*1)>1,1,0)) | J13: =IF(C13="","",SUMPRODUCT((Mapping!$F$5:$F$504=Setup!$B$4&"||"&C13)*ROW(Mapping!$F$5:$F$504))) | K13: =IF(C13="","",IF(J13=0,"UNMAPPED",LOWER(INDEX(Mapping!$D$1:$D$504,J13)))) | L13: =IF(K13="mapped",TRIM(INDEX(Mapping!$C$1:$C$504,J13)),"") | M13: =IF(C13="","",IF(SUMPRODUCT(($C$12:C13=C13)*1)=1,1,0)) | N13: =IF(AND(K13="UNMAPPED",M13=1),ROW(),"") | O13: =IF(AND(I13=1,M13=1),ROW(),"") | P13: =IF(AND(K13="ignored",M13=1),ROW(),"")
A14: Sales - Marketplace (Amazon/Flipkart) | B14: 3,27,00,000.00 Cr | C14: =TRIM(A14&"") | D14: =IF(C14="","",SUBSTITUTE(SUBSTITUTE(SUBSTITUTE(SUBSTITUTE(SUBSTITUTE(SUBSTITUTE(SUBSTITUTE(UPPER(TRIM(B14&"")),"₹",""),"RS.",""),"RS",""),"INR",""),"$",""),",","")," ","")) | E14: =IF(C14="","",IF(RIGHT(D14,2)="CR","Cr",IF(RIGHT(D14,2)="DR","Dr",""))) | F14: =IF(C14="","",IF(E14<>"",LEFT(D14,LEN(D14)-2),D14)) | G14: =IF(C14="","",IF(OR(IF(AND(LEFT(F14,1)="(",RIGHT(F14,1)=")"),MID(F14,2,LEN(F14)-2),F14)="",IF(AND(LEFT(F14,1)="(",RIGHT(F14,1)=")"),MID(F14,2,LEN(F14)-2),F14)="-"),0,IFERROR(VALUE(IF(AND(LEFT(F14,1)="(",RIGHT(F14,1)=")"),MID(F14,2,LEN(F14)-2),F14))*IF(AND(LEFT(F14,1)="(",RIGHT(F14,1)=")"),-1,1)*IF(E14="Cr",Setup!$B$6,1),"ERR"))) | H14: =IF(C14="","",IF(ISNUMBER(G14),1,0)) | I14: =IF(C14="","",IF(SUMPRODUCT(($C$12:$C$1511=C14)*1)>1,1,0)) | J14: =IF(C14="","",SUMPRODUCT((Mapping!$F$5:$F$504=Setup!$B$4&"||"&C14)*ROW(Mapping!$F$5:$F$504))) | K14: =IF(C14="","",IF(J14=0,"UNMAPPED",LOWER(INDEX(Mapping!$D$1:$D$504,J14)))) | L14: =IF(K14="mapped",TRIM(INDEX(Mapping!$C$1:$C$504,J14)),"") | M14: =IF(C14="","",IF(SUMPRODUCT(($C$12:C14=C14)*1)=1,1,0)) | N14: =IF(AND(K14="UNMAPPED",M14=1),ROW(),"") | O14: =IF(AND(I14=1,M14=1),ROW(),"") | P14: =IF(AND(K14="ignored",M14=1),ROW(),"")
A15: Sales Returns & Dealer Schemes | B15: 41,00,000.00 Dr | C15: =TRIM(A15&"") | D15: =IF(C15="","",SUBSTITUTE(SUBSTITUTE(SUBSTITUTE(SUBSTITUTE(SUBSTITUTE(SUBSTITUTE(SUBSTITUTE(UPPER(TRIM(B15&"")),"₹",""),"RS.",""),"RS",""),"INR",""),"$",""),",","")," ","")) | E15: =IF(C15="","",IF(RIGHT(D15,2)="CR","Cr",IF(RIGHT(D15,2)="DR","Dr",""))) | F15: =IF(C15="","",IF(E15<>"",LEFT(D15,LEN(D15)-2),D15)) | G15: =IF(C15="","",IF(OR(IF(AND(LEFT(F15,1)="(",RIGHT(F15,1)=")"),MID(F15,2,LEN(F15)-2),F15)="",IF(AND(LEFT(F15,1)="(",RIGHT(F15,1)=")"),MID(F15,2,LEN(F15)-2),F15)="-"),0,IFERROR(VALUE(IF(AND(LEFT(F15,1)="(",RIGHT(F15,1)=")"),MID(F15,2,LEN(F15)-2),F15))*IF(AND(LEFT(F15,1)="(",RIGHT(F15,1)=")"),-1,1)*IF(E15="Cr",Setup!$B$6,1),"ERR"))) | H15: =IF(C15="","",IF(ISNUMBER(G15),1,0)) | I15: =IF(C15="","",IF(SUMPRODUCT(($C$12:$C$1511=C15)*1)>1,1,0)) | J15: =IF(C15="","",SUMPRODUCT((Mapping!$F$5:$F$504=Setup!$B$4&"||"&C15)*ROW(Mapping!$F$5:$F$504))) | K15: =IF(C15="","",IF(J15=0,"UNMAPPED",LOWER(INDEX(Mapping!$D$1:$D$504,J15)))) | L15: =IF(K15="mapped",TRIM(INDEX(Mapping!$C$1:$C$504,J15)),"") | M15: =IF(C15="","",IF(SUMPRODUCT(($C$12:C15=C15)*1)=1,1,0)) | N15: =IF(AND(K15="UNMAPPED",M15=1),ROW(),"") | O15: =IF(AND(I15=1,M15=1),ROW(),"") | P15: =IF(AND(K15="ignored",M15=1),ROW(),"")
A16: Purchase - Rubberwood & Teak | B16: 9,12,00,000.00 Dr | C16: =TRIM(A16&"") | D16: =IF(C16="","",SUBSTITUTE(SUBSTITUTE(SUBSTITUTE(SUBSTITUTE(SUBSTITUTE(SUBSTITUTE(SUBSTITUTE(UPPER(TRIM(B16&"")),"₹",""),"RS.",""),"RS",""),"INR",""),"$",""),",","")," ","")) | E16: =IF(C16="","",IF(RIGHT(D16,2)="CR","Cr",IF(RIGHT(D16,2)="DR","Dr",""))) | F16: =IF(C16="","",IF(E16<>"",LEFT(D16,LEN(D16)-2),D16)) | G16: =IF(C16="","",IF(OR(IF(AND(LEFT(F16,1)="(",RIGHT(F16,1)=")"),MID(F16,2,LEN(F16)-2),F16)="",IF(AND(LEFT(F16,1)="(",RIGHT(F16,1)=")"),MID(F16,2,LEN(F16)-2),F16)="-"),0,IFERROR(VALUE(IF(AND(LEFT(F16,1)="(",RIGHT(F16,1)=")"),MID(F16,2,LEN(F16)-2),F16))*IF(AND(LEFT(F16,1)="(",RIGHT(F16,1)=")"),-1,1)*IF(E16="Cr",Setup!$B$6,1),"ERR"))) | H16: =IF(C16="","",IF(ISNUMBER(G16),1,0)) | I16: =IF(C16="","",IF(SUMPRODUCT(($C$12:$C$1511=C16)*1)>1,1,0)) | J16: =IF(C16="","",SUMPRODUCT((Mapping!$F$5:$F$504=Setup!$B$4&"||"&C16)*ROW(Mapping!$F$5:$F$504))) | K16: =IF(C16="","",IF(J16=0,"UNMAPPED",LOWER(INDEX(Mapping!$D$1:$D$504,J16)))) | L16: =IF(K16="mapped",TRIM(INDEX(Mapping!$C$1:$C$504,J16)),"") | M16: =IF(C16="","",IF(SUMPRODUCT(($C$12:C16=C16)*1)=1,1,0)) | N16: =IF(AND(K16="UNMAPPED",M16=1),ROW(),"") | O16: =IF(AND(I16=1,M16=1),ROW(),"") | P16: =IF(AND(K16="ignored",M16=1),ROW(),"")
A17: Purchase - Steel & Mechanisms (incl. import) | B17: 6,05,00,000.00 Dr | C17: =TRIM(A17&"") | D17: =IF(C17="","",SUBSTITUTE(SUBSTITUTE(SUBSTITUTE(SUBSTITUTE(SUBSTITUTE(SUBSTITUTE(SUBSTITUTE(UPPER(TRIM(B17&"")),"₹",""),"RS.",""),"RS",""),"INR",""),"$",""),",","")," ","")) | E17: =IF(C17="","",IF(RIGHT(D17,2)="CR","Cr",IF(RIGHT(D17,2)="DR","Dr",""))) | F17: =IF(C17="","",IF(E17<>"",LEFT(D17,LEN(D17)-2),D17)) | G17: =IF(C17="","",IF(OR(IF(AND(LEFT(F17,1)="(",RIGHT(F17,1)=")"),MID(F17,2,LEN(F17)-2),F17)="",IF(AND(LEFT(F17,1)="(",RIGHT(F17,1)=")"),MID(F17,2,LEN(F17)-2),F17)="-"),0,IFERROR(VALUE(IF(AND(LEFT(F17,1)="(",RIGHT(F17,1)=")"),MID(F17,2,LEN(F17)-2),F17))*IF(AND(LEFT(F17,1)="(",RIGHT(F17,1)=")"),-1,1)*IF(E17="Cr",Setup!$B$6,1),"ERR"))) | H17: =IF(C17="","",IF(ISNUMBER(G17),1,0)) | I17: =IF(C17="","",IF(SUMPRODUCT(($C$12:$C$1511=C17)*1)>1,1,0)) | J17: =IF(C17="","",SUMPRODUCT((Mapping!$F$5:$F$504=Setup!$B$4&"||"&C17)*ROW(Mapping!$F$5:$F$504))) | K17: =IF(C17="","",IF(J17=0,"UNMAPPED",LOWER(INDEX(Mapping!$D$1:$D$504,J17)))) | L17: =IF(K17="mapped",TRIM(INDEX(Mapping!$C$1:$C$504,J17)),"") | M17: =IF(C17="","",IF(SUMPRODUCT(($C$12:C17=C17)*1)=1,1,0)) | N17: =IF(AND(K17="UNMAPPED",M17=1),ROW(),"") | O17: =IF(AND(I17=1,M17=1),ROW(),"") | P17: =IF(AND(K17="ignored",M17=1),ROW(),"")
A18: Factory Wages & Job Work | B18: 1,38,00,000.00 Dr | C18: =TRIM(A18&"") | D18: =IF(C18="","",SUBSTITUTE(SUBSTITUTE(SUBSTITUTE(SUBSTITUTE(SUBSTITUTE(SUBSTITUTE(SUBSTITUTE(UPPER(TRIM(B18&"")),"₹",""),"RS.",""),"RS",""),"INR",""),"$",""),",","")," ","")) | E18: =IF(C18="","",IF(RIGHT(D18,2)="CR","Cr",IF(RIGHT(D18,2)="DR","Dr",""))) | F18: =IF(C18="","",IF(E18<>"",LEFT(D18,LEN(D18)-2),D18)) | G18: =IF(C18="","",IF(OR(IF(AND(LEFT(F18,1)="(",RIGHT(F18,1)=")"),MID(F18,2,LEN(F18)-2),F18)="",IF(AND(LEFT(F18,1)="(",RIGHT(F18,1)=")"),MID(F18,2,LEN(F18)-2),F18)="-"),0,IFERROR(VALUE(IF(AND(LEFT(F18,1)="(",RIGHT(F18,1)=")"),MID(F18,2,LEN(F18)-2),F18))*IF(AND(LEFT(F18,1)="(",RIGHT(F18,1)=")"),-1,1)*IF(E18="Cr",Setup!$B$6,1),"ERR"))) | H18: =IF(C18="","",IF(ISNUMBER(G18),1,0)) | I18: =IF(C18="","",IF(SUMPRODUCT(($C$12:$C$1511=C18)*1)>1,1,0)) | J18: =IF(C18="","",SUMPRODUCT((Mapping!$F$5:$F$504=Setup!$B$4&"||"&C18)*ROW(Mapping!$F$5:$F$504))) | K18: =IF(C18="","",IF(J18=0,"UNMAPPED",LOWER(INDEX(Mapping!$D$1:$D$504,J18)))) | L18: =IF(K18="mapped",TRIM(INDEX(Mapping!$C$1:$C$504,J18)),"") | M18: =IF(C18="","",IF(SUMPRODUCT(($C$12:C18=C18)*1)=1,1,0)) | N18: =IF(AND(K18="UNMAPPED",M18=1),ROW(),"") | O18: =IF(AND(I18=1,M18=1),ROW(),"") | P18: =IF(AND(K18="ignored",M18=1),ROW(),"")
A19: Marketplace Commission & Fees | B19: 52,00,000.00 Dr | C19: =TRIM(A19&"") | D19: =IF(C19="","",SUBSTITUTE(SUBSTITUTE(SUBSTITUTE(SUBSTITUTE(SUBSTITUTE(SUBSTITUTE(SUBSTITUTE(UPPER(TRIM(B19&"")),"₹",""),"RS.",""),"RS",""),"INR",""),"$",""),",","")," ","")) | E19: =IF(C19="","",IF(RIGHT(D19,2)="CR","Cr",IF(RIGHT(D19,2)="DR","Dr",""))) | F19: =IF(C19="","",IF(E19<>"",LEFT(D19,LEN(D19)-2),D19)) | G19: =IF(C19="","",IF(OR(IF(AND(LEFT(F19,1)="(",RIGHT(F19,1)=")"),MID(F19,2,LEN(F19)-2),F19)="",IF(AND(LEFT(F19,1)="(",RIGHT(F19,1)=")"),MID(F19,2,LEN(F19)-2),F19)="-"),0,IFERROR(VALUE(IF(AND(LEFT(F19,1)="(",RIGHT(F19,1)=")"),MID(F19,2,LEN(F19)-2),F19))*IF(AND(LEFT(F19,1)="(",RIGHT(F19,1)=")"),-1,1)*IF(E19="Cr",Setup!$B$6,1),"ERR"))) | H19: =IF(C19="","",IF(ISNUMBER(G19),1,0)) | I19: =IF(C19="","",IF(SUMPRODUCT(($C$12:$C$1511=C19)*1)>1,1,0)) | J19: =IF(C19="","",SUMPRODUCT((Mapping!$F$5:$F$504=Setup!$B$4&"||"&C19)*ROW(Mapping!$F$5:$F$504))) | K19: =IF(C19="","",IF(J19=0,"UNMAPPED",LOWER(INDEX(Mapping!$D$1:$D$504,J19)))) | L19: =IF(K19="mapped",TRIM(INDEX(Mapping!$C$1:$C$504,J19)),"") | M19: =IF(C19="","",IF(SUMPRODUCT(($C$12:C19=C19)*1)=1,1,0)) | N19: =IF(AND(K19="UNMAPPED",M19=1),ROW(),"") | O19: =IF(AND(I19=1,M19=1),ROW(),"") | P19: =IF(AND(K19="ignored",M19=1),ROW(),"")
A20: Salaries & Staff Welfare (office/sales) | B20: 2,46,00,000.00 Dr | C20: =TRIM(A20&"") | D20: =IF(C20="","",SUBSTITUTE(SUBSTITUTE(SUBSTITUTE(SUBSTITUTE(SUBSTITUTE(SUBSTITUTE(SUBSTITUTE(UPPER(TRIM(B20&"")),"₹",""),"RS.",""),"RS",""),"INR",""),"$",""),",","")," ","")) | E20: =IF(C20="","",IF(RIGHT(D20,2)="CR","Cr",IF(RIGHT(D20,2)="DR","Dr",""))) | F20: =IF(C20="","",IF(E20<>"",LEFT(D20,LEN(D20)-2),D20)) | G20: =IF(C20="","",IF(OR(IF(AND(LEFT(F20,1)="(",RIGHT(F20,1)=")"),MID(F20,2,LEN(F20)-2),F20)="",IF(AND(LEFT(F20,1)="(",RIGHT(F20,1)=")"),MID(F20,2,LEN(F20)-2),F20)="-"),0,IFERROR(VALUE(IF(AND(LEFT(F20,1)="(",RIGHT(F20,1)=")"),MID(F20,2,LEN(F20)-2),F20))*IF(AND(LEFT(F20,1)="(",RIGHT(F20,1)=")"),-1,1)*IF(E20="Cr",Setup!$B$6,1),"ERR"))) | H20: =IF(C20="","",IF(ISNUMBER(G20),1,0)) | I20: =IF(C20="","",IF(SUMPRODUCT(($C$12:$C$1511=C20)*1)>1,1,0)) | J20: =IF(C20="","",SUMPRODUCT((Mapping!$F$5:$F$504=Setup!$B$4&"||"&C20)*ROW(Mapping!$F$5:$F$504))) | K20: =IF(C20="","",IF(J20=0,"UNMAPPED",LOWER(INDEX(Mapping!$D$1:$D$504,J20)))) | L20: =IF(K20="mapped",TRIM(INDEX(Mapping!$C$1:$C$504,J20)),"") | M20: =IF(C20="","",IF(SUMPRODUCT(($C$12:C20=C20)*1)=1,1,0)) | N20: =IF(AND(K20="UNMAPPED",M20=1),ROW(),"") | O20: =IF(AND(I20=1,M20=1),ROW(),"") | P20: =IF(AND(K20="ignored",M20=1),ROW(),"")
A21: PF & ESI - Employer | B21: 38,40,000.00 Dr | C21: =TRIM(A21&"") | D21: =IF(C21="","",SUBSTITUTE(SUBSTITUTE(SUBSTITUTE(SUBSTITUTE(SUBSTITUTE(SUBSTITUTE(SUBSTITUTE(UPPER(TRIM(B21&"")),"₹",""),"RS.",""),"RS",""),"INR",""),"$",""),",","")," ","")) | E21: =IF(C21="","",IF(RIGHT(D21,2)="CR","Cr",IF(RIGHT(D21,2)="DR","Dr",""))) | F21: =IF(C21="","",IF(E21<>"",LEFT(D21,LEN(D21)-2),D21)) | G21: =IF(C21="","",IF(OR(IF(AND(LEFT(F21,1)="(",RIGHT(F21,1)=")"),MID(F21,2,LEN(F21)-2),F21)="",IF(AND(LEFT(F21,1)="(",RIGHT(F21,1)=")"),MID(F21,2,LEN(F21)-2),F21)="-"),0,IFERROR(VALUE(IF(AND(LEFT(F21,1)="(",RIGHT(F21,1)=")"),MID(F21,2,LEN(F21)-2),F21))*IF(AND(LEFT(F21,1)="(",RIGHT(F21,1)=")"),-1,1)*IF(E21="Cr",Setup!$B$6,1),"ERR"))) | H21: =IF(C21="","",IF(ISNUMBER(G21),1,0)) | I21: =IF(C21="","",IF(SUMPRODUCT(($C$12:$C$1511=C21)*1)>1,1,0)) | J21: =IF(C21="","",SUMPRODUCT((Mapping!$F$5:$F$504=Setup!$B$4&"||"&C21)*ROW(Mapping!$F$5:$F$504))) | K21: =IF(C21="","",IF(J21=0,"UNMAPPED",LOWER(INDEX(Mapping!$D$1:$D$504,J21)))) | L21: =IF(K21="mapped",TRIM(INDEX(Mapping!$C$1:$C$504,J21)),"") | M21: =IF(C21="","",IF(SUMPRODUCT(($C$12:C21=C21)*1)=1,1,0)) | N21: =IF(AND(K21="UNMAPPED",M21=1),ROW(),"") | O21: =IF(AND(I21=1,M21=1),ROW(),"") | P21: =IF(AND(K21="ignored",M21=1),ROW(),"")
A22: Advertisement & Dealer Meets | B22: 1,68,00,000.00 Dr | C22: =TRIM(A22&"") | D22: =IF(C22="","",SUBSTITUTE(SUBSTITUTE(SUBSTITUTE(SUBSTITUTE(SUBSTITUTE(SUBSTITUTE(SUBSTITUTE(UPPER(TRIM(B22&"")),"₹",""),"RS.",""),"RS",""),"INR",""),"$",""),",","")," ","")) | E22: =IF(C22="","",IF(RIGHT(D22,2)="CR","Cr",IF(RIGHT(D22,2)="DR","Dr",""))) | F22: =IF(C22="","",IF(E22<>"",LEFT(D22,LEN(D22)-2),D22)) | G22: =IF(C22="","",IF(OR(IF(AND(LEFT(F22,1)="(",RIGHT(F22,1)=")"),MID(F22,2,LEN(F22)-2),F22)="",IF(AND(LEFT(F22,1)="(",RIGHT(F22,1)=")"),MID(F22,2,LEN(F22)-2),F22)="-"),0,IFERROR(VALUE(IF(AND(LEFT(F22,1)="(",RIGHT(F22,1)=")"),MID(F22,2,LEN(F22)-2),F22))*IF(AND(LEFT(F22,1)="(",RIGHT(F22,1)=")"),-1,1)*IF(E22="Cr",Setup!$B$6,1),"ERR"))) | H22: =IF(C22="","",IF(ISNUMBER(G22),1,0)) | I22: =IF(C22="","",IF(SUMPRODUCT(($C$12:$C$1511=C22)*1)>1,1,0)) | J22: =IF(C22="","",SUMPRODUCT((Mapping!$F$5:$F$504=Setup!$B$4&"||"&C22)*ROW(Mapping!$F$5:$F$504))) | K22: =IF(C22="","",IF(J22=0,"UNMAPPED",LOWER(INDEX(Mapping!$D$1:$D$504,J22)))) | L22: =IF(K22="mapped",TRIM(INDEX(Mapping!$C$1:$C$504,J22)),"") | M22: =IF(C22="","",IF(SUMPRODUCT(($C$12:C22=C22)*1)=1,1,0)) | N22: =IF(AND(K22="UNMAPPED",M22=1),ROW(),"") | O22: =IF(AND(I22=1,M22=1),ROW(),"") | P22: =IF(AND(K22="ignored",M22=1),ROW(),"")
A23: Freight Outward | B23: 1,09,00,000.00 Dr | C23: =TRIM(A23&"") | D23: =IF(C23="","",SUBSTITUTE(SUBSTITUTE(SUBSTITUTE(SUBSTITUTE(SUBSTITUTE(SUBSTITUTE(SUBSTITUTE(UPPER(TRIM(B23&"")),"₹",""),"RS.",""),"RS",""),"INR",""),"$",""),",","")," ","")) | E23: =IF(C23="","",IF(RIGHT(D23,2)="CR","Cr",IF(RIGHT(D23,2)="DR","Dr",""))) | F23: =IF(C23="","",IF(E23<>"",LEFT(D23,LEN(D23)-2),D23)) | G23: =IF(C23="","",IF(OR(IF(AND(LEFT(F23,1)="(",RIGHT(F23,1)=")"),MID(F23,2,LEN(F23)-2),F23)="",IF(AND(LEFT(F23,1)="(",RIGHT(F23,1)=")"),MID(F23,2,LEN(F23)-2),F23)="-"),0,IFERROR(VALUE(IF(AND(LEFT(F23,1)="(",RIGHT(F23,1)=")"),MID(F23,2,LEN(F23)-2),F23))*IF(AND(LEFT(F23,1)="(",RIGHT(F23,1)=")"),-1,1)*IF(E23="Cr",Setup!$B$6,1),"ERR"))) | H23: =IF(C23="","",IF(ISNUMBER(G23),1,0)) | I23: =IF(C23="","",IF(SUMPRODUCT(($C$12:$C$1511=C23)*1)>1,1,0)) | J23: =IF(C23="","",SUMPRODUCT((Mapping!$F$5:$F$504=Setup!$B$4&"||"&C23)*ROW(Mapping!$F$5:$F$504))) | K23: =IF(C23="","",IF(J23=0,"UNMAPPED",LOWER(INDEX(Mapping!$D$1:$D$504,J23)))) | L23: =IF(K23="mapped",TRIM(INDEX(Mapping!$C$1:$C$504,J23)),"") | M23: =IF(C23="","",IF(SUMPRODUCT(($C$12:C23=C23)*1)=1,1,0)) | N23: =IF(AND(K23="UNMAPPED",M23=1),ROW(),"") | O23: =IF(AND(I23=1,M23=1),ROW(),"") | P23: =IF(AND(K23="ignored",M23=1),ROW(),"")
... A31: Output SGST | B31: 2,36,00,000.00 Cr | C31: =TRIM(A31&"") | D31: =IF(C31="","",SUBSTITUTE(SUBSTITUTE(SUBSTITUTE(SUBSTITUTE(SUBSTITUTE(SUBSTITUTE(SUBSTITUTE(UPPER(TRIM(B31&"")),"₹",""),"RS.",""),"RS",""),"INR",""),"$",""),",","")," ","")) | E31: =IF(C31="","",IF(RIGHT(D31,2)="CR","Cr",IF(RIGHT(D31,2)="DR","Dr",""))) | F31: =IF(C31="","",IF(E31<>"",LEFT(D31,LEN(D31)-2),D31)) | G31: =IF(C31="","",IF(OR(IF(AND(LEFT(F31,1)="(",RIGHT(F31,1)=")"),MID(F31,2,LEN(F31)-2),F31)="",IF(AND(LEFT(F31,1)="(",RIGHT(F31,1)=")"),MID(F31,2,LEN(F31)-2),F31)="-"),0,IFERROR(VALUE(IF(AND(LEFT(F31,1)="(",RIGHT(F31,1)=")"),MID(F31,2,LEN(F31)-2),F31))*IF(AND(LEFT(F31,1)="(",RIGHT(F31,1)=")"),-1,1)*IF(E31="Cr",Setup!$B$6,1),"ERR"))) | H31: =IF(C31="","",IF(ISNUMBER(G31),1,0)) | I31: =IF(C31="","",IF(SUMPRODUCT(($C$12:$C$1511=C31)*1)>1,1,0)) | J31: =IF(C31="","",SUMPRODUCT((Mapping!$F$5:$F$504=Setup!$B$4&"||"&C31)*ROW(Mapping!$F$5:$F$504))) | K31: =IF(C31="","",IF(J31=0,"UNMAPPED",LOWER(INDEX(Mapping!$D$1:$D$504,J31)))) | L31: =IF(K31="mapped",TRIM(INDEX(Mapping!$C$1:$C$504,J31)),"") | M31: =IF(C31="","",IF(SUMPRODUCT(($C$12:C31=C31)*1)=1,1,0)) | N31: =IF(AND(K31="UNMAPPED",M31=1),ROW(),"") | O31: =IF(AND(I31=1,M31=1),ROW(),"") | P31: =IF(AND(K31="ignored",M31=1),ROW(),"")
C32: =TRIM(A32&"") | D32: =IF(C32="","",SUBSTITUTE(SUBSTITUTE(SUBSTITUTE(SUBSTITUTE(SUBSTITUTE(SUBSTITUTE(SUBSTITUTE(UPPER(TRIM(B32&"")),"₹",""),"RS.",""),"RS",""),"INR",""),"$",""),",","")," ","")) | E32: =IF(C32="","",IF(RIGHT(D32,2)="CR","Cr",IF(RIGHT(D32,2)="DR","Dr",""))) | F32: =IF(C32="","",IF(E32<>"",LEFT(D32,LEN(D32)-2),D32)) | G32: =IF(C32="","",IF(OR(IF(AND(LEFT(F32,1)="(",RIGHT(F32,1)=")"),MID(F32,2,LEN(F32)-2),F32)="",IF(AND(LEFT(F32,1)="(",RIGHT(F32,1)=")"),MID(F32,2,LEN(F32)-2),F32)="-"),0,IFERROR(VALUE(IF(AND(LEFT(F32,1)="(",RIGHT(F32,1)=")"),MID(F32,2,LEN(F32)-2),F32))*IF(AND(LEFT(F32,1)="(",RIGHT(F32,1)=")"),-1,1)*IF(E32="Cr",Setup!$B$6,1),"ERR"))) | H32: =IF(C32="","",IF(ISNUMBER(G32),1,0)) | I32: =IF(C32="","",IF(SUMPRODUCT(($C$12:$C$1511=C32)*1)>1,1,0)) | J32: =IF(C32="","",SUMPRODUCT((Mapping!$F$5:$F$504=Setup!$B$4&"||"&C32)*ROW(Mapping!$F$5:$F$504))) | K32: =IF(C32="","",IF(J32=0,"UNMAPPED",LOWER(INDEX(Mapping!$D$1:$D$504,J32)))) | L32: =IF(K32="mapped",TRIM(INDEX(Mapping!$C$1:$C$504,J32)),"") | M32: =IF(C32="","",IF(SUMPRODUCT(($C$12:C32=C32)*1)=1,1,0)) | N32: =IF(AND(K32="UNMAPPED",M32=1),ROW(),"") | O32: =IF(AND(I32=1,M32=1),ROW(),"") | P32: =IF(AND(K32="ignored",M32=1),ROW(),"")
C33: =TRIM(A33&"") | D33: =IF(C33="","",SUBSTITUTE(SUBSTITUTE(SUBSTITUTE(SUBSTITUTE(SUBSTITUTE(SUBSTITUTE(SUBSTITUTE(UPPER(TRIM(B33&"")),"₹",""),"RS.",""),"RS",""),"INR",""),"$",""),",","")," ","")) | E33: =IF(C33="","",IF(RIGHT(D33,2)="CR","Cr",IF(RIGHT(D33,2)="DR","Dr",""))) | F33: =IF(C33="","",IF(E33<>"",LEFT(D33,LEN(D33)-2),D33)) | G33: =IF(C33="","",IF(OR(IF(AND(LEFT(F33,1)="(",RIGHT(F33,1)=")"),MID(F33,2,LEN(F33)-2),F33)="",IF(AND(LEFT(F33,1)="(",RIGHT(F33,1)=")"),MID(F33,2,LEN(F33)-2),F33)="-"),0,IFERROR(VALUE(IF(AND(LEFT(F33,1)="(",RIGHT(F33,1)=")"),MID(F33,2,LEN(F33)-2),F33))*IF(AND(LEFT(F33,1)="(",RIGHT(F33,1)=")"),-1,1)*IF(E33="Cr",Setup!$B$6,1),"ERR"))) | H33: =IF(C33="","",IF(ISNUMBER(G33),1,0)) | I33: =IF(C33="","",IF(SUMPRODUCT(($C$12:$C$1511=C33)*1)>1,1,0)) | J33: =IF(C33="","",SUMPRODUCT((Mapping!$F$5:$F$504=Setup!$B$4&"||"&C33)*ROW(Mapping!$F$5:$F$504))) | K33: =IF(C33="","",IF(J33=0,"UNMAPPED",LOWER(INDEX(Mapping!$D$1:$D$504,J33)))) | L33: =IF(K33="mapped",TRIM(INDEX(Mapping!$C$1:$C$504,J33)),"") | M33: =IF(C33="","",IF(SUMPRODUCT(($C$12:C33=C33)*1)=1,1,0)) | N33: =IF(AND(K33="UNMAPPED",M33=1),ROW(),"") | O33: =IF(AND(I33=1,M33=1),ROW(),"") | P33: =IF(AND(K33="ignored",M33=1),ROW(),"")
C34: =TRIM(A34&"") | D34: =IF(C34="","",SUBSTITUTE(SUBSTITUTE(SUBSTITUTE(SUBSTITUTE(SUBSTITUTE(SUBSTITUTE(SUBSTITUTE(UPPER(TRIM(B34&"")),"₹",""),"RS.",""),"RS",""),"INR",""),"$",""),",","")," ","")) | E34: =IF(C34="","",IF(RIGHT(D34,2)="CR","Cr",IF(RIGHT(D34,2)="DR","Dr",""))) | F34: =IF(C34="","",IF(E34<>"",LEFT(D34,LEN(D34)-2),D34)) | G34: =IF(C34="","",IF(OR(IF(AND(LEFT(F34,1)="(",RIGHT(F34,1)=")"),MID(F34,2,LEN(F34)-2),F34)="",IF(AND(LEFT(F34,1)="(",RIGHT(F34,1)=")"),MID(F34,2,LEN(F34)-2),F34)="-"),0,IFERROR(VALUE(IF(AND(LEFT(F34,1)="(",RIGHT(F34,1)=")"),MID(F34,2,LEN(F34)-2),F34))*IF(AND(LEFT(F34,1)="(",RIGHT(F34,1)=")"),-1,1)*IF(E34="Cr",Setup!$B$6,1),"ERR"))) | H34: =IF(C34="","",IF(ISNUMBER(G34),1,0)) | I34: =IF(C34="","",IF(SUMPRODUCT(($C$12:$C$1511=C34)*1)>1,1,0)) | J34: =IF(C34="","",SUMPRODUCT((Mapping!$F$5:$F$504=Setup!$B$4&"||"&C34)*ROW(Mapping!$F$5:$F$504))) | K34: =IF(C34="","",IF(J34=0,"UNMAPPED",LOWER(INDEX(Mapping!$D$1:$D$504,J34)))) | L34: =IF(K34="mapped",TRIM(INDEX(Mapping!$C$1:$C$504,J34)),"") | M34: =IF(C34="","",IF(SUMPRODUCT(($C$12:C34=C34)*1)=1,1,0)) | N34: =IF(AND(K34="UNMAPPED",M34=1),ROW(),"") | O34: =IF(AND(I34=1,M34=1),ROW(),"") | P34: =IF(AND(K34="ignored",M34=1),ROW(),"")
C35: =TRIM(A35&"") | D35: =IF(C35="","",SUBSTITUTE(SUBSTITUTE(SUBSTITUTE(SUBSTITUTE(SUBSTITUTE(SUBSTITUTE(SUBSTITUTE(UPPER(TRIM(B35&"")),"₹",""),"RS.",""),"RS",""),"INR",""),"$",""),",","")," ","")) | E35: =IF(C35="","",IF(RIGHT(D35,2)="CR","Cr",IF(RIGHT(D35,2)="DR","Dr",""))) | F35: =IF(C35="","",IF(E35<>"",LEFT(D35,LEN(D35)-2),D35)) | G35: =IF(C35="","",IF(OR(IF(AND(LEFT(F35,1)="(",RIGHT(F35,1)=")"),MID(F35,2,LEN(F35)-2),F35)="",IF(AND(LEFT(F35,1)="(",RIGHT(F35,1)=")"),MID(F35,2,LEN(F35)-2),F35)="-"),0,IFERROR(VALUE(IF(AND(LEFT(F35,1)="(",RIGHT(F35,1)=")"),MID(F35,2,LEN(F35)-2),F35))*IF(AND(LEFT(F35,1)="(",RIGHT(F35,1)=")"),-1,1)*IF(E35="Cr",Setup!$B$6,1),"ERR"))) | H35: =IF(C35="","",IF(ISNUMBER(G35),1,0)) | I35: =IF(C35="","",IF(SUMPRODUCT(($C$12:$C$1511=C35)*1)>1,1,0)) | J35: =IF(C35="","",SUMPRODUCT((Mapping!$F$5:$F$504=Setup!$B$4&"||"&C35)*ROW(Mapping!$F$5:$F$504))) | K35: =IF(C35="","",IF(J35=0,"UNMAPPED",LOWER(INDEX(Mapping!$D$1:$D$504,J35)))) | L35: =IF(K35="mapped",TRIM(INDEX(Mapping!$C$1:$C$504,J35)),"") | M35: =IF(C35="","",IF(SUMPRODUCT(($C$12:C35=C35)*1)=1,1,0)) | N35: =IF(AND(K35="UNMAPPED",M35=1),ROW(),"") | O35: =IF(AND(I35=1,M35=1),ROW(),"") | P35: =IF(AND(K35="ignored",M35=1),ROW(),"")
C36: =TRIM(A36&"") | D36: =IF(C36="","",SUBSTITUTE(SUBSTITUTE(SUBSTITUTE(SUBSTITUTE(SUBSTITUTE(SUBSTITUTE(SUBSTITUTE(UPPER(TRIM(B36&"")),"₹",""),"RS.",""),"RS",""),"INR",""),"$",""),",","")," ","")) | E36: =IF(C36="","",IF(RIGHT(D36,2)="CR","Cr",IF(RIGHT(D36,2)="DR","Dr",""))) | F36: =IF(C36="","",IF(E36<>"",LEFT(D36,LEN(D36)-2),D36)) | G36: =IF(C36="","",IF(OR(IF(AND(LEFT(F36,1)="(",RIGHT(F36,1)=")"),MID(F36,2,LEN(F36)-2),F36)="",IF(AND(LEFT(F36,1)="(",RIGHT(F36,1)=")"),MID(F36,2,LEN(F36)-2),F36)="-"),0,IFERROR(VALUE(IF(AND(LEFT(F36,1)="(",RIGHT(F36,1)=")"),MID(F36,2,LEN(F36)-2),F36))*IF(AND(LEFT(F36,1)="(",RIGHT(F36,1)=")"),-1,1)*IF(E36="Cr",Setup!$B$6,1),"ERR"))) | H36: =IF(C36="","",IF(ISNUMBER(G36),1,0)) | I36: =IF(C36="","",IF(SUMPRODUCT(($C$12:$C$1511=C36)*1)>1,1,0)) | J36: =IF(C36="","",SUMPRODUCT((Mapping!$F$5:$F$504=Setup!$B$4&"||"&C36)*ROW(Mapping!$F$5:$F$504))) | K36: =IF(C36="","",IF(J36=0,"UNMAPPED",LOWER(INDEX(Mapping!$D$1:$D$504,J36)))) | L36: =IF(K36="mapped",TRIM(INDEX(Mapping!$C$1:$C$504,J36)),"") | M36: =IF(C36="","",IF(SUMPRODUCT(($C$12:C36=C36)*1)=1,1,0)) | N36: =IF(AND(K36="UNMAPPED",M36=1),ROW(),"") | O36: =IF(AND(I36=1,M36=1),ROW(),"") | P36: =IF(AND(K36="ignored",M36=1),ROW(),"")
C37: =TRIM(A37&"") | D37: =IF(C37="","",SUBSTITUTE(SUBSTITUTE(SUBSTITUTE(SUBSTITUTE(SUBSTITUTE(SUBSTITUTE(SUBSTITUTE(UPPER(TRIM(B37&"")),"₹",""),"RS.",""),"RS",""),"INR",""),"$",""),",","")," ","")) | E37: =IF(C37="","",IF(RIGHT(D37,2)="CR","Cr",IF(RIGHT(D37,2)="DR","Dr",""))) | F37: =IF(C37="","",IF(E37<>"",LEFT(D37,LEN(D37)-2),D37)) | G37: =IF(C37="","",IF(OR(IF(AND(LEFT(F37,1)="(",RIGHT(F37,1)=")"),MID(F37,2,LEN(F37)-2),F37)="",IF(AND(LEFT(F37,1)="(",RIGHT(F37,1)=")"),MID(F37,2,LEN(F37)-2),F37)="-"),0,IFERROR(VALUE(IF(AND(LEFT(F37,1)="(",RIGHT(F37,1)=")"),MID(F37,2,LEN(F37)-2),F37))*IF(AND(LEFT(F37,1)="(",RIGHT(F37,1)=")"),-1,1)*IF(E37="Cr",Setup!$B$6,1),"ERR"))) | H37: =IF(C37="","",IF(ISNUMBER(G37),1,0)) | I37: =IF(C37="","",IF(SUMPRODUCT(($C$12:$C$1511=C37)*1)>1,1,0)) | J37: =IF(C37="","",SUMPRODUCT((Mapping!$F$5:$F$504=Setup!$B$4&"||"&C37)*ROW(Mapping!$F$5:$F$504))) | K37: =IF(C37="","",IF(J37=0,"UNMAPPED",LOWER(INDEX(Mapping!$D$1:$D$504,J37)))) | L37: =IF(K37="mapped",TRIM(INDEX(Mapping!$C$1:$C$504,J37)),"") | M37: =IF(C37="","",IF(SUMPRODUCT(($C$12:C37=C37)*1)=1,1,0)) | N37: =IF(AND(K37="UNMAPPED",M37=1),ROW(),"") | O37: =IF(AND(I37=1,M37=1),ROW(),"") | P37: =IF(AND(K37="ignored",M37=1),ROW(),"")
C38: =TRIM(A38&"") | D38: =IF(C38="","",SUBSTITUTE(SUBSTITUTE(SUBSTITUTE(SUBSTITUTE(SUBSTITUTE(SUBSTITUTE(SUBSTITUTE(UPPER(TRIM(B38&"")),"₹",""),"RS.",""),"RS",""),"INR",""),"$",""),",","")," ","")) | E38: =IF(C38="","",IF(RIGHT(D38,2)="CR","Cr",IF(RIGHT(D38,2)="DR","Dr",""))) | F38: =IF(C38="","",IF(E38<>"",LEFT(D38,LEN(D38)-2),D38)) | G38: =IF(C38="","",IF(OR(IF(AND(LEFT(F38,1)="(",RIGHT(F38,1)=")"),MID(F38,2,LEN(F38)-2),F38)="",IF(AND(LEFT(F38,1)="(",RIGHT(F38,1)=")"),MID(F38,2,LEN(F38)-2),F38)="-"),0,IFERROR(VALUE(IF(AND(LEFT(F38,1)="(",RIGHT(F38,1)=")"),MID(F38,2,LEN(F38)-2),F38))*IF(AND(LEFT(F38,1)="(",RIGHT(F38,1)=")"),-1,1)*IF(E38="Cr",Setup!$B$6,1),"ERR"))) | H38: =IF(C38="","",IF(ISNUMBER(G38),1,0)) | I38: =IF(C38="","",IF(SUMPRODUCT(($C$12:$C$1511=C38)*1)>1,1,0)) | J38: =IF(C38="","",SUMPRODUCT((Mapping!$F$5:$F$504=Setup!$B$4&"||"&C38)*ROW(Mapping!$F$5:$F$504))) | K38: =IF(C38="","",IF(J38=0,"UNMAPPED",LOWER(INDEX(Mapping!$D$1:$D$504,J38)))) | L38: =IF(K38="mapped",TRIM(INDEX(Mapping!$C$1:$C$504,J38)),"") | M38: =IF(C38="","",IF(SUMPRODUCT(($C$12:C38=C38)*1)=1,1,0)) | N38: =IF(AND(K38="UNMAPPED",M38=1),ROW(),"") | O38: =IF(AND(I38=1,M38=1),ROW(),"") | P38: =IF(AND(K38="ignored",M38=1),ROW(),"")
C39: =TRIM(A39&"") | D39: =IF(C39="","",SUBSTITUTE(SUBSTITUTE(SUBSTITUTE(SUBSTITUTE(SUBSTITUTE(SUBSTITUTE(SUBSTITUTE(UPPER(TRIM(B39&"")),"₹",""),"RS.",""),"RS",""),"INR",""),"$",""),",","")," ","")) | E39: =IF(C39="","",IF(RIGHT(D39,2)="CR","Cr",IF(RIGHT(D39,2)="DR","Dr",""))) | F39: =IF(C39="","",IF(E39<>"",LEFT(D39,LEN(D39)-2),D39)) | G39: =IF(C39="","",IF(OR(IF(AND(LEFT(F39,1)="(",RIGHT(F39,1)=")"),MID(F39,2,LEN(F39)-2),F39)="",IF(AND(LEFT(F39,1)="(",RIGHT(F39,1)=")"),MID(F39,2,LEN(F39)-2),F39)="-"),0,IFERROR(VALUE(IF(AND(LEFT(F39,1)="(",RIGHT(F39,1)=")"),MID(F39,2,LEN(F39)-2),F39))*IF(AND(LEFT(F39,1)="(",RIGHT(F39,1)=")"),-1,1)*IF(E39="Cr",Setup!$B$6,1),"ERR"))) | H39: =IF(C39="","",IF(ISNUMBER(G39),1,0)) | I39: =IF(C39="","",IF(SUMPRODUCT(($C$12:$C$1511=C39)*1)>1,1,0)) | J39: =IF(C39="","",SUMPRODUCT((Mapping!$F$5:$F$504=Setup!$B$4&"||"&C39)*ROW(Mapping!$F$5:$F$504))) | K39: =IF(C39="","",IF(J39=0,"UNMAPPED",LOWER(INDEX(Mapping!$D$1:$D$504,J39)))) | L39: =IF(K39="mapped",TRIM(INDEX(Mapping!$C$1:$C$504,J39)),"") | M39: =IF(C39="","",IF(SUMPRODUCT(($C$12:C39=C39)*1)=1,1,0)) | N39: =IF(AND(K39="UNMAPPED",M39=1),ROW(),"") | O39: =IF(AND(I39=1,M39=1),ROW(),"") | P39: =IF(AND(K39="ignored",M39=1),ROW(),"")
C40: =TRIM(A40&"") | D40: =IF(C40="","",SUBSTITUTE(SUBSTITUTE(SUBSTITUTE(SUBSTITUTE(SUBSTITUTE(SUBSTITUTE(SUBSTITUTE(UPPER(TRIM(B40&"")),"₹",""),"RS.",""),"RS",""),"INR",""),"$",""),",","")," ","")) | E40: =IF(C40="","",IF(RIGHT(D40,2)="CR","Cr",IF(RIGHT(D40,2)="DR","Dr",""))) | F40: =IF(C40="","",IF(E40<>"",LEFT(D40,LEN(D40)-2),D40)) | G40: =IF(C40="","",IF(OR(IF(AND(LEFT(F40,1)="(",RIGHT(F40,1)=")"),MID(F40,2,LEN(F40)-2),F40)="",IF(AND(LEFT(F40,1)="(",RIGHT(F40,1)=")"),MID(F40,2,LEN(F40)-2),F40)="-"),0,IFERROR(VALUE(IF(AND(LEFT(F40,1)="(",RIGHT(F40,1)=")"),MID(F40,2,LEN(F40)-2),F40))*IF(AND(LEFT(F40,1)="(",RIGHT(F40,1)=")"),-1,1)*IF(E40="Cr",Setup!$B$6,1),"ERR"))) | H40: =IF(C40="","",IF(ISNUMBER(G40),1,0)) | I40: =IF(C40="","",IF(SUMPRODUCT(($C$12:$C$1511=C40)*1)>1,1,0)) | J40: =IF(C40="","",SUMPRODUCT((Mapping!$F$5:$F$504=Setup!$B$4&"||"&C40)*ROW(Mapping!$F$5:$F$504))) | K40: =IF(C40="","",IF(J40=0,"UNMAPPED",LOWER(INDEX(Mapping!$D$1:$D$504,J40)))) | L40: =IF(K40="mapped",TRIM(INDEX(Mapping!$C$1:$C$504,J40)),"") | M40: =IF(C40="","",IF(SUMPRODUCT(($C$12:C40=C40)*1)=1,1,0)) | N40: =IF(AND(K40="UNMAPPED",M40=1),ROW(),"") | O40: =IF(AND(I40=1,M40=1),ROW(),"") | P40: =IF(AND(K40="ignored",M40=1),ROW(),"")
C41: =TRIM(A41&"") | D41: =IF(C41="","",SUBSTITUTE(SUBSTITUTE(SUBSTITUTE(SUBSTITUTE(SUBSTITUTE(SUBSTITUTE(SUBSTITUTE(UPPER(TRIM(B41&"")),"₹",""),"RS.",""),"RS",""),"INR",""),"$",""),",","")," ","")) | E41: =IF(C41="","",IF(RIGHT(D41,2)="CR","Cr",IF(RIGHT(D41,2)="DR","Dr",""))) | F41: =IF(C41="","",IF(E41<>"",LEFT(D41,LEN(D41)-2),D41)) | G41: =IF(C41="","",IF(OR(IF(AND(LEFT(F41,1)="(",RIGHT(F41,1)=")"),MID(F41,2,LEN(F41)-2),F41)="",IF(AND(LEFT(F41,1)="(",RIGHT(F41,1)=")"),MID(F41,2,LEN(F41)-2),F41)="-"),0,IFERROR(VALUE(IF(AND(LEFT(F41,1)="(",RIGHT(F41,1)=")"),MID(F41,2,LEN(F41)-2),F41))*IF(AND(LEFT(F41,1)="(",RIGHT(F41,1)=")"),-1,1)*IF(E41="Cr",Setup!$B$6,1),"ERR"))) | H41: =IF(C41="","",IF(ISNUMBER(G41),1,0)) | I41: =IF(C41="","",IF(SUMPRODUCT(($C$12:$C$1511=C41)*1)>1,1,0)) | J41: =IF(C41="","",SUMPRODUCT((Mapping!$F$5:$F$504=Setup!$B$4&"||"&C41)*ROW(Mapping!$F$5:$F$504))) | K41: =IF(C41="","",IF(J41=0,"UNMAPPED",LOWER(INDEX(Mapping!$D$1:$D$504,J41)))) | L41: =IF(K41="mapped",TRIM(INDEX(Mapping!$C$1:$C$504,J41)),"") | M41: =IF(C41="","",IF(SUMPRODUCT(($C$12:C41=C41)*1)=1,1,0)) | N41: =IF(AND(K41="UNMAPPED",M41=1),ROW(),"") | O41: =IF(AND(I41=1,M41=1),ROW(),"") | P41: =IF(AND(K41="ignored",M41=1),ROW(),"")
C42: =TRIM(A42&"") | D42: =IF(C42="","",SUBSTITUTE(SUBSTITUTE(SUBSTITUTE(SUBSTITUTE(SUBSTITUTE(SUBSTITUTE(SUBSTITUTE(UPPER(TRIM(B42&"")),"₹",""),"RS.",""),"RS",""),"INR",""),"$",""),",","")," ","")) | E42: =IF(C42="","",IF(RIGHT(D42,2)="CR","Cr",IF(RIGHT(D42,2)="DR","Dr",""))) | F42: =IF(C42="","",IF(E42<>"",LEFT(D42,LEN(D42)-2),D42)) | G42: =IF(C42="","",IF(OR(IF(AND(LEFT(F42,1)="(",RIGHT(F42,1)=")"),MID(F42,2,LEN(F42)-2),F42)="",IF(AND(LEFT(F42,1)="(",RIGHT(F42,1)=")"),MID(F42,2,LEN(F42)-2),F42)="-"),0,IFERROR(VALUE(IF(AND(LEFT(F42,1)="(",RIGHT(F42,1)=")"),MID(F42,2,LEN(F42)-2),F42))*IF(AND(LEFT(F42,1)="(",RIGHT(F42,1)=")"),-1,1)*IF(E42="Cr",Setup!$B$6,1),"ERR"))) | H42: =IF(C42="","",IF(ISNUMBER(G42),1,0)) | I42: =IF(C42="","",IF(SUMPRODUCT(($C$12:$C$1511=C42)*1)>1,1,0)) | J42: =IF(C42="","",SUMPRODUCT((Mapping!$F$5:$F$504=Setup!$B$4&"||"&C42)*ROW(Mapping!$F$5:$F$504))) | K42: =IF(C42="","",IF(J42=0,"UNMAPPED",LOWER(INDEX(Mapping!$D$1:$D$504,J42)))) | L42: =IF(K42="mapped",TRIM(INDEX(Mapping!$C$1:$C$504,J42)),"") | M42: =IF(C42="","",IF(SUMPRODUCT(($C$12:C42=C42)*1)=1,1,0)) | N42: =IF(AND(K42="UNMAPPED",M42=1),ROW(),"") | O42: =IF(AND(I42=1,M42=1),ROW(),"") | P42: =IF(AND(K42="ignored",M42=1),ROW(),"")
C43: =TRIM(A43&"") | D43: =IF(C43="","",SUBSTITUTE(SUBSTITUTE(SUBSTITUTE(SUBSTITUTE(SUBSTITUTE(SUBSTITUTE(SUBSTITUTE(UPPER(TRIM(B43&"")),"₹",""),"RS.",""),"RS",""),"INR",""),"$",""),",","")," ","")) | E43: =IF(C43="","",IF(RIGHT(D43,2)="CR","Cr",IF(RIGHT(D43,2)="DR","Dr",""))) | F43: =IF(C43="","",IF(E43<>"",LEFT(D43,LEN(D43)-2),D43)) | G43: =IF(C43="","",IF(OR(IF(AND(LEFT(F43,1)="(",RIGHT(F43,1)=")"),MID(F43,2,LEN(F43)-2),F43)="",IF(AND(LEFT(F43,1)="(",RIGHT(F43,1)=")"),MID(F43,2,LEN(F43)-2),F43)="-"),0,IFERROR(VALUE(IF(AND(LEFT(F43,1)="(",RIGHT(F43,1)=")"),MID(F43,2,LEN(F43)-2),F43))*IF(AND(LEFT(F43,1)="(",RIGHT(F43,1)=")"),-1,1)*IF(E43="Cr",Setup!$B$6,1),"ERR"))) | H43: =IF(C43="","",IF(ISNUMBER(G43),1,0)) | I43: =IF(C43="","",IF(SUMPRODUCT(($C$12:$C$1511=C43)*1)>1,1,0)) | J43: =IF(C43="","",SUMPRODUCT((Mapping!$F$5:$F$504=Setup!$B$4&"||"&C43)*ROW(Mapping!$F$5:$F$504))) | K43: =IF(C43="","",IF(J43=0,"UNMAPPED",LOWER(INDEX(Mapping!$D$1:$D$504,J43)))) | L43: =IF(K43="mapped",TRIM(INDEX(Mapping!$C$1:$C$504,J43)),"") | M43: =IF(C43="","",IF(SUMPRODUCT(($C$12:C43=C43)*1)=1,1,0)) | N43: =IF(AND(K43="UNMAPPED",M43=1),ROW(),"") | O43: =IF(AND(I43=1,M43=1),ROW(),"") | P43: =IF(AND(K43="ignored",M43=1),ROW(),"")
... C1511: =TRIM(A1511&"") | D1511: =IF(C1511="","",SUBSTITUTE(SUBSTITUTE(SUBSTITUTE(SUBSTITUTE(SUBSTITUTE(SUBSTITUTE(SUBSTITUTE(UPPER(TRIM(B1511&"")),"₹",""),"RS.",""),"RS",""),"INR",""),"$",""),",","")," ","")) | E1511: =IF(C1511="","",IF(RIGHT(D1511,2)="CR","Cr",IF(RIGHT(D1511,2)="DR","Dr",""))) | F1511: =IF(C1511="","",IF(E1511<>"",LEFT(D1511,LEN(D1511)-2),D1511)) | G1511: =IF(C1511="","",IF(OR(IF(AND(LEFT(F1511,1)="(",RIGHT(F1511,1)=")"),MID(F1511,2,LEN(F1511)-2),F1511)="",IF(AND(LEFT(F1511,1)="(",RIGHT(F1511,1)=")"),MID(F1511,2,LEN(F1511)-2),F1511)="-"),0,IFERROR(VALUE(IF(AND(LEFT(F1511,1)="(",RIGHT(F1511,1)=")"),MID(F1511,2,LEN(F1511)-2),F1511))*IF(AND(LEFT(F1511,1)="(",RIGHT(F1511,1)=")"),-1,1)*IF(E1511="Cr",Setup!$B$6,1),"ERR"))) | H1511: =IF(C1511="","",IF(ISNUMBER(G1511),1,0)) | I1511: =IF(C1511="","",IF(SUMPRODUCT(($C$12:$C$1511=C1511)*1)>1,1,0)) | J1511: =IF(C1511="","",SUMPRODUCT((Mapping!$F$5:$F$504=Setup!$B$4&"||"&C1511)*ROW(Mapping!$F$5:$F$504))) | K1511: =IF(C1511="","",IF(J1511=0,"UNMAPPED",LOWER(INDEX(Mapping!$D$1:$D$504,J1511)))) | L1511: =IF(K1511="mapped",TRIM(INDEX(Mapping!$C$1:$C$504,J1511)),"") | M1511: =IF(C1511="","",IF(SUMPRODUCT(($C$12:C1511=C1511)*1)=1,1,0)) | N1511: =IF(AND(K1511="UNMAPPED",M1511=1),ROW(),"") | O1511: =IF(AND(I1511=1,M1511=1),ROW(),"") | P1511: =IF(AND(K1511="ignored",M1511=1),ROW(),"")

Sheet Results
A1: Results: mapped totals by target, expected totals and variances; lists of problems
A3: expected totals provided and all within tolerance (TRUE when none provided) | B3: =AND(COUNTIF(I6:I105,FALSE)=0,COUNTIF(L6:L105,FALSE)=0)
A5: mapped target | B5: mapped total | D5: expected target | E5: expected | F5: mapped | G5: variance | H5: variance_pct | I5: within_tolerance | K5: mapped target missing from expected (compared to 0) | L5: within?
A6: =IFERROR(INDEX(Mapping!$C$1:$C$504,SMALL(Mapping!$H$5:$H$504,1)),"") | B6: =IF(A6="","",SUMIF(Reconcile!$L$12:$L$1511,A6,Reconcile!$G$12:$G$1511)) | D6: income_statement.revenue | E6: -293800000 | F6: =IF(D6="","",SUMIF(Reconcile!$L$12:$L$1511,D6,Reconcile!$G$12:$G$1511)) | G6: =IF(D6="","",F6-N(E6)) | H6: =IF(D6="","",IF(N(E6)=0,0,G6/E6)) | I6: =IF(D6="","",IF(N(E6)=0,F6=0,ABS(H6)<=Setup!$B$5)) | K6: =IF(OR(A6="",SUMPRODUCT(($D$6:$D$105<>"")*1)=0),"",IF(SUMPRODUCT(($D$6:$D$105=A6)*1)>0,"",A6)) | L6: =IF(K6="","",B6=0)
A7: =IFERROR(INDEX(Mapping!$C$1:$C$504,SMALL(Mapping!$H$5:$H$504,2)),"") | B7: =IF(A7="","",SUMIF(Reconcile!$L$12:$L$1511,A7,Reconcile!$G$12:$G$1511)) | D7: income_statement.cogs | E7: 170700000 | F7: =IF(D7="","",SUMIF(Reconcile!$L$12:$L$1511,D7,Reconcile!$G$12:$G$1511)) | G7: =IF(D7="","",F7-N(E7)) | H7: =IF(D7="","",IF(N(E7)=0,0,G7/E7)) | I7: =IF(D7="","",IF(N(E7)=0,F7=0,ABS(H7)<=Setup!$B$5)) | K7: =IF(OR(A7="",SUMPRODUCT(($D$6:$D$105<>"")*1)=0),"",IF(SUMPRODUCT(($D$6:$D$105=A7)*1)>0,"",A7)) | L7: =IF(K7="","",B7=0)
A8: =IFERROR(INDEX(Mapping!$C$1:$C$504,SMALL(Mapping!$H$5:$H$504,3)),"") | B8: =IF(A8="","",SUMIF(Reconcile!$L$12:$L$1511,A8,Reconcile!$G$12:$G$1511)) | D8: opex.payroll | E8: 28440000 | F8: =IF(D8="","",SUMIF(Reconcile!$L$12:$L$1511,D8,Reconcile!$G$12:$G$1511)) | G8: =IF(D8="","",F8-N(E8)) | H8: =IF(D8="","",IF(N(E8)=0,0,G8/E8)) | I8: =IF(D8="","",IF(N(E8)=0,F8=0,ABS(H8)<=Setup!$B$5)) | K8: =IF(OR(A8="",SUMPRODUCT(($D$6:$D$105<>"")*1)=0),"",IF(SUMPRODUCT(($D$6:$D$105=A8)*1)>0,"",A8)) | L8: =IF(K8="","",B8=0)
A9: =IFERROR(INDEX(Mapping!$C$1:$C$504,SMALL(Mapping!$H$5:$H$504,4)),"") | B9: =IF(A9="","",SUMIF(Reconcile!$L$12:$L$1511,A9,Reconcile!$G$12:$G$1511)) | D9: opex.marketing | E9: 16800000 | F9: =IF(D9="","",SUMIF(Reconcile!$L$12:$L$1511,D9,Reconcile!$G$12:$G$1511)) | G9: =IF(D9="","",F9-N(E9)) | H9: =IF(D9="","",IF(N(E9)=0,0,G9/E9)) | I9: =IF(D9="","",IF(N(E9)=0,F9=0,ABS(H9)<=Setup!$B$5)) | K9: =IF(OR(A9="",SUMPRODUCT(($D$6:$D$105<>"")*1)=0),"",IF(SUMPRODUCT(($D$6:$D$105=A9)*1)>0,"",A9)) | L9: =IF(K9="","",B9=0)
A10: =IFERROR(INDEX(Mapping!$C$1:$C$504,SMALL(Mapping!$H$5:$H$504,5)),"") | B10: =IF(A10="","",SUMIF(Reconcile!$L$12:$L$1511,A10,Reconcile!$G$12:$G$1511)) | D10: opex.freight | E10: 10900000 | F10: =IF(D10="","",SUMIF(Reconcile!$L$12:$L$1511,D10,Reconcile!$G$12:$G$1511)) | G10: =IF(D10="","",F10-N(E10)) | H10: =IF(D10="","",IF(N(E10)=0,0,G10/E10)) | I10: =IF(D10="","",IF(N(E10)=0,F10=0,ABS(H10)<=Setup!$B$5)) | K10: =IF(OR(A10="",SUMPRODUCT(($D$6:$D$105<>"")*1)=0),"",IF(SUMPRODUCT(($D$6:$D$105=A10)*1)>0,"",A10)) | L10: =IF(K10="","",B10=0)
A11: =IFERROR(INDEX(Mapping!$C$1:$C$504,SMALL(Mapping!$H$5:$H$504,6)),"") | B11: =IF(A11="","",SUMIF(Reconcile!$L$12:$L$1511,A11,Reconcile!$G$12:$G$1511)) | D11: opex.rent_facilities | E11: 7800000 | F11: =IF(D11="","",SUMIF(Reconcile!$L$12:$L$1511,D11,Reconcile!$G$12:$G$1511)) | G11: =IF(D11="","",F11-N(E11)) | H11: =IF(D11="","",IF(N(E11)=0,0,G11/E11)) | I11: =IF(D11="","",IF(N(E11)=0,F11=0,ABS(H11)<=Setup!$B$5)) | K11: =IF(OR(A11="",SUMPRODUCT(($D$6:$D$105<>"")*1)=0),"",IF(SUMPRODUCT(($D$6:$D$105=A11)*1)>0,"",A11)) | L11: =IF(K11="","",B11=0)
A12: =IFERROR(INDEX(Mapping!$C$1:$C$504,SMALL(Mapping!$H$5:$H$504,7)),"") | B12: =IF(A12="","",SUMIF(Reconcile!$L$12:$L$1511,A12,Reconcile!$G$12:$G$1511)) | D12: opex.admin | E12: 4600000 | F12: =IF(D12="","",SUMIF(Reconcile!$L$12:$L$1511,D12,Reconcile!$G$12:$G$1511)) | G12: =IF(D12="","",F12-N(E12)) | H12: =IF(D12="","",IF(N(E12)=0,0,G12/E12)) | I12: =IF(D12="","",IF(N(E12)=0,F12=0,ABS(H12)<=Setup!$B$5)) | K12: =IF(OR(A12="",SUMPRODUCT(($D$6:$D$105<>"")*1)=0),"",IF(SUMPRODUCT(($D$6:$D$105=A12)*1)>0,"",A12)) | L12: =IF(K12="","",B12=0)
A13: =IFERROR(INDEX(Mapping!$C$1:$C$504,SMALL(Mapping!$H$5:$H$504,8)),"") | B13: =IF(A13="","",SUMIF(Reconcile!$L$12:$L$1511,A13,Reconcile!$G$12:$G$1511)) | D13: da | E13: 10200000 | F13: =IF(D13="","",SUMIF(Reconcile!$L$12:$L$1511,D13,Reconcile!$G$12:$G$1511)) | G13: =IF(D13="","",F13-N(E13)) | H13: =IF(D13="","",IF(N(E13)=0,0,G13/E13)) | I13: =IF(D13="","",IF(N(E13)=0,F13=0,ABS(H13)<=Setup!$B$5)) | K13: =IF(OR(A13="",SUMPRODUCT(($D$6:$D$105<>"")*1)=0),"",IF(SUMPRODUCT(($D$6:$D$105=A13)*1)>0,"",A13)) | L13: =IF(K13="","",B13=0)
A14: =IFERROR(INDEX(Mapping!$C$1:$C$504,SMALL(Mapping!$H$5:$H$504,9)),"") | B14: =IF(A14="","",SUMIF(Reconcile!$L$12:$L$1511,A14,Reconcile!$G$12:$G$1511)) | F14: =IF(D14="","",SUMIF(Reconcile!$L$12:$L$1511,D14,Reconcile!$G$12:$G$1511)) | G14: =IF(D14="","",F14-N(E14)) | H14: =IF(D14="","",IF(N(E14)=0,0,G14/E14)) | I14: =IF(D14="","",IF(N(E14)=0,F14=0,ABS(H14)<=Setup!$B$5)) | K14: =IF(OR(A14="",SUMPRODUCT(($D$6:$D$105<>"")*1)=0),"",IF(SUMPRODUCT(($D$6:$D$105=A14)*1)>0,"",A14)) | L14: =IF(K14="","",B14=0)
A15: =IFERROR(INDEX(Mapping!$C$1:$C$504,SMALL(Mapping!$H$5:$H$504,10)),"") | B15: =IF(A15="","",SUMIF(Reconcile!$L$12:$L$1511,A15,Reconcile!$G$12:$G$1511)) | F15: =IF(D15="","",SUMIF(Reconcile!$L$12:$L$1511,D15,Reconcile!$G$12:$G$1511)) | G15: =IF(D15="","",F15-N(E15)) | H15: =IF(D15="","",IF(N(E15)=0,0,G15/E15)) | I15: =IF(D15="","",IF(N(E15)=0,F15=0,ABS(H15)<=Setup!$B$5)) | K15: =IF(OR(A15="",SUMPRODUCT(($D$6:$D$105<>"")*1)=0),"",IF(SUMPRODUCT(($D$6:$D$105=A15)*1)>0,"",A15)) | L15: =IF(K15="","",B15=0)
A16: =IFERROR(INDEX(Mapping!$C$1:$C$504,SMALL(Mapping!$H$5:$H$504,11)),"") | B16: =IF(A16="","",SUMIF(Reconcile!$L$12:$L$1511,A16,Reconcile!$G$12:$G$1511)) | F16: =IF(D16="","",SUMIF(Reconcile!$L$12:$L$1511,D16,Reconcile!$G$12:$G$1511)) | G16: =IF(D16="","",F16-N(E16)) | H16: =IF(D16="","",IF(N(E16)=0,0,G16/E16)) | I16: =IF(D16="","",IF(N(E16)=0,F16=0,ABS(H16)<=Setup!$B$5)) | K16: =IF(OR(A16="",SUMPRODUCT(($D$6:$D$105<>"")*1)=0),"",IF(SUMPRODUCT(($D$6:$D$105=A16)*1)>0,"",A16)) | L16: =IF(K16="","",B16=0)
A17: =IFERROR(INDEX(Mapping!$C$1:$C$504,SMALL(Mapping!$H$5:$H$504,12)),"") | B17: =IF(A17="","",SUMIF(Reconcile!$L$12:$L$1511,A17,Reconcile!$G$12:$G$1511)) | F17: =IF(D17="","",SUMIF(Reconcile!$L$12:$L$1511,D17,Reconcile!$G$12:$G$1511)) | G17: =IF(D17="","",F17-N(E17)) | H17: =IF(D17="","",IF(N(E17)=0,0,G17/E17)) | I17: =IF(D17="","",IF(N(E17)=0,F17=0,ABS(H17)<=Setup!$B$5)) | K17: =IF(OR(A17="",SUMPRODUCT(($D$6:$D$105<>"")*1)=0),"",IF(SUMPRODUCT(($D$6:$D$105=A17)*1)>0,"",A17)) | L17: =IF(K17="","",B17=0)
A18: =IFERROR(INDEX(Mapping!$C$1:$C$504,SMALL(Mapping!$H$5:$H$504,13)),"") | B18: =IF(A18="","",SUMIF(Reconcile!$L$12:$L$1511,A18,Reconcile!$G$12:$G$1511)) | F18: =IF(D18="","",SUMIF(Reconcile!$L$12:$L$1511,D18,Reconcile!$G$12:$G$1511)) | G18: =IF(D18="","",F18-N(E18)) | H18: =IF(D18="","",IF(N(E18)=0,0,G18/E18)) | I18: =IF(D18="","",IF(N(E18)=0,F18=0,ABS(H18)<=Setup!$B$5)) | K18: =IF(OR(A18="",SUMPRODUCT(($D$6:$D$105<>"")*1)=0),"",IF(SUMPRODUCT(($D$6:$D$105=A18)*1)>0,"",A18)) | L18: =IF(K18="","",B18=0)
A19: =IFERROR(INDEX(Mapping!$C$1:$C$504,SMALL(Mapping!$H$5:$H$504,14)),"") | B19: =IF(A19="","",SUMIF(Reconcile!$L$12:$L$1511,A19,Reconcile!$G$12:$G$1511)) | F19: =IF(D19="","",SUMIF(Reconcile!$L$12:$L$1511,D19,Reconcile!$G$12:$G$1511)) | G19: =IF(D19="","",F19-N(E19)) | H19: =IF(D19="","",IF(N(E19)=0,0,G19/E19)) | I19: =IF(D19="","",IF(N(E19)=0,F19=0,ABS(H19)<=Setup!$B$5)) | K19: =IF(OR(A19="",SUMPRODUCT(($D$6:$D$105<>"")*1)=0),"",IF(SUMPRODUCT(($D$6:$D$105=A19)*1)>0,"",A19)) | L19: =IF(K19="","",B19=0)
A20: =IFERROR(INDEX(Mapping!$C$1:$C$504,SMALL(Mapping!$H$5:$H$504,15)),"") | B20: =IF(A20="","",SUMIF(Reconcile!$L$12:$L$1511,A20,Reconcile!$G$12:$G$1511)) | F20: =IF(D20="","",SUMIF(Reconcile!$L$12:$L$1511,D20,Reconcile!$G$12:$G$1511)) | G20: =IF(D20="","",F20-N(E20)) | H20: =IF(D20="","",IF(N(E20)=0,0,G20/E20)) | I20: =IF(D20="","",IF(N(E20)=0,F20=0,ABS(H20)<=Setup!$B$5)) | K20: =IF(OR(A20="",SUMPRODUCT(($D$6:$D$105<>"")*1)=0),"",IF(SUMPRODUCT(($D$6:$D$105=A20)*1)>0,"",A20)) | L20: =IF(K20="","",B20=0)
A21: =IFERROR(INDEX(Mapping!$C$1:$C$504,SMALL(Mapping!$H$5:$H$504,16)),"") | B21: =IF(A21="","",SUMIF(Reconcile!$L$12:$L$1511,A21,Reconcile!$G$12:$G$1511)) | F21: =IF(D21="","",SUMIF(Reconcile!$L$12:$L$1511,D21,Reconcile!$G$12:$G$1511)) | G21: =IF(D21="","",F21-N(E21)) | H21: =IF(D21="","",IF(N(E21)=0,0,G21/E21)) | I21: =IF(D21="","",IF(N(E21)=0,F21=0,ABS(H21)<=Setup!$B$5)) | K21: =IF(OR(A21="",SUMPRODUCT(($D$6:$D$105<>"")*1)=0),"",IF(SUMPRODUCT(($D$6:$D$105=A21)*1)>0,"",A21)) | L21: =IF(K21="","",B21=0)
A22: =IFERROR(INDEX(Mapping!$C$1:$C$504,SMALL(Mapping!$H$5:$H$504,17)),"") | B22: =IF(A22="","",SUMIF(Reconcile!$L$12:$L$1511,A22,Reconcile!$G$12:$G$1511)) | F22: =IF(D22="","",SUMIF(Reconcile!$L$12:$L$1511,D22,Reconcile!$G$12:$G$1511)) | G22: =IF(D22="","",F22-N(E22)) | H22: =IF(D22="","",IF(N(E22)=0,0,G22/E22)) | I22: =IF(D22="","",IF(N(E22)=0,F22=0,ABS(H22)<=Setup!$B$5)) | K22: =IF(OR(A22="",SUMPRODUCT(($D$6:$D$105<>"")*1)=0),"",IF(SUMPRODUCT(($D$6:$D$105=A22)*1)>0,"",A22)) | L22: =IF(K22="","",B22=0)
A23: =IFERROR(INDEX(Mapping!$C$1:$C$504,SMALL(Mapping!$H$5:$H$504,18)),"") | B23: =IF(A23="","",SUMIF(Reconcile!$L$12:$L$1511,A23,Reconcile!$G$12:$G$1511)) | F23: =IF(D23="","",SUMIF(Reconcile!$L$12:$L$1511,D23,Reconcile!$G$12:$G$1511)) | G23: =IF(D23="","",F23-N(E23)) | H23: =IF(D23="","",IF(N(E23)=0,0,G23/E23)) | I23: =IF(D23="","",IF(N(E23)=0,F23=0,ABS(H23)<=Setup!$B$5)) | K23: =IF(OR(A23="",SUMPRODUCT(($D$6:$D$105<>"")*1)=0),"",IF(SUMPRODUCT(($D$6:$D$105=A23)*1)>0,"",A23)) | L23: =IF(K23="","",B23=0)
A24: =IFERROR(INDEX(Mapping!$C$1:$C$504,SMALL(Mapping!$H$5:$H$504,19)),"") | B24: =IF(A24="","",SUMIF(Reconcile!$L$12:$L$1511,A24,Reconcile!$G$12:$G$1511)) | F24: =IF(D24="","",SUMIF(Reconcile!$L$12:$L$1511,D24,Reconcile!$G$12:$G$1511)) | G24: =IF(D24="","",F24-N(E24)) | H24: =IF(D24="","",IF(N(E24)=0,0,G24/E24)) | I24: =IF(D24="","",IF(N(E24)=0,F24=0,ABS(H24)<=Setup!$B$5)) | K24: =IF(OR(A24="",SUMPRODUCT(($D$6:$D$105<>"")*1)=0),"",IF(SUMPRODUCT(($D$6:$D$105=A24)*1)>0,"",A24)) | L24: =IF(K24="","",B24=0)
A25: =IFERROR(INDEX(Mapping!$C$1:$C$504,SMALL(Mapping!$H$5:$H$504,20)),"") | B25: =IF(A25="","",SUMIF(Reconcile!$L$12:$L$1511,A25,Reconcile!$G$12:$G$1511)) | F25: =IF(D25="","",SUMIF(Reconcile!$L$12:$L$1511,D25,Reconcile!$G$12:$G$1511)) | G25: =IF(D25="","",F25-N(E25)) | H25: =IF(D25="","",IF(N(E25)=0,0,G25/E25)) | I25: =IF(D25="","",IF(N(E25)=0,F25=0,ABS(H25)<=Setup!$B$5)) | K25: =IF(OR(A25="",SUMPRODUCT(($D$6:$D$105<>"")*1)=0),"",IF(SUMPRODUCT(($D$6:$D$105=A25)*1)>0,"",A25)) | L25: =IF(K25="","",B25=0)
A26: =IFERROR(INDEX(Mapping!$C$1:$C$504,SMALL(Mapping!$H$5:$H$504,21)),"") | B26: =IF(A26="","",SUMIF(Reconcile!$L$12:$L$1511,A26,Reconcile!$G$12:$G$1511)) | F26: =IF(D26="","",SUMIF(Reconcile!$L$12:$L$1511,D26,Reconcile!$G$12:$G$1511)) | G26: =IF(D26="","",F26-N(E26)) | H26: =IF(D26="","",IF(N(E26)=0,0,G26/E26)) | I26: =IF(D26="","",IF(N(E26)=0,F26=0,ABS(H26)<=Setup!$B$5)) | K26: =IF(OR(A26="",SUMPRODUCT(($D$6:$D$105<>"")*1)=0),"",IF(SUMPRODUCT(($D$6:$D$105=A26)*1)>0,"",A26)) | L26: =IF(K26="","",B26=0)
A27: =IFERROR(INDEX(Mapping!$C$1:$C$504,SMALL(Mapping!$H$5:$H$504,22)),"") | B27: =IF(A27="","",SUMIF(Reconcile!$L$12:$L$1511,A27,Reconcile!$G$12:$G$1511)) | F27: =IF(D27="","",SUMIF(Reconcile!$L$12:$L$1511,D27,Reconcile!$G$12:$G$1511)) | G27: =IF(D27="","",F27-N(E27)) | H27: =IF(D27="","",IF(N(E27)=0,0,G27/E27)) | I27: =IF(D27="","",IF(N(E27)=0,F27=0,ABS(H27)<=Setup!$B$5)) | K27: =IF(OR(A27="",SUMPRODUCT(($D$6:$D$105<>"")*1)=0),"",IF(SUMPRODUCT(($D$6:$D$105=A27)*1)>0,"",A27)) | L27: =IF(K27="","",B27=0)
A28: =IFERROR(INDEX(Mapping!$C$1:$C$504,SMALL(Mapping!$H$5:$H$504,23)),"") | B28: =IF(A28="","",SUMIF(Reconcile!$L$12:$L$1511,A28,Reconcile!$G$12:$G$1511)) | F28: =IF(D28="","",SUMIF(Reconcile!$L$12:$L$1511,D28,Reconcile!$G$12:$G$1511)) | G28: =IF(D28="","",F28-N(E28)) | H28: =IF(D28="","",IF(N(E28)=0,0,G28/E28)) | I28: =IF(D28="","",IF(N(E28)=0,F28=0,ABS(H28)<=Setup!$B$5)) | K28: =IF(OR(A28="",SUMPRODUCT(($D$6:$D$105<>"")*1)=0),"",IF(SUMPRODUCT(($D$6:$D$105=A28)*1)>0,"",A28)) | L28: =IF(K28="","",B28=0)
A29: =IFERROR(INDEX(Mapping!$C$1:$C$504,SMALL(Mapping!$H$5:$H$504,24)),"") | B29: =IF(A29="","",SUMIF(Reconcile!$L$12:$L$1511,A29,Reconcile!$G$12:$G$1511)) | F29: =IF(D29="","",SUMIF(Reconcile!$L$12:$L$1511,D29,Reconcile!$G$12:$G$1511)) | G29: =IF(D29="","",F29-N(E29)) | H29: =IF(D29="","",IF(N(E29)=0,0,G29/E29)) | I29: =IF(D29="","",IF(N(E29)=0,F29=0,ABS(H29)<=Setup!$B$5)) | K29: =IF(OR(A29="",SUMPRODUCT(($D$6:$D$105<>"")*1)=0),"",IF(SUMPRODUCT(($D$6:$D$105=A29)*1)>0,"",A29)) | L29: =IF(K29="","",B29=0)
A30: =IFERROR(INDEX(Mapping!$C$1:$C$504,SMALL(Mapping!$H$5:$H$504,25)),"") | B30: =IF(A30="","",SUMIF(Reconcile!$L$12:$L$1511,A30,Reconcile!$G$12:$G$1511)) | F30: =IF(D30="","",SUMIF(Reconcile!$L$12:$L$1511,D30,Reconcile!$G$12:$G$1511)) | G30: =IF(D30="","",F30-N(E30)) | H30: =IF(D30="","",IF(N(E30)=0,0,G30/E30)) | I30: =IF(D30="","",IF(N(E30)=0,F30=0,ABS(H30)<=Setup!$B$5)) | K30: =IF(OR(A30="",SUMPRODUCT(($D$6:$D$105<>"")*1)=0),"",IF(SUMPRODUCT(($D$6:$D$105=A30)*1)>0,"",A30)) | L30: =IF(K30="","",B30=0)
A31: =IFERROR(INDEX(Mapping!$C$1:$C$504,SMALL(Mapping!$H$5:$H$504,26)),"") | B31: =IF(A31="","",SUMIF(Reconcile!$L$12:$L$1511,A31,Reconcile!$G$12:$G$1511)) | F31: =IF(D31="","",SUMIF(Reconcile!$L$12:$L$1511,D31,Reconcile!$G$12:$G$1511)) | G31: =IF(D31="","",F31-N(E31)) | H31: =IF(D31="","",IF(N(E31)=0,0,G31/E31)) | I31: =IF(D31="","",IF(N(E31)=0,F31=0,ABS(H31)<=Setup!$B$5)) | K31: =IF(OR(A31="",SUMPRODUCT(($D$6:$D$105<>"")*1)=0),"",IF(SUMPRODUCT(($D$6:$D$105=A31)*1)>0,"",A31)) | L31: =IF(K31="","",B31=0)
A32: =IFERROR(INDEX(Mapping!$C$1:$C$504,SMALL(Mapping!$H$5:$H$504,27)),"") | B32: =IF(A32="","",SUMIF(Reconcile!$L$12:$L$1511,A32,Reconcile!$G$12:$G$1511)) | F32: =IF(D32="","",SUMIF(Reconcile!$L$12:$L$1511,D32,Reconcile!$G$12:$G$1511)) | G32: =IF(D32="","",F32-N(E32)) | H32: =IF(D32="","",IF(N(E32)=0,0,G32/E32)) | I32: =IF(D32="","",IF(N(E32)=0,F32=0,ABS(H32)<=Setup!$B$5)) | K32: =IF(OR(A32="",SUMPRODUCT(($D$6:$D$105<>"")*1)=0),"",IF(SUMPRODUCT(($D$6:$D$105=A32)*1)>0,"",A32)) | L32: =IF(K32="","",B32=0)
A33: =IFERROR(INDEX(Mapping!$C$1:$C$504,SMALL(Mapping!$H$5:$H$504,28)),"") | B33: =IF(A33="","",SUMIF(Reconcile!$L$12:$L$1511,A33,Reconcile!$G$12:$G$1511)) | F33: =IF(D33="","",SUMIF(Reconcile!$L$12:$L$1511,D33,Reconcile!$G$12:$G$1511)) | G33: =IF(D33="","",F33-N(E33)) | H33: =IF(D33="","",IF(N(E33)=0,0,G33/E33)) | I33: =IF(D33="","",IF(N(E33)=0,F33=0,ABS(H33)<=Setup!$B$5)) | K33: =IF(OR(A33="",SUMPRODUCT(($D$6:$D$105<>"")*1)=0),"",IF(SUMPRODUCT(($D$6:$D$105=A33)*1)>0,"",A33)) | L33: =IF(K33="","",B33=0)
A34: =IFERROR(INDEX(Mapping!$C$1:$C$504,SMALL(Mapping!$H$5:$H$504,29)),"") | B34: =IF(A34="","",SUMIF(Reconcile!$L$12:$L$1511,A34,Reconcile!$G$12:$G$1511)) | F34: =IF(D34="","",SUMIF(Reconcile!$L$12:$L$1511,D34,Reconcile!$G$12:$G$1511)) | G34: =IF(D34="","",F34-N(E34)) | H34: =IF(D34="","",IF(N(E34)=0,0,G34/E34)) | I34: =IF(D34="","",IF(N(E34)=0,F34=0,ABS(H34)<=Setup!$B$5)) | K34: =IF(OR(A34="",SUMPRODUCT(($D$6:$D$105<>"")*1)=0),"",IF(SUMPRODUCT(($D$6:$D$105=A34)*1)>0,"",A34)) | L34: =IF(K34="","",B34=0)
A35: =IFERROR(INDEX(Mapping!$C$1:$C$504,SMALL(Mapping!$H$5:$H$504,30)),"") | B35: =IF(A35="","",SUMIF(Reconcile!$L$12:$L$1511,A35,Reconcile!$G$12:$G$1511)) | F35: =IF(D35="","",SUMIF(Reconcile!$L$12:$L$1511,D35,Reconcile!$G$12:$G$1511)) | G35: =IF(D35="","",F35-N(E35)) | H35: =IF(D35="","",IF(N(E35)=0,0,G35/E35)) | I35: =IF(D35="","",IF(N(E35)=0,F35=0,ABS(H35)<=Setup!$B$5)) | K35: =IF(OR(A35="",SUMPRODUCT(($D$6:$D$105<>"")*1)=0),"",IF(SUMPRODUCT(($D$6:$D$105=A35)*1)>0,"",A35)) | L35: =IF(K35="","",B35=0)
A36: =IFERROR(INDEX(Mapping!$C$1:$C$504,SMALL(Mapping!$H$5:$H$504,31)),"") | B36: =IF(A36="","",SUMIF(Reconcile!$L$12:$L$1511,A36,Reconcile!$G$12:$G$1511)) | F36: =IF(D36="","",SUMIF(Reconcile!$L$12:$L$1511,D36,Reconcile!$G$12:$G$1511)) | G36: =IF(D36="","",F36-N(E36)) | H36: =IF(D36="","",IF(N(E36)=0,0,G36/E36)) | I36: =IF(D36="","",IF(N(E36)=0,F36=0,ABS(H36)<=Setup!$B$5)) | K36: =IF(OR(A36="",SUMPRODUCT(($D$6:$D$105<>"")*1)=0),"",IF(SUMPRODUCT(($D$6:$D$105=A36)*1)>0,"",A36)) | L36: =IF(K36="","",B36=0)
A37: =IFERROR(INDEX(Mapping!$C$1:$C$504,SMALL(Mapping!$H$5:$H$504,32)),"") | B37: =IF(A37="","",SUMIF(Reconcile!$L$12:$L$1511,A37,Reconcile!$G$12:$G$1511)) | F37: =IF(D37="","",SUMIF(Reconcile!$L$12:$L$1511,D37,Reconcile!$G$12:$G$1511)) | G37: =IF(D37="","",F37-N(E37)) | H37: =IF(D37="","",IF(N(E37)=0,0,G37/E37)) | I37: =IF(D37="","",IF(N(E37)=0,F37=0,ABS(H37)<=Setup!$B$5)) | K37: =IF(OR(A37="",SUMPRODUCT(($D$6:$D$105<>"")*1)=0),"",IF(SUMPRODUCT(($D$6:$D$105=A37)*1)>0,"",A37)) | L37: =IF(K37="","",B37=0)
A38: =IFERROR(INDEX(Mapping!$C$1:$C$504,SMALL(Mapping!$H$5:$H$504,33)),"") | B38: =IF(A38="","",SUMIF(Reconcile!$L$12:$L$1511,A38,Reconcile!$G$12:$G$1511)) | F38: =IF(D38="","",SUMIF(Reconcile!$L$12:$L$1511,D38,Reconcile!$G$12:$G$1511)) | G38: =IF(D38="","",F38-N(E38)) | H38: =IF(D38="","",IF(N(E38)=0,0,G38/E38)) | I38: =IF(D38="","",IF(N(E38)=0,F38=0,ABS(H38)<=Setup!$B$5)) | K38: =IF(OR(A38="",SUMPRODUCT(($D$6:$D$105<>"")*1)=0),"",IF(SUMPRODUCT(($D$6:$D$105=A38)*1)>0,"",A38)) | L38: =IF(K38="","",B38=0)
A39: =IFERROR(INDEX(Mapping!$C$1:$C$504,SMALL(Mapping!$H$5:$H$504,34)),"") | B39: =IF(A39="","",SUMIF(Reconcile!$L$12:$L$1511,A39,Reconcile!$G$12:$G$1511)) | F39: =IF(D39="","",SUMIF(Reconcile!$L$12:$L$1511,D39,Reconcile!$G$12:$G$1511)) | G39: =IF(D39="","",F39-N(E39)) | H39: =IF(D39="","",IF(N(E39)=0,0,G39/E39)) | I39: =IF(D39="","",IF(N(E39)=0,F39=0,ABS(H39)<=Setup!$B$5)) | K39: =IF(OR(A39="",SUMPRODUCT(($D$6:$D$105<>"")*1)=0),"",IF(SUMPRODUCT(($D$6:$D$105=A39)*1)>0,"",A39)) | L39: =IF(K39="","",B39=0)
A40: =IFERROR(INDEX(Mapping!$C$1:$C$504,SMALL(Mapping!$H$5:$H$504,35)),"") | B40: =IF(A40="","",SUMIF(Reconcile!$L$12:$L$1511,A40,Reconcile!$G$12:$G$1511)) | F40: =IF(D40="","",SUMIF(Reconcile!$L$12:$L$1511,D40,Reconcile!$G$12:$G$1511)) | G40: =IF(D40="","",F40-N(E40)) | H40: =IF(D40="","",IF(N(E40)=0,0,G40/E40)) | I40: =IF(D40="","",IF(N(E40)=0,F40=0,ABS(H40)<=Setup!$B$5)) | K40: =IF(OR(A40="",SUMPRODUCT(($D$6:$D$105<>"")*1)=0),"",IF(SUMPRODUCT(($D$6:$D$105=A40)*1)>0,"",A40)) | L40: =IF(K40="","",B40=0)
A41: =IFERROR(INDEX(Mapping!$C$1:$C$504,SMALL(Mapping!$H$5:$H$504,36)),"") | B41: =IF(A41="","",SUMIF(Reconcile!$L$12:$L$1511,A41,Reconcile!$G$12:$G$1511)) | F41: =IF(D41="","",SUMIF(Reconcile!$L$12:$L$1511,D41,Reconcile!$G$12:$G$1511)) | G41: =IF(D41="","",F41-N(E41)) | H41: =IF(D41="","",IF(N(E41)=0,0,G41/E41)) | I41: =IF(D41="","",IF(N(E41)=0,F41=0,ABS(H41)<=Setup!$B$5)) | K41: =IF(OR(A41="",SUMPRODUCT(($D$6:$D$105<>"")*1)=0),"",IF(SUMPRODUCT(($D$6:$D$105=A41)*1)>0,"",A41)) | L41: =IF(K41="","",B41=0)
A42: =IFERROR(INDEX(Mapping!$C$1:$C$504,SMALL(Mapping!$H$5:$H$504,37)),"") | B42: =IF(A42="","",SUMIF(Reconcile!$L$12:$L$1511,A42,Reconcile!$G$12:$G$1511)) | F42: =IF(D42="","",SUMIF(Reconcile!$L$12:$L$1511,D42,Reconcile!$G$12:$G$1511)) | G42: =IF(D42="","",F42-N(E42)) | H42: =IF(D42="","",IF(N(E42)=0,0,G42/E42)) | I42: =IF(D42="","",IF(N(E42)=0,F42=0,ABS(H42)<=Setup!$B$5)) | K42: =IF(OR(A42="",SUMPRODUCT(($D$6:$D$105<>"")*1)=0),"",IF(SUMPRODUCT(($D$6:$D$105=A42)*1)>0,"",A42)) | L42: =IF(K42="","",B42=0)
A43: =IFERROR(INDEX(Mapping!$C$1:$C$504,SMALL(Mapping!$H$5:$H$504,38)),"") | B43: =IF(A43="","",SUMIF(Reconcile!$L$12:$L$1511,A43,Reconcile!$G$12:$G$1511)) | F43: =IF(D43="","",SUMIF(Reconcile!$L$12:$L$1511,D43,Reconcile!$G$12:$G$1511)) | G43: =IF(D43="","",F43-N(E43)) | H43: =IF(D43="","",IF(N(E43)=0,0,G43/E43)) | I43: =IF(D43="","",IF(N(E43)=0,F43=0,ABS(H43)<=Setup!$B$5)) | K43: =IF(OR(A43="",SUMPRODUCT(($D$6:$D$105<>"")*1)=0),"",IF(SUMPRODUCT(($D$6:$D$105=A43)*1)>0,"",A43)) | L43: =IF(K43="","",B43=0)
A44: =IFERROR(INDEX(Mapping!$C$1:$C$504,SMALL(Mapping!$H$5:$H$504,39)),"") | B44: =IF(A44="","",SUMIF(Reconcile!$L$12:$L$1511,A44,Reconcile!$G$12:$G$1511)) | F44: =IF(D44="","",SUMIF(Reconcile!$L$12:$L$1511,D44,Reconcile!$G$12:$G$1511)) | G44: =IF(D44="","",F44-N(E44)) | H44: =IF(D44="","",IF(N(E44)=0,0,G44/E44)) | I44: =IF(D44="","",IF(N(E44)=0,F44=0,ABS(H44)<=Setup!$B$5)) | K44: =IF(OR(A44="",SUMPRODUCT(($D$6:$D$105<>"")*1)=0),"",IF(SUMPRODUCT(($D$6:$D$105=A44)*1)>0,"",A44)) | L44: =IF(K44="","",B44=0)
A45: =IFERROR(INDEX(Mapping!$C$1:$C$504,SMALL(Mapping!$H$5:$H$504,40)),"") | B45: =IF(A45="","",SUMIF(Reconcile!$L$12:$L$1511,A45,Reconcile!$G$12:$G$1511)) | F45: =IF(D45="","",SUMIF(Reconcile!$L$12:$L$1511,D45,Reconcile!$G$12:$G$1511)) | G45: =IF(D45="","",F45-N(E45)) | H45: =IF(D45="","",IF(N(E45)=0,0,G45/E45)) | I45: =IF(D45="","",IF(N(E45)=0,F45=0,ABS(H45)<=Setup!$B$5)) | K45: =IF(OR(A45="",SUMPRODUCT(($D$6:$D$105<>"")*1)=0),"",IF(SUMPRODUCT(($D$6:$D$105=A45)*1)>0,"",A45)) | L45: =IF(K45="","",B45=0)
A46: =IFERROR(INDEX(Mapping!$C$1:$C$504,SMALL(Mapping!$H$5:$H$504,41)),"") | B46: =IF(A46="","",SUMIF(Reconcile!$L$12:$L$1511,A46,Reconcile!$G$12:$G$1511)) | F46: =IF(D46="","",SUMIF(Reconcile!$L$12:$L$1511,D46,Reconcile!$G$12:$G$1511)) | G46: =IF(D46="","",F46-N(E46)) | H46: =IF(D46="","",IF(N(E46)=0,0,G46/E46)) | I46: =IF(D46="","",IF(N(E46)=0,F46=0,ABS(H46)<=Setup!$B$5)) | K46: =IF(OR(A46="",SUMPRODUCT(($D$6:$D$105<>"")*1)=0),"",IF(SUMPRODUCT(($D$6:$D$105=A46)*1)>0,"",A46)) | L46: =IF(K46="","",B46=0)
A47: =IFERROR(INDEX(Mapping!$C$1:$C$504,SMALL(Mapping!$H$5:$H$504,42)),"") | B47: =IF(A47="","",SUMIF(Reconcile!$L$12:$L$1511,A47,Reconcile!$G$12:$G$1511)) | F47: =IF(D47="","",SUMIF(Reconcile!$L$12:$L$1511,D47,Reconcile!$G$12:$G$1511)) | G47: =IF(D47="","",F47-N(E47)) | H47: =IF(D47="","",IF(N(E47)=0,0,G47/E47)) | I47: =IF(D47="","",IF(N(E47)=0,F47=0,ABS(H47)<=Setup!$B$5)) | K47: =IF(OR(A47="",SUMPRODUCT(($D$6:$D$105<>"")*1)=0),"",IF(SUMPRODUCT(($D$6:$D$105=A47)*1)>0,"",A47)) | L47: =IF(K47="","",B47=0)
A48: =IFERROR(INDEX(Mapping!$C$1:$C$504,SMALL(Mapping!$H$5:$H$504,43)),"") | B48: =IF(A48="","",SUMIF(Reconcile!$L$12:$L$1511,A48,Reconcile!$G$12:$G$1511)) | F48: =IF(D48="","",SUMIF(Reconcile!$L$12:$L$1511,D48,Reconcile!$G$12:$G$1511)) | G48: =IF(D48="","",F48-N(E48)) | H48: =IF(D48="","",IF(N(E48)=0,0,G48/E48)) | I48: =IF(D48="","",IF(N(E48)=0,F48=0,ABS(H48)<=Setup!$B$5)) | K48: =IF(OR(A48="",SUMPRODUCT(($D$6:$D$105<>"")*1)=0),"",IF(SUMPRODUCT(($D$6:$D$105=A48)*1)>0,"",A48)) | L48: =IF(K48="","",B48=0)
A49: =IFERROR(INDEX(Mapping!$C$1:$C$504,SMALL(Mapping!$H$5:$H$504,44)),"") | B49: =IF(A49="","",SUMIF(Reconcile!$L$12:$L$1511,A49,Reconcile!$G$12:$G$1511)) | F49: =IF(D49="","",SUMIF(Reconcile!$L$12:$L$1511,D49,Reconcile!$G$12:$G$1511)) | G49: =IF(D49="","",F49-N(E49)) | H49: =IF(D49="","",IF(N(E49)=0,0,G49/E49)) | I49: =IF(D49="","",IF(N(E49)=0,F49=0,ABS(H49)<=Setup!$B$5)) | K49: =IF(OR(A49="",SUMPRODUCT(($D$6:$D$105<>"")*1)=0),"",IF(SUMPRODUCT(($D$6:$D$105=A49)*1)>0,"",A49)) | L49: =IF(K49="","",B49=0)
A50: =IFERROR(INDEX(Mapping!$C$1:$C$504,SMALL(Mapping!$H$5:$H$504,45)),"") | B50: =IF(A50="","",SUMIF(Reconcile!$L$12:$L$1511,A50,Reconcile!$G$12:$G$1511)) | F50: =IF(D50="","",SUMIF(Reconcile!$L$12:$L$1511,D50,Reconcile!$G$12:$G$1511)) | G50: =IF(D50="","",F50-N(E50)) | H50: =IF(D50="","",IF(N(E50)=0,0,G50/E50)) | I50: =IF(D50="","",IF(N(E50)=0,F50=0,ABS(H50)<=Setup!$B$5)) | K50: =IF(OR(A50="",SUMPRODUCT(($D$6:$D$105<>"")*1)=0),"",IF(SUMPRODUCT(($D$6:$D$105=A50)*1)>0,"",A50)) | L50: =IF(K50="","",B50=0)
A51: =IFERROR(INDEX(Mapping!$C$1:$C$504,SMALL(Mapping!$H$5:$H$504,46)),"") | B51: =IF(A51="","",SUMIF(Reconcile!$L$12:$L$1511,A51,Reconcile!$G$12:$G$1511)) | F51: =IF(D51="","",SUMIF(Reconcile!$L$12:$L$1511,D51,Reconcile!$G$12:$G$1511)) | G51: =IF(D51="","",F51-N(E51)) | H51: =IF(D51="","",IF(N(E51)=0,0,G51/E51)) | I51: =IF(D51="","",IF(N(E51)=0,F51=0,ABS(H51)<=Setup!$B$5)) | K51: =IF(OR(A51="",SUMPRODUCT(($D$6:$D$105<>"")*1)=0),"",IF(SUMPRODUCT(($D$6:$D$105=A51)*1)>0,"",A51)) | L51: =IF(K51="","",B51=0)
A52: =IFERROR(INDEX(Mapping!$C$1:$C$504,SMALL(Mapping!$H$5:$H$504,47)),"") | B52: =IF(A52="","",SUMIF(Reconcile!$L$12:$L$1511,A52,Reconcile!$G$12:$G$1511)) | F52: =IF(D52="","",SUMIF(Reconcile!$L$12:$L$1511,D52,Reconcile!$G$12:$G$1511)) | G52: =IF(D52="","",F52-N(E52)) | H52: =IF(D52="","",IF(N(E52)=0,0,G52/E52)) | I52: =IF(D52="","",IF(N(E52)=0,F52=0,ABS(H52)<=Setup!$B$5)) | K52: =IF(OR(A52="",SUMPRODUCT(($D$6:$D$105<>"")*1)=0),"",IF(SUMPRODUCT(($D$6:$D$105=A52)*1)>0,"",A52)) | L52: =IF(K52="","",B52=0)
A53: =IFERROR(INDEX(Mapping!$C$1:$C$504,SMALL(Mapping!$H$5:$H$504,48)),"") | B53: =IF(A53="","",SUMIF(Reconcile!$L$12:$L$1511,A53,Reconcile!$G$12:$G$1511)) | F53: =IF(D53="","",SUMIF(Reconcile!$L$12:$L$1511,D53,Reconcile!$G$12:$G$1511)) | G53: =IF(D53="","",F53-N(E53)) | H53: =IF(D53="","",IF(N(E53)=0,0,G53/E53)) | I53: =IF(D53="","",IF(N(E53)=0,F53=0,ABS(H53)<=Setup!$B$5)) | K53: =IF(OR(A53="",SUMPRODUCT(($D$6:$D$105<>"")*1)=0),"",IF(SUMPRODUCT(($D$6:$D$105=A53)*1)>0,"",A53)) | L53: =IF(K53="","",B53=0)
A54: =IFERROR(INDEX(Mapping!$C$1:$C$504,SMALL(Mapping!$H$5:$H$504,49)),"") | B54: =IF(A54="","",SUMIF(Reconcile!$L$12:$L$1511,A54,Reconcile!$G$12:$G$1511)) | F54: =IF(D54="","",SUMIF(Reconcile!$L$12:$L$1511,D54,Reconcile!$G$12:$G$1511)) | G54: =IF(D54="","",F54-N(E54)) | H54: =IF(D54="","",IF(N(E54)=0,0,G54/E54)) | I54: =IF(D54="","",IF(N(E54)=0,F54=0,ABS(H54)<=Setup!$B$5)) | K54: =IF(OR(A54="",SUMPRODUCT(($D$6:$D$105<>"")*1)=0),"",IF(SUMPRODUCT(($D$6:$D$105=A54)*1)>0,"",A54)) | L54: =IF(K54="","",B54=0)
A55: =IFERROR(INDEX(Mapping!$C$1:$C$504,SMALL(Mapping!$H$5:$H$504,50)),"") | B55: =IF(A55="","",SUMIF(Reconcile!$L$12:$L$1511,A55,Reconcile!$G$12:$G$1511)) | F55: =IF(D55="","",SUMIF(Reconcile!$L$12:$L$1511,D55,Reconcile!$G$12:$G$1511)) | G55: =IF(D55="","",F55-N(E55)) | H55: =IF(D55="","",IF(N(E55)=0,0,G55/E55)) | I55: =IF(D55="","",IF(N(E55)=0,F55=0,ABS(H55)<=Setup!$B$5)) | K55: =IF(OR(A55="",SUMPRODUCT(($D$6:$D$105<>"")*1)=0),"",IF(SUMPRODUCT(($D$6:$D$105=A55)*1)>0,"",A55)) | L55: =IF(K55="","",B55=0)
A56: =IFERROR(INDEX(Mapping!$C$1:$C$504,SMALL(Mapping!$H$5:$H$504,51)),"") | B56: =IF(A56="","",SUMIF(Reconcile!$L$12:$L$1511,A56,Reconcile!$G$12:$G$1511)) | F56: =IF(D56="","",SUMIF(Reconcile!$L$12:$L$1511,D56,Reconcile!$G$12:$G$1511)) | G56: =IF(D56="","",F56-N(E56)) | H56: =IF(D56="","",IF(N(E56)=0,0,G56/E56)) | I56: =IF(D56="","",IF(N(E56)=0,F56=0,ABS(H56)<=Setup!$B$5)) | K56: =IF(OR(A56="",SUMPRODUCT(($D$6:$D$105<>"")*1)=0),"",IF(SUMPRODUCT(($D$6:$D$105=A56)*1)>0,"",A56)) | L56: =IF(K56="","",B56=0)
A57: =IFERROR(INDEX(Mapping!$C$1:$C$504,SMALL(Mapping!$H$5:$H$504,52)),"") | B57: =IF(A57="","",SUMIF(Reconcile!$L$12:$L$1511,A57,Reconcile!$G$12:$G$1511)) | F57: =IF(D57="","",SUMIF(Reconcile!$L$12:$L$1511,D57,Reconcile!$G$12:$G$1511)) | G57: =IF(D57="","",F57-N(E57)) | H57: =IF(D57="","",IF(N(E57)=0,0,G57/E57)) | I57: =IF(D57="","",IF(N(E57)=0,F57=0,ABS(H57)<=Setup!$B$5)) | K57: =IF(OR(A57="",SUMPRODUCT(($D$6:$D$105<>"")*1)=0),"",IF(SUMPRODUCT(($D$6:$D$105=A57)*1)>0,"",A57)) | L57: =IF(K57="","",B57=0)
A58: =IFERROR(INDEX(Mapping!$C$1:$C$504,SMALL(Mapping!$H$5:$H$504,53)),"") | B58: =IF(A58="","",SUMIF(Reconcile!$L$12:$L$1511,A58,Reconcile!$G$12:$G$1511)) | F58: =IF(D58="","",SUMIF(Reconcile!$L$12:$L$1511,D58,Reconcile!$G$12:$G$1511)) | G58: =IF(D58="","",F58-N(E58)) | H58: =IF(D58="","",IF(N(E58)=0,0,G58/E58)) | I58: =IF(D58="","",IF(N(E58)=0,F58=0,ABS(H58)<=Setup!$B$5)) | K58: =IF(OR(A58="",SUMPRODUCT(($D$6:$D$105<>"")*1)=0),"",IF(SUMPRODUCT(($D$6:$D$105=A58)*1)>0,"",A58)) | L58: =IF(K58="","",B58=0)
A59: =IFERROR(INDEX(Mapping!$C$1:$C$504,SMALL(Mapping!$H$5:$H$504,54)),"") | B59: =IF(A59="","",SUMIF(Reconcile!$L$12:$L$1511,A59,Reconcile!$G$12:$G$1511)) | F59: =IF(D59="","",SUMIF(Reconcile!$L$12:$L$1511,D59,Reconcile!$G$12:$G$1511)) | G59: =IF(D59="","",F59-N(E59)) | H59: =IF(D59="","",IF(N(E59)=0,0,G59/E59)) | I59: =IF(D59="","",IF(N(E59)=0,F59=0,ABS(H59)<=Setup!$B$5)) | K59: =IF(OR(A59="",SUMPRODUCT(($D$6:$D$105<>"")*1)=0),"",IF(SUMPRODUCT(($D$6:$D$105=A59)*1)>0,"",A59)) | L59: =IF(K59="","",B59=0)
A60: =IFERROR(INDEX(Mapping!$C$1:$C$504,SMALL(Mapping!$H$5:$H$504,55)),"") | B60: =IF(A60="","",SUMIF(Reconcile!$L$12:$L$1511,A60,Reconcile!$G$12:$G$1511)) | F60: =IF(D60="","",SUMIF(Reconcile!$L$12:$L$1511,D60,Reconcile!$G$12:$G$1511)) | G60: =IF(D60="","",F60-N(E60)) | H60: =IF(D60="","",IF(N(E60)=0,0,G60/E60)) | I60: =IF(D60="","",IF(N(E60)=0,F60=0,ABS(H60)<=Setup!$B$5)) | K60: =IF(OR(A60="",SUMPRODUCT(($D$6:$D$105<>"")*1)=0),"",IF(SUMPRODUCT(($D$6:$D$105=A60)*1)>0,"",A60)) | L60: =IF(K60="","",B60=0)
A61: =IFERROR(INDEX(Mapping!$C$1:$C$504,SMALL(Mapping!$H$5:$H$504,56)),"") | B61: =IF(A61="","",SUMIF(Reconcile!$L$12:$L$1511,A61,Reconcile!$G$12:$G$1511)) | F61: =IF(D61="","",SUMIF(Reconcile!$L$12:$L$1511,D61,Reconcile!$G$12:$G$1511)) | G61: =IF(D61="","",F61-N(E61)) | H61: =IF(D61="","",IF(N(E61)=0,0,G61/E61)) | I61: =IF(D61="","",IF(N(E61)=0,F61=0,ABS(H61)<=Setup!$B$5)) | K61: =IF(OR(A61="",SUMPRODUCT(($D$6:$D$105<>"")*1)=0),"",IF(SUMPRODUCT(($D$6:$D$105=A61)*1)>0,"",A61)) | L61: =IF(K61="","",B61=0)
A62: =IFERROR(INDEX(Mapping!$C$1:$C$504,SMALL(Mapping!$H$5:$H$504,57)),"") | B62: =IF(A62="","",SUMIF(Reconcile!$L$12:$L$1511,A62,Reconcile!$G$12:$G$1511)) | F62: =IF(D62="","",SUMIF(Reconcile!$L$12:$L$1511,D62,Reconcile!$G$12:$G$1511)) | G62: =IF(D62="","",F62-N(E62)) | H62: =IF(D62="","",IF(N(E62)=0,0,G62/E62)) | I62: =IF(D62="","",IF(N(E62)=0,F62=0,ABS(H62)<=Setup!$B$5)) | K62: =IF(OR(A62="",SUMPRODUCT(($D$6:$D$105<>"")*1)=0),"",IF(SUMPRODUCT(($D$6:$D$105=A62)*1)>0,"",A62)) | L62: =IF(K62="","",B62=0)
A63: =IFERROR(INDEX(Mapping!$C$1:$C$504,SMALL(Mapping!$H$5:$H$504,58)),"") | B63: =IF(A63="","",SUMIF(Reconcile!$L$12:$L$1511,A63,Reconcile!$G$12:$G$1511)) | F63: =IF(D63="","",SUMIF(Reconcile!$L$12:$L$1511,D63,Reconcile!$G$12:$G$1511)) | G63: =IF(D63="","",F63-N(E63)) | H63: =IF(D63="","",IF(N(E63)=0,0,G63/E63)) | I63: =IF(D63="","",IF(N(E63)=0,F63=0,ABS(H63)<=Setup!$B$5)) | K63: =IF(OR(A63="",SUMPRODUCT(($D$6:$D$105<>"")*1)=0),"",IF(SUMPRODUCT(($D$6:$D$105=A63)*1)>0,"",A63)) | L63: =IF(K63="","",B63=0)
A64: =IFERROR(INDEX(Mapping!$C$1:$C$504,SMALL(Mapping!$H$5:$H$504,59)),"") | B64: =IF(A64="","",SUMIF(Reconcile!$L$12:$L$1511,A64,Reconcile!$G$12:$G$1511)) | F64: =IF(D64="","",SUMIF(Reconcile!$L$12:$L$1511,D64,Reconcile!$G$12:$G$1511)) | G64: =IF(D64="","",F64-N(E64)) | H64: =IF(D64="","",IF(N(E64)=0,0,G64/E64)) | I64: =IF(D64="","",IF(N(E64)=0,F64=0,ABS(H64)<=Setup!$B$5)) | K64: =IF(OR(A64="",SUMPRODUCT(($D$6:$D$105<>"")*1)=0),"",IF(SUMPRODUCT(($D$6:$D$105=A64)*1)>0,"",A64)) | L64: =IF(K64="","",B64=0)
