Workbook
Name tb_diff: 'Summary'!$B$6
Name tb_unmapped: 'Summary'!$B$7

Sheet README
A1: D02 · ERP & core accounting systems
A3: Domain D02: ERP & core accounting systems.
A4: Bring the books in cleanly: trial balance integrity (Dr = Cr), ledger → Schedule III → kernel-target mapping, and the export recipe per ERP.
A5: How to use
A6: Copy this workbook into companies/<slug>/domains/D02_erp-core-accounting/ before typing. Replace the SAMPLE rows (illustrative Tamil Nadu data) with company data.
A7: Type only into pale-yellow cells; white cells are formulas. Checks › OVERALL must be PASS before any value feeds K01/K02.
A8: Statutory rates are starting values - verify in 01_tamil-nadu/verification-register.md.
A9: Feeds
A10: memory/mappings/registry.csv <= TrialBalance mapping columns
A11: K03 Reconcile <= mapped TB
A12: K01 opening_balances.* <= balance-sheet ledgers

Sheet Checks
A1: Checks - OVERALL must be PASS before this domain feeds the kernel
B3: OVERALL | C3: =IF(COUNTIF(C5:C6,"PASS")=COUNT(A5:A6),"PASS","FAIL")
A4: # | B4: check | C4: result
A5: 1 | B5: trial balance balances (Dr = Cr) | C5: =IF(ABS(Summary!$B$6)<0.01,"PASS","FAIL")
A6: 2 | B6: every ledger mapped to Schedule III line and kernel target | C6: =IF(Summary!$B$7=0,"PASS","FAIL")

Sheet TrialBalance
A1: Trial balance check (paste Tally Prime / Zoho Books / SAP B1 TB: ledger, group, debit, credit)
A4: ledger | B4: Tally group / ERP account group | C4: debit | D4: credit | E4: net (Dr - Cr) | F4: Schedule III line (from 01_tamil-nadu/schedule-iii-mapping.csv) | G4: kernel target (mapping target) | H4: mapped?
A5: Sales - Domestic (TN) @18% | B5: Sales Accounts | D5: 850000000 | E5: =IF(A5="","",N(C5)-N(D5)) | F5: Revenue from operations | G5: income_statement.revenue | H5: =IF(A5="","",IF(OR(F5="",G5=""),"UNMAPPED","ok"))
A6: Purchase - Raw Material | B6: Purchase Accounts | C6: 520000000 | E6: =IF(A6="","",N(C6)-N(D6)) | F6: Cost of materials consumed | G6: income_statement.cogs | H6: =IF(A6="","",IF(OR(F6="",G6=""),"UNMAPPED","ok"))
A7: Salaries & Wages | B7: Indirect Expenses | C7: 96000000 | E7: =IF(A7="","",N(C7)-N(D7)) | F7: Employee benefits expense | G7: opex.payroll | H7: =IF(A7="","",IF(OR(F7="",G7=""),"UNMAPPED","ok"))
A8: HDFC Bank CC A/c | B8: Bank OD A/c | D8: 45000000 | E8: =IF(A8="","",N(C8)-N(D8)) | F8: Short-term borrowings | G8: debt.cash_credit | H8: =IF(A8="","",IF(OR(F8="",G8=""),"UNMAPPED","ok"))
A9: Sundry Debtors | B9: Sundry Debtors | C9: 120000000 | E9: =IF(A9="","",N(C9)-N(D9)) | F9: Trade receivables | G9: balance_sheet.ar | H9: =IF(A9="","",IF(OR(F9="",G9=""),"UNMAPPED","ok"))
A10: Capital Account | B10: Capital Account | D10: 241000000 | E10: =IF(A10="","",N(C10)-N(D10)) | F10: Equity share capital | G10: balance_sheet.equity | H10: =IF(A10="","",IF(OR(F10="",G10=""),"UNMAPPED","ok"))
A11: Plant & Machinery | B11: Fixed Assets | C11: 400000000 | E11: =IF(A11="","",N(C11)-N(D11)) | F11: Property, plant and equipment | G11: balance_sheet.ppe | H11: =IF(A11="","",IF(OR(F11="",G11=""),"UNMAPPED","ok"))
E12: =IF(A12="","",N(C12)-N(D12)) | H12: =IF(A12="","",IF(OR(F12="",G12=""),"UNMAPPED","ok"))
E13: =IF(A13="","",N(C13)-N(D13)) | H13: =IF(A13="","",IF(OR(F13="",G13=""),"UNMAPPED","ok"))
E14: =IF(A14="","",N(C14)-N(D14)) | H14: =IF(A14="","",IF(OR(F14="",G14=""),"UNMAPPED","ok"))
E15: =IF(A15="","",N(C15)-N(D15)) | H15: =IF(A15="","",IF(OR(F15="",G15=""),"UNMAPPED","ok"))
E16: =IF(A16="","",N(C16)-N(D16)) | H16: =IF(A16="","",IF(OR(F16="",G16=""),"UNMAPPED","ok"))
E17: =IF(A17="","",N(C17)-N(D17)) | H17: =IF(A17="","",IF(OR(F17="",G17=""),"UNMAPPED","ok"))
E18: =IF(A18="","",N(C18)-N(D18)) | H18: =IF(A18="","",IF(OR(F18="",G18=""),"UNMAPPED","ok"))
E19: =IF(A19="","",N(C19)-N(D19)) | H19: =IF(A19="","",IF(OR(F19="",G19=""),"UNMAPPED","ok"))
E20: =IF(A20="","",N(C20)-N(D20)) | H20: =IF(A20="","",IF(OR(F20="",G20=""),"UNMAPPED","ok"))
E21: =IF(A21="","",N(C21)-N(D21)) | H21: =IF(A21="","",IF(OR(F21="",G21=""),"UNMAPPED","ok"))
E22: =IF(A22="","",N(C22)-N(D22)) | H22: =IF(A22="","",IF(OR(F22="",G22=""),"UNMAPPED","ok"))
E23: =IF(A23="","",N(C23)-N(D23)) | H23: =IF(A23="","",IF(OR(F23="",G23=""),"UNMAPPED","ok"))
... E604: =IF(A604="","",N(C604)-N(D604)) | H604: =IF(A604="","",IF(OR(F604="",G604=""),"UNMAPPED","ok"))

Sheet Summary
A1: TB summary
A4: total debit | B4: =SUM(TrialBalance!C5:C604)
A5: total credit | B5: =SUM(TrialBalance!D5:D604)
A6: difference (must be 0) | B6: =B4-B5
A7: unmapped ledgers | B7: =COUNTIF(TrialBalance!H5:H604,"UNMAPPED")
