Workbook
Name cv_ebitda: 'Covenants'!$B$4
Name cv_int: 'Covenants'!$B$5
Name cv_prin: 'Covenants'!$B$6
Name cv_tax: 'Covenants'!$B$7
Name cv_ca: 'Covenants'!$B$8
Name cv_cl: 'Covenants'!$B$9
Name cv_tol: 'Covenants'!$B$10
Name cv_tnw: 'Covenants'!$B$11
Name cv_nd: 'Covenants'!$B$12
Name min_dscr: 'Covenants'!$B$17
Name min_cr: 'Covenants'!$B$18
Name max_toltnw: 'Covenants'!$B$19

Sheet README
A1: D15 · Risk & treasury management systems
A3: Domain D15: Risk & treasury management systems.
A4: Enterprise risk register with heat-map ratings and owners, bank covenant tests from model outputs, and FX exposure/hedge ratios.
A5: How to use
A6: Copy this workbook into companies/<slug>/domains/D15_risk-treasury/ before typing. Replace the SAMPLE rows (illustrative Tamil Nadu data) with company data.
A7: Type only into pale-yellow cells; white cells are formulas. Checks › OVERALL must be PASS before any value feeds K01/K02.
A8: Statutory rates are starting values - verify in 01_tamil-nadu/verification-register.md.
A9: Feeds
A10: K01 debt slots (CC/OD as loc, term loans) <= facility terms
A11: K02 stress (D27) <= risk links
A12: W07 covenant headroom <= Covenants

Sheet Checks
A1: Checks - OVERALL must be PASS before this domain feeds the kernel
B3: OVERALL | C3: =IF(COUNTIF(C5:C6,"PASS")=COUNT(A5:A6),"PASS","FAIL")
A4: # | B4: check | C4: result
A5: 1 | B5: likelihood and impact within 1..5 | C5: =IF(COUNTIF(RiskRegister!D5:E104,">5")+COUNTIF(RiskRegister!D5:E104,"<0")=0,"PASS","FAIL")
A6: 2 | B6: every HIGH risk has an owner and mitigation | C6: =IF(SUMPRODUCT((RiskRegister!G5:G104="HIGH")*((RiskRegister!H5:H104="")+(RiskRegister!I5:I104="")>0))=0,"PASS","FAIL")

Sheet RiskRegister
A1: Enterprise risk register (Companies Act s.134(3)(n); LODR Reg 21 for top-1000 listed)
A4: risk id | B4: risk | C4: category | D4: likelihood 1-5 | E4: impact 1-5 | F4: score | G4: rating | H4: owner | I4: mitigation | J4: K02 stress link (D27 scenario id)
A5: R01 | B5: Cyclone / flood shuts Chennai plant for 10 days | C5: Operational | D5: 3 | E5: 4 | F5: =IF(A5="","",D5*E5) | G5: =IF(F5="","",IF(F5>=15,"HIGH",IF(F5>=8,"MEDIUM","LOW"))) | H5: Plant head | I5: BI cover; dual sourcing | J5: CR-FLOOD
A6: R02 | B6: Large dealer default (Madurai cluster) | C6: Credit | D6: 2 | E6: 4 | F6: =IF(A6="","",D6*E6) | G6: =IF(F6="","",IF(F6>=15,"HIGH",IF(F6>=8,"MEDIUM","LOW"))) | H6: CFO | I6: credit limits; ECGC-style cover | J6: CR-DEBTOR
A7: R03 | B7: Cotton / steel input price spike | C7: Market | D7: 4 | E7: 3 | F7: =IF(A7="","",D7*E7) | G7: =IF(F7="","",IF(F7>=15,"HIGH",IF(F7>=8,"MEDIUM","LOW"))) | H7: Purchase head | I7: price escalation clauses
F8: =IF(A8="","",D8*E8) | G8: =IF(F8="","",IF(F8>=15,"HIGH",IF(F8>=8,"MEDIUM","LOW")))
F9: =IF(A9="","",D9*E9) | G9: =IF(F9="","",IF(F9>=15,"HIGH",IF(F9>=8,"MEDIUM","LOW")))
F10: =IF(A10="","",D10*E10) | G10: =IF(F10="","",IF(F10>=15,"HIGH",IF(F10>=8,"MEDIUM","LOW")))
F11: =IF(A11="","",D11*E11) | G11: =IF(F11="","",IF(F11>=15,"HIGH",IF(F11>=8,"MEDIUM","LOW")))
F12: =IF(A12="","",D12*E12) | G12: =IF(F12="","",IF(F12>=15,"HIGH",IF(F12>=8,"MEDIUM","LOW")))
F13: =IF(A13="","",D13*E13) | G13: =IF(F13="","",IF(F13>=15,"HIGH",IF(F13>=8,"MEDIUM","LOW")))
F14: =IF(A14="","",D14*E14) | G14: =IF(F14="","",IF(F14>=15,"HIGH",IF(F14>=8,"MEDIUM","LOW")))
F15: =IF(A15="","",D15*E15) | G15: =IF(F15="","",IF(F15>=15,"HIGH",IF(F15>=8,"MEDIUM","LOW")))
F16: =IF(A16="","",D16*E16) | G16: =IF(F16="","",IF(F16>=15,"HIGH",IF(F16>=8,"MEDIUM","LOW")))
F17: =IF(A17="","",D17*E17) | G17: =IF(F17="","",IF(F17>=15,"HIGH",IF(F17>=8,"MEDIUM","LOW")))
F18: =IF(A18="","",D18*E18) | G18: =IF(F18="","",IF(F18>=15,"HIGH",IF(F18>=8,"MEDIUM","LOW")))
F19: =IF(A19="","",D19*E19) | G19: =IF(F19="","",IF(F19>=15,"HIGH",IF(F19>=8,"MEDIUM","LOW")))
... F104: =IF(A104="","",D104*E104) | G104: =IF(F104="","",IF(F104>=15,"HIGH",IF(F104>=8,"MEDIUM","LOW")))

Sheet Covenants
A1: Bank covenant tests (enter from K01 Summary / balance sheet)
A4: EBITDA (TTM)
A5: interest (TTM)
A6: principal repaid (TTM)
A7: tax paid (TTM)
A8: current assets
A9: current liabilities
A10: total outside liabilities
A11: tangible net worth
A12: net debt
A13: DSCR = (EBITDA - tax) / (interest + principal) | B13: =IFERROR((Covenants!$B$4-Covenants!$B$7)/(Covenants!$B$5+Covenants!$B$6),"")
A14: current ratio | B14: =IFERROR(Covenants!$B$8/Covenants!$B$9,"")
A15: TOL / TNW | B15: =IFERROR(Covenants!$B$10/Covenants!$B$11,"")
A16: net debt / EBITDA | B16: =IFERROR(Covenants!$B$12/Covenants!$B$4,"")
A17: covenant: DSCR minimum | B17: 1.25
A18: covenant: current ratio minimum | B18: 1.33
A19: covenant: TOL/TNW maximum | B19: 3
A20: ALL COVENANTS MET? | B20: =IF(OR(B13="",B14="",B15=""),"enter inputs",IF(AND(B13>=Covenants!$B$17,B14>=Covenants!$B$18,B15<=Covenants!$B$19),"MET","BREACH - escalate"))

Sheet FXExposure
A1: FX exposure & hedge ratio
A4: exposure | B4: currency | C4: amount (FCY) | D4: due month | E4: hedged (FCY) | F4: hedge ratio
A5: Import of CNC spares | B5: USD | C5: 250000 | D5: 2026-12 | E5: 150000 | F5: =IF(OR(A5="",N(C5)=0),"",E5/C5)
F6: =IF(OR(A6="",N(C6)=0),"",E6/C6)
F7: =IF(OR(A7="",N(C7)=0),"",E7/C7)
F8: =IF(OR(A8="",N(C8)=0),"",E8/C8)
F9: =IF(OR(A9="",N(C9)=0),"",E9/C9)
F10: =IF(OR(A10="",N(C10)=0),"",E10/C10)
F11: =IF(OR(A11="",N(C11)=0),"",E11/C11)
F12: =IF(OR(A12="",N(C12)=0),"",E12/C12)
F13: =IF(OR(A13="",N(C13)=0),"",E13/C13)
F14: =IF(OR(A14="",N(C14)=0),"",E14/C14)
F15: =IF(OR(A15="",N(C15)=0),"",E15/C15)
F16: =IF(OR(A16="",N(C16)=0),"",E16/C16)
F17: =IF(OR(A17="",N(C17)=0),"",E17/C17)
... F44: =IF(OR(A44="",N(C44)=0),"",E44/C44)
