Workbook
Name msme_days: 'Setup'!$B$4
Name asof: 'Setup'!$B$5

Sheet README
A1: D12 (Kaveri copy)
A3: Kaveri Chairs domain record (illustrative sample rows).

Sheet Checks
A1: Checks - OVERALL must be PASS before this domain feeds the kernel
B3: OVERALL | C3: =IF(COUNTIF(C5:C5,"PASS")=COUNT(A5:A5),"PASS","FAIL")
A4: # | B4: check | C4: result
A5: 1 | B5: Udyam flag is y or n on every invoice | C5: =IF(SUMPRODUCT((Invoices!D5:D1004<>"")*(LOWER(Invoices!B5:B1004)<>"y")*(LOWER(Invoices!B5:B1004)<>"n"))=0,"PASS","FAIL")

Sheet Setup
A1: Setup
A4: MSME payment limit (days, MSMED Act s.15 / IT Act s.43B(h)) | B4: 45
A5: as-of date | B5: 46313

Sheet Invoices
A1: Supplier invoices (export from ERP / Tally purchase register)
A4: supplier | B4: Udyam registered (micro/small)? y/n | C4: category | D4: invoice no. | E4: acceptance date | F4: amount incl. GST | G4: paid date (blank = unpaid) | H4: days to pay / days outstanding | I4: MSME breach? | J4: 43B(h) exposure (unpaid MSME past limit at year end) | K4: paid amount (helper) | L4: paid days x amount (helper)
A5: Kovai Castings | B5: y | C5: Raw material | D5: KC/0921 | E5: 46244 | F5: 1450000 | H5: =IF(D5="","",IF(G5="",Setup!$B$5,G5)-E5) | I5: =IF(D5="","",AND(LOWER(B5)="y",H5>Setup!$B$4)) | J5: =IF(D5="","",IF(AND(I5=TRUE,G5=""),F5,0)) | K5: =IF(OR(D5="",G5=""),0,F5) | L5: =IF(OR(D5="",G5=""),0,H5*F5)
A6: Tiruppur Packaging | B6: y | C6: Packaging | D6: TP/553 | E6: 46266 | F6: 220000 | G6: 46290 | H6: =IF(D6="","",IF(G6="",Setup!$B$5,G6)-E6) | I6: =IF(D6="","",AND(LOWER(B6)="y",H6>Setup!$B$4)) | J6: =IF(D6="","",IF(AND(I6=TRUE,G6=""),F6,0)) | K6: =IF(OR(D6="",G6=""),0,F6) | L6: =IF(OR(D6="",G6=""),0,H6*F6)
A7: SKF India | B7: n | C7: Bearings | D7: SKF/88812 | E7: 46254 | F7: 980000 | G7: 46300 | H7: =IF(D7="","",IF(G7="",Setup!$B$5,G7)-E7) | I7: =IF(D7="","",AND(LOWER(B7)="y",H7>Setup!$B$4)) | J7: =IF(D7="","",IF(AND(I7=TRUE,G7=""),F7,0)) | K7: =IF(OR(D7="",G7=""),0,F7) | L7: =IF(OR(D7="",G7=""),0,H7*F7)
H8: =IF(D8="","",IF(G8="",Setup!$B$5,G8)-E8) | I8: =IF(D8="","",AND(LOWER(B8)="y",H8>Setup!$B$4)) | J8: =IF(D8="","",IF(AND(I8=TRUE,G8=""),F8,0)) | K8: =IF(OR(D8="",G8=""),0,F8) | L8: =IF(OR(D8="",G8=""),0,H8*F8)
H9: =IF(D9="","",IF(G9="",Setup!$B$5,G9)-E9) | I9: =IF(D9="","",AND(LOWER(B9)="y",H9>Setup!$B$4)) | J9: =IF(D9="","",IF(AND(I9=TRUE,G9=""),F9,0)) | K9: =IF(OR(D9="",G9=""),0,F9) | L9: =IF(OR(D9="",G9=""),0,H9*F9)
H10: =IF(D10="","",IF(G10="",Setup!$B$5,G10)-E10) | I10: =IF(D10="","",AND(LOWER(B10)="y",H10>Setup!$B$4)) | J10: =IF(D10="","",IF(AND(I10=TRUE,G10=""),F10,0)) | K10: =IF(OR(D10="",G10=""),0,F10) | L10: =IF(OR(D10="",G10=""),0,H10*F10)
H11: =IF(D11="","",IF(G11="",Setup!$B$5,G11)-E11) | I11: =IF(D11="","",AND(LOWER(B11)="y",H11>Setup!$B$4)) | J11: =IF(D11="","",IF(AND(I11=TRUE,G11=""),F11,0)) | K11: =IF(OR(D11="",G11=""),0,F11) | L11: =IF(OR(D11="",G11=""),0,H11*F11)
H12: =IF(D12="","",IF(G12="",Setup!$B$5,G12)-E12) | I12: =IF(D12="","",AND(LOWER(B12)="y",H12>Setup!$B$4)) | J12: =IF(D12="","",IF(AND(I12=TRUE,G12=""),F12,0)) | K12: =IF(OR(D12="",G12=""),0,F12) | L12: =IF(OR(D12="",G12=""),0,H12*F12)
H13: =IF(D13="","",IF(G13="",Setup!$B$5,G13)-E13) | I13: =IF(D13="","",AND(LOWER(B13)="y",H13>Setup!$B$4)) | J13: =IF(D13="","",IF(AND(I13=TRUE,G13=""),F13,0)) | K13: =IF(OR(D13="",G13=""),0,F13) | L13: =IF(OR(D13="",G13=""),0,H13*F13)
H14: =IF(D14="","",IF(G14="",Setup!$B$5,G14)-E14) | I14: =IF(D14="","",AND(LOWER(B14)="y",H14>Setup!$B$4)) | J14: =IF(D14="","",IF(AND(I14=TRUE,G14=""),F14,0)) | K14: =IF(OR(D14="",G14=""),0,F14) | L14: =IF(OR(D14="",G14=""),0,H14*F14)
H15: =IF(D15="","",IF(G15="",Setup!$B$5,G15)-E15) | I15: =IF(D15="","",AND(LOWER(B15)="y",H15>Setup!$B$4)) | J15: =IF(D15="","",IF(AND(I15=TRUE,G15=""),F15,0)) | K15: =IF(OR(D15="",G15=""),0,F15) | L15: =IF(OR(D15="",G15=""),0,H15*F15)
H16: =IF(D16="","",IF(G16="",Setup!$B$5,G16)-E16) | I16: =IF(D16="","",AND(LOWER(B16)="y",H16>Setup!$B$4)) | J16: =IF(D16="","",IF(AND(I16=TRUE,G16=""),F16,0)) | K16: =IF(OR(D16="",G16=""),0,F16) | L16: =IF(OR(D16="",G16=""),0,H16*F16)
H17: =IF(D17="","",IF(G17="",Setup!$B$5,G17)-E17) | I17: =IF(D17="","",AND(LOWER(B17)="y",H17>Setup!$B$4)) | J17: =IF(D17="","",IF(AND(I17=TRUE,G17=""),F17,0)) | K17: =IF(OR(D17="",G17=""),0,F17) | L17: =IF(OR(D17="",G17=""),0,H17*F17)
H18: =IF(D18="","",IF(G18="",Setup!$B$5,G18)-E18) | I18: =IF(D18="","",AND(LOWER(B18)="y",H18>Setup!$B$4)) | J18: =IF(D18="","",IF(AND(I18=TRUE,G18=""),F18,0)) | K18: =IF(OR(D18="",G18=""),0,F18) | L18: =IF(OR(D18="",G18=""),0,H18*F18)
H19: =IF(D19="","",IF(G19="",Setup!$B$5,G19)-E19) | I19: =IF(D19="","",AND(LOWER(B19)="y",H19>Setup!$B$4)) | J19: =IF(D19="","",IF(AND(I19=TRUE,G19=""),F19,0)) | K19: =IF(OR(D19="",G19=""),0,F19) | L19: =IF(OR(D19="",G19=""),0,H19*F19)
... H1004: =IF(D1004="","",IF(G1004="",Setup!$B$5,G1004)-E1004) | I1004: =IF(D1004="","",AND(LOWER(B1004)="y",H1004>Setup!$B$4)) | J1004: =IF(D1004="","",IF(AND(I1004=TRUE,G1004=""),F1004,0)) | K1004: =IF(OR(D1004="",G1004=""),0,F1004) | L1004: =IF(OR(D1004="",G1004=""),0,H1004*F1004)

Sheet Cube
A1: Spend cube by category
A4: category | B4: spend | C4: share
A5: Raw material | B5: =IF(A5="","",SUMIF(Invoices!$C$5:$C$1004,A5,Invoices!$F$5:$F$1004)) | C5: =IF(A5="","",IF(SUM(Invoices!$F$5:$F$1004)=0,0,B5/SUM(Invoices!$F$5:$F$1004)))
A6: Packaging | B6: =IF(A6="","",SUMIF(Invoices!$C$5:$C$1004,A6,Invoices!$F$5:$F$1004)) | C6: =IF(A6="","",IF(SUM(Invoices!$F$5:$F$1004)=0,0,B6/SUM(Invoices!$F$5:$F$1004)))
A7: Bearings | B7: =IF(A7="","",SUMIF(Invoices!$C$5:$C$1004,A7,Invoices!$F$5:$F$1004)) | C7: =IF(A7="","",IF(SUM(Invoices!$F$5:$F$1004)=0,0,B7/SUM(Invoices!$F$5:$F$1004)))
B8: =IF(A8="","",SUMIF(Invoices!$C$5:$C$1004,A8,Invoices!$F$5:$F$1004)) | C8: =IF(A8="","",IF(SUM(Invoices!$F$5:$F$1004)=0,0,B8/SUM(Invoices!$F$5:$F$1004)))
B9: =IF(A9="","",SUMIF(Invoices!$C$5:$C$1004,A9,Invoices!$F$5:$F$1004)) | C9: =IF(A9="","",IF(SUM(Invoices!$F$5:$F$1004)=0,0,B9/SUM(Invoices!$F$5:$F$1004)))
B10: =IF(A10="","",SUMIF(Invoices!$C$5:$C$1004,A10,Invoices!$F$5:$F$1004)) | C10: =IF(A10="","",IF(SUM(Invoices!$F$5:$F$1004)=0,0,B10/SUM(Invoices!$F$5:$F$1004)))
B11: =IF(A11="","",SUMIF(Invoices!$C$5:$C$1004,A11,Invoices!$F$5:$F$1004)) | C11: =IF(A11="","",IF(SUM(Invoices!$F$5:$F$1004)=0,0,B11/SUM(Invoices!$F$5:$F$1004)))
B12: =IF(A12="","",SUMIF(Invoices!$C$5:$C$1004,A12,Invoices!$F$5:$F$1004)) | C12: =IF(A12="","",IF(SUM(Invoices!$F$5:$F$1004)=0,0,B12/SUM(Invoices!$F$5:$F$1004)))
B13: =IF(A13="","",SUMIF(Invoices!$C$5:$C$1004,A13,Invoices!$F$5:$F$1004)) | C13: =IF(A13="","",IF(SUM(Invoices!$F$5:$F$1004)=0,0,B13/SUM(Invoices!$F$5:$F$1004)))
B14: =IF(A14="","",SUMIF(Invoices!$C$5:$C$1004,A14,Invoices!$F$5:$F$1004)) | C14: =IF(A14="","",IF(SUM(Invoices!$F$5:$F$1004)=0,0,B14/SUM(Invoices!$F$5:$F$1004)))
B15: =IF(A15="","",SUMIF(Invoices!$C$5:$C$1004,A15,Invoices!$F$5:$F$1004)) | C15: =IF(A15="","",IF(SUM(Invoices!$F$5:$F$1004)=0,0,B15/SUM(Invoices!$F$5:$F$1004)))
B16: =IF(A16="","",SUMIF(Invoices!$C$5:$C$1004,A16,Invoices!$F$5:$F$1004)) | C16: =IF(A16="","",IF(SUM(Invoices!$F$5:$F$1004)=0,0,B16/SUM(Invoices!$F$5:$F$1004)))
B17: =IF(A17="","",SUMIF(Invoices!$C$5:$C$1004,A17,Invoices!$F$5:$F$1004)) | C17: =IF(A17="","",IF(SUM(Invoices!$F$5:$F$1004)=0,0,B17/SUM(Invoices!$F$5:$F$1004)))
B18: =IF(A18="","",SUMIF(Invoices!$C$5:$C$1004,A18,Invoices!$F$5:$F$1004)) | C18: =IF(A18="","",IF(SUM(Invoices!$F$5:$F$1004)=0,0,B18/SUM(Invoices!$F$5:$F$1004)))
B19: =IF(A19="","",SUMIF(Invoices!$C$5:$C$1004,A19,Invoices!$F$5:$F$1004)) | C19: =IF(A19="","",IF(SUM(Invoices!$F$5:$F$1004)=0,0,B19/SUM(Invoices!$F$5:$F$1004)))
... B34: =IF(A34="","",SUMIF(Invoices!$C$5:$C$1004,A34,Invoices!$F$5:$F$1004)) | C34: =IF(A34="","",IF(SUM(Invoices!$F$5:$F$1004)=0,0,B34/SUM(Invoices!$F$5:$F$1004)))

Sheet ToKernel
A1: Feeds K01 working_capital.dpo_days and K02 supplier flows
A4: weighted average days to pay (paid invoices) -> DPO evidence | B4: =IF(SUM(Invoices!K5:K1004)=0,0,SUM(Invoices!L5:L1004)/SUM(Invoices!K5:K1004))
A5: MSME breaches | B5: =COUNTIF(Invoices!I5:I1004,TRUE)
A6: 43B(h) exposure (₹) | B6: =SUM(Invoices!J5:J1004)
