Workbook

Sheet README
A1: Monthly MIS in ₹ lakh (presentation template)
A3: Paste K01 › Export_Rows VALUES into 'Paste_K01' (and optional budget values into 'Paste_Budget' in the same layout).
A4: 'MIS_lakh' shows the month-by-month MIS in ₹ lakh (÷ 1,00,000, 2 decimals) with Indian FY totals; 'Checks' proves the lakh view ties to the pasted rupees.
A5: No formulas reference other files; nothing refreshes automatically.

Sheet Checks
A1: Checks
B3: OVERALL | C3: =IF(COUNTIF(C5:C6,"PASS")=COUNT(A5:A6),"PASS","FAIL")
A4: # | B4: check | C4: result
A5: 1 | B5: lakh revenue total ties to pasted rupees (within rounding) | C5: =IF(ABS(MIS_lakh!N5*100000-SUM(Paste_K01!E5:E16))<=12*500,"PASS","FAIL")
A6: 2 | B6: period labels present when data pasted | C6: =IF(OR(COUNT(Paste_K01!E5:E16)=0,COUNTA(Paste_K01!B5:B16)>0),"PASS","FAIL")

Sheet Paste_K01
A1: Paste_K01 - paste values with this header (row 4)
A4: month_no | B4: period | C4: indian_fiscal_year | D4: fiscal_quarter | E4: revenue | F4: cogs | G4: gross_profit | H4: opex | I4: ebitda | J4: da | K4: interest | L4: pretax_income | M4: tax | N4: net_income | O4: wc_cash_impact | P4: operating_cash_flow | Q4: capex | R4: principal | S4: free_cash_flow | T4: change_in_cash | U4: ending_cash

Sheet Paste_Budget
A1: Paste_Budget - paste values with this header (row 4)
A4: month_no | B4: period | C4: indian_fiscal_year | D4: fiscal_quarter | E4: revenue | F4: cogs | G4: gross_profit | H4: opex | I4: ebitda | J4: da | K4: interest | L4: pretax_income | M4: tax | N4: net_income | O4: wc_cash_impact | P4: operating_cash_flow | Q4: capex | R4: principal | S4: free_cash_flow | T4: change_in_cash | U4: ending_cash

Sheet MIS_lakh
A1: MIS (₹ lakh)
A2: Actual/forecast vs budget
A4: line | B4: =IF(Paste_K01!B5="","M1",Paste_K01!B5) | C4: =IF(Paste_K01!B6="","M2",Paste_K01!B6) | D4: =IF(Paste_K01!B7="","M3",Paste_K01!B7) | E4: =IF(Paste_K01!B8="","M4",Paste_K01!B8) | F4: =IF(Paste_K01!B9="","M5",Paste_K01!B9) | G4: =IF(Paste_K01!B10="","M6",Paste_K01!B10) | H4: =IF(Paste_K01!B11="","M7",Paste_K01!B11) | I4: =IF(Paste_K01!B12="","M8",Paste_K01!B12) | J4: =IF(Paste_K01!B13="","M9",Paste_K01!B13) | K4: =IF(Paste_K01!B14="","M10",Paste_K01!B14) | L4: =IF(Paste_K01!B15="","M11",Paste_K01!B15) | M4: =IF(Paste_K01!B16="","M12",Paste_K01!B16) | N4: 12-month total (ending cash: last) | O4: budget (12 m) | P4: variance | Q4: variance %
A5: revenue | B5: =IF(Paste_K01!E5="","",ROUND(Paste_K01!E5/100000,2)) | C5: =IF(Paste_K01!E6="","",ROUND(Paste_K01!E6/100000,2)) | D5: =IF(Paste_K01!E7="","",ROUND(Paste_K01!E7/100000,2)) | E5: =IF(Paste_K01!E8="","",ROUND(Paste_K01!E8/100000,2)) | F5: =IF(Paste_K01!E9="","",ROUND(Paste_K01!E9/100000,2)) | G5: =IF(Paste_K01!E10="","",ROUND(Paste_K01!E10/100000,2)) | H5: =IF(Paste_K01!E11="","",ROUND(Paste_K01!E11/100000,2)) | I5: =IF(Paste_K01!E12="","",ROUND(Paste_K01!E12/100000,2)) | J5: =IF(Paste_K01!E13="","",ROUND(Paste_K01!E13/100000,2)) | K5: =IF(Paste_K01!E14="","",ROUND(Paste_K01!E14/100000,2)) | L5: =IF(Paste_K01!E15="","",ROUND(Paste_K01!E15/100000,2)) | M5: =IF(Paste_K01!E16="","",ROUND(Paste_K01!E16/100000,2)) | N5: =ROUND(SUM(Paste_K01!E5:E16)/100000,2) | O5: =IF(COUNT(Paste_Budget!E5:E16)=0,"",ROUND(SUM(Paste_Budget!E5:E16)/100000,2)) | P5: =IF(OR(N5="",O5=""),"",N5-O5) | Q5: =IF(OR(P5="",N(O5)=0),"",P5/ABS(O5))
A6: gross_profit | B6: =IF(Paste_K01!G5="","",ROUND(Paste_K01!G5/100000,2)) | C6: =IF(Paste_K01!G6="","",ROUND(Paste_K01!G6/100000,2)) | D6: =IF(Paste_K01!G7="","",ROUND(Paste_K01!G7/100000,2)) | E6: =IF(Paste_K01!G8="","",ROUND(Paste_K01!G8/100000,2)) | F6: =IF(Paste_K01!G9="","",ROUND(Paste_K01!G9/100000,2)) | G6: =IF(Paste_K01!G10="","",ROUND(Paste_K01!G10/100000,2)) | H6: =IF(Paste_K01!G11="","",ROUND(Paste_K01!G11/100000,2)) | I6: =IF(Paste_K01!G12="","",ROUND(Paste_K01!G12/100000,2)) | J6: =IF(Paste_K01!G13="","",ROUND(Paste_K01!G13/100000,2)) | K6: =IF(Paste_K01!G14="","",ROUND(Paste_K01!G14/100000,2)) | L6: =IF(Paste_K01!G15="","",ROUND(Paste_K01!G15/100000,2)) | M6: =IF(Paste_K01!G16="","",ROUND(Paste_K01!G16/100000,2)) | N6: =ROUND(SUM(Paste_K01!G5:G16)/100000,2) | O6: =IF(COUNT(Paste_Budget!G5:G16)=0,"",ROUND(SUM(Paste_Budget!G5:G16)/100000,2)) | P6: =IF(OR(N6="",O6=""),"",N6-O6) | Q6: =IF(OR(P6="",N(O6)=0),"",P6/ABS(O6))
A7: ebitda | B7: =IF(Paste_K01!I5="","",ROUND(Paste_K01!I5/100000,2)) | C7: =IF(Paste_K01!I6="","",ROUND(Paste_K01!I6/100000,2)) | D7: =IF(Paste_K01!I7="","",ROUND(Paste_K01!I7/100000,2)) | E7: =IF(Paste_K01!I8="","",ROUND(Paste_K01!I8/100000,2)) | F7: =IF(Paste_K01!I9="","",ROUND(Paste_K01!I9/100000,2)) | G7: =IF(Paste_K01!I10="","",ROUND(Paste_K01!I10/100000,2)) | H7: =IF(Paste_K01!I11="","",ROUND(Paste_K01!I11/100000,2)) | I7: =IF(Paste_K01!I12="","",ROUND(Paste_K01!I12/100000,2)) | J7: =IF(Paste_K01!I13="","",ROUND(Paste_K01!I13/100000,2)) | K7: =IF(Paste_K01!I14="","",ROUND(Paste_K01!I14/100000,2)) | L7: =IF(Paste_K01!I15="","",ROUND(Paste_K01!I15/100000,2)) | M7: =IF(Paste_K01!I16="","",ROUND(Paste_K01!I16/100000,2)) | N7: =ROUND(SUM(Paste_K01!I5:I16)/100000,2) | O7: =IF(COUNT(Paste_Budget!I5:I16)=0,"",ROUND(SUM(Paste_Budget!I5:I16)/100000,2)) | P7: =IF(OR(N7="",O7=""),"",N7-O7) | Q7: =IF(OR(P7="",N(O7)=0),"",P7/ABS(O7))
A8: net_income | B8: =IF(Paste_K01!N5="","",ROUND(Paste_K01!N5/100000,2)) | C8: =IF(Paste_K01!N6="","",ROUND(Paste_K01!N6/100000,2)) | D8: =IF(Paste_K01!N7="","",ROUND(Paste_K01!N7/100000,2)) | E8: =IF(Paste_K01!N8="","",ROUND(Paste_K01!N8/100000,2)) | F8: =IF(Paste_K01!N9="","",ROUND(Paste_K01!N9/100000,2)) | G8: =IF(Paste_K01!N10="","",ROUND(Paste_K01!N10/100000,2)) | H8: =IF(Paste_K01!N11="","",ROUND(Paste_K01!N11/100000,2)) | I8: =IF(Paste_K01!N12="","",ROUND(Paste_K01!N12/100000,2)) | J8: =IF(Paste_K01!N13="","",ROUND(Paste_K01!N13/100000,2)) | K8: =IF(Paste_K01!N14="","",ROUND(Paste_K01!N14/100000,2)) | L8: =IF(Paste_K01!N15="","",ROUND(Paste_K01!N15/100000,2)) | M8: =IF(Paste_K01!N16="","",ROUND(Paste_K01!N16/100000,2)) | N8: =ROUND(SUM(Paste_K01!N5:N16)/100000,2) | O8: =IF(COUNT(Paste_Budget!N5:N16)=0,"",ROUND(SUM(Paste_Budget!N5:N16)/100000,2)) | P8: =IF(OR(N8="",O8=""),"",N8-O8) | Q8: =IF(OR(P8="",N(O8)=0),"",P8/ABS(O8))
A9: free_cash_flow | B9: =IF(Paste_K01!S5="","",ROUND(Paste_K01!S5/100000,2)) | C9: =IF(Paste_K01!S6="","",ROUND(Paste_K01!S6/100000,2)) | D9: =IF(Paste_K01!S7="","",ROUND(Paste_K01!S7/100000,2)) | E9: =IF(Paste_K01!S8="","",ROUND(Paste_K01!S8/100000,2)) | F9: =IF(Paste_K01!S9="","",ROUND(Paste_K01!S9/100000,2)) | G9: =IF(Paste_K01!S10="","",ROUND(Paste_K01!S10/100000,2)) | H9: =IF(Paste_K01!S11="","",ROUND(Paste_K01!S11/100000,2)) | I9: =IF(Paste_K01!S12="","",ROUND(Paste_K01!S12/100000,2)) | J9: =IF(Paste_K01!S13="","",ROUND(Paste_K01!S13/100000,2)) | K9: =IF(Paste_K01!S14="","",ROUND(Paste_K01!S14/100000,2)) | L9: =IF(Paste_K01!S15="","",ROUND(Paste_K01!S15/100000,2)) | M9: =IF(Paste_K01!S16="","",ROUND(Paste_K01!S16/100000,2)) | N9: =ROUND(SUM(Paste_K01!S5:S16)/100000,2) | O9: =IF(COUNT(Paste_Budget!S5:S16)=0,"",ROUND(SUM(Paste_Budget!S5:S16)/100000,2)) | P9: =IF(OR(N9="",O9=""),"",N9-O9) | Q9: =IF(OR(P9="",N(O9)=0),"",P9/ABS(O9))
A10: ending_cash | B10: =IF(Paste_K01!U5="","",ROUND(Paste_K01!U5/100000,2)) | C10: =IF(Paste_K01!U6="","",ROUND(Paste_K01!U6/100000,2)) | D10: =IF(Paste_K01!U7="","",ROUND(Paste_K01!U7/100000,2)) | E10: =IF(Paste_K01!U8="","",ROUND(Paste_K01!U8/100000,2)) | F10: =IF(Paste_K01!U9="","",ROUND(Paste_K01!U9/100000,2)) | G10: =IF(Paste_K01!U10="","",ROUND(Paste_K01!U10/100000,2)) | H10: =IF(Paste_K01!U11="","",ROUND(Paste_K01!U11/100000,2)) | I10: =IF(Paste_K01!U12="","",ROUND(Paste_K01!U12/100000,2)) | J10: =IF(Paste_K01!U13="","",ROUND(Paste_K01!U13/100000,2)) | K10: =IF(Paste_K01!U14="","",ROUND(Paste_K01!U14/100000,2)) | L10: =IF(Paste_K01!U15="","",ROUND(Paste_K01!U15/100000,2)) | M10: =IF(Paste_K01!U16="","",ROUND(Paste_K01!U16/100000,2)) | N10: =IF(COUNT(B10:M10)=0,"",INDEX(B10:M10,1,COUNT(B10:M10))) | O10: =IF(COUNT(Paste_Budget!U5:U16)=0,"",ROUND(INDEX(Paste_Budget!U5:U16,COUNT(Paste_Budget!U5:U16),1)/100000,2)) | P10: =IF(OR(N10="",O10=""),"",N10-O10) | Q10: =IF(OR(P10="",N(O10)=0),"",P10/ABS(O10))
