Workbook
Name g_disc: 'Assumptions'!$B$4
Name g_esc: 'Assumptions'!$B$5
Name g_wd: 'Assumptions'!$B$6
Name g_mort: 'Assumptions'!$B$7
Name g_ret: 'Assumptions'!$B$8
Name g_cap: 'Assumptions'!$B$9
Name g_vest: 'Assumptions'!$B$10

Sheet README
A1: D16 · Actuarial & insurance / risk modelling engines
A3: Domain D16: Actuarial & insurance / risk modelling engines.
A4: Simplified projected-unit-credit gratuity liability, insurance programme register, and catastrophe business-interruption loss estimate.
A5: How to use
A6: Copy this workbook into companies/<slug>/domains/D16_actuarial-insurance-risk/ before typing. Replace the SAMPLE rows (illustrative Tamil Nadu data) with company data.
A7: Type only into pale-yellow cells; white cells are formulas. Checks › OVERALL must be PASS before any value feeds K01/K02.
A8: Statutory rates are starting values - verify in 01_tamil-nadu/verification-register.md.
A9: Feeds
A10: K01 opex payroll benefits <= service cost
A11: K02 gratuity payouts on exit <= Employees
A12: D27 crisis scenarios <= BI loss

Sheet Checks
A1: Checks - OVERALL must be PASS before this domain feeds the kernel
B3: OVERALL | C3: =IF(COUNTIF(C5:C6,"PASS")=COUNT(A5:A6),"PASS","FAIL")
A4: # | B4: check | C4: result
A5: 1 | B5: discount rate positive | C5: =IF(Assumptions!$B$4>0,"PASS","FAIL")
A6: 2 | B6: ages below retirement | C6: =IF(SUMPRODUCT((Employees!A5:A504<>"")*(Employees!B5:B504>=Assumptions!$B$8))=0,"PASS","FAIL")

Sheet Assumptions
A1: Gratuity (Payment of Gratuity Act) - simplified projected-unit-credit; replace with the actuary's Ind AS 19 report when available
A4: discount rate (G-sec yield matching duration) | B4: 0.07
A5: salary escalation | B5: 0.07
A6: annual withdrawal (attrition) rate | B6: 0.08
A7: annual mortality (IALM 2012-14 average proxy) | B7: 0.001
A8: retirement age | B8: 58
A9: gratuity ceiling (₹) | B9: 2000000
A10: minimum service for vesting (years) | B10: 5

Sheet Employees
A1: Employee data (from D04 / payroll)
A4: employee id | B4: age | C4: past service (years) | D4: monthly basic + DA | E4: years to retirement | F4: projected salary at exit | G4: accrued benefit at exit (15/26 x salary x past service, capped) | H4: survival to retirement | I4: PV of accrued benefit (DBO proxy) | J4: current-service vested?
A5: E001 | B5: 34 | C5: 6 | D5: 14000 | E5: =IF(A5="","",MAX(0,Assumptions!$B$8-B5)) | F5: =IF(A5="","",D5*(1+Assumptions!$B$5)^E5) | G5: =IF(A5="","",MIN(Assumptions!$B$9,15/26*F5*C5)) | H5: =IF(A5="","",(1-Assumptions!$B$6-Assumptions!$B$7)^E5) | I5: =IF(A5="","",G5*H5/(1+Assumptions!$B$4)^E5) | J5: =IF(A5="","",C5>=Assumptions!$B$10)
A6: E002 | B6: 47 | C6: 12 | D6: 34000 | E6: =IF(A6="","",MAX(0,Assumptions!$B$8-B6)) | F6: =IF(A6="","",D6*(1+Assumptions!$B$5)^E6) | G6: =IF(A6="","",MIN(Assumptions!$B$9,15/26*F6*C6)) | H6: =IF(A6="","",(1-Assumptions!$B$6-Assumptions!$B$7)^E6) | I6: =IF(A6="","",G6*H6/(1+Assumptions!$B$4)^E6) | J6: =IF(A6="","",C6>=Assumptions!$B$10)
A7: E003 | B7: 29 | C7: 2 | D7: 18000 | E7: =IF(A7="","",MAX(0,Assumptions!$B$8-B7)) | F7: =IF(A7="","",D7*(1+Assumptions!$B$5)^E7) | G7: =IF(A7="","",MIN(Assumptions!$B$9,15/26*F7*C7)) | H7: =IF(A7="","",(1-Assumptions!$B$6-Assumptions!$B$7)^E7) | I7: =IF(A7="","",G7*H7/(1+Assumptions!$B$4)^E7) | J7: =IF(A7="","",C7>=Assumptions!$B$10)
E8: =IF(A8="","",MAX(0,Assumptions!$B$8-B8)) | F8: =IF(A8="","",D8*(1+Assumptions!$B$5)^E8) | G8: =IF(A8="","",MIN(Assumptions!$B$9,15/26*F8*C8)) | H8: =IF(A8="","",(1-Assumptions!$B$6-Assumptions!$B$7)^E8) | I8: =IF(A8="","",G8*H8/(1+Assumptions!$B$4)^E8) | J8: =IF(A8="","",C8>=Assumptions!$B$10)
E9: =IF(A9="","",MAX(0,Assumptions!$B$8-B9)) | F9: =IF(A9="","",D9*(1+Assumptions!$B$5)^E9) | G9: =IF(A9="","",MIN(Assumptions!$B$9,15/26*F9*C9)) | H9: =IF(A9="","",(1-Assumptions!$B$6-Assumptions!$B$7)^E9) | I9: =IF(A9="","",G9*H9/(1+Assumptions!$B$4)^E9) | J9: =IF(A9="","",C9>=Assumptions!$B$10)
E10: =IF(A10="","",MAX(0,Assumptions!$B$8-B10)) | F10: =IF(A10="","",D10*(1+Assumptions!$B$5)^E10) | G10: =IF(A10="","",MIN(Assumptions!$B$9,15/26*F10*C10)) | H10: =IF(A10="","",(1-Assumptions!$B$6-Assumptions!$B$7)^E10) | I10: =IF(A10="","",G10*H10/(1+Assumptions!$B$4)^E10) | J10: =IF(A10="","",C10>=Assumptions!$B$10)
E11: =IF(A11="","",MAX(0,Assumptions!$B$8-B11)) | F11: =IF(A11="","",D11*(1+Assumptions!$B$5)^E11) | G11: =IF(A11="","",MIN(Assumptions!$B$9,15/26*F11*C11)) | H11: =IF(A11="","",(1-Assumptions!$B$6-Assumptions!$B$7)^E11) | I11: =IF(A11="","",G11*H11/(1+Assumptions!$B$4)^E11) | J11: =IF(A11="","",C11>=Assumptions!$B$10)
E12: =IF(A12="","",MAX(0,Assumptions!$B$8-B12)) | F12: =IF(A12="","",D12*(1+Assumptions!$B$5)^E12) | G12: =IF(A12="","",MIN(Assumptions!$B$9,15/26*F12*C12)) | H12: =IF(A12="","",(1-Assumptions!$B$6-Assumptions!$B$7)^E12) | I12: =IF(A12="","",G12*H12/(1+Assumptions!$B$4)^E12) | J12: =IF(A12="","",C12>=Assumptions!$B$10)
E13: =IF(A13="","",MAX(0,Assumptions!$B$8-B13)) | F13: =IF(A13="","",D13*(1+Assumptions!$B$5)^E13) | G13: =IF(A13="","",MIN(Assumptions!$B$9,15/26*F13*C13)) | H13: =IF(A13="","",(1-Assumptions!$B$6-Assumptions!$B$7)^E13) | I13: =IF(A13="","",G13*H13/(1+Assumptions!$B$4)^E13) | J13: =IF(A13="","",C13>=Assumptions!$B$10)
E14: =IF(A14="","",MAX(0,Assumptions!$B$8-B14)) | F14: =IF(A14="","",D14*(1+Assumptions!$B$5)^E14) | G14: =IF(A14="","",MIN(Assumptions!$B$9,15/26*F14*C14)) | H14: =IF(A14="","",(1-Assumptions!$B$6-Assumptions!$B$7)^E14) | I14: =IF(A14="","",G14*H14/(1+Assumptions!$B$4)^E14) | J14: =IF(A14="","",C14>=Assumptions!$B$10)
E15: =IF(A15="","",MAX(0,Assumptions!$B$8-B15)) | F15: =IF(A15="","",D15*(1+Assumptions!$B$5)^E15) | G15: =IF(A15="","",MIN(Assumptions!$B$9,15/26*F15*C15)) | H15: =IF(A15="","",(1-Assumptions!$B$6-Assumptions!$B$7)^E15) | I15: =IF(A15="","",G15*H15/(1+Assumptions!$B$4)^E15) | J15: =IF(A15="","",C15>=Assumptions!$B$10)
E16: =IF(A16="","",MAX(0,Assumptions!$B$8-B16)) | F16: =IF(A16="","",D16*(1+Assumptions!$B$5)^E16) | G16: =IF(A16="","",MIN(Assumptions!$B$9,15/26*F16*C16)) | H16: =IF(A16="","",(1-Assumptions!$B$6-Assumptions!$B$7)^E16) | I16: =IF(A16="","",G16*H16/(1+Assumptions!$B$4)^E16) | J16: =IF(A16="","",C16>=Assumptions!$B$10)
E17: =IF(A17="","",MAX(0,Assumptions!$B$8-B17)) | F17: =IF(A17="","",D17*(1+Assumptions!$B$5)^E17) | G17: =IF(A17="","",MIN(Assumptions!$B$9,15/26*F17*C17)) | H17: =IF(A17="","",(1-Assumptions!$B$6-Assumptions!$B$7)^E17) | I17: =IF(A17="","",G17*H17/(1+Assumptions!$B$4)^E17) | J17: =IF(A17="","",C17>=Assumptions!$B$10)
E18: =IF(A18="","",MAX(0,Assumptions!$B$8-B18)) | F18: =IF(A18="","",D18*(1+Assumptions!$B$5)^E18) | G18: =IF(A18="","",MIN(Assumptions!$B$9,15/26*F18*C18)) | H18: =IF(A18="","",(1-Assumptions!$B$6-Assumptions!$B$7)^E18) | I18: =IF(A18="","",G18*H18/(1+Assumptions!$B$4)^E18) | J18: =IF(A18="","",C18>=Assumptions!$B$10)
E19: =IF(A19="","",MAX(0,Assumptions!$B$8-B19)) | F19: =IF(A19="","",D19*(1+Assumptions!$B$5)^E19) | G19: =IF(A19="","",MIN(Assumptions!$B$9,15/26*F19*C19)) | H19: =IF(A19="","",(1-Assumptions!$B$6-Assumptions!$B$7)^E19) | I19: =IF(A19="","",G19*H19/(1+Assumptions!$B$4)^E19) | J19: =IF(A19="","",C19>=Assumptions!$B$10)
... E504: =IF(A504="","",MAX(0,Assumptions!$B$8-B504)) | F504: =IF(A504="","",D504*(1+Assumptions!$B$5)^E504) | G504: =IF(A504="","",MIN(Assumptions!$B$9,15/26*F504*C504)) | H504: =IF(A504="","",(1-Assumptions!$B$6-Assumptions!$B$7)^E504) | I504: =IF(A504="","",G504*H504/(1+Assumptions!$B$4)^E504) | J504: =IF(A504="","",C504>=Assumptions!$B$10)

Sheet Results
A1: Results
A4: DBO proxy (sum of PV) | B4: =SUM(Employees!I5:I504)
A5: note | B5: Book via K01 opex (payroll benefits) as annual service cost; gratuity paid in cash only on exit (K02).

Sheet Insurance
A1: Insurance programme & catastrophe BI scenario (Chennai floods 2015, Cyclone Michaung 2023 are reference events)
A4: policy | B4: insurer | C4: sum insured | D4: premium | E4: renewal date | F4: days of interruption (scenario) | G4: daily gross profit at risk | H4: indemnity period days | I4: deductible days | J4: insured BI loss | K4: uninsured BI loss
A5: Fire & special perils + BI | B5: New India Assurance | C5: 450000000 | D5: 1250000 | E5: 46477 | F5: 10 | G5: 1100000 | H5: 90 | I5: 3 | J5: =IF(A5="","",MAX(0,MIN(F5,N(H5))-N(I5))*N(G5)) | K5: =IF(A5="","",N(F5)*N(G5)-J5)
J6: =IF(A6="","",MAX(0,MIN(F6,N(H6))-N(I6))*N(G6)) | K6: =IF(A6="","",N(F6)*N(G6)-J6)
J7: =IF(A7="","",MAX(0,MIN(F7,N(H7))-N(I7))*N(G7)) | K7: =IF(A7="","",N(F7)*N(G7)-J7)
J8: =IF(A8="","",MAX(0,MIN(F8,N(H8))-N(I8))*N(G8)) | K8: =IF(A8="","",N(F8)*N(G8)-J8)
J9: =IF(A9="","",MAX(0,MIN(F9,N(H9))-N(I9))*N(G9)) | K9: =IF(A9="","",N(F9)*N(G9)-J9)
J10: =IF(A10="","",MAX(0,MIN(F10,N(H10))-N(I10))*N(G10)) | K10: =IF(A10="","",N(F10)*N(G10)-J10)
J11: =IF(A11="","",MAX(0,MIN(F11,N(H11))-N(I11))*N(G11)) | K11: =IF(A11="","",N(F11)*N(G11)-J11)
J12: =IF(A12="","",MAX(0,MIN(F12,N(H12))-N(I12))*N(G12)) | K12: =IF(A12="","",N(F12)*N(G12)-J12)
J13: =IF(A13="","",MAX(0,MIN(F13,N(H13))-N(I13))*N(G13)) | K13: =IF(A13="","",N(F13)*N(G13)-J13)
J14: =IF(A14="","",MAX(0,MIN(F14,N(H14))-N(I14))*N(G14)) | K14: =IF(A14="","",N(F14)*N(G14)-J14)
J15: =IF(A15="","",MAX(0,MIN(F15,N(H15))-N(I15))*N(G15)) | K15: =IF(A15="","",N(F15)*N(G15)-J15)
J16: =IF(A16="","",MAX(0,MIN(F16,N(H16))-N(I16))*N(G16)) | K16: =IF(A16="","",N(F16)*N(G16)-J16)
J17: =IF(A17="","",MAX(0,MIN(F17,N(H17))-N(I17))*N(G17)) | K17: =IF(A17="","",N(F17)*N(G17)-J17)
... J44: =IF(A44="","",MAX(0,MIN(F44,N(H44))-N(I44))*N(G44)) | K44: =IF(A44="","",N(F44)*N(G44)-J44)
