Workbook
Name icm_thr: 'Plan'!$B$4
Name icm_thr_pay: 'Plan'!$B$5
Name icm_acc: 'Plan'!$B$6
Name icm_cap: 'Plan'!$B$7

Sheet README
A1: D06 · Incentive compensation management & sales performance management
A3: Domain D06: Incentive compensation management & sales performance management.
A4: Compute rep/dealer incentive payouts on a threshold–target–accelerator–cap curve and convert them into a variable opex rate and payout cash weeks.
A5: How to use
A6: Copy this workbook into companies/<slug>/domains/D06_incentive-comp-sales-performance/ before typing. Replace the SAMPLE rows (illustrative Tamil Nadu data) with company data.
A7: Type only into pale-yellow cells; white cells are formulas. Checks › OVERALL must be PASS before any value feeds K01/K02.
A8: Statutory rates are starting values - verify in 01_tamil-nadu/verification-register.md.
A9: Feeds
A10: K01 opex variable 'Sales incentives' pct_of_revenue <= ToKernel B6
A11: K02 quarterly payout flows <= Plan cadence

Sheet Checks
A1: Checks - OVERALL must be PASS before this domain feeds the kernel
B3: OVERALL | C3: =IF(COUNTIF(C5:C6,"PASS")=COUNT(A5:A6),"PASS","FAIL")
A4: # | B4: check | C4: result
A5: 1 | B5: payout never exceeds cap x target | C5: =IF(COUNTIF(Reps!I5:I204,TRUE)=0,"PASS","FAIL")
A6: 2 | B6: threshold below 100% | C6: =IF(Plan!$B$4<1,"PASS","FAIL")

Sheet Plan
A1: Incentive plan design (one plan per workbook copy)
A4: threshold attainment (no payout below) | B4: 0.8
A5: payout at threshold (% of target incentive) | B5: 0.5
A6: accelerator multiple above 100% | B6: 1.5
A7: cap (% of target incentive) | B7: 2
A8: payout cadence (quarterly / monthly) | B8: quarterly
A9: tax: incentives are salary - TDS u/s 192 at payout; employer PF only if part of basic | B9: note

Sheet Reps
A1: Reps / dealers - attainment and payout
A4: rep / dealer | B4: territory (TN district) | C4: quota | D4: actual (booked & invoiced) | E4: target incentive | F4: attainment | G4: payout % of target | H4: payout | I4: over cap?
A5: R-Madurai-01 | B5: Madurai | C5: 24000000 | D5: 26500000 | E5: 300000 | F5: =IF(OR(A5="",N(C5)=0),"",D5/C5) | G5: =IF(F5="","",IF(F5<Plan!$B$4,0,IF(F5<=1,Plan!$B$5+(1-Plan!$B$5)*(F5-Plan!$B$4)/(1-Plan!$B$4),MIN(Plan!$B$7,1+Plan!$B$6*(F5-1))))) | H5: =IF(G5="","",G5*E5) | I5: =IF(H5="","",H5>Plan!$B$7*E5+0.01)
A6: R-Salem-02 | B6: Salem | C6: 18000000 | D6: 14000000 | E6: 240000 | F6: =IF(OR(A6="",N(C6)=0),"",D6/C6) | G6: =IF(F6="","",IF(F6<Plan!$B$4,0,IF(F6<=1,Plan!$B$5+(1-Plan!$B$5)*(F6-Plan!$B$4)/(1-Plan!$B$4),MIN(Plan!$B$7,1+Plan!$B$6*(F6-1))))) | H6: =IF(G6="","",G6*E6) | I6: =IF(H6="","",H6>Plan!$B$7*E6+0.01)
A7: D-Tiruppur-07 | B7: Tiruppur | C7: 30000000 | D7: 31000000 | E7: 360000 | F7: =IF(OR(A7="",N(C7)=0),"",D7/C7) | G7: =IF(F7="","",IF(F7<Plan!$B$4,0,IF(F7<=1,Plan!$B$5+(1-Plan!$B$5)*(F7-Plan!$B$4)/(1-Plan!$B$4),MIN(Plan!$B$7,1+Plan!$B$6*(F7-1))))) | H7: =IF(G7="","",G7*E7) | I7: =IF(H7="","",H7>Plan!$B$7*E7+0.01)
F8: =IF(OR(A8="",N(C8)=0),"",D8/C8) | G8: =IF(F8="","",IF(F8<Plan!$B$4,0,IF(F8<=1,Plan!$B$5+(1-Plan!$B$5)*(F8-Plan!$B$4)/(1-Plan!$B$4),MIN(Plan!$B$7,1+Plan!$B$6*(F8-1))))) | H8: =IF(G8="","",G8*E8) | I8: =IF(H8="","",H8>Plan!$B$7*E8+0.01)
F9: =IF(OR(A9="",N(C9)=0),"",D9/C9) | G9: =IF(F9="","",IF(F9<Plan!$B$4,0,IF(F9<=1,Plan!$B$5+(1-Plan!$B$5)*(F9-Plan!$B$4)/(1-Plan!$B$4),MIN(Plan!$B$7,1+Plan!$B$6*(F9-1))))) | H9: =IF(G9="","",G9*E9) | I9: =IF(H9="","",H9>Plan!$B$7*E9+0.01)
F10: =IF(OR(A10="",N(C10)=0),"",D10/C10) | G10: =IF(F10="","",IF(F10<Plan!$B$4,0,IF(F10<=1,Plan!$B$5+(1-Plan!$B$5)*(F10-Plan!$B$4)/(1-Plan!$B$4),MIN(Plan!$B$7,1+Plan!$B$6*(F10-1))))) | H10: =IF(G10="","",G10*E10) | I10: =IF(H10="","",H10>Plan!$B$7*E10+0.01)
F11: =IF(OR(A11="",N(C11)=0),"",D11/C11) | G11: =IF(F11="","",IF(F11<Plan!$B$4,0,IF(F11<=1,Plan!$B$5+(1-Plan!$B$5)*(F11-Plan!$B$4)/(1-Plan!$B$4),MIN(Plan!$B$7,1+Plan!$B$6*(F11-1))))) | H11: =IF(G11="","",G11*E11) | I11: =IF(H11="","",H11>Plan!$B$7*E11+0.01)
F12: =IF(OR(A12="",N(C12)=0),"",D12/C12) | G12: =IF(F12="","",IF(F12<Plan!$B$4,0,IF(F12<=1,Plan!$B$5+(1-Plan!$B$5)*(F12-Plan!$B$4)/(1-Plan!$B$4),MIN(Plan!$B$7,1+Plan!$B$6*(F12-1))))) | H12: =IF(G12="","",G12*E12) | I12: =IF(H12="","",H12>Plan!$B$7*E12+0.01)
F13: =IF(OR(A13="",N(C13)=0),"",D13/C13) | G13: =IF(F13="","",IF(F13<Plan!$B$4,0,IF(F13<=1,Plan!$B$5+(1-Plan!$B$5)*(F13-Plan!$B$4)/(1-Plan!$B$4),MIN(Plan!$B$7,1+Plan!$B$6*(F13-1))))) | H13: =IF(G13="","",G13*E13) | I13: =IF(H13="","",H13>Plan!$B$7*E13+0.01)
F14: =IF(OR(A14="",N(C14)=0),"",D14/C14) | G14: =IF(F14="","",IF(F14<Plan!$B$4,0,IF(F14<=1,Plan!$B$5+(1-Plan!$B$5)*(F14-Plan!$B$4)/(1-Plan!$B$4),MIN(Plan!$B$7,1+Plan!$B$6*(F14-1))))) | H14: =IF(G14="","",G14*E14) | I14: =IF(H14="","",H14>Plan!$B$7*E14+0.01)
F15: =IF(OR(A15="",N(C15)=0),"",D15/C15) | G15: =IF(F15="","",IF(F15<Plan!$B$4,0,IF(F15<=1,Plan!$B$5+(1-Plan!$B$5)*(F15-Plan!$B$4)/(1-Plan!$B$4),MIN(Plan!$B$7,1+Plan!$B$6*(F15-1))))) | H15: =IF(G15="","",G15*E15) | I15: =IF(H15="","",H15>Plan!$B$7*E15+0.01)
F16: =IF(OR(A16="",N(C16)=0),"",D16/C16) | G16: =IF(F16="","",IF(F16<Plan!$B$4,0,IF(F16<=1,Plan!$B$5+(1-Plan!$B$5)*(F16-Plan!$B$4)/(1-Plan!$B$4),MIN(Plan!$B$7,1+Plan!$B$6*(F16-1))))) | H16: =IF(G16="","",G16*E16) | I16: =IF(H16="","",H16>Plan!$B$7*E16+0.01)
F17: =IF(OR(A17="",N(C17)=0),"",D17/C17) | G17: =IF(F17="","",IF(F17<Plan!$B$4,0,IF(F17<=1,Plan!$B$5+(1-Plan!$B$5)*(F17-Plan!$B$4)/(1-Plan!$B$4),MIN(Plan!$B$7,1+Plan!$B$6*(F17-1))))) | H17: =IF(G17="","",G17*E17) | I17: =IF(H17="","",H17>Plan!$B$7*E17+0.01)
F18: =IF(OR(A18="",N(C18)=0),"",D18/C18) | G18: =IF(F18="","",IF(F18<Plan!$B$4,0,IF(F18<=1,Plan!$B$5+(1-Plan!$B$5)*(F18-Plan!$B$4)/(1-Plan!$B$4),MIN(Plan!$B$7,1+Plan!$B$6*(F18-1))))) | H18: =IF(G18="","",G18*E18) | I18: =IF(H18="","",H18>Plan!$B$7*E18+0.01)
F19: =IF(OR(A19="",N(C19)=0),"",D19/C19) | G19: =IF(F19="","",IF(F19<Plan!$B$4,0,IF(F19<=1,Plan!$B$5+(1-Plan!$B$5)*(F19-Plan!$B$4)/(1-Plan!$B$4),MIN(Plan!$B$7,1+Plan!$B$6*(F19-1))))) | H19: =IF(G19="","",G19*E19) | I19: =IF(H19="","",H19>Plan!$B$7*E19+0.01)
... F204: =IF(OR(A204="",N(C204)=0),"",D204/C204) | G204: =IF(F204="","",IF(F204<Plan!$B$4,0,IF(F204<=1,Plan!$B$5+(1-Plan!$B$5)*(F204-Plan!$B$4)/(1-Plan!$B$4),MIN(Plan!$B$7,1+Plan!$B$6*(F204-1))))) | H204: =IF(G204="","",G204*E204) | I204: =IF(H204="","",H204>Plan!$B$7*E204+0.01)

Sheet ToKernel
A1: Feeds K01 opex (variable 'Sales incentives' pct_of_revenue) and K02 payout weeks
A4: total payout | B4: =SUM(Reps!H5:H204)
A5: total actual sales | B5: =SUM(Reps!D5:D204)
A6: incentive as % of revenue -> K01 opex variable pct_of_revenue | B6: =IF(B5=0,0,B4/B5)
