Workbook
Name corr_key: 'Corrections'!$H$5:$H$64
Name corr_value: 'Corrections'!$G$5:$G$64
Name company_name: 'Effective'!$B$5
Name start_month: 'Effective'!$B$6
Name horizon_months: 'Effective'!$B$7
Name tax_rate: 'Effective'!$B$8
Name da_monthly: 'Effective'!$B$9
Name capex_monthly: 'Effective'!$B$10
Name dso_days: 'Effective'!$B$11
Name dpo_days: 'Effective'!$B$12
Name dio_days: 'Effective'!$B$13
Name open_cash: 'Effective'!$B$14
Name open_ar: 'Effective'!$B$15
Name open_ap: 'Effective'!$B$16
Name open_inventory: 'Effective'!$B$17
Name open_nol: 'Effective'!$B$18
Name currency_code: 'Effective'!$B$19
Name currency_symbol: 'Effective'!$B$20
Name number_style: 'Effective'!$B$21
Name display_divisor: 'Effective'!$B$22
Name display_unit: 'Effective'!$B$23
Name valid_keys: 'ValidKeys'!$A$3:$A$207
Name tot_revenue: 'Summary'!$B$5
Name tot_ebitda: 'Summary'!$B$9
Name tot_net_income: 'Summary'!$B$14
Name tot_ending_cash: 'Summary'!$B$21
Name tot_gross_margin: 'Summary'!$B$26
Name tot_free_cash_flow: 'Summary'!$B$19
Name briefing_lines: 'Briefing'!$D$10:$D$147
Name checks_overall: 'Checks'!$C$3

Sheet README
A1: K01 · Monthly P&L + Cash-Flow Engine (no-code kernel)
A3: Replaces openfpa: pyfpa.cashflow_from_config, revenue/cogs/opex/debt/working_capital/tax models, apply_corrections, model_to_excel, verify_workbook, extract_lines, to_briefing_md, forecast_to_excel.
A4: How an agent uses this workbook
A5: 1. Copy this file into companies/<slug>/models/ (never edit the kernel copy in 02_kernel/).
A6: 2. Type drivers ONLY into pale-yellow cells on 'Assumptions' (scalars, up to 8 channels, 15 opex lines, 5 debt instruments).
A7: 3. Transcribe every memory/corrections/*.md with type: parametric into 'Corrections' (path, value, status, type).
A8: 4. Let the spreadsheet engine recalculate (Excel, LibreOffice Calc, Google Sheets, OnlyOffice, Zoho Sheet, WPS). Never type numbers into white cells.
A9: 5. Read 'Checks' first: OVERALL must be PASS before any number leaves the workbook.
A10: 6. Read results from 'Summary' (headline, Indian-FY and quarterly roll-ups, scoring lines) and 'Briefing' (board markdown).
A11: 7. 'Export_Rows' is the month-per-row fact table for K08 divestiture and the BI layer (05_bi-and-presentation).
A12: Sheet map
A13: Assumptions = inputs · Corrections = parametric overrides · Effective = inputs after corrections (formulas) · Model = the engine (one formula per line per month, up to 120 months) · Summary · Briefing · Export_Rows · Checks · ValidKeys.
... A26: FY2026-27 budget, ₹, Indian FY, one applied parametric correction (dealer November seasonality 1.45). GOLDEN rows = reference-engine results.

Sheet Checks
A1: Checks - schema validation + accounting invariants. OVERALL must be PASS before use.
B3: OVERALL | C3: =IF(COUNTIF(C5:C36,"PASS")=COUNT(A5:A36),"PASS","FAIL") | D3: =COUNTIF(C5:C36,"PASS")&" pass / "&COUNTIF(C5:C36,"FAIL")&" fail / "&(COUNT(A5:A36)-COUNTIF(C5:C36,"PASS")-COUNTIF(C5:C36,"FAIL"))&" error"
A4: # | B4: check | C4: result | D4: detail
A5: 1 | B5: start_month is a date on the 1st of a month | C5: =IF(AND(ISNUMBER(Effective!$B$6),DAY(Effective!$B$6)=1),"PASS","FAIL") | D5: ="start_month="&TEXT(Effective!$B$6,"yyyy-mm-dd")
A6: 2 | B6: horizon_months is an integer 1..120 | C6: =IF(AND(ISNUMBER(Effective!$B$7),Effective!$B$7>=1,Effective!$B$7<=120,INT(Effective!$B$7)=Effective!$B$7),"PASS","FAIL") | D6: =Effective!$B$7
A7: 3 | B7: tax_rate within 0..1 | C7: =IF(AND(Effective!$B$8>=0,Effective!$B$8<=1),"PASS","FAIL") | D7: =Effective!$B$8
A8: 4 | B8: da_monthly, capex_monthly, WC days, opening NOL are >= 0 | C8: =IF(AND(Effective!$B$9>=0,Effective!$B$10>=0,Effective!$B$11>=0,Effective!$B$12>=0,Effective!$B$13>=0,Effective!$B$18>=0),"PASS","FAIL")
A9: 5 | B9: at least one revenue channel | C9: =IF(SUMPRODUCT((Effective!$B$26:$B$33<>"")*1)>=1,"PASS","FAIL") | D9: =SUMPRODUCT((Effective!$B$26:$B$33<>"")*1)&" channels"
A10: 6 | B10: 'total' is not used as a channel or opex name (reserved) | C10: =IF(COUNTIF(Effective!$B$26:$B$33,"total")+COUNTIF(Effective!$B$36:$B$50,"total")=0,"PASS","FAIL")
A11: 7 | B11: channel names unique (case-insensitive) | C11: =IF((IF(Effective!$B$26="",0,IF(COUNTIF(Effective!$B$26:$B$33,Effective!$B$26)>1,1,0))+IF(Effective!$B$27="",0,IF(COUNTIF(Effective!$B$26:$B$33,Effective!$B$27)>1,1,0))+IF(Effective!$B$28="",0,IF(COUNTIF(Effective!$B$26:$B$33,Effective!$B$28)>1,1,0))+IF(Effective!$B$29="",0,IF(COUNTIF(Effective!$B$26:$B$33,Effective!$B$29)>1,1,0))+IF(Effective!$B$30="",0,IF(COUNTIF(Effective!$B$26:$B$33,Effective!$B$30)>1,1,0))+IF(Effective!$B$31="",0,IF(COUNTIF(Effective!$B$26:$B$33,Effective!$B$31)>1,1,0))+IF(Effective!$B$32="",0,IF(COUNTIF(Effective!$B$26:$B$33,Effective!$B$32)>1,1,0))+IF(Effective!$B$33="",0,IF(COUNTIF(Effective!$B$26:$B$33,Effective!$B$33)>1,1,0)))=0,"PASS","FAIL")
A12: 8 | B12: opex names unique (case-insensitive) | C12: =IF((IF(Effective!$B$36="",0,IF(COUNTIF(Effective!$B$36:$B$50,Effective!$B$36)>1,1,0))+IF(Effective!$B$37="",0,IF(COUNTIF(Effective!$B$36:$B$50,Effective!$B$37)>1,1,0))+IF(Effective!$B$38="",0,IF(COUNTIF(Effective!$B$36:$B$50,Effective!$B$38)>1,1,0))+IF(Effective!$B$39="",0,IF(COUNTIF(Effective!$B$36:$B$50,Effective!$B$39)>1,1,0))+IF(Effective!$B$40="",0,IF(COUNTIF(Effective!$B$36:$B$50,Effective!$B$40)>1,1,0))+IF(Effective!$B$41="",0,IF(COUNTIF(Effective!$B$36:$B$50,Effective!$B$41)>1,1,0))+IF(Effective!$B$42="",0,IF(COUNTIF(Effective!$B$36:$B$50,Effective!$B$42)>1,1,0))+IF(Effective!$B$43="",0,IF(COUNTIF(Effective!$B$36:$B$50,Effective!$B$43)>1,1,0))+IF(Effective!$B$44="",0,IF(COUNTIF(Effective!$B$36:$B$50,Effective!$B$44)>1,1,0))+IF(Effective!$B$45="",0,IF(COUNTIF(Effective!$B$36:$B$50,Effective!$B$45)>1,1,0))+IF(Effective!$B$46="",0,IF(COUNTIF(Effective!$B$36:$B$50,Effective!$B$46)>1,1,0))+IF(Effective!$B$47="",0,IF(COUNTIF(Effective!$B$36:$B$50,Effective!$B$47)>1,1,0))+IF(Effective!$B$48="",0,IF(COUNTIF(Effective!$B$36:$B$50,Effective!$B$48)>1,1,0))+IF(Effective!$B$49="",0,IF(COUNTIF(Effective!$B$36:$B$50,Effective!$B$49)>1,1,0))+IF(Effective!$B$50="",0,IF(COUNTIF(Effective!$B$36:$B$50,Effective!$B$50)>1,1,0)))=0,"PASS","FAIL")
A13: 9 | B13: debt names unique (case-insensitive) | C13: =IF((IF(Effective!$B$53="",0,IF(COUNTIF(Effective!$B$53:$B$57,Effective!$B$53)>1,1,0))+IF(Effective!$B$54="",0,IF(COUNTIF(Effective!$B$53:$B$57,Effective!$B$54)>1,1,0))+IF(Effective!$B$55="",0,IF(COUNTIF(Effective!$B$53:$B$57,Effective!$B$55)>1,1,0))+IF(Effective!$B$56="",0,IF(COUNTIF(Effective!$B$53:$B$57,Effective!$B$56)>1,1,0))+IF(Effective!$B$57="",0,IF(COUNTIF(Effective!$B$53:$B$57,Effective!$B$57)>1,1,0)))=0,"PASS","FAIL")
A14: 10 | B14: channel fields valid (revenue>=0, growth>-100%, 0<=cogs_pct<=1, 12 seasonality weights with positive sum; unnamed rows empty) | C14: =IF((IF(Effective!$B$26="",IF(N(Effective!$C$26)<>0,1,0),IF(OR(Effective!$C$26<0,Effective!$D$26<=-1,Effective!$E$26<0,Effective!$E$26>1,SUM(Effective!$F$26:$Q$26)<=0,COUNT(Assumptions!$F$26:$Q$26)<12),1,0))+IF(Effective!$B$27="",IF(N(Effective!$C$27)<>0,1,0),IF(OR(Effective!$C$27<0,Effective!$D$27<=-1,Effective!$E$27<0,Effective!$E$27>1,SUM(Effective!$F$27:$Q$27)<=0,COUNT(Assumptions!$F$27:$Q$27)<12),1,0))+IF(Effective!$B$28="",IF(N(Effective!$C$28)<>0,1,0),IF(OR(Effective!$C$28<0,Effective!$D$28<=-1,Effective!$E$28<0,Effective!$E$28>1,SUM(Effective!$F$28:$Q$28)<=0,COUNT(Assumptions!$F$28:$Q$28)<12),1,0))+IF(Effective!$B$29="",IF(N(Effective!$C$29)<>0,1,0),IF(OR(Effective!$C$29<0,Effective!$D$29<=-1,Effective!$E$29<0,Effective!$E$29>1,SUM(Effective!$F$29:$Q$29)<=0,COUNT(Assumptions!$F$29:$Q$29)<12),1,0))+IF(Effective!$B$30="",IF(N(Effective!$C$30)<>0,1,0),IF(OR(Effective!$C$30<0,Effective!$D$30<=-1,Effective!$E$30<0,Effective!$E$30>1,SUM(Effective!$F$30:$Q$30)<=0,COUNT(Assumptions!$F$30:$Q$30)<12),1,0))+IF(Effective!$B$31="",IF(N(Effective!$C$31)<>0,1,0),IF(OR(Effective!$C$31<0,Effective!$D$31<=-1,Effective!$E$31<0,Effective!$E$31>1,SUM(Effective!$F$31:$Q$31)<=0,COUNT(Assumptions!$F$31:$Q$31)<12),1,0))+IF(Effective!$B$32="",IF(N(Effective!$C$32)<>0,1,0),IF(OR(Effective!$C$32<0,Effective!$D$32<=-1,Effective!$E$32<0,Effective!$E$32>1,SUM(Effective!$F$32:$Q$32)<=0,COUNT(Assumptions!$F$32:$Q$32)<12),1,0))+IF(Effective!$B$33="",IF(N(Effective!$C$33)<>0,1,0),IF(OR(Effective!$C$33<0,Effective!$D$33<=-1,Effective!$E$33<0,Effective!$E$33>1,SUM(Effective!$F$33:$Q$33)<=0,COUNT(Assumptions!$F$33:$Q$33)<12),1,0)))=0,"PASS","FAIL") | D14: =(IF(Effective!$B$26="",IF(N(Effective!$C$26)<>0,1,0),IF(OR(Effective!$C$26<0,Effective!$D$26<=-1,Effective!$E$26<0,Effective!$E$26>1,SUM(Effective!$F$26:$Q$26)<=0,COUNT(Assumptions!$F$26:$Q$26)<12),1,0))+IF(Effective!$B$27="",IF(N(Effective!$C$27)<>0,1,0),IF(OR(Effective!$C$27<0,Effective!$D$27<=-1,Effective!$E$27<0,Effective!$E$27>1,SUM(Effective!$F$27:$Q$27)<=0,COUNT(Assumptions!$F$27:$Q$27)<12),1,0))+IF(Effective!$B$28="",IF(N(Effective!$C$28)<>0,1,0),IF(OR(Effective!$C$28<0,Effective!$D$28<=-1,Effective!$E$28<0,Effective!$E$28>1,SUM(Effective!$F$28:$Q$28)<=0,COUNT(Assumptions!$F$28:$Q$28)<12),1,0))+IF(Effective!$B$29="",IF(N(Effective!$C$29)<>0,1,0),IF(OR(Effective!$C$29<0,Effective!$D$29<=-1,Effective!$E$29<0,Effective!$E$29>1,SUM(Effective!$F$29:$Q$29)<=0,COUNT(Assumptions!$F$29:$Q$29)<12),1,0))+IF(Effective!$B$30="",IF(N(Effective!$C$30)<>0,1,0),IF(OR(Effective!$C$30<0,Effective!$D$30<=-1,Effective!$E$30<0,Effective!$E$30>1,SUM(Effective!$F$30:$Q$30)<=0,COUNT(Assumptions!$F$30:$Q$30)<12),1,0))+IF(Effective!$B$31="",IF(N(Effective!$C$31)<>0,1,0),IF(OR(Effective!$C$31<0,Effective!$D$31<=-1,Effective!$E$31<0,Effective!$E$31>1,SUM(Effective!$F$31:$Q$31)<=0,COUNT(Assumptions!$F$31:$Q$31)<12),1,0))+IF(Effective!$B$32="",IF(N(Effective!$C$32)<>0,1,0),IF(OR(Effective!$C$32<0,Effective!$D$32<=-1,Effective!$E$32<0,Effective!$E$32>1,SUM(Effective!$F$32:$Q$32)<=0,COUNT(Assumptions!$F$32:$Q$32)<12),1,0))+IF(Effective!$B$33="",IF(N(Effective!$C$33)<>0,1,0),IF(OR(Effective!$C$33<0,Effective!$D$33<=-1,Effective!$E$33<0,Effective!$E$33>1,SUM(Effective!$F$33:$Q$33)<=0,COUNT(Assumptions!$F$33:$Q$33)<12),1,0)))&" bad channel rows"
A15: 11 | B15: opex kind is fixed or variable for every named line | C15: =IF((IF(Effective!$B$36="",0,IF(OR(Effective!$C$36="fixed",Effective!$C$36="variable"),0,1))+IF(Effective!$B$37="",0,IF(OR(Effective!$C$37="fixed",Effective!$C$37="variable"),0,1))+IF(Effective!$B$38="",0,IF(OR(Effective!$C$38="fixed",Effective!$C$38="variable"),0,1))+IF(Effective!$B$39="",0,IF(OR(Effective!$C$39="fixed",Effective!$C$39="variable"),0,1))+IF(Effective!$B$40="",0,IF(OR(Effective!$C$40="fixed",Effective!$C$40="variable"),0,1))+IF(Effective!$B$41="",0,IF(OR(Effective!$C$41="fixed",Effective!$C$41="variable"),0,1))+IF(Effective!$B$42="",0,IF(OR(Effective!$C$42="fixed",Effective!$C$42="variable"),0,1))+IF(Effective!$B$43="",0,IF(OR(Effective!$C$43="fixed",Effective!$C$43="variable"),0,1))+IF(Effective!$B$44="",0,IF(OR(Effective!$C$44="fixed",Effective!$C$44="variable"),0,1))+IF(Effective!$B$45="",0,IF(OR(Effective!$C$45="fixed",Effective!$C$45="variable"),0,1))+IF(Effective!$B$46="",0,IF(OR(Effective!$C$46="fixed",Effective!$C$46="variable"),0,1))+IF(Effective!$B$47="",0,IF(OR(Effective!$C$47="fixed",Effective!$C$47="variable"),0,1))+IF(Effective!$B$48="",0,IF(OR(Effective!$C$48="fixed",Effective!$C$48="variable"),0,1))+IF(Effective!$B$49="",0,IF(OR(Effective!$C$49="fixed",Effective!$C$49="variable"),0,1))+IF(Effective!$B$50="",0,IF(OR(Effective!$C$50="fixed",Effective!$C$50="variable"),0,1)))=0,"PASS","FAIL")
A16: 12 | B16: debt kind term_loan/loc and balances/rates/principal >= 0 | C16: =IF((IF(Effective!$B$53="",0,IF(AND(OR(Effective!$C$53="term_loan",Effective!$C$53="loc"),Effective!$D$53>=0,Effective!$E$53>=0,Effective!$F$53>=0),0,1))+IF(Effective!$B$54="",0,IF(AND(OR(Effective!$C$54="term_loan",Effective!$C$54="loc"),Effective!$D$54>=0,Effective!$E$54>=0,Effective!$F$54>=0),0,1))+IF(Effective!$B$55="",0,IF(AND(OR(Effective!$C$55="term_loan",Effective!$C$55="loc"),Effective!$D$55>=0,Effective!$E$55>=0,Effective!$F$55>=0),0,1))+IF(Effective!$B$56="",0,IF(AND(OR(Effective!$C$56="term_loan",Effective!$C$56="loc"),Effective!$D$56>=0,Effective!$E$56>=0,Effective!$F$56>=0),0,1))+IF(Effective!$B$57="",0,IF(AND(OR(Effective!$C$57="term_loan",Effective!$C$57="loc"),Effective!$D$57>=0,Effective!$E$57>=0,Effective!$F$57>=0),0,1)))=0,"PASS","FAIL")
A17: 13 | B17: no two applied parametric corrections on the same path | C17: =IF((IF(RIGHT(Corrections!$H$5,19)="|applied|parametric",IF(COUNTIF(Corrections!$H$5:$H$64,Corrections!$H$5)>1,1,0),0)+IF(RIGHT(Corrections!$H$6,19)="|applied|parametric",IF(COUNTIF(Corrections!$H$5:$H$64,Corrections!$H$6)>1,1,0),0)+IF(RIGHT(Corrections!$H$7,19)="|applied|parametric",IF(COUNTIF(Corrections!$H$5:$H$64,Corrections!$H$7)>1,1,0),0)+IF(RIGHT(Corrections!$H$8,19)="|applied|parametric",IF(COUNTIF(Corrections!$H$5:$H$64,Corrections!$H$8)>1,1,0),0)+IF(RIGHT(Corrections!$H$9,19)="|applied|parametric",IF(COUNTIF(Corrections!$H$5:$H$64,Corrections!$H$9)>1,1,0),0)+IF(RIGHT(Corrections!$H$10,19)="|applied|parametric",IF(COUNTIF(Corrections!$H$5:$H$64,Corrections!$H$10)>1,1,0),0)+IF(RIGHT(Corrections!$H$11,19)="|applied|parametric",IF(COUNTIF(Corrections!$H$5:$H$64,Corrections!$H$11)>1,1,0),0)+IF(RIGHT(Corrections!$H$12,19)="|applied|parametric",IF(COUNTIF(Corrections!$H$5:$H$64,Corrections!$H$12)>1,1,0),0)+IF(RIGHT(Corrections!$H$13,19)="|applied|parametric",IF(COUNTIF(Corrections!$H$5:$H$64,Corrections!$H$13)>1,1,0),0)+IF(RIGHT(Corrections!$H$14,19)="|applied|parametric",IF(COUNTIF(Corrections!$H$5:$H$64,Corrections!$H$14)>1,1,0),0)+IF(RIGHT(Corrections!$H$15,19)="|applied|parametric",IF(COUNTIF(Corrections!$H$5:$H$64,Corrections!$H$15)>1,1,0),0)+IF(RIGHT(Corrections!$H$16,19)="|applied|parametric",IF(COUNTIF(Corrections!$H$5:$H$64,Corrections!$H$16)>1,1,0),0)+IF(RIGHT(Corrections!$H$17,19)="|applied|parametric",IF(COUNTIF(Corrections!$H$5:$H$64,Corrections!$H$17)>1,1,0),0)+IF(RIGHT(Corrections!$H$18,19)="|applied|parametric",IF(COUNTIF(Corrections!$H$5:$H$64,Corrections!$H$18)>1,1,0),0)+IF(RIGHT(Corrections!$H$19,19)="|applied|parametric",IF(COUNTIF(Corrections!$H$5:$H$64,Corrections!$H$19)>1,1,0),0)+IF(RIGHT(Corrections!$H$20,19)="|applied|parametric",IF(COUNTIF(Corrections!$H$5:$H$64,Corrections!$H$20)>1,1,0),0)+IF(RIGHT(Corrections!$H$21,19)="|applied|parametric",IF(COUNTIF(Corrections!$H$5:$H$64,Corrections!$H$21)>1,1,0),0)+IF(RIGHT(Corrections!$H$22,19)="|applied|parametric",IF(COUNTIF(Corrections!$H$5:$H$64,Corrections!$H$22)>1,1,0),0)+IF(RIGHT(Corrections!$H$23,19)="|applied|parametric",IF(COUNTIF(Corrections!$H$5:$H$64,Corrections!$H$23)>1,1,0),0)+IF(RIGHT(Corrections!$H$24,19)="|applied|parametric",IF(COUNTIF(Corrections!$H$5:$H$64,Corrections!$H$24)>1,1,0),0)+IF(RIGHT(Corrections!$H$25,19)="|applied|parametric",IF(COUNTIF(Corrections!$H$5:$H$64,Corrections!$H$25)>1,1,0),0)+IF(RIGHT(Corrections!$H$26,19)="|applied|parametric",IF(COUNTIF(Corrections!$H$5:$H$64,Corrections!$H$26)>1,1,0),0)+IF(RIGHT(Corrections!$H$27,19)="|applied|parametric",IF(COUNTIF(Corrections!$H$5:$H$64,Corrections!$H$27)>1,1,0),0)+IF(RIGHT(Corrections!$H$28,19)="|applied|parametric",IF(COUNTIF(Corrections!$H$5:$H$64,Corrections!$H$28)>1,1,0),0)+IF(RIGHT(Corrections!$H$29,19)="|applied|parametric",IF(COUNTIF(Corrections!$H$5:$H$64,Corrections!$H$29)>1,1,0),0)+IF(RIGHT(Corrections!$H$30,19)="|applied|parametric",IF(COUNTIF(Corrections!$H$5:$H$64,Corrections!$H$30)>1,1,0),0)+IF(RIGHT(Corrections!$H$31,19)="|applied|parametric",IF(COUNTIF(Corrections!$H$5:$H$64,Corrections!$H$31)>1,1,0),0)+IF(RIGHT(Corrections!$H$32,19)="|applied|parametric",IF(COUNTIF(Corrections!$H$5:$H$64,Corrections!$H$32)>1,1,0),0)+IF(RIGHT(Corrections!$H$33,19)="|applied|parametric",IF(COUNTIF(Corrections!$H$5:$H$64,Corrections!$H$33)>1,1,0),0)+IF(RIGHT(Corrections!$H$34,19)="|applied|parametric",IF(COUNTIF(Corrections!$H$5:$H$64,Corrections!$H$34)>1,1,0),0)+IF(RIGHT(Corrections!$H$35,19)="|applied|parametric",IF(COUNTIF(Corrections!$H$5:$H$64,Corrections!$H$35)>1,1,0),0)+IF(RIGHT(Corrections!$H$36,19)="|applied|parametric",IF(COUNTIF(Corrections!$H$5:$H$64,Corrections!$H$36)>1,1,0),0)+IF(RIGHT(Corrections!$H$37,19)="|applied|parametric",IF(COUNTIF(Corrections!$H$5:$H$64,Corrections!$H$37)>1,1,0),0)+IF(RIGHT(Corrections!$H$38,19)="|applied|parametric",IF(COUNTIF(Corrections!$H$5:$H$64,Corrections!$H$38)>1,1,0),0)+IF(RIGHT(Corrections!$H$39,19)="|applied|parametric",IF(COUNTIF(Corrections!$H$5:$H$64,Corrections!$H$39)>1,1,0),0)+IF(RIGHT(Corrections!$H$40,19)="|applied|parametric",IF(COUNTIF(Corrections!$H$5:$H$64,Corrections!$H$40)>1,1,0),0)+IF(RIGHT(Corrections!$H$41,19)="|applied|parametric",IF(COUNTIF(Corrections!$H$5:$H$64,Corrections!$H$41)>1,1,0),0)+IF(RIGHT(Corrections!$H$42,19)="|applied|parametric",IF(COUNTIF(Corrections!$H$5:$H$64,Corrections!$H$42)>1,1,0),0)+IF(RIGHT(Corrections!$H$43,19)="|applied|parametric",IF(COUNTIF(Corrections!$H$5:$H$64,Corrections!$H$43)>1,1,0),0)+IF(RIGHT(Corrections!$H$44,19)="|applied|parametric",IF(COUNTIF(Corrections!$H$5:$H$64,Corrections!$H$44)>1,1,0),0)+IF(RIGHT(Corrections!$H$45,19)="|applied|parametric",IF(COUNTIF(Corrections!$H$5:$H$64,Corrections!$H$45)>1,1,0),0)+IF(RIGHT(Corrections!$H$46,19)="|applied|parametric",IF(COUNTIF(Corrections!$H$5:$H$64,Corrections!$H$46)>1,1,0),0)+IF(RIGHT(Corrections!$H$47,19)="|applied|parametric",IF(COUNTIF(Corrections!$H$5:$H$64,Corrections!$H$47)>1,1,0),0)+IF(RIGHT(Corrections!$H$48,19)="|applied|parametric",IF(COUNTIF(Corrections!$H$5:$H$64,Corrections!$H$48)>1,1,0),0)+IF(RIGHT(Corrections!$H$49,19)="|applied|parametric",IF(COUNTIF(Corrections!$H$5:$H$64,Corrections!$H$49)>1,1,0),0)+IF(RIGHT(Corrections!$H$50,19)="|applied|parametric",IF(COUNTIF(Corrections!$H$5:$H$64,Corrections!$H$50)>1,1,0),0)+IF(RIGHT(Corrections!$H$51,19)="|applied|parametric",IF(COUNTIF(Corrections!$H$5:$H$64,Corrections!$H$51)>1,1,0),0)+IF(RIGHT(Corrections!$H$52,19)="|applied|parametric",IF(COUNTIF(Corrections!$H$5:$H$64,Corrections!$H$52)>1,1,0),0)+IF(RIGHT(Corrections!$H$53,19)="|applied|parametric",IF(COUNTIF(Corrections!$H$5:$H$64,Corrections!$H$53)>1,1,0),0)+IF(RIGHT(Corrections!$H$54,19)="|applied|parametric",IF(COUNTIF(Corrections!$H$5:$H$64,Corrections!$H$54)>1,1,0),0)+IF(RIGHT(Corrections!$H$55,19)="|applied|parametric",IF(COUNTIF(Corrections!$H$5:$H$64,Corrections!$H$55)>1,1,0),0)+IF(RIGHT(Corrections!$H$56,19)="|applied|parametric",IF(COUNTIF(Corrections!$H$5:$H$64,Corrections!$H$56)>1,1,0),0)+IF(RIGHT(Corrections!$H$57,19)="|applied|parametric",IF(COUNTIF(Corrections!$H$5:$H$64,Corrections!$H$57)>1,1,0),0)+IF(RIGHT(Corrections!$H$58,19)="|applied|parametric",IF(COUNTIF(Corrections!$H$5:$H$64,Corrections!$H$58)>1,1,0),0)+IF(RIGHT(Corrections!$H$59,19)="|applied|parametric",IF(COUNTIF(Corrections!$H$5:$H$64,Corrections!$H$59)>1,1,0),0)+IF(RIGHT(Corrections!$H$60,19)="|applied|parametric",IF(COUNTIF(Corrections!$H$5:$H$64,Corrections!$H$60)>1,1,0),0)+IF(RIGHT(Corrections!$H$61,19)="|applied|parametric",IF(COUNTIF(Corrections!$H$5:$H$64,Corrections!$H$61)>1,1,0),0)+IF(RIGHT(Corrections!$H$62,19)="|applied|parametric",IF(COUNTIF(Corrections!$H$5:$H$64,Corrections!$H$62)>1,1,0),0)+IF(RIGHT(Corrections!$H$63,19)="|applied|parametric",IF(COUNTIF(Corrections!$H$5:$H$64,Corrections!$H$63)>1,1,0),0)+IF(RIGHT(Corrections!$H$64,19)="|applied|parametric",IF(COUNTIF(Corrections!$H$5:$H$64,Corrections!$H$64)>1,1,0),0))=0,"PASS","FAIL") | D17: =(IF(RIGHT(Corrections!$H$5,19)="|applied|parametric",IF(COUNTIF(Corrections!$H$5:$H$64,Corrections!$H$5)>1,1,0),0)+IF(RIGHT(Corrections!$H$6,19)="|applied|parametric",IF(COUNTIF(Corrections!$H$5:$H$64,Corrections!$H$6)>1,1,0),0)+IF(RIGHT(Corrections!$H$7,19)="|applied|parametric",IF(COUNTIF(Corrections!$H$5:$H$64,Corrections!$H$7)>1,1,0),0)+IF(RIGHT(Corrections!$H$8,19)="|applied|parametric",IF(COUNTIF(Corrections!$H$5:$H$64,Corrections!$H$8)>1,1,0),0)+IF(RIGHT(Corrections!$H$9,19)="|applied|parametric",IF(COUNTIF(Corrections!$H$5:$H$64,Corrections!$H$9)>1,1,0),0)+IF(RIGHT(Corrections!$H$10,19)="|applied|parametric",IF(COUNTIF(Corrections!$H$5:$H$64,Corrections!$H$10)>1,1,0),0)+IF(RIGHT(Corrections!$H$11,19)="|applied|parametric",IF(COUNTIF(Corrections!$H$5:$H$64,Corrections!$H$11)>1,1,0),0)+IF(RIGHT(Corrections!$H$12,19)="|applied|parametric",IF(COUNTIF(Corrections!$H$5:$H$64,Corrections!$H$12)>1,1,0),0)+IF(RIGHT(Corrections!$H$13,19)="|applied|parametric",IF(COUNTIF(Corrections!$H$5:$H$64,Corrections!$H$13)>1,1,0),0)+IF(RIGHT(Corrections!$H$14,19)="|applied|parametric",IF(COUNTIF(Corrections!$H$5:$H$64,Corrections!$H$14)>1,1,0),0)+IF(RIGHT(Corrections!$H$15,19)="|applied|parametric",IF(COUNTIF(Corrections!$H$5:$H$64,Corrections!$H$15)>1,1,0),0)+IF(RIGHT(Corrections!$H$16,19)="|applied|parametric",IF(COUNTIF(Corrections!$H$5:$H$64,Corrections!$H$16)>1,1,0),0)+IF(RIGHT(Corrections!$H$17,19)="|applied|parametric",IF(COUNTIF(Corrections!$H$5:$H$64,Corrections!$H$17)>1,1,0),0)+IF(RIGHT(Corrections!$H$18,19)="|applied|parametric",IF(COUNTIF(Corrections!$H$5:$H$64,Corrections!$H$18)>1,1,0),0)+IF(RIGHT(Corrections!$H$19,19)="|applied|parametric",IF(COUNTIF(Corrections!$H$5:$H$64,Corrections!$H$19)>1,1,0),0)+IF(RIGHT(Corrections!$H$20,19)="|applied|parametric",IF(COUNTIF(Corrections!$H$5:$H$64,Corrections!$H$20)>1,1,0),0)+IF(RIGHT(Corrections!$H$21,19)="|applied|parametric",IF(COUNTIF(Corrections!$H$5:$H$64,Corrections!$H$21)>1,1,0),0)+IF(RIGHT(Corrections!$H$22,19)="|applied|parametric",IF(COUNTIF(Corrections!$H$5:$H$64,Corrections!$H$22)>1,1,0),0)+IF(RIGHT(Corrections!$H$23,19)="|applied|parametric",IF(COUNTIF(Corrections!$H$5:$H$64,Corrections!$H$23)>1,1,0),0)+IF(RIGHT(Corrections!$H$24,19)="|applied|parametric",IF(COUNTIF(Corrections!$H$5:$H$64,Corrections!$H$24)>1,1,0),0)+IF(RIGHT(Corrections!$H$25,19)="|applied|parametric",IF(COUNTIF(Corrections!$H$5:$H$64,Corrections!$H$25)>1,1,0),0)+IF(RIGHT(Corrections!$H$26,19)="|applied|parametric",IF(COUNTIF(Corrections!$H$5:$H$64,Corrections!$H$26)>1,1,0),0)+IF(RIGHT(Corrections!$H$27,19)="|applied|parametric",IF(COUNTIF(Corrections!$H$5:$H$64,Corrections!$H$27)>1,1,0),0)+IF(RIGHT(Corrections!$H$28,19)="|applied|parametric",IF(COUNTIF(Corrections!$H$5:$H$64,Corrections!$H$28)>1,1,0),0)+IF(RIGHT(Corrections!$H$29,19)="|applied|parametric",IF(COUNTIF(Corrections!$H$5:$H$64,Corrections!$H$29)>1,1,0),0)+IF(RIGHT(Corrections!$H$30,19)="|applied|parametric",IF(COUNTIF(Corrections!$H$5:$H$64,Corrections!$H$30)>1,1,0),0)+IF(RIGHT(Corrections!$H$31,19)="|applied|parametric",IF(COUNTIF(Corrections!$H$5:$H$64,Corrections!$H$31)>1,1,0),0)+IF(RIGHT(Corrections!$H$32,19)="|applied|parametric",IF(COUNTIF(Corrections!$H$5:$H$64,Corrections!$H$32)>1,1,0),0)+IF(RIGHT(Corrections!$H$33,19)="|applied|parametric",IF(COUNTIF(Corrections!$H$5:$H$64,Corrections!$H$33)>1,1,0),0)+IF(RIGHT(Corrections!$H$34,19)="|applied|parametric",IF(COUNTIF(Corrections!$H$5:$H$64,Corrections!$H$34)>1,1,0),0)+IF(RIGHT(Corrections!$H$35,19)="|applied|parametric",IF(COUNTIF(Corrections!$H$5:$H$64,Corrections!$H$35)>1,1,0),0)+IF(RIGHT(Corrections!$H$36,19)="|applied|parametric",IF(COUNTIF(Corrections!$H$5:$H$64,Corrections!$H$36)>1,1,0),0)+IF(RIGHT(Corrections!$H$37,19)="|applied|parametric",IF(COUNTIF(Corrections!$H$5:$H$64,Corrections!$H$37)>1,1,0),0)+IF(RIGHT(Corrections!$H$38,19)="|applied|parametric",IF(COUNTIF(Corrections!$H$5:$H$64,Corrections!$H$38)>1,1,0),0)+IF(RIGHT(Corrections!$H$39,19)="|applied|parametric",IF(COUNTIF(Corrections!$H$5:$H$64,Corrections!$H$39)>1,1,0),0)+IF(RIGHT(Corrections!$H$40,19)="|applied|parametric",IF(COUNTIF(Corrections!$H$5:$H$64,Corrections!$H$40)>1,1,0),0)+IF(RIGHT(Corrections!$H$41,19)="|applied|parametric",IF(COUNTIF(Corrections!$H$5:$H$64,Corrections!$H$41)>1,1,0),0)+IF(RIGHT(Corrections!$H$42,19)="|applied|parametric",IF(COUNTIF(Corrections!$H$5:$H$64,Corrections!$H$42)>1,1,0),0)+IF(RIGHT(Corrections!$H$43,19)="|applied|parametric",IF(COUNTIF(Corrections!$H$5:$H$64,Corrections!$H$43)>1,1,0),0)+IF(RIGHT(Corrections!$H$44,19)="|applied|parametric",IF(COUNTIF(Corrections!$H$5:$H$64,Corrections!$H$44)>1,1,0),0)+IF(RIGHT(Corrections!$H$45,19)="|applied|parametric",IF(COUNTIF(Corrections!$H$5:$H$64,Corrections!$H$45)>1,1,0),0)+IF(RIGHT(Corrections!$H$46,19)="|applied|parametric",IF(COUNTIF(Corrections!$H$5:$H$64,Corrections!$H$46)>1,1,0),0)+IF(RIGHT(Corrections!$H$47,19)="|applied|parametric",IF(COUNTIF(Corrections!$H$5:$H$64,Corrections!$H$47)>1,1,0),0)+IF(RIGHT(Corrections!$H$48,19)="|applied|parametric",IF(COUNTIF(Corrections!$H$5:$H$64,Corrections!$H$48)>1,1,0),0)+IF(RIGHT(Corrections!$H$49,19)="|applied|parametric",IF(COUNTIF(Corrections!$H$5:$H$64,Corrections!$H$49)>1,1,0),0)+IF(RIGHT(Corrections!$H$50,19)="|applied|parametric",IF(COUNTIF(Corrections!$H$5:$H$64,Corrections!$H$50)>1,1,0),0)+IF(RIGHT(Corrections!$H$51,19)="|applied|parametric",IF(COUNTIF(Corrections!$H$5:$H$64,Corrections!$H$51)>1,1,0),0)+IF(RIGHT(Corrections!$H$52,19)="|applied|parametric",IF(COUNTIF(Corrections!$H$5:$H$64,Corrections!$H$52)>1,1,0),0)+IF(RIGHT(Corrections!$H$53,19)="|applied|parametric",IF(COUNTIF(Corrections!$H$5:$H$64,Corrections!$H$53)>1,1,0),0)+IF(RIGHT(Corrections!$H$54,19)="|applied|parametric",IF(COUNTIF(Corrections!$H$5:$H$64,Corrections!$H$54)>1,1,0),0)+IF(RIGHT(Corrections!$H$55,19)="|applied|parametric",IF(COUNTIF(Corrections!$H$5:$H$64,Corrections!$H$55)>1,1,0),0)+IF(RIGHT(Corrections!$H$56,19)="|applied|parametric",IF(COUNTIF(Corrections!$H$5:$H$64,Corrections!$H$56)>1,1,0),0)+IF(RIGHT(Corrections!$H$57,19)="|applied|parametric",IF(COUNTIF(Corrections!$H$5:$H$64,Corrections!$H$57)>1,1,0),0)+IF(RIGHT(Corrections!$H$58,19)="|applied|parametric",IF(COUNTIF(Corrections!$H$5:$H$64,Corrections!$H$58)>1,1,0),0)+IF(RIGHT(Corrections!$H$59,19)="|applied|parametric",IF(COUNTIF(Corrections!$H$5:$H$64,Corrections!$H$59)>1,1,0),0)+IF(RIGHT(Corrections!$H$60,19)="|applied|parametric",IF(COUNTIF(Corrections!$H$5:$H$64,Corrections!$H$60)>1,1,0),0)+IF(RIGHT(Corrections!$H$61,19)="|applied|parametric",IF(COUNTIF(Corrections!$H$5:$H$64,Corrections!$H$61)>1,1,0),0)+IF(RIGHT(Corrections!$H$62,19)="|applied|parametric",IF(COUNTIF(Corrections!$H$5:$H$64,Corrections!$H$62)>1,1,0),0)+IF(RIGHT(Corrections!$H$63,19)="|applied|parametric",IF(COUNTIF(Corrections!$H$5:$H$64,Corrections!$H$63)>1,1,0),0)+IF(RIGHT(Corrections!$H$64,19)="|applied|parametric",IF(COUNTIF(Corrections!$H$5:$H$64,Corrections!$H$64)>1,1,0),0))&" duplicate rows"
A18: 14 | B18: every applied parametric correction path resolves (see ValidKeys) | C18: =IF((IF(RIGHT(Corrections!$H$5,19)="|applied|parametric",IF(COUNTIF(ValidKeys!$A$3:$A$207,LEFT(Corrections!$H$5,LEN(Corrections!$H$5)-19))=0,1,0),0)+IF(RIGHT(Corrections!$H$6,19)="|applied|parametric",IF(COUNTIF(ValidKeys!$A$3:$A$207,LEFT(Corrections!$H$6,LEN(Corrections!$H$6)-19))=0,1,0),0)+IF(RIGHT(Corrections!$H$7,19)="|applied|parametric",IF(COUNTIF(ValidKeys!$A$3:$A$207,LEFT(Corrections!$H$7,LEN(Corrections!$H$7)-19))=0,1,0),0)+IF(RIGHT(Corrections!$H$8,19)="|applied|parametric",IF(COUNTIF(ValidKeys!$A$3:$A$207,LEFT(Corrections!$H$8,LEN(Corrections!$H$8)-19))=0,1,0),0)+IF(RIGHT(Corrections!$H$9,19)="|applied|parametric",IF(COUNTIF(ValidKeys!$A$3:$A$207,LEFT(Corrections!$H$9,LEN(Corrections!$H$9)-19))=0,1,0),0)+IF(RIGHT(Corrections!$H$10,19)="|applied|parametric",IF(COUNTIF(ValidKeys!$A$3:$A$207,LEFT(Corrections!$H$10,LEN(Corrections!$H$10)-19))=0,1,0),0)+IF(RIGHT(Corrections!$H$11,19)="|applied|parametric",IF(COUNTIF(ValidKeys!$A$3:$A$207,LEFT(Corrections!$H$11,LEN(Corrections!$H$11)-19))=0,1,0),0)+IF(RIGHT(Corrections!$H$12,19)="|applied|parametric",IF(COUNTIF(ValidKeys!$A$3:$A$207,LEFT(Corrections!$H$12,LEN(Corrections!$H$12)-19))=0,1,0),0)+IF(RIGHT(Corrections!$H$13,19)="|applied|parametric",IF(COUNTIF(ValidKeys!$A$3:$A$207,LEFT(Corrections!$H$13,LEN(Corrections!$H$13)-19))=0,1,0),0)+IF(RIGHT(Corrections!$H$14,19)="|applied|parametric",IF(COUNTIF(ValidKeys!$A$3:$A$207,LEFT(Corrections!$H$14,LEN(Corrections!$H$14)-19))=0,1,0),0)+IF(RIGHT(Corrections!$H$15,19)="|applied|parametric",IF(COUNTIF(ValidKeys!$A$3:$A$207,LEFT(Corrections!$H$15,LEN(Corrections!$H$15)-19))=0,1,0),0)+IF(RIGHT(Corrections!$H$16,19)="|applied|parametric",IF(COUNTIF(ValidKeys!$A$3:$A$207,LEFT(Corrections!$H$16,LEN(Corrections!$H$16)-19))=0,1,0),0)+IF(RIGHT(Corrections!$H$17,19)="|applied|parametric",IF(COUNTIF(ValidKeys!$A$3:$A$207,LEFT(Corrections!$H$17,LEN(Corrections!$H$17)-19))=0,1,0),0)+IF(RIGHT(Corrections!$H$18,19)="|applied|parametric",IF(COUNTIF(ValidKeys!$A$3:$A$207,LEFT(Corrections!$H$18,LEN(Corrections!$H$18)-19))=0,1,0),0)+IF(RIGHT(Corrections!$H$19,19)="|applied|parametric",IF(COUNTIF(ValidKeys!$A$3:$A$207,LEFT(Corrections!$H$19,LEN(Corrections!$H$19)-19))=0,1,0),0)+IF(RIGHT(Corrections!$H$20,19)="|applied|parametric",IF(COUNTIF(ValidKeys!$A$3:$A$207,LEFT(Corrections!$H$20,LEN(Corrections!$H$20)-19))=0,1,0),0)+IF(RIGHT(Corrections!$H$21,19)="|applied|parametric",IF(COUNTIF(ValidKeys!$A$3:$A$207,LEFT(Corrections!$H$21,LEN(Corrections!$H$21)-19))=0,1,0),0)+IF(RIGHT(Corrections!$H$22,19)="|applied|parametric",IF(COUNTIF(ValidKeys!$A$3:$A$207,LEFT(Corrections!$H$22,LEN(Corrections!$H$22)-19))=0,1,0),0)+IF(RIGHT(Corrections!$H$23,19)="|applied|parametric",IF(COUNTIF(ValidKeys!$A$3:$A$207,LEFT(Corrections!$H$23,LEN(Corrections!$H$23)-19))=0,1,0),0)+IF(RIGHT(Corrections!$H$24,19)="|applied|parametric",IF(COUNTIF(ValidKeys!$A$3:$A$207,LEFT(Corrections!$H$24,LEN(Corrections!$H$24)-19))=0,1,0),0)+IF(RIGHT(Corrections!$H$25,19)="|applied|parametric",IF(COUNTIF(ValidKeys!$A$3:$A$207,LEFT(Corrections!$H$25,LEN(Corrections!$H$25)-19))=0,1,0),0)+IF(RIGHT(Corrections!$H$26,19)="|applied|parametric",IF(COUNTIF(ValidKeys!$A$3:$A$207,LEFT(Corrections!$H$26,LEN(Corrections!$H$26)-19))=0,1,0),0)+IF(RIGHT(Corrections!$H$27,19)="|applied|parametric",IF(COUNTIF(ValidKeys!$A$3:$A$207,LEFT(Corrections!$H$27,LEN(Corrections!$H$27)-19))=0,1,0),0)+IF(RIGHT(Corrections!$H$28,19)="|applied|parametric",IF(COUNTIF(ValidKeys!$A$3:$A$207,LEFT(Corrections!$H$28,LEN(Corrections!$H$28)-19))=0,1,0),0)+IF(RIGHT(Corrections!$H$29,19)="|applied|parametric",IF(COUNTIF(ValidKeys!$A$3:$A$207,LEFT(Corrections!$H$29,LEN(Corrections!$H$29)-19))=0,1,0),0)+IF(RIGHT(Corrections!$H$30,19)="|applied|parametric",IF(COUNTIF(ValidKeys!$A$3:$A$207,LEFT(Corrections!$H$30,LEN(Corrections!$H$30)-19))=0,1,0),0)+IF(RIGHT(Corrections!$H$31,19)="|applied|parametric",IF(COUNTIF(ValidKeys!$A$3:$A$207,LEFT(Corrections!$H$31,LEN(Corrections!$H$31)-19))=0,1,0),0)+IF(RIGHT(Corrections!$H$32,19)="|applied|parametric",IF(COUNTIF(ValidKeys!$A$3:$A$207,LEFT(Corrections!$H$32,LEN(Corrections!$H$32)-19))=0,1,0),0)+IF(RIGHT(Corrections!$H$33,19)="|applied|parametric",IF(COUNTIF(ValidKeys!$A$3:$A$207,LEFT(Corrections!$H$33,LEN(Corrections!$H$33)-19))=0,1,0),0)+IF(RIGHT(Corrections!$H$34,19)="|applied|parametric",IF(COUNTIF(ValidKeys!$A$3:$A$207,LEFT(Corrections!$H$34,LEN(Corrections!$H$34)-19))=0,1,0),0)+IF(RIGHT(Corrections!$H$35,19)="|applied|parametric",IF(COUNTIF(ValidKeys!$A$3:$A$207,LEFT(Corrections!$H$35,LEN(Corrections!$H$35)-19))=0,1,0),0)+IF(RIGHT(Corrections!$H$36,19)="|applied|parametric",IF(COUNTIF(ValidKeys!$A$3:$A$207,LEFT(Corrections!$H$36,LEN(Corrections!$H$36)-19))=0,1,0),0)+IF(RIGHT(Corrections!$H$37,19)="|applied|parametric",IF(COUNTIF(ValidKeys!$A$3:$A$207,LEFT(Corrections!$H$37,LEN(Corrections!$H$37)-19))=0,1,0),0)+IF(RIGHT(Corrections!$H$38,19)="|applied|parametric",IF(COUNTIF(ValidKeys!$A$3:$A$207,LEFT(Corrections!$H$38,LEN(Corrections!$H$38)-19))=0,1,0),0)+IF(RIGHT(Corrections!$H$39,19)="|applied|parametric",IF(COUNTIF(ValidKeys!$A$3:$A$207,LEFT(Corrections!$H$39,LEN(Corrections!$H$39)-19))=0,1,0),0)+IF(RIGHT(Corrections!$H$40,19)="|applied|parametric",IF(COUNTIF(ValidKeys!$A$3:$A$207,LEFT(Corrections!$H$40,LEN(Corrections!$H$40)-19))=0,1,0),0)+IF(RIGHT(Corrections!$H$41,19)="|applied|parametric",IF(COUNTIF(ValidKeys!$A$3:$A$207,LEFT(Corrections!$H$41,LEN(Corrections!$H$41)-19))=0,1,0),0)+IF(RIGHT(Corrections!$H$42,19)="|applied|parametric",IF(COUNTIF(ValidKeys!$A$3:$A$207,LEFT(Corrections!$H$42,LEN(Corrections!$H$42)-19))=0,1,0),0)+IF(RIGHT(Corrections!$H$43,19)="|applied|parametric",IF(COUNTIF(ValidKeys!$A$3:$A$207,LEFT(Corrections!$H$43,LEN(Corrections!$H$43)-19))=0,1,0),0)+IF(RIGHT(Corrections!$H$44,19)="|applied|parametric",IF(COUNTIF(ValidKeys!$A$3:$A$207,LEFT(Corrections!$H$44,LEN(Corrections!$H$44)-19))=0,1,0),0)+IF(RIGHT(Corrections!$H$45,19)="|applied|parametric",IF(COUNTIF(ValidKeys!$A$3:$A$207,LEFT(Corrections!$H$45,LEN(Corrections!$H$45)-19))=0,1,0),0)+IF(RIGHT(Corrections!$H$46,19)="|applied|parametric",IF(COUNTIF(ValidKeys!$A$3:$A$207,LEFT(Corrections!$H$46,LEN(Corrections!$H$46)-19))=0,1,0),0)+IF(RIGHT(Corrections!$H$47,19)="|applied|parametric",IF(COUNTIF(ValidKeys!$A$3:$A$207,LEFT(Corrections!$H$47,LEN(Corrections!$H$47)-19))=0,1,0),0)+IF(RIGHT(Corrections!$H$48,19)="|applied|parametric",IF(COUNTIF(ValidKeys!$A$3:$A$207,LEFT(Corrections!$H$48,LEN(Corrections!$H$48)-19))=0,1,0),0)+IF(RIGHT(Corrections!$H$49,19)="|applied|parametric",IF(COUNTIF(ValidKeys!$A$3:$A$207,LEFT(Corrections!$H$49,LEN(Corrections!$H$49)-19))=0,1,0),0)+IF(RIGHT(Corrections!$H$50,19)="|applied|parametric",IF(COUNTIF(ValidKeys!$A$3:$A$207,LEFT(Corrections!$H$50,LEN(Corrections!$H$50)-19))=0,1,0),0)+IF(RIGHT(Corrections!$H$51,19)="|applied|parametric",IF(COUNTIF(ValidKeys!$A$3:$A$207,LEFT(Corrections!$H$51,LEN(Corrections!$H$51)-19))=0,1,0),0)+IF(RIGHT(Corrections!$H$52,19)="|applied|parametric",IF(COUNTIF(ValidKeys!$A$3:$A$207,LEFT(Corrections!$H$52,LEN(Corrections!$H$52)-19))=0,1,0),0)+IF(RIGHT(Corrections!$H$53,19)="|applied|parametric",IF(COUNTIF(ValidKeys!$A$3:$A$207,LEFT(Corrections!$H$53,LEN(Corrections!$H$53)-19))=0,1,0),0)+IF(RIGHT(Corrections!$H$54,19)="|applied|parametric",IF(COUNTIF(ValidKeys!$A$3:$A$207,LEFT(Corrections!$H$54,LEN(Corrections!$H$54)-19))=0,1,0),0)+IF(RIGHT(Corrections!$H$55,19)="|applied|parametric",IF(COUNTIF(ValidKeys!$A$3:$A$207,LEFT(Corrections!$H$55,LEN(Corrections!$H$55)-19))=0,1,0),0)+IF(RIGHT(Corrections!$H$56,19)="|applied|parametric",IF(COUNTIF(ValidKeys!$A$3:$A$207,LEFT(Corrections!$H$56,LEN(Corrections!$H$56)-19))=0,1,0),0)+IF(RIGHT(Corrections!$H$57,19)="|applied|parametric",IF(COUNTIF(ValidKeys!$A$3:$A$207,LEFT(Corrections!$H$57,LEN(Corrections!$H$57)-19))=0,1,0),0)+IF(RIGHT(Corrections!$H$58,19)="|applied|parametric",IF(COUNTIF(ValidKeys!$A$3:$A$207,LEFT(Corrections!$H$58,LEN(Corrections!$H$58)-19))=0,1,0),0)+IF(RIGHT(Corrections!$H$59,19)="|applied|parametric",IF(COUNTIF(ValidKeys!$A$3:$A$207,LEFT(Corrections!$H$59,LEN(Corrections!$H$59)-19))=0,1,0),0)+IF(RIGHT(Corrections!$H$60,19)="|applied|parametric",IF(COUNTIF(ValidKeys!$A$3:$A$207,LEFT(Corrections!$H$60,LEN(Corrections!$H$60)-19))=0,1,0),0)+IF(RIGHT(Corrections!$H$61,19)="|applied|parametric",IF(COUNTIF(ValidKeys!$A$3:$A$207,LEFT(Corrections!$H$61,LEN(Corrections!$H$61)-19))=0,1,0),0)+IF(RIGHT(Corrections!$H$62,19)="|applied|parametric",IF(COUNTIF(ValidKeys!$A$3:$A$207,LEFT(Corrections!$H$62,LEN(Corrections!$H$62)-19))=0,1,0),0)+IF(RIGHT(Corrections!$H$63,19)="|applied|parametric",IF(COUNTIF(ValidKeys!$A$3:$A$207,LEFT(Corrections!$H$63,LEN(Corrections!$H$63)-19))=0,1,0),0)+IF(RIGHT(Corrections!$H$64,19)="|applied|parametric",IF(COUNTIF(ValidKeys!$A$3:$A$207,LEFT(Corrections!$H$64,LEN(Corrections!$H$64)-19))=0,1,0),0))=0,"PASS","FAIL") | D18: =(IF(RIGHT(Corrections!$H$5,19)="|applied|parametric",IF(COUNTIF(ValidKeys!$A$3:$A$207,LEFT(Corrections!$H$5,LEN(Corrections!$H$5)-19))=0,1,0),0)+IF(RIGHT(Corrections!$H$6,19)="|applied|parametric",IF(COUNTIF(ValidKeys!$A$3:$A$207,LEFT(Corrections!$H$6,LEN(Corrections!$H$6)-19))=0,1,0),0)+IF(RIGHT(Corrections!$H$7,19)="|applied|parametric",IF(COUNTIF(ValidKeys!$A$3:$A$207,LEFT(Corrections!$H$7,LEN(Corrections!$H$7)-19))=0,1,0),0)+IF(RIGHT(Corrections!$H$8,19)="|applied|parametric",IF(COUNTIF(ValidKeys!$A$3:$A$207,LEFT(Corrections!$H$8,LEN(Corrections!$H$8)-19))=0,1,0),0)+IF(RIGHT(Corrections!$H$9,19)="|applied|parametric",IF(COUNTIF(ValidKeys!$A$3:$A$207,LEFT(Corrections!$H$9,LEN(Corrections!$H$9)-19))=0,1,0),0)+IF(RIGHT(Corrections!$H$10,19)="|applied|parametric",IF(COUNTIF(ValidKeys!$A$3:$A$207,LEFT(Corrections!$H$10,LEN(Corrections!$H$10)-19))=0,1,0),0)+IF(RIGHT(Corrections!$H$11,19)="|applied|parametric",IF(COUNTIF(ValidKeys!$A$3:$A$207,LEFT(Corrections!$H$11,LEN(Corrections!$H$11)-19))=0,1,0),0)+IF(RIGHT(Corrections!$H$12,19)="|applied|parametric",IF(COUNTIF(ValidKeys!$A$3:$A$207,LEFT(Corrections!$H$12,LEN(Corrections!$H$12)-19))=0,1,0),0)+IF(RIGHT(Corrections!$H$13,19)="|applied|parametric",IF(COUNTIF(ValidKeys!$A$3:$A$207,LEFT(Corrections!$H$13,LEN(Corrections!$H$13)-19))=0,1,0),0)+IF(RIGHT(Corrections!$H$14,19)="|applied|parametric",IF(COUNTIF(ValidKeys!$A$3:$A$207,LEFT(Corrections!$H$14,LEN(Corrections!$H$14)-19))=0,1,0),0)+IF(RIGHT(Corrections!$H$15,19)="|applied|parametric",IF(COUNTIF(ValidKeys!$A$3:$A$207,LEFT(Corrections!$H$15,LEN(Corrections!$H$15)-19))=0,1,0),0)+IF(RIGHT(Corrections!$H$16,19)="|applied|parametric",IF(COUNTIF(ValidKeys!$A$3:$A$207,LEFT(Corrections!$H$16,LEN(Corrections!$H$16)-19))=0,1,0),0)+IF(RIGHT(Corrections!$H$17,19)="|applied|parametric",IF(COUNTIF(ValidKeys!$A$3:$A$207,LEFT(Corrections!$H$17,LEN(Corrections!$H$17)-19))=0,1,0),0)+IF(RIGHT(Corrections!$H$18,19)="|applied|parametric",IF(COUNTIF(ValidKeys!$A$3:$A$207,LEFT(Corrections!$H$18,LEN(Corrections!$H$18)-19))=0,1,0),0)+IF(RIGHT(Corrections!$H$19,19)="|applied|parametric",IF(COUNTIF(ValidKeys!$A$3:$A$207,LEFT(Corrections!$H$19,LEN(Corrections!$H$19)-19))=0,1,0),0)+IF(RIGHT(Corrections!$H$20,19)="|applied|parametric",IF(COUNTIF(ValidKeys!$A$3:$A$207,LEFT(Corrections!$H$20,LEN(Corrections!$H$20)-19))=0,1,0),0)+IF(RIGHT(Corrections!$H$21,19)="|applied|parametric",IF(COUNTIF(ValidKeys!$A$3:$A$207,LEFT(Corrections!$H$21,LEN(Corrections!$H$21)-19))=0,1,0),0)+IF(RIGHT(Corrections!$H$22,19)="|applied|parametric",IF(COUNTIF(ValidKeys!$A$3:$A$207,LEFT(Corrections!$H$22,LEN(Corrections!$H$22)-19))=0,1,0),0)+IF(RIGHT(Corrections!$H$23,19)="|applied|parametric",IF(COUNTIF(ValidKeys!$A$3:$A$207,LEFT(Corrections!$H$23,LEN(Corrections!$H$23)-19))=0,1,0),0)+IF(RIGHT(Corrections!$H$24,19)="|applied|parametric",IF(COUNTIF(ValidKeys!$A$3:$A$207,LEFT(Corrections!$H$24,LEN(Corrections!$H$24)-19))=0,1,0),0)+IF(RIGHT(Corrections!$H$25,19)="|applied|parametric",IF(COUNTIF(ValidKeys!$A$3:$A$207,LEFT(Corrections!$H$25,LEN(Corrections!$H$25)-19))=0,1,0),0)+IF(RIGHT(Corrections!$H$26,19)="|applied|parametric",IF(COUNTIF(ValidKeys!$A$3:$A$207,LEFT(Corrections!$H$26,LEN(Corrections!$H$26)-19))=0,1,0),0)+IF(RIGHT(Corrections!$H$27,19)="|applied|parametric",IF(COUNTIF(ValidKeys!$A$3:$A$207,LEFT(Corrections!$H$27,LEN(Corrections!$H$27)-19))=0,1,0),0)+IF(RIGHT(Corrections!$H$28,19)="|applied|parametric",IF(COUNTIF(ValidKeys!$A$3:$A$207,LEFT(Corrections!$H$28,LEN(Corrections!$H$28)-19))=0,1,0),0)+IF(RIGHT(Corrections!$H$29,19)="|applied|parametric",IF(COUNTIF(ValidKeys!$A$3:$A$207,LEFT(Corrections!$H$29,LEN(Corrections!$H$29)-19))=0,1,0),0)+IF(RIGHT(Corrections!$H$30,19)="|applied|parametric",IF(COUNTIF(ValidKeys!$A$3:$A$207,LEFT(Corrections!$H$30,LEN(Corrections!$H$30)-19))=0,1,0),0)+IF(RIGHT(Corrections!$H$31,19)="|applied|parametric",IF(COUNTIF(ValidKeys!$A$3:$A$207,LEFT(Corrections!$H$31,LEN(Corrections!$H$31)-19))=0,1,0),0)+IF(RIGHT(Corrections!$H$32,19)="|applied|parametric",IF(COUNTIF(ValidKeys!$A$3:$A$207,LEFT(Corrections!$H$32,LEN(Corrections!$H$32)-19))=0,1,0),0)+IF(RIGHT(Corrections!$H$33,19)="|applied|parametric",IF(COUNTIF(ValidKeys!$A$3:$A$207,LEFT(Corrections!$H$33,LEN(Corrections!$H$33)-19))=0,1,0),0)+IF(RIGHT(Corrections!$H$34,19)="|applied|parametric",IF(COUNTIF(ValidKeys!$A$3:$A$207,LEFT(Corrections!$H$34,LEN(Corrections!$H$34)-19))=0,1,0),0)+IF(RIGHT(Corrections!$H$35,19)="|applied|parametric",IF(COUNTIF(ValidKeys!$A$3:$A$207,LEFT(Corrections!$H$35,LEN(Corrections!$H$35)-19))=0,1,0),0)+IF(RIGHT(Corrections!$H$36,19)="|applied|parametric",IF(COUNTIF(ValidKeys!$A$3:$A$207,LEFT(Corrections!$H$36,LEN(Corrections!$H$36)-19))=0,1,0),0)+IF(RIGHT(Corrections!$H$37,19)="|applied|parametric",IF(COUNTIF(ValidKeys!$A$3:$A$207,LEFT(Corrections!$H$37,LEN(Corrections!$H$37)-19))=0,1,0),0)+IF(RIGHT(Corrections!$H$38,19)="|applied|parametric",IF(COUNTIF(ValidKeys!$A$3:$A$207,LEFT(Corrections!$H$38,LEN(Corrections!$H$38)-19))=0,1,0),0)+IF(RIGHT(Corrections!$H$39,19)="|applied|parametric",IF(COUNTIF(ValidKeys!$A$3:$A$207,LEFT(Corrections!$H$39,LEN(Corrections!$H$39)-19))=0,1,0),0)+IF(RIGHT(Corrections!$H$40,19)="|applied|parametric",IF(COUNTIF(ValidKeys!$A$3:$A$207,LEFT(Corrections!$H$40,LEN(Corrections!$H$40)-19))=0,1,0),0)+IF(RIGHT(Corrections!$H$41,19)="|applied|parametric",IF(COUNTIF(ValidKeys!$A$3:$A$207,LEFT(Corrections!$H$41,LEN(Corrections!$H$41)-19))=0,1,0),0)+IF(RIGHT(Corrections!$H$42,19)="|applied|parametric",IF(COUNTIF(ValidKeys!$A$3:$A$207,LEFT(Corrections!$H$42,LEN(Corrections!$H$42)-19))=0,1,0),0)+IF(RIGHT(Corrections!$H$43,19)="|applied|parametric",IF(COUNTIF(ValidKeys!$A$3:$A$207,LEFT(Corrections!$H$43,LEN(Corrections!$H$43)-19))=0,1,0),0)+IF(RIGHT(Corrections!$H$44,19)="|applied|parametric",IF(COUNTIF(ValidKeys!$A$3:$A$207,LEFT(Corrections!$H$44,LEN(Corrections!$H$44)-19))=0,1,0),0)+IF(RIGHT(Corrections!$H$45,19)="|applied|parametric",IF(COUNTIF(ValidKeys!$A$3:$A$207,LEFT(Corrections!$H$45,LEN(Corrections!$H$45)-19))=0,1,0),0)+IF(RIGHT(Corrections!$H$46,19)="|applied|parametric",IF(COUNTIF(ValidKeys!$A$3:$A$207,LEFT(Corrections!$H$46,LEN(Corrections!$H$46)-19))=0,1,0),0)+IF(RIGHT(Corrections!$H$47,19)="|applied|parametric",IF(COUNTIF(ValidKeys!$A$3:$A$207,LEFT(Corrections!$H$47,LEN(Corrections!$H$47)-19))=0,1,0),0)+IF(RIGHT(Corrections!$H$48,19)="|applied|parametric",IF(COUNTIF(ValidKeys!$A$3:$A$207,LEFT(Corrections!$H$48,LEN(Corrections!$H$48)-19))=0,1,0),0)+IF(RIGHT(Corrections!$H$49,19)="|applied|parametric",IF(COUNTIF(ValidKeys!$A$3:$A$207,LEFT(Corrections!$H$49,LEN(Corrections!$H$49)-19))=0,1,0),0)+IF(RIGHT(Corrections!$H$50,19)="|applied|parametric",IF(COUNTIF(ValidKeys!$A$3:$A$207,LEFT(Corrections!$H$50,LEN(Corrections!$H$50)-19))=0,1,0),0)+IF(RIGHT(Corrections!$H$51,19)="|applied|parametric",IF(COUNTIF(ValidKeys!$A$3:$A$207,LEFT(Corrections!$H$51,LEN(Corrections!$H$51)-19))=0,1,0),0)+IF(RIGHT(Corrections!$H$52,19)="|applied|parametric",IF(COUNTIF(ValidKeys!$A$3:$A$207,LEFT(Corrections!$H$52,LEN(Corrections!$H$52)-19))=0,1,0),0)+IF(RIGHT(Corrections!$H$53,19)="|applied|parametric",IF(COUNTIF(ValidKeys!$A$3:$A$207,LEFT(Corrections!$H$53,LEN(Corrections!$H$53)-19))=0,1,0),0)+IF(RIGHT(Corrections!$H$54,19)="|applied|parametric",IF(COUNTIF(ValidKeys!$A$3:$A$207,LEFT(Corrections!$H$54,LEN(Corrections!$H$54)-19))=0,1,0),0)+IF(RIGHT(Corrections!$H$55,19)="|applied|parametric",IF(COUNTIF(ValidKeys!$A$3:$A$207,LEFT(Corrections!$H$55,LEN(Corrections!$H$55)-19))=0,1,0),0)+IF(RIGHT(Corrections!$H$56,19)="|applied|parametric",IF(COUNTIF(ValidKeys!$A$3:$A$207,LEFT(Corrections!$H$56,LEN(Corrections!$H$56)-19))=0,1,0),0)+IF(RIGHT(Corrections!$H$57,19)="|applied|parametric",IF(COUNTIF(ValidKeys!$A$3:$A$207,LEFT(Corrections!$H$57,LEN(Corrections!$H$57)-19))=0,1,0),0)+IF(RIGHT(Corrections!$H$58,19)="|applied|parametric",IF(COUNTIF(ValidKeys!$A$3:$A$207,LEFT(Corrections!$H$58,LEN(Corrections!$H$58)-19))=0,1,0),0)+IF(RIGHT(Corrections!$H$59,19)="|applied|parametric",IF(COUNTIF(ValidKeys!$A$3:$A$207,LEFT(Corrections!$H$59,LEN(Corrections!$H$59)-19))=0,1,0),0)+IF(RIGHT(Corrections!$H$60,19)="|applied|parametric",IF(COUNTIF(ValidKeys!$A$3:$A$207,LEFT(Corrections!$H$60,LEN(Corrections!$H$60)-19))=0,1,0),0)+IF(RIGHT(Corrections!$H$61,19)="|applied|parametric",IF(COUNTIF(ValidKeys!$A$3:$A$207,LEFT(Corrections!$H$61,LEN(Corrections!$H$61)-19))=0,1,0),0)+IF(RIGHT(Corrections!$H$62,19)="|applied|parametric",IF(COUNTIF(ValidKeys!$A$3:$A$207,LEFT(Corrections!$H$62,LEN(Corrections!$H$62)-19))=0,1,0),0)+IF(RIGHT(Corrections!$H$63,19)="|applied|parametric",IF(COUNTIF(ValidKeys!$A$3:$A$207,LEFT(Corrections!$H$63,LEN(Corrections!$H$63)-19))=0,1,0),0)+IF(RIGHT(Corrections!$H$64,19)="|applied|parametric",IF(COUNTIF(ValidKeys!$A$3:$A$207,LEFT(Corrections!$H$64,LEN(Corrections!$H$64)-19))=0,1,0),0))&" unresolved"
A19: 15 | B19: every applied parametric correction has a numeric value | C19: =IF((IF(RIGHT(Corrections!$H$5,19)="|applied|parametric",IF(ISNUMBER(Corrections!$G$5),0,1),0)+IF(RIGHT(Corrections!$H$6,19)="|applied|parametric",IF(ISNUMBER(Corrections!$G$6),0,1),0)+IF(RIGHT(Corrections!$H$7,19)="|applied|parametric",IF(ISNUMBER(Corrections!$G$7),0,1),0)+IF(RIGHT(Corrections!$H$8,19)="|applied|parametric",IF(ISNUMBER(Corrections!$G$8),0,1),0)+IF(RIGHT(Corrections!$H$9,19)="|applied|parametric",IF(ISNUMBER(Corrections!$G$9),0,1),0)+IF(RIGHT(Corrections!$H$10,19)="|applied|parametric",IF(ISNUMBER(Corrections!$G$10),0,1),0)+IF(RIGHT(Corrections!$H$11,19)="|applied|parametric",IF(ISNUMBER(Corrections!$G$11),0,1),0)+IF(RIGHT(Corrections!$H$12,19)="|applied|parametric",IF(ISNUMBER(Corrections!$G$12),0,1),0)+IF(RIGHT(Corrections!$H$13,19)="|applied|parametric",IF(ISNUMBER(Corrections!$G$13),0,1),0)+IF(RIGHT(Corrections!$H$14,19)="|applied|parametric",IF(ISNUMBER(Corrections!$G$14),0,1),0)+IF(RIGHT(Corrections!$H$15,19)="|applied|parametric",IF(ISNUMBER(Corrections!$G$15),0,1),0)+IF(RIGHT(Corrections!$H$16,19)="|applied|parametric",IF(ISNUMBER(Corrections!$G$16),0,1),0)+IF(RIGHT(Corrections!$H$17,19)="|applied|parametric",IF(ISNUMBER(Corrections!$G$17),0,1),0)+IF(RIGHT(Corrections!$H$18,19)="|applied|parametric",IF(ISNUMBER(Corrections!$G$18),0,1),0)+IF(RIGHT(Corrections!$H$19,19)="|applied|parametric",IF(ISNUMBER(Corrections!$G$19),0,1),0)+IF(RIGHT(Corrections!$H$20,19)="|applied|parametric",IF(ISNUMBER(Corrections!$G$20),0,1),0)+IF(RIGHT(Corrections!$H$21,19)="|applied|parametric",IF(ISNUMBER(Corrections!$G$21),0,1),0)+IF(RIGHT(Corrections!$H$22,19)="|applied|parametric",IF(ISNUMBER(Corrections!$G$22),0,1),0)+IF(RIGHT(Corrections!$H$23,19)="|applied|parametric",IF(ISNUMBER(Corrections!$G$23),0,1),0)+IF(RIGHT(Corrections!$H$24,19)="|applied|parametric",IF(ISNUMBER(Corrections!$G$24),0,1),0)+IF(RIGHT(Corrections!$H$25,19)="|applied|parametric",IF(ISNUMBER(Corrections!$G$25),0,1),0)+IF(RIGHT(Corrections!$H$26,19)="|applied|parametric",IF(ISNUMBER(Corrections!$G$26),0,1),0)+IF(RIGHT(Corrections!$H$27,19)="|applied|parametric",IF(ISNUMBER(Corrections!$G$27),0,1),0)+IF(RIGHT(Corrections!$H$28,19)="|applied|parametric",IF(ISNUMBER(Corrections!$G$28),0,1),0)+IF(RIGHT(Corrections!$H$29,19)="|applied|parametric",IF(ISNUMBER(Corrections!$G$29),0,1),0)+IF(RIGHT(Corrections!$H$30,19)="|applied|parametric",IF(ISNUMBER(Corrections!$G$30),0,1),0)+IF(RIGHT(Corrections!$H$31,19)="|applied|parametric",IF(ISNUMBER(Corrections!$G$31),0,1),0)+IF(RIGHT(Corrections!$H$32,19)="|applied|parametric",IF(ISNUMBER(Corrections!$G$32),0,1),0)+IF(RIGHT(Corrections!$H$33,19)="|applied|parametric",IF(ISNUMBER(Corrections!$G$33),0,1),0)+IF(RIGHT(Corrections!$H$34,19)="|applied|parametric",IF(ISNUMBER(Corrections!$G$34),0,1),0)+IF(RIGHT(Corrections!$H$35,19)="|applied|parametric",IF(ISNUMBER(Corrections!$G$35),0,1),0)+IF(RIGHT(Corrections!$H$36,19)="|applied|parametric",IF(ISNUMBER(Corrections!$G$36),0,1),0)+IF(RIGHT(Corrections!$H$37,19)="|applied|parametric",IF(ISNUMBER(Corrections!$G$37),0,1),0)+IF(RIGHT(Corrections!$H$38,19)="|applied|parametric",IF(ISNUMBER(Corrections!$G$38),0,1),0)+IF(RIGHT(Corrections!$H$39,19)="|applied|parametric",IF(ISNUMBER(Corrections!$G$39),0,1),0)+IF(RIGHT(Corrections!$H$40,19)="|applied|parametric",IF(ISNUMBER(Corrections!$G$40),0,1),0)+IF(RIGHT(Corrections!$H$41,19)="|applied|parametric",IF(ISNUMBER(Corrections!$G$41),0,1),0)+IF(RIGHT(Corrections!$H$42,19)="|applied|parametric",IF(ISNUMBER(Corrections!$G$42),0,1),0)+IF(RIGHT(Corrections!$H$43,19)="|applied|parametric",IF(ISNUMBER(Corrections!$G$43),0,1),0)+IF(RIGHT(Corrections!$H$44,19)="|applied|parametric",IF(ISNUMBER(Corrections!$G$44),0,1),0)+IF(RIGHT(Corrections!$H$45,19)="|applied|parametric",IF(ISNUMBER(Corrections!$G$45),0,1),0)+IF(RIGHT(Corrections!$H$46,19)="|applied|parametric",IF(ISNUMBER(Corrections!$G$46),0,1),0)+IF(RIGHT(Corrections!$H$47,19)="|applied|parametric",IF(ISNUMBER(Corrections!$G$47),0,1),0)+IF(RIGHT(Corrections!$H$48,19)="|applied|parametric",IF(ISNUMBER(Corrections!$G$48),0,1),0)+IF(RIGHT(Corrections!$H$49,19)="|applied|parametric",IF(ISNUMBER(Corrections!$G$49),0,1),0)+IF(RIGHT(Corrections!$H$50,19)="|applied|parametric",IF(ISNUMBER(Corrections!$G$50),0,1),0)+IF(RIGHT(Corrections!$H$51,19)="|applied|parametric",IF(ISNUMBER(Corrections!$G$51),0,1),0)+IF(RIGHT(Corrections!$H$52,19)="|applied|parametric",IF(ISNUMBER(Corrections!$G$52),0,1),0)+IF(RIGHT(Corrections!$H$53,19)="|applied|parametric",IF(ISNUMBER(Corrections!$G$53),0,1),0)+IF(RIGHT(Corrections!$H$54,19)="|applied|parametric",IF(ISNUMBER(Corrections!$G$54),0,1),0)+IF(RIGHT(Corrections!$H$55,19)="|applied|parametric",IF(ISNUMBER(Corrections!$G$55),0,1),0)+IF(RIGHT(Corrections!$H$56,19)="|applied|parametric",IF(ISNUMBER(Corrections!$G$56),0,1),0)+IF(RIGHT(Corrections!$H$57,19)="|applied|parametric",IF(ISNUMBER(Corrections!$G$57),0,1),0)+IF(RIGHT(Corrections!$H$58,19)="|applied|parametric",IF(ISNUMBER(Corrections!$G$58),0,1),0)+IF(RIGHT(Corrections!$H$59,19)="|applied|parametric",IF(ISNUMBER(Corrections!$G$59),0,1),0)+IF(RIGHT(Corrections!$H$60,19)="|applied|parametric",IF(ISNUMBER(Corrections!$G$60),0,1),0)+IF(RIGHT(Corrections!$H$61,19)="|applied|parametric",IF(ISNUMBER(Corrections!$G$61),0,1),0)+IF(RIGHT(Corrections!$H$62,19)="|applied|parametric",IF(ISNUMBER(Corrections!$G$62),0,1),0)+IF(RIGHT(Corrections!$H$63,19)="|applied|parametric",IF(ISNUMBER(Corrections!$G$63),0,1),0)+IF(RIGHT(Corrections!$H$64,19)="|applied|parametric",IF(ISNUMBER(Corrections!$G$64),0,1),0))=0,"PASS","FAIL")
A20: 16 | B20: revenue = sum of channel revenue (every month) | C20: =IF(MAX($E$60:$DS$60)<=0.005,"PASS","FAIL") | D20: =ROUND(MAX($E$60:$DS$60),6)
A21: 17 | B21: gross_profit = revenue - cogs (every month) | C21: =IF(MAX($E$61:$DS$61)<=0.005,"PASS","FAIL") | D21: =ROUND(MAX($E$61:$DS$61),6)
A22: 18 | B22: ebitda = gross_profit - opex (every month) | C22: =IF(MAX($E$62:$DS$62)<=0.005,"PASS","FAIL") | D22: =ROUND(MAX($E$62:$DS$62),6)
A23: 19 | B23: pretax = ebitda - da - interest (every month) | C23: =IF(MAX($E$63:$DS$63)<=0.005,"PASS","FAIL") | D23: =ROUND(MAX($E$63:$DS$63),6)
A24: 20 | B24: net_income = pretax - tax (every month) | C24: =IF(MAX($E$64:$DS$64)<=0.005,"PASS","FAIL") | D24: =ROUND(MAX($E$64:$DS$64),6)
A25: 21 | B25: operating_cash_flow = net_income + da + wc_cash_impact (every month) | C25: =IF(MAX($E$65:$DS$65)<=0.005,"PASS","FAIL") | D25: =ROUND(MAX($E$65:$DS$65),6)
A26: 22 | B26: free_cash_flow = ocf - capex (every month) | C26: =IF(MAX($E$66:$DS$66)<=0.005,"PASS","FAIL") | D26: =ROUND(MAX($E$66:$DS$66),6)
A27: 23 | B27: change_in_cash = fcf - principal (every month) | C27: =IF(MAX($E$67:$DS$67)<=0.005,"PASS","FAIL") | D27: =ROUND(MAX($E$67:$DS$67),6)
A28: 24 | B28: tax is never negative (every month) | C28: =IF(MAX($E$68:$DS$68)<=0.005,"PASS","FAIL") | D28: =ROUND(MAX($E$68:$DS$68),6)
A29: 25 | B29: tax-loss carryforward never negative (every month) | C29: =IF(MAX($E$69:$DS$69)<=0.005,"PASS","FAIL") | D29: =ROUND(MAX($E$69:$DS$69),6)
A30: 26 | B30: ending cash = opening cash + cumulative change in cash | C30: =IF(ABS(Summary!$B$21-(Effective!$B$14+SUM(Model!$C$78:$DR$78)))<=0.005,"PASS","FAIL") | D30: =ROUND(ABS(Summary!$B$21-(Effective!$B$14+SUM(Model!$C$78:$DR$78))),6)
A31: 27 | B31: debt roll-forward: sum opening debt - principal paid = ending debt | C31: =IF(ABS(INDEX(Model!$C$64:$DR$64,1,Effective!$B$7)-(SUM(Effective!$D$53:$D$57)-SUM(Model!$C$63:$DR$63)))<=0.005,"PASS","FAIL") | D31: =ROUND(ABS(INDEX(Model!$C$64:$DR$64,1,Effective!$B$7)-(SUM(Effective!$D$53:$D$57)-SUM(Model!$C$63:$DR$63))),6)
A32: 28 | B32: cumulative WC impact = -(closing AR - open AR) + (closing AP - open AP) - (closing inv - open inv) | C32: =IF(ABS(SUM(Model!$C$74:$DR$74)-(-(INDEX(Model!$C$71:$DR$71,1,Effective!$B$7)-Effective!$B$15)+(INDEX(Model!$C$72:$DR$72,1,Effective!$B$7)-Effective!$B$16)-(INDEX(Model!$C$73:$DR$73,1,Effective!$B$7)-Effective!$B$17)))<=0.005,"PASS","FAIL") | D32: =ROUND(ABS(SUM(Model!$C$74:$DR$74)-(-(INDEX(Model!$C$71:$DR$71,1,Effective!$B$7)-Effective!$B$15)+(INDEX(Model!$C$72:$DR$72,1,Effective!$B$7)-Effective!$B$16)-(INDEX(Model!$C$73:$DR$73,1,Effective!$B$7)-Effective!$B$17))),6)
A33: 29 | B33: GOLDEN parity with original openfpa output: revenue = 350,000,000 | C33: =IF(ABS(ROUND(Summary!$B$5,0)-(350000000))<=1,"PASS","FAIL") | D33: =ROUND(Summary!$B$5,0)
A34: 30 | B34: GOLDEN parity with original openfpa output: ebitda = 62,900,000 | C34: =IF(ABS(ROUND(Summary!$B$9,0)-(62900000))<=1,"PASS","FAIL") | D34: =ROUND(Summary!$B$9,0)
A35: 31 | B35: GOLDEN parity with original openfpa output: net_income = 35,022,779 | C35: =IF(ABS(ROUND(Summary!$B$14,0)-(35022779))<=1,"PASS","FAIL") | D35: =ROUND(Summary!$B$14,0)
A36: 32 | B36: GOLDEN parity with original openfpa output: ending_cash = 45,445,776 | C36: =IF(ABS(ROUND(Summary!$B$21,0)-(45445776))<=1,"PASS","FAIL") | D36: =ROUND(Summary!$B$21,0)
A59: Identity helper rows (absolute deviation per month)
B60: revenue = sum of channel revenue | E60: =ABS(Model!C18-SUM(Model!C10:C17)) | F60: =ABS(Model!D18-SUM(Model!D10:D17)) | G60: =ABS(Model!E18-SUM(Model!E10:E17)) | H60: =ABS(Model!F18-SUM(Model!F10:F17)) | I60: =ABS(Model!G18-SUM(Model!G10:G17)) | J60: =ABS(Model!H18-SUM(Model!H10:H17)) | K60: =ABS(Model!I18-SUM(Model!I10:I17)) | L60: =ABS(Model!J18-SUM(Model!J10:J17)) | ... DT60: =ABS(Model!DR18-SUM(Model!DR10:DR17))
B61: gross_profit = revenue - cogs | E61: =ABS(Model!C28-(Model!C18-Model!C27)) | F61: =ABS(Model!D28-(Model!D18-Model!D27)) | G61: =ABS(Model!E28-(Model!E18-Model!E27)) | H61: =ABS(Model!F28-(Model!F18-Model!F27)) | I61: =ABS(Model!G28-(Model!G18-Model!G27)) | J61: =ABS(Model!H28-(Model!H18-Model!H27)) | K61: =ABS(Model!I28-(Model!I18-Model!I27)) | L61: =ABS(Model!J28-(Model!J18-Model!J27)) | ... DT61: =ABS(Model!DR28-(Model!DR18-Model!DR27))
B62: ebitda = gross_profit - opex | E62: =ABS(Model!C45-(Model!C28-Model!C44)) | F62: =ABS(Model!D45-(Model!D28-Model!D44)) | G62: =ABS(Model!E45-(Model!E28-Model!E44)) | H62: =ABS(Model!F45-(Model!F28-Model!F44)) | I62: =ABS(Model!G45-(Model!G28-Model!G44)) | J62: =ABS(Model!H45-(Model!H28-Model!H44)) | K62: =ABS(Model!I45-(Model!I28-Model!I44)) | L62: =ABS(Model!J45-(Model!J28-Model!J44)) | ... DT62: =ABS(Model!DR45-(Model!DR28-Model!DR44))
B63: pretax = ebitda - da - interest | E63: =ABS(Model!C65-(Model!C45-Model!C46-Model!C62)) | F63: =ABS(Model!D65-(Model!D45-Model!D46-Model!D62)) | G63: =ABS(Model!E65-(Model!E45-Model!E46-Model!E62)) | H63: =ABS(Model!F65-(Model!F45-Model!F46-Model!F62)) | I63: =ABS(Model!G65-(Model!G45-Model!G46-Model!G62)) | J63: =ABS(Model!H65-(Model!H45-Model!H46-Model!H62)) | K63: =ABS(Model!I65-(Model!I45-Model!I46-Model!I62)) | L63: =ABS(Model!J65-(Model!J45-Model!J46-Model!J62)) | ... DT63: =ABS(Model!DR65-(Model!DR45-Model!DR46-Model!DR62))
B64: net_income = pretax - tax | E64: =ABS(Model!C70-(Model!C65-Model!C69)) | F64: =ABS(Model!D70-(Model!D65-Model!D69)) | G64: =ABS(Model!E70-(Model!E65-Model!E69)) | H64: =ABS(Model!F70-(Model!F65-Model!F69)) | I64: =ABS(Model!G70-(Model!G65-Model!G69)) | J64: =ABS(Model!H70-(Model!H65-Model!H69)) | K64: =ABS(Model!I70-(Model!I65-Model!I69)) | L64: =ABS(Model!J70-(Model!J65-Model!J69)) | ... DT64: =ABS(Model!DR70-(Model!DR65-Model!DR69))
B65: operating_cash_flow = net_income + da + wc_cash_impact | E65: =ABS(Model!C75-(Model!C70+Model!C46+Model!C74)) | F65: =ABS(Model!D75-(Model!D70+Model!D46+Model!D74)) | G65: =ABS(Model!E75-(Model!E70+Model!E46+Model!E74)) | H65: =ABS(Model!F75-(Model!F70+Model!F46+Model!F74)) | I65: =ABS(Model!G75-(Model!G70+Model!G46+Model!G74)) | J65: =ABS(Model!H75-(Model!H70+Model!H46+Model!H74)) | K65: =ABS(Model!I75-(Model!I70+Model!I46+Model!I74)) | L65: =ABS(Model!J75-(Model!J70+Model!J46+Model!J74)) | ... DT65: =ABS(Model!DR75-(Model!DR70+Model!DR46+Model!DR74))
B66: free_cash_flow = ocf - capex | E66: =ABS(Model!C77-(Model!C75-Model!C76)) | F66: =ABS(Model!D77-(Model!D75-Model!D76)) | G66: =ABS(Model!E77-(Model!E75-Model!E76)) | H66: =ABS(Model!F77-(Model!F75-Model!F76)) | I66: =ABS(Model!G77-(Model!G75-Model!G76)) | J66: =ABS(Model!H77-(Model!H75-Model!H76)) | K66: =ABS(Model!I77-(Model!I75-Model!I76)) | L66: =ABS(Model!J77-(Model!J75-Model!J76)) | ... DT66: =ABS(Model!DR77-(Model!DR75-Model!DR76))
B67: change_in_cash = fcf - principal | E67: =ABS(Model!C78-(Model!C77-Model!C63)) | F67: =ABS(Model!D78-(Model!D77-Model!D63)) | G67: =ABS(Model!E78-(Model!E77-Model!E63)) | H67: =ABS(Model!F78-(Model!F77-Model!F63)) | I67: =ABS(Model!G78-(Model!G77-Model!G63)) | J67: =ABS(Model!H78-(Model!H77-Model!H63)) | K67: =ABS(Model!I78-(Model!I77-Model!I63)) | L67: =ABS(Model!J78-(Model!J77-Model!J63)) | ... DT67: =ABS(Model!DR78-(Model!DR77-Model!DR63))
B68: tax is never negative | E68: =MAX(0,-Model!C69) | F68: =MAX(0,-Model!D69) | G68: =MAX(0,-Model!E69) | H68: =MAX(0,-Model!F69) | I68: =MAX(0,-Model!G69) | J68: =MAX(0,-Model!H69) | K68: =MAX(0,-Model!I69) | L68: =MAX(0,-Model!J69) | ... DT68: =MAX(0,-Model!DR69)
B69: tax-loss carryforward never negative | E69: =MAX(0,-Model!C68) | F69: =MAX(0,-Model!D68) | G69: =MAX(0,-Model!E68) | H69: =MAX(0,-Model!F68) | I69: =MAX(0,-Model!G68) | J69: =MAX(0,-Model!H68) | K69: =MAX(0,-Model!I68) | L69: =MAX(0,-Model!J68) | ... DT69: =MAX(0,-Model!DR68)

Sheet Assumptions
A1: Assumptions (inputs only - pale yellow)
A2: Edit here. Everything else is formula-driven. Keys in column A are the correction paths.
A4: key (correction path) | B4: value | C4: meaning
A5: name | B5: Kaveri Chairs Pvt Ltd (Coimbatore) - FY2026-27 budget | C5: Company / entity name
A6: start_month | B6: 46113 | C6: First forecast month (enter 1st of month)
A7: horizon_months | B7: 12 | C7: Horizon (months, 1-120)
A8: tax_rate | B8: 0.25168 | C8: Tax rate on positive pre-tax income
A9: da_monthly | B9: 900000 | C9: Depreciation & amortisation per month
A10: capex_monthly | B10: 600000 | C10: Capital expenditure per month
A11: working_capital.dso_days | B11: 52 | C11: DSO days (AR = revenue x DSO/30)
A12: working_capital.dpo_days | B12: 48 | C12: DPO days (AP = COGS x DPO/30)
A13: working_capital.dio_days | B13: 85 | C13: DIO days (Inventory = COGS x DIO/30)
A14: opening_balances.cash | B14: 11000000 | C14: Opening cash
A15: opening_balances.ar | B15: 52563570 | C15: Opening AR
A16: opening_balances.ap | B16: 28071727 | C16: Opening AP
A17: opening_balances.inventory | B17: 49710349 | C17: Opening inventory
A18: opening_balances.nol | B18: 0 | C18: Opening tax-loss carryforward (unabsorbed loss)
A19: currency_code | B19: INR | C19: Currency (ISO)
A20: currency_symbol | B20: ₹ | C20: Currency symbol for reports
A21: number_style | B21: indian | C21: Report digit grouping: indian / western
A22: display_divisor | B22: 100000 | C22: Report unit divisor (1, 1000, 100000=lakh, 10000000=crore)
A23: display_unit | B23: ₹ lakh | C23: Report unit label
A25: idx | B25: channel name | C25: annual_revenue | D25: growth_rate | E25: cogs_pct | F25: season Jan | G25: season Feb | H25: season Mar | I25: season Apr | J25: season May | K25: season Jun | L25: season Jul | M25: season Aug | N25: season Sep | O25: season Oct | P25: season Nov | Q25: season Dec
A26: 0 | B26: Dealer network (TN & Kerala) | C26: 180000000 | D26: 0.12 | E26: 0.58 | F26: 1.1 | G26: 0.85 | H26: 1 | I26: 1.05 | J26: 0.95 | K26: 0.85 | L26: 0.75 | M26: 0.9 | N26: 1.05 | O26: 1.4 | P26: 1.25 | Q26: 0.85
A27: 1 | B27: Online marketplaces (Amazon.in / Flipkart) | C27: 90000000 | D27: 0.25 | E27: 0.62 | F27: 1 | G27: 0.85 | H27: 0.95 | I27: 1 | J27: 0.95 | K27: 0.85 | L27: 0.95 | M27: 1.05 | N27: 1.15 | O27: 1.35 | P27: 1.05 | Q27: 0.85
A28: 2 | B28: D2C website & Coimbatore experience store | C28: 45000000 | D28: 0.18 | E28: 0.45 | F28: 1.15 | G28: 0.9 | H28: 0.95 | I28: 1.1 | J28: 1 | K28: 0.85 | L28: 0.75 | M28: 0.9 | N28: 1 | O28: 1.3 | P28: 1.2 | Q28: 0.9
A29: 3 | B29: Institutional (schools, hotels, offices) | C29: 35000000 | D29: 0.05 | E29: 0.64 | F29: 0.7 | G29: 0.8 | H29: 1.4 | I29: 1.1 | J29: 1.4 | K29: 1.5 | L29: 0.9 | M29: 0.8 | N29: 0.8 | O29: 0.8 | P29: 0.9 | Q29: 0.9
A30: 4
A31: 5
A32: 6
A33: 7
A35: idx | B35: opex line name | C35: kind (fixed/variable) | D35: monthly_amount | E35: pct_of_revenue
A36: 0 | B36: Payroll & benefits (from D04) | C36: fixed | D36: 3200000 | E36: 0
A37: 1 | B37: Marketing & dealer promotion | C37: variable | D37: 0 | E37: 0.06
A38: 2 | B38: Freight outward | C38: variable | D38: 0 | E38: 0.035
A39: 3 | B39: Rent & facilities (from D18) | C39: fixed | D39: 650000 | E39: 0
A40: 4 | B40: Admin, software & professional fees | C40: fixed | D40: 400000 | E40: 0
A41: 5
A42: 6
A43: 7
A44: 8
A45: 9
A46: 10
A47: 11
A48: 12
A49: 13
A50: 14
A52: idx | B52: debt instrument | C52: kind (term_loan/loc) | D52: opening_balance | E52: annual_rate | F52: monthly_principal
A53: 0 | B53: Cash credit - Indian Bank (CC) | C53: loc | D53: 32000000 | E53: 0.0975 | F53: 0
A54: 1 | B54: Term loan - TIIC (plant expansion) | C54: term_loan | D54: 24000000 | E54: 0.1025 | F54: 500000
A55: 2
A56: 3
A57: 4

Sheet Corrections
A1: Corrections (transcribed from memory/corrections/*.md)
A2: One row per correction file. Only applied + parametric rows change the model. Home of the fact = the .md file.
A4: slug | B4: type | C4: target | D4: status | E4: date | F4: override_path | G4: override_value | H4: key (formula)
A5: 2026-03-20-dealer-november-deepavali | B5: parametric | C5: channels[0].seasonality[10] | D5: applied | E5: 2026-03-20 | F5: channels[0].seasonality[10] | G5: 1.45 | H5: =IF(F5="","",SUBSTITUTE(SUBSTITUTE(F5," ",""),"*","ALL")&"|"&LOWER(D5)&"|"&LOWER(B5))
A6: 2025-12-05-cyclone-dispatch-delay | B6: context | C6: FY2025-26 November-December dealer revenue | D6: applied | E6: 2025-12-05 | H6: =IF(F6="","",SUBSTITUTE(SUBSTITUTE(F6," ",""),"*","ALL")&"|"&LOWER(D6)&"|"&LOWER(B6))
H7: =IF(F7="","",SUBSTITUTE(SUBSTITUTE(F7," ",""),"*","ALL")&"|"&LOWER(D7)&"|"&LOWER(B7))
H8: =IF(F8="","",SUBSTITUTE(SUBSTITUTE(F8," ",""),"*","ALL")&"|"&LOWER(D8)&"|"&LOWER(B8))
H9: =IF(F9="","",SUBSTITUTE(SUBSTITUTE(F9," ",""),"*","ALL")&"|"&LOWER(D9)&"|"&LOWER(B9))
H10: =IF(F10="","",SUBSTITUTE(SUBSTITUTE(F10," ",""),"*","ALL")&"|"&LOWER(D10)&"|"&LOWER(B10))
H11: =IF(F11="","",SUBSTITUTE(SUBSTITUTE(F11," ",""),"*","ALL")&"|"&LOWER(D11)&"|"&LOWER(B11))
H12: =IF(F12="","",SUBSTITUTE(SUBSTITUTE(F12," ",""),"*","ALL")&"|"&LOWER(D12)&"|"&LOWER(B12))
H13: =IF(F13="","",SUBSTITUTE(SUBSTITUTE(F13," ",""),"*","ALL")&"|"&LOWER(D13)&"|"&LOWER(B13))
H14: =IF(F14="","",SUBSTITUTE(SUBSTITUTE(F14," ",""),"*","ALL")&"|"&LOWER(D14)&"|"&LOWER(B14))
H15: =IF(F15="","",SUBSTITUTE(SUBSTITUTE(F15," ",""),"*","ALL")&"|"&LOWER(D15)&"|"&LOWER(B15))
H16: =IF(F16="","",SUBSTITUTE(SUBSTITUTE(F16," ",""),"*","ALL")&"|"&LOWER(D16)&"|"&LOWER(B16))
H17: =IF(F17="","",SUBSTITUTE(SUBSTITUTE(F17," ",""),"*","ALL")&"|"&LOWER(D17)&"|"&LOWER(B17))
H18: =IF(F18="","",SUBSTITUTE(SUBSTITUTE(F18," ",""),"*","ALL")&"|"&LOWER(D18)&"|"&LOWER(B18))
... H64: =IF(F64="","",SUBSTITUTE(SUBSTITUTE(F64," ",""),"*","ALL")&"|"&LOWER(D64)&"|"&LOWER(B64))

Sheet Effective
A1: Effective drivers = Assumptions after applied parametric corrections (formulas only)
A4: key | B4: effective value
A5: name | B5: =IF(Assumptions!B5="","",Assumptions!B5)
A6: start_month | B6: =Assumptions!B6
A7: horizon_months | B7: =Assumptions!B7
A8: tax_rate | B8: =IF(COUNTIF(Corrections!$H$5:$H$64,"tax_rate|applied|parametric")>0,SUMIF(Corrections!$H$5:$H$64,"tax_rate|applied|parametric",Corrections!$G$5:$G$64),Assumptions!B8)
A9: da_monthly | B9: =IF(COUNTIF(Corrections!$H$5:$H$64,"da_monthly|applied|parametric")>0,SUMIF(Corrections!$H$5:$H$64,"da_monthly|applied|parametric",Corrections!$G$5:$G$64),Assumptions!B9)
A10: capex_monthly | B10: =IF(COUNTIF(Corrections!$H$5:$H$64,"capex_monthly|applied|parametric")>0,SUMIF(Corrections!$H$5:$H$64,"capex_monthly|applied|parametric",Corrections!$G$5:$G$64),Assumptions!B10)
A11: working_capital.dso_days | B11: =IF(COUNTIF(Corrections!$H$5:$H$64,"working_capital.dso_days|applied|parametric")>0,SUMIF(Corrections!$H$5:$H$64,"working_capital.dso_days|applied|parametric",Corrections!$G$5:$G$64),Assumptions!B11)
A12: working_capital.dpo_days | B12: =IF(COUNTIF(Corrections!$H$5:$H$64,"working_capital.dpo_days|applied|parametric")>0,SUMIF(Corrections!$H$5:$H$64,"working_capital.dpo_days|applied|parametric",Corrections!$G$5:$G$64),Assumptions!B12)
A13: working_capital.dio_days | B13: =IF(COUNTIF(Corrections!$H$5:$H$64,"working_capital.dio_days|applied|parametric")>0,SUMIF(Corrections!$H$5:$H$64,"working_capital.dio_days|applied|parametric",Corrections!$G$5:$G$64),Assumptions!B13)
A14: opening_balances.cash | B14: =IF(COUNTIF(Corrections!$H$5:$H$64,"opening_balances.cash|applied|parametric")>0,SUMIF(Corrections!$H$5:$H$64,"opening_balances.cash|applied|parametric",Corrections!$G$5:$G$64),Assumptions!B14)
A15: opening_balances.ar | B15: =IF(COUNTIF(Corrections!$H$5:$H$64,"opening_balances.ar|applied|parametric")>0,SUMIF(Corrections!$H$5:$H$64,"opening_balances.ar|applied|parametric",Corrections!$G$5:$G$64),Assumptions!B15)
A16: opening_balances.ap | B16: =IF(COUNTIF(Corrections!$H$5:$H$64,"opening_balances.ap|applied|parametric")>0,SUMIF(Corrections!$H$5:$H$64,"opening_balances.ap|applied|parametric",Corrections!$G$5:$G$64),Assumptions!B16)
A17: opening_balances.inventory | B17: =IF(COUNTIF(Corrections!$H$5:$H$64,"opening_balances.inventory|applied|parametric")>0,SUMIF(Corrections!$H$5:$H$64,"opening_balances.inventory|applied|parametric",Corrections!$G$5:$G$64),Assumptions!B17)
A18: opening_balances.nol | B18: =IF(COUNTIF(Corrections!$H$5:$H$64,"opening_balances.nol|applied|parametric")>0,SUMIF(Corrections!$H$5:$H$64,"opening_balances.nol|applied|parametric",Corrections!$G$5:$G$64),Assumptions!B18)
A19: currency_code | B19: =IF(Assumptions!B19="","",Assumptions!B19)
A20: currency_symbol | B20: =IF(Assumptions!B20="","",Assumptions!B20)
A21: number_style | B21: =IF(Assumptions!B21="","",Assumptions!B21)
A22: display_divisor | B22: =IF(Assumptions!B22="","",Assumptions!B22)
A23: display_unit | B23: =IF(Assumptions!B23="","",Assumptions!B23)
A25: idx | B25: channel name | C25: annual_revenue | D25: growth_rate | E25: cogs_pct | F25: season Jan | G25: season Feb | H25: season Mar | I25: season Apr | J25: season May | K25: season Jun | L25: season Jul | M25: season Aug | N25: season Sep | O25: season Oct | P25: season Nov | Q25: season Dec
A26: 0 | B26: =IF(Assumptions!B26="","",TRIM(Assumptions!B26)) | C26: =IF(COUNTIF(Corrections!$H$5:$H$64,"channels[0].annual_revenue|applied|parametric")>0,SUMIF(Corrections!$H$5:$H$64,"channels[0].annual_revenue|applied|parametric",Corrections!$G$5:$G$64),IF(COUNTIF(Corrections!$H$5:$H$64,"channels[ALL].annual_revenue|applied|parametric")>0,SUMIF(Corrections!$H$5:$H$64,"channels[ALL].annual_revenue|applied|parametric",Corrections!$G$5:$G$64),N(Assumptions!C26))) | D26: =IF(COUNTIF(Corrections!$H$5:$H$64,"channels[0].growth_rate|applied|parametric")>0,SUMIF(Corrections!$H$5:$H$64,"channels[0].growth_rate|applied|parametric",Corrections!$G$5:$G$64),IF(COUNTIF(Corrections!$H$5:$H$64,"channels[ALL].growth_rate|applied|parametric")>0,SUMIF(Corrections!$H$5:$H$64,"channels[ALL].growth_rate|applied|parametric",Corrections!$G$5:$G$64),N(Assumptions!D26))) | E26: =IF(COUNTIF(Corrections!$H$5:$H$64,"channels[0].cogs_pct|applied|parametric")>0,SUMIF(Corrections!$H$5:$H$64,"channels[0].cogs_pct|applied|parametric",Corrections!$G$5:$G$64),IF(COUNTIF(Corrections!$H$5:$H$64,"channels[ALL].cogs_pct|applied|parametric")>0,SUMIF(Corrections!$H$5:$H$64,"channels[ALL].cogs_pct|applied|parametric",Corrections!$G$5:$G$64),N(Assumptions!E26))) | F26: =IF(COUNTIF(Corrections!$H$5:$H$64,"channels[0].seasonality[0]|applied|parametric")>0,SUMIF(Corrections!$H$5:$H$64,"channels[0].seasonality[0]|applied|parametric",Corrections!$G$5:$G$64),IF(COUNTIF(Corrections!$H$5:$H$64,"channels[ALL].seasonality[0]|applied|parametric")>0,SUMIF(Corrections!$H$5:$H$64,"channels[ALL].seasonality[0]|applied|parametric",Corrections!$G$5:$G$64),IF(COUNTIF(Corrections!$H$5:$H$64,"channels[0].seasonality[ALL]|applied|parametric")>0,SUMIF(Corrections!$H$5:$H$64,"channels[0].seasonality[ALL]|applied|parametric",Corrections!$G$5:$G$64),IF(COUNTIF(Corrections!$H$5:$H$64,"channels[ALL].seasonality[ALL]|applied|parametric")>0,SUMIF(Corrections!$H$5:$H$64,"channels[ALL].seasonality[ALL]|applied|parametric",Corrections!$G$5:$G$64),N(Assumptions!F26))))) | G26: =IF(COUNTIF(Corrections!$H$5:$H$64,"channels[0].seasonality[1]|applied|parametric")>0,SUMIF(Corrections!$H$5:$H$64,"channels[0].seasonality[1]|applied|parametric",Corrections!$G$5:$G$64),IF(COUNTIF(Corrections!$H$5:$H$64,"channels[ALL].seasonality[1]|applied|parametric")>0,SUMIF(Corrections!$H$5:$H$64,"channels[ALL].seasonality[1]|applied|parametric",Corrections!$G$5:$G$64),IF(COUNTIF(Corrections!$H$5:$H$64,"channels[0].seasonality[ALL]|applied|parametric")>0,SUMIF(Corrections!$H$5:$H$64,"channels[0].seasonality[ALL]|applied|parametric",Corrections!$G$5:$G$64),IF(COUNTIF(Corrections!$H$5:$H$64,"channels[ALL].seasonality[ALL]|applied|parametric")>0,SUMIF(Corrections!$H$5:$H$64,"channels[ALL].seasonality[ALL]|applied|parametric",Corrections!$G$5:$G$64),N(Assumptions!G26))))) | H26: =IF(COUNTIF(Corrections!$H$5:$H$64,"channels[0].seasonality[2]|applied|parametric")>0,SUMIF(Corrections!$H$5:$H$64,"channels[0].seasonality[2]|applied|parametric",Corrections!$G$5:$G$64),IF(COUNTIF(Corrections!$H$5:$H$64,"channels[ALL].seasonality[2]|applied|parametric")>0,SUMIF(Corrections!$H$5:$H$64,"channels[ALL].seasonality[2]|applied|parametric",Corrections!$G$5:$G$64),IF(COUNTIF(Corrections!$H$5:$H$64,"channels[0].seasonality[ALL]|applied|parametric")>0,SUMIF(Corrections!$H$5:$H$64,"channels[0].seasonality[ALL]|applied|parametric",Corrections!$G$5:$G$64),IF(COUNTIF(Corrections!$H$5:$H$64,"channels[ALL].seasonality[ALL]|applied|parametric")>0,SUMIF(Corrections!$H$5:$H$64,"channels[ALL].seasonality[ALL]|applied|parametric",Corrections!$G$5:$G$64),N(Assumptions!H26))))) | I26: =IF(COUNTIF(Corrections!$H$5:$H$64,"channels[0].seasonality[3]|applied|parametric")>0,SUMIF(Corrections!$H$5:$H$64,"channels[0].seasonality[3]|applied|parametric",Corrections!$G$5:$G$64),IF(COUNTIF(Corrections!$H$5:$H$64,"channels[ALL].seasonality[3]|applied|parametric")>0,SUMIF(Corrections!$H$5:$H$64,"channels[ALL].seasonality[3]|applied|parametric",Corrections!$G$5:$G$64),IF(COUNTIF(Corrections!$H$5:$H$64,"channels[0].seasonality[ALL]|applied|parametric")>0,SUMIF(Corrections!$H$5:$H$64,"channels[0].seasonality[ALL]|applied|parametric",Corrections!$G$5:$G$64),IF(COUNTIF(Corrections!$H$5:$H$64,"channels[ALL].seasonality[ALL]|applied|parametric")>0,SUMIF(Corrections!$H$5:$H$64,"channels[ALL].seasonality[ALL]|applied|parametric",Corrections!$G$5:$G$64),N(Assumptions!I26))))) | J26: =IF(COUNTIF(Corrections!$H$5:$H$64,"channels[0].seasonality[4]|applied|parametric")>0,SUMIF(Corrections!$H$5:$H$64,"channels[0].seasonality[4]|applied|parametric",Corrections!$G$5:$G$64),IF(COUNTIF(Corrections!$H$5:$H$64,"channels[ALL].seasonality[4]|applied|parametric")>0,SUMIF(Corrections!$H$5:$H$64,"channels[ALL].seasonality[4]|applied|parametric",Corrections!$G$5:$G$64),IF(COUNTIF(Corrections!$H$5:$H$64,"channels[0].seasonality[ALL]|applied|parametric")>0,SUMIF(Corrections!$H$5:$H$64,"channels[0].seasonality[ALL]|applied|parametric",Corrections!$G$5:$G$64),IF(COUNTIF(Corrections!$H$5:$H$64,"channels[ALL].seasonality[ALL]|applied|parametric")>0,SUMIF(Corrections!$H$5:$H$64,"channels[ALL].seasonality[ALL]|applied|parametric",Corrections!$G$5:$G$64),N(Assumptions!J26))))) | K26: =IF(COUNTIF(Corrections!$H$5:$H$64,"channels[0].seasonality[5]|applied|parametric")>0,SUMIF(Corrections!$H$5:$H$64,"channels[0].seasonality[5]|applied|parametric",Corrections!$G$5:$G$64),IF(COUNTIF(Corrections!$H$5:$H$64,"channels[ALL].seasonality[5]|applied|parametric")>0,SUMIF(Corrections!$H$5:$H$64,"channels[ALL].seasonality[5]|applied|parametric",Corrections!$G$5:$G$64),IF(COUNTIF(Corrections!$H$5:$H$64,"channels[0].seasonality[ALL]|applied|parametric")>0,SUMIF(Corrections!$H$5:$H$64,"channels[0].seasonality[ALL]|applied|parametric",Corrections!$G$5:$G$64),IF(COUNTIF(Corrections!$H$5:$H$64,"channels[ALL].seasonality[ALL]|applied|parametric")>0,SUMIF(Corrections!$H$5:$H$64,"channels[ALL].seasonality[ALL]|applied|parametric",Corrections!$G$5:$G$64),N(Assumptions!K26))))) | L26: =IF(COUNTIF(Corrections!$H$5:$H$64,"channels[0].seasonality[6]|applied|parametric")>0,SUMIF(Corrections!$H$5:$H$64,"channels[0].seasonality[6]|applied|parametric",Corrections!$G$5:$G$64),IF(COUNTIF(Corrections!$H$5:$H$64,"channels[ALL].seasonality[6]|applied|parametric")>0,SUMIF(Corrections!$H$5:$H$64,"channels[ALL].seasonality[6]|applied|parametric",Corrections!$G$5:$G$64),IF(COUNTIF(Corrections!$H$5:$H$64,"channels[0].seasonality[ALL]|applied|parametric")>0,SUMIF(Corrections!$H$5:$H$64,"channels[0].seasonality[ALL]|applied|parametric",Corrections!$G$5:$G$64),IF(COUNTIF(Corrections!$H$5:$H$64,"channels[ALL].seasonality[ALL]|applied|parametric")>0,SUMIF(Corrections!$H$5:$H$64,"channels[ALL].seasonality[ALL]|applied|parametric",Corrections!$G$5:$G$64),N(Assumptions!L26))))) | M26: =IF(COUNTIF(Corrections!$H$5:$H$64,"channels[0].seasonality[7]|applied|parametric")>0,SUMIF(Corrections!$H$5:$H$64,"channels[0].seasonality[7]|applied|parametric",Corrections!$G$5:$G$64),IF(COUNTIF(Corrections!$H$5:$H$64,"channels[ALL].seasonality[7]|applied|parametric")>0,SUMIF(Corrections!$H$5:$H$64,"channels[ALL].seasonality[7]|applied|parametric",Corrections!$G$5:$G$64),IF(COUNTIF(Corrections!$H$5:$H$64,"channels[0].seasonality[ALL]|applied|parametric")>0,SUMIF(Corrections!$H$5:$H$64,"channels[0].seasonality[ALL]|applied|parametric",Corrections!$G$5:$G$64),IF(COUNTIF(Corrections!$H$5:$H$64,"channels[ALL].seasonality[ALL]|applied|parametric")>0,SUMIF(Corrections!$H$5:$H$64,"channels[ALL].seasonality[ALL]|applied|parametric",Corrections!$G$5:$G$64),N(Assumptions!M26))))) | N26: =IF(COUNTIF(Corrections!$H$5:$H$64,"channels[0].seasonality[8]|applied|parametric")>0,SUMIF(Corrections!$H$5:$H$64,"channels[0].seasonality[8]|applied|parametric",Corrections!$G$5:$G$64),IF(COUNTIF(Corrections!$H$5:$H$64,"channels[ALL].seasonality[8]|applied|parametric")>0,SUMIF(Corrections!$H$5:$H$64,"channels[ALL].seasonality[8]|applied|parametric",Corrections!$G$5:$G$64),IF(COUNTIF(Corrections!$H$5:$H$64,"channels[0].seasonality[ALL]|applied|parametric")>0,SUMIF(Corrections!$H$5:$H$64,"channels[0].seasonality[ALL]|applied|parametric",Corrections!$G$5:$G$64),IF(COUNTIF(Corrections!$H$5:$H$64,"channels[ALL].seasonality[ALL]|applied|parametric")>0,SUMIF(Corrections!$H$5:$H$64,"channels[ALL].seasonality[ALL]|applied|parametric",Corrections!$G$5:$G$64),N(Assumptions!N26))))) | O26: =IF(COUNTIF(Corrections!$H$5:$H$64,"channels[0].seasonality[9]|applied|parametric")>0,SUMIF(Corrections!$H$5:$H$64,"channels[0].seasonality[9]|applied|parametric",Corrections!$G$5:$G$64),IF(COUNTIF(Corrections!$H$5:$H$64,"channels[ALL].seasonality[9]|applied|parametric")>0,SUMIF(Corrections!$H$5:$H$64,"channels[ALL].seasonality[9]|applied|parametric",Corrections!$G$5:$G$64),IF(COUNTIF(Corrections!$H$5:$H$64,"channels[0].seasonality[ALL]|applied|parametric")>0,SUMIF(Corrections!$H$5:$H$64,"channels[0].seasonality[ALL]|applied|parametric",Corrections!$G$5:$G$64),IF(COUNTIF(Corrections!$H$5:$H$64,"channels[ALL].seasonality[ALL]|applied|parametric")>0,SUMIF(Corrections!$H$5:$H$64,"channels[ALL].seasonality[ALL]|applied|parametric",Corrections!$G$5:$G$64),N(Assumptions!O26))))) | P26: =IF(COUNTIF(Corrections!$H$5:$H$64,"channels[0].seasonality[10]|applied|parametric")>0,SUMIF(Corrections!$H$5:$H$64,"channels[0].seasonality[10]|applied|parametric",Corrections!$G$5:$G$64),IF(COUNTIF(Corrections!$H$5:$H$64,"channels[ALL].seasonality[10]|applied|parametric")>0,SUMIF(Corrections!$H$5:$H$64,"channels[ALL].seasonality[10]|applied|parametric",Corrections!$G$5:$G$64),IF(COUNTIF(Corrections!$H$5:$H$64,"channels[0].seasonality[ALL]|applied|parametric")>0,SUMIF(Corrections!$H$5:$H$64,"channels[0].seasonality[ALL]|applied|parametric",Corrections!$G$5:$G$64),IF(COUNTIF(Corrections!$H$5:$H$64,"channels[ALL].seasonality[ALL]|applied|parametric")>0,SUMIF(Corrections!$H$5:$H$64,"channels[ALL].seasonality[ALL]|applied|parametric",Corrections!$G$5:$G$64),N(Assumptions!P26))))) | Q26: =IF(COUNTIF(Corrections!$H$5:$H$64,"channels[0].seasonality[11]|applied|parametric")>0,SUMIF(Corrections!$H$5:$H$64,"channels[0].seasonality[11]|applied|parametric",Corrections!$G$5:$G$64),IF(COUNTIF(Corrections!$H$5:$H$64,"channels[ALL].seasonality[11]|applied|parametric")>0,SUMIF(Corrections!$H$5:$H$64,"channels[ALL].seasonality[11]|applied|parametric",Corrections!$G$5:$G$64),IF(COUNTIF(Corrections!$H$5:$H$64,"channels[0].seasonality[ALL]|applied|parametric")>0,SUMIF(Corrections!$H$5:$H$64,"channels[0].seasonality[ALL]|applied|parametric",Corrections!$G$5:$G$64),IF(COUNTIF(Corrections!$H$5:$H$64,"channels[ALL].seasonality[ALL]|applied|parametric")>0,SUMIF(Corrections!$H$5:$H$64,"channels[ALL].seasonality[ALL]|applied|parametric",Corrections!$G$5:$G$64),N(Assumptions!Q26)))))
A27: 1 | B27: =IF(Assumptions!B27="","",TRIM(Assumptions!B27)) | C27: =IF(COUNTIF(Corrections!$H$5:$H$64,"channels[1].annual_revenue|applied|parametric")>0,SUMIF(Corrections!$H$5:$H$64,"channels[1].annual_revenue|applied|parametric",Corrections!$G$5:$G$64),IF(COUNTIF(Corrections!$H$5:$H$64,"channels[ALL].annual_revenue|applied|parametric")>0,SUMIF(Corrections!$H$5:$H$64,"channels[ALL].annual_revenue|applied|parametric",Corrections!$G$5:$G$64),N(Assumptions!C27))) | D27: =IF(COUNTIF(Corrections!$H$5:$H$64,"channels[1].growth_rate|applied|parametric")>0,SUMIF(Corrections!$H$5:$H$64,"channels[1].growth_rate|applied|parametric",Corrections!$G$5:$G$64),IF(COUNTIF(Corrections!$H$5:$H$64,"channels[ALL].growth_rate|applied|parametric")>0,SUMIF(Corrections!$H$5:$H$64,"channels[ALL].growth_rate|applied|parametric",Corrections!$G$5:$G$64),N(Assumptions!D27))) | E27: =IF(COUNTIF(Corrections!$H$5:$H$64,"channels[1].cogs_pct|applied|parametric")>0,SUMIF(Corrections!$H$5:$H$64,"channels[1].cogs_pct|applied|parametric",Corrections!$G$5:$G$64),IF(COUNTIF(Corrections!$H$5:$H$64,"channels[ALL].cogs_pct|applied|parametric")>0,SUMIF(Corrections!$H$5:$H$64,"channels[ALL].cogs_pct|applied|parametric",Corrections!$G$5:$G$64),N(Assumptions!E27))) | F27: =IF(COUNTIF(Corrections!$H$5:$H$64,"channels[1].seasonality[0]|applied|parametric")>0,SUMIF(Corrections!$H$5:$H$64,"channels[1].seasonality[0]|applied|parametric",Corrections!$G$5:$G$64),IF(COUNTIF(Corrections!$H$5:$H$64,"channels[ALL].seasonality[0]|applied|parametric")>0,SUMIF(Corrections!$H$5:$H$64,"channels[ALL].seasonality[0]|applied|parametric",Corrections!$G$5:$G$64),IF(COUNTIF(Corrections!$H$5:$H$64,"channels[1].seasonality[ALL]|applied|parametric")>0,SUMIF(Corrections!$H$5:$H$64,"channels[1].seasonality[ALL]|applied|parametric",Corrections!$G$5:$G$64),IF(COUNTIF(Corrections!$H$5:$H$64,"channels[ALL].seasonality[ALL]|applied|parametric")>0,SUMIF(Corrections!$H$5:$H$64,"channels[ALL].seasonality[ALL]|applied|parametric",Corrections!$G$5:$G$64),N(Assumptions!F27))))) | G27: =IF(COUNTIF(Corrections!$H$5:$H$64,"channels[1].seasonality[1]|applied|parametric")>0,SUMIF(Corrections!$H$5:$H$64,"channels[1].seasonality[1]|applied|parametric",Corrections!$G$5:$G$64),IF(COUNTIF(Corrections!$H$5:$H$64,"channels[ALL].seasonality[1]|applied|parametric")>0,SUMIF(Corrections!$H$5:$H$64,"channels[ALL].seasonality[1]|applied|parametric",Corrections!$G$5:$G$64),IF(COUNTIF(Corrections!$H$5:$H$64,"channels[1].seasonality[ALL]|applied|parametric")>0,SUMIF(Corrections!$H$5:$H$64,"channels[1].seasonality[ALL]|applied|parametric",Corrections!$G$5:$G$64),IF(COUNTIF(Corrections!$H$5:$H$64,"channels[ALL].seasonality[ALL]|applied|parametric")>0,SUMIF(Corrections!$H$5:$H$64,"channels[ALL].seasonality[ALL]|applied|parametric",Corrections!$G$5:$G$64),N(Assumptions!G27))))) | H27: =IF(COUNTIF(Corrections!$H$5:$H$64,"channels[1].seasonality[2]|applied|parametric")>0,SUMIF(Corrections!$H$5:$H$64,"channels[1].seasonality[2]|applied|parametric",Corrections!$G$5:$G$64),IF(COUNTIF(Corrections!$H$5:$H$64,"channels[ALL].seasonality[2]|applied|parametric")>0,SUMIF(Corrections!$H$5:$H$64,"channels[ALL].seasonality[2]|applied|parametric",Corrections!$G$5:$G$64),IF(COUNTIF(Corrections!$H$5:$H$64,"channels[1].seasonality[ALL]|applied|parametric")>0,SUMIF(Corrections!$H$5:$H$64,"channels[1].seasonality[ALL]|applied|parametric",Corrections!$G$5:$G$64),IF(COUNTIF(Corrections!$H$5:$H$64,"channels[ALL].seasonality[ALL]|applied|parametric")>0,SUMIF(Corrections!$H$5:$H$64,"channels[ALL].seasonality[ALL]|applied|parametric",Corrections!$G$5:$G$64),N(Assumptions!H27))))) | I27: =IF(COUNTIF(Corrections!$H$5:$H$64,"channels[1].seasonality[3]|applied|parametric")>0,SUMIF(Corrections!$H$5:$H$64,"channels[1].seasonality[3]|applied|parametric",Corrections!$G$5:$G$64),IF(COUNTIF(Corrections!$H$5:$H$64,"channels[ALL].seasonality[3]|applied|parametric")>0,SUMIF(Corrections!$H$5:$H$64,"channels[ALL].seasonality[3]|applied|parametric",Corrections!$G$5:$G$64),IF(COUNTIF(Corrections!$H$5:$H$64,"channels[1].seasonality[ALL]|applied|parametric")>0,SUMIF(Corrections!$H$5:$H$64,"channels[1].seasonality[ALL]|applied|parametric",Corrections!$G$5:$G$64),IF(COUNTIF(Corrections!$H$5:$H$64,"channels[ALL].seasonality[ALL]|applied|parametric")>0,SUMIF(Corrections!$H$5:$H$64,"channels[ALL].seasonality[ALL]|applied|parametric",Corrections!$G$5:$G$64),N(Assumptions!I27))))) | J27: =IF(COUNTIF(Corrections!$H$5:$H$64,"channels[1].seasonality[4]|applied|parametric")>0,SUMIF(Corrections!$H$5:$H$64,"channels[1].seasonality[4]|applied|parametric",Corrections!$G$5:$G$64),IF(COUNTIF(Corrections!$H$5:$H$64,"channels[ALL].seasonality[4]|applied|parametric")>0,SUMIF(Corrections!$H$5:$H$64,"channels[ALL].seasonality[4]|applied|parametric",Corrections!$G$5:$G$64),IF(COUNTIF(Corrections!$H$5:$H$64,"channels[1].seasonality[ALL]|applied|parametric")>0,SUMIF(Corrections!$H$5:$H$64,"channels[1].seasonality[ALL]|applied|parametric",Corrections!$G$5:$G$64),IF(COUNTIF(Corrections!$H$5:$H$64,"channels[ALL].seasonality[ALL]|applied|parametric")>0,SUMIF(Corrections!$H$5:$H$64,"channels[ALL].seasonality[ALL]|applied|parametric",Corrections!$G$5:$G$64),N(Assumptions!J27))))) | K27: =IF(COUNTIF(Corrections!$H$5:$H$64,"channels[1].seasonality[5]|applied|parametric")>0,SUMIF(Corrections!$H$5:$H$64,"channels[1].seasonality[5]|applied|parametric",Corrections!$G$5:$G$64),IF(COUNTIF(Corrections!$H$5:$H$64,"channels[ALL].seasonality[5]|applied|parametric")>0,SUMIF(Corrections!$H$5:$H$64,"channels[ALL].seasonality[5]|applied|parametric",Corrections!$G$5:$G$64),IF(COUNTIF(Corrections!$H$5:$H$64,"channels[1].seasonality[ALL]|applied|parametric")>0,SUMIF(Corrections!$H$5:$H$64,"channels[1].seasonality[ALL]|applied|parametric",Corrections!$G$5:$G$64),IF(COUNTIF(Corrections!$H$5:$H$64,"channels[ALL].seasonality[ALL]|applied|parametric")>0,SUMIF(Corrections!$H$5:$H$64,"channels[ALL].seasonality[ALL]|applied|parametric",Corrections!$G$5:$G$64),N(Assumptions!K27))))) | L27: =IF(COUNTIF(Corrections!$H$5:$H$64,"channels[1].seasonality[6]|applied|parametric")>0,SUMIF(Corrections!$H$5:$H$64,"channels[1].seasonality[6]|applied|parametric",Corrections!$G$5:$G$64),IF(COUNTIF(Corrections!$H$5:$H$64,"channels[ALL].seasonality[6]|applied|parametric")>0,SUMIF(Corrections!$H$5:$H$64,"channels[ALL].seasonality[6]|applied|parametric",Corrections!$G$5:$G$64),IF(COUNTIF(Corrections!$H$5:$H$64,"channels[1].seasonality[ALL]|applied|parametric")>0,SUMIF(Corrections!$H$5:$H$64,"channels[1].seasonality[ALL]|applied|parametric",Corrections!$G$5:$G$64),IF(COUNTIF(Corrections!$H$5:$H$64,"channels[ALL].seasonality[ALL]|applied|parametric")>0,SUMIF(Corrections!$H$5:$H$64,"channels[ALL].seasonality[ALL]|applied|parametric",Corrections!$G$5:$G$64),N(Assumptions!L27))))) | M27: =IF(COUNTIF(Corrections!$H$5:$H$64,"channels[1].seasonality[7]|applied|parametric")>0,SUMIF(Corrections!$H$5:$H$64,"channels[1].seasonality[7]|applied|parametric",Corrections!$G$5:$G$64),IF(COUNTIF(Corrections!$H$5:$H$64,"channels[ALL].seasonality[7]|applied|parametric")>0,SUMIF(Corrections!$H$5:$H$64,"channels[ALL].seasonality[7]|applied|parametric",Corrections!$G$5:$G$64),IF(COUNTIF(Corrections!$H$5:$H$64,"channels[1].seasonality[ALL]|applied|parametric")>0,SUMIF(Corrections!$H$5:$H$64,"channels[1].seasonality[ALL]|applied|parametric",Corrections!$G$5:$G$64),IF(COUNTIF(Corrections!$H$5:$H$64,"channels[ALL].seasonality[ALL]|applied|parametric")>0,SUMIF(Corrections!$H$5:$H$64,"channels[ALL].seasonality[ALL]|applied|parametric",Corrections!$G$5:$G$64),N(Assumptions!M27))))) | N27: =IF(COUNTIF(Corrections!$H$5:$H$64,"channels[1].seasonality[8]|applied|parametric")>0,SUMIF(Corrections!$H$5:$H$64,"channels[1].seasonality[8]|applied|parametric",Corrections!$G$5:$G$64),IF(COUNTIF(Corrections!$H$5:$H$64,"channels[ALL].seasonality[8]|applied|parametric")>0,SUMIF(Corrections!$H$5:$H$64,"channels[ALL].seasonality[8]|applied|parametric",Corrections!$G$5:$G$64),IF(COUNTIF(Corrections!$H$5:$H$64,"channels[1].seasonality[ALL]|applied|parametric")>0,SUMIF(Corrections!$H$5:$H$64,"channels[1].seasonality[ALL]|applied|parametric",Corrections!$G$5:$G$64),IF(COUNTIF(Corrections!$H$5:$H$64,"channels[ALL].seasonality[ALL]|applied|parametric")>0,SUMIF(Corrections!$H$5:$H$64,"channels[ALL].seasonality[ALL]|applied|parametric",Corrections!$G$5:$G$64),N(Assumptions!N27))))) | O27: =IF(COUNTIF(Corrections!$H$5:$H$64,"channels[1].seasonality[9]|applied|parametric")>0,SUMIF(Corrections!$H$5:$H$64,"channels[1].seasonality[9]|applied|parametric",Corrections!$G$5:$G$64),IF(COUNTIF(Corrections!$H$5:$H$64,"channels[ALL].seasonality[9]|applied|parametric")>0,SUMIF(Corrections!$H$5:$H$64,"channels[ALL].seasonality[9]|applied|parametric",Corrections!$G$5:$G$64),IF(COUNTIF(Corrections!$H$5:$H$64,"channels[1].seasonality[ALL]|applied|parametric")>0,SUMIF(Corrections!$H$5:$H$64,"channels[1].seasonality[ALL]|applied|parametric",Corrections!$G$5:$G$64),IF(COUNTIF(Corrections!$H$5:$H$64,"channels[ALL].seasonality[ALL]|applied|parametric")>0,SUMIF(Corrections!$H$5:$H$64,"channels[ALL].seasonality[ALL]|applied|parametric",Corrections!$G$5:$G$64),N(Assumptions!O27))))) | P27: =IF(COUNTIF(Corrections!$H$5:$H$64,"channels[1].seasonality[10]|applied|parametric")>0,SUMIF(Corrections!$H$5:$H$64,"channels[1].seasonality[10]|applied|parametric",Corrections!$G$5:$G$64),IF(COUNTIF(Corrections!$H$5:$H$64,"channels[ALL].seasonality[10]|applied|parametric")>0,SUMIF(Corrections!$H$5:$H$64,"channels[ALL].seasonality[10]|applied|parametric",Corrections!$G$5:$G$64),IF(COUNTIF(Corrections!$H$5:$H$64,"channels[1].seasonality[ALL]|applied|parametric")>0,SUMIF(Corrections!$H$5:$H$64,"channels[1].seasonality[ALL]|applied|parametric",Corrections!$G$5:$G$64),IF(COUNTIF(Corrections!$H$5:$H$64,"channels[ALL].seasonality[ALL]|applied|parametric")>0,SUMIF(Corrections!$H$5:$H$64,"channels[ALL].seasonality[ALL]|applied|parametric",Corrections!$G$5:$G$64),N(Assumptions!P27))))) | Q27: =IF(COUNTIF(Corrections!$H$5:$H$64,"channels[1].seasonality[11]|applied|parametric")>0,SUMIF(Corrections!$H$5:$H$64,"channels[1].seasonality[11]|applied|parametric",Corrections!$G$5:$G$64),IF(COUNTIF(Corrections!$H$5:$H$64,"channels[ALL].seasonality[11]|applied|parametric")>0,SUMIF(Corrections!$H$5:$H$64,"channels[ALL].seasonality[11]|applied|parametric",Corrections!$G$5:$G$64),IF(COUNTIF(Corrections!$H$5:$H$64,"channels[1].seasonality[ALL]|applied|parametric")>0,SUMIF(Corrections!$H$5:$H$64,"channels[1].seasonality[ALL]|applied|parametric",Corrections!$G$5:$G$64),IF(COUNTIF(Corrections!$H$5:$H$64,"channels[ALL].seasonality[ALL]|applied|parametric")>0,SUMIF(Corrections!$H$5:$H$64,"channels[ALL].seasonality[ALL]|applied|parametric",Corrections!$G$5:$G$64),N(Assumptions!Q27)))))
A28: 2 | B28: =IF(Assumptions!B28="","",TRIM(Assumptions!B28)) | C28: =IF(COUNTIF(Corrections!$H$5:$H$64,"channels[2].annual_revenue|applied|parametric")>0,SUMIF(Corrections!$H$5:$H$64,"channels[2].annual_revenue|applied|parametric",Corrections!$G$5:$G$64),IF(COUNTIF(Corrections!$H$5:$H$64,"channels[ALL].annual_revenue|applied|parametric")>0,SUMIF(Corrections!$H$5:$H$64,"channels[ALL].annual_revenue|applied|parametric",Corrections!$G$5:$G$64),N(Assumptions!C28))) | D28: =IF(COUNTIF(Corrections!$H$5:$H$64,"channels[2].growth_rate|applied|parametric")>0,SUMIF(Corrections!$H$5:$H$64,"channels[2].growth_rate|applied|parametric",Corrections!$G$5:$G$64),IF(COUNTIF(Corrections!$H$5:$H$64,"channels[ALL].growth_rate|applied|parametric")>0,SUMIF(Corrections!$H$5:$H$64,"channels[ALL].growth_rate|applied|parametric",Corrections!$G$5:$G$64),N(Assumptions!D28))) | E28: =IF(COUNTIF(Corrections!$H$5:$H$64,"channels[2].cogs_pct|applied|parametric")>0,SUMIF(Corrections!$H$5:$H$64,"channels[2].cogs_pct|applied|parametric",Corrections!$G$5:$G$64),IF(COUNTIF(Corrections!$H$5:$H$64,"channels[ALL].cogs_pct|applied|parametric")>0,SUMIF(Corrections!$H$5:$H$64,"channels[ALL].cogs_pct|applied|parametric",Corrections!$G$5:$G$64),N(Assumptions!E28))) | F28: =IF(COUNTIF(Corrections!$H$5:$H$64,"channels[2].seasonality[0]|applied|parametric")>0,SUMIF(Corrections!$H$5:$H$64,"channels[2].seasonality[0]|applied|parametric",Corrections!$G$5:$G$64),IF(COUNTIF(Corrections!$H$5:$H$64,"channels[ALL].seasonality[0]|applied|parametric")>0,SUMIF(Corrections!$H$5:$H$64,"channels[ALL].seasonality[0]|applied|parametric",Corrections!$G$5:$G$64),IF(COUNTIF(Corrections!$H$5:$H$64,"channels[2].seasonality[ALL]|applied|parametric")>0,SUMIF(Corrections!$H$5:$H$64,"channels[2].seasonality[ALL]|applied|parametric",Corrections!$G$5:$G$64),IF(COUNTIF(Corrections!$H$5:$H$64,"channels[ALL].seasonality[ALL]|applied|parametric")>0,SUMIF(Corrections!$H$5:$H$64,"channels[ALL].seasonality[ALL]|applied|parametric",Corrections!$G$5:$G$64),N(Assumptions!F28))))) | G28: =IF(COUNTIF(Corrections!$H$5:$H$64,"channels[2].seasonality[1]|applied|parametric")>0,SUMIF(Corrections!$H$5:$H$64,"channels[2].seasonality[1]|applied|parametric",Corrections!$G$5:$G$64),IF(COUNTIF(Corrections!$H$5:$H$64,"channels[ALL].seasonality[1]|applied|parametric")>0,SUMIF(Corrections!$H$5:$H$64,"channels[ALL].seasonality[1]|applied|parametric",Corrections!$G$5:$G$64),IF(COUNTIF(Corrections!$H$5:$H$64,"channels[2].seasonality[ALL]|applied|parametric")>0,SUMIF(Corrections!$H$5:$H$64,"channels[2].seasonality[ALL]|applied|parametric",Corrections!$G$5:$G$64),IF(COUNTIF(Corrections!$H$5:$H$64,"channels[ALL].seasonality[ALL]|applied|parametric")>0,SUMIF(Corrections!$H$5:$H$64,"channels[ALL].seasonality[ALL]|applied|parametric",Corrections!$G$5:$G$64),N(Assumptions!G28))))) | H28: =IF(COUNTIF(Corrections!$H$5:$H$64,"channels[2].seasonality[2]|applied|parametric")>0,SUMIF(Corrections!$H$5:$H$64,"channels[2].seasonality[2]|applied|parametric",Corrections!$G$5:$G$64),IF(COUNTIF(Corrections!$H$5:$H$64,"channels[ALL].seasonality[2]|applied|parametric")>0,SUMIF(Corrections!$H$5:$H$64,"channels[ALL].seasonality[2]|applied|parametric",Corrections!$G$5:$G$64),IF(COUNTIF(Corrections!$H$5:$H$64,"channels[2].seasonality[ALL]|applied|parametric")>0,SUMIF(Corrections!$H$5:$H$64,"channels[2].seasonality[ALL]|applied|parametric",Corrections!$G$5:$G$64),IF(COUNTIF(Corrections!$H$5:$H$64,"channels[ALL].seasonality[ALL]|applied|parametric")>0,SUMIF(Corrections!$H$5:$H$64,"channels[ALL].seasonality[ALL]|applied|parametric",Corrections!$G$5:$G$64),N(Assumptions!H28))))) | I28: =IF(COUNTIF(Corrections!$H$5:$H$64,"channels[2].seasonality[3]|applied|parametric")>0,SUMIF(Corrections!$H$5:$H$64,"channels[2].seasonality[3]|applied|parametric",Corrections!$G$5:$G$64),IF(COUNTIF(Corrections!$H$5:$H$64,"channels[ALL].seasonality[3]|applied|parametric")>0,SUMIF(Corrections!$H$5:$H$64,"channels[ALL].seasonality[3]|applied|parametric",Corrections!$G$5:$G$64),IF(COUNTIF(Corrections!$H$5:$H$64,"channels[2].seasonality[ALL]|applied|parametric")>0,SUMIF(Corrections!$H$5:$H$64,"channels[2].seasonality[ALL]|applied|parametric",Corrections!$G$5:$G$64),IF(COUNTIF(Corrections!$H$5:$H$64,"channels[ALL].seasonality[ALL]|applied|parametric")>0,SUMIF(Corrections!$H$5:$H$64,"channels[ALL].seasonality[ALL]|applied|parametric",Corrections!$G$5:$G$64),N(Assumptions!I28))))) | J28: =IF(COUNTIF(Corrections!$H$5:$H$64,"channels[2].seasonality[4]|applied|parametric")>0,SUMIF(Corrections!$H$5:$H$64,"channels[2].seasonality[4]|applied|parametric",Corrections!$G$5:$G$64),IF(COUNTIF(Corrections!$H$5:$H$64,"channels[ALL].seasonality[4]|applied|parametric")>0,SUMIF(Corrections!$H$5:$H$64,"channels[ALL].seasonality[4]|applied|parametric",Corrections!$G$5:$G$64),IF(COUNTIF(Corrections!$H$5:$H$64,"channels[2].seasonality[ALL]|applied|parametric")>0,SUMIF(Corrections!$H$5:$H$64,"channels[2].seasonality[ALL]|applied|parametric",Corrections!$G$5:$G$64),IF(COUNTIF(Corrections!$H$5:$H$64,"channels[ALL].seasonality[ALL]|applied|parametric")>0,SUMIF(Corrections!$H$5:$H$64,"channels[ALL].seasonality[ALL]|applied|parametric",Corrections!$G$5:$G$64),N(Assumptions!J28))))) | K28: =IF(COUNTIF(Corrections!$H$5:$H$64,"channels[2].seasonality[5]|applied|parametric")>0,SUMIF(Corrections!$H$5:$H$64,"channels[2].seasonality[5]|applied|parametric",Corrections!$G$5:$G$64),IF(COUNTIF(Corrections!$H$5:$H$64,"channels[ALL].seasonality[5]|applied|parametric")>0,SUMIF(Corrections!$H$5:$H$64,"channels[ALL].seasonality[5]|applied|parametric",Corrections!$G$5:$G$64),IF(COUNTIF(Corrections!$H$5:$H$64,"channels[2].seasonality[ALL]|applied|parametric")>0,SUMIF(Corrections!$H$5:$H$64,"channels[2].seasonality[ALL]|applied|parametric",Corrections!$G$5:$G$64),IF(COUNTIF(Corrections!$H$5:$H$64,"channels[ALL].seasonality[ALL]|applied|parametric")>0,SUMIF(Corrections!$H$5:$H$64,"channels[ALL].seasonality[ALL]|applied|parametric",Corrections!$G$5:$G$64),N(Assumptions!K28))))) | L28: =IF(COUNTIF(Corrections!$H$5:$H$64,"channels[2].seasonality[6]|applied|parametric")>0,SUMIF(Corrections!$H$5:$H$64,"channels[2].seasonality[6]|applied|parametric",Corrections!$G$5:$G$64),IF(COUNTIF(Corrections!$H$5:$H$64,"channels[ALL].seasonality[6]|applied|parametric")>0,SUMIF(Corrections!$H$5:$H$64,"channels[ALL].seasonality[6]|applied|parametric",Corrections!$G$5:$G$64),IF(COUNTIF(Corrections!$H$5:$H$64,"channels[2].seasonality[ALL]|applied|parametric")>0,SUMIF(Corrections!$H$5:$H$64,"channels[2].seasonality[ALL]|applied|parametric",Corrections!$G$5:$G$64),IF(COUNTIF(Corrections!$H$5:$H$64,"channels[ALL].seasonality[ALL]|applied|parametric")>0,SUMIF(Corrections!$H$5:$H$64,"channels[ALL].seasonality[ALL]|applied|parametric",Corrections!$G$5:$G$64),N(Assumptions!L28))))) | M28: =IF(COUNTIF(Corrections!$H$5:$H$64,"channels[2].seasonality[7]|applied|parametric")>0,SUMIF(Corrections!$H$5:$H$64,"channels[2].seasonality[7]|applied|parametric",Corrections!$G$5:$G$64),IF(COUNTIF(Corrections!$H$5:$H$64,"channels[ALL].seasonality[7]|applied|parametric")>0,SUMIF(Corrections!$H$5:$H$64,"channels[ALL].seasonality[7]|applied|parametric",Corrections!$G$5:$G$64),IF(COUNTIF(Corrections!$H$5:$H$64,"channels[2].seasonality[ALL]|applied|parametric")>0,SUMIF(Corrections!$H$5:$H$64,"channels[2].seasonality[ALL]|applied|parametric",Corrections!$G$5:$G$64),IF(COUNTIF(Corrections!$H$5:$H$64,"channels[ALL].seasonality[ALL]|applied|parametric")>0,SUMIF(Corrections!$H$5:$H$64,"channels[ALL].seasonality[ALL]|applied|parametric",Corrections!$G$5:$G$64),N(Assumptions!M28))))) | N28: =IF(COUNTIF(Corrections!$H$5:$H$64,"channels[2].seasonality[8]|applied|parametric")>0,SUMIF(Corrections!$H$5:$H$64,"channels[2].seasonality[8]|applied|parametric",Corrections!$G$5:$G$64),IF(COUNTIF(Corrections!$H$5:$H$64,"channels[ALL].seasonality[8]|applied|parametric")>0,SUMIF(Corrections!$H$5:$H$64,"channels[ALL].seasonality[8]|applied|parametric",Corrections!$G$5:$G$64),IF(COUNTIF(Corrections!$H$5:$H$64,"channels[2].seasonality[ALL]|applied|parametric")>0,SUMIF(Corrections!$H$5:$H$64,"channels[2].seasonality[ALL]|applied|parametric",Corrections!$G$5:$G$64),IF(COUNTIF(Corrections!$H$5:$H$64,"channels[ALL].seasonality[ALL]|applied|parametric")>0,SUMIF(Corrections!$H$5:$H$64,"channels[ALL].seasonality[ALL]|applied|parametric",Corrections!$G$5:$G$64),N(Assumptions!N28))))) | O28: =IF(COUNTIF(Corrections!$H$5:$H$64,"channels[2].seasonality[9]|applied|parametric")>0,SUMIF(Corrections!$H$5:$H$64,"channels[2].seasonality[9]|applied|parametric",Corrections!$G$5:$G$64),IF(COUNTIF(Corrections!$H$5:$H$64,"channels[ALL].seasonality[9]|applied|parametric")>0,SUMIF(Corrections!$H$5:$H$64,"channels[ALL].seasonality[9]|applied|parametric",Corrections!$G$5:$G$64),IF(COUNTIF(Corrections!$H$5:$H$64,"channels[2].seasonality[ALL]|applied|parametric")>0,SUMIF(Corrections!$H$5:$H$64,"channels[2].seasonality[ALL]|applied|parametric",Corrections!$G$5:$G$64),IF(COUNTIF(Corrections!$H$5:$H$64,"channels[ALL].seasonality[ALL]|applied|parametric")>0,SUMIF(Corrections!$H$5:$H$64,"channels[ALL].seasonality[ALL]|applied|parametric",Corrections!$G$5:$G$64),N(Assumptions!O28))))) | P28: =IF(COUNTIF(Corrections!$H$5:$H$64,"channels[2].seasonality[10]|applied|parametric")>0,SUMIF(Corrections!$H$5:$H$64,"channels[2].seasonality[10]|applied|parametric",Corrections!$G$5:$G$64),IF(COUNTIF(Corrections!$H$5:$H$64,"channels[ALL].seasonality[10]|applied|parametric")>0,SUMIF(Corrections!$H$5:$H$64,"channels[ALL].seasonality[10]|applied|parametric",Corrections!$G$5:$G$64),IF(COUNTIF(Corrections!$H$5:$H$64,"channels[2].seasonality[ALL]|applied|parametric")>0,SUMIF(Corrections!$H$5:$H$64,"channels[2].seasonality[ALL]|applied|parametric",Corrections!$G$5:$G$64),IF(COUNTIF(Corrections!$H$5:$H$64,"channels[ALL].seasonality[ALL]|applied|parametric")>0,SUMIF(Corrections!$H$5:$H$64,"channels[ALL].seasonality[ALL]|applied|parametric",Corrections!$G$5:$G$64),N(Assumptions!P28))))) | Q28: =IF(COUNTIF(Corrections!$H$5:$H$64,"channels[2].seasonality[11]|applied|parametric")>0,SUMIF(Corrections!$H$5:$H$64,"channels[2].seasonality[11]|applied|parametric",Corrections!$G$5:$G$64),IF(COUNTIF(Corrections!$H$5:$H$64,"channels[ALL].seasonality[11]|applied|parametric")>0,SUMIF(Corrections!$H$5:$H$64,"channels[ALL].seasonality[11]|applied|parametric",Corrections!$G$5:$G$64),IF(COUNTIF(Corrections!$H$5:$H$64,"channels[2].seasonality[ALL]|applied|parametric")>0,SUMIF(Corrections!$H$5:$H$64,"channels[2].seasonality[ALL]|applied|parametric",Corrections!$G$5:$G$64),IF(COUNTIF(Corrections!$H$5:$H$64,"channels[ALL].seasonality[ALL]|applied|parametric")>0,SUMIF(Corrections!$H$5:$H$64,"channels[ALL].seasonality[ALL]|applied|parametric",Corrections!$G$5:$G$64),N(Assumptions!Q28)))))
A29: 3 | B29: =IF(Assumptions!B29="","",TRIM(Assumptions!B29)) | C29: =IF(COUNTIF(Corrections!$H$5:$H$64,"channels[3].annual_revenue|applied|parametric")>0,SUMIF(Corrections!$H$5:$H$64,"channels[3].annual_revenue|applied|parametric",Corrections!$G$5:$G$64),IF(COUNTIF(Corrections!$H$5:$H$64,"channels[ALL].annual_revenue|applied|parametric")>0,SUMIF(Corrections!$H$5:$H$64,"channels[ALL].annual_revenue|applied|parametric",Corrections!$G$5:$G$64),N(Assumptions!C29))) | D29: =IF(COUNTIF(Corrections!$H$5:$H$64,"channels[3].growth_rate|applied|parametric")>0,SUMIF(Corrections!$H$5:$H$64,"channels[3].growth_rate|applied|parametric",Corrections!$G$5:$G$64),IF(COUNTIF(Corrections!$H$5:$H$64,"channels[ALL].growth_rate|applied|parametric")>0,SUMIF(Corrections!$H$5:$H$64,"channels[ALL].growth_rate|applied|parametric",Corrections!$G$5:$G$64),N(Assumptions!D29))) | E29: =IF(COUNTIF(Corrections!$H$5:$H$64,"channels[3].cogs_pct|applied|parametric")>0,SUMIF(Corrections!$H$5:$H$64,"channels[3].cogs_pct|applied|parametric",Corrections!$G$5:$G$64),IF(COUNTIF(Corrections!$H$5:$H$64,"channels[ALL].cogs_pct|applied|parametric")>0,SUMIF(Corrections!$H$5:$H$64,"channels[ALL].cogs_pct|applied|parametric",Corrections!$G$5:$G$64),N(Assumptions!E29))) | F29: =IF(COUNTIF(Corrections!$H$5:$H$64,"channels[3].seasonality[0]|applied|parametric")>0,SUMIF(Corrections!$H$5:$H$64,"channels[3].seasonality[0]|applied|parametric",Corrections!$G$5:$G$64),IF(COUNTIF(Corrections!$H$5:$H$64,"channels[ALL].seasonality[0]|applied|parametric")>0,SUMIF(Corrections!$H$5:$H$64,"channels[ALL].seasonality[0]|applied|parametric",Corrections!$G$5:$G$64),IF(COUNTIF(Corrections!$H$5:$H$64,"channels[3].seasonality[ALL]|applied|parametric")>0,SUMIF(Corrections!$H$5:$H$64,"channels[3].seasonality[ALL]|applied|parametric",Corrections!$G$5:$G$64),IF(COUNTIF(Corrections!$H$5:$H$64,"channels[ALL].seasonality[ALL]|applied|parametric")>0,SUMIF(Corrections!$H$5:$H$64,"channels[ALL].seasonality[ALL]|applied|parametric",Corrections!$G$5:$G$64),N(Assumptions!F29))))) | G29: =IF(COUNTIF(Corrections!$H$5:$H$64,"channels[3].seasonality[1]|applied|parametric")>0,SUMIF(Corrections!$H$5:$H$64,"channels[3].seasonality[1]|applied|parametric",Corrections!$G$5:$G$64),IF(COUNTIF(Corrections!$H$5:$H$64,"channels[ALL].seasonality[1]|applied|parametric")>0,SUMIF(Corrections!$H$5:$H$64,"channels[ALL].seasonality[1]|applied|parametric",Corrections!$G$5:$G$64),IF(COUNTIF(Corrections!$H$5:$H$64,"channels[3].seasonality[ALL]|applied|parametric")>0,SUMIF(Corrections!$H$5:$H$64,"channels[3].seasonality[ALL]|applied|parametric",Corrections!$G$5:$G$64),IF(COUNTIF(Corrections!$H$5:$H$64,"channels[ALL].seasonality[ALL]|applied|parametric")>0,SUMIF(Corrections!$H$5:$H$64,"channels[ALL].seasonality[ALL]|applied|parametric",Corrections!$G$5:$G$64),N(Assumptions!G29))))) | H29: =IF(COUNTIF(Corrections!$H$5:$H$64,"channels[3].seasonality[2]|applied|parametric")>0,SUMIF(Corrections!$H$5:$H$64,"channels[3].seasonality[2]|applied|parametric",Corrections!$G$5:$G$64),IF(COUNTIF(Corrections!$H$5:$H$64,"channels[ALL].seasonality[2]|applied|parametric")>0,SUMIF(Corrections!$H$5:$H$64,"channels[ALL].seasonality[2]|applied|parametric",Corrections!$G$5:$G$64),IF(COUNTIF(Corrections!$H$5:$H$64,"channels[3].seasonality[ALL]|applied|parametric")>0,SUMIF(Corrections!$H$5:$H$64,"channels[3].seasonality[ALL]|applied|parametric",Corrections!$G$5:$G$64),IF(COUNTIF(Corrections!$H$5:$H$64,"channels[ALL].seasonality[ALL]|applied|parametric")>0,SUMIF(Corrections!$H$5:$H$64,"channels[ALL].seasonality[ALL]|applied|parametric",Corrections!$G$5:$G$64),N(Assumptions!H29))))) | I29: =IF(COUNTIF(Corrections!$H$5:$H$64,"channels[3].seasonality[3]|applied|parametric")>0,SUMIF(Corrections!$H$5:$H$64,"channels[3].seasonality[3]|applied|parametric",Corrections!$G$5:$G$64),IF(COUNTIF(Corrections!$H$5:$H$64,"channels[ALL].seasonality[3]|applied|parametric")>0,SUMIF(Corrections!$H$5:$H$64,"channels[ALL].seasonality[3]|applied|parametric",Corrections!$G$5:$G$64),IF(COUNTIF(Corrections!$H$5:$H$64,"channels[3].seasonality[ALL]|applied|parametric")>0,SUMIF(Corrections!$H$5:$H$64,"channels[3].seasonality[ALL]|applied|parametric",Corrections!$G$5:$G$64),IF(COUNTIF(Corrections!$H$5:$H$64,"channels[ALL].seasonality[ALL]|applied|parametric")>0,SUMIF(Corrections!$H$5:$H$64,"channels[ALL].seasonality[ALL]|applied|parametric",Corrections!$G$5:$G$64),N(Assumptions!I29))))) | J29: =IF(COUNTIF(Corrections!$H$5:$H$64,"channels[3].seasonality[4]|applied|parametric")>0,SUMIF(Corrections!$H$5:$H$64,"channels[3].seasonality[4]|applied|parametric",Corrections!$G$5:$G$64),IF(COUNTIF(Corrections!$H$5:$H$64,"channels[ALL].seasonality[4]|applied|parametric")>0,SUMIF(Corrections!$H$5:$H$64,"channels[ALL].seasonality[4]|applied|parametric",Corrections!$G$5:$G$64),IF(COUNTIF(Corrections!$H$5:$H$64,"channels[3].seasonality[ALL]|applied|parametric")>0,SUMIF(Corrections!$H$5:$H$64,"channels[3].seasonality[ALL]|applied|parametric",Corrections!$G$5:$G$64),IF(COUNTIF(Corrections!$H$5:$H$64,"channels[ALL].seasonality[ALL]|applied|parametric")>0,SUMIF(Corrections!$H$5:$H$64,"channels[ALL].seasonality[ALL]|applied|parametric",Corrections!$G$5:$G$64),N(Assumptions!J29))))) | K29: =IF(COUNTIF(Corrections!$H$5:$H$64,"channels[3].seasonality[5]|applied|parametric")>0,SUMIF(Corrections!$H$5:$H$64,"channels[3].seasonality[5]|applied|parametric",Corrections!$G$5:$G$64),IF(COUNTIF(Corrections!$H$5:$H$64,"channels[ALL].seasonality[5]|applied|parametric")>0,SUMIF(Corrections!$H$5:$H$64,"channels[ALL].seasonality[5]|applied|parametric",Corrections!$G$5:$G$64),IF(COUNTIF(Corrections!$H$5:$H$64,"channels[3].seasonality[ALL]|applied|parametric")>0,SUMIF(Corrections!$H$5:$H$64,"channels[3].seasonality[ALL]|applied|parametric",Corrections!$G$5:$G$64),IF(COUNTIF(Corrections!$H$5:$H$64,"channels[ALL].seasonality[ALL]|applied|parametric")>0,SUMIF(Corrections!$H$5:$H$64,"channels[ALL].seasonality[ALL]|applied|parametric",Corrections!$G$5:$G$64),N(Assumptions!K29))))) | L29: =IF(COUNTIF(Corrections!$H$5:$H$64,"channels[3].seasonality[6]|applied|parametric")>0,SUMIF(Corrections!$H$5:$H$64,"channels[3].seasonality[6]|applied|parametric",Corrections!$G$5:$G$64),IF(COUNTIF(Corrections!$H$5:$H$64,"channels[ALL].seasonality[6]|applied|parametric")>0,SUMIF(Corrections!$H$5:$H$64,"channels[ALL].seasonality[6]|applied|parametric",Corrections!$G$5:$G$64),IF(COUNTIF(Corrections!$H$5:$H$64,"channels[3].seasonality[ALL]|applied|parametric")>0,SUMIF(Corrections!$H$5:$H$64,"channels[3].seasonality[ALL]|applied|parametric",Corrections!$G$5:$G$64),IF(COUNTIF(Corrections!$H$5:$H$64,"channels[ALL].seasonality[ALL]|applied|parametric")>0,SUMIF(Corrections!$H$5:$H$64,"channels[ALL].seasonality[ALL]|applied|parametric",Corrections!$G$5:$G$64),N(Assumptions!L29))))) | M29: =IF(COUNTIF(Corrections!$H$5:$H$64,"channels[3].seasonality[7]|applied|parametric")>0,SUMIF(Corrections!$H$5:$H$64,"channels[3].seasonality[7]|applied|parametric",Corrections!$G$5:$G$64),IF(COUNTIF(Corrections!$H$5:$H$64,"channels[ALL].seasonality[7]|applied|parametric")>0,SUMIF(Corrections!$H$5:$H$64,"channels[ALL].seasonality[7]|applied|parametric",Corrections!$G$5:$G$64),IF(COUNTIF(Corrections!$H$5:$H$64,"channels[3].seasonality[ALL]|applied|parametric")>0,SUMIF(Corrections!$H$5:$H$64,"channels[3].seasonality[ALL]|applied|parametric",Corrections!$G$5:$G$64),IF(COUNTIF(Corrections!$H$5:$H$64,"channels[ALL].seasonality[ALL]|applied|parametric")>0,SUMIF(Corrections!$H$5:$H$64,"channels[ALL].seasonality[ALL]|applied|parametric",Corrections!$G$5:$G$64),N(Assumptions!M29))))) | N29: =IF(COUNTIF(Corrections!$H$5:$H$64,"channels[3].seasonality[8]|applied|parametric")>0,SUMIF(Corrections!$H$5:$H$64,"channels[3].seasonality[8]|applied|parametric",Corrections!$G$5:$G$64),IF(COUNTIF(Corrections!$H$5:$H$64,"channels[ALL].seasonality[8]|applied|parametric")>0,SUMIF(Corrections!$H$5:$H$64,"channels[ALL].seasonality[8]|applied|parametric",Corrections!$G$5:$G$64),IF(COUNTIF(Corrections!$H$5:$H$64,"channels[3].seasonality[ALL]|applied|parametric")>0,SUMIF(Corrections!$H$5:$H$64,"channels[3].seasonality[ALL]|applied|parametric",Corrections!$G$5:$G$64),IF(COUNTIF(Corrections!$H$5:$H$64,"channels[ALL].seasonality[ALL]|applied|parametric")>0,SUMIF(Corrections!$H$5:$H$64,"channels[ALL].seasonality[ALL]|applied|parametric",Corrections!$G$5:$G$64),N(Assumptions!N29))))) | O29: =IF(COUNTIF(Corrections!$H$5:$H$64,"channels[3].seasonality[9]|applied|parametric")>0,SUMIF(Corrections!$H$5:$H$64,"channels[3].seasonality[9]|applied|parametric",Corrections!$G$5:$G$64),IF(COUNTIF(Corrections!$H$5:$H$64,"channels[ALL].seasonality[9]|applied|parametric")>0,SUMIF(Corrections!$H$5:$H$64,"channels[ALL].seasonality[9]|applied|parametric",Corrections!$G$5:$G$64),IF(COUNTIF(Corrections!$H$5:$H$64,"channels[3].seasonality[ALL]|applied|parametric")>0,SUMIF(Corrections!$H$5:$H$64,"channels[3].seasonality[ALL]|applied|parametric",Corrections!$G$5:$G$64),IF(COUNTIF(Corrections!$H$5:$H$64,"channels[ALL].seasonality[ALL]|applied|parametric")>0,SUMIF(Corrections!$H$5:$H$64,"channels[ALL].seasonality[ALL]|applied|parametric",Corrections!$G$5:$G$64),N(Assumptions!O29))))) | P29: =IF(COUNTIF(Corrections!$H$5:$H$64,"channels[3].seasonality[10]|applied|parametric")>0,SUMIF(Corrections!$H$5:$H$64,"channels[3].seasonality[10]|applied|parametric",Corrections!$G$5:$G$64),IF(COUNTIF(Corrections!$H$5:$H$64,"channels[ALL].seasonality[10]|applied|parametric")>0,SUMIF(Corrections!$H$5:$H$64,"channels[ALL].seasonality[10]|applied|parametric",Corrections!$G$5:$G$64),IF(COUNTIF(Corrections!$H$5:$H$64,"channels[3].seasonality[ALL]|applied|parametric")>0,SUMIF(Corrections!$H$5:$H$64,"channels[3].seasonality[ALL]|applied|parametric",Corrections!$G$5:$G$64),IF(COUNTIF(Corrections!$H$5:$H$64,"channels[ALL].seasonality[ALL]|applied|parametric")>0,SUMIF(Corrections!$H$5:$H$64,"channels[ALL].seasonality[ALL]|applied|parametric",Corrections!$G$5:$G$64),N(Assumptions!P29))))) | Q29: =IF(COUNTIF(Corrections!$H$5:$H$64,"channels[3].seasonality[11]|applied|parametric")>0,SUMIF(Corrections!$H$5:$H$64,"channels[3].seasonality[11]|applied|parametric",Corrections!$G$5:$G$64),IF(COUNTIF(Corrections!$H$5:$H$64,"channels[ALL].seasonality[11]|applied|parametric")>0,SUMIF(Corrections!$H$5:$H$64,"channels[ALL].seasonality[11]|applied|parametric",Corrections!$G$5:$G$64),IF(COUNTIF(Corrections!$H$5:$H$64,"channels[3].seasonality[ALL]|applied|parametric")>0,SUMIF(Corrections!$H$5:$H$64,"channels[3].seasonality[ALL]|applied|parametric",Corrections!$G$5:$G$64),IF(COUNTIF(Corrections!$H$5:$H$64,"channels[ALL].seasonality[ALL]|applied|parametric")>0,SUMIF(Corrections!$H$5:$H$64,"channels[ALL].seasonality[ALL]|applied|parametric",Corrections!$G$5:$G$64),N(Assumptions!Q29)))))
A30: 4 | B30: =IF(Assumptions!B30="","",TRIM(Assumptions!B30)) | C30: =IF(COUNTIF(Corrections!$H$5:$H$64,"channels[4].annual_revenue|applied|parametric")>0,SUMIF(Corrections!$H$5:$H$64,"channels[4].annual_revenue|applied|parametric",Corrections!$G$5:$G$64),IF(COUNTIF(Corrections!$H$5:$H$64,"channels[ALL].annual_revenue|applied|parametric")>0,SUMIF(Corrections!$H$5:$H$64,"channels[ALL].annual_revenue|applied|parametric",Corrections!$G$5:$G$64),N(Assumptions!C30))) | D30: =IF(COUNTIF(Corrections!$H$5:$H$64,"channels[4].growth_rate|applied|parametric")>0,SUMIF(Corrections!$H$5:$H$64,"channels[4].growth_rate|applied|parametric",Corrections!$G$5:$G$64),IF(COUNTIF(Corrections!$H$5:$H$64,"channels[ALL].growth_rate|applied|parametric")>0,SUMIF(Corrections!$H$5:$H$64,"channels[ALL].growth_rate|applied|parametric",Corrections!$G$5:$G$64),N(Assumptions!D30))) | E30: =IF(COUNTIF(Corrections!$H$5:$H$64,"channels[4].cogs_pct|applied|parametric")>0,SUMIF(Corrections!$H$5:$H$64,"channels[4].cogs_pct|applied|parametric",Corrections!$G$5:$G$64),IF(COUNTIF(Corrections!$H$5:$H$64,"channels[ALL].cogs_pct|applied|parametric")>0,SUMIF(Corrections!$H$5:$H$64,"channels[ALL].cogs_pct|applied|parametric",Corrections!$G$5:$G$64),N(Assumptions!E30))) | F30: =IF(COUNTIF(Corrections!$H$5:$H$64,"channels[4].seasonality[0]|applied|parametric")>0,SUMIF(Corrections!$H$5:$H$64,"channels[4].seasonality[0]|applied|parametric",Corrections!$G$5:$G$64),IF(COUNTIF(Corrections!$H$5:$H$64,"channels[ALL].seasonality[0]|applied|parametric")>0,SUMIF(Corrections!$H$5:$H$64,"channels[ALL].seasonality[0]|applied|parametric",Corrections!$G$5:$G$64),IF(COUNTIF(Corrections!$H$5:$H$64,"channels[4].seasonality[ALL]|applied|parametric")>0,SUMIF(Corrections!$H$5:$H$64,"channels[4].seasonality[ALL]|applied|parametric",Corrections!$G$5:$G$64),IF(COUNTIF(Corrections!$H$5:$H$64,"channels[ALL].seasonality[ALL]|applied|parametric")>0,SUMIF(Corrections!$H$5:$H$64,"channels[ALL].seasonality[ALL]|applied|parametric",Corrections!$G$5:$G$64),N(Assumptions!F30))))) | G30: =IF(COUNTIF(Corrections!$H$5:$H$64,"channels[4].seasonality[1]|applied|parametric")>0,SUMIF(Corrections!$H$5:$H$64,"channels[4].seasonality[1]|applied|parametric",Corrections!$G$5:$G$64),IF(COUNTIF(Corrections!$H$5:$H$64,"channels[ALL].seasonality[1]|applied|parametric")>0,SUMIF(Corrections!$H$5:$H$64,"channels[ALL].seasonality[1]|applied|parametric",Corrections!$G$5:$G$64),IF(COUNTIF(Corrections!$H$5:$H$64,"channels[4].seasonality[ALL]|applied|parametric")>0,SUMIF(Corrections!$H$5:$H$64,"channels[4].seasonality[ALL]|applied|parametric",Corrections!$G$5:$G$64),IF(COUNTIF(Corrections!$H$5:$H$64,"channels[ALL].seasonality[ALL]|applied|parametric")>0,SUMIF(Corrections!$H$5:$H$64,"channels[ALL].seasonality[ALL]|applied|parametric",Corrections!$G$5:$G$64),N(Assumptions!G30))))) | H30: =IF(COUNTIF(Corrections!$H$5:$H$64,"channels[4].seasonality[2]|applied|parametric")>0,SUMIF(Corrections!$H$5:$H$64,"channels[4].seasonality[2]|applied|parametric",Corrections!$G$5:$G$64),IF(COUNTIF(Corrections!$H$5:$H$64,"channels[ALL].seasonality[2]|applied|parametric")>0,SUMIF(Corrections!$H$5:$H$64,"channels[ALL].seasonality[2]|applied|parametric",Corrections!$G$5:$G$64),IF(COUNTIF(Corrections!$H$5:$H$64,"channels[4].seasonality[ALL]|applied|parametric")>0,SUMIF(Corrections!$H$5:$H$64,"channels[4].seasonality[ALL]|applied|parametric",Corrections!$G$5:$G$64),IF(COUNTIF(Corrections!$H$5:$H$64,"channels[ALL].seasonality[ALL]|applied|parametric")>0,SUMIF(Corrections!$H$5:$H$64,"channels[ALL].seasonality[ALL]|applied|parametric",Corrections!$G$5:$G$64),N(Assumptions!H30))))) | I30: =IF(COUNTIF(Corrections!$H$5:$H$64,"channels[4].seasonality[3]|applied|parametric")>0,SUMIF(Corrections!$H$5:$H$64,"channels[4].seasonality[3]|applied|parametric",Corrections!$G$5:$G$64),IF(COUNTIF(Corrections!$H$5:$H$64,"channels[ALL].seasonality[3]|applied|parametric")>0,SUMIF(Corrections!$H$5:$H$64,"channels[ALL].seasonality[3]|applied|parametric",Corrections!$G$5:$G$64),IF(COUNTIF(Corrections!$H$5:$H$64,"channels[4].seasonality[ALL]|applied|parametric")>0,SUMIF(Corrections!$H$5:$H$64,"channels[4].seasonality[ALL]|applied|parametric",Corrections!$G$5:$G$64),IF(COUNTIF(Corrections!$H$5:$H$64,"channels[ALL].seasonality[ALL]|applied|parametric")>0,SUMIF(Corrections!$H$5:$H$64,"channels[ALL].seasonality[ALL]|applied|parametric",Corrections!$G$5:$G$64),N(Assumptions!I30))))) | J30: =IF(COUNTIF(Corrections!$H$5:$H$64,"channels[4].seasonality[4]|applied|parametric")>0,SUMIF(Corrections!$H$5:$H$64,"channels[4].seasonality[4]|applied|parametric",Corrections!$G$5:$G$64),IF(COUNTIF(Corrections!$H$5:$H$64,"channels[ALL].seasonality[4]|applied|parametric")>0,SUMIF(Corrections!$H$5:$H$64,"channels[ALL].seasonality[4]|applied|parametric",Corrections!$G$5:$G$64),IF(COUNTIF(Corrections!$H$5:$H$64,"channels[4].seasonality[ALL]|applied|parametric")>0,SUMIF(Corrections!$H$5:$H$64,"channels[4].seasonality[ALL]|applied|parametric",Corrections!$G$5:$G$64),IF(COUNTIF(Corrections!$H$5:$H$64,"channels[ALL].seasonality[ALL]|applied|parametric")>0,SUMIF(Corrections!$H$5:$H$64,"channels[ALL].seasonality[ALL]|applied|parametric",Corrections!$G$5:$G$64),N(Assumptions!J30))))) | K30: =IF(COUNTIF(Corrections!$H$5:$H$64,"channels[4].seasonality[5]|applied|parametric")>0,SUMIF(Corrections!$H$5:$H$64,"channels[4].seasonality[5]|applied|parametric",Corrections!$G$5:$G$64),IF(COUNTIF(Corrections!$H$5:$H$64,"channels[ALL].seasonality[5]|applied|parametric")>0,SUMIF(Corrections!$H$5:$H$64,"channels[ALL].seasonality[5]|applied|parametric",Corrections!$G$5:$G$64),IF(COUNTIF(Corrections!$H$5:$H$64,"channels[4].seasonality[ALL]|applied|parametric")>0,SUMIF(Corrections!$H$5:$H$64,"channels[4].seasonality[ALL]|applied|parametric",Corrections!$G$5:$G$64),IF(COUNTIF(Corrections!$H$5:$H$64,"channels[ALL].seasonality[ALL]|applied|parametric")>0,SUMIF(Corrections!$H$5:$H$64,"channels[ALL].seasonality[ALL]|applied|parametric",Corrections!$G$5:$G$64),N(Assumptions!K30))))) | L30: =IF(COUNTIF(Corrections!$H$5:$H$64,"channels[4].seasonality[6]|applied|parametric")>0,SUMIF(Corrections!$H$5:$H$64,"channels[4].seasonality[6]|applied|parametric",Corrections!$G$5:$G$64),IF(COUNTIF(Corrections!$H$5:$H$64,"channels[ALL].seasonality[6]|applied|parametric")>0,SUMIF(Corrections!$H$5:$H$64,"channels[ALL].seasonality[6]|applied|parametric",Corrections!$G$5:$G$64),IF(COUNTIF(Corrections!$H$5:$H$64,"channels[4].seasonality[ALL]|applied|parametric")>0,SUMIF(Corrections!$H$5:$H$64,"channels[4].seasonality[ALL]|applied|parametric",Corrections!$G$5:$G$64),IF(COUNTIF(Corrections!$H$5:$H$64,"channels[ALL].seasonality[ALL]|applied|parametric")>0,SUMIF(Corrections!$H$5:$H$64,"channels[ALL].seasonality[ALL]|applied|parametric",Corrections!$G$5:$G$64),N(Assumptions!L30))))) | M30: =IF(COUNTIF(Corrections!$H$5:$H$64,"channels[4].seasonality[7]|applied|parametric")>0,SUMIF(Corrections!$H$5:$H$64,"channels[4].seasonality[7]|applied|parametric",Corrections!$G$5:$G$64),IF(COUNTIF(Corrections!$H$5:$H$64,"channels[ALL].seasonality[7]|applied|parametric")>0,SUMIF(Corrections!$H$5:$H$64,"channels[ALL].seasonality[7]|applied|parametric",Corrections!$G$5:$G$64),IF(COUNTIF(Corrections!$H$5:$H$64,"channels[4].seasonality[ALL]|applied|parametric")>0,SUMIF(Corrections!$H$5:$H$64,"channels[4].seasonality[ALL]|applied|parametric",Corrections!$G$5:$G$64),IF(COUNTIF(Corrections!$H$5:$H$64,"channels[ALL].seasonality[ALL]|applied|parametric")>0,SUMIF(Corrections!$H$5:$H$64,"channels[ALL].seasonality[ALL]|applied|parametric",Corrections!$G$5:$G$64),N(Assumptions!M30))))) | N30: =IF(COUNTIF(Corrections!$H$5:$H$64,"channels[4].seasonality[8]|applied|parametric")>0,SUMIF(Corrections!$H$5:$H$64,"channels[4].seasonality[8]|applied|parametric",Corrections!$G$5:$G$64),IF(COUNTIF(Corrections!$H$5:$H$64,"channels[ALL].seasonality[8]|applied|parametric")>0,SUMIF(Corrections!$H$5:$H$64,"channels[ALL].seasonality[8]|applied|parametric",Corrections!$G$5:$G$64),IF(COUNTIF(Corrections!$H$5:$H$64,"channels[4].seasonality[ALL]|applied|parametric")>0,SUMIF(Corrections!$H$5:$H$64,"channels[4].seasonality[ALL]|applied|parametric",Corrections!$G$5:$G$64),IF(COUNTIF(Corrections!$H$5:$H$64,"channels[ALL].seasonality[ALL]|applied|parametric")>0,SUMIF(Corrections!$H$5:$H$64,"channels[ALL].seasonality[ALL]|applied|parametric",Corrections!$G$5:$G$64),N(Assumptions!N30))))) | O30: =IF(COUNTIF(Corrections!$H$5:$H$64,"channels[4].seasonality[9]|applied|parametric")>0,SUMIF(Corrections!$H$5:$H$64,"channels[4].seasonality[9]|applied|parametric",Corrections!$G$5:$G$64),IF(COUNTIF(Corrections!$H$5:$H$64,"channels[ALL].seasonality[9]|applied|parametric")>0,SUMIF(Corrections!$H$5:$H$64,"channels[ALL].seasonality[9]|applied|parametric",Corrections!$G$5:$G$64),IF(COUNTIF(Corrections!$H$5:$H$64,"channels[4].seasonality[ALL]|applied|parametric")>0,SUMIF(Corrections!$H$5:$H$64,"channels[4].seasonality[ALL]|applied|parametric",Corrections!$G$5:$G$64),IF(COUNTIF(Corrections!$H$5:$H$64,"channels[ALL].seasonality[ALL]|applied|parametric")>0,SUMIF(Corrections!$H$5:$H$64,"channels[ALL].seasonality[ALL]|applied|parametric",Corrections!$G$5:$G$64),N(Assumptions!O30))))) | P30: =IF(COUNTIF(Corrections!$H$5:$H$64,"channels[4].seasonality[10]|applied|parametric")>0,SUMIF(Corrections!$H$5:$H$64,"channels[4].seasonality[10]|applied|parametric",Corrections!$G$5:$G$64),IF(COUNTIF(Corrections!$H$5:$H$64,"channels[ALL].seasonality[10]|applied|parametric")>0,SUMIF(Corrections!$H$5:$H$64,"channels[ALL].seasonality[10]|applied|parametric",Corrections!$G$5:$G$64),IF(COUNTIF(Corrections!$H$5:$H$64,"channels[4].seasonality[ALL]|applied|parametric")>0,SUMIF(Corrections!$H$5:$H$64,"channels[4].seasonality[ALL]|applied|parametric",Corrections!$G$5:$G$64),IF(COUNTIF(Corrections!$H$5:$H$64,"channels[ALL].seasonality[ALL]|applied|parametric")>0,SUMIF(Corrections!$H$5:$H$64,"channels[ALL].seasonality[ALL]|applied|parametric",Corrections!$G$5:$G$64),N(Assumptions!P30))))) | Q30: =IF(COUNTIF(Corrections!$H$5:$H$64,"channels[4].seasonality[11]|applied|parametric")>0,SUMIF(Corrections!$H$5:$H$64,"channels[4].seasonality[11]|applied|parametric",Corrections!$G$5:$G$64),IF(COUNTIF(Corrections!$H$5:$H$64,"channels[ALL].seasonality[11]|applied|parametric")>0,SUMIF(Corrections!$H$5:$H$64,"channels[ALL].seasonality[11]|applied|parametric",Corrections!$G$5:$G$64),IF(COUNTIF(Corrections!$H$5:$H$64,"channels[4].seasonality[ALL]|applied|parametric")>0,SUMIF(Corrections!$H$5:$H$64,"channels[4].seasonality[ALL]|applied|parametric",Corrections!$G$5:$G$64),IF(COUNTIF(Corrections!$H$5:$H$64,"channels[ALL].seasonality[ALL]|applied|parametric")>0,SUMIF(Corrections!$H$5:$H$64,"channels[ALL].seasonality[ALL]|applied|parametric",Corrections!$G$5:$G$64),N(Assumptions!Q30)))))
A31: 5 | B31: =IF(Assumptions!B31="","",TRIM(Assumptions!B31)) | C31: =IF(COUNTIF(Corrections!$H$5:$H$64,"channels[5].annual_revenue|applied|parametric")>0,SUMIF(Corrections!$H$5:$H$64,"channels[5].annual_revenue|applied|parametric",Corrections!$G$5:$G$64),IF(COUNTIF(Corrections!$H$5:$H$64,"channels[ALL].annual_revenue|applied|parametric")>0,SUMIF(Corrections!$H$5:$H$64,"channels[ALL].annual_revenue|applied|parametric",Corrections!$G$5:$G$64),N(Assumptions!C31))) | D31: =IF(COUNTIF(Corrections!$H$5:$H$64,"channels[5].growth_rate|applied|parametric")>0,SUMIF(Corrections!$H$5:$H$64,"channels[5].growth_rate|applied|parametric",Corrections!$G$5:$G$64),IF(COUNTIF(Corrections!$H$5:$H$64,"channels[ALL].growth_rate|applied|parametric")>0,SUMIF(Corrections!$H$5:$H$64,"channels[ALL].growth_rate|applied|parametric",Corrections!$G$5:$G$64),N(Assumptions!D31))) | E31: =IF(COUNTIF(Corrections!$H$5:$H$64,"channels[5].cogs_pct|applied|parametric")>0,SUMIF(Corrections!$H$5:$H$64,"channels[5].cogs_pct|applied|parametric",Corrections!$G$5:$G$64),IF(COUNTIF(Corrections!$H$5:$H$64,"channels[ALL].cogs_pct|applied|parametric")>0,SUMIF(Corrections!$H$5:$H$64,"channels[ALL].cogs_pct|applied|parametric",Corrections!$G$5:$G$64),N(Assumptions!E31))) | F31: =IF(COUNTIF(Corrections!$H$5:$H$64,"channels[5].seasonality[0]|applied|parametric")>0,SUMIF(Corrections!$H$5:$H$64,"channels[5].seasonality[0]|applied|parametric",Corrections!$G$5:$G$64),IF(COUNTIF(Corrections!$H$5:$H$64,"channels[ALL].seasonality[0]|applied|parametric")>0,SUMIF(Corrections!$H$5:$H$64,"channels[ALL].seasonality[0]|applied|parametric",Corrections!$G$5:$G$64),IF(COUNTIF(Corrections!$H$5:$H$64,"channels[5].seasonality[ALL]|applied|parametric")>0,SUMIF(Corrections!$H$5:$H$64,"channels[5].seasonality[ALL]|applied|parametric",Corrections!$G$5:$G$64),IF(COUNTIF(Corrections!$H$5:$H$64,"channels[ALL].seasonality[ALL]|applied|parametric")>0,SUMIF(Corrections!$H$5:$H$64,"channels[ALL].seasonality[ALL]|applied|parametric",Corrections!$G$5:$G$64),N(Assumptions!F31))))) | G31: =IF(COUNTIF(Corrections!$H$5:$H$64,"channels[5].seasonality[1]|applied|parametric")>0,SUMIF(Corrections!$H$5:$H$64,"channels[5].seasonality[1]|applied|parametric",Corrections!$G$5:$G$64),IF(COUNTIF(Corrections!$H$5:$H$64,"channels[ALL].seasonality[1]|applied|parametric")>0,SUMIF(Corrections!$H$5:$H$64,"channels[ALL].seasonality[1]|applied|parametric",Corrections!$G$5:$G$64),IF(COUNTIF(Corrections!$H$5:$H$64,"channels[5].seasonality[ALL]|applied|parametric")>0,SUMIF(Corrections!$H$5:$H$64,"channels[5].seasonality[ALL]|applied|parametric",Corrections!$G$5:$G$64),IF(COUNTIF(Corrections!$H$5:$H$64,"channels[ALL].seasonality[ALL]|applied|parametric")>0,SUMIF(Corrections!$H$5:$H$64,"channels[ALL].seasonality[ALL]|applied|parametric",Corrections!$G$5:$G$64),N(Assumptions!G31))))) | H31: =IF(COUNTIF(Corrections!$H$5:$H$64,"channels[5].seasonality[2]|applied|parametric")>0,SUMIF(Corrections!$H$5:$H$64,"channels[5].seasonality[2]|applied|parametric",Corrections!$G$5:$G$64),IF(COUNTIF(Corrections!$H$5:$H$64,"channels[ALL].seasonality[2]|applied|parametric")>0,SUMIF(Corrections!$H$5:$H$64,"channels[ALL].seasonality[2]|applied|parametric",Corrections!$G$5:$G$64),IF(COUNTIF(Corrections!$H$5:$H$64,"channels[5].seasonality[ALL]|applied|parametric")>0,SUMIF(Corrections!$H$5:$H$64,"channels[5].seasonality[ALL]|applied|parametric",Corrections!$G$5:$G$64),IF(COUNTIF(Corrections!$H$5:$H$64,"channels[ALL].seasonality[ALL]|applied|parametric")>0,SUMIF(Corrections!$H$5:$H$64,"channels[ALL].seasonality[ALL]|applied|parametric",Corrections!$G$5:$G$64),N(Assumptions!H31))))) | I31: =IF(COUNTIF(Corrections!$H$5:$H$64,"channels[5].seasonality[3]|applied|parametric")>0,SUMIF(Corrections!$H$5:$H$64,"channels[5].seasonality[3]|applied|parametric",Corrections!$G$5:$G$64),IF(COUNTIF(Corrections!$H$5:$H$64,"channels[ALL].seasonality[3]|applied|parametric")>0,SUMIF(Corrections!$H$5:$H$64,"channels[ALL].seasonality[3]|applied|parametric",Corrections!$G$5:$G$64),IF(COUNTIF(Corrections!$H$5:$H$64,"channels[5].seasonality[ALL]|applied|parametric")>0,SUMIF(Corrections!$H$5:$H$64,"channels[5].seasonality[ALL]|applied|parametric",Corrections!$G$5:$G$64),IF(COUNTIF(Corrections!$H$5:$H$64,"channels[ALL].seasonality[ALL]|applied|parametric")>0,SUMIF(Corrections!$H$5:$H$64,"channels[ALL].seasonality[ALL]|applied|parametric",Corrections!$G$5:$G$64),N(Assumptions!I31))))) | J31: =IF(COUNTIF(Corrections!$H$5:$H$64,"channels[5].seasonality[4]|applied|parametric")>0,SUMIF(Corrections!$H$5:$H$64,"channels[5].seasonality[4]|applied|parametric",Corrections!$G$5:$G$64),IF(COUNTIF(Corrections!$H$5:$H$64,"channels[ALL].seasonality[4]|applied|parametric")>0,SUMIF(Corrections!$H$5:$H$64,"channels[ALL].seasonality[4]|applied|parametric",Corrections!$G$5:$G$64),IF(COUNTIF(Corrections!$H$5:$H$64,"channels[5].seasonality[ALL]|applied|parametric")>0,SUMIF(Corrections!$H$5:$H$64,"channels[5].seasonality[ALL]|applied|parametric",Corrections!$G$5:$G$64),IF(COUNTIF(Corrections!$H$5:$H$64,"channels[ALL].seasonality[ALL]|applied|parametric")>0,SUMIF(Corrections!$H$5:$H$64,"channels[ALL].seasonality[ALL]|applied|parametric",Corrections!$G$5:$G$64),N(Assumptions!J31))))) | K31: =IF(COUNTIF(Corrections!$H$5:$H$64,"channels[5].seasonality[5]|applied|parametric")>0,SUMIF(Corrections!$H$5:$H$64,"channels[5].seasonality[5]|applied|parametric",Corrections!$G$5:$G$64),IF(COUNTIF(Corrections!$H$5:$H$64,"channels[ALL].seasonality[5]|applied|parametric")>0,SUMIF(Corrections!$H$5:$H$64,"channels[ALL].seasonality[5]|applied|parametric",Corrections!$G$5:$G$64),IF(COUNTIF(Corrections!$H$5:$H$64,"channels[5].seasonality[ALL]|applied|parametric")>0,SUMIF(Corrections!$H$5:$H$64,"channels[5].seasonality[ALL]|applied|parametric",Corrections!$G$5:$G$64),IF(COUNTIF(Corrections!$H$5:$H$64,"channels[ALL].seasonality[ALL]|applied|parametric")>0,SUMIF(Corrections!$H$5:$H$64,"channels[ALL].seasonality[ALL]|applied|parametric",Corrections!$G$5:$G$64),N(Assumptions!K31))))) | L31: =IF(COUNTIF(Corrections!$H$5:$H$64,"channels[5].seasonality[6]|applied|parametric")>0,SUMIF(Corrections!$H$5:$H$64,"channels[5].seasonality[6]|applied|parametric",Corrections!$G$5:$G$64),IF(COUNTIF(Corrections!$H$5:$H$64,"channels[ALL].seasonality[6]|applied|parametric")>0,SUMIF(Corrections!$H$5:$H$64,"channels[ALL].seasonality[6]|applied|parametric",Corrections!$G$5:$G$64),IF(COUNTIF(Corrections!$H$5:$H$64,"channels[5].seasonality[ALL]|applied|parametric")>0,SUMIF(Corrections!$H$5:$H$64,"channels[5].seasonality[ALL]|applied|parametric",Corrections!$G$5:$G$64),IF(COUNTIF(Corrections!$H$5:$H$64,"channels[ALL].seasonality[ALL]|applied|parametric")>0,SUMIF(Corrections!$H$5:$H$64,"channels[ALL].seasonality[ALL]|applied|parametric",Corrections!$G$5:$G$64),N(Assumptions!L31))))) | M31: =IF(COUNTIF(Corrections!$H$5:$H$64,"channels[5].seasonality[7]|applied|parametric")>0,SUMIF(Corrections!$H$5:$H$64,"channels[5].seasonality[7]|applied|parametric",Corrections!$G$5:$G$64),IF(COUNTIF(Corrections!$H$5:$H$64,"channels[ALL].seasonality[7]|applied|parametric")>0,SUMIF(Corrections!$H$5:$H$64,"channels[ALL].seasonality[7]|applied|parametric",Corrections!$G$5:$G$64),IF(COUNTIF(Corrections!$H$5:$H$64,"channels[5].seasonality[ALL]|applied|parametric")>0,SUMIF(Corrections!$H$5:$H$64,"channels[5].seasonality[ALL]|applied|parametric",Corrections!$G$5:$G$64),IF(COUNTIF(Corrections!$H$5:$H$64,"channels[ALL].seasonality[ALL]|applied|parametric")>0,SUMIF(Corrections!$H$5:$H$64,"channels[ALL].seasonality[ALL]|applied|parametric",Corrections!$G$5:$G$64),N(Assumptions!M31))))) | N31: =IF(COUNTIF(Corrections!$H$5:$H$64,"channels[5].seasonality[8]|applied|parametric")>0,SUMIF(Corrections!$H$5:$H$64,"channels[5].seasonality[8]|applied|parametric",Corrections!$G$5:$G$64),IF(COUNTIF(Corrections!$H$5:$H$64,"channels[ALL].seasonality[8]|applied|parametric")>0,SUMIF(Corrections!$H$5:$H$64,"channels[ALL].seasonality[8]|applied|parametric",Corrections!$G$5:$G$64),IF(COUNTIF(Corrections!$H$5:$H$64,"channels[5].seasonality[ALL]|applied|parametric")>0,SUMIF(Corrections!$H$5:$H$64,"channels[5].seasonality[ALL]|applied|parametric",Corrections!$G$5:$G$64),IF(COUNTIF(Corrections!$H$5:$H$64,"channels[ALL].seasonality[ALL]|applied|parametric")>0,SUMIF(Corrections!$H$5:$H$64,"channels[ALL].seasonality[ALL]|applied|parametric",Corrections!$G$5:$G$64),N(Assumptions!N31))))) | O31: =IF(COUNTIF(Corrections!$H$5:$H$64,"channels[5].seasonality[9]|applied|parametric")>0,SUMIF(Corrections!$H$5:$H$64,"channels[5].seasonality[9]|applied|parametric",Corrections!$G$5:$G$64),IF(COUNTIF(Corrections!$H$5:$H$64,"channels[ALL].seasonality[9]|applied|parametric")>0,SUMIF(Corrections!$H$5:$H$64,"channels[ALL].seasonality[9]|applied|parametric",Corrections!$G$5:$G$64),IF(COUNTIF(Corrections!$H$5:$H$64,"channels[5].seasonality[ALL]|applied|parametric")>0,SUMIF(Corrections!$H$5:$H$64,"channels[5].seasonality[ALL]|applied|parametric",Corrections!$G$5:$G$64),IF(COUNTIF(Corrections!$H$5:$H$64,"channels[ALL].seasonality[ALL]|applied|parametric")>0,SUMIF(Corrections!$H$5:$H$64,"channels[ALL].seasonality[ALL]|applied|parametric",Corrections!$G$5:$G$64),N(Assumptions!O31))))) | P31: =IF(COUNTIF(Corrections!$H$5:$H$64,"channels[5].seasonality[10]|applied|parametric")>0,SUMIF(Corrections!$H$5:$H$64,"channels[5].seasonality[10]|applied|parametric",Corrections!$G$5:$G$64),IF(COUNTIF(Corrections!$H$5:$H$64,"channels[ALL].seasonality[10]|applied|parametric")>0,SUMIF(Corrections!$H$5:$H$64,"channels[ALL].seasonality[10]|applied|parametric",Corrections!$G$5:$G$64),IF(COUNTIF(Corrections!$H$5:$H$64,"channels[5].seasonality[ALL]|applied|parametric")>0,SUMIF(Corrections!$H$5:$H$64,"channels[5].seasonality[ALL]|applied|parametric",Corrections!$G$5:$G$64),IF(COUNTIF(Corrections!$H$5:$H$64,"channels[ALL].seasonality[ALL]|applied|parametric")>0,SUMIF(Corrections!$H$5:$H$64,"channels[ALL].seasonality[ALL]|applied|parametric",Corrections!$G$5:$G$64),N(Assumptions!P31))))) | Q31: =IF(COUNTIF(Corrections!$H$5:$H$64,"channels[5].seasonality[11]|applied|parametric")>0,SUMIF(Corrections!$H$5:$H$64,"channels[5].seasonality[11]|applied|parametric",Corrections!$G$5:$G$64),IF(COUNTIF(Corrections!$H$5:$H$64,"channels[ALL].seasonality[11]|applied|parametric")>0,SUMIF(Corrections!$H$5:$H$64,"channels[ALL].seasonality[11]|applied|parametric",Corrections!$G$5:$G$64),IF(COUNTIF(Corrections!$H$5:$H$64,"channels[5].seasonality[ALL]|applied|parametric")>0,SUMIF(Corrections!$H$5:$H$64,"channels[5].seasonality[ALL]|applied|parametric",Corrections!$G$5:$G$64),IF(COUNTIF(Corrections!$H$5:$H$64,"channels[ALL].seasonality[ALL]|applied|parametric")>0,SUMIF(Corrections!$H$5:$H$64,"channels[ALL].seasonality[ALL]|applied|parametric",Corrections!$G$5:$G$64),N(Assumptions!Q31)))))
A32: 6 | B32: =IF(Assumptions!B32="","",TRIM(Assumptions!B32)) | C32: =IF(COUNTIF(Corrections!$H$5:$H$64,"channels[6].annual_revenue|applied|parametric")>0,SUMIF(Corrections!$H$5:$H$64,"channels[6].annual_revenue|applied|parametric",Corrections!$G$5:$G$64),IF(COUNTIF(Corrections!$H$5:$H$64,"channels[ALL].annual_revenue|applied|parametric")>0,SUMIF(Corrections!$H$5:$H$64,"channels[ALL].annual_revenue|applied|parametric",Corrections!$G$5:$G$64),N(Assumptions!C32))) | D32: =IF(COUNTIF(Corrections!$H$5:$H$64,"channels[6].growth_rate|applied|parametric")>0,SUMIF(Corrections!$H$5:$H$64,"channels[6].growth_rate|applied|parametric",Corrections!$G$5:$G$64),IF(COUNTIF(Corrections!$H$5:$H$64,"channels[ALL].growth_rate|applied|parametric")>0,SUMIF(Corrections!$H$5:$H$64,"channels[ALL].growth_rate|applied|parametric",Corrections!$G$5:$G$64),N(Assumptions!D32))) | E32: =IF(COUNTIF(Corrections!$H$5:$H$64,"channels[6].cogs_pct|applied|parametric")>0,SUMIF(Corrections!$H$5:$H$64,"channels[6].cogs_pct|applied|parametric",Corrections!$G$5:$G$64),IF(COUNTIF(Corrections!$H$5:$H$64,"channels[ALL].cogs_pct|applied|parametric")>0,SUMIF(Corrections!$H$5:$H$64,"channels[ALL].cogs_pct|applied|parametric",Corrections!$G$5:$G$64),N(Assumptions!E32))) | F32: =IF(COUNTIF(Corrections!$H$5:$H$64,"channels[6].seasonality[0]|applied|parametric")>0,SUMIF(Corrections!$H$5:$H$64,"channels[6].seasonality[0]|applied|parametric",Corrections!$G$5:$G$64),IF(COUNTIF(Corrections!$H$5:$H$64,"channels[ALL].seasonality[0]|applied|parametric")>0,SUMIF(Corrections!$H$5:$H$64,"channels[ALL].seasonality[0]|applied|parametric",Corrections!$G$5:$G$64),IF(COUNTIF(Corrections!$H$5:$H$64,"channels[6].seasonality[ALL]|applied|parametric")>0,SUMIF(Corrections!$H$5:$H$64,"channels[6].seasonality[ALL]|applied|parametric",Corrections!$G$5:$G$64),IF(COUNTIF(Corrections!$H$5:$H$64,"channels[ALL].seasonality[ALL]|applied|parametric")>0,SUMIF(Corrections!$H$5:$H$64,"channels[ALL].seasonality[ALL]|applied|parametric",Corrections!$G$5:$G$64),N(Assumptions!F32))))) | G32: =IF(COUNTIF(Corrections!$H$5:$H$64,"channels[6].seasonality[1]|applied|parametric")>0,SUMIF(Corrections!$H$5:$H$64,"channels[6].seasonality[1]|applied|parametric",Corrections!$G$5:$G$64),IF(COUNTIF(Corrections!$H$5:$H$64,"channels[ALL].seasonality[1]|applied|parametric")>0,SUMIF(Corrections!$H$5:$H$64,"channels[ALL].seasonality[1]|applied|parametric",Corrections!$G$5:$G$64),IF(COUNTIF(Corrections!$H$5:$H$64,"channels[6].seasonality[ALL]|applied|parametric")>0,SUMIF(Corrections!$H$5:$H$64,"channels[6].seasonality[ALL]|applied|parametric",Corrections!$G$5:$G$64),IF(COUNTIF(Corrections!$H$5:$H$64,"channels[ALL].seasonality[ALL]|applied|parametric")>0,SUMIF(Corrections!$H$5:$H$64,"channels[ALL].seasonality[ALL]|applied|parametric",Corrections!$G$5:$G$64),N(Assumptions!G32))))) | H32: =IF(COUNTIF(Corrections!$H$5:$H$64,"channels[6].seasonality[2]|applied|parametric")>0,SUMIF(Corrections!$H$5:$H$64,"channels[6].seasonality[2]|applied|parametric",Corrections!$G$5:$G$64),IF(COUNTIF(Corrections!$H$5:$H$64,"channels[ALL].seasonality[2]|applied|parametric")>0,SUMIF(Corrections!$H$5:$H$64,"channels[ALL].seasonality[2]|applied|parametric",Corrections!$G$5:$G$64),IF(COUNTIF(Corrections!$H$5:$H$64,"channels[6].seasonality[ALL]|applied|parametric")>0,SUMIF(Corrections!$H$5:$H$64,"channels[6].seasonality[ALL]|applied|parametric",Corrections!$G$5:$G$64),IF(COUNTIF(Corrections!$H$5:$H$64,"channels[ALL].seasonality[ALL]|applied|parametric")>0,SUMIF(Corrections!$H$5:$H$64,"channels[ALL].seasonality[ALL]|applied|parametric",Corrections!$G$5:$G$64),N(Assumptions!H32))))) | I32: =IF(COUNTIF(Corrections!$H$5:$H$64,"channels[6].seasonality[3]|applied|parametric")>0,SUMIF(Corrections!$H$5:$H$64,"channels[6].seasonality[3]|applied|parametric",Corrections!$G$5:$G$64),IF(COUNTIF(Corrections!$H$5:$H$64,"channels[ALL].seasonality[3]|applied|parametric")>0,SUMIF(Corrections!$H$5:$H$64,"channels[ALL].seasonality[3]|applied|parametric",Corrections!$G$5:$G$64),IF(COUNTIF(Corrections!$H$5:$H$64,"channels[6].seasonality[ALL]|applied|parametric")>0,SUMIF(Corrections!$H$5:$H$64,"channels[6].seasonality[ALL]|applied|parametric",Corrections!$G$5:$G$64),IF(COUNTIF(Corrections!$H$5:$H$64,"channels[ALL].seasonality[ALL]|applied|parametric")>0,SUMIF(Corrections!$H$5:$H$64,"channels[ALL].seasonality[ALL]|applied|parametric",Corrections!$G$5:$G$64),N(Assumptions!I32))))) | J32: =IF(COUNTIF(Corrections!$H$5:$H$64,"channels[6].seasonality[4]|applied|parametric")>0,SUMIF(Corrections!$H$5:$H$64,"channels[6].seasonality[4]|applied|parametric",Corrections!$G$5:$G$64),IF(COUNTIF(Corrections!$H$5:$H$64,"channels[ALL].seasonality[4]|applied|parametric")>0,SUMIF(Corrections!$H$5:$H$64,"channels[ALL].seasonality[4]|applied|parametric",Corrections!$G$5:$G$64),IF(COUNTIF(Corrections!$H$5:$H$64,"channels[6].seasonality[ALL]|applied|parametric")>0,SUMIF(Corrections!$H$5:$H$64,"channels[6].seasonality[ALL]|applied|parametric",Corrections!$G$5:$G$64),IF(COUNTIF(Corrections!$H$5:$H$64,"channels[ALL].seasonality[ALL]|applied|parametric")>0,SUMIF(Corrections!$H$5:$H$64,"channels[ALL].seasonality[ALL]|applied|parametric",Corrections!$G$5:$G$64),N(Assumptions!J32))))) | K32: =IF(COUNTIF(Corrections!$H$5:$H$64,"channels[6].seasonality[5]|applied|parametric")>0,SUMIF(Corrections!$H$5:$H$64,"channels[6].seasonality[5]|applied|parametric",Corrections!$G$5:$G$64),IF(COUNTIF(Corrections!$H$5:$H$64,"channels[ALL].seasonality[5]|applied|parametric")>0,SUMIF(Corrections!$H$5:$H$64,"channels[ALL].seasonality[5]|applied|parametric",Corrections!$G$5:$G$64),IF(COUNTIF(Corrections!$H$5:$H$64,"channels[6].seasonality[ALL]|applied|parametric")>0,SUMIF(Corrections!$H$5:$H$64,"channels[6].seasonality[ALL]|applied|parametric",Corrections!$G$5:$G$64),IF(COUNTIF(Corrections!$H$5:$H$64,"channels[ALL].seasonality[ALL]|applied|parametric")>0,SUMIF(Corrections!$H$5:$H$64,"channels[ALL].seasonality[ALL]|applied|parametric",Corrections!$G$5:$G$64),N(Assumptions!K32))))) | L32: =IF(COUNTIF(Corrections!$H$5:$H$64,"channels[6].seasonality[6]|applied|parametric")>0,SUMIF(Corrections!$H$5:$H$64,"channels[6].seasonality[6]|applied|parametric",Corrections!$G$5:$G$64),IF(COUNTIF(Corrections!$H$5:$H$64,"channels[ALL].seasonality[6]|applied|parametric")>0,SUMIF(Corrections!$H$5:$H$64,"channels[ALL].seasonality[6]|applied|parametric",Corrections!$G$5:$G$64),IF(COUNTIF(Corrections!$H$5:$H$64,"channels[6].seasonality[ALL]|applied|parametric")>0,SUMIF(Corrections!$H$5:$H$64,"channels[6].seasonality[ALL]|applied|parametric",Corrections!$G$5:$G$64),IF(COUNTIF(Corrections!$H$5:$H$64,"channels[ALL].seasonality[ALL]|applied|parametric")>0,SUMIF(Corrections!$H$5:$H$64,"channels[ALL].seasonality[ALL]|applied|parametric",Corrections!$G$5:$G$64),N(Assumptions!L32))))) | M32: =IF(COUNTIF(Corrections!$H$5:$H$64,"channels[6].seasonality[7]|applied|parametric")>0,SUMIF(Corrections!$H$5:$H$64,"channels[6].seasonality[7]|applied|parametric",Corrections!$G$5:$G$64),IF(COUNTIF(Corrections!$H$5:$H$64,"channels[ALL].seasonality[7]|applied|parametric")>0,SUMIF(Corrections!$H$5:$H$64,"channels[ALL].seasonality[7]|applied|parametric",Corrections!$G$5:$G$64),IF(COUNTIF(Corrections!$H$5:$H$64,"channels[6].seasonality[ALL]|applied|parametric")>0,SUMIF(Corrections!$H$5:$H$64,"channels[6].seasonality[ALL]|applied|parametric",Corrections!$G$5:$G$64),IF(COUNTIF(Corrections!$H$5:$H$64,"channels[ALL].seasonality[ALL]|applied|parametric")>0,SUMIF(Corrections!$H$5:$H$64,"channels[ALL].seasonality[ALL]|applied|parametric",Corrections!$G$5:$G$64),N(Assumptions!M32))))) | N32: =IF(COUNTIF(Corrections!$H$5:$H$64,"channels[6].seasonality[8]|applied|parametric")>0,SUMIF(Corrections!$H$5:$H$64,"channels[6].seasonality[8]|applied|parametric",Corrections!$G$5:$G$64),IF(COUNTIF(Corrections!$H$5:$H$64,"channels[ALL].seasonality[8]|applied|parametric")>0,SUMIF(Corrections!$H$5:$H$64,"channels[ALL].seasonality[8]|applied|parametric",Corrections!$G$5:$G$64),IF(COUNTIF(Corrections!$H$5:$H$64,"channels[6].seasonality[ALL]|applied|parametric")>0,SUMIF(Corrections!$H$5:$H$64,"channels[6].seasonality[ALL]|applied|parametric",Corrections!$G$5:$G$64),IF(COUNTIF(Corrections!$H$5:$H$64,"channels[ALL].seasonality[ALL]|applied|parametric")>0,SUMIF(Corrections!$H$5:$H$64,"channels[ALL].seasonality[ALL]|applied|parametric",Corrections!$G$5:$G$64),N(Assumptions!N32))))) | O32: =IF(COUNTIF(Corrections!$H$5:$H$64,"channels[6].seasonality[9]|applied|parametric")>0,SUMIF(Corrections!$H$5:$H$64,"channels[6].seasonality[9]|applied|parametric",Corrections!$G$5:$G$64),IF(COUNTIF(Corrections!$H$5:$H$64,"channels[ALL].seasonality[9]|applied|parametric")>0,SUMIF(Corrections!$H$5:$H$64,"channels[ALL].seasonality[9]|applied|parametric",Corrections!$G$5:$G$64),IF(COUNTIF(Corrections!$H$5:$H$64,"channels[6].seasonality[ALL]|applied|parametric")>0,SUMIF(Corrections!$H$5:$H$64,"channels[6].seasonality[ALL]|applied|parametric",Corrections!$G$5:$G$64),IF(COUNTIF(Corrections!$H$5:$H$64,"channels[ALL].seasonality[ALL]|applied|parametric")>0,SUMIF(Corrections!$H$5:$H$64,"channels[ALL].seasonality[ALL]|applied|parametric",Corrections!$G$5:$G$64),N(Assumptions!O32))))) | P32: =IF(COUNTIF(Corrections!$H$5:$H$64,"channels[6].seasonality[10]|applied|parametric")>0,SUMIF(Corrections!$H$5:$H$64,"channels[6].seasonality[10]|applied|parametric",Corrections!$G$5:$G$64),IF(COUNTIF(Corrections!$H$5:$H$64,"channels[ALL].seasonality[10]|applied|parametric")>0,SUMIF(Corrections!$H$5:$H$64,"channels[ALL].seasonality[10]|applied|parametric",Corrections!$G$5:$G$64),IF(COUNTIF(Corrections!$H$5:$H$64,"channels[6].seasonality[ALL]|applied|parametric")>0,SUMIF(Corrections!$H$5:$H$64,"channels[6].seasonality[ALL]|applied|parametric",Corrections!$G$5:$G$64),IF(COUNTIF(Corrections!$H$5:$H$64,"channels[ALL].seasonality[ALL]|applied|parametric")>0,SUMIF(Corrections!$H$5:$H$64,"channels[ALL].seasonality[ALL]|applied|parametric",Corrections!$G$5:$G$64),N(Assumptions!P32))))) | Q32: =IF(COUNTIF(Corrections!$H$5:$H$64,"channels[6].seasonality[11]|applied|parametric")>0,SUMIF(Corrections!$H$5:$H$64,"channels[6].seasonality[11]|applied|parametric",Corrections!$G$5:$G$64),IF(COUNTIF(Corrections!$H$5:$H$64,"channels[ALL].seasonality[11]|applied|parametric")>0,SUMIF(Corrections!$H$5:$H$64,"channels[ALL].seasonality[11]|applied|parametric",Corrections!$G$5:$G$64),IF(COUNTIF(Corrections!$H$5:$H$64,"channels[6].seasonality[ALL]|applied|parametric")>0,SUMIF(Corrections!$H$5:$H$64,"channels[6].seasonality[ALL]|applied|parametric",Corrections!$G$5:$G$64),IF(COUNTIF(Corrections!$H$5:$H$64,"channels[ALL].seasonality[ALL]|applied|parametric")>0,SUMIF(Corrections!$H$5:$H$64,"channels[ALL].seasonality[ALL]|applied|parametric",Corrections!$G$5:$G$64),N(Assumptions!Q32)))))
A33: 7 | B33: =IF(Assumptions!B33="","",TRIM(Assumptions!B33)) | C33: =IF(COUNTIF(Corrections!$H$5:$H$64,"channels[7].annual_revenue|applied|parametric")>0,SUMIF(Corrections!$H$5:$H$64,"channels[7].annual_revenue|applied|parametric",Corrections!$G$5:$G$64),IF(COUNTIF(Corrections!$H$5:$H$64,"channels[ALL].annual_revenue|applied|parametric")>0,SUMIF(Corrections!$H$5:$H$64,"channels[ALL].annual_revenue|applied|parametric",Corrections!$G$5:$G$64),N(Assumptions!C33))) | D33: =IF(COUNTIF(Corrections!$H$5:$H$64,"channels[7].growth_rate|applied|parametric")>0,SUMIF(Corrections!$H$5:$H$64,"channels[7].growth_rate|applied|parametric",Corrections!$G$5:$G$64),IF(COUNTIF(Corrections!$H$5:$H$64,"channels[ALL].growth_rate|applied|parametric")>0,SUMIF(Corrections!$H$5:$H$64,"channels[ALL].growth_rate|applied|parametric",Corrections!$G$5:$G$64),N(Assumptions!D33))) | E33: =IF(COUNTIF(Corrections!$H$5:$H$64,"channels[7].cogs_pct|applied|parametric")>0,SUMIF(Corrections!$H$5:$H$64,"channels[7].cogs_pct|applied|parametric",Corrections!$G$5:$G$64),IF(COUNTIF(Corrections!$H$5:$H$64,"channels[ALL].cogs_pct|applied|parametric")>0,SUMIF(Corrections!$H$5:$H$64,"channels[ALL].cogs_pct|applied|parametric",Corrections!$G$5:$G$64),N(Assumptions!E33))) | F33: =IF(COUNTIF(Corrections!$H$5:$H$64,"channels[7].seasonality[0]|applied|parametric")>0,SUMIF(Corrections!$H$5:$H$64,"channels[7].seasonality[0]|applied|parametric",Corrections!$G$5:$G$64),IF(COUNTIF(Corrections!$H$5:$H$64,"channels[ALL].seasonality[0]|applied|parametric")>0,SUMIF(Corrections!$H$5:$H$64,"channels[ALL].seasonality[0]|applied|parametric",Corrections!$G$5:$G$64),IF(COUNTIF(Corrections!$H$5:$H$64,"channels[7].seasonality[ALL]|applied|parametric")>0,SUMIF(Corrections!$H$5:$H$64,"channels[7].seasonality[ALL]|applied|parametric",Corrections!$G$5:$G$64),IF(COUNTIF(Corrections!$H$5:$H$64,"channels[ALL].seasonality[ALL]|applied|parametric")>0,SUMIF(Corrections!$H$5:$H$64,"channels[ALL].seasonality[ALL]|applied|parametric",Corrections!$G$5:$G$64),N(Assumptions!F33))))) | G33: =IF(COUNTIF(Corrections!$H$5:$H$64,"channels[7].seasonality[1]|applied|parametric")>0,SUMIF(Corrections!$H$5:$H$64,"channels[7].seasonality[1]|applied|parametric",Corrections!$G$5:$G$64),IF(COUNTIF(Corrections!$H$5:$H$64,"channels[ALL].seasonality[1]|applied|parametric")>0,SUMIF(Corrections!$H$5:$H$64,"channels[ALL].seasonality[1]|applied|parametric",Corrections!$G$5:$G$64),IF(COUNTIF(Corrections!$H$5:$H$64,"channels[7].seasonality[ALL]|applied|parametric")>0,SUMIF(Corrections!$H$5:$H$64,"channels[7].seasonality[ALL]|applied|parametric",Corrections!$G$5:$G$64),IF(COUNTIF(Corrections!$H$5:$H$64,"channels[ALL].seasonality[ALL]|applied|parametric")>0,SUMIF(Corrections!$H$5:$H$64,"channels[ALL].seasonality[ALL]|applied|parametric",Corrections!$G$5:$G$64),N(Assumptions!G33))))) | H33: =IF(COUNTIF(Corrections!$H$5:$H$64,"channels[7].seasonality[2]|applied|parametric")>0,SUMIF(Corrections!$H$5:$H$64,"channels[7].seasonality[2]|applied|parametric",Corrections!$G$5:$G$64),IF(COUNTIF(Corrections!$H$5:$H$64,"channels[ALL].seasonality[2]|applied|parametric")>0,SUMIF(Corrections!$H$5:$H$64,"channels[ALL].seasonality[2]|applied|parametric",Corrections!$G$5:$G$64),IF(COUNTIF(Corrections!$H$5:$H$64,"channels[7].seasonality[ALL]|applied|parametric")>0,SUMIF(Corrections!$H$5:$H$64,"channels[7].seasonality[ALL]|applied|parametric",Corrections!$G$5:$G$64),IF(COUNTIF(Corrections!$H$5:$H$64,"channels[ALL].seasonality[ALL]|applied|parametric")>0,SUMIF(Corrections!$H$5:$H$64,"channels[ALL].seasonality[ALL]|applied|parametric",Corrections!$G$5:$G$64),N(Assumptions!H33))))) | I33: =IF(COUNTIF(Corrections!$H$5:$H$64,"channels[7].seasonality[3]|applied|parametric")>0,SUMIF(Corrections!$H$5:$H$64,"channels[7].seasonality[3]|applied|parametric",Corrections!$G$5:$G$64),IF(COUNTIF(Corrections!$H$5:$H$64,"channels[ALL].seasonality[3]|applied|parametric")>0,SUMIF(Corrections!$H$5:$H$64,"channels[ALL].seasonality[3]|applied|parametric",Corrections!$G$5:$G$64),IF(COUNTIF(Corrections!$H$5:$H$64,"channels[7].seasonality[ALL]|applied|parametric")>0,SUMIF(Corrections!$H$5:$H$64,"channels[7].seasonality[ALL]|applied|parametric",Corrections!$G$5:$G$64),IF(COUNTIF(Corrections!$H$5:$H$64,"channels[ALL].seasonality[ALL]|applied|parametric")>0,SUMIF(Corrections!$H$5:$H$64,"channels[ALL].seasonality[ALL]|applied|parametric",Corrections!$G$5:$G$64),N(Assumptions!I33))))) | J33: =IF(COUNTIF(Corrections!$H$5:$H$64,"channels[7].seasonality[4]|applied|parametric")>0,SUMIF(Corrections!$H$5:$H$64,"channels[7].seasonality[4]|applied|parametric",Corrections!$G$5:$G$64),IF(COUNTIF(Corrections!$H$5:$H$64,"channels[ALL].seasonality[4]|applied|parametric")>0,SUMIF(Corrections!$H$5:$H$64,"channels[ALL].seasonality[4]|applied|parametric",Corrections!$G$5:$G$64),IF(COUNTIF(Corrections!$H$5:$H$64,"channels[7].seasonality[ALL]|applied|parametric")>0,SUMIF(Corrections!$H$5:$H$64,"channels[7].seasonality[ALL]|applied|parametric",Corrections!$G$5:$G$64),IF(COUNTIF(Corrections!$H$5:$H$64,"channels[ALL].seasonality[ALL]|applied|parametric")>0,SUMIF(Corrections!$H$5:$H$64,"channels[ALL].seasonality[ALL]|applied|parametric",Corrections!$G$5:$G$64),N(Assumptions!J33))))) | K33: =IF(COUNTIF(Corrections!$H$5:$H$64,"channels[7].seasonality[5]|applied|parametric")>0,SUMIF(Corrections!$H$5:$H$64,"channels[7].seasonality[5]|applied|parametric",Corrections!$G$5:$G$64),IF(COUNTIF(Corrections!$H$5:$H$64,"channels[ALL].seasonality[5]|applied|parametric")>0,SUMIF(Corrections!$H$5:$H$64,"channels[ALL].seasonality[5]|applied|parametric",Corrections!$G$5:$G$64),IF(COUNTIF(Corrections!$H$5:$H$64,"channels[7].seasonality[ALL]|applied|parametric")>0,SUMIF(Corrections!$H$5:$H$64,"channels[7].seasonality[ALL]|applied|parametric",Corrections!$G$5:$G$64),IF(COUNTIF(Corrections!$H$5:$H$64,"channels[ALL].seasonality[ALL]|applied|parametric")>0,SUMIF(Corrections!$H$5:$H$64,"channels[ALL].seasonality[ALL]|applied|parametric",Corrections!$G$5:$G$64),N(Assumptions!K33))))) | L33: =IF(COUNTIF(Corrections!$H$5:$H$64,"channels[7].seasonality[6]|applied|parametric")>0,SUMIF(Corrections!$H$5:$H$64,"channels[7].seasonality[6]|applied|parametric",Corrections!$G$5:$G$64),IF(COUNTIF(Corrections!$H$5:$H$64,"channels[ALL].seasonality[6]|applied|parametric")>0,SUMIF(Corrections!$H$5:$H$64,"channels[ALL].seasonality[6]|applied|parametric",Corrections!$G$5:$G$64),IF(COUNTIF(Corrections!$H$5:$H$64,"channels[7].seasonality[ALL]|applied|parametric")>0,SUMIF(Corrections!$H$5:$H$64,"channels[7].seasonality[ALL]|applied|parametric",Corrections!$G$5:$G$64),IF(COUNTIF(Corrections!$H$5:$H$64,"channels[ALL].seasonality[ALL]|applied|parametric")>0,SUMIF(Corrections!$H$5:$H$64,"channels[ALL].seasonality[ALL]|applied|parametric",Corrections!$G$5:$G$64),N(Assumptions!L33))))) | M33: =IF(COUNTIF(Corrections!$H$5:$H$64,"channels[7].seasonality[7]|applied|parametric")>0,SUMIF(Corrections!$H$5:$H$64,"channels[7].seasonality[7]|applied|parametric",Corrections!$G$5:$G$64),IF(COUNTIF(Corrections!$H$5:$H$64,"channels[ALL].seasonality[7]|applied|parametric")>0,SUMIF(Corrections!$H$5:$H$64,"channels[ALL].seasonality[7]|applied|parametric",Corrections!$G$5:$G$64),IF(COUNTIF(Corrections!$H$5:$H$64,"channels[7].seasonality[ALL]|applied|parametric")>0,SUMIF(Corrections!$H$5:$H$64,"channels[7].seasonality[ALL]|applied|parametric",Corrections!$G$5:$G$64),IF(COUNTIF(Corrections!$H$5:$H$64,"channels[ALL].seasonality[ALL]|applied|parametric")>0,SUMIF(Corrections!$H$5:$H$64,"channels[ALL].seasonality[ALL]|applied|parametric",Corrections!$G$5:$G$64),N(Assumptions!M33))))) | N33: =IF(COUNTIF(Corrections!$H$5:$H$64,"channels[7].seasonality[8]|applied|parametric")>0,SUMIF(Corrections!$H$5:$H$64,"channels[7].seasonality[8]|applied|parametric",Corrections!$G$5:$G$64),IF(COUNTIF(Corrections!$H$5:$H$64,"channels[ALL].seasonality[8]|applied|parametric")>0,SUMIF(Corrections!$H$5:$H$64,"channels[ALL].seasonality[8]|applied|parametric",Corrections!$G$5:$G$64),IF(COUNTIF(Corrections!$H$5:$H$64,"channels[7].seasonality[ALL]|applied|parametric")>0,SUMIF(Corrections!$H$5:$H$64,"channels[7].seasonality[ALL]|applied|parametric",Corrections!$G$5:$G$64),IF(COUNTIF(Corrections!$H$5:$H$64,"channels[ALL].seasonality[ALL]|applied|parametric")>0,SUMIF(Corrections!$H$5:$H$64,"channels[ALL].seasonality[ALL]|applied|parametric",Corrections!$G$5:$G$64),N(Assumptions!N33))))) | O33: =IF(COUNTIF(Corrections!$H$5:$H$64,"channels[7].seasonality[9]|applied|parametric")>0,SUMIF(Corrections!$H$5:$H$64,"channels[7].seasonality[9]|applied|parametric",Corrections!$G$5:$G$64),IF(COUNTIF(Corrections!$H$5:$H$64,"channels[ALL].seasonality[9]|applied|parametric")>0,SUMIF(Corrections!$H$5:$H$64,"channels[ALL].seasonality[9]|applied|parametric",Corrections!$G$5:$G$64),IF(COUNTIF(Corrections!$H$5:$H$64,"channels[7].seasonality[ALL]|applied|parametric")>0,SUMIF(Corrections!$H$5:$H$64,"channels[7].seasonality[ALL]|applied|parametric",Corrections!$G$5:$G$64),IF(COUNTIF(Corrections!$H$5:$H$64,"channels[ALL].seasonality[ALL]|applied|parametric")>0,SUMIF(Corrections!$H$5:$H$64,"channels[ALL].seasonality[ALL]|applied|parametric",Corrections!$G$5:$G$64),N(Assumptions!O33))))) | P33: =IF(COUNTIF(Corrections!$H$5:$H$64,"channels[7].seasonality[10]|applied|parametric")>0,SUMIF(Corrections!$H$5:$H$64,"channels[7].seasonality[10]|applied|parametric",Corrections!$G$5:$G$64),IF(COUNTIF(Corrections!$H$5:$H$64,"channels[ALL].seasonality[10]|applied|parametric")>0,SUMIF(Corrections!$H$5:$H$64,"channels[ALL].seasonality[10]|applied|parametric",Corrections!$G$5:$G$64),IF(COUNTIF(Corrections!$H$5:$H$64,"channels[7].seasonality[ALL]|applied|parametric")>0,SUMIF(Corrections!$H$5:$H$64,"channels[7].seasonality[ALL]|applied|parametric",Corrections!$G$5:$G$64),IF(COUNTIF(Corrections!$H$5:$H$64,"channels[ALL].seasonality[ALL]|applied|parametric")>0,SUMIF(Corrections!$H$5:$H$64,"channels[ALL].seasonality[ALL]|applied|parametric",Corrections!$G$5:$G$64),N(Assumptions!P33))))) | Q33: =IF(COUNTIF(Corrections!$H$5:$H$64,"channels[7].seasonality[11]|applied|parametric")>0,SUMIF(Corrections!$H$5:$H$64,"channels[7].seasonality[11]|applied|parametric",Corrections!$G$5:$G$64),IF(COUNTIF(Corrections!$H$5:$H$64,"channels[ALL].seasonality[11]|applied|parametric")>0,SUMIF(Corrections!$H$5:$H$64,"channels[ALL].seasonality[11]|applied|parametric",Corrections!$G$5:$G$64),IF(COUNTIF(Corrections!$H$5:$H$64,"channels[7].seasonality[ALL]|applied|parametric")>0,SUMIF(Corrections!$H$5:$H$64,"channels[7].seasonality[ALL]|applied|parametric",Corrections!$G$5:$G$64),IF(COUNTIF(Corrections!$H$5:$H$64,"channels[ALL].seasonality[ALL]|applied|parametric")>0,SUMIF(Corrections!$H$5:$H$64,"channels[ALL].seasonality[ALL]|applied|parametric",Corrections!$G$5:$G$64),N(Assumptions!Q33)))))
A35: idx | B35: opex line name | C35: kind | D35: monthly_amount | E35: pct_of_revenue
A36: 0 | B36: =IF(Assumptions!B36="","",TRIM(Assumptions!B36)) | C36: =IF(Assumptions!C36="","",LOWER(TRIM(Assumptions!C36))) | D36: =IF(COUNTIF(Corrections!$H$5:$H$64,"opex[0].monthly_amount|applied|parametric")>0,SUMIF(Corrections!$H$5:$H$64,"opex[0].monthly_amount|applied|parametric",Corrections!$G$5:$G$64),IF(COUNTIF(Corrections!$H$5:$H$64,"opex[ALL].monthly_amount|applied|parametric")>0,SUMIF(Corrections!$H$5:$H$64,"opex[ALL].monthly_amount|applied|parametric",Corrections!$G$5:$G$64),N(Assumptions!D36))) | E36: =IF(COUNTIF(Corrections!$H$5:$H$64,"opex[0].pct_of_revenue|applied|parametric")>0,SUMIF(Corrections!$H$5:$H$64,"opex[0].pct_of_revenue|applied|parametric",Corrections!$G$5:$G$64),IF(COUNTIF(Corrections!$H$5:$H$64,"opex[ALL].pct_of_revenue|applied|parametric")>0,SUMIF(Corrections!$H$5:$H$64,"opex[ALL].pct_of_revenue|applied|parametric",Corrections!$G$5:$G$64),N(Assumptions!E36)))
A37: 1 | B37: =IF(Assumptions!B37="","",TRIM(Assumptions!B37)) | C37: =IF(Assumptions!C37="","",LOWER(TRIM(Assumptions!C37))) | D37: =IF(COUNTIF(Corrections!$H$5:$H$64,"opex[1].monthly_amount|applied|parametric")>0,SUMIF(Corrections!$H$5:$H$64,"opex[1].monthly_amount|applied|parametric",Corrections!$G$5:$G$64),IF(COUNTIF(Corrections!$H$5:$H$64,"opex[ALL].monthly_amount|applied|parametric")>0,SUMIF(Corrections!$H$5:$H$64,"opex[ALL].monthly_amount|applied|parametric",Corrections!$G$5:$G$64),N(Assumptions!D37))) | E37: =IF(COUNTIF(Corrections!$H$5:$H$64,"opex[1].pct_of_revenue|applied|parametric")>0,SUMIF(Corrections!$H$5:$H$64,"opex[1].pct_of_revenue|applied|parametric",Corrections!$G$5:$G$64),IF(COUNTIF(Corrections!$H$5:$H$64,"opex[ALL].pct_of_revenue|applied|parametric")>0,SUMIF(Corrections!$H$5:$H$64,"opex[ALL].pct_of_revenue|applied|parametric",Corrections!$G$5:$G$64),N(Assumptions!E37)))
A38: 2 | B38: =IF(Assumptions!B38="","",TRIM(Assumptions!B38)) | C38: =IF(Assumptions!C38="","",LOWER(TRIM(Assumptions!C38))) | D38: =IF(COUNTIF(Corrections!$H$5:$H$64,"opex[2].monthly_amount|applied|parametric")>0,SUMIF(Corrections!$H$5:$H$64,"opex[2].monthly_amount|applied|parametric",Corrections!$G$5:$G$64),IF(COUNTIF(Corrections!$H$5:$H$64,"opex[ALL].monthly_amount|applied|parametric")>0,SUMIF(Corrections!$H$5:$H$64,"opex[ALL].monthly_amount|applied|parametric",Corrections!$G$5:$G$64),N(Assumptions!D38))) | E38: =IF(COUNTIF(Corrections!$H$5:$H$64,"opex[2].pct_of_revenue|applied|parametric")>0,SUMIF(Corrections!$H$5:$H$64,"opex[2].pct_of_revenue|applied|parametric",Corrections!$G$5:$G$64),IF(COUNTIF(Corrections!$H$5:$H$64,"opex[ALL].pct_of_revenue|applied|parametric")>0,SUMIF(Corrections!$H$5:$H$64,"opex[ALL].pct_of_revenue|applied|parametric",Corrections!$G$5:$G$64),N(Assumptions!E38)))
A39: 3 | B39: =IF(Assumptions!B39="","",TRIM(Assumptions!B39)) | C39: =IF(Assumptions!C39="","",LOWER(TRIM(Assumptions!C39))) | D39: =IF(COUNTIF(Corrections!$H$5:$H$64,"opex[3].monthly_amount|applied|parametric")>0,SUMIF(Corrections!$H$5:$H$64,"opex[3].monthly_amount|applied|parametric",Corrections!$G$5:$G$64),IF(COUNTIF(Corrections!$H$5:$H$64,"opex[ALL].monthly_amount|applied|parametric")>0,SUMIF(Corrections!$H$5:$H$64,"opex[ALL].monthly_amount|applied|parametric",Corrections!$G$5:$G$64),N(Assumptions!D39))) | E39: =IF(COUNTIF(Corrections!$H$5:$H$64,"opex[3].pct_of_revenue|applied|parametric")>0,SUMIF(Corrections!$H$5:$H$64,"opex[3].pct_of_revenue|applied|parametric",Corrections!$G$5:$G$64),IF(COUNTIF(Corrections!$H$5:$H$64,"opex[ALL].pct_of_revenue|applied|parametric")>0,SUMIF(Corrections!$H$5:$H$64,"opex[ALL].pct_of_revenue|applied|parametric",Corrections!$G$5:$G$64),N(Assumptions!E39)))
A40: 4 | B40: =IF(Assumptions!B40="","",TRIM(Assumptions!B40)) | C40: =IF(Assumptions!C40="","",LOWER(TRIM(Assumptions!C40))) | D40: =IF(COUNTIF(Corrections!$H$5:$H$64,"opex[4].monthly_amount|applied|parametric")>0,SUMIF(Corrections!$H$5:$H$64,"opex[4].monthly_amount|applied|parametric",Corrections!$G$5:$G$64),IF(COUNTIF(Corrections!$H$5:$H$64,"opex[ALL].monthly_amount|applied|parametric")>0,SUMIF(Corrections!$H$5:$H$64,"opex[ALL].monthly_amount|applied|parametric",Corrections!$G$5:$G$64),N(Assumptions!D40))) | E40: =IF(COUNTIF(Corrections!$H$5:$H$64,"opex[4].pct_of_revenue|applied|parametric")>0,SUMIF(Corrections!$H$5:$H$64,"opex[4].pct_of_revenue|applied|parametric",Corrections!$G$5:$G$64),IF(COUNTIF(Corrections!$H$5:$H$64,"opex[ALL].pct_of_revenue|applied|parametric")>0,SUMIF(Corrections!$H$5:$H$64,"opex[ALL].pct_of_revenue|applied|parametric",Corrections!$G$5:$G$64),N(Assumptions!E40)))
A41: 5 | B41: =IF(Assumptions!B41="","",TRIM(Assumptions!B41)) | C41: =IF(Assumptions!C41="","",LOWER(TRIM(Assumptions!C41))) | D41: =IF(COUNTIF(Corrections!$H$5:$H$64,"opex[5].monthly_amount|applied|parametric")>0,SUMIF(Corrections!$H$5:$H$64,"opex[5].monthly_amount|applied|parametric",Corrections!$G$5:$G$64),IF(COUNTIF(Corrections!$H$5:$H$64,"opex[ALL].monthly_amount|applied|parametric")>0,SUMIF(Corrections!$H$5:$H$64,"opex[ALL].monthly_amount|applied|parametric",Corrections!$G$5:$G$64),N(Assumptions!D41))) | E41: =IF(COUNTIF(Corrections!$H$5:$H$64,"opex[5].pct_of_revenue|applied|parametric")>0,SUMIF(Corrections!$H$5:$H$64,"opex[5].pct_of_revenue|applied|parametric",Corrections!$G$5:$G$64),IF(COUNTIF(Corrections!$H$5:$H$64,"opex[ALL].pct_of_revenue|applied|parametric")>0,SUMIF(Corrections!$H$5:$H$64,"opex[ALL].pct_of_revenue|applied|parametric",Corrections!$G$5:$G$64),N(Assumptions!E41)))
A42: 6 | B42: =IF(Assumptions!B42="","",TRIM(Assumptions!B42)) | C42: =IF(Assumptions!C42="","",LOWER(TRIM(Assumptions!C42))) | D42: =IF(COUNTIF(Corrections!$H$5:$H$64,"opex[6].monthly_amount|applied|parametric")>0,SUMIF(Corrections!$H$5:$H$64,"opex[6].monthly_amount|applied|parametric",Corrections!$G$5:$G$64),IF(COUNTIF(Corrections!$H$5:$H$64,"opex[ALL].monthly_amount|applied|parametric")>0,SUMIF(Corrections!$H$5:$H$64,"opex[ALL].monthly_amount|applied|parametric",Corrections!$G$5:$G$64),N(Assumptions!D42))) | E42: =IF(COUNTIF(Corrections!$H$5:$H$64,"opex[6].pct_of_revenue|applied|parametric")>0,SUMIF(Corrections!$H$5:$H$64,"opex[6].pct_of_revenue|applied|parametric",Corrections!$G$5:$G$64),IF(COUNTIF(Corrections!$H$5:$H$64,"opex[ALL].pct_of_revenue|applied|parametric")>0,SUMIF(Corrections!$H$5:$H$64,"opex[ALL].pct_of_revenue|applied|parametric",Corrections!$G$5:$G$64),N(Assumptions!E42)))
A43: 7 | B43: =IF(Assumptions!B43="","",TRIM(Assumptions!B43)) | C43: =IF(Assumptions!C43="","",LOWER(TRIM(Assumptions!C43))) | D43: =IF(COUNTIF(Corrections!$H$5:$H$64,"opex[7].monthly_amount|applied|parametric")>0,SUMIF(Corrections!$H$5:$H$64,"opex[7].monthly_amount|applied|parametric",Corrections!$G$5:$G$64),IF(COUNTIF(Corrections!$H$5:$H$64,"opex[ALL].monthly_amount|applied|parametric")>0,SUMIF(Corrections!$H$5:$H$64,"opex[ALL].monthly_amount|applied|parametric",Corrections!$G$5:$G$64),N(Assumptions!D43))) | E43: =IF(COUNTIF(Corrections!$H$5:$H$64,"opex[7].pct_of_revenue|applied|parametric")>0,SUMIF(Corrections!$H$5:$H$64,"opex[7].pct_of_revenue|applied|parametric",Corrections!$G$5:$G$64),IF(COUNTIF(Corrections!$H$5:$H$64,"opex[ALL].pct_of_revenue|applied|parametric")>0,SUMIF(Corrections!$H$5:$H$64,"opex[ALL].pct_of_revenue|applied|parametric",Corrections!$G$5:$G$64),N(Assumptions!E43)))
A44: 8 | B44: =IF(Assumptions!B44="","",TRIM(Assumptions!B44)) | C44: =IF(Assumptions!C44="","",LOWER(TRIM(Assumptions!C44))) | D44: =IF(COUNTIF(Corrections!$H$5:$H$64,"opex[8].monthly_amount|applied|parametric")>0,SUMIF(Corrections!$H$5:$H$64,"opex[8].monthly_amount|applied|parametric",Corrections!$G$5:$G$64),IF(COUNTIF(Corrections!$H$5:$H$64,"opex[ALL].monthly_amount|applied|parametric")>0,SUMIF(Corrections!$H$5:$H$64,"opex[ALL].monthly_amount|applied|parametric",Corrections!$G$5:$G$64),N(Assumptions!D44))) | E44: =IF(COUNTIF(Corrections!$H$5:$H$64,"opex[8].pct_of_revenue|applied|parametric")>0,SUMIF(Corrections!$H$5:$H$64,"opex[8].pct_of_revenue|applied|parametric",Corrections!$G$5:$G$64),IF(COUNTIF(Corrections!$H$5:$H$64,"opex[ALL].pct_of_revenue|applied|parametric")>0,SUMIF(Corrections!$H$5:$H$64,"opex[ALL].pct_of_revenue|applied|parametric",Corrections!$G$5:$G$64),N(Assumptions!E44)))
A45: 9 | B45: =IF(Assumptions!B45="","",TRIM(Assumptions!B45)) | C45: =IF(Assumptions!C45="","",LOWER(TRIM(Assumptions!C45))) | D45: =IF(COUNTIF(Corrections!$H$5:$H$64,"opex[9].monthly_amount|applied|parametric")>0,SUMIF(Corrections!$H$5:$H$64,"opex[9].monthly_amount|applied|parametric",Corrections!$G$5:$G$64),IF(COUNTIF(Corrections!$H$5:$H$64,"opex[ALL].monthly_amount|applied|parametric")>0,SUMIF(Corrections!$H$5:$H$64,"opex[ALL].monthly_amount|applied|parametric",Corrections!$G$5:$G$64),N(Assumptions!D45))) | E45: =IF(COUNTIF(Corrections!$H$5:$H$64,"opex[9].pct_of_revenue|applied|parametric")>0,SUMIF(Corrections!$H$5:$H$64,"opex[9].pct_of_revenue|applied|parametric",Corrections!$G$5:$G$64),IF(COUNTIF(Corrections!$H$5:$H$64,"opex[ALL].pct_of_revenue|applied|parametric")>0,SUMIF(Corrections!$H$5:$H$64,"opex[ALL].pct_of_revenue|applied|parametric",Corrections!$G$5:$G$64),N(Assumptions!E45)))
A46: 10 | B46: =IF(Assumptions!B46="","",TRIM(Assumptions!B46)) | C46: =IF(Assumptions!C46="","",LOWER(TRIM(Assumptions!C46))) | D46: =IF(COUNTIF(Corrections!$H$5:$H$64,"opex[10].monthly_amount|applied|parametric")>0,SUMIF(Corrections!$H$5:$H$64,"opex[10].monthly_amount|applied|parametric",Corrections!$G$5:$G$64),IF(COUNTIF(Corrections!$H$5:$H$64,"opex[ALL].monthly_amount|applied|parametric")>0,SUMIF(Corrections!$H$5:$H$64,"opex[ALL].monthly_amount|applied|parametric",Corrections!$G$5:$G$64),N(Assumptions!D46))) | E46: =IF(COUNTIF(Corrections!$H$5:$H$64,"opex[10].pct_of_revenue|applied|parametric")>0,SUMIF(Corrections!$H$5:$H$64,"opex[10].pct_of_revenue|applied|parametric",Corrections!$G$5:$G$64),IF(COUNTIF(Corrections!$H$5:$H$64,"opex[ALL].pct_of_revenue|applied|parametric")>0,SUMIF(Corrections!$H$5:$H$64,"opex[ALL].pct_of_revenue|applied|parametric",Corrections!$G$5:$G$64),N(Assumptions!E46)))
A47: 11 | B47: =IF(Assumptions!B47="","",TRIM(Assumptions!B47)) | C47: =IF(Assumptions!C47="","",LOWER(TRIM(Assumptions!C47))) | D47: =IF(COUNTIF(Corrections!$H$5:$H$64,"opex[11].monthly_amount|applied|parametric")>0,SUMIF(Corrections!$H$5:$H$64,"opex[11].monthly_amount|applied|parametric",Corrections!$G$5:$G$64),IF(COUNTIF(Corrections!$H$5:$H$64,"opex[ALL].monthly_amount|applied|parametric")>0,SUMIF(Corrections!$H$5:$H$64,"opex[ALL].monthly_amount|applied|parametric",Corrections!$G$5:$G$64),N(Assumptions!D47))) | E47: =IF(COUNTIF(Corrections!$H$5:$H$64,"opex[11].pct_of_revenue|applied|parametric")>0,SUMIF(Corrections!$H$5:$H$64,"opex[11].pct_of_revenue|applied|parametric",Corrections!$G$5:$G$64),IF(COUNTIF(Corrections!$H$5:$H$64,"opex[ALL].pct_of_revenue|applied|parametric")>0,SUMIF(Corrections!$H$5:$H$64,"opex[ALL].pct_of_revenue|applied|parametric",Corrections!$G$5:$G$64),N(Assumptions!E47)))
A48: 12 | B48: =IF(Assumptions!B48="","",TRIM(Assumptions!B48)) | C48: =IF(Assumptions!C48="","",LOWER(TRIM(Assumptions!C48))) | D48: =IF(COUNTIF(Corrections!$H$5:$H$64,"opex[12].monthly_amount|applied|parametric")>0,SUMIF(Corrections!$H$5:$H$64,"opex[12].monthly_amount|applied|parametric",Corrections!$G$5:$G$64),IF(COUNTIF(Corrections!$H$5:$H$64,"opex[ALL].monthly_amount|applied|parametric")>0,SUMIF(Corrections!$H$5:$H$64,"opex[ALL].monthly_amount|applied|parametric",Corrections!$G$5:$G$64),N(Assumptions!D48))) | E48: =IF(COUNTIF(Corrections!$H$5:$H$64,"opex[12].pct_of_revenue|applied|parametric")>0,SUMIF(Corrections!$H$5:$H$64,"opex[12].pct_of_revenue|applied|parametric",Corrections!$G$5:$G$64),IF(COUNTIF(Corrections!$H$5:$H$64,"opex[ALL].pct_of_revenue|applied|parametric")>0,SUMIF(Corrections!$H$5:$H$64,"opex[ALL].pct_of_revenue|applied|parametric",Corrections!$G$5:$G$64),N(Assumptions!E48)))
A49: 13 | B49: =IF(Assumptions!B49="","",TRIM(Assumptions!B49)) | C49: =IF(Assumptions!C49="","",LOWER(TRIM(Assumptions!C49))) | D49: =IF(COUNTIF(Corrections!$H$5:$H$64,"opex[13].monthly_amount|applied|parametric")>0,SUMIF(Corrections!$H$5:$H$64,"opex[13].monthly_amount|applied|parametric",Corrections!$G$5:$G$64),IF(COUNTIF(Corrections!$H$5:$H$64,"opex[ALL].monthly_amount|applied|parametric")>0,SUMIF(Corrections!$H$5:$H$64,"opex[ALL].monthly_amount|applied|parametric",Corrections!$G$5:$G$64),N(Assumptions!D49))) | E49: =IF(COUNTIF(Corrections!$H$5:$H$64,"opex[13].pct_of_revenue|applied|parametric")>0,SUMIF(Corrections!$H$5:$H$64,"opex[13].pct_of_revenue|applied|parametric",Corrections!$G$5:$G$64),IF(COUNTIF(Corrections!$H$5:$H$64,"opex[ALL].pct_of_revenue|applied|parametric")>0,SUMIF(Corrections!$H$5:$H$64,"opex[ALL].pct_of_revenue|applied|parametric",Corrections!$G$5:$G$64),N(Assumptions!E49)))
A50: 14 | B50: =IF(Assumptions!B50="","",TRIM(Assumptions!B50)) | C50: =IF(Assumptions!C50="","",LOWER(TRIM(Assumptions!C50))) | D50: =IF(COUNTIF(Corrections!$H$5:$H$64,"opex[14].monthly_amount|applied|parametric")>0,SUMIF(Corrections!$H$5:$H$64,"opex[14].monthly_amount|applied|parametric",Corrections!$G$5:$G$64),IF(COUNTIF(Corrections!$H$5:$H$64,"opex[ALL].monthly_amount|applied|parametric")>0,SUMIF(Corrections!$H$5:$H$64,"opex[ALL].monthly_amount|applied|parametric",Corrections!$G$5:$G$64),N(Assumptions!D50))) | E50: =IF(COUNTIF(Corrections!$H$5:$H$64,"opex[14].pct_of_revenue|applied|parametric")>0,SUMIF(Corrections!$H$5:$H$64,"opex[14].pct_of_revenue|applied|parametric",Corrections!$G$5:$G$64),IF(COUNTIF(Corrections!$H$5:$H$64,"opex[ALL].pct_of_revenue|applied|parametric")>0,SUMIF(Corrections!$H$5:$H$64,"opex[ALL].pct_of_revenue|applied|parametric",Corrections!$G$5:$G$64),N(Assumptions!E50)))
A52: idx | B52: debt instrument | C52: kind | D52: opening_balance | E52: annual_rate | F52: monthly_principal
A53: 0 | B53: =IF(Assumptions!B53="","",TRIM(Assumptions!B53)) | C53: =IF(Assumptions!C53="","",LOWER(TRIM(Assumptions!C53))) | D53: =IF(COUNTIF(Corrections!$H$5:$H$64,"debt[0].opening_balance|applied|parametric")>0,SUMIF(Corrections!$H$5:$H$64,"debt[0].opening_balance|applied|parametric",Corrections!$G$5:$G$64),IF(COUNTIF(Corrections!$H$5:$H$64,"debt[ALL].opening_balance|applied|parametric")>0,SUMIF(Corrections!$H$5:$H$64,"debt[ALL].opening_balance|applied|parametric",Corrections!$G$5:$G$64),N(Assumptions!D53))) | E53: =IF(COUNTIF(Corrections!$H$5:$H$64,"debt[0].annual_rate|applied|parametric")>0,SUMIF(Corrections!$H$5:$H$64,"debt[0].annual_rate|applied|parametric",Corrections!$G$5:$G$64),IF(COUNTIF(Corrections!$H$5:$H$64,"debt[ALL].annual_rate|applied|parametric")>0,SUMIF(Corrections!$H$5:$H$64,"debt[ALL].annual_rate|applied|parametric",Corrections!$G$5:$G$64),N(Assumptions!E53))) | F53: =IF(COUNTIF(Corrections!$H$5:$H$64,"debt[0].monthly_principal|applied|parametric")>0,SUMIF(Corrections!$H$5:$H$64,"debt[0].monthly_principal|applied|parametric",Corrections!$G$5:$G$64),IF(COUNTIF(Corrections!$H$5:$H$64,"debt[ALL].monthly_principal|applied|parametric")>0,SUMIF(Corrections!$H$5:$H$64,"debt[ALL].monthly_principal|applied|parametric",Corrections!$G$5:$G$64),N(Assumptions!F53)))
A54: 1 | B54: =IF(Assumptions!B54="","",TRIM(Assumptions!B54)) | C54: =IF(Assumptions!C54="","",LOWER(TRIM(Assumptions!C54))) | D54: =IF(COUNTIF(Corrections!$H$5:$H$64,"debt[1].opening_balance|applied|parametric")>0,SUMIF(Corrections!$H$5:$H$64,"debt[1].opening_balance|applied|parametric",Corrections!$G$5:$G$64),IF(COUNTIF(Corrections!$H$5:$H$64,"debt[ALL].opening_balance|applied|parametric")>0,SUMIF(Corrections!$H$5:$H$64,"debt[ALL].opening_balance|applied|parametric",Corrections!$G$5:$G$64),N(Assumptions!D54))) | E54: =IF(COUNTIF(Corrections!$H$5:$H$64,"debt[1].annual_rate|applied|parametric")>0,SUMIF(Corrections!$H$5:$H$64,"debt[1].annual_rate|applied|parametric",Corrections!$G$5:$G$64),IF(COUNTIF(Corrections!$H$5:$H$64,"debt[ALL].annual_rate|applied|parametric")>0,SUMIF(Corrections!$H$5:$H$64,"debt[ALL].annual_rate|applied|parametric",Corrections!$G$5:$G$64),N(Assumptions!E54))) | F54: =IF(COUNTIF(Corrections!$H$5:$H$64,"debt[1].monthly_principal|applied|parametric")>0,SUMIF(Corrections!$H$5:$H$64,"debt[1].monthly_principal|applied|parametric",Corrections!$G$5:$G$64),IF(COUNTIF(Corrections!$H$5:$H$64,"debt[ALL].monthly_principal|applied|parametric")>0,SUMIF(Corrections!$H$5:$H$64,"debt[ALL].monthly_principal|applied|parametric",Corrections!$G$5:$G$64),N(Assumptions!F54)))
A55: 2 | B55: =IF(Assumptions!B55="","",TRIM(Assumptions!B55)) | C55: =IF(Assumptions!C55="","",LOWER(TRIM(Assumptions!C55))) | D55: =IF(COUNTIF(Corrections!$H$5:$H$64,"debt[2].opening_balance|applied|parametric")>0,SUMIF(Corrections!$H$5:$H$64,"debt[2].opening_balance|applied|parametric",Corrections!$G$5:$G$64),IF(COUNTIF(Corrections!$H$5:$H$64,"debt[ALL].opening_balance|applied|parametric")>0,SUMIF(Corrections!$H$5:$H$64,"debt[ALL].opening_balance|applied|parametric",Corrections!$G$5:$G$64),N(Assumptions!D55))) | E55: =IF(COUNTIF(Corrections!$H$5:$H$64,"debt[2].annual_rate|applied|parametric")>0,SUMIF(Corrections!$H$5:$H$64,"debt[2].annual_rate|applied|parametric",Corrections!$G$5:$G$64),IF(COUNTIF(Corrections!$H$5:$H$64,"debt[ALL].annual_rate|applied|parametric")>0,SUMIF(Corrections!$H$5:$H$64,"debt[ALL].annual_rate|applied|parametric",Corrections!$G$5:$G$64),N(Assumptions!E55))) | F55: =IF(COUNTIF(Corrections!$H$5:$H$64,"debt[2].monthly_principal|applied|parametric")>0,SUMIF(Corrections!$H$5:$H$64,"debt[2].monthly_principal|applied|parametric",Corrections!$G$5:$G$64),IF(COUNTIF(Corrections!$H$5:$H$64,"debt[ALL].monthly_principal|applied|parametric")>0,SUMIF(Corrections!$H$5:$H$64,"debt[ALL].monthly_principal|applied|parametric",Corrections!$G$5:$G$64),N(Assumptions!F55)))
A56: 3 | B56: =IF(Assumptions!B56="","",TRIM(Assumptions!B56)) | C56: =IF(Assumptions!C56="","",LOWER(TRIM(Assumptions!C56))) | D56: =IF(COUNTIF(Corrections!$H$5:$H$64,"debt[3].opening_balance|applied|parametric")>0,SUMIF(Corrections!$H$5:$H$64,"debt[3].opening_balance|applied|parametric",Corrections!$G$5:$G$64),IF(COUNTIF(Corrections!$H$5:$H$64,"debt[ALL].opening_balance|applied|parametric")>0,SUMIF(Corrections!$H$5:$H$64,"debt[ALL].opening_balance|applied|parametric",Corrections!$G$5:$G$64),N(Assumptions!D56))) | E56: =IF(COUNTIF(Corrections!$H$5:$H$64,"debt[3].annual_rate|applied|parametric")>0,SUMIF(Corrections!$H$5:$H$64,"debt[3].annual_rate|applied|parametric",Corrections!$G$5:$G$64),IF(COUNTIF(Corrections!$H$5:$H$64,"debt[ALL].annual_rate|applied|parametric")>0,SUMIF(Corrections!$H$5:$H$64,"debt[ALL].annual_rate|applied|parametric",Corrections!$G$5:$G$64),N(Assumptions!E56))) | F56: =IF(COUNTIF(Corrections!$H$5:$H$64,"debt[3].monthly_principal|applied|parametric")>0,SUMIF(Corrections!$H$5:$H$64,"debt[3].monthly_principal|applied|parametric",Corrections!$G$5:$G$64),IF(COUNTIF(Corrections!$H$5:$H$64,"debt[ALL].monthly_principal|applied|parametric")>0,SUMIF(Corrections!$H$5:$H$64,"debt[ALL].monthly_principal|applied|parametric",Corrections!$G$5:$G$64),N(Assumptions!F56)))
A57: 4 | B57: =IF(Assumptions!B57="","",TRIM(Assumptions!B57)) | C57: =IF(Assumptions!C57="","",LOWER(TRIM(Assumptions!C57))) | D57: =IF(COUNTIF(Corrections!$H$5:$H$64,"debt[4].opening_balance|applied|parametric")>0,SUMIF(Corrections!$H$5:$H$64,"debt[4].opening_balance|applied|parametric",Corrections!$G$5:$G$64),IF(COUNTIF(Corrections!$H$5:$H$64,"debt[ALL].opening_balance|applied|parametric")>0,SUMIF(Corrections!$H$5:$H$64,"debt[ALL].opening_balance|applied|parametric",Corrections!$G$5:$G$64),N(Assumptions!D57))) | E57: =IF(COUNTIF(Corrections!$H$5:$H$64,"debt[4].annual_rate|applied|parametric")>0,SUMIF(Corrections!$H$5:$H$64,"debt[4].annual_rate|applied|parametric",Corrections!$G$5:$G$64),IF(COUNTIF(Corrections!$H$5:$H$64,"debt[ALL].annual_rate|applied|parametric")>0,SUMIF(Corrections!$H$5:$H$64,"debt[ALL].annual_rate|applied|parametric",Corrections!$G$5:$G$64),N(Assumptions!E57))) | F57: =IF(COUNTIF(Corrections!$H$5:$H$64,"debt[4].monthly_principal|applied|parametric")>0,SUMIF(Corrections!$H$5:$H$64,"debt[4].monthly_principal|applied|parametric",Corrections!$G$5:$G$64),IF(COUNTIF(Corrections!$H$5:$H$64,"debt[ALL].monthly_principal|applied|parametric")>0,SUMIF(Corrections!$H$5:$H$64,"debt[ALL].monthly_principal|applied|parametric",Corrections!$G$5:$G$64),N(Assumptions!F57)))

Sheet ValidKeys
A1: Valid correction paths (normalised: * written as ALL)
A3: tax_rate
A4: da_monthly
A5: capex_monthly
A6: working_capital.dso_days
A7: working_capital.dpo_days
A8: working_capital.dio_days
A9: opening_balances.cash
A10: opening_balances.ar
A11: opening_balances.ap
A12: opening_balances.inventory
A13: opening_balances.nol
... A207: debt[ALL].monthly_principal

Sheet Model
A1: line | B1: note | C1: =IF(C4=1,TEXT(C3,"yyyy-mm"),"") | D1: =IF(D4=1,TEXT(D3,"yyyy-mm"),"") | E1: =IF(E4=1,TEXT(E3,"yyyy-mm"),"") | F1: =IF(F4=1,TEXT(F3,"yyyy-mm"),"") | G1: =IF(G4=1,TEXT(G3,"yyyy-mm"),"") | H1: =IF(H4=1,TEXT(H3,"yyyy-mm"),"") | I1: =IF(I4=1,TEXT(I3,"yyyy-mm"),"") | J1: =IF(J4=1,TEXT(J3,"yyyy-mm"),"") | ... DR1: =IF(DR4=1,TEXT(DR3,"yyyy-mm"),"")
A2: month_no | B2: 1..120 | C2: 1 | D2: 2 | E2: 3 | F2: 4 | G2: 5 | H2: 6 | I2: 7 | J2: 8 | K2: 9 | L2: 10 | M2: 11 | N2: 12 | O2: 13 | P2: 14 | Q2: 15 | R2: 16 | S2: 17 | T2: 18 | U2: 19 | V2: 20 | W2: 21 | X2: 22 | Y2: 23 | Z2: 24 | AA2: 25 | AB2: 26 | AC2: 27 | AD2: 28 | AE2: 29 | AF2: 30 | AG2: 31 | AH2: 32 | AI2: 33 | AJ2: 34 | AK2: 35 | AL2: 36 | AM2: 37 | AN2: 38 | AO2: 39 | AP2: 40 | AQ2: 41 | AR2: 42 | AS2: 43 | AT2: 44 | AU2: 45 | AV2: 46 | AW2: 47 | AX2: 48 | AY2: 49 | AZ2: 50 | BA2: 51 | BB2: 52 | BC2: 53 | BD2: 54 | BE2: 55 | BF2: 56 | BG2: 57 | BH2: 58 | BI2: 59 | BJ2: 60 | BK2: 61 | BL2: 62 | BM2: 63 | BN2: 64 | BO2: 65 | BP2: 66 | BQ2: 67 | BR2: 68 | BS2: 69 | BT2: 70 | BU2: 71 | BV2: 72 | BW2: 73 | BX2: 74 | BY2: 75 | BZ2: 76 | CA2: 77 | CB2: 78 | CC2: 79 | CD2: 80 | CE2: 81 | CF2: 82 | CG2: 83 | CH2: 84 | CI2: 85 | CJ2: 86 | CK2: 87 | CL2: 88 | CM2: 89 | CN2: 90 | CO2: 91 | CP2: 92 | CQ2: 93 | CR2: 94 | CS2: 95 | CT2: 96 | CU2: 97 | CV2: 98 | CW2: 99 | CX2: 100 | CY2: 101 | CZ2: 102 | DA2: 103 | DB2: 104 | DC2: 105 | DD2: 106 | DE2: 107 | DF2: 108 | DG2: 109 | DH2: 110 | DI2: 111 | DJ2: 112 | DK2: 113 | DL2: 114 | DM2: 115 | DN2: 116 | DO2: 117 | DP2: 118 | DQ2: 119 | DR2: 120
A3: period_start | B3: EDATE(start_month, n-1) | C3: =EDATE(Effective!$B$6,C2-1) | D3: =EDATE(Effective!$B$6,D2-1) | E3: =EDATE(Effective!$B$6,E2-1) | F3: =EDATE(Effective!$B$6,F2-1) | G3: =EDATE(Effective!$B$6,G2-1) | H3: =EDATE(Effective!$B$6,H2-1) | I3: =EDATE(Effective!$B$6,I2-1) | J3: =EDATE(Effective!$B$6,J2-1) | ... DR3: =EDATE(Effective!$B$6,DR2-1)
A4: active | B4: 1 if n <= horizon | C4: =IF(C2<=Effective!$B$7,1,0) | D4: =IF(D2<=Effective!$B$7,1,0) | E4: =IF(E2<=Effective!$B$7,1,0) | F4: =IF(F2<=Effective!$B$7,1,0) | G4: =IF(G2<=Effective!$B$7,1,0) | H4: =IF(H2<=Effective!$B$7,1,0) | I4: =IF(I2<=Effective!$B$7,1,0) | J4: =IF(J2<=Effective!$B$7,1,0) | ... DR4: =IF(DR2<=Effective!$B$7,1,0)
A5: calendar_month | C5: =MONTH(C3) | D5: =MONTH(D3) | E5: =MONTH(E3) | F5: =MONTH(F3) | G5: =MONTH(G3) | H5: =MONTH(H3) | I5: =MONTH(I3) | J5: =MONTH(J3) | ... DR5: =MONTH(DR3)
A6: year_offset | B6: growth exponent | C6: =INT((C2-1)/12) | D6: =INT((D2-1)/12) | E6: =INT((E2-1)/12) | F6: =INT((F2-1)/12) | G6: =INT((G2-1)/12) | H6: =INT((H2-1)/12) | I6: =INT((I2-1)/12) | J6: =INT((J2-1)/12) | ... DR6: =INT((DR2-1)/12)
A7: indian_fiscal_year | B7: Apr-Mar | C7: =IF(C5>=4,"FY"&YEAR(C3)&"-"&RIGHT(YEAR(C3)+1,2),"FY"&(YEAR(C3)-1)&"-"&RIGHT(YEAR(C3),2)) | D7: =IF(D5>=4,"FY"&YEAR(D3)&"-"&RIGHT(YEAR(D3)+1,2),"FY"&(YEAR(D3)-1)&"-"&RIGHT(YEAR(D3),2)) | E7: =IF(E5>=4,"FY"&YEAR(E3)&"-"&RIGHT(YEAR(E3)+1,2),"FY"&(YEAR(E3)-1)&"-"&RIGHT(YEAR(E3),2)) | F7: =IF(F5>=4,"FY"&YEAR(F3)&"-"&RIGHT(YEAR(F3)+1,2),"FY"&(YEAR(F3)-1)&"-"&RIGHT(YEAR(F3),2)) | G7: =IF(G5>=4,"FY"&YEAR(G3)&"-"&RIGHT(YEAR(G3)+1,2),"FY"&(YEAR(G3)-1)&"-"&RIGHT(YEAR(G3),2)) | H7: =IF(H5>=4,"FY"&YEAR(H3)&"-"&RIGHT(YEAR(H3)+1,2),"FY"&(YEAR(H3)-1)&"-"&RIGHT(YEAR(H3),2)) | I7: =IF(I5>=4,"FY"&YEAR(I3)&"-"&RIGHT(YEAR(I3)+1,2),"FY"&(YEAR(I3)-1)&"-"&RIGHT(YEAR(I3),2)) | J7: =IF(J5>=4,"FY"&YEAR(J3)&"-"&RIGHT(YEAR(J3)+1,2),"FY"&(YEAR(J3)-1)&"-"&RIGHT(YEAR(J3),2)) | ... DR7: =IF(DR5>=4,"FY"&YEAR(DR3)&"-"&RIGHT(YEAR(DR3)+1,2),"FY"&(YEAR(DR3)-1)&"-"&RIGHT(YEAR(DR3),2))
A8: fiscal_quarter | B8: Q1=Apr-Jun | C8: ="Q"&(INT(MOD(C5-4,12)/3)+1) | D8: ="Q"&(INT(MOD(D5-4,12)/3)+1) | E8: ="Q"&(INT(MOD(E5-4,12)/3)+1) | F8: ="Q"&(INT(MOD(F5-4,12)/3)+1) | G8: ="Q"&(INT(MOD(G5-4,12)/3)+1) | H8: ="Q"&(INT(MOD(H5-4,12)/3)+1) | I8: ="Q"&(INT(MOD(I5-4,12)/3)+1) | J8: ="Q"&(INT(MOD(J5-4,12)/3)+1) | ... DR8: ="Q"&(INT(MOD(DR5-4,12)/3)+1)
A9: fy_quarter_key | C9: =C7&" "&C8 | D9: =D7&" "&D8 | E9: =E7&" "&E8 | F9: =F7&" "&F8 | G9: =G7&" "&G8 | H9: =H7&" "&H8 | I9: =I7&" "&I8 | J9: =J7&" "&J8 | ... DR9: =DR7&" "&DR8
A10: revenue_ch1 | B10: channel idx 0 | C10: =IF(OR(C$4=0,SUM(Effective!$F$26:$Q$26)<=0),0,Effective!$C$26*INDEX(Effective!$F$26:$Q$26,1,C$5)/SUM(Effective!$F$26:$Q$26)*(1+Effective!$D$26)^C$6) | D10: =IF(OR(D$4=0,SUM(Effective!$F$26:$Q$26)<=0),0,Effective!$C$26*INDEX(Effective!$F$26:$Q$26,1,D$5)/SUM(Effective!$F$26:$Q$26)*(1+Effective!$D$26)^D$6) | E10: =IF(OR(E$4=0,SUM(Effective!$F$26:$Q$26)<=0),0,Effective!$C$26*INDEX(Effective!$F$26:$Q$26,1,E$5)/SUM(Effective!$F$26:$Q$26)*(1+Effective!$D$26)^E$6) | F10: =IF(OR(F$4=0,SUM(Effective!$F$26:$Q$26)<=0),0,Effective!$C$26*INDEX(Effective!$F$26:$Q$26,1,F$5)/SUM(Effective!$F$26:$Q$26)*(1+Effective!$D$26)^F$6) | G10: =IF(OR(G$4=0,SUM(Effective!$F$26:$Q$26)<=0),0,Effective!$C$26*INDEX(Effective!$F$26:$Q$26,1,G$5)/SUM(Effective!$F$26:$Q$26)*(1+Effective!$D$26)^G$6) | H10: =IF(OR(H$4=0,SUM(Effective!$F$26:$Q$26)<=0),0,Effective!$C$26*INDEX(Effective!$F$26:$Q$26,1,H$5)/SUM(Effective!$F$26:$Q$26)*(1+Effective!$D$26)^H$6) | I10: =IF(OR(I$4=0,SUM(Effective!$F$26:$Q$26)<=0),0,Effective!$C$26*INDEX(Effective!$F$26:$Q$26,1,I$5)/SUM(Effective!$F$26:$Q$26)*(1+Effective!$D$26)^I$6) | J10: =IF(OR(J$4=0,SUM(Effective!$F$26:$Q$26)<=0),0,Effective!$C$26*INDEX(Effective!$F$26:$Q$26,1,J$5)/SUM(Effective!$F$26:$Q$26)*(1+Effective!$D$26)^J$6) | ... DR10: =IF(OR(DR$4=0,SUM(Effective!$F$26:$Q$26)<=0),0,Effective!$C$26*INDEX(Effective!$F$26:$Q$26,1,DR$5)/SUM(Effective!$F$26:$Q$26)*(1+Effective!$D$26)^DR$6)
A11: revenue_ch2 | B11: channel idx 1 | C11: =IF(OR(C$4=0,SUM(Effective!$F$27:$Q$27)<=0),0,Effective!$C$27*INDEX(Effective!$F$27:$Q$27,1,C$5)/SUM(Effective!$F$27:$Q$27)*(1+Effective!$D$27)^C$6) | D11: =IF(OR(D$4=0,SUM(Effective!$F$27:$Q$27)<=0),0,Effective!$C$27*INDEX(Effective!$F$27:$Q$27,1,D$5)/SUM(Effective!$F$27:$Q$27)*(1+Effective!$D$27)^D$6) | E11: =IF(OR(E$4=0,SUM(Effective!$F$27:$Q$27)<=0),0,Effective!$C$27*INDEX(Effective!$F$27:$Q$27,1,E$5)/SUM(Effective!$F$27:$Q$27)*(1+Effective!$D$27)^E$6) | F11: =IF(OR(F$4=0,SUM(Effective!$F$27:$Q$27)<=0),0,Effective!$C$27*INDEX(Effective!$F$27:$Q$27,1,F$5)/SUM(Effective!$F$27:$Q$27)*(1+Effective!$D$27)^F$6) | G11: =IF(OR(G$4=0,SUM(Effective!$F$27:$Q$27)<=0),0,Effective!$C$27*INDEX(Effective!$F$27:$Q$27,1,G$5)/SUM(Effective!$F$27:$Q$27)*(1+Effective!$D$27)^G$6) | H11: =IF(OR(H$4=0,SUM(Effective!$F$27:$Q$27)<=0),0,Effective!$C$27*INDEX(Effective!$F$27:$Q$27,1,H$5)/SUM(Effective!$F$27:$Q$27)*(1+Effective!$D$27)^H$6) | I11: =IF(OR(I$4=0,SUM(Effective!$F$27:$Q$27)<=0),0,Effective!$C$27*INDEX(Effective!$F$27:$Q$27,1,I$5)/SUM(Effective!$F$27:$Q$27)*(1+Effective!$D$27)^I$6) | J11: =IF(OR(J$4=0,SUM(Effective!$F$27:$Q$27)<=0),0,Effective!$C$27*INDEX(Effective!$F$27:$Q$27,1,J$5)/SUM(Effective!$F$27:$Q$27)*(1+Effective!$D$27)^J$6) | ... DR11: =IF(OR(DR$4=0,SUM(Effective!$F$27:$Q$27)<=0),0,Effective!$C$27*INDEX(Effective!$F$27:$Q$27,1,DR$5)/SUM(Effective!$F$27:$Q$27)*(1+Effective!$D$27)^DR$6)
A12: revenue_ch3 | B12: channel idx 2 | C12: =IF(OR(C$4=0,SUM(Effective!$F$28:$Q$28)<=0),0,Effective!$C$28*INDEX(Effective!$F$28:$Q$28,1,C$5)/SUM(Effective!$F$28:$Q$28)*(1+Effective!$D$28)^C$6) | D12: =IF(OR(D$4=0,SUM(Effective!$F$28:$Q$28)<=0),0,Effective!$C$28*INDEX(Effective!$F$28:$Q$28,1,D$5)/SUM(Effective!$F$28:$Q$28)*(1+Effective!$D$28)^D$6) | E12: =IF(OR(E$4=0,SUM(Effective!$F$28:$Q$28)<=0),0,Effective!$C$28*INDEX(Effective!$F$28:$Q$28,1,E$5)/SUM(Effective!$F$28:$Q$28)*(1+Effective!$D$28)^E$6) | F12: =IF(OR(F$4=0,SUM(Effective!$F$28:$Q$28)<=0),0,Effective!$C$28*INDEX(Effective!$F$28:$Q$28,1,F$5)/SUM(Effective!$F$28:$Q$28)*(1+Effective!$D$28)^F$6) | G12: =IF(OR(G$4=0,SUM(Effective!$F$28:$Q$28)<=0),0,Effective!$C$28*INDEX(Effective!$F$28:$Q$28,1,G$5)/SUM(Effective!$F$28:$Q$28)*(1+Effective!$D$28)^G$6) | H12: =IF(OR(H$4=0,SUM(Effective!$F$28:$Q$28)<=0),0,Effective!$C$28*INDEX(Effective!$F$28:$Q$28,1,H$5)/SUM(Effective!$F$28:$Q$28)*(1+Effective!$D$28)^H$6) | I12: =IF(OR(I$4=0,SUM(Effective!$F$28:$Q$28)<=0),0,Effective!$C$28*INDEX(Effective!$F$28:$Q$28,1,I$5)/SUM(Effective!$F$28:$Q$28)*(1+Effective!$D$28)^I$6) | J12: =IF(OR(J$4=0,SUM(Effective!$F$28:$Q$28)<=0),0,Effective!$C$28*INDEX(Effective!$F$28:$Q$28,1,J$5)/SUM(Effective!$F$28:$Q$28)*(1+Effective!$D$28)^J$6) | ... DR12: =IF(OR(DR$4=0,SUM(Effective!$F$28:$Q$28)<=0),0,Effective!$C$28*INDEX(Effective!$F$28:$Q$28,1,DR$5)/SUM(Effective!$F$28:$Q$28)*(1+Effective!$D$28)^DR$6)
A13: revenue_ch4 | B13: channel idx 3 | C13: =IF(OR(C$4=0,SUM(Effective!$F$29:$Q$29)<=0),0,Effective!$C$29*INDEX(Effective!$F$29:$Q$29,1,C$5)/SUM(Effective!$F$29:$Q$29)*(1+Effective!$D$29)^C$6) | D13: =IF(OR(D$4=0,SUM(Effective!$F$29:$Q$29)<=0),0,Effective!$C$29*INDEX(Effective!$F$29:$Q$29,1,D$5)/SUM(Effective!$F$29:$Q$29)*(1+Effective!$D$29)^D$6) | E13: =IF(OR(E$4=0,SUM(Effective!$F$29:$Q$29)<=0),0,Effective!$C$29*INDEX(Effective!$F$29:$Q$29,1,E$5)/SUM(Effective!$F$29:$Q$29)*(1+Effective!$D$29)^E$6) | F13: =IF(OR(F$4=0,SUM(Effective!$F$29:$Q$29)<=0),0,Effective!$C$29*INDEX(Effective!$F$29:$Q$29,1,F$5)/SUM(Effective!$F$29:$Q$29)*(1+Effective!$D$29)^F$6) | G13: =IF(OR(G$4=0,SUM(Effective!$F$29:$Q$29)<=0),0,Effective!$C$29*INDEX(Effective!$F$29:$Q$29,1,G$5)/SUM(Effective!$F$29:$Q$29)*(1+Effective!$D$29)^G$6) | H13: =IF(OR(H$4=0,SUM(Effective!$F$29:$Q$29)<=0),0,Effective!$C$29*INDEX(Effective!$F$29:$Q$29,1,H$5)/SUM(Effective!$F$29:$Q$29)*(1+Effective!$D$29)^H$6) | I13: =IF(OR(I$4=0,SUM(Effective!$F$29:$Q$29)<=0),0,Effective!$C$29*INDEX(Effective!$F$29:$Q$29,1,I$5)/SUM(Effective!$F$29:$Q$29)*(1+Effective!$D$29)^I$6) | J13: =IF(OR(J$4=0,SUM(Effective!$F$29:$Q$29)<=0),0,Effective!$C$29*INDEX(Effective!$F$29:$Q$29,1,J$5)/SUM(Effective!$F$29:$Q$29)*(1+Effective!$D$29)^J$6) | ... DR13: =IF(OR(DR$4=0,SUM(Effective!$F$29:$Q$29)<=0),0,Effective!$C$29*INDEX(Effective!$F$29:$Q$29,1,DR$5)/SUM(Effective!$F$29:$Q$29)*(1+Effective!$D$29)^DR$6)
A14: revenue_ch5 | B14: channel idx 4 | C14: =IF(OR(C$4=0,SUM(Effective!$F$30:$Q$30)<=0),0,Effective!$C$30*INDEX(Effective!$F$30:$Q$30,1,C$5)/SUM(Effective!$F$30:$Q$30)*(1+Effective!$D$30)^C$6) | D14: =IF(OR(D$4=0,SUM(Effective!$F$30:$Q$30)<=0),0,Effective!$C$30*INDEX(Effective!$F$30:$Q$30,1,D$5)/SUM(Effective!$F$30:$Q$30)*(1+Effective!$D$30)^D$6) | E14: =IF(OR(E$4=0,SUM(Effective!$F$30:$Q$30)<=0),0,Effective!$C$30*INDEX(Effective!$F$30:$Q$30,1,E$5)/SUM(Effective!$F$30:$Q$30)*(1+Effective!$D$30)^E$6) | F14: =IF(OR(F$4=0,SUM(Effective!$F$30:$Q$30)<=0),0,Effective!$C$30*INDEX(Effective!$F$30:$Q$30,1,F$5)/SUM(Effective!$F$30:$Q$30)*(1+Effective!$D$30)^F$6) | G14: =IF(OR(G$4=0,SUM(Effective!$F$30:$Q$30)<=0),0,Effective!$C$30*INDEX(Effective!$F$30:$Q$30,1,G$5)/SUM(Effective!$F$30:$Q$30)*(1+Effective!$D$30)^G$6) | H14: =IF(OR(H$4=0,SUM(Effective!$F$30:$Q$30)<=0),0,Effective!$C$30*INDEX(Effective!$F$30:$Q$30,1,H$5)/SUM(Effective!$F$30:$Q$30)*(1+Effective!$D$30)^H$6) | I14: =IF(OR(I$4=0,SUM(Effective!$F$30:$Q$30)<=0),0,Effective!$C$30*INDEX(Effective!$F$30:$Q$30,1,I$5)/SUM(Effective!$F$30:$Q$30)*(1+Effective!$D$30)^I$6) | J14: =IF(OR(J$4=0,SUM(Effective!$F$30:$Q$30)<=0),0,Effective!$C$30*INDEX(Effective!$F$30:$Q$30,1,J$5)/SUM(Effective!$F$30:$Q$30)*(1+Effective!$D$30)^J$6) | ... DR14: =IF(OR(DR$4=0,SUM(Effective!$F$30:$Q$30)<=0),0,Effective!$C$30*INDEX(Effective!$F$30:$Q$30,1,DR$5)/SUM(Effective!$F$30:$Q$30)*(1+Effective!$D$30)^DR$6)
A15: revenue_ch6 | B15: channel idx 5 | C15: =IF(OR(C$4=0,SUM(Effective!$F$31:$Q$31)<=0),0,Effective!$C$31*INDEX(Effective!$F$31:$Q$31,1,C$5)/SUM(Effective!$F$31:$Q$31)*(1+Effective!$D$31)^C$6) | D15: =IF(OR(D$4=0,SUM(Effective!$F$31:$Q$31)<=0),0,Effective!$C$31*INDEX(Effective!$F$31:$Q$31,1,D$5)/SUM(Effective!$F$31:$Q$31)*(1+Effective!$D$31)^D$6) | E15: =IF(OR(E$4=0,SUM(Effective!$F$31:$Q$31)<=0),0,Effective!$C$31*INDEX(Effective!$F$31:$Q$31,1,E$5)/SUM(Effective!$F$31:$Q$31)*(1+Effective!$D$31)^E$6) | F15: =IF(OR(F$4=0,SUM(Effective!$F$31:$Q$31)<=0),0,Effective!$C$31*INDEX(Effective!$F$31:$Q$31,1,F$5)/SUM(Effective!$F$31:$Q$31)*(1+Effective!$D$31)^F$6) | G15: =IF(OR(G$4=0,SUM(Effective!$F$31:$Q$31)<=0),0,Effective!$C$31*INDEX(Effective!$F$31:$Q$31,1,G$5)/SUM(Effective!$F$31:$Q$31)*(1+Effective!$D$31)^G$6) | H15: =IF(OR(H$4=0,SUM(Effective!$F$31:$Q$31)<=0),0,Effective!$C$31*INDEX(Effective!$F$31:$Q$31,1,H$5)/SUM(Effective!$F$31:$Q$31)*(1+Effective!$D$31)^H$6) | I15: =IF(OR(I$4=0,SUM(Effective!$F$31:$Q$31)<=0),0,Effective!$C$31*INDEX(Effective!$F$31:$Q$31,1,I$5)/SUM(Effective!$F$31:$Q$31)*(1+Effective!$D$31)^I$6) | J15: =IF(OR(J$4=0,SUM(Effective!$F$31:$Q$31)<=0),0,Effective!$C$31*INDEX(Effective!$F$31:$Q$31,1,J$5)/SUM(Effective!$F$31:$Q$31)*(1+Effective!$D$31)^J$6) | ... DR15: =IF(OR(DR$4=0,SUM(Effective!$F$31:$Q$31)<=0),0,Effective!$C$31*INDEX(Effective!$F$31:$Q$31,1,DR$5)/SUM(Effective!$F$31:$Q$31)*(1+Effective!$D$31)^DR$6)
A16: revenue_ch7 | B16: channel idx 6 | C16: =IF(OR(C$4=0,SUM(Effective!$F$32:$Q$32)<=0),0,Effective!$C$32*INDEX(Effective!$F$32:$Q$32,1,C$5)/SUM(Effective!$F$32:$Q$32)*(1+Effective!$D$32)^C$6) | D16: =IF(OR(D$4=0,SUM(Effective!$F$32:$Q$32)<=0),0,Effective!$C$32*INDEX(Effective!$F$32:$Q$32,1,D$5)/SUM(Effective!$F$32:$Q$32)*(1+Effective!$D$32)^D$6) | E16: =IF(OR(E$4=0,SUM(Effective!$F$32:$Q$32)<=0),0,Effective!$C$32*INDEX(Effective!$F$32:$Q$32,1,E$5)/SUM(Effective!$F$32:$Q$32)*(1+Effective!$D$32)^E$6) | F16: =IF(OR(F$4=0,SUM(Effective!$F$32:$Q$32)<=0),0,Effective!$C$32*INDEX(Effective!$F$32:$Q$32,1,F$5)/SUM(Effective!$F$32:$Q$32)*(1+Effective!$D$32)^F$6) | G16: =IF(OR(G$4=0,SUM(Effective!$F$32:$Q$32)<=0),0,Effective!$C$32*INDEX(Effective!$F$32:$Q$32,1,G$5)/SUM(Effective!$F$32:$Q$32)*(1+Effective!$D$32)^G$6) | H16: =IF(OR(H$4=0,SUM(Effective!$F$32:$Q$32)<=0),0,Effective!$C$32*INDEX(Effective!$F$32:$Q$32,1,H$5)/SUM(Effective!$F$32:$Q$32)*(1+Effective!$D$32)^H$6) | I16: =IF(OR(I$4=0,SUM(Effective!$F$32:$Q$32)<=0),0,Effective!$C$32*INDEX(Effective!$F$32:$Q$32,1,I$5)/SUM(Effective!$F$32:$Q$32)*(1+Effective!$D$32)^I$6) | J16: =IF(OR(J$4=0,SUM(Effective!$F$32:$Q$32)<=0),0,Effective!$C$32*INDEX(Effective!$F$32:$Q$32,1,J$5)/SUM(Effective!$F$32:$Q$32)*(1+Effective!$D$32)^J$6) | ... DR16: =IF(OR(DR$4=0,SUM(Effective!$F$32:$Q$32)<=0),0,Effective!$C$32*INDEX(Effective!$F$32:$Q$32,1,DR$5)/SUM(Effective!$F$32:$Q$32)*(1+Effective!$D$32)^DR$6)
A17: revenue_ch8 | B17: channel idx 7 | C17: =IF(OR(C$4=0,SUM(Effective!$F$33:$Q$33)<=0),0,Effective!$C$33*INDEX(Effective!$F$33:$Q$33,1,C$5)/SUM(Effective!$F$33:$Q$33)*(1+Effective!$D$33)^C$6) | D17: =IF(OR(D$4=0,SUM(Effective!$F$33:$Q$33)<=0),0,Effective!$C$33*INDEX(Effective!$F$33:$Q$33,1,D$5)/SUM(Effective!$F$33:$Q$33)*(1+Effective!$D$33)^D$6) | E17: =IF(OR(E$4=0,SUM(Effective!$F$33:$Q$33)<=0),0,Effective!$C$33*INDEX(Effective!$F$33:$Q$33,1,E$5)/SUM(Effective!$F$33:$Q$33)*(1+Effective!$D$33)^E$6) | F17: =IF(OR(F$4=0,SUM(Effective!$F$33:$Q$33)<=0),0,Effective!$C$33*INDEX(Effective!$F$33:$Q$33,1,F$5)/SUM(Effective!$F$33:$Q$33)*(1+Effective!$D$33)^F$6) | G17: =IF(OR(G$4=0,SUM(Effective!$F$33:$Q$33)<=0),0,Effective!$C$33*INDEX(Effective!$F$33:$Q$33,1,G$5)/SUM(Effective!$F$33:$Q$33)*(1+Effective!$D$33)^G$6) | H17: =IF(OR(H$4=0,SUM(Effective!$F$33:$Q$33)<=0),0,Effective!$C$33*INDEX(Effective!$F$33:$Q$33,1,H$5)/SUM(Effective!$F$33:$Q$33)*(1+Effective!$D$33)^H$6) | I17: =IF(OR(I$4=0,SUM(Effective!$F$33:$Q$33)<=0),0,Effective!$C$33*INDEX(Effective!$F$33:$Q$33,1,I$5)/SUM(Effective!$F$33:$Q$33)*(1+Effective!$D$33)^I$6) | J17: =IF(OR(J$4=0,SUM(Effective!$F$33:$Q$33)<=0),0,Effective!$C$33*INDEX(Effective!$F$33:$Q$33,1,J$5)/SUM(Effective!$F$33:$Q$33)*(1+Effective!$D$33)^J$6) | ... DR17: =IF(OR(DR$4=0,SUM(Effective!$F$33:$Q$33)<=0),0,Effective!$C$33*INDEX(Effective!$F$33:$Q$33,1,DR$5)/SUM(Effective!$F$33:$Q$33)*(1+Effective!$D$33)^DR$6)
A18: revenue | C18: =SUM(C10:C17) | D18: =SUM(D10:D17) | E18: =SUM(E10:E17) | F18: =SUM(F10:F17) | G18: =SUM(G10:G17) | H18: =SUM(H10:H17) | I18: =SUM(I10:I17) | J18: =SUM(J10:J17) | ... DR18: =SUM(DR10:DR17)
A19: cogs_ch1 | C19: =C10*Effective!$E$26 | D19: =D10*Effective!$E$26 | E19: =E10*Effective!$E$26 | F19: =F10*Effective!$E$26 | G19: =G10*Effective!$E$26 | H19: =H10*Effective!$E$26 | I19: =I10*Effective!$E$26 | J19: =J10*Effective!$E$26 | ... DR19: =DR10*Effective!$E$26
A20: cogs_ch2 | C20: =C11*Effective!$E$27 | D20: =D11*Effective!$E$27 | E20: =E11*Effective!$E$27 | F20: =F11*Effective!$E$27 | G20: =G11*Effective!$E$27 | H20: =H11*Effective!$E$27 | I20: =I11*Effective!$E$27 | J20: =J11*Effective!$E$27 | ... DR20: =DR11*Effective!$E$27
A21: cogs_ch3 | C21: =C12*Effective!$E$28 | D21: =D12*Effective!$E$28 | E21: =E12*Effective!$E$28 | F21: =F12*Effective!$E$28 | G21: =G12*Effective!$E$28 | H21: =H12*Effective!$E$28 | I21: =I12*Effective!$E$28 | J21: =J12*Effective!$E$28 | ... DR21: =DR12*Effective!$E$28
A22: cogs_ch4 | C22: =C13*Effective!$E$29 | D22: =D13*Effective!$E$29 | E22: =E13*Effective!$E$29 | F22: =F13*Effective!$E$29 | G22: =G13*Effective!$E$29 | H22: =H13*Effective!$E$29 | I22: =I13*Effective!$E$29 | J22: =J13*Effective!$E$29 | ... DR22: =DR13*Effective!$E$29
A23: cogs_ch5 | C23: =C14*Effective!$E$30 | D23: =D14*Effective!$E$30 | E23: =E14*Effective!$E$30 | F23: =F14*Effective!$E$30 | G23: =G14*Effective!$E$30 | H23: =H14*Effective!$E$30 | I23: =I14*Effective!$E$30 | J23: =J14*Effective!$E$30 | ... DR23: =DR14*Effective!$E$30
A24: cogs_ch6 | C24: =C15*Effective!$E$31 | D24: =D15*Effective!$E$31 | E24: =E15*Effective!$E$31 | F24: =F15*Effective!$E$31 | G24: =G15*Effective!$E$31 | H24: =H15*Effective!$E$31 | I24: =I15*Effective!$E$31 | J24: =J15*Effective!$E$31 | ... DR24: =DR15*Effective!$E$31
A25: cogs_ch7 | C25: =C16*Effective!$E$32 | D25: =D16*Effective!$E$32 | E25: =E16*Effective!$E$32 | F25: =F16*Effective!$E$32 | G25: =G16*Effective!$E$32 | H25: =H16*Effective!$E$32 | I25: =I16*Effective!$E$32 | J25: =J16*Effective!$E$32 | ... DR25: =DR16*Effective!$E$32
A26: cogs_ch8 | C26: =C17*Effective!$E$33 | D26: =D17*Effective!$E$33 | E26: =E17*Effective!$E$33 | F26: =F17*Effective!$E$33 | G26: =G17*Effective!$E$33 | H26: =H17*Effective!$E$33 | I26: =I17*Effective!$E$33 | J26: =J17*Effective!$E$33 | ... DR26: =DR17*Effective!$E$33
A27: cogs | C27: =SUM(C19:C26) | D27: =SUM(D19:D26) | E27: =SUM(E19:E26) | F27: =SUM(F19:F26) | G27: =SUM(G19:G26) | H27: =SUM(H19:H26) | I27: =SUM(I19:I26) | J27: =SUM(J19:J26) | ... DR27: =SUM(DR19:DR26)
A28: gross_profit | C28: =C18-C27 | D28: =D18-D27 | E28: =E18-E27 | F28: =F18-F27 | G28: =G18-G27 | H28: =H18-H27 | I28: =I18-I27 | J28: =J18-J27 | ... DR28: =DR18-DR27
A29: opex_1 | B29: opex idx 0 | C29: =IF(C$4=0,0,IF(Effective!$C$36="fixed",Effective!$D$36,IF(Effective!$C$36="variable",C18*Effective!$E$36,0))) | D29: =IF(D$4=0,0,IF(Effective!$C$36="fixed",Effective!$D$36,IF(Effective!$C$36="variable",D18*Effective!$E$36,0))) | E29: =IF(E$4=0,0,IF(Effective!$C$36="fixed",Effective!$D$36,IF(Effective!$C$36="variable",E18*Effective!$E$36,0))) | F29: =IF(F$4=0,0,IF(Effective!$C$36="fixed",Effective!$D$36,IF(Effective!$C$36="variable",F18*Effective!$E$36,0))) | G29: =IF(G$4=0,0,IF(Effective!$C$36="fixed",Effective!$D$36,IF(Effective!$C$36="variable",G18*Effective!$E$36,0))) | H29: =IF(H$4=0,0,IF(Effective!$C$36="fixed",Effective!$D$36,IF(Effective!$C$36="variable",H18*Effective!$E$36,0))) | I29: =IF(I$4=0,0,IF(Effective!$C$36="fixed",Effective!$D$36,IF(Effective!$C$36="variable",I18*Effective!$E$36,0))) | J29: =IF(J$4=0,0,IF(Effective!$C$36="fixed",Effective!$D$36,IF(Effective!$C$36="variable",J18*Effective!$E$36,0))) | ... DR29: =IF(DR$4=0,0,IF(Effective!$C$36="fixed",Effective!$D$36,IF(Effective!$C$36="variable",DR18*Effective!$E$36,0)))
A30: opex_2 | B30: opex idx 1 | C30: =IF(C$4=0,0,IF(Effective!$C$37="fixed",Effective!$D$37,IF(Effective!$C$37="variable",C18*Effective!$E$37,0))) | D30: =IF(D$4=0,0,IF(Effective!$C$37="fixed",Effective!$D$37,IF(Effective!$C$37="variable",D18*Effective!$E$37,0))) | E30: =IF(E$4=0,0,IF(Effective!$C$37="fixed",Effective!$D$37,IF(Effective!$C$37="variable",E18*Effective!$E$37,0))) | F30: =IF(F$4=0,0,IF(Effective!$C$37="fixed",Effective!$D$37,IF(Effective!$C$37="variable",F18*Effective!$E$37,0))) | G30: =IF(G$4=0,0,IF(Effective!$C$37="fixed",Effective!$D$37,IF(Effective!$C$37="variable",G18*Effective!$E$37,0))) | H30: =IF(H$4=0,0,IF(Effective!$C$37="fixed",Effective!$D$37,IF(Effective!$C$37="variable",H18*Effective!$E$37,0))) | I30: =IF(I$4=0,0,IF(Effective!$C$37="fixed",Effective!$D$37,IF(Effective!$C$37="variable",I18*Effective!$E$37,0))) | J30: =IF(J$4=0,0,IF(Effective!$C$37="fixed",Effective!$D$37,IF(Effective!$C$37="variable",J18*Effective!$E$37,0))) | ... DR30: =IF(DR$4=0,0,IF(Effective!$C$37="fixed",Effective!$D$37,IF(Effective!$C$37="variable",DR18*Effective!$E$37,0)))
A31: opex_3 | B31: opex idx 2 | C31: =IF(C$4=0,0,IF(Effective!$C$38="fixed",Effective!$D$38,IF(Effective!$C$38="variable",C18*Effective!$E$38,0))) | D31: =IF(D$4=0,0,IF(Effective!$C$38="fixed",Effective!$D$38,IF(Effective!$C$38="variable",D18*Effective!$E$38,0))) | E31: =IF(E$4=0,0,IF(Effective!$C$38="fixed",Effective!$D$38,IF(Effective!$C$38="variable",E18*Effective!$E$38,0))) | F31: =IF(F$4=0,0,IF(Effective!$C$38="fixed",Effective!$D$38,IF(Effective!$C$38="variable",F18*Effective!$E$38,0))) | G31: =IF(G$4=0,0,IF(Effective!$C$38="fixed",Effective!$D$38,IF(Effective!$C$38="variable",G18*Effective!$E$38,0))) | H31: =IF(H$4=0,0,IF(Effective!$C$38="fixed",Effective!$D$38,IF(Effective!$C$38="variable",H18*Effective!$E$38,0))) | I31: =IF(I$4=0,0,IF(Effective!$C$38="fixed",Effective!$D$38,IF(Effective!$C$38="variable",I18*Effective!$E$38,0))) | J31: =IF(J$4=0,0,IF(Effective!$C$38="fixed",Effective!$D$38,IF(Effective!$C$38="variable",J18*Effective!$E$38,0))) | ... DR31: =IF(DR$4=0,0,IF(Effective!$C$38="fixed",Effective!$D$38,IF(Effective!$C$38="variable",DR18*Effective!$E$38,0)))
A32: opex_4 | B32: opex idx 3 | C32: =IF(C$4=0,0,IF(Effective!$C$39="fixed",Effective!$D$39,IF(Effective!$C$39="variable",C18*Effective!$E$39,0))) | D32: =IF(D$4=0,0,IF(Effective!$C$39="fixed",Effective!$D$39,IF(Effective!$C$39="variable",D18*Effective!$E$39,0))) | E32: =IF(E$4=0,0,IF(Effective!$C$39="fixed",Effective!$D$39,IF(Effective!$C$39="variable",E18*Effective!$E$39,0))) | F32: =IF(F$4=0,0,IF(Effective!$C$39="fixed",Effective!$D$39,IF(Effective!$C$39="variable",F18*Effective!$E$39,0))) | G32: =IF(G$4=0,0,IF(Effective!$C$39="fixed",Effective!$D$39,IF(Effective!$C$39="variable",G18*Effective!$E$39,0))) | H32: =IF(H$4=0,0,IF(Effective!$C$39="fixed",Effective!$D$39,IF(Effective!$C$39="variable",H18*Effective!$E$39,0))) | I32: =IF(I$4=0,0,IF(Effective!$C$39="fixed",Effective!$D$39,IF(Effective!$C$39="variable",I18*Effective!$E$39,0))) | J32: =IF(J$4=0,0,IF(Effective!$C$39="fixed",Effective!$D$39,IF(Effective!$C$39="variable",J18*Effective!$E$39,0))) | ... DR32: =IF(DR$4=0,0,IF(Effective!$C$39="fixed",Effective!$D$39,IF(Effective!$C$39="variable",DR18*Effective!$E$39,0)))
A33: opex_5 | B33: opex idx 4 | C33: =IF(C$4=0,0,IF(Effective!$C$40="fixed",Effective!$D$40,IF(Effective!$C$40="variable",C18*Effective!$E$40,0))) | D33: =IF(D$4=0,0,IF(Effective!$C$40="fixed",Effective!$D$40,IF(Effective!$C$40="variable",D18*Effective!$E$40,0))) | E33: =IF(E$4=0,0,IF(Effective!$C$40="fixed",Effective!$D$40,IF(Effective!$C$40="variable",E18*Effective!$E$40,0))) | F33: =IF(F$4=0,0,IF(Effective!$C$40="fixed",Effective!$D$40,IF(Effective!$C$40="variable",F18*Effective!$E$40,0))) | G33: =IF(G$4=0,0,IF(Effective!$C$40="fixed",Effective!$D$40,IF(Effective!$C$40="variable",G18*Effective!$E$40,0))) | H33: =IF(H$4=0,0,IF(Effective!$C$40="fixed",Effective!$D$40,IF(Effective!$C$40="variable",H18*Effective!$E$40,0))) | I33: =IF(I$4=0,0,IF(Effective!$C$40="fixed",Effective!$D$40,IF(Effective!$C$40="variable",I18*Effective!$E$40,0))) | J33: =IF(J$4=0,0,IF(Effective!$C$40="fixed",Effective!$D$40,IF(Effective!$C$40="variable",J18*Effective!$E$40,0))) | ... DR33: =IF(DR$4=0,0,IF(Effective!$C$40="fixed",Effective!$D$40,IF(Effective!$C$40="variable",DR18*Effective!$E$40,0)))
A34: opex_6 | B34: opex idx 5 | C34: =IF(C$4=0,0,IF(Effective!$C$41="fixed",Effective!$D$41,IF(Effective!$C$41="variable",C18*Effective!$E$41,0))) | D34: =IF(D$4=0,0,IF(Effective!$C$41="fixed",Effective!$D$41,IF(Effective!$C$41="variable",D18*Effective!$E$41,0))) | E34: =IF(E$4=0,0,IF(Effective!$C$41="fixed",Effective!$D$41,IF(Effective!$C$41="variable",E18*Effective!$E$41,0))) | F34: =IF(F$4=0,0,IF(Effective!$C$41="fixed",Effective!$D$41,IF(Effective!$C$41="variable",F18*Effective!$E$41,0))) | G34: =IF(G$4=0,0,IF(Effective!$C$41="fixed",Effective!$D$41,IF(Effective!$C$41="variable",G18*Effective!$E$41,0))) | H34: =IF(H$4=0,0,IF(Effective!$C$41="fixed",Effective!$D$41,IF(Effective!$C$41="variable",H18*Effective!$E$41,0))) | I34: =IF(I$4=0,0,IF(Effective!$C$41="fixed",Effective!$D$41,IF(Effective!$C$41="variable",I18*Effective!$E$41,0))) | J34: =IF(J$4=0,0,IF(Effective!$C$41="fixed",Effective!$D$41,IF(Effective!$C$41="variable",J18*Effective!$E$41,0))) | ... DR34: =IF(DR$4=0,0,IF(Effective!$C$41="fixed",Effective!$D$41,IF(Effective!$C$41="variable",DR18*Effective!$E$41,0)))
A35: opex_7 | B35: opex idx 6 | C35: =IF(C$4=0,0,IF(Effective!$C$42="fixed",Effective!$D$42,IF(Effective!$C$42="variable",C18*Effective!$E$42,0))) | D35: =IF(D$4=0,0,IF(Effective!$C$42="fixed",Effective!$D$42,IF(Effective!$C$42="variable",D18*Effective!$E$42,0))) | E35: =IF(E$4=0,0,IF(Effective!$C$42="fixed",Effective!$D$42,IF(Effective!$C$42="variable",E18*Effective!$E$42,0))) | F35: =IF(F$4=0,0,IF(Effective!$C$42="fixed",Effective!$D$42,IF(Effective!$C$42="variable",F18*Effective!$E$42,0))) | G35: =IF(G$4=0,0,IF(Effective!$C$42="fixed",Effective!$D$42,IF(Effective!$C$42="variable",G18*Effective!$E$42,0))) | H35: =IF(H$4=0,0,IF(Effective!$C$42="fixed",Effective!$D$42,IF(Effective!$C$42="variable",H18*Effective!$E$42,0))) | I35: =IF(I$4=0,0,IF(Effective!$C$42="fixed",Effective!$D$42,IF(Effective!$C$42="variable",I18*Effective!$E$42,0))) | J35: =IF(J$4=0,0,IF(Effective!$C$42="fixed",Effective!$D$42,IF(Effective!$C$42="variable",J18*Effective!$E$42,0))) | ... DR35: =IF(DR$4=0,0,IF(Effective!$C$42="fixed",Effective!$D$42,IF(Effective!$C$42="variable",DR18*Effective!$E$42,0)))
