Workbook
Name materiality: 'Setup'!$B$4

Sheet README
A1: D01 · Enterprise performance management & planning
A3: Domain D01: Enterprise performance management & planning.
A4: Run budgets, latest estimates and plan-vs-actual on top of the K01 champion: versions, driver trees, variance attribution and materiality.
A5: How to use
A6: Copy this workbook into companies/<slug>/domains/D01_epm-planning/ before typing. Replace the SAMPLE rows (illustrative Tamil Nadu data) with company data.
A7: Type only into pale-yellow cells; white cells are formulas. Checks › OVERALL must be PASS before any value feeds K01/K02.
A8: Statutory rates are starting values - verify in 01_tamil-nadu/verification-register.md.
A9: Feeds
A10: K01 channels[i].cogs_pct <= DriverTree cogs_pct
A11: K01 channels[i].annual_revenue <= DriverTree revenue
A12: W04 variance narrative <= Versions sheet

Sheet Checks
A1: Checks - OVERALL must be PASS before this domain feeds the kernel
B3: OVERALL | C3: =IF(COUNTIF(C5:C6,"PASS")=COUNT(A5:A6),"PASS","FAIL")
A4: # | B4: check | C4: result
A5: 1 | B5: every material variance has a driver | C5: =IF(SUMPRODUCT((Versions!J5:J44=TRUE)*(Versions!H5:H44=""))=0,"PASS","FAIL")
A6: 2 | B6: every material variance has an explanation | C6: =IF(SUMPRODUCT((Versions!J5:J44=TRUE)*(Versions!I5:I44=""))=0,"PASS","FAIL")

Sheet Versions
A1: Plan versions & variance (Budget / Latest Estimate / Actual)
A4: line (K01 line name) | B4: budget | C4: latest estimate | D4: actual (closed periods) | E4: var vs budget | F4: var % vs budget | G4: var vs LE | H4: primary driver (volume/price/cost ratio/timing/one-time) | I4: explanation (1 line) | J4: material? (|var%|>= threshold)
A5: revenue | B5: 1200000000 | C5: 1180000000 | D5: 1150000000 | E5: =IF(A5="","",D5-B5) | F5: =IF(OR(A5="",N(B5)=0),"",E5/ABS(B5)) | G5: =IF(A5="","",D5-C5) | H5: volume | I5: Deepavali shipments slipped to November | J5: =IF(F5="","",ABS(F5)>=Setup!$B$4)
A6: gross_profit | B6: 456000000 | C6: 448000000 | D6: 430000000 | E6: =IF(A6="","",D6-B6) | F6: =IF(OR(A6="",N(B6)=0),"",E6/ABS(B6)) | G6: =IF(A6="","",D6-C6) | H6: cost ratio | I6: cotton yarn price up | J6: =IF(F6="","",ABS(F6)>=Setup!$B$4)
A7: ebitda | B7: 140000000 | C7: 132000000 | D7: 118000000 | E7: =IF(A7="","",D7-B7) | F7: =IF(OR(A7="",N(B7)=0),"",E7/ABS(B7)) | G7: =IF(A7="","",D7-C7) | H7: volume | I7: lower absorption on slipped volume | J7: =IF(F7="","",ABS(F7)>=Setup!$B$4)
E8: =IF(A8="","",D8-B8) | F8: =IF(OR(A8="",N(B8)=0),"",E8/ABS(B8)) | G8: =IF(A8="","",D8-C8) | J8: =IF(F8="","",ABS(F8)>=Setup!$B$4)
E9: =IF(A9="","",D9-B9) | F9: =IF(OR(A9="",N(B9)=0),"",E9/ABS(B9)) | G9: =IF(A9="","",D9-C9) | J9: =IF(F9="","",ABS(F9)>=Setup!$B$4)
E10: =IF(A10="","",D10-B10) | F10: =IF(OR(A10="",N(B10)=0),"",E10/ABS(B10)) | G10: =IF(A10="","",D10-C10) | J10: =IF(F10="","",ABS(F10)>=Setup!$B$4)
E11: =IF(A11="","",D11-B11) | F11: =IF(OR(A11="",N(B11)=0),"",E11/ABS(B11)) | G11: =IF(A11="","",D11-C11) | J11: =IF(F11="","",ABS(F11)>=Setup!$B$4)
E12: =IF(A12="","",D12-B12) | F12: =IF(OR(A12="",N(B12)=0),"",E12/ABS(B12)) | G12: =IF(A12="","",D12-C12) | J12: =IF(F12="","",ABS(F12)>=Setup!$B$4)
E13: =IF(A13="","",D13-B13) | F13: =IF(OR(A13="",N(B13)=0),"",E13/ABS(B13)) | G13: =IF(A13="","",D13-C13) | J13: =IF(F13="","",ABS(F13)>=Setup!$B$4)
E14: =IF(A14="","",D14-B14) | F14: =IF(OR(A14="",N(B14)=0),"",E14/ABS(B14)) | G14: =IF(A14="","",D14-C14) | J14: =IF(F14="","",ABS(F14)>=Setup!$B$4)
E15: =IF(A15="","",D15-B15) | F15: =IF(OR(A15="",N(B15)=0),"",E15/ABS(B15)) | G15: =IF(A15="","",D15-C15) | J15: =IF(F15="","",ABS(F15)>=Setup!$B$4)
E16: =IF(A16="","",D16-B16) | F16: =IF(OR(A16="",N(B16)=0),"",E16/ABS(B16)) | G16: =IF(A16="","",D16-C16) | J16: =IF(F16="","",ABS(F16)>=Setup!$B$4)
E17: =IF(A17="","",D17-B17) | F17: =IF(OR(A17="",N(B17)=0),"",E17/ABS(B17)) | G17: =IF(A17="","",D17-C17) | J17: =IF(F17="","",ABS(F17)>=Setup!$B$4)
E18: =IF(A18="","",D18-B18) | F18: =IF(OR(A18="",N(B18)=0),"",E18/ABS(B18)) | G18: =IF(A18="","",D18-C18) | J18: =IF(F18="","",ABS(F18)>=Setup!$B$4)
E19: =IF(A19="","",D19-B19) | F19: =IF(OR(A19="",N(B19)=0),"",E19/ABS(B19)) | G19: =IF(A19="","",D19-C19) | J19: =IF(F19="","",ABS(F19)>=Setup!$B$4)
... E44: =IF(A44="","",D44-B44) | F44: =IF(OR(A44="",N(B44)=0),"",E44/ABS(B44)) | G44: =IF(A44="","",D44-C44) | J44: =IF(F44="","",ABS(F44)>=Setup!$B$4)

Sheet Setup
A1: Setup
A4: materiality threshold (|variance %|) | B4: 0.05
A5: version naming: Budget FY2026-27 / LE-Mn (month of re-forecast) / Actual | B5: LE-Oct

Sheet DriverTree
A1: Driver tree (revenue = units x price; cost = units x unit cost)
A4: product / channel | B4: units | C4: price | D4: unit cost | E4: revenue | F4: cogs | G4: cogs_pct (feeds K01 channels[i].cogs_pct)
A5: Dealer network | B5: 120000 | C5: 4500 | D5: 2700 | E5: =IF(A5="","",B5*C5) | F5: =IF(A5="","",B5*D5) | G5: =IF(OR(A5="",N(E5)=0),"",F5/E5)
A6: Amazon.in / Flipkart | B6: 60000 | C6: 5200 | D6: 2900 | E6: =IF(A6="","",B6*C6) | F6: =IF(A6="","",B6*D6) | G6: =IF(OR(A6="",N(E6)=0),"",F6/E6)
E7: =IF(A7="","",B7*C7) | F7: =IF(A7="","",B7*D7) | G7: =IF(OR(A7="",N(E7)=0),"",F7/E7)
E8: =IF(A8="","",B8*C8) | F8: =IF(A8="","",B8*D8) | G8: =IF(OR(A8="",N(E8)=0),"",F8/E8)
E9: =IF(A9="","",B9*C9) | F9: =IF(A9="","",B9*D9) | G9: =IF(OR(A9="",N(E9)=0),"",F9/E9)
E10: =IF(A10="","",B10*C10) | F10: =IF(A10="","",B10*D10) | G10: =IF(OR(A10="",N(E10)=0),"",F10/E10)
E11: =IF(A11="","",B11*C11) | F11: =IF(A11="","",B11*D11) | G11: =IF(OR(A11="",N(E11)=0),"",F11/E11)
E12: =IF(A12="","",B12*C12) | F12: =IF(A12="","",B12*D12) | G12: =IF(OR(A12="",N(E12)=0),"",F12/E12)
E13: =IF(A13="","",B13*C13) | F13: =IF(A13="","",B13*D13) | G13: =IF(OR(A13="",N(E13)=0),"",F13/E13)
E14: =IF(A14="","",B14*C14) | F14: =IF(A14="","",B14*D14) | G14: =IF(OR(A14="",N(E14)=0),"",F14/E14)
E15: =IF(A15="","",B15*C15) | F15: =IF(A15="","",B15*D15) | G15: =IF(OR(A15="",N(E15)=0),"",F15/E15)
E16: =IF(A16="","",B16*C16) | F16: =IF(A16="","",B16*D16) | G16: =IF(OR(A16="",N(E16)=0),"",F16/E16)
E17: =IF(A17="","",B17*C17) | F17: =IF(A17="","",B17*D17) | G17: =IF(OR(A17="",N(E17)=0),"",F17/E17)
E18: =IF(A18="","",B18*C18) | F18: =IF(A18="","",B18*D18) | G18: =IF(OR(A18="",N(E18)=0),"",F18/E18)
... E34: =IF(A34="","",B34*C34) | F34: =IF(A34="","",B34*D34) | G34: =IF(OR(A34="",N(E34)=0),"",F34/E34)
