Workbook
Name c13_open: 'Setup'!$B$4
Name c13_weeks: 'Setup'!$B$5
Name c13_start: 'Setup'!$B$6
Name c13_buffer: 'Setup'!$B$7
Name rw_min_cash: 'Runway'!$B$4
Name rw_min_week: 'Runway'!$B$5
Name rw_first_negative: 'Runway'!$B$6

Sheet README
A1: K02 · 13-Week Direct Cash Forecast + Runway (no-code kernel)
A3: Replaces openfpa: pyfpa.cash13 (WeeklyFlow, Cash13Config, expand_flow, cash13_forecast) and runway_summary.
A4: How an agent uses this workbook
A5: 1. Copy into companies/<slug>/models/. Enter opening_cash, weeks (default 13, max 52) and week-1 start date on 'Setup'.
A6: 2. List every KNOWN lumpy receipt and disbursement on 'Flows' (direction, name, amount as a positive magnitude, start_week, recurrence once/weekly/biweekly, optional end_week).
A7: Use 'DateToWeek' to convert a calendar due date (e.g. GST GSTR-3B on the 20th, TDS on the 7th, PF/ESI on the 15th, advance tax 15 Jun/Sep/Dec/Mar) into a week number.
A8: 3. Recalculate. Read 'Runway': min_cash, min_week, first_negative_week, and the suggested credit line (trough + buffer).
A9: 4. The position is RAW / UNFINANCED: no automatic overdraft or cash-credit draws. A visible shortfall is the point - it sizes the line (W05 cash runway).
A10: Rules (identical to openfpa)
A11: once = only start_week; weekly = every week start..end; biweekly = every 2nd week start..end; end defaults to the horizon; weeks outside 1..weeks are ignored.
A12: net = receipts - disbursements; ending cash is cumulative from opening cash. min_week is the FIRST week at the minimum; first_negative_week is the first week ending below zero (blank = none).
A13: Amounts must be >= 0 and end_week >= start_week - see Checks.

Sheet Checks
A1: Checks - schema validation. OVERALL must be PASS.
B3: OVERALL | C3: =IF(COUNTIF(C5:C13,"PASS")=COUNT(A5:A13),"PASS","FAIL")
A4: # | B4: check | C4: result | D4: detail
A5: 1 | B5: weeks is an integer 1..52 | C5: =IF(AND(Setup!$B$5>=1,Setup!$B$5<=52,INT(Setup!$B$5)=Setup!$B$5),"PASS","FAIL") | D5: =Setup!$B$5
A6: 2 | B6: opening_cash is a number | C6: =IF(ISNUMBER(Setup!$B$4),"PASS","FAIL")
A7: 3 | B7: every direction is receipt or disbursement | C7: =IF(SUMPRODUCT((Flows!$A$5:$A$84<>"")*1)=COUNTIF(Flows!$A$5:$A$84,"receipt")+COUNTIF(Flows!$A$5:$A$84,"disbursement"),"PASS","FAIL")
A8: 4 | B8: each flow: amount >= 0, start_week >= 1, valid recurrence, end_week >= start_week | C8: =IF((IF(Flows!A5="",0,IF(AND(ISNUMBER(Flows!C5),Flows!C5>=0,ISNUMBER(Flows!D5),Flows!D5>=1,OR(Flows!E5="",Flows!E5="once",Flows!E5="weekly",Flows!E5="biweekly"),OR(Flows!F5="",AND(ISNUMBER(Flows!F5),Flows!F5>=Flows!D5))),0,1))+IF(Flows!A6="",0,IF(AND(ISNUMBER(Flows!C6),Flows!C6>=0,ISNUMBER(Flows!D6),Flows!D6>=1,OR(Flows!E6="",Flows!E6="once",Flows!E6="weekly",Flows!E6="biweekly"),OR(Flows!F6="",AND(ISNUMBER(Flows!F6),Flows!F6>=Flows!D6))),0,1))+IF(Flows!A7="",0,IF(AND(ISNUMBER(Flows!C7),Flows!C7>=0,ISNUMBER(Flows!D7),Flows!D7>=1,OR(Flows!E7="",Flows!E7="once",Flows!E7="weekly",Flows!E7="biweekly"),OR(Flows!F7="",AND(ISNUMBER(Flows!F7),Flows!F7>=Flows!D7))),0,1))+IF(Flows!A8="",0,IF(AND(ISNUMBER(Flows!C8),Flows!C8>=0,ISNUMBER(Flows!D8),Flows!D8>=1,OR(Flows!E8="",Flows!E8="once",Flows!E8="weekly",Flows!E8="biweekly"),OR(Flows!F8="",AND(ISNUMBER(Flows!F8),Flows!F8>=Flows!D8))),0,1))+IF(Flows!A9="",0,IF(AND(ISNUMBER(Flows!C9),Flows!C9>=0,ISNUMBER(Flows!D9),Flows!D9>=1,OR(Flows!E9="",Flows!E9="once",Flows!E9="weekly",Flows!E9="biweekly"),OR(Flows!F9="",AND(ISNUMBER(Flows!F9),Flows!F9>=Flows!D9))),0,1))+IF(Flows!A10="",0,IF(AND(ISNUMBER(Flows!C10),Flows!C10>=0,ISNUMBER(Flows!D10),Flows!D10>=1,OR(Flows!E10="",Flows!E10="once",Flows!E10="weekly",Flows!E10="biweekly"),OR(Flows!F10="",AND(ISNUMBER(Flows!F10),Flows!F10>=Flows!D10))),0,1))+IF(Flows!A11="",0,IF(AND(ISNUMBER(Flows!C11),Flows!C11>=0,ISNUMBER(Flows!D11),Flows!D11>=1,OR(Flows!E11="",Flows!E11="once",Flows!E11="weekly",Flows!E11="biweekly"),OR(Flows!F11="",AND(ISNUMBER(Flows!F11),Flows!F11>=Flows!D11))),0,1))+IF(Flows!A12="",0,IF(AND(ISNUMBER(Flows!C12),Flows!C12>=0,ISNUMBER(Flows!D12),Flows!D12>=1,OR(Flows!E12="",Flows!E12="once",Flows!E12="weekly",Flows!E12="biweekly"),OR(Flows!F12="",AND(ISNUMBER(Flows!F12),Flows!F12>=Flows!D12))),0,1))+IF(Flows!A13="",0,IF(AND(ISNUMBER(Flows!C13),Flows!C13>=0,ISNUMBER(Flows!D13),Flows!D13>=1,OR(Flows!E13="",Flows!E13="once",Flows!E13="weekly",Flows!E13="biweekly"),OR(Flows!F13="",AND(ISNUMBER(Flows!F13),Flows!F13>=Flows!D13))),0,1))+IF(Flows!A14="",0,IF(AND(ISNUMBER(Flows!C14),Flows!C14>=0,ISNUMBER(Flows!D14),Flows!D14>=1,OR(Flows!E14="",Flows!E14="once",Flows!E14="weekly",Flows!E14="biweekly"),OR(Flows!F14="",AND(ISNUMBER(Flows!F14),Flows!F14>=Flows!D14))),0,1))+IF(Flows!A15="",0,IF(AND(ISNUMBER(Flows!C15),Flows!C15>=0,ISNUMBER(Flows!D15),Flows!D15>=1,OR(Flows!E15="",Flows!E15="once",Flows!E15="weekly",Flows!E15="biweekly"),OR(Flows!F15="",AND(ISNUMBER(Flows!F15),Flows!F15>=Flows!D15))),0,1))+IF(Flows!A16="",0,IF(AND(ISNUMBER(Flows!C16),Flows!C16>=0,ISNUMBER(Flows!D16),Flows!D16>=1,OR(Flows!E16="",Flows!E16="once",Flows!E16="weekly",Flows!E16="biweekly"),OR(Flows!F16="",AND(ISNUMBER(Flows!F16),Flows!F16>=Flows!D16))),0,1))+IF(Flows!A17="",0,IF(AND(ISNUMBER(Flows!C17),Flows!C17>=0,ISNUMBER(Flows!D17),Flows!D17>=1,OR(Flows!E17="",Flows!E17="once",Flows!E17="weekly",Flows!E17="biweekly"),OR(Flows!F17="",AND(ISNUMBER(Flows!F17),Flows!F17>=Flows!D17))),0,1))+IF(Flows!A18="",0,IF(AND(ISNUMBER(Flows!C18),Flows!C18>=0,ISNUMBER(Flows!D18),Flows!D18>=1,OR(Flows!E18="",Flows!E18="once",Flows!E18="weekly",Flows!E18="biweekly"),OR(Flows!F18="",AND(ISNUMBER(Flows!F18),Flows!F18>=Flows!D18))),0,1))+IF(Flows!A19="",0,IF(AND(ISNUMBER(Flows!C19),Flows!C19>=0,ISNUMBER(Flows!D19),Flows!D19>=1,OR(Flows!E19="",Flows!E19="once",Flows!E19="weekly",Flows!E19="biweekly"),OR(Flows!F19="",AND(ISNUMBER(Flows!F19),Flows!F19>=Flows!D19))),0,1))+IF(Flows!A20="",0,IF(AND(ISNUMBER(Flows!C20),Flows!C20>=0,ISNUMBER(Flows!D20),Flows!D20>=1,OR(Flows!E20="",Flows!E20="once",Flows!E20="weekly",Flows!E20="biweekly"),OR(Flows!F20="",AND(ISNUMBER(Flows!F20),Flows!F20>=Flows!D20))),0,1))+IF(Flows!A21="",0,IF(AND(ISNUMBER(Flows!C21),Flows!C21>=0,ISNUMBER(Flows!D21),Flows!D21>=1,OR(Flows!E21="",Flows!E21="once",Flows!E21="weekly",Flows!E21="biweekly"),OR(Flows!F21="",AND(ISNUMBER(Flows!F21),Flows!F21>=Flows!D21))),0,1))+IF(Flows!A22="",0,IF(AND(ISNUMBER(Flows!C22),Flows!C22>=0,ISNUMBER(Flows!D22),Flows!D22>=1,OR(Flows!E22="",Flows!E22="once",Flows!E22="weekly",Flows!E22="biweekly"),OR(Flows!F22="",AND(ISNUMBER(Flows!F22),Flows!F22>=Flows!D22))),0,1))+IF(Flows!A23="",0,IF(AND(ISNUMBER(Flows!C23),Flows!C23>=0,ISNUMBER(Flows!D23),Flows!D23>=1,OR(Flows!E23="",Flows!E23="once",Flows!E23="weekly",Flows!E23="biweekly"),OR(Flows!F23="",AND(ISNUMBER(Flows!F23),Flows!F23>=Flows!D23))),0,1))+IF(Flows!A24="",0,IF(AND(ISNUMBER(Flows!C24),Flows!C24>=0,ISNUMBER(Flows!D24),Flows!D24>=1,OR(Flows!E24="",Flows!E24="once",Flows!E24="weekly",Flows!E24="biweekly"),OR(Flows!F24="",AND(ISNUMBER(Flows!F24),Flows!F24>=Flows!D24))),0,1))+IF(Flows!A25="",0,IF(AND(ISNUMBER(Flows!C25),Flows!C25>=0,ISNUMBER(Flows!D25),Flows!D25>=1,OR(Flows!E25="",Flows!E25="once",Flows!E25="weekly",Flows!E25="biweekly"),OR(Flows!F25="",AND(ISNUMBER(Flows!F25),Flows!F25>=Flows!D25))),0,1))+IF(Flows!A26="",0,IF(AND(ISNUMBER(Flows!C26),Flows!C26>=0,ISNUMBER(Flows!D26),Flows!D26>=1,OR(Flows!E26="",Flows!E26="once",Flows!E26="weekly",Flows!E26="biweekly"),OR(Flows!F26="",AND(ISNUMBER(Flows!F26),Flows!F26>=Flows!D26))),0,1))+IF(Flows!A27="",0,IF(AND(ISNUMBER(Flows!C27),Flows!C27>=0,ISNUMBER(Flows!D27),Flows!D27>=1,OR(Flows!E27="",Flows!E27="once",Flows!E27="weekly",Flows!E27="biweekly"),OR(Flows!F27="",AND(ISNUMBER(Flows!F27),Flows!F27>=Flows!D27))),0,1))+IF(Flows!A28="",0,IF(AND(ISNUMBER(Flows!C28),Flows!C28>=0,ISNUMBER(Flows!D28),Flows!D28>=1,OR(Flows!E28="",Flows!E28="once",Flows!E28="weekly",Flows!E28="biweekly"),OR(Flows!F28="",AND(ISNUMBER(Flows!F28),Flows!F28>=Flows!D28))),0,1))+IF(Flows!A29="",0,IF(AND(ISNUMBER(Flows!C29),Flows!C29>=0,ISNUMBER(Flows!D29),Flows!D29>=1,OR(Flows!E29="",Flows!E29="once",Flows!E29="weekly",Flows!E29="biweekly"),OR(Flows!F29="",AND(ISNUMBER(Flows!F29),Flows!F29>=Flows!D29))),0,1))+IF(Flows!A30="",0,IF(AND(ISNUMBER(Flows!C30),Flows!C30>=0,ISNUMBER(Flows!D30),Flows!D30>=1,OR(Flows!E30="",Flows!E30="once",Flows!E30="weekly",Flows!E30="biweekly"),OR(Flows!F30="",AND(ISNUMBER(Flows!F30),Flows!F30>=Flows!D30))),0,1))+IF(Flows!A31="",0,IF(AND(ISNUMBER(Flows!C31),Flows!C31>=0,ISNUMBER(Flows!D31),Flows!D31>=1,OR(Flows!E31="",Flows!E31="once",Flows!E31="weekly",Flows!E31="biweekly"),OR(Flows!F31="",AND(ISNUMBER(Flows!F31),Flows!F31>=Flows!D31))),0,1))+IF(Flows!A32="",0,IF(AND(ISNUMBER(Flows!C32),Flows!C32>=0,ISNUMBER(Flows!D32),Flows!D32>=1,OR(Flows!E32="",Flows!E32="once",Flows!E32="weekly",Flows!E32="biweekly"),OR(Flows!F32="",AND(ISNUMBER(Flows!F32),Flows!F32>=Flows!D32))),0,1))+IF(Flows!A33="",0,IF(AND(ISNUMBER(Flows!C33),Flows!C33>=0,ISNUMBER(Flows!D33),Flows!D33>=1,OR(Flows!E33="",Flows!E33="once",Flows!E33="weekly",Flows!E33="biweekly"),OR(Flows!F33="",AND(ISNUMBER(Flows!F33),Flows!F33>=Flows!D33))),0,1))+IF(Flows!A34="",0,IF(AND(ISNUMBER(Flows!C34),Flows!C34>=0,ISNUMBER(Flows!D34),Flows!D34>=1,OR(Flows!E34="",Flows!E34="once",Flows!E34="weekly",Flows!E34="biweekly"),OR(Flows!F34="",AND(ISNUMBER(Flows!F34),Flows!F34>=Flows!D34))),0,1))+IF(Flows!A35="",0,IF(AND(ISNUMBER(Flows!C35),Flows!C35>=0,ISNUMBER(Flows!D35),Flows!D35>=1,OR(Flows!E35="",Flows!E35="once",Flows!E35="weekly",Flows!E35="biweekly"),OR(Flows!F35="",AND(ISNUMBER(Flows!F35),Flows!F35>=Flows!D35))),0,1))+IF(Flows!A36="",0,IF(AND(ISNUMBER(Flows!C36),Flows!C36>=0,ISNUMBER(Flows!D36),Flows!D36>=1,OR(Flows!E36="",Flows!E36="once",Flows!E36="weekly",Flows!E36="biweekly"),OR(Flows!F36="",AND(ISNUMBER(Flows!F36),Flows!F36>=Flows!D36))),0,1))+IF(Flows!A37="",0,IF(AND(ISNUMBER(Flows!C37),Flows!C37>=0,ISNUMBER(Flows!D37),Flows!D37>=1,OR(Flows!E37="",Flows!E37="once",Flows!E37="weekly",Flows!E37="biweekly"),OR(Flows!F37="",AND(ISNUMBER(Flows!F37),Flows!F37>=Flows!D37))),0,1))+IF(Flows!A38="",0,IF(AND(ISNUMBER(Flows!C38),Flows!C38>=0,ISNUMBER(Flows!D38),Flows!D38>=1,OR(Flows!E38="",Flows!E38="once",Flows!E38="weekly",Flows!E38="biweekly"),OR(Flows!F38="",AND(ISNUMBER(Flows!F38),Flows!F38>=Flows!D38))),0,1))+IF(Flows!A39="",0,IF(AND(ISNUMBER(Flows!C39),Flows!C39>=0,ISNUMBER(Flows!D39),Flows!D39>=1,OR(Flows!E39="",Flows!E39="once",Flows!E39="weekly",Flows!E39="biweekly"),OR(Flows!F39="",AND(ISNUMBER(Flows!F39),Flows!F39>=Flows!D39))),0,1))+IF(Flows!A40="",0,IF(AND(ISNUMBER(Flows!C40),Flows!C40>=0,ISNUMBER(Flows!D40),Flows!D40>=1,OR(Flows!E40="",Flows!E40="once",Flows!E40="weekly",Flows!E40="biweekly"),OR(Flows!F40="",AND(ISNUMBER(Flows!F40),Flows!F40>=Flows!D40))),0,1))+IF(Flows!A41="",0,IF(AND(ISNUMBER(Flows!C41),Flows!C41>=0,ISNUMBER(Flows!D41),Flows!D41>=1,OR(Flows!E41="",Flows!E41="once",Flows!E41="weekly",Flows!E41="biweekly"),OR(Flows!F41="",AND(ISNUMBER(Flows!F41),Flows!F41>=Flows!D41))),0,1))+IF(Flows!A42="",0,IF(AND(ISNUMBER(Flows!C42),Flows!C42>=0,ISNUMBER(Flows!D42),Flows!D42>=1,OR(Flows!E42="",Flows!E42="once",Flows!E42="weekly",Flows!E42="biweekly"),OR(Flows!F42="",AND(ISNUMBER(Flows!F42),Flows!F42>=Flows!D42))),0,1))+IF(Flows!A43="",0,IF(AND(ISNUMBER(Flows!C43),Flows!C43>=0,ISNUMBER(Flows!D43),Flows!D43>=1,OR(Flows!E43="",Flows!E43="once",Flows!E43="weekly",Flows!E43="biweekly"),OR(Flows!F43="",AND(ISNUMBER(Flows!F43),Flows!F43>=Flows!D43))),0,1))+IF(Flows!A44="",0,IF(AND(ISNUMBER(Flows!C44),Flows!C44>=0,ISNUMBER(Flows!D44),Flows!D44>=1,OR(Flows!E44="",Flows!E44="once",Flows!E44="weekly",Flows!E44="biweekly"),OR(Flows!F44="",AND(ISNUMBER(Flows!F44),Flows!F44>=Flows!D44))),0,1))+IF(Flows!A45="",0,IF(AND(ISNUMBER(Flows!C45),Flows!C45>=0,ISNUMBER(Flows!D45),Flows!D45>=1,OR(Flows!E45="",Flows!E45="once",Flows!E45="weekly",Flows!E45="biweekly"),OR(Flows!F45="",AND(ISNUMBER(Flows!F45),Flows!F45>=Flows!D45))),0,1))+IF(Flows!A46="",0,IF(AND(ISNUMBER(Flows!C46),Flows!C46>=0,ISNUMBER(Flows!D46),Flows!D46>=1,OR(Flows!E46="",Flows!E46="once",Flows!E46="weekly",Flows!E46="biweekly"),OR(Flows!F46="",AND(ISNUMBER(Flows!F46),Flows!F46>=Flows!D46))),0,1))+IF(Flows!A47="",0,IF(AND(ISNUMBER(Flows!C47),Flows!C47>=0,ISNUMBER(Flows!D47),Flows!D47>=1,OR(Flows!E47="",Flows!E47="once",Flows!E47="weekly",Flows!E47="biweekly"),OR(Flows!F47="",AND(ISNUMBER(Flows!F47),Flows!F47>=Flows!D47))),0,1))+IF(Flows!A48="",0,IF(AND(ISNUMBER(Flows!C48),Flows!C48>=0,ISNUMBER(Flows!D48),Flows!D48>=1,OR(Flows!E48="",Flows!E48="once",Flows!E48="weekly",Flows!E48="biweekly"),OR(Flows!F48="",AND(ISNUMBER(Flows!F48),Flows!F48>=Flows!D48))),0,1))+IF(Flows!A49="",0,IF(AND(ISNUMBER(Flows!C49),Flows!C49>=0,ISNUMBER(Flows!D49),Flows!D49>=1,OR(Flows!E49="",Flows!E49="once",Flows!E49="weekly",Flows!E49="biweekly"),OR(Flows!F49="",AND(ISNUMBER(Flows!F49),Flows!F49>=Flows!D49))),0,1))+IF(Flows!A50="",0,IF(AND(ISNUMBER(Flows!C50),Flows!C50>=0,ISNUMBER(Flows!D50),Flows!D50>=1,OR(Flows!E50="",Flows!E50="once",Flows!E50="weekly",Flows!E50="biweekly"),OR(Flows!F50="",AND(ISNUMBER(Flows!F50),Flows!F50>=Flows!D50))),0,1))+IF(Flows!A51="",0,IF(AND(ISNUMBER(Flows!C51),Flows!C51>=0,ISNUMBER(Flows!D51),Flows!D51>=1,OR(Flows!E51="",Flows!E51="once",Flows!E51="weekly",Flows!E51="biweekly"),OR(Flows!F51="",AND(ISNUMBER(Flows!F51),Flows!F51>=Flows!D51))),0,1))+IF(Flows!A52="",0,IF(AND(ISNUMBER(Flows!C52),Flows!C52>=0,ISNUMBER(Flows!D52),Flows!D52>=1,OR(Flows!E52="",Flows!E52="once",Flows!E52="weekly",Flows!E52="biweekly"),OR(Flows!F52="",AND(ISNUMBER(Flows!F52),Flows!F52>=Flows!D52))),0,1))+IF(Flows!A53="",0,IF(AND(ISNUMBER(Flows!C53),Flows!C53>=0,ISNUMBER(Flows!D53),Flows!D53>=1,OR(Flows!E53="",Flows!E53="once",Flows!E53="weekly",Flows!E53="biweekly"),OR(Flows!F53="",AND(ISNUMBER(Flows!F53),Flows!F53>=Flows!D53))),0,1))+IF(Flows!A54="",0,IF(AND(ISNUMBER(Flows!C54),Flows!C54>=0,ISNUMBER(Flows!D54),Flows!D54>=1,OR(Flows!E54="",Flows!E54="once",Flows!E54="weekly",Flows!E54="biweekly"),OR(Flows!F54="",AND(ISNUMBER(Flows!F54),Flows!F54>=Flows!D54))),0,1))+IF(Flows!A55="",0,IF(AND(ISNUMBER(Flows!C55),Flows!C55>=0,ISNUMBER(Flows!D55),Flows!D55>=1,OR(Flows!E55="",Flows!E55="once",Flows!E55="weekly",Flows!E55="biweekly"),OR(Flows!F55="",AND(ISNUMBER(Flows!F55),Flows!F55>=Flows!D55))),0,1))+IF(Flows!A56="",0,IF(AND(ISNUMBER(Flows!C56),Flows!C56>=0,ISNUMBER(Flows!D56),Flows!D56>=1,OR(Flows!E56="",Flows!E56="once",Flows!E56="weekly",Flows!E56="biweekly"),OR(Flows!F56="",AND(ISNUMBER(Flows!F56),Flows!F56>=Flows!D56))),0,1))+IF(Flows!A57="",0,IF(AND(ISNUMBER(Flows!C57),Flows!C57>=0,ISNUMBER(Flows!D57),Flows!D57>=1,OR(Flows!E57="",Flows!E57="once",Flows!E57="weekly",Flows!E57="biweekly"),OR(Flows!F57="",AND(ISNUMBER(Flows!F57),Flows!F57>=Flows!D57))),0,1))+IF(Flows!A58="",0,IF(AND(ISNUMBER(Flows!C58),Flows!C58>=0,ISNUMBER(Flows!D58),Flows!D58>=1,OR(Flows!E58="",Flows!E58="once",Flows!E58="weekly",Flows!E58="biweekly"),OR(Flows!F58="",AND(ISNUMBER(Flows!F58),Flows!F58>=Flows!D58))),0,1))+IF(Flows!A59="",0,IF(AND(ISNUMBER(Flows!C59),Flows!C59>=0,ISNUMBER(Flows!D59),Flows!D59>=1,OR(Flows!E59="",Flows!E59="once",Flows!E59="weekly",Flows!E59="biweekly"),OR(Flows!F59="",AND(ISNUMBER(Flows!F59),Flows!F59>=Flows!D59))),0,1))+IF(Flows!A60="",0,IF(AND(ISNUMBER(Flows!C60),Flows!C60>=0,ISNUMBER(Flows!D60),Flows!D60>=1,OR(Flows!E60="",Flows!E60="once",Flows!E60="weekly",Flows!E60="biweekly"),OR(Flows!F60="",AND(ISNUMBER(Flows!F60),Flows!F60>=Flows!D60))),0,1))+IF(Flows!A61="",0,IF(AND(ISNUMBER(Flows!C61),Flows!C61>=0,ISNUMBER(Flows!D61),Flows!D61>=1,OR(Flows!E61="",Flows!E61="once",Flows!E61="weekly",Flows!E61="biweekly"),OR(Flows!F61="",AND(ISNUMBER(Flows!F61),Flows!F61>=Flows!D61))),0,1))+IF(Flows!A62="",0,IF(AND(ISNUMBER(Flows!C62),Flows!C62>=0,ISNUMBER(Flows!D62),Flows!D62>=1,OR(Flows!E62="",Flows!E62="once",Flows!E62="weekly",Flows!E62="biweekly"),OR(Flows!F62="",AND(ISNUMBER(Flows!F62),Flows!F62>=Flows!D62))),0,1))+IF(Flows!A63="",0,IF(AND(ISNUMBER(Flows!C63),Flows!C63>=0,ISNUMBER(Flows!D63),Flows!D63>=1,OR(Flows!E63="",Flows!E63="once",Flows!E63="weekly",Flows!E63="biweekly"),OR(Flows!F63="",AND(ISNUMBER(Flows!F63),Flows!F63>=Flows!D63))),0,1))+IF(Flows!A64="",0,IF(AND(ISNUMBER(Flows!C64),Flows!C64>=0,ISNUMBER(Flows!D64),Flows!D64>=1,OR(Flows!E64="",Flows!E64="once",Flows!E64="weekly",Flows!E64="biweekly"),OR(Flows!F64="",AND(ISNUMBER(Flows!F64),Flows!F64>=Flows!D64))),0,1))+IF(Flows!A65="",0,IF(AND(ISNUMBER(Flows!C65),Flows!C65>=0,ISNUMBER(Flows!D65),Flows!D65>=1,OR(Flows!E65="",Flows!E65="once",Flows!E65="weekly",Flows!E65="biweekly"),OR(Flows!F65="",AND(ISNUMBER(Flows!F65),Flows!F65>=Flows!D65))),0,1))+IF(Flows!A66="",0,IF(AND(ISNUMBER(Flows!C66),Flows!C66>=0,ISNUMBER(Flows!D66),Flows!D66>=1,OR(Flows!E66="",Flows!E66="once",Flows!E66="weekly",Flows!E66="biweekly"),OR(Flows!F66="",AND(ISNUMBER(Flows!F66),Flows!F66>=Flows!D66))),0,1))+IF(Flows!A67="",0,IF(AND(ISNUMBER(Flows!C67),Flows!C67>=0,ISNUMBER(Flows!D67),Flows!D67>=1,OR(Flows!E67="",Flows!E67="once",Flows!E67="weekly",Flows!E67="biweekly"),OR(Flows!F67="",AND(ISNUMBER(Flows!F67),Flows!F67>=Flows!D67))),0,1))+IF(Flows!A68="",0,IF(AND(ISNUMBER(Flows!C68),Flows!C68>=0,ISNUMBER(Flows!D68),Flows!D68>=1,OR(Flows!E68="",Flows!E68="once",Flows!E68="weekly",Flows!E68="biweekly"),OR(Flows!F68="",AND(ISNUMBER(Flows!F68),Flows!F68>=Flows!D68))),0,1))+IF(Flows!A69="",0,IF(AND(ISNUMBER(Flows!C69),Flows!C69>=0,ISNUMBER(Flows!D69),Flows!D69>=1,OR(Flows!E69="",Flows!E69="once",Flows!E69="weekly",Flows!E69="biweekly"),OR(Flows!F69="",AND(ISNUMBER(Flows!F69),Flows!F69>=Flows!D69))),0,1))+IF(Flows!A70="",0,IF(AND(ISNUMBER(Flows!C70),Flows!C70>=0,ISNUMBER(Flows!D70),Flows!D70>=1,OR(Flows!E70="",Flows!E70="once",Flows!E70="weekly",Flows!E70="biweekly"),OR(Flows!F70="",AND(ISNUMBER(Flows!F70),Flows!F70>=Flows!D70))),0,1))+IF(Flows!A71="",0,IF(AND(ISNUMBER(Flows!C71),Flows!C71>=0,ISNUMBER(Flows!D71),Flows!D71>=1,OR(Flows!E71="",Flows!E71="once",Flows!E71="weekly",Flows!E71="biweekly"),OR(Flows!F71="",AND(ISNUMBER(Flows!F71),Flows!F71>=Flows!D71))),0,1))+IF(Flows!A72="",0,IF(AND(ISNUMBER(Flows!C72),Flows!C72>=0,ISNUMBER(Flows!D72),Flows!D72>=1,OR(Flows!E72="",Flows!E72="once",Flows!E72="weekly",Flows!E72="biweekly"),OR(Flows!F72="",AND(ISNUMBER(Flows!F72),Flows!F72>=Flows!D72))),0,1))+IF(Flows!A73="",0,IF(AND(ISNUMBER(Flows!C73),Flows!C73>=0,ISNUMBER(Flows!D73),Flows!D73>=1,OR(Flows!E73="",Flows!E73="once",Flows!E73="weekly",Flows!E73="biweekly"),OR(Flows!F73="",AND(ISNUMBER(Flows!F73),Flows!F73>=Flows!D73))),0,1))+IF(Flows!A74="",0,IF(AND(ISNUMBER(Flows!C74),Flows!C74>=0,ISNUMBER(Flows!D74),Flows!D74>=1,OR(Flows!E74="",Flows!E74="once",Flows!E74="weekly",Flows!E74="biweekly"),OR(Flows!F74="",AND(ISNUMBER(Flows!F74),Flows!F74>=Flows!D74))),0,1))+IF(Flows!A75="",0,IF(AND(ISNUMBER(Flows!C75),Flows!C75>=0,ISNUMBER(Flows!D75),Flows!D75>=1,OR(Flows!E75="",Flows!E75="once",Flows!E75="weekly",Flows!E75="biweekly"),OR(Flows!F75="",AND(ISNUMBER(Flows!F75),Flows!F75>=Flows!D75))),0,1))+IF(Flows!A76="",0,IF(AND(ISNUMBER(Flows!C76),Flows!C76>=0,ISNUMBER(Flows!D76),Flows!D76>=1,OR(Flows!E76="",Flows!E76="once",Flows!E76="weekly",Flows!E76="biweekly"),OR(Flows!F76="",AND(ISNUMBER(Flows!F76),Flows!F76>=Flows!D76))),0,1))+IF(Flows!A77="",0,IF(AND(ISNUMBER(Flows!C77),Flows!C77>=0,ISNUMBER(Flows!D77),Flows!D77>=1,OR(Flows!E77="",Flows!E77="once",Flows!E77="weekly",Flows!E77="biweekly"),OR(Flows!F77="",AND(ISNUMBER(Flows!F77),Flows!F77>=Flows!D77))),0,1))+IF(Flows!A78="",0,IF(AND(ISNUMBER(Flows!C78),Flows!C78>=0,ISNUMBER(Flows!D78),Flows!D78>=1,OR(Flows!E78="",Flows!E78="once",Flows!E78="weekly",Flows!E78="biweekly"),OR(Flows!F78="",AND(ISNUMBER(Flows!F78),Flows!F78>=Flows!D78))),0,1))+IF(Flows!A79="",0,IF(AND(ISNUMBER(Flows!C79),Flows!C79>=0,ISNUMBER(Flows!D79),Flows!D79>=1,OR(Flows!E79="",Flows!E79="once",Flows!E79="weekly",Flows!E79="biweekly"),OR(Flows!F79="",AND(ISNUMBER(Flows!F79),Flows!F79>=Flows!D79))),0,1))+IF(Flows!A80="",0,IF(AND(ISNUMBER(Flows!C80),Flows!C80>=0,ISNUMBER(Flows!D80),Flows!D80>=1,OR(Flows!E80="",Flows!E80="once",Flows!E80="weekly",Flows!E80="biweekly"),OR(Flows!F80="",AND(ISNUMBER(Flows!F80),Flows!F80>=Flows!D80))),0,1))+IF(Flows!A81="",0,IF(AND(ISNUMBER(Flows!C81),Flows!C81>=0,ISNUMBER(Flows!D81),Flows!D81>=1,OR(Flows!E81="",Flows!E81="once",Flows!E81="weekly",Flows!E81="biweekly"),OR(Flows!F81="",AND(ISNUMBER(Flows!F81),Flows!F81>=Flows!D81))),0,1))+IF(Flows!A82="",0,IF(AND(ISNUMBER(Flows!C82),Flows!C82>=0,ISNUMBER(Flows!D82),Flows!D82>=1,OR(Flows!E82="",Flows!E82="once",Flows!E82="weekly",Flows!E82="biweekly"),OR(Flows!F82="",AND(ISNUMBER(Flows!F82),Flows!F82>=Flows!D82))),0,1))+IF(Flows!A83="",0,IF(AND(ISNUMBER(Flows!C83),Flows!C83>=0,ISNUMBER(Flows!D83),Flows!D83>=1,OR(Flows!E83="",Flows!E83="once",Flows!E83="weekly",Flows!E83="biweekly"),OR(Flows!F83="",AND(ISNUMBER(Flows!F83),Flows!F83>=Flows!D83))),0,1))+IF(Flows!A84="",0,IF(AND(ISNUMBER(Flows!C84),Flows!C84>=0,ISNUMBER(Flows!D84),Flows!D84>=1,OR(Flows!E84="",Flows!E84="once",Flows!E84="weekly",Flows!E84="biweekly"),OR(Flows!F84="",AND(ISNUMBER(Flows!F84),Flows!F84>=Flows!D84))),0,1)))=0,"PASS","FAIL") | D8: =(IF(Flows!A5="",0,IF(AND(ISNUMBER(Flows!C5),Flows!C5>=0,ISNUMBER(Flows!D5),Flows!D5>=1,OR(Flows!E5="",Flows!E5="once",Flows!E5="weekly",Flows!E5="biweekly"),OR(Flows!F5="",AND(ISNUMBER(Flows!F5),Flows!F5>=Flows!D5))),0,1))+IF(Flows!A6="",0,IF(AND(ISNUMBER(Flows!C6),Flows!C6>=0,ISNUMBER(Flows!D6),Flows!D6>=1,OR(Flows!E6="",Flows!E6="once",Flows!E6="weekly",Flows!E6="biweekly"),OR(Flows!F6="",AND(ISNUMBER(Flows!F6),Flows!F6>=Flows!D6))),0,1))+IF(Flows!A7="",0,IF(AND(ISNUMBER(Flows!C7),Flows!C7>=0,ISNUMBER(Flows!D7),Flows!D7>=1,OR(Flows!E7="",Flows!E7="once",Flows!E7="weekly",Flows!E7="biweekly"),OR(Flows!F7="",AND(ISNUMBER(Flows!F7),Flows!F7>=Flows!D7))),0,1))+IF(Flows!A8="",0,IF(AND(ISNUMBER(Flows!C8),Flows!C8>=0,ISNUMBER(Flows!D8),Flows!D8>=1,OR(Flows!E8="",Flows!E8="once",Flows!E8="weekly",Flows!E8="biweekly"),OR(Flows!F8="",AND(ISNUMBER(Flows!F8),Flows!F8>=Flows!D8))),0,1))+IF(Flows!A9="",0,IF(AND(ISNUMBER(Flows!C9),Flows!C9>=0,ISNUMBER(Flows!D9),Flows!D9>=1,OR(Flows!E9="",Flows!E9="once",Flows!E9="weekly",Flows!E9="biweekly"),OR(Flows!F9="",AND(ISNUMBER(Flows!F9),Flows!F9>=Flows!D9))),0,1))+IF(Flows!A10="",0,IF(AND(ISNUMBER(Flows!C10),Flows!C10>=0,ISNUMBER(Flows!D10),Flows!D10>=1,OR(Flows!E10="",Flows!E10="once",Flows!E10="weekly",Flows!E10="biweekly"),OR(Flows!F10="",AND(ISNUMBER(Flows!F10),Flows!F10>=Flows!D10))),0,1))+IF(Flows!A11="",0,IF(AND(ISNUMBER(Flows!C11),Flows!C11>=0,ISNUMBER(Flows!D11),Flows!D11>=1,OR(Flows!E11="",Flows!E11="once",Flows!E11="weekly",Flows!E11="biweekly"),OR(Flows!F11="",AND(ISNUMBER(Flows!F11),Flows!F11>=Flows!D11))),0,1))+IF(Flows!A12="",0,IF(AND(ISNUMBER(Flows!C12),Flows!C12>=0,ISNUMBER(Flows!D12),Flows!D12>=1,OR(Flows!E12="",Flows!E12="once",Flows!E12="weekly",Flows!E12="biweekly"),OR(Flows!F12="",AND(ISNUMBER(Flows!F12),Flows!F12>=Flows!D12))),0,1))+IF(Flows!A13="",0,IF(AND(ISNUMBER(Flows!C13),Flows!C13>=0,ISNUMBER(Flows!D13),Flows!D13>=1,OR(Flows!E13="",Flows!E13="once",Flows!E13="weekly",Flows!E13="biweekly"),OR(Flows!F13="",AND(ISNUMBER(Flows!F13),Flows!F13>=Flows!D13))),0,1))+IF(Flows!A14="",0,IF(AND(ISNUMBER(Flows!C14),Flows!C14>=0,ISNUMBER(Flows!D14),Flows!D14>=1,OR(Flows!E14="",Flows!E14="once",Flows!E14="weekly",Flows!E14="biweekly"),OR(Flows!F14="",AND(ISNUMBER(Flows!F14),Flows!F14>=Flows!D14))),0,1))+IF(Flows!A15="",0,IF(AND(ISNUMBER(Flows!C15),Flows!C15>=0,ISNUMBER(Flows!D15),Flows!D15>=1,OR(Flows!E15="",Flows!E15="once",Flows!E15="weekly",Flows!E15="biweekly"),OR(Flows!F15="",AND(ISNUMBER(Flows!F15),Flows!F15>=Flows!D15))),0,1))+IF(Flows!A16="",0,IF(AND(ISNUMBER(Flows!C16),Flows!C16>=0,ISNUMBER(Flows!D16),Flows!D16>=1,OR(Flows!E16="",Flows!E16="once",Flows!E16="weekly",Flows!E16="biweekly"),OR(Flows!F16="",AND(ISNUMBER(Flows!F16),Flows!F16>=Flows!D16))),0,1))+IF(Flows!A17="",0,IF(AND(ISNUMBER(Flows!C17),Flows!C17>=0,ISNUMBER(Flows!D17),Flows!D17>=1,OR(Flows!E17="",Flows!E17="once",Flows!E17="weekly",Flows!E17="biweekly"),OR(Flows!F17="",AND(ISNUMBER(Flows!F17),Flows!F17>=Flows!D17))),0,1))+IF(Flows!A18="",0,IF(AND(ISNUMBER(Flows!C18),Flows!C18>=0,ISNUMBER(Flows!D18),Flows!D18>=1,OR(Flows!E18="",Flows!E18="once",Flows!E18="weekly",Flows!E18="biweekly"),OR(Flows!F18="",AND(ISNUMBER(Flows!F18),Flows!F18>=Flows!D18))),0,1))+IF(Flows!A19="",0,IF(AND(ISNUMBER(Flows!C19),Flows!C19>=0,ISNUMBER(Flows!D19),Flows!D19>=1,OR(Flows!E19="",Flows!E19="once",Flows!E19="weekly",Flows!E19="biweekly"),OR(Flows!F19="",AND(ISNUMBER(Flows!F19),Flows!F19>=Flows!D19))),0,1))+IF(Flows!A20="",0,IF(AND(ISNUMBER(Flows!C20),Flows!C20>=0,ISNUMBER(Flows!D20),Flows!D20>=1,OR(Flows!E20="",Flows!E20="once",Flows!E20="weekly",Flows!E20="biweekly"),OR(Flows!F20="",AND(ISNUMBER(Flows!F20),Flows!F20>=Flows!D20))),0,1))+IF(Flows!A21="",0,IF(AND(ISNUMBER(Flows!C21),Flows!C21>=0,ISNUMBER(Flows!D21),Flows!D21>=1,OR(Flows!E21="",Flows!E21="once",Flows!E21="weekly",Flows!E21="biweekly"),OR(Flows!F21="",AND(ISNUMBER(Flows!F21),Flows!F21>=Flows!D21))),0,1))+IF(Flows!A22="",0,IF(AND(ISNUMBER(Flows!C22),Flows!C22>=0,ISNUMBER(Flows!D22),Flows!D22>=1,OR(Flows!E22="",Flows!E22="once",Flows!E22="weekly",Flows!E22="biweekly"),OR(Flows!F22="",AND(ISNUMBER(Flows!F22),Flows!F22>=Flows!D22))),0,1))+IF(Flows!A23="",0,IF(AND(ISNUMBER(Flows!C23),Flows!C23>=0,ISNUMBER(Flows!D23),Flows!D23>=1,OR(Flows!E23="",Flows!E23="once",Flows!E23="weekly",Flows!E23="biweekly"),OR(Flows!F23="",AND(ISNUMBER(Flows!F23),Flows!F23>=Flows!D23))),0,1))+IF(Flows!A24="",0,IF(AND(ISNUMBER(Flows!C24),Flows!C24>=0,ISNUMBER(Flows!D24),Flows!D24>=1,OR(Flows!E24="",Flows!E24="once",Flows!E24="weekly",Flows!E24="biweekly"),OR(Flows!F24="",AND(ISNUMBER(Flows!F24),Flows!F24>=Flows!D24))),0,1))+IF(Flows!A25="",0,IF(AND(ISNUMBER(Flows!C25),Flows!C25>=0,ISNUMBER(Flows!D25),Flows!D25>=1,OR(Flows!E25="",Flows!E25="once",Flows!E25="weekly",Flows!E25="biweekly"),OR(Flows!F25="",AND(ISNUMBER(Flows!F25),Flows!F25>=Flows!D25))),0,1))+IF(Flows!A26="",0,IF(AND(ISNUMBER(Flows!C26),Flows!C26>=0,ISNUMBER(Flows!D26),Flows!D26>=1,OR(Flows!E26="",Flows!E26="once",Flows!E26="weekly",Flows!E26="biweekly"),OR(Flows!F26="",AND(ISNUMBER(Flows!F26),Flows!F26>=Flows!D26))),0,1))+IF(Flows!A27="",0,IF(AND(ISNUMBER(Flows!C27),Flows!C27>=0,ISNUMBER(Flows!D27),Flows!D27>=1,OR(Flows!E27="",Flows!E27="once",Flows!E27="weekly",Flows!E27="biweekly"),OR(Flows!F27="",AND(ISNUMBER(Flows!F27),Flows!F27>=Flows!D27))),0,1))+IF(Flows!A28="",0,IF(AND(ISNUMBER(Flows!C28),Flows!C28>=0,ISNUMBER(Flows!D28),Flows!D28>=1,OR(Flows!E28="",Flows!E28="once",Flows!E28="weekly",Flows!E28="biweekly"),OR(Flows!F28="",AND(ISNUMBER(Flows!F28),Flows!F28>=Flows!D28))),0,1))+IF(Flows!A29="",0,IF(AND(ISNUMBER(Flows!C29),Flows!C29>=0,ISNUMBER(Flows!D29),Flows!D29>=1,OR(Flows!E29="",Flows!E29="once",Flows!E29="weekly",Flows!E29="biweekly"),OR(Flows!F29="",AND(ISNUMBER(Flows!F29),Flows!F29>=Flows!D29))),0,1))+IF(Flows!A30="",0,IF(AND(ISNUMBER(Flows!C30),Flows!C30>=0,ISNUMBER(Flows!D30),Flows!D30>=1,OR(Flows!E30="",Flows!E30="once",Flows!E30="weekly",Flows!E30="biweekly"),OR(Flows!F30="",AND(ISNUMBER(Flows!F30),Flows!F30>=Flows!D30))),0,1))+IF(Flows!A31="",0,IF(AND(ISNUMBER(Flows!C31),Flows!C31>=0,ISNUMBER(Flows!D31),Flows!D31>=1,OR(Flows!E31="",Flows!E31="once",Flows!E31="weekly",Flows!E31="biweekly"),OR(Flows!F31="",AND(ISNUMBER(Flows!F31),Flows!F31>=Flows!D31))),0,1))+IF(Flows!A32="",0,IF(AND(ISNUMBER(Flows!C32),Flows!C32>=0,ISNUMBER(Flows!D32),Flows!D32>=1,OR(Flows!E32="",Flows!E32="once",Flows!E32="weekly",Flows!E32="biweekly"),OR(Flows!F32="",AND(ISNUMBER(Flows!F32),Flows!F32>=Flows!D32))),0,1))+IF(Flows!A33="",0,IF(AND(ISNUMBER(Flows!C33),Flows!C33>=0,ISNUMBER(Flows!D33),Flows!D33>=1,OR(Flows!E33="",Flows!E33="once",Flows!E33="weekly",Flows!E33="biweekly"),OR(Flows!F33="",AND(ISNUMBER(Flows!F33),Flows!F33>=Flows!D33))),0,1))+IF(Flows!A34="",0,IF(AND(ISNUMBER(Flows!C34),Flows!C34>=0,ISNUMBER(Flows!D34),Flows!D34>=1,OR(Flows!E34="",Flows!E34="once",Flows!E34="weekly",Flows!E34="biweekly"),OR(Flows!F34="",AND(ISNUMBER(Flows!F34),Flows!F34>=Flows!D34))),0,1))+IF(Flows!A35="",0,IF(AND(ISNUMBER(Flows!C35),Flows!C35>=0,ISNUMBER(Flows!D35),Flows!D35>=1,OR(Flows!E35="",Flows!E35="once",Flows!E35="weekly",Flows!E35="biweekly"),OR(Flows!F35="",AND(ISNUMBER(Flows!F35),Flows!F35>=Flows!D35))),0,1))+IF(Flows!A36="",0,IF(AND(ISNUMBER(Flows!C36),Flows!C36>=0,ISNUMBER(Flows!D36),Flows!D36>=1,OR(Flows!E36="",Flows!E36="once",Flows!E36="weekly",Flows!E36="biweekly"),OR(Flows!F36="",AND(ISNUMBER(Flows!F36),Flows!F36>=Flows!D36))),0,1))+IF(Flows!A37="",0,IF(AND(ISNUMBER(Flows!C37),Flows!C37>=0,ISNUMBER(Flows!D37),Flows!D37>=1,OR(Flows!E37="",Flows!E37="once",Flows!E37="weekly",Flows!E37="biweekly"),OR(Flows!F37="",AND(ISNUMBER(Flows!F37),Flows!F37>=Flows!D37))),0,1))+IF(Flows!A38="",0,IF(AND(ISNUMBER(Flows!C38),Flows!C38>=0,ISNUMBER(Flows!D38),Flows!D38>=1,OR(Flows!E38="",Flows!E38="once",Flows!E38="weekly",Flows!E38="biweekly"),OR(Flows!F38="",AND(ISNUMBER(Flows!F38),Flows!F38>=Flows!D38))),0,1))+IF(Flows!A39="",0,IF(AND(ISNUMBER(Flows!C39),Flows!C39>=0,ISNUMBER(Flows!D39),Flows!D39>=1,OR(Flows!E39="",Flows!E39="once",Flows!E39="weekly",Flows!E39="biweekly"),OR(Flows!F39="",AND(ISNUMBER(Flows!F39),Flows!F39>=Flows!D39))),0,1))+IF(Flows!A40="",0,IF(AND(ISNUMBER(Flows!C40),Flows!C40>=0,ISNUMBER(Flows!D40),Flows!D40>=1,OR(Flows!E40="",Flows!E40="once",Flows!E40="weekly",Flows!E40="biweekly"),OR(Flows!F40="",AND(ISNUMBER(Flows!F40),Flows!F40>=Flows!D40))),0,1))+IF(Flows!A41="",0,IF(AND(ISNUMBER(Flows!C41),Flows!C41>=0,ISNUMBER(Flows!D41),Flows!D41>=1,OR(Flows!E41="",Flows!E41="once",Flows!E41="weekly",Flows!E41="biweekly"),OR(Flows!F41="",AND(ISNUMBER(Flows!F41),Flows!F41>=Flows!D41))),0,1))+IF(Flows!A42="",0,IF(AND(ISNUMBER(Flows!C42),Flows!C42>=0,ISNUMBER(Flows!D42),Flows!D42>=1,OR(Flows!E42="",Flows!E42="once",Flows!E42="weekly",Flows!E42="biweekly"),OR(Flows!F42="",AND(ISNUMBER(Flows!F42),Flows!F42>=Flows!D42))),0,1))+IF(Flows!A43="",0,IF(AND(ISNUMBER(Flows!C43),Flows!C43>=0,ISNUMBER(Flows!D43),Flows!D43>=1,OR(Flows!E43="",Flows!E43="once",Flows!E43="weekly",Flows!E43="biweekly"),OR(Flows!F43="",AND(ISNUMBER(Flows!F43),Flows!F43>=Flows!D43))),0,1))+IF(Flows!A44="",0,IF(AND(ISNUMBER(Flows!C44),Flows!C44>=0,ISNUMBER(Flows!D44),Flows!D44>=1,OR(Flows!E44="",Flows!E44="once",Flows!E44="weekly",Flows!E44="biweekly"),OR(Flows!F44="",AND(ISNUMBER(Flows!F44),Flows!F44>=Flows!D44))),0,1))+IF(Flows!A45="",0,IF(AND(ISNUMBER(Flows!C45),Flows!C45>=0,ISNUMBER(Flows!D45),Flows!D45>=1,OR(Flows!E45="",Flows!E45="once",Flows!E45="weekly",Flows!E45="biweekly"),OR(Flows!F45="",AND(ISNUMBER(Flows!F45),Flows!F45>=Flows!D45))),0,1))+IF(Flows!A46="",0,IF(AND(ISNUMBER(Flows!C46),Flows!C46>=0,ISNUMBER(Flows!D46),Flows!D46>=1,OR(Flows!E46="",Flows!E46="once",Flows!E46="weekly",Flows!E46="biweekly"),OR(Flows!F46="",AND(ISNUMBER(Flows!F46),Flows!F46>=Flows!D46))),0,1))+IF(Flows!A47="",0,IF(AND(ISNUMBER(Flows!C47),Flows!C47>=0,ISNUMBER(Flows!D47),Flows!D47>=1,OR(Flows!E47="",Flows!E47="once",Flows!E47="weekly",Flows!E47="biweekly"),OR(Flows!F47="",AND(ISNUMBER(Flows!F47),Flows!F47>=Flows!D47))),0,1))+IF(Flows!A48="",0,IF(AND(ISNUMBER(Flows!C48),Flows!C48>=0,ISNUMBER(Flows!D48),Flows!D48>=1,OR(Flows!E48="",Flows!E48="once",Flows!E48="weekly",Flows!E48="biweekly"),OR(Flows!F48="",AND(ISNUMBER(Flows!F48),Flows!F48>=Flows!D48))),0,1))+IF(Flows!A49="",0,IF(AND(ISNUMBER(Flows!C49),Flows!C49>=0,ISNUMBER(Flows!D49),Flows!D49>=1,OR(Flows!E49="",Flows!E49="once",Flows!E49="weekly",Flows!E49="biweekly"),OR(Flows!F49="",AND(ISNUMBER(Flows!F49),Flows!F49>=Flows!D49))),0,1))+IF(Flows!A50="",0,IF(AND(ISNUMBER(Flows!C50),Flows!C50>=0,ISNUMBER(Flows!D50),Flows!D50>=1,OR(Flows!E50="",Flows!E50="once",Flows!E50="weekly",Flows!E50="biweekly"),OR(Flows!F50="",AND(ISNUMBER(Flows!F50),Flows!F50>=Flows!D50))),0,1))+IF(Flows!A51="",0,IF(AND(ISNUMBER(Flows!C51),Flows!C51>=0,ISNUMBER(Flows!D51),Flows!D51>=1,OR(Flows!E51="",Flows!E51="once",Flows!E51="weekly",Flows!E51="biweekly"),OR(Flows!F51="",AND(ISNUMBER(Flows!F51),Flows!F51>=Flows!D51))),0,1))+IF(Flows!A52="",0,IF(AND(ISNUMBER(Flows!C52),Flows!C52>=0,ISNUMBER(Flows!D52),Flows!D52>=1,OR(Flows!E52="",Flows!E52="once",Flows!E52="weekly",Flows!E52="biweekly"),OR(Flows!F52="",AND(ISNUMBER(Flows!F52),Flows!F52>=Flows!D52))),0,1))+IF(Flows!A53="",0,IF(AND(ISNUMBER(Flows!C53),Flows!C53>=0,ISNUMBER(Flows!D53),Flows!D53>=1,OR(Flows!E53="",Flows!E53="once",Flows!E53="weekly",Flows!E53="biweekly"),OR(Flows!F53="",AND(ISNUMBER(Flows!F53),Flows!F53>=Flows!D53))),0,1))+IF(Flows!A54="",0,IF(AND(ISNUMBER(Flows!C54),Flows!C54>=0,ISNUMBER(Flows!D54),Flows!D54>=1,OR(Flows!E54="",Flows!E54="once",Flows!E54="weekly",Flows!E54="biweekly"),OR(Flows!F54="",AND(ISNUMBER(Flows!F54),Flows!F54>=Flows!D54))),0,1))+IF(Flows!A55="",0,IF(AND(ISNUMBER(Flows!C55),Flows!C55>=0,ISNUMBER(Flows!D55),Flows!D55>=1,OR(Flows!E55="",Flows!E55="once",Flows!E55="weekly",Flows!E55="biweekly"),OR(Flows!F55="",AND(ISNUMBER(Flows!F55),Flows!F55>=Flows!D55))),0,1))+IF(Flows!A56="",0,IF(AND(ISNUMBER(Flows!C56),Flows!C56>=0,ISNUMBER(Flows!D56),Flows!D56>=1,OR(Flows!E56="",Flows!E56="once",Flows!E56="weekly",Flows!E56="biweekly"),OR(Flows!F56="",AND(ISNUMBER(Flows!F56),Flows!F56>=Flows!D56))),0,1))+IF(Flows!A57="",0,IF(AND(ISNUMBER(Flows!C57),Flows!C57>=0,ISNUMBER(Flows!D57),Flows!D57>=1,OR(Flows!E57="",Flows!E57="once",Flows!E57="weekly",Flows!E57="biweekly"),OR(Flows!F57="",AND(ISNUMBER(Flows!F57),Flows!F57>=Flows!D57))),0,1))+IF(Flows!A58="",0,IF(AND(ISNUMBER(Flows!C58),Flows!C58>=0,ISNUMBER(Flows!D58),Flows!D58>=1,OR(Flows!E58="",Flows!E58="once",Flows!E58="weekly",Flows!E58="biweekly"),OR(Flows!F58="",AND(ISNUMBER(Flows!F58),Flows!F58>=Flows!D58))),0,1))+IF(Flows!A59="",0,IF(AND(ISNUMBER(Flows!C59),Flows!C59>=0,ISNUMBER(Flows!D59),Flows!D59>=1,OR(Flows!E59="",Flows!E59="once",Flows!E59="weekly",Flows!E59="biweekly"),OR(Flows!F59="",AND(ISNUMBER(Flows!F59),Flows!F59>=Flows!D59))),0,1))+IF(Flows!A60="",0,IF(AND(ISNUMBER(Flows!C60),Flows!C60>=0,ISNUMBER(Flows!D60),Flows!D60>=1,OR(Flows!E60="",Flows!E60="once",Flows!E60="weekly",Flows!E60="biweekly"),OR(Flows!F60="",AND(ISNUMBER(Flows!F60),Flows!F60>=Flows!D60))),0,1))+IF(Flows!A61="",0,IF(AND(ISNUMBER(Flows!C61),Flows!C61>=0,ISNUMBER(Flows!D61),Flows!D61>=1,OR(Flows!E61="",Flows!E61="once",Flows!E61="weekly",Flows!E61="biweekly"),OR(Flows!F61="",AND(ISNUMBER(Flows!F61),Flows!F61>=Flows!D61))),0,1))+IF(Flows!A62="",0,IF(AND(ISNUMBER(Flows!C62),Flows!C62>=0,ISNUMBER(Flows!D62),Flows!D62>=1,OR(Flows!E62="",Flows!E62="once",Flows!E62="weekly",Flows!E62="biweekly"),OR(Flows!F62="",AND(ISNUMBER(Flows!F62),Flows!F62>=Flows!D62))),0,1))+IF(Flows!A63="",0,IF(AND(ISNUMBER(Flows!C63),Flows!C63>=0,ISNUMBER(Flows!D63),Flows!D63>=1,OR(Flows!E63="",Flows!E63="once",Flows!E63="weekly",Flows!E63="biweekly"),OR(Flows!F63="",AND(ISNUMBER(Flows!F63),Flows!F63>=Flows!D63))),0,1))+IF(Flows!A64="",0,IF(AND(ISNUMBER(Flows!C64),Flows!C64>=0,ISNUMBER(Flows!D64),Flows!D64>=1,OR(Flows!E64="",Flows!E64="once",Flows!E64="weekly",Flows!E64="biweekly"),OR(Flows!F64="",AND(ISNUMBER(Flows!F64),Flows!F64>=Flows!D64))),0,1))+IF(Flows!A65="",0,IF(AND(ISNUMBER(Flows!C65),Flows!C65>=0,ISNUMBER(Flows!D65),Flows!D65>=1,OR(Flows!E65="",Flows!E65="once",Flows!E65="weekly",Flows!E65="biweekly"),OR(Flows!F65="",AND(ISNUMBER(Flows!F65),Flows!F65>=Flows!D65))),0,1))+IF(Flows!A66="",0,IF(AND(ISNUMBER(Flows!C66),Flows!C66>=0,ISNUMBER(Flows!D66),Flows!D66>=1,OR(Flows!E66="",Flows!E66="once",Flows!E66="weekly",Flows!E66="biweekly"),OR(Flows!F66="",AND(ISNUMBER(Flows!F66),Flows!F66>=Flows!D66))),0,1))+IF(Flows!A67="",0,IF(AND(ISNUMBER(Flows!C67),Flows!C67>=0,ISNUMBER(Flows!D67),Flows!D67>=1,OR(Flows!E67="",Flows!E67="once",Flows!E67="weekly",Flows!E67="biweekly"),OR(Flows!F67="",AND(ISNUMBER(Flows!F67),Flows!F67>=Flows!D67))),0,1))+IF(Flows!A68="",0,IF(AND(ISNUMBER(Flows!C68),Flows!C68>=0,ISNUMBER(Flows!D68),Flows!D68>=1,OR(Flows!E68="",Flows!E68="once",Flows!E68="weekly",Flows!E68="biweekly"),OR(Flows!F68="",AND(ISNUMBER(Flows!F68),Flows!F68>=Flows!D68))),0,1))+IF(Flows!A69="",0,IF(AND(ISNUMBER(Flows!C69),Flows!C69>=0,ISNUMBER(Flows!D69),Flows!D69>=1,OR(Flows!E69="",Flows!E69="once",Flows!E69="weekly",Flows!E69="biweekly"),OR(Flows!F69="",AND(ISNUMBER(Flows!F69),Flows!F69>=Flows!D69))),0,1))+IF(Flows!A70="",0,IF(AND(ISNUMBER(Flows!C70),Flows!C70>=0,ISNUMBER(Flows!D70),Flows!D70>=1,OR(Flows!E70="",Flows!E70="once",Flows!E70="weekly",Flows!E70="biweekly"),OR(Flows!F70="",AND(ISNUMBER(Flows!F70),Flows!F70>=Flows!D70))),0,1))+IF(Flows!A71="",0,IF(AND(ISNUMBER(Flows!C71),Flows!C71>=0,ISNUMBER(Flows!D71),Flows!D71>=1,OR(Flows!E71="",Flows!E71="once",Flows!E71="weekly",Flows!E71="biweekly"),OR(Flows!F71="",AND(ISNUMBER(Flows!F71),Flows!F71>=Flows!D71))),0,1))+IF(Flows!A72="",0,IF(AND(ISNUMBER(Flows!C72),Flows!C72>=0,ISNUMBER(Flows!D72),Flows!D72>=1,OR(Flows!E72="",Flows!E72="once",Flows!E72="weekly",Flows!E72="biweekly"),OR(Flows!F72="",AND(ISNUMBER(Flows!F72),Flows!F72>=Flows!D72))),0,1))+IF(Flows!A73="",0,IF(AND(ISNUMBER(Flows!C73),Flows!C73>=0,ISNUMBER(Flows!D73),Flows!D73>=1,OR(Flows!E73="",Flows!E73="once",Flows!E73="weekly",Flows!E73="biweekly"),OR(Flows!F73="",AND(ISNUMBER(Flows!F73),Flows!F73>=Flows!D73))),0,1))+IF(Flows!A74="",0,IF(AND(ISNUMBER(Flows!C74),Flows!C74>=0,ISNUMBER(Flows!D74),Flows!D74>=1,OR(Flows!E74="",Flows!E74="once",Flows!E74="weekly",Flows!E74="biweekly"),OR(Flows!F74="",AND(ISNUMBER(Flows!F74),Flows!F74>=Flows!D74))),0,1))+IF(Flows!A75="",0,IF(AND(ISNUMBER(Flows!C75),Flows!C75>=0,ISNUMBER(Flows!D75),Flows!D75>=1,OR(Flows!E75="",Flows!E75="once",Flows!E75="weekly",Flows!E75="biweekly"),OR(Flows!F75="",AND(ISNUMBER(Flows!F75),Flows!F75>=Flows!D75))),0,1))+IF(Flows!A76="",0,IF(AND(ISNUMBER(Flows!C76),Flows!C76>=0,ISNUMBER(Flows!D76),Flows!D76>=1,OR(Flows!E76="",Flows!E76="once",Flows!E76="weekly",Flows!E76="biweekly"),OR(Flows!F76="",AND(ISNUMBER(Flows!F76),Flows!F76>=Flows!D76))),0,1))+IF(Flows!A77="",0,IF(AND(ISNUMBER(Flows!C77),Flows!C77>=0,ISNUMBER(Flows!D77),Flows!D77>=1,OR(Flows!E77="",Flows!E77="once",Flows!E77="weekly",Flows!E77="biweekly"),OR(Flows!F77="",AND(ISNUMBER(Flows!F77),Flows!F77>=Flows!D77))),0,1))+IF(Flows!A78="",0,IF(AND(ISNUMBER(Flows!C78),Flows!C78>=0,ISNUMBER(Flows!D78),Flows!D78>=1,OR(Flows!E78="",Flows!E78="once",Flows!E78="weekly",Flows!E78="biweekly"),OR(Flows!F78="",AND(ISNUMBER(Flows!F78),Flows!F78>=Flows!D78))),0,1))+IF(Flows!A79="",0,IF(AND(ISNUMBER(Flows!C79),Flows!C79>=0,ISNUMBER(Flows!D79),Flows!D79>=1,OR(Flows!E79="",Flows!E79="once",Flows!E79="weekly",Flows!E79="biweekly"),OR(Flows!F79="",AND(ISNUMBER(Flows!F79),Flows!F79>=Flows!D79))),0,1))+IF(Flows!A80="",0,IF(AND(ISNUMBER(Flows!C80),Flows!C80>=0,ISNUMBER(Flows!D80),Flows!D80>=1,OR(Flows!E80="",Flows!E80="once",Flows!E80="weekly",Flows!E80="biweekly"),OR(Flows!F80="",AND(ISNUMBER(Flows!F80),Flows!F80>=Flows!D80))),0,1))+IF(Flows!A81="",0,IF(AND(ISNUMBER(Flows!C81),Flows!C81>=0,ISNUMBER(Flows!D81),Flows!D81>=1,OR(Flows!E81="",Flows!E81="once",Flows!E81="weekly",Flows!E81="biweekly"),OR(Flows!F81="",AND(ISNUMBER(Flows!F81),Flows!F81>=Flows!D81))),0,1))+IF(Flows!A82="",0,IF(AND(ISNUMBER(Flows!C82),Flows!C82>=0,ISNUMBER(Flows!D82),Flows!D82>=1,OR(Flows!E82="",Flows!E82="once",Flows!E82="weekly",Flows!E82="biweekly"),OR(Flows!F82="",AND(ISNUMBER(Flows!F82),Flows!F82>=Flows!D82))),0,1))+IF(Flows!A83="",0,IF(AND(ISNUMBER(Flows!C83),Flows!C83>=0,ISNUMBER(Flows!D83),Flows!D83>=1,OR(Flows!E83="",Flows!E83="once",Flows!E83="weekly",Flows!E83="biweekly"),OR(Flows!F83="",AND(ISNUMBER(Flows!F83),Flows!F83>=Flows!D83))),0,1))+IF(Flows!A84="",0,IF(AND(ISNUMBER(Flows!C84),Flows!C84>=0,ISNUMBER(Flows!D84),Flows!D84>=1,OR(Flows!E84="",Flows!E84="once",Flows!E84="weekly",Flows!E84="biweekly"),OR(Flows!F84="",AND(ISNUMBER(Flows!F84),Flows!F84>=Flows!D84))),0,1)))&" bad rows"
A9: 5 | B9: ending cash roll-forward = opening + sum(net) | C9: =IF(ABS(Runway!B8-(Setup!$B$4+SUMPRODUCT(Weekly!E5:E56*Weekly!G5:G56)))<0.005,"PASS","FAIL")
A10: 6 | B10: receipts + disbursements in grid = weekly totals | C10: =IF(ABS(SUM(Weekly!C5:D56)-SUM(Grid!F4:BE83))<0.005,"PASS","FAIL")
A11: 7 | B11: GOLDEN parity with original openfpa: min_cash = -146000 | C11: =IF(ABS(Runway!$B$4-(-146000))<0.005,"PASS","FAIL") | D11: =Runway!$B$4
A12: 8 | B12: GOLDEN parity with original openfpa: min_week = 7 | C12: =IF(ABS(Runway!$B$5-(7))<0.005,"PASS","FAIL") | D12: =Runway!$B$5
A13: 9 | B13: GOLDEN parity with original openfpa: first_negative_week = 3 | C13: =IF(ABS(Runway!$B$6-(3))<0.005,"PASS","FAIL") | D13: =Runway!$B$6

Sheet Setup
A1: Setup
A4: opening_cash | B4: 150000
A5: weeks (1-52) | B5: 13
A6: week 1 start date (Monday recommended) | B6: 46027
A7: credit-line buffer over trough | B7: 0.15
A8: currency symbol | B8: ₹

Sheet Flows
A1: Flows (one row per scheduled flow; amount is a positive magnitude)
A4: direction (receipt/disbursement) | B4: name | C4: amount | D4: start_week | E4: recurrence (once/weekly/biweekly) | F4: end_week (optional) | G4: category (optional) | H4: source / evidence
A5: receipt | B5: D2C daily sales | C5: 38000 | D5: 1 | E5: weekly
A6: receipt | B6: Amazon payout | C6: 95000 | D6: 2 | E6: biweekly
A7: receipt | B7: Wholesale AR collection | C7: 120000 | D7: 4 | E7: once
A8: receipt | B8: Wholesale AR collection | C8: 120000 | D8: 9 | E8: once
A9: disbursement | B9: Payroll | C9: 55000 | D9: 1 | E9: biweekly
A10: disbursement | B10: Inventory PO deposit | C10: 220000 | D10: 3 | E10: once
A11: disbursement | B11: Inventory PO balance | C11: 240000 | D11: 6 | E11: once
A12: disbursement | B12: Operating overhead | C12: 23000 | D12: 1 | E12: weekly
A13: disbursement | B13: Marketing | C13: 18000 | D13: 1 | E13: weekly
A14: disbursement | B14: Quarterly tax estimate | C14: 60000 | D14: 11 | E14: once

Sheet Grid
A1: Grid - expand_flow: amount landing in each week per flow (formulas)
A3: direction | B3: name | C3: start | D3: end (resolved) | E3: recurrence | F3: 1 | G3: 2 | H3: 3 | I3: 4 | J3: 5 | K3: 6 | L3: 7 | M3: 8 | N3: 9 | O3: 10 | P3: 11 | Q3: 12 | R3: 13 | S3: 14 | T3: 15 | U3: 16 | V3: 17 | W3: 18 | X3: 19 | Y3: 20 | Z3: 21 | AA3: 22 | AB3: 23 | AC3: 24 | AD3: 25 | AE3: 26 | AF3: 27 | AG3: 28 | AH3: 29 | AI3: 30 | AJ3: 31 | AK3: 32 | AL3: 33 | AM3: 34 | AN3: 35 | AO3: 36 | AP3: 37 | AQ3: 38 | AR3: 39 | AS3: 40 | AT3: 41 | AU3: 42 | AV3: 43 | AW3: 44 | AX3: 45 | AY3: 46 | AZ3: 47 | BA3: 48 | BB3: 49 | BC3: 50 | BD3: 51 | BE3: 52
A4: =IF(Flows!A5="","",LOWER(Flows!A5)) | B4: =IF(Flows!B5="","",Flows!B5) | C4: =N(Flows!D5) | D4: =IF(Flows!F5="",Setup!$B$5,Flows!F5) | E4: =IF(Flows!E5="","once",LOWER(Flows!E5)) | F4: =IF(OR($A4="",Flows!$C5=""),0,IF(AND(1<=Setup!$B$5,1>=$C4,OR(AND($E4="once",1=$C4),AND($E4="weekly",1<=$D4),AND($E4="biweekly",1<=$D4,MOD(1-$C4,2)=0))),Flows!$C5,0)) | G4: =IF(OR($A4="",Flows!$C5=""),0,IF(AND(2<=Setup!$B$5,2>=$C4,OR(AND($E4="once",2=$C4),AND($E4="weekly",2<=$D4),AND($E4="biweekly",2<=$D4,MOD(2-$C4,2)=0))),Flows!$C5,0)) | H4: =IF(OR($A4="",Flows!$C5=""),0,IF(AND(3<=Setup!$B$5,3>=$C4,OR(AND($E4="once",3=$C4),AND($E4="weekly",3<=$D4),AND($E4="biweekly",3<=$D4,MOD(3-$C4,2)=0))),Flows!$C5,0)) | I4: =IF(OR($A4="",Flows!$C5=""),0,IF(AND(4<=Setup!$B$5,4>=$C4,OR(AND($E4="once",4=$C4),AND($E4="weekly",4<=$D4),AND($E4="biweekly",4<=$D4,MOD(4-$C4,2)=0))),Flows!$C5,0)) | J4: =IF(OR($A4="",Flows!$C5=""),0,IF(AND(5<=Setup!$B$5,5>=$C4,OR(AND($E4="once",5=$C4),AND($E4="weekly",5<=$D4),AND($E4="biweekly",5<=$D4,MOD(5-$C4,2)=0))),Flows!$C5,0)) | K4: =IF(OR($A4="",Flows!$C5=""),0,IF(AND(6<=Setup!$B$5,6>=$C4,OR(AND($E4="once",6=$C4),AND($E4="weekly",6<=$D4),AND($E4="biweekly",6<=$D4,MOD(6-$C4,2)=0))),Flows!$C5,0)) | L4: =IF(OR($A4="",Flows!$C5=""),0,IF(AND(7<=Setup!$B$5,7>=$C4,OR(AND($E4="once",7=$C4),AND($E4="weekly",7<=$D4),AND($E4="biweekly",7<=$D4,MOD(7-$C4,2)=0))),Flows!$C5,0)) | M4: =IF(OR($A4="",Flows!$C5=""),0,IF(AND(8<=Setup!$B$5,8>=$C4,OR(AND($E4="once",8=$C4),AND($E4="weekly",8<=$D4),AND($E4="biweekly",8<=$D4,MOD(8-$C4,2)=0))),Flows!$C5,0)) | N4: =IF(OR($A4="",Flows!$C5=""),0,IF(AND(9<=Setup!$B$5,9>=$C4,OR(AND($E4="once",9=$C4),AND($E4="weekly",9<=$D4),AND($E4="biweekly",9<=$D4,MOD(9-$C4,2)=0))),Flows!$C5,0)) | O4: =IF(OR($A4="",Flows!$C5=""),0,IF(AND(10<=Setup!$B$5,10>=$C4,OR(AND($E4="once",10=$C4),AND($E4="weekly",10<=$D4),AND($E4="biweekly",10<=$D4,MOD(10-$C4,2)=0))),Flows!$C5,0)) | P4: =IF(OR($A4="",Flows!$C5=""),0,IF(AND(11<=Setup!$B$5,11>=$C4,OR(AND($E4="once",11=$C4),AND($E4="weekly",11<=$D4),AND($E4="biweekly",11<=$D4,MOD(11-$C4,2)=0))),Flows!$C5,0)) | Q4: =IF(OR($A4="",Flows!$C5=""),0,IF(AND(12<=Setup!$B$5,12>=$C4,OR(AND($E4="once",12=$C4),AND($E4="weekly",12<=$D4),AND($E4="biweekly",12<=$D4,MOD(12-$C4,2)=0))),Flows!$C5,0)) | R4: =IF(OR($A4="",Flows!$C5=""),0,IF(AND(13<=Setup!$B$5,13>=$C4,OR(AND($E4="once",13=$C4),AND($E4="weekly",13<=$D4),AND($E4="biweekly",13<=$D4,MOD(13-$C4,2)=0))),Flows!$C5,0)) | S4: =IF(OR($A4="",Flows!$C5=""),0,IF(AND(14<=Setup!$B$5,14>=$C4,OR(AND($E4="once",14=$C4),AND($E4="weekly",14<=$D4),AND($E4="biweekly",14<=$D4,MOD(14-$C4,2)=0))),Flows!$C5,0)) | T4: =IF(OR($A4="",Flows!$C5=""),0,IF(AND(15<=Setup!$B$5,15>=$C4,OR(AND($E4="once",15=$C4),AND($E4="weekly",15<=$D4),AND($E4="biweekly",15<=$D4,MOD(15-$C4,2)=0))),Flows!$C5,0)) | U4: =IF(OR($A4="",Flows!$C5=""),0,IF(AND(16<=Setup!$B$5,16>=$C4,OR(AND($E4="once",16=$C4),AND($E4="weekly",16<=$D4),AND($E4="biweekly",16<=$D4,MOD(16-$C4,2)=0))),Flows!$C5,0)) | V4: =IF(OR($A4="",Flows!$C5=""),0,IF(AND(17<=Setup!$B$5,17>=$C4,OR(AND($E4="once",17=$C4),AND($E4="weekly",17<=$D4),AND($E4="biweekly",17<=$D4,MOD(17-$C4,2)=0))),Flows!$C5,0)) | W4: =IF(OR($A4="",Flows!$C5=""),0,IF(AND(18<=Setup!$B$5,18>=$C4,OR(AND($E4="once",18=$C4),AND($E4="weekly",18<=$D4),AND($E4="biweekly",18<=$D4,MOD(18-$C4,2)=0))),Flows!$C5,0)) | X4: =IF(OR($A4="",Flows!$C5=""),0,IF(AND(19<=Setup!$B$5,19>=$C4,OR(AND($E4="once",19=$C4),AND($E4="weekly",19<=$D4),AND($E4="biweekly",19<=$D4,MOD(19-$C4,2)=0))),Flows!$C5,0)) | Y4: =IF(OR($A4="",Flows!$C5=""),0,IF(AND(20<=Setup!$B$5,20>=$C4,OR(AND($E4="once",20=$C4),AND($E4="weekly",20<=$D4),AND($E4="biweekly",20<=$D4,MOD(20-$C4,2)=0))),Flows!$C5,0)) | Z4: =IF(OR($A4="",Flows!$C5=""),0,IF(AND(21<=Setup!$B$5,21>=$C4,OR(AND($E4="once",21=$C4),AND($E4="weekly",21<=$D4),AND($E4="biweekly",21<=$D4,MOD(21-$C4,2)=0))),Flows!$C5,0)) | AA4: =IF(OR($A4="",Flows!$C5=""),0,IF(AND(22<=Setup!$B$5,22>=$C4,OR(AND($E4="once",22=$C4),AND($E4="weekly",22<=$D4),AND($E4="biweekly",22<=$D4,MOD(22-$C4,2)=0))),Flows!$C5,0)) | AB4: =IF(OR($A4="",Flows!$C5=""),0,IF(AND(23<=Setup!$B$5,23>=$C4,OR(AND($E4="once",23=$C4),AND($E4="weekly",23<=$D4),AND($E4="biweekly",23<=$D4,MOD(23-$C4,2)=0))),Flows!$C5,0)) | AC4: =IF(OR($A4="",Flows!$C5=""),0,IF(AND(24<=Setup!$B$5,24>=$C4,OR(AND($E4="once",24=$C4),AND($E4="weekly",24<=$D4),AND($E4="biweekly",24<=$D4,MOD(24-$C4,2)=0))),Flows!$C5,0)) | AD4: =IF(OR($A4="",Flows!$C5=""),0,IF(AND(25<=Setup!$B$5,25>=$C4,OR(AND($E4="once",25=$C4),AND($E4="weekly",25<=$D4),AND($E4="biweekly",25<=$D4,MOD(25-$C4,2)=0))),Flows!$C5,0)) | AE4: =IF(OR($A4="",Flows!$C5=""),0,IF(AND(26<=Setup!$B$5,26>=$C4,OR(AND($E4="once",26=$C4),AND($E4="weekly",26<=$D4),AND($E4="biweekly",26<=$D4,MOD(26-$C4,2)=0))),Flows!$C5,0)) | AF4: =IF(OR($A4="",Flows!$C5=""),0,IF(AND(27<=Setup!$B$5,27>=$C4,OR(AND($E4="once",27=$C4),AND($E4="weekly",27<=$D4),AND($E4="biweekly",27<=$D4,MOD(27-$C4,2)=0))),Flows!$C5,0)) | AG4: =IF(OR($A4="",Flows!$C5=""),0,IF(AND(28<=Setup!$B$5,28>=$C4,OR(AND($E4="once",28=$C4),AND($E4="weekly",28<=$D4),AND($E4="biweekly",28<=$D4,MOD(28-$C4,2)=0))),Flows!$C5,0)) | AH4: =IF(OR($A4="",Flows!$C5=""),0,IF(AND(29<=Setup!$B$5,29>=$C4,OR(AND($E4="once",29=$C4),AND($E4="weekly",29<=$D4),AND($E4="biweekly",29<=$D4,MOD(29-$C4,2)=0))),Flows!$C5,0)) | AI4: =IF(OR($A4="",Flows!$C5=""),0,IF(AND(30<=Setup!$B$5,30>=$C4,OR(AND($E4="once",30=$C4),AND($E4="weekly",30<=$D4),AND($E4="biweekly",30<=$D4,MOD(30-$C4,2)=0))),Flows!$C5,0)) | AJ4: =IF(OR($A4="",Flows!$C5=""),0,IF(AND(31<=Setup!$B$5,31>=$C4,OR(AND($E4="once",31=$C4),AND($E4="weekly",31<=$D4),AND($E4="biweekly",31<=$D4,MOD(31-$C4,2)=0))),Flows!$C5,0)) | AK4: =IF(OR($A4="",Flows!$C5=""),0,IF(AND(32<=Setup!$B$5,32>=$C4,OR(AND($E4="once",32=$C4),AND($E4="weekly",32<=$D4),AND($E4="biweekly",32<=$D4,MOD(32-$C4,2)=0))),Flows!$C5,0)) | AL4: =IF(OR($A4="",Flows!$C5=""),0,IF(AND(33<=Setup!$B$5,33>=$C4,OR(AND($E4="once",33=$C4),AND($E4="weekly",33<=$D4),AND($E4="biweekly",33<=$D4,MOD(33-$C4,2)=0))),Flows!$C5,0)) | AM4: =IF(OR($A4="",Flows!$C5=""),0,IF(AND(34<=Setup!$B$5,34>=$C4,OR(AND($E4="once",34=$C4),AND($E4="weekly",34<=$D4),AND($E4="biweekly",34<=$D4,MOD(34-$C4,2)=0))),Flows!$C5,0)) | AN4: =IF(OR($A4="",Flows!$C5=""),0,IF(AND(35<=Setup!$B$5,35>=$C4,OR(AND($E4="once",35=$C4),AND($E4="weekly",35<=$D4),AND($E4="biweekly",35<=$D4,MOD(35-$C4,2)=0))),Flows!$C5,0)) | AO4: =IF(OR($A4="",Flows!$C5=""),0,IF(AND(36<=Setup!$B$5,36>=$C4,OR(AND($E4="once",36=$C4),AND($E4="weekly",36<=$D4),AND($E4="biweekly",36<=$D4,MOD(36-$C4,2)=0))),Flows!$C5,0)) | AP4: =IF(OR($A4="",Flows!$C5=""),0,IF(AND(37<=Setup!$B$5,37>=$C4,OR(AND($E4="once",37=$C4),AND($E4="weekly",37<=$D4),AND($E4="biweekly",37<=$D4,MOD(37-$C4,2)=0))),Flows!$C5,0)) | AQ4: =IF(OR($A4="",Flows!$C5=""),0,IF(AND(38<=Setup!$B$5,38>=$C4,OR(AND($E4="once",38=$C4),AND($E4="weekly",38<=$D4),AND($E4="biweekly",38<=$D4,MOD(38-$C4,2)=0))),Flows!$C5,0)) | AR4: =IF(OR($A4="",Flows!$C5=""),0,IF(AND(39<=Setup!$B$5,39>=$C4,OR(AND($E4="once",39=$C4),AND($E4="weekly",39<=$D4),AND($E4="biweekly",39<=$D4,MOD(39-$C4,2)=0))),Flows!$C5,0)) | AS4: =IF(OR($A4="",Flows!$C5=""),0,IF(AND(40<=Setup!$B$5,40>=$C4,OR(AND($E4="once",40=$C4),AND($E4="weekly",40<=$D4),AND($E4="biweekly",40<=$D4,MOD(40-$C4,2)=0))),Flows!$C5,0)) | AT4: =IF(OR($A4="",Flows!$C5=""),0,IF(AND(41<=Setup!$B$5,41>=$C4,OR(AND($E4="once",41=$C4),AND($E4="weekly",41<=$D4),AND($E4="biweekly",41<=$D4,MOD(41-$C4,2)=0))),Flows!$C5,0)) | AU4: =IF(OR($A4="",Flows!$C5=""),0,IF(AND(42<=Setup!$B$5,42>=$C4,OR(AND($E4="once",42=$C4),AND($E4="weekly",42<=$D4),AND($E4="biweekly",42<=$D4,MOD(42-$C4,2)=0))),Flows!$C5,0)) | AV4: =IF(OR($A4="",Flows!$C5=""),0,IF(AND(43<=Setup!$B$5,43>=$C4,OR(AND($E4="once",43=$C4),AND($E4="weekly",43<=$D4),AND($E4="biweekly",43<=$D4,MOD(43-$C4,2)=0))),Flows!$C5,0)) | AW4: =IF(OR($A4="",Flows!$C5=""),0,IF(AND(44<=Setup!$B$5,44>=$C4,OR(AND($E4="once",44=$C4),AND($E4="weekly",44<=$D4),AND($E4="biweekly",44<=$D4,MOD(44-$C4,2)=0))),Flows!$C5,0)) | AX4: =IF(OR($A4="",Flows!$C5=""),0,IF(AND(45<=Setup!$B$5,45>=$C4,OR(AND($E4="once",45=$C4),AND($E4="weekly",45<=$D4),AND($E4="biweekly",45<=$D4,MOD(45-$C4,2)=0))),Flows!$C5,0)) | AY4: =IF(OR($A4="",Flows!$C5=""),0,IF(AND(46<=Setup!$B$5,46>=$C4,OR(AND($E4="once",46=$C4),AND($E4="weekly",46<=$D4),AND($E4="biweekly",46<=$D4,MOD(46-$C4,2)=0))),Flows!$C5,0)) | AZ4: =IF(OR($A4="",Flows!$C5=""),0,IF(AND(47<=Setup!$B$5,47>=$C4,OR(AND($E4="once",47=$C4),AND($E4="weekly",47<=$D4),AND($E4="biweekly",47<=$D4,MOD(47-$C4,2)=0))),Flows!$C5,0)) | BA4: =IF(OR($A4="",Flows!$C5=""),0,IF(AND(48<=Setup!$B$5,48>=$C4,OR(AND($E4="once",48=$C4),AND($E4="weekly",48<=$D4),AND($E4="biweekly",48<=$D4,MOD(48-$C4,2)=0))),Flows!$C5,0)) | BB4: =IF(OR($A4="",Flows!$C5=""),0,IF(AND(49<=Setup!$B$5,49>=$C4,OR(AND($E4="once",49=$C4),AND($E4="weekly",49<=$D4),AND($E4="biweekly",49<=$D4,MOD(49-$C4,2)=0))),Flows!$C5,0)) | BC4: =IF(OR($A4="",Flows!$C5=""),0,IF(AND(50<=Setup!$B$5,50>=$C4,OR(AND($E4="once",50=$C4),AND($E4="weekly",50<=$D4),AND($E4="biweekly",50<=$D4,MOD(50-$C4,2)=0))),Flows!$C5,0)) | BD4: =IF(OR($A4="",Flows!$C5=""),0,IF(AND(51<=Setup!$B$5,51>=$C4,OR(AND($E4="once",51=$C4),AND($E4="weekly",51<=$D4),AND($E4="biweekly",51<=$D4,MOD(51-$C4,2)=0))),Flows!$C5,0)) | BE4: =IF(OR($A4="",Flows!$C5=""),0,IF(AND(52<=Setup!$B$5,52>=$C4,OR(AND($E4="once",52=$C4),AND($E4="weekly",52<=$D4),AND($E4="biweekly",52<=$D4,MOD(52-$C4,2)=0))),Flows!$C5,0))
A5: =IF(Flows!A6="","",LOWER(Flows!A6)) | B5: =IF(Flows!B6="","",Flows!B6) | C5: =N(Flows!D6) | D5: =IF(Flows!F6="",Setup!$B$5,Flows!F6) | E5: =IF(Flows!E6="","once",LOWER(Flows!E6)) | F5: =IF(OR($A5="",Flows!$C6=""),0,IF(AND(1<=Setup!$B$5,1>=$C5,OR(AND($E5="once",1=$C5),AND($E5="weekly",1<=$D5),AND($E5="biweekly",1<=$D5,MOD(1-$C5,2)=0))),Flows!$C6,0)) | G5: =IF(OR($A5="",Flows!$C6=""),0,IF(AND(2<=Setup!$B$5,2>=$C5,OR(AND($E5="once",2=$C5),AND($E5="weekly",2<=$D5),AND($E5="biweekly",2<=$D5,MOD(2-$C5,2)=0))),Flows!$C6,0)) | H5: =IF(OR($A5="",Flows!$C6=""),0,IF(AND(3<=Setup!$B$5,3>=$C5,OR(AND($E5="once",3=$C5),AND($E5="weekly",3<=$D5),AND($E5="biweekly",3<=$D5,MOD(3-$C5,2)=0))),Flows!$C6,0)) | I5: =IF(OR($A5="",Flows!$C6=""),0,IF(AND(4<=Setup!$B$5,4>=$C5,OR(AND($E5="once",4=$C5),AND($E5="weekly",4<=$D5),AND($E5="biweekly",4<=$D5,MOD(4-$C5,2)=0))),Flows!$C6,0)) | J5: =IF(OR($A5="",Flows!$C6=""),0,IF(AND(5<=Setup!$B$5,5>=$C5,OR(AND($E5="once",5=$C5),AND($E5="weekly",5<=$D5),AND($E5="biweekly",5<=$D5,MOD(5-$C5,2)=0))),Flows!$C6,0)) | K5: =IF(OR($A5="",Flows!$C6=""),0,IF(AND(6<=Setup!$B$5,6>=$C5,OR(AND($E5="once",6=$C5),AND($E5="weekly",6<=$D5),AND($E5="biweekly",6<=$D5,MOD(6-$C5,2)=0))),Flows!$C6,0)) | L5: =IF(OR($A5="",Flows!$C6=""),0,IF(AND(7<=Setup!$B$5,7>=$C5,OR(AND($E5="once",7=$C5),AND($E5="weekly",7<=$D5),AND($E5="biweekly",7<=$D5,MOD(7-$C5,2)=0))),Flows!$C6,0)) | M5: =IF(OR($A5="",Flows!$C6=""),0,IF(AND(8<=Setup!$B$5,8>=$C5,OR(AND($E5="once",8=$C5),AND($E5="weekly",8<=$D5),AND($E5="biweekly",8<=$D5,MOD(8-$C5,2)=0))),Flows!$C6,0)) | N5: =IF(OR($A5="",Flows!$C6=""),0,IF(AND(9<=Setup!$B$5,9>=$C5,OR(AND($E5="once",9=$C5),AND($E5="weekly",9<=$D5),AND($E5="biweekly",9<=$D5,MOD(9-$C5,2)=0))),Flows!$C6,0)) | O5: =IF(OR($A5="",Flows!$C6=""),0,IF(AND(10<=Setup!$B$5,10>=$C5,OR(AND($E5="once",10=$C5),AND($E5="weekly",10<=$D5),AND($E5="biweekly",10<=$D5,MOD(10-$C5,2)=0))),Flows!$C6,0)) | P5: =IF(OR($A5="",Flows!$C6=""),0,IF(AND(11<=Setup!$B$5,11>=$C5,OR(AND($E5="once",11=$C5),AND($E5="weekly",11<=$D5),AND($E5="biweekly",11<=$D5,MOD(11-$C5,2)=0))),Flows!$C6,0)) | Q5: =IF(OR($A5="",Flows!$C6=""),0,IF(AND(12<=Setup!$B$5,12>=$C5,OR(AND($E5="once",12=$C5),AND($E5="weekly",12<=$D5),AND($E5="biweekly",12<=$D5,MOD(12-$C5,2)=0))),Flows!$C6,0)) | R5: =IF(OR($A5="",Flows!$C6=""),0,IF(AND(13<=Setup!$B$5,13>=$C5,OR(AND($E5="once",13=$C5),AND($E5="weekly",13<=$D5),AND($E5="biweekly",13<=$D5,MOD(13-$C5,2)=0))),Flows!$C6,0)) | S5: =IF(OR($A5="",Flows!$C6=""),0,IF(AND(14<=Setup!$B$5,14>=$C5,OR(AND($E5="once",14=$C5),AND($E5="weekly",14<=$D5),AND($E5="biweekly",14<=$D5,MOD(14-$C5,2)=0))),Flows!$C6,0)) | T5: =IF(OR($A5="",Flows!$C6=""),0,IF(AND(15<=Setup!$B$5,15>=$C5,OR(AND($E5="once",15=$C5),AND($E5="weekly",15<=$D5),AND($E5="biweekly",15<=$D5,MOD(15-$C5,2)=0))),Flows!$C6,0)) | U5: =IF(OR($A5="",Flows!$C6=""),0,IF(AND(16<=Setup!$B$5,16>=$C5,OR(AND($E5="once",16=$C5),AND($E5="weekly",16<=$D5),AND($E5="biweekly",16<=$D5,MOD(16-$C5,2)=0))),Flows!$C6,0)) | V5: =IF(OR($A5="",Flows!$C6=""),0,IF(AND(17<=Setup!$B$5,17>=$C5,OR(AND($E5="once",17=$C5),AND($E5="weekly",17<=$D5),AND($E5="biweekly",17<=$D5,MOD(17-$C5,2)=0))),Flows!$C6,0)) | W5: =IF(OR($A5="",Flows!$C6=""),0,IF(AND(18<=Setup!$B$5,18>=$C5,OR(AND($E5="once",18=$C5),AND($E5="weekly",18<=$D5),AND($E5="biweekly",18<=$D5,MOD(18-$C5,2)=0))),Flows!$C6,0)) | X5: =IF(OR($A5="",Flows!$C6=""),0,IF(AND(19<=Setup!$B$5,19>=$C5,OR(AND($E5="once",19=$C5),AND($E5="weekly",19<=$D5),AND($E5="biweekly",19<=$D5,MOD(19-$C5,2)=0))),Flows!$C6,0)) | Y5: =IF(OR($A5="",Flows!$C6=""),0,IF(AND(20<=Setup!$B$5,20>=$C5,OR(AND($E5="once",20=$C5),AND($E5="weekly",20<=$D5),AND($E5="biweekly",20<=$D5,MOD(20-$C5,2)=0))),Flows!$C6,0)) | Z5: =IF(OR($A5="",Flows!$C6=""),0,IF(AND(21<=Setup!$B$5,21>=$C5,OR(AND($E5="once",21=$C5),AND($E5="weekly",21<=$D5),AND($E5="biweekly",21<=$D5,MOD(21-$C5,2)=0))),Flows!$C6,0)) | AA5: =IF(OR($A5="",Flows!$C6=""),0,IF(AND(22<=Setup!$B$5,22>=$C5,OR(AND($E5="once",22=$C5),AND($E5="weekly",22<=$D5),AND($E5="biweekly",22<=$D5,MOD(22-$C5,2)=0))),Flows!$C6,0)) | AB5: =IF(OR($A5="",Flows!$C6=""),0,IF(AND(23<=Setup!$B$5,23>=$C5,OR(AND($E5="once",23=$C5),AND($E5="weekly",23<=$D5),AND($E5="biweekly",23<=$D5,MOD(23-$C5,2)=0))),Flows!$C6,0)) | AC5: =IF(OR($A5="",Flows!$C6=""),0,IF(AND(24<=Setup!$B$5,24>=$C5,OR(AND($E5="once",24=$C5),AND($E5="weekly",24<=$D5),AND($E5="biweekly",24<=$D5,MOD(24-$C5,2)=0))),Flows!$C6,0)) | AD5: =IF(OR($A5="",Flows!$C6=""),0,IF(AND(25<=Setup!$B$5,25>=$C5,OR(AND($E5="once",25=$C5),AND($E5="weekly",25<=$D5),AND($E5="biweekly",25<=$D5,MOD(25-$C5,2)=0))),Flows!$C6,0)) | AE5: =IF(OR($A5="",Flows!$C6=""),0,IF(AND(26<=Setup!$B$5,26>=$C5,OR(AND($E5="once",26=$C5),AND($E5="weekly",26<=$D5),AND($E5="biweekly",26<=$D5,MOD(26-$C5,2)=0))),Flows!$C6,0)) | AF5: =IF(OR($A5="",Flows!$C6=""),0,IF(AND(27<=Setup!$B$5,27>=$C5,OR(AND($E5="once",27=$C5),AND($E5="weekly",27<=$D5),AND($E5="biweekly",27<=$D5,MOD(27-$C5,2)=0))),Flows!$C6,0)) | AG5: =IF(OR($A5="",Flows!$C6=""),0,IF(AND(28<=Setup!$B$5,28>=$C5,OR(AND($E5="once",28=$C5),AND($E5="weekly",28<=$D5),AND($E5="biweekly",28<=$D5,MOD(28-$C5,2)=0))),Flows!$C6,0)) | AH5: =IF(OR($A5="",Flows!$C6=""),0,IF(AND(29<=Setup!$B$5,29>=$C5,OR(AND($E5="once",29=$C5),AND($E5="weekly",29<=$D5),AND($E5="biweekly",29<=$D5,MOD(29-$C5,2)=0))),Flows!$C6,0)) | AI5: =IF(OR($A5="",Flows!$C6=""),0,IF(AND(30<=Setup!$B$5,30>=$C5,OR(AND($E5="once",30=$C5),AND($E5="weekly",30<=$D5),AND($E5="biweekly",30<=$D5,MOD(30-$C5,2)=0))),Flows!$C6,0)) | AJ5: =IF(OR($A5="",Flows!$C6=""),0,IF(AND(31<=Setup!$B$5,31>=$C5,OR(AND($E5="once",31=$C5),AND($E5="weekly",31<=$D5),AND($E5="biweekly",31<=$D5,MOD(31-$C5,2)=0))),Flows!$C6,0)) | AK5: =IF(OR($A5="",Flows!$C6=""),0,IF(AND(32<=Setup!$B$5,32>=$C5,OR(AND($E5="once",32=$C5),AND($E5="weekly",32<=$D5),AND($E5="biweekly",32<=$D5,MOD(32-$C5,2)=0))),Flows!$C6,0)) | AL5: =IF(OR($A5="",Flows!$C6=""),0,IF(AND(33<=Setup!$B$5,33>=$C5,OR(AND($E5="once",33=$C5),AND($E5="weekly",33<=$D5),AND($E5="biweekly",33<=$D5,MOD(33-$C5,2)=0))),Flows!$C6,0)) | AM5: =IF(OR($A5="",Flows!$C6=""),0,IF(AND(34<=Setup!$B$5,34>=$C5,OR(AND($E5="once",34=$C5),AND($E5="weekly",34<=$D5),AND($E5="biweekly",34<=$D5,MOD(34-$C5,2)=0))),Flows!$C6,0)) | AN5: =IF(OR($A5="",Flows!$C6=""),0,IF(AND(35<=Setup!$B$5,35>=$C5,OR(AND($E5="once",35=$C5),AND($E5="weekly",35<=$D5),AND($E5="biweekly",35<=$D5,MOD(35-$C5,2)=0))),Flows!$C6,0)) | AO5: =IF(OR($A5="",Flows!$C6=""),0,IF(AND(36<=Setup!$B$5,36>=$C5,OR(AND($E5="once",36=$C5),AND($E5="weekly",36<=$D5),AND($E5="biweekly",36<=$D5,MOD(36-$C5,2)=0))),Flows!$C6,0)) | AP5: =IF(OR($A5="",Flows!$C6=""),0,IF(AND(37<=Setup!$B$5,37>=$C5,OR(AND($E5="once",37=$C5),AND($E5="weekly",37<=$D5),AND($E5="biweekly",37<=$D5,MOD(37-$C5,2)=0))),Flows!$C6,0)) | AQ5: =IF(OR($A5="",Flows!$C6=""),0,IF(AND(38<=Setup!$B$5,38>=$C5,OR(AND($E5="once",38=$C5),AND($E5="weekly",38<=$D5),AND($E5="biweekly",38<=$D5,MOD(38-$C5,2)=0))),Flows!$C6,0)) | AR5: =IF(OR($A5="",Flows!$C6=""),0,IF(AND(39<=Setup!$B$5,39>=$C5,OR(AND($E5="once",39=$C5),AND($E5="weekly",39<=$D5),AND($E5="biweekly",39<=$D5,MOD(39-$C5,2)=0))),Flows!$C6,0)) | AS5: =IF(OR($A5="",Flows!$C6=""),0,IF(AND(40<=Setup!$B$5,40>=$C5,OR(AND($E5="once",40=$C5),AND($E5="weekly",40<=$D5),AND($E5="biweekly",40<=$D5,MOD(40-$C5,2)=0))),Flows!$C6,0)) | AT5: =IF(OR($A5="",Flows!$C6=""),0,IF(AND(41<=Setup!$B$5,41>=$C5,OR(AND($E5="once",41=$C5),AND($E5="weekly",41<=$D5),AND($E5="biweekly",41<=$D5,MOD(41-$C5,2)=0))),Flows!$C6,0)) | AU5: =IF(OR($A5="",Flows!$C6=""),0,IF(AND(42<=Setup!$B$5,42>=$C5,OR(AND($E5="once",42=$C5),AND($E5="weekly",42<=$D5),AND($E5="biweekly",42<=$D5,MOD(42-$C5,2)=0))),Flows!$C6,0)) | AV5: =IF(OR($A5="",Flows!$C6=""),0,IF(AND(43<=Setup!$B$5,43>=$C5,OR(AND($E5="once",43=$C5),AND($E5="weekly",43<=$D5),AND($E5="biweekly",43<=$D5,MOD(43-$C5,2)=0))),Flows!$C6,0)) | AW5: =IF(OR($A5="",Flows!$C6=""),0,IF(AND(44<=Setup!$B$5,44>=$C5,OR(AND($E5="once",44=$C5),AND($E5="weekly",44<=$D5),AND($E5="biweekly",44<=$D5,MOD(44-$C5,2)=0))),Flows!$C6,0)) | AX5: =IF(OR($A5="",Flows!$C6=""),0,IF(AND(45<=Setup!$B$5,45>=$C5,OR(AND($E5="once",45=$C5),AND($E5="weekly",45<=$D5),AND($E5="biweekly",45<=$D5,MOD(45-$C5,2)=0))),Flows!$C6,0)) | AY5: =IF(OR($A5="",Flows!$C6=""),0,IF(AND(46<=Setup!$B$5,46>=$C5,OR(AND($E5="once",46=$C5),AND($E5="weekly",46<=$D5),AND($E5="biweekly",46<=$D5,MOD(46-$C5,2)=0))),Flows!$C6,0)) | AZ5: =IF(OR($A5="",Flows!$C6=""),0,IF(AND(47<=Setup!$B$5,47>=$C5,OR(AND($E5="once",47=$C5),AND($E5="weekly",47<=$D5),AND($E5="biweekly",47<=$D5,MOD(47-$C5,2)=0))),Flows!$C6,0)) | BA5: =IF(OR($A5="",Flows!$C6=""),0,IF(AND(48<=Setup!$B$5,48>=$C5,OR(AND($E5="once",48=$C5),AND($E5="weekly",48<=$D5),AND($E5="biweekly",48<=$D5,MOD(48-$C5,2)=0))),Flows!$C6,0)) | BB5: =IF(OR($A5="",Flows!$C6=""),0,IF(AND(49<=Setup!$B$5,49>=$C5,OR(AND($E5="once",49=$C5),AND($E5="weekly",49<=$D5),AND($E5="biweekly",49<=$D5,MOD(49-$C5,2)=0))),Flows!$C6,0)) | BC5: =IF(OR($A5="",Flows!$C6=""),0,IF(AND(50<=Setup!$B$5,50>=$C5,OR(AND($E5="once",50=$C5),AND($E5="weekly",50<=$D5),AND($E5="biweekly",50<=$D5,MOD(50-$C5,2)=0))),Flows!$C6,0)) | BD5: =IF(OR($A5="",Flows!$C6=""),0,IF(AND(51<=Setup!$B$5,51>=$C5,OR(AND($E5="once",51=$C5),AND($E5="weekly",51<=$D5),AND($E5="biweekly",51<=$D5,MOD(51-$C5,2)=0))),Flows!$C6,0)) | BE5: =IF(OR($A5="",Flows!$C6=""),0,IF(AND(52<=Setup!$B$5,52>=$C5,OR(AND($E5="once",52=$C5),AND($E5="weekly",52<=$D5),AND($E5="biweekly",52<=$D5,MOD(52-$C5,2)=0))),Flows!$C6,0))
A6: =IF(Flows!A7="","",LOWER(Flows!A7)) | B6: =IF(Flows!B7="","",Flows!B7) | C6: =N(Flows!D7) | D6: =IF(Flows!F7="",Setup!$B$5,Flows!F7) | E6: =IF(Flows!E7="","once",LOWER(Flows!E7)) | F6: =IF(OR($A6="",Flows!$C7=""),0,IF(AND(1<=Setup!$B$5,1>=$C6,OR(AND($E6="once",1=$C6),AND($E6="weekly",1<=$D6),AND($E6="biweekly",1<=$D6,MOD(1-$C6,2)=0))),Flows!$C7,0)) | G6: =IF(OR($A6="",Flows!$C7=""),0,IF(AND(2<=Setup!$B$5,2>=$C6,OR(AND($E6="once",2=$C6),AND($E6="weekly",2<=$D6),AND($E6="biweekly",2<=$D6,MOD(2-$C6,2)=0))),Flows!$C7,0)) | H6: =IF(OR($A6="",Flows!$C7=""),0,IF(AND(3<=Setup!$B$5,3>=$C6,OR(AND($E6="once",3=$C6),AND($E6="weekly",3<=$D6),AND($E6="biweekly",3<=$D6,MOD(3-$C6,2)=0))),Flows!$C7,0)) | I6: =IF(OR($A6="",Flows!$C7=""),0,IF(AND(4<=Setup!$B$5,4>=$C6,OR(AND($E6="once",4=$C6),AND($E6="weekly",4<=$D6),AND($E6="biweekly",4<=$D6,MOD(4-$C6,2)=0))),Flows!$C7,0)) | J6: =IF(OR($A6="",Flows!$C7=""),0,IF(AND(5<=Setup!$B$5,5>=$C6,OR(AND($E6="once",5=$C6),AND($E6="weekly",5<=$D6),AND($E6="biweekly",5<=$D6,MOD(5-$C6,2)=0))),Flows!$C7,0)) | K6: =IF(OR($A6="",Flows!$C7=""),0,IF(AND(6<=Setup!$B$5,6>=$C6,OR(AND($E6="once",6=$C6),AND($E6="weekly",6<=$D6),AND($E6="biweekly",6<=$D6,MOD(6-$C6,2)=0))),Flows!$C7,0)) | L6: =IF(OR($A6="",Flows!$C7=""),0,IF(AND(7<=Setup!$B$5,7>=$C6,OR(AND($E6="once",7=$C6),AND($E6="weekly",7<=$D6),AND($E6="biweekly",7<=$D6,MOD(7-$C6,2)=0))),Flows!$C7,0)) | M6: =IF(OR($A6="",Flows!$C7=""),0,IF(AND(8<=Setup!$B$5,8>=$C6,OR(AND($E6="once",8=$C6),AND($E6="weekly",8<=$D6),AND($E6="biweekly",8<=$D6,MOD(8-$C6,2)=0))),Flows!$C7,0)) | N6: =IF(OR($A6="",Flows!$C7=""),0,IF(AND(9<=Setup!$B$5,9>=$C6,OR(AND($E6="once",9=$C6),AND($E6="weekly",9<=$D6),AND($E6="biweekly",9<=$D6,MOD(9-$C6,2)=0))),Flows!$C7,0)) | O6: =IF(OR($A6="",Flows!$C7=""),0,IF(AND(10<=Setup!$B$5,10>=$C6,OR(AND($E6="once",10=$C6),AND($E6="weekly",10<=$D6),AND($E6="biweekly",10<=$D6,MOD(10-$C6,2)=0))),Flows!$C7,0)) | P6: =IF(OR($A6="",Flows!$C7=""),0,IF(AND(11<=Setup!$B$5,11>=$C6,OR(AND($E6="once",11=$C6),AND($E6="weekly",11<=$D6),AND($E6="biweekly",11<=$D6,MOD(11-$C6,2)=0))),Flows!$C7,0)) | Q6: =IF(OR($A6="",Flows!$C7=""),0,IF(AND(12<=Setup!$B$5,12>=$C6,OR(AND($E6="once",12=$C6),AND($E6="weekly",12<=$D6),AND($E6="biweekly",12<=$D6,MOD(12-$C6,2)=0))),Flows!$C7,0)) | R6: =IF(OR($A6="",Flows!$C7=""),0,IF(AND(13<=Setup!$B$5,13>=$C6,OR(AND($E6="once",13=$C6),AND($E6="weekly",13<=$D6),AND($E6="biweekly",13<=$D6,MOD(13-$C6,2)=0))),Flows!$C7,0)) | S6: =IF(OR($A6="",Flows!$C7=""),0,IF(AND(14<=Setup!$B$5,14>=$C6,OR(AND($E6="once",14=$C6),AND($E6="weekly",14<=$D6),AND($E6="biweekly",14<=$D6,MOD(14-$C6,2)=0))),Flows!$C7,0)) | T6: =IF(OR($A6="",Flows!$C7=""),0,IF(AND(15<=Setup!$B$5,15>=$C6,OR(AND($E6="once",15=$C6),AND($E6="weekly",15<=$D6),AND($E6="biweekly",15<=$D6,MOD(15-$C6,2)=0))),Flows!$C7,0)) | U6: =IF(OR($A6="",Flows!$C7=""),0,IF(AND(16<=Setup!$B$5,16>=$C6,OR(AND($E6="once",16=$C6),AND($E6="weekly",16<=$D6),AND($E6="biweekly",16<=$D6,MOD(16-$C6,2)=0))),Flows!$C7,0)) | V6: =IF(OR($A6="",Flows!$C7=""),0,IF(AND(17<=Setup!$B$5,17>=$C6,OR(AND($E6="once",17=$C6),AND($E6="weekly",17<=$D6),AND($E6="biweekly",17<=$D6,MOD(17-$C6,2)=0))),Flows!$C7,0)) | W6: =IF(OR($A6="",Flows!$C7=""),0,IF(AND(18<=Setup!$B$5,18>=$C6,OR(AND($E6="once",18=$C6),AND($E6="weekly",18<=$D6),AND($E6="biweekly",18<=$D6,MOD(18-$C6,2)=0))),Flows!$C7,0)) | X6: =IF(OR($A6="",Flows!$C7=""),0,IF(AND(19<=Setup!$B$5,19>=$C6,OR(AND($E6="once",19=$C6),AND($E6="weekly",19<=$D6),AND($E6="biweekly",19<=$D6,MOD(19-$C6,2)=0))),Flows!$C7,0)) | Y6: =IF(OR($A6="",Flows!$C7=""),0,IF(AND(20<=Setup!$B$5,20>=$C6,OR(AND($E6="once",20=$C6),AND($E6="weekly",20<=$D6),AND($E6="biweekly",20<=$D6,MOD(20-$C6,2)=0))),Flows!$C7,0)) | Z6: =IF(OR($A6="",Flows!$C7=""),0,IF(AND(21<=Setup!$B$5,21>=$C6,OR(AND($E6="once",21=$C6),AND($E6="weekly",21<=$D6),AND($E6="biweekly",21<=$D6,MOD(21-$C6,2)=0))),Flows!$C7,0)) | AA6: =IF(OR($A6="",Flows!$C7=""),0,IF(AND(22<=Setup!$B$5,22>=$C6,OR(AND($E6="once",22=$C6),AND($E6="weekly",22<=$D6),AND($E6="biweekly",22<=$D6,MOD(22-$C6,2)=0))),Flows!$C7,0)) | AB6: =IF(OR($A6="",Flows!$C7=""),0,IF(AND(23<=Setup!$B$5,23>=$C6,OR(AND($E6="once",23=$C6),AND($E6="weekly",23<=$D6),AND($E6="biweekly",23<=$D6,MOD(23-$C6,2)=0))),Flows!$C7,0)) | AC6: =IF(OR($A6="",Flows!$C7=""),0,IF(AND(24<=Setup!$B$5,24>=$C6,OR(AND($E6="once",24=$C6),AND($E6="weekly",24<=$D6),AND($E6="biweekly",24<=$D6,MOD(24-$C6,2)=0))),Flows!$C7,0)) | AD6: =IF(OR($A6="",Flows!$C7=""),0,IF(AND(25<=Setup!$B$5,25>=$C6,OR(AND($E6="once",25=$C6),AND($E6="weekly",25<=$D6),AND($E6="biweekly",25<=$D6,MOD(25-$C6,2)=0))),Flows!$C7,0)) | AE6: =IF(OR($A6="",Flows!$C7=""),0,IF(AND(26<=Setup!$B$5,26>=$C6,OR(AND($E6="once",26=$C6),AND($E6="weekly",26<=$D6),AND($E6="biweekly",26<=$D6,MOD(26-$C6,2)=0))),Flows!$C7,0)) | AF6: =IF(OR($A6="",Flows!$C7=""),0,IF(AND(27<=Setup!$B$5,27>=$C6,OR(AND($E6="once",27=$C6),AND($E6="weekly",27<=$D6),AND($E6="biweekly",27<=$D6,MOD(27-$C6,2)=0))),Flows!$C7,0)) | AG6: =IF(OR($A6="",Flows!$C7=""),0,IF(AND(28<=Setup!$B$5,28>=$C6,OR(AND($E6="once",28=$C6),AND($E6="weekly",28<=$D6),AND($E6="biweekly",28<=$D6,MOD(28-$C6,2)=0))),Flows!$C7,0)) | AH6: =IF(OR($A6="",Flows!$C7=""),0,IF(AND(29<=Setup!$B$5,29>=$C6,OR(AND($E6="once",29=$C6),AND($E6="weekly",29<=$D6),AND($E6="biweekly",29<=$D6,MOD(29-$C6,2)=0))),Flows!$C7,0)) | AI6: =IF(OR($A6="",Flows!$C7=""),0,IF(AND(30<=Setup!$B$5,30>=$C6,OR(AND($E6="once",30=$C6),AND($E6="weekly",30<=$D6),AND($E6="biweekly",30<=$D6,MOD(30-$C6,2)=0))),Flows!$C7,0)) | AJ6: =IF(OR($A6="",Flows!$C7=""),0,IF(AND(31<=Setup!$B$5,31>=$C6,OR(AND($E6="once",31=$C6),AND($E6="weekly",31<=$D6),AND($E6="biweekly",31<=$D6,MOD(31-$C6,2)=0))),Flows!$C7,0)) | AK6: =IF(OR($A6="",Flows!$C7=""),0,IF(AND(32<=Setup!$B$5,32>=$C6,OR(AND($E6="once",32=$C6),AND($E6="weekly",32<=$D6),AND($E6="biweekly",32<=$D6,MOD(32-$C6,2)=0))),Flows!$C7,0)) | AL6: =IF(OR($A6="",Flows!$C7=""),0,IF(AND(33<=Setup!$B$5,33>=$C6,OR(AND($E6="once",33=$C6),AND($E6="weekly",33<=$D6),AND($E6="biweekly",33<=$D6,MOD(33-$C6,2)=0))),Flows!$C7,0)) | AM6: =IF(OR($A6="",Flows!$C7=""),0,IF(AND(34<=Setup!$B$5,34>=$C6,OR(AND($E6="once",34=$C6),AND($E6="weekly",34<=$D6),AND($E6="biweekly",34<=$D6,MOD(34-$C6,2)=0))),Flows!$C7,0)) | AN6: =IF(OR($A6="",Flows!$C7=""),0,IF(AND(35<=Setup!$B$5,35>=$C6,OR(AND($E6="once",35=$C6),AND($E6="weekly",35<=$D6),AND($E6="biweekly",35<=$D6,MOD(35-$C6,2)=0))),Flows!$C7,0)) | AO6: =IF(OR($A6="",Flows!$C7=""),0,IF(AND(36<=Setup!$B$5,36>=$C6,OR(AND($E6="once",36=$C6),AND($E6="weekly",36<=$D6),AND($E6="biweekly",36<=$D6,MOD(36-$C6,2)=0))),Flows!$C7,0)) | AP6: =IF(OR($A6="",Flows!$C7=""),0,IF(AND(37<=Setup!$B$5,37>=$C6,OR(AND($E6="once",37=$C6),AND($E6="weekly",37<=$D6),AND($E6="biweekly",37<=$D6,MOD(37-$C6,2)=0))),Flows!$C7,0)) | AQ6: =IF(OR($A6="",Flows!$C7=""),0,IF(AND(38<=Setup!$B$5,38>=$C6,OR(AND($E6="once",38=$C6),AND($E6="weekly",38<=$D6),AND($E6="biweekly",38<=$D6,MOD(38-$C6,2)=0))),Flows!$C7,0)) | AR6: =IF(OR($A6="",Flows!$C7=""),0,IF(AND(39<=Setup!$B$5,39>=$C6,OR(AND($E6="once",39=$C6),AND($E6="weekly",39<=$D6),AND($E6="biweekly",39<=$D6,MOD(39-$C6,2)=0))),Flows!$C7,0)) | AS6: =IF(OR($A6="",Flows!$C7=""),0,IF(AND(40<=Setup!$B$5,40>=$C6,OR(AND($E6="once",40=$C6),AND($E6="weekly",40<=$D6),AND($E6="biweekly",40<=$D6,MOD(40-$C6,2)=0))),Flows!$C7,0)) | AT6: =IF(OR($A6="",Flows!$C7=""),0,IF(AND(41<=Setup!$B$5,41>=$C6,OR(AND($E6="once",41=$C6),AND($E6="weekly",41<=$D6),AND($E6="biweekly",41<=$D6,MOD(41-$C6,2)=0))),Flows!$C7,0)) | AU6: =IF(OR($A6="",Flows!$C7=""),0,IF(AND(42<=Setup!$B$5,42>=$C6,OR(AND($E6="once",42=$C6),AND($E6="weekly",42<=$D6),AND($E6="biweekly",42<=$D6,MOD(42-$C6,2)=0))),Flows!$C7,0)) | AV6: =IF(OR($A6="",Flows!$C7=""),0,IF(AND(43<=Setup!$B$5,43>=$C6,OR(AND($E6="once",43=$C6),AND($E6="weekly",43<=$D6),AND($E6="biweekly",43<=$D6,MOD(43-$C6,2)=0))),Flows!$C7,0)) | AW6: =IF(OR($A6="",Flows!$C7=""),0,IF(AND(44<=Setup!$B$5,44>=$C6,OR(AND($E6="once",44=$C6),AND($E6="weekly",44<=$D6),AND($E6="biweekly",44<=$D6,MOD(44-$C6,2)=0))),Flows!$C7,0)) | AX6: =IF(OR($A6="",Flows!$C7=""),0,IF(AND(45<=Setup!$B$5,45>=$C6,OR(AND($E6="once",45=$C6),AND($E6="weekly",45<=$D6),AND($E6="biweekly",45<=$D6,MOD(45-$C6,2)=0))),Flows!$C7,0)) | AY6: =IF(OR($A6="",Flows!$C7=""),0,IF(AND(46<=Setup!$B$5,46>=$C6,OR(AND($E6="once",46=$C6),AND($E6="weekly",46<=$D6),AND($E6="biweekly",46<=$D6,MOD(46-$C6,2)=0))),Flows!$C7,0)) | AZ6: =IF(OR($A6="",Flows!$C7=""),0,IF(AND(47<=Setup!$B$5,47>=$C6,OR(AND($E6="once",47=$C6),AND($E6="weekly",47<=$D6),AND($E6="biweekly",47<=$D6,MOD(47-$C6,2)=0))),Flows!$C7,0)) | BA6: =IF(OR($A6="",Flows!$C7=""),0,IF(AND(48<=Setup!$B$5,48>=$C6,OR(AND($E6="once",48=$C6),AND($E6="weekly",48<=$D6),AND($E6="biweekly",48<=$D6,MOD(48-$C6,2)=0))),Flows!$C7,0)) | BB6: =IF(OR($A6="",Flows!$C7=""),0,IF(AND(49<=Setup!$B$5,49>=$C6,OR(AND($E6="once",49=$C6),AND($E6="weekly",49<=$D6),AND($E6="biweekly",49<=$D6,MOD(49-$C6,2)=0))),Flows!$C7,0)) | BC6: =IF(OR($A6="",Flows!$C7=""),0,IF(AND(50<=Setup!$B$5,50>=$C6,OR(AND($E6="once",50=$C6),AND($E6="weekly",50<=$D6),AND($E6="biweekly",50<=$D6,MOD(50-$C6,2)=0))),Flows!$C7,0)) | BD6: =IF(OR($A6="",Flows!$C7=""),0,IF(AND(51<=Setup!$B$5,51>=$C6,OR(AND($E6="once",51=$C6),AND($E6="weekly",51<=$D6),AND($E6="biweekly",51<=$D6,MOD(51-$C6,2)=0))),Flows!$C7,0)) | BE6: =IF(OR($A6="",Flows!$C7=""),0,IF(AND(52<=Setup!$B$5,52>=$C6,OR(AND($E6="once",52=$C6),AND($E6="weekly",52<=$D6),AND($E6="biweekly",52<=$D6,MOD(52-$C6,2)=0))),Flows!$C7,0))
A7: =IF(Flows!A8="","",LOWER(Flows!A8)) | B7: =IF(Flows!B8="","",Flows!B8) | C7: =N(Flows!D8) | D7: =IF(Flows!F8="",Setup!$B$5,Flows!F8) | E7: =IF(Flows!E8="","once",LOWER(Flows!E8)) | F7: =IF(OR($A7="",Flows!$C8=""),0,IF(AND(1<=Setup!$B$5,1>=$C7,OR(AND($E7="once",1=$C7),AND($E7="weekly",1<=$D7),AND($E7="biweekly",1<=$D7,MOD(1-$C7,2)=0))),Flows!$C8,0)) | G7: =IF(OR($A7="",Flows!$C8=""),0,IF(AND(2<=Setup!$B$5,2>=$C7,OR(AND($E7="once",2=$C7),AND($E7="weekly",2<=$D7),AND($E7="biweekly",2<=$D7,MOD(2-$C7,2)=0))),Flows!$C8,0)) | H7: =IF(OR($A7="",Flows!$C8=""),0,IF(AND(3<=Setup!$B$5,3>=$C7,OR(AND($E7="once",3=$C7),AND($E7="weekly",3<=$D7),AND($E7="biweekly",3<=$D7,MOD(3-$C7,2)=0))),Flows!$C8,0)) | I7: =IF(OR($A7="",Flows!$C8=""),0,IF(AND(4<=Setup!$B$5,4>=$C7,OR(AND($E7="once",4=$C7),AND($E7="weekly",4<=$D7),AND($E7="biweekly",4<=$D7,MOD(4-$C7,2)=0))),Flows!$C8,0)) | J7: =IF(OR($A7="",Flows!$C8=""),0,IF(AND(5<=Setup!$B$5,5>=$C7,OR(AND($E7="once",5=$C7),AND($E7="weekly",5<=$D7),AND($E7="biweekly",5<=$D7,MOD(5-$C7,2)=0))),Flows!$C8,0)) | K7: =IF(OR($A7="",Flows!$C8=""),0,IF(AND(6<=Setup!$B$5,6>=$C7,OR(AND($E7="once",6=$C7),AND($E7="weekly",6<=$D7),AND($E7="biweekly",6<=$D7,MOD(6-$C7,2)=0))),Flows!$C8,0)) | L7: =IF(OR($A7="",Flows!$C8=""),0,IF(AND(7<=Setup!$B$5,7>=$C7,OR(AND($E7="once",7=$C7),AND($E7="weekly",7<=$D7),AND($E7="biweekly",7<=$D7,MOD(7-$C7,2)=0))),Flows!$C8,0)) | M7: =IF(OR($A7="",Flows!$C8=""),0,IF(AND(8<=Setup!$B$5,8>=$C7,OR(AND($E7="once",8=$C7),AND($E7="weekly",8<=$D7),AND($E7="biweekly",8<=$D7,MOD(8-$C7,2)=0))),Flows!$C8,0)) | N7: =IF(OR($A7="",Flows!$C8=""),0,IF(AND(9<=Setup!$B$5,9>=$C7,OR(AND($E7="once",9=$C7),AND($E7="weekly",9<=$D7),AND($E7="biweekly",9<=$D7,MOD(9-$C7,2)=0))),Flows!$C8,0)) | O7: =IF(OR($A7="",Flows!$C8=""),0,IF(AND(10<=Setup!$B$5,10>=$C7,OR(AND($E7="once",10=$C7),AND($E7="weekly",10<=$D7),AND($E7="biweekly",10<=$D7,MOD(10-$C7,2)=0))),Flows!$C8,0)) | P7: =IF(OR($A7="",Flows!$C8=""),0,IF(AND(11<=Setup!$B$5,11>=$C7,OR(AND($E7="once",11=$C7),AND($E7="weekly",11<=$D7),AND($E7="biweekly",11<=$D7,MOD(11-$C7,2)=0))),Flows!$C8,0)) | Q7: =IF(OR($A7="",Flows!$C8=""),0,IF(AND(12<=Setup!$B$5,12>=$C7,OR(AND($E7="once",12=$C7),AND($E7="weekly",12<=$D7),AND($E7="biweekly",12<=$D7,MOD(12-$C7,2)=0))),Flows!$C8,0)) | R7: =IF(OR($A7="",Flows!$C8=""),0,IF(AND(13<=Setup!$B$5,13>=$C7,OR(AND($E7="once",13=$C7),AND($E7="weekly",13<=$D7),AND($E7="biweekly",13<=$D7,MOD(13-$C7,2)=0))),Flows!$C8,0)) | S7: =IF(OR($A7="",Flows!$C8=""),0,IF(AND(14<=Setup!$B$5,14>=$C7,OR(AND($E7="once",14=$C7),AND($E7="weekly",14<=$D7),AND($E7="biweekly",14<=$D7,MOD(14-$C7,2)=0))),Flows!$C8,0)) | T7: =IF(OR($A7="",Flows!$C8=""),0,IF(AND(15<=Setup!$B$5,15>=$C7,OR(AND($E7="once",15=$C7),AND($E7="weekly",15<=$D7),AND($E7="biweekly",15<=$D7,MOD(15-$C7,2)=0))),Flows!$C8,0)) | U7: =IF(OR($A7="",Flows!$C8=""),0,IF(AND(16<=Setup!$B$5,16>=$C7,OR(AND($E7="once",16=$C7),AND($E7="weekly",16<=$D7),AND($E7="biweekly",16<=$D7,MOD(16-$C7,2)=0))),Flows!$C8,0)) | V7: =IF(OR($A7="",Flows!$C8=""),0,IF(AND(17<=Setup!$B$5,17>=$C7,OR(AND($E7="once",17=$C7),AND($E7="weekly",17<=$D7),AND($E7="biweekly",17<=$D7,MOD(17-$C7,2)=0))),Flows!$C8,0)) | W7: =IF(OR($A7="",Flows!$C8=""),0,IF(AND(18<=Setup!$B$5,18>=$C7,OR(AND($E7="once",18=$C7),AND($E7="weekly",18<=$D7),AND($E7="biweekly",18<=$D7,MOD(18-$C7,2)=0))),Flows!$C8,0)) | X7: =IF(OR($A7="",Flows!$C8=""),0,IF(AND(19<=Setup!$B$5,19>=$C7,OR(AND($E7="once",19=$C7),AND($E7="weekly",19<=$D7),AND($E7="biweekly",19<=$D7,MOD(19-$C7,2)=0))),Flows!$C8,0)) | Y7: =IF(OR($A7="",Flows!$C8=""),0,IF(AND(20<=Setup!$B$5,20>=$C7,OR(AND($E7="once",20=$C7),AND($E7="weekly",20<=$D7),AND($E7="biweekly",20<=$D7,MOD(20-$C7,2)=0))),Flows!$C8,0)) | Z7: =IF(OR($A7="",Flows!$C8=""),0,IF(AND(21<=Setup!$B$5,21>=$C7,OR(AND($E7="once",21=$C7),AND($E7="weekly",21<=$D7),AND($E7="biweekly",21<=$D7,MOD(21-$C7,2)=0))),Flows!$C8,0)) | AA7: =IF(OR($A7="",Flows!$C8=""),0,IF(AND(22<=Setup!$B$5,22>=$C7,OR(AND($E7="once",22=$C7),AND($E7="weekly",22<=$D7),AND($E7="biweekly",22<=$D7,MOD(22-$C7,2)=0))),Flows!$C8,0)) | AB7: =IF(OR($A7="",Flows!$C8=""),0,IF(AND(23<=Setup!$B$5,23>=$C7,OR(AND($E7="once",23=$C7),AND($E7="weekly",23<=$D7),AND($E7="biweekly",23<=$D7,MOD(23-$C7,2)=0))),Flows!$C8,0)) | AC7: =IF(OR($A7="",Flows!$C8=""),0,IF(AND(24<=Setup!$B$5,24>=$C7,OR(AND($E7="once",24=$C7),AND($E7="weekly",24<=$D7),AND($E7="biweekly",24<=$D7,MOD(24-$C7,2)=0))),Flows!$C8,0)) | AD7: =IF(OR($A7="",Flows!$C8=""),0,IF(AND(25<=Setup!$B$5,25>=$C7,OR(AND($E7="once",25=$C7),AND($E7="weekly",25<=$D7),AND($E7="biweekly",25<=$D7,MOD(25-$C7,2)=0))),Flows!$C8,0)) | AE7: =IF(OR($A7="",Flows!$C8=""),0,IF(AND(26<=Setup!$B$5,26>=$C7,OR(AND($E7="once",26=$C7),AND($E7="weekly",26<=$D7),AND($E7="biweekly",26<=$D7,MOD(26-$C7,2)=0))),Flows!$C8,0)) | AF7: =IF(OR($A7="",Flows!$C8=""),0,IF(AND(27<=Setup!$B$5,27>=$C7,OR(AND($E7="once",27=$C7),AND($E7="weekly",27<=$D7),AND($E7="biweekly",27<=$D7,MOD(27-$C7,2)=0))),Flows!$C8,0)) | AG7: =IF(OR($A7="",Flows!$C8=""),0,IF(AND(28<=Setup!$B$5,28>=$C7,OR(AND($E7="once",28=$C7),AND($E7="weekly",28<=$D7),AND($E7="biweekly",28<=$D7,MOD(28-$C7,2)=0))),Flows!$C8,0)) | AH7: =IF(OR($A7="",Flows!$C8=""),0,IF(AND(29<=Setup!$B$5,29>=$C7,OR(AND($E7="once",29=$C7),AND($E7="weekly",29<=$D7),AND($E7="biweekly",29<=$D7,MOD(29-$C7,2)=0))),Flows!$C8,0)) | AI7: =IF(OR($A7="",Flows!$C8=""),0,IF(AND(30<=Setup!$B$5,30>=$C7,OR(AND($E7="once",30=$C7),AND($E7="weekly",30<=$D7),AND($E7="biweekly",30<=$D7,MOD(30-$C7,2)=0))),Flows!$C8,0)) | AJ7: =IF(OR($A7="",Flows!$C8=""),0,IF(AND(31<=Setup!$B$5,31>=$C7,OR(AND($E7="once",31=$C7),AND($E7="weekly",31<=$D7),AND($E7="biweekly",31<=$D7,MOD(31-$C7,2)=0))),Flows!$C8,0)) | AK7: =IF(OR($A7="",Flows!$C8=""),0,IF(AND(32<=Setup!$B$5,32>=$C7,OR(AND($E7="once",32=$C7),AND($E7="weekly",32<=$D7),AND($E7="biweekly",32<=$D7,MOD(32-$C7,2)=0))),Flows!$C8,0)) | AL7: =IF(OR($A7="",Flows!$C8=""),0,IF(AND(33<=Setup!$B$5,33>=$C7,OR(AND($E7="once",33=$C7),AND($E7="weekly",33<=$D7),AND($E7="biweekly",33<=$D7,MOD(33-$C7,2)=0))),Flows!$C8,0)) | AM7: =IF(OR($A7="",Flows!$C8=""),0,IF(AND(34<=Setup!$B$5,34>=$C7,OR(AND($E7="once",34=$C7),AND($E7="weekly",34<=$D7),AND($E7="biweekly",34<=$D7,MOD(34-$C7,2)=0))),Flows!$C8,0)) | AN7: =IF(OR($A7="",Flows!$C8=""),0,IF(AND(35<=Setup!$B$5,35>=$C7,OR(AND($E7="once",35=$C7),AND($E7="weekly",35<=$D7),AND($E7="biweekly",35<=$D7,MOD(35-$C7,2)=0))),Flows!$C8,0)) | AO7: =IF(OR($A7="",Flows!$C8=""),0,IF(AND(36<=Setup!$B$5,36>=$C7,OR(AND($E7="once",36=$C7),AND($E7="weekly",36<=$D7),AND($E7="biweekly",36<=$D7,MOD(36-$C7,2)=0))),Flows!$C8,0)) | AP7: =IF(OR($A7="",Flows!$C8=""),0,IF(AND(37<=Setup!$B$5,37>=$C7,OR(AND($E7="once",37=$C7),AND($E7="weekly",37<=$D7),AND($E7="biweekly",37<=$D7,MOD(37-$C7,2)=0))),Flows!$C8,0)) | AQ7: =IF(OR($A7="",Flows!$C8=""),0,IF(AND(38<=Setup!$B$5,38>=$C7,OR(AND($E7="once",38=$C7),AND($E7="weekly",38<=$D7),AND($E7="biweekly",38<=$D7,MOD(38-$C7,2)=0))),Flows!$C8,0)) | AR7: =IF(OR($A7="",Flows!$C8=""),0,IF(AND(39<=Setup!$B$5,39>=$C7,OR(AND($E7="once",39=$C7),AND($E7="weekly",39<=$D7),AND($E7="biweekly",39<=$D7,MOD(39-$C7,2)=0))),Flows!$C8,0)) | AS7: =IF(OR($A7="",Flows!$C8=""),0,IF(AND(40<=Setup!$B$5,40>=$C7,OR(AND($E7="once",40=$C7),AND($E7="weekly",40<=$D7),AND($E7="biweekly",40<=$D7,MOD(40-$C7,2)=0))),Flows!$C8,0)) | AT7: =IF(OR($A7="",Flows!$C8=""),0,IF(AND(41<=Setup!$B$5,41>=$C7,OR(AND($E7="once",41=$C7),AND($E7="weekly",41<=$D7),AND($E7="biweekly",41<=$D7,MOD(41-$C7,2)=0))),Flows!$C8,0)) | AU7: =IF(OR($A7="",Flows!$C8=""),0,IF(AND(42<=Setup!$B$5,42>=$C7,OR(AND($E7="once",42=$C7),AND($E7="weekly",42<=$D7),AND($E7="biweekly",42<=$D7,MOD(42-$C7,2)=0))),Flows!$C8,0)) | AV7: =IF(OR($A7="",Flows!$C8=""),0,IF(AND(43<=Setup!$B$5,43>=$C7,OR(AND($E7="once",43=$C7),AND($E7="weekly",43<=$D7),AND($E7="biweekly",43<=$D7,MOD(43-$C7,2)=0))),Flows!$C8,0)) | AW7: =IF(OR($A7="",Flows!$C8=""),0,IF(AND(44<=Setup!$B$5,44>=$C7,OR(AND($E7="once",44=$C7),AND($E7="weekly",44<=$D7),AND($E7="biweekly",44<=$D7,MOD(44-$C7,2)=0))),Flows!$C8,0)) | AX7: =IF(OR($A7="",Flows!$C8=""),0,IF(AND(45<=Setup!$B$5,45>=$C7,OR(AND($E7="once",45=$C7),AND($E7="weekly",45<=$D7),AND($E7="biweekly",45<=$D7,MOD(45-$C7,2)=0))),Flows!$C8,0)) | AY7: =IF(OR($A7="",Flows!$C8=""),0,IF(AND(46<=Setup!$B$5,46>=$C7,OR(AND($E7="once",46=$C7),AND($E7="weekly",46<=$D7),AND($E7="biweekly",46<=$D7,MOD(46-$C7,2)=0))),Flows!$C8,0)) | AZ7: =IF(OR($A7="",Flows!$C8=""),0,IF(AND(47<=Setup!$B$5,47>=$C7,OR(AND($E7="once",47=$C7),AND($E7="weekly",47<=$D7),AND($E7="biweekly",47<=$D7,MOD(47-$C7,2)=0))),Flows!$C8,0)) | BA7: =IF(OR($A7="",Flows!$C8=""),0,IF(AND(48<=Setup!$B$5,48>=$C7,OR(AND($E7="once",48=$C7),AND($E7="weekly",48<=$D7),AND($E7="biweekly",48<=$D7,MOD(48-$C7,2)=0))),Flows!$C8,0)) | BB7: =IF(OR($A7="",Flows!$C8=""),0,IF(AND(49<=Setup!$B$5,49>=$C7,OR(AND($E7="once",49=$C7),AND($E7="weekly",49<=$D7),AND($E7="biweekly",49<=$D7,MOD(49-$C7,2)=0))),Flows!$C8,0)) | BC7: =IF(OR($A7="",Flows!$C8=""),0,IF(AND(50<=Setup!$B$5,50>=$C7,OR(AND($E7="once",50=$C7),AND($E7="weekly",50<=$D7),AND($E7="biweekly",50<=$D7,MOD(50-$C7,2)=0))),Flows!$C8,0)) | BD7: =IF(OR($A7="",Flows!$C8=""),0,IF(AND(51<=Setup!$B$5,51>=$C7,OR(AND($E7="once",51=$C7),AND($E7="weekly",51<=$D7),AND($E7="biweekly",51<=$D7,MOD(51-$C7,2)=0))),Flows!$C8,0)) | BE7: =IF(OR($A7="",Flows!$C8=""),0,IF(AND(52<=Setup!$B$5,52>=$C7,OR(AND($E7="once",52=$C7),AND($E7="weekly",52<=$D7),AND($E7="biweekly",52<=$D7,MOD(52-$C7,2)=0))),Flows!$C8,0))
A8: =IF(Flows!A9="","",LOWER(Flows!A9)) | B8: =IF(Flows!B9="","",Flows!B9) | C8: =N(Flows!D9) | D8: =IF(Flows!F9="",Setup!$B$5,Flows!F9) | E8: =IF(Flows!E9="","once",LOWER(Flows!E9)) | F8: =IF(OR($A8="",Flows!$C9=""),0,IF(AND(1<=Setup!$B$5,1>=$C8,OR(AND($E8="once",1=$C8),AND($E8="weekly",1<=$D8),AND($E8="biweekly",1<=$D8,MOD(1-$C8,2)=0))),Flows!$C9,0)) | G8: =IF(OR($A8="",Flows!$C9=""),0,IF(AND(2<=Setup!$B$5,2>=$C8,OR(AND($E8="once",2=$C8),AND($E8="weekly",2<=$D8),AND($E8="biweekly",2<=$D8,MOD(2-$C8,2)=0))),Flows!$C9,0)) | H8: =IF(OR($A8="",Flows!$C9=""),0,IF(AND(3<=Setup!$B$5,3>=$C8,OR(AND($E8="once",3=$C8),AND($E8="weekly",3<=$D8),AND($E8="biweekly",3<=$D8,MOD(3-$C8,2)=0))),Flows!$C9,0)) | I8: =IF(OR($A8="",Flows!$C9=""),0,IF(AND(4<=Setup!$B$5,4>=$C8,OR(AND($E8="once",4=$C8),AND($E8="weekly",4<=$D8),AND($E8="biweekly",4<=$D8,MOD(4-$C8,2)=0))),Flows!$C9,0)) | J8: =IF(OR($A8="",Flows!$C9=""),0,IF(AND(5<=Setup!$B$5,5>=$C8,OR(AND($E8="once",5=$C8),AND($E8="weekly",5<=$D8),AND($E8="biweekly",5<=$D8,MOD(5-$C8,2)=0))),Flows!$C9,0)) | K8: =IF(OR($A8="",Flows!$C9=""),0,IF(AND(6<=Setup!$B$5,6>=$C8,OR(AND($E8="once",6=$C8),AND($E8="weekly",6<=$D8),AND($E8="biweekly",6<=$D8,MOD(6-$C8,2)=0))),Flows!$C9,0)) | L8: =IF(OR($A8="",Flows!$C9=""),0,IF(AND(7<=Setup!$B$5,7>=$C8,OR(AND($E8="once",7=$C8),AND($E8="weekly",7<=$D8),AND($E8="biweekly",7<=$D8,MOD(7-$C8,2)=0))),Flows!$C9,0)) | M8: =IF(OR($A8="",Flows!$C9=""),0,IF(AND(8<=Setup!$B$5,8>=$C8,OR(AND($E8="once",8=$C8),AND($E8="weekly",8<=$D8),AND($E8="biweekly",8<=$D8,MOD(8-$C8,2)=0))),Flows!$C9,0)) | N8: =IF(OR($A8="",Flows!$C9=""),0,IF(AND(9<=Setup!$B$5,9>=$C8,OR(AND($E8="once",9=$C8),AND($E8="weekly",9<=$D8),AND($E8="biweekly",9<=$D8,MOD(9-$C8,2)=0))),Flows!$C9,0)) | O8: =IF(OR($A8="",Flows!$C9=""),0,IF(AND(10<=Setup!$B$5,10>=$C8,OR(AND($E8="once",10=$C8),AND($E8="weekly",10<=$D8),AND($E8="biweekly",10<=$D8,MOD(10-$C8,2)=0))),Flows!$C9,0)) | P8: =IF(OR($A8="",Flows!$C9=""),0,IF(AND(11<=Setup!$B$5,11>=$C8,OR(AND($E8="once",11=$C8),AND($E8="weekly",11<=$D8),AND($E8="biweekly",11<=$D8,MOD(11-$C8,2)=0))),Flows!$C9,0)) | Q8: =IF(OR($A8="",Flows!$C9=""),0,IF(AND(12<=Setup!$B$5,12>=$C8,OR(AND($E8="once",12=$C8),AND($E8="weekly",12<=$D8),AND($E8="biweekly",12<=$D8,MOD(12-$C8,2)=0))),Flows!$C9,0)) | R8: =IF(OR($A8="",Flows!$C9=""),0,IF(AND(13<=Setup!$B$5,13>=$C8,OR(AND($E8="once",13=$C8),AND($E8="weekly",13<=$D8),AND($E8="biweekly",13<=$D8,MOD(13-$C8,2)=0))),Flows!$C9,0)) | S8: =IF(OR($A8="",Flows!$C9=""),0,IF(AND(14<=Setup!$B$5,14>=$C8,OR(AND($E8="once",14=$C8),AND($E8="weekly",14<=$D8),AND($E8="biweekly",14<=$D8,MOD(14-$C8,2)=0))),Flows!$C9,0)) | T8: =IF(OR($A8="",Flows!$C9=""),0,IF(AND(15<=Setup!$B$5,15>=$C8,OR(AND($E8="once",15=$C8),AND($E8="weekly",15<=$D8),AND($E8="biweekly",15<=$D8,MOD(15-$C8,2)=0))),Flows!$C9,0)) | U8: =IF(OR($A8="",Flows!$C9=""),0,IF(AND(16<=Setup!$B$5,16>=$C8,OR(AND($E8="once",16=$C8),AND($E8="weekly",16<=$D8),AND($E8="biweekly",16<=$D8,MOD(16-$C8,2)=0))),Flows!$C9,0)) | V8: =IF(OR($A8="",Flows!$C9=""),0,IF(AND(17<=Setup!$B$5,17>=$C8,OR(AND($E8="once",17=$C8),AND($E8="weekly",17<=$D8),AND($E8="biweekly",17<=$D8,MOD(17-$C8,2)=0))),Flows!$C9,0)) | W8: =IF(OR($A8="",Flows!$C9=""),0,IF(AND(18<=Setup!$B$5,18>=$C8,OR(AND($E8="once",18=$C8),AND($E8="weekly",18<=$D8),AND($E8="biweekly",18<=$D8,MOD(18-$C8,2)=0))),Flows!$C9,0)) | X8: =IF(OR($A8="",Flows!$C9=""),0,IF(AND(19<=Setup!$B$5,19>=$C8,OR(AND($E8="once",19=$C8),AND($E8="weekly",19<=$D8),AND($E8="biweekly",19<=$D8,MOD(19-$C8,2)=0))),Flows!$C9,0)) | Y8: =IF(OR($A8="",Flows!$C9=""),0,IF(AND(20<=Setup!$B$5,20>=$C8,OR(AND($E8="once",20=$C8),AND($E8="weekly",20<=$D8),AND($E8="biweekly",20<=$D8,MOD(20-$C8,2)=0))),Flows!$C9,0)) | Z8: =IF(OR($A8="",Flows!$C9=""),0,IF(AND(21<=Setup!$B$5,21>=$C8,OR(AND($E8="once",21=$C8),AND($E8="weekly",21<=$D8),AND($E8="biweekly",21<=$D8,MOD(21-$C8,2)=0))),Flows!$C9,0)) | AA8: =IF(OR($A8="",Flows!$C9=""),0,IF(AND(22<=Setup!$B$5,22>=$C8,OR(AND($E8="once",22=$C8),AND($E8="weekly",22<=$D8),AND($E8="biweekly",22<=$D8,MOD(22-$C8,2)=0))),Flows!$C9,0)) | AB8: =IF(OR($A8="",Flows!$C9=""),0,IF(AND(23<=Setup!$B$5,23>=$C8,OR(AND($E8="once",23=$C8),AND($E8="weekly",23<=$D8),AND($E8="biweekly",23<=$D8,MOD(23-$C8,2)=0))),Flows!$C9,0)) | AC8: =IF(OR($A8="",Flows!$C9=""),0,IF(AND(24<=Setup!$B$5,24>=$C8,OR(AND($E8="once",24=$C8),AND($E8="weekly",24<=$D8),AND($E8="biweekly",24<=$D8,MOD(24-$C8,2)=0))),Flows!$C9,0)) | AD8: =IF(OR($A8="",Flows!$C9=""),0,IF(AND(25<=Setup!$B$5,25>=$C8,OR(AND($E8="once",25=$C8),AND($E8="weekly",25<=$D8),AND($E8="biweekly",25<=$D8,MOD(25-$C8,2)=0))),Flows!$C9,0)) | AE8: =IF(OR($A8="",Flows!$C9=""),0,IF(AND(26<=Setup!$B$5,26>=$C8,OR(AND($E8="once",26=$C8),AND($E8="weekly",26<=$D8),AND($E8="biweekly",26<=$D8,MOD(26-$C8,2)=0))),Flows!$C9,0)) | AF8: =IF(OR($A8="",Flows!$C9=""),0,IF(AND(27<=Setup!$B$5,27>=$C8,OR(AND($E8="once",27=$C8),AND($E8="weekly",27<=$D8),AND($E8="biweekly",27<=$D8,MOD(27-$C8,2)=0))),Flows!$C9,0)) | AG8: =IF(OR($A8="",Flows!$C9=""),0,IF(AND(28<=Setup!$B$5,28>=$C8,OR(AND($E8="once",28=$C8),AND($E8="weekly",28<=$D8),AND($E8="biweekly",28<=$D8,MOD(28-$C8,2)=0))),Flows!$C9,0)) | AH8: =IF(OR($A8="",Flows!$C9=""),0,IF(AND(29<=Setup!$B$5,29>=$C8,OR(AND($E8="once",29=$C8),AND($E8="weekly",29<=$D8),AND($E8="biweekly",29<=$D8,MOD(29-$C8,2)=0))),Flows!$C9,0)) | AI8: =IF(OR($A8="",Flows!$C9=""),0,IF(AND(30<=Setup!$B$5,30>=$C8,OR(AND($E8="once",30=$C8),AND($E8="weekly",30<=$D8),AND($E8="biweekly",30<=$D8,MOD(30-$C8,2)=0))),Flows!$C9,0)) | AJ8: =IF(OR($A8="",Flows!$C9=""),0,IF(AND(31<=Setup!$B$5,31>=$C8,OR(AND($E8="once",31=$C8),AND($E8="weekly",31<=$D8),AND($E8="biweekly",31<=$D8,MOD(31-$C8,2)=0))),Flows!$C9,0)) | AK8: =IF(OR($A8="",Flows!$C9=""),0,IF(AND(32<=Setup!$B$5,32>=$C8,OR(AND($E8="once",32=$C8),AND($E8="weekly",32<=$D8),AND($E8="biweekly",32<=$D8,MOD(32-$C8,2)=0))),Flows!$C9,0)) | AL8: =IF(OR($A8="",Flows!$C9=""),0,IF(AND(33<=Setup!$B$5,33>=$C8,OR(AND($E8="once",33=$C8),AND($E8="weekly",33<=$D8),AND($E8="biweekly",33<=$D8,MOD(33-$C8,2)=0))),Flows!$C9,0)) | AM8: =IF(OR($A8="",Flows!$C9=""),0,IF(AND(34<=Setup!$B$5,34>=$C8,OR(AND($E8="once",34=$C8),AND($E8="weekly",34<=$D8),AND($E8="biweekly",34<=$D8,MOD(34-$C8,2)=0))),Flows!$C9,0)) | AN8: =IF(OR($A8="",Flows!$C9=""),0,IF(AND(35<=Setup!$B$5,35>=$C8,OR(AND($E8="once",35=$C8),AND($E8="weekly",35<=$D8),AND($E8="biweekly",35<=$D8,MOD(35-$C8,2)=0))),Flows!$C9,0)) | AO8: =IF(OR($A8="",Flows!$C9=""),0,IF(AND(36<=Setup!$B$5,36>=$C8,OR(AND($E8="once",36=$C8),AND($E8="weekly",36<=$D8),AND($E8="biweekly",36<=$D8,MOD(36-$C8,2)=0))),Flows!$C9,0)) | AP8: =IF(OR($A8="",Flows!$C9=""),0,IF(AND(37<=Setup!$B$5,37>=$C8,OR(AND($E8="once",37=$C8),AND($E8="weekly",37<=$D8),AND($E8="biweekly",37<=$D8,MOD(37-$C8,2)=0))),Flows!$C9,0)) | AQ8: =IF(OR($A8="",Flows!$C9=""),0,IF(AND(38<=Setup!$B$5,38>=$C8,OR(AND($E8="once",38=$C8),AND($E8="weekly",38<=$D8),AND($E8="biweekly",38<=$D8,MOD(38-$C8,2)=0))),Flows!$C9,0)) | AR8: =IF(OR($A8="",Flows!$C9=""),0,IF(AND(39<=Setup!$B$5,39>=$C8,OR(AND($E8="once",39=$C8),AND($E8="weekly",39<=$D8),AND($E8="biweekly",39<=$D8,MOD(39-$C8,2)=0))),Flows!$C9,0)) | AS8: =IF(OR($A8="",Flows!$C9=""),0,IF(AND(40<=Setup!$B$5,40>=$C8,OR(AND($E8="once",40=$C8),AND($E8="weekly",40<=$D8),AND($E8="biweekly",40<=$D8,MOD(40-$C8,2)=0))),Flows!$C9,0)) | AT8: =IF(OR($A8="",Flows!$C9=""),0,IF(AND(41<=Setup!$B$5,41>=$C8,OR(AND($E8="once",41=$C8),AND($E8="weekly",41<=$D8),AND($E8="biweekly",41<=$D8,MOD(41-$C8,2)=0))),Flows!$C9,0)) | AU8: =IF(OR($A8="",Flows!$C9=""),0,IF(AND(42<=Setup!$B$5,42>=$C8,OR(AND($E8="once",42=$C8),AND($E8="weekly",42<=$D8),AND($E8="biweekly",42<=$D8,MOD(42-$C8,2)=0))),Flows!$C9,0)) | AV8: =IF(OR($A8="",Flows!$C9=""),0,IF(AND(43<=Setup!$B$5,43>=$C8,OR(AND($E8="once",43=$C8),AND($E8="weekly",43<=$D8),AND($E8="biweekly",43<=$D8,MOD(43-$C8,2)=0))),Flows!$C9,0)) | AW8: =IF(OR($A8="",Flows!$C9=""),0,IF(AND(44<=Setup!$B$5,44>=$C8,OR(AND($E8="once",44=$C8),AND($E8="weekly",44<=$D8),AND($E8="biweekly",44<=$D8,MOD(44-$C8,2)=0))),Flows!$C9,0)) | AX8: =IF(OR($A8="",Flows!$C9=""),0,IF(AND(45<=Setup!$B$5,45>=$C8,OR(AND($E8="once",45=$C8),AND($E8="weekly",45<=$D8),AND($E8="biweekly",45<=$D8,MOD(45-$C8,2)=0))),Flows!$C9,0)) | AY8: =IF(OR($A8="",Flows!$C9=""),0,IF(AND(46<=Setup!$B$5,46>=$C8,OR(AND($E8="once",46=$C8),AND($E8="weekly",46<=$D8),AND($E8="biweekly",46<=$D8,MOD(46-$C8,2)=0))),Flows!$C9,0)) | AZ8: =IF(OR($A8="",Flows!$C9=""),0,IF(AND(47<=Setup!$B$5,47>=$C8,OR(AND($E8="once",47=$C8),AND($E8="weekly",47<=$D8),AND($E8="biweekly",47<=$D8,MOD(47-$C8,2)=0))),Flows!$C9,0)) | BA8: =IF(OR($A8="",Flows!$C9=""),0,IF(AND(48<=Setup!$B$5,48>=$C8,OR(AND($E8="once",48=$C8),AND($E8="weekly",48<=$D8),AND($E8="biweekly",48<=$D8,MOD(48-$C8,2)=0))),Flows!$C9,0)) | BB8: =IF(OR($A8="",Flows!$C9=""),0,IF(AND(49<=Setup!$B$5,49>=$C8,OR(AND($E8="once",49=$C8),AND($E8="weekly",49<=$D8),AND($E8="biweekly",49<=$D8,MOD(49-$C8,2)=0))),Flows!$C9,0)) | BC8: =IF(OR($A8="",Flows!$C9=""),0,IF(AND(50<=Setup!$B$5,50>=$C8,OR(AND($E8="once",50=$C8),AND($E8="weekly",50<=$D8),AND($E8="biweekly",50<=$D8,MOD(50-$C8,2)=0))),Flows!$C9,0)) | BD8: =IF(OR($A8="",Flows!$C9=""),0,IF(AND(51<=Setup!$B$5,51>=$C8,OR(AND($E8="once",51=$C8),AND($E8="weekly",51<=$D8),AND($E8="biweekly",51<=$D8,MOD(51-$C8,2)=0))),Flows!$C9,0)) | BE8: =IF(OR($A8="",Flows!$C9=""),0,IF(AND(52<=Setup!$B$5,52>=$C8,OR(AND($E8="once",52=$C8),AND($E8="weekly",52<=$D8),AND($E8="biweekly",52<=$D8,MOD(52-$C8,2)=0))),Flows!$C9,0))
A9: =IF(Flows!A10="","",LOWER(Flows!A10)) | B9: =IF(Flows!B10="","",Flows!B10) | C9: =N(Flows!D10) | D9: =IF(Flows!F10="",Setup!$B$5,Flows!F10) | E9: =IF(Flows!E10="","once",LOWER(Flows!E10)) | F9: =IF(OR($A9="",Flows!$C10=""),0,IF(AND(1<=Setup!$B$5,1>=$C9,OR(AND($E9="once",1=$C9),AND($E9="weekly",1<=$D9),AND($E9="biweekly",1<=$D9,MOD(1-$C9,2)=0))),Flows!$C10,0)) | G9: =IF(OR($A9="",Flows!$C10=""),0,IF(AND(2<=Setup!$B$5,2>=$C9,OR(AND($E9="once",2=$C9),AND($E9="weekly",2<=$D9),AND($E9="biweekly",2<=$D9,MOD(2-$C9,2)=0))),Flows!$C10,0)) | H9: =IF(OR($A9="",Flows!$C10=""),0,IF(AND(3<=Setup!$B$5,3>=$C9,OR(AND($E9="once",3=$C9),AND($E9="weekly",3<=$D9),AND($E9="biweekly",3<=$D9,MOD(3-$C9,2)=0))),Flows!$C10,0)) | I9: =IF(OR($A9="",Flows!$C10=""),0,IF(AND(4<=Setup!$B$5,4>=$C9,OR(AND($E9="once",4=$C9),AND($E9="weekly",4<=$D9),AND($E9="biweekly",4<=$D9,MOD(4-$C9,2)=0))),Flows!$C10,0)) | J9: =IF(OR($A9="",Flows!$C10=""),0,IF(AND(5<=Setup!$B$5,5>=$C9,OR(AND($E9="once",5=$C9),AND($E9="weekly",5<=$D9),AND($E9="biweekly",5<=$D9,MOD(5-$C9,2)=0))),Flows!$C10,0)) | K9: =IF(OR($A9="",Flows!$C10=""),0,IF(AND(6<=Setup!$B$5,6>=$C9,OR(AND($E9="once",6=$C9),AND($E9="weekly",6<=$D9),AND($E9="biweekly",6<=$D9,MOD(6-$C9,2)=0))),Flows!$C10,0)) | L9: =IF(OR($A9="",Flows!$C10=""),0,IF(AND(7<=Setup!$B$5,7>=$C9,OR(AND($E9="once",7=$C9),AND($E9="weekly",7<=$D9),AND($E9="biweekly",7<=$D9,MOD(7-$C9,2)=0))),Flows!$C10,0)) | M9: =IF(OR($A9="",Flows!$C10=""),0,IF(AND(8<=Setup!$B$5,8>=$C9,OR(AND($E9="once",8=$C9),AND($E9="weekly",8<=$D9),AND($E9="biweekly",8<=$D9,MOD(8-$C9,2)=0))),Flows!$C10,0)) | N9: =IF(OR($A9="",Flows!$C10=""),0,IF(AND(9<=Setup!$B$5,9>=$C9,OR(AND($E9="once",9=$C9),AND($E9="weekly",9<=$D9),AND($E9="biweekly",9<=$D9,MOD(9-$C9,2)=0))),Flows!$C10,0)) | O9: =IF(OR($A9="",Flows!$C10=""),0,IF(AND(10<=Setup!$B$5,10>=$C9,OR(AND($E9="once",10=$C9),AND($E9="weekly",10<=$D9),AND($E9="biweekly",10<=$D9,MOD(10-$C9,2)=0))),Flows!$C10,0)) | P9: =IF(OR($A9="",Flows!$C10=""),0,IF(AND(11<=Setup!$B$5,11>=$C9,OR(AND($E9="once",11=$C9),AND($E9="weekly",11<=$D9),AND($E9="biweekly",11<=$D9,MOD(11-$C9,2)=0))),Flows!$C10,0)) | Q9: =IF(OR($A9="",Flows!$C10=""),0,IF(AND(12<=Setup!$B$5,12>=$C9,OR(AND($E9="once",12=$C9),AND($E9="weekly",12<=$D9),AND($E9="biweekly",12<=$D9,MOD(12-$C9,2)=0))),Flows!$C10,0)) | R9: =IF(OR($A9="",Flows!$C10=""),0,IF(AND(13<=Setup!$B$5,13>=$C9,OR(AND($E9="once",13=$C9),AND($E9="weekly",13<=$D9),AND($E9="biweekly",13<=$D9,MOD(13-$C9,2)=0))),Flows!$C10,0)) | S9: =IF(OR($A9="",Flows!$C10=""),0,IF(AND(14<=Setup!$B$5,14>=$C9,OR(AND($E9="once",14=$C9),AND($E9="weekly",14<=$D9),AND($E9="biweekly",14<=$D9,MOD(14-$C9,2)=0))),Flows!$C10,0)) | T9: =IF(OR($A9="",Flows!$C10=""),0,IF(AND(15<=Setup!$B$5,15>=$C9,OR(AND($E9="once",15=$C9),AND($E9="weekly",15<=$D9),AND($E9="biweekly",15<=$D9,MOD(15-$C9,2)=0))),Flows!$C10,0)) | U9: =IF(OR($A9="",Flows!$C10=""),0,IF(AND(16<=Setup!$B$5,16>=$C9,OR(AND($E9="once",16=$C9),AND($E9="weekly",16<=$D9),AND($E9="biweekly",16<=$D9,MOD(16-$C9,2)=0))),Flows!$C10,0)) | V9: =IF(OR($A9="",Flows!$C10=""),0,IF(AND(17<=Setup!$B$5,17>=$C9,OR(AND($E9="once",17=$C9),AND($E9="weekly",17<=$D9),AND($E9="biweekly",17<=$D9,MOD(17-$C9,2)=0))),Flows!$C10,0)) | W9: =IF(OR($A9="",Flows!$C10=""),0,IF(AND(18<=Setup!$B$5,18>=$C9,OR(AND($E9="once",18=$C9),AND($E9="weekly",18<=$D9),AND($E9="biweekly",18<=$D9,MOD(18-$C9,2)=0))),Flows!$C10,0)) | X9: =IF(OR($A9="",Flows!$C10=""),0,IF(AND(19<=Setup!$B$5,19>=$C9,OR(AND($E9="once",19=$C9),AND($E9="weekly",19<=$D9),AND($E9="biweekly",19<=$D9,MOD(19-$C9,2)=0))),Flows!$C10,0)) | Y9: =IF(OR($A9="",Flows!$C10=""),0,IF(AND(20<=Setup!$B$5,20>=$C9,OR(AND($E9="once",20=$C9),AND($E9="weekly",20<=$D9),AND($E9="biweekly",20<=$D9,MOD(20-$C9,2)=0))),Flows!$C10,0)) | Z9: =IF(OR($A9="",Flows!$C10=""),0,IF(AND(21<=Setup!$B$5,21>=$C9,OR(AND($E9="once",21=$C9),AND($E9="weekly",21<=$D9),AND($E9="biweekly",21<=$D9,MOD(21-$C9,2)=0))),Flows!$C10,0)) | AA9: =IF(OR($A9="",Flows!$C10=""),0,IF(AND(22<=Setup!$B$5,22>=$C9,OR(AND($E9="once",22=$C9),AND($E9="weekly",22<=$D9),AND($E9="biweekly",22<=$D9,MOD(22-$C9,2)=0))),Flows!$C10,0)) | AB9: =IF(OR($A9="",Flows!$C10=""),0,IF(AND(23<=Setup!$B$5,23>=$C9,OR(AND($E9="once",23=$C9),AND($E9="weekly",23<=$D9),AND($E9="biweekly",23<=$D9,MOD(23-$C9,2)=0))),Flows!$C10,0)) | AC9: =IF(OR($A9="",Flows!$C10=""),0,IF(AND(24<=Setup!$B$5,24>=$C9,OR(AND($E9="once",24=$C9),AND($E9="weekly",24<=$D9),AND($E9="biweekly",24<=$D9,MOD(24-$C9,2)=0))),Flows!$C10,0)) | AD9: =IF(OR($A9="",Flows!$C10=""),0,IF(AND(25<=Setup!$B$5,25>=$C9,OR(AND($E9="once",25=$C9),AND($E9="weekly",25<=$D9),AND($E9="biweekly",25<=$D9,MOD(25-$C9,2)=0))),Flows!$C10,0)) | AE9: =IF(OR($A9="",Flows!$C10=""),0,IF(AND(26<=Setup!$B$5,26>=$C9,OR(AND($E9="once",26=$C9),AND($E9="weekly",26<=$D9),AND($E9="biweekly",26<=$D9,MOD(26-$C9,2)=0))),Flows!$C10,0)) | AF9: =IF(OR($A9="",Flows!$C10=""),0,IF(AND(27<=Setup!$B$5,27>=$C9,OR(AND($E9="once",27=$C9),AND($E9="weekly",27<=$D9),AND($E9="biweekly",27<=$D9,MOD(27-$C9,2)=0))),Flows!$C10,0)) | AG9: =IF(OR($A9="",Flows!$C10=""),0,IF(AND(28<=Setup!$B$5,28>=$C9,OR(AND($E9="once",28=$C9),AND($E9="weekly",28<=$D9),AND($E9="biweekly",28<=$D9,MOD(28-$C9,2)=0))),Flows!$C10,0)) | AH9: =IF(OR($A9="",Flows!$C10=""),0,IF(AND(29<=Setup!$B$5,29>=$C9,OR(AND($E9="once",29=$C9),AND($E9="weekly",29<=$D9),AND($E9="biweekly",29<=$D9,MOD(29-$C9,2)=0))),Flows!$C10,0)) | AI9: =IF(OR($A9="",Flows!$C10=""),0,IF(AND(30<=Setup!$B$5,30>=$C9,OR(AND($E9="once",30=$C9),AND($E9="weekly",30<=$D9),AND($E9="biweekly",30<=$D9,MOD(30-$C9,2)=0))),Flows!$C10,0)) | AJ9: =IF(OR($A9="",Flows!$C10=""),0,IF(AND(31<=Setup!$B$5,31>=$C9,OR(AND($E9="once",31=$C9),AND($E9="weekly",31<=$D9),AND($E9="biweekly",31<=$D9,MOD(31-$C9,2)=0))),Flows!$C10,0)) | AK9: =IF(OR($A9="",Flows!$C10=""),0,IF(AND(32<=Setup!$B$5,32>=$C9,OR(AND($E9="once",32=$C9),AND($E9="weekly",32<=$D9),AND($E9="biweekly",32<=$D9,MOD(32-$C9,2)=0))),Flows!$C10,0)) | AL9: =IF(OR($A9="",Flows!$C10=""),0,IF(AND(33<=Setup!$B$5,33>=$C9,OR(AND($E9="once",33=$C9),AND($E9="weekly",33<=$D9),AND($E9="biweekly",33<=$D9,MOD(33-$C9,2)=0))),Flows!$C10,0)) | AM9: =IF(OR($A9="",Flows!$C10=""),0,IF(AND(34<=Setup!$B$5,34>=$C9,OR(AND($E9="once",34=$C9),AND($E9="weekly",34<=$D9),AND($E9="biweekly",34<=$D9,MOD(34-$C9,2)=0))),Flows!$C10,0)) | AN9: =IF(OR($A9="",Flows!$C10=""),0,IF(AND(35<=Setup!$B$5,35>=$C9,OR(AND($E9="once",35=$C9),AND($E9="weekly",35<=$D9),AND($E9="biweekly",35<=$D9,MOD(35-$C9,2)=0))),Flows!$C10,0)) | AO9: =IF(OR($A9="",Flows!$C10=""),0,IF(AND(36<=Setup!$B$5,36>=$C9,OR(AND($E9="once",36=$C9),AND($E9="weekly",36<=$D9),AND($E9="biweekly",36<=$D9,MOD(36-$C9,2)=0))),Flows!$C10,0)) | AP9: =IF(OR($A9="",Flows!$C10=""),0,IF(AND(37<=Setup!$B$5,37>=$C9,OR(AND($E9="once",37=$C9),AND($E9="weekly",37<=$D9),AND($E9="biweekly",37<=$D9,MOD(37-$C9,2)=0))),Flows!$C10,0)) | AQ9: =IF(OR($A9="",Flows!$C10=""),0,IF(AND(38<=Setup!$B$5,38>=$C9,OR(AND($E9="once",38=$C9),AND($E9="weekly",38<=$D9),AND($E9="biweekly",38<=$D9,MOD(38-$C9,2)=0))),Flows!$C10,0)) | AR9: =IF(OR($A9="",Flows!$C10=""),0,IF(AND(39<=Setup!$B$5,39>=$C9,OR(AND($E9="once",39=$C9),AND($E9="weekly",39<=$D9),AND($E9="biweekly",39<=$D9,MOD(39-$C9,2)=0))),Flows!$C10,0)) | AS9: =IF(OR($A9="",Flows!$C10=""),0,IF(AND(40<=Setup!$B$5,40>=$C9,OR(AND($E9="once",40=$C9),AND($E9="weekly",40<=$D9),AND($E9="biweekly",40<=$D9,MOD(40-$C9,2)=0))),Flows!$C10,0)) | AT9: =IF(OR($A9="",Flows!$C10=""),0,IF(AND(41<=Setup!$B$5,41>=$C9,OR(AND($E9="once",41=$C9),AND($E9="weekly",41<=$D9),AND($E9="biweekly",41<=$D9,MOD(41-$C9,2)=0))),Flows!$C10,0)) | AU9: =IF(OR($A9="",Flows!$C10=""),0,IF(AND(42<=Setup!$B$5,42>=$C9,OR(AND($E9="once",42=$C9),AND($E9="weekly",42<=$D9),AND($E9="biweekly",42<=$D9,MOD(42-$C9,2)=0))),Flows!$C10,0)) | AV9: =IF(OR($A9="",Flows!$C10=""),0,IF(AND(43<=Setup!$B$5,43>=$C9,OR(AND($E9="once",43=$C9),AND($E9="weekly",43<=$D9),AND($E9="biweekly",43<=$D9,MOD(43-$C9,2)=0))),Flows!$C10,0)) | AW9: =IF(OR($A9="",Flows!$C10=""),0,IF(AND(44<=Setup!$B$5,44>=$C9,OR(AND($E9="once",44=$C9),AND($E9="weekly",44<=$D9),AND($E9="biweekly",44<=$D9,MOD(44-$C9,2)=0))),Flows!$C10,0)) | AX9: =IF(OR($A9="",Flows!$C10=""),0,IF(AND(45<=Setup!$B$5,45>=$C9,OR(AND($E9="once",45=$C9),AND($E9="weekly",45<=$D9),AND($E9="biweekly",45<=$D9,MOD(45-$C9,2)=0))),Flows!$C10,0)) | AY9: =IF(OR($A9="",Flows!$C10=""),0,IF(AND(46<=Setup!$B$5,46>=$C9,OR(AND($E9="once",46=$C9),AND($E9="weekly",46<=$D9),AND($E9="biweekly",46<=$D9,MOD(46-$C9,2)=0))),Flows!$C10,0)) | AZ9: =IF(OR($A9="",Flows!$C10=""),0,IF(AND(47<=Setup!$B$5,47>=$C9,OR(AND($E9="once",47=$C9),AND($E9="weekly",47<=$D9),AND($E9="biweekly",47<=$D9,MOD(47-$C9,2)=0))),Flows!$C10,0)) | BA9: =IF(OR($A9="",Flows!$C10=""),0,IF(AND(48<=Setup!$B$5,48>=$C9,OR(AND($E9="once",48=$C9),AND($E9="weekly",48<=$D9),AND($E9="biweekly",48<=$D9,MOD(48-$C9,2)=0))),Flows!$C10,0)) | BB9: =IF(OR($A9="",Flows!$C10=""),0,IF(AND(49<=Setup!$B$5,49>=$C9,OR(AND($E9="once",49=$C9),AND($E9="weekly",49<=$D9),AND($E9="biweekly",49<=$D9,MOD(49-$C9,2)=0))),Flows!$C10,0)) | BC9: =IF(OR($A9="",Flows!$C10=""),0,IF(AND(50<=Setup!$B$5,50>=$C9,OR(AND($E9="once",50=$C9),AND($E9="weekly",50<=$D9),AND($E9="biweekly",50<=$D9,MOD(50-$C9,2)=0))),Flows!$C10,0)) | BD9: =IF(OR($A9="",Flows!$C10=""),0,IF(AND(51<=Setup!$B$5,51>=$C9,OR(AND($E9="once",51=$C9),AND($E9="weekly",51<=$D9),AND($E9="biweekly",51<=$D9,MOD(51-$C9,2)=0))),Flows!$C10,0)) | BE9: =IF(OR($A9="",Flows!$C10=""),0,IF(AND(52<=Setup!$B$5,52>=$C9,OR(AND($E9="once",52=$C9),AND($E9="weekly",52<=$D9),AND($E9="biweekly",52<=$D9,MOD(52-$C9,2)=0))),Flows!$C10,0))
A10: =IF(Flows!A11="","",LOWER(Flows!A11)) | B10: =IF(Flows!B11="","",Flows!B11) | C10: =N(Flows!D11) | D10: =IF(Flows!F11="",Setup!$B$5,Flows!F11) | E10: =IF(Flows!E11="","once",LOWER(Flows!E11)) | F10: =IF(OR($A10="",Flows!$C11=""),0,IF(AND(1<=Setup!$B$5,1>=$C10,OR(AND($E10="once",1=$C10),AND($E10="weekly",1<=$D10),AND($E10="biweekly",1<=$D10,MOD(1-$C10,2)=0))),Flows!$C11,0)) | G10: =IF(OR($A10="",Flows!$C11=""),0,IF(AND(2<=Setup!$B$5,2>=$C10,OR(AND($E10="once",2=$C10),AND($E10="weekly",2<=$D10),AND($E10="biweekly",2<=$D10,MOD(2-$C10,2)=0))),Flows!$C11,0)) | H10: =IF(OR($A10="",Flows!$C11=""),0,IF(AND(3<=Setup!$B$5,3>=$C10,OR(AND($E10="once",3=$C10),AND($E10="weekly",3<=$D10),AND($E10="biweekly",3<=$D10,MOD(3-$C10,2)=0))),Flows!$C11,0)) | I10: =IF(OR($A10="",Flows!$C11=""),0,IF(AND(4<=Setup!$B$5,4>=$C10,OR(AND($E10="once",4=$C10),AND($E10="weekly",4<=$D10),AND($E10="biweekly",4<=$D10,MOD(4-$C10,2)=0))),Flows!$C11,0)) | J10: =IF(OR($A10="",Flows!$C11=""),0,IF(AND(5<=Setup!$B$5,5>=$C10,OR(AND($E10="once",5=$C10),AND($E10="weekly",5<=$D10),AND($E10="biweekly",5<=$D10,MOD(5-$C10,2)=0))),Flows!$C11,0)) | K10: =IF(OR($A10="",Flows!$C11=""),0,IF(AND(6<=Setup!$B$5,6>=$C10,OR(AND($E10="once",6=$C10),AND($E10="weekly",6<=$D10),AND($E10="biweekly",6<=$D10,MOD(6-$C10,2)=0))),Flows!$C11,0)) | L10: =IF(OR($A10="",Flows!$C11=""),0,IF(AND(7<=Setup!$B$5,7>=$C10,OR(AND($E10="once",7=$C10),AND($E10="weekly",7<=$D10),AND($E10="biweekly",7<=$D10,MOD(7-$C10,2)=0))),Flows!$C11,0)) | M10: =IF(OR($A10="",Flows!$C11=""),0,IF(AND(8<=Setup!$B$5,8>=$C10,OR(AND($E10="once",8=$C10),AND($E10="weekly",8<=$D10),AND($E10="biweekly",8<=$D10,MOD(8-$C10,2)=0))),Flows!$C11,0)) | N10: =IF(OR($A10="",Flows!$C11=""),0,IF(AND(9<=Setup!$B$5,9>=$C10,OR(AND($E10="once",9=$C10),AND($E10="weekly",9<=$D10),AND($E10="biweekly",9<=$D10,MOD(9-$C10,2)=0))),Flows!$C11,0)) | O10: =IF(OR($A10="",Flows!$C11=""),0,IF(AND(10<=Setup!$B$5,10>=$C10,OR(AND($E10="once",10=$C10),AND($E10="weekly",10<=$D10),AND($E10="biweekly",10<=$D10,MOD(10-$C10,2)=0))),Flows!$C11,0)) | P10: =IF(OR($A10="",Flows!$C11=""),0,IF(AND(11<=Setup!$B$5,11>=$C10,OR(AND($E10="once",11=$C10),AND($E10="weekly",11<=$D10),AND($E10="biweekly",11<=$D10,MOD(11-$C10,2)=0))),Flows!$C11,0)) | Q10: =IF(OR($A10="",Flows!$C11=""),0,IF(AND(12<=Setup!$B$5,12>=$C10,OR(AND($E10="once",12=$C10),AND($E10="weekly",12<=$D10),AND($E10="biweekly",12<=$D10,MOD(12-$C10,2)=0))),Flows!$C11,0)) | R10: =IF(OR($A10="",Flows!$C11=""),0,IF(AND(13<=Setup!$B$5,13>=$C10,OR(AND($E10="once",13=$C10),AND($E10="weekly",13<=$D10),AND($E10="biweekly",13<=$D10,MOD(13-$C10,2)=0))),Flows!$C11,0)) | S10: =IF(OR($A10="",Flows!$C11=""),0,IF(AND(14<=Setup!$B$5,14>=$C10,OR(AND($E10="once",14=$C10),AND($E10="weekly",14<=$D10),AND($E10="biweekly",14<=$D10,MOD(14-$C10,2)=0))),Flows!$C11,0)) | T10: =IF(OR($A10="",Flows!$C11=""),0,IF(AND(15<=Setup!$B$5,15>=$C10,OR(AND($E10="once",15=$C10),AND($E10="weekly",15<=$D10),AND($E10="biweekly",15<=$D10,MOD(15-$C10,2)=0))),Flows!$C11,0)) | U10: =IF(OR($A10="",Flows!$C11=""),0,IF(AND(16<=Setup!$B$5,16>=$C10,OR(AND($E10="once",16=$C10),AND($E10="weekly",16<=$D10),AND($E10="biweekly",16<=$D10,MOD(16-$C10,2)=0))),Flows!$C11,0)) | V10: =IF(OR($A10="",Flows!$C11=""),0,IF(AND(17<=Setup!$B$5,17>=$C10,OR(AND($E10="once",17=$C10),AND($E10="weekly",17<=$D10),AND($E10="biweekly",17<=$D10,MOD(17-$C10,2)=0))),Flows!$C11,0)) | W10: =IF(OR($A10="",Flows!$C11=""),0,IF(AND(18<=Setup!$B$5,18>=$C10,OR(AND($E10="once",18=$C10),AND($E10="weekly",18<=$D10),AND($E10="biweekly",18<=$D10,MOD(18-$C10,2)=0))),Flows!$C11,0)) | X10: =IF(OR($A10="",Flows!$C11=""),0,IF(AND(19<=Setup!$B$5,19>=$C10,OR(AND($E10="once",19=$C10),AND($E10="weekly",19<=$D10),AND($E10="biweekly",19<=$D10,MOD(19-$C10,2)=0))),Flows!$C11,0)) | Y10: =IF(OR($A10="",Flows!$C11=""),0,IF(AND(20<=Setup!$B$5,20>=$C10,OR(AND($E10="once",20=$C10),AND($E10="weekly",20<=$D10),AND($E10="biweekly",20<=$D10,MOD(20-$C10,2)=0))),Flows!$C11,0)) | Z10: =IF(OR($A10="",Flows!$C11=""),0,IF(AND(21<=Setup!$B$5,21>=$C10,OR(AND($E10="once",21=$C10),AND($E10="weekly",21<=$D10),AND($E10="biweekly",21<=$D10,MOD(21-$C10,2)=0))),Flows!$C11,0)) | AA10: =IF(OR($A10="",Flows!$C11=""),0,IF(AND(22<=Setup!$B$5,22>=$C10,OR(AND($E10="once",22=$C10),AND($E10="weekly",22<=$D10),AND($E10="biweekly",22<=$D10,MOD(22-$C10,2)=0))),Flows!$C11,0)) | AB10: =IF(OR($A10="",Flows!$C11=""),0,IF(AND(23<=Setup!$B$5,23>=$C10,OR(AND($E10="once",23=$C10),AND($E10="weekly",23<=$D10),AND($E10="biweekly",23<=$D10,MOD(23-$C10,2)=0))),Flows!$C11,0)) | AC10: =IF(OR($A10="",Flows!$C11=""),0,IF(AND(24<=Setup!$B$5,24>=$C10,OR(AND($E10="once",24=$C10),AND($E10="weekly",24<=$D10),AND($E10="biweekly",24<=$D10,MOD(24-$C10,2)=0))),Flows!$C11,0)) | AD10: =IF(OR($A10="",Flows!$C11=""),0,IF(AND(25<=Setup!$B$5,25>=$C10,OR(AND($E10="once",25=$C10),AND($E10="weekly",25<=$D10),AND($E10="biweekly",25<=$D10,MOD(25-$C10,2)=0))),Flows!$C11,0)) | AE10: =IF(OR($A10="",Flows!$C11=""),0,IF(AND(26<=Setup!$B$5,26>=$C10,OR(AND($E10="once",26=$C10),AND($E10="weekly",26<=$D10),AND($E10="biweekly",26<=$D10,MOD(26-$C10,2)=0))),Flows!$C11,0)) | AF10: =IF(OR($A10="",Flows!$C11=""),0,IF(AND(27<=Setup!$B$5,27>=$C10,OR(AND($E10="once",27=$C10),AND($E10="weekly",27<=$D10),AND($E10="biweekly",27<=$D10,MOD(27-$C10,2)=0))),Flows!$C11,0)) | AG10: =IF(OR($A10="",Flows!$C11=""),0,IF(AND(28<=Setup!$B$5,28>=$C10,OR(AND($E10="once",28=$C10),AND($E10="weekly",28<=$D10),AND($E10="biweekly",28<=$D10,MOD(28-$C10,2)=0))),Flows!$C11,0)) | AH10: =IF(OR($A10="",Flows!$C11=""),0,IF(AND(29<=Setup!$B$5,29>=$C10,OR(AND($E10="once",29=$C10),AND($E10="weekly",29<=$D10),AND($E10="biweekly",29<=$D10,MOD(29-$C10,2)=0))),Flows!$C11,0)) | AI10: =IF(OR($A10="",Flows!$C11=""),0,IF(AND(30<=Setup!$B$5,30>=$C10,OR(AND($E10="once",30=$C10),AND($E10="weekly",30<=$D10),AND($E10="biweekly",30<=$D10,MOD(30-$C10,2)=0))),Flows!$C11,0)) | AJ10: =IF(OR($A10="",Flows!$C11=""),0,IF(AND(31<=Setup!$B$5,31>=$C10,OR(AND($E10="once",31=$C10),AND($E10="weekly",31<=$D10),AND($E10="biweekly",31<=$D10,MOD(31-$C10,2)=0))),Flows!$C11,0)) | AK10: =IF(OR($A10="",Flows!$C11=""),0,IF(AND(32<=Setup!$B$5,32>=$C10,OR(AND($E10="once",32=$C10),AND($E10="weekly",32<=$D10),AND($E10="biweekly",32<=$D10,MOD(32-$C10,2)=0))),Flows!$C11,0)) | AL10: =IF(OR($A10="",Flows!$C11=""),0,IF(AND(33<=Setup!$B$5,33>=$C10,OR(AND($E10="once",33=$C10),AND($E10="weekly",33<=$D10),AND($E10="biweekly",33<=$D10,MOD(33-$C10,2)=0))),Flows!$C11,0)) | AM10: =IF(OR($A10="",Flows!$C11=""),0,IF(AND(34<=Setup!$B$5,34>=$C10,OR(AND($E10="once",34=$C10),AND($E10="weekly",34<=$D10),AND($E10="biweekly",34<=$D10,MOD(34-$C10,2)=0))),Flows!$C11,0)) | AN10: =IF(OR($A10="",Flows!$C11=""),0,IF(AND(35<=Setup!$B$5,35>=$C10,OR(AND($E10="once",35=$C10),AND($E10="weekly",35<=$D10),AND($E10="biweekly",35<=$D10,MOD(35-$C10,2)=0))),Flows!$C11,0)) | AO10: =IF(OR($A10="",Flows!$C11=""),0,IF(AND(36<=Setup!$B$5,36>=$C10,OR(AND($E10="once",36=$C10),AND($E10="weekly",36<=$D10),AND($E10="biweekly",36<=$D10,MOD(36-$C10,2)=0))),Flows!$C11,0)) | AP10: =IF(OR($A10="",Flows!$C11=""),0,IF(AND(37<=Setup!$B$5,37>=$C10,OR(AND($E10="once",37=$C10),AND($E10="weekly",37<=$D10),AND($E10="biweekly",37<=$D10,MOD(37-$C10,2)=0))),Flows!$C11,0)) | AQ10: =IF(OR($A10="",Flows!$C11=""),0,IF(AND(38<=Setup!$B$5,38>=$C10,OR(AND($E10="once",38=$C10),AND($E10="weekly",38<=$D10),AND($E10="biweekly",38<=$D10,MOD(38-$C10,2)=0))),Flows!$C11,0)) | AR10: =IF(OR($A10="",Flows!$C11=""),0,IF(AND(39<=Setup!$B$5,39>=$C10,OR(AND($E10="once",39=$C10),AND($E10="weekly",39<=$D10),AND($E10="biweekly",39<=$D10,MOD(39-$C10,2)=0))),Flows!$C11,0)) | AS10: =IF(OR($A10="",Flows!$C11=""),0,IF(AND(40<=Setup!$B$5,40>=$C10,OR(AND($E10="once",40=$C10),AND($E10="weekly",40<=$D10),AND($E10="biweekly",40<=$D10,MOD(40-$C10,2)=0))),Flows!$C11,0)) | AT10: =IF(OR($A10="",Flows!$C11=""),0,IF(AND(41<=Setup!$B$5,41>=$C10,OR(AND($E10="once",41=$C10),AND($E10="weekly",41<=$D10),AND($E10="biweekly",41<=$D10,MOD(41-$C10,2)=0))),Flows!$C11,0)) | AU10: =IF(OR($A10="",Flows!$C11=""),0,IF(AND(42<=Setup!$B$5,42>=$C10,OR(AND($E10="once",42=$C10),AND($E10="weekly",42<=$D10),AND($E10="biweekly",42<=$D10,MOD(42-$C10,2)=0))),Flows!$C11,0)) | AV10: =IF(OR($A10="",Flows!$C11=""),0,IF(AND(43<=Setup!$B$5,43>=$C10,OR(AND($E10="once",43=$C10),AND($E10="weekly",43<=$D10),AND($E10="biweekly",43<=$D10,MOD(43-$C10,2)=0))),Flows!$C11,0)) | AW10: =IF(OR($A10="",Flows!$C11=""),0,IF(AND(44<=Setup!$B$5,44>=$C10,OR(AND($E10="once",44=$C10),AND($E10="weekly",44<=$D10),AND($E10="biweekly",44<=$D10,MOD(44-$C10,2)=0))),Flows!$C11,0)) | AX10: =IF(OR($A10="",Flows!$C11=""),0,IF(AND(45<=Setup!$B$5,45>=$C10,OR(AND($E10="once",45=$C10),AND($E10="weekly",45<=$D10),AND($E10="biweekly",45<=$D10,MOD(45-$C10,2)=0))),Flows!$C11,0)) | AY10: =IF(OR($A10="",Flows!$C11=""),0,IF(AND(46<=Setup!$B$5,46>=$C10,OR(AND($E10="once",46=$C10),AND($E10="weekly",46<=$D10),AND($E10="biweekly",46<=$D10,MOD(46-$C10,2)=0))),Flows!$C11,0)) | AZ10: =IF(OR($A10="",Flows!$C11=""),0,IF(AND(47<=Setup!$B$5,47>=$C10,OR(AND($E10="once",47=$C10),AND($E10="weekly",47<=$D10),AND($E10="biweekly",47<=$D10,MOD(47-$C10,2)=0))),Flows!$C11,0)) | BA10: =IF(OR($A10="",Flows!$C11=""),0,IF(AND(48<=Setup!$B$5,48>=$C10,OR(AND($E10="once",48=$C10),AND($E10="weekly",48<=$D10),AND($E10="biweekly",48<=$D10,MOD(48-$C10,2)=0))),Flows!$C11,0)) | BB10: =IF(OR($A10="",Flows!$C11=""),0,IF(AND(49<=Setup!$B$5,49>=$C10,OR(AND($E10="once",49=$C10),AND($E10="weekly",49<=$D10),AND($E10="biweekly",49<=$D10,MOD(49-$C10,2)=0))),Flows!$C11,0)) | BC10: =IF(OR($A10="",Flows!$C11=""),0,IF(AND(50<=Setup!$B$5,50>=$C10,OR(AND($E10="once",50=$C10),AND($E10="weekly",50<=$D10),AND($E10="biweekly",50<=$D10,MOD(50-$C10,2)=0))),Flows!$C11,0)) | BD10: =IF(OR($A10="",Flows!$C11=""),0,IF(AND(51<=Setup!$B$5,51>=$C10,OR(AND($E10="once",51=$C10),AND($E10="weekly",51<=$D10),AND($E10="biweekly",51<=$D10,MOD(51-$C10,2)=0))),Flows!$C11,0)) | BE10: =IF(OR($A10="",Flows!$C11=""),0,IF(AND(52<=Setup!$B$5,52>=$C10,OR(AND($E10="once",52=$C10),AND($E10="weekly",52<=$D10),AND($E10="biweekly",52<=$D10,MOD(52-$C10,2)=0))),Flows!$C11,0))
A11: =IF(Flows!A12="","",LOWER(Flows!A12)) | B11: =IF(Flows!B12="","",Flows!B12) | C11: =N(Flows!D12) | D11: =IF(Flows!F12="",Setup!$B$5,Flows!F12) | E11: =IF(Flows!E12="","once",LOWER(Flows!E12)) | F11: =IF(OR($A11="",Flows!$C12=""),0,IF(AND(1<=Setup!$B$5,1>=$C11,OR(AND($E11="once",1=$C11),AND($E11="weekly",1<=$D11),AND($E11="biweekly",1<=$D11,MOD(1-$C11,2)=0))),Flows!$C12,0)) | G11: =IF(OR($A11="",Flows!$C12=""),0,IF(AND(2<=Setup!$B$5,2>=$C11,OR(AND($E11="once",2=$C11),AND($E11="weekly",2<=$D11),AND($E11="biweekly",2<=$D11,MOD(2-$C11,2)=0))),Flows!$C12,0)) | H11: =IF(OR($A11="",Flows!$C12=""),0,IF(AND(3<=Setup!$B$5,3>=$C11,OR(AND($E11="once",3=$C11),AND($E11="weekly",3<=$D11),AND($E11="biweekly",3<=$D11,MOD(3-$C11,2)=0))),Flows!$C12,0)) | I11: =IF(OR($A11="",Flows!$C12=""),0,IF(AND(4<=Setup!$B$5,4>=$C11,OR(AND($E11="once",4=$C11),AND($E11="weekly",4<=$D11),AND($E11="biweekly",4<=$D11,MOD(4-$C11,2)=0))),Flows!$C12,0)) | J11: =IF(OR($A11="",Flows!$C12=""),0,IF(AND(5<=Setup!$B$5,5>=$C11,OR(AND($E11="once",5=$C11),AND($E11="weekly",5<=$D11),AND($E11="biweekly",5<=$D11,MOD(5-$C11,2)=0))),Flows!$C12,0)) | K11: =IF(OR($A11="",Flows!$C12=""),0,IF(AND(6<=Setup!$B$5,6>=$C11,OR(AND($E11="once",6=$C11),AND($E11="weekly",6<=$D11),AND($E11="biweekly",6<=$D11,MOD(6-$C11,2)=0))),Flows!$C12,0)) | L11: =IF(OR($A11="",Flows!$C12=""),0,IF(AND(7<=Setup!$B$5,7>=$C11,OR(AND($E11="once",7=$C11),AND($E11="weekly",7<=$D11),AND($E11="biweekly",7<=$D11,MOD(7-$C11,2)=0))),Flows!$C12,0)) | M11: =IF(OR($A11="",Flows!$C12=""),0,IF(AND(8<=Setup!$B$5,8>=$C11,OR(AND($E11="once",8=$C11),AND($E11="weekly",8<=$D11),AND($E11="biweekly",8<=$D11,MOD(8-$C11,2)=0))),Flows!$C12,0)) | N11: =IF(OR($A11="",Flows!$C12=""),0,IF(AND(9<=Setup!$B$5,9>=$C11,OR(AND($E11="once",9=$C11),AND($E11="weekly",9<=$D11),AND($E11="biweekly",9<=$D11,MOD(9-$C11,2)=0))),Flows!$C12,0)) | O11: =IF(OR($A11="",Flows!$C12=""),0,IF(AND(10<=Setup!$B$5,10>=$C11,OR(AND($E11="once",10=$C11),AND($E11="weekly",10<=$D11),AND($E11="biweekly",10<=$D11,MOD(10-$C11,2)=0))),Flows!$C12,0)) | P11: =IF(OR($A11="",Flows!$C12=""),0,IF(AND(11<=Setup!$B$5,11>=$C11,OR(AND($E11="once",11=$C11),AND($E11="weekly",11<=$D11),AND($E11="biweekly",11<=$D11,MOD(11-$C11,2)=0))),Flows!$C12,0)) | Q11: =IF(OR($A11="",Flows!$C12=""),0,IF(AND(12<=Setup!$B$5,12>=$C11,OR(AND($E11="once",12=$C11),AND($E11="weekly",12<=$D11),AND($E11="biweekly",12<=$D11,MOD(12-$C11,2)=0))),Flows!$C12,0)) | R11: =IF(OR($A11="",Flows!$C12=""),0,IF(AND(13<=Setup!$B$5,13>=$C11,OR(AND($E11="once",13=$C11),AND($E11="weekly",13<=$D11),AND($E11="biweekly",13<=$D11,MOD(13-$C11,2)=0))),Flows!$C12,0)) | S11: =IF(OR($A11="",Flows!$C12=""),0,IF(AND(14<=Setup!$B$5,14>=$C11,OR(AND($E11="once",14=$C11),AND($E11="weekly",14<=$D11),AND($E11="biweekly",14<=$D11,MOD(14-$C11,2)=0))),Flows!$C12,0)) | T11: =IF(OR($A11="",Flows!$C12=""),0,IF(AND(15<=Setup!$B$5,15>=$C11,OR(AND($E11="once",15=$C11),AND($E11="weekly",15<=$D11),AND($E11="biweekly",15<=$D11,MOD(15-$C11,2)=0))),Flows!$C12,0)) | U11: =IF(OR($A11="",Flows!$C12=""),0,IF(AND(16<=Setup!$B$5,16>=$C11,OR(AND($E11="once",16=$C11),AND($E11="weekly",16<=$D11),AND($E11="biweekly",16<=$D11,MOD(16-$C11,2)=0))),Flows!$C12,0)) | V11: =IF(OR($A11="",Flows!$C12=""),0,IF(AND(17<=Setup!$B$5,17>=$C11,OR(AND($E11="once",17=$C11),AND($E11="weekly",17<=$D11),AND($E11="biweekly",17<=$D11,MOD(17-$C11,2)=0))),Flows!$C12,0)) | W11: =IF(OR($A11="",Flows!$C12=""),0,IF(AND(18<=Setup!$B$5,18>=$C11,OR(AND($E11="once",18=$C11),AND($E11="weekly",18<=$D11),AND($E11="biweekly",18<=$D11,MOD(18-$C11,2)=0))),Flows!$C12,0)) | X11: =IF(OR($A11="",Flows!$C12=""),0,IF(AND(19<=Setup!$B$5,19>=$C11,OR(AND($E11="once",19=$C11),AND($E11="weekly",19<=$D11),AND($E11="biweekly",19<=$D11,MOD(19-$C11,2)=0))),Flows!$C12,0)) | Y11: =IF(OR($A11="",Flows!$C12=""),0,IF(AND(20<=Setup!$B$5,20>=$C11,OR(AND($E11="once",20=$C11),AND($E11="weekly",20<=$D11),AND($E11="biweekly",20<=$D11,MOD(20-$C11,2)=0))),Flows!$C12,0)) | Z11: =IF(OR($A11="",Flows!$C12=""),0,IF(AND(21<=Setup!$B$5,21>=$C11,OR(AND($E11="once",21=$C11),AND($E11="weekly",21<=$D11),AND($E11="biweekly",21<=$D11,MOD(21-$C11,2)=0))),Flows!$C12,0)) | AA11: =IF(OR($A11="",Flows!$C12=""),0,IF(AND(22<=Setup!$B$5,22>=$C11,OR(AND($E11="once",22=$C11),AND($E11="weekly",22<=$D11),AND($E11="biweekly",22<=$D11,MOD(22-$C11,2)=0))),Flows!$C12,0)) | AB11: =IF(OR($A11="",Flows!$C12=""),0,IF(AND(23<=Setup!$B$5,23>=$C11,OR(AND($E11="once",23=$C11),AND($E11="weekly",23<=$D11),AND($E11="biweekly",23<=$D11,MOD(23-$C11,2)=0))),Flows!$C12,0)) | AC11: =IF(OR($A11="",Flows!$C12=""),0,IF(AND(24<=Setup!$B$5,24>=$C11,OR(AND($E11="once",24=$C11),AND($E11="weekly",24<=$D11),AND($E11="biweekly",24<=$D11,MOD(24-$C11,2)=0))),Flows!$C12,0)) | AD11: =IF(OR($A11="",Flows!$C12=""),0,IF(AND(25<=Setup!$B$5,25>=$C11,OR(AND($E11="once",25=$C11),AND($E11="weekly",25<=$D11),AND($E11="biweekly",25<=$D11,MOD(25-$C11,2)=0))),Flows!$C12,0)) | AE11: =IF(OR($A11="",Flows!$C12=""),0,IF(AND(26<=Setup!$B$5,26>=$C11,OR(AND($E11="once",26=$C11),AND($E11="weekly",26<=$D11),AND($E11="biweekly",26<=$D11,MOD(26-$C11,2)=0))),Flows!$C12,0)) | AF11: =IF(OR($A11="",Flows!$C12=""),0,IF(AND(27<=Setup!$B$5,27>=$C11,OR(AND($E11="once",27=$C11),AND($E11="weekly",27<=$D11),AND($E11="biweekly",27<=$D11,MOD(27-$C11,2)=0))),Flows!$C12,0)) | AG11: =IF(OR($A11="",Flows!$C12=""),0,IF(AND(28<=Setup!$B$5,28>=$C11,OR(AND($E11="once",28=$C11),AND($E11="weekly",28<=$D11),AND($E11="biweekly",28<=$D11,MOD(28-$C11,2)=0))),Flows!$C12,0)) | AH11: =IF(OR($A11="",Flows!$C12=""),0,IF(AND(29<=Setup!$B$5,29>=$C11,OR(AND($E11="once",29=$C11),AND($E11="weekly",29<=$D11),AND($E11="biweekly",29<=$D11,MOD(29-$C11,2)=0))),Flows!$C12,0)) | AI11: =IF(OR($A11="",Flows!$C12=""),0,IF(AND(30<=Setup!$B$5,30>=$C11,OR(AND($E11="once",30=$C11),AND($E11="weekly",30<=$D11),AND($E11="biweekly",30<=$D11,MOD(30-$C11,2)=0))),Flows!$C12,0)) | AJ11: =IF(OR($A11="",Flows!$C12=""),0,IF(AND(31<=Setup!$B$5,31>=$C11,OR(AND($E11="once",31=$C11),AND($E11="weekly",31<=$D11),AND($E11="biweekly",31<=$D11,MOD(31-$C11,2)=0))),Flows!$C12,0)) | AK11: =IF(OR($A11="",Flows!$C12=""),0,IF(AND(32<=Setup!$B$5,32>=$C11,OR(AND($E11="once",32=$C11),AND($E11="weekly",32<=$D11),AND($E11="biweekly",32<=$D11,MOD(32-$C11,2)=0))),Flows!$C12,0)) | AL11: =IF(OR($A11="",Flows!$C12=""),0,IF(AND(33<=Setup!$B$5,33>=$C11,OR(AND($E11="once",33=$C11),AND($E11="weekly",33<=$D11),AND($E11="biweekly",33<=$D11,MOD(33-$C11,2)=0))),Flows!$C12,0)) | AM11: =IF(OR($A11="",Flows!$C12=""),0,IF(AND(34<=Setup!$B$5,34>=$C11,OR(AND($E11="once",34=$C11),AND($E11="weekly",34<=$D11),AND($E11="biweekly",34<=$D11,MOD(34-$C11,2)=0))),Flows!$C12,0)) | AN11: =IF(OR($A11="",Flows!$C12=""),0,IF(AND(35<=Setup!$B$5,35>=$C11,OR(AND($E11="once",35=$C11),AND($E11="weekly",35<=$D11),AND($E11="biweekly",35<=$D11,MOD(35-$C11,2)=0))),Flows!$C12,0)) | AO11: =IF(OR($A11="",Flows!$C12=""),0,IF(AND(36<=Setup!$B$5,36>=$C11,OR(AND($E11="once",36=$C11),AND($E11="weekly",36<=$D11),AND($E11="biweekly",36<=$D11,MOD(36-$C11,2)=0))),Flows!$C12,0)) | AP11: =IF(OR($A11="",Flows!$C12=""),0,IF(AND(37<=Setup!$B$5,37>=$C11,OR(AND($E11="once",37=$C11),AND($E11="weekly",37<=$D11),AND($E11="biweekly",37<=$D11,MOD(37-$C11,2)=0))),Flows!$C12,0)) | AQ11: =IF(OR($A11="",Flows!$C12=""),0,IF(AND(38<=Setup!$B$5,38>=$C11,OR(AND($E11="once",38=$C11),AND($E11="weekly",38<=$D11),AND($E11="biweekly",38<=$D11,MOD(38-$C11,2)=0))),Flows!$C12,0)) | AR11: =IF(OR($A11="",Flows!$C12=""),0,IF(AND(39<=Setup!$B$5,39>=$C11,OR(AND($E11="once",39=$C11),AND($E11="weekly",39<=$D11),AND($E11="biweekly",39<=$D11,MOD(39-$C11,2)=0))),Flows!$C12,0)) | AS11: =IF(OR($A11="",Flows!$C12=""),0,IF(AND(40<=Setup!$B$5,40>=$C11,OR(AND($E11="once",40=$C11),AND($E11="weekly",40<=$D11),AND($E11="biweekly",40<=$D11,MOD(40-$C11,2)=0))),Flows!$C12,0)) | AT11: =IF(OR($A11="",Flows!$C12=""),0,IF(AND(41<=Setup!$B$5,41>=$C11,OR(AND($E11="once",41=$C11),AND($E11="weekly",41<=$D11),AND($E11="biweekly",41<=$D11,MOD(41-$C11,2)=0))),Flows!$C12,0)) | AU11: =IF(OR($A11="",Flows!$C12=""),0,IF(AND(42<=Setup!$B$5,42>=$C11,OR(AND($E11="once",42=$C11),AND($E11="weekly",42<=$D11),AND($E11="biweekly",42<=$D11,MOD(42-$C11,2)=0))),Flows!$C12,0)) | AV11: =IF(OR($A11="",Flows!$C12=""),0,IF(AND(43<=Setup!$B$5,43>=$C11,OR(AND($E11="once",43=$C11),AND($E11="weekly",43<=$D11),AND($E11="biweekly",43<=$D11,MOD(43-$C11,2)=0))),Flows!$C12,0)) | AW11: =IF(OR($A11="",Flows!$C12=""),0,IF(AND(44<=Setup!$B$5,44>=$C11,OR(AND($E11="once",44=$C11),AND($E11="weekly",44<=$D11),AND($E11="biweekly",44<=$D11,MOD(44-$C11,2)=0))),Flows!$C12,0)) | AX11: =IF(OR($A11="",Flows!$C12=""),0,IF(AND(45<=Setup!$B$5,45>=$C11,OR(AND($E11="once",45=$C11),AND($E11="weekly",45<=$D11),AND($E11="biweekly",45<=$D11,MOD(45-$C11,2)=0))),Flows!$C12,0)) | AY11: =IF(OR($A11="",Flows!$C12=""),0,IF(AND(46<=Setup!$B$5,46>=$C11,OR(AND($E11="once",46=$C11),AND($E11="weekly",46<=$D11),AND($E11="biweekly",46<=$D11,MOD(46-$C11,2)=0))),Flows!$C12,0)) | AZ11: =IF(OR($A11="",Flows!$C12=""),0,IF(AND(47<=Setup!$B$5,47>=$C11,OR(AND($E11="once",47=$C11),AND($E11="weekly",47<=$D11),AND($E11="biweekly",47<=$D11,MOD(47-$C11,2)=0))),Flows!$C12,0)) | BA11: =IF(OR($A11="",Flows!$C12=""),0,IF(AND(48<=Setup!$B$5,48>=$C11,OR(AND($E11="once",48=$C11),AND($E11="weekly",48<=$D11),AND($E11="biweekly",48<=$D11,MOD(48-$C11,2)=0))),Flows!$C12,0)) | BB11: =IF(OR($A11="",Flows!$C12=""),0,IF(AND(49<=Setup!$B$5,49>=$C11,OR(AND($E11="once",49=$C11),AND($E11="weekly",49<=$D11),AND($E11="biweekly",49<=$D11,MOD(49-$C11,2)=0))),Flows!$C12,0)) | BC11: =IF(OR($A11="",Flows!$C12=""),0,IF(AND(50<=Setup!$B$5,50>=$C11,OR(AND($E11="once",50=$C11),AND($E11="weekly",50<=$D11),AND($E11="biweekly",50<=$D11,MOD(50-$C11,2)=0))),Flows!$C12,0)) | BD11: =IF(OR($A11="",Flows!$C12=""),0,IF(AND(51<=Setup!$B$5,51>=$C11,OR(AND($E11="once",51=$C11),AND($E11="weekly",51<=$D11),AND($E11="biweekly",51<=$D11,MOD(51-$C11,2)=0))),Flows!$C12,0)) | BE11: =IF(OR($A11="",Flows!$C12=""),0,IF(AND(52<=Setup!$B$5,52>=$C11,OR(AND($E11="once",52=$C11),AND($E11="weekly",52<=$D11),AND($E11="biweekly",52<=$D11,MOD(52-$C11,2)=0))),Flows!$C12,0))
A12: =IF(Flows!A13="","",LOWER(Flows!A13)) | B12: =IF(Flows!B13="","",Flows!B13) | C12: =N(Flows!D13) | D12: =IF(Flows!F13="",Setup!$B$5,Flows!F13) | E12: =IF(Flows!E13="","once",LOWER(Flows!E13)) | F12: =IF(OR($A12="",Flows!$C13=""),0,IF(AND(1<=Setup!$B$5,1>=$C12,OR(AND($E12="once",1=$C12),AND($E12="weekly",1<=$D12),AND($E12="biweekly",1<=$D12,MOD(1-$C12,2)=0))),Flows!$C13,0)) | G12: =IF(OR($A12="",Flows!$C13=""),0,IF(AND(2<=Setup!$B$5,2>=$C12,OR(AND($E12="once",2=$C12),AND($E12="weekly",2<=$D12),AND($E12="biweekly",2<=$D12,MOD(2-$C12,2)=0))),Flows!$C13,0)) | H12: =IF(OR($A12="",Flows!$C13=""),0,IF(AND(3<=Setup!$B$5,3>=$C12,OR(AND($E12="once",3=$C12),AND($E12="weekly",3<=$D12),AND($E12="biweekly",3<=$D12,MOD(3-$C12,2)=0))),Flows!$C13,0)) | I12: =IF(OR($A12="",Flows!$C13=""),0,IF(AND(4<=Setup!$B$5,4>=$C12,OR(AND($E12="once",4=$C12),AND($E12="weekly",4<=$D12),AND($E12="biweekly",4<=$D12,MOD(4-$C12,2)=0))),Flows!$C13,0)) | J12: =IF(OR($A12="",Flows!$C13=""),0,IF(AND(5<=Setup!$B$5,5>=$C12,OR(AND($E12="once",5=$C12),AND($E12="weekly",5<=$D12),AND($E12="biweekly",5<=$D12,MOD(5-$C12,2)=0))),Flows!$C13,0)) | K12: =IF(OR($A12="",Flows!$C13=""),0,IF(AND(6<=Setup!$B$5,6>=$C12,OR(AND($E12="once",6=$C12),AND($E12="weekly",6<=$D12),AND($E12="biweekly",6<=$D12,MOD(6-$C12,2)=0))),Flows!$C13,0)) | L12: =IF(OR($A12="",Flows!$C13=""),0,IF(AND(7<=Setup!$B$5,7>=$C12,OR(AND($E12="once",7=$C12),AND($E12="weekly",7<=$D12),AND($E12="biweekly",7<=$D12,MOD(7-$C12,2)=0))),Flows!$C13,0)) | M12: =IF(OR($A12="",Flows!$C13=""),0,IF(AND(8<=Setup!$B$5,8>=$C12,OR(AND($E12="once",8=$C12),AND($E12="weekly",8<=$D12),AND($E12="biweekly",8<=$D12,MOD(8-$C12,2)=0))),Flows!$C13,0)) | N12: =IF(OR($A12="",Flows!$C13=""),0,IF(AND(9<=Setup!$B$5,9>=$C12,OR(AND($E12="once",9=$C12),AND($E12="weekly",9<=$D12),AND($E12="biweekly",9<=$D12,MOD(9-$C12,2)=0))),Flows!$C13,0)) | O12: =IF(OR($A12="",Flows!$C13=""),0,IF(AND(10<=Setup!$B$5,10>=$C12,OR(AND($E12="once",10=$C12),AND($E12="weekly",10<=$D12),AND($E12="biweekly",10<=$D12,MOD(10-$C12,2)=0))),Flows!$C13,0)) | P12: =IF(OR($A12="",Flows!$C13=""),0,IF(AND(11<=Setup!$B$5,11>=$C12,OR(AND($E12="once",11=$C12),AND($E12="weekly",11<=$D12),AND($E12="biweekly",11<=$D12,MOD(11-$C12,2)=0))),Flows!$C13,0)) | Q12: =IF(OR($A12="",Flows!$C13=""),0,IF(AND(12<=Setup!$B$5,12>=$C12,OR(AND($E12="once",12=$C12),AND($E12="weekly",12<=$D12),AND($E12="biweekly",12<=$D12,MOD(12-$C12,2)=0))),Flows!$C13,0)) | R12: =IF(OR($A12="",Flows!$C13=""),0,IF(AND(13<=Setup!$B$5,13>=$C12,OR(AND($E12="once",13=$C12),AND($E12="weekly",13<=$D12),AND($E12="biweekly",13<=$D12,MOD(13-$C12,2)=0))),Flows!$C13,0)) | S12: =IF(OR($A12="",Flows!$C13=""),0,IF(AND(14<=Setup!$B$5,14>=$C12,OR(AND($E12="once",14=$C12),AND($E12="weekly",14<=$D12),AND($E12="biweekly",14<=$D12,MOD(14-$C12,2)=0))),Flows!$C13,0)) | T12: =IF(OR($A12="",Flows!$C13=""),0,IF(AND(15<=Setup!$B$5,15>=$C12,OR(AND($E12="once",15=$C12),AND($E12="weekly",15<=$D12),AND($E12="biweekly",15<=$D12,MOD(15-$C12,2)=0))),Flows!$C13,0)) | U12: =IF(OR($A12="",Flows!$C13=""),0,IF(AND(16<=Setup!$B$5,16>=$C12,OR(AND($E12="once",16=$C12),AND($E12="weekly",16<=$D12),AND($E12="biweekly",16<=$D12,MOD(16-$C12,2)=0))),Flows!$C13,0)) | V12: =IF(OR($A12="",Flows!$C13=""),0,IF(AND(17<=Setup!$B$5,17>=$C12,OR(AND($E12="once",17=$C12),AND($E12="weekly",17<=$D12),AND($E12="biweekly",17<=$D12,MOD(17-$C12,2)=0))),Flows!$C13,0)) | W12: =IF(OR($A12="",Flows!$C13=""),0,IF(AND(18<=Setup!$B$5,18>=$C12,OR(AND($E12="once",18=$C12),AND($E12="weekly",18<=$D12),AND($E12="biweekly",18<=$D12,MOD(18-$C12,2)=0))),Flows!$C13,0)) | X12: =IF(OR($A12="",Flows!$C13=""),0,IF(AND(19<=Setup!$B$5,19>=$C12,OR(AND($E12="once",19=$C12),AND($E12="weekly",19<=$D12),AND($E12="biweekly",19<=$D12,MOD(19-$C12,2)=0))),Flows!$C13,0)) | Y12: =IF(OR($A12="",Flows!$C13=""),0,IF(AND(20<=Setup!$B$5,20>=$C12,OR(AND($E12="once",20=$C12),AND($E12="weekly",20<=$D12),AND($E12="biweekly",20<=$D12,MOD(20-$C12,2)=0))),Flows!$C13,0)) | Z12: =IF(OR($A12="",Flows!$C13=""),0,IF(AND(21<=Setup!$B$5,21>=$C12,OR(AND($E12="once",21=$C12),AND($E12="weekly",21<=$D12),AND($E12="biweekly",21<=$D12,MOD(21-$C12,2)=0))),Flows!$C13,0)) | AA12: =IF(OR($A12="",Flows!$C13=""),0,IF(AND(22<=Setup!$B$5,22>=$C12,OR(AND($E12="once",22=$C12),AND($E12="weekly",22<=$D12),AND($E12="biweekly",22<=$D12,MOD(22-$C12,2)=0))),Flows!$C13,0)) | AB12: =IF(OR($A12="",Flows!$C13=""),0,IF(AND(23<=Setup!$B$5,23>=$C12,OR(AND($E12="once",23=$C12),AND($E12="weekly",23<=$D12),AND($E12="biweekly",23<=$D12,MOD(23-$C12,2)=0))),Flows!$C13,0)) | AC12: =IF(OR($A12="",Flows!$C13=""),0,IF(AND(24<=Setup!$B$5,24>=$C12,OR(AND($E12="once",24=$C12),AND($E12="weekly",24<=$D12),AND($E12="biweekly",24<=$D12,MOD(24-$C12,2)=0))),Flows!$C13,0)) | AD12: =IF(OR($A12="",Flows!$C13=""),0,IF(AND(25<=Setup!$B$5,25>=$C12,OR(AND($E12="once",25=$C12),AND($E12="weekly",25<=$D12),AND($E12="biweekly",25<=$D12,MOD(25-$C12,2)=0))),Flows!$C13,0)) | AE12: =IF(OR($A12="",Flows!$C13=""),0,IF(AND(26<=Setup!$B$5,26>=$C12,OR(AND($E12="once",26=$C12),AND($E12="weekly",26<=$D12),AND($E12="biweekly",26<=$D12,MOD(26-$C12,2)=0))),Flows!$C13,0)) | AF12: =IF(OR($A12="",Flows!$C13=""),0,IF(AND(27<=Setup!$B$5,27>=$C12,OR(AND($E12="once",27=$C12),AND($E12="weekly",27<=$D12),AND($E12="biweekly",27<=$D12,MOD(27-$C12,2)=0))),Flows!$C13,0)) | AG12: =IF(OR($A12="",Flows!$C13=""),0,IF(AND(28<=Setup!$B$5,28>=$C12,OR(AND($E12="once",28=$C12),AND($E12="weekly",28<=$D12),AND($E12="biweekly",28<=$D12,MOD(28-$C12,2)=0))),Flows!$C13,0)) | AH12: =IF(OR($A12="",Flows!$C13=""),0,IF(AND(29<=Setup!$B$5,29>=$C12,OR(AND($E12="once",29=$C12),AND($E12="weekly",29<=$D12),AND($E12="biweekly",29<=$D12,MOD(29-$C12,2)=0))),Flows!$C13,0)) | AI12: =IF(OR($A12="",Flows!$C13=""),0,IF(AND(30<=Setup!$B$5,30>=$C12,OR(AND($E12="once",30=$C12),AND($E12="weekly",30<=$D12),AND($E12="biweekly",30<=$D12,MOD(30-$C12,2)=0))),Flows!$C13,0)) | AJ12: =IF(OR($A12="",Flows!$C13=""),0,IF(AND(31<=Setup!$B$5,31>=$C12,OR(AND($E12="once",31=$C12),AND($E12="weekly",31<=$D12),AND($E12="biweekly",31<=$D12,MOD(31-$C12,2)=0))),Flows!$C13,0)) | AK12: =IF(OR($A12="",Flows!$C13=""),0,IF(AND(32<=Setup!$B$5,32>=$C12,OR(AND($E12="once",32=$C12),AND($E12="weekly",32<=$D12),AND($E12="biweekly",32<=$D12,MOD(32-$C12,2)=0))),Flows!$C13,0)) | AL12: =IF(OR($A12="",Flows!$C13=""),0,IF(AND(33<=Setup!$B$5,33>=$C12,OR(AND($E12="once",33=$C12),AND($E12="weekly",33<=$D12),AND($E12="biweekly",33<=$D12,MOD(33-$C12,2)=0))),Flows!$C13,0)) | AM12: =IF(OR($A12="",Flows!$C13=""),0,IF(AND(34<=Setup!$B$5,34>=$C12,OR(AND($E12="once",34=$C12),AND($E12="weekly",34<=$D12),AND($E12="biweekly",34<=$D12,MOD(34-$C12,2)=0))),Flows!$C13,0)) | AN12: =IF(OR($A12="",Flows!$C13=""),0,IF(AND(35<=Setup!$B$5,35>=$C12,OR(AND($E12="once",35=$C12),AND($E12="weekly",35<=$D12),AND($E12="biweekly",35<=$D12,MOD(35-$C12,2)=0))),Flows!$C13,0)) | AO12: =IF(OR($A12="",Flows!$C13=""),0,IF(AND(36<=Setup!$B$5,36>=$C12,OR(AND($E12="once",36=$C12),AND($E12="weekly",36<=$D12),AND($E12="biweekly",36<=$D12,MOD(36-$C12,2)=0))),Flows!$C13,0)) | AP12: =IF(OR($A12="",Flows!$C13=""),0,IF(AND(37<=Setup!$B$5,37>=$C12,OR(AND($E12="once",37=$C12),AND($E12="weekly",37<=$D12),AND($E12="biweekly",37<=$D12,MOD(37-$C12,2)=0))),Flows!$C13,0)) | AQ12: =IF(OR($A12="",Flows!$C13=""),0,IF(AND(38<=Setup!$B$5,38>=$C12,OR(AND($E12="once",38=$C12),AND($E12="weekly",38<=$D12),AND($E12="biweekly",38<=$D12,MOD(38-$C12,2)=0))),Flows!$C13,0)) | AR12: =IF(OR($A12="",Flows!$C13=""),0,IF(AND(39<=Setup!$B$5,39>=$C12,OR(AND($E12="once",39=$C12),AND($E12="weekly",39<=$D12),AND($E12="biweekly",39<=$D12,MOD(39-$C12,2)=0))),Flows!$C13,0)) | AS12: =IF(OR($A12="",Flows!$C13=""),0,IF(AND(40<=Setup!$B$5,40>=$C12,OR(AND($E12="once",40=$C12),AND($E12="weekly",40<=$D12),AND($E12="biweekly",40<=$D12,MOD(40-$C12,2)=0))),Flows!$C13,0)) | AT12: =IF(OR($A12="",Flows!$C13=""),0,IF(AND(41<=Setup!$B$5,41>=$C12,OR(AND($E12="once",41=$C12),AND($E12="weekly",41<=$D12),AND($E12="biweekly",41<=$D12,MOD(41-$C12,2)=0))),Flows!$C13,0)) | AU12: =IF(OR($A12="",Flows!$C13=""),0,IF(AND(42<=Setup!$B$5,42>=$C12,OR(AND($E12="once",42=$C12),AND($E12="weekly",42<=$D12),AND($E12="biweekly",42<=$D12,MOD(42-$C12,2)=0))),Flows!$C13,0)) | AV12: =IF(OR($A12="",Flows!$C13=""),0,IF(AND(43<=Setup!$B$5,43>=$C12,OR(AND($E12="once",43=$C12),AND($E12="weekly",43<=$D12),AND($E12="biweekly",43<=$D12,MOD(43-$C12,2)=0))),Flows!$C13,0)) | AW12: =IF(OR($A12="",Flows!$C13=""),0,IF(AND(44<=Setup!$B$5,44>=$C12,OR(AND($E12="once",44=$C12),AND($E12="weekly",44<=$D12),AND($E12="biweekly",44<=$D12,MOD(44-$C12,2)=0))),Flows!$C13,0)) | AX12: =IF(OR($A12="",Flows!$C13=""),0,IF(AND(45<=Setup!$B$5,45>=$C12,OR(AND($E12="once",45=$C12),AND($E12="weekly",45<=$D12),AND($E12="biweekly",45<=$D12,MOD(45-$C12,2)=0))),Flows!$C13,0)) | AY12: =IF(OR($A12="",Flows!$C13=""),0,IF(AND(46<=Setup!$B$5,46>=$C12,OR(AND($E12="once",46=$C12),AND($E12="weekly",46<=$D12),AND($E12="biweekly",46<=$D12,MOD(46-$C12,2)=0))),Flows!$C13,0)) | AZ12: =IF(OR($A12="",Flows!$C13=""),0,IF(AND(47<=Setup!$B$5,47>=$C12,OR(AND($E12="once",47=$C12),AND($E12="weekly",47<=$D12),AND($E12="biweekly",47<=$D12,MOD(47-$C12,2)=0))),Flows!$C13,0)) | BA12: =IF(OR($A12="",Flows!$C13=""),0,IF(AND(48<=Setup!$B$5,48>=$C12,OR(AND($E12="once",48=$C12),AND($E12="weekly",48<=$D12),AND($E12="biweekly",48<=$D12,MOD(48-$C12,2)=0))),Flows!$C13,0)) | BB12: =IF(OR($A12="",Flows!$C13=""),0,IF(AND(49<=Setup!$B$5,49>=$C12,OR(AND($E12="once",49=$C12),AND($E12="weekly",49<=$D12),AND($E12="biweekly",49<=$D12,MOD(49-$C12,2)=0))),Flows!$C13,0)) | BC12: =IF(OR($A12="",Flows!$C13=""),0,IF(AND(50<=Setup!$B$5,50>=$C12,OR(AND($E12="once",50=$C12),AND($E12="weekly",50<=$D12),AND($E12="biweekly",50<=$D12,MOD(50-$C12,2)=0))),Flows!$C13,0)) | BD12: =IF(OR($A12="",Flows!$C13=""),0,IF(AND(51<=Setup!$B$5,51>=$C12,OR(AND($E12="once",51=$C12),AND($E12="weekly",51<=$D12),AND($E12="biweekly",51<=$D12,MOD(51-$C12,2)=0))),Flows!$C13,0)) | BE12: =IF(OR($A12="",Flows!$C13=""),0,IF(AND(52<=Setup!$B$5,52>=$C12,OR(AND($E12="once",52=$C12),AND($E12="weekly",52<=$D12),AND($E12="biweekly",52<=$D12,MOD(52-$C12,2)=0))),Flows!$C13,0))
A13: =IF(Flows!A14="","",LOWER(Flows!A14)) | B13: =IF(Flows!B14="","",Flows!B14) | C13: =N(Flows!D14) | D13: =IF(Flows!F14="",Setup!$B$5,Flows!F14) | E13: =IF(Flows!E14="","once",LOWER(Flows!E14)) | F13: =IF(OR($A13="",Flows!$C14=""),0,IF(AND(1<=Setup!$B$5,1>=$C13,OR(AND($E13="once",1=$C13),AND($E13="weekly",1<=$D13),AND($E13="biweekly",1<=$D13,MOD(1-$C13,2)=0))),Flows!$C14,0)) | G13: =IF(OR($A13="",Flows!$C14=""),0,IF(AND(2<=Setup!$B$5,2>=$C13,OR(AND($E13="once",2=$C13),AND($E13="weekly",2<=$D13),AND($E13="biweekly",2<=$D13,MOD(2-$C13,2)=0))),Flows!$C14,0)) | H13: =IF(OR($A13="",Flows!$C14=""),0,IF(AND(3<=Setup!$B$5,3>=$C13,OR(AND($E13="once",3=$C13),AND($E13="weekly",3<=$D13),AND($E13="biweekly",3<=$D13,MOD(3-$C13,2)=0))),Flows!$C14,0)) | I13: =IF(OR($A13="",Flows!$C14=""),0,IF(AND(4<=Setup!$B$5,4>=$C13,OR(AND($E13="once",4=$C13),AND($E13="weekly",4<=$D13),AND($E13="biweekly",4<=$D13,MOD(4-$C13,2)=0))),Flows!$C14,0)) | J13: =IF(OR($A13="",Flows!$C14=""),0,IF(AND(5<=Setup!$B$5,5>=$C13,OR(AND($E13="once",5=$C13),AND($E13="weekly",5<=$D13),AND($E13="biweekly",5<=$D13,MOD(5-$C13,2)=0))),Flows!$C14,0)) | K13: =IF(OR($A13="",Flows!$C14=""),0,IF(AND(6<=Setup!$B$5,6>=$C13,OR(AND($E13="once",6=$C13),AND($E13="weekly",6<=$D13),AND($E13="biweekly",6<=$D13,MOD(6-$C13,2)=0))),Flows!$C14,0)) | L13: =IF(OR($A13="",Flows!$C14=""),0,IF(AND(7<=Setup!$B$5,7>=$C13,OR(AND($E13="once",7=$C13),AND($E13="weekly",7<=$D13),AND($E13="biweekly",7<=$D13,MOD(7-$C13,2)=0))),Flows!$C14,0)) | M13: =IF(OR($A13="",Flows!$C14=""),0,IF(AND(8<=Setup!$B$5,8>=$C13,OR(AND($E13="once",8=$C13),AND($E13="weekly",8<=$D13),AND($E13="biweekly",8<=$D13,MOD(8-$C13,2)=0))),Flows!$C14,0)) | N13: =IF(OR($A13="",Flows!$C14=""),0,IF(AND(9<=Setup!$B$5,9>=$C13,OR(AND($E13="once",9=$C13),AND($E13="weekly",9<=$D13),AND($E13="biweekly",9<=$D13,MOD(9-$C13,2)=0))),Flows!$C14,0)) | O13: =IF(OR($A13="",Flows!$C14=""),0,IF(AND(10<=Setup!$B$5,10>=$C13,OR(AND($E13="once",10=$C13),AND($E13="weekly",10<=$D13),AND($E13="biweekly",10<=$D13,MOD(10-$C13,2)=0))),Flows!$C14,0)) | P13: =IF(OR($A13="",Flows!$C14=""),0,IF(AND(11<=Setup!$B$5,11>=$C13,OR(AND($E13="once",11=$C13),AND($E13="weekly",11<=$D13),AND($E13="biweekly",11<=$D13,MOD(11-$C13,2)=0))),Flows!$C14,0)) | Q13: =IF(OR($A13="",Flows!$C14=""),0,IF(AND(12<=Setup!$B$5,12>=$C13,OR(AND($E13="once",12=$C13),AND($E13="weekly",12<=$D13),AND($E13="biweekly",12<=$D13,MOD(12-$C13,2)=0))),Flows!$C14,0)) | R13: =IF(OR($A13="",Flows!$C14=""),0,IF(AND(13<=Setup!$B$5,13>=$C13,OR(AND($E13="once",13=$C13),AND($E13="weekly",13<=$D13),AND($E13="biweekly",13<=$D13,MOD(13-$C13,2)=0))),Flows!$C14,0)) | S13: =IF(OR($A13="",Flows!$C14=""),0,IF(AND(14<=Setup!$B$5,14>=$C13,OR(AND($E13="once",14=$C13),AND($E13="weekly",14<=$D13),AND($E13="biweekly",14<=$D13,MOD(14-$C13,2)=0))),Flows!$C14,0)) | T13: =IF(OR($A13="",Flows!$C14=""),0,IF(AND(15<=Setup!$B$5,15>=$C13,OR(AND($E13="once",15=$C13),AND($E13="weekly",15<=$D13),AND($E13="biweekly",15<=$D13,MOD(15-$C13,2)=0))),Flows!$C14,0)) | U13: =IF(OR($A13="",Flows!$C14=""),0,IF(AND(16<=Setup!$B$5,16>=$C13,OR(AND($E13="once",16=$C13),AND($E13="weekly",16<=$D13),AND($E13="biweekly",16<=$D13,MOD(16-$C13,2)=0))),Flows!$C14,0)) | V13: =IF(OR($A13="",Flows!$C14=""),0,IF(AND(17<=Setup!$B$5,17>=$C13,OR(AND($E13="once",17=$C13),AND($E13="weekly",17<=$D13),AND($E13="biweekly",17<=$D13,MOD(17-$C13,2)=0))),Flows!$C14,0)) | W13: =IF(OR($A13="",Flows!$C14=""),0,IF(AND(18<=Setup!$B$5,18>=$C13,OR(AND($E13="once",18=$C13),AND($E13="weekly",18<=$D13),AND($E13="biweekly",18<=$D13,MOD(18-$C13,2)=0))),Flows!$C14,0)) | X13: =IF(OR($A13="",Flows!$C14=""),0,IF(AND(19<=Setup!$B$5,19>=$C13,OR(AND($E13="once",19=$C13),AND($E13="weekly",19<=$D13),AND($E13="biweekly",19<=$D13,MOD(19-$C13,2)=0))),Flows!$C14,0)) | Y13: =IF(OR($A13="",Flows!$C14=""),0,IF(AND(20<=Setup!$B$5,20>=$C13,OR(AND($E13="once",20=$C13),AND($E13="weekly",20<=$D13),AND($E13="biweekly",20<=$D13,MOD(20-$C13,2)=0))),Flows!$C14,0)) | Z13: =IF(OR($A13="",Flows!$C14=""),0,IF(AND(21<=Setup!$B$5,21>=$C13,OR(AND($E13="once",21=$C13),AND($E13="weekly",21<=$D13),AND($E13="biweekly",21<=$D13,MOD(21-$C13,2)=0))),Flows!$C14,0)) | AA13: =IF(OR($A13="",Flows!$C14=""),0,IF(AND(22<=Setup!$B$5,22>=$C13,OR(AND($E13="once",22=$C13),AND($E13="weekly",22<=$D13),AND($E13="biweekly",22<=$D13,MOD(22-$C13,2)=0))),Flows!$C14,0)) | AB13: =IF(OR($A13="",Flows!$C14=""),0,IF(AND(23<=Setup!$B$5,23>=$C13,OR(AND($E13="once",23=$C13),AND($E13="weekly",23<=$D13),AND($E13="biweekly",23<=$D13,MOD(23-$C13,2)=0))),Flows!$C14,0)) | AC13: =IF(OR($A13="",Flows!$C14=""),0,IF(AND(24<=Setup!$B$5,24>=$C13,OR(AND($E13="once",24=$C13),AND($E13="weekly",24<=$D13),AND($E13="biweekly",24<=$D13,MOD(24-$C13,2)=0))),Flows!$C14,0)) | AD13: =IF(OR($A13="",Flows!$C14=""),0,IF(AND(25<=Setup!$B$5,25>=$C13,OR(AND($E13="once",25=$C13),AND($E13="weekly",25<=$D13),AND($E13="biweekly",25<=$D13,MOD(25-$C13,2)=0))),Flows!$C14,0)) | AE13: =IF(OR($A13="",Flows!$C14=""),0,IF(AND(26<=Setup!$B$5,26>=$C13,OR(AND($E13="once",26=$C13),AND($E13="weekly",26<=$D13),AND($E13="biweekly",26<=$D13,MOD(26-$C13,2)=0))),Flows!$C14,0)) | AF13: =IF(OR($A13="",Flows!$C14=""),0,IF(AND(27<=Setup!$B$5,27>=$C13,OR(AND($E13="once",27=$C13),AND($E13="weekly",27<=$D13),AND($E13="biweekly",27<=$D13,MOD(27-$C13,2)=0))),Flows!$C14,0)) | AG13: =IF(OR($A13="",Flows!$C14=""),0,IF(AND(28<=Setup!$B$5,28>=$C13,OR(AND($E13="once",28=$C13),AND($E13="weekly",28<=$D13),AND($E13="biweekly",28<=$D13,MOD(28-$C13,2)=0))),Flows!$C14,0)) | AH13: =IF(OR($A13="",Flows!$C14=""),0,IF(AND(29<=Setup!$B$5,29>=$C13,OR(AND($E13="once",29=$C13),AND($E13="weekly",29<=$D13),AND($E13="biweekly",29<=$D13,MOD(29-$C13,2)=0))),Flows!$C14,0)) | AI13: =IF(OR($A13="",Flows!$C14=""),0,IF(AND(30<=Setup!$B$5,30>=$C13,OR(AND($E13="once",30=$C13),AND($E13="weekly",30<=$D13),AND($E13="biweekly",30<=$D13,MOD(30-$C13,2)=0))),Flows!$C14,0)) | AJ13: =IF(OR($A13="",Flows!$C14=""),0,IF(AND(31<=Setup!$B$5,31>=$C13,OR(AND($E13="once",31=$C13),AND($E13="weekly",31<=$D13),AND($E13="biweekly",31<=$D13,MOD(31-$C13,2)=0))),Flows!$C14,0)) | AK13: =IF(OR($A13="",Flows!$C14=""),0,IF(AND(32<=Setup!$B$5,32>=$C13,OR(AND($E13="once",32=$C13),AND($E13="weekly",32<=$D13),AND($E13="biweekly",32<=$D13,MOD(32-$C13,2)=0))),Flows!$C14,0)) | AL13: =IF(OR($A13="",Flows!$C14=""),0,IF(AND(33<=Setup!$B$5,33>=$C13,OR(AND($E13="once",33=$C13),AND($E13="weekly",33<=$D13),AND($E13="biweekly",33<=$D13,MOD(33-$C13,2)=0))),Flows!$C14,0)) | AM13: =IF(OR($A13="",Flows!$C14=""),0,IF(AND(34<=Setup!$B$5,34>=$C13,OR(AND($E13="once",34=$C13),AND($E13="weekly",34<=$D13),AND($E13="biweekly",34<=$D13,MOD(34-$C13,2)=0))),Flows!$C14,0)) | AN13: =IF(OR($A13="",Flows!$C14=""),0,IF(AND(35<=Setup!$B$5,35>=$C13,OR(AND($E13="once",35=$C13),AND($E13="weekly",35<=$D13),AND($E13="biweekly",35<=$D13,MOD(35-$C13,2)=0))),Flows!$C14,0)) | AO13: =IF(OR($A13="",Flows!$C14=""),0,IF(AND(36<=Setup!$B$5,36>=$C13,OR(AND($E13="once",36=$C13),AND($E13="weekly",36<=$D13),AND($E13="biweekly",36<=$D13,MOD(36-$C13,2)=0))),Flows!$C14,0)) | AP13: =IF(OR($A13="",Flows!$C14=""),0,IF(AND(37<=Setup!$B$5,37>=$C13,OR(AND($E13="once",37=$C13),AND($E13="weekly",37<=$D13),AND($E13="biweekly",37<=$D13,MOD(37-$C13,2)=0))),Flows!$C14,0)) | AQ13: =IF(OR($A13="",Flows!$C14=""),0,IF(AND(38<=Setup!$B$5,38>=$C13,OR(AND($E13="once",38=$C13),AND($E13="weekly",38<=$D13),AND($E13="biweekly",38<=$D13,MOD(38-$C13,2)=0))),Flows!$C14,0)) | AR13: =IF(OR($A13="",Flows!$C14=""),0,IF(AND(39<=Setup!$B$5,39>=$C13,OR(AND($E13="once",39=$C13),AND($E13="weekly",39<=$D13),AND($E13="biweekly",39<=$D13,MOD(39-$C13,2)=0))),Flows!$C14,0)) | AS13: =IF(OR($A13="",Flows!$C14=""),0,IF(AND(40<=Setup!$B$5,40>=$C13,OR(AND($E13="once",40=$C13),AND($E13="weekly",40<=$D13),AND($E13="biweekly",40<=$D13,MOD(40-$C13,2)=0))),Flows!$C14,0)) | AT13: =IF(OR($A13="",Flows!$C14=""),0,IF(AND(41<=Setup!$B$5,41>=$C13,OR(AND($E13="once",41=$C13),AND($E13="weekly",41<=$D13),AND($E13="biweekly",41<=$D13,MOD(41-$C13,2)=0))),Flows!$C14,0)) | AU13: =IF(OR($A13="",Flows!$C14=""),0,IF(AND(42<=Setup!$B$5,42>=$C13,OR(AND($E13="once",42=$C13),AND($E13="weekly",42<=$D13),AND($E13="biweekly",42<=$D13,MOD(42-$C13,2)=0))),Flows!$C14,0)) | AV13: =IF(OR($A13="",Flows!$C14=""),0,IF(AND(43<=Setup!$B$5,43>=$C13,OR(AND($E13="once",43=$C13),AND($E13="weekly",43<=$D13),AND($E13="biweekly",43<=$D13,MOD(43-$C13,2)=0))),Flows!$C14,0)) | AW13: =IF(OR($A13="",Flows!$C14=""),0,IF(AND(44<=Setup!$B$5,44>=$C13,OR(AND($E13="once",44=$C13),AND($E13="weekly",44<=$D13),AND($E13="biweekly",44<=$D13,MOD(44-$C13,2)=0))),Flows!$C14,0)) | AX13: =IF(OR($A13="",Flows!$C14=""),0,IF(AND(45<=Setup!$B$5,45>=$C13,OR(AND($E13="once",45=$C13),AND($E13="weekly",45<=$D13),AND($E13="biweekly",45<=$D13,MOD(45-$C13,2)=0))),Flows!$C14,0)) | AY13: =IF(OR($A13="",Flows!$C14=""),0,IF(AND(46<=Setup!$B$5,46>=$C13,OR(AND($E13="once",46=$C13),AND($E13="weekly",46<=$D13),AND($E13="biweekly",46<=$D13,MOD(46-$C13,2)=0))),Flows!$C14,0)) | AZ13: =IF(OR($A13="",Flows!$C14=""),0,IF(AND(47<=Setup!$B$5,47>=$C13,OR(AND($E13="once",47=$C13),AND($E13="weekly",47<=$D13),AND($E13="biweekly",47<=$D13,MOD(47-$C13,2)=0))),Flows!$C14,0)) | BA13: =IF(OR($A13="",Flows!$C14=""),0,IF(AND(48<=Setup!$B$5,48>=$C13,OR(AND($E13="once",48=$C13),AND($E13="weekly",48<=$D13),AND($E13="biweekly",48<=$D13,MOD(48-$C13,2)=0))),Flows!$C14,0)) | BB13: =IF(OR($A13="",Flows!$C14=""),0,IF(AND(49<=Setup!$B$5,49>=$C13,OR(AND($E13="once",49=$C13),AND($E13="weekly",49<=$D13),AND($E13="biweekly",49<=$D13,MOD(49-$C13,2)=0))),Flows!$C14,0)) | BC13: =IF(OR($A13="",Flows!$C14=""),0,IF(AND(50<=Setup!$B$5,50>=$C13,OR(AND($E13="once",50=$C13),AND($E13="weekly",50<=$D13),AND($E13="biweekly",50<=$D13,MOD(50-$C13,2)=0))),Flows!$C14,0)) | BD13: =IF(OR($A13="",Flows!$C14=""),0,IF(AND(51<=Setup!$B$5,51>=$C13,OR(AND($E13="once",51=$C13),AND($E13="weekly",51<=$D13),AND($E13="biweekly",51<=$D13,MOD(51-$C13,2)=0))),Flows!$C14,0)) | BE13: =IF(OR($A13="",Flows!$C14=""),0,IF(AND(52<=Setup!$B$5,52>=$C13,OR(AND($E13="once",52=$C13),AND($E13="weekly",52<=$D13),AND($E13="biweekly",52<=$D13,MOD(52-$C13,2)=0))),Flows!$C14,0))
A14: =IF(Flows!A15="","",LOWER(Flows!A15)) | B14: =IF(Flows!B15="","",Flows!B15) | C14: =N(Flows!D15) | D14: =IF(Flows!F15="",Setup!$B$5,Flows!F15) | E14: =IF(Flows!E15="","once",LOWER(Flows!E15)) | F14: =IF(OR($A14="",Flows!$C15=""),0,IF(AND(1<=Setup!$B$5,1>=$C14,OR(AND($E14="once",1=$C14),AND($E14="weekly",1<=$D14),AND($E14="biweekly",1<=$D14,MOD(1-$C14,2)=0))),Flows!$C15,0)) | G14: =IF(OR($A14="",Flows!$C15=""),0,IF(AND(2<=Setup!$B$5,2>=$C14,OR(AND($E14="once",2=$C14),AND($E14="weekly",2<=$D14),AND($E14="biweekly",2<=$D14,MOD(2-$C14,2)=0))),Flows!$C15,0)) | H14: =IF(OR($A14="",Flows!$C15=""),0,IF(AND(3<=Setup!$B$5,3>=$C14,OR(AND($E14="once",3=$C14),AND($E14="weekly",3<=$D14),AND($E14="biweekly",3<=$D14,MOD(3-$C14,2)=0))),Flows!$C15,0)) | I14: =IF(OR($A14="",Flows!$C15=""),0,IF(AND(4<=Setup!$B$5,4>=$C14,OR(AND($E14="once",4=$C14),AND($E14="weekly",4<=$D14),AND($E14="biweekly",4<=$D14,MOD(4-$C14,2)=0))),Flows!$C15,0)) | J14: =IF(OR($A14="",Flows!$C15=""),0,IF(AND(5<=Setup!$B$5,5>=$C14,OR(AND($E14="once",5=$C14),AND($E14="weekly",5<=$D14),AND($E14="biweekly",5<=$D14,MOD(5-$C14,2)=0))),Flows!$C15,0)) | K14: =IF(OR($A14="",Flows!$C15=""),0,IF(AND(6<=Setup!$B$5,6>=$C14,OR(AND($E14="once",6=$C14),AND($E14="weekly",6<=$D14),AND($E14="biweekly",6<=$D14,MOD(6-$C14,2)=0))),Flows!$C15,0)) | L14: =IF(OR($A14="",Flows!$C15=""),0,IF(AND(7<=Setup!$B$5,7>=$C14,OR(AND($E14="once",7=$C14),AND($E14="weekly",7<=$D14),AND($E14="biweekly",7<=$D14,MOD(7-$C14,2)=0))),Flows!$C15,0)) | M14: =IF(OR($A14="",Flows!$C15=""),0,IF(AND(8<=Setup!$B$5,8>=$C14,OR(AND($E14="once",8=$C14),AND($E14="weekly",8<=$D14),AND($E14="biweekly",8<=$D14,MOD(8-$C14,2)=0))),Flows!$C15,0)) | N14: =IF(OR($A14="",Flows!$C15=""),0,IF(AND(9<=Setup!$B$5,9>=$C14,OR(AND($E14="once",9=$C14),AND($E14="weekly",9<=$D14),AND($E14="biweekly",9<=$D14,MOD(9-$C14,2)=0))),Flows!$C15,0)) | O14: =IF(OR($A14="",Flows!$C15=""),0,IF(AND(10<=Setup!$B$5,10>=$C14,OR(AND($E14="once",10=$C14),AND($E14="weekly",10<=$D14),AND($E14="biweekly",10<=$D14,MOD(10-$C14,2)=0))),Flows!$C15,0)) | P14: =IF(OR($A14="",Flows!$C15=""),0,IF(AND(11<=Setup!$B$5,11>=$C14,OR(AND($E14="once",11=$C14),AND($E14="weekly",11<=$D14),AND($E14="biweekly",11<=$D14,MOD(11-$C14,2)=0))),Flows!$C15,0)) | Q14: =IF(OR($A14="",Flows!$C15=""),0,IF(AND(12<=Setup!$B$5,12>=$C14,OR(AND($E14="once",12=$C14),AND($E14="weekly",12<=$D14),AND($E14="biweekly",12<=$D14,MOD(12-$C14,2)=0))),Flows!$C15,0)) | R14: =IF(OR($A14="",Flows!$C15=""),0,IF(AND(13<=Setup!$B$5,13>=$C14,OR(AND($E14="once",13=$C14),AND($E14="weekly",13<=$D14),AND($E14="biweekly",13<=$D14,MOD(13-$C14,2)=0))),Flows!$C15,0)) | S14: =IF(OR($A14="",Flows!$C15=""),0,IF(AND(14<=Setup!$B$5,14>=$C14,OR(AND($E14="once",14=$C14),AND($E14="weekly",14<=$D14),AND($E14="biweekly",14<=$D14,MOD(14-$C14,2)=0))),Flows!$C15,0)) | T14: =IF(OR($A14="",Flows!$C15=""),0,IF(AND(15<=Setup!$B$5,15>=$C14,OR(AND($E14="once",15=$C14),AND($E14="weekly",15<=$D14),AND($E14="biweekly",15<=$D14,MOD(15-$C14,2)=0))),Flows!$C15,0)) | U14: =IF(OR($A14="",Flows!$C15=""),0,IF(AND(16<=Setup!$B$5,16>=$C14,OR(AND($E14="once",16=$C14),AND($E14="weekly",16<=$D14),AND($E14="biweekly",16<=$D14,MOD(16-$C14,2)=0))),Flows!$C15,0)) | V14: =IF(OR($A14="",Flows!$C15=""),0,IF(AND(17<=Setup!$B$5,17>=$C14,OR(AND($E14="once",17=$C14),AND($E14="weekly",17<=$D14),AND($E14="biweekly",17<=$D14,MOD(17-$C14,2)=0))),Flows!$C15,0)) | W14: =IF(OR($A14="",Flows!$C15=""),0,IF(AND(18<=Setup!$B$5,18>=$C14,OR(AND($E14="once",18=$C14),AND($E14="weekly",18<=$D14),AND($E14="biweekly",18<=$D14,MOD(18-$C14,2)=0))),Flows!$C15,0)) | X14: =IF(OR($A14="",Flows!$C15=""),0,IF(AND(19<=Setup!$B$5,19>=$C14,OR(AND($E14="once",19=$C14),AND($E14="weekly",19<=$D14),AND($E14="biweekly",19<=$D14,MOD(19-$C14,2)=0))),Flows!$C15,0)) | Y14: =IF(OR($A14="",Flows!$C15=""),0,IF(AND(20<=Setup!$B$5,20>=$C14,OR(AND($E14="once",20=$C14),AND($E14="weekly",20<=$D14),AND($E14="biweekly",20<=$D14,MOD(20-$C14,2)=0))),Flows!$C15,0)) | Z14: =IF(OR($A14="",Flows!$C15=""),0,IF(AND(21<=Setup!$B$5,21>=$C14,OR(AND($E14="once",21=$C14),AND($E14="weekly",21<=$D14),AND($E14="biweekly",21<=$D14,MOD(21-$C14,2)=0))),Flows!$C15,0)) | AA14: =IF(OR($A14="",Flows!$C15=""),0,IF(AND(22<=Setup!$B$5,22>=$C14,OR(AND($E14="once",22=$C14),AND($E14="weekly",22<=$D14),AND($E14="biweekly",22<=$D14,MOD(22-$C14,2)=0))),Flows!$C15,0)) | AB14: =IF(OR($A14="",Flows!$C15=""),0,IF(AND(23<=Setup!$B$5,23>=$C14,OR(AND($E14="once",23=$C14),AND($E14="weekly",23<=$D14),AND($E14="biweekly",23<=$D14,MOD(23-$C14,2)=0))),Flows!$C15,0)) | AC14: =IF(OR($A14="",Flows!$C15=""),0,IF(AND(24<=Setup!$B$5,24>=$C14,OR(AND($E14="once",24=$C14),AND($E14="weekly",24<=$D14),AND($E14="biweekly",24<=$D14,MOD(24-$C14,2)=0))),Flows!$C15,0)) | AD14: =IF(OR($A14="",Flows!$C15=""),0,IF(AND(25<=Setup!$B$5,25>=$C14,OR(AND($E14="once",25=$C14),AND($E14="weekly",25<=$D14),AND($E14="biweekly",25<=$D14,MOD(25-$C14,2)=0))),Flows!$C15,0)) | AE14: =IF(OR($A14="",Flows!$C15=""),0,IF(AND(26<=Setup!$B$5,26>=$C14,OR(AND($E14="once",26=$C14),AND($E14="weekly",26<=$D14),AND($E14="biweekly",26<=$D14,MOD(26-$C14,2)=0))),Flows!$C15,0)) | AF14: =IF(OR($A14="",Flows!$C15=""),0,IF(AND(27<=Setup!$B$5,27>=$C14,OR(AND($E14="once",27=$C14),AND($E14="weekly",27<=$D14),AND($E14="biweekly",27<=$D14,MOD(27-$C14,2)=0))),Flows!$C15,0)) | AG14: =IF(OR($A14="",Flows!$C15=""),0,IF(AND(28<=Setup!$B$5,28>=$C14,OR(AND($E14="once",28=$C14),AND($E14="weekly",28<=$D14),AND($E14="biweekly",28<=$D14,MOD(28-$C14,2)=0))),Flows!$C15,0)) | AH14: =IF(OR($A14="",Flows!$C15=""),0,IF(AND(29<=Setup!$B$5,29>=$C14,OR(AND($E14="once",29=$C14),AND($E14="weekly",29<=$D14),AND($E14="biweekly",29<=$D14,MOD(29-$C14,2)=0))),Flows!$C15,0)) | AI14: =IF(OR($A14="",Flows!$C15=""),0,IF(AND(30<=Setup!$B$5,30>=$C14,OR(AND($E14="once",30=$C14),AND($E14="weekly",30<=$D14),AND($E14="biweekly",30<=$D14,MOD(30-$C14,2)=0))),Flows!$C15,0)) | AJ14: =IF(OR($A14="",Flows!$C15=""),0,IF(AND(31<=Setup!$B$5,31>=$C14,OR(AND($E14="once",31=$C14),AND($E14="weekly",31<=$D14),AND($E14="biweekly",31<=$D14,MOD(31-$C14,2)=0))),Flows!$C15,0)) | AK14: =IF(OR($A14="",Flows!$C15=""),0,IF(AND(32<=Setup!$B$5,32>=$C14,OR(AND($E14="once",32=$C14),AND($E14="weekly",32<=$D14),AND($E14="biweekly",32<=$D14,MOD(32-$C14,2)=0))),Flows!$C15,0)) | AL14: =IF(OR($A14="",Flows!$C15=""),0,IF(AND(33<=Setup!$B$5,33>=$C14,OR(AND($E14="once",33=$C14),AND($E14="weekly",33<=$D14),AND($E14="biweekly",33<=$D14,MOD(33-$C14,2)=0))),Flows!$C15,0)) | AM14: =IF(OR($A14="",Flows!$C15=""),0,IF(AND(34<=Setup!$B$5,34>=$C14,OR(AND($E14="once",34=$C14),AND($E14="weekly",34<=$D14),AND($E14="biweekly",34<=$D14,MOD(34-$C14,2)=0))),Flows!$C15,0)) | AN14: =IF(OR($A14="",Flows!$C15=""),0,IF(AND(35<=Setup!$B$5,35>=$C14,OR(AND($E14="once",35=$C14),AND($E14="weekly",35<=$D14),AND($E14="biweekly",35<=$D14,MOD(35-$C14,2)=0))),Flows!$C15,0)) | AO14: =IF(OR($A14="",Flows!$C15=""),0,IF(AND(36<=Setup!$B$5,36>=$C14,OR(AND($E14="once",36=$C14),AND($E14="weekly",36<=$D14),AND($E14="biweekly",36<=$D14,MOD(36-$C14,2)=0))),Flows!$C15,0)) | AP14: =IF(OR($A14="",Flows!$C15=""),0,IF(AND(37<=Setup!$B$5,37>=$C14,OR(AND($E14="once",37=$C14),AND($E14="weekly",37<=$D14),AND($E14="biweekly",37<=$D14,MOD(37-$C14,2)=0))),Flows!$C15,0)) | AQ14: =IF(OR($A14="",Flows!$C15=""),0,IF(AND(38<=Setup!$B$5,38>=$C14,OR(AND($E14="once",38=$C14),AND($E14="weekly",38<=$D14),AND($E14="biweekly",38<=$D14,MOD(38-$C14,2)=0))),Flows!$C15,0)) | AR14: =IF(OR($A14="",Flows!$C15=""),0,IF(AND(39<=Setup!$B$5,39>=$C14,OR(AND($E14="once",39=$C14),AND($E14="weekly",39<=$D14),AND($E14="biweekly",39<=$D14,MOD(39-$C14,2)=0))),Flows!$C15,0)) | AS14: =IF(OR($A14="",Flows!$C15=""),0,IF(AND(40<=Setup!$B$5,40>=$C14,OR(AND($E14="once",40=$C14),AND($E14="weekly",40<=$D14),AND($E14="biweekly",40<=$D14,MOD(40-$C14,2)=0))),Flows!$C15,0)) | AT14: =IF(OR($A14="",Flows!$C15=""),0,IF(AND(41<=Setup!$B$5,41>=$C14,OR(AND($E14="once",41=$C14),AND($E14="weekly",41<=$D14),AND($E14="biweekly",41<=$D14,MOD(41-$C14,2)=0))),Flows!$C15,0)) | AU14: =IF(OR($A14="",Flows!$C15=""),0,IF(AND(42<=Setup!$B$5,42>=$C14,OR(AND($E14="once",42=$C14),AND($E14="weekly",42<=$D14),AND($E14="biweekly",42<=$D14,MOD(42-$C14,2)=0))),Flows!$C15,0)) | AV14: =IF(OR($A14="",Flows!$C15=""),0,IF(AND(43<=Setup!$B$5,43>=$C14,OR(AND($E14="once",43=$C14),AND($E14="weekly",43<=$D14),AND($E14="biweekly",43<=$D14,MOD(43-$C14,2)=0))),Flows!$C15,0)) | AW14: =IF(OR($A14="",Flows!$C15=""),0,IF(AND(44<=Setup!$B$5,44>=$C14,OR(AND($E14="once",44=$C14),AND($E14="weekly",44<=$D14),AND($E14="biweekly",44<=$D14,MOD(44-$C14,2)=0))),Flows!$C15,0)) | AX14: =IF(OR($A14="",Flows!$C15=""),0,IF(AND(45<=Setup!$B$5,45>=$C14,OR(AND($E14="once",45=$C14),AND($E14="weekly",45<=$D14),AND($E14="biweekly",45<=$D14,MOD(45-$C14,2)=0))),Flows!$C15,0)) | AY14: =IF(OR($A14="",Flows!$C15=""),0,IF(AND(46<=Setup!$B$5,46>=$C14,OR(AND($E14="once",46=$C14),AND($E14="weekly",46<=$D14),AND($E14="biweekly",46<=$D14,MOD(46-$C14,2)=0))),Flows!$C15,0)) | AZ14: =IF(OR($A14="",Flows!$C15=""),0,IF(AND(47<=Setup!$B$5,47>=$C14,OR(AND($E14="once",47=$C14),AND($E14="weekly",47<=$D14),AND($E14="biweekly",47<=$D14,MOD(47-$C14,2)=0))),Flows!$C15,0)) | BA14: =IF(OR($A14="",Flows!$C15=""),0,IF(AND(48<=Setup!$B$5,48>=$C14,OR(AND($E14="once",48=$C14),AND($E14="weekly",48<=$D14),AND($E14="biweekly",48<=$D14,MOD(48-$C14,2)=0))),Flows!$C15,0)) | BB14: =IF(OR($A14="",Flows!$C15=""),0,IF(AND(49<=Setup!$B$5,49>=$C14,OR(AND($E14="once",49=$C14),AND($E14="weekly",49<=$D14),AND($E14="biweekly",49<=$D14,MOD(49-$C14,2)=0))),Flows!$C15,0)) | BC14: =IF(OR($A14="",Flows!$C15=""),0,IF(AND(50<=Setup!$B$5,50>=$C14,OR(AND($E14="once",50=$C14),AND($E14="weekly",50<=$D14),AND($E14="biweekly",50<=$D14,MOD(50-$C14,2)=0))),Flows!$C15,0)) | BD14: =IF(OR($A14="",Flows!$C15=""),0,IF(AND(51<=Setup!$B$5,51>=$C14,OR(AND($E14="once",51=$C14),AND($E14="weekly",51<=$D14),AND($E14="biweekly",51<=$D14,MOD(51-$C14,2)=0))),Flows!$C15,0)) | BE14: =IF(OR($A14="",Flows!$C15=""),0,IF(AND(52<=Setup!$B$5,52>=$C14,OR(AND($E14="once",52=$C14),AND($E14="weekly",52<=$D14),AND($E14="biweekly",52<=$D14,MOD(52-$C14,2)=0))),Flows!$C15,0))
A15: =IF(Flows!A16="","",LOWER(Flows!A16)) | B15: =IF(Flows!B16="","",Flows!B16) | C15: =N(Flows!D16) | D15: =IF(Flows!F16="",Setup!$B$5,Flows!F16) | E15: =IF(Flows!E16="","once",LOWER(Flows!E16)) | F15: =IF(OR($A15="",Flows!$C16=""),0,IF(AND(1<=Setup!$B$5,1>=$C15,OR(AND($E15="once",1=$C15),AND($E15="weekly",1<=$D15),AND($E15="biweekly",1<=$D15,MOD(1-$C15,2)=0))),Flows!$C16,0)) | G15: =IF(OR($A15="",Flows!$C16=""),0,IF(AND(2<=Setup!$B$5,2>=$C15,OR(AND($E15="once",2=$C15),AND($E15="weekly",2<=$D15),AND($E15="biweekly",2<=$D15,MOD(2-$C15,2)=0))),Flows!$C16,0)) | H15: =IF(OR($A15="",Flows!$C16=""),0,IF(AND(3<=Setup!$B$5,3>=$C15,OR(AND($E15="once",3=$C15),AND($E15="weekly",3<=$D15),AND($E15="biweekly",3<=$D15,MOD(3-$C15,2)=0))),Flows!$C16,0)) | I15: =IF(OR($A15="",Flows!$C16=""),0,IF(AND(4<=Setup!$B$5,4>=$C15,OR(AND($E15="once",4=$C15),AND($E15="weekly",4<=$D15),AND($E15="biweekly",4<=$D15,MOD(4-$C15,2)=0))),Flows!$C16,0)) | J15: =IF(OR($A15="",Flows!$C16=""),0,IF(AND(5<=Setup!$B$5,5>=$C15,OR(AND($E15="once",5=$C15),AND($E15="weekly",5<=$D15),AND($E15="biweekly",5<=$D15,MOD(5-$C15,2)=0))),Flows!$C16,0)) | K15: =IF(OR($A15="",Flows!$C16=""),0,IF(AND(6<=Setup!$B$5,6>=$C15,OR(AND($E15="once",6=$C15),AND($E15="weekly",6<=$D15),AND($E15="biweekly",6<=$D15,MOD(6-$C15,2)=0))),Flows!$C16,0)) | L15: =IF(OR($A15="",Flows!$C16=""),0,IF(AND(7<=Setup!$B$5,7>=$C15,OR(AND($E15="once",7=$C15),AND($E15="weekly",7<=$D15),AND($E15="biweekly",7<=$D15,MOD(7-$C15,2)=0))),Flows!$C16,0)) | M15: =IF(OR($A15="",Flows!$C16=""),0,IF(AND(8<=Setup!$B$5,8>=$C15,OR(AND($E15="once",8=$C15),AND($E15="weekly",8<=$D15),AND($E15="biweekly",8<=$D15,MOD(8-$C15,2)=0))),Flows!$C16,0)) | N15: =IF(OR($A15="",Flows!$C16=""),0,IF(AND(9<=Setup!$B$5,9>=$C15,OR(AND($E15="once",9=$C15),AND($E15="weekly",9<=$D15),AND($E15="biweekly",9<=$D15,MOD(9-$C15,2)=0))),Flows!$C16,0)) | O15: =IF(OR($A15="",Flows!$C16=""),0,IF(AND(10<=Setup!$B$5,10>=$C15,OR(AND($E15="once",10=$C15),AND($E15="weekly",10<=$D15),AND($E15="biweekly",10<=$D15,MOD(10-$C15,2)=0))),Flows!$C16,0)) | P15: =IF(OR($A15="",Flows!$C16=""),0,IF(AND(11<=Setup!$B$5,11>=$C15,OR(AND($E15="once",11=$C15),AND($E15="weekly",11<=$D15),AND($E15="biweekly",11<=$D15,MOD(11-$C15,2)=0))),Flows!$C16,0)) | Q15: =IF(OR($A15="",Flows!$C16=""),0,IF(AND(12<=Setup!$B$5,12>=$C15,OR(AND($E15="once",12=$C15),AND($E15="weekly",12<=$D15),AND($E15="biweekly",12<=$D15,MOD(12-$C15,2)=0))),Flows!$C16,0)) | R15: =IF(OR($A15="",Flows!$C16=""),0,IF(AND(13<=Setup!$B$5,13>=$C15,OR(AND($E15="once",13=$C15),AND($E15="weekly",13<=$D15),AND($E15="biweekly",13<=$D15,MOD(13-$C15,2)=0))),Flows!$C16,0)) | S15: =IF(OR($A15="",Flows!$C16=""),0,IF(AND(14<=Setup!$B$5,14>=$C15,OR(AND($E15="once",14=$C15),AND($E15="weekly",14<=$D15),AND($E15="biweekly",14<=$D15,MOD(14-$C15,2)=0))),Flows!$C16,0)) | T15: =IF(OR($A15="",Flows!$C16=""),0,IF(AND(15<=Setup!$B$5,15>=$C15,OR(AND($E15="once",15=$C15),AND($E15="weekly",15<=$D15),AND($E15="biweekly",15<=$D15,MOD(15-$C15,2)=0))),Flows!$C16,0)) | U15: =IF(OR($A15="",Flows!$C16=""),0,IF(AND(16<=Setup!$B$5,16>=$C15,OR(AND($E15="once",16=$C15),AND($E15="weekly",16<=$D15),AND($E15="biweekly",16<=$D15,MOD(16-$C15,2)=0))),Flows!$C16,0)) | V15: =IF(OR($A15="",Flows!$C16=""),0,IF(AND(17<=Setup!$B$5,17>=$C15,OR(AND($E15="once",17=$C15),AND($E15="weekly",17<=$D15),AND($E15="biweekly",17<=$D15,MOD(17-$C15,2)=0))),Flows!$C16,0)) | W15: =IF(OR($A15="",Flows!$C16=""),0,IF(AND(18<=Setup!$B$5,18>=$C15,OR(AND($E15="once",18=$C15),AND($E15="weekly",18<=$D15),AND($E15="biweekly",18<=$D15,MOD(18-$C15,2)=0))),Flows!$C16,0)) | X15: =IF(OR($A15="",Flows!$C16=""),0,IF(AND(19<=Setup!$B$5,19>=$C15,OR(AND($E15="once",19=$C15),AND($E15="weekly",19<=$D15),AND($E15="biweekly",19<=$D15,MOD(19-$C15,2)=0))),Flows!$C16,0)) | Y15: =IF(OR($A15="",Flows!$C16=""),0,IF(AND(20<=Setup!$B$5,20>=$C15,OR(AND($E15="once",20=$C15),AND($E15="weekly",20<=$D15),AND($E15="biweekly",20<=$D15,MOD(20-$C15,2)=0))),Flows!$C16,0)) | Z15: =IF(OR($A15="",Flows!$C16=""),0,IF(AND(21<=Setup!$B$5,21>=$C15,OR(AND($E15="once",21=$C15),AND($E15="weekly",21<=$D15),AND($E15="biweekly",21<=$D15,MOD(21-$C15,2)=0))),Flows!$C16,0)) | AA15: =IF(OR($A15="",Flows!$C16=""),0,IF(AND(22<=Setup!$B$5,22>=$C15,OR(AND($E15="once",22=$C15),AND($E15="weekly",22<=$D15),AND($E15="biweekly",22<=$D15,MOD(22-$C15,2)=0))),Flows!$C16,0)) | AB15: =IF(OR($A15="",Flows!$C16=""),0,IF(AND(23<=Setup!$B$5,23>=$C15,OR(AND($E15="once",23=$C15),AND($E15="weekly",23<=$D15),AND($E15="biweekly",23<=$D15,MOD(23-$C15,2)=0))),Flows!$C16,0)) | AC15: =IF(OR($A15="",Flows!$C16=""),0,IF(AND(24<=Setup!$B$5,24>=$C15,OR(AND($E15="once",24=$C15),AND($E15="weekly",24<=$D15),AND($E15="biweekly",24<=$D15,MOD(24-$C15,2)=0))),Flows!$C16,0)) | AD15: =IF(OR($A15="",Flows!$C16=""),0,IF(AND(25<=Setup!$B$5,25>=$C15,OR(AND($E15="once",25=$C15),AND($E15="weekly",25<=$D15),AND($E15="biweekly",25<=$D15,MOD(25-$C15,2)=0))),Flows!$C16,0)) | AE15: =IF(OR($A15="",Flows!$C16=""),0,IF(AND(26<=Setup!$B$5,26>=$C15,OR(AND($E15="once",26=$C15),AND($E15="weekly",26<=$D15),AND($E15="biweekly",26<=$D15,MOD(26-$C15,2)=0))),Flows!$C16,0)) | AF15: =IF(OR($A15="",Flows!$C16=""),0,IF(AND(27<=Setup!$B$5,27>=$C15,OR(AND($E15="once",27=$C15),AND($E15="weekly",27<=$D15),AND($E15="biweekly",27<=$D15,MOD(27-$C15,2)=0))),Flows!$C16,0)) | AG15: =IF(OR($A15="",Flows!$C16=""),0,IF(AND(28<=Setup!$B$5,28>=$C15,OR(AND($E15="once",28=$C15),AND($E15="weekly",28<=$D15),AND($E15="biweekly",28<=$D15,MOD(28-$C15,2)=0))),Flows!$C16,0)) | AH15: =IF(OR($A15="",Flows!$C16=""),0,IF(AND(29<=Setup!$B$5,29>=$C15,OR(AND($E15="once",29=$C15),AND($E15="weekly",29<=$D15),AND($E15="biweekly",29<=$D15,MOD(29-$C15,2)=0))),Flows!$C16,0)) | AI15: =IF(OR($A15="",Flows!$C16=""),0,IF(AND(30<=Setup!$B$5,30>=$C15,OR(AND($E15="once",30=$C15),AND($E15="weekly",30<=$D15),AND($E15="biweekly",30<=$D15,MOD(30-$C15,2)=0))),Flows!$C16,0)) | AJ15: =IF(OR($A15="",Flows!$C16=""),0,IF(AND(31<=Setup!$B$5,31>=$C15,OR(AND($E15="once",31=$C15),AND($E15="weekly",31<=$D15),AND($E15="biweekly",31<=$D15,MOD(31-$C15,2)=0))),Flows!$C16,0)) | AK15: =IF(OR($A15="",Flows!$C16=""),0,IF(AND(32<=Setup!$B$5,32>=$C15,OR(AND($E15="once",32=$C15),AND($E15="weekly",32<=$D15),AND($E15="biweekly",32<=$D15,MOD(32-$C15,2)=0))),Flows!$C16,0)) | AL15: =IF(OR($A15="",Flows!$C16=""),0,IF(AND(33<=Setup!$B$5,33>=$C15,OR(AND($E15="once",33=$C15),AND($E15="weekly",33<=$D15),AND($E15="biweekly",33<=$D15,MOD(33-$C15,2)=0))),Flows!$C16,0)) | AM15: =IF(OR($A15="",Flows!$C16=""),0,IF(AND(34<=Setup!$B$5,34>=$C15,OR(AND($E15="once",34=$C15),AND($E15="weekly",34<=$D15),AND($E15="biweekly",34<=$D15,MOD(34-$C15,2)=0))),Flows!$C16,0)) | AN15: =IF(OR($A15="",Flows!$C16=""),0,IF(AND(35<=Setup!$B$5,35>=$C15,OR(AND($E15="once",35=$C15),AND($E15="weekly",35<=$D15),AND($E15="biweekly",35<=$D15,MOD(35-$C15,2)=0))),Flows!$C16,0)) | AO15: =IF(OR($A15="",Flows!$C16=""),0,IF(AND(36<=Setup!$B$5,36>=$C15,OR(AND($E15="once",36=$C15),AND($E15="weekly",36<=$D15),AND($E15="biweekly",36<=$D15,MOD(36-$C15,2)=0))),Flows!$C16,0)) | AP15: =IF(OR($A15="",Flows!$C16=""),0,IF(AND(37<=Setup!$B$5,37>=$C15,OR(AND($E15="once",37=$C15),AND($E15="weekly",37<=$D15),AND($E15="biweekly",37<=$D15,MOD(37-$C15,2)=0))),Flows!$C16,0)) | AQ15: =IF(OR($A15="",Flows!$C16=""),0,IF(AND(38<=Setup!$B$5,38>=$C15,OR(AND($E15="once",38=$C15),AND($E15="weekly",38<=$D15),AND($E15="biweekly",38<=$D15,MOD(38-$C15,2)=0))),Flows!$C16,0)) | AR15: =IF(OR($A15="",Flows!$C16=""),0,IF(AND(39<=Setup!$B$5,39>=$C15,OR(AND($E15="once",39=$C15),AND($E15="weekly",39<=$D15),AND($E15="biweekly",39<=$D15,MOD(39-$C15,2)=0))),Flows!$C16,0)) | AS15: =IF(OR($A15="",Flows!$C16=""),0,IF(AND(40<=Setup!$B$5,40>=$C15,OR(AND($E15="once",40=$C15),AND($E15="weekly",40<=$D15),AND($E15="biweekly",40<=$D15,MOD(40-$C15,2)=0))),Flows!$C16,0)) | AT15: =IF(OR($A15="",Flows!$C16=""),0,IF(AND(41<=Setup!$B$5,41>=$C15,OR(AND($E15="once",41=$C15),AND($E15="weekly",41<=$D15),AND($E15="biweekly",41<=$D15,MOD(41-$C15,2)=0))),Flows!$C16,0)) | AU15: =IF(OR($A15="",Flows!$C16=""),0,IF(AND(42<=Setup!$B$5,42>=$C15,OR(AND($E15="once",42=$C15),AND($E15="weekly",42<=$D15),AND($E15="biweekly",42<=$D15,MOD(42-$C15,2)=0))),Flows!$C16,0)) | AV15: =IF(OR($A15="",Flows!$C16=""),0,IF(AND(43<=Setup!$B$5,43>=$C15,OR(AND($E15="once",43=$C15),AND($E15="weekly",43<=$D15),AND($E15="biweekly",43<=$D15,MOD(43-$C15,2)=0))),Flows!$C16,0)) | AW15: =IF(OR($A15="",Flows!$C16=""),0,IF(AND(44<=Setup!$B$5,44>=$C15,OR(AND($E15="once",44=$C15),AND($E15="weekly",44<=$D15),AND($E15="biweekly",44<=$D15,MOD(44-$C15,2)=0))),Flows!$C16,0)) | AX15: =IF(OR($A15="",Flows!$C16=""),0,IF(AND(45<=Setup!$B$5,45>=$C15,OR(AND($E15="once",45=$C15),AND($E15="weekly",45<=$D15),AND($E15="biweekly",45<=$D15,MOD(45-$C15,2)=0))),Flows!$C16,0)) | AY15: =IF(OR($A15="",Flows!$C16=""),0,IF(AND(46<=Setup!$B$5,46>=$C15,OR(AND($E15="once",46=$C15),AND($E15="weekly",46<=$D15),AND($E15="biweekly",46<=$D15,MOD(46-$C15,2)=0))),Flows!$C16,0)) | AZ15: =IF(OR($A15="",Flows!$C16=""),0,IF(AND(47<=Setup!$B$5,47>=$C15,OR(AND($E15="once",47=$C15),AND($E15="weekly",47<=$D15),AND($E15="biweekly",47<=$D15,MOD(47-$C15,2)=0))),Flows!$C16,0)) | BA15: =IF(OR($A15="",Flows!$C16=""),0,IF(AND(48<=Setup!$B$5,48>=$C15,OR(AND($E15="once",48=$C15),AND($E15="weekly",48<=$D15),AND($E15="biweekly",48<=$D15,MOD(48-$C15,2)=0))),Flows!$C16,0)) | BB15: =IF(OR($A15="",Flows!$C16=""),0,IF(AND(49<=Setup!$B$5,49>=$C15,OR(AND($E15="once",49=$C15),AND($E15="weekly",49<=$D15),AND($E15="biweekly",49<=$D15,MOD(49-$C15,2)=0))),Flows!$C16,0)) | BC15: =IF(OR($A15="",Flows!$C16=""),0,IF(AND(50<=Setup!$B$5,50>=$C15,OR(AND($E15="once",50=$C15),AND($E15="weekly",50<=$D15),AND($E15="biweekly",50<=$D15,MOD(50-$C15,2)=0))),Flows!$C16,0)) | BD15: =IF(OR($A15="",Flows!$C16=""),0,IF(AND(51<=Setup!$B$5,51>=$C15,OR(AND($E15="once",51=$C15),AND($E15="weekly",51<=$D15),AND($E15="biweekly",51<=$D15,MOD(51-$C15,2)=0))),Flows!$C16,0)) | BE15: =IF(OR($A15="",Flows!$C16=""),0,IF(AND(52<=Setup!$B$5,52>=$C15,OR(AND($E15="once",52=$C15),AND($E15="weekly",52<=$D15),AND($E15="biweekly",52<=$D15,MOD(52-$C15,2)=0))),Flows!$C16,0))
... A83: =IF(Flows!A84="","",LOWER(Flows!A84)) | B83: =IF(Flows!B84="","",Flows!B84) | C83: =N(Flows!D84) | D83: =IF(Flows!F84="",Setup!$B$5,Flows!F84) | E83: =IF(Flows!E84="","once",LOWER(Flows!E84)) | F83: =IF(OR($A83="",Flows!$C84=""),0,IF(AND(1<=Setup!$B$5,1>=$C83,OR(AND($E83="once",1=$C83),AND($E83="weekly",1<=$D83),AND($E83="biweekly",1<=$D83,MOD(1-$C83,2)=0))),Flows!$C84,0)) | G83: =IF(OR($A83="",Flows!$C84=""),0,IF(AND(2<=Setup!$B$5,2>=$C83,OR(AND($E83="once",2=$C83),AND($E83="weekly",2<=$D83),AND($E83="biweekly",2<=$D83,MOD(2-$C83,2)=0))),Flows!$C84,0)) | H83: =IF(OR($A83="",Flows!$C84=""),0,IF(AND(3<=Setup!$B$5,3>=$C83,OR(AND($E83="once",3=$C83),AND($E83="weekly",3<=$D83),AND($E83="biweekly",3<=$D83,MOD(3-$C83,2)=0))),Flows!$C84,0)) | I83: =IF(OR($A83="",Flows!$C84=""),0,IF(AND(4<=Setup!$B$5,4>=$C83,OR(AND($E83="once",4=$C83),AND($E83="weekly",4<=$D83),AND($E83="biweekly",4<=$D83,MOD(4-$C83,2)=0))),Flows!$C84,0)) | J83: =IF(OR($A83="",Flows!$C84=""),0,IF(AND(5<=Setup!$B$5,5>=$C83,OR(AND($E83="once",5=$C83),AND($E83="weekly",5<=$D83),AND($E83="biweekly",5<=$D83,MOD(5-$C83,2)=0))),Flows!$C84,0)) | K83: =IF(OR($A83="",Flows!$C84=""),0,IF(AND(6<=Setup!$B$5,6>=$C83,OR(AND($E83="once",6=$C83),AND($E83="weekly",6<=$D83),AND($E83="biweekly",6<=$D83,MOD(6-$C83,2)=0))),Flows!$C84,0)) | L83: =IF(OR($A83="",Flows!$C84=""),0,IF(AND(7<=Setup!$B$5,7>=$C83,OR(AND($E83="once",7=$C83),AND($E83="weekly",7<=$D83),AND($E83="biweekly",7<=$D83,MOD(7-$C83,2)=0))),Flows!$C84,0)) | M83: =IF(OR($A83="",Flows!$C84=""),0,IF(AND(8<=Setup!$B$5,8>=$C83,OR(AND($E83="once",8=$C83),AND($E83="weekly",8<=$D83),AND($E83="biweekly",8<=$D83,MOD(8-$C83,2)=0))),Flows!$C84,0)) | N83: =IF(OR($A83="",Flows!$C84=""),0,IF(AND(9<=Setup!$B$5,9>=$C83,OR(AND($E83="once",9=$C83),AND($E83="weekly",9<=$D83),AND($E83="biweekly",9<=$D83,MOD(9-$C83,2)=0))),Flows!$C84,0)) | O83: =IF(OR($A83="",Flows!$C84=""),0,IF(AND(10<=Setup!$B$5,10>=$C83,OR(AND($E83="once",10=$C83),AND($E83="weekly",10<=$D83),AND($E83="biweekly",10<=$D83,MOD(10-$C83,2)=0))),Flows!$C84,0)) | P83: =IF(OR($A83="",Flows!$C84=""),0,IF(AND(11<=Setup!$B$5,11>=$C83,OR(AND($E83="once",11=$C83),AND($E83="weekly",11<=$D83),AND($E83="biweekly",11<=$D83,MOD(11-$C83,2)=0))),Flows!$C84,0)) | Q83: =IF(OR($A83="",Flows!$C84=""),0,IF(AND(12<=Setup!$B$5,12>=$C83,OR(AND($E83="once",12=$C83),AND($E83="weekly",12<=$D83),AND($E83="biweekly",12<=$D83,MOD(12-$C83,2)=0))),Flows!$C84,0)) | R83: =IF(OR($A83="",Flows!$C84=""),0,IF(AND(13<=Setup!$B$5,13>=$C83,OR(AND($E83="once",13=$C83),AND($E83="weekly",13<=$D83),AND($E83="biweekly",13<=$D83,MOD(13-$C83,2)=0))),Flows!$C84,0)) | S83: =IF(OR($A83="",Flows!$C84=""),0,IF(AND(14<=Setup!$B$5,14>=$C83,OR(AND($E83="once",14=$C83),AND($E83="weekly",14<=$D83),AND($E83="biweekly",14<=$D83,MOD(14-$C83,2)=0))),Flows!$C84,0)) | T83: =IF(OR($A83="",Flows!$C84=""),0,IF(AND(15<=Setup!$B$5,15>=$C83,OR(AND($E83="once",15=$C83),AND($E83="weekly",15<=$D83),AND($E83="biweekly",15<=$D83,MOD(15-$C83,2)=0))),Flows!$C84,0)) | U83: =IF(OR($A83="",Flows!$C84=""),0,IF(AND(16<=Setup!$B$5,16>=$C83,OR(AND($E83="once",16=$C83),AND($E83="weekly",16<=$D83),AND($E83="biweekly",16<=$D83,MOD(16-$C83,2)=0))),Flows!$C84,0)) | V83: =IF(OR($A83="",Flows!$C84=""),0,IF(AND(17<=Setup!$B$5,17>=$C83,OR(AND($E83="once",17=$C83),AND($E83="weekly",17<=$D83),AND($E83="biweekly",17<=$D83,MOD(17-$C83,2)=0))),Flows!$C84,0)) | W83: =IF(OR($A83="",Flows!$C84=""),0,IF(AND(18<=Setup!$B$5,18>=$C83,OR(AND($E83="once",18=$C83),AND($E83="weekly",18<=$D83),AND($E83="biweekly",18<=$D83,MOD(18-$C83,2)=0))),Flows!$C84,0)) | X83: =IF(OR($A83="",Flows!$C84=""),0,IF(AND(19<=Setup!$B$5,19>=$C83,OR(AND($E83="once",19=$C83),AND($E83="weekly",19<=$D83),AND($E83="biweekly",19<=$D83,MOD(19-$C83,2)=0))),Flows!$C84,0)) | Y83: =IF(OR($A83="",Flows!$C84=""),0,IF(AND(20<=Setup!$B$5,20>=$C83,OR(AND($E83="once",20=$C83),AND($E83="weekly",20<=$D83),AND($E83="biweekly",20<=$D83,MOD(20-$C83,2)=0))),Flows!$C84,0)) | Z83: =IF(OR($A83="",Flows!$C84=""),0,IF(AND(21<=Setup!$B$5,21>=$C83,OR(AND($E83="once",21=$C83),AND($E83="weekly",21<=$D83),AND($E83="biweekly",21<=$D83,MOD(21-$C83,2)=0))),Flows!$C84,0)) | AA83: =IF(OR($A83="",Flows!$C84=""),0,IF(AND(22<=Setup!$B$5,22>=$C83,OR(AND($E83="once",22=$C83),AND($E83="weekly",22<=$D83),AND($E83="biweekly",22<=$D83,MOD(22-$C83,2)=0))),Flows!$C84,0)) | AB83: =IF(OR($A83="",Flows!$C84=""),0,IF(AND(23<=Setup!$B$5,23>=$C83,OR(AND($E83="once",23=$C83),AND($E83="weekly",23<=$D83),AND($E83="biweekly",23<=$D83,MOD(23-$C83,2)=0))),Flows!$C84,0)) | AC83: =IF(OR($A83="",Flows!$C84=""),0,IF(AND(24<=Setup!$B$5,24>=$C83,OR(AND($E83="once",24=$C83),AND($E83="weekly",24<=$D83),AND($E83="biweekly",24<=$D83,MOD(24-$C83,2)=0))),Flows!$C84,0)) | AD83: =IF(OR($A83="",Flows!$C84=""),0,IF(AND(25<=Setup!$B$5,25>=$C83,OR(AND($E83="once",25=$C83),AND($E83="weekly",25<=$D83),AND($E83="biweekly",25<=$D83,MOD(25-$C83,2)=0))),Flows!$C84,0)) | AE83: =IF(OR($A83="",Flows!$C84=""),0,IF(AND(26<=Setup!$B$5,26>=$C83,OR(AND($E83="once",26=$C83),AND($E83="weekly",26<=$D83),AND($E83="biweekly",26<=$D83,MOD(26-$C83,2)=0))),Flows!$C84,0)) | AF83: =IF(OR($A83="",Flows!$C84=""),0,IF(AND(27<=Setup!$B$5,27>=$C83,OR(AND($E83="once",27=$C83),AND($E83="weekly",27<=$D83),AND($E83="biweekly",27<=$D83,MOD(27-$C83,2)=0))),Flows!$C84,0)) | AG83: =IF(OR($A83="",Flows!$C84=""),0,IF(AND(28<=Setup!$B$5,28>=$C83,OR(AND($E83="once",28=$C83),AND($E83="weekly",28<=$D83),AND($E83="biweekly",28<=$D83,MOD(28-$C83,2)=0))),Flows!$C84,0)) | AH83: =IF(OR($A83="",Flows!$C84=""),0,IF(AND(29<=Setup!$B$5,29>=$C83,OR(AND($E83="once",29=$C83),AND($E83="weekly",29<=$D83),AND($E83="biweekly",29<=$D83,MOD(29-$C83,2)=0))),Flows!$C84,0)) | AI83: =IF(OR($A83="",Flows!$C84=""),0,IF(AND(30<=Setup!$B$5,30>=$C83,OR(AND($E83="once",30=$C83),AND($E83="weekly",30<=$D83),AND($E83="biweekly",30<=$D83,MOD(30-$C83,2)=0))),Flows!$C84,0)) | AJ83: =IF(OR($A83="",Flows!$C84=""),0,IF(AND(31<=Setup!$B$5,31>=$C83,OR(AND($E83="once",31=$C83),AND($E83="weekly",31<=$D83),AND($E83="biweekly",31<=$D83,MOD(31-$C83,2)=0))),Flows!$C84,0)) | AK83: =IF(OR($A83="",Flows!$C84=""),0,IF(AND(32<=Setup!$B$5,32>=$C83,OR(AND($E83="once",32=$C83),AND($E83="weekly",32<=$D83),AND($E83="biweekly",32<=$D83,MOD(32-$C83,2)=0))),Flows!$C84,0)) | AL83: =IF(OR($A83="",Flows!$C84=""),0,IF(AND(33<=Setup!$B$5,33>=$C83,OR(AND($E83="once",33=$C83),AND($E83="weekly",33<=$D83),AND($E83="biweekly",33<=$D83,MOD(33-$C83,2)=0))),Flows!$C84,0)) | AM83: =IF(OR($A83="",Flows!$C84=""),0,IF(AND(34<=Setup!$B$5,34>=$C83,OR(AND($E83="once",34=$C83),AND($E83="weekly",34<=$D83),AND($E83="biweekly",34<=$D83,MOD(34-$C83,2)=0))),Flows!$C84,0)) | AN83: =IF(OR($A83="",Flows!$C84=""),0,IF(AND(35<=Setup!$B$5,35>=$C83,OR(AND($E83="once",35=$C83),AND($E83="weekly",35<=$D83),AND($E83="biweekly",35<=$D83,MOD(35-$C83,2)=0))),Flows!$C84,0)) | AO83: =IF(OR($A83="",Flows!$C84=""),0,IF(AND(36<=Setup!$B$5,36>=$C83,OR(AND($E83="once",36=$C83),AND($E83="weekly",36<=$D83),AND($E83="biweekly",36<=$D83,MOD(36-$C83,2)=0))),Flows!$C84,0)) | AP83: =IF(OR($A83="",Flows!$C84=""),0,IF(AND(37<=Setup!$B$5,37>=$C83,OR(AND($E83="once",37=$C83),AND($E83="weekly",37<=$D83),AND($E83="biweekly",37<=$D83,MOD(37-$C83,2)=0))),Flows!$C84,0)) | AQ83: =IF(OR($A83="",Flows!$C84=""),0,IF(AND(38<=Setup!$B$5,38>=$C83,OR(AND($E83="once",38=$C83),AND($E83="weekly",38<=$D83),AND($E83="biweekly",38<=$D83,MOD(38-$C83,2)=0))),Flows!$C84,0)) | AR83: =IF(OR($A83="",Flows!$C84=""),0,IF(AND(39<=Setup!$B$5,39>=$C83,OR(AND($E83="once",39=$C83),AND($E83="weekly",39<=$D83),AND($E83="biweekly",39<=$D83,MOD(39-$C83,2)=0))),Flows!$C84,0)) | AS83: =IF(OR($A83="",Flows!$C84=""),0,IF(AND(40<=Setup!$B$5,40>=$C83,OR(AND($E83="once",40=$C83),AND($E83="weekly",40<=$D83),AND($E83="biweekly",40<=$D83,MOD(40-$C83,2)=0))),Flows!$C84,0)) | AT83: =IF(OR($A83="",Flows!$C84=""),0,IF(AND(41<=Setup!$B$5,41>=$C83,OR(AND($E83="once",41=$C83),AND($E83="weekly",41<=$D83),AND($E83="biweekly",41<=$D83,MOD(41-$C83,2)=0))),Flows!$C84,0)) | AU83: =IF(OR($A83="",Flows!$C84=""),0,IF(AND(42<=Setup!$B$5,42>=$C83,OR(AND($E83="once",42=$C83),AND($E83="weekly",42<=$D83),AND($E83="biweekly",42<=$D83,MOD(42-$C83,2)=0))),Flows!$C84,0)) | AV83: =IF(OR($A83="",Flows!$C84=""),0,IF(AND(43<=Setup!$B$5,43>=$C83,OR(AND($E83="once",43=$C83),AND($E83="weekly",43<=$D83),AND($E83="biweekly",43<=$D83,MOD(43-$C83,2)=0))),Flows!$C84,0)) | AW83: =IF(OR($A83="",Flows!$C84=""),0,IF(AND(44<=Setup!$B$5,44>=$C83,OR(AND($E83="once",44=$C83),AND($E83="weekly",44<=$D83),AND($E83="biweekly",44<=$D83,MOD(44-$C83,2)=0))),Flows!$C84,0)) | AX83: =IF(OR($A83="",Flows!$C84=""),0,IF(AND(45<=Setup!$B$5,45>=$C83,OR(AND($E83="once",45=$C83),AND($E83="weekly",45<=$D83),AND($E83="biweekly",45<=$D83,MOD(45-$C83,2)=0))),Flows!$C84,0)) | AY83: =IF(OR($A83="",Flows!$C84=""),0,IF(AND(46<=Setup!$B$5,46>=$C83,OR(AND($E83="once",46=$C83),AND($E83="weekly",46<=$D83),AND($E83="biweekly",46<=$D83,MOD(46-$C83,2)=0))),Flows!$C84,0)) | AZ83: =IF(OR($A83="",Flows!$C84=""),0,IF(AND(47<=Setup!$B$5,47>=$C83,OR(AND($E83="once",47=$C83),AND($E83="weekly",47<=$D83),AND($E83="biweekly",47<=$D83,MOD(47-$C83,2)=0))),Flows!$C84,0)) | BA83: =IF(OR($A83="",Flows!$C84=""),0,IF(AND(48<=Setup!$B$5,48>=$C83,OR(AND($E83="once",48=$C83),AND($E83="weekly",48<=$D83),AND($E83="biweekly",48<=$D83,MOD(48-$C83,2)=0))),Flows!$C84,0)) | BB83: =IF(OR($A83="",Flows!$C84=""),0,IF(AND(49<=Setup!$B$5,49>=$C83,OR(AND($E83="once",49=$C83),AND($E83="weekly",49<=$D83),AND($E83="biweekly",49<=$D83,MOD(49-$C83,2)=0))),Flows!$C84,0)) | BC83: =IF(OR($A83="",Flows!$C84=""),0,IF(AND(50<=Setup!$B$5,50>=$C83,OR(AND($E83="once",50=$C83),AND($E83="weekly",50<=$D83),AND($E83="biweekly",50<=$D83,MOD(50-$C83,2)=0))),Flows!$C84,0)) | BD83: =IF(OR($A83="",Flows!$C84=""),0,IF(AND(51<=Setup!$B$5,51>=$C83,OR(AND($E83="once",51=$C83),AND($E83="weekly",51<=$D83),AND($E83="biweekly",51<=$D83,MOD(51-$C83,2)=0))),Flows!$C84,0)) | BE83: =IF(OR($A83="",Flows!$C84=""),0,IF(AND(52<=Setup!$B$5,52>=$C83,OR(AND($E83="once",52=$C83),AND($E83="weekly",52<=$D83),AND($E83="biweekly",52<=$D83,MOD(52-$C83,2)=0))),Flows!$C84,0))

Sheet Weekly
A1: Weekly forecast (cash13_forecast)
A4: week | B4: week starting | C4: receipts | D4: disbursements | E4: net_cash | F4: ending_cash | G4: active | H4: trough helper | I4: negative helper
A5: 1 | B5: =IF(G5=1,Setup!$B$6+7*(1-1),"") | C5: =IF(G5=1,SUMIF(Grid!$A$4:$A$83,"receipt",Grid!F$4:F$83),0) | D5: =IF(G5=1,SUMIF(Grid!$A$4:$A$83,"disbursement",Grid!F$4:F$83),0) | E5: =C5-D5 | F5: =Setup!$B$4+E5 | G5: =IF(1<=Setup!$B$5,1,0) | H5: =IF(G5=1,F5,9.99E+307) | I5: =IF(AND(G5=1,F5<0),A5,9999)
A6: 2 | B6: =IF(G6=1,Setup!$B$6+7*(2-1),"") | C6: =IF(G6=1,SUMIF(Grid!$A$4:$A$83,"receipt",Grid!G$4:G$83),0) | D6: =IF(G6=1,SUMIF(Grid!$A$4:$A$83,"disbursement",Grid!G$4:G$83),0) | E6: =C6-D6 | F6: =F5+E6 | G6: =IF(2<=Setup!$B$5,1,0) | H6: =IF(G6=1,F6,9.99E+307) | I6: =IF(AND(G6=1,F6<0),A6,9999)
A7: 3 | B7: =IF(G7=1,Setup!$B$6+7*(3-1),"") | C7: =IF(G7=1,SUMIF(Grid!$A$4:$A$83,"receipt",Grid!H$4:H$83),0) | D7: =IF(G7=1,SUMIF(Grid!$A$4:$A$83,"disbursement",Grid!H$4:H$83),0) | E7: =C7-D7 | F7: =F6+E7 | G7: =IF(3<=Setup!$B$5,1,0) | H7: =IF(G7=1,F7,9.99E+307) | I7: =IF(AND(G7=1,F7<0),A7,9999)
A8: 4 | B8: =IF(G8=1,Setup!$B$6+7*(4-1),"") | C8: =IF(G8=1,SUMIF(Grid!$A$4:$A$83,"receipt",Grid!I$4:I$83),0) | D8: =IF(G8=1,SUMIF(Grid!$A$4:$A$83,"disbursement",Grid!I$4:I$83),0) | E8: =C8-D8 | F8: =F7+E8 | G8: =IF(4<=Setup!$B$5,1,0) | H8: =IF(G8=1,F8,9.99E+307) | I8: =IF(AND(G8=1,F8<0),A8,9999)
A9: 5 | B9: =IF(G9=1,Setup!$B$6+7*(5-1),"") | C9: =IF(G9=1,SUMIF(Grid!$A$4:$A$83,"receipt",Grid!J$4:J$83),0) | D9: =IF(G9=1,SUMIF(Grid!$A$4:$A$83,"disbursement",Grid!J$4:J$83),0) | E9: =C9-D9 | F9: =F8+E9 | G9: =IF(5<=Setup!$B$5,1,0) | H9: =IF(G9=1,F9,9.99E+307) | I9: =IF(AND(G9=1,F9<0),A9,9999)
A10: 6 | B10: =IF(G10=1,Setup!$B$6+7*(6-1),"") | C10: =IF(G10=1,SUMIF(Grid!$A$4:$A$83,"receipt",Grid!K$4:K$83),0) | D10: =IF(G10=1,SUMIF(Grid!$A$4:$A$83,"disbursement",Grid!K$4:K$83),0) | E10: =C10-D10 | F10: =F9+E10 | G10: =IF(6<=Setup!$B$5,1,0) | H10: =IF(G10=1,F10,9.99E+307) | I10: =IF(AND(G10=1,F10<0),A10,9999)
A11: 7 | B11: =IF(G11=1,Setup!$B$6+7*(7-1),"") | C11: =IF(G11=1,SUMIF(Grid!$A$4:$A$83,"receipt",Grid!L$4:L$83),0) | D11: =IF(G11=1,SUMIF(Grid!$A$4:$A$83,"disbursement",Grid!L$4:L$83),0) | E11: =C11-D11 | F11: =F10+E11 | G11: =IF(7<=Setup!$B$5,1,0) | H11: =IF(G11=1,F11,9.99E+307) | I11: =IF(AND(G11=1,F11<0),A11,9999)
A12: 8 | B12: =IF(G12=1,Setup!$B$6+7*(8-1),"") | C12: =IF(G12=1,SUMIF(Grid!$A$4:$A$83,"receipt",Grid!M$4:M$83),0) | D12: =IF(G12=1,SUMIF(Grid!$A$4:$A$83,"disbursement",Grid!M$4:M$83),0) | E12: =C12-D12 | F12: =F11+E12 | G12: =IF(8<=Setup!$B$5,1,0) | H12: =IF(G12=1,F12,9.99E+307) | I12: =IF(AND(G12=1,F12<0),A12,9999)
A13: 9 | B13: =IF(G13=1,Setup!$B$6+7*(9-1),"") | C13: =IF(G13=1,SUMIF(Grid!$A$4:$A$83,"receipt",Grid!N$4:N$83),0) | D13: =IF(G13=1,SUMIF(Grid!$A$4:$A$83,"disbursement",Grid!N$4:N$83),0) | E13: =C13-D13 | F13: =F12+E13 | G13: =IF(9<=Setup!$B$5,1,0) | H13: =IF(G13=1,F13,9.99E+307) | I13: =IF(AND(G13=1,F13<0),A13,9999)
A14: 10 | B14: =IF(G14=1,Setup!$B$6+7*(10-1),"") | C14: =IF(G14=1,SUMIF(Grid!$A$4:$A$83,"receipt",Grid!O$4:O$83),0) | D14: =IF(G14=1,SUMIF(Grid!$A$4:$A$83,"disbursement",Grid!O$4:O$83),0) | E14: =C14-D14 | F14: =F13+E14 | G14: =IF(10<=Setup!$B$5,1,0) | H14: =IF(G14=1,F14,9.99E+307) | I14: =IF(AND(G14=1,F14<0),A14,9999)
A15: 11 | B15: =IF(G15=1,Setup!$B$6+7*(11-1),"") | C15: =IF(G15=1,SUMIF(Grid!$A$4:$A$83,"receipt",Grid!P$4:P$83),0) | D15: =IF(G15=1,SUMIF(Grid!$A$4:$A$83,"disbursement",Grid!P$4:P$83),0) | E15: =C15-D15 | F15: =F14+E15 | G15: =IF(11<=Setup!$B$5,1,0) | H15: =IF(G15=1,F15,9.99E+307) | I15: =IF(AND(G15=1,F15<0),A15,9999)
A16: 12 | B16: =IF(G16=1,Setup!$B$6+7*(12-1),"") | C16: =IF(G16=1,SUMIF(Grid!$A$4:$A$83,"receipt",Grid!Q$4:Q$83),0) | D16: =IF(G16=1,SUMIF(Grid!$A$4:$A$83,"disbursement",Grid!Q$4:Q$83),0) | E16: =C16-D16 | F16: =F15+E16 | G16: =IF(12<=Setup!$B$5,1,0) | H16: =IF(G16=1,F16,9.99E+307) | I16: =IF(AND(G16=1,F16<0),A16,9999)
A17: 13 | B17: =IF(G17=1,Setup!$B$6+7*(13-1),"") | C17: =IF(G17=1,SUMIF(Grid!$A$4:$A$83,"receipt",Grid!R$4:R$83),0) | D17: =IF(G17=1,SUMIF(Grid!$A$4:$A$83,"disbursement",Grid!R$4:R$83),0) | E17: =C17-D17 | F17: =F16+E17 | G17: =IF(13<=Setup!$B$5,1,0) | H17: =IF(G17=1,F17,9.99E+307) | I17: =IF(AND(G17=1,F17<0),A17,9999)
A18: 14 | B18: =IF(G18=1,Setup!$B$6+7*(14-1),"") | C18: =IF(G18=1,SUMIF(Grid!$A$4:$A$83,"receipt",Grid!S$4:S$83),0) | D18: =IF(G18=1,SUMIF(Grid!$A$4:$A$83,"disbursement",Grid!S$4:S$83),0) | E18: =C18-D18 | F18: =F17+E18 | G18: =IF(14<=Setup!$B$5,1,0) | H18: =IF(G18=1,F18,9.99E+307) | I18: =IF(AND(G18=1,F18<0),A18,9999)
A19: 15 | B19: =IF(G19=1,Setup!$B$6+7*(15-1),"") | C19: =IF(G19=1,SUMIF(Grid!$A$4:$A$83,"receipt",Grid!T$4:T$83),0) | D19: =IF(G19=1,SUMIF(Grid!$A$4:$A$83,"disbursement",Grid!T$4:T$83),0) | E19: =C19-D19 | F19: =F18+E19 | G19: =IF(15<=Setup!$B$5,1,0) | H19: =IF(G19=1,F19,9.99E+307) | I19: =IF(AND(G19=1,F19<0),A19,9999)
A20: 16 | B20: =IF(G20=1,Setup!$B$6+7*(16-1),"") | C20: =IF(G20=1,SUMIF(Grid!$A$4:$A$83,"receipt",Grid!U$4:U$83),0) | D20: =IF(G20=1,SUMIF(Grid!$A$4:$A$83,"disbursement",Grid!U$4:U$83),0) | E20: =C20-D20 | F20: =F19+E20 | G20: =IF(16<=Setup!$B$5,1,0) | H20: =IF(G20=1,F20,9.99E+307) | I20: =IF(AND(G20=1,F20<0),A20,9999)
A21: 17 | B21: =IF(G21=1,Setup!$B$6+7*(17-1),"") | C21: =IF(G21=1,SUMIF(Grid!$A$4:$A$83,"receipt",Grid!V$4:V$83),0) | D21: =IF(G21=1,SUMIF(Grid!$A$4:$A$83,"disbursement",Grid!V$4:V$83),0) | E21: =C21-D21 | F21: =F20+E21 | G21: =IF(17<=Setup!$B$5,1,0) | H21: =IF(G21=1,F21,9.99E+307) | I21: =IF(AND(G21=1,F21<0),A21,9999)
A22: 18 | B22: =IF(G22=1,Setup!$B$6+7*(18-1),"") | C22: =IF(G22=1,SUMIF(Grid!$A$4:$A$83,"receipt",Grid!W$4:W$83),0) | D22: =IF(G22=1,SUMIF(Grid!$A$4:$A$83,"disbursement",Grid!W$4:W$83),0) | E22: =C22-D22 | F22: =F21+E22 | G22: =IF(18<=Setup!$B$5,1,0) | H22: =IF(G22=1,F22,9.99E+307) | I22: =IF(AND(G22=1,F22<0),A22,9999)
A23: 19 | B23: =IF(G23=1,Setup!$B$6+7*(19-1),"") | C23: =IF(G23=1,SUMIF(Grid!$A$4:$A$83,"receipt",Grid!X$4:X$83),0) | D23: =IF(G23=1,SUMIF(Grid!$A$4:$A$83,"disbursement",Grid!X$4:X$83),0) | E23: =C23-D23 | F23: =F22+E23 | G23: =IF(19<=Setup!$B$5,1,0) | H23: =IF(G23=1,F23,9.99E+307) | I23: =IF(AND(G23=1,F23<0),A23,9999)
A24: 20 | B24: =IF(G24=1,Setup!$B$6+7*(20-1),"") | C24: =IF(G24=1,SUMIF(Grid!$A$4:$A$83,"receipt",Grid!Y$4:Y$83),0) | D24: =IF(G24=1,SUMIF(Grid!$A$4:$A$83,"disbursement",Grid!Y$4:Y$83),0) | E24: =C24-D24 | F24: =F23+E24 | G24: =IF(20<=Setup!$B$5,1,0) | H24: =IF(G24=1,F24,9.99E+307) | I24: =IF(AND(G24=1,F24<0),A24,9999)
A25: 21 | B25: =IF(G25=1,Setup!$B$6+7*(21-1),"") | C25: =IF(G25=1,SUMIF(Grid!$A$4:$A$83,"receipt",Grid!Z$4:Z$83),0) | D25: =IF(G25=1,SUMIF(Grid!$A$4:$A$83,"disbursement",Grid!Z$4:Z$83),0) | E25: =C25-D25 | F25: =F24+E25 | G25: =IF(21<=Setup!$B$5,1,0) | H25: =IF(G25=1,F25,9.99E+307) | I25: =IF(AND(G25=1,F25<0),A25,9999)
A26: 22 | B26: =IF(G26=1,Setup!$B$6+7*(22-1),"") | C26: =IF(G26=1,SUMIF(Grid!$A$4:$A$83,"receipt",Grid!AA$4:AA$83),0) | D26: =IF(G26=1,SUMIF(Grid!$A$4:$A$83,"disbursement",Grid!AA$4:AA$83),0) | E26: =C26-D26 | F26: =F25+E26 | G26: =IF(22<=Setup!$B$5,1,0) | H26: =IF(G26=1,F26,9.99E+307) | I26: =IF(AND(G26=1,F26<0),A26,9999)
A27: 23 | B27: =IF(G27=1,Setup!$B$6+7*(23-1),"") | C27: =IF(G27=1,SUMIF(Grid!$A$4:$A$83,"receipt",Grid!AB$4:AB$83),0) | D27: =IF(G27=1,SUMIF(Grid!$A$4:$A$83,"disbursement",Grid!AB$4:AB$83),0) | E27: =C27-D27 | F27: =F26+E27 | G27: =IF(23<=Setup!$B$5,1,0) | H27: =IF(G27=1,F27,9.99E+307) | I27: =IF(AND(G27=1,F27<0),A27,9999)
A28: 24 | B28: =IF(G28=1,Setup!$B$6+7*(24-1),"") | C28: =IF(G28=1,SUMIF(Grid!$A$4:$A$83,"receipt",Grid!AC$4:AC$83),0) | D28: =IF(G28=1,SUMIF(Grid!$A$4:$A$83,"disbursement",Grid!AC$4:AC$83),0) | E28: =C28-D28 | F28: =F27+E28 | G28: =IF(24<=Setup!$B$5,1,0) | H28: =IF(G28=1,F28,9.99E+307) | I28: =IF(AND(G28=1,F28<0),A28,9999)
A29: 25 | B29: =IF(G29=1,Setup!$B$6+7*(25-1),"") | C29: =IF(G29=1,SUMIF(Grid!$A$4:$A$83,"receipt",Grid!AD$4:AD$83),0) | D29: =IF(G29=1,SUMIF(Grid!$A$4:$A$83,"disbursement",Grid!AD$4:AD$83),0) | E29: =C29-D29 | F29: =F28+E29 | G29: =IF(25<=Setup!$B$5,1,0) | H29: =IF(G29=1,F29,9.99E+307) | I29: =IF(AND(G29=1,F29<0),A29,9999)
A30: 26 | B30: =IF(G30=1,Setup!$B$6+7*(26-1),"") | C30: =IF(G30=1,SUMIF(Grid!$A$4:$A$83,"receipt",Grid!AE$4:AE$83),0) | D30: =IF(G30=1,SUMIF(Grid!$A$4:$A$83,"disbursement",Grid!AE$4:AE$83),0) | E30: =C30-D30 | F30: =F29+E30 | G30: =IF(26<=Setup!$B$5,1,0) | H30: =IF(G30=1,F30,9.99E+307) | I30: =IF(AND(G30=1,F30<0),A30,9999)
A31: 27 | B31: =IF(G31=1,Setup!$B$6+7*(27-1),"") | C31: =IF(G31=1,SUMIF(Grid!$A$4:$A$83,"receipt",Grid!AF$4:AF$83),0) | D31: =IF(G31=1,SUMIF(Grid!$A$4:$A$83,"disbursement",Grid!AF$4:AF$83),0) | E31: =C31-D31 | F31: =F30+E31 | G31: =IF(27<=Setup!$B$5,1,0) | H31: =IF(G31=1,F31,9.99E+307) | I31: =IF(AND(G31=1,F31<0),A31,9999)
A32: 28 | B32: =IF(G32=1,Setup!$B$6+7*(28-1),"") | C32: =IF(G32=1,SUMIF(Grid!$A$4:$A$83,"receipt",Grid!AG$4:AG$83),0) | D32: =IF(G32=1,SUMIF(Grid!$A$4:$A$83,"disbursement",Grid!AG$4:AG$83),0) | E32: =C32-D32 | F32: =F31+E32 | G32: =IF(28<=Setup!$B$5,1,0) | H32: =IF(G32=1,F32,9.99E+307) | I32: =IF(AND(G32=1,F32<0),A32,9999)
A33: 29 | B33: =IF(G33=1,Setup!$B$6+7*(29-1),"") | C33: =IF(G33=1,SUMIF(Grid!$A$4:$A$83,"receipt",Grid!AH$4:AH$83),0) | D33: =IF(G33=1,SUMIF(Grid!$A$4:$A$83,"disbursement",Grid!AH$4:AH$83),0) | E33: =C33-D33 | F33: =F32+E33 | G33: =IF(29<=Setup!$B$5,1,0) | H33: =IF(G33=1,F33,9.99E+307) | I33: =IF(AND(G33=1,F33<0),A33,9999)
A34: 30 | B34: =IF(G34=1,Setup!$B$6+7*(30-1),"") | C34: =IF(G34=1,SUMIF(Grid!$A$4:$A$83,"receipt",Grid!AI$4:AI$83),0) | D34: =IF(G34=1,SUMIF(Grid!$A$4:$A$83,"disbursement",Grid!AI$4:AI$83),0) | E34: =C34-D34 | F34: =F33+E34 | G34: =IF(30<=Setup!$B$5,1,0) | H34: =IF(G34=1,F34,9.99E+307) | I34: =IF(AND(G34=1,F34<0),A34,9999)
A35: 31 | B35: =IF(G35=1,Setup!$B$6+7*(31-1),"") | C35: =IF(G35=1,SUMIF(Grid!$A$4:$A$83,"receipt",Grid!AJ$4:AJ$83),0) | D35: =IF(G35=1,SUMIF(Grid!$A$4:$A$83,"disbursement",Grid!AJ$4:AJ$83),0) | E35: =C35-D35 | F35: =F34+E35 | G35: =IF(31<=Setup!$B$5,1,0) | H35: =IF(G35=1,F35,9.99E+307) | I35: =IF(AND(G35=1,F35<0),A35,9999)
A36: 32 | B36: =IF(G36=1,Setup!$B$6+7*(32-1),"") | C36: =IF(G36=1,SUMIF(Grid!$A$4:$A$83,"receipt",Grid!AK$4:AK$83),0) | D36: =IF(G36=1,SUMIF(Grid!$A$4:$A$83,"disbursement",Grid!AK$4:AK$83),0) | E36: =C36-D36 | F36: =F35+E36 | G36: =IF(32<=Setup!$B$5,1,0) | H36: =IF(G36=1,F36,9.99E+307) | I36: =IF(AND(G36=1,F36<0),A36,9999)
A37: 33 | B37: =IF(G37=1,Setup!$B$6+7*(33-1),"") | C37: =IF(G37=1,SUMIF(Grid!$A$4:$A$83,"receipt",Grid!AL$4:AL$83),0) | D37: =IF(G37=1,SUMIF(Grid!$A$4:$A$83,"disbursement",Grid!AL$4:AL$83),0) | E37: =C37-D37 | F37: =F36+E37 | G37: =IF(33<=Setup!$B$5,1,0) | H37: =IF(G37=1,F37,9.99E+307) | I37: =IF(AND(G37=1,F37<0),A37,9999)
A38: 34 | B38: =IF(G38=1,Setup!$B$6+7*(34-1),"") | C38: =IF(G38=1,SUMIF(Grid!$A$4:$A$83,"receipt",Grid!AM$4:AM$83),0) | D38: =IF(G38=1,SUMIF(Grid!$A$4:$A$83,"disbursement",Grid!AM$4:AM$83),0) | E38: =C38-D38 | F38: =F37+E38 | G38: =IF(34<=Setup!$B$5,1,0) | H38: =IF(G38=1,F38,9.99E+307) | I38: =IF(AND(G38=1,F38<0),A38,9999)
A39: 35 | B39: =IF(G39=1,Setup!$B$6+7*(35-1),"") | C39: =IF(G39=1,SUMIF(Grid!$A$4:$A$83,"receipt",Grid!AN$4:AN$83),0) | D39: =IF(G39=1,SUMIF(Grid!$A$4:$A$83,"disbursement",Grid!AN$4:AN$83),0) | E39: =C39-D39 | F39: =F38+E39 | G39: =IF(35<=Setup!$B$5,1,0) | H39: =IF(G39=1,F39,9.99E+307) | I39: =IF(AND(G39=1,F39<0),A39,9999)
A40: 36 | B40: =IF(G40=1,Setup!$B$6+7*(36-1),"") | C40: =IF(G40=1,SUMIF(Grid!$A$4:$A$83,"receipt",Grid!AO$4:AO$83),0) | D40: =IF(G40=1,SUMIF(Grid!$A$4:$A$83,"disbursement",Grid!AO$4:AO$83),0) | E40: =C40-D40 | F40: =F39+E40 | G40: =IF(36<=Setup!$B$5,1,0) | H40: =IF(G40=1,F40,9.99E+307) | I40: =IF(AND(G40=1,F40<0),A40,9999)
A41: 37 | B41: =IF(G41=1,Setup!$B$6+7*(37-1),"") | C41: =IF(G41=1,SUMIF(Grid!$A$4:$A$83,"receipt",Grid!AP$4:AP$83),0) | D41: =IF(G41=1,SUMIF(Grid!$A$4:$A$83,"disbursement",Grid!AP$4:AP$83),0) | E41: =C41-D41 | F41: =F40+E41 | G41: =IF(37<=Setup!$B$5,1,0) | H41: =IF(G41=1,F41,9.99E+307) | I41: =IF(AND(G41=1,F41<0),A41,9999)
A42: 38 | B42: =IF(G42=1,Setup!$B$6+7*(38-1),"") | C42: =IF(G42=1,SUMIF(Grid!$A$4:$A$83,"receipt",Grid!AQ$4:AQ$83),0) | D42: =IF(G42=1,SUMIF(Grid!$A$4:$A$83,"disbursement",Grid!AQ$4:AQ$83),0) | E42: =C42-D42 | F42: =F41+E42 | G42: =IF(38<=Setup!$B$5,1,0) | H42: =IF(G42=1,F42,9.99E+307) | I42: =IF(AND(G42=1,F42<0),A42,9999)
A43: 39 | B43: =IF(G43=1,Setup!$B$6+7*(39-1),"") | C43: =IF(G43=1,SUMIF(Grid!$A$4:$A$83,"receipt",Grid!AR$4:AR$83),0) | D43: =IF(G43=1,SUMIF(Grid!$A$4:$A$83,"disbursement",Grid!AR$4:AR$83),0) | E43: =C43-D43 | F43: =F42+E43 | G43: =IF(39<=Setup!$B$5,1,0) | H43: =IF(G43=1,F43,9.99E+307) | I43: =IF(AND(G43=1,F43<0),A43,9999)
A44: 40 | B44: =IF(G44=1,Setup!$B$6+7*(40-1),"") | C44: =IF(G44=1,SUMIF(Grid!$A$4:$A$83,"receipt",Grid!AS$4:AS$83),0) | D44: =IF(G44=1,SUMIF(Grid!$A$4:$A$83,"disbursement",Grid!AS$4:AS$83),0) | E44: =C44-D44 | F44: =F43+E44 | G44: =IF(40<=Setup!$B$5,1,0) | H44: =IF(G44=1,F44,9.99E+307) | I44: =IF(AND(G44=1,F44<0),A44,9999)
A45: 41 | B45: =IF(G45=1,Setup!$B$6+7*(41-1),"") | C45: =IF(G45=1,SUMIF(Grid!$A$4:$A$83,"receipt",Grid!AT$4:AT$83),0) | D45: =IF(G45=1,SUMIF(Grid!$A$4:$A$83,"disbursement",Grid!AT$4:AT$83),0) | E45: =C45-D45 | F45: =F44+E45 | G45: =IF(41<=Setup!$B$5,1,0) | H45: =IF(G45=1,F45,9.99E+307) | I45: =IF(AND(G45=1,F45<0),A45,9999)
A46: 42 | B46: =IF(G46=1,Setup!$B$6+7*(42-1),"") | C46: =IF(G46=1,SUMIF(Grid!$A$4:$A$83,"receipt",Grid!AU$4:AU$83),0) | D46: =IF(G46=1,SUMIF(Grid!$A$4:$A$83,"disbursement",Grid!AU$4:AU$83),0) | E46: =C46-D46 | F46: =F45+E46 | G46: =IF(42<=Setup!$B$5,1,0) | H46: =IF(G46=1,F46,9.99E+307) | I46: =IF(AND(G46=1,F46<0),A46,9999)
A47: 43 | B47: =IF(G47=1,Setup!$B$6+7*(43-1),"") | C47: =IF(G47=1,SUMIF(Grid!$A$4:$A$83,"receipt",Grid!AV$4:AV$83),0) | D47: =IF(G47=1,SUMIF(Grid!$A$4:$A$83,"disbursement",Grid!AV$4:AV$83),0) | E47: =C47-D47 | F47: =F46+E47 | G47: =IF(43<=Setup!$B$5,1,0) | H47: =IF(G47=1,F47,9.99E+307) | I47: =IF(AND(G47=1,F47<0),A47,9999)
A48: 44 | B48: =IF(G48=1,Setup!$B$6+7*(44-1),"") | C48: =IF(G48=1,SUMIF(Grid!$A$4:$A$83,"receipt",Grid!AW$4:AW$83),0) | D48: =IF(G48=1,SUMIF(Grid!$A$4:$A$83,"disbursement",Grid!AW$4:AW$83),0) | E48: =C48-D48 | F48: =F47+E48 | G48: =IF(44<=Setup!$B$5,1,0) | H48: =IF(G48=1,F48,9.99E+307) | I48: =IF(AND(G48=1,F48<0),A48,9999)
A49: 45 | B49: =IF(G49=1,Setup!$B$6+7*(45-1),"") | C49: =IF(G49=1,SUMIF(Grid!$A$4:$A$83,"receipt",Grid!AX$4:AX$83),0) | D49: =IF(G49=1,SUMIF(Grid!$A$4:$A$83,"disbursement",Grid!AX$4:AX$83),0) | E49: =C49-D49 | F49: =F48+E49 | G49: =IF(45<=Setup!$B$5,1,0) | H49: =IF(G49=1,F49,9.99E+307) | I49: =IF(AND(G49=1,F49<0),A49,9999)
A50: 46 | B50: =IF(G50=1,Setup!$B$6+7*(46-1),"") | C50: =IF(G50=1,SUMIF(Grid!$A$4:$A$83,"receipt",Grid!AY$4:AY$83),0) | D50: =IF(G50=1,SUMIF(Grid!$A$4:$A$83,"disbursement",Grid!AY$4:AY$83),0) | E50: =C50-D50 | F50: =F49+E50 | G50: =IF(46<=Setup!$B$5,1,0) | H50: =IF(G50=1,F50,9.99E+307) | I50: =IF(AND(G50=1,F50<0),A50,9999)
A51: 47 | B51: =IF(G51=1,Setup!$B$6+7*(47-1),"") | C51: =IF(G51=1,SUMIF(Grid!$A$4:$A$83,"receipt",Grid!AZ$4:AZ$83),0) | D51: =IF(G51=1,SUMIF(Grid!$A$4:$A$83,"disbursement",Grid!AZ$4:AZ$83),0) | E51: =C51-D51 | F51: =F50+E51 | G51: =IF(47<=Setup!$B$5,1,0) | H51: =IF(G51=1,F51,9.99E+307) | I51: =IF(AND(G51=1,F51<0),A51,9999)
A52: 48 | B52: =IF(G52=1,Setup!$B$6+7*(48-1),"") | C52: =IF(G52=1,SUMIF(Grid!$A$4:$A$83,"receipt",Grid!BA$4:BA$83),0) | D52: =IF(G52=1,SUMIF(Grid!$A$4:$A$83,"disbursement",Grid!BA$4:BA$83),0) | E52: =C52-D52 | F52: =F51+E52 | G52: =IF(48<=Setup!$B$5,1,0) | H52: =IF(G52=1,F52,9.99E+307) | I52: =IF(AND(G52=1,F52<0),A52,9999)
A53: 49 | B53: =IF(G53=1,Setup!$B$6+7*(49-1),"") | C53: =IF(G53=1,SUMIF(Grid!$A$4:$A$83,"receipt",Grid!BB$4:BB$83),0) | D53: =IF(G53=1,SUMIF(Grid!$A$4:$A$83,"disbursement",Grid!BB$4:BB$83),0) | E53: =C53-D53 | F53: =F52+E53 | G53: =IF(49<=Setup!$B$5,1,0) | H53: =IF(G53=1,F53,9.99E+307) | I53: =IF(AND(G53=1,F53<0),A53,9999)
A54: 50 | B54: =IF(G54=1,Setup!$B$6+7*(50-1),"") | C54: =IF(G54=1,SUMIF(Grid!$A$4:$A$83,"receipt",Grid!BC$4:BC$83),0) | D54: =IF(G54=1,SUMIF(Grid!$A$4:$A$83,"disbursement",Grid!BC$4:BC$83),0) | E54: =C54-D54 | F54: =F53+E54 | G54: =IF(50<=Setup!$B$5,1,0) | H54: =IF(G54=1,F54,9.99E+307) | I54: =IF(AND(G54=1,F54<0),A54,9999)
A55: 51 | B55: =IF(G55=1,Setup!$B$6+7*(51-1),"") | C55: =IF(G55=1,SUMIF(Grid!$A$4:$A$83,"receipt",Grid!BD$4:BD$83),0) | D55: =IF(G55=1,SUMIF(Grid!$A$4:$A$83,"disbursement",Grid!BD$4:BD$83),0) | E55: =C55-D55 | F55: =F54+E55 | G55: =IF(51<=Setup!$B$5,1,0) | H55: =IF(G55=1,F55,9.99E+307) | I55: =IF(AND(G55=1,F55<0),A55,9999)
A56: 52 | B56: =IF(G56=1,Setup!$B$6+7*(52-1),"") | C56: =IF(G56=1,SUMIF(Grid!$A$4:$A$83,"receipt",Grid!BE$4:BE$83),0) | D56: =IF(G56=1,SUMIF(Grid!$A$4:$A$83,"disbursement",Grid!BE$4:BE$83),0) | E56: =C56-D56 | F56: =F55+E56 | G56: =IF(52<=Setup!$B$5,1,0) | H56: =IF(G56=1,F56,9.99E+307) | I56: =IF(AND(G56=1,F56<0),A56,9999)

Sheet Runway
A1: Runway summary (runway_summary) + credit-line sizing
A4: min_cash (trough) | B4: =MIN(Weekly!$H$5:$H$56)
A5: min_week (first week at trough) | B5: =MATCH(B4,Weekly!$H$5:$H$56,0)
A6: first_negative_week (blank = none) | B6: =IF(MIN(Weekly!$I$5:$I$56)=9999,"",MIN(Weekly!$I$5:$I$56))
A7: trough week starting | B7: =INDEX(Weekly!$B$5:$B$56,1,1)+7*(B5-1)
A8: ending cash at horizon | B8: =INDEX(Weekly!$F$5:$F$56,Setup!$B$5,1)
A9: draw needed at trough (0 if never negative) | B9: =MAX(0,-B4)
A10: suggested working-capital line (trough x (1+buffer)) | B10: =ROUND(B9*(1+Setup!$B$7),-3)
A11: weeks of warning before first negative week | B11: =IF(B6="","n/a",B6-1)
A13: Report lines (copy verbatim)
A14: ="- **Trough:** "&IF(B4<0,"-","")&Setup!B8&TEXT(ABS(B4),"#,##0")&" (week "&B5&")"
A15: ="- **First negative week:** "&IF(B6="","none","week "&B6)
A16: ="- **Recommended action:** "&IF(B9=0,"no draw needed inside the horizon","arrange a line of at least "&Setup!B8&TEXT(B10,"#,##0")&" before week "&B6)

Sheet DateToWeek
A1: DateToWeek - convert due dates to week numbers (week 1 = Setup start date)
A4: item | B4: due date | C4: week number | D4: inside horizon?
A5: GSTR-3B / GST cash payment (monthly filer, 20th) | C5: =IF(B5="","",INT((B5-Setup!$B$6)/7)+1) | D5: =IF(C5="","",IF(AND(C5>=1,C5<=Setup!$B$5),"yes","no"))
A6: TDS/TCS deposit (7th of next month) | C6: =IF(B6="","",INT((B6-Setup!$B$6)/7)+1) | D6: =IF(C6="","",IF(AND(C6>=1,C6<=Setup!$B$5),"yes","no"))
A7: PF (EPF) remittance (15th) | C7: =IF(B7="","",INT((B7-Setup!$B$6)/7)+1) | D7: =IF(C7="","",IF(AND(C7>=1,C7<=Setup!$B$5),"yes","no"))
A8: ESI contribution (15th) | C8: =IF(B8="","",INT((B8-Setup!$B$6)/7)+1) | D8: =IF(C8="","",IF(AND(C8>=1,C8<=Setup!$B$5),"yes","no"))
A9: Advance tax instalment (15 Jun / 15 Sep / 15 Dec / 15 Mar) | C9: =IF(B9="","",INT((B9-Setup!$B$6)/7)+1) | D9: =IF(C9="","",IF(AND(C9>=1,C9<=Setup!$B$5),"yes","no"))
A10: Tamil Nadu Professional Tax (half-yearly, employer remits) | C10: =IF(B10="","",INT((B10-Setup!$B$6)/7)+1) | D10: =IF(C10="","",IF(AND(C10>=1,C10<=Setup!$B$5),"yes","no"))
A11: Salary payout (last working day / 1st) | C11: =IF(B11="","",INT((B11-Setup!$B$6)/7)+1) | D11: =IF(C11="","",IF(AND(C11>=1,C11<=Setup!$B$5),"yes","no"))
A12: Customer collection (invoice date + credit days) | C12: =IF(B12="","",INT((B12-Setup!$B$6)/7)+1) | D12: =IF(C12="","",IF(AND(C12>=1,C12<=Setup!$B$5),"yes","no"))
A13: MSME supplier payment (max 45 days from acceptance, s.43B(h)) | C13: =IF(B13="","",INT((B13-Setup!$B$6)/7)+1) | D13: =IF(C13="","",IF(AND(C13>=1,C13<=Setup!$B$5),"yes","no"))
C14: =IF(B14="","",INT((B14-Setup!$B$6)/7)+1) | D14: =IF(C14="","",IF(AND(C14>=1,C14<=Setup!$B$5),"yes","no"))
C15: =IF(B15="","",INT((B15-Setup!$B$6)/7)+1) | D15: =IF(C15="","",IF(AND(C15>=1,C15<=Setup!$B$5),"yes","no"))
C16: =IF(B16="","",INT((B16-Setup!$B$6)/7)+1) | D16: =IF(C16="","",IF(AND(C16>=1,C16<=Setup!$B$5),"yes","no"))
C17: =IF(B17="","",INT((B17-Setup!$B$6)/7)+1) | D17: =IF(C17="","",IF(AND(C17>=1,C17<=Setup!$B$5),"yes","no"))
C18: =IF(B18="","",INT((B18-Setup!$B$6)/7)+1) | D18: =IF(C18="","",IF(AND(C18>=1,C18<=Setup!$B$5),"yes","no"))
C19: =IF(B19="","",INT((B19-Setup!$B$6)/7)+1) | D19: =IF(C19="","",IF(AND(C19>=1,C19<=Setup!$B$5),"yes","no"))
C20: =IF(B20="","",INT((B20-Setup!$B$6)/7)+1) | D20: =IF(C20="","",IF(AND(C20>=1,C20<=Setup!$B$5),"yes","no"))
C21: =IF(B21="","",INT((B21-Setup!$B$6)/7)+1) | D21: =IF(C21="","",IF(AND(C21>=1,C21<=Setup!$B$5),"yes","no"))
C22: =IF(B22="","",INT((B22-Setup!$B$6)/7)+1) | D22: =IF(C22="","",IF(AND(C22>=1,C22<=Setup!$B$5),"yes","no"))
C23: =IF(B23="","",INT((B23-Setup!$B$6)/7)+1) | D23: =IF(C23="","",IF(AND(C23>=1,C23<=Setup!$B$5),"yes","no"))
C24: =IF(B24="","",INT((B24-Setup!$B$6)/7)+1) | D24: =IF(C24="","",IF(AND(C24>=1,C24<=Setup!$B$5),"yes","no"))
C25: =IF(B25="","",INT((B25-Setup!$B$6)/7)+1) | D25: =IF(C25="","",IF(AND(C25>=1,C25<=Setup!$B$5),"yes","no"))
... C34: =IF(B34="","",INT((B34-Setup!$B$6)/7)+1) | D34: =IF(C34="","",IF(AND(C34>=1,C34<=Setup!$B$5),"yes","no"))
