Workbook
Name pareto_breakpoint: 'Ranked'!$E$3

Sheet README
A1: K06 · SKU Profitability & Pareto (no-code kernel)
A3: Replaces openfpa: pyfpa.analysis.sku (Sku, sku_profitability, pareto_breakpoint) and the generated sku-profitability skill.
A4: Enter annual units, selling price and unit cost per SKU (up to 300). Revenue = units x price; COGS = units x unit cost; gross profit; gross margin (0 if revenue 0).
A5: 'Ranked' sorts by gross profit DESC (ties keep input order), adds revenue share and cumulative revenue % (Pareto). pareto_breakpoint = number of SKUs whose cumulative revenue first reaches the threshold (default 80%).
A6: Judgment: gross margin here is price minus unit cost only - it excludes marketplace commission (Amazon.in/Flipkart), GST input-credit leakage, returns, freight and fulfilment. Weigh contribution rupees, not just %.

Sheet Checks
A1: Checks - OVERALL must be PASS
B3: OVERALL | C3: =IF(COUNTIF(C5:C7,"PASS")=COUNT(A5:A7),"PASS","FAIL") | D3: =COUNTIF(C5:C7,"PASS")&" pass / "&COUNTIF(C5:C7,"FAIL")&" fail / "&(COUNT(A5:A7)-COUNTIF(C5:C7,"PASS")-COUNTIF(C5:C7,"FAIL"))&" error"
A4: # | B4: check | C4: result | D4: detail
A5: 1 | B5: units, price, unit_cost >= 0 for every SKU | C5: =IF(AND(COUNTIF(SKUs!B5:D304,"<0")=0),"PASS","FAIL")
A6: 2 | B6: SKU names unique | C6: =IF(SUMPRODUCT((SKUs!A5:A304<>"")*(COUNTIF(SKUs!A5:A304,SKUs!A5:A304)>1))=0,"PASS","FAIL")
A7: 3 | B7: cumulative revenue % ends at 100% (when revenue > 0) | C7: =IF(OR(SUM(SKUs!E5:E304)=0,ABS(MAX(Ranked!I6:I305)-1)<1E-9),"PASS","FAIL")

Sheet SKUs
A1: SKU inputs
A4: sku name | B4: units (annual) | C4: price | D4: unit_cost | E4: revenue | F4: cogs | G4: gross_profit | H4: gross_margin | I4: rank by GP (desc, stable)
E5: =IF(A5="","",B5*C5) | F5: =IF(A5="","",B5*D5) | G5: =IF(A5="","",E5-F5) | H5: =IF(A5="","",IF(E5=0,0,G5/E5)) | I5: =IF(A5="","",COUNTIF($G$5:$G$304,">"&G5)+COUNTIF($G$5:G5,G5))
E6: =IF(A6="","",B6*C6) | F6: =IF(A6="","",B6*D6) | G6: =IF(A6="","",E6-F6) | H6: =IF(A6="","",IF(E6=0,0,G6/E6)) | I6: =IF(A6="","",COUNTIF($G$5:$G$304,">"&G6)+COUNTIF($G$5:G6,G6))
E7: =IF(A7="","",B7*C7) | F7: =IF(A7="","",B7*D7) | G7: =IF(A7="","",E7-F7) | H7: =IF(A7="","",IF(E7=0,0,G7/E7)) | I7: =IF(A7="","",COUNTIF($G$5:$G$304,">"&G7)+COUNTIF($G$5:G7,G7))
E8: =IF(A8="","",B8*C8) | F8: =IF(A8="","",B8*D8) | G8: =IF(A8="","",E8-F8) | H8: =IF(A8="","",IF(E8=0,0,G8/E8)) | I8: =IF(A8="","",COUNTIF($G$5:$G$304,">"&G8)+COUNTIF($G$5:G8,G8))
E9: =IF(A9="","",B9*C9) | F9: =IF(A9="","",B9*D9) | G9: =IF(A9="","",E9-F9) | H9: =IF(A9="","",IF(E9=0,0,G9/E9)) | I9: =IF(A9="","",COUNTIF($G$5:$G$304,">"&G9)+COUNTIF($G$5:G9,G9))
E10: =IF(A10="","",B10*C10) | F10: =IF(A10="","",B10*D10) | G10: =IF(A10="","",E10-F10) | H10: =IF(A10="","",IF(E10=0,0,G10/E10)) | I10: =IF(A10="","",COUNTIF($G$5:$G$304,">"&G10)+COUNTIF($G$5:G10,G10))
E11: =IF(A11="","",B11*C11) | F11: =IF(A11="","",B11*D11) | G11: =IF(A11="","",E11-F11) | H11: =IF(A11="","",IF(E11=0,0,G11/E11)) | I11: =IF(A11="","",COUNTIF($G$5:$G$304,">"&G11)+COUNTIF($G$5:G11,G11))
E12: =IF(A12="","",B12*C12) | F12: =IF(A12="","",B12*D12) | G12: =IF(A12="","",E12-F12) | H12: =IF(A12="","",IF(E12=0,0,G12/E12)) | I12: =IF(A12="","",COUNTIF($G$5:$G$304,">"&G12)+COUNTIF($G$5:G12,G12))
E13: =IF(A13="","",B13*C13) | F13: =IF(A13="","",B13*D13) | G13: =IF(A13="","",E13-F13) | H13: =IF(A13="","",IF(E13=0,0,G13/E13)) | I13: =IF(A13="","",COUNTIF($G$5:$G$304,">"&G13)+COUNTIF($G$5:G13,G13))
E14: =IF(A14="","",B14*C14) | F14: =IF(A14="","",B14*D14) | G14: =IF(A14="","",E14-F14) | H14: =IF(A14="","",IF(E14=0,0,G14/E14)) | I14: =IF(A14="","",COUNTIF($G$5:$G$304,">"&G14)+COUNTIF($G$5:G14,G14))
E15: =IF(A15="","",B15*C15) | F15: =IF(A15="","",B15*D15) | G15: =IF(A15="","",E15-F15) | H15: =IF(A15="","",IF(E15=0,0,G15/E15)) | I15: =IF(A15="","",COUNTIF($G$5:$G$304,">"&G15)+COUNTIF($G$5:G15,G15))
E16: =IF(A16="","",B16*C16) | F16: =IF(A16="","",B16*D16) | G16: =IF(A16="","",E16-F16) | H16: =IF(A16="","",IF(E16=0,0,G16/E16)) | I16: =IF(A16="","",COUNTIF($G$5:$G$304,">"&G16)+COUNTIF($G$5:G16,G16))
... E304: =IF(A304="","",B304*C304) | F304: =IF(A304="","",B304*D304) | G304: =IF(A304="","",E304-F304) | H304: =IF(A304="","",IF(E304=0,0,G304/E304)) | I304: =IF(A304="","",COUNTIF($G$5:$G$304,">"&G304)+COUNTIF($G$5:G304,G304))

Sheet Ranked
A1: Ranked by gross profit (sku_profitability output)
A3: Pareto threshold | B3: 0.8 | D3: pareto_breakpoint (SKU count) | E3: =IF(COUNT(A6:A305)=0,0,IFERROR(MATCH(1,J6:J305,0),COUNT(A6:A305)))
A5: rank | B5: sku | C5: units | D5: revenue | E5: cogs | F5: gross_profit | G5: gross_margin | H5: revenue_share | I5: cumulative_revenue_pct | J5: reaches threshold?
A6: =IF(1>COUNT(SKUs!$I$5:$I$304),"",1) | B6: =IF(A6="","",INDEX(SKUs!$A$5:$A$304,MATCH(A6,SKUs!$I$5:$I$304,0))) | C6: =IF(A6="","",INDEX(SKUs!$B$5:$B$304,MATCH(A6,SKUs!$I$5:$I$304,0))) | D6: =IF(A6="","",INDEX(SKUs!$E$5:$E$304,MATCH(A6,SKUs!$I$5:$I$304,0))) | E6: =IF(A6="","",INDEX(SKUs!$F$5:$F$304,MATCH(A6,SKUs!$I$5:$I$304,0))) | F6: =IF(A6="","",INDEX(SKUs!$G$5:$G$304,MATCH(A6,SKUs!$I$5:$I$304,0))) | G6: =IF(A6="","",INDEX(SKUs!$H$5:$H$304,MATCH(A6,SKUs!$I$5:$I$304,0))) | H6: =IF(A6="","",IF(SUM(SKUs!$E$5:$E$304)=0,0,D6/SUM(SKUs!$E$5:$E$304))) | I6: =IF(A6="","",SUM($H$6:H6)) | J6: =IF(A6="","",IF(I6>=$B$3,1,0))
A7: =IF(2>COUNT(SKUs!$I$5:$I$304),"",2) | B7: =IF(A7="","",INDEX(SKUs!$A$5:$A$304,MATCH(A7,SKUs!$I$5:$I$304,0))) | C7: =IF(A7="","",INDEX(SKUs!$B$5:$B$304,MATCH(A7,SKUs!$I$5:$I$304,0))) | D7: =IF(A7="","",INDEX(SKUs!$E$5:$E$304,MATCH(A7,SKUs!$I$5:$I$304,0))) | E7: =IF(A7="","",INDEX(SKUs!$F$5:$F$304,MATCH(A7,SKUs!$I$5:$I$304,0))) | F7: =IF(A7="","",INDEX(SKUs!$G$5:$G$304,MATCH(A7,SKUs!$I$5:$I$304,0))) | G7: =IF(A7="","",INDEX(SKUs!$H$5:$H$304,MATCH(A7,SKUs!$I$5:$I$304,0))) | H7: =IF(A7="","",IF(SUM(SKUs!$E$5:$E$304)=0,0,D7/SUM(SKUs!$E$5:$E$304))) | I7: =IF(A7="","",SUM($H$6:H7)) | J7: =IF(A7="","",IF(I7>=$B$3,1,0))
A8: =IF(3>COUNT(SKUs!$I$5:$I$304),"",3) | B8: =IF(A8="","",INDEX(SKUs!$A$5:$A$304,MATCH(A8,SKUs!$I$5:$I$304,0))) | C8: =IF(A8="","",INDEX(SKUs!$B$5:$B$304,MATCH(A8,SKUs!$I$5:$I$304,0))) | D8: =IF(A8="","",INDEX(SKUs!$E$5:$E$304,MATCH(A8,SKUs!$I$5:$I$304,0))) | E8: =IF(A8="","",INDEX(SKUs!$F$5:$F$304,MATCH(A8,SKUs!$I$5:$I$304,0))) | F8: =IF(A8="","",INDEX(SKUs!$G$5:$G$304,MATCH(A8,SKUs!$I$5:$I$304,0))) | G8: =IF(A8="","",INDEX(SKUs!$H$5:$H$304,MATCH(A8,SKUs!$I$5:$I$304,0))) | H8: =IF(A8="","",IF(SUM(SKUs!$E$5:$E$304)=0,0,D8/SUM(SKUs!$E$5:$E$304))) | I8: =IF(A8="","",SUM($H$6:H8)) | J8: =IF(A8="","",IF(I8>=$B$3,1,0))
A9: =IF(4>COUNT(SKUs!$I$5:$I$304),"",4) | B9: =IF(A9="","",INDEX(SKUs!$A$5:$A$304,MATCH(A9,SKUs!$I$5:$I$304,0))) | C9: =IF(A9="","",INDEX(SKUs!$B$5:$B$304,MATCH(A9,SKUs!$I$5:$I$304,0))) | D9: =IF(A9="","",INDEX(SKUs!$E$5:$E$304,MATCH(A9,SKUs!$I$5:$I$304,0))) | E9: =IF(A9="","",INDEX(SKUs!$F$5:$F$304,MATCH(A9,SKUs!$I$5:$I$304,0))) | F9: =IF(A9="","",INDEX(SKUs!$G$5:$G$304,MATCH(A9,SKUs!$I$5:$I$304,0))) | G9: =IF(A9="","",INDEX(SKUs!$H$5:$H$304,MATCH(A9,SKUs!$I$5:$I$304,0))) | H9: =IF(A9="","",IF(SUM(SKUs!$E$5:$E$304)=0,0,D9/SUM(SKUs!$E$5:$E$304))) | I9: =IF(A9="","",SUM($H$6:H9)) | J9: =IF(A9="","",IF(I9>=$B$3,1,0))
A10: =IF(5>COUNT(SKUs!$I$5:$I$304),"",5) | B10: =IF(A10="","",INDEX(SKUs!$A$5:$A$304,MATCH(A10,SKUs!$I$5:$I$304,0))) | C10: =IF(A10="","",INDEX(SKUs!$B$5:$B$304,MATCH(A10,SKUs!$I$5:$I$304,0))) | D10: =IF(A10="","",INDEX(SKUs!$E$5:$E$304,MATCH(A10,SKUs!$I$5:$I$304,0))) | E10: =IF(A10="","",INDEX(SKUs!$F$5:$F$304,MATCH(A10,SKUs!$I$5:$I$304,0))) | F10: =IF(A10="","",INDEX(SKUs!$G$5:$G$304,MATCH(A10,SKUs!$I$5:$I$304,0))) | G10: =IF(A10="","",INDEX(SKUs!$H$5:$H$304,MATCH(A10,SKUs!$I$5:$I$304,0))) | H10: =IF(A10="","",IF(SUM(SKUs!$E$5:$E$304)=0,0,D10/SUM(SKUs!$E$5:$E$304))) | I10: =IF(A10="","",SUM($H$6:H10)) | J10: =IF(A10="","",IF(I10>=$B$3,1,0))
A11: =IF(6>COUNT(SKUs!$I$5:$I$304),"",6) | B11: =IF(A11="","",INDEX(SKUs!$A$5:$A$304,MATCH(A11,SKUs!$I$5:$I$304,0))) | C11: =IF(A11="","",INDEX(SKUs!$B$5:$B$304,MATCH(A11,SKUs!$I$5:$I$304,0))) | D11: =IF(A11="","",INDEX(SKUs!$E$5:$E$304,MATCH(A11,SKUs!$I$5:$I$304,0))) | E11: =IF(A11="","",INDEX(SKUs!$F$5:$F$304,MATCH(A11,SKUs!$I$5:$I$304,0))) | F11: =IF(A11="","",INDEX(SKUs!$G$5:$G$304,MATCH(A11,SKUs!$I$5:$I$304,0))) | G11: =IF(A11="","",INDEX(SKUs!$H$5:$H$304,MATCH(A11,SKUs!$I$5:$I$304,0))) | H11: =IF(A11="","",IF(SUM(SKUs!$E$5:$E$304)=0,0,D11/SUM(SKUs!$E$5:$E$304))) | I11: =IF(A11="","",SUM($H$6:H11)) | J11: =IF(A11="","",IF(I11>=$B$3,1,0))
A12: =IF(7>COUNT(SKUs!$I$5:$I$304),"",7) | B12: =IF(A12="","",INDEX(SKUs!$A$5:$A$304,MATCH(A12,SKUs!$I$5:$I$304,0))) | C12: =IF(A12="","",INDEX(SKUs!$B$5:$B$304,MATCH(A12,SKUs!$I$5:$I$304,0))) | D12: =IF(A12="","",INDEX(SKUs!$E$5:$E$304,MATCH(A12,SKUs!$I$5:$I$304,0))) | E12: =IF(A12="","",INDEX(SKUs!$F$5:$F$304,MATCH(A12,SKUs!$I$5:$I$304,0))) | F12: =IF(A12="","",INDEX(SKUs!$G$5:$G$304,MATCH(A12,SKUs!$I$5:$I$304,0))) | G12: =IF(A12="","",INDEX(SKUs!$H$5:$H$304,MATCH(A12,SKUs!$I$5:$I$304,0))) | H12: =IF(A12="","",IF(SUM(SKUs!$E$5:$E$304)=0,0,D12/SUM(SKUs!$E$5:$E$304))) | I12: =IF(A12="","",SUM($H$6:H12)) | J12: =IF(A12="","",IF(I12>=$B$3,1,0))
A13: =IF(8>COUNT(SKUs!$I$5:$I$304),"",8) | B13: =IF(A13="","",INDEX(SKUs!$A$5:$A$304,MATCH(A13,SKUs!$I$5:$I$304,0))) | C13: =IF(A13="","",INDEX(SKUs!$B$5:$B$304,MATCH(A13,SKUs!$I$5:$I$304,0))) | D13: =IF(A13="","",INDEX(SKUs!$E$5:$E$304,MATCH(A13,SKUs!$I$5:$I$304,0))) | E13: =IF(A13="","",INDEX(SKUs!$F$5:$F$304,MATCH(A13,SKUs!$I$5:$I$304,0))) | F13: =IF(A13="","",INDEX(SKUs!$G$5:$G$304,MATCH(A13,SKUs!$I$5:$I$304,0))) | G13: =IF(A13="","",INDEX(SKUs!$H$5:$H$304,MATCH(A13,SKUs!$I$5:$I$304,0))) | H13: =IF(A13="","",IF(SUM(SKUs!$E$5:$E$304)=0,0,D13/SUM(SKUs!$E$5:$E$304))) | I13: =IF(A13="","",SUM($H$6:H13)) | J13: =IF(A13="","",IF(I13>=$B$3,1,0))
A14: =IF(9>COUNT(SKUs!$I$5:$I$304),"",9) | B14: =IF(A14="","",INDEX(SKUs!$A$5:$A$304,MATCH(A14,SKUs!$I$5:$I$304,0))) | C14: =IF(A14="","",INDEX(SKUs!$B$5:$B$304,MATCH(A14,SKUs!$I$5:$I$304,0))) | D14: =IF(A14="","",INDEX(SKUs!$E$5:$E$304,MATCH(A14,SKUs!$I$5:$I$304,0))) | E14: =IF(A14="","",INDEX(SKUs!$F$5:$F$304,MATCH(A14,SKUs!$I$5:$I$304,0))) | F14: =IF(A14="","",INDEX(SKUs!$G$5:$G$304,MATCH(A14,SKUs!$I$5:$I$304,0))) | G14: =IF(A14="","",INDEX(SKUs!$H$5:$H$304,MATCH(A14,SKUs!$I$5:$I$304,0))) | H14: =IF(A14="","",IF(SUM(SKUs!$E$5:$E$304)=0,0,D14/SUM(SKUs!$E$5:$E$304))) | I14: =IF(A14="","",SUM($H$6:H14)) | J14: =IF(A14="","",IF(I14>=$B$3,1,0))
A15: =IF(10>COUNT(SKUs!$I$5:$I$304),"",10) | B15: =IF(A15="","",INDEX(SKUs!$A$5:$A$304,MATCH(A15,SKUs!$I$5:$I$304,0))) | C15: =IF(A15="","",INDEX(SKUs!$B$5:$B$304,MATCH(A15,SKUs!$I$5:$I$304,0))) | D15: =IF(A15="","",INDEX(SKUs!$E$5:$E$304,MATCH(A15,SKUs!$I$5:$I$304,0))) | E15: =IF(A15="","",INDEX(SKUs!$F$5:$F$304,MATCH(A15,SKUs!$I$5:$I$304,0))) | F15: =IF(A15="","",INDEX(SKUs!$G$5:$G$304,MATCH(A15,SKUs!$I$5:$I$304,0))) | G15: =IF(A15="","",INDEX(SKUs!$H$5:$H$304,MATCH(A15,SKUs!$I$5:$I$304,0))) | H15: =IF(A15="","",IF(SUM(SKUs!$E$5:$E$304)=0,0,D15/SUM(SKUs!$E$5:$E$304))) | I15: =IF(A15="","",SUM($H$6:H15)) | J15: =IF(A15="","",IF(I15>=$B$3,1,0))
A16: =IF(11>COUNT(SKUs!$I$5:$I$304),"",11) | B16: =IF(A16="","",INDEX(SKUs!$A$5:$A$304,MATCH(A16,SKUs!$I$5:$I$304,0))) | C16: =IF(A16="","",INDEX(SKUs!$B$5:$B$304,MATCH(A16,SKUs!$I$5:$I$304,0))) | D16: =IF(A16="","",INDEX(SKUs!$E$5:$E$304,MATCH(A16,SKUs!$I$5:$I$304,0))) | E16: =IF(A16="","",INDEX(SKUs!$F$5:$F$304,MATCH(A16,SKUs!$I$5:$I$304,0))) | F16: =IF(A16="","",INDEX(SKUs!$G$5:$G$304,MATCH(A16,SKUs!$I$5:$I$304,0))) | G16: =IF(A16="","",INDEX(SKUs!$H$5:$H$304,MATCH(A16,SKUs!$I$5:$I$304,0))) | H16: =IF(A16="","",IF(SUM(SKUs!$E$5:$E$304)=0,0,D16/SUM(SKUs!$E$5:$E$304))) | I16: =IF(A16="","",SUM($H$6:H16)) | J16: =IF(A16="","",IF(I16>=$B$3,1,0))
A17: =IF(12>COUNT(SKUs!$I$5:$I$304),"",12) | B17: =IF(A17="","",INDEX(SKUs!$A$5:$A$304,MATCH(A17,SKUs!$I$5:$I$304,0))) | C17: =IF(A17="","",INDEX(SKUs!$B$5:$B$304,MATCH(A17,SKUs!$I$5:$I$304,0))) | D17: =IF(A17="","",INDEX(SKUs!$E$5:$E$304,MATCH(A17,SKUs!$I$5:$I$304,0))) | E17: =IF(A17="","",INDEX(SKUs!$F$5:$F$304,MATCH(A17,SKUs!$I$5:$I$304,0))) | F17: =IF(A17="","",INDEX(SKUs!$G$5:$G$304,MATCH(A17,SKUs!$I$5:$I$304,0))) | G17: =IF(A17="","",INDEX(SKUs!$H$5:$H$304,MATCH(A17,SKUs!$I$5:$I$304,0))) | H17: =IF(A17="","",IF(SUM(SKUs!$E$5:$E$304)=0,0,D17/SUM(SKUs!$E$5:$E$304))) | I17: =IF(A17="","",SUM($H$6:H17)) | J17: =IF(A17="","",IF(I17>=$B$3,1,0))
A18: =IF(13>COUNT(SKUs!$I$5:$I$304),"",13) | B18: =IF(A18="","",INDEX(SKUs!$A$5:$A$304,MATCH(A18,SKUs!$I$5:$I$304,0))) | C18: =IF(A18="","",INDEX(SKUs!$B$5:$B$304,MATCH(A18,SKUs!$I$5:$I$304,0))) | D18: =IF(A18="","",INDEX(SKUs!$E$5:$E$304,MATCH(A18,SKUs!$I$5:$I$304,0))) | E18: =IF(A18="","",INDEX(SKUs!$F$5:$F$304,MATCH(A18,SKUs!$I$5:$I$304,0))) | F18: =IF(A18="","",INDEX(SKUs!$G$5:$G$304,MATCH(A18,SKUs!$I$5:$I$304,0))) | G18: =IF(A18="","",INDEX(SKUs!$H$5:$H$304,MATCH(A18,SKUs!$I$5:$I$304,0))) | H18: =IF(A18="","",IF(SUM(SKUs!$E$5:$E$304)=0,0,D18/SUM(SKUs!$E$5:$E$304))) | I18: =IF(A18="","",SUM($H$6:H18)) | J18: =IF(A18="","",IF(I18>=$B$3,1,0))
A19: =IF(14>COUNT(SKUs!$I$5:$I$304),"",14) | B19: =IF(A19="","",INDEX(SKUs!$A$5:$A$304,MATCH(A19,SKUs!$I$5:$I$304,0))) | C19: =IF(A19="","",INDEX(SKUs!$B$5:$B$304,MATCH(A19,SKUs!$I$5:$I$304,0))) | D19: =IF(A19="","",INDEX(SKUs!$E$5:$E$304,MATCH(A19,SKUs!$I$5:$I$304,0))) | E19: =IF(A19="","",INDEX(SKUs!$F$5:$F$304,MATCH(A19,SKUs!$I$5:$I$304,0))) | F19: =IF(A19="","",INDEX(SKUs!$G$5:$G$304,MATCH(A19,SKUs!$I$5:$I$304,0))) | G19: =IF(A19="","",INDEX(SKUs!$H$5:$H$304,MATCH(A19,SKUs!$I$5:$I$304,0))) | H19: =IF(A19="","",IF(SUM(SKUs!$E$5:$E$304)=0,0,D19/SUM(SKUs!$E$5:$E$304))) | I19: =IF(A19="","",SUM($H$6:H19)) | J19: =IF(A19="","",IF(I19>=$B$3,1,0))
A20: =IF(15>COUNT(SKUs!$I$5:$I$304),"",15) | B20: =IF(A20="","",INDEX(SKUs!$A$5:$A$304,MATCH(A20,SKUs!$I$5:$I$304,0))) | C20: =IF(A20="","",INDEX(SKUs!$B$5:$B$304,MATCH(A20,SKUs!$I$5:$I$304,0))) | D20: =IF(A20="","",INDEX(SKUs!$E$5:$E$304,MATCH(A20,SKUs!$I$5:$I$304,0))) | E20: =IF(A20="","",INDEX(SKUs!$F$5:$F$304,MATCH(A20,SKUs!$I$5:$I$304,0))) | F20: =IF(A20="","",INDEX(SKUs!$G$5:$G$304,MATCH(A20,SKUs!$I$5:$I$304,0))) | G20: =IF(A20="","",INDEX(SKUs!$H$5:$H$304,MATCH(A20,SKUs!$I$5:$I$304,0))) | H20: =IF(A20="","",IF(SUM(SKUs!$E$5:$E$304)=0,0,D20/SUM(SKUs!$E$5:$E$304))) | I20: =IF(A20="","",SUM($H$6:H20)) | J20: =IF(A20="","",IF(I20>=$B$3,1,0))
A21: =IF(16>COUNT(SKUs!$I$5:$I$304),"",16) | B21: =IF(A21="","",INDEX(SKUs!$A$5:$A$304,MATCH(A21,SKUs!$I$5:$I$304,0))) | C21: =IF(A21="","",INDEX(SKUs!$B$5:$B$304,MATCH(A21,SKUs!$I$5:$I$304,0))) | D21: =IF(A21="","",INDEX(SKUs!$E$5:$E$304,MATCH(A21,SKUs!$I$5:$I$304,0))) | E21: =IF(A21="","",INDEX(SKUs!$F$5:$F$304,MATCH(A21,SKUs!$I$5:$I$304,0))) | F21: =IF(A21="","",INDEX(SKUs!$G$5:$G$304,MATCH(A21,SKUs!$I$5:$I$304,0))) | G21: =IF(A21="","",INDEX(SKUs!$H$5:$H$304,MATCH(A21,SKUs!$I$5:$I$304,0))) | H21: =IF(A21="","",IF(SUM(SKUs!$E$5:$E$304)=0,0,D21/SUM(SKUs!$E$5:$E$304))) | I21: =IF(A21="","",SUM($H$6:H21)) | J21: =IF(A21="","",IF(I21>=$B$3,1,0))
A22: =IF(17>COUNT(SKUs!$I$5:$I$304),"",17) | B22: =IF(A22="","",INDEX(SKUs!$A$5:$A$304,MATCH(A22,SKUs!$I$5:$I$304,0))) | C22: =IF(A22="","",INDEX(SKUs!$B$5:$B$304,MATCH(A22,SKUs!$I$5:$I$304,0))) | D22: =IF(A22="","",INDEX(SKUs!$E$5:$E$304,MATCH(A22,SKUs!$I$5:$I$304,0))) | E22: =IF(A22="","",INDEX(SKUs!$F$5:$F$304,MATCH(A22,SKUs!$I$5:$I$304,0))) | F22: =IF(A22="","",INDEX(SKUs!$G$5:$G$304,MATCH(A22,SKUs!$I$5:$I$304,0))) | G22: =IF(A22="","",INDEX(SKUs!$H$5:$H$304,MATCH(A22,SKUs!$I$5:$I$304,0))) | H22: =IF(A22="","",IF(SUM(SKUs!$E$5:$E$304)=0,0,D22/SUM(SKUs!$E$5:$E$304))) | I22: =IF(A22="","",SUM($H$6:H22)) | J22: =IF(A22="","",IF(I22>=$B$3,1,0))
A23: =IF(18>COUNT(SKUs!$I$5:$I$304),"",18) | B23: =IF(A23="","",INDEX(SKUs!$A$5:$A$304,MATCH(A23,SKUs!$I$5:$I$304,0))) | C23: =IF(A23="","",INDEX(SKUs!$B$5:$B$304,MATCH(A23,SKUs!$I$5:$I$304,0))) | D23: =IF(A23="","",INDEX(SKUs!$E$5:$E$304,MATCH(A23,SKUs!$I$5:$I$304,0))) | E23: =IF(A23="","",INDEX(SKUs!$F$5:$F$304,MATCH(A23,SKUs!$I$5:$I$304,0))) | F23: =IF(A23="","",INDEX(SKUs!$G$5:$G$304,MATCH(A23,SKUs!$I$5:$I$304,0))) | G23: =IF(A23="","",INDEX(SKUs!$H$5:$H$304,MATCH(A23,SKUs!$I$5:$I$304,0))) | H23: =IF(A23="","",IF(SUM(SKUs!$E$5:$E$304)=0,0,D23/SUM(SKUs!$E$5:$E$304))) | I23: =IF(A23="","",SUM($H$6:H23)) | J23: =IF(A23="","",IF(I23>=$B$3,1,0))
A24: =IF(19>COUNT(SKUs!$I$5:$I$304),"",19) | B24: =IF(A24="","",INDEX(SKUs!$A$5:$A$304,MATCH(A24,SKUs!$I$5:$I$304,0))) | C24: =IF(A24="","",INDEX(SKUs!$B$5:$B$304,MATCH(A24,SKUs!$I$5:$I$304,0))) | D24: =IF(A24="","",INDEX(SKUs!$E$5:$E$304,MATCH(A24,SKUs!$I$5:$I$304,0))) | E24: =IF(A24="","",INDEX(SKUs!$F$5:$F$304,MATCH(A24,SKUs!$I$5:$I$304,0))) | F24: =IF(A24="","",INDEX(SKUs!$G$5:$G$304,MATCH(A24,SKUs!$I$5:$I$304,0))) | G24: =IF(A24="","",INDEX(SKUs!$H$5:$H$304,MATCH(A24,SKUs!$I$5:$I$304,0))) | H24: =IF(A24="","",IF(SUM(SKUs!$E$5:$E$304)=0,0,D24/SUM(SKUs!$E$5:$E$304))) | I24: =IF(A24="","",SUM($H$6:H24)) | J24: =IF(A24="","",IF(I24>=$B$3,1,0))
A25: =IF(20>COUNT(SKUs!$I$5:$I$304),"",20) | B25: =IF(A25="","",INDEX(SKUs!$A$5:$A$304,MATCH(A25,SKUs!$I$5:$I$304,0))) | C25: =IF(A25="","",INDEX(SKUs!$B$5:$B$304,MATCH(A25,SKUs!$I$5:$I$304,0))) | D25: =IF(A25="","",INDEX(SKUs!$E$5:$E$304,MATCH(A25,SKUs!$I$5:$I$304,0))) | E25: =IF(A25="","",INDEX(SKUs!$F$5:$F$304,MATCH(A25,SKUs!$I$5:$I$304,0))) | F25: =IF(A25="","",INDEX(SKUs!$G$5:$G$304,MATCH(A25,SKUs!$I$5:$I$304,0))) | G25: =IF(A25="","",INDEX(SKUs!$H$5:$H$304,MATCH(A25,SKUs!$I$5:$I$304,0))) | H25: =IF(A25="","",IF(SUM(SKUs!$E$5:$E$304)=0,0,D25/SUM(SKUs!$E$5:$E$304))) | I25: =IF(A25="","",SUM($H$6:H25)) | J25: =IF(A25="","",IF(I25>=$B$3,1,0))
A26: =IF(21>COUNT(SKUs!$I$5:$I$304),"",21) | B26: =IF(A26="","",INDEX(SKUs!$A$5:$A$304,MATCH(A26,SKUs!$I$5:$I$304,0))) | C26: =IF(A26="","",INDEX(SKUs!$B$5:$B$304,MATCH(A26,SKUs!$I$5:$I$304,0))) | D26: =IF(A26="","",INDEX(SKUs!$E$5:$E$304,MATCH(A26,SKUs!$I$5:$I$304,0))) | E26: =IF(A26="","",INDEX(SKUs!$F$5:$F$304,MATCH(A26,SKUs!$I$5:$I$304,0))) | F26: =IF(A26="","",INDEX(SKUs!$G$5:$G$304,MATCH(A26,SKUs!$I$5:$I$304,0))) | G26: =IF(A26="","",INDEX(SKUs!$H$5:$H$304,MATCH(A26,SKUs!$I$5:$I$304,0))) | H26: =IF(A26="","",IF(SUM(SKUs!$E$5:$E$304)=0,0,D26/SUM(SKUs!$E$5:$E$304))) | I26: =IF(A26="","",SUM($H$6:H26)) | J26: =IF(A26="","",IF(I26>=$B$3,1,0))
A27: =IF(22>COUNT(SKUs!$I$5:$I$304),"",22) | B27: =IF(A27="","",INDEX(SKUs!$A$5:$A$304,MATCH(A27,SKUs!$I$5:$I$304,0))) | C27: =IF(A27="","",INDEX(SKUs!$B$5:$B$304,MATCH(A27,SKUs!$I$5:$I$304,0))) | D27: =IF(A27="","",INDEX(SKUs!$E$5:$E$304,MATCH(A27,SKUs!$I$5:$I$304,0))) | E27: =IF(A27="","",INDEX(SKUs!$F$5:$F$304,MATCH(A27,SKUs!$I$5:$I$304,0))) | F27: =IF(A27="","",INDEX(SKUs!$G$5:$G$304,MATCH(A27,SKUs!$I$5:$I$304,0))) | G27: =IF(A27="","",INDEX(SKUs!$H$5:$H$304,MATCH(A27,SKUs!$I$5:$I$304,0))) | H27: =IF(A27="","",IF(SUM(SKUs!$E$5:$E$304)=0,0,D27/SUM(SKUs!$E$5:$E$304))) | I27: =IF(A27="","",SUM($H$6:H27)) | J27: =IF(A27="","",IF(I27>=$B$3,1,0))
A28: =IF(23>COUNT(SKUs!$I$5:$I$304),"",23) | B28: =IF(A28="","",INDEX(SKUs!$A$5:$A$304,MATCH(A28,SKUs!$I$5:$I$304,0))) | C28: =IF(A28="","",INDEX(SKUs!$B$5:$B$304,MATCH(A28,SKUs!$I$5:$I$304,0))) | D28: =IF(A28="","",INDEX(SKUs!$E$5:$E$304,MATCH(A28,SKUs!$I$5:$I$304,0))) | E28: =IF(A28="","",INDEX(SKUs!$F$5:$F$304,MATCH(A28,SKUs!$I$5:$I$304,0))) | F28: =IF(A28="","",INDEX(SKUs!$G$5:$G$304,MATCH(A28,SKUs!$I$5:$I$304,0))) | G28: =IF(A28="","",INDEX(SKUs!$H$5:$H$304,MATCH(A28,SKUs!$I$5:$I$304,0))) | H28: =IF(A28="","",IF(SUM(SKUs!$E$5:$E$304)=0,0,D28/SUM(SKUs!$E$5:$E$304))) | I28: =IF(A28="","",SUM($H$6:H28)) | J28: =IF(A28="","",IF(I28>=$B$3,1,0))
A29: =IF(24>COUNT(SKUs!$I$5:$I$304),"",24) | B29: =IF(A29="","",INDEX(SKUs!$A$5:$A$304,MATCH(A29,SKUs!$I$5:$I$304,0))) | C29: =IF(A29="","",INDEX(SKUs!$B$5:$B$304,MATCH(A29,SKUs!$I$5:$I$304,0))) | D29: =IF(A29="","",INDEX(SKUs!$E$5:$E$304,MATCH(A29,SKUs!$I$5:$I$304,0))) | E29: =IF(A29="","",INDEX(SKUs!$F$5:$F$304,MATCH(A29,SKUs!$I$5:$I$304,0))) | F29: =IF(A29="","",INDEX(SKUs!$G$5:$G$304,MATCH(A29,SKUs!$I$5:$I$304,0))) | G29: =IF(A29="","",INDEX(SKUs!$H$5:$H$304,MATCH(A29,SKUs!$I$5:$I$304,0))) | H29: =IF(A29="","",IF(SUM(SKUs!$E$5:$E$304)=0,0,D29/SUM(SKUs!$E$5:$E$304))) | I29: =IF(A29="","",SUM($H$6:H29)) | J29: =IF(A29="","",IF(I29>=$B$3,1,0))
A30: =IF(25>COUNT(SKUs!$I$5:$I$304),"",25) | B30: =IF(A30="","",INDEX(SKUs!$A$5:$A$304,MATCH(A30,SKUs!$I$5:$I$304,0))) | C30: =IF(A30="","",INDEX(SKUs!$B$5:$B$304,MATCH(A30,SKUs!$I$5:$I$304,0))) | D30: =IF(A30="","",INDEX(SKUs!$E$5:$E$304,MATCH(A30,SKUs!$I$5:$I$304,0))) | E30: =IF(A30="","",INDEX(SKUs!$F$5:$F$304,MATCH(A30,SKUs!$I$5:$I$304,0))) | F30: =IF(A30="","",INDEX(SKUs!$G$5:$G$304,MATCH(A30,SKUs!$I$5:$I$304,0))) | G30: =IF(A30="","",INDEX(SKUs!$H$5:$H$304,MATCH(A30,SKUs!$I$5:$I$304,0))) | H30: =IF(A30="","",IF(SUM(SKUs!$E$5:$E$304)=0,0,D30/SUM(SKUs!$E$5:$E$304))) | I30: =IF(A30="","",SUM($H$6:H30)) | J30: =IF(A30="","",IF(I30>=$B$3,1,0))
A31: =IF(26>COUNT(SKUs!$I$5:$I$304),"",26) | B31: =IF(A31="","",INDEX(SKUs!$A$5:$A$304,MATCH(A31,SKUs!$I$5:$I$304,0))) | C31: =IF(A31="","",INDEX(SKUs!$B$5:$B$304,MATCH(A31,SKUs!$I$5:$I$304,0))) | D31: =IF(A31="","",INDEX(SKUs!$E$5:$E$304,MATCH(A31,SKUs!$I$5:$I$304,0))) | E31: =IF(A31="","",INDEX(SKUs!$F$5:$F$304,MATCH(A31,SKUs!$I$5:$I$304,0))) | F31: =IF(A31="","",INDEX(SKUs!$G$5:$G$304,MATCH(A31,SKUs!$I$5:$I$304,0))) | G31: =IF(A31="","",INDEX(SKUs!$H$5:$H$304,MATCH(A31,SKUs!$I$5:$I$304,0))) | H31: =IF(A31="","",IF(SUM(SKUs!$E$5:$E$304)=0,0,D31/SUM(SKUs!$E$5:$E$304))) | I31: =IF(A31="","",SUM($H$6:H31)) | J31: =IF(A31="","",IF(I31>=$B$3,1,0))
A32: =IF(27>COUNT(SKUs!$I$5:$I$304),"",27) | B32: =IF(A32="","",INDEX(SKUs!$A$5:$A$304,MATCH(A32,SKUs!$I$5:$I$304,0))) | C32: =IF(A32="","",INDEX(SKUs!$B$5:$B$304,MATCH(A32,SKUs!$I$5:$I$304,0))) | D32: =IF(A32="","",INDEX(SKUs!$E$5:$E$304,MATCH(A32,SKUs!$I$5:$I$304,0))) | E32: =IF(A32="","",INDEX(SKUs!$F$5:$F$304,MATCH(A32,SKUs!$I$5:$I$304,0))) | F32: =IF(A32="","",INDEX(SKUs!$G$5:$G$304,MATCH(A32,SKUs!$I$5:$I$304,0))) | G32: =IF(A32="","",INDEX(SKUs!$H$5:$H$304,MATCH(A32,SKUs!$I$5:$I$304,0))) | H32: =IF(A32="","",IF(SUM(SKUs!$E$5:$E$304)=0,0,D32/SUM(SKUs!$E$5:$E$304))) | I32: =IF(A32="","",SUM($H$6:H32)) | J32: =IF(A32="","",IF(I32>=$B$3,1,0))
A33: =IF(28>COUNT(SKUs!$I$5:$I$304),"",28) | B33: =IF(A33="","",INDEX(SKUs!$A$5:$A$304,MATCH(A33,SKUs!$I$5:$I$304,0))) | C33: =IF(A33="","",INDEX(SKUs!$B$5:$B$304,MATCH(A33,SKUs!$I$5:$I$304,0))) | D33: =IF(A33="","",INDEX(SKUs!$E$5:$E$304,MATCH(A33,SKUs!$I$5:$I$304,0))) | E33: =IF(A33="","",INDEX(SKUs!$F$5:$F$304,MATCH(A33,SKUs!$I$5:$I$304,0))) | F33: =IF(A33="","",INDEX(SKUs!$G$5:$G$304,MATCH(A33,SKUs!$I$5:$I$304,0))) | G33: =IF(A33="","",INDEX(SKUs!$H$5:$H$304,MATCH(A33,SKUs!$I$5:$I$304,0))) | H33: =IF(A33="","",IF(SUM(SKUs!$E$5:$E$304)=0,0,D33/SUM(SKUs!$E$5:$E$304))) | I33: =IF(A33="","",SUM($H$6:H33)) | J33: =IF(A33="","",IF(I33>=$B$3,1,0))
A34: =IF(29>COUNT(SKUs!$I$5:$I$304),"",29) | B34: =IF(A34="","",INDEX(SKUs!$A$5:$A$304,MATCH(A34,SKUs!$I$5:$I$304,0))) | C34: =IF(A34="","",INDEX(SKUs!$B$5:$B$304,MATCH(A34,SKUs!$I$5:$I$304,0))) | D34: =IF(A34="","",INDEX(SKUs!$E$5:$E$304,MATCH(A34,SKUs!$I$5:$I$304,0))) | E34: =IF(A34="","",INDEX(SKUs!$F$5:$F$304,MATCH(A34,SKUs!$I$5:$I$304,0))) | F34: =IF(A34="","",INDEX(SKUs!$G$5:$G$304,MATCH(A34,SKUs!$I$5:$I$304,0))) | G34: =IF(A34="","",INDEX(SKUs!$H$5:$H$304,MATCH(A34,SKUs!$I$5:$I$304,0))) | H34: =IF(A34="","",IF(SUM(SKUs!$E$5:$E$304)=0,0,D34/SUM(SKUs!$E$5:$E$304))) | I34: =IF(A34="","",SUM($H$6:H34)) | J34: =IF(A34="","",IF(I34>=$B$3,1,0))
A35: =IF(30>COUNT(SKUs!$I$5:$I$304),"",30) | B35: =IF(A35="","",INDEX(SKUs!$A$5:$A$304,MATCH(A35,SKUs!$I$5:$I$304,0))) | C35: =IF(A35="","",INDEX(SKUs!$B$5:$B$304,MATCH(A35,SKUs!$I$5:$I$304,0))) | D35: =IF(A35="","",INDEX(SKUs!$E$5:$E$304,MATCH(A35,SKUs!$I$5:$I$304,0))) | E35: =IF(A35="","",INDEX(SKUs!$F$5:$F$304,MATCH(A35,SKUs!$I$5:$I$304,0))) | F35: =IF(A35="","",INDEX(SKUs!$G$5:$G$304,MATCH(A35,SKUs!$I$5:$I$304,0))) | G35: =IF(A35="","",INDEX(SKUs!$H$5:$H$304,MATCH(A35,SKUs!$I$5:$I$304,0))) | H35: =IF(A35="","",IF(SUM(SKUs!$E$5:$E$304)=0,0,D35/SUM(SKUs!$E$5:$E$304))) | I35: =IF(A35="","",SUM($H$6:H35)) | J35: =IF(A35="","",IF(I35>=$B$3,1,0))
A36: =IF(31>COUNT(SKUs!$I$5:$I$304),"",31) | B36: =IF(A36="","",INDEX(SKUs!$A$5:$A$304,MATCH(A36,SKUs!$I$5:$I$304,0))) | C36: =IF(A36="","",INDEX(SKUs!$B$5:$B$304,MATCH(A36,SKUs!$I$5:$I$304,0))) | D36: =IF(A36="","",INDEX(SKUs!$E$5:$E$304,MATCH(A36,SKUs!$I$5:$I$304,0))) | E36: =IF(A36="","",INDEX(SKUs!$F$5:$F$304,MATCH(A36,SKUs!$I$5:$I$304,0))) | F36: =IF(A36="","",INDEX(SKUs!$G$5:$G$304,MATCH(A36,SKUs!$I$5:$I$304,0))) | G36: =IF(A36="","",INDEX(SKUs!$H$5:$H$304,MATCH(A36,SKUs!$I$5:$I$304,0))) | H36: =IF(A36="","",IF(SUM(SKUs!$E$5:$E$304)=0,0,D36/SUM(SKUs!$E$5:$E$304))) | I36: =IF(A36="","",SUM($H$6:H36)) | J36: =IF(A36="","",IF(I36>=$B$3,1,0))
A37: =IF(32>COUNT(SKUs!$I$5:$I$304),"",32) | B37: =IF(A37="","",INDEX(SKUs!$A$5:$A$304,MATCH(A37,SKUs!$I$5:$I$304,0))) | C37: =IF(A37="","",INDEX(SKUs!$B$5:$B$304,MATCH(A37,SKUs!$I$5:$I$304,0))) | D37: =IF(A37="","",INDEX(SKUs!$E$5:$E$304,MATCH(A37,SKUs!$I$5:$I$304,0))) | E37: =IF(A37="","",INDEX(SKUs!$F$5:$F$304,MATCH(A37,SKUs!$I$5:$I$304,0))) | F37: =IF(A37="","",INDEX(SKUs!$G$5:$G$304,MATCH(A37,SKUs!$I$5:$I$304,0))) | G37: =IF(A37="","",INDEX(SKUs!$H$5:$H$304,MATCH(A37,SKUs!$I$5:$I$304,0))) | H37: =IF(A37="","",IF(SUM(SKUs!$E$5:$E$304)=0,0,D37/SUM(SKUs!$E$5:$E$304))) | I37: =IF(A37="","",SUM($H$6:H37)) | J37: =IF(A37="","",IF(I37>=$B$3,1,0))
A38: =IF(33>COUNT(SKUs!$I$5:$I$304),"",33) | B38: =IF(A38="","",INDEX(SKUs!$A$5:$A$304,MATCH(A38,SKUs!$I$5:$I$304,0))) | C38: =IF(A38="","",INDEX(SKUs!$B$5:$B$304,MATCH(A38,SKUs!$I$5:$I$304,0))) | D38: =IF(A38="","",INDEX(SKUs!$E$5:$E$304,MATCH(A38,SKUs!$I$5:$I$304,0))) | E38: =IF(A38="","",INDEX(SKUs!$F$5:$F$304,MATCH(A38,SKUs!$I$5:$I$304,0))) | F38: =IF(A38="","",INDEX(SKUs!$G$5:$G$304,MATCH(A38,SKUs!$I$5:$I$304,0))) | G38: =IF(A38="","",INDEX(SKUs!$H$5:$H$304,MATCH(A38,SKUs!$I$5:$I$304,0))) | H38: =IF(A38="","",IF(SUM(SKUs!$E$5:$E$304)=0,0,D38/SUM(SKUs!$E$5:$E$304))) | I38: =IF(A38="","",SUM($H$6:H38)) | J38: =IF(A38="","",IF(I38>=$B$3,1,0))
A39: =IF(34>COUNT(SKUs!$I$5:$I$304),"",34) | B39: =IF(A39="","",INDEX(SKUs!$A$5:$A$304,MATCH(A39,SKUs!$I$5:$I$304,0))) | C39: =IF(A39="","",INDEX(SKUs!$B$5:$B$304,MATCH(A39,SKUs!$I$5:$I$304,0))) | D39: =IF(A39="","",INDEX(SKUs!$E$5:$E$304,MATCH(A39,SKUs!$I$5:$I$304,0))) | E39: =IF(A39="","",INDEX(SKUs!$F$5:$F$304,MATCH(A39,SKUs!$I$5:$I$304,0))) | F39: =IF(A39="","",INDEX(SKUs!$G$5:$G$304,MATCH(A39,SKUs!$I$5:$I$304,0))) | G39: =IF(A39="","",INDEX(SKUs!$H$5:$H$304,MATCH(A39,SKUs!$I$5:$I$304,0))) | H39: =IF(A39="","",IF(SUM(SKUs!$E$5:$E$304)=0,0,D39/SUM(SKUs!$E$5:$E$304))) | I39: =IF(A39="","",SUM($H$6:H39)) | J39: =IF(A39="","",IF(I39>=$B$3,1,0))
A40: =IF(35>COUNT(SKUs!$I$5:$I$304),"",35) | B40: =IF(A40="","",INDEX(SKUs!$A$5:$A$304,MATCH(A40,SKUs!$I$5:$I$304,0))) | C40: =IF(A40="","",INDEX(SKUs!$B$5:$B$304,MATCH(A40,SKUs!$I$5:$I$304,0))) | D40: =IF(A40="","",INDEX(SKUs!$E$5:$E$304,MATCH(A40,SKUs!$I$5:$I$304,0))) | E40: =IF(A40="","",INDEX(SKUs!$F$5:$F$304,MATCH(A40,SKUs!$I$5:$I$304,0))) | F40: =IF(A40="","",INDEX(SKUs!$G$5:$G$304,MATCH(A40,SKUs!$I$5:$I$304,0))) | G40: =IF(A40="","",INDEX(SKUs!$H$5:$H$304,MATCH(A40,SKUs!$I$5:$I$304,0))) | H40: =IF(A40="","",IF(SUM(SKUs!$E$5:$E$304)=0,0,D40/SUM(SKUs!$E$5:$E$304))) | I40: =IF(A40="","",SUM($H$6:H40)) | J40: =IF(A40="","",IF(I40>=$B$3,1,0))
A41: =IF(36>COUNT(SKUs!$I$5:$I$304),"",36) | B41: =IF(A41="","",INDEX(SKUs!$A$5:$A$304,MATCH(A41,SKUs!$I$5:$I$304,0))) | C41: =IF(A41="","",INDEX(SKUs!$B$5:$B$304,MATCH(A41,SKUs!$I$5:$I$304,0))) | D41: =IF(A41="","",INDEX(SKUs!$E$5:$E$304,MATCH(A41,SKUs!$I$5:$I$304,0))) | E41: =IF(A41="","",INDEX(SKUs!$F$5:$F$304,MATCH(A41,SKUs!$I$5:$I$304,0))) | F41: =IF(A41="","",INDEX(SKUs!$G$5:$G$304,MATCH(A41,SKUs!$I$5:$I$304,0))) | G41: =IF(A41="","",INDEX(SKUs!$H$5:$H$304,MATCH(A41,SKUs!$I$5:$I$304,0))) | H41: =IF(A41="","",IF(SUM(SKUs!$E$5:$E$304)=0,0,D41/SUM(SKUs!$E$5:$E$304))) | I41: =IF(A41="","",SUM($H$6:H41)) | J41: =IF(A41="","",IF(I41>=$B$3,1,0))
A42: =IF(37>COUNT(SKUs!$I$5:$I$304),"",37) | B42: =IF(A42="","",INDEX(SKUs!$A$5:$A$304,MATCH(A42,SKUs!$I$5:$I$304,0))) | C42: =IF(A42="","",INDEX(SKUs!$B$5:$B$304,MATCH(A42,SKUs!$I$5:$I$304,0))) | D42: =IF(A42="","",INDEX(SKUs!$E$5:$E$304,MATCH(A42,SKUs!$I$5:$I$304,0))) | E42: =IF(A42="","",INDEX(SKUs!$F$5:$F$304,MATCH(A42,SKUs!$I$5:$I$304,0))) | F42: =IF(A42="","",INDEX(SKUs!$G$5:$G$304,MATCH(A42,SKUs!$I$5:$I$304,0))) | G42: =IF(A42="","",INDEX(SKUs!$H$5:$H$304,MATCH(A42,SKUs!$I$5:$I$304,0))) | H42: =IF(A42="","",IF(SUM(SKUs!$E$5:$E$304)=0,0,D42/SUM(SKUs!$E$5:$E$304))) | I42: =IF(A42="","",SUM($H$6:H42)) | J42: =IF(A42="","",IF(I42>=$B$3,1,0))
A43: =IF(38>COUNT(SKUs!$I$5:$I$304),"",38) | B43: =IF(A43="","",INDEX(SKUs!$A$5:$A$304,MATCH(A43,SKUs!$I$5:$I$304,0))) | C43: =IF(A43="","",INDEX(SKUs!$B$5:$B$304,MATCH(A43,SKUs!$I$5:$I$304,0))) | D43: =IF(A43="","",INDEX(SKUs!$E$5:$E$304,MATCH(A43,SKUs!$I$5:$I$304,0))) | E43: =IF(A43="","",INDEX(SKUs!$F$5:$F$304,MATCH(A43,SKUs!$I$5:$I$304,0))) | F43: =IF(A43="","",INDEX(SKUs!$G$5:$G$304,MATCH(A43,SKUs!$I$5:$I$304,0))) | G43: =IF(A43="","",INDEX(SKUs!$H$5:$H$304,MATCH(A43,SKUs!$I$5:$I$304,0))) | H43: =IF(A43="","",IF(SUM(SKUs!$E$5:$E$304)=0,0,D43/SUM(SKUs!$E$5:$E$304))) | I43: =IF(A43="","",SUM($H$6:H43)) | J43: =IF(A43="","",IF(I43>=$B$3,1,0))
A44: =IF(39>COUNT(SKUs!$I$5:$I$304),"",39) | B44: =IF(A44="","",INDEX(SKUs!$A$5:$A$304,MATCH(A44,SKUs!$I$5:$I$304,0))) | C44: =IF(A44="","",INDEX(SKUs!$B$5:$B$304,MATCH(A44,SKUs!$I$5:$I$304,0))) | D44: =IF(A44="","",INDEX(SKUs!$E$5:$E$304,MATCH(A44,SKUs!$I$5:$I$304,0))) | E44: =IF(A44="","",INDEX(SKUs!$F$5:$F$304,MATCH(A44,SKUs!$I$5:$I$304,0))) | F44: =IF(A44="","",INDEX(SKUs!$G$5:$G$304,MATCH(A44,SKUs!$I$5:$I$304,0))) | G44: =IF(A44="","",INDEX(SKUs!$H$5:$H$304,MATCH(A44,SKUs!$I$5:$I$304,0))) | H44: =IF(A44="","",IF(SUM(SKUs!$E$5:$E$304)=0,0,D44/SUM(SKUs!$E$5:$E$304))) | I44: =IF(A44="","",SUM($H$6:H44)) | J44: =IF(A44="","",IF(I44>=$B$3,1,0))
A45: =IF(40>COUNT(SKUs!$I$5:$I$304),"",40) | B45: =IF(A45="","",INDEX(SKUs!$A$5:$A$304,MATCH(A45,SKUs!$I$5:$I$304,0))) | C45: =IF(A45="","",INDEX(SKUs!$B$5:$B$304,MATCH(A45,SKUs!$I$5:$I$304,0))) | D45: =IF(A45="","",INDEX(SKUs!$E$5:$E$304,MATCH(A45,SKUs!$I$5:$I$304,0))) | E45: =IF(A45="","",INDEX(SKUs!$F$5:$F$304,MATCH(A45,SKUs!$I$5:$I$304,0))) | F45: =IF(A45="","",INDEX(SKUs!$G$5:$G$304,MATCH(A45,SKUs!$I$5:$I$304,0))) | G45: =IF(A45="","",INDEX(SKUs!$H$5:$H$304,MATCH(A45,SKUs!$I$5:$I$304,0))) | H45: =IF(A45="","",IF(SUM(SKUs!$E$5:$E$304)=0,0,D45/SUM(SKUs!$E$5:$E$304))) | I45: =IF(A45="","",SUM($H$6:H45)) | J45: =IF(A45="","",IF(I45>=$B$3,1,0))
A46: =IF(41>COUNT(SKUs!$I$5:$I$304),"",41) | B46: =IF(A46="","",INDEX(SKUs!$A$5:$A$304,MATCH(A46,SKUs!$I$5:$I$304,0))) | C46: =IF(A46="","",INDEX(SKUs!$B$5:$B$304,MATCH(A46,SKUs!$I$5:$I$304,0))) | D46: =IF(A46="","",INDEX(SKUs!$E$5:$E$304,MATCH(A46,SKUs!$I$5:$I$304,0))) | E46: =IF(A46="","",INDEX(SKUs!$F$5:$F$304,MATCH(A46,SKUs!$I$5:$I$304,0))) | F46: =IF(A46="","",INDEX(SKUs!$G$5:$G$304,MATCH(A46,SKUs!$I$5:$I$304,0))) | G46: =IF(A46="","",INDEX(SKUs!$H$5:$H$304,MATCH(A46,SKUs!$I$5:$I$304,0))) | H46: =IF(A46="","",IF(SUM(SKUs!$E$5:$E$304)=0,0,D46/SUM(SKUs!$E$5:$E$304))) | I46: =IF(A46="","",SUM($H$6:H46)) | J46: =IF(A46="","",IF(I46>=$B$3,1,0))
A47: =IF(42>COUNT(SKUs!$I$5:$I$304),"",42) | B47: =IF(A47="","",INDEX(SKUs!$A$5:$A$304,MATCH(A47,SKUs!$I$5:$I$304,0))) | C47: =IF(A47="","",INDEX(SKUs!$B$5:$B$304,MATCH(A47,SKUs!$I$5:$I$304,0))) | D47: =IF(A47="","",INDEX(SKUs!$E$5:$E$304,MATCH(A47,SKUs!$I$5:$I$304,0))) | E47: =IF(A47="","",INDEX(SKUs!$F$5:$F$304,MATCH(A47,SKUs!$I$5:$I$304,0))) | F47: =IF(A47="","",INDEX(SKUs!$G$5:$G$304,MATCH(A47,SKUs!$I$5:$I$304,0))) | G47: =IF(A47="","",INDEX(SKUs!$H$5:$H$304,MATCH(A47,SKUs!$I$5:$I$304,0))) | H47: =IF(A47="","",IF(SUM(SKUs!$E$5:$E$304)=0,0,D47/SUM(SKUs!$E$5:$E$304))) | I47: =IF(A47="","",SUM($H$6:H47)) | J47: =IF(A47="","",IF(I47>=$B$3,1,0))
A48: =IF(43>COUNT(SKUs!$I$5:$I$304),"",43) | B48: =IF(A48="","",INDEX(SKUs!$A$5:$A$304,MATCH(A48,SKUs!$I$5:$I$304,0))) | C48: =IF(A48="","",INDEX(SKUs!$B$5:$B$304,MATCH(A48,SKUs!$I$5:$I$304,0))) | D48: =IF(A48="","",INDEX(SKUs!$E$5:$E$304,MATCH(A48,SKUs!$I$5:$I$304,0))) | E48: =IF(A48="","",INDEX(SKUs!$F$5:$F$304,MATCH(A48,SKUs!$I$5:$I$304,0))) | F48: =IF(A48="","",INDEX(SKUs!$G$5:$G$304,MATCH(A48,SKUs!$I$5:$I$304,0))) | G48: =IF(A48="","",INDEX(SKUs!$H$5:$H$304,MATCH(A48,SKUs!$I$5:$I$304,0))) | H48: =IF(A48="","",IF(SUM(SKUs!$E$5:$E$304)=0,0,D48/SUM(SKUs!$E$5:$E$304))) | I48: =IF(A48="","",SUM($H$6:H48)) | J48: =IF(A48="","",IF(I48>=$B$3,1,0))
A49: =IF(44>COUNT(SKUs!$I$5:$I$304),"",44) | B49: =IF(A49="","",INDEX(SKUs!$A$5:$A$304,MATCH(A49,SKUs!$I$5:$I$304,0))) | C49: =IF(A49="","",INDEX(SKUs!$B$5:$B$304,MATCH(A49,SKUs!$I$5:$I$304,0))) | D49: =IF(A49="","",INDEX(SKUs!$E$5:$E$304,MATCH(A49,SKUs!$I$5:$I$304,0))) | E49: =IF(A49="","",INDEX(SKUs!$F$5:$F$304,MATCH(A49,SKUs!$I$5:$I$304,0))) | F49: =IF(A49="","",INDEX(SKUs!$G$5:$G$304,MATCH(A49,SKUs!$I$5:$I$304,0))) | G49: =IF(A49="","",INDEX(SKUs!$H$5:$H$304,MATCH(A49,SKUs!$I$5:$I$304,0))) | H49: =IF(A49="","",IF(SUM(SKUs!$E$5:$E$304)=0,0,D49/SUM(SKUs!$E$5:$E$304))) | I49: =IF(A49="","",SUM($H$6:H49)) | J49: =IF(A49="","",IF(I49>=$B$3,1,0))
A50: =IF(45>COUNT(SKUs!$I$5:$I$304),"",45) | B50: =IF(A50="","",INDEX(SKUs!$A$5:$A$304,MATCH(A50,SKUs!$I$5:$I$304,0))) | C50: =IF(A50="","",INDEX(SKUs!$B$5:$B$304,MATCH(A50,SKUs!$I$5:$I$304,0))) | D50: =IF(A50="","",INDEX(SKUs!$E$5:$E$304,MATCH(A50,SKUs!$I$5:$I$304,0))) | E50: =IF(A50="","",INDEX(SKUs!$F$5:$F$304,MATCH(A50,SKUs!$I$5:$I$304,0))) | F50: =IF(A50="","",INDEX(SKUs!$G$5:$G$304,MATCH(A50,SKUs!$I$5:$I$304,0))) | G50: =IF(A50="","",INDEX(SKUs!$H$5:$H$304,MATCH(A50,SKUs!$I$5:$I$304,0))) | H50: =IF(A50="","",IF(SUM(SKUs!$E$5:$E$304)=0,0,D50/SUM(SKUs!$E$5:$E$304))) | I50: =IF(A50="","",SUM($H$6:H50)) | J50: =IF(A50="","",IF(I50>=$B$3,1,0))
A51: =IF(46>COUNT(SKUs!$I$5:$I$304),"",46) | B51: =IF(A51="","",INDEX(SKUs!$A$5:$A$304,MATCH(A51,SKUs!$I$5:$I$304,0))) | C51: =IF(A51="","",INDEX(SKUs!$B$5:$B$304,MATCH(A51,SKUs!$I$5:$I$304,0))) | D51: =IF(A51="","",INDEX(SKUs!$E$5:$E$304,MATCH(A51,SKUs!$I$5:$I$304,0))) | E51: =IF(A51="","",INDEX(SKUs!$F$5:$F$304,MATCH(A51,SKUs!$I$5:$I$304,0))) | F51: =IF(A51="","",INDEX(SKUs!$G$5:$G$304,MATCH(A51,SKUs!$I$5:$I$304,0))) | G51: =IF(A51="","",INDEX(SKUs!$H$5:$H$304,MATCH(A51,SKUs!$I$5:$I$304,0))) | H51: =IF(A51="","",IF(SUM(SKUs!$E$5:$E$304)=0,0,D51/SUM(SKUs!$E$5:$E$304))) | I51: =IF(A51="","",SUM($H$6:H51)) | J51: =IF(A51="","",IF(I51>=$B$3,1,0))
A52: =IF(47>COUNT(SKUs!$I$5:$I$304),"",47) | B52: =IF(A52="","",INDEX(SKUs!$A$5:$A$304,MATCH(A52,SKUs!$I$5:$I$304,0))) | C52: =IF(A52="","",INDEX(SKUs!$B$5:$B$304,MATCH(A52,SKUs!$I$5:$I$304,0))) | D52: =IF(A52="","",INDEX(SKUs!$E$5:$E$304,MATCH(A52,SKUs!$I$5:$I$304,0))) | E52: =IF(A52="","",INDEX(SKUs!$F$5:$F$304,MATCH(A52,SKUs!$I$5:$I$304,0))) | F52: =IF(A52="","",INDEX(SKUs!$G$5:$G$304,MATCH(A52,SKUs!$I$5:$I$304,0))) | G52: =IF(A52="","",INDEX(SKUs!$H$5:$H$304,MATCH(A52,SKUs!$I$5:$I$304,0))) | H52: =IF(A52="","",IF(SUM(SKUs!$E$5:$E$304)=0,0,D52/SUM(SKUs!$E$5:$E$304))) | I52: =IF(A52="","",SUM($H$6:H52)) | J52: =IF(A52="","",IF(I52>=$B$3,1,0))
A53: =IF(48>COUNT(SKUs!$I$5:$I$304),"",48) | B53: =IF(A53="","",INDEX(SKUs!$A$5:$A$304,MATCH(A53,SKUs!$I$5:$I$304,0))) | C53: =IF(A53="","",INDEX(SKUs!$B$5:$B$304,MATCH(A53,SKUs!$I$5:$I$304,0))) | D53: =IF(A53="","",INDEX(SKUs!$E$5:$E$304,MATCH(A53,SKUs!$I$5:$I$304,0))) | E53: =IF(A53="","",INDEX(SKUs!$F$5:$F$304,MATCH(A53,SKUs!$I$5:$I$304,0))) | F53: =IF(A53="","",INDEX(SKUs!$G$5:$G$304,MATCH(A53,SKUs!$I$5:$I$304,0))) | G53: =IF(A53="","",INDEX(SKUs!$H$5:$H$304,MATCH(A53,SKUs!$I$5:$I$304,0))) | H53: =IF(A53="","",IF(SUM(SKUs!$E$5:$E$304)=0,0,D53/SUM(SKUs!$E$5:$E$304))) | I53: =IF(A53="","",SUM($H$6:H53)) | J53: =IF(A53="","",IF(I53>=$B$3,1,0))
A54: =IF(49>COUNT(SKUs!$I$5:$I$304),"",49) | B54: =IF(A54="","",INDEX(SKUs!$A$5:$A$304,MATCH(A54,SKUs!$I$5:$I$304,0))) | C54: =IF(A54="","",INDEX(SKUs!$B$5:$B$304,MATCH(A54,SKUs!$I$5:$I$304,0))) | D54: =IF(A54="","",INDEX(SKUs!$E$5:$E$304,MATCH(A54,SKUs!$I$5:$I$304,0))) | E54: =IF(A54="","",INDEX(SKUs!$F$5:$F$304,MATCH(A54,SKUs!$I$5:$I$304,0))) | F54: =IF(A54="","",INDEX(SKUs!$G$5:$G$304,MATCH(A54,SKUs!$I$5:$I$304,0))) | G54: =IF(A54="","",INDEX(SKUs!$H$5:$H$304,MATCH(A54,SKUs!$I$5:$I$304,0))) | H54: =IF(A54="","",IF(SUM(SKUs!$E$5:$E$304)=0,0,D54/SUM(SKUs!$E$5:$E$304))) | I54: =IF(A54="","",SUM($H$6:H54)) | J54: =IF(A54="","",IF(I54>=$B$3,1,0))
A55: =IF(50>COUNT(SKUs!$I$5:$I$304),"",50) | B55: =IF(A55="","",INDEX(SKUs!$A$5:$A$304,MATCH(A55,SKUs!$I$5:$I$304,0))) | C55: =IF(A55="","",INDEX(SKUs!$B$5:$B$304,MATCH(A55,SKUs!$I$5:$I$304,0))) | D55: =IF(A55="","",INDEX(SKUs!$E$5:$E$304,MATCH(A55,SKUs!$I$5:$I$304,0))) | E55: =IF(A55="","",INDEX(SKUs!$F$5:$F$304,MATCH(A55,SKUs!$I$5:$I$304,0))) | F55: =IF(A55="","",INDEX(SKUs!$G$5:$G$304,MATCH(A55,SKUs!$I$5:$I$304,0))) | G55: =IF(A55="","",INDEX(SKUs!$H$5:$H$304,MATCH(A55,SKUs!$I$5:$I$304,0))) | H55: =IF(A55="","",IF(SUM(SKUs!$E$5:$E$304)=0,0,D55/SUM(SKUs!$E$5:$E$304))) | I55: =IF(A55="","",SUM($H$6:H55)) | J55: =IF(A55="","",IF(I55>=$B$3,1,0))
A56: =IF(51>COUNT(SKUs!$I$5:$I$304),"",51) | B56: =IF(A56="","",INDEX(SKUs!$A$5:$A$304,MATCH(A56,SKUs!$I$5:$I$304,0))) | C56: =IF(A56="","",INDEX(SKUs!$B$5:$B$304,MATCH(A56,SKUs!$I$5:$I$304,0))) | D56: =IF(A56="","",INDEX(SKUs!$E$5:$E$304,MATCH(A56,SKUs!$I$5:$I$304,0))) | E56: =IF(A56="","",INDEX(SKUs!$F$5:$F$304,MATCH(A56,SKUs!$I$5:$I$304,0))) | F56: =IF(A56="","",INDEX(SKUs!$G$5:$G$304,MATCH(A56,SKUs!$I$5:$I$304,0))) | G56: =IF(A56="","",INDEX(SKUs!$H$5:$H$304,MATCH(A56,SKUs!$I$5:$I$304,0))) | H56: =IF(A56="","",IF(SUM(SKUs!$E$5:$E$304)=0,0,D56/SUM(SKUs!$E$5:$E$304))) | I56: =IF(A56="","",SUM($H$6:H56)) | J56: =IF(A56="","",IF(I56>=$B$3,1,0))
A57: =IF(52>COUNT(SKUs!$I$5:$I$304),"",52) | B57: =IF(A57="","",INDEX(SKUs!$A$5:$A$304,MATCH(A57,SKUs!$I$5:$I$304,0))) | C57: =IF(A57="","",INDEX(SKUs!$B$5:$B$304,MATCH(A57,SKUs!$I$5:$I$304,0))) | D57: =IF(A57="","",INDEX(SKUs!$E$5:$E$304,MATCH(A57,SKUs!$I$5:$I$304,0))) | E57: =IF(A57="","",INDEX(SKUs!$F$5:$F$304,MATCH(A57,SKUs!$I$5:$I$304,0))) | F57: =IF(A57="","",INDEX(SKUs!$G$5:$G$304,MATCH(A57,SKUs!$I$5:$I$304,0))) | G57: =IF(A57="","",INDEX(SKUs!$H$5:$H$304,MATCH(A57,SKUs!$I$5:$I$304,0))) | H57: =IF(A57="","",IF(SUM(SKUs!$E$5:$E$304)=0,0,D57/SUM(SKUs!$E$5:$E$304))) | I57: =IF(A57="","",SUM($H$6:H57)) | J57: =IF(A57="","",IF(I57>=$B$3,1,0))
A58: =IF(53>COUNT(SKUs!$I$5:$I$304),"",53) | B58: =IF(A58="","",INDEX(SKUs!$A$5:$A$304,MATCH(A58,SKUs!$I$5:$I$304,0))) | C58: =IF(A58="","",INDEX(SKUs!$B$5:$B$304,MATCH(A58,SKUs!$I$5:$I$304,0))) | D58: =IF(A58="","",INDEX(SKUs!$E$5:$E$304,MATCH(A58,SKUs!$I$5:$I$304,0))) | E58: =IF(A58="","",INDEX(SKUs!$F$5:$F$304,MATCH(A58,SKUs!$I$5:$I$304,0))) | F58: =IF(A58="","",INDEX(SKUs!$G$5:$G$304,MATCH(A58,SKUs!$I$5:$I$304,0))) | G58: =IF(A58="","",INDEX(SKUs!$H$5:$H$304,MATCH(A58,SKUs!$I$5:$I$304,0))) | H58: =IF(A58="","",IF(SUM(SKUs!$E$5:$E$304)=0,0,D58/SUM(SKUs!$E$5:$E$304))) | I58: =IF(A58="","",SUM($H$6:H58)) | J58: =IF(A58="","",IF(I58>=$B$3,1,0))
A59: =IF(54>COUNT(SKUs!$I$5:$I$304),"",54) | B59: =IF(A59="","",INDEX(SKUs!$A$5:$A$304,MATCH(A59,SKUs!$I$5:$I$304,0))) | C59: =IF(A59="","",INDEX(SKUs!$B$5:$B$304,MATCH(A59,SKUs!$I$5:$I$304,0))) | D59: =IF(A59="","",INDEX(SKUs!$E$5:$E$304,MATCH(A59,SKUs!$I$5:$I$304,0))) | E59: =IF(A59="","",INDEX(SKUs!$F$5:$F$304,MATCH(A59,SKUs!$I$5:$I$304,0))) | F59: =IF(A59="","",INDEX(SKUs!$G$5:$G$304,MATCH(A59,SKUs!$I$5:$I$304,0))) | G59: =IF(A59="","",INDEX(SKUs!$H$5:$H$304,MATCH(A59,SKUs!$I$5:$I$304,0))) | H59: =IF(A59="","",IF(SUM(SKUs!$E$5:$E$304)=0,0,D59/SUM(SKUs!$E$5:$E$304))) | I59: =IF(A59="","",SUM($H$6:H59)) | J59: =IF(A59="","",IF(I59>=$B$3,1,0))
A60: =IF(55>COUNT(SKUs!$I$5:$I$304),"",55) | B60: =IF(A60="","",INDEX(SKUs!$A$5:$A$304,MATCH(A60,SKUs!$I$5:$I$304,0))) | C60: =IF(A60="","",INDEX(SKUs!$B$5:$B$304,MATCH(A60,SKUs!$I$5:$I$304,0))) | D60: =IF(A60="","",INDEX(SKUs!$E$5:$E$304,MATCH(A60,SKUs!$I$5:$I$304,0))) | E60: =IF(A60="","",INDEX(SKUs!$F$5:$F$304,MATCH(A60,SKUs!$I$5:$I$304,0))) | F60: =IF(A60="","",INDEX(SKUs!$G$5:$G$304,MATCH(A60,SKUs!$I$5:$I$304,0))) | G60: =IF(A60="","",INDEX(SKUs!$H$5:$H$304,MATCH(A60,SKUs!$I$5:$I$304,0))) | H60: =IF(A60="","",IF(SUM(SKUs!$E$5:$E$304)=0,0,D60/SUM(SKUs!$E$5:$E$304))) | I60: =IF(A60="","",SUM($H$6:H60)) | J60: =IF(A60="","",IF(I60>=$B$3,1,0))
A61: =IF(56>COUNT(SKUs!$I$5:$I$304),"",56) | B61: =IF(A61="","",INDEX(SKUs!$A$5:$A$304,MATCH(A61,SKUs!$I$5:$I$304,0))) | C61: =IF(A61="","",INDEX(SKUs!$B$5:$B$304,MATCH(A61,SKUs!$I$5:$I$304,0))) | D61: =IF(A61="","",INDEX(SKUs!$E$5:$E$304,MATCH(A61,SKUs!$I$5:$I$304,0))) | E61: =IF(A61="","",INDEX(SKUs!$F$5:$F$304,MATCH(A61,SKUs!$I$5:$I$304,0))) | F61: =IF(A61="","",INDEX(SKUs!$G$5:$G$304,MATCH(A61,SKUs!$I$5:$I$304,0))) | G61: =IF(A61="","",INDEX(SKUs!$H$5:$H$304,MATCH(A61,SKUs!$I$5:$I$304,0))) | H61: =IF(A61="","",IF(SUM(SKUs!$E$5:$E$304)=0,0,D61/SUM(SKUs!$E$5:$E$304))) | I61: =IF(A61="","",SUM($H$6:H61)) | J61: =IF(A61="","",IF(I61>=$B$3,1,0))
A62: =IF(57>COUNT(SKUs!$I$5:$I$304),"",57) | B62: =IF(A62="","",INDEX(SKUs!$A$5:$A$304,MATCH(A62,SKUs!$I$5:$I$304,0))) | C62: =IF(A62="","",INDEX(SKUs!$B$5:$B$304,MATCH(A62,SKUs!$I$5:$I$304,0))) | D62: =IF(A62="","",INDEX(SKUs!$E$5:$E$304,MATCH(A62,SKUs!$I$5:$I$304,0))) | E62: =IF(A62="","",INDEX(SKUs!$F$5:$F$304,MATCH(A62,SKUs!$I$5:$I$304,0))) | F62: =IF(A62="","",INDEX(SKUs!$G$5:$G$304,MATCH(A62,SKUs!$I$5:$I$304,0))) | G62: =IF(A62="","",INDEX(SKUs!$H$5:$H$304,MATCH(A62,SKUs!$I$5:$I$304,0))) | H62: =IF(A62="","",IF(SUM(SKUs!$E$5:$E$304)=0,0,D62/SUM(SKUs!$E$5:$E$304))) | I62: =IF(A62="","",SUM($H$6:H62)) | J62: =IF(A62="","",IF(I62>=$B$3,1,0))
A63: =IF(58>COUNT(SKUs!$I$5:$I$304),"",58) | B63: =IF(A63="","",INDEX(SKUs!$A$5:$A$304,MATCH(A63,SKUs!$I$5:$I$304,0))) | C63: =IF(A63="","",INDEX(SKUs!$B$5:$B$304,MATCH(A63,SKUs!$I$5:$I$304,0))) | D63: =IF(A63="","",INDEX(SKUs!$E$5:$E$304,MATCH(A63,SKUs!$I$5:$I$304,0))) | E63: =IF(A63="","",INDEX(SKUs!$F$5:$F$304,MATCH(A63,SKUs!$I$5:$I$304,0))) | F63: =IF(A63="","",INDEX(SKUs!$G$5:$G$304,MATCH(A63,SKUs!$I$5:$I$304,0))) | G63: =IF(A63="","",INDEX(SKUs!$H$5:$H$304,MATCH(A63,SKUs!$I$5:$I$304,0))) | H63: =IF(A63="","",IF(SUM(SKUs!$E$5:$E$304)=0,0,D63/SUM(SKUs!$E$5:$E$304))) | I63: =IF(A63="","",SUM($H$6:H63)) | J63: =IF(A63="","",IF(I63>=$B$3,1,0))
A64: =IF(59>COUNT(SKUs!$I$5:$I$304),"",59) | B64: =IF(A64="","",INDEX(SKUs!$A$5:$A$304,MATCH(A64,SKUs!$I$5:$I$304,0))) | C64: =IF(A64="","",INDEX(SKUs!$B$5:$B$304,MATCH(A64,SKUs!$I$5:$I$304,0))) | D64: =IF(A64="","",INDEX(SKUs!$E$5:$E$304,MATCH(A64,SKUs!$I$5:$I$304,0))) | E64: =IF(A64="","",INDEX(SKUs!$F$5:$F$304,MATCH(A64,SKUs!$I$5:$I$304,0))) | F64: =IF(A64="","",INDEX(SKUs!$G$5:$G$304,MATCH(A64,SKUs!$I$5:$I$304,0))) | G64: =IF(A64="","",INDEX(SKUs!$H$5:$H$304,MATCH(A64,SKUs!$I$5:$I$304,0))) | H64: =IF(A64="","",IF(SUM(SKUs!$E$5:$E$304)=0,0,D64/SUM(SKUs!$E$5:$E$304))) | I64: =IF(A64="","",SUM($H$6:H64)) | J64: =IF(A64="","",IF(I64>=$B$3,1,0))
A65: =IF(60>COUNT(SKUs!$I$5:$I$304),"",60) | B65: =IF(A65="","",INDEX(SKUs!$A$5:$A$304,MATCH(A65,SKUs!$I$5:$I$304,0))) | C65: =IF(A65="","",INDEX(SKUs!$B$5:$B$304,MATCH(A65,SKUs!$I$5:$I$304,0))) | D65: =IF(A65="","",INDEX(SKUs!$E$5:$E$304,MATCH(A65,SKUs!$I$5:$I$304,0))) | E65: =IF(A65="","",INDEX(SKUs!$F$5:$F$304,MATCH(A65,SKUs!$I$5:$I$304,0))) | F65: =IF(A65="","",INDEX(SKUs!$G$5:$G$304,MATCH(A65,SKUs!$I$5:$I$304,0))) | G65: =IF(A65="","",INDEX(SKUs!$H$5:$H$304,MATCH(A65,SKUs!$I$5:$I$304,0))) | H65: =IF(A65="","",IF(SUM(SKUs!$E$5:$E$304)=0,0,D65/SUM(SKUs!$E$5:$E$304))) | I65: =IF(A65="","",SUM($H$6:H65)) | J65: =IF(A65="","",IF(I65>=$B$3,1,0))
A66: =IF(61>COUNT(SKUs!$I$5:$I$304),"",61) | B66: =IF(A66="","",INDEX(SKUs!$A$5:$A$304,MATCH(A66,SKUs!$I$5:$I$304,0))) | C66: =IF(A66="","",INDEX(SKUs!$B$5:$B$304,MATCH(A66,SKUs!$I$5:$I$304,0))) | D66: =IF(A66="","",INDEX(SKUs!$E$5:$E$304,MATCH(A66,SKUs!$I$5:$I$304,0))) | E66: =IF(A66="","",INDEX(SKUs!$F$5:$F$304,MATCH(A66,SKUs!$I$5:$I$304,0))) | F66: =IF(A66="","",INDEX(SKUs!$G$5:$G$304,MATCH(A66,SKUs!$I$5:$I$304,0))) | G66: =IF(A66="","",INDEX(SKUs!$H$5:$H$304,MATCH(A66,SKUs!$I$5:$I$304,0))) | H66: =IF(A66="","",IF(SUM(SKUs!$E$5:$E$304)=0,0,D66/SUM(SKUs!$E$5:$E$304))) | I66: =IF(A66="","",SUM($H$6:H66)) | J66: =IF(A66="","",IF(I66>=$B$3,1,0))
A67: =IF(62>COUNT(SKUs!$I$5:$I$304),"",62) | B67: =IF(A67="","",INDEX(SKUs!$A$5:$A$304,MATCH(A67,SKUs!$I$5:$I$304,0))) | C67: =IF(A67="","",INDEX(SKUs!$B$5:$B$304,MATCH(A67,SKUs!$I$5:$I$304,0))) | D67: =IF(A67="","",INDEX(SKUs!$E$5:$E$304,MATCH(A67,SKUs!$I$5:$I$304,0))) | E67: =IF(A67="","",INDEX(SKUs!$F$5:$F$304,MATCH(A67,SKUs!$I$5:$I$304,0))) | F67: =IF(A67="","",INDEX(SKUs!$G$5:$G$304,MATCH(A67,SKUs!$I$5:$I$304,0))) | G67: =IF(A67="","",INDEX(SKUs!$H$5:$H$304,MATCH(A67,SKUs!$I$5:$I$304,0))) | H67: =IF(A67="","",IF(SUM(SKUs!$E$5:$E$304)=0,0,D67/SUM(SKUs!$E$5:$E$304))) | I67: =IF(A67="","",SUM($H$6:H67)) | J67: =IF(A67="","",IF(I67>=$B$3,1,0))
A68: =IF(63>COUNT(SKUs!$I$5:$I$304),"",63) | B68: =IF(A68="","",INDEX(SKUs!$A$5:$A$304,MATCH(A68,SKUs!$I$5:$I$304,0))) | C68: =IF(A68="","",INDEX(SKUs!$B$5:$B$304,MATCH(A68,SKUs!$I$5:$I$304,0))) | D68: =IF(A68="","",INDEX(SKUs!$E$5:$E$304,MATCH(A68,SKUs!$I$5:$I$304,0))) | E68: =IF(A68="","",INDEX(SKUs!$F$5:$F$304,MATCH(A68,SKUs!$I$5:$I$304,0))) | F68: =IF(A68="","",INDEX(SKUs!$G$5:$G$304,MATCH(A68,SKUs!$I$5:$I$304,0))) | G68: =IF(A68="","",INDEX(SKUs!$H$5:$H$304,MATCH(A68,SKUs!$I$5:$I$304,0))) | H68: =IF(A68="","",IF(SUM(SKUs!$E$5:$E$304)=0,0,D68/SUM(SKUs!$E$5:$E$304))) | I68: =IF(A68="","",SUM($H$6:H68)) | J68: =IF(A68="","",IF(I68>=$B$3,1,0))
A69: =IF(64>COUNT(SKUs!$I$5:$I$304),"",64) | B69: =IF(A69="","",INDEX(SKUs!$A$5:$A$304,MATCH(A69,SKUs!$I$5:$I$304,0))) | C69: =IF(A69="","",INDEX(SKUs!$B$5:$B$304,MATCH(A69,SKUs!$I$5:$I$304,0))) | D69: =IF(A69="","",INDEX(SKUs!$E$5:$E$304,MATCH(A69,SKUs!$I$5:$I$304,0))) | E69: =IF(A69="","",INDEX(SKUs!$F$5:$F$304,MATCH(A69,SKUs!$I$5:$I$304,0))) | F69: =IF(A69="","",INDEX(SKUs!$G$5:$G$304,MATCH(A69,SKUs!$I$5:$I$304,0))) | G69: =IF(A69="","",INDEX(SKUs!$H$5:$H$304,MATCH(A69,SKUs!$I$5:$I$304,0))) | H69: =IF(A69="","",IF(SUM(SKUs!$E$5:$E$304)=0,0,D69/SUM(SKUs!$E$5:$E$304))) | I69: =IF(A69="","",SUM($H$6:H69)) | J69: =IF(A69="","",IF(I69>=$B$3,1,0))
A70: =IF(65>COUNT(SKUs!$I$5:$I$304),"",65) | B70: =IF(A70="","",INDEX(SKUs!$A$5:$A$304,MATCH(A70,SKUs!$I$5:$I$304,0))) | C70: =IF(A70="","",INDEX(SKUs!$B$5:$B$304,MATCH(A70,SKUs!$I$5:$I$304,0))) | D70: =IF(A70="","",INDEX(SKUs!$E$5:$E$304,MATCH(A70,SKUs!$I$5:$I$304,0))) | E70: =IF(A70="","",INDEX(SKUs!$F$5:$F$304,MATCH(A70,SKUs!$I$5:$I$304,0))) | F70: =IF(A70="","",INDEX(SKUs!$G$5:$G$304,MATCH(A70,SKUs!$I$5:$I$304,0))) | G70: =IF(A70="","",INDEX(SKUs!$H$5:$H$304,MATCH(A70,SKUs!$I$5:$I$304,0))) | H70: =IF(A70="","",IF(SUM(SKUs!$E$5:$E$304)=0,0,D70/SUM(SKUs!$E$5:$E$304))) | I70: =IF(A70="","",SUM($H$6:H70)) | J70: =IF(A70="","",IF(I70>=$B$3,1,0))
A71: =IF(66>COUNT(SKUs!$I$5:$I$304),"",66) | B71: =IF(A71="","",INDEX(SKUs!$A$5:$A$304,MATCH(A71,SKUs!$I$5:$I$304,0))) | C71: =IF(A71="","",INDEX(SKUs!$B$5:$B$304,MATCH(A71,SKUs!$I$5:$I$304,0))) | D71: =IF(A71="","",INDEX(SKUs!$E$5:$E$304,MATCH(A71,SKUs!$I$5:$I$304,0))) | E71: =IF(A71="","",INDEX(SKUs!$F$5:$F$304,MATCH(A71,SKUs!$I$5:$I$304,0))) | F71: =IF(A71="","",INDEX(SKUs!$G$5:$G$304,MATCH(A71,SKUs!$I$5:$I$304,0))) | G71: =IF(A71="","",INDEX(SKUs!$H$5:$H$304,MATCH(A71,SKUs!$I$5:$I$304,0))) | H71: =IF(A71="","",IF(SUM(SKUs!$E$5:$E$304)=0,0,D71/SUM(SKUs!$E$5:$E$304))) | I71: =IF(A71="","",SUM($H$6:H71)) | J71: =IF(A71="","",IF(I71>=$B$3,1,0))
A72: =IF(67>COUNT(SKUs!$I$5:$I$304),"",67) | B72: =IF(A72="","",INDEX(SKUs!$A$5:$A$304,MATCH(A72,SKUs!$I$5:$I$304,0))) | C72: =IF(A72="","",INDEX(SKUs!$B$5:$B$304,MATCH(A72,SKUs!$I$5:$I$304,0))) | D72: =IF(A72="","",INDEX(SKUs!$E$5:$E$304,MATCH(A72,SKUs!$I$5:$I$304,0))) | E72: =IF(A72="","",INDEX(SKUs!$F$5:$F$304,MATCH(A72,SKUs!$I$5:$I$304,0))) | F72: =IF(A72="","",INDEX(SKUs!$G$5:$G$304,MATCH(A72,SKUs!$I$5:$I$304,0))) | G72: =IF(A72="","",INDEX(SKUs!$H$5:$H$304,MATCH(A72,SKUs!$I$5:$I$304,0))) | H72: =IF(A72="","",IF(SUM(SKUs!$E$5:$E$304)=0,0,D72/SUM(SKUs!$E$5:$E$304))) | I72: =IF(A72="","",SUM($H$6:H72)) | J72: =IF(A72="","",IF(I72>=$B$3,1,0))
A73: =IF(68>COUNT(SKUs!$I$5:$I$304),"",68) | B73: =IF(A73="","",INDEX(SKUs!$A$5:$A$304,MATCH(A73,SKUs!$I$5:$I$304,0))) | C73: =IF(A73="","",INDEX(SKUs!$B$5:$B$304,MATCH(A73,SKUs!$I$5:$I$304,0))) | D73: =IF(A73="","",INDEX(SKUs!$E$5:$E$304,MATCH(A73,SKUs!$I$5:$I$304,0))) | E73: =IF(A73="","",INDEX(SKUs!$F$5:$F$304,MATCH(A73,SKUs!$I$5:$I$304,0))) | F73: =IF(A73="","",INDEX(SKUs!$G$5:$G$304,MATCH(A73,SKUs!$I$5:$I$304,0))) | G73: =IF(A73="","",INDEX(SKUs!$H$5:$H$304,MATCH(A73,SKUs!$I$5:$I$304,0))) | H73: =IF(A73="","",IF(SUM(SKUs!$E$5:$E$304)=0,0,D73/SUM(SKUs!$E$5:$E$304))) | I73: =IF(A73="","",SUM($H$6:H73)) | J73: =IF(A73="","",IF(I73>=$B$3,1,0))
A74: =IF(69>COUNT(SKUs!$I$5:$I$304),"",69) | B74: =IF(A74="","",INDEX(SKUs!$A$5:$A$304,MATCH(A74,SKUs!$I$5:$I$304,0))) | C74: =IF(A74="","",INDEX(SKUs!$B$5:$B$304,MATCH(A74,SKUs!$I$5:$I$304,0))) | D74: =IF(A74="","",INDEX(SKUs!$E$5:$E$304,MATCH(A74,SKUs!$I$5:$I$304,0))) | E74: =IF(A74="","",INDEX(SKUs!$F$5:$F$304,MATCH(A74,SKUs!$I$5:$I$304,0))) | F74: =IF(A74="","",INDEX(SKUs!$G$5:$G$304,MATCH(A74,SKUs!$I$5:$I$304,0))) | G74: =IF(A74="","",INDEX(SKUs!$H$5:$H$304,MATCH(A74,SKUs!$I$5:$I$304,0))) | H74: =IF(A74="","",IF(SUM(SKUs!$E$5:$E$304)=0,0,D74/SUM(SKUs!$E$5:$E$304))) | I74: =IF(A74="","",SUM($H$6:H74)) | J74: =IF(A74="","",IF(I74>=$B$3,1,0))
A75: =IF(70>COUNT(SKUs!$I$5:$I$304),"",70) | B75: =IF(A75="","",INDEX(SKUs!$A$5:$A$304,MATCH(A75,SKUs!$I$5:$I$304,0))) | C75: =IF(A75="","",INDEX(SKUs!$B$5:$B$304,MATCH(A75,SKUs!$I$5:$I$304,0))) | D75: =IF(A75="","",INDEX(SKUs!$E$5:$E$304,MATCH(A75,SKUs!$I$5:$I$304,0))) | E75: =IF(A75="","",INDEX(SKUs!$F$5:$F$304,MATCH(A75,SKUs!$I$5:$I$304,0))) | F75: =IF(A75="","",INDEX(SKUs!$G$5:$G$304,MATCH(A75,SKUs!$I$5:$I$304,0))) | G75: =IF(A75="","",INDEX(SKUs!$H$5:$H$304,MATCH(A75,SKUs!$I$5:$I$304,0))) | H75: =IF(A75="","",IF(SUM(SKUs!$E$5:$E$304)=0,0,D75/SUM(SKUs!$E$5:$E$304))) | I75: =IF(A75="","",SUM($H$6:H75)) | J75: =IF(A75="","",IF(I75>=$B$3,1,0))
A76: =IF(71>COUNT(SKUs!$I$5:$I$304),"",71) | B76: =IF(A76="","",INDEX(SKUs!$A$5:$A$304,MATCH(A76,SKUs!$I$5:$I$304,0))) | C76: =IF(A76="","",INDEX(SKUs!$B$5:$B$304,MATCH(A76,SKUs!$I$5:$I$304,0))) | D76: =IF(A76="","",INDEX(SKUs!$E$5:$E$304,MATCH(A76,SKUs!$I$5:$I$304,0))) | E76: =IF(A76="","",INDEX(SKUs!$F$5:$F$304,MATCH(A76,SKUs!$I$5:$I$304,0))) | F76: =IF(A76="","",INDEX(SKUs!$G$5:$G$304,MATCH(A76,SKUs!$I$5:$I$304,0))) | G76: =IF(A76="","",INDEX(SKUs!$H$5:$H$304,MATCH(A76,SKUs!$I$5:$I$304,0))) | H76: =IF(A76="","",IF(SUM(SKUs!$E$5:$E$304)=0,0,D76/SUM(SKUs!$E$5:$E$304))) | I76: =IF(A76="","",SUM($H$6:H76)) | J76: =IF(A76="","",IF(I76>=$B$3,1,0))
A77: =IF(72>COUNT(SKUs!$I$5:$I$304),"",72) | B77: =IF(A77="","",INDEX(SKUs!$A$5:$A$304,MATCH(A77,SKUs!$I$5:$I$304,0))) | C77: =IF(A77="","",INDEX(SKUs!$B$5:$B$304,MATCH(A77,SKUs!$I$5:$I$304,0))) | D77: =IF(A77="","",INDEX(SKUs!$E$5:$E$304,MATCH(A77,SKUs!$I$5:$I$304,0))) | E77: =IF(A77="","",INDEX(SKUs!$F$5:$F$304,MATCH(A77,SKUs!$I$5:$I$304,0))) | F77: =IF(A77="","",INDEX(SKUs!$G$5:$G$304,MATCH(A77,SKUs!$I$5:$I$304,0))) | G77: =IF(A77="","",INDEX(SKUs!$H$5:$H$304,MATCH(A77,SKUs!$I$5:$I$304,0))) | H77: =IF(A77="","",IF(SUM(SKUs!$E$5:$E$304)=0,0,D77/SUM(SKUs!$E$5:$E$304))) | I77: =IF(A77="","",SUM($H$6:H77)) | J77: =IF(A77="","",IF(I77>=$B$3,1,0))
A78: =IF(73>COUNT(SKUs!$I$5:$I$304),"",73) | B78: =IF(A78="","",INDEX(SKUs!$A$5:$A$304,MATCH(A78,SKUs!$I$5:$I$304,0))) | C78: =IF(A78="","",INDEX(SKUs!$B$5:$B$304,MATCH(A78,SKUs!$I$5:$I$304,0))) | D78: =IF(A78="","",INDEX(SKUs!$E$5:$E$304,MATCH(A78,SKUs!$I$5:$I$304,0))) | E78: =IF(A78="","",INDEX(SKUs!$F$5:$F$304,MATCH(A78,SKUs!$I$5:$I$304,0))) | F78: =IF(A78="","",INDEX(SKUs!$G$5:$G$304,MATCH(A78,SKUs!$I$5:$I$304,0))) | G78: =IF(A78="","",INDEX(SKUs!$H$5:$H$304,MATCH(A78,SKUs!$I$5:$I$304,0))) | H78: =IF(A78="","",IF(SUM(SKUs!$E$5:$E$304)=0,0,D78/SUM(SKUs!$E$5:$E$304))) | I78: =IF(A78="","",SUM($H$6:H78)) | J78: =IF(A78="","",IF(I78>=$B$3,1,0))
A79: =IF(74>COUNT(SKUs!$I$5:$I$304),"",74) | B79: =IF(A79="","",INDEX(SKUs!$A$5:$A$304,MATCH(A79,SKUs!$I$5:$I$304,0))) | C79: =IF(A79="","",INDEX(SKUs!$B$5:$B$304,MATCH(A79,SKUs!$I$5:$I$304,0))) | D79: =IF(A79="","",INDEX(SKUs!$E$5:$E$304,MATCH(A79,SKUs!$I$5:$I$304,0))) | E79: =IF(A79="","",INDEX(SKUs!$F$5:$F$304,MATCH(A79,SKUs!$I$5:$I$304,0))) | F79: =IF(A79="","",INDEX(SKUs!$G$5:$G$304,MATCH(A79,SKUs!$I$5:$I$304,0))) | G79: =IF(A79="","",INDEX(SKUs!$H$5:$H$304,MATCH(A79,SKUs!$I$5:$I$304,0))) | H79: =IF(A79="","",IF(SUM(SKUs!$E$5:$E$304)=0,0,D79/SUM(SKUs!$E$5:$E$304))) | I79: =IF(A79="","",SUM($H$6:H79)) | J79: =IF(A79="","",IF(I79>=$B$3,1,0))
A80: =IF(75>COUNT(SKUs!$I$5:$I$304),"",75) | B80: =IF(A80="","",INDEX(SKUs!$A$5:$A$304,MATCH(A80,SKUs!$I$5:$I$304,0))) | C80: =IF(A80="","",INDEX(SKUs!$B$5:$B$304,MATCH(A80,SKUs!$I$5:$I$304,0))) | D80: =IF(A80="","",INDEX(SKUs!$E$5:$E$304,MATCH(A80,SKUs!$I$5:$I$304,0))) | E80: =IF(A80="","",INDEX(SKUs!$F$5:$F$304,MATCH(A80,SKUs!$I$5:$I$304,0))) | F80: =IF(A80="","",INDEX(SKUs!$G$5:$G$304,MATCH(A80,SKUs!$I$5:$I$304,0))) | G80: =IF(A80="","",INDEX(SKUs!$H$5:$H$304,MATCH(A80,SKUs!$I$5:$I$304,0))) | H80: =IF(A80="","",IF(SUM(SKUs!$E$5:$E$304)=0,0,D80/SUM(SKUs!$E$5:$E$304))) | I80: =IF(A80="","",SUM($H$6:H80)) | J80: =IF(A80="","",IF(I80>=$B$3,1,0))
A81: =IF(76>COUNT(SKUs!$I$5:$I$304),"",76) | B81: =IF(A81="","",INDEX(SKUs!$A$5:$A$304,MATCH(A81,SKUs!$I$5:$I$304,0))) | C81: =IF(A81="","",INDEX(SKUs!$B$5:$B$304,MATCH(A81,SKUs!$I$5:$I$304,0))) | D81: =IF(A81="","",INDEX(SKUs!$E$5:$E$304,MATCH(A81,SKUs!$I$5:$I$304,0))) | E81: =IF(A81="","",INDEX(SKUs!$F$5:$F$304,MATCH(A81,SKUs!$I$5:$I$304,0))) | F81: =IF(A81="","",INDEX(SKUs!$G$5:$G$304,MATCH(A81,SKUs!$I$5:$I$304,0))) | G81: =IF(A81="","",INDEX(SKUs!$H$5:$H$304,MATCH(A81,SKUs!$I$5:$I$304,0))) | H81: =IF(A81="","",IF(SUM(SKUs!$E$5:$E$304)=0,0,D81/SUM(SKUs!$E$5:$E$304))) | I81: =IF(A81="","",SUM($H$6:H81)) | J81: =IF(A81="","",IF(I81>=$B$3,1,0))
A82: =IF(77>COUNT(SKUs!$I$5:$I$304),"",77) | B82: =IF(A82="","",INDEX(SKUs!$A$5:$A$304,MATCH(A82,SKUs!$I$5:$I$304,0))) | C82: =IF(A82="","",INDEX(SKUs!$B$5:$B$304,MATCH(A82,SKUs!$I$5:$I$304,0))) | D82: =IF(A82="","",INDEX(SKUs!$E$5:$E$304,MATCH(A82,SKUs!$I$5:$I$304,0))) | E82: =IF(A82="","",INDEX(SKUs!$F$5:$F$304,MATCH(A82,SKUs!$I$5:$I$304,0))) | F82: =IF(A82="","",INDEX(SKUs!$G$5:$G$304,MATCH(A82,SKUs!$I$5:$I$304,0))) | G82: =IF(A82="","",INDEX(SKUs!$H$5:$H$304,MATCH(A82,SKUs!$I$5:$I$304,0))) | H82: =IF(A82="","",IF(SUM(SKUs!$E$5:$E$304)=0,0,D82/SUM(SKUs!$E$5:$E$304))) | I82: =IF(A82="","",SUM($H$6:H82)) | J82: =IF(A82="","",IF(I82>=$B$3,1,0))
A83: =IF(78>COUNT(SKUs!$I$5:$I$304),"",78) | B83: =IF(A83="","",INDEX(SKUs!$A$5:$A$304,MATCH(A83,SKUs!$I$5:$I$304,0))) | C83: =IF(A83="","",INDEX(SKUs!$B$5:$B$304,MATCH(A83,SKUs!$I$5:$I$304,0))) | D83: =IF(A83="","",INDEX(SKUs!$E$5:$E$304,MATCH(A83,SKUs!$I$5:$I$304,0))) | E83: =IF(A83="","",INDEX(SKUs!$F$5:$F$304,MATCH(A83,SKUs!$I$5:$I$304,0))) | F83: =IF(A83="","",INDEX(SKUs!$G$5:$G$304,MATCH(A83,SKUs!$I$5:$I$304,0))) | G83: =IF(A83="","",INDEX(SKUs!$H$5:$H$304,MATCH(A83,SKUs!$I$5:$I$304,0))) | H83: =IF(A83="","",IF(SUM(SKUs!$E$5:$E$304)=0,0,D83/SUM(SKUs!$E$5:$E$304))) | I83: =IF(A83="","",SUM($H$6:H83)) | J83: =IF(A83="","",IF(I83>=$B$3,1,0))
A84: =IF(79>COUNT(SKUs!$I$5:$I$304),"",79) | B84: =IF(A84="","",INDEX(SKUs!$A$5:$A$304,MATCH(A84,SKUs!$I$5:$I$304,0))) | C84: =IF(A84="","",INDEX(SKUs!$B$5:$B$304,MATCH(A84,SKUs!$I$5:$I$304,0))) | D84: =IF(A84="","",INDEX(SKUs!$E$5:$E$304,MATCH(A84,SKUs!$I$5:$I$304,0))) | E84: =IF(A84="","",INDEX(SKUs!$F$5:$F$304,MATCH(A84,SKUs!$I$5:$I$304,0))) | F84: =IF(A84="","",INDEX(SKUs!$G$5:$G$304,MATCH(A84,SKUs!$I$5:$I$304,0))) | G84: =IF(A84="","",INDEX(SKUs!$H$5:$H$304,MATCH(A84,SKUs!$I$5:$I$304,0))) | H84: =IF(A84="","",IF(SUM(SKUs!$E$5:$E$304)=0,0,D84/SUM(SKUs!$E$5:$E$304))) | I84: =IF(A84="","",SUM($H$6:H84)) | J84: =IF(A84="","",IF(I84>=$B$3,1,0))
A85: =IF(80>COUNT(SKUs!$I$5:$I$304),"",80) | B85: =IF(A85="","",INDEX(SKUs!$A$5:$A$304,MATCH(A85,SKUs!$I$5:$I$304,0))) | C85: =IF(A85="","",INDEX(SKUs!$B$5:$B$304,MATCH(A85,SKUs!$I$5:$I$304,0))) | D85: =IF(A85="","",INDEX(SKUs!$E$5:$E$304,MATCH(A85,SKUs!$I$5:$I$304,0))) | E85: =IF(A85="","",INDEX(SKUs!$F$5:$F$304,MATCH(A85,SKUs!$I$5:$I$304,0))) | F85: =IF(A85="","",INDEX(SKUs!$G$5:$G$304,MATCH(A85,SKUs!$I$5:$I$304,0))) | G85: =IF(A85="","",INDEX(SKUs!$H$5:$H$304,MATCH(A85,SKUs!$I$5:$I$304,0))) | H85: =IF(A85="","",IF(SUM(SKUs!$E$5:$E$304)=0,0,D85/SUM(SKUs!$E$5:$E$304))) | I85: =IF(A85="","",SUM($H$6:H85)) | J85: =IF(A85="","",IF(I85>=$B$3,1,0))
A86: =IF(81>COUNT(SKUs!$I$5:$I$304),"",81) | B86: =IF(A86="","",INDEX(SKUs!$A$5:$A$304,MATCH(A86,SKUs!$I$5:$I$304,0))) | C86: =IF(A86="","",INDEX(SKUs!$B$5:$B$304,MATCH(A86,SKUs!$I$5:$I$304,0))) | D86: =IF(A86="","",INDEX(SKUs!$E$5:$E$304,MATCH(A86,SKUs!$I$5:$I$304,0))) | E86: =IF(A86="","",INDEX(SKUs!$F$5:$F$304,MATCH(A86,SKUs!$I$5:$I$304,0))) | F86: =IF(A86="","",INDEX(SKUs!$G$5:$G$304,MATCH(A86,SKUs!$I$5:$I$304,0))) | G86: =IF(A86="","",INDEX(SKUs!$H$5:$H$304,MATCH(A86,SKUs!$I$5:$I$304,0))) | H86: =IF(A86="","",IF(SUM(SKUs!$E$5:$E$304)=0,0,D86/SUM(SKUs!$E$5:$E$304))) | I86: =IF(A86="","",SUM($H$6:H86)) | J86: =IF(A86="","",IF(I86>=$B$3,1,0))
A87: =IF(82>COUNT(SKUs!$I$5:$I$304),"",82) | B87: =IF(A87="","",INDEX(SKUs!$A$5:$A$304,MATCH(A87,SKUs!$I$5:$I$304,0))) | C87: =IF(A87="","",INDEX(SKUs!$B$5:$B$304,MATCH(A87,SKUs!$I$5:$I$304,0))) | D87: =IF(A87="","",INDEX(SKUs!$E$5:$E$304,MATCH(A87,SKUs!$I$5:$I$304,0))) | E87: =IF(A87="","",INDEX(SKUs!$F$5:$F$304,MATCH(A87,SKUs!$I$5:$I$304,0))) | F87: =IF(A87="","",INDEX(SKUs!$G$5:$G$304,MATCH(A87,SKUs!$I$5:$I$304,0))) | G87: =IF(A87="","",INDEX(SKUs!$H$5:$H$304,MATCH(A87,SKUs!$I$5:$I$304,0))) | H87: =IF(A87="","",IF(SUM(SKUs!$E$5:$E$304)=0,0,D87/SUM(SKUs!$E$5:$E$304))) | I87: =IF(A87="","",SUM($H$6:H87)) | J87: =IF(A87="","",IF(I87>=$B$3,1,0))
A88: =IF(83>COUNT(SKUs!$I$5:$I$304),"",83) | B88: =IF(A88="","",INDEX(SKUs!$A$5:$A$304,MATCH(A88,SKUs!$I$5:$I$304,0))) | C88: =IF(A88="","",INDEX(SKUs!$B$5:$B$304,MATCH(A88,SKUs!$I$5:$I$304,0))) | D88: =IF(A88="","",INDEX(SKUs!$E$5:$E$304,MATCH(A88,SKUs!$I$5:$I$304,0))) | E88: =IF(A88="","",INDEX(SKUs!$F$5:$F$304,MATCH(A88,SKUs!$I$5:$I$304,0))) | F88: =IF(A88="","",INDEX(SKUs!$G$5:$G$304,MATCH(A88,SKUs!$I$5:$I$304,0))) | G88: =IF(A88="","",INDEX(SKUs!$H$5:$H$304,MATCH(A88,SKUs!$I$5:$I$304,0))) | H88: =IF(A88="","",IF(SUM(SKUs!$E$5:$E$304)=0,0,D88/SUM(SKUs!$E$5:$E$304))) | I88: =IF(A88="","",SUM($H$6:H88)) | J88: =IF(A88="","",IF(I88>=$B$3,1,0))
A89: =IF(84>COUNT(SKUs!$I$5:$I$304),"",84) | B89: =IF(A89="","",INDEX(SKUs!$A$5:$A$304,MATCH(A89,SKUs!$I$5:$I$304,0))) | C89: =IF(A89="","",INDEX(SKUs!$B$5:$B$304,MATCH(A89,SKUs!$I$5:$I$304,0))) | D89: =IF(A89="","",INDEX(SKUs!$E$5:$E$304,MATCH(A89,SKUs!$I$5:$I$304,0))) | E89: =IF(A89="","",INDEX(SKUs!$F$5:$F$304,MATCH(A89,SKUs!$I$5:$I$304,0))) | F89: =IF(A89="","",INDEX(SKUs!$G$5:$G$304,MATCH(A89,SKUs!$I$5:$I$304,0))) | G89: =IF(A89="","",INDEX(SKUs!$H$5:$H$304,MATCH(A89,SKUs!$I$5:$I$304,0))) | H89: =IF(A89="","",IF(SUM(SKUs!$E$5:$E$304)=0,0,D89/SUM(SKUs!$E$5:$E$304))) | I89: =IF(A89="","",SUM($H$6:H89)) | J89: =IF(A89="","",IF(I89>=$B$3,1,0))
A90: =IF(85>COUNT(SKUs!$I$5:$I$304),"",85) | B90: =IF(A90="","",INDEX(SKUs!$A$5:$A$304,MATCH(A90,SKUs!$I$5:$I$304,0))) | C90: =IF(A90="","",INDEX(SKUs!$B$5:$B$304,MATCH(A90,SKUs!$I$5:$I$304,0))) | D90: =IF(A90="","",INDEX(SKUs!$E$5:$E$304,MATCH(A90,SKUs!$I$5:$I$304,0))) | E90: =IF(A90="","",INDEX(SKUs!$F$5:$F$304,MATCH(A90,SKUs!$I$5:$I$304,0))) | F90: =IF(A90="","",INDEX(SKUs!$G$5:$G$304,MATCH(A90,SKUs!$I$5:$I$304,0))) | G90: =IF(A90="","",INDEX(SKUs!$H$5:$H$304,MATCH(A90,SKUs!$I$5:$I$304,0))) | H90: =IF(A90="","",IF(SUM(SKUs!$E$5:$E$304)=0,0,D90/SUM(SKUs!$E$5:$E$304))) | I90: =IF(A90="","",SUM($H$6:H90)) | J90: =IF(A90="","",IF(I90>=$B$3,1,0))
A91: =IF(86>COUNT(SKUs!$I$5:$I$304),"",86) | B91: =IF(A91="","",INDEX(SKUs!$A$5:$A$304,MATCH(A91,SKUs!$I$5:$I$304,0))) | C91: =IF(A91="","",INDEX(SKUs!$B$5:$B$304,MATCH(A91,SKUs!$I$5:$I$304,0))) | D91: =IF(A91="","",INDEX(SKUs!$E$5:$E$304,MATCH(A91,SKUs!$I$5:$I$304,0))) | E91: =IF(A91="","",INDEX(SKUs!$F$5:$F$304,MATCH(A91,SKUs!$I$5:$I$304,0))) | F91: =IF(A91="","",INDEX(SKUs!$G$5:$G$304,MATCH(A91,SKUs!$I$5:$I$304,0))) | G91: =IF(A91="","",INDEX(SKUs!$H$5:$H$304,MATCH(A91,SKUs!$I$5:$I$304,0))) | H91: =IF(A91="","",IF(SUM(SKUs!$E$5:$E$304)=0,0,D91/SUM(SKUs!$E$5:$E$304))) | I91: =IF(A91="","",SUM($H$6:H91)) | J91: =IF(A91="","",IF(I91>=$B$3,1,0))
A92: =IF(87>COUNT(SKUs!$I$5:$I$304),"",87) | B92: =IF(A92="","",INDEX(SKUs!$A$5:$A$304,MATCH(A92,SKUs!$I$5:$I$304,0))) | C92: =IF(A92="","",INDEX(SKUs!$B$5:$B$304,MATCH(A92,SKUs!$I$5:$I$304,0))) | D92: =IF(A92="","",INDEX(SKUs!$E$5:$E$304,MATCH(A92,SKUs!$I$5:$I$304,0))) | E92: =IF(A92="","",INDEX(SKUs!$F$5:$F$304,MATCH(A92,SKUs!$I$5:$I$304,0))) | F92: =IF(A92="","",INDEX(SKUs!$G$5:$G$304,MATCH(A92,SKUs!$I$5:$I$304,0))) | G92: =IF(A92="","",INDEX(SKUs!$H$5:$H$304,MATCH(A92,SKUs!$I$5:$I$304,0))) | H92: =IF(A92="","",IF(SUM(SKUs!$E$5:$E$304)=0,0,D92/SUM(SKUs!$E$5:$E$304))) | I92: =IF(A92="","",SUM($H$6:H92)) | J92: =IF(A92="","",IF(I92>=$B$3,1,0))
A93: =IF(88>COUNT(SKUs!$I$5:$I$304),"",88) | B93: =IF(A93="","",INDEX(SKUs!$A$5:$A$304,MATCH(A93,SKUs!$I$5:$I$304,0))) | C93: =IF(A93="","",INDEX(SKUs!$B$5:$B$304,MATCH(A93,SKUs!$I$5:$I$304,0))) | D93: =IF(A93="","",INDEX(SKUs!$E$5:$E$304,MATCH(A93,SKUs!$I$5:$I$304,0))) | E93: =IF(A93="","",INDEX(SKUs!$F$5:$F$304,MATCH(A93,SKUs!$I$5:$I$304,0))) | F93: =IF(A93="","",INDEX(SKUs!$G$5:$G$304,MATCH(A93,SKUs!$I$5:$I$304,0))) | G93: =IF(A93="","",INDEX(SKUs!$H$5:$H$304,MATCH(A93,SKUs!$I$5:$I$304,0))) | H93: =IF(A93="","",IF(SUM(SKUs!$E$5:$E$304)=0,0,D93/SUM(SKUs!$E$5:$E$304))) | I93: =IF(A93="","",SUM($H$6:H93)) | J93: =IF(A93="","",IF(I93>=$B$3,1,0))
A94: =IF(89>COUNT(SKUs!$I$5:$I$304),"",89) | B94: =IF(A94="","",INDEX(SKUs!$A$5:$A$304,MATCH(A94,SKUs!$I$5:$I$304,0))) | C94: =IF(A94="","",INDEX(SKUs!$B$5:$B$304,MATCH(A94,SKUs!$I$5:$I$304,0))) | D94: =IF(A94="","",INDEX(SKUs!$E$5:$E$304,MATCH(A94,SKUs!$I$5:$I$304,0))) | E94: =IF(A94="","",INDEX(SKUs!$F$5:$F$304,MATCH(A94,SKUs!$I$5:$I$304,0))) | F94: =IF(A94="","",INDEX(SKUs!$G$5:$G$304,MATCH(A94,SKUs!$I$5:$I$304,0))) | G94: =IF(A94="","",INDEX(SKUs!$H$5:$H$304,MATCH(A94,SKUs!$I$5:$I$304,0))) | H94: =IF(A94="","",IF(SUM(SKUs!$E$5:$E$304)=0,0,D94/SUM(SKUs!$E$5:$E$304))) | I94: =IF(A94="","",SUM($H$6:H94)) | J94: =IF(A94="","",IF(I94>=$B$3,1,0))
A95: =IF(90>COUNT(SKUs!$I$5:$I$304),"",90) | B95: =IF(A95="","",INDEX(SKUs!$A$5:$A$304,MATCH(A95,SKUs!$I$5:$I$304,0))) | C95: =IF(A95="","",INDEX(SKUs!$B$5:$B$304,MATCH(A95,SKUs!$I$5:$I$304,0))) | D95: =IF(A95="","",INDEX(SKUs!$E$5:$E$304,MATCH(A95,SKUs!$I$5:$I$304,0))) | E95: =IF(A95="","",INDEX(SKUs!$F$5:$F$304,MATCH(A95,SKUs!$I$5:$I$304,0))) | F95: =IF(A95="","",INDEX(SKUs!$G$5:$G$304,MATCH(A95,SKUs!$I$5:$I$304,0))) | G95: =IF(A95="","",INDEX(SKUs!$H$5:$H$304,MATCH(A95,SKUs!$I$5:$I$304,0))) | H95: =IF(A95="","",IF(SUM(SKUs!$E$5:$E$304)=0,0,D95/SUM(SKUs!$E$5:$E$304))) | I95: =IF(A95="","",SUM($H$6:H95)) | J95: =IF(A95="","",IF(I95>=$B$3,1,0))
A96: =IF(91>COUNT(SKUs!$I$5:$I$304),"",91) | B96: =IF(A96="","",INDEX(SKUs!$A$5:$A$304,MATCH(A96,SKUs!$I$5:$I$304,0))) | C96: =IF(A96="","",INDEX(SKUs!$B$5:$B$304,MATCH(A96,SKUs!$I$5:$I$304,0))) | D96: =IF(A96="","",INDEX(SKUs!$E$5:$E$304,MATCH(A96,SKUs!$I$5:$I$304,0))) | E96: =IF(A96="","",INDEX(SKUs!$F$5:$F$304,MATCH(A96,SKUs!$I$5:$I$304,0))) | F96: =IF(A96="","",INDEX(SKUs!$G$5:$G$304,MATCH(A96,SKUs!$I$5:$I$304,0))) | G96: =IF(A96="","",INDEX(SKUs!$H$5:$H$304,MATCH(A96,SKUs!$I$5:$I$304,0))) | H96: =IF(A96="","",IF(SUM(SKUs!$E$5:$E$304)=0,0,D96/SUM(SKUs!$E$5:$E$304))) | I96: =IF(A96="","",SUM($H$6:H96)) | J96: =IF(A96="","",IF(I96>=$B$3,1,0))
A97: =IF(92>COUNT(SKUs!$I$5:$I$304),"",92) | B97: =IF(A97="","",INDEX(SKUs!$A$5:$A$304,MATCH(A97,SKUs!$I$5:$I$304,0))) | C97: =IF(A97="","",INDEX(SKUs!$B$5:$B$304,MATCH(A97,SKUs!$I$5:$I$304,0))) | D97: =IF(A97="","",INDEX(SKUs!$E$5:$E$304,MATCH(A97,SKUs!$I$5:$I$304,0))) | E97: =IF(A97="","",INDEX(SKUs!$F$5:$F$304,MATCH(A97,SKUs!$I$5:$I$304,0))) | F97: =IF(A97="","",INDEX(SKUs!$G$5:$G$304,MATCH(A97,SKUs!$I$5:$I$304,0))) | G97: =IF(A97="","",INDEX(SKUs!$H$5:$H$304,MATCH(A97,SKUs!$I$5:$I$304,0))) | H97: =IF(A97="","",IF(SUM(SKUs!$E$5:$E$304)=0,0,D97/SUM(SKUs!$E$5:$E$304))) | I97: =IF(A97="","",SUM($H$6:H97)) | J97: =IF(A97="","",IF(I97>=$B$3,1,0))
A98: =IF(93>COUNT(SKUs!$I$5:$I$304),"",93) | B98: =IF(A98="","",INDEX(SKUs!$A$5:$A$304,MATCH(A98,SKUs!$I$5:$I$304,0))) | C98: =IF(A98="","",INDEX(SKUs!$B$5:$B$304,MATCH(A98,SKUs!$I$5:$I$304,0))) | D98: =IF(A98="","",INDEX(SKUs!$E$5:$E$304,MATCH(A98,SKUs!$I$5:$I$304,0))) | E98: =IF(A98="","",INDEX(SKUs!$F$5:$F$304,MATCH(A98,SKUs!$I$5:$I$304,0))) | F98: =IF(A98="","",INDEX(SKUs!$G$5:$G$304,MATCH(A98,SKUs!$I$5:$I$304,0))) | G98: =IF(A98="","",INDEX(SKUs!$H$5:$H$304,MATCH(A98,SKUs!$I$5:$I$304,0))) | H98: =IF(A98="","",IF(SUM(SKUs!$E$5:$E$304)=0,0,D98/SUM(SKUs!$E$5:$E$304))) | I98: =IF(A98="","",SUM($H$6:H98)) | J98: =IF(A98="","",IF(I98>=$B$3,1,0))
A99: =IF(94>COUNT(SKUs!$I$5:$I$304),"",94) | B99: =IF(A99="","",INDEX(SKUs!$A$5:$A$304,MATCH(A99,SKUs!$I$5:$I$304,0))) | C99: =IF(A99="","",INDEX(SKUs!$B$5:$B$304,MATCH(A99,SKUs!$I$5:$I$304,0))) | D99: =IF(A99="","",INDEX(SKUs!$E$5:$E$304,MATCH(A99,SKUs!$I$5:$I$304,0))) | E99: =IF(A99="","",INDEX(SKUs!$F$5:$F$304,MATCH(A99,SKUs!$I$5:$I$304,0))) | F99: =IF(A99="","",INDEX(SKUs!$G$5:$G$304,MATCH(A99,SKUs!$I$5:$I$304,0))) | G99: =IF(A99="","",INDEX(SKUs!$H$5:$H$304,MATCH(A99,SKUs!$I$5:$I$304,0))) | H99: =IF(A99="","",IF(SUM(SKUs!$E$5:$E$304)=0,0,D99/SUM(SKUs!$E$5:$E$304))) | I99: =IF(A99="","",SUM($H$6:H99)) | J99: =IF(A99="","",IF(I99>=$B$3,1,0))
A100: =IF(95>COUNT(SKUs!$I$5:$I$304),"",95) | B100: =IF(A100="","",INDEX(SKUs!$A$5:$A$304,MATCH(A100,SKUs!$I$5:$I$304,0))) | C100: =IF(A100="","",INDEX(SKUs!$B$5:$B$304,MATCH(A100,SKUs!$I$5:$I$304,0))) | D100: =IF(A100="","",INDEX(SKUs!$E$5:$E$304,MATCH(A100,SKUs!$I$5:$I$304,0))) | E100: =IF(A100="","",INDEX(SKUs!$F$5:$F$304,MATCH(A100,SKUs!$I$5:$I$304,0))) | F100: =IF(A100="","",INDEX(SKUs!$G$5:$G$304,MATCH(A100,SKUs!$I$5:$I$304,0))) | G100: =IF(A100="","",INDEX(SKUs!$H$5:$H$304,MATCH(A100,SKUs!$I$5:$I$304,0))) | H100: =IF(A100="","",IF(SUM(SKUs!$E$5:$E$304)=0,0,D100/SUM(SKUs!$E$5:$E$304))) | I100: =IF(A100="","",SUM($H$6:H100)) | J100: =IF(A100="","",IF(I100>=$B$3,1,0))
A101: =IF(96>COUNT(SKUs!$I$5:$I$304),"",96) | B101: =IF(A101="","",INDEX(SKUs!$A$5:$A$304,MATCH(A101,SKUs!$I$5:$I$304,0))) | C101: =IF(A101="","",INDEX(SKUs!$B$5:$B$304,MATCH(A101,SKUs!$I$5:$I$304,0))) | D101: =IF(A101="","",INDEX(SKUs!$E$5:$E$304,MATCH(A101,SKUs!$I$5:$I$304,0))) | E101: =IF(A101="","",INDEX(SKUs!$F$5:$F$304,MATCH(A101,SKUs!$I$5:$I$304,0))) | F101: =IF(A101="","",INDEX(SKUs!$G$5:$G$304,MATCH(A101,SKUs!$I$5:$I$304,0))) | G101: =IF(A101="","",INDEX(SKUs!$H$5:$H$304,MATCH(A101,SKUs!$I$5:$I$304,0))) | H101: =IF(A101="","",IF(SUM(SKUs!$E$5:$E$304)=0,0,D101/SUM(SKUs!$E$5:$E$304))) | I101: =IF(A101="","",SUM($H$6:H101)) | J101: =IF(A101="","",IF(I101>=$B$3,1,0))
A102: =IF(97>COUNT(SKUs!$I$5:$I$304),"",97) | B102: =IF(A102="","",INDEX(SKUs!$A$5:$A$304,MATCH(A102,SKUs!$I$5:$I$304,0))) | C102: =IF(A102="","",INDEX(SKUs!$B$5:$B$304,MATCH(A102,SKUs!$I$5:$I$304,0))) | D102: =IF(A102="","",INDEX(SKUs!$E$5:$E$304,MATCH(A102,SKUs!$I$5:$I$304,0))) | E102: =IF(A102="","",INDEX(SKUs!$F$5:$F$304,MATCH(A102,SKUs!$I$5:$I$304,0))) | F102: =IF(A102="","",INDEX(SKUs!$G$5:$G$304,MATCH(A102,SKUs!$I$5:$I$304,0))) | G102: =IF(A102="","",INDEX(SKUs!$H$5:$H$304,MATCH(A102,SKUs!$I$5:$I$304,0))) | H102: =IF(A102="","",IF(SUM(SKUs!$E$5:$E$304)=0,0,D102/SUM(SKUs!$E$5:$E$304))) | I102: =IF(A102="","",SUM($H$6:H102)) | J102: =IF(A102="","",IF(I102>=$B$3,1,0))
...
