Workbook
Name seg_total_sales: 'Segments'!$B$18
Name seg_total_ebitda: 'Segments'!$E$18

Sheet README
A1: K07 · Segment P&L, Roll-up & Segment Forecast (no-code kernel)
A3: Replaces openfpa: pyfpa.analysis.segments (Segment, segment_pnl, roll_up_segments, segments_to_channels) and the generated segment-rollup skill.
A4: Segment = net sales + Adjusted-EBITDA margin (+ annual growth). Adjusted EBITDA = net sales x margin. Consolidated margin is RECOMPUTED from totals (revenue-weighted), never averaged.
A5: segments_to_channels: each segment becomes a K01 revenue channel with flat seasonality (1 x 12), its own growth, and the CONSOLIDATED blended cogs_pct (segment COGS is usually not disclosed - Ind AS 108 / ASU 2023-07 style). Copy the 'ToChannels' block into K01 Assumptions.
A6: SegmentForecast applies per-year growth and margin assumptions (the _grow step used in the Fox Factory example) for up to 5 forecast years.

Sheet Checks
A1: Checks - OVERALL must be PASS
B3: OVERALL | C3: =IF(COUNTIF(C5:C8,"PASS")=COUNT(A5:A8),"PASS","FAIL") | D3: =COUNTIF(C5:C8,"PASS")&" pass / "&COUNTIF(C5:C8,"FAIL")&" fail / "&(COUNT(A5:A8)-COUNTIF(C5:C8,"PASS")-COUNTIF(C5:C8,"FAIL"))&" error"
A4: # | B4: check | C4: result | D4: detail
A5: 1 | B5: segment net_sales >= 0 | C5: =IF(COUNTIF(Segments!B5:B16,"<0")=0,"PASS","FAIL")
A6: 2 | B6: segment names unique | C6: =IF(SUMPRODUCT((Segments!A5:A16<>"")*(COUNTIF(Segments!A5:A16,Segments!A5:A16)>1))=0,"PASS","FAIL")
A7: 3 | B7: channel block sums back to consolidated net sales | C7: =IF(ABS(SUM(ToChannels!B5:B16)-Segments!$B$18)<0.005,"PASS","FAIL")
A8: 4 | B8: blended cogs_pct within 0..1 | C8: =IF(AND(Segments!B20>=0,Segments!B20<=1),"PASS","FAIL")

Sheet Segments
A1: Segments (segment_pnl + roll_up_segments)
A4: segment | B4: net_sales | C4: growth_rate | D4: ebitda_margin | E4: adjusted_ebitda
E5: =IF(A5="","",B5*D5)
E6: =IF(A6="","",B6*D6)
E7: =IF(A7="","",B7*D7)
E8: =IF(A8="","",B8*D8)
E9: =IF(A9="","",B9*D9)
E10: =IF(A10="","",B10*D10)
E11: =IF(A11="","",B11*D11)
E12: =IF(A12="","",B12*D12)
E13: =IF(A13="","",B13*D13)
E14: =IF(A14="","",B14*D14)
E15: =IF(A15="","",B15*D15)
E16: =IF(A16="","",B16*D16)
A18: TOTAL | B18: =SUM(B5:B16) | D18: =IF(B18=0,0,E18/B18) | E18: =SUM(E5:E16)
A20: blended consolidated cogs_pct | B20: 0

Sheet ToChannels
A1: segments_to_channels - paste into K01 Assumptions channel rows
A4: channel name | B4: annual_revenue | C4: growth_rate | D4: cogs_pct | E4: season 1 | F4: season 2 | G4: season 3 | H4: season 4 | I4: season 5 | J4: season 6 | K4: season 7 | L4: season 8 | M4: season 9 | N4: season 10 | O4: season 11 | P4: season 12
A5: =IF(Segments!A5="","",Segments!A5) | B5: =IF(A5="","",Segments!B5) | C5: =IF(A5="","",Segments!C5) | D5: =IF(A5="","",Segments!$B$20) | E5: =IF(A5="","",1) | F5: =IF(A5="","",1) | G5: =IF(A5="","",1) | H5: =IF(A5="","",1) | I5: =IF(A5="","",1) | J5: =IF(A5="","",1) | K5: =IF(A5="","",1) | L5: =IF(A5="","",1) | M5: =IF(A5="","",1) | N5: =IF(A5="","",1) | O5: =IF(A5="","",1) | P5: =IF(A5="","",1)
A6: =IF(Segments!A6="","",Segments!A6) | B6: =IF(A6="","",Segments!B6) | C6: =IF(A6="","",Segments!C6) | D6: =IF(A6="","",Segments!$B$20) | E6: =IF(A6="","",1) | F6: =IF(A6="","",1) | G6: =IF(A6="","",1) | H6: =IF(A6="","",1) | I6: =IF(A6="","",1) | J6: =IF(A6="","",1) | K6: =IF(A6="","",1) | L6: =IF(A6="","",1) | M6: =IF(A6="","",1) | N6: =IF(A6="","",1) | O6: =IF(A6="","",1) | P6: =IF(A6="","",1)
A7: =IF(Segments!A7="","",Segments!A7) | B7: =IF(A7="","",Segments!B7) | C7: =IF(A7="","",Segments!C7) | D7: =IF(A7="","",Segments!$B$20) | E7: =IF(A7="","",1) | F7: =IF(A7="","",1) | G7: =IF(A7="","",1) | H7: =IF(A7="","",1) | I7: =IF(A7="","",1) | J7: =IF(A7="","",1) | K7: =IF(A7="","",1) | L7: =IF(A7="","",1) | M7: =IF(A7="","",1) | N7: =IF(A7="","",1) | O7: =IF(A7="","",1) | P7: =IF(A7="","",1)
A8: =IF(Segments!A8="","",Segments!A8) | B8: =IF(A8="","",Segments!B8) | C8: =IF(A8="","",Segments!C8) | D8: =IF(A8="","",Segments!$B$20) | E8: =IF(A8="","",1) | F8: =IF(A8="","",1) | G8: =IF(A8="","",1) | H8: =IF(A8="","",1) | I8: =IF(A8="","",1) | J8: =IF(A8="","",1) | K8: =IF(A8="","",1) | L8: =IF(A8="","",1) | M8: =IF(A8="","",1) | N8: =IF(A8="","",1) | O8: =IF(A8="","",1) | P8: =IF(A8="","",1)
A9: =IF(Segments!A9="","",Segments!A9) | B9: =IF(A9="","",Segments!B9) | C9: =IF(A9="","",Segments!C9) | D9: =IF(A9="","",Segments!$B$20) | E9: =IF(A9="","",1) | F9: =IF(A9="","",1) | G9: =IF(A9="","",1) | H9: =IF(A9="","",1) | I9: =IF(A9="","",1) | J9: =IF(A9="","",1) | K9: =IF(A9="","",1) | L9: =IF(A9="","",1) | M9: =IF(A9="","",1) | N9: =IF(A9="","",1) | O9: =IF(A9="","",1) | P9: =IF(A9="","",1)
A10: =IF(Segments!A10="","",Segments!A10) | B10: =IF(A10="","",Segments!B10) | C10: =IF(A10="","",Segments!C10) | D10: =IF(A10="","",Segments!$B$20) | E10: =IF(A10="","",1) | F10: =IF(A10="","",1) | G10: =IF(A10="","",1) | H10: =IF(A10="","",1) | I10: =IF(A10="","",1) | J10: =IF(A10="","",1) | K10: =IF(A10="","",1) | L10: =IF(A10="","",1) | M10: =IF(A10="","",1) | N10: =IF(A10="","",1) | O10: =IF(A10="","",1) | P10: =IF(A10="","",1)
A11: =IF(Segments!A11="","",Segments!A11) | B11: =IF(A11="","",Segments!B11) | C11: =IF(A11="","",Segments!C11) | D11: =IF(A11="","",Segments!$B$20) | E11: =IF(A11="","",1) | F11: =IF(A11="","",1) | G11: =IF(A11="","",1) | H11: =IF(A11="","",1) | I11: =IF(A11="","",1) | J11: =IF(A11="","",1) | K11: =IF(A11="","",1) | L11: =IF(A11="","",1) | M11: =IF(A11="","",1) | N11: =IF(A11="","",1) | O11: =IF(A11="","",1) | P11: =IF(A11="","",1)
A12: =IF(Segments!A12="","",Segments!A12) | B12: =IF(A12="","",Segments!B12) | C12: =IF(A12="","",Segments!C12) | D12: =IF(A12="","",Segments!$B$20) | E12: =IF(A12="","",1) | F12: =IF(A12="","",1) | G12: =IF(A12="","",1) | H12: =IF(A12="","",1) | I12: =IF(A12="","",1) | J12: =IF(A12="","",1) | K12: =IF(A12="","",1) | L12: =IF(A12="","",1) | M12: =IF(A12="","",1) | N12: =IF(A12="","",1) | O12: =IF(A12="","",1) | P12: =IF(A12="","",1)
A13: =IF(Segments!A13="","",Segments!A13) | B13: =IF(A13="","",Segments!B13) | C13: =IF(A13="","",Segments!C13) | D13: =IF(A13="","",Segments!$B$20) | E13: =IF(A13="","",1) | F13: =IF(A13="","",1) | G13: =IF(A13="","",1) | H13: =IF(A13="","",1) | I13: =IF(A13="","",1) | J13: =IF(A13="","",1) | K13: =IF(A13="","",1) | L13: =IF(A13="","",1) | M13: =IF(A13="","",1) | N13: =IF(A13="","",1) | O13: =IF(A13="","",1) | P13: =IF(A13="","",1)
A14: =IF(Segments!A14="","",Segments!A14) | B14: =IF(A14="","",Segments!B14) | C14: =IF(A14="","",Segments!C14) | D14: =IF(A14="","",Segments!$B$20) | E14: =IF(A14="","",1) | F14: =IF(A14="","",1) | G14: =IF(A14="","",1) | H14: =IF(A14="","",1) | I14: =IF(A14="","",1) | J14: =IF(A14="","",1) | K14: =IF(A14="","",1) | L14: =IF(A14="","",1) | M14: =IF(A14="","",1) | N14: =IF(A14="","",1) | O14: =IF(A14="","",1) | P14: =IF(A14="","",1)
A15: =IF(Segments!A15="","",Segments!A15) | B15: =IF(A15="","",Segments!B15) | C15: =IF(A15="","",Segments!C15) | D15: =IF(A15="","",Segments!$B$20) | E15: =IF(A15="","",1) | F15: =IF(A15="","",1) | G15: =IF(A15="","",1) | H15: =IF(A15="","",1) | I15: =IF(A15="","",1) | J15: =IF(A15="","",1) | K15: =IF(A15="","",1) | L15: =IF(A15="","",1) | M15: =IF(A15="","",1) | N15: =IF(A15="","",1) | O15: =IF(A15="","",1) | P15: =IF(A15="","",1)
A16: =IF(Segments!A16="","",Segments!A16) | B16: =IF(A16="","",Segments!B16) | C16: =IF(A16="","",Segments!C16) | D16: =IF(A16="","",Segments!$B$20) | E16: =IF(A16="","",1) | F16: =IF(A16="","",1) | G16: =IF(A16="","",1) | H16: =IF(A16="","",1) | I16: =IF(A16="","",1) | J16: =IF(A16="","",1) | K16: =IF(A16="","",1) | L16: =IF(A16="","",1) | M16: =IF(A16="","",1) | N16: =IF(A16="","",1) | O16: =IF(A16="","",1) | P16: =IF(A16="","",1)

Sheet SegmentForecast
A1: Segment forecast: year-by-year growth and margin assumptions (_grow)
A3: year labels ->
A4: segment | B4: base net_sales | C4: Y1 growth | D4: Y1 margin | E4: Y1 net_sales | F4: Y1 adj EBITDA | G4: Y2 growth | H4: Y2 margin | I4: Y2 net_sales | J4: Y2 adj EBITDA | K4: Y3 growth | L4: Y3 margin | M4: Y3 net_sales | N4: Y3 adj EBITDA | O4: Y4 growth | P4: Y4 margin | Q4: Y4 net_sales | R4: Y4 adj EBITDA | S4: Y5 growth | T4: Y5 margin | U4: Y5 net_sales | V4: Y5 adj EBITDA
A5: =IF(Segments!A5="","",Segments!A5) | B5: =IF(A5="","",Segments!B5) | E5: =IF(OR(A5="",C5=""),"",B5*(1+C5)) | F5: =IF(E5="","",E5*D5) | I5: =IF(OR(A5="",G5=""),"",E5*(1+G5)) | J5: =IF(I5="","",I5*H5) | M5: =IF(OR(A5="",K5=""),"",I5*(1+K5)) | N5: =IF(M5="","",M5*L5) | Q5: =IF(OR(A5="",O5=""),"",M5*(1+O5)) | R5: =IF(Q5="","",Q5*P5) | U5: =IF(OR(A5="",S5=""),"",Q5*(1+S5)) | V5: =IF(U5="","",U5*T5)
A6: =IF(Segments!A6="","",Segments!A6) | B6: =IF(A6="","",Segments!B6) | E6: =IF(OR(A6="",C6=""),"",B6*(1+C6)) | F6: =IF(E6="","",E6*D6) | I6: =IF(OR(A6="",G6=""),"",E6*(1+G6)) | J6: =IF(I6="","",I6*H6) | M6: =IF(OR(A6="",K6=""),"",I6*(1+K6)) | N6: =IF(M6="","",M6*L6) | Q6: =IF(OR(A6="",O6=""),"",M6*(1+O6)) | R6: =IF(Q6="","",Q6*P6) | U6: =IF(OR(A6="",S6=""),"",Q6*(1+S6)) | V6: =IF(U6="","",U6*T6)
A7: =IF(Segments!A7="","",Segments!A7) | B7: =IF(A7="","",Segments!B7) | E7: =IF(OR(A7="",C7=""),"",B7*(1+C7)) | F7: =IF(E7="","",E7*D7) | I7: =IF(OR(A7="",G7=""),"",E7*(1+G7)) | J7: =IF(I7="","",I7*H7) | M7: =IF(OR(A7="",K7=""),"",I7*(1+K7)) | N7: =IF(M7="","",M7*L7) | Q7: =IF(OR(A7="",O7=""),"",M7*(1+O7)) | R7: =IF(Q7="","",Q7*P7) | U7: =IF(OR(A7="",S7=""),"",Q7*(1+S7)) | V7: =IF(U7="","",U7*T7)
A8: =IF(Segments!A8="","",Segments!A8) | B8: =IF(A8="","",Segments!B8) | E8: =IF(OR(A8="",C8=""),"",B8*(1+C8)) | F8: =IF(E8="","",E8*D8) | I8: =IF(OR(A8="",G8=""),"",E8*(1+G8)) | J8: =IF(I8="","",I8*H8) | M8: =IF(OR(A8="",K8=""),"",I8*(1+K8)) | N8: =IF(M8="","",M8*L8) | Q8: =IF(OR(A8="",O8=""),"",M8*(1+O8)) | R8: =IF(Q8="","",Q8*P8) | U8: =IF(OR(A8="",S8=""),"",Q8*(1+S8)) | V8: =IF(U8="","",U8*T8)
A9: =IF(Segments!A9="","",Segments!A9) | B9: =IF(A9="","",Segments!B9) | E9: =IF(OR(A9="",C9=""),"",B9*(1+C9)) | F9: =IF(E9="","",E9*D9) | I9: =IF(OR(A9="",G9=""),"",E9*(1+G9)) | J9: =IF(I9="","",I9*H9) | M9: =IF(OR(A9="",K9=""),"",I9*(1+K9)) | N9: =IF(M9="","",M9*L9) | Q9: =IF(OR(A9="",O9=""),"",M9*(1+O9)) | R9: =IF(Q9="","",Q9*P9) | U9: =IF(OR(A9="",S9=""),"",Q9*(1+S9)) | V9: =IF(U9="","",U9*T9)
A10: =IF(Segments!A10="","",Segments!A10) | B10: =IF(A10="","",Segments!B10) | E10: =IF(OR(A10="",C10=""),"",B10*(1+C10)) | F10: =IF(E10="","",E10*D10) | I10: =IF(OR(A10="",G10=""),"",E10*(1+G10)) | J10: =IF(I10="","",I10*H10) | M10: =IF(OR(A10="",K10=""),"",I10*(1+K10)) | N10: =IF(M10="","",M10*L10) | Q10: =IF(OR(A10="",O10=""),"",M10*(1+O10)) | R10: =IF(Q10="","",Q10*P10) | U10: =IF(OR(A10="",S10=""),"",Q10*(1+S10)) | V10: =IF(U10="","",U10*T10)
A11: =IF(Segments!A11="","",Segments!A11) | B11: =IF(A11="","",Segments!B11) | E11: =IF(OR(A11="",C11=""),"",B11*(1+C11)) | F11: =IF(E11="","",E11*D11) | I11: =IF(OR(A11="",G11=""),"",E11*(1+G11)) | J11: =IF(I11="","",I11*H11) | M11: =IF(OR(A11="",K11=""),"",I11*(1+K11)) | N11: =IF(M11="","",M11*L11) | Q11: =IF(OR(A11="",O11=""),"",M11*(1+O11)) | R11: =IF(Q11="","",Q11*P11) | U11: =IF(OR(A11="",S11=""),"",Q11*(1+S11)) | V11: =IF(U11="","",U11*T11)
A12: =IF(Segments!A12="","",Segments!A12) | B12: =IF(A12="","",Segments!B12) | E12: =IF(OR(A12="",C12=""),"",B12*(1+C12)) | F12: =IF(E12="","",E12*D12) | I12: =IF(OR(A12="",G12=""),"",E12*(1+G12)) | J12: =IF(I12="","",I12*H12) | M12: =IF(OR(A12="",K12=""),"",I12*(1+K12)) | N12: =IF(M12="","",M12*L12) | Q12: =IF(OR(A12="",O12=""),"",M12*(1+O12)) | R12: =IF(Q12="","",Q12*P12) | U12: =IF(OR(A12="",S12=""),"",Q12*(1+S12)) | V12: =IF(U12="","",U12*T12)
A13: =IF(Segments!A13="","",Segments!A13) | B13: =IF(A13="","",Segments!B13) | E13: =IF(OR(A13="",C13=""),"",B13*(1+C13)) | F13: =IF(E13="","",E13*D13) | I13: =IF(OR(A13="",G13=""),"",E13*(1+G13)) | J13: =IF(I13="","",I13*H13) | M13: =IF(OR(A13="",K13=""),"",I13*(1+K13)) | N13: =IF(M13="","",M13*L13) | Q13: =IF(OR(A13="",O13=""),"",M13*(1+O13)) | R13: =IF(Q13="","",Q13*P13) | U13: =IF(OR(A13="",S13=""),"",Q13*(1+S13)) | V13: =IF(U13="","",U13*T13)
A14: =IF(Segments!A14="","",Segments!A14) | B14: =IF(A14="","",Segments!B14) | E14: =IF(OR(A14="",C14=""),"",B14*(1+C14)) | F14: =IF(E14="","",E14*D14) | I14: =IF(OR(A14="",G14=""),"",E14*(1+G14)) | J14: =IF(I14="","",I14*H14) | M14: =IF(OR(A14="",K14=""),"",I14*(1+K14)) | N14: =IF(M14="","",M14*L14) | Q14: =IF(OR(A14="",O14=""),"",M14*(1+O14)) | R14: =IF(Q14="","",Q14*P14) | U14: =IF(OR(A14="",S14=""),"",Q14*(1+S14)) | V14: =IF(U14="","",U14*T14)
A15: =IF(Segments!A15="","",Segments!A15) | B15: =IF(A15="","",Segments!B15) | E15: =IF(OR(A15="",C15=""),"",B15*(1+C15)) | F15: =IF(E15="","",E15*D15) | I15: =IF(OR(A15="",G15=""),"",E15*(1+G15)) | J15: =IF(I15="","",I15*H15) | M15: =IF(OR(A15="",K15=""),"",I15*(1+K15)) | N15: =IF(M15="","",M15*L15) | Q15: =IF(OR(A15="",O15=""),"",M15*(1+O15)) | R15: =IF(Q15="","",Q15*P15) | U15: =IF(OR(A15="",S15=""),"",Q15*(1+S15)) | V15: =IF(U15="","",U15*T15)
A16: =IF(Segments!A16="","",Segments!A16) | B16: =IF(A16="","",Segments!B16) | E16: =IF(OR(A16="",C16=""),"",B16*(1+C16)) | F16: =IF(E16="","",E16*D16) | I16: =IF(OR(A16="",G16=""),"",E16*(1+G16)) | J16: =IF(I16="","",I16*H16) | M16: =IF(OR(A16="",K16=""),"",I16*(1+K16)) | N16: =IF(M16="","",M16*L16) | Q16: =IF(OR(A16="",O16=""),"",M16*(1+O16)) | R16: =IF(Q16="","",Q16*P16) | U16: =IF(OR(A16="",S16=""),"",Q16*(1+S16)) | V16: =IF(U16="","",U16*T16)
A18: TOTAL | E18: =SUM(E5:E16) | F18: =SUM(F5:F16) | I18: =SUM(I5:I16) | J18: =SUM(J5:J16) | M18: =SUM(M5:M16) | N18: =SUM(N5:N16) | Q18: =SUM(Q5:Q16) | R18: =SUM(R5:R16) | U18: =SUM(U5:U16) | V18: =SUM(V5:V16)
A19: consolidated margin (recomputed) | F19: =IF(N(E18)=0,"",F18/E18) | J19: =IF(N(I18)=0,"",J18/I18) | N19: =IF(N(M18)=0,"",N18/M18) | R19: =IF(N(Q18)=0,"",R18/Q18) | V19: =IF(N(U18)=0,"",V18/U18)
