Workbook
Name epf_er: 'Rates'!$B$4
Name epf_cap: 'Rates'!$B$5
Name epf_capflag: 'Rates'!$B$6
Name esi_er: 'Rates'!$B$7
Name esi_limit: 'Rates'!$B$8
Name grat: 'Rates'!$B$9
Name bonus: 'Rates'!$B$10
Name bonus_limit: 'Rates'!$B$11
Name lwf_er: 'Rates'!$B$12
Name edli: 'Rates'!$B$13

Sheet README
A1: D04 (Kaveri copy)
A3: Kaveri Chairs domain record (illustrative sample rows).

Sheet Checks
A1: Checks - OVERALL must be PASS before this domain feeds the kernel
B3: OVERALL | C3: =IF(COUNTIF(C5:C6,"PASS")=COUNT(A5:A6),"PASS","FAIL")
A4: # | B4: check | C4: result
A5: 1 | B5: employee ids unique | C5: =IF(SUMPRODUCT((People!A5:A504<>"")*(COUNTIF(People!A5:A504,People!A5:A504)>1))=0,"PASS","FAIL")
A6: 2 | B6: basic % within 0..1 | C6: =IF(COUNTIF(People!E5:E504,">1")+COUNTIF(People!E5:E504,"<0")=0,"PASS","FAIL")

Sheet Rates
A1: Statutory rates (verify each April and on Labour Code notifications - see 01_tamil-nadu/labour-and-payroll.md)
A4: employer EPF % of PF wage | B4: 0.12
A5: EPF wage ceiling per month (if capped) | B5: 15000
A6: cap employer PF at ceiling? (1 yes / 0 no) | B6: 1
A7: employer ESI % | B7: 0.0325
A8: ESI gross wage limit per month | B8: 21000
A9: gratuity accrual % of basic (15/26/12) | B9: 0.048076923
A10: statutory bonus % (eligible staff) | B10: 0.0833
A11: bonus eligibility wage limit per month | B11: 21000
A12: TN Labour Welfare Fund employer per year | B12: 40
A13: EDLI + admin % of PF wage (employer) | B13: 0.01

Sheet People
A1: Headcount plan (one row per employee or planned hire)
A4: employee / role id | B4: location (Chennai / Coimbatore / Hosur / ...) | C4: department | D4: monthly gross | E4: basic % of gross | F4: start month no. (1 = K01 month 1) | G4: end month no. (blank = horizon) | H4: PF wage | I4: employer PF/month | J4: employer ESI/month | K4: gratuity accrual/month | L4: bonus accrual/month | M4: LWF/month | N4: loaded monthly cost | O4: months active in 12 | P4: cost in first 12 months | Q4: employee PF/month (12%) | R4: employee ESI/month (0.75%)
A5: E001 | B5: Coimbatore | C5: Production | D5: 28000 | E5: 0.5 | F5: 1 | H5: =IF(A5="","",D5*E5) | I5: =IF(A5="","",IF(Rates!$B$6=1,MIN(H5,Rates!$B$5),H5)*(Rates!$B$4+Rates!$B$13)) | J5: =IF(A5="","",IF(D5<=Rates!$B$8,D5*Rates!$B$7,0)) | K5: =IF(A5="","",H5*Rates!$B$9) | L5: =IF(A5="","",IF(D5<=Rates!$B$11,H5*Rates!$B$10,0)) | M5: =IF(A5="","",Rates!$B$12/12) | N5: =IF(A5="","",D5+I5+J5+K5+L5+M5) | O5: =IF(A5="","",MAX(0,MIN(12,IF(G5="",12,G5))-MAX(1,F5)+1)) | P5: =IF(A5="","",N5*O5) | Q5: =IF(A5="","",0.12*IF(Rates!$B$6=1,MIN(H5,Rates!$B$5),H5)) | R5: =IF(A5="","",IF(D5<=Rates!$B$8,D5*0.0075,0))
A6: E002 | B6: Chennai | C6: Finance | D6: 85000 | E6: 0.4 | F6: 1 | H6: =IF(A6="","",D6*E6) | I6: =IF(A6="","",IF(Rates!$B$6=1,MIN(H6,Rates!$B$5),H6)*(Rates!$B$4+Rates!$B$13)) | J6: =IF(A6="","",IF(D6<=Rates!$B$8,D6*Rates!$B$7,0)) | K6: =IF(A6="","",H6*Rates!$B$9) | L6: =IF(A6="","",IF(D6<=Rates!$B$11,H6*Rates!$B$10,0)) | M6: =IF(A6="","",Rates!$B$12/12) | N6: =IF(A6="","",D6+I6+J6+K6+L6+M6) | O6: =IF(A6="","",MAX(0,MIN(12,IF(G6="",12,G6))-MAX(1,F6)+1)) | P6: =IF(A6="","",N6*O6) | Q6: =IF(A6="","",0.12*IF(Rates!$B$6=1,MIN(H6,Rates!$B$5),H6)) | R6: =IF(A6="","",IF(D6<=Rates!$B$8,D6*0.0075,0))
A7: HIRE-01 | B7: Hosur | C7: Sales | D7: 45000 | E7: 0.45 | F7: 4 | H7: =IF(A7="","",D7*E7) | I7: =IF(A7="","",IF(Rates!$B$6=1,MIN(H7,Rates!$B$5),H7)*(Rates!$B$4+Rates!$B$13)) | J7: =IF(A7="","",IF(D7<=Rates!$B$8,D7*Rates!$B$7,0)) | K7: =IF(A7="","",H7*Rates!$B$9) | L7: =IF(A7="","",IF(D7<=Rates!$B$11,H7*Rates!$B$10,0)) | M7: =IF(A7="","",Rates!$B$12/12) | N7: =IF(A7="","",D7+I7+J7+K7+L7+M7) | O7: =IF(A7="","",MAX(0,MIN(12,IF(G7="",12,G7))-MAX(1,F7)+1)) | P7: =IF(A7="","",N7*O7) | Q7: =IF(A7="","",0.12*IF(Rates!$B$6=1,MIN(H7,Rates!$B$5),H7)) | R7: =IF(A7="","",IF(D7<=Rates!$B$8,D7*0.0075,0))
H8: =IF(A8="","",D8*E8) | I8: =IF(A8="","",IF(Rates!$B$6=1,MIN(H8,Rates!$B$5),H8)*(Rates!$B$4+Rates!$B$13)) | J8: =IF(A8="","",IF(D8<=Rates!$B$8,D8*Rates!$B$7,0)) | K8: =IF(A8="","",H8*Rates!$B$9) | L8: =IF(A8="","",IF(D8<=Rates!$B$11,H8*Rates!$B$10,0)) | M8: =IF(A8="","",Rates!$B$12/12) | N8: =IF(A8="","",D8+I8+J8+K8+L8+M8) | O8: =IF(A8="","",MAX(0,MIN(12,IF(G8="",12,G8))-MAX(1,F8)+1)) | P8: =IF(A8="","",N8*O8) | Q8: =IF(A8="","",0.12*IF(Rates!$B$6=1,MIN(H8,Rates!$B$5),H8)) | R8: =IF(A8="","",IF(D8<=Rates!$B$8,D8*0.0075,0))
H9: =IF(A9="","",D9*E9) | I9: =IF(A9="","",IF(Rates!$B$6=1,MIN(H9,Rates!$B$5),H9)*(Rates!$B$4+Rates!$B$13)) | J9: =IF(A9="","",IF(D9<=Rates!$B$8,D9*Rates!$B$7,0)) | K9: =IF(A9="","",H9*Rates!$B$9) | L9: =IF(A9="","",IF(D9<=Rates!$B$11,H9*Rates!$B$10,0)) | M9: =IF(A9="","",Rates!$B$12/12) | N9: =IF(A9="","",D9+I9+J9+K9+L9+M9) | O9: =IF(A9="","",MAX(0,MIN(12,IF(G9="",12,G9))-MAX(1,F9)+1)) | P9: =IF(A9="","",N9*O9) | Q9: =IF(A9="","",0.12*IF(Rates!$B$6=1,MIN(H9,Rates!$B$5),H9)) | R9: =IF(A9="","",IF(D9<=Rates!$B$8,D9*0.0075,0))
H10: =IF(A10="","",D10*E10) | I10: =IF(A10="","",IF(Rates!$B$6=1,MIN(H10,Rates!$B$5),H10)*(Rates!$B$4+Rates!$B$13)) | J10: =IF(A10="","",IF(D10<=Rates!$B$8,D10*Rates!$B$7,0)) | K10: =IF(A10="","",H10*Rates!$B$9) | L10: =IF(A10="","",IF(D10<=Rates!$B$11,H10*Rates!$B$10,0)) | M10: =IF(A10="","",Rates!$B$12/12) | N10: =IF(A10="","",D10+I10+J10+K10+L10+M10) | O10: =IF(A10="","",MAX(0,MIN(12,IF(G10="",12,G10))-MAX(1,F10)+1)) | P10: =IF(A10="","",N10*O10) | Q10: =IF(A10="","",0.12*IF(Rates!$B$6=1,MIN(H10,Rates!$B$5),H10)) | R10: =IF(A10="","",IF(D10<=Rates!$B$8,D10*0.0075,0))
H11: =IF(A11="","",D11*E11) | I11: =IF(A11="","",IF(Rates!$B$6=1,MIN(H11,Rates!$B$5),H11)*(Rates!$B$4+Rates!$B$13)) | J11: =IF(A11="","",IF(D11<=Rates!$B$8,D11*Rates!$B$7,0)) | K11: =IF(A11="","",H11*Rates!$B$9) | L11: =IF(A11="","",IF(D11<=Rates!$B$11,H11*Rates!$B$10,0)) | M11: =IF(A11="","",Rates!$B$12/12) | N11: =IF(A11="","",D11+I11+J11+K11+L11+M11) | O11: =IF(A11="","",MAX(0,MIN(12,IF(G11="",12,G11))-MAX(1,F11)+1)) | P11: =IF(A11="","",N11*O11) | Q11: =IF(A11="","",0.12*IF(Rates!$B$6=1,MIN(H11,Rates!$B$5),H11)) | R11: =IF(A11="","",IF(D11<=Rates!$B$8,D11*0.0075,0))
H12: =IF(A12="","",D12*E12) | I12: =IF(A12="","",IF(Rates!$B$6=1,MIN(H12,Rates!$B$5),H12)*(Rates!$B$4+Rates!$B$13)) | J12: =IF(A12="","",IF(D12<=Rates!$B$8,D12*Rates!$B$7,0)) | K12: =IF(A12="","",H12*Rates!$B$9) | L12: =IF(A12="","",IF(D12<=Rates!$B$11,H12*Rates!$B$10,0)) | M12: =IF(A12="","",Rates!$B$12/12) | N12: =IF(A12="","",D12+I12+J12+K12+L12+M12) | O12: =IF(A12="","",MAX(0,MIN(12,IF(G12="",12,G12))-MAX(1,F12)+1)) | P12: =IF(A12="","",N12*O12) | Q12: =IF(A12="","",0.12*IF(Rates!$B$6=1,MIN(H12,Rates!$B$5),H12)) | R12: =IF(A12="","",IF(D12<=Rates!$B$8,D12*0.0075,0))
H13: =IF(A13="","",D13*E13) | I13: =IF(A13="","",IF(Rates!$B$6=1,MIN(H13,Rates!$B$5),H13)*(Rates!$B$4+Rates!$B$13)) | J13: =IF(A13="","",IF(D13<=Rates!$B$8,D13*Rates!$B$7,0)) | K13: =IF(A13="","",H13*Rates!$B$9) | L13: =IF(A13="","",IF(D13<=Rates!$B$11,H13*Rates!$B$10,0)) | M13: =IF(A13="","",Rates!$B$12/12) | N13: =IF(A13="","",D13+I13+J13+K13+L13+M13) | O13: =IF(A13="","",MAX(0,MIN(12,IF(G13="",12,G13))-MAX(1,F13)+1)) | P13: =IF(A13="","",N13*O13) | Q13: =IF(A13="","",0.12*IF(Rates!$B$6=1,MIN(H13,Rates!$B$5),H13)) | R13: =IF(A13="","",IF(D13<=Rates!$B$8,D13*0.0075,0))
H14: =IF(A14="","",D14*E14) | I14: =IF(A14="","",IF(Rates!$B$6=1,MIN(H14,Rates!$B$5),H14)*(Rates!$B$4+Rates!$B$13)) | J14: =IF(A14="","",IF(D14<=Rates!$B$8,D14*Rates!$B$7,0)) | K14: =IF(A14="","",H14*Rates!$B$9) | L14: =IF(A14="","",IF(D14<=Rates!$B$11,H14*Rates!$B$10,0)) | M14: =IF(A14="","",Rates!$B$12/12) | N14: =IF(A14="","",D14+I14+J14+K14+L14+M14) | O14: =IF(A14="","",MAX(0,MIN(12,IF(G14="",12,G14))-MAX(1,F14)+1)) | P14: =IF(A14="","",N14*O14) | Q14: =IF(A14="","",0.12*IF(Rates!$B$6=1,MIN(H14,Rates!$B$5),H14)) | R14: =IF(A14="","",IF(D14<=Rates!$B$8,D14*0.0075,0))
H15: =IF(A15="","",D15*E15) | I15: =IF(A15="","",IF(Rates!$B$6=1,MIN(H15,Rates!$B$5),H15)*(Rates!$B$4+Rates!$B$13)) | J15: =IF(A15="","",IF(D15<=Rates!$B$8,D15*Rates!$B$7,0)) | K15: =IF(A15="","",H15*Rates!$B$9) | L15: =IF(A15="","",IF(D15<=Rates!$B$11,H15*Rates!$B$10,0)) | M15: =IF(A15="","",Rates!$B$12/12) | N15: =IF(A15="","",D15+I15+J15+K15+L15+M15) | O15: =IF(A15="","",MAX(0,MIN(12,IF(G15="",12,G15))-MAX(1,F15)+1)) | P15: =IF(A15="","",N15*O15) | Q15: =IF(A15="","",0.12*IF(Rates!$B$6=1,MIN(H15,Rates!$B$5),H15)) | R15: =IF(A15="","",IF(D15<=Rates!$B$8,D15*0.0075,0))
H16: =IF(A16="","",D16*E16) | I16: =IF(A16="","",IF(Rates!$B$6=1,MIN(H16,Rates!$B$5),H16)*(Rates!$B$4+Rates!$B$13)) | J16: =IF(A16="","",IF(D16<=Rates!$B$8,D16*Rates!$B$7,0)) | K16: =IF(A16="","",H16*Rates!$B$9) | L16: =IF(A16="","",IF(D16<=Rates!$B$11,H16*Rates!$B$10,0)) | M16: =IF(A16="","",Rates!$B$12/12) | N16: =IF(A16="","",D16+I16+J16+K16+L16+M16) | O16: =IF(A16="","",MAX(0,MIN(12,IF(G16="",12,G16))-MAX(1,F16)+1)) | P16: =IF(A16="","",N16*O16) | Q16: =IF(A16="","",0.12*IF(Rates!$B$6=1,MIN(H16,Rates!$B$5),H16)) | R16: =IF(A16="","",IF(D16<=Rates!$B$8,D16*0.0075,0))
H17: =IF(A17="","",D17*E17) | I17: =IF(A17="","",IF(Rates!$B$6=1,MIN(H17,Rates!$B$5),H17)*(Rates!$B$4+Rates!$B$13)) | J17: =IF(A17="","",IF(D17<=Rates!$B$8,D17*Rates!$B$7,0)) | K17: =IF(A17="","",H17*Rates!$B$9) | L17: =IF(A17="","",IF(D17<=Rates!$B$11,H17*Rates!$B$10,0)) | M17: =IF(A17="","",Rates!$B$12/12) | N17: =IF(A17="","",D17+I17+J17+K17+L17+M17) | O17: =IF(A17="","",MAX(0,MIN(12,IF(G17="",12,G17))-MAX(1,F17)+1)) | P17: =IF(A17="","",N17*O17) | Q17: =IF(A17="","",0.12*IF(Rates!$B$6=1,MIN(H17,Rates!$B$5),H17)) | R17: =IF(A17="","",IF(D17<=Rates!$B$8,D17*0.0075,0))
H18: =IF(A18="","",D18*E18) | I18: =IF(A18="","",IF(Rates!$B$6=1,MIN(H18,Rates!$B$5),H18)*(Rates!$B$4+Rates!$B$13)) | J18: =IF(A18="","",IF(D18<=Rates!$B$8,D18*Rates!$B$7,0)) | K18: =IF(A18="","",H18*Rates!$B$9) | L18: =IF(A18="","",IF(D18<=Rates!$B$11,H18*Rates!$B$10,0)) | M18: =IF(A18="","",Rates!$B$12/12) | N18: =IF(A18="","",D18+I18+J18+K18+L18+M18) | O18: =IF(A18="","",MAX(0,MIN(12,IF(G18="",12,G18))-MAX(1,F18)+1)) | P18: =IF(A18="","",N18*O18) | Q18: =IF(A18="","",0.12*IF(Rates!$B$6=1,MIN(H18,Rates!$B$5),H18)) | R18: =IF(A18="","",IF(D18<=Rates!$B$8,D18*0.0075,0))
H19: =IF(A19="","",D19*E19) | I19: =IF(A19="","",IF(Rates!$B$6=1,MIN(H19,Rates!$B$5),H19)*(Rates!$B$4+Rates!$B$13)) | J19: =IF(A19="","",IF(D19<=Rates!$B$8,D19*Rates!$B$7,0)) | K19: =IF(A19="","",H19*Rates!$B$9) | L19: =IF(A19="","",IF(D19<=Rates!$B$11,H19*Rates!$B$10,0)) | M19: =IF(A19="","",Rates!$B$12/12) | N19: =IF(A19="","",D19+I19+J19+K19+L19+M19) | O19: =IF(A19="","",MAX(0,MIN(12,IF(G19="",12,G19))-MAX(1,F19)+1)) | P19: =IF(A19="","",N19*O19) | Q19: =IF(A19="","",0.12*IF(Rates!$B$6=1,MIN(H19,Rates!$B$5),H19)) | R19: =IF(A19="","",IF(D19<=Rates!$B$8,D19*0.0075,0))
... H504: =IF(A504="","",D504*E504) | I504: =IF(A504="","",IF(Rates!$B$6=1,MIN(H504,Rates!$B$5),H504)*(Rates!$B$4+Rates!$B$13)) | J504: =IF(A504="","",IF(D504<=Rates!$B$8,D504*Rates!$B$7,0)) | K504: =IF(A504="","",H504*Rates!$B$9) | L504: =IF(A504="","",IF(D504<=Rates!$B$11,H504*Rates!$B$10,0)) | M504: =IF(A504="","",Rates!$B$12/12) | N504: =IF(A504="","",D504+I504+J504+K504+L504+M504) | O504: =IF(A504="","",MAX(0,MIN(12,IF(G504="",12,G504))-MAX(1,F504)+1)) | P504: =IF(A504="","",N504*O504) | Q504: =IF(A504="","",0.12*IF(Rates!$B$6=1,MIN(H504,Rates!$B$5),H504)) | R504: =IF(A504="","",IF(D504<=Rates!$B$8,D504*0.0075,0))

Sheet ToKernel
A1: Feeds K01 opex (fixed 'Payroll & benefits' monthly_amount) and K02 flows
A4: average loaded payroll per month (first 12 months) -> K01 opex fixed monthly_amount | B4: =SUM(People!P5:P504)/12
A5: month-1 gross salary payout (before employee deductions) | B5: =SUMIFS(People!D5:D504,People!F5:F504,"<=1")
A6: month-1 PF remittance (due 15th): employer + employee | B6: =SUMIFS(People!I5:I504,People!F5:F504,"<=1")+SUMIFS(People!Q5:Q504,People!F5:F504,"<=1")
A7: month-1 ESI remittance (due 15th): employer + employee | B7: =SUMIFS(People!J5:J504,People!F5:F504,"<=1")+SUMIFS(People!R5:R504,People!F5:F504,"<=1")
A8: headcount active in month 1 | B8: =COUNTIFS(People!F5:F504,"<=1")
