Workbook
Name usdinr: 'Setup'!$B$4
Name rcm: 'Setup'!$B$5
Name rcm_leak: 'Setup'!$B$6
Name units: 'Setup'!$B$7

Sheet README
A1: D11 · FinOps & cloud optimisation systems
A3: Domain D11: FinOps & cloud optimisation systems.
A4: Make cloud and SaaS spend visible in rupees, including reverse-charge GST leakage, commitment coverage and unit cost, and feed it to K01 opex.
A5: How to use
A6: Copy this workbook into companies/<slug>/domains/D11_finops-cloud-optimisation/ before typing. Replace the SAMPLE rows (illustrative Tamil Nadu data) with company data.
A7: Type only into pale-yellow cells; white cells are formulas. Checks › OVERALL must be PASS before any value feeds K01/K02.
A8: Statutory rates are starting values - verify in 01_tamil-nadu/verification-register.md.
A9: Feeds
A10: K01 opex fixed 'Cloud & software' monthly_amount <= Unit B4
A11: D24 GST (RCM on imported services) <= RCM
A12: D13 unit economics <= cost per unit

Sheet Checks
A1: Checks - OVERALL must be PASS before this domain feeds the kernel
B3: OVERALL | C3: =IF(COUNTIF(C5:C5,"PASS")=COUNT(A5:A5),"PASS","FAIL")
A4: # | B4: check | C4: result
A5: 1 | B5: billing currency is USD or INR | C5: =IF(SUMPRODUCT((CloudCosts!A5:A304<>"")*(CloudCosts!D5:D304<>"USD")*(CloudCosts!D5:D304<>"INR"))=0,"PASS","FAIL")

Sheet Setup
A1: FinOps setup
A4: USD/INR (FBIL/RBI reference, dated) | B4: 88
A5: IGST under reverse charge on imported services (if ITC blocked/partial, cost) | B5: 0.18
A6: share of RCM IGST NOT recoverable as ITC | B6: 0
A7: units of usage this month (orders / invoices / users) | B7: 250000

Sheet CloudCosts
A1: Cloud & SaaS cost register (AWS / Azure (South India = Chennai) / GCP / Zoho / Microsoft 365 ...)
A4: service | B4: provider | C4: region | D4: billing currency (USD/INR) | E4: monthly amount (billing currency) | F4: allocation (cost centre / product) | G4: committed (RI/savings plan)? y/n | H4: INR cost | I4: RCM IGST leakage | J4: all-in INR
A5: EC2 + RDS | B5: AWS | C5: ap-south-1 | D5: USD | E5: 6200 | F5: Platform | G5: y | H5: =IF(A5="","",E5*IF(D5="USD",Setup!$B$4,1)) | I5: =IF(A5="","",IF(D5="USD",H5*Setup!$B$5*Setup!$B$6,0)) | J5: =IF(A5="","",H5+I5)
A6: Zoho One | B6: Zoho | C6: IN | D6: INR | E6: 145000 | F6: G&A | G6: n | H6: =IF(A6="","",E6*IF(D6="USD",Setup!$B$4,1)) | I6: =IF(A6="","",IF(D6="USD",H6*Setup!$B$5*Setup!$B$6,0)) | J6: =IF(A6="","",H6+I6)
A7: Azure VMs | B7: Microsoft | C7: South India | D7: USD | E7: 1800 | F7: Analytics | G7: n | H7: =IF(A7="","",E7*IF(D7="USD",Setup!$B$4,1)) | I7: =IF(A7="","",IF(D7="USD",H7*Setup!$B$5*Setup!$B$6,0)) | J7: =IF(A7="","",H7+I7)
H8: =IF(A8="","",E8*IF(D8="USD",Setup!$B$4,1)) | I8: =IF(A8="","",IF(D8="USD",H8*Setup!$B$5*Setup!$B$6,0)) | J8: =IF(A8="","",H8+I8)
H9: =IF(A9="","",E9*IF(D9="USD",Setup!$B$4,1)) | I9: =IF(A9="","",IF(D9="USD",H9*Setup!$B$5*Setup!$B$6,0)) | J9: =IF(A9="","",H9+I9)
H10: =IF(A10="","",E10*IF(D10="USD",Setup!$B$4,1)) | I10: =IF(A10="","",IF(D10="USD",H10*Setup!$B$5*Setup!$B$6,0)) | J10: =IF(A10="","",H10+I10)
H11: =IF(A11="","",E11*IF(D11="USD",Setup!$B$4,1)) | I11: =IF(A11="","",IF(D11="USD",H11*Setup!$B$5*Setup!$B$6,0)) | J11: =IF(A11="","",H11+I11)
H12: =IF(A12="","",E12*IF(D12="USD",Setup!$B$4,1)) | I12: =IF(A12="","",IF(D12="USD",H12*Setup!$B$5*Setup!$B$6,0)) | J12: =IF(A12="","",H12+I12)
H13: =IF(A13="","",E13*IF(D13="USD",Setup!$B$4,1)) | I13: =IF(A13="","",IF(D13="USD",H13*Setup!$B$5*Setup!$B$6,0)) | J13: =IF(A13="","",H13+I13)
H14: =IF(A14="","",E14*IF(D14="USD",Setup!$B$4,1)) | I14: =IF(A14="","",IF(D14="USD",H14*Setup!$B$5*Setup!$B$6,0)) | J14: =IF(A14="","",H14+I14)
H15: =IF(A15="","",E15*IF(D15="USD",Setup!$B$4,1)) | I15: =IF(A15="","",IF(D15="USD",H15*Setup!$B$5*Setup!$B$6,0)) | J15: =IF(A15="","",H15+I15)
H16: =IF(A16="","",E16*IF(D16="USD",Setup!$B$4,1)) | I16: =IF(A16="","",IF(D16="USD",H16*Setup!$B$5*Setup!$B$6,0)) | J16: =IF(A16="","",H16+I16)
H17: =IF(A17="","",E17*IF(D17="USD",Setup!$B$4,1)) | I17: =IF(A17="","",IF(D17="USD",H17*Setup!$B$5*Setup!$B$6,0)) | J17: =IF(A17="","",H17+I17)
H18: =IF(A18="","",E18*IF(D18="USD",Setup!$B$4,1)) | I18: =IF(A18="","",IF(D18="USD",H18*Setup!$B$5*Setup!$B$6,0)) | J18: =IF(A18="","",H18+I18)
H19: =IF(A19="","",E19*IF(D19="USD",Setup!$B$4,1)) | I19: =IF(A19="","",IF(D19="USD",H19*Setup!$B$5*Setup!$B$6,0)) | J19: =IF(A19="","",H19+I19)
... H304: =IF(A304="","",E304*IF(D304="USD",Setup!$B$4,1)) | I304: =IF(A304="","",IF(D304="USD",H304*Setup!$B$5*Setup!$B$6,0)) | J304: =IF(A304="","",H304+I304)

Sheet Unit
A1: Unit economics -> K01 opex line 'Cloud & software'
A4: total monthly all-in INR -> K01 fixed opex monthly_amount | B4: =SUM(CloudCosts!J5:J304)
A5: cost per unit | B5: =IF(Setup!$B$7=0,0,B4/Setup!$B$7)
A6: commitment coverage % (committed spend / total) | B6: =IF(B4=0,0,SUMIF(CloudCosts!G5:G304,"y",CloudCosts!J5:J304)/B4)
