Workbook
Name nw: 'CSR'!$B$4
Name to: 'CSR'!$B$5
Name np: 'CSR'!$B$6
Name avgnp: 'CSR'!$B$8

Sheet README
A1: D28 · Ethical oversight & governance culture
A3: Domain D28: Ethical oversight & governance culture.
A4: Evidence-based governance scorecard, related-party transaction register with approval flags, CSR obligation, and the habits that keep forecasts honest.
A5: How to use
A6: Copy this workbook into companies/<slug>/domains/D28_ethics-governance-culture/ before typing. Replace the SAMPLE rows (illustrative Tamil Nadu data) with company data.
A7: Type only into pale-yellow cells; white cells are formulas. Checks › OVERALL must be PASS before any value feeds K01/K02.
A8: Statutory rates are starting values - verify in 01_tamil-nadu/verification-register.md.
A9: Feeds
A10: D10 evidence register <= policies and minutes
A11: W10 Gate 2 <= promotion approvals
A12: K01 opex <= CSR spend

Sheet Checks
A1: Checks - OVERALL must be PASS before this domain feeds the kernel
B3: OVERALL | C3: =IF(COUNTIF(C5:C6,"PASS")=COUNT(A5:A6),"PASS","FAIL")
A4: # | B4: check | C4: result
A5: 1 | B5: scorecard weights sum to 100% | C5: =IF(ABS(Index!B5-1)<1E-9,"PASS","FAIL")
A6: 2 | B6: scores within 0..3 | C6: =IF(COUNTIF(Scorecard!D5:D34,">3")+COUNTIF(Scorecard!D5:D34,"<0")=0,"PASS","FAIL")

Sheet Scorecard
A1: Governance & ethics culture scorecard (evidence-based; score 0-3)
A4: criterion | B4: weight | C4: evidence (file / link) | D4: score 0-3 | E4: weighted
A5: Code of conduct acknowledged by all staff this year | B5: 0.1 | E5: =IF(A5="","",B5*D5/3)
A6: Vigil mechanism / whistle-blower channel live (s.177, LODR Reg 22) | B6: 0.15 | E6: =IF(A6="","",B6*D6/3)
A7: Related-party transactions approved per s.188 / Reg 23 | B7: 0.15 | E7: =IF(A7="","",B7*D7/3)
A8: POSH Internal Committee constituted, annual report filed | B8: 0.1 | E8: =IF(A8="","",B8*D8/3)
A9: Audit trail enabled in accounting software (Rule 3(1) Accounts Rules) | B9: 0.15 | E9: =IF(A9="","",B9*D9/3)
A10: CSR spend & unspent account per s.135 | B10: 0.1 | E10: =IF(A10="","",B10*D10/3)
A11: Board / audit committee minutes record challenge of forecasts | B11: 0.1 | E11: =IF(A11="","",B11*D11/3)
A12: Forecast champion promotions human-approved (K05) | B12: 0.15 | E12: =IF(A12="","",B12*D12/3)
E13: =IF(A13="","",B13*D13/3)
E14: =IF(A14="","",B14*D14/3)
E15: =IF(A15="","",B15*D15/3)
E16: =IF(A16="","",B16*D16/3)
E17: =IF(A17="","",B17*D17/3)
E18: =IF(A18="","",B18*D18/3)
E19: =IF(A19="","",B19*D19/3)
E20: =IF(A20="","",B20*D20/3)
E21: =IF(A21="","",B21*D21/3)
E22: =IF(A22="","",B22*D22/3)
E23: =IF(A23="","",B23*D23/3)
E24: =IF(A24="","",B24*D24/3)
... E34: =IF(A34="","",B34*D34/3)

Sheet Index
A1: Governance index
A4: weighted index (0-100%) | B4: =SUM(Scorecard!E5:E34)
A5: weights sum | B5: =SUM(Scorecard!B5:B34)

Sheet RPT
A1: Related-party transactions register
A4: related party | B4: relationship | C4: nature | D4: amount (₹) | E4: arm's length? evidence | F4: ordinary course? y/n | G4: approval obtained (audit committee / board / shareholders) | H4: needs approval?
A5: Promoter's spouse firm (Erode) | B5: relative of director | C5: job-work | D5: 3600000 | E5: quotes x3 | F5: y | G5: audit committee | H5: =IF(A5="","",OR(LOWER(F5)="n",E5=""))
H6: =IF(A6="","",OR(LOWER(F6)="n",E6=""))
H7: =IF(A7="","",OR(LOWER(F7)="n",E7=""))
H8: =IF(A8="","",OR(LOWER(F8)="n",E8=""))
H9: =IF(A9="","",OR(LOWER(F9)="n",E9=""))
H10: =IF(A10="","",OR(LOWER(F10)="n",E10=""))
H11: =IF(A11="","",OR(LOWER(F11)="n",E11=""))
H12: =IF(A12="","",OR(LOWER(F12)="n",E12=""))
H13: =IF(A13="","",OR(LOWER(F13)="n",E13=""))
H14: =IF(A14="","",OR(LOWER(F14)="n",E14=""))
H15: =IF(A15="","",OR(LOWER(F15)="n",E15=""))
H16: =IF(A16="","",OR(LOWER(F16)="n",E16=""))
H17: =IF(A17="","",OR(LOWER(F17)="n",E17=""))
... H104: =IF(A104="","",OR(LOWER(F104)="n",E104=""))

Sheet CSR
A1: CSR obligation (s.135 Companies Act)
A4: net worth
A5: turnover
A6: net profit (current FY, s.198)
A7: applicable? (NW >= 500 cr or TO >= 1000 cr or NP >= 5 cr) | B7: =OR(N(CSR!$B$4)>=5000000000,N(CSR!$B$5)>=10000000000,N(CSR!$B$6)>=50000000)
A8: average net profit of last 3 FYs (s.198)
A9: CSR obligation (2%) | B9: =IF(B7,MAX(0,0.02*N(CSR!$B$8)),0)
