Workbook
Name pre_money: 'Round'!$B$4
Name invest: 'Round'!$B$5
Name pool_pct: 'Round'!$B$6
Name pps: 'Round'!$B$8
Name exit_v: 'Waterfall'!$B$4

Sheet README
A1: D22 · Cap table management systems
A3: Domain D22: Cap table management systems.
A4: Fully diluted cap table, new-round pricing, ESOP pool top-up and a simple liquidation-preference waterfall.
A5: How to use
A6: Copy this workbook into companies/<slug>/domains/D22_cap-table-management/ before typing. Replace the SAMPLE rows (illustrative Tamil Nadu data) with company data.
A7: Type only into pale-yellow cells; white cells are formulas. Checks › OVERALL must be PASS before any value feeds K01/K02.
A8: Statutory rates are starting values - verify in 01_tamil-nadu/verification-register.md.
A9: Feeds
A10: D21 accretion/dilution <= shares
A11: D19 shareholding <= categories
A12: K01 opening cash <= new money

Sheet Checks
A1: Checks - OVERALL must be PASS before this domain feeds the kernel
B3: OVERALL | C3: =IF(COUNTIF(C5:C6,"PASS")=COUNT(A5:A6),"PASS","FAIL")
A4: # | B4: check | C4: result
A5: 1 | B5: pre-round shares positive | C5: =IF(Round!B7>0,"PASS","FAIL")
A6: 2 | B6: pool % below 50% | C6: =IF(Round!$B$6<0.5,"PASS","FAIL")

Sheet Holders
A1: Cap table (pre-round)
A4: holder | B4: class (equity / CCPS / ESOP granted / ESOP pool unallocated) | C4: shares (as-converted) | D4: liquidation preference multiple (CCPS) | E4: invested amount (for preference) | F4: pre-round % (fully diluted) | G4: post-round shares | H4: post-round % | I4: preference amount (helper)
A5: Founders (Coimbatore) | B5: equity | C5: 8000000 | F5: =IF(A5="","",C5/SUM($C$5:$C$54)) | G5: =IF(A5="","",C5) | H5: =IF(A5="","",G5/(SUM($G$5:$G$54)+Round!$B$9+Round!$B$10)) | I5: =IF(A5="","",N(D5)*N(E5))
A6: Angel syndicate | B6: CCPS | C6: 1200000 | D6: 1 | E6: 30000000 | F6: =IF(A6="","",C6/SUM($C$5:$C$54)) | G6: =IF(A6="","",C6) | H6: =IF(A6="","",G6/(SUM($G$5:$G$54)+Round!$B$9+Round!$B$10)) | I6: =IF(A6="","",N(D6)*N(E6))
A7: ESOP granted | B7: ESOP granted | C7: 400000 | F7: =IF(A7="","",C7/SUM($C$5:$C$54)) | G7: =IF(A7="","",C7) | H7: =IF(A7="","",G7/(SUM($G$5:$G$54)+Round!$B$9+Round!$B$10)) | I7: =IF(A7="","",N(D7)*N(E7))
A8: ESOP pool unallocated | B8: ESOP pool unallocated | C8: 400000 | F8: =IF(A8="","",C8/SUM($C$5:$C$54)) | G8: =IF(A8="","",C8) | H8: =IF(A8="","",G8/(SUM($G$5:$G$54)+Round!$B$9+Round!$B$10)) | I8: =IF(A8="","",N(D8)*N(E8))
F9: =IF(A9="","",C9/SUM($C$5:$C$54)) | G9: =IF(A9="","",C9) | H9: =IF(A9="","",G9/(SUM($G$5:$G$54)+Round!$B$9+Round!$B$10)) | I9: =IF(A9="","",N(D9)*N(E9))
F10: =IF(A10="","",C10/SUM($C$5:$C$54)) | G10: =IF(A10="","",C10) | H10: =IF(A10="","",G10/(SUM($G$5:$G$54)+Round!$B$9+Round!$B$10)) | I10: =IF(A10="","",N(D10)*N(E10))
F11: =IF(A11="","",C11/SUM($C$5:$C$54)) | G11: =IF(A11="","",C11) | H11: =IF(A11="","",G11/(SUM($G$5:$G$54)+Round!$B$9+Round!$B$10)) | I11: =IF(A11="","",N(D11)*N(E11))
F12: =IF(A12="","",C12/SUM($C$5:$C$54)) | G12: =IF(A12="","",C12) | H12: =IF(A12="","",G12/(SUM($G$5:$G$54)+Round!$B$9+Round!$B$10)) | I12: =IF(A12="","",N(D12)*N(E12))
F13: =IF(A13="","",C13/SUM($C$5:$C$54)) | G13: =IF(A13="","",C13) | H13: =IF(A13="","",G13/(SUM($G$5:$G$54)+Round!$B$9+Round!$B$10)) | I13: =IF(A13="","",N(D13)*N(E13))
F14: =IF(A14="","",C14/SUM($C$5:$C$54)) | G14: =IF(A14="","",C14) | H14: =IF(A14="","",G14/(SUM($G$5:$G$54)+Round!$B$9+Round!$B$10)) | I14: =IF(A14="","",N(D14)*N(E14))
F15: =IF(A15="","",C15/SUM($C$5:$C$54)) | G15: =IF(A15="","",C15) | H15: =IF(A15="","",G15/(SUM($G$5:$G$54)+Round!$B$9+Round!$B$10)) | I15: =IF(A15="","",N(D15)*N(E15))
F16: =IF(A16="","",C16/SUM($C$5:$C$54)) | G16: =IF(A16="","",C16) | H16: =IF(A16="","",G16/(SUM($G$5:$G$54)+Round!$B$9+Round!$B$10)) | I16: =IF(A16="","",N(D16)*N(E16))
F17: =IF(A17="","",C17/SUM($C$5:$C$54)) | G17: =IF(A17="","",C17) | H17: =IF(A17="","",G17/(SUM($G$5:$G$54)+Round!$B$9+Round!$B$10)) | I17: =IF(A17="","",N(D17)*N(E17))
F18: =IF(A18="","",C18/SUM($C$5:$C$54)) | G18: =IF(A18="","",C18) | H18: =IF(A18="","",G18/(SUM($G$5:$G$54)+Round!$B$9+Round!$B$10)) | I18: =IF(A18="","",N(D18)*N(E18))
F19: =IF(A19="","",C19/SUM($C$5:$C$54)) | G19: =IF(A19="","",C19) | H19: =IF(A19="","",G19/(SUM($G$5:$G$54)+Round!$B$9+Round!$B$10)) | I19: =IF(A19="","",N(D19)*N(E19))
F20: =IF(A20="","",C20/SUM($C$5:$C$54)) | G20: =IF(A20="","",C20) | H20: =IF(A20="","",G20/(SUM($G$5:$G$54)+Round!$B$9+Round!$B$10)) | I20: =IF(A20="","",N(D20)*N(E20))
... F54: =IF(A54="","",C54/SUM($C$5:$C$54)) | G54: =IF(A54="","",C54) | H54: =IF(A54="","",G54/(SUM($G$5:$G$54)+Round!$B$9+Round!$B$10)) | I54: =IF(A54="","",N(D54)*N(E54))

Sheet Round
A1: New round
A4: pre-money valuation (fully diluted) | B4: 600000000
A5: investment | B5: 150000000
A6: target post-round ESOP pool % (unallocated + granted) | B6: 0.1
A7: pre-round fully diluted shares | B7: =SUM(Holders!C5:C54)
A8: price per share | B8: =Round!$B$4/B7
A9: new investor shares | B9: =ROUND(Round!$B$5/Round!$B$8,0)
A10: ESOP top-up shares needed (post-money basis, simplified) | B10: =MAX(0,ROUND((Round!$B$6*(B7+B9)-SUMIF(Holders!B5:B54,"ESOP*",Holders!C5:C54))/(1-Round!$B$6),0))
A11: post-money valuation | B11: =Round!$B$4+Round!$B$5

Sheet Waterfall
A1: Exit waterfall (1x non-participating CCPS; investor takes the greater of preference or as-converted)
A4: exit equity value | B4: 2000000000
A5: total preference (multiple x invested, existing CCPS + new round 1x) | B5: =SUM(Holders!I5:I54)+Round!$B$5
A6: new investor as-converted value | B6: =Waterfall!$B$4*Round!B9/(SUM(Holders!G5:G54)+Round!B9+Round!B10)
A7: new investor takes | B7: =MAX(MIN(Round!$B$5,Waterfall!$B$4),B6)
A8: note | B8: Model each CCPS series separately in a copy for participating / >1x terms; follow SHA, Companies Act and FEMA pricing.
